{
  "type": "Feature",
  "properties": {
    "gn:admin1_code":"3.0",
    "gn:asciiname":"Zemmoura",
    "gn:country_code":"MA",
    "gn:dem":343,
    "gn:feature_class":"P",
    "gn:feature_code":"PPL",
    "gn:name":"Zemmoura",
    "gn:population":0,
    "gn:timezone":"Africa/Casablanca",
    "iso:country":"MA",
    "name:ara_x_preferred":[
        "\u0632\u0645\u0648\u0631\u0629"
    ],
    "name:azb_x_preferred":[
        "\u0632\u0645\u0648\u0631\u0647"
    ],
    "name:ceb_x_preferred":[
        "Zemoura"
    ],
    "name:fas_x_preferred":[
        "\u0632\u0645\u0648\u0631\u0647"
    ],
    "name:fra_x_preferred":[
        "Zemmora"
    ],
    "name:ita_x_preferred":[
        "Zemmora"
    ],
    "name:msa_x_preferred":[
        "Zemmoura"
    ],
    "name:por_x_preferred":[
        "Zemmoura"
    ],
    "name:ron_x_preferred":[
        "Zemmora"
    ],
    "name:spa_x_preferred":[
        "Zemmora"
    ],
    "name:swe_x_preferred":[
        "Zemmoura"
    ],
    "name:vie_x_preferred":[
        "Zemmoura"
    ],
    "name:zho_x_preferred":[
        "\u5bb0\u7a46\u62c9"
    ],
    "wof:name":"Zemmoura",
    "wof:placetype":"locality"
},
  "geometry": {"coordinates":[-5.07382,34.61107],"type":"Point"}
}