{
  "type": "Feature",
  "properties": {
    "gn:admin1_code":"09",
    "gn:asciiname":"Mira",
    "gn:country_code":"MA",
    "gn:dem":282,
    "gn:feature_class":"P",
    "gn:feature_code":"PPL",
    "gn:name":"Mira",
    "gn:population":0,
    "gn:timezone":"Africa/Casablanca",
    "iso:country":"MA",
    "wof:name":"Mira",
    "wof:placetype":"locality"
},
  "geometry": {"coordinates":[-9.45811,29.70212],"type":"Point"}
}