{
  "type": "Feature",
  "properties": {
    "gn:admin1_code":"03",
    "gn:asciiname":"Douar Dar Haqqoune",
    "gn:country_code":"MA",
    "gn:dem":990,
    "gn:feature_class":"P",
    "gn:feature_code":"PPL",
    "gn:name":"Douar Dar Haqqoune",
    "gn:population":0,
    "gn:timezone":"Africa/Casablanca",
    "iso:country":"MA",
    "name:und_x_variant":[
        "Dkakkoun",
        "Dar Hakoun",
        "Douar Dar Haqqoune"
    ],
    "wof:name":"Douar Dar Haqqoune",
    "wof:placetype":"locality"
},
  "geometry": {"coordinates":[-4.53711,33.80782],"type":"Point"}
}