{
  "type": "Feature",
  "properties": {
    "gn:country":"MA",
    "gn:fcode":"ADM3",
    "gn:pop":12101,
    "iso:country":"MA",
    "name:ara_x_preferred":[
        "\u0645\u0648\u062d\u0649 \u0623\u0648\u062d\u0645\u0648 \u0627\u0644\u0632\u064a\u0627\u0646\u064a"
    ],
    "name:fra_x_preferred":[
        "Ait Boubidmane"
    ],
    "name:fra_x_variant":[
        "Ait Boubidmane (CR)",
        "Ait Boubidmane (Commune Rurale)"
    ],
    "qs:name":"Ait Boubidmane",
    "qs:photos_9r":0,
    "qs:photos_sr":0,
    "qs:pop_sr":"6",
    "wd:wordcount":33,
    "wof:name":"Ait Boubidmane",
    "wof:placetype":"localadmin",
    "wof:population":12101
},
  "geometry": {"coordinates":[-5.33065,33.85045],"type":"Point"}
}