{
  "type": "Feature",
  "properties": {
    "gn:admin1_code":"08",
    "gn:asciiname":"Tazansout",
    "gn:country_code":"MA",
    "gn:dem":1171,
    "gn:feature_class":"P",
    "gn:feature_code":"PPL",
    "gn:name":"Tazansout",
    "gn:population":0,
    "gn:timezone":"Africa/Casablanca",
    "iso:country":"MA",
    "name:und_x_variant":[
        "Tazensout"
    ],
    "wof:name":"Tazansout",
    "wof:placetype":"locality"
},
  "geometry": {"coordinates":[-4.59254,32.81142],"type":"Point"}
}