{
  "type": "Feature",
  "properties": {
    "gn:admin1_code":"7.0",
    "gn:asciiname":"Dar Ouiad Si Abdessaham Fachi",
    "gn:country_code":"MA",
    "gn:dem":348,
    "gn:feature_class":"P",
    "gn:feature_code":"PPL",
    "gn:name":"Dar Ouiad Si Abdessaham Fachi",
    "gn:population":0,
    "gn:timezone":"Africa/Casablanca",
    "iso:country":"MA",
    "wof:name":"Dar Ouiad Si Abdessaham Fachi",
    "wof:placetype":"locality"
},
  "geometry": {"coordinates":[-8.81221,31.98995],"type":"Point"}
}