{
  "type": "Feature",
  "properties": {
    "iso:country":"MA",
    "qs:gn_pop":0,
    "qs:name":"\u0645\u064a\u062f\u0644\u062a",
    "qs:name_adm0":"\u0627\u0644\u0645\u063a\u0631\u0628",
    "qs:name_adm1":"\u0645\u0643\u0646\u0627\u0633 \u0640 \u062a\u0627\u0641\u064a\u0644\u0627\u0644\u062a",
    "qs:photos":350,
    "qs:photos_1k":71,
    "qs:photos_9k":2,
    "qs:photos_9r":5,
    "qs:photos_all":350,
    "qs:photos_sr":5,
    "qs:placetype":"Town",
    "qs:pop_sr":"0",
    "qs:woe_adm0":23424893,
    "wof:name":"\u0645\u064a\u062f\u0644\u062a",
    "wof:placetype":"locality"
},
  "geometry": {"coordinates":[-4.74163,32.698601],"type":"Point"}
}