{
  "type": "Feature",
  "properties": {
    "gn:admin1_code":"10",
    "gn:asciiname":"Id Tajir",
    "gn:country_code":"MA",
    "gn:dem":773,
    "gn:feature_class":"P",
    "gn:feature_code":"PPL",
    "gn:name":"Id Tajir",
    "gn:population":0,
    "gn:timezone":"Africa/Casablanca",
    "iso:country":"MA",
    "name:und_x_variant":[
        "Id Tajet"
    ],
    "wof:name":"Id Tajir",
    "wof:placetype":"locality"
},
  "geometry": {"coordinates":[-9.7604,29.42732],"type":"Point"}
}