{
  "type": "Feature",
  "properties": {
    "gn:admin1_code":"5.0",
    "gn:asciiname":"Illagat",
    "gn:country_code":"MA",
    "gn:dem":1262,
    "gn:feature_class":"P",
    "gn:feature_code":"PPL",
    "gn:name":"Illagat",
    "gn:population":0,
    "gn:timezone":"Africa/Casablanca",
    "iso:country":"MA",
    "wof:name":"Illagat",
    "wof:placetype":"locality"
},
  "geometry": {"coordinates":[-6.85792,31.6775],"type":"Point"}
}