{
  "type": "Feature",
  "properties": {
    "gn:admin1_code":"7.0",
    "gn:asciiname":"Oulad Brikiyya",
    "gn:country_code":"MA",
    "gn:dem":473,
    "gn:feature_class":"P",
    "gn:feature_code":"PPL",
    "gn:name":"Oulad Brikiyya",
    "gn:population":0,
    "gn:timezone":"Africa/Casablanca",
    "iso:country":"MA",
    "wof:name":"Oulad Brikiyya",
    "wof:placetype":"locality"
},
  "geometry": {"coordinates":[-8.01684,32.35043],"type":"Point"}
}