{
  "type": "Feature",
  "properties": {
    "gn:admin1_code":"5.0",
    "gn:asciiname":"Ghasat",
    "gn:country_code":"MA",
    "gn:dem":640,
    "gn:feature_class":"P",
    "gn:feature_code":"PPL",
    "gn:name":"Ghasat",
    "gn:population":0,
    "gn:timezone":"Africa/Casablanca",
    "iso:country":"MA",
    "wof:name":"Ghasat",
    "wof:placetype":"locality"
},
  "geometry": {"coordinates":[-6.46094,32.20054],"type":"Point"}
}