{
  "type": "Feature",
  "properties": {
    "gn:admin1_code":"7.0",
    "gn:asciiname":"Tabarha",
    "gn:country_code":"MA",
    "gn:dem":526,
    "gn:feature_class":"P",
    "gn:feature_code":"PPL",
    "gn:name":"Tabarha",
    "gn:population":0,
    "gn:timezone":"Africa/Casablanca",
    "iso:country":"MA",
    "wof:name":"Tabarha",
    "wof:placetype":"locality"
},
  "geometry": {"coordinates":[-9.70117,30.80662],"type":"Point"}
}