{
  "type": "Feature",
  "properties": {
    "gn:admin1_code":"7.0",
    "gn:asciiname":"Tnirt",
    "gn:country_code":"MA",
    "gn:dem":1692,
    "gn:feature_class":"P",
    "gn:feature_code":"PPL",
    "gn:name":"Tnirt",
    "gn:population":0,
    "gn:timezone":"Africa/Casablanca",
    "iso:country":"MA",
    "wof:name":"Tnirt",
    "wof:placetype":"locality"
},
  "geometry": {"coordinates":[-8.31911,31.10514],"type":"Point"}
}