{
  "type": "Feature",
  "properties": {
    "gn:admin1_code":"02",
    "gn:asciiname":"Tighrar",
    "gn:country_code":"MA",
    "gn:dem":51,
    "gn:feature_class":"P",
    "gn:feature_code":"PPL",
    "gn:name":"Tighrar",
    "gn:population":0,
    "gn:timezone":"Africa/Casablanca",
    "iso:country":"MA",
    "wof:name":"Tighrar",
    "wof:placetype":"locality"
},
  "geometry": {"coordinates":[-3.67747,35.2742],"type":"Point"}
}