{
  "type": "Feature",
  "properties": {
    "gn:admin1_code":"07",
    "gn:asciiname":"Oulad Boujamaa",
    "gn:country_code":"MA",
    "gn:dem":192,
    "gn:feature_class":"P",
    "gn:feature_code":"PPL",
    "gn:name":"Oulad Boujamaa",
    "gn:population":0,
    "gn:timezone":"Africa/Casablanca",
    "iso:country":"MA",
    "name:und_x_variant":[
        "Douar Oulad Boujema",
        "Oulad boujam\u00e2a",
        "Oulad Boujema",
        "Oulad Boujamaa"
    ],
    "wof:name":"Oulad Boujamaa",
    "wof:placetype":"locality"
},
  "geometry": {"coordinates":[-8.79929,32.26919],"type":"Point"}
}