{
  "type": "Feature",
  "properties": {
    "gn:admin1_code":"4.0",
    "gn:asciiname":"Ait Mhamed",
    "gn:country_code":"MA",
    "gn:dem":538,
    "gn:feature_class":"P",
    "gn:feature_code":"PPL",
    "gn:name":"Ait Mhamed",
    "gn:population":0,
    "gn:timezone":"Africa/Casablanca",
    "iso:country":"MA",
    "wof:name":"Ait Mhamed",
    "wof:placetype":"locality"
},
  "geometry": {"coordinates":[-6.22988,33.52184],"type":"Point"}
}