{
  "type": "Feature",
  "properties": {
    "gn:admin1_code":"07",
    "gn:asciiname":"Tizgui",
    "gn:country_code":"MA",
    "gn:dem":1083,
    "gn:feature_class":"P",
    "gn:feature_code":"PPL",
    "gn:name":"Tizgui",
    "gn:population":0,
    "gn:timezone":"Africa/Casablanca",
    "iso:country":"MA",
    "wof:name":"Tizgui",
    "wof:placetype":"locality"
},
  "geometry": {"coordinates":[-9.26049,30.91829],"type":"Point"}
}