{
  "type": "Feature",
  "properties": {
    "gn:admin1_code":"7.0",
    "gn:asciiname":"Taouja",
    "gn:country_code":"MA",
    "gn:dem":1277,
    "gn:feature_class":"P",
    "gn:feature_code":"PPL",
    "gn:name":"Taouja",
    "gn:population":0,
    "gn:timezone":"Africa/Casablanca",
    "iso:country":"MA",
    "wof:name":"Taouja",
    "wof:placetype":"locality"
},
  "geometry": {"coordinates":[-9.07515,31.1561],"type":"Point"}
}