{
  "type": "Feature",
  "properties": {
    "gn:admin1_code":"2.0",
    "gn:asciiname":"Tamiouat",
    "gn:country_code":"MA",
    "gn:dem":145,
    "gn:feature_class":"P",
    "gn:feature_code":"PPL",
    "gn:name":"Tamiouat",
    "gn:population":0,
    "gn:timezone":"Africa/Casablanca",
    "iso:country":"MA",
    "wof:name":"Tamiouat",
    "wof:placetype":"locality"
},
  "geometry": {"coordinates":[-2.92901,35.01895],"type":"Point"}
}