{
  "type": "Feature",
  "properties": {
    "gn:admin1_code":"07",
    "gn:asciiname":"Douar Ali Ben Lahsen",
    "gn:country_code":"MA",
    "gn:dem":461,
    "gn:feature_class":"P",
    "gn:feature_code":"PPL",
    "gn:name":"Douar Ali Ben Lahsen",
    "gn:population":0,
    "gn:timezone":"Africa/Casablanca",
    "iso:country":"MA",
    "name:und_x_variant":[
        "Che\u00efkh Ali ben Chalah",
        "Douar Che\u00efkh Ali Ben Chalah",
        "Douar Che\u00efk Ali Ben Chalah",
        "Douar Ali Ben Lahsen"
    ],
    "wof:name":"Douar Ali Ben Lahsen",
    "wof:placetype":"locality"
},
  "geometry": {"coordinates":[-8.37683,32.0065],"type":"Point"}
}