{
  "type": "Feature",
  "properties": {
    "gn:admin1_code":"3.0",
    "gn:asciiname":"Douar Ben Abbou",
    "gn:country_code":"MA",
    "gn:dem":554,
    "gn:feature_class":"P",
    "gn:feature_code":"PPL",
    "gn:name":"Douar Ben Abbou",
    "gn:population":0,
    "gn:timezone":"Africa/Casablanca",
    "iso:country":"MA",
    "wof:name":"Douar Ben Abbou",
    "wof:placetype":"locality"
},
  "geometry": {"coordinates":[-4.86774,33.94627],"type":"Point"}
}