{
  "type": "Feature",
  "properties": {
    "gn:admin1_code":"6.0",
    "gn:asciiname":"Oulad Zaghdoud",
    "gn:country_code":"MA",
    "gn:dem":431,
    "gn:feature_class":"P",
    "gn:feature_code":"PPL",
    "gn:name":"Oulad Zaghdoud",
    "gn:population":0,
    "gn:timezone":"Africa/Casablanca",
    "iso:country":"MA",
    "wof:name":"Oulad Zaghdoud",
    "wof:placetype":"locality"
},
  "geometry": {"coordinates":[-7.47706,33.07805],"type":"Point"}
}