{
  "type": "Feature",
  "properties": {
    "gn:admin1_code":"9.0",
    "gn:asciiname":"Tagmout",
    "gn:country_code":"MA",
    "gn:dem":1182,
    "gn:feature_class":"P",
    "gn:feature_code":"PPL",
    "gn:name":"Tagmout",
    "gn:population":0,
    "gn:timezone":"Africa/Casablanca",
    "iso:country":"MA",
    "wof:name":"Tagmout",
    "wof:placetype":"locality"
},
  "geometry": {"coordinates":[-9.0921,30.72334],"type":"Point"}
}