{
  "type": "Feature",
  "properties": {
    "gn:admin1_code":"09",
    "gn:asciiname":"Imi-n-Tanout",
    "gn:country_code":"MA",
    "gn:dem":1369,
    "gn:feature_class":"P",
    "gn:feature_code":"PPL",
    "gn:name":"Imi-n-Tanout",
    "gn:population":0,
    "gn:timezone":"Africa/Casablanca",
    "iso:country":"MA",
    "name:und_x_variant":[
        "Imi n\u2019Tanoute",
        "Imi Ntauout",
        "Imi n\u2019Tanout",
        "Imi-n-Tanout",
        "Imi n\u2019 Tanout"
    ],
    "wof:name":"Imi-n-Tanout",
    "wof:placetype":"locality"
},
  "geometry": {"coordinates":[-8.88342,29.79613],"type":"Point"}
}