{
  "type": "Feature",
  "properties": {
    "gn:admin1_code":"7.0",
    "gn:asciiname":"Oulad Ali Ben Ahmed",
    "gn:country_code":"MA",
    "gn:dem":101,
    "gn:feature_class":"P",
    "gn:feature_code":"PPL",
    "gn:name":"Oulad Ali Ben Ahmed",
    "gn:population":0,
    "gn:timezone":"Africa/Casablanca",
    "iso:country":"MA",
    "wof:name":"Oulad Ali Ben Ahmed",
    "wof:placetype":"locality"
},
  "geometry": {"coordinates":[-9.37752,31.97192],"type":"Point"}
}