{
  "type": "Feature",
  "properties": {
    "gn:admin1_code":"07",
    "gn:asciiname":"Oulad Brahim",
    "gn:country_code":"MA",
    "gn:dem":580,
    "gn:feature_class":"P",
    "gn:feature_code":"PPL",
    "gn:name":"Oulad Brahim",
    "gn:population":0,
    "gn:timezone":"Africa/Casablanca",
    "iso:country":"MA",
    "name:und_x_variant":[
        "Douar Oulad Brahim",
        "Oulad Sidi Brahim",
        "Oulad Brahim",
        "Ouled Brahim"
    ],
    "wof:name":"Oulad Brahim",
    "wof:placetype":"locality"
},
  "geometry": {"coordinates":[-7.32281,31.89272],"type":"Point"}
}