{
  "type": "Feature",
  "properties": {
    "gn:admin1_code":"04",
    "gn:admin2_code":"481.0",
    "gn:admin3_code":"548107152.0",
    "gn:asciiname":"Sidi Redouane",
    "gn:country_code":"MA",
    "gn:dem":199,
    "gn:feature_class":"P",
    "gn:feature_code":"PPLA3",
    "gn:name":"Sidi Redouane",
    "gn:population":0,
    "gn:timezone":"Africa/Casablanca",
    "iso:country":"MA",
    "name:und_x_variant":[
        "Redouane",
        "Sidi Reduan",
        "Sidi Redouane"
    ],
    "wof:name":"Sidi Redouane",
    "wof:placetype":"locality"
},
  "geometry": {"coordinates":[-5.44538,34.68692],"type":"Point"}
}