{
  "type": "Feature",
  "properties": {
    "gn:admin1_code":"04",
    "gn:admin2_code":"481.0",
    "gn:admin3_code":"548107152.0",
    "gn:asciiname":"Sidi Redouane",
    "gn:country_code":"MA",
    "gn:dem":199,
    "gn:feature_class":"P",
    "gn:feature_code":"PPLA3",
    "gn:name":"Sidi Redouane",
    "gn:population":0,
    "gn:timezone":"Africa/Casablanca",
    "iso:country":"MA",
    "name:ara_x_preferred":[
        "\u0633\u064a\u062f\u064a \u0631\u0636\u0648\u0627\u0646"
    ],
    "name:cat_x_preferred":[
        "Sidi Redouane"
    ],
    "name:ceb_x_preferred":[
        "Sidi Redouane"
    ],
    "name:ita_x_preferred":[
        "Sidi Redouane"
    ],
    "name:swe_x_preferred":[
        "Sidi Redouane"
    ],
    "name:und_x_variant":[
        "Redouane",
        "Sidi Reduan"
    ],
    "name:urd_x_preferred":[
        "\u0633\u06cc\u062f\u06cc \u0631\u0636\u0648\u0627\u0646"
    ],
    "wof:name":"Sidi Redouane",
    "wof:placetype":"locality"
},
  "geometry": {"coordinates":[-5.44538,34.68692],"type":"Point"}
}