{
  "type": "Feature",
  "properties": {
    "gn:admin1_code":"9.0",
    "gn:asciiname":"Amrkn",
    "gn:country_code":"MA",
    "gn:dem":496,
    "gn:feature_class":"P",
    "gn:feature_code":"PPL",
    "gn:name":"Amrkn",
    "gn:population":0,
    "gn:timezone":"Africa/Casablanca",
    "iso:country":"MA",
    "wof:name":"Amrkn",
    "wof:placetype":"locality"
},
  "geometry": {"coordinates":[-9.43318,29.66259],"type":"Point"}
}