{
  "type": "Feature",
  "properties": {
    "gn:admin1_code":"7.0",
    "gn:asciiname":"Tirest",
    "gn:country_code":"MA",
    "gn:dem":626,
    "gn:feature_class":"P",
    "gn:feature_code":"PPL",
    "gn:name":"Tirest",
    "gn:population":0,
    "gn:timezone":"Africa/Casablanca",
    "iso:country":"MA",
    "wof:name":"Tirest",
    "wof:placetype":"locality"
},
  "geometry": {"coordinates":[-7.70804,31.52739],"type":"Point"}
}