{
  "type": "Feature",
  "properties": {
    "gn:admin1_code":"09",
    "gn:asciiname":"Tiyrouma",
    "gn:country_code":"MA",
    "gn:dem":852,
    "gn:feature_class":"P",
    "gn:feature_code":"PPL",
    "gn:name":"Tiyrouma",
    "gn:population":0,
    "gn:timezone":"Africa/Casablanca",
    "iso:country":"MA",
    "name:und_x_variant":[
        "Tirouma",
        "Tourouma",
        "Tiyrouma"
    ],
    "wof:name":"Tiyrouma",
    "wof:placetype":"locality"
},
  "geometry": {"coordinates":[-9.34418,29.7427],"type":"Point"}
}