{
  "type": "Feature",
  "properties": {
    "gn:admin1_code":"01",
    "gn:asciiname":"Douar Saaydi El Forjani",
    "gn:country_code":"MA",
    "gn:dem":99,
    "gn:feature_class":"P",
    "gn:feature_code":"PPL",
    "gn:name":"Douar Saaydi El Forjani",
    "gn:population":0,
    "gn:timezone":"Africa/Casablanca",
    "iso:country":"MA",
    "name:und_x_variant":[
        "Ferjane"
    ],
    "wof:name":"Douar Saaydi El Forjani",
    "wof:placetype":"locality"
},
  "geometry": {"coordinates":[-5.91758,35.33880999999999],"type":"Point"}
}