{
  "type": "Feature",
  "properties": {
    "gn:admin1_code":"01",
    "gn:asciiname":"Ain Bellout",
    "gn:country_code":"MA",
    "gn:dem":91,
    "gn:feature_class":"P",
    "gn:feature_code":"PPL",
    "gn:name":"Ain Bellout",
    "gn:population":0,
    "gn:timezone":"Africa/Casablanca",
    "iso:country":"MA",
    "name:und_x_variant":[
        "A\u00efn Belot",
        "A\u00efn Bellout",
        "Ain Bellout"
    ],
    "wof:name":"Ain Bellout",
    "wof:placetype":"locality"
},
  "geometry": {"coordinates":[-5.8468,35.67499],"type":"Point"}
}