{
  "type": "Feature",
  "properties": {
    "gn:gn_country":"MA",
    "gn:gn_fcode":"ADM3",
    "gn:gn_pop":8310,
    "gn:population":8715,
    "iso:country":"MA",
    "name:ara_x_preferred":[
        "\u0627\u0645\u0631\u0627\u0628\u0637\u0646"
    ],
    "name:ara_x_variant":[
        "\u0625\u0645\u0631\u0627\u0628\u0637\u0646"
    ],
    "name:cat_x_preferred":[
        "Imrabten"
    ],
    "name:ceb_x_preferred":[
        "Imrabten"
    ],
    "name:fra_x_preferred":[
        "Imrabten"
    ],
    "name:fra_x_variant":[
        "Imrabten (CR)",
        "Imrabten (Commune Rurale)"
    ],
    "name:ita_x_preferred":[
        "Imrabten"
    ],
    "name:swe_x_preferred":[
        "Imrabten"
    ],
    "name:urd_x_preferred":[
        "\u0627\u0645\u0631\u0627\u0628\u0637\u0646"
    ],
    "qs_pg:aaroncc":"MA",
    "qs_pg:gn_country":"MA",
    "qs_pg:gn_fcode":"ADM3",
    "qs_pg:gn_pop":8310,
    "qs_pg:name":"Imrabten",
    "qs_pg:photos_9r":0,
    "qs_pg:photos_sr":0,
    "qs_pg:pop_sr":5,
    "qs_pg:qs_pg_placetype":"localadmin",
    "wof:name":"Imrabten",
    "wof:placetype":"localadmin",
    "wof:population":8715
},
  "geometry": {"coordinates":[-3.98674,35.04643],"type":"Point"}
}