{
  "type": "Feature",
  "properties": {
    "gn:admin1_code":"6.0",
    "gn:asciiname":"Douar Oulad Ali Bon Ali",
    "gn:country_code":"MA",
    "gn:dem":555,
    "gn:feature_class":"P",
    "gn:feature_code":"PPL",
    "gn:name":"Douar Oulad Ali Bon Ali",
    "gn:population":0,
    "gn:timezone":"Africa/Casablanca",
    "iso:country":"MA",
    "wof:name":"Douar Oulad Ali Bon Ali",
    "wof:placetype":"locality"
},
  "geometry": {"coordinates":[-7.37889,33.04136],"type":"Point"}
}