{
  "type": "Feature",
  "properties": {
    "gn:admin1_code":"07",
    "gn:asciiname":"Sour Tedrara",
    "gn:country_code":"MA",
    "gn:dem":930,
    "gn:feature_class":"P",
    "gn:feature_code":"PPL",
    "gn:name":"Sour Tedrara",
    "gn:population":0,
    "gn:timezone":"Africa/Casablanca",
    "iso:country":"MA",
    "name:und_x_variant":[
        "Maouttadrara",
        "Souk Tedrara",
        "Sour Tedrara"
    ],
    "wof:name":"Sour Tedrara",
    "wof:placetype":"locality"
},
  "geometry": {"coordinates":[-7.88732,31.34806],"type":"Point"}
}