{
  "type": "Feature",
  "properties": {
    "gn:admin1_code":"3.0",
    "gn:asciiname":"Dar El Haddad",
    "gn:country_code":"MA",
    "gn:dem":1351,
    "gn:feature_class":"P",
    "gn:feature_code":"PPL",
    "gn:name":"Dar El Haddad",
    "gn:population":0,
    "gn:timezone":"Africa/Casablanca",
    "iso:country":"MA",
    "wof:name":"Dar El Haddad",
    "wof:placetype":"locality"
},
  "geometry": {"coordinates":[-4.0591,34.04594],"type":"Point"}
}