{
  "type": "Feature",
  "properties": {
    "gn:admin1_code":"3.0",
    "gn:asciiname":"Dar El Haddad",
    "gn:country_code":"MA",
    "gn:dem":1351,
    "gn:feature_class":"P",
    "gn:feature_code":"PPL",
    "gn:name":"Dar El Haddad",
    "gn:population":0,
    "gn:timezone":"Africa/Casablanca",
    "iso:country":"MA",
    "name:ara_x_preferred":[
        "\u062f\u0627\u0631 \u0627\u0644\u062d\u062f\u0627\u062f"
    ],
    "name:fra_x_preferred":[
        "Dar El Haddad"
    ],
    "wof:name":"Dar El Haddad",
    "wof:placetype":"locality"
},
  "geometry": {"coordinates":[-4.0591,34.04594],"type":"Point"}
}