{
  "type": "Feature",
  "properties": {
    "gn:admin1_code":"01",
    "gn:asciiname":"Ain er Rami",
    "gn:country_code":"MA",
    "gn:dem":580,
    "gn:feature_class":"P",
    "gn:feature_code":"PPL",
    "gn:name":"A\u00efn er Rami",
    "gn:population":0,
    "gn:timezone":"Africa/Casablanca",
    "iso:country":"MA",
    "wof:name":"Ain er Rami",
    "wof:placetype":"locality"
},
  "geometry": {"coordinates":[-5.27538,35.1326],"type":"Point"}
}