{
  "type": "Feature",
  "properties": {
    "gn:admin1_code":"7.0",
    "gn:asciiname":"Boutaghradine",
    "gn:country_code":"MA",
    "gn:dem":1047,
    "gn:feature_class":"P",
    "gn:feature_code":"PPL",
    "gn:name":"Boutaghradine",
    "gn:population":0,
    "gn:timezone":"Africa/Casablanca",
    "iso:country":"MA",
    "wof:name":"Boutaghradine",
    "wof:placetype":"locality"
},
  "geometry": {"coordinates":[-8.78938,31.11636],"type":"Point"}
}