{
  "type": "Feature",
  "properties": {
    "gn:admin1_code":"4.0",
    "gn:asciiname":"Dar Ben Ayyad",
    "gn:country_code":"MA",
    "gn:dem":12,
    "gn:feature_class":"P",
    "gn:feature_code":"PPL",
    "gn:name":"Dar Ben Ayyad",
    "gn:population":0,
    "gn:timezone":"Africa/Casablanca",
    "iso:country":"MA",
    "wof:name":"Dar Ben Ayyad",
    "wof:placetype":"locality"
},
  "geometry": {"coordinates":[-6.14509,34.84614000000001],"type":"Point"}
}