{
  "type": "Feature",
  "properties": {
    "gn:admin1_code":"1.0",
    "gn:asciiname":"Dar Chtiba",
    "gn:country_code":"MA",
    "gn:dem":281,
    "gn:feature_class":"P",
    "gn:feature_code":"PPL",
    "gn:name":"Dar Chtiba",
    "gn:population":0,
    "gn:timezone":"Africa/Casablanca",
    "iso:country":"MA",
    "wof:name":"Dar Chtiba",
    "wof:placetype":"locality"
},
  "geometry": {"coordinates":[-5.50152,35.74193],"type":"Point"}
}