{
  "type": "Feature",
  "properties": {
    "gn:admin1_code":"3.0",
    "gn:asciiname":"Douar Sidi Abderrazzaq",
    "gn:country_code":"MA",
    "gn:dem":522,
    "gn:feature_class":"P",
    "gn:feature_code":"PPL",
    "gn:name":"Douar Sidi Abderrazzaq",
    "gn:population":0,
    "gn:timezone":"Africa/Casablanca",
    "iso:country":"MA",
    "wof:name":"Douar Sidi Abderrazzaq",
    "wof:placetype":"locality"
},
  "geometry": {"coordinates":[-4.778,34.03013],"type":"Point"}
}