{
  "type": "Feature",
  "properties": {
    "gn:admin1_code":"01",
    "gn:asciiname":"Sidi Boutanouar",
    "gn:country_code":"MA",
    "gn:dem":150,
    "gn:feature_class":"P",
    "gn:feature_code":"PPL",
    "gn:name":"Sidi Boutanouar",
    "gn:population":0,
    "gn:timezone":"Africa/Casablanca",
    "iso:country":"MA",
    "name:und_x_variant":[
        "Zaara Sidi Bunuar",
        "Zaouia Sidi Boumiar",
        "Sidi Boutanouar"
    ],
    "wof:name":"Sidi Boutanouar",
    "wof:placetype":"locality"
},
  "geometry": {"coordinates":[-5.95637,35.38760999999999],"type":"Point"}
}