{
  "type": "Feature",
  "properties": {
    "gn:admin1_code":"7.0",
    "gn:asciiname":"Dar Faddoul",
    "gn:country_code":"MA",
    "gn:dem":328,
    "gn:feature_class":"P",
    "gn:feature_code":"PPL",
    "gn:name":"Dar Faddoul",
    "gn:population":0,
    "gn:timezone":"Africa/Casablanca",
    "iso:country":"MA",
    "wof:name":"Dar Faddoul",
    "wof:placetype":"locality"
},
  "geometry": {"coordinates":[-8.68331,31.9488],"type":"Point"}
}