{
  "type": "Feature",
  "properties": {
    "gn:admin1_code":"08",
    "gn:asciiname":"Agouchtine",
    "gn:country_code":"MA",
    "gn:dem":1986,
    "gn:feature_class":"P",
    "gn:feature_code":"PPL",
    "gn:name":"Agouchtine",
    "gn:population":0,
    "gn:timezone":"Africa/Casablanca",
    "iso:country":"MA",
    "name:und_x_variant":[
        "Akouchtine",
        "Agouchtine"
    ],
    "wof:name":"Agouchtine",
    "wof:placetype":"locality"
},
  "geometry": {"coordinates":[-7.6344,31.10369],"type":"Point"}
}