{
  "type": "Feature",
  "properties": {
    "gn:admin1_code":"7.0",
    "gn:asciiname":"Cooperative D Argane",
    "gn:country_code":"MA",
    "gn:dem":248,
    "gn:feature_class":"P",
    "gn:feature_code":"PPL",
    "gn:name":"Coop\u00e9rative D Argane",
    "gn:population":0,
    "gn:timezone":"Africa/Casablanca",
    "iso:country":"MA",
    "wof:name":"Cooperative D Argane",
    "wof:placetype":"locality"
},
  "geometry": {"coordinates":[-9.80729,31.12231],"type":"Point"}
}