{
  "type": "Feature",
  "properties": {
    "gn:admin1_code":"08",
    "gn:asciiname":"Toufassemane",
    "gn:country_code":"MA",
    "gn:dem":978,
    "gn:feature_class":"P",
    "gn:feature_code":"PPL",
    "gn:name":"Toufassemane",
    "gn:population":0,
    "gn:timezone":"Africa/Casablanca",
    "iso:country":"MA",
    "name:und_x_variant":[
        "Toufasamam",
        "Toufassemane"
    ],
    "wof:name":"Toufassemane",
    "wof:placetype":"locality"
},
  "geometry": {"coordinates":[-4.95594,31.27388],"type":"Point"}
}