{
  "type": "Feature",
  "properties": {
    "gn:admin1_code":"05",
    "gn:asciiname":"Ait Roboa",
    "gn:country_code":"MA",
    "gn:dem":2116,
    "gn:feature_class":"P",
    "gn:feature_code":"PPL",
    "gn:name":"A\u00eft Robo\u00e2",
    "gn:population":0,
    "gn:timezone":"Africa/Casablanca",
    "iso:country":"MA",
    "name:und_x_variant":[
        "Ksar A\u00eft Roboa",
        "A\u00eft Robo\u00e2"
    ],
    "wof:name":"Ait Roboa",
    "wof:placetype":"locality"
},
  "geometry": {"coordinates":[-5.7786,32.21774],"type":"Point"}
}