{
  "type": "Feature",
  "properties": {
    "gn:admin1_code":"02",
    "gn:asciiname":"Wawzert",
    "gn:country_code":"MA",
    "gn:dem":1720,
    "gn:feature_class":"P",
    "gn:feature_code":"PPL",
    "gn:name":"Wawzert",
    "gn:population":0,
    "gn:timezone":"Africa/Casablanca",
    "iso:country":"MA",
    "name:und_x_variant":[
        "Ouaouzert"
    ],
    "wof:name":"Wawzert",
    "wof:placetype":"locality"
},
  "geometry": {"coordinates":[-3.64873,32.50804],"type":"Point"}
}