{
  "type": "Feature",
  "properties": {
    "gn:admin1_code":"08",
    "gn:asciiname":"Achbarou",
    "gn:country_code":"MA",
    "gn:dem":836,
    "gn:feature_class":"P",
    "gn:feature_code":"PPL",
    "gn:name":"Achbarou",
    "gn:population":0,
    "gn:timezone":"Africa/Casablanca",
    "iso:country":"MA",
    "name:und_x_variant":[
        "Irhnit",
        "Ksar Achbarou",
        "Achbarou"
    ],
    "wof:name":"Achbarou",
    "wof:placetype":"locality"
},
  "geometry": {"coordinates":[-5.07068,31.14754000000001],"type":"Point"}
}