{
  "type": "Feature",
  "properties": {
    "gn:admin1_code":"6.0",
    "gn:asciiname":"Hait Ahmed Bou Ali",
    "gn:country_code":"MA",
    "gn:dem":81,
    "gn:feature_class":"P",
    "gn:feature_code":"PPL",
    "gn:name":"Ha\u00eft Ahmed Bou Ali",
    "gn:population":0,
    "gn:timezone":"Africa/Casablanca",
    "iso:country":"MA",
    "wof:name":"Hait Ahmed Bou Ali",
    "wof:placetype":"locality"
},
  "geometry": {"coordinates":[-8.97631,32.76446],"type":"Point"}
}