{
  "type": "Feature",
  "properties": {
    "gn:admin1_code":"3.0",
    "gn:asciiname":"Douar Mtaza",
    "gn:country_code":"MA",
    "gn:dem":805,
    "gn:feature_class":"P",
    "gn:feature_code":"PPL",
    "gn:name":"Douar Mtaza",
    "gn:population":0,
    "gn:timezone":"Africa/Casablanca",
    "iso:country":"MA",
    "wof:name":"Douar Mtaza",
    "wof:placetype":"locality"
},
  "geometry": {"coordinates":[-4.34341,34.37665],"type":"Point"}
}