{
  "type": "Feature",
  "properties": {
    "gn:admin1_code":"07",
    "gn:asciiname":"Oulad Mello",
    "gn:country_code":"MA",
    "gn:dem":345,
    "gn:feature_class":"P",
    "gn:feature_code":"PPL",
    "gn:name":"Oulad Mello",
    "gn:population":0,
    "gn:timezone":"Africa/Casablanca",
    "iso:country":"MA",
    "wof:name":"Oulad Mello",
    "wof:placetype":"locality"
},
  "geometry": {"coordinates":[-8.88,31.85],"type":"Point"}
}