{
  "type": "Feature",
  "properties": {
    "gn:admin1_code":"02",
    "gn:asciiname":"Douar Touzzaline n-Ouadday",
    "gn:country_code":"MA",
    "gn:dem":79,
    "gn:feature_class":"P",
    "gn:feature_code":"PPL",
    "gn:name":"Douar Touzzaline n-Ouadday",
    "gn:population":0,
    "gn:timezone":"Africa/Casablanca",
    "iso:country":"MA",
    "wof:name":"Douar Touzzaline n-Ouadday",
    "wof:placetype":"locality"
},
  "geometry": {"coordinates":[-3.69223,35.26487],"type":"Point"}
}