{
  "type": "Feature",
  "properties": {
    "gn:admin1_code":"9.0",
    "gn:asciiname":"Dar",
    "gn:country_code":"MA",
    "gn:dem":140,
    "gn:feature_class":"P",
    "gn:feature_code":"PPL",
    "gn:name":"Dar",
    "gn:population":0,
    "gn:timezone":"Africa/Casablanca",
    "iso:country":"MA",
    "name:ceb_x_preferred":[
        "Dar"
    ],
    "name:ces_x_preferred":[
        "Dar"
    ],
    "name:fra_x_preferred":[
        "Dar"
    ],
    "name:hrv_x_preferred":[
        "Dar"
    ],
    "name:pol_x_preferred":[
        "Dar"
    ],
    "name:slk_x_preferred":[
        "Dar"
    ],
    "name:swe_x_preferred":[
        "Dar"
    ],
    "wof:name":"Dar",
    "wof:placetype":"locality"
},
  "geometry": {"coordinates":[-9.14016,30.43712],"type":"Point"}
}