{
  "type": "Feature",
  "properties": {
    "gn:admin1_code":"06",
    "gn:asciiname":"Douar El Maatga",
    "gn:country_code":"MA",
    "gn:dem":37,
    "gn:feature_class":"P",
    "gn:feature_code":"PPL",
    "gn:name":"Douar El Maatga",
    "gn:population":0,
    "gn:timezone":"Africa/Casablanca",
    "iso:country":"MA",
    "name:und_x_variant":[
        "Dar el Ma\u00e2tga"
    ],
    "wof:name":"Douar El Maatga",
    "wof:placetype":"locality"
},
  "geometry": {"coordinates":[-8.47634,33.15085999999999],"type":"Point"}
}