{
  "type": "Feature",
  "properties": {
    "gn:admin1_code":"7.0",
    "gn:asciiname":"Dar Miloud Ben Daoui",
    "gn:country_code":"MA",
    "gn:dem":415,
    "gn:feature_class":"P",
    "gn:feature_code":"PPL",
    "gn:name":"Dar Miloud Ben Daoui",
    "gn:population":0,
    "gn:timezone":"Africa/Casablanca",
    "iso:country":"MA",
    "wof:name":"Dar Miloud Ben Daoui",
    "wof:placetype":"locality"
},
  "geometry": {"coordinates":[-7.8292,32.0871],"type":"Point"}
}