{
  "type": "Feature",
  "properties": {
    "gn:admin1_code":"7.0",
    "gn:asciiname":"Afritsat",
    "gn:country_code":"MA",
    "gn:dem":502,
    "gn:feature_class":"P",
    "gn:feature_code":"PPL",
    "gn:name":"Afritsat",
    "gn:population":0,
    "gn:timezone":"Africa/Casablanca",
    "iso:country":"MA",
    "wof:name":"Afritsat",
    "wof:placetype":"locality"
},
  "geometry": {"coordinates":[-8.71548,31.41955],"type":"Point"}
}