{
  "type": "Feature",
  "properties": {
    "gn:admin1_code":"1.0",
    "gn:asciiname":"Douar Oulad Bouchta",
    "gn:country_code":"MA",
    "gn:dem":112,
    "gn:feature_class":"P",
    "gn:feature_code":"PPL",
    "gn:name":"Douar Oulad Bouchta",
    "gn:population":0,
    "gn:timezone":"Africa/Casablanca",
    "iso:country":"MA",
    "wof:name":"Douar Oulad Bouchta",
    "wof:placetype":"locality"
},
  "geometry": {"coordinates":[-4.82527,35.21023],"type":"Point"}
}