{
  "type": "Feature",
  "properties": {
    "gn:admin1_code":"07",
    "gn:asciiname":"Tassila Ou Zaddar",
    "gn:country_code":"MA",
    "gn:dem":756,
    "gn:feature_class":"P",
    "gn:feature_code":"PPL",
    "gn:name":"Tassila Ou Zaddar",
    "gn:population":0,
    "gn:timezone":"Africa/Casablanca",
    "iso:country":"MA",
    "name:und_x_variant":[
        "A\u00eft Masfor",
        "Imadarhn",
        "Tassila Ou Zaddar"
    ],
    "wof:name":"Tassila Ou Zaddar",
    "wof:placetype":"locality"
},
  "geometry": {"coordinates":[-9.51778,30.99936],"type":"Point"}
}