{
  "type": "Feature",
  "properties": {
    "gn:admin1_code":"7.0",
    "gn:asciiname":"Dar Khadija Ben El Arbi",
    "gn:country_code":"MA",
    "gn:dem":457,
    "gn:feature_class":"P",
    "gn:feature_code":"PPL",
    "gn:name":"Dar Khadija Ben El Arbi",
    "gn:population":0,
    "gn:timezone":"Africa/Casablanca",
    "iso:country":"MA",
    "wof:name":"Dar Khadija Ben El Arbi",
    "wof:placetype":"locality"
},
  "geometry": {"coordinates":[-7.81739,32.18163],"type":"Point"}
}