{
  "type": "Feature",
  "properties": {
    "gn:admin1_code":"1.0",
    "gn:asciiname":"Tagouguit",
    "gn:country_code":"MA",
    "gn:dem":918,
    "gn:feature_class":"P",
    "gn:feature_code":"PPL",
    "gn:name":"Tagouguit",
    "gn:population":0,
    "gn:timezone":"Africa/Casablanca",
    "iso:country":"MA",
    "wof:name":"Tagouguit",
    "wof:placetype":"locality"
},
  "geometry": {"coordinates":[-3.92364,35.00223],"type":"Point"}
}