{
  "type": "Feature",
  "properties": {
    "gn:admin1_code":"08",
    "gn:asciiname":"Ait Hakkou Ou'Ali",
    "gn:country_code":"MA",
    "gn:dem":1434,
    "gn:feature_class":"P",
    "gn:feature_code":"PPL",
    "gn:name":"A\u00eft Hakkou Ou\u2019Ali",
    "gn:population":0,
    "gn:timezone":"Africa/Casablanca",
    "iso:country":"MA",
    "name:und_x_variant":[
        "A\u00eft Hakkou Ou Ali",
        "A\u00eft Akka Ou Ali",
        "A\u00eft Hakkou Ou\u2019Ali"
    ],
    "wof:name":"Ait Hakkou Ou'Ali",
    "wof:placetype":"locality"
},
  "geometry": {"coordinates":[-6.07815,31.24113],"type":"Point"}
}