{
  "type": "Feature",
  "properties": {
    "gn:admin1_code":"1.0",
    "gn:asciiname":"Houmat Ben Issef",
    "gn:country_code":"MA",
    "gn:dem":401,
    "gn:feature_class":"P",
    "gn:feature_code":"PPL",
    "gn:name":"Houmat Ben Issef",
    "gn:population":0,
    "gn:timezone":"Africa/Casablanca",
    "iso:country":"MA",
    "wof:name":"Houmat Ben Issef",
    "wof:placetype":"locality"
},
  "geometry": {"coordinates":[-5.55202,35.13351],"type":"Point"}
}