{
  "type": "Feature",
  "properties": {
    "gn:admin1_code":"03",
    "gn:asciiname":"Douar Ait Ou Lghazi",
    "gn:country_code":"MA",
    "gn:dem":807,
    "gn:feature_class":"P",
    "gn:feature_code":"PPL",
    "gn:name":"Douar Ait Ou Lghazi",
    "gn:population":0,
    "gn:timezone":"Africa/Casablanca",
    "iso:country":"MA",
    "wof:name":"Douar Ait Ou Lghazi",
    "wof:placetype":"locality"
},
  "geometry": {"coordinates":[-5.5619,33.67928],"type":"Point"}
}