{
  "type": "Feature",
  "properties": {
    "gn:admin1_code":"7.0",
    "gn:asciiname":"Douar Mguibra",
    "gn:country_code":"MA",
    "gn:dem":291,
    "gn:feature_class":"P",
    "gn:feature_code":"PPL",
    "gn:name":"Douar Mguibra",
    "gn:population":0,
    "gn:timezone":"Africa/Casablanca",
    "iso:country":"MA",
    "wof:name":"Douar Mguibra",
    "wof:placetype":"locality"
},
  "geometry": {"coordinates":[-8.69208,31.62891],"type":"Point"}
}