{
  "type": "Feature",
  "properties": {
    "gn:admin1_code":"03",
    "gn:asciiname":"Douar Iknane",
    "gn:country_code":"MA",
    "gn:dem":875,
    "gn:feature_class":"P",
    "gn:feature_code":"PPL",
    "gn:name":"Douar Iknane",
    "gn:population":0,
    "gn:timezone":"Africa/Casablanca",
    "iso:country":"MA",
    "name:und_x_variant":[
        "Iknane"
    ],
    "wof:name":"Douar Iknane",
    "wof:placetype":"locality"
},
  "geometry": {"coordinates":[-4.3404,33.92162],"type":"Point"}
}