{
  "type": "Feature",
  "properties": {
    "gn:admin1_code":"09",
    "gn:asciiname":"Tanouzagt",
    "gn:country_code":"MA",
    "gn:dem":1899,
    "gn:feature_class":"P",
    "gn:feature_code":"PPL",
    "gn:name":"Tanouzagt",
    "gn:population":0,
    "gn:timezone":"Africa/Casablanca",
    "iso:country":"MA",
    "name:und_x_variant":[
        "Tanouzegt"
    ],
    "wof:name":"Tanouzagt",
    "wof:placetype":"locality"
},
  "geometry": {"coordinates":[-8.81823,30.90922],"type":"Point"}
}