{
  "type": "Feature",
  "properties": {
    "gn:admin1_code":"7.0",
    "gn:asciiname":"Dar Mohamed Ben El Hafad",
    "gn:country_code":"MA",
    "gn:dem":332,
    "gn:feature_class":"P",
    "gn:feature_code":"PPL",
    "gn:name":"Dar Mohamed Ben El Hafad",
    "gn:population":0,
    "gn:timezone":"Africa/Casablanca",
    "iso:country":"MA",
    "wof:name":"Dar Mohamed Ben El Hafad",
    "wof:placetype":"locality"
},
  "geometry": {"coordinates":[-8.37808,31.68535],"type":"Point"}
}