{
  "type": "Feature",
  "properties": {
    "gn:admin1_code":"9.0",
    "gn:asciiname":"Agar-n-Wal",
    "gn:country_code":"MA",
    "gn:dem":1131,
    "gn:feature_class":"P",
    "gn:feature_code":"PPL",
    "gn:name":"Agar-n-Wal",
    "gn:population":0,
    "gn:timezone":"Africa/Casablanca",
    "iso:country":"MA",
    "wof:name":"Agar-n-Wal",
    "wof:placetype":"locality"
},
  "geometry": {"coordinates":[-8.75448,30.12018],"type":"Point"}
}