{
  "type": "Feature",
  "properties": {
    "gn:admin1_code":"07",
    "gn:asciiname":"Sidi bou Brahim",
    "gn:country_code":"MA",
    "gn:dem":1278,
    "gn:feature_class":"P",
    "gn:feature_code":"PPL",
    "gn:name":"Sidi bou Brahim",
    "gn:population":0,
    "gn:timezone":"Africa/Casablanca",
    "iso:country":"MA",
    "wof:name":"Sidi bou Brahim",
    "wof:placetype":"locality"
},
  "geometry": {"coordinates":[-9.02164,31.01032],"type":"Point"}
}