{
  "type": "Feature",
  "properties": {
    "gn:admin1_code":"02",
    "gn:asciiname":"Dar Mohannd Abd el Jellil",
    "gn:country_code":"MA",
    "gn:dem":524,
    "gn:feature_class":"P",
    "gn:feature_code":"PPL",
    "gn:name":"Dar Mohannd Abd el Jellil",
    "gn:population":0,
    "gn:timezone":"Africa/Casablanca",
    "iso:country":"MA",
    "name:und_x_variant":[
        "Mohannd Abd el Jellil",
        "Mohand Abd el Jellil"
    ],
    "wof:name":"Dar Mohannd Abd el Jellil",
    "wof:placetype":"locality"
},
  "geometry": {"coordinates":[-3.77278,34.25312],"type":"Point"}
}