{
  "type": "Feature",
  "properties": {
    "gn:admin1_code":"3.0",
    "gn:asciiname":"Douar Oulad Belaid",
    "gn:country_code":"MA",
    "gn:dem":345,
    "gn:feature_class":"P",
    "gn:feature_code":"PPL",
    "gn:name":"Douar Oulad Belaid",
    "gn:population":0,
    "gn:timezone":"Africa/Casablanca",
    "iso:country":"MA",
    "wof:name":"Douar Oulad Belaid",
    "wof:placetype":"locality"
},
  "geometry": {"coordinates":[-5.16765,34.23104],"type":"Point"}
}