{
  "type": "Feature",
  "properties": {
    "gn:admin1_code":"2.0",
    "gn:asciiname":"Douar Oulad Essaidi",
    "gn:country_code":"MA",
    "gn:dem":675,
    "gn:feature_class":"P",
    "gn:feature_code":"PPL",
    "gn:name":"Douar Oulad Essaidi",
    "gn:population":0,
    "gn:timezone":"Africa/Casablanca",
    "iso:country":"MA",
    "wof:name":"Douar Oulad Essaidi",
    "wof:placetype":"locality"
},
  "geometry": {"coordinates":[-1.91729,34.60848],"type":"Point"}
}