{
  "type": "Feature",
  "properties": {
    "gn:admin1_code":"7.0",
    "gn:asciiname":"Douar n'Ait Taik",
    "gn:country_code":"MA",
    "gn:dem":667,
    "gn:feature_class":"P",
    "gn:feature_code":"PPL",
    "gn:name":"Douar n\u2019A\u00eft Ta\u00efk",
    "gn:population":0,
    "gn:timezone":"Africa/Casablanca",
    "iso:country":"MA",
    "wof:name":"Douar n'Ait Taik",
    "wof:placetype":"locality"
},
  "geometry": {"coordinates":[-9.61175,30.89137],"type":"Point"}
}