{
  "type": "Feature",
  "properties": {
    "gn:admin1_code":"3.0",
    "gn:asciiname":"Douar Bni Mellah",
    "gn:country_code":"MA",
    "gn:dem":1245,
    "gn:feature_class":"P",
    "gn:feature_code":"PPL",
    "gn:name":"Douar Bni Mellah",
    "gn:population":0,
    "gn:timezone":"Africa/Casablanca",
    "iso:country":"MA",
    "wof:name":"Douar Bni Mellah",
    "wof:placetype":"locality"
},
  "geometry": {"coordinates":[-4.05449,34.04423],"type":"Point"}
}