{
  "type": "Feature",
  "properties": {
    "gn:admin1_code":"6.0",
    "gn:asciiname":"'Anabra",
    "gn:country_code":"MA",
    "gn:dem":273,
    "gn:feature_class":"P",
    "gn:feature_code":"PPL",
    "gn:name":"\u2019Anabra",
    "gn:population":0,
    "gn:timezone":"Africa/Casablanca",
    "iso:country":"MA",
    "wof:name":"'Anabra",
    "wof:placetype":"locality"
},
  "geometry": {"coordinates":[-7.92933,33.0245],"type":"Point"}
}