{
  "type": "Feature",
  "properties": {
    "gn:admin1_code":"5.0",
    "gn:asciiname":"Cherragat",
    "gn:country_code":"MA",
    "gn:dem":598,
    "gn:feature_class":"P",
    "gn:feature_code":"PPL",
    "gn:name":"Cherragat",
    "gn:population":0,
    "gn:timezone":"Africa/Casablanca",
    "iso:country":"MA",
    "wof:name":"Cherragat",
    "wof:placetype":"locality"
},
  "geometry": {"coordinates":[-6.84403,32.67737],"type":"Point"}
}