{
  "type": "Feature",
  "properties": {
    "gn:admin1_code":"01",
    "gn:asciiname":"Douar Lharich",
    "gn:country_code":"MA",
    "gn:dem":441,
    "gn:feature_class":"P",
    "gn:feature_code":"PPL",
    "gn:name":"Douar Lharich",
    "gn:population":0,
    "gn:timezone":"Africa/Casablanca",
    "iso:country":"MA",
    "name:und_x_variant":[
        "El Harech"
    ],
    "wof:name":"Douar Lharich",
    "wof:placetype":"locality"
},
  "geometry": {"coordinates":[-5.57089,35.32472],"type":"Point"}
}