{
  "type": "Feature",
  "properties": {
    "gn:admin1_code":"7.0",
    "gn:asciiname":"Ait Ouzineb",
    "gn:country_code":"MA",
    "gn:dem":591,
    "gn:feature_class":"P",
    "gn:feature_code":"PPL",
    "gn:name":"Ait Ouzineb",
    "gn:population":0,
    "gn:timezone":"Africa/Casablanca",
    "iso:country":"MA",
    "wof:name":"Ait Ouzineb",
    "wof:placetype":"locality"
},
  "geometry": {"coordinates":[-7.6924,31.61057000000001],"type":"Point"}
}