{
  "type": "Feature",
  "properties": {
    "gn:admin1_code":"03",
    "gn:asciiname":"Tikoutamine",
    "gn:country_code":"MA",
    "gn:dem":1130,
    "gn:feature_class":"P",
    "gn:feature_code":"PPL",
    "gn:name":"Tikoutamine",
    "gn:population":0,
    "gn:timezone":"Africa/Casablanca",
    "iso:country":"MA",
    "name:und_x_variant":[
        "Tougoutamine",
        "Tikoutamine"
    ],
    "wof:name":"Tikoutamine",
    "wof:placetype":"locality"
},
  "geometry": {"coordinates":[-4.06402,32.78025],"type":"Point"}
}