{
  "type": "Feature",
  "properties": {
    "gn:admin1_code":"6.0",
    "gn:asciiname":"Douar Dbalza",
    "gn:country_code":"MA",
    "gn:dem":396,
    "gn:feature_class":"P",
    "gn:feature_code":"PPL",
    "gn:name":"Douar Dbalza",
    "gn:population":0,
    "gn:timezone":"Africa/Casablanca",
    "iso:country":"MA",
    "wof:name":"Douar Dbalza",
    "wof:placetype":"locality"
},
  "geometry": {"coordinates":[-7.27621,32.51299],"type":"Point"}
}