{
  "type": "Feature",
  "properties": {
    "gn:admin1_code":"09",
    "gn:asciiname":"Ichnigline",
    "gn:country_code":"MA",
    "gn:dem":318,
    "gn:feature_class":"P",
    "gn:feature_code":"PPL",
    "gn:name":"Ichnigline",
    "gn:population":0,
    "gn:timezone":"Africa/Casablanca",
    "iso:country":"MA",
    "name:und_x_variant":[
        "Naiba",
        "Ichnegline",
        "Ichnigline"
    ],
    "wof:name":"Ichnigline",
    "wof:placetype":"locality"
},
  "geometry": {"coordinates":[-9.22639,30.1177],"type":"Point"}
}