{
  "type": "Feature",
  "properties": {
    "gn:admin1_code":"7.0",
    "gn:asciiname":"Imi Iguider",
    "gn:country_code":"MA",
    "gn:dem":1284,
    "gn:feature_class":"P",
    "gn:feature_code":"PPL",
    "gn:name":"Imi Iguider",
    "gn:population":0,
    "gn:timezone":"Africa/Casablanca",
    "iso:country":"MA",
    "wof:name":"Imi Iguider",
    "wof:placetype":"locality"
},
  "geometry": {"coordinates":[-9.20321,30.89954],"type":"Point"}
}