{
  "type": "Feature",
  "properties": {
    "gn:admin1_code":"05",
    "gn:asciiname":"Ayt Mohamed",
    "gn:country_code":"MA",
    "gn:dem":470,
    "gn:feature_class":"P",
    "gn:feature_code":"PPL",
    "gn:name":"Ayt Mohamed",
    "gn:population":0,
    "gn:timezone":"Africa/Casablanca",
    "iso:country":"MA",
    "name:ara_x_preferred":[
        "\u0622\u064a\u062a \u0627\u0645\u062d\u0645\u062f"
    ],
    "name:azb_x_preferred":[
        "\u0622\u06cc\u062a \u0627\u0645\u200c\u062d\u0627\u0645\u062f"
    ],
    "name:cat_x_preferred":[
        "Ait M'Hamed"
    ],
    "name:deu_x_preferred":[
        "A\u00eft M\u2019hamed"
    ],
    "name:fas_x_preferred":[
        "\u0622\u06cc\u062a \u0627\u0645\u200c\u062d\u0627\u0645\u062f"
    ],
    "name:fra_x_preferred":[
        "A\u00eft M'hamed"
    ],
    "name:ita_x_preferred":[
        "Ait M'Hamed"
    ],
    "name:und_x_variant":[
        "A\u00eft Mohamed",
        "A\u00eft M\u2019Hamed",
        "Douar A\u00eft Mohammed",
        "Ayt Mohamed"
    ],
    "wof:name":"Ayt Mohamed",
    "wof:placetype":"locality"
},
  "geometry": {"coordinates":[-6.97722,32.55624],"type":"Point"}
}