{
  "type": "Feature",
  "properties": {
    "gn:admin1_code":"10.0",
    "gn:asciiname":"Id Fard",
    "gn:country_code":"MA",
    "gn:dem":225,
    "gn:feature_class":"P",
    "gn:feature_code":"PPL",
    "gn:name":"Id Fard",
    "gn:population":0,
    "gn:timezone":"Africa/Casablanca",
    "iso:country":"MA",
    "wof:name":"Id Fard",
    "wof:placetype":"locality"
},
  "geometry": {"coordinates":[-9.99601,29.4143],"type":"Point"}
}