{
  "type": "Feature",
  "properties": {
    "gn:admin1_code":"7.0",
    "gn:asciiname":"Taddart",
    "gn:country_code":"MA",
    "gn:dem":984,
    "gn:feature_class":"P",
    "gn:feature_code":"PPL",
    "gn:name":"Taddart",
    "gn:population":0,
    "gn:timezone":"Africa/Casablanca",
    "iso:country":"MA",
    "wof:name":"Taddart",
    "wof:placetype":"locality"
},
  "geometry": {"coordinates":[-8.63416,31.20233],"type":"Point"}
}