{
  "type": "Feature",
  "properties": {
    "gn:admin1_code":"7.0",
    "gn:asciiname":"Taddart",
    "gn:country_code":"MA",
    "gn:dem":984,
    "gn:feature_class":"P",
    "gn:feature_code":"PPL",
    "gn:name":"Taddart",
    "gn:population":0,
    "gn:timezone":"Africa/Casablanca",
    "iso:country":"MA",
    "name:ara_x_preferred":[
        "\u062a\u0627\u062f\u0631\u062a"
    ],
    "name:cat_x_preferred":[
        "Taddart"
    ],
    "name:ceb_x_preferred":[
        "Taddart"
    ],
    "name:fra_x_preferred":[
        "Taddart"
    ],
    "name:swe_x_preferred":[
        "Taddart"
    ],
    "wof:name":"Taddart",
    "wof:placetype":"locality"
},
  "geometry": {"coordinates":[-8.63416,31.20233],"type":"Point"}
}