{
  "type": "Feature",
  "properties": {
    "gn:admin1_code":"09",
    "gn:asciiname":"Amzaour",
    "gn:country_code":"MA",
    "gn:dem":1558,
    "gn:feature_class":"P",
    "gn:feature_code":"PPL",
    "gn:name":"Amzaour",
    "gn:population":0,
    "gn:timezone":"Africa/Casablanca",
    "iso:country":"MA",
    "name:und_x_variant":[
        "Amezzaourou",
        "Amzaourou",
        "Amzaour"
    ],
    "wof:name":"Amzaour",
    "wof:placetype":"locality"
},
  "geometry": {"coordinates":[-8.74798,29.82806],"type":"Point"}
}