{
  "type": "Feature",
  "properties": {
    "gn:admin1_code":"9.0",
    "gn:asciiname":"Tagragra",
    "gn:country_code":"MA",
    "gn:dem":547,
    "gn:feature_class":"P",
    "gn:feature_code":"PPL",
    "gn:name":"Tagragra",
    "gn:population":0,
    "gn:timezone":"Africa/Casablanca",
    "iso:country":"MA",
    "wof:name":"Tagragra",
    "wof:placetype":"locality"
},
  "geometry": {"coordinates":[-9.23046,29.90142],"type":"Point"}
}