{
  "type": "Feature",
  "properties": {
    "gn:admin1_code":"8.0",
    "gn:asciiname":"Aghri",
    "gn:country_code":"MA",
    "gn:dem":1794,
    "gn:feature_class":"P",
    "gn:feature_code":"PPL",
    "gn:name":"Aghri",
    "gn:population":0,
    "gn:timezone":"Africa/Casablanca",
    "iso:country":"MA",
    "wof:name":"Aghri",
    "wof:placetype":"locality"
},
  "geometry": {"coordinates":[-6.86042,31.30353],"type":"Point"}
}