{
  "type": "Feature",
  "properties": {
    "gn:admin1_code":"08",
    "gn:asciiname":"Zaouia Sidi Ali",
    "gn:country_code":"MA",
    "gn:dem":692,
    "gn:feature_class":"P",
    "gn:feature_code":"PPL",
    "gn:name":"Zaouia Sidi Ali",
    "gn:population":0,
    "gn:timezone":"Africa/Casablanca",
    "iso:country":"MA",
    "wof:name":"Zaouia Sidi Ali",
    "wof:placetype":"locality"
},
  "geometry": {"coordinates":[-5.71,30.26],"type":"Point"}
}