{
  "type": "Feature",
  "properties": {
    "gn:admin1_code":"4.0",
    "gn:asciiname":"Fourar",
    "gn:country_code":"MA",
    "gn:dem":18,
    "gn:feature_class":"P",
    "gn:feature_code":"PPL",
    "gn:name":"Fourar",
    "gn:population":0,
    "gn:timezone":"Africa/Casablanca",
    "iso:country":"MA",
    "wof:name":"Fourar",
    "wof:placetype":"locality"
},
  "geometry": {"coordinates":[-6.0199,34.59256],"type":"Point"}
}