{
  "type": "Feature",
  "properties": {
    "gn:admin1_code":"09",
    "gn:asciiname":"Ikourane",
    "gn:country_code":"MA",
    "gn:dem":155,
    "gn:feature_class":"P",
    "gn:feature_code":"PPL",
    "gn:name":"Ikourane",
    "gn:population":0,
    "gn:timezone":"Africa/Casablanca",
    "iso:country":"MA",
    "name:und_x_variant":[
        "Kourene"
    ],
    "wof:name":"Ikourane",
    "wof:placetype":"locality"
},
  "geometry": {"coordinates":[-9.41539,29.93881],"type":"Point"}
}