{
  "type": "Feature",
  "properties": {
    "gn:admin1_code":"07",
    "gn:asciiname":"Kassine",
    "gn:country_code":"MA",
    "gn:dem":103,
    "gn:feature_class":"P",
    "gn:feature_code":"PPL",
    "gn:name":"Kassine",
    "gn:population":0,
    "gn:timezone":"Africa/Casablanca",
    "iso:country":"MA",
    "name:und_x_variant":[
        "Douar Kassine",
        "Kassine"
    ],
    "wof:name":"Kassine",
    "wof:placetype":"locality"
},
  "geometry": {"coordinates":[-9.17414,32.59096],"type":"Point"}
}