{
  "type": "Feature",
  "properties": {
    "gn:admin1_code":"09",
    "gn:asciiname":"Aguenza",
    "gn:country_code":"MA",
    "gn:dem":761,
    "gn:feature_class":"P",
    "gn:feature_code":"PPL",
    "gn:name":"Aguenza",
    "gn:population":0,
    "gn:timezone":"Africa/Casablanca",
    "iso:country":"MA",
    "name:und_x_variant":[
        "Aguinza",
        "Aguenza"
    ],
    "wof:name":"Aguenza",
    "wof:placetype":"locality"
},
  "geometry": {"coordinates":[-9.14522,30.75911],"type":"Point"}
}