{
  "type": "Feature",
  "properties": {
    "gn:admin1_code":"03",
    "gn:asciiname":"Douar Mhajer",
    "gn:country_code":"MA",
    "gn:dem":444,
    "gn:feature_class":"P",
    "gn:feature_code":"PPL",
    "gn:name":"Douar Mhajer",
    "gn:population":0,
    "gn:timezone":"Africa/Casablanca",
    "iso:country":"MA",
    "wof:name":"Douar Mhajer",
    "wof:placetype":"locality"
},
  "geometry": {"coordinates":[-4.72587,34.38127],"type":"Point"}
}