{
  "type": "Feature",
  "properties": {
    "gn:admin1_code":"2.0",
    "gn:asciiname":"Douar Ajdir",
    "gn:country_code":"MA",
    "gn:dem":966,
    "gn:feature_class":"P",
    "gn:feature_code":"PPL",
    "gn:name":"Douar Ajdir",
    "gn:population":0,
    "gn:timezone":"Africa/Casablanca",
    "iso:country":"MA",
    "wof:name":"Douar Ajdir",
    "wof:placetype":"locality"
},
  "geometry": {"coordinates":[-2.3361,34.77185],"type":"Point"}
}