{
  "type": "Feature",
  "properties": {
    "gn:admin1_code":"7.0",
    "gn:asciiname":"Ifagn",
    "gn:country_code":"MA",
    "gn:dem":1093,
    "gn:feature_class":"P",
    "gn:feature_code":"PPL",
    "gn:name":"Ifagn",
    "gn:population":0,
    "gn:timezone":"Africa/Casablanca",
    "iso:country":"MA",
    "wof:name":"Ifagn",
    "wof:placetype":"locality"
},
  "geometry": {"coordinates":[-7.62676,31.43527000000001],"type":"Point"}
}