{
  "type": "Feature",
  "properties": {
    "gn:admin1_code":"5.0",
    "gn:asciiname":"Dar Ait Abdi",
    "gn:country_code":"MA",
    "gn:dem":1711,
    "gn:feature_class":"P",
    "gn:feature_code":"PPL",
    "gn:name":"Dar A\u00eft Abdi",
    "gn:population":0,
    "gn:timezone":"Africa/Casablanca",
    "iso:country":"MA",
    "wof:name":"Dar Ait Abdi",
    "wof:placetype":"locality"
},
  "geometry": {"coordinates":[-7.07932,31.6211],"type":"Point"}
}