{
  "type": "Feature",
  "properties": {
    "gn:admin1_code":"1.0",
    "gn:asciiname":"Essayyida El Horra",
    "gn:country_code":"MA",
    "gn:dem":229,
    "gn:feature_class":"P",
    "gn:feature_code":"PPL",
    "gn:name":"Essayyida El Horra",
    "gn:population":0,
    "gn:timezone":"Africa/Casablanca",
    "iso:country":"MA",
    "wof:name":"Essayyida El Horra",
    "wof:placetype":"locality"
},
  "geometry": {"coordinates":[-5.4206,35.50125999999999],"type":"Point"}
}