{
  "type": "Feature",
  "properties": {
    "gn:country":"MA",
    "gn:fcode":"ADM3",
    "gn:population":13203,
    "iso:country":"MA",
    "name:ara_x_preferred":[
        "\u0627\u0645\u062e\u0627\u0644\u064a\u0641"
    ],
    "name:ara_x_variant":[
        "\u0633\u064a\u062f\u064a \u0644\u0639\u0631\u0648\u0633\u064a"
    ],
    "name:ary_x_preferred":[
        "\u0633\u064a\u062f\u064a \u0644\u0639\u0631\u0648\u0635\u064a"
    ],
    "name:cat_x_preferred":[
        "Sidi Laaroussi"
    ],
    "name:ceb_x_preferred":[
        "Sidi Laaroussi"
    ],
    "name:eng_x_preferred":[
        "Sidi Laaroussi"
    ],
    "name:fas_x_preferred":[
        "\u0633\u06cc\u062f\u06cc \u0644\u0639\u0631\u0648\u0633\u06cc"
    ],
    "name:fra_x_preferred":[
        "Sidi Laaroussi"
    ],
    "name:fra_x_variant":[
        "Sidi Laaroussi (CR)",
        "Sidi Laaroussi (Commune Rurale)"
    ],
    "name:ita_x_preferred":[
        "Sidi Laaroussi"
    ],
    "name:swe_x_preferred":[
        "Sidi Laaroussi"
    ],
    "qs:name":"Sidi Laaroussi",
    "qs:photos_9r":0,
    "qs:photos_sr":0,
    "qs:pop_sr":"6",
    "wd:wordcount":62,
    "wof:name":"Sidi Laaroussi",
    "wof:placetype":"localadmin",
    "wof:population":13203
},
  "geometry": {"coordinates":[-9.15476,31.81834],"type":"Point"}
}