{
  "type": "Feature",
  "properties": {
    "gn:admin1_code":"7.0",
    "gn:asciiname":"Maabt",
    "gn:country_code":"MA",
    "gn:dem":986,
    "gn:feature_class":"P",
    "gn:feature_code":"PPL",
    "gn:name":"Maabt",
    "gn:population":0,
    "gn:timezone":"Africa/Casablanca",
    "iso:country":"MA",
    "wof:name":"Maabt",
    "wof:placetype":"locality"
},
  "geometry": {"coordinates":[-7.34408,31.59132],"type":"Point"}
}