{
  "type": "Feature",
  "properties": {
    "gn:country":"MA",
    "gn:fcode":"ADM3",
    "gn:population":10500,
    "iso:country":"MA",
    "name:ara_x_preferred":[
        "\u0633\u064a\u062f\u064a \u0639\u0644\u064a \u0628\u0648\u0631\u0642\u0628\u0629"
    ],
    "name:ary_x_preferred":[
        "\u0633\u064a\u062f\u064a \u0639\u0644\u064a \u0628\u0648\u0631\u0643\u0628\u0629"
    ],
    "name:cat_x_preferred":[
        "Sidi Ali Bourakba"
    ],
    "name:ceb_x_preferred":[
        "Sidi Ali Bourakba"
    ],
    "name:eng_x_preferred":[
        "Sidi Ali Bourakba"
    ],
    "name:fra_x_preferred":[
        "Sidi Ali Bourakba"
    ],
    "name:fra_x_variant":[
        "Sidi Ali Bourakba (CR)",
        "Sidi Ali Bourakba (Commune Rurale)"
    ],
    "name:ita_x_preferred":[
        "Sidi Ali Bourakba"
    ],
    "name:spa_x_preferred":[
        "Sidi Ali Bourakba"
    ],
    "name:swe_x_preferred":[
        "Sidi Ali Bourakba"
    ],
    "qs:name":"Sidi Ali Bourakba",
    "qs:photos_9r":0,
    "qs:photos_sr":0,
    "qs:pop_sr":"6",
    "wd:wordcount":61,
    "wof:name":"Sidi Ali Bourakba",
    "wof:placetype":"localadmin",
    "wof:population":10500
},
  "geometry": {"coordinates":[-3.721,34.82167],"type":"Point"}
}