{
  "type": "Feature",
  "properties": {
    "gn:admin1_code":"10",
    "gn:asciiname":"Id Abeid",
    "gn:country_code":"MA",
    "gn:dem":1000,
    "gn:feature_class":"P",
    "gn:feature_code":"PPL",
    "gn:name":"Id Abeid",
    "gn:population":0,
    "gn:timezone":"Africa/Casablanca",
    "iso:country":"MA",
    "name:und_x_variant":[
        "Id Bela\u00efd",
        "Id A\u00e2bd",
        "Id Abeid"
    ],
    "wof:name":"Id Abeid",
    "wof:placetype":"locality"
},
  "geometry": {"coordinates":[-9.74679,29.23985],"type":"Point"}
}