{
  "type": "Feature",
  "properties": {
    "gn:admin1_code":"3.0",
    "gn:asciiname":"Douar Laamour",
    "gn:country_code":"MA",
    "gn:dem":118,
    "gn:feature_class":"P",
    "gn:feature_code":"PPL",
    "gn:name":"Douar Laamour",
    "gn:population":0,
    "gn:timezone":"Africa/Casablanca",
    "iso:country":"MA",
    "wof:name":"Douar Laamour",
    "wof:placetype":"locality"
},
  "geometry": {"coordinates":[-5.20188,34.28237],"type":"Point"}
}