{
  "type": "Feature",
  "properties": {
    "gn:admin1_code":"05",
    "gn:asciiname":"Igramane",
    "gn:country_code":"MA",
    "gn:dem":1179,
    "gn:feature_class":"P",
    "gn:feature_code":"PPL",
    "gn:name":"Igramane",
    "gn:population":0,
    "gn:timezone":"Africa/Casablanca",
    "iso:country":"MA",
    "wof:name":"Igramane",
    "wof:placetype":"locality"
},
  "geometry": {"coordinates":[-7.11038,31.53457],"type":"Point"}
}