{
  "type": "Feature",
  "properties": {
    "gn:admin1_code":"5.0",
    "gn:asciiname":"Aguerd -n- Oudra",
    "gn:country_code":"MA",
    "gn:dem":1418,
    "gn:feature_class":"P",
    "gn:feature_code":"PPL",
    "gn:name":"Aguerd -n- Oudra",
    "gn:population":0,
    "gn:timezone":"Africa/Casablanca",
    "iso:country":"MA",
    "wof:name":"Aguerd -n- Oudra",
    "wof:placetype":"locality"
},
  "geometry": {"coordinates":[-6.51946,32.0532],"type":"Point"}
}