{
  "type": "Feature",
  "properties": {
    "gn:admin1_code":"01",
    "gn:asciiname":"Douar Imaaroune",
    "gn:country_code":"MA",
    "gn:dem":104,
    "gn:feature_class":"P",
    "gn:feature_code":"PPL",
    "gn:name":"Douar Imaaroune",
    "gn:population":0,
    "gn:timezone":"Africa/Casablanca",
    "iso:country":"MA",
    "wof:name":"Douar Imaaroune",
    "wof:placetype":"locality"
},
  "geometry": {"coordinates":[-3.86924,35.16565],"type":"Point"}
}