{
  "type": "Feature",
  "properties": {
    "gn:admin1_code":"7.0",
    "gn:asciiname":"Jradat",
    "gn:country_code":"MA",
    "gn:dem":443,
    "gn:feature_class":"P",
    "gn:feature_code":"PPL",
    "gn:name":"Jradat",
    "gn:population":0,
    "gn:timezone":"Africa/Casablanca",
    "iso:country":"MA",
    "wof:name":"Jradat",
    "wof:placetype":"locality"
},
  "geometry": {"coordinates":[-9.05749,31.98565],"type":"Point"}
}