{
  "type": "Feature",
  "properties": {
    "gn:admin1_code":"9.0",
    "gn:asciiname":"Imi n'Tiguirt",
    "gn:country_code":"MA",
    "gn:dem":1236,
    "gn:feature_class":"P",
    "gn:feature_code":"PPL",
    "gn:name":"Imi n\u2019Tiguirt",
    "gn:population":0,
    "gn:timezone":"Africa/Casablanca",
    "iso:country":"MA",
    "wof:name":"Imi n'Tiguirt",
    "wof:placetype":"locality"
},
  "geometry": {"coordinates":[-9.4708,30.68052],"type":"Point"}
}