{
  "type": "Feature",
  "properties": {
    "gn:admin1_code":"7.0",
    "gn:asciiname":"Lahdadja",
    "gn:country_code":"MA",
    "gn:dem":119,
    "gn:feature_class":"P",
    "gn:feature_code":"PPL",
    "gn:name":"Lahdadja",
    "gn:population":0,
    "gn:timezone":"Africa/Casablanca",
    "iso:country":"MA",
    "wof:name":"Lahdadja",
    "wof:placetype":"locality"
},
  "geometry": {"coordinates":[-9.07125,32.35581],"type":"Point"}
}