{
  "type": "Feature",
  "properties": {
    "gn:admin1_code":"01",
    "gn:asciiname":"Sidi Ali Ben Demna",
    "gn:country_code":"MA",
    "gn:dem":34,
    "gn:feature_class":"P",
    "gn:feature_code":"PPL",
    "gn:name":"Sidi Ali Ben Demna",
    "gn:population":0,
    "gn:timezone":"Africa/Casablanca",
    "iso:country":"MA",
    "name:und_x_variant":[
        "Oulad Ali Medouna",
        "Ulad Aali Medina",
        "Oulad Ali Medoauna",
        "Sidi Ali Ben Demna"
    ],
    "wof:name":"Sidi Ali Ben Demna",
    "wof:placetype":"locality"
},
  "geometry": {"coordinates":[-5.85596,35.12694],"type":"Point"}
}