{
  "type": "Feature",
  "properties": {
    "gn:admin1_code":"07",
    "gn:asciiname":"Aghbalou",
    "gn:country_code":"MA",
    "gn:dem":1519,
    "gn:feature_class":"P",
    "gn:feature_code":"PPL",
    "gn:name":"Aghbalou",
    "gn:population":0,
    "gn:timezone":"Africa/Casablanca",
    "iso:country":"MA",
    "name:und_x_variant":[
        "Taourirt",
        "Arhbalou",
        "Aghaballou"
    ],
    "wof:name":"Aghbalou",
    "wof:placetype":"locality"
},
  "geometry": {"coordinates":[-8.89423,31.12093],"type":"Point"}
}