{
  "type": "Feature",
  "properties": {
    "gn:admin1_code":"4.0",
    "gn:asciiname":"Dar Driss Chafiqi",
    "gn:country_code":"MA",
    "gn:dem":355,
    "gn:feature_class":"P",
    "gn:feature_code":"PPL",
    "gn:name":"Dar Driss Chafiqi",
    "gn:population":0,
    "gn:timezone":"Africa/Casablanca",
    "iso:country":"MA",
    "wof:name":"Dar Driss Chafiqi",
    "wof:placetype":"locality"
},
  "geometry": {"coordinates":[-6.61322,33.73888],"type":"Point"}
}