{
  "type": "Feature",
  "properties": {
    "iso:country":"MA",
    "name:ara_x_preferred":[
        "\u062a\u064a\u0645\u062d\u0636\u064a\u062a"
    ],
    "name:eng_x_preferred":[
        "Timahdite"
    ],
    "qs:gn_pop":0,
    "qs:name":"\u062a\u064a\u0645\u062d\u0636\u064a\u062a",
    "qs:name_adm0":"\u0627\u0644\u0645\u063a\u0631\u0628",
    "qs:name_adm1":"\u0645\u0643\u0646\u0627\u0633 \u0640 \u062a\u0627\u0641\u064a\u0644\u0627\u0644\u062a",
    "qs:photos":45,
    "qs:photos_1k":9,
    "qs:photos_9k":1,
    "qs:photos_9r":2,
    "qs:photos_all":45,
    "qs:photos_sr":2,
    "qs:placetype":"Town",
    "qs:pop_sr":"0",
    "qs:woe_adm0":23424893,
    "wof:name":"Timahdite",
    "wof:placetype":"locality"
},
  "geometry": {"coordinates":[-5.068817,33.239944],"type":"Point"}
}