{
  "type": "Feature",
  "properties": {
    "gn:admin1_code":"09",
    "gn:asciiname":"Agadirane",
    "gn:country_code":"MA",
    "gn:dem":776,
    "gn:feature_class":"P",
    "gn:feature_code":"PPL",
    "gn:name":"Agadirane",
    "gn:population":0,
    "gn:timezone":"Africa/Casablanca",
    "iso:country":"MA",
    "name:und_x_variant":[
        "Agadiram",
        "Agadirene",
        "Agadirane"
    ],
    "wof:name":"Agadirane",
    "wof:placetype":"locality"
},
  "geometry": {"coordinates":[-9.20035,29.72928],"type":"Point"}
}