{
  "type": "Feature",
  "properties": {
    "gn:admin1_code":"01",
    "gn:asciiname":"Agarane",
    "gn:country_code":"MA",
    "gn:dem":524,
    "gn:feature_class":"P",
    "gn:feature_code":"PPL",
    "gn:name":"Agarane",
    "gn:population":0,
    "gn:timezone":"Africa/Casablanca",
    "iso:country":"MA",
    "name:und_x_variant":[
        "Agaran",
        "Agarane"
    ],
    "wof:name":"Agarane",
    "wof:placetype":"locality"
},
  "geometry": {"coordinates":[-4.61184,35.15763],"type":"Point"}
}