{
  "type": "Feature",
  "properties": {
    "gn:admin1_code":"01",
    "gn:asciiname":"Ait Ziam",
    "gn:country_code":"MA",
    "gn:dem":196,
    "gn:feature_class":"P",
    "gn:feature_code":"PPL",
    "gn:name":"A\u00eft Ziam",
    "gn:population":0,
    "gn:timezone":"Africa/Casablanca",
    "iso:country":"MA",
    "wof:name":"Ait Ziam",
    "wof:placetype":"locality"
},
  "geometry": {"coordinates":[-3.98965,35.0905],"type":"Point"}
}