{
  "type": "Feature",
  "properties": {
    "gn:admin1_code":"05",
    "gn:asciiname":"Ayt 'Alwi",
    "gn:country_code":"MA",
    "gn:dem":449,
    "gn:feature_class":"P",
    "gn:feature_code":"PPL",
    "gn:name":"Ayt \u2019Alwi",
    "gn:population":0,
    "gn:timezone":"Africa/Casablanca",
    "iso:country":"MA",
    "name:und_x_variant":[
        "Ayt \u2019Alwi",
        "A\u00eft Olroum"
    ],
    "wof:name":"Ayt 'Alwi",
    "wof:placetype":"locality"
},
  "geometry": {"coordinates":[-6.55359,32.22915],"type":"Point"}
}