{
  "type": "Feature",
  "properties": {
    "gn:admin1_code":"3.0",
    "gn:asciiname":"Karia Leqdima",
    "gn:country_code":"MA",
    "gn:dem":163,
    "gn:feature_class":"P",
    "gn:feature_code":"PPL",
    "gn:name":"Karia Leqdima",
    "gn:population":0,
    "gn:timezone":"Africa/Casablanca",
    "iso:country":"MA",
    "wof:name":"Karia Leqdima",
    "wof:placetype":"locality"
},
  "geometry": {"coordinates":[-5.22314,34.36923],"type":"Point"}
}