{
  "type": "Feature",
  "properties": {
    "gn:admin1_code":"03",
    "gn:asciiname":"Douar Laalalma",
    "gn:country_code":"MA",
    "gn:dem":882,
    "gn:feature_class":"P",
    "gn:feature_code":"PPL",
    "gn:name":"Douar Laalalma",
    "gn:population":0,
    "gn:timezone":"Africa/Casablanca",
    "iso:country":"MA",
    "name:und_x_variant":[
        "Douar Lallama",
        "Laalama"
    ],
    "wof:name":"Douar Laalalma",
    "wof:placetype":"locality"
},
  "geometry": {"coordinates":[-4.23346,34.35595],"type":"Point"}
}