{
  "type": "Feature",
  "properties": {
    "gn:admin1_code":"07",
    "gn:asciiname":"Rmel",
    "gn:country_code":"MA",
    "gn:dem":80,
    "gn:feature_class":"P",
    "gn:feature_code":"PPL",
    "gn:name":"Rmel",
    "gn:population":0,
    "gn:timezone":"Africa/Casablanca",
    "iso:country":"MA",
    "name:und_x_variant":[
        "Oulad Ben Rehal"
    ],
    "wof:name":"Rmel",
    "wof:placetype":"locality"
},
  "geometry": {"coordinates":[-9.12443,32.4407],"type":"Point"}
}