{
  "type": "Feature",
  "properties": {
    "gn:admin1_code":"9.0",
    "gn:asciiname":"Ighirm",
    "gn:country_code":"MA",
    "gn:dem":1136,
    "gn:feature_class":"P",
    "gn:feature_code":"PPL",
    "gn:name":"Ighirm",
    "gn:population":0,
    "gn:timezone":"Africa/Casablanca",
    "iso:country":"MA",
    "wof:name":"Ighirm",
    "wof:placetype":"locality"
},
  "geometry": {"coordinates":[-9.12283,29.73423],"type":"Point"}
}