{
  "type": "Feature",
  "properties": {
    "gn:admin1_code":"9.0",
    "gn:asciiname":"Tou Ben Hammou",
    "gn:country_code":"MA",
    "gn:dem":156,
    "gn:feature_class":"P",
    "gn:feature_code":"PPL",
    "gn:name":"Tou Ben Hammou",
    "gn:population":0,
    "gn:timezone":"Africa/Casablanca",
    "iso:country":"MA",
    "wof:name":"Tou Ben Hammou",
    "wof:placetype":"locality"
},
  "geometry": {"coordinates":[-9.31141,30.22579],"type":"Point"}
}