{
  "type": "Feature",
  "properties": {
    "gn:admin1_code":"08",
    "gn:asciiname":"Ait Ou Mazir",
    "gn:country_code":"MA",
    "gn:dem":1618,
    "gn:feature_class":"P",
    "gn:feature_code":"PPL",
    "gn:name":"A\u00eft Ou Mazir",
    "gn:population":0,
    "gn:timezone":"Africa/Casablanca",
    "iso:country":"MA",
    "wof:name":"Ait Ou Mazir",
    "wof:placetype":"locality"
},
  "geometry": {"coordinates":[-7.13617,31.21519],"type":"Point"}
}