{
  "type": "Feature",
  "properties": {
    "gn:admin1_code":"3.0",
    "gn:asciiname":"Douar Ali Ou Balboub",
    "gn:country_code":"MA",
    "gn:dem":1515,
    "gn:feature_class":"P",
    "gn:feature_code":"PPL",
    "gn:name":"Douar Ali Ou Balboub",
    "gn:population":0,
    "gn:timezone":"Africa/Casablanca",
    "iso:country":"MA",
    "wof:name":"Douar Ali Ou Balboub",
    "wof:placetype":"locality"
},
  "geometry": {"coordinates":[-4.76546,33.59898],"type":"Point"}
}