{
  "type": "Feature",
  "properties": {
    "gn:admin1_code":"03",
    "gn:asciiname":"Iharechliene",
    "gn:country_code":"MA",
    "gn:dem":1083,
    "gn:feature_class":"P",
    "gn:feature_code":"PPL",
    "gn:name":"Iharechliene",
    "gn:population":0,
    "gn:timezone":"Africa/Casablanca",
    "iso:country":"MA",
    "name:und_x_variant":[
        "Iharchli\u00e8ne",
        "Douar Iherouchene",
        "Iharechliene"
    ],
    "wof:name":"Iharechliene",
    "wof:placetype":"locality"
},
  "geometry": {"coordinates":[-3.96448,34.73315],"type":"Point"}
}