{
  "type": "Feature",
  "properties": {
    "gn:admin1_code":"7.0",
    "gn:asciiname":"Toulaoualt",
    "gn:country_code":"MA",
    "gn:dem":1335,
    "gn:feature_class":"P",
    "gn:feature_code":"PPL",
    "gn:name":"Toulaoualt",
    "gn:population":0,
    "gn:timezone":"Africa/Casablanca",
    "iso:country":"MA",
    "wof:name":"Toulaoualt",
    "wof:placetype":"locality"
},
  "geometry": {"coordinates":[-9.19586,31.00291],"type":"Point"}
}