{
  "type": "Feature",
  "properties": {
    "gn:admin1_code":"7.0",
    "gn:asciiname":"Al Falah",
    "gn:country_code":"MA",
    "gn:dem":614,
    "gn:feature_class":"P",
    "gn:feature_code":"PPL",
    "gn:name":"Al Falah",
    "gn:population":0,
    "gn:timezone":"Africa/Casablanca",
    "iso:country":"MA",
    "wof:name":"Al Falah",
    "wof:placetype":"locality"
},
  "geometry": {"coordinates":[-7.41693,31.82478],"type":"Point"}
}