{
  "type": "Feature",
  "properties": {
    "gn:admin1_code":"07",
    "gn:asciiname":"Bou Haddou",
    "gn:country_code":"MA",
    "gn:dem":795,
    "gn:feature_class":"P",
    "gn:feature_code":"PPL",
    "gn:name":"Bou Haddou",
    "gn:population":0,
    "gn:timezone":"Africa/Casablanca",
    "iso:country":"MA",
    "name:und_x_variant":[
        "Bouhadou",
        "Bou Haddou"
    ],
    "wof:name":"Bou Haddou",
    "wof:placetype":"locality"
},
  "geometry": {"coordinates":[-7.77696,31.40997],"type":"Point"}
}