{
  "type": "Feature",
  "properties": {
    "gn:admin1_code":"01",
    "gn:asciiname":"Aguebal",
    "gn:country_code":"MA",
    "gn:dem":843,
    "gn:feature_class":"P",
    "gn:feature_code":"PPL",
    "gn:name":"Aguebal",
    "gn:population":0,
    "gn:timezone":"Africa/Casablanca",
    "iso:country":"MA",
    "wof:name":"Aguebal",
    "wof:placetype":"locality"
},
  "geometry": {"coordinates":[-4.62368,34.79711],"type":"Point"}
}