{
  "type": "Feature",
  "properties": {
    "gn:admin1_code":"01",
    "gn:asciiname":"Douar Mesker",
    "gn:country_code":"MA",
    "gn:dem":304,
    "gn:feature_class":"P",
    "gn:feature_code":"PPL",
    "gn:name":"Douar Mesker",
    "gn:population":0,
    "gn:timezone":"Africa/Casablanca",
    "iso:country":"MA",
    "name:und_x_variant":[
        "Mesker"
    ],
    "wof:name":"Douar Mesker",
    "wof:placetype":"locality"
},
  "geometry": {"coordinates":[-5.39484,34.58955],"type":"Point"}
}