{
  "type": "Feature",
  "properties": {
    "gn:admin1_code":"09",
    "gn:asciiname":"Ikhoulane",
    "gn:country_code":"MA",
    "gn:dem":1234,
    "gn:feature_class":"P",
    "gn:feature_code":"PPL",
    "gn:name":"Ikhoulane",
    "gn:population":0,
    "gn:timezone":"Africa/Casablanca",
    "iso:country":"MA",
    "name:und_x_variant":[
        "Ikhoullane"
    ],
    "wof:name":"Ikhoulane",
    "wof:placetype":"locality"
},
  "geometry": {"coordinates":[-8.97402,29.8332],"type":"Point"}
}