{
  "type": "Feature",
  "properties": {
    "gn:admin1_code":"9.0",
    "gn:asciiname":"Tasguint",
    "gn:country_code":"MA",
    "gn:dem":1115,
    "gn:feature_class":"P",
    "gn:feature_code":"PPL",
    "gn:name":"Tasguint",
    "gn:population":0,
    "gn:timezone":"Africa/Casablanca",
    "iso:country":"MA",
    "wof:name":"Tasguint",
    "wof:placetype":"locality"
},
  "geometry": {"coordinates":[-9.02166,29.90662],"type":"Point"}
}