{
  "type": "Feature",
  "properties": {
    "gn:admin1_code":"7.0",
    "gn:asciiname":"Douar Sidi Lahsen",
    "gn:country_code":"MA",
    "gn:dem":530,
    "gn:feature_class":"P",
    "gn:feature_code":"PPL",
    "gn:name":"Douar Sidi Lahsen",
    "gn:population":0,
    "gn:timezone":"Africa/Casablanca",
    "iso:country":"MA",
    "wof:name":"Douar Sidi Lahsen",
    "wof:placetype":"locality"
},
  "geometry": {"coordinates":[-9.5078,31.41214],"type":"Point"}
}