{
  "type": "Feature",
  "properties": {
    "gn:admin1_code":"3.0",
    "gn:asciiname":"Douar Bisabsa",
    "gn:country_code":"MA",
    "gn:dem":378,
    "gn:feature_class":"P",
    "gn:feature_code":"PPL",
    "gn:name":"Douar Bisabsa",
    "gn:population":0,
    "gn:timezone":"Africa/Casablanca",
    "iso:country":"MA",
    "wof:name":"Douar Bisabsa",
    "wof:placetype":"locality"
},
  "geometry": {"coordinates":[-4.7176,34.36274],"type":"Point"}
}