{
  "type": "Feature",
  "properties": {
    "gn:admin1_code":"04",
    "gn:asciiname":"Lehricha",
    "gn:country_code":"MA",
    "gn:dem":62,
    "gn:feature_class":"P",
    "gn:feature_code":"PPL",
    "gn:name":"Lehricha",
    "gn:population":0,
    "gn:timezone":"Africa/Casablanca",
    "iso:country":"MA",
    "name:und_x_variant":[
        "Douar el Haricha",
        "El Hararcha",
        "El Haricha",
        "Lehricha"
    ],
    "wof:name":"Lehricha",
    "wof:placetype":"locality"
},
  "geometry": {"coordinates":[-5.56779,34.57065],"type":"Point"}
}