{
  "type": "Feature",
  "properties": {
    "gn:admin1_code":"06",
    "gn:asciiname":"Douar Ahmed el Cheikh",
    "gn:country_code":"MA",
    "gn:dem":206,
    "gn:feature_class":"P",
    "gn:feature_code":"PPL",
    "gn:name":"Douar Ahmed el Che\u00efkh",
    "gn:population":0,
    "gn:timezone":"Africa/Casablanca",
    "iso:country":"MA",
    "name:und_x_variant":[
        "Douar Ahmed Lecheb",
        "Douar Ahmed el Che\u00efkh"
    ],
    "wof:name":"Douar Ahmed el Cheikh",
    "wof:placetype":"locality"
},
  "geometry": {"coordinates":[-8.59657,32.46935999999999],"type":"Point"}
}