{
  "type": "Feature",
  "properties": {
    "gn:admin1_code":"6.0",
    "gn:asciiname":"Bwirat",
    "gn:country_code":"MA",
    "gn:dem":617,
    "gn:feature_class":"P",
    "gn:feature_code":"PPL",
    "gn:name":"Bwirat",
    "gn:population":0,
    "gn:timezone":"Africa/Casablanca",
    "iso:country":"MA",
    "wof:name":"Bwirat",
    "wof:placetype":"locality"
},
  "geometry": {"coordinates":[-7.15702,32.70242],"type":"Point"}
}