{
  "type": "Feature",
  "properties": {
    "gn:admin1_code":"09",
    "gn:asciiname":"Zawyat-n-Iguer",
    "gn:country_code":"MA",
    "gn:dem":916,
    "gn:feature_class":"P",
    "gn:feature_code":"PPL",
    "gn:name":"Zawyat-n-Iguer",
    "gn:population":0,
    "gn:timezone":"Africa/Casablanca",
    "iso:country":"MA",
    "name:und_x_variant":[
        "Zaouia n\u2019Iguerbeziz"
    ],
    "wof:name":"Zawyat-n-Iguer",
    "wof:placetype":"locality"
},
  "geometry": {"coordinates":[-8.47945,30.77215],"type":"Point"}
}