{
  "type": "Feature",
  "properties": {
    "gn:admin1_code":"7.0",
    "gn:asciiname":"Jbabra",
    "gn:country_code":"MA",
    "gn:dem":193,
    "gn:feature_class":"P",
    "gn:feature_code":"PPL",
    "gn:name":"Jbabra",
    "gn:population":0,
    "gn:timezone":"Africa/Casablanca",
    "iso:country":"MA",
    "name:ara_x_preferred":[
        "\u0627\u062c\u0628\u0627\u0628\u0631\u0629"
    ],
    "name:cat_x_preferred":[
        "Jbabra"
    ],
    "name:ceb_x_preferred":[
        "Jbabra"
    ],
    "name:ita_x_preferred":[
        "Jbabra"
    ],
    "name:swe_x_preferred":[
        "Jbabra"
    ],
    "wof:name":"Jbabra",
    "wof:placetype":"locality"
},
  "geometry": {"coordinates":[-9.54403,31.59589],"type":"Point"}
}