{
  "type": "Feature",
  "properties": {
    "gn:admin1_code":"03",
    "gn:asciiname":"'Ain Ghattab",
    "gn:country_code":"MA",
    "gn:dem":491,
    "gn:feature_class":"P",
    "gn:feature_code":"PPL",
    "gn:name":"\u2019A\u00efn Ghattab",
    "gn:population":0,
    "gn:timezone":"Africa/Casablanca",
    "iso:country":"MA",
    "wof:name":"'Ain Ghattab",
    "wof:placetype":"locality"
},
  "geometry": {"coordinates":[-4.99267,34.7008],"type":"Point"}
}