{
  "type": "Feature",
  "properties": {
    "gn:admin1_code":"09",
    "gn:asciiname":"Imrzgane",
    "gn:country_code":"MA",
    "gn:dem":1334,
    "gn:feature_class":"P",
    "gn:feature_code":"PPL",
    "gn:name":"Imrzgane",
    "gn:population":0,
    "gn:timezone":"Africa/Casablanca",
    "iso:country":"MA",
    "name:und_x_variant":[
        "Imezgane"
    ],
    "wof:name":"Imrzgane",
    "wof:placetype":"locality"
},
  "geometry": {"coordinates":[-9.21565,29.62363],"type":"Point"}
}