{
  "type": "Feature",
  "properties": {
    "gn:admin1_code":"07",
    "gn:asciiname":"Tagradjout",
    "gn:country_code":"MA",
    "gn:dem":572,
    "gn:feature_class":"P",
    "gn:feature_code":"PPL",
    "gn:name":"Tagradjout",
    "gn:population":0,
    "gn:timezone":"Africa/Casablanca",
    "iso:country":"MA",
    "name:und_x_variant":[
        "A\u00efn Tagrajout",
        "Tagradjoute",
        "Tagradjout",
        "Tagrajout"
    ],
    "wof:name":"Tagradjout",
    "wof:placetype":"locality"
},
  "geometry": {"coordinates":[-9.5054,30.94548],"type":"Point"}
}