{
  "type": "Feature",
  "properties": {
    "gn:admin1_code":"1.0",
    "gn:asciiname":"Douar Braghi",
    "gn:country_code":"MA",
    "gn:dem":242,
    "gn:feature_class":"P",
    "gn:feature_code":"PPL",
    "gn:name":"Douar Braghi",
    "gn:population":0,
    "gn:timezone":"Africa/Casablanca",
    "iso:country":"MA",
    "wof:name":"Douar Braghi",
    "wof:placetype":"locality"
},
  "geometry": {"coordinates":[-5.59226,35.57394],"type":"Point"}
}