{
  "type": "Feature",
  "properties": {
    "gn:admin1_code":"04",
    "gn:asciiname":"Oulad Talha Lehbabna",
    "gn:country_code":"MA",
    "gn:dem":16,
    "gn:feature_class":"P",
    "gn:feature_code":"PPL",
    "gn:name":"Oulad Talha Lehbabna",
    "gn:population":0,
    "gn:timezone":"Africa/Casablanca",
    "iso:country":"MA",
    "name:und_x_variant":[
        "Oulad Talha"
    ],
    "wof:name":"Oulad Talha Lehbabna",
    "wof:placetype":"locality"
},
  "geometry": {"coordinates":[-6.22765,34.75743],"type":"Point"}
}