{
  "type": "Feature",
  "properties": {
    "gn:admin1_code":"7.0",
    "gn:asciiname":"Eddchar",
    "gn:country_code":"MA",
    "gn:dem":479,
    "gn:feature_class":"P",
    "gn:feature_code":"PPL",
    "gn:name":"Eddchar",
    "gn:population":0,
    "gn:timezone":"Africa/Casablanca",
    "iso:country":"MA",
    "wof:name":"Eddchar",
    "wof:placetype":"locality"
},
  "geometry": {"coordinates":[-9.65319,31.20043],"type":"Point"}
}