{
  "type": "Feature",
  "properties": {
    "gn:admin1_code":"05",
    "gn:asciiname":"Ait Bou Zid",
    "gn:country_code":"MA",
    "gn:dem":577,
    "gn:feature_class":"P",
    "gn:feature_code":"PPL",
    "gn:name":"A\u00eft Bou Zid",
    "gn:population":0,
    "gn:timezone":"Africa/Casablanca",
    "iso:country":"MA",
    "wof:name":"Ait Bou Zid",
    "wof:placetype":"locality"
},
  "geometry": {"coordinates":[-6.45902,32.21505],"type":"Point"}
}