{
  "type": "Feature",
  "properties": {
    "gn:admin1_code":"03",
    "gn:asciiname":"Douar Lmeqrinat",
    "gn:country_code":"MA",
    "gn:dem":657,
    "gn:feature_class":"P",
    "gn:feature_code":"PPL",
    "gn:name":"Douar Lmeqrinat",
    "gn:population":0,
    "gn:timezone":"Africa/Casablanca",
    "iso:country":"MA",
    "name:und_x_variant":[
        "Koudiat Mokhinat",
        "El Mokrinat",
        "Douar Lmeqrinat"
    ],
    "wof:name":"Douar Lmeqrinat",
    "wof:placetype":"locality"
},
  "geometry": {"coordinates":[-4.54445,33.94338],"type":"Point"}
}