{
  "type": "Feature",
  "properties": {
    "gn:admin1_code":"3.0",
    "gn:asciiname":"Dar Ettijani Omar",
    "gn:country_code":"MA",
    "gn:dem":1237,
    "gn:feature_class":"P",
    "gn:feature_code":"PPL",
    "gn:name":"Dar Ettijani Omar",
    "gn:population":0,
    "gn:timezone":"Africa/Casablanca",
    "iso:country":"MA",
    "wof:name":"Dar Ettijani Omar",
    "wof:placetype":"locality"
},
  "geometry": {"coordinates":[-5.64045,33.51446],"type":"Point"}
}