{
  "type": "Feature",
  "properties": {
    "gn:admin1_code":"7.0",
    "gn:asciiname":"Lougrich Qedim",
    "gn:country_code":"MA",
    "gn:dem":777,
    "gn:feature_class":"P",
    "gn:feature_code":"PPL",
    "gn:name":"Lougrich Qedim",
    "gn:population":0,
    "gn:timezone":"Africa/Casablanca",
    "iso:country":"MA",
    "wof:name":"Lougrich Qedim",
    "wof:placetype":"locality"
},
  "geometry": {"coordinates":[-7.97378,31.41658],"type":"Point"}
}