{
  "type": "Feature",
  "properties": {
    "gn:admin1_code":"09",
    "gn:asciiname":"Targa-n-Oufra",
    "gn:country_code":"MA",
    "gn:dem":1742,
    "gn:feature_class":"P",
    "gn:feature_code":"PPL",
    "gn:name":"Targa-n-Oufra",
    "gn:population":0,
    "gn:timezone":"Africa/Casablanca",
    "iso:country":"MA",
    "name:und_x_variant":[
        "Targa",
        "Agadir oufra",
        "Agadir n\u2019 Afra"
    ],
    "wof:name":"Targa-n-Oufra",
    "wof:placetype":"locality"
},
  "geometry": {"coordinates":[-8.0719,30.89682],"type":"Point"}
}