{
  "type": "Feature",
  "properties": {
    "gn:admin1_code":"1.0",
    "gn:asciiname":"Aouechtame Soufla",
    "gn:country_code":"MA",
    "gn:dem":28,
    "gn:feature_class":"P",
    "gn:feature_code":"PPL",
    "gn:name":"Aouechtame Soufla",
    "gn:population":0,
    "gn:timezone":"Africa/Casablanca",
    "iso:country":"MA",
    "wof:name":"Aouechtame Soufla",
    "wof:placetype":"locality"
},
  "geometry": {"coordinates":[-5.13201,35.42111],"type":"Point"}
}