{
  "type": "Feature",
  "properties": {
    "gn:admin1_code":"1.0",
    "gn:asciiname":"Douar Itiganiaroune",
    "gn:country_code":"MA",
    "gn:dem":843,
    "gn:feature_class":"P",
    "gn:feature_code":"PPL",
    "gn:name":"Douar Itiganiaroune",
    "gn:population":0,
    "gn:timezone":"Africa/Casablanca",
    "iso:country":"MA",
    "wof:name":"Douar Itiganiaroune",
    "wof:placetype":"locality"
},
  "geometry": {"coordinates":[-4.12631,35.01657],"type":"Point"}
}