{
  "type": "Feature",
  "properties": {
    "gn:admin1_code":"6.0",
    "gn:asciiname":"Sgamna",
    "gn:country_code":"MA",
    "gn:dem":606,
    "gn:feature_class":"P",
    "gn:feature_code":"PPL",
    "gn:name":"Sgamna",
    "gn:population":0,
    "gn:timezone":"Africa/Casablanca",
    "iso:country":"MA",
    "name:ara_x_preferred":[
        "\u0627\u0644\u0633\u06ad\u0627\u0645\u0646\u0629"
    ],
    "name:cat_x_preferred":[
        "Sgamna"
    ],
    "name:ceb_x_preferred":[
        "Sgamna"
    ],
    "name:ita_x_preferred":[
        "Sgamna"
    ],
    "name:swe_x_preferred":[
        "Sgamna"
    ],
    "wof:name":"Sgamna",
    "wof:placetype":"locality"
},
  "geometry": {"coordinates":[-7.20314,32.73437],"type":"Point"}
}