{
  "type": "Feature",
  "properties": {
    "gn:admin1_code":"09",
    "gn:asciiname":"Irhilane",
    "gn:country_code":"MA",
    "gn:dem":446,
    "gn:feature_class":"P",
    "gn:feature_code":"PPL",
    "gn:name":"Irhilane",
    "gn:population":0,
    "gn:timezone":"Africa/Casablanca",
    "iso:country":"MA",
    "name:und_x_variant":[
        "Ighirane",
        "Ighilene",
        "Irhil\u00e8n",
        "Ighzzilen",
        "Iyhilalen",
        "Irhilene",
        "Irhilane"
    ],
    "wof:name":"Irhilane",
    "wof:placetype":"locality"
},
  "geometry": {"coordinates":[-8.8234,30.347],"type":"Point"}
}