{
  "type": "Feature",
  "properties": {
    "gn:admin1_code":"3.0",
    "gn:asciiname":"Douar Ait Alihen",
    "gn:country_code":"MA",
    "gn:dem":740,
    "gn:feature_class":"P",
    "gn:feature_code":"PPL",
    "gn:name":"Douar Ait Alihen",
    "gn:population":0,
    "gn:timezone":"Africa/Casablanca",
    "iso:country":"MA",
    "wof:name":"Douar Ait Alihen",
    "wof:placetype":"locality"
},
  "geometry": {"coordinates":[-4.8015,33.863],"type":"Point"}
}