{
  "type": "Feature",
  "properties": {
    "gn:admin1_code":"4.0",
    "gn:asciiname":"Dar Louachami",
    "gn:country_code":"MA",
    "gn:dem":205,
    "gn:feature_class":"P",
    "gn:feature_code":"PPL",
    "gn:name":"Dar Louachami",
    "gn:population":0,
    "gn:timezone":"Africa/Casablanca",
    "iso:country":"MA",
    "wof:name":"Dar Louachami",
    "wof:placetype":"locality"
},
  "geometry": {"coordinates":[-6.85048,33.84064],"type":"Point"}
}