{
  "type": "Feature",
  "properties": {
    "gn:admin1_code":"08",
    "gn:asciiname":"El Borouj",
    "gn:country_code":"MA",
    "gn:dem":815,
    "gn:feature_class":"P",
    "gn:feature_code":"PPL",
    "gn:name":"El Borouj",
    "gn:population":0,
    "gn:timezone":"Africa/Casablanca",
    "iso:country":"MA",
    "name:ara_x_preferred":[
        "\u0627\u0644\u0628\u0631\u0648\u062c"
    ],
    "name:cat_x_preferred":[
        "El Borouj"
    ],
    "name:deu_x_preferred":[
        "El Borouj"
    ],
    "name:fra_x_preferred":[
        "El Borouj"
    ],
    "name:ita_x_preferred":[
        "El Borouj"
    ],
    "name:und_x_variant":[
        "Broj"
    ],
    "wof:name":"El Borouj",
    "wof:placetype":"locality"
},
  "geometry": {"coordinates":[-4.18,31.48],"type":"Point"}
}