{
  "type": "Feature",
  "properties": {
    "gn:admin1_code":"08",
    "gn:asciiname":"El Borouj",
    "gn:country_code":"MA",
    "gn:dem":815,
    "gn:feature_class":"P",
    "gn:feature_code":"PPL",
    "gn:name":"El Borouj",
    "gn:population":0,
    "gn:timezone":"Africa/Casablanca",
    "iso:country":"MA",
    "name:und_x_variant":[
        "Broj",
        "El Borouj"
    ],
    "wof:name":"El Borouj",
    "wof:placetype":"locality"
},
  "geometry": {"coordinates":[-4.18,31.48],"type":"Point"}
}