{
  "type": "Feature",
  "properties": {
    "gn:admin1_code":"07",
    "gn:asciiname":"Guers",
    "gn:country_code":"MA",
    "gn:dem":747,
    "gn:feature_class":"P",
    "gn:feature_code":"PPL",
    "gn:name":"Guers",
    "gn:population":0,
    "gn:timezone":"Africa/Casablanca",
    "iso:country":"MA",
    "name:und_x_variant":[
        "Guarsse",
        "Guers"
    ],
    "wof:name":"Guers",
    "wof:placetype":"locality"
},
  "geometry": {"coordinates":[-7.62508,31.5356],"type":"Point"}
}