{
  "type": "Feature",
  "properties": {
    "gn:admin1_code":"07",
    "gn:asciiname":"Mohammed Ben Abdarrahmane",
    "gn:country_code":"MA",
    "gn:dem":604,
    "gn:feature_class":"P",
    "gn:feature_code":"PPL",
    "gn:name":"Mohammed Ben Abdarrahmane",
    "gn:population":0,
    "gn:timezone":"Africa/Casablanca",
    "iso:country":"MA",
    "wof:name":"Mohammed Ben Abdarrahmane",
    "wof:placetype":"locality"
},
  "geometry": {"coordinates":[-8.23,31.45],"type":"Point"}
}