{
  "type": "Feature",
  "properties": {
    "gn:admin1_code":"03",
    "gn:asciiname":"Oulad Mohammed",
    "gn:country_code":"MA",
    "gn:dem":853,
    "gn:feature_class":"P",
    "gn:feature_code":"PPL",
    "gn:name":"Oulad Mohammed",
    "gn:population":0,
    "gn:timezone":"Africa/Casablanca",
    "iso:country":"MA",
    "wof:name":"Oulad Mohammed",
    "wof:placetype":"locality"
},
  "geometry": {"coordinates":[-4.5452,33.83618],"type":"Point"}
}