{
  "type": "Feature",
  "properties": {
    "gn:admin1_code":"7.0",
    "gn:asciiname":"Douar Jaaouqa",
    "gn:country_code":"MA",
    "gn:dem":324,
    "gn:feature_class":"P",
    "gn:feature_code":"PPL",
    "gn:name":"Douar Jaaouqa",
    "gn:population":0,
    "gn:timezone":"Africa/Casablanca",
    "iso:country":"MA",
    "wof:name":"Douar Jaaouqa",
    "wof:placetype":"locality"
},
  "geometry": {"coordinates":[-8.8269,31.80267000000001],"type":"Point"}
}