{
  "type": "Feature",
  "properties": {
    "gn:admin1_code":"6.0",
    "gn:asciiname":"Laarad",
    "gn:country_code":"MA",
    "gn:dem":329,
    "gn:feature_class":"P",
    "gn:feature_code":"PPL",
    "gn:name":"Laarad",
    "gn:population":0,
    "gn:timezone":"Africa/Casablanca",
    "iso:country":"MA",
    "wof:name":"Laarad",
    "wof:placetype":"locality"
},
  "geometry": {"coordinates":[-7.03322,33.35440999999999],"type":"Point"}
}