{
  "type": "Feature",
  "properties": {
    "gn:admin1_code":"9.0",
    "gn:asciiname":"Cimilf",
    "gn:country_code":"MA",
    "gn:dem":666,
    "gn:feature_class":"P",
    "gn:feature_code":"PPL",
    "gn:name":"Cimilf",
    "gn:population":0,
    "gn:timezone":"Africa/Casablanca",
    "iso:country":"MA",
    "wof:name":"Cimilf",
    "wof:placetype":"locality"
},
  "geometry": {"coordinates":[-8.18635,30.68203],"type":"Point"}
}