{
  "type": "Feature",
  "properties": {
    "gn:admin1_code":"04",
    "gn:asciiname":"Arbaoua Lghaba",
    "gn:country_code":"MA",
    "gn:dem":171,
    "gn:feature_class":"P",
    "gn:feature_code":"PPL",
    "gn:name":"Arbaoua Lghaba",
    "gn:population":0,
    "gn:timezone":"Africa/Casablanca",
    "iso:country":"MA",
    "name:und_x_variant":[
        "Douar Arbaoua Akbat",
        "Arbaoua Ghaba",
        "Arbaoua Akbat el Begor",
        "Arbaoua Lghaba"
    ],
    "wof:name":"Arbaoua Lghaba",
    "wof:placetype":"locality"
},
  "geometry": {"coordinates":[-6.04496,34.93026],"type":"Point"}
}