{
  "type": "Feature",
  "properties": {
    "gn:admin1_code":"9.0",
    "gn:asciiname":"Id Bedene",
    "gn:country_code":"MA",
    "gn:dem":428,
    "gn:feature_class":"P",
    "gn:feature_code":"PPL",
    "gn:name":"Id Bedene",
    "gn:population":0,
    "gn:timezone":"Africa/Casablanca",
    "iso:country":"MA",
    "wof:name":"Id Bedene",
    "wof:placetype":"locality"
},
  "geometry": {"coordinates":[-9.24941,29.77784],"type":"Point"}
}