{
  "type": "Feature",
  "properties": {
    "gn:admin1_code":"7.0",
    "gn:asciiname":"Timzoughine",
    "gn:country_code":"MA",
    "gn:dem":889,
    "gn:feature_class":"P",
    "gn:feature_code":"PPL",
    "gn:name":"Timzoughine",
    "gn:population":0,
    "gn:timezone":"Africa/Casablanca",
    "iso:country":"MA",
    "wof:name":"Timzoughine",
    "wof:placetype":"locality"
},
  "geometry": {"coordinates":[-8.57145,31.23391],"type":"Point"}
}