{
  "type": "Feature",
  "properties": {
    "gn:admin1_code":"01",
    "gn:asciiname":"Oulad Massaoud",
    "gn:country_code":"MA",
    "gn:dem":51,
    "gn:feature_class":"P",
    "gn:feature_code":"PPL",
    "gn:name":"Oulad Massaoud",
    "gn:population":0,
    "gn:timezone":"Africa/Casablanca",
    "iso:country":"MA",
    "name:ara_x_preferred":[
        "\u0623\u0648\u0644\u0627\u062f \u0645\u0633\u0639\u0648\u062f"
    ],
    "name:cat_x_preferred":[
        "Oulad Massaoud"
    ],
    "name:ceb_x_preferred":[
        "Oulad Massaoud"
    ],
    "name:ita_x_preferred":[
        "Oulad Massaoud"
    ],
    "name:swe_x_preferred":[
        "Oulad Massaoud"
    ],
    "name:und_x_variant":[
        "Oulad Al Mehdi",
        "Oulad Messaoud",
        "Oulad el Mehdi"
    ],
    "wof:name":"Oulad Massaoud",
    "wof:placetype":"locality"
},
  "geometry": {"coordinates":[-5.98731,35.5187],"type":"Point"}
}