{
  "type": "Feature",
  "properties": {
    "gn:admin1_code":"01",
    "gn:asciiname":"Oulad Massaoud",
    "gn:country_code":"MA",
    "gn:dem":51,
    "gn:feature_class":"P",
    "gn:feature_code":"PPL",
    "gn:name":"Oulad Massaoud",
    "gn:population":0,
    "gn:timezone":"Africa/Casablanca",
    "iso:country":"MA",
    "name:und_x_variant":[
        "Oulad Al Mehdi",
        "Oulad Messaoud",
        "Oulad el Mehdi",
        "Oulad Massaoud"
    ],
    "wof:name":"Oulad Massaoud",
    "wof:placetype":"locality"
},
  "geometry": {"coordinates":[-5.98731,35.5187],"type":"Point"}
}