{
  "type": "Feature",
  "properties": {
    "gn:admin1_code":"7.0",
    "gn:asciiname":"Azib Souilha",
    "gn:country_code":"MA",
    "gn:dem":375,
    "gn:feature_class":"P",
    "gn:feature_code":"PPL",
    "gn:name":"Azib Souilha",
    "gn:population":0,
    "gn:timezone":"Africa/Casablanca",
    "iso:country":"MA",
    "wof:name":"Azib Souilha",
    "wof:placetype":"locality"
},
  "geometry": {"coordinates":[-9.44322,31.48484],"type":"Point"}
}