{
  "type": "Feature",
  "properties": {
    "gn:admin1_code":"01",
    "gn:asciiname":"Kouebbach",
    "gn:country_code":"MA",
    "gn:dem":440,
    "gn:feature_class":"P",
    "gn:feature_code":"PPL",
    "gn:name":"Kouebbach",
    "gn:population":0,
    "gn:timezone":"Africa/Casablanca",
    "iso:country":"MA",
    "wof:name":"Kouebbach",
    "wof:placetype":"locality"
},
  "geometry": {"coordinates":[-5.33157,35.26028],"type":"Point"}
}