{
  "type": "Feature",
  "properties": {
    "gn:admin1_code":"5.0",
    "gn:asciiname":"Qachla-n-Hatwine",
    "gn:country_code":"MA",
    "gn:dem":1790,
    "gn:feature_class":"P",
    "gn:feature_code":"PPL",
    "gn:name":"Qachla-n-Hatwine",
    "gn:population":0,
    "gn:timezone":"Africa/Casablanca",
    "iso:country":"MA",
    "wof:name":"Qachla-n-Hatwine",
    "wof:placetype":"locality"
},
  "geometry": {"coordinates":[-6.42817,32.00660999999999],"type":"Point"}
}