{
  "type": "Feature",
  "properties": {
    "gn:admin1_code":"10",
    "gn:asciiname":"Azad",
    "gn:country_code":"MA",
    "gn:dem":367,
    "gn:feature_class":"P",
    "gn:feature_code":"PPL",
    "gn:name":"Azad",
    "gn:population":0,
    "gn:timezone":"Africa/Casablanca",
    "iso:country":"MA",
    "name:ara_x_preferred":[
        "\u0622\u0632\u0627\u062f"
    ],
    "name:aze_x_preferred":[
        "Azad"
    ],
    "name:deu_x_preferred":[
        "Azad"
    ],
    "name:fas_x_preferred":[
        "\u0622\u0632\u0627\u062f"
    ],
    "name:fra_x_preferred":[
        "Azad"
    ],
    "name:kat_x_preferred":[
        "\u10d0\u10d6\u10d0\u10d3\u10d8"
    ],
    "name:kor_x_preferred":[
        "\uc544\uc790\ub4dc"
    ],
    "name:tur_x_preferred":[
        "Azad"
    ],
    "name:ukr_x_preferred":[
        "\u0410\u0437\u0430\u0434"
    ],
    "wof:name":"Azad",
    "wof:placetype":"locality"
},
  "geometry": {"coordinates":[-10.18,29.15],"type":"Point"}
}