{
  "type": "Feature",
  "properties": {
    "gn:admin1_code":"2.0",
    "gn:asciiname":"Douar Tarraint",
    "gn:country_code":"MA",
    "gn:dem":415,
    "gn:feature_class":"P",
    "gn:feature_code":"PPL",
    "gn:name":"Douar Tarraint",
    "gn:population":0,
    "gn:timezone":"Africa/Casablanca",
    "iso:country":"MA",
    "wof:name":"Douar Tarraint",
    "wof:placetype":"locality"
},
  "geometry": {"coordinates":[-2.22913,34.89080999999999],"type":"Point"}
}