{
  "type": "Feature",
  "properties": {
    "gn:admin1_code":"9.0",
    "gn:asciiname":"Iskla",
    "gn:country_code":"MA",
    "gn:dem":494,
    "gn:feature_class":"P",
    "gn:feature_code":"PPL",
    "gn:name":"Iskla",
    "gn:population":0,
    "gn:timezone":"Africa/Casablanca",
    "iso:country":"MA",
    "wof:name":"Iskla",
    "wof:placetype":"locality"
},
  "geometry": {"coordinates":[-9.55751,30.79766],"type":"Point"}
}