{
  "type": "Feature",
  "properties": {
    "gn:admin1_code":"02",
    "gn:asciiname":"Mezguitem",
    "gn:country_code":"MA",
    "gn:dem":916,
    "gn:feature_class":"P",
    "gn:feature_code":"PPL",
    "gn:name":"Mezguitem",
    "gn:population":0,
    "gn:timezone":"Africa/Casablanca",
    "iso:country":"MA",
    "name:und_x_variant":[
        "Mesguitem",
        "Mezguittem",
        "Mezguitem"
    ],
    "wof:name":"Mezguitem",
    "wof:placetype":"locality"
},
  "geometry": {"coordinates":[-3.63974,34.49914],"type":"Point"}
}