{
  "type": "Feature",
  "properties": {
    "gn:admin1_code":"08",
    "gn:asciiname":"Zaouia Sidi Moha Ou Ayachi",
    "gn:country_code":"MA",
    "gn:dem":2096,
    "gn:feature_class":"P",
    "gn:feature_code":"PPL",
    "gn:name":"Zaouia Sidi Moha Ou Ayachi",
    "gn:population":0,
    "gn:timezone":"Africa/Casablanca",
    "iso:country":"MA",
    "name:und_x_variant":[
        "Sidi Moha ou Ayachi",
        "Zaouia Sidi Moha Ou Ayachi"
    ],
    "wof:name":"Zaouia Sidi Moha Ou Ayachi",
    "wof:placetype":"locality"
},
  "geometry": {"coordinates":[-5.83,31.65],"type":"Point"}
}