{
  "type": "Feature",
  "properties": {
    "gn:admin1_code":"07",
    "gn:asciiname":"Tamelloukt",
    "gn:country_code":"MA",
    "gn:dem":1255,
    "gn:feature_class":"P",
    "gn:feature_code":"PPL",
    "gn:name":"Tamelloukt",
    "gn:population":0,
    "gn:timezone":"Africa/Casablanca",
    "iso:country":"MA",
    "wof:name":"Tamelloukt",
    "wof:placetype":"locality"
},
  "geometry": {"coordinates":[-8.95396,31.17607000000001],"type":"Point"}
}