{
  "type": "Feature",
  "properties": {
    "gn:admin1_code":"7.0",
    "gn:asciiname":"Ait Lqadi",
    "gn:country_code":"MA",
    "gn:dem":662,
    "gn:feature_class":"P",
    "gn:feature_code":"PPL",
    "gn:name":"Ait Lqadi",
    "gn:population":0,
    "gn:timezone":"Africa/Casablanca",
    "iso:country":"MA",
    "wof:name":"Ait Lqadi",
    "wof:placetype":"locality"
},
  "geometry": {"coordinates":[-7.67083,31.56025],"type":"Point"}
}