{
  "type": "Feature",
  "properties": {
    "gn:admin1_code":"9.0",
    "gn:asciiname":"Kakt",
    "gn:country_code":"MA",
    "gn:dem":1635,
    "gn:feature_class":"P",
    "gn:feature_code":"PPL",
    "gn:name":"Kakt",
    "gn:population":0,
    "gn:timezone":"Africa/Casablanca",
    "iso:country":"MA",
    "wof:name":"Kakt",
    "wof:placetype":"locality"
},
  "geometry": {"coordinates":[-8.85431,30.86209],"type":"Point"}
}