{
  "type": "Feature",
  "properties": {
    "gn:admin1_code":"03",
    "gn:asciiname":"Ait Youssef",
    "gn:country_code":"MA",
    "gn:dem":1062,
    "gn:feature_class":"P",
    "gn:feature_code":"PPL",
    "gn:name":"A\u00eft Youssef",
    "gn:population":0,
    "gn:timezone":"Africa/Casablanca",
    "iso:country":"MA",
    "name:und_x_variant":[
        "Kasba A\u00eft Youssef",
        "A\u00eft Youssef"
    ],
    "wof:name":"Ait Youssef",
    "wof:placetype":"locality"
},
  "geometry": {"coordinates":[-5.35765,33.4106],"type":"Point"}
}