{
  "type": "Feature",
  "properties": {
    "gn:admin1_code":"4.0",
    "gn:asciiname":"Lamtarfa",
    "gn:country_code":"MA",
    "gn:dem":10,
    "gn:feature_class":"P",
    "gn:feature_code":"PPL",
    "gn:name":"Lamtarfa",
    "gn:population":0,
    "gn:timezone":"Africa/Casablanca",
    "iso:country":"MA",
    "wof:name":"Lamtarfa",
    "wof:placetype":"locality"
},
  "geometry": {"coordinates":[-6.36119,34.50863],"type":"Point"}
}