{
  "type": "Feature",
  "properties": {
    "gn:admin1_code":"08",
    "gn:asciiname":"Tazoult",
    "gn:country_code":"MA",
    "gn:dem":1508,
    "gn:feature_class":"P",
    "gn:feature_code":"PPL",
    "gn:name":"Tazoult",
    "gn:population":0,
    "gn:timezone":"Africa/Casablanca",
    "iso:country":"MA",
    "name:und_x_variant":[
        "Tazouit",
        "Tazoult"
    ],
    "wof:name":"Tazoult",
    "wof:placetype":"locality"
},
  "geometry": {"coordinates":[-7.28345,30.30917],"type":"Point"}
}