{
  "type": "Feature",
  "properties": {
    "gn:admin1_code":"01",
    "gn:asciiname":"Draouene",
    "gn:country_code":"MA",
    "gn:dem":450,
    "gn:feature_class":"P",
    "gn:feature_code":"PPL",
    "gn:name":"Draouene",
    "gn:population":0,
    "gn:timezone":"Africa/Casablanca",
    "iso:country":"MA",
    "wof:name":"Draouene",
    "wof:placetype":"locality"
},
  "geometry": {"coordinates":[-5.18661,35.30257],"type":"Point"}
}