{
  "type": "Feature",
  "properties": {
    "gn:admin1_code":"03",
    "gn:asciiname":"Ain 'Aicha Hmad",
    "gn:country_code":"MA",
    "gn:dem":1532,
    "gn:feature_class":"P",
    "gn:feature_code":"PPL",
    "gn:name":"A\u00efn \u2019A\u00efcha Hmad",
    "gn:population":0,
    "gn:timezone":"Africa/Casablanca",
    "iso:country":"MA",
    "name:und_x_variant":[
        "A\u00efn \u2019A\u00efcha Hmad",
        "Kasba A\u00efcha Hammad"
    ],
    "wof:name":"Ain 'Aicha Hmad",
    "wof:placetype":"locality"
},
  "geometry": {"coordinates":[-5.38271,33.24056],"type":"Point"}
}