{
  "type": "Feature",
  "properties": {
    "gn:admin1_code":"3.0",
    "gn:asciiname":"Douar Lemfabrayine",
    "gn:country_code":"MA",
    "gn:dem":478,
    "gn:feature_class":"P",
    "gn:feature_code":"PPL",
    "gn:name":"Douar Lemfabrayine",
    "gn:population":0,
    "gn:timezone":"Africa/Casablanca",
    "iso:country":"MA",
    "wof:name":"Douar Lemfabrayine",
    "wof:placetype":"locality"
},
  "geometry": {"coordinates":[-4.85891,33.94808],"type":"Point"}
}