{
  "type": "Feature",
  "properties": {
    "gn:country":"MA",
    "gn:fcode":"ADM3",
    "gn:pop":11645,
    "iso:country":"MA",
    "name:ara_x_preferred":[
        "\u0627\u0644\u0639\u062b\u0627\u0645\u0646\u0629"
    ],
    "name:eng_x_preferred":[
        "Madagh"
    ],
    "name:fra_x_preferred":[
        "Madagh"
    ],
    "name:fra_x_variant":[
        "Madagh (CR)",
        "Madagh (Commune Rurale)"
    ],
    "qs:name":"Madagh",
    "qs:photos_9r":0,
    "qs:photos_sr":0,
    "qs:pop_sr":"6",
    "wd:wordcount":728,
    "wof:name":"Madagh",
    "wof:placetype":"localadmin",
    "wof:population":11645
},
  "geometry": {"coordinates":[-2.37466,35.05068],"type":"Point"}
}