{
  "type": "Feature",
  "properties": {
    "gn:admin1_code":"2.0",
    "gn:asciiname":"Iaouadene",
    "gn:country_code":"MA",
    "gn:dem":848,
    "gn:feature_class":"P",
    "gn:feature_code":"PPL",
    "gn:name":"Iaouadene",
    "gn:population":0,
    "gn:timezone":"Africa/Casablanca",
    "iso:country":"MA",
    "wof:name":"Iaouadene",
    "wof:placetype":"locality"
},
  "geometry": {"coordinates":[-3.42173,35.1198],"type":"Point"}
}