{
  "type": "Feature",
  "properties": {
    "gn:admin1_code":"3.0",
    "gn:asciiname":"Douar Ail Enakh",
    "gn:country_code":"MA",
    "gn:dem":610,
    "gn:feature_class":"P",
    "gn:feature_code":"PPL",
    "gn:name":"Douar Ail Enakh",
    "gn:population":0,
    "gn:timezone":"Africa/Casablanca",
    "iso:country":"MA",
    "wof:name":"Douar Ail Enakh",
    "wof:placetype":"locality"
},
  "geometry": {"coordinates":[-4.79409,33.91240999999999],"type":"Point"}
}