{
  "type": "Feature",
  "properties": {
    "gn:admin1_code":"6.0",
    "gn:asciiname":"Oulad Chaayb",
    "gn:country_code":"MA",
    "gn:dem":614,
    "gn:feature_class":"P",
    "gn:feature_code":"PPL",
    "gn:name":"Oulad Chaayb",
    "gn:population":0,
    "gn:timezone":"Africa/Casablanca",
    "iso:country":"MA",
    "wof:name":"Oulad Chaayb",
    "wof:placetype":"locality"
},
  "geometry": {"coordinates":[-7.02816,33.13788],"type":"Point"}
}