{
  "type": "Feature",
  "properties": {
    "gn:admin1_code":"08",
    "gn:asciiname":"Izilf",
    "gn:country_code":"MA",
    "gn:dem":980,
    "gn:feature_class":"P",
    "gn:feature_code":"PPL",
    "gn:name":"Izilf",
    "gn:population":0,
    "gn:timezone":"Africa/Casablanca",
    "iso:country":"MA",
    "name:und_x_variant":[
        "Ksar Isilf",
        "Isilf",
        "Izilf"
    ],
    "wof:name":"Izilf",
    "wof:placetype":"locality"
},
  "geometry": {"coordinates":[-4.96862,31.52882],"type":"Point"}
}