{
  "type": "Feature",
  "properties": {
    "gn:admin1_code":"01",
    "gn:asciiname":"Douar Rhouna",
    "gn:country_code":"MA",
    "gn:dem":146,
    "gn:feature_class":"P",
    "gn:feature_code":"PPL",
    "gn:name":"Douar Rhouna",
    "gn:population":0,
    "gn:timezone":"Africa/Casablanca",
    "iso:country":"MA",
    "name:und_x_variant":[
        "Renouna",
        "Rehouna",
        "Douar Rhouna"
    ],
    "wof:name":"Douar Rhouna",
    "wof:placetype":"locality"
},
  "geometry": {"coordinates":[-6.0623,35.3508],"type":"Point"}
}