{
  "type": "Feature",
  "properties": {
    "gn:admin1_code":"09",
    "gn:asciiname":"Zaouia Sidi ben Mimoun",
    "gn:country_code":"MA",
    "gn:dem":335,
    "gn:feature_class":"P",
    "gn:feature_code":"PPL",
    "gn:name":"Zaouia Sidi ben Mimoun",
    "gn:population":0,
    "gn:timezone":"Africa/Casablanca",
    "iso:country":"MA",
    "wof:name":"Zaouia Sidi ben Mimoun",
    "wof:placetype":"locality"
},
  "geometry": {"coordinates":[-8.91277,30.57164],"type":"Point"}
}