{
  "type": "Feature",
  "properties": {
    "gn:admin1_code":"10.0",
    "gn:asciiname":"Talat-n-Ghwilast",
    "gn:country_code":"MA",
    "gn:dem":662,
    "gn:feature_class":"P",
    "gn:feature_code":"PPL",
    "gn:name":"Talat-n-Ghwilast",
    "gn:population":0,
    "gn:timezone":"Africa/Casablanca",
    "iso:country":"MA",
    "wof:name":"Talat-n-Ghwilast",
    "wof:placetype":"locality"
},
  "geometry": {"coordinates":[-9.8796,29.23382],"type":"Point"}
}