{
  "type": "Feature",
  "properties": {
    "gn:admin1_code":"01",
    "gn:asciiname":"Takhyamt",
    "gn:country_code":"MA",
    "gn:dem":433,
    "gn:feature_class":"P",
    "gn:feature_code":"PPL",
    "gn:name":"Takhyamt",
    "gn:population":0,
    "gn:timezone":"Africa/Casablanca",
    "iso:country":"MA",
    "name:und_x_variant":[
        "Tahiants",
        "Takhiant",
        "Takhyamt"
    ],
    "wof:name":"Takhyamt",
    "wof:placetype":"locality"
},
  "geometry": {"coordinates":[-5.53764,35.40566],"type":"Point"}
}