{
  "type": "Feature",
  "properties": {
    "gn:admin1_code":"6.0",
    "gn:asciiname":"Oulad El Haj Kaddour",
    "gn:country_code":"MA",
    "gn:dem":291,
    "gn:feature_class":"P",
    "gn:feature_code":"PPL",
    "gn:name":"Oulad El Haj Kaddour",
    "gn:population":0,
    "gn:timezone":"Africa/Casablanca",
    "iso:country":"MA",
    "wof:name":"Oulad El Haj Kaddour",
    "wof:placetype":"locality"
},
  "geometry": {"coordinates":[-7.43727,33.16735],"type":"Point"}
}