{
  "type": "Feature",
  "properties": {
    "gn:admin1_code":"08",
    "gn:asciiname":"Bleida",
    "gn:country_code":"MA",
    "gn:dem":1304,
    "gn:feature_class":"P",
    "gn:feature_code":"PPL",
    "gn:name":"Ble\u00efda",
    "gn:population":0,
    "gn:timezone":"Africa/Casablanca",
    "iso:country":"MA",
    "wof:name":"Bleida",
    "wof:placetype":"locality"
},
  "geometry": {"coordinates":[-6.42413,30.35372000000001],"type":"Point"}
}