{
  "type": "Feature",
  "properties": {
    "gn:admin1_code":"01",
    "gn:asciiname":"Chalourad",
    "gn:country_code":"MA",
    "gn:dem":489,
    "gn:feature_class":"P",
    "gn:feature_code":"PPL",
    "gn:name":"Chalourad",
    "gn:population":0,
    "gn:timezone":"Africa/Casablanca",
    "iso:country":"MA",
    "wof:name":"Chalourad",
    "wof:placetype":"locality"
},
  "geometry": {"coordinates":[-5.20887,35.37455999999999],"type":"Point"}
}