{
  "type": "Feature",
  "properties": {
    "gn:admin1_code":"09",
    "gn:asciiname":"Ighit Ibarkak",
    "gn:country_code":"MA",
    "gn:dem":1735,
    "gn:feature_class":"P",
    "gn:feature_code":"PPL",
    "gn:name":"Ighit Ibarkak",
    "gn:population":0,
    "gn:timezone":"Africa/Casablanca",
    "iso:country":"MA",
    "name:und_x_variant":[
        "Ighil A\u00eft Ali",
        "Irhil",
        "Ighit Ibarkak"
    ],
    "wof:name":"Ighit Ibarkak",
    "wof:placetype":"locality"
},
  "geometry": {"coordinates":[-8.65035,29.91467],"type":"Point"}
}