{
  "type": "Feature",
  "properties": {
    "gn:admin1_code":"4.0",
    "gn:asciiname":"Oulad Boubker",
    "gn:country_code":"MA",
    "gn:dem":176,
    "gn:feature_class":"P",
    "gn:feature_code":"PPL",
    "gn:name":"Oulad Boubker",
    "gn:population":0,
    "gn:timezone":"Africa/Casablanca",
    "iso:country":"MA",
    "name:ara_x_preferred":[
        "\u0623\u0648\u0644\u0627\u062f \u0628\u0648\u0628\u0643\u0631"
    ],
    "name:cat_x_preferred":[
        "Oulad Boubker"
    ],
    "name:ceb_x_preferred":[
        "Oulad Boubker"
    ],
    "name:swe_x_preferred":[
        "Oulad Boubker"
    ],
    "wof:name":"Oulad Boubker",
    "wof:placetype":"locality"
},
  "geometry": {"coordinates":[-5.46755,34.16528],"type":"Point"}
}