{
  "type": "Feature",
  "properties": {
    "gn:admin1_code":"06",
    "gn:asciiname":"Douar Sidi Smail",
    "gn:country_code":"MA",
    "gn:dem":140,
    "gn:feature_class":"P",
    "gn:feature_code":"PPL",
    "gn:name":"Douar Sidi Sma\u00efl",
    "gn:population":0,
    "gn:timezone":"Africa/Casablanca",
    "iso:country":"MA",
    "name:und_x_variant":[
        "Dar Sidi Sma\u00efl",
        "Sidi-Sm\u00e2\u00efl",
        "Douar Sidi Sma\u00efl"
    ],
    "wof:name":"Douar Sidi Smail",
    "wof:placetype":"locality"
},
  "geometry": {"coordinates":[-8.40845,32.8211],"type":"Point"}
}