{
  "type": "Feature",
  "properties": {
    "gn:admin1_code":"04",
    "gn:asciiname":"Douar Oulad Meryem",
    "gn:country_code":"MA",
    "gn:dem":381,
    "gn:feature_class":"P",
    "gn:feature_code":"PPL",
    "gn:name":"Douar Oulad Meryem",
    "gn:population":0,
    "gn:timezone":"Africa/Casablanca",
    "iso:country":"MA",
    "name:und_x_variant":[
        "Douar Ouled Azzi"
    ],
    "wof:name":"Douar Oulad Meryem",
    "wof:placetype":"locality"
},
  "geometry": {"coordinates":[-5.56503,34.14351],"type":"Point"}
}