{
  "type": "Feature",
  "properties": {
    "gn:admin1_code":"09",
    "gn:asciiname":"Iousrane",
    "gn:country_code":"MA",
    "gn:dem":937,
    "gn:feature_class":"P",
    "gn:feature_code":"PPL",
    "gn:name":"Iousrane",
    "gn:population":0,
    "gn:timezone":"Africa/Casablanca",
    "iso:country":"MA",
    "wof:name":"Iousrane",
    "wof:placetype":"locality"
},
  "geometry": {"coordinates":[-8.8885,30.69952],"type":"Point"}
}