{
  "type": "Feature",
  "properties": {
    "gn:country":"MA",
    "gn:fcode":"ADM3",
    "gn:population":3232,
    "iso:country":"MA",
    "name:ara_x_preferred":[
        "\u0645\u064a\u0636\u0627\u0631"
    ],
    "name:fra_x_preferred":[
        "M Hajer"
    ],
    "name:fra_x_variant":[
        "M Hajer (CR)",
        "M Hajer (Commune Rurale)"
    ],
    "qs_pg:aaroncc":"MA",
    "qs_pg:gn_country":"MA",
    "qs_pg:gn_fcode":"ADM3",
    "qs_pg:gn_pop":3232,
    "qs_pg:name":"M Hajer",
    "qs_pg:photos_9r":0,
    "qs_pg:photos_sr":0,
    "qs_pg:pop_sr":4,
    "qs_pg:qs_pg_placetype":"localadmin",
    "wof:name":"M Hajer",
    "wof:placetype":"localadmin",
    "wof:population":3232
},
  "geometry": {"coordinates":[-3.49508,35.14316],"type":"Point"}
}