{
  "type": "Feature",
  "properties": {
    "gn:admin1_code":"1.0",
    "gn:asciiname":"Cap Negro II",
    "gn:country_code":"MA",
    "gn:dem":7,
    "gn:feature_class":"P",
    "gn:feature_code":"PPL",
    "gn:name":"Cap Negro II",
    "gn:population":0,
    "gn:timezone":"Africa/Casablanca",
    "iso:country":"MA",
    "name:eng_x_preferred":[
        "Cabo Negro"
    ],
    "name:rus_x_preferred":[
        "\u041a\u0430\u0431\u043e \u041d\u0435\u0433\u0440\u043e"
    ],
    "wof:name":"Cap Negro II",
    "wof:placetype":"locality"
},
  "geometry": {"coordinates":[-5.28525,35.6597],"type":"Point"}
}