{
  "type": "Feature",
  "properties": {
    "gn:admin1_code":"09",
    "gn:asciiname":"Zaouit Issoukal",
    "gn:country_code":"MA",
    "gn:dem":821,
    "gn:feature_class":"P",
    "gn:feature_code":"PPL",
    "gn:name":"Zaouit Issoukal",
    "gn:population":0,
    "gn:timezone":"Africa/Casablanca",
    "iso:country":"MA",
    "name:und_x_variant":[
        "Zaouia Issougal",
        "Zaouia Issoukal",
        "Zaouit Issoukal"
    ],
    "wof:name":"Zaouit Issoukal",
    "wof:placetype":"locality"
},
  "geometry": {"coordinates":[-9.39107,30.8467],"type":"Point"}
}