{
  "type": "Feature",
  "properties": {
    "gn:admin1_code":"09",
    "gn:asciiname":"Azaghar-n-Ouzliy",
    "gn:country_code":"MA",
    "gn:dem":1658,
    "gn:feature_class":"P",
    "gn:feature_code":"PPL",
    "gn:name":"Azaghar-n-Ouzliy",
    "gn:population":0,
    "gn:timezone":"Africa/Casablanca",
    "iso:country":"MA",
    "name:und_x_variant":[
        "Azaghar",
        "Azarhar",
        "Azaghar-n-Ouzliy"
    ],
    "wof:name":"Azaghar-n-Ouzliy",
    "wof:placetype":"locality"
},
  "geometry": {"coordinates":[-7.94235,30.2482],"type":"Point"}
}