{
  "type": "Feature",
  "properties": {
    "gn:admin1_code":"03",
    "gn:asciiname":"Douar Bni Jennad",
    "gn:country_code":"MA",
    "gn:dem":625,
    "gn:feature_class":"P",
    "gn:feature_code":"PPL",
    "gn:name":"Douar Bni Jennad",
    "gn:population":0,
    "gn:timezone":"Africa/Casablanca",
    "iso:country":"MA",
    "name:und_x_variant":[
        "Beni Djenade",
        "Beni Jenade",
        "Beni Jenad",
        "Douar Bni Jennad"
    ],
    "wof:name":"Douar Bni Jennad",
    "wof:placetype":"locality"
},
  "geometry": {"coordinates":[-5.55153,34.0243],"type":"Point"}
}