{
  "type": "Feature",
  "properties": {
    "gn:country":"MA",
    "gn:fcode":"ADM3",
    "gn:pop":15339,
    "iso:country":"MA",
    "name:ara_x_preferred":[
        "\u062e\u0632\u0627\u0645\u0629"
    ],
    "name:fra_x_preferred":[
        "Ouisselsate"
    ],
    "name:fra_x_variant":[
        "Ouisselsate (CR)",
        "Ouisselsate (Commune Rurale)"
    ],
    "qs:name":"Ouisselsate",
    "qs:photos_9r":0,
    "qs:photos_sr":0,
    "qs:pop_sr":"6",
    "wd:wordcount":58,
    "wof:name":"Ouisselsate",
    "wof:placetype":"localadmin",
    "wof:population":15339
},
  "geometry": {"coordinates":[-7.16989,30.51956],"type":"Point"}
}