{
  "type": "Feature",
  "properties": {
    "gn:country":"MA",
    "gn:fcode":"ADM3",
    "gn:pop":15339,
    "iso:country":"MA",
    "name:ara_x_preferred":[
        "\u062e\u0632\u0627\u0645\u0629"
    ],
    "name:ara_x_variant":[
        "\u0648\u064a\u0633\u0644\u0633\u0627\u062a"
    ],
    "name:azb_x_preferred":[
        "\u0648\u06cc\u0633\u0644\u0633\u0627\u062a"
    ],
    "name:bul_x_preferred":[
        "\u041e\u0443\u0438\u0441\u0435\u043b\u0441\u0430\u0442\u0435"
    ],
    "name:cat_x_preferred":[
        "Ouisselsate"
    ],
    "name:ceb_x_preferred":[
        "Ouisselsate"
    ],
    "name:eng_x_preferred":[
        "Ouisselsate"
    ],
    "name:fas_x_preferred":[
        "\u0648\u06cc\u0633\u0644\u0633\u0627\u062a"
    ],
    "name:fra_x_preferred":[
        "Ouisselsate"
    ],
    "name:fra_x_variant":[
        "Ouisselsate (CR)",
        "Ouisselsate (Commune Rurale)"
    ],
    "name:ita_x_preferred":[
        "Ouisselsate"
    ],
    "name:swe_x_preferred":[
        "Ouisselsate"
    ],
    "qs:name":"Ouisselsate",
    "qs:photos_9r":0,
    "qs:photos_sr":0,
    "qs:pop_sr":"6",
    "wd:wordcount":58,
    "wof:name":"Ouisselsate",
    "wof:placetype":"localadmin",
    "wof:population":15339
},
  "geometry": {"coordinates":[-7.16989,30.51956],"type":"Point"}
}