{
  "type": "Feature",
  "properties": {
    "iso:country":"MA",
    "name:ara_x_preferred":[
        "\u0625\u0645\u0644\u0634\u064a\u0644"
    ],
    "name:cat_x_preferred":[
        "Imilchil"
    ],
    "name:ceb_x_preferred":[
        "Imilchil"
    ],
    "name:deu_x_preferred":[
        "Imilchil"
    ],
    "name:eng_x_preferred":[
        "Imilchil"
    ],
    "name:fra_x_preferred":[
        "Imilchil"
    ],
    "name:ita_x_preferred":[
        "Imilchil"
    ],
    "name:jpn_x_preferred":[
        "\u30a4\u30df\u30eb\u30b7\u30eb"
    ],
    "name:kab_x_preferred":[
        "Imilcil"
    ],
    "name:nld_x_preferred":[
        "Imilchil"
    ],
    "name:por_x_preferred":[
        "Imilchil"
    ],
    "name:spa_x_preferred":[
        "Imilchil"
    ],
    "name:swe_x_preferred":[
        "Imilchil"
    ],
    "name:tur_x_preferred":[
        "\u0130milchil"
    ],
    "qs:gn_pop":0,
    "qs:name":"Imilchil",
    "qs:name_adm0":"\u0627\u0644\u0645\u063a\u0631\u0628",
    "qs:name_adm1":"\u0645\u0643\u0646\u0627\u0633 \u0640 \u062a\u0627\u0641\u064a\u0644\u0627\u0644\u062a",
    "qs:photos":315,
    "qs:photos_1k":64,
    "qs:photos_9k":1,
    "qs:photos_9r":5,
    "qs:photos_all":315,
    "qs:photos_sr":5,
    "qs:placetype":"Town",
    "qs:pop_sr":"0",
    "qs:woe_adm0":23424893,
    "wd:wordcount":443,
    "wof:name":"Imilchil",
    "wof:placetype":"locality"
},
  "geometry": {"coordinates":[-5.657958,32.170672],"type":"Point"}
}