{
  "type": "Feature",
  "properties": {
    "gn:admin1_code":"9.0",
    "gn:asciiname":"Tislanerou Mohammed",
    "gn:country_code":"MA",
    "gn:dem":458,
    "gn:feature_class":"P",
    "gn:feature_code":"PPL",
    "gn:name":"Tislanerou Mohammed",
    "gn:population":0,
    "gn:timezone":"Africa/Casablanca",
    "iso:country":"MA",
    "wof:name":"Tislanerou Mohammed",
    "wof:placetype":"locality"
},
  "geometry": {"coordinates":[-9.13561,30.18056],"type":"Point"}
}