{
  "type": "Feature",
  "properties": {
    "gn:admin1_code":"6.0",
    "gn:asciiname":"Douar Zabla",
    "gn:country_code":"MA",
    "gn:dem":144,
    "gn:feature_class":"P",
    "gn:feature_code":"PPL",
    "gn:name":"Douar Zabla",
    "gn:population":0,
    "gn:timezone":"Africa/Casablanca",
    "iso:country":"MA",
    "wof:name":"Douar Zabla",
    "wof:placetype":"locality"
},
  "geometry": {"coordinates":[-8.64725,32.76947],"type":"Point"}
}