{
  "type": "Feature",
  "properties": {
    "gn:admin1_code":"6.0",
    "gn:asciiname":"Douar Lasouafat",
    "gn:country_code":"MA",
    "gn:dem":149,
    "gn:feature_class":"P",
    "gn:feature_code":"PPL",
    "gn:name":"Douar Lasouafat",
    "gn:population":0,
    "gn:timezone":"Africa/Casablanca",
    "iso:country":"MA",
    "wof:name":"Douar Lasouafat",
    "wof:placetype":"locality"
},
  "geometry": {"coordinates":[-8.77148,32.57226],"type":"Point"}
}