{
  "type": "Feature",
  "properties": {
    "gn:admin1_code":"9.0",
    "gn:asciiname":"Tamenndert",
    "gn:country_code":"MA",
    "gn:dem":1596,
    "gn:feature_class":"P",
    "gn:feature_code":"PPL",
    "gn:name":"Tamenndert",
    "gn:population":0,
    "gn:timezone":"Africa/Casablanca",
    "iso:country":"MA",
    "wof:name":"Tamenndert",
    "wof:placetype":"locality"
},
  "geometry": {"coordinates":[-8.90922,30.72996],"type":"Point"}
}