{
  "type": "Feature",
  "properties": {
    "gn:admin1_code":"3.0",
    "gn:asciiname":"Makraz Essoufla",
    "gn:country_code":"MA",
    "gn:dem":539,
    "gn:feature_class":"P",
    "gn:feature_code":"PPL",
    "gn:name":"Makraz Essoufla",
    "gn:population":0,
    "gn:timezone":"Africa/Casablanca",
    "iso:country":"MA",
    "wof:name":"Makraz Essoufla",
    "wof:placetype":"locality"
},
  "geometry": {"coordinates":[-4.90951,33.9734],"type":"Point"}
}