{
  "type": "Feature",
  "properties": {
    "gn:admin1_code":"5.0",
    "gn:asciiname":"Ait Waghghad",
    "gn:country_code":"MA",
    "gn:dem":1337,
    "gn:feature_class":"P",
    "gn:feature_code":"PPL",
    "gn:name":"A\u00eft Waghghad",
    "gn:population":0,
    "gn:timezone":"Africa/Casablanca",
    "iso:country":"MA",
    "wof:name":"Ait Waghghad",
    "wof:placetype":"locality"
},
  "geometry": {"coordinates":[-6.59672,31.94961],"type":"Point"}
}