{
  "type": "Feature",
  "properties": {
    "gn:admin1_code":"3.0",
    "gn:asciiname":"Douar Ait Eddaa",
    "gn:country_code":"MA",
    "gn:dem":1438,
    "gn:feature_class":"P",
    "gn:feature_code":"PPL",
    "gn:name":"Douar Ait Eddaa",
    "gn:population":0,
    "gn:timezone":"Africa/Casablanca",
    "iso:country":"MA",
    "wof:name":"Douar Ait Eddaa",
    "wof:placetype":"locality"
},
  "geometry": {"coordinates":[-4.79431,33.6188],"type":"Point"}
}