{
  "type": "Feature",
  "properties": {
    "gn:country":"MA",
    "gn:fcode":"ADM3",
    "gn:pop":143419,
    "iso:country":"MA",
    "name:ara_x_preferred":[
        "\u0627\u0632\u0645\u0648\u0631 (\u0627\u0644\u0628\u0644\u062f\u064a\u0629)"
    ],
    "name:fra_x_preferred":[
        "El-Jadida"
    ],
    "name:fra_x_variant":[
        "El-Jadida (MU)",
        "El-Jadida (Commune Urbaine)"
    ],
    "qs:name":"El-Jadida",
    "qs:photos_9r":0,
    "qs:photos_sr":0,
    "qs:pop_sr":"9",
    "wd:wordcount":930,
    "wof:name":"El-Jadida",
    "wof:placetype":"localadmin",
    "wof:population":143419
},
  "geometry": {"coordinates":[-8.50668,33.2492],"type":"Point"}
}