{
  "type": "Feature",
  "properties": {
    "gn:admin1_code":"08",
    "gn:asciiname":"Imarighene",
    "gn:country_code":"MA",
    "gn:dem":1082,
    "gn:feature_class":"P",
    "gn:feature_code":"PPL",
    "gn:name":"Imarighene",
    "gn:population":0,
    "gn:timezone":"Africa/Casablanca",
    "iso:country":"MA",
    "name:und_x_variant":[
        "Imarirene"
    ],
    "wof:name":"Imarighene",
    "wof:placetype":"locality"
},
  "geometry": {"coordinates":[-4.68497,31.87271],"type":"Point"}
}