{
  "type": "Feature",
  "properties": {
    "gn:admin1_code":"06",
    "gn:asciiname":"Douar el Gaabra",
    "gn:country_code":"MA",
    "gn:dem":213,
    "gn:feature_class":"P",
    "gn:feature_code":"PPL",
    "gn:name":"Douar el Gaabra",
    "gn:population":0,
    "gn:timezone":"Africa/Casablanca",
    "iso:country":"MA",
    "name:und_x_variant":[
        "Douar Gahbeur",
        "Douar el Gaabra"
    ],
    "wof:name":"Douar el Gaabra",
    "wof:placetype":"locality"
},
  "geometry": {"coordinates":[-8.30771,32.59583],"type":"Point"}
}