{
  "type": "Feature",
  "properties": {
    "gn:admin1_code":"09",
    "gn:asciiname":"Igourar Ou Allouk",
    "gn:country_code":"MA",
    "gn:dem":321,
    "gn:feature_class":"P",
    "gn:feature_code":"PPL",
    "gn:name":"Igourar Ou Allouk",
    "gn:population":0,
    "gn:timezone":"Africa/Casablanca",
    "iso:country":"MA",
    "name:und_x_variant":[
        "Aalouk",
        "Igourar Ou Allouk"
    ],
    "wof:name":"Igourar Ou Allouk",
    "wof:placetype":"locality"
},
  "geometry": {"coordinates":[-9.84,29.72],"type":"Point"}
}