{
  "type": "Feature",
  "properties": {
    "gn:admin1_code":"7.0",
    "gn:asciiname":"Douar Laaouadla",
    "gn:country_code":"MA",
    "gn:dem":209,
    "gn:feature_class":"P",
    "gn:feature_code":"PPL",
    "gn:name":"Douar Laaouadla",
    "gn:population":0,
    "gn:timezone":"Africa/Casablanca",
    "iso:country":"MA",
    "wof:name":"Douar Laaouadla",
    "wof:placetype":"locality"
},
  "geometry": {"coordinates":[-9.18692,32.00508],"type":"Point"}
}