{
  "type": "Feature",
  "properties": {
    "gn:admin1_code":"9.0",
    "gn:asciiname":"Tarayst",
    "gn:country_code":"MA",
    "gn:dem":168,
    "gn:feature_class":"P",
    "gn:feature_code":"PPL",
    "gn:name":"Tarayst",
    "gn:population":0,
    "gn:timezone":"Africa/Casablanca",
    "iso:country":"MA",
    "wof:name":"Tarayst",
    "wof:placetype":"locality"
},
  "geometry": {"coordinates":[-9.45363,30.00817],"type":"Point"}
}