{
  "type": "Feature",
  "properties": {
    "gn:country":"MA",
    "gn:fcode":"ADM3",
    "gn:population":8164,
    "iso:country":"MA",
    "name:ara_x_preferred":[
        "\u0645\u0631\u0643\u0632 \u0627\u0644\u0632\u0631\u0627\u0631\u062f\u0629"
    ],
    "name:fra_x_preferred":[
        "Enjil"
    ],
    "name:fra_x_variant":[
        "Enjil (CR)",
        "Enjil (Commune Rurale)"
    ],
    "qs_pg:aaroncc":"MA",
    "qs_pg:gn_country":"MA",
    "qs_pg:gn_fcode":"ADM3",
    "qs_pg:gn_pop":8164,
    "qs_pg:name":"Enjil",
    "qs_pg:photos_9r":0,
    "qs_pg:photos_sr":0,
    "qs_pg:pop_sr":5,
    "qs_pg:qs_pg_placetype":"localadmin",
    "wof:name":"Enjil",
    "wof:placetype":"localadmin",
    "wof:population":8364
},
  "geometry": {"coordinates":[-4.58481,33.09338],"type":"Point"}
}