{
  "type": "Feature",
  "properties": {
    "gn:admin1_code":"3.0",
    "gn:asciiname":"Dar El Caid Med. Ameharref",
    "gn:country_code":"MA",
    "gn:dem":1529,
    "gn:feature_class":"P",
    "gn:feature_code":"PPL",
    "gn:name":"Dar El Caid Med. Ameharref",
    "gn:population":0,
    "gn:timezone":"Africa/Casablanca",
    "iso:country":"MA",
    "wof:name":"Dar El Caid Med. Ameharref",
    "wof:placetype":"locality"
},
  "geometry": {"coordinates":[-4.03389,34.09133],"type":"Point"}
}