{
  "type": "Feature",
  "properties": {
    "gn:admin1_code":"5.0",
    "gn:asciiname":"Oulad Amer",
    "gn:country_code":"MA",
    "gn:dem":652,
    "gn:feature_class":"P",
    "gn:feature_code":"PPL",
    "gn:name":"Oulad Amer",
    "gn:population":0,
    "gn:timezone":"Africa/Casablanca",
    "iso:country":"MA",
    "wof:name":"Oulad Amer",
    "wof:placetype":"locality"
},
  "geometry": {"coordinates":[-6.86154,32.72894],"type":"Point"}
}