{
  "type": "Feature",
  "properties": {
    "gn:admin1_code":"9.0",
    "gn:asciiname":"Afagha",
    "gn:country_code":"MA",
    "gn:dem":1097,
    "gn:feature_class":"P",
    "gn:feature_code":"PPL",
    "gn:name":"Afagha",
    "gn:population":0,
    "gn:timezone":"Africa/Casablanca",
    "iso:country":"MA",
    "wof:name":"Afagha",
    "wof:placetype":"locality"
},
  "geometry": {"coordinates":[-8.82947,30.15742],"type":"Point"}
}