{
  "type": "Feature",
  "properties": {
    "gn:admin1_code":"7.0",
    "gn:asciiname":"Douar Ait Chnad",
    "gn:country_code":"MA",
    "gn:dem":520,
    "gn:feature_class":"P",
    "gn:feature_code":"PPL",
    "gn:name":"Douar Ait Chnad",
    "gn:population":0,
    "gn:timezone":"Africa/Casablanca",
    "iso:country":"MA",
    "wof:name":"Douar Ait Chnad",
    "wof:placetype":"locality"
},
  "geometry": {"coordinates":[-7.80865,31.58455],"type":"Point"}
}