{
  "type": "Feature",
  "properties": {
    "gn:admin1_code":"7.0",
    "gn:asciiname":"Sidi Othmane",
    "gn:country_code":"MA",
    "gn:dem":561,
    "gn:feature_class":"P",
    "gn:feature_code":"PPL",
    "gn:name":"Sidi Othmane",
    "gn:population":0,
    "gn:timezone":"Africa/Casablanca",
    "iso:country":"MA",
    "wof:name":"Sidi Othmane",
    "wof:placetype":"locality"
},
  "geometry": {"coordinates":[-7.26979,31.9358],"type":"Point"}
}