{
  "type": "Feature",
  "properties": {
    "gn:admin1_code":"05",
    "gn:asciiname":"Ait Tagant",
    "gn:country_code":"MA",
    "gn:dem":836,
    "gn:elevation":"0.0",
    "gn:feature_class":"P",
    "gn:feature_code":"PPL",
    "gn:name":"A\u00eft Tagant",
    "gn:population":0,
    "gn:timezone":"Africa/Casablanca",
    "iso:country":"MA",
    "wof:name":"Ait Tagant",
    "wof:placetype":"locality"
},
  "geometry": {"coordinates":[-6.94402,31.97873],"type":"Point"}
}