{
  "type": "Feature",
  "properties": {
    "gn:admin1_code":"08",
    "gn:asciiname":"Ayt Waeyne",
    "gn:country_code":"MA",
    "gn:dem":1063,
    "gn:feature_class":"P",
    "gn:feature_code":"PPL",
    "gn:name":"Ayt Waeyne",
    "gn:population":0,
    "gn:timezone":"Africa/Casablanca",
    "iso:country":"MA",
    "name:und_x_variant":[
        "Ibarbat\u00e8n",
        "Ibakhaten",
        "Ibarbatene",
        "Ayt Waeyne"
    ],
    "wof:name":"Ayt Waeyne",
    "wof:placetype":"locality"
},
  "geometry": {"coordinates":[-4.45782,31.97396],"type":"Point"}
}