{
  "type": "Feature",
  "properties": {
    "gn:admin1_code":"09",
    "gn:asciiname":"Tagadirt-n-Bazmad",
    "gn:country_code":"MA",
    "gn:dem":626,
    "gn:feature_class":"P",
    "gn:feature_code":"PPL",
    "gn:name":"Tagadirt-n-Bazmad",
    "gn:population":0,
    "gn:timezone":"Africa/Casablanca",
    "iso:country":"MA",
    "name:und_x_variant":[
        "Tagadirt n\u2019Lbaz"
    ],
    "wof:name":"Tagadirt-n-Bazmad",
    "wof:placetype":"locality"
},
  "geometry": {"coordinates":[-8.19679,30.63785],"type":"Point"}
}