{
  "type": "Feature",
  "properties": {
    "gn:admin1_code":"7.0",
    "gn:asciiname":"Inflas",
    "gn:country_code":"MA",
    "gn:dem":1021,
    "gn:feature_class":"P",
    "gn:feature_code":"PPL",
    "gn:name":"Inflas",
    "gn:population":0,
    "gn:timezone":"Africa/Casablanca",
    "iso:country":"MA",
    "wof:name":"Inflas",
    "wof:placetype":"locality"
},
  "geometry": {"coordinates":[-7.71343,31.39857],"type":"Point"}
}