{
  "type": "Feature",
  "properties": {
    "gn:admin1_code":"04",
    "gn:asciiname":"Douar Miloudat",
    "gn:country_code":"MA",
    "gn:dem":145,
    "gn:feature_class":"P",
    "gn:feature_code":"PPL",
    "gn:name":"Douar Miloudat",
    "gn:population":0,
    "gn:timezone":"Africa/Casablanca",
    "iso:country":"MA",
    "name:und_x_variant":[
        "Miloudate",
        "Miloudat"
    ],
    "wof:name":"Douar Miloudat",
    "wof:placetype":"locality"
},
  "geometry": {"coordinates":[-5.80273,34.81766],"type":"Point"}
}