{
  "type": "Feature",
  "properties": {
    "gn:country":"MA",
    "gn:fcode":"ADM3",
    "gn:pop":17412,
    "iso:country":"MA",
    "name:ara_x_preferred":[
        "\u062a\u0627\u0641\u062a\u0634\u0646\u0627"
    ],
    "name:fra_x_preferred":[
        "Tagounite"
    ],
    "name:fra_x_variant":[
        "Tagounite (CR)",
        "Tagounite (Commune Rurale)"
    ],
    "qs:name":"Tagounite",
    "qs:photos_9r":0,
    "qs:photos_sr":0,
    "qs:pop_sr":"6",
    "wof:name":"Tagounite",
    "wof:placetype":"localadmin",
    "wof:population":17412
},
  "geometry": {"coordinates":[-5.91509,29.95854],"type":"Point"}
}