{
  "type": "Feature",
  "properties": {
    "gn:admin1_code":"03",
    "gn:asciiname":"Douar Lemrabeh",
    "gn:country_code":"MA",
    "gn:dem":180,
    "gn:feature_class":"P",
    "gn:feature_code":"PPL",
    "gn:name":"Douar Lemrabeh",
    "gn:population":0,
    "gn:timezone":"Africa/Casablanca",
    "iso:country":"MA",
    "name:und_x_variant":[
        "Mrabeih",
        "Douar Mrabiha",
        "Douar Lemrabeh"
    ],
    "wof:name":"Douar Lemrabeh",
    "wof:placetype":"locality"
},
  "geometry": {"coordinates":[-5.35412,34.36623],"type":"Point"}
}