{
  "type": "Feature",
  "properties": {
    "gn:admin1_code":"2.0",
    "gn:asciiname":"Douar El Gazzara",
    "gn:country_code":"MA",
    "gn:dem":646,
    "gn:feature_class":"P",
    "gn:feature_code":"PPL",
    "gn:name":"Douar El Gazzara",
    "gn:population":0,
    "gn:timezone":"Africa/Casablanca",
    "iso:country":"MA",
    "wof:name":"Douar El Gazzara",
    "wof:placetype":"locality"
},
  "geometry": {"coordinates":[-2.42054,34.70334],"type":"Point"}
}