{
  "type": "Feature",
  "properties": {
    "gn:admin1_code":"6.0",
    "gn:asciiname":"Douar Qnadcha",
    "gn:country_code":"MA",
    "gn:dem":443,
    "gn:feature_class":"P",
    "gn:feature_code":"PPL",
    "gn:name":"Douar Qnadcha",
    "gn:population":0,
    "gn:timezone":"Africa/Casablanca",
    "iso:country":"MA",
    "wof:name":"Douar Qnadcha",
    "wof:placetype":"locality"
},
  "geometry": {"coordinates":[-7.21011,33.19387],"type":"Point"}
}