{
  "type": "Feature",
  "properties": {
    "gn:admin1_code":"08",
    "gn:asciiname":"Tamasgount",
    "gn:country_code":"MA",
    "gn:dem":1498,
    "gn:feature_class":"P",
    "gn:feature_code":"PPL",
    "gn:name":"Tamasgount",
    "gn:population":0,
    "gn:timezone":"Africa/Casablanca",
    "iso:country":"MA",
    "name:und_x_variant":[
        "Tamzgourt",
        "Tamasgount"
    ],
    "wof:name":"Tamasgount",
    "wof:placetype":"locality"
},
  "geometry": {"coordinates":[-5.16363,32.01689],"type":"Point"}
}