{
  "type": "Feature",
  "properties": {
    "gn:admin1_code":"09",
    "gn:asciiname":"Tijefert",
    "gn:country_code":"MA",
    "gn:dem":1521,
    "gn:feature_class":"P",
    "gn:feature_code":"PPL",
    "gn:name":"Tijefert",
    "gn:population":0,
    "gn:timezone":"Africa/Casablanca",
    "iso:country":"MA",
    "name:und_x_variant":[
        "Tijeferte",
        "Tijferte",
        "Tijefert"
    ],
    "wof:name":"Tijefert",
    "wof:placetype":"locality"
},
  "geometry": {"coordinates":[-8.7227,29.62513],"type":"Point"}
}