{
  "type": "Feature",
  "properties": {
    "gn:admin1_code":"7.0",
    "gn:asciiname":"Dar Sidi Othmane",
    "gn:country_code":"MA",
    "gn:dem":539,
    "gn:feature_class":"P",
    "gn:feature_code":"PPL",
    "gn:name":"Dar Sidi Othmane",
    "gn:population":0,
    "gn:timezone":"Africa/Casablanca",
    "iso:country":"MA",
    "wof:name":"Dar Sidi Othmane",
    "wof:placetype":"locality"
},
  "geometry": {"coordinates":[-7.78181,31.57829000000001],"type":"Point"}
}