{
  "type": "Feature",
  "properties": {
    "gn:asciiname":"Tnine Ourika",
    "gn:country_code":"MA",
    "gn:dem":1021,
    "gn:feature_class":"P",
    "gn:feature_code":"PPL",
    "gn:name":"Tnine Ourika",
    "gn:population":0,
    "gn:timezone":"Africa/Casablanca",
    "iso:country":"MA",
    "wof:name":"Tnine Ourika",
    "wof:placetype":"locality"
},
  "geometry": {"coordinates":[-7.74562,31.31137],"type":"Point"}
}