{
  "type": "Feature",
  "properties": {
    "gn:admin1_code":"08",
    "gn:asciiname":"Ait Tiourhza",
    "gn:country_code":"MA",
    "gn:dem":848,
    "gn:feature_class":"P",
    "gn:feature_code":"PPL",
    "gn:name":"A\u00eft Tiourhza",
    "gn:population":0,
    "gn:timezone":"Africa/Casablanca",
    "iso:country":"MA",
    "wof:name":"Ait Tiourhza",
    "wof:placetype":"locality"
},
  "geometry": {"coordinates":[-6.14662,30.64291],"type":"Point"}
}