{
  "type": "Feature",
  "properties": {
    "gn:admin1_code":"07",
    "gn:asciiname":"Douar Tinagra",
    "gn:country_code":"MA",
    "gn:dem":373,
    "gn:feature_class":"P",
    "gn:feature_code":"PPL",
    "gn:name":"Douar Tinagra",
    "gn:population":0,
    "gn:timezone":"Africa/Casablanca",
    "iso:country":"MA",
    "name:und_x_variant":[
        "Tanegra",
        "Douar Tnarga",
        "Douar Tinagra"
    ],
    "wof:name":"Douar Tinagra",
    "wof:placetype":"locality"
},
  "geometry": {"coordinates":[-9.15222,31.60186],"type":"Point"}
}