{
  "type": "Feature",
  "properties": {
    "gn:admin1_code":"55.0",
    "gn:asciiname":"Id Bou Aabane",
    "gn:country_code":"MA",
    "gn:dem":787,
    "gn:feature_class":"P",
    "gn:feature_code":"PPL",
    "gn:name":"Id Bou Aabane",
    "gn:population":0,
    "gn:timezone":"Africa/Casablanca",
    "iso:country":"MA",
    "wof:name":"Id Bou Aabane",
    "wof:placetype":"locality"
},
  "geometry": {"coordinates":[-9.62456,29.50888],"type":"Point"}
}