{
  "type": "Feature",
  "properties": {
    "gn:admin1_code":"7.0",
    "gn:asciiname":"Dar Oulad Miloud",
    "gn:country_code":"MA",
    "gn:dem":416,
    "gn:feature_class":"P",
    "gn:feature_code":"PPL",
    "gn:name":"Dar Oulad Miloud",
    "gn:population":0,
    "gn:timezone":"Africa/Casablanca",
    "iso:country":"MA",
    "wof:name":"Dar Oulad Miloud",
    "wof:placetype":"locality"
},
  "geometry": {"coordinates":[-7.72356,32.15064],"type":"Point"}
}