{
  "type": "Feature",
  "properties": {
    "gn:admin1_code":"9.0",
    "gn:asciiname":"El Khmis",
    "gn:country_code":"MA",
    "gn:dem":1163,
    "gn:feature_class":"P",
    "gn:feature_code":"PPL",
    "gn:name":"El Khmis",
    "gn:population":0,
    "gn:timezone":"Africa/Casablanca",
    "iso:country":"MA",
    "wof:name":"El Khmis",
    "wof:placetype":"neighbourhood"
},
  "geometry": {"coordinates":[-9.47936,30.67482],"type":"Point"}
}