{
  "type": "Feature",
  "properties": {
    "gn:admin1_code":"08",
    "gn:asciiname":"Ksir Ignaouene",
    "gn:country_code":"MA",
    "gn:dem":637,
    "gn:feature_class":"P",
    "gn:feature_code":"PPL",
    "gn:name":"Ksir Ignaouene",
    "gn:population":0,
    "gn:timezone":"Africa/Casablanca",
    "iso:country":"MA",
    "name:und_x_variant":[
        "Ksir Ignaoene",
        "Ksir Ignaouene"
    ],
    "wof:name":"Ksir Ignaouene",
    "wof:placetype":"locality"
},
  "geometry": {"coordinates":[-5.53,30.08],"type":"Point"}
}