{
  "type": "Feature",
  "properties": {
    "gn:admin1_code":"7.0",
    "gn:asciiname":"Douar Meryem Rzazqa",
    "gn:country_code":"MA",
    "gn:dem":417,
    "gn:feature_class":"P",
    "gn:feature_code":"PPL",
    "gn:name":"Douar Meryem Rzazqa",
    "gn:population":0,
    "gn:timezone":"Africa/Casablanca",
    "iso:country":"MA",
    "wof:name":"Douar Meryem Rzazqa",
    "wof:placetype":"locality"
},
  "geometry": {"coordinates":[-7.38236,32.1687],"type":"Point"}
}