{
  "type": "Feature",
  "properties": {
    "gn:admin1_code":"07",
    "gn:asciiname":"El Mokhtar ben Hamdane",
    "gn:country_code":"MA",
    "gn:dem":516,
    "gn:feature_class":"P",
    "gn:feature_code":"PPL",
    "gn:name":"El Mokhtar ben Hamdane",
    "gn:population":0,
    "gn:timezone":"Africa/Casablanca",
    "iso:country":"MA",
    "name:und_x_variant":[
        "Al Mokhtar Ben Hamdane"
    ],
    "wof:name":"El Mokhtar ben Hamdane",
    "wof:placetype":"locality"
},
  "geometry": {"coordinates":[-9.36592,31.43966],"type":"Point"}
}