{
  "type": "Feature",
  "properties": {
    "gn:admin1_code":"9.0",
    "gn:asciiname":"Dou-ou-Azrou",
    "gn:country_code":"MA",
    "gn:dem":1068,
    "gn:feature_class":"P",
    "gn:feature_code":"PPL",
    "gn:name":"Dou-ou-Azrou",
    "gn:population":0,
    "gn:timezone":"Africa/Casablanca",
    "iso:country":"MA",
    "wof:name":"Dou-ou-Azrou",
    "wof:placetype":"locality"
},
  "geometry": {"coordinates":[-7.91658,30.77182],"type":"Point"}
}