{
  "type": "Feature",
  "properties": {
    "gn:admin1_code":"6.0",
    "gn:asciiname":"Douar Tolba",
    "gn:country_code":"MA",
    "gn:dem":238,
    "gn:feature_class":"P",
    "gn:feature_code":"PPL",
    "gn:name":"Douar Tolba",
    "gn:population":0,
    "gn:timezone":"Africa/Casablanca",
    "iso:country":"MA",
    "wof:name":"Douar Tolba",
    "wof:placetype":"locality"
},
  "geometry": {"coordinates":[-8.38255,32.51374000000001],"type":"Point"}
}