{
  "type": "Feature",
  "properties": {
    "gn:admin1_code":"01",
    "gn:asciiname":"Douar Dar Lgarraf",
    "gn:country_code":"MA",
    "gn:dem":418,
    "gn:feature_class":"P",
    "gn:feature_code":"PPL",
    "gn:name":"Douar Dar Lgarraf",
    "gn:population":0,
    "gn:timezone":"Africa/Casablanca",
    "iso:country":"MA",
    "name:und_x_variant":[
        "Dar el Guerrafe",
        "Dar Gouerraf",
        "Douar Dar Lgarraf"
    ],
    "wof:name":"Douar Dar Lgarraf",
    "wof:placetype":"locality"
},
  "geometry": {"coordinates":[-5.42415,35.31618],"type":"Point"}
}