{
  "type": "Feature",
  "properties": {
    "gn:admin1_code":"7.0",
    "gn:asciiname":"Imchakene",
    "gn:country_code":"MA",
    "gn:dem":598,
    "gn:feature_class":"P",
    "gn:feature_code":"PPL",
    "gn:name":"Imchakene",
    "gn:population":0,
    "gn:timezone":"Africa/Casablanca",
    "iso:country":"MA",
    "wof:name":"Imchakene",
    "wof:placetype":"locality"
},
  "geometry": {"coordinates":[-7.74314,31.52161],"type":"Point"}
}