{
  "type": "Feature",
  "properties": {
    "gn:admin1_code":"5.0",
    "gn:asciiname":"Tighzat-n-Tiyni",
    "gn:country_code":"MA",
    "gn:dem":1660,
    "gn:feature_class":"P",
    "gn:feature_code":"PPL",
    "gn:name":"Tighzat-n-Tiyni",
    "gn:population":0,
    "gn:timezone":"Africa/Casablanca",
    "iso:country":"MA",
    "wof:name":"Tighzat-n-Tiyni",
    "wof:placetype":"locality"
},
  "geometry": {"coordinates":[-6.5523,31.85772],"type":"Point"}
}