{
  "type": "Feature",
  "properties": {
    "gn:admin1_code":"01",
    "gn:asciiname":"Jbinate",
    "gn:country_code":"MA",
    "gn:dem":17,
    "gn:feature_class":"P",
    "gn:feature_code":"PPL",
    "gn:name":"Jbinate",
    "gn:population":0,
    "gn:timezone":"Africa/Casablanca",
    "iso:country":"MA",
    "wof:name":"Jbinate",
    "wof:placetype":"locality"
},
  "geometry": {"coordinates":[-5.95115,35.1166],"type":"Point"}
}