{
  "type": "Feature",
  "properties": {
    "gn:admin1_code":"02",
    "gn:asciiname":"Tikhamine",
    "gn:country_code":"MA",
    "gn:dem":1245,
    "gn:feature_class":"P",
    "gn:feature_code":"PPL",
    "gn:name":"Tikhamine",
    "gn:population":0,
    "gn:timezone":"Africa/Casablanca",
    "iso:country":"MA",
    "wof:name":"Tikhamine",
    "wof:placetype":"locality"
},
  "geometry": {"coordinates":[-3.66912,33.78832],"type":"Point"}
}