{
  "type": "Feature",
  "properties": {
    "gn:admin1_code":"09",
    "gn:asciiname":"Ait Mimoun",
    "gn:country_code":"MA",
    "gn:dem":1415,
    "gn:feature_class":"P",
    "gn:feature_code":"PPL",
    "gn:name":"A\u00eft Mimoun",
    "gn:population":0,
    "gn:timezone":"Africa/Casablanca",
    "iso:country":"MA",
    "wof:name":"Ait Mimoun",
    "wof:placetype":"locality"
},
  "geometry": {"coordinates":[-8.39364,30.43318],"type":"Point"}
}