{
  "type": "Feature",
  "properties": {
    "gn:admin1_code":"55",
    "gn:asciiname":"Ait Tiouine",
    "gn:cc2":"MA",
    "gn:country_code":"MA",
    "gn:dem":521,
    "gn:feature_class":"P",
    "gn:feature_code":"PPL",
    "gn:name":"A\u00eft Tiouine",
    "gn:population":0,
    "gn:timezone":"Africa/Casablanca",
    "iso:country":"MA",
    "name:und_x_variant":[
        "A\u00eft Tiyouwine",
        "A\u00eft Tiouine"
    ],
    "wof:name":"Ait Tiouine",
    "wof:placetype":"locality"
},
  "geometry": {"coordinates":[-9.55,30.85],"type":"Point"}
}