{
  "type": "Feature",
  "properties": {
    "gn:admin1_code":"09",
    "gn:asciiname":"Igounane",
    "gn:country_code":"MA",
    "gn:dem":1633,
    "gn:feature_class":"P",
    "gn:feature_code":"PPL",
    "gn:name":"Igounane",
    "gn:population":0,
    "gn:timezone":"Africa/Casablanca",
    "iso:country":"MA",
    "name:und_x_variant":[
        "Iougnane"
    ],
    "wof:name":"Igounane",
    "wof:placetype":"locality"
},
  "geometry": {"coordinates":[-8.76865,30.80324],"type":"Point"}
}