{
  "type": "Feature",
  "properties": {
    "gn:admin1_code":"1.0",
    "gn:asciiname":"Yadrene",
    "gn:country_code":"MA",
    "gn:dem":684,
    "gn:feature_class":"P",
    "gn:feature_code":"PPL",
    "gn:name":"Yadrene",
    "gn:population":0,
    "gn:timezone":"Africa/Casablanca",
    "iso:country":"MA",
    "wof:name":"Yadrene",
    "wof:placetype":"locality"
},
  "geometry": {"coordinates":[-5.20985,35.41636],"type":"Point"}
}