{
  "type": "Feature",
  "properties": {
    "gn:country":"MA",
    "gn:fcode":"ADM3",
    "gn:pop":19864,
    "iso:country":"MA",
    "name:ara_x_preferred":[
        "\u062b\u0648\u0627\u0644\u062a"
    ],
    "name:fra_x_preferred":[
        "Ait Ourir"
    ],
    "name:fra_x_variant":[
        "Ait Ourir (MU)",
        "Ait Ourir (Commune Urbaine)"
    ],
    "qs:name":"Ait Ourir",
    "qs:photos_9r":0,
    "qs:photos_sr":0,
    "qs:pop_sr":"6",
    "wd:wordcount":349,
    "wof:name":"Ait Ourir",
    "wof:placetype":"localadmin",
    "wof:population":19864
},
  "geometry": {"coordinates":[-7.66636,31.56708],"type":"Point"}
}