{
  "type": "Feature",
  "properties": {
    "gn:country":"MA",
    "gn:fcode":"ADM3",
    "gn:population":19864,
    "iso:country":"MA",
    "name:ara_x_preferred":[
        "\u062b\u0648\u0627\u0644\u062a"
    ],
    "name:ara_x_variant":[
        "\u0622\u064a\u062a \u0623\u0648\u0631\u064a\u0631"
    ],
    "name:ary_x_preferred":[
        "\u0622\u064a\u062a \u0648\u0631\u064a\u0631"
    ],
    "name:azb_x_preferred":[
        "\u0622\u06cc\u062a \u0648\u0631\u06cc\u0631"
    ],
    "name:cat_x_preferred":[
        "Ait Ourir"
    ],
    "name:ceb_x_preferred":[
        "A\u00eft Ourir"
    ],
    "name:deu_x_preferred":[
        "A\u00eft Ourir"
    ],
    "name:eng_x_preferred":[
        "Ait Ourir"
    ],
    "name:fas_x_preferred":[
        "\u0622\u06cc\u062a \u0648\u0631\u06cc\u0631"
    ],
    "name:fra_x_preferred":[
        "Ait Ourir"
    ],
    "name:fra_x_variant":[
        "Ait Ourir (MU)",
        "Ait Ourir (Commune Urbaine)",
        "A\u00eft Ourir"
    ],
    "name:nld_x_preferred":[
        "Ait Ourir"
    ],
    "name:pol_x_preferred":[
        "Ajt Warir"
    ],
    "name:por_x_preferred":[
        "Ait Ourir"
    ],
    "name:shi_x_preferred":[
        "Ayt Urir"
    ],
    "name:swe_x_preferred":[
        "A\u00eft Ourir"
    ],
    "name:urd_x_preferred":[
        "\u0622\u06cc\u062a \u0627\u0648\u0631\u06cc\u0631"
    ],
    "qs:name":"Ait Ourir",
    "qs:photos_9r":0,
    "qs:photos_sr":0,
    "qs:pop_sr":"6",
    "wd:wordcount":349,
    "wof:name":"Ait Ourir",
    "wof:placetype":"localadmin",
    "wof:population":19864
},
  "geometry": {"coordinates":[-7.66636,31.56708],"type":"Point"}
}