{
  "type": "Feature",
  "properties": {
    "gn:admin1_code":"09",
    "gn:asciiname":"Tiskht",
    "gn:country_code":"MA",
    "gn:dem":1754,
    "gn:feature_class":"P",
    "gn:feature_code":"PPL",
    "gn:name":"Tiskht",
    "gn:population":0,
    "gn:timezone":"Africa/Casablanca",
    "iso:country":"MA",
    "name:und_x_variant":[
        "Tissekhte n\u2019A\u00eft Ouadif",
        "Tissekht",
        "Tiskht"
    ],
    "wof:name":"Tiskht",
    "wof:placetype":"locality"
},
  "geometry": {"coordinates":[-7.81991,30.73683],"type":"Point"}
}