{
  "type": "Feature",
  "properties": {
    "gn:admin1_code":"3.0",
    "gn:asciiname":"Ait Moussa",
    "gn:country_code":"MA",
    "gn:dem":1390,
    "gn:feature_class":"P",
    "gn:feature_code":"PPL",
    "gn:name":"Ait Moussa",
    "gn:population":0,
    "gn:timezone":"Africa/Casablanca",
    "iso:country":"MA",
    "wof:name":"Ait Moussa",
    "wof:placetype":"locality"
},
  "geometry": {"coordinates":[-4.8522,33.673],"type":"Point"}
}