{
  "type": "Feature",
  "properties": {
    "gn:admin1_code":"7.0",
    "gn:asciiname":"Al Khemis",
    "gn:country_code":"MA",
    "gn:dem":861,
    "gn:feature_class":"P",
    "gn:feature_code":"PPL",
    "gn:name":"Al Khemis",
    "gn:population":0,
    "gn:timezone":"Africa/Casablanca",
    "iso:country":"MA",
    "wof:name":"Al Khemis",
    "wof:placetype":"locality"
},
  "geometry": {"coordinates":[-7.76969,31.3874],"type":"Point"}
}