{
  "type": "Feature",
  "properties": {
    "gn:admin1_code":"7.0",
    "gn:asciiname":"Zouinat",
    "gn:country_code":"MA",
    "gn:dem":297,
    "gn:feature_class":"P",
    "gn:feature_code":"PPL",
    "gn:name":"Zouinat",
    "gn:population":0,
    "gn:timezone":"Africa/Casablanca",
    "iso:country":"MA",
    "wof:name":"Zouinat",
    "wof:placetype":"locality"
},
  "geometry": {"coordinates":[-8.80706,31.88258],"type":"Point"}
}