{
  "type": "Feature",
  "properties": {
    "gn:admin1_code":"07",
    "gn:asciiname":"Douar Lehouifrat",
    "gn:country_code":"MA",
    "gn:dem":384,
    "gn:feature_class":"P",
    "gn:feature_code":"PPL",
    "gn:name":"Douar Lehouifrat",
    "gn:population":0,
    "gn:timezone":"Africa/Casablanca",
    "iso:country":"MA",
    "name:und_x_variant":[
        "Douar Bouhane",
        "Bouhane",
        "Douar Lehouifrat"
    ],
    "wof:name":"Douar Lehouifrat",
    "wof:placetype":"locality"
},
  "geometry": {"coordinates":[-8.39952,32.23795],"type":"Point"}
}