{
  "type": "Feature",
  "properties": {
    "gn:country":"MA",
    "gn:fcode":"ADM3",
    "gn:population":4211,
    "iso:country":"MA",
    "name:ara_x_preferred":[
        "\u0644\u0643\u0641\u0627\u0641"
    ],
    "name:fra_x_preferred":[
        "Elfoqra"
    ],
    "name:fra_x_variant":[
        "Elfoqra (CR)",
        "Elfoqra (Commune Rurale)"
    ],
    "qs:name":"Elfoqra",
    "qs:photos_9r":0,
    "qs:photos_sr":0,
    "qs:pop_sr":"4",
    "wof:name":"Elfoqra",
    "wof:placetype":"localadmin",
    "wof:population":4211
},
  "geometry": {"coordinates":[-6.97032,32.70504],"type":"Point"}
}