{
  "type": "Feature",
  "properties": {
    "gn:admin1_code":"05",
    "gn:asciiname":"Ait 'Ali ou Mhand",
    "gn:country_code":"MA",
    "gn:dem":829,
    "gn:feature_class":"P",
    "gn:feature_code":"PPL",
    "gn:name":"A\u00eft \u2019Ali ou Mhand",
    "gn:population":0,
    "gn:timezone":"Africa/Casablanca",
    "iso:country":"MA",
    "name:und_x_variant":[
        "A\u00eft \u2019Ali ou Mhand",
        "A\u00eft Ali Ou Mhand"
    ],
    "wof:name":"Ait 'Ali ou Mhand",
    "wof:placetype":"locality"
},
  "geometry": {"coordinates":[-6.42502,32.11109],"type":"Point"}
}