{
  "type": "Feature",
  "properties": {
    "gn:admin1_code":"9.0",
    "gn:asciiname":"Arhoummif ou Azar",
    "gn:country_code":"MA",
    "gn:dem":1281,
    "gn:feature_class":"P",
    "gn:feature_code":"PPL",
    "gn:name":"Arhoummif ou Azar",
    "gn:population":0,
    "gn:timezone":"Africa/Casablanca",
    "iso:country":"MA",
    "wof:name":"Arhoummif ou Azar",
    "wof:placetype":"locality"
},
  "geometry": {"coordinates":[-9.45105,30.69195],"type":"Point"}
}