{
  "type": "Feature",
  "properties": {
    "gn:admin1_code":"6.0",
    "gn:asciiname":"Oulad El Haj Lahsene",
    "gn:country_code":"MA",
    "gn:dem":542,
    "gn:feature_class":"P",
    "gn:feature_code":"PPL",
    "gn:name":"Oulad El Haj Lahsene",
    "gn:population":0,
    "gn:timezone":"Africa/Casablanca",
    "iso:country":"MA",
    "wof:name":"Oulad El Haj Lahsene",
    "wof:placetype":"locality"
},
  "geometry": {"coordinates":[-7.5291,32.95424000000001],"type":"Point"}
}