{
  "type": "Feature",
  "properties": {
    "gn:admin1_code":"4.0",
    "gn:asciiname":"Jouaber",
    "gn:country_code":"MA",
    "gn:dem":64,
    "gn:feature_class":"P",
    "gn:feature_code":"PPL",
    "gn:name":"Jouaber",
    "gn:population":0,
    "gn:timezone":"Africa/Casablanca",
    "iso:country":"MA",
    "wof:name":"Jouaber",
    "wof:placetype":"locality"
},
  "geometry": {"coordinates":[-6.50319,34.19789],"type":"Point"}
}