{
  "type": "Feature",
  "properties": {
    "gn:admin1_code":"01",
    "gn:asciiname":"Douar Lgara",
    "gn:country_code":"MA",
    "gn:dem":141,
    "gn:feature_class":"P",
    "gn:feature_code":"PPL",
    "gn:name":"Douar Lgara",
    "gn:population":0,
    "gn:timezone":"Africa/Casablanca",
    "iso:country":"MA",
    "name:und_x_variant":[
        "Gara",
        "El Gara",
        "Douar Lgara"
    ],
    "wof:name":"Douar Lgara",
    "wof:placetype":"locality"
},
  "geometry": {"coordinates":[-5.74693,35.02800999999999],"type":"Point"}
}