{
  "type": "Feature",
  "properties": {
    "gn:admin1_code":"07",
    "gn:asciiname":"Douar el Ksour",
    "gn:country_code":"MA",
    "gn:dem":462,
    "gn:feature_class":"P",
    "gn:feature_code":"PPL",
    "gn:name":"Douar el Ksour",
    "gn:population":0,
    "gn:timezone":"Africa/Casablanca",
    "iso:country":"MA",
    "name:und_x_variant":[
        "Oulad Ksour",
        "El Ksour",
        "Douar el Ksour"
    ],
    "wof:name":"Douar el Ksour",
    "wof:placetype":"locality"
},
  "geometry": {"coordinates":[-7.43599,32.03803],"type":"Point"}
}