{
  "type": "Feature",
  "properties": {
    "gn:admin1_code":"08",
    "gn:asciiname":"Anzal",
    "gn:country_code":"MA",
    "gn:dem":1596,
    "gn:feature_class":"P",
    "gn:feature_code":"PPL",
    "gn:name":"Anzal",
    "gn:population":0,
    "gn:timezone":"Africa/Casablanca",
    "iso:country":"MA",
    "name:und_x_variant":[
        "Anezal",
        "Amzel",
        "Anzal",
        "Anzel"
    ],
    "wof:name":"Anzal",
    "wof:placetype":"locality"
},
  "geometry": {"coordinates":[-7.29885,30.75625],"type":"Point"}
}