{
  "type": "Feature",
  "properties": {
    "gn:admin1_code":"7.0",
    "gn:asciiname":"Jaaydat Ait El Haj Thami",
    "gn:country_code":"MA",
    "gn:dem":722,
    "gn:feature_class":"P",
    "gn:feature_code":"PPL",
    "gn:name":"Jaaydat Ait El Haj Thami",
    "gn:population":0,
    "gn:timezone":"Africa/Casablanca",
    "iso:country":"MA",
    "wof:name":"Jaaydat Ait El Haj Thami",
    "wof:placetype":"locality"
},
  "geometry": {"coordinates":[-7.8058,31.90474],"type":"Point"}
}