{
  "type": "Feature",
  "properties": {
    "gn:admin1_code":"07",
    "gn:asciiname":"Ikis",
    "gn:country_code":"MA",
    "gn:dem":1990,
    "gn:feature_class":"P",
    "gn:feature_code":"PPL",
    "gn:name":"Ikis",
    "gn:population":0,
    "gn:timezone":"Africa/Casablanca",
    "iso:country":"MA",
    "name:und_x_variant":[
        "Ikkis"
    ],
    "wof:name":"Ikis",
    "wof:placetype":"locality"
},
  "geometry": {"coordinates":[-8.39513,30.93173],"type":"Point"}
}