{
  "type": "Feature",
  "properties": {
    "gn:admin1_code":"6.0",
    "gn:asciiname":"El Koub",
    "gn:country_code":"MA",
    "gn:dem":176,
    "gn:feature_class":"P",
    "gn:feature_code":"PPL",
    "gn:name":"El Koub",
    "gn:population":0,
    "gn:timezone":"Africa/Casablanca",
    "iso:country":"MA",
    "wof:name":"El Koub",
    "wof:placetype":"locality"
},
  "geometry": {"coordinates":[-8.14464,32.81389],"type":"Point"}
}