{
  "type": "Feature",
  "properties": {
    "gn:gn_country":"MA",
    "gn:gn_fcode":"ADM3",
    "gn:gn_pop":16614,
    "gn:population":17360,
    "iso:country":"MA",
    "name:ara_x_preferred":[
        "\u0627\u063a\u0631\u064a\u0633 \u0627\u0644\u0633\u0641\u0644\u064a"
    ],
    "name:fra_x_preferred":[
        "Melaab"
    ],
    "name:fra_x_variant":[
        "Melaab (CR)",
        "Melaab (Commune Rurale)"
    ],
    "qs_pg:aaroncc":"MA",
    "qs_pg:gn_country":"MA",
    "qs_pg:gn_fcode":"ADM3",
    "qs_pg:gn_pop":16614,
    "qs_pg:name":"Melaab",
    "qs_pg:photos_9r":0,
    "qs_pg:photos_sr":0,
    "qs_pg:pop_sr":6,
    "qs_pg:qs_pg_placetype":"localadmin",
    "wof:name":"Melaab",
    "wof:placetype":"localadmin",
    "wof:population":17360
},
  "geometry": {"coordinates":[-4.74238,31.47375],"type":"Point"}
}