{
  "type": "Feature",
  "properties": {
    "gn:admin1_code":"06",
    "gn:asciiname":"Douar Ali Ben Larbi",
    "gn:country_code":"MA",
    "gn:dem":97,
    "gn:feature_class":"P",
    "gn:feature_code":"PPL",
    "gn:name":"Douar Ali Ben Larbi",
    "gn:population":0,
    "gn:timezone":"Africa/Casablanca",
    "iso:country":"MA",
    "name:und_x_variant":[
        "Douar Abdallah"
    ],
    "wof:name":"Douar Ali Ben Larbi",
    "wof:placetype":"locality"
},
  "geometry": {"coordinates":[-8.42983,33.01893],"type":"Point"}
}