{
  "type": "Feature",
  "properties": {
    "gn:admin1_code":"03",
    "gn:asciiname":"El Merj",
    "gn:country_code":"MA",
    "gn:dem":1331,
    "gn:feature_class":"P",
    "gn:feature_code":"PPL",
    "gn:name":"El Merj",
    "gn:population":0,
    "gn:timezone":"Africa/Casablanca",
    "iso:country":"MA",
    "name:und_x_variant":[
        "Al Merj"
    ],
    "wof:name":"El Merj",
    "wof:placetype":"locality"
},
  "geometry": {"coordinates":[-3.91371,34.65951],"type":"Point"}
}