{
  "type": "Feature",
  "properties": {
    "gn:admin1_code":"4.0",
    "gn:asciiname":"Haoumat Sougzera",
    "gn:country_code":"MA",
    "gn:dem":283,
    "gn:feature_class":"P",
    "gn:feature_code":"PPL",
    "gn:name":"Haoumat Sougzera",
    "gn:population":0,
    "gn:timezone":"Africa/Casablanca",
    "iso:country":"MA",
    "wof:name":"Haoumat Sougzera",
    "wof:placetype":"locality"
},
  "geometry": {"coordinates":[-5.67313,34.71448],"type":"Point"}
}