{
  "type": "Feature",
  "properties": {
    "gn:admin1_code":"06",
    "gn:asciiname":"Douar el Hadda",
    "gn:country_code":"MA",
    "gn:dem":259,
    "gn:feature_class":"P",
    "gn:feature_code":"PPL",
    "gn:name":"Douar el Hadda",
    "gn:population":0,
    "gn:timezone":"Africa/Casablanca",
    "iso:country":"MA",
    "wof:name":"Douar el Hadda",
    "wof:placetype":"locality"
},
  "geometry": {"coordinates":[-8.32995,32.51923],"type":"Point"}
}