{
  "type": "Feature",
  "properties": {
    "gn:admin1_code":"4.0",
    "gn:asciiname":"Dar Hargua",
    "gn:country_code":"MA",
    "gn:dem":4,
    "gn:feature_class":"P",
    "gn:feature_code":"PPL",
    "gn:name":"Dar Hargua",
    "gn:population":0,
    "gn:timezone":"Africa/Casablanca",
    "iso:country":"MA",
    "wof:name":"Dar Hargua",
    "wof:placetype":"locality"
},
  "geometry": {"coordinates":[-6.57282,34.29544],"type":"Point"}
}