{
  "type": "Feature",
  "properties": {
    "gn:admin1_code":"09",
    "gn:asciiname":"Asgoun",
    "gn:country_code":"MA",
    "gn:dem":771,
    "gn:feature_class":"P",
    "gn:feature_code":"PPL",
    "gn:name":"Asgoun",
    "gn:population":0,
    "gn:timezone":"Africa/Casablanca",
    "iso:country":"MA",
    "name:und_x_variant":[
        "Agadir Afzaou"
    ],
    "wof:name":"Asgoun",
    "wof:placetype":"locality"
},
  "geometry": {"coordinates":[-8.35762,30.51439],"type":"Point"}
}