{
  "type": "Feature",
  "properties": {
    "gn:admin1_code":"8.0",
    "gn:asciiname":"Talat",
    "gn:country_code":"MA",
    "gn:dem":1397,
    "gn:feature_class":"P",
    "gn:feature_code":"PPL",
    "gn:name":"Talat",
    "gn:population":0,
    "gn:timezone":"Africa/Casablanca",
    "iso:country":"MA",
    "name:ceb_x_preferred":[
        "Talat"
    ],
    "name:deu_x_preferred":[
        "Talat"
    ],
    "name:rus_x_preferred":[
        "\u0422\u0430\u043b\u0430\u0442"
    ],
    "wof:name":"Talat",
    "wof:placetype":"locality"
},
  "geometry": {"coordinates":[-6.15568,31.20119],"type":"Point"}
}