{
  "type": "Feature",
  "properties": {
    "gn:admin1_code":"08",
    "gn:asciiname":"Saheli",
    "gn:country_code":"MA",
    "gn:dem":907,
    "gn:feature_class":"P",
    "gn:feature_code":"PPL",
    "gn:name":"Saheli",
    "gn:population":0,
    "gn:timezone":"Africa/Casablanca",
    "iso:country":"MA",
    "name:und_x_variant":[
        "Ksar Sahli",
        "Sahli",
        "Saheli"
    ],
    "wof:name":"Saheli",
    "wof:placetype":"locality"
},
  "geometry": {"coordinates":[-3.43991,31.95384],"type":"Point"}
}