{
  "type": "Feature",
  "properties": {
    "gn:admin1_code":"9.0",
    "gn:asciiname":"Id Yahya",
    "gn:country_code":"MA",
    "gn:dem":311,
    "gn:feature_class":"P",
    "gn:feature_code":"PPL",
    "gn:name":"Id Yahya",
    "gn:population":0,
    "gn:timezone":"Africa/Casablanca",
    "iso:country":"MA",
    "wof:name":"Id Yahya",
    "wof:placetype":"locality"
},
  "geometry": {"coordinates":[-9.75258,30.82615],"type":"Point"}
}