{
  "type": "Feature",
  "properties": {
    "gn:admin1_code":"06",
    "gn:asciiname":"Oulad Youssef",
    "gn:country_code":"MA",
    "gn:dem":214,
    "gn:feature_class":"P",
    "gn:feature_code":"PPL",
    "gn:name":"Oulad Youssef",
    "gn:population":0,
    "gn:timezone":"Africa/Casablanca",
    "iso:country":"MA",
    "name:ara_x_preferred":[
        "\u0623\u0648\u0644\u0627\u062f \u064a\u0648\u0633\u0641"
    ],
    "name:cat_x_preferred":[
        "Oulad Youssef"
    ],
    "name:fra_x_preferred":[
        "Oulad Youssef"
    ],
    "name:ita_x_preferred":[
        "Ouled Youssef"
    ],
    "wof:name":"Oulad Youssef",
    "wof:placetype":"locality"
},
  "geometry": {"coordinates":[-7.31309,33.52591],"type":"Point"}
}