{
  "type": "Feature",
  "properties": {
    "gn:admin1_code":"09",
    "gn:asciiname":"Ammiyl",
    "gn:country_code":"MA",
    "gn:dem":976,
    "gn:feature_class":"P",
    "gn:feature_code":"PPL",
    "gn:name":"Ammiyl",
    "gn:population":0,
    "gn:timezone":"Africa/Casablanca",
    "iso:country":"MA",
    "name:und_x_variant":[
        "Anil"
    ],
    "wof:name":"Ammiyl",
    "wof:placetype":"locality"
},
  "geometry": {"coordinates":[-9.02516,29.76152],"type":"Point"}
}