{
  "type": "Feature",
  "properties": {
    "gn:admin1_code":"01",
    "gn:asciiname":"Douar Ikhrifene",
    "gn:country_code":"MA",
    "gn:dem":729,
    "gn:feature_class":"P",
    "gn:feature_code":"PPL",
    "gn:name":"Douar Ikhrifene",
    "gn:population":0,
    "gn:timezone":"Africa/Casablanca",
    "iso:country":"MA",
    "name:und_x_variant":[
        "Yjerfen",
        "Ikhrifane",
        "Ikherifene",
        "Douar Ikhrifene"
    ],
    "wof:name":"Douar Ikhrifene",
    "wof:placetype":"locality"
},
  "geometry": {"coordinates":[-4.59122,35.10572],"type":"Point"}
}