{
  "type": "Feature",
  "properties": {
    "iso:country":"MA",
    "name:ara_x_colloquial":[
        "L'Ocean",
        "Ocean",
        "Quartier de l'Ocean"
    ],
    "name:ara_x_preferred":[
        "Oc\u00e9an"
    ],
    "name:ara_x_variant":[
        "Aguedal",
        "Grand Aguedal",
        "L'Oc\u00e9an",
        "Quartier de l'Oc\u00e9an",
        "Rabat Ocean"
    ],
    "name:deu_x_preferred":[
        "Oc\u00e9an"
    ],
    "name:fra_x_preferred":[
        "Oc\u00e9an"
    ],
    "name:ita_x_preferred":[
        "Dipartimento di Oc\u00e9an"
    ],
    "name:nld_x_preferred":[
        "Oc\u00e9an"
    ],
    "name:nor_x_preferred":[
        "Oc\u00e9an"
    ],
    "name:pol_x_preferred":[
        "Oc\u00e9an"
    ],
    "name:rus_x_preferred":[
        "\u041e\u0441\u0435\u0430\u043d"
    ],
    "name:spa_x_preferred":[
        "Oc\u00e9an"
    ],
    "name:und_x_variant":[
        "Quartier de l\u2019Oc\u00e9an"
    ],
    "name:zho_x_preferred":[
        "\u5927\u6d0b\u5dde"
    ],
    "qs:gn_adm0_cc":"MA",
    "qs:gn_fcode":"PPLX",
    "qs:gn_local":2538475,
    "qs:gn_namadm1":"49",
    "qs:gn_name":"Oc\u00e9an",
    "qs:local_max":6601,
    "qs:local_sum":11673,
    "qs:localhoods":6,
    "qs:name":"Oc\u00e9an",
    "qs:name_adm0":"\u0627\u0644\u0645\u063a\u0631\u0628",
    "qs:name_adm1":"\u0627\u0644\u0631\u0628\u0627\u0637-\u0633\u0644\u0627-\u0632\u0645\u0648\u0631-\u0632\u0639\u064a\u0631",
    "qs:name_adm2":"\u0627\u0644\u0631\u0628\u0627\u0637",
    "qs:name_lau":"\u0627\u0644\u0631\u0628\u0627\u0637",
    "qs:name_local":"\u0627\u0644\u0631\u0628\u0627\u0637",
    "qs:photo_max":450,
    "qs:photo_sum":2645,
    "qs:placetype":"Suburb",
    "qs:quad_count":46,
    "qs:woe_adm0":23424893,
    "qs:woe_adm1":56120059,
    "qs:woe_adm2":56120074,
    "qs:woe_lau":56439566,
    "qs:woe_local":1539359,
    "qs:woe_ver":"7.10.0",
    "wd:wordcount":81,
    "wof:lang":[
        "ara"
    ],
    "wof:name":"Oc\u00e9an",
    "wof:placetype":"neighbourhood"
},
  "geometry": {"coordinates":[-6.839281,34.017399],"type":"Point"}
}