{
  "type": "Feature",
  "properties": {
    "gn:admin1_code":"1.0",
    "gn:asciiname":"Douar Mhajjar",
    "gn:country_code":"MA",
    "gn:dem":147,
    "gn:feature_class":"P",
    "gn:feature_code":"PPL",
    "gn:name":"Douar Mhajjar",
    "gn:population":0,
    "gn:timezone":"Africa/Casablanca",
    "iso:country":"MA",
    "wof:name":"Douar Mhajjar",
    "wof:placetype":"locality"
},
  "geometry": {"coordinates":[-5.39739,34.62107],"type":"Point"}
}