{
  "type": "Feature",
  "properties": {
    "gn:admin1_code":"8.0",
    "gn:asciiname":"Ali Ou Hammou Iblah",
    "gn:country_code":"MA",
    "gn:dem":2002,
    "gn:feature_class":"P",
    "gn:feature_code":"PPL",
    "gn:name":"Ali Ou Hammou Iblah",
    "gn:population":0,
    "gn:timezone":"Africa/Casablanca",
    "iso:country":"MA",
    "wof:name":"Ali Ou Hammou Iblah",
    "wof:placetype":"locality"
},
  "geometry": {"coordinates":[-5.734,31.17669],"type":"Point"}
}