{
  "type": "Feature",
  "properties": {
    "gn:country":"MA",
    "gn:fcode":"ADM3",
    "gn:population":1638,
    "iso:country":"MA",
    "name:ara_x_preferred":[
        "\u0645\u0631\u0643\u0632 \u0627\u0644\u0639\u0648\u0646\u0627\u062a"
    ],
    "name:fra_x_preferred":[
        "Sebt Lamaarif"
    ],
    "name:fra_x_variant":[
        "Sebt Lamaarif (AC)",
        "Sebt Lamaarif (Agglomeration Communale)"
    ],
    "qs:name":"Sebt Lamaarif",
    "qs:photos_9r":0,
    "qs:photos_sr":0,
    "qs:pop_sr":"3",
    "wof:name":"Sebt Lamaarif",
    "wof:placetype":"localadmin",
    "wof:population":1638
},
  "geometry": {"coordinates":[-8.57472,32.50288],"type":"Point"}
}