{
  "type": "Feature",
  "properties": {
    "gn:admin1_code":"09",
    "gn:asciiname":"Tifkilt",
    "gn:country_code":"MA",
    "gn:dem":1565,
    "gn:feature_class":"P",
    "gn:feature_code":"PPL",
    "gn:name":"Tifkilt",
    "gn:population":0,
    "gn:timezone":"Africa/Casablanca",
    "iso:country":"MA",
    "name:und_x_variant":[
        "Tifkilte",
        "Tifkilt"
    ],
    "wof:name":"Tifkilt",
    "wof:placetype":"locality"
},
  "geometry": {"coordinates":[-7.92428,30.88791],"type":"Point"}
}