{
  "type": "Feature",
  "properties": {
    "gn:admin1_code":"5.0",
    "gn:asciiname":"Ait Sarghint",
    "gn:country_code":"MA",
    "gn:dem":1280,
    "gn:feature_class":"P",
    "gn:feature_code":"PPL",
    "gn:name":"A\u00eft Sarghint",
    "gn:population":0,
    "gn:timezone":"Africa/Casablanca",
    "iso:country":"MA",
    "wof:name":"Ait Sarghint",
    "wof:placetype":"locality"
},
  "geometry": {"coordinates":[-6.91912,31.64698],"type":"Point"}
}