{
  "type": "Feature",
  "properties": {
    "gn:admin1_code":"07",
    "gn:asciiname":"Tarhzout",
    "gn:country_code":"MA",
    "gn:dem":1413,
    "gn:feature_class":"P",
    "gn:feature_code":"PPL",
    "gn:name":"Tarhzout",
    "gn:population":0,
    "gn:timezone":"Africa/Casablanca",
    "iso:country":"MA",
    "name:und_x_variant":[
        "Taghzoute",
        "Tarhzout"
    ],
    "wof:name":"Tarhzout",
    "wof:placetype":"locality"
},
  "geometry": {"coordinates":[-8.20849,31.1024],"type":"Point"}
}