{
  "type": "Feature",
  "properties": {
    "gn:admin1_code":"9.0",
    "gn:asciiname":"Agadiyr Ouzour",
    "gn:country_code":"MA",
    "gn:dem":1000,
    "gn:feature_class":"P",
    "gn:feature_code":"PPL",
    "gn:name":"Agadiyr Ouzour",
    "gn:population":0,
    "gn:timezone":"Africa/Casablanca",
    "iso:country":"MA",
    "wof:name":"Agadiyr Ouzour",
    "wof:placetype":"locality"
},
  "geometry": {"coordinates":[-9.23611,29.86726],"type":"Point"}
}