{
  "type": "Feature",
  "properties": {
    "gn:admin1_code":"9.0",
    "gn:asciiname":"Aqdz",
    "gn:country_code":"MA",
    "gn:dem":1226,
    "gn:feature_class":"P",
    "gn:feature_code":"PPL",
    "gn:name":"Aqdz",
    "gn:population":0,
    "gn:timezone":"Africa/Casablanca",
    "iso:country":"MA",
    "wof:name":"Aqdz",
    "wof:placetype":"locality"
},
  "geometry": {"coordinates":[-8.14689,30.87322],"type":"Point"}
}