{
  "type": "Feature",
  "properties": {
    "gn:country":"MA",
    "gn:fcode":"ADM3",
    "gn:population":24500,
    "iso:country":"MA",
    "name:ara_x_preferred":[
        "\u0645\u0635\u0645\u0648\u062f\u0629"
    ],
    "name:ara_x_variant":[
        "\u0639\u064a\u0646 \u0627\u0644\u062f\u0641\u0627\u0644\u064a"
    ],
    "name:ary_x_preferred":[
        "\u0639\u064a\u0646 \u0627\u0644\u062f\u0641\u0627\u0644\u064a"
    ],
    "name:azb_x_preferred":[
        "\u0639\u06cc\u0646 \u0627\u0644\u062f\u0641\u0627\u0644\u06cc"
    ],
    "name:cat_x_preferred":[
        "Ain Dfali"
    ],
    "name:ceb_x_preferred":[
        "Ain Dfali"
    ],
    "name:eng_x_preferred":[
        "Ain Dfali"
    ],
    "name:fas_x_preferred":[
        "\u0639\u06cc\u0646 \u0627\u0644\u062f\u0641\u0627\u0644\u06cc"
    ],
    "name:fra_x_preferred":[
        "Ain Dfali"
    ],
    "name:fra_x_variant":[
        "Ain Dfali (CR)",
        "Ain Dfali (Commune Rurale)",
        "A\u00efn Dfali"
    ],
    "name:ita_x_preferred":[
        "A\u00efn Dfali"
    ],
    "name:swe_x_preferred":[
        "Ain Dfali"
    ],
    "qs:name":"Ain Dfali",
    "qs:photos_9r":0,
    "qs:photos_sr":0,
    "qs:pop_sr":"7",
    "wd:wordcount":80,
    "wof:name":"Ain Dfali",
    "wof:placetype":"localadmin",
    "wof:population":24500
},
  "geometry": {"coordinates":[-5.54828,34.61544],"type":"Point"}
}