{
  "type": "Feature",
  "properties": {
    "gn:admin1_code":"3.0",
    "gn:asciiname":"Almou Abouri",
    "gn:country_code":"MA",
    "gn:dem":1681,
    "gn:feature_class":"P",
    "gn:feature_code":"PPL",
    "gn:name":"Almou Abouri",
    "gn:population":0,
    "gn:timezone":"Africa/Casablanca",
    "iso:country":"MA",
    "wof:name":"Almou Abouri",
    "wof:placetype":"locality"
},
  "geometry": {"coordinates":[-4.9759,33.56382],"type":"Point"}
}