{
  "type": "Feature",
  "properties": {
    "gn:admin1_code":"3.0",
    "gn:asciiname":"Srijat",
    "gn:country_code":"MA",
    "gn:dem":346,
    "gn:feature_class":"P",
    "gn:feature_code":"PPL",
    "gn:name":"Srijat",
    "gn:population":0,
    "gn:timezone":"Africa/Casablanca",
    "iso:country":"MA",
    "wof:name":"Srijat",
    "wof:placetype":"locality"
},
  "geometry": {"coordinates":[-4.78292,34.44405],"type":"Point"}
}