{
  "type": "Feature",
  "properties": {
    "gn:admin1_code":"5.0",
    "gn:asciiname":"Iskawn",
    "gn:country_code":"MA",
    "gn:dem":1648,
    "gn:feature_class":"P",
    "gn:feature_code":"PPL",
    "gn:name":"Iskawn",
    "gn:population":0,
    "gn:timezone":"Africa/Casablanca",
    "iso:country":"MA",
    "wof:name":"Iskawn",
    "wof:placetype":"locality"
},
  "geometry": {"coordinates":[-6.66285,31.66245],"type":"Point"}
}