{
  "type": "Feature",
  "properties": {
    "gn:admin1_code":"4.0",
    "gn:asciiname":"Douar Oulad Leila",
    "gn:country_code":"MA",
    "gn:dem":365,
    "gn:feature_class":"P",
    "gn:feature_code":"PPL",
    "gn:name":"Douar Oulad Leila",
    "gn:population":0,
    "gn:timezone":"Africa/Casablanca",
    "iso:country":"MA",
    "wof:name":"Douar Oulad Leila",
    "wof:placetype":"locality"
},
  "geometry": {"coordinates":[-6.54975,33.63126],"type":"Point"}
}