{
  "type": "Feature",
  "properties": {
    "gn:admin1_code":"09",
    "gn:asciiname":"Ait As Sine",
    "gn:country_code":"MA",
    "gn:dem":1677,
    "gn:feature_class":"P",
    "gn:feature_code":"PPL",
    "gn:name":"A\u00eft As Sine",
    "gn:population":0,
    "gn:timezone":"Africa/Casablanca",
    "iso:country":"MA",
    "name:und_x_variant":[
        "A\u00eft As Sine",
        "A\u00eft Sine"
    ],
    "wof:name":"Ait As Sine",
    "wof:placetype":"locality"
},
  "geometry": {"coordinates":[-7.57368,30.57365],"type":"Point"}
}