{
  "type": "Feature",
  "properties": {
    "gn:admin1_code":"4.0",
    "gn:asciiname":"Hsinat",
    "gn:country_code":"MA",
    "gn:dem":16,
    "gn:feature_class":"P",
    "gn:feature_code":"PPL",
    "gn:name":"Hsinat",
    "gn:population":0,
    "gn:timezone":"Africa/Casablanca",
    "iso:country":"MA",
    "wof:name":"Hsinat",
    "wof:placetype":"locality"
},
  "geometry": {"coordinates":[-6.02634,34.60171],"type":"Point"}
}