{
  "type": "Feature",
  "properties": {
    "gn:admin1_code":"7.0",
    "gn:asciiname":"Tagnit Niidane",
    "gn:country_code":"MA",
    "gn:dem":1371,
    "gn:feature_class":"P",
    "gn:feature_code":"PPL",
    "gn:name":"Tagnit Niidane",
    "gn:population":0,
    "gn:timezone":"Africa/Casablanca",
    "iso:country":"MA",
    "wof:name":"Tagnit Niidane",
    "wof:placetype":"locality"
},
  "geometry": {"coordinates":[-7.36006,31.53757],"type":"Point"}
}