{
  "type": "Feature",
  "properties": {
    "iso:country":"MA",
    "name:ara_x_preferred":[
        "\u0627\u0644\u062f\u0627\u0631 \u0627\u0644\u0628\u064a\u0636\u0627\u0621"
    ],
    "name:eng_x_preferred":[
        "Casablanca"
    ],
    "qs:gn_pop":0,
    "qs:name":"\u0627\u0644\u062f\u0627\u0631 \u0627\u0644\u0628\u064a\u0636\u0627\u0621",
    "qs:name_adm0":"\u0627\u0644\u0645\u063a\u0631\u0628",
    "qs:name_adm1":"\u0627\u0644\u062f\u0627\u0631 \u0627\u0644\u0628\u064a\u0636\u0627\u0621 \u0627\u0644\u0643\u0628\u0631\u0649",
    "qs:photos":3316,
    "qs:photos_1k":672,
    "qs:photos_9k":45,
    "qs:photos_9r":16,
    "qs:photos_all":10206,
    "qs:photos_sr":20,
    "qs:placetype":"Town",
    "qs:pop_sr":"0",
    "qs:woe_adm0":23424893,
    "wof:name":"Casablanca",
    "wof:placetype":"locality"
},
  "geometry": {"coordinates":[-7.621765,33.600108],"type":"Point"}
}