{
  "type": "Feature",
  "properties": {
    "gn:admin1_code":"7.0",
    "gn:asciiname":"Darb",
    "gn:country_code":"MA",
    "gn:dem":1462,
    "gn:feature_class":"P",
    "gn:feature_code":"PPL",
    "gn:name":"Darb",
    "gn:population":0,
    "gn:timezone":"Africa/Casablanca",
    "iso:country":"MA",
    "name:ara_x_preferred":[
        "\u062f\u0631\u0628"
    ],
    "name:fas_x_preferred":[
        "\u062f\u0631\u0628"
    ],
    "wof:name":"Darb",
    "wof:placetype":"locality"
},
  "geometry": {"coordinates":[-7.49254,31.37228],"type":"Point"}
}