{
  "type": "Feature",
  "properties": {
    "gn:admin1_code":"7.0",
    "gn:asciiname":"Sidi bou Atmane",
    "gn:country_code":"MA",
    "gn:dem":1284,
    "gn:feature_class":"P",
    "gn:feature_code":"PPL",
    "gn:name":"Sidi bou \u00c2tmane",
    "gn:population":0,
    "gn:timezone":"Africa/Casablanca",
    "iso:country":"MA",
    "wof:name":"Sidi bou Atmane",
    "wof:placetype":"locality"
},
  "geometry": {"coordinates":[-9.05261,31.00964],"type":"Point"}
}