{
  "type": "Feature",
  "properties": {
    "gn:admin1_code":"7.0",
    "gn:asciiname":"Douar Omar Lekehal",
    "gn:country_code":"MA",
    "gn:dem":235,
    "gn:feature_class":"P",
    "gn:feature_code":"PPL",
    "gn:name":"Douar Omar Lekehal",
    "gn:population":0,
    "gn:timezone":"Africa/Casablanca",
    "iso:country":"MA",
    "wof:name":"Douar Omar Lekehal",
    "wof:placetype":"locality"
},
  "geometry": {"coordinates":[-8.68414,32.29315],"type":"Point"}
}