{
  "type": "Feature",
  "properties": {
    "gn:admin1_code":"05",
    "gn:asciiname":"Oulad er Rahi",
    "gn:country_code":"MA",
    "gn:dem":561,
    "gn:feature_class":"P",
    "gn:feature_code":"PPL",
    "gn:name":"Oulad er Rahi",
    "gn:population":0,
    "gn:timezone":"Africa/Casablanca",
    "iso:country":"MA",
    "name:und_x_variant":[
        "Lbat\u00e8n Ben Arar",
        "Lbatene Ben Arar",
        "Oulad er Rahi"
    ],
    "wof:name":"Oulad er Rahi",
    "wof:placetype":"locality"
},
  "geometry": {"coordinates":[-6.91257,32.09184],"type":"Point"}
}