{
  "type": "Feature",
  "properties": {
    "gn:admin1_code":"6.0",
    "gn:asciiname":"Douar Lefiadla",
    "gn:country_code":"MA",
    "gn:dem":551,
    "gn:feature_class":"P",
    "gn:feature_code":"PPL",
    "gn:name":"Douar Lefiadla",
    "gn:population":0,
    "gn:timezone":"Africa/Casablanca",
    "iso:country":"MA",
    "wof:name":"Douar Lefiadla",
    "wof:placetype":"locality"
},
  "geometry": {"coordinates":[-7.43408,32.65569],"type":"Point"}
}