{
  "type": "Feature",
  "properties": {
    "iso:country":"MA",
    "qs:gn_pop":0,
    "qs:name":"\u0628\u0648\u0645\u0627\u0644\u0646 \u062f\u0627\u062f\u0633",
    "qs:name_adm0":"\u0627\u0644\u0645\u063a\u0631\u0628",
    "qs:name_adm1":"\u0633\u0648\u0633 \u0640 \u0645\u0627\u0633\u0629 \u0640 \u062f\u0631\u0639\u0629",
    "qs:photos":477,
    "qs:photos_1k":97,
    "qs:photos_9k":2,
    "qs:photos_9r":5,
    "qs:photos_all":477,
    "qs:photos_sr":7,
    "qs:placetype":"Town",
    "qs:pop_sr":"0",
    "qs:woe_adm0":23424893,
    "wof:name":"\u0628\u0648\u0645\u0627\u0644\u0646 \u062f\u0627\u062f\u0633",
    "wof:placetype":"locality"
},
  "geometry": {"coordinates":[-5.991926,31.376502],"type":"Point"}
}