{
  "type": "Feature",
  "properties": {
    "gn:admin1_code":"6.0",
    "gn:asciiname":"Oulad Bou Talgan",
    "gn:country_code":"MA",
    "gn:dem":250,
    "gn:feature_class":"P",
    "gn:feature_code":"PPL",
    "gn:name":"Oulad Bou Talgan",
    "gn:population":0,
    "gn:timezone":"Africa/Casablanca",
    "iso:country":"MA",
    "wof:name":"Oulad Bou Talgan",
    "wof:placetype":"locality"
},
  "geometry": {"coordinates":[-7.48933,33.17349],"type":"Point"}
}