{
  "type": "Feature",
  "properties": {
    "gn:admin1_code":"9.0",
    "gn:asciiname":"Ait Lahmayd",
    "gn:country_code":"MA",
    "gn:dem":73,
    "gn:feature_class":"P",
    "gn:feature_code":"PPL",
    "gn:name":"Ait Lahmayd",
    "gn:population":0,
    "gn:timezone":"Africa/Casablanca",
    "iso:country":"MA",
    "wof:name":"Ait Lahmayd",
    "wof:placetype":"locality"
},
  "geometry": {"coordinates":[-9.54465,30.10934],"type":"Point"}
}