{
  "type": "Feature",
  "properties": {
    "gn:admin1_code":"6.0",
    "gn:asciiname":"Lemnasra",
    "gn:country_code":"MA",
    "gn:dem":196,
    "gn:feature_class":"P",
    "gn:feature_code":"PPL",
    "gn:name":"Lemnasra",
    "gn:population":0,
    "gn:timezone":"Africa/Casablanca",
    "iso:country":"MA",
    "wof:name":"Lemnasra",
    "wof:placetype":"locality"
},
  "geometry": {"coordinates":[-8.63028,32.48632],"type":"Point"}
}