{
  "type": "Feature",
  "properties": {
    "gn:admin1_code":"07",
    "gn:asciiname":"Oulad Assila",
    "gn:country_code":"MA",
    "gn:dem":69,
    "gn:feature_class":"P",
    "gn:feature_code":"PPL",
    "gn:name":"Oulad Assila",
    "gn:population":0,
    "gn:timezone":"Africa/Casablanca",
    "iso:country":"MA",
    "name:und_x_variant":[
        "Douar Oulad Assila",
        "Oulad Assila"
    ],
    "wof:name":"Oulad Assila",
    "wof:placetype":"locality"
},
  "geometry": {"coordinates":[-9.19718,32.45991],"type":"Point"}
}