{
  "type": "Feature",
  "properties": {
    "gn:admin1_code":"09",
    "gn:asciiname":"El Mers Oulad Amer",
    "gn:country_code":"MA",
    "gn:dem":116,
    "gn:feature_class":"P",
    "gn:feature_code":"PPL",
    "gn:name":"El Mers Oulad Amer",
    "gn:population":0,
    "gn:timezone":"Africa/Casablanca",
    "iso:country":"MA",
    "name:und_x_variant":[
        "El Mers"
    ],
    "wof:name":"El Mers Oulad Amer",
    "wof:placetype":"locality"
},
  "geometry": {"coordinates":[-9.7143,29.81618],"type":"Point"}
}