{
  "type": "Feature",
  "properties": {
    "gn:admin1_code":"7.0",
    "gn:asciiname":"Ilzougarene",
    "gn:country_code":"MA",
    "gn:dem":692,
    "gn:feature_class":"P",
    "gn:feature_code":"PPL",
    "gn:name":"Ilzougarene",
    "gn:population":0,
    "gn:timezone":"Africa/Casablanca",
    "iso:country":"MA",
    "wof:name":"Ilzougarene",
    "wof:placetype":"locality"
},
  "geometry": {"coordinates":[-9.29949,31.32717],"type":"Point"}
}