{
  "type": "Feature",
  "properties": {
    "gn:admin1_code":"1.0",
    "gn:asciiname":"Hbaq",
    "gn:country_code":"MA",
    "gn:dem":439,
    "gn:feature_class":"P",
    "gn:feature_code":"PPL",
    "gn:name":"Hbaq",
    "gn:population":0,
    "gn:timezone":"Africa/Casablanca",
    "iso:country":"MA",
    "wof:name":"Hbaq",
    "wof:placetype":"locality"
},
  "geometry": {"coordinates":[-5.44526,35.41308],"type":"Point"}
}