{
  "type": "Feature",
  "properties": {
    "gn:admin1_code":"01",
    "gn:asciiname":"Ain Dourij",
    "gn:country_code":"MA",
    "gn:dem":146,
    "gn:feature_class":"P",
    "gn:feature_code":"PPL",
    "gn:name":"Ain Dourij",
    "gn:population":0,
    "gn:timezone":"Africa/Casablanca",
    "iso:country":"MA",
    "name:ara_x_preferred":[
        "\u0639\u064a\u0646 \u062f\u0631\u064a\u062c"
    ],
    "name:azb_x_preferred":[
        "\u0639\u06cc\u0646 \u062f\u0631\u06cc\u062c"
    ],
    "name:ceb_x_preferred":[
        "A\u00efn Dorij"
    ],
    "name:fas_x_preferred":[
        "\u0639\u06cc\u0646 \u062f\u0631\u06cc\u062c"
    ],
    "name:fra_x_preferred":[
        "A\u00efn Dorij"
    ],
    "name:pol_x_preferred":[
        "Ajn ad-Durajd\u017c"
    ],
    "name:swe_x_preferred":[
        "A\u00efn Dorij"
    ],
    "name:und_x_variant":[
        "A\u00efn Dourij",
        "Ain Dourij"
    ],
    "wof:name":"Ain Dourij",
    "wof:placetype":"locality"
},
  "geometry": {"coordinates":[-5.28733,34.61427],"type":"Point"}
}