{
  "type": "Feature",
  "properties": {
    "gn:admin1_code":"01",
    "gn:asciiname":"Ain Dourij",
    "gn:country_code":"MA",
    "gn:dem":146,
    "gn:feature_class":"P",
    "gn:feature_code":"PPL",
    "gn:name":"Ain Dourij",
    "gn:population":0,
    "gn:timezone":"Africa/Casablanca",
    "iso:country":"MA",
    "name:und_x_variant":[
        "A\u00efn Dourij",
        "A\u00efn Dorij",
        "Ain Dourij"
    ],
    "wof:name":"Ain Dourij",
    "wof:placetype":"locality"
},
  "geometry": {"coordinates":[-5.28733,34.61427],"type":"Point"}
}