{
  "type": "Feature",
  "properties": {
    "gn:admin1_code":"1.0",
    "gn:asciiname":"Lhouma Louastiya",
    "gn:country_code":"MA",
    "gn:dem":320,
    "gn:feature_class":"P",
    "gn:feature_code":"PPL",
    "gn:name":"Lhouma Louastiya",
    "gn:population":0,
    "gn:timezone":"Africa/Casablanca",
    "iso:country":"MA",
    "wof:name":"Lhouma Louastiya",
    "wof:placetype":"locality"
},
  "geometry": {"coordinates":[-5.43886,35.59042],"type":"Point"}
}