{
  "type": "Feature",
  "properties": {
    "gn:admin1_code":"7.0",
    "gn:asciiname":"Dar El Haj Ahmed Ettati",
    "gn:country_code":"MA",
    "gn:dem":359,
    "gn:feature_class":"P",
    "gn:feature_code":"PPL",
    "gn:name":"Dar El Haj Ahmed Ettati",
    "gn:population":0,
    "gn:timezone":"Africa/Casablanca",
    "iso:country":"MA",
    "wof:name":"Dar El Haj Ahmed Ettati",
    "wof:placetype":"locality"
},
  "geometry": {"coordinates":[-8.45032,31.62536],"type":"Point"}
}