{
  "type": "Feature",
  "properties": {
    "gn:admin1_code":"2.0",
    "gn:asciiname":"Iqourabene",
    "gn:country_code":"MA",
    "gn:dem":409,
    "gn:feature_class":"P",
    "gn:feature_code":"PPL",
    "gn:name":"Iqourabene",
    "gn:population":0,
    "gn:timezone":"Africa/Casablanca",
    "iso:country":"MA",
    "wof:name":"Iqourabene",
    "wof:placetype":"locality"
},
  "geometry": {"coordinates":[-3.07103,35.20755],"type":"Point"}
}