{
  "type": "Feature",
  "properties": {
    "gn:admin1_code":"07",
    "gn:asciiname":"Douar Filala",
    "gn:country_code":"MA",
    "gn:dem":374,
    "gn:feature_class":"P",
    "gn:feature_code":"PPL",
    "gn:name":"Douar Filala",
    "gn:population":0,
    "gn:timezone":"Africa/Casablanca",
    "iso:country":"MA",
    "name:und_x_variant":[
        "Filala",
        "Douar Harilli",
        "Douar Filala"
    ],
    "wof:name":"Douar Filala",
    "wof:placetype":"locality"
},
  "geometry": {"coordinates":[-8.10436,31.70786],"type":"Point"}
}