{
  "type": "Feature",
  "properties": {
    "gn:admin1_code":"09",
    "gn:asciiname":"Tahouaouat",
    "gn:country_code":"MA",
    "gn:dem":1262,
    "gn:feature_class":"P",
    "gn:feature_code":"PPL",
    "gn:name":"Tahouaouat",
    "gn:population":0,
    "gn:timezone":"Africa/Casablanca",
    "iso:country":"MA",
    "name:und_x_variant":[
        "Tahawawat",
        "Tahouaouat"
    ],
    "wof:name":"Tahouaouat",
    "wof:placetype":"locality"
},
  "geometry": {"coordinates":[-9.0657,29.45193],"type":"Point"}
}