{
  "type": "Feature",
  "properties": {
    "gn:admin1_code":"08",
    "gn:asciiname":"Mougueur",
    "gn:country_code":"MA",
    "gn:dem":1486,
    "gn:feature_class":"P",
    "gn:feature_code":"PPL",
    "gn:name":"Mougueur",
    "gn:population":0,
    "gn:timezone":"Africa/Casablanca",
    "iso:country":"MA",
    "wof:name":"Mougueur",
    "wof:placetype":"locality"
},
  "geometry": {"coordinates":[-4.16366,32.40885],"type":"Point"}
}