{
  "type": "Feature",
  "properties": {
    "gn:admin1_code":"3.0",
    "gn:asciiname":"Douar Jouichat",
    "gn:country_code":"MA",
    "gn:dem":409,
    "gn:feature_class":"P",
    "gn:feature_code":"PPL",
    "gn:name":"Douar Jouichat",
    "gn:population":0,
    "gn:timezone":"Africa/Casablanca",
    "iso:country":"MA",
    "wof:name":"Douar Jouichat",
    "wof:placetype":"locality"
},
  "geometry": {"coordinates":[-5.314,34.22955],"type":"Point"}
}