{
  "type": "Feature",
  "properties": {
    "gn:admin1_code":"2.0",
    "gn:asciiname":"Douar Oulad Ali Ben Yahya",
    "gn:country_code":"MA",
    "gn:dem":752,
    "gn:feature_class":"P",
    "gn:feature_code":"PPL",
    "gn:name":"Douar Oulad Ali Ben Yahya",
    "gn:population":0,
    "gn:timezone":"Africa/Casablanca",
    "iso:country":"MA",
    "wof:name":"Douar Oulad Ali Ben Yahya",
    "wof:placetype":"locality"
},
  "geometry": {"coordinates":[-2.07427,34.53337],"type":"Point"}
}