{
  "type": "Feature",
  "properties": {
    "gn:admin1_code":"9.0",
    "gn:asciiname":"Tigemmi N'mon Ou Aho",
    "gn:country_code":"MA",
    "gn:dem":592,
    "gn:feature_class":"P",
    "gn:feature_code":"PPL",
    "gn:name":"Tigemmi N\u2019mon Ou Aho",
    "gn:population":0,
    "gn:timezone":"Africa/Casablanca",
    "iso:country":"MA",
    "wof:name":"Tigemmi N'mon Ou Aho",
    "wof:placetype":"locality"
},
  "geometry": {"coordinates":[-9.04202,30.15942],"type":"Point"}
}