{
  "type": "Feature",
  "properties": {
    "gn:admin1_code":"09",
    "gn:asciiname":"Dou ou Tsoulilt",
    "gn:country_code":"MA",
    "gn:dem":798,
    "gn:feature_class":"P",
    "gn:feature_code":"PPL",
    "gn:name":"Dou ou Tsoulilt",
    "gn:population":0,
    "gn:timezone":"Africa/Casablanca",
    "iso:country":"MA",
    "name:und_x_variant":[
        "Bou Ou Tsoulilt"
    ],
    "wof:name":"Dou ou Tsoulilt",
    "wof:placetype":"locality"
},
  "geometry": {"coordinates":[-9.3961,30.60044000000001],"type":"Point"}
}