{
  "type": "Feature",
  "properties": {
    "gn:admin1_code":"10",
    "gn:asciiname":"Sidi Jbara",
    "gn:country_code":"MA",
    "gn:dem":118,
    "gn:feature_class":"P",
    "gn:feature_code":"PPL",
    "gn:name":"Sidi Jbara",
    "gn:population":0,
    "gn:timezone":"Africa/Casablanca",
    "iso:country":"MA",
    "name:und_x_variant":[
        "Sidi Abel Sbaar",
        "Sidi Abd es Sbaar",
        "Sidi Jbara"
    ],
    "wof:name":"Sidi Jbara",
    "wof:placetype":"locality"
},
  "geometry": {"coordinates":[-10.04928,29.52698],"type":"Point"}
}