{
  "type": "Feature",
  "properties": {
    "gn:admin1_code":"7.0",
    "gn:asciiname":"Tawkart",
    "gn:country_code":"MA",
    "gn:dem":758,
    "gn:feature_class":"P",
    "gn:feature_code":"PPL",
    "gn:name":"Tawkart",
    "gn:population":0,
    "gn:timezone":"Africa/Casablanca",
    "iso:country":"MA",
    "wof:name":"Tawkart",
    "wof:placetype":"locality"
},
  "geometry": {"coordinates":[-7.85755,31.40322],"type":"Point"}
}