{
  "type": "Feature",
  "properties": {
    "gn:admin1_code":"7.0",
    "gn:asciiname":"Douar Nwaji",
    "gn:country_code":"MA",
    "gn:dem":362,
    "gn:feature_class":"P",
    "gn:feature_code":"PPL",
    "gn:name":"Douar Nwaji",
    "gn:population":0,
    "gn:timezone":"Africa/Casablanca",
    "iso:country":"MA",
    "wof:name":"Douar Nwaji",
    "wof:placetype":"locality"
},
  "geometry": {"coordinates":[-8.24098,31.70169000000001],"type":"Point"}
}