{
  "type": "Feature",
  "properties": {
    "gn:admin1_code":"7.0",
    "gn:asciiname":"Dar Salem Laaribi",
    "gn:country_code":"MA",
    "gn:dem":446,
    "gn:feature_class":"P",
    "gn:feature_code":"PPL",
    "gn:name":"Dar Salem Laaribi",
    "gn:population":0,
    "gn:timezone":"Africa/Casablanca",
    "iso:country":"MA",
    "wof:name":"Dar Salem Laaribi",
    "wof:placetype":"locality"
},
  "geometry": {"coordinates":[-7.95427,31.9887],"type":"Point"}
}