{
  "type": "Feature",
  "properties": {
    "gn:admin1_code":"9.0",
    "gn:asciiname":"Tafouhamt",
    "gn:country_code":"MA",
    "gn:dem":1193,
    "gn:feature_class":"P",
    "gn:feature_code":"PPL",
    "gn:name":"Tafouhamt",
    "gn:population":0,
    "gn:timezone":"Africa/Casablanca",
    "iso:country":"MA",
    "wof:name":"Tafouhamt",
    "wof:placetype":"locality"
},
  "geometry": {"coordinates":[-9.15053,29.86032],"type":"Point"}
}