{
  "type": "Feature",
  "properties": {
    "gn:admin1_code":"9.0",
    "gn:asciiname":"Taboucalht",
    "gn:country_code":"MA",
    "gn:dem":566,
    "gn:feature_class":"P",
    "gn:feature_code":"PPL",
    "gn:name":"Taboucalht",
    "gn:population":0,
    "gn:timezone":"Africa/Casablanca",
    "iso:country":"MA",
    "wof:name":"Taboucalht",
    "wof:placetype":"locality"
},
  "geometry": {"coordinates":[-9.34659,29.59298],"type":"Point"}
}