{
  "type": "Feature",
  "properties": {
    "gn:admin1_code":"7.0",
    "gn:asciiname":"Abderrrahmane Douar Zaouiat Sidi",
    "gn:country_code":"MA",
    "gn:dem":444,
    "gn:feature_class":"P",
    "gn:feature_code":"PPL",
    "gn:name":"Abderrrahmane Douar Zaouiat Sidi",
    "gn:population":0,
    "gn:timezone":"Africa/Casablanca",
    "iso:country":"MA",
    "wof:name":"Abderrrahmane Douar Zaouiat Sidi",
    "wof:placetype":"locality"
},
  "geometry": {"coordinates":[-9.62053,31.07339],"type":"Point"}
}