{
  "type": "Feature",
  "properties": {
    "gn:admin1_code":"7.0",
    "gn:asciiname":"Oulad Ben Cheikh",
    "gn:country_code":"MA",
    "gn:dem":85,
    "gn:feature_class":"P",
    "gn:feature_code":"PPL",
    "gn:name":"Oulad Ben Cheikh",
    "gn:population":0,
    "gn:timezone":"Africa/Casablanca",
    "iso:country":"MA",
    "wof:name":"Oulad Ben Cheikh",
    "wof:placetype":"locality"
},
  "geometry": {"coordinates":[-9.17712,32.55512],"type":"Point"}
}