{
  "type": "Feature",
  "properties": {
    "gn:admin1_code":"7.0",
    "gn:asciiname":"'Azib Wawamghilt",
    "gn:country_code":"MA",
    "gn:dem":2124,
    "gn:feature_class":"P",
    "gn:feature_code":"PPL",
    "gn:name":"\u2019Azib Wawamghilt",
    "gn:population":0,
    "gn:timezone":"Africa/Casablanca",
    "iso:country":"MA",
    "wof:name":"'Azib Wawamghilt",
    "wof:placetype":"locality"
},
  "geometry": {"coordinates":[-7.45294,31.44291],"type":"Point"}
}