{
  "type": "Feature",
  "properties": {
    "gn:admin1_code":"03",
    "gn:asciiname":"Sarij",
    "gn:country_code":"MA",
    "gn:dem":1451,
    "gn:feature_class":"P",
    "gn:feature_code":"PPL",
    "gn:name":"Sarij",
    "gn:population":0,
    "gn:timezone":"Africa/Casablanca",
    "iso:country":"MA",
    "wof:name":"Sarij",
    "wof:placetype":"locality"
},
  "geometry": {"coordinates":[-4.37019,33.48587],"type":"Point"}
}