{
  "type": "Feature",
  "properties": {
    "gn:admin1_code":"7.0",
    "gn:asciiname":"'Azib Tekna",
    "gn:country_code":"MA",
    "gn:dem":538,
    "gn:feature_class":"P",
    "gn:feature_code":"PPL",
    "gn:name":"\u2019Azib Tekna",
    "gn:population":0,
    "gn:timezone":"Africa/Casablanca",
    "iso:country":"MA",
    "wof:name":"'Azib Tekna",
    "wof:placetype":"locality"
},
  "geometry": {"coordinates":[-8.4029,31.45381],"type":"Point"}
}