{
  "type": "Feature",
  "properties": {
    "gn:admin1_code":"6.0",
    "gn:asciiname":"Douar Ballouta",
    "gn:country_code":"MA",
    "gn:dem":142,
    "gn:feature_class":"P",
    "gn:feature_code":"PPL",
    "gn:name":"Douar Ballouta",
    "gn:population":0,
    "gn:timezone":"Africa/Casablanca",
    "iso:country":"MA",
    "wof:name":"Douar Ballouta",
    "wof:placetype":"locality"
},
  "geometry": {"coordinates":[-7.32774,33.60565],"type":"Point"}
}