{
  "type": "Feature",
  "properties": {
    "gn:admin1_code":"7.0",
    "gn:asciiname":"Labrourat",
    "gn:country_code":"MA",
    "gn:dem":263,
    "gn:feature_class":"P",
    "gn:feature_code":"PPL",
    "gn:name":"Labrourat",
    "gn:population":0,
    "gn:timezone":"Africa/Casablanca",
    "iso:country":"MA",
    "wof:name":"Labrourat",
    "wof:placetype":"locality"
},
  "geometry": {"coordinates":[-9.01546,31.87582],"type":"Point"}
}