{
  "type": "Feature",
  "properties": {
    "gn:admin1_code":"01",
    "gn:asciiname":"Douar Azagnar Safli",
    "gn:country_code":"MA",
    "gn:dem":517,
    "gn:feature_class":"P",
    "gn:feature_code":"PPL",
    "gn:name":"Douar Azagnar Safli",
    "gn:population":0,
    "gn:timezone":"Africa/Casablanca",
    "iso:country":"MA",
    "name:und_x_variant":[
        "Az Ghar",
        "Asgar",
        "Douar Azagnar Safli"
    ],
    "wof:name":"Douar Azagnar Safli",
    "wof:placetype":"locality"
},
  "geometry": {"coordinates":[-5.02465,35.3218],"type":"Point"}
}