{
  "type": "Feature",
  "properties": {
    "gn:admin1_code":"09",
    "gn:asciiname":"Tiliwa",
    "gn:country_code":"MA",
    "gn:dem":959,
    "gn:feature_class":"P",
    "gn:feature_code":"PPL",
    "gn:name":"Tiliwa",
    "gn:population":0,
    "gn:timezone":"Africa/Casablanca",
    "iso:country":"MA",
    "name:und_x_variant":[
        "Tilioua"
    ],
    "wof:name":"Tiliwa",
    "wof:placetype":"locality"
},
  "geometry": {"coordinates":[-8.82241,30.2335],"type":"Point"}
}