{
  "type": "Feature",
  "properties": {
    "gn:admin1_code":"07",
    "gn:asciiname":"Ighris",
    "gn:country_code":"MA",
    "gn:dem":992,
    "gn:feature_class":"P",
    "gn:feature_code":"PPL",
    "gn:name":"Ighris",
    "gn:population":0,
    "gn:timezone":"Africa/Casablanca",
    "iso:country":"MA",
    "name:und_x_variant":[
        "Irhris"
    ],
    "wof:name":"Ighris",
    "wof:placetype":"locality"
},
  "geometry": {"coordinates":[-7.48421,31.5379],"type":"Point"}
}