{
  "type": "Feature",
  "properties": {
    "gn:admin1_code":"7.0",
    "gn:asciiname":"Twahra",
    "gn:country_code":"MA",
    "gn:dem":661,
    "gn:feature_class":"P",
    "gn:feature_code":"PPL",
    "gn:name":"Twahra",
    "gn:population":0,
    "gn:timezone":"Africa/Casablanca",
    "iso:country":"MA",
    "wof:name":"Twahra",
    "wof:placetype":"locality"
},
  "geometry": {"coordinates":[-7.25024,31.79901],"type":"Point"}
}