{
  "type": "Feature",
  "properties": {
    "gn:admin1_code":"9.0",
    "gn:asciiname":"Timsala",
    "gn:country_code":"MA",
    "gn:dem":1286,
    "gn:feature_class":"P",
    "gn:feature_code":"PPL",
    "gn:name":"Timsala",
    "gn:population":0,
    "gn:timezone":"Africa/Casablanca",
    "iso:country":"MA",
    "wof:name":"Timsala",
    "wof:placetype":"locality"
},
  "geometry": {"coordinates":[-9.45358,30.68362],"type":"Point"}
}