{
  "type": "Feature",
  "properties": {
    "gn:admin1_code":"09",
    "gn:asciiname":"Tamdaloucht",
    "gn:country_code":"MA",
    "gn:dem":750,
    "gn:feature_class":"P",
    "gn:feature_code":"PPL",
    "gn:name":"Tamdaloucht",
    "gn:population":0,
    "gn:timezone":"Africa/Casablanca",
    "iso:country":"MA",
    "name:und_x_variant":[
        "Taourirt",
        "Tamdloucht",
        "Tamdaloucht"
    ],
    "wof:name":"Tamdaloucht",
    "wof:placetype":"locality"
},
  "geometry": {"coordinates":[-9.0998,29.71125],"type":"Point"}
}