{
  "type": "Feature",
  "properties": {
    "gn:country":"MA",
    "gn:fcode":"ADM3",
    "gn:pop":12619,
    "iso:country":"MA",
    "name:ara_x_preferred":[
        "\u0641\u0631\u0643\u0644\u0629 \u0627\u0644\u0639\u0644\u064a\u0627"
    ],
    "name:fra_x_preferred":[
        "Ferkla Es-Soufla"
    ],
    "name:fra_x_variant":[
        "Ferkla Es-Soufla (CR)",
        "Ferkla Es-Soufla (Commune Rurale)"
    ],
    "qs:name":"Ferkla Es-Soufla",
    "qs:photos_9r":0,
    "qs:photos_sr":0,
    "qs:pop_sr":"6",
    "wof:name":"Ferkla Es-Soufla",
    "wof:placetype":"localadmin",
    "wof:population":12619
},
  "geometry": {"coordinates":[-5.03594,31.58738],"type":"Point"}
}