{
  "type": "Feature",
  "properties": {
    "gn:admin1_code":"1.0",
    "gn:asciiname":"Tougganat",
    "gn:country_code":"MA",
    "gn:dem":441,
    "gn:feature_class":"P",
    "gn:feature_code":"PPL",
    "gn:name":"Tougganat",
    "gn:population":0,
    "gn:timezone":"Africa/Casablanca",
    "iso:country":"MA",
    "wof:name":"Tougganat",
    "wof:placetype":"locality"
},
  "geometry": {"coordinates":[-5.17677,35.40971],"type":"Point"}
}