{
  "type": "Feature",
  "properties": {
    "gn:admin1_code":"3.0",
    "gn:asciiname":"Dar Rahou ou Mmma",
    "gn:country_code":"MA",
    "gn:dem":649,
    "gn:feature_class":"P",
    "gn:feature_code":"PPL",
    "gn:name":"Dar Rahou ou Mmma",
    "gn:population":0,
    "gn:timezone":"Africa/Casablanca",
    "iso:country":"MA",
    "wof:name":"Dar Rahou ou Mmma",
    "wof:placetype":"locality"
},
  "geometry": {"coordinates":[-5.31274,33.8641],"type":"Point"}
}