{
  "type": "Feature",
  "properties": {
    "gn:admin1_code":"9.0",
    "gn:asciiname":"Izeroualeo",
    "gn:country_code":"MA",
    "gn:dem":633,
    "gn:feature_class":"P",
    "gn:feature_code":"PPL",
    "gn:name":"Izeroualeo",
    "gn:population":0,
    "gn:timezone":"Africa/Casablanca",
    "iso:country":"MA",
    "wof:name":"Izeroualeo",
    "wof:placetype":"locality"
},
  "geometry": {"coordinates":[-9.03823,30.67539],"type":"Point"}
}