{
  "type": "Feature",
  "properties": {
    "gn:admin1_code":"9.0",
    "gn:asciiname":"Amalou",
    "gn:country_code":"MA",
    "gn:dem":1180,
    "gn:feature_class":"P",
    "gn:feature_code":"PPL",
    "gn:name":"Amalou",
    "gn:population":0,
    "gn:timezone":"Africa/Casablanca",
    "iso:country":"MA",
    "name:ceb_x_preferred":[
        "Amalou"
    ],
    "name:fra_x_preferred":[
        "Amalou"
    ],
    "name:swe_x_preferred":[
        "Amalou"
    ],
    "wof:name":"Amalou",
    "wof:placetype":"locality"
},
  "geometry": {"coordinates":[-8.58016,30.25932],"type":"Point"}
}