{
  "type": "Feature",
  "properties": {
    "gn:admin1_code":"02",
    "gn:asciiname":"Amharrar",
    "gn:country_code":"MA",
    "gn:dem":1487,
    "gn:feature_class":"P",
    "gn:feature_code":"PPL",
    "gn:name":"Amharrar",
    "gn:population":0,
    "gn:timezone":"Africa/Casablanca",
    "iso:country":"MA",
    "wof:name":"Amharrar",
    "wof:placetype":"locality"
},
  "geometry": {"coordinates":[-3.75617,33.72216],"type":"Point"}
}