{
  "type": "Feature",
  "properties": {
    "gn:admin1_code":"6.0",
    "gn:asciiname":"Douar Mohamed El Khatir",
    "gn:country_code":"MA",
    "gn:dem":475,
    "gn:feature_class":"P",
    "gn:feature_code":"PPL",
    "gn:name":"Douar Mohamed El Khatir",
    "gn:population":0,
    "gn:timezone":"Africa/Casablanca",
    "iso:country":"MA",
    "wof:name":"Douar Mohamed El Khatir",
    "wof:placetype":"locality"
},
  "geometry": {"coordinates":[-7.14288,33.21066],"type":"Point"}
}