{
  "type": "Feature",
  "properties": {
    "gn:admin1_code":"4.0",
    "gn:asciiname":"Dar Riyahi",
    "gn:country_code":"MA",
    "gn:dem":25,
    "gn:feature_class":"P",
    "gn:feature_code":"PPL",
    "gn:name":"Dar Riyahi",
    "gn:population":0,
    "gn:timezone":"Africa/Casablanca",
    "iso:country":"MA",
    "wof:name":"Dar Riyahi",
    "wof:placetype":"locality"
},
  "geometry": {"coordinates":[-6.20389,34.76013],"type":"Point"}
}