{
  "type": "Feature",
  "properties": {
    "gn:admin1_code":"7.0",
    "gn:asciiname":"Dar El Haj Abid",
    "gn:country_code":"MA",
    "gn:dem":171,
    "gn:feature_class":"P",
    "gn:feature_code":"PPL",
    "gn:name":"Dar El Haj Abid",
    "gn:population":0,
    "gn:timezone":"Africa/Casablanca",
    "iso:country":"MA",
    "wof:name":"Dar El Haj Abid",
    "wof:placetype":"locality"
},
  "geometry": {"coordinates":[-8.76706,32.49313],"type":"Point"}
}