{
  "type": "Feature",
  "properties": {
    "gn:admin1_code":"7.0",
    "gn:asciiname":"Sidi Ahmed",
    "gn:country_code":"MA",
    "gn:dem":392,
    "gn:feature_class":"P",
    "gn:feature_code":"PPL",
    "gn:name":"Sidi Ahmed",
    "gn:population":0,
    "gn:timezone":"Africa/Casablanca",
    "iso:country":"MA",
    "name:azb_x_preferred":[
        "\u0633\u06cc\u062f\u06cc \u0627\u062d\u0645\u062f"
    ],
    "name:ceb_x_preferred":[
        "Sidi Ahmed"
    ],
    "name:fas_x_preferred":[
        "\u0633\u06cc\u062f\u06cc \u0627\u062d\u0645\u062f"
    ],
    "name:fra_x_preferred":[
        "Sidi Ahmed"
    ],
    "name:msa_x_preferred":[
        "Sidi Ahmed"
    ],
    "name:swe_x_preferred":[
        "Sidi Ahmed"
    ],
    "wof:name":"Sidi Ahmed",
    "wof:placetype":"locality"
},
  "geometry": {"coordinates":[-8.49141,32.20807],"type":"Point"}
}