{
  "type": "Feature",
  "properties": {
    "gn:admin1_code":"7.0",
    "gn:asciiname":"Talborjt",
    "gn:country_code":"MA",
    "gn:dem":391,
    "gn:feature_class":"P",
    "gn:feature_code":"PPL",
    "gn:name":"Talborjt",
    "gn:population":0,
    "gn:timezone":"Africa/Casablanca",
    "iso:country":"MA",
    "wof:name":"Talborjt",
    "wof:placetype":"locality"
},
  "geometry": {"coordinates":[-9.6627,30.95153],"type":"Point"}
}