{
  "type": "Feature",
  "properties": {
    "gn:admin1_code":"5.0",
    "gn:asciiname":"Ayt Ou Gharbll",
    "gn:country_code":"MA",
    "gn:dem":1045,
    "gn:feature_class":"P",
    "gn:feature_code":"PPL",
    "gn:name":"Ayt Ou Gharbll",
    "gn:population":0,
    "gn:timezone":"Africa/Casablanca",
    "iso:country":"MA",
    "wof:name":"Ayt Ou Gharbll",
    "wof:placetype":"locality"
},
  "geometry": {"coordinates":[-6.55488,32.14184],"type":"Point"}
}