{
  "type": "Feature",
  "properties": {
    "gn:admin1_code":"9.0",
    "gn:asciiname":"Tinzert",
    "gn:country_code":"MA",
    "gn:dem":1135,
    "gn:feature_class":"P",
    "gn:feature_code":"PPL",
    "gn:name":"Tinzert",
    "gn:population":0,
    "gn:timezone":"Africa/Casablanca",
    "iso:country":"MA",
    "wof:name":"Tinzert",
    "wof:placetype":"locality"
},
  "geometry": {"coordinates":[-9.28244,30.68862],"type":"Point"}
}