{
  "type": "Feature",
  "properties": {
    "gn:admin1_code":"07",
    "gn:asciiname":"Mejdid",
    "gn:country_code":"MA",
    "gn:dem":1104,
    "gn:feature_class":"P",
    "gn:feature_code":"PPL",
    "gn:name":"Mejdid",
    "gn:population":0,
    "gn:timezone":"Africa/Casablanca",
    "iso:country":"MA",
    "wof:name":"Mejdid",
    "wof:placetype":"locality"
},
  "geometry": {"coordinates":[-8.49081,31.1187],"type":"Point"}
}