{
  "type": "Feature",
  "properties": {
    "gn:admin1_code":"1.0",
    "gn:asciiname":"Douar Ahouli",
    "gn:country_code":"MA",
    "gn:dem":296,
    "gn:feature_class":"P",
    "gn:feature_code":"PPL",
    "gn:name":"Douar Ahouli",
    "gn:population":0,
    "gn:timezone":"Africa/Casablanca",
    "iso:country":"MA",
    "wof:name":"Douar Ahouli",
    "wof:placetype":"locality"
},
  "geometry": {"coordinates":[-4.2964,35.04953],"type":"Point"}
}