{
  "type": "Feature",
  "properties": {
    "gn:gn_country":"MA",
    "gn:gn_fcode":"ADM3",
    "gn:gn_pop":2776,
    "gn:population":2401,
    "iso:country":"MA",
    "name:ara_x_preferred":[
        "\u0637\u0627\u0637\u0627 (\u0627\u0644\u0628\u0644\u062f\u064a\u0629)"
    ],
    "name:fra_x_preferred":[
        "Ait Ouabelli"
    ],
    "name:fra_x_variant":[
        "Ait Ouabelli (CR)",
        "Ait Ouabelli (Commune Rurale)"
    ],
    "qs_pg:aaroncc":"MA",
    "qs_pg:gn_country":"MA",
    "qs_pg:gn_fcode":"ADM3",
    "qs_pg:gn_pop":2776,
    "qs_pg:name":"Ait Ouabelli",
    "qs_pg:photos_9r":0,
    "qs_pg:photos_sr":0,
    "qs_pg:pop_sr":4,
    "qs_pg:qs_pg_placetype":"localadmin",
    "wof:name":"Ait Ouabelli",
    "wof:placetype":"localadmin",
    "wof:population":2401
},
  "geometry": {"coordinates":[-8.59028,29.13402],"type":"Point"}
}