{
  "type": "Feature",
  "properties": {
    "gn:admin1_code":"9.0",
    "gn:asciiname":"Ait Mout Ou'l",
    "gn:country_code":"MA",
    "gn:dem":929,
    "gn:feature_class":"P",
    "gn:feature_code":"PPL",
    "gn:name":"A\u00eft Mout Ou\u2019l",
    "gn:population":0,
    "gn:timezone":"Africa/Casablanca",
    "iso:country":"MA",
    "wof:name":"Ait Mout Ou'l",
    "wof:placetype":"locality"
},
  "geometry": {"coordinates":[-9.18383,29.71996],"type":"Point"}
}