{
  "type": "Feature",
  "properties": {
    "gn:admin1_code":"6.0",
    "gn:asciiname":"Dahah",
    "gn:country_code":"MA",
    "gn:dem":204,
    "gn:feature_class":"P",
    "gn:feature_code":"PPL",
    "gn:name":"Dahah",
    "gn:population":0,
    "gn:timezone":"Africa/Casablanca",
    "iso:country":"MA",
    "wof:name":"Dahah",
    "wof:placetype":"locality"
},
  "geometry": {"coordinates":[-7.98585,33.15904],"type":"Point"}
}