{
  "type": "Feature",
  "properties": {
    "gn:admin1_code":"1.0",
    "gn:asciiname":"Nouidrech",
    "gn:country_code":"MA",
    "gn:dem":33,
    "gn:feature_class":"P",
    "gn:feature_code":"PPL",
    "gn:name":"Nouidrech",
    "gn:population":0,
    "gn:timezone":"Africa/Casablanca",
    "iso:country":"MA",
    "wof:name":"Nouidrech",
    "wof:placetype":"locality"
},
  "geometry": {"coordinates":[-5.70481,35.82636],"type":"Point"}
}