{
  "type": "Feature",
  "properties": {
    "gn:country":"MA",
    "gn:fcode":"ADM3",
    "gn:pop":25655,
    "iso:country":"MA",
    "name:ara_x_preferred":[
        "\u0648\u0627\u062f \u0645\u0644\u062d\u0629"
    ],
    "name:fra_x_preferred":[
        "Tahla"
    ],
    "name:fra_x_variant":[
        "Tahla (MU)",
        "Tahla (Commune Urbaine)"
    ],
    "qs:name":"Tahla",
    "qs:photos_9r":0,
    "qs:photos_sr":0,
    "qs:pop_sr":"7",
    "wd:wordcount":22,
    "wof:name":"Tahla",
    "wof:placetype":"localadmin",
    "wof:population":25655
},
  "geometry": {"coordinates":[-4.42889,34.0476],"type":"Point"}
}