{
  "type": "Feature",
  "properties": {
    "gn:admin1_code":"3.0",
    "gn:asciiname":"Douar Ain Lbarda",
    "gn:country_code":"MA",
    "gn:dem":628,
    "gn:feature_class":"P",
    "gn:feature_code":"PPL",
    "gn:name":"Douar Ain Lbarda",
    "gn:population":0,
    "gn:timezone":"Africa/Casablanca",
    "iso:country":"MA",
    "wof:name":"Douar Ain Lbarda",
    "wof:placetype":"locality"
},
  "geometry": {"coordinates":[-5.04121,34.07722],"type":"Point"}
}