{
  "type": "Feature",
  "properties": {
    "gn:admin1_code":"03",
    "gn:asciiname":"El Arsa",
    "gn:country_code":"MA",
    "gn:dem":976,
    "gn:feature_class":"P",
    "gn:feature_code":"PPL",
    "gn:name":"El Arsa",
    "gn:population":0,
    "gn:timezone":"Africa/Casablanca",
    "iso:country":"MA",
    "name:und_x_variant":[
        "Douar el Arsa",
        "El Arsa"
    ],
    "wof:name":"El Arsa",
    "wof:placetype":"locality"
},
  "geometry": {"coordinates":[-4.05483,33.87241],"type":"Point"}
}