{
  "type": "Feature",
  "properties": {
    "gn:admin1_code":"7.0",
    "gn:asciiname":"Ait Ali Ou Hammou",
    "gn:country_code":"MA",
    "gn:dem":640,
    "gn:feature_class":"P",
    "gn:feature_code":"PPL",
    "gn:name":"Ait Ali Ou Hammou",
    "gn:population":0,
    "gn:timezone":"Africa/Casablanca",
    "iso:country":"MA",
    "wof:name":"Ait Ali Ou Hammou",
    "wof:placetype":"locality"
},
  "geometry": {"coordinates":[-7.68255,31.57058],"type":"Point"}
}