{
  "type": "Feature",
  "properties": {
    "gn:admin1_code":"5.0",
    "gn:asciiname":"Wawissakht",
    "gn:country_code":"MA",
    "gn:dem":886,
    "gn:feature_class":"P",
    "gn:feature_code":"PPL",
    "gn:name":"Wawissakht",
    "gn:population":0,
    "gn:timezone":"Africa/Casablanca",
    "iso:country":"MA",
    "wof:name":"Wawissakht",
    "wof:placetype":"locality"
},
  "geometry": {"coordinates":[-6.91282,31.85699],"type":"Point"}
}