{
  "type": "Feature",
  "properties": {
    "gn:admin1_code":"10",
    "gn:asciiname":"Id Xilab",
    "gn:country_code":"MA",
    "gn:dem":236,
    "gn:feature_class":"P",
    "gn:feature_code":"PPL",
    "gn:name":"Id Xilab",
    "gn:population":0,
    "gn:timezone":"Africa/Casablanca",
    "iso:country":"MA",
    "wof:name":"Id Xilab",
    "wof:placetype":"locality"
},
  "geometry": {"coordinates":[-10.01,29.41],"type":"Point"}
}