{
  "type": "Feature",
  "properties": {
    "gn:admin1_code":"9.0",
    "gn:asciiname":"Tazdout",
    "gn:country_code":"MA",
    "gn:dem":1722,
    "gn:feature_class":"P",
    "gn:feature_code":"PPL",
    "gn:name":"Tazdout",
    "gn:population":0,
    "gn:timezone":"Africa/Casablanca",
    "iso:country":"MA",
    "wof:name":"Tazdout",
    "wof:placetype":"locality"
},
  "geometry": {"coordinates":[-7.73179,30.36676],"type":"Point"}
}