{
  "type": "Feature",
  "properties": {
    "gn:admin1_code":"07",
    "gn:admin2_code":"41.0",
    "gn:admin3_code":"704105192.0",
    "gn:asciiname":"Tizguine",
    "gn:country_code":"MA",
    "gn:dem":1097,
    "gn:feature_class":"P",
    "gn:feature_code":"PPLA3",
    "gn:name":"Tizguine",
    "gn:population":0,
    "gn:timezone":"Africa/Casablanca",
    "iso:country":"MA",
    "name:ara_x_preferred":[
        "\u062a\u0632\u0643\u064a\u0646"
    ],
    "name:azb_x_preferred":[
        "\u062a\u0632\u06a9\u06cc\u0646"
    ],
    "name:cat_x_preferred":[
        "Tizguine"
    ],
    "name:ceb_x_preferred":[
        "Tizguine"
    ],
    "name:fas_x_preferred":[
        "\u062a\u0632\u06a9\u06cc\u0646"
    ],
    "name:fra_x_preferred":[
        "Tizguine"
    ],
    "name:ita_x_preferred":[
        "Tizguine"
    ],
    "name:swe_x_preferred":[
        "Tizguine"
    ],
    "name:urd_x_preferred":[
        "\u062a\u06cc\u0632\u06af\u06cc\u0646"
    ],
    "wof:name":"Tizguine",
    "wof:placetype":"locality"
},
  "geometry": {"coordinates":[-8.31611,31.22836],"type":"Point"}
}