{
  "type": "Feature",
  "properties": {
    "gn:admin1_code":"07",
    "gn:admin2_code":"41.0",
    "gn:admin3_code":"704105192.0",
    "gn:asciiname":"Tizguine",
    "gn:country_code":"MA",
    "gn:dem":1097,
    "gn:feature_class":"P",
    "gn:feature_code":"PPLA3",
    "gn:name":"Tizguine",
    "gn:population":0,
    "gn:timezone":"Africa/Casablanca",
    "iso:country":"MA",
    "wof:name":"Tizguine",
    "wof:placetype":"locality"
},
  "geometry": {"coordinates":[-8.31611,31.22836],"type":"Point"}
}