{
  "type": "Feature",
  "properties": {
    "gn:admin1_code":"9.0",
    "gn:asciiname":"Tizeggorine",
    "gn:country_code":"MA",
    "gn:dem":600,
    "gn:feature_class":"P",
    "gn:feature_code":"PPL",
    "gn:name":"Tizeggorine",
    "gn:population":0,
    "gn:timezone":"Africa/Casablanca",
    "iso:country":"MA",
    "wof:name":"Tizeggorine",
    "wof:placetype":"locality"
},
  "geometry": {"coordinates":[-9.32841,29.7714],"type":"Point"}
}