{
  "type": "Feature",
  "properties": {
    "gn:admin1_code":"01",
    "gn:asciiname":"Douar Baguem",
    "gn:country_code":"MA",
    "gn:dem":147,
    "gn:feature_class":"P",
    "gn:feature_code":"PPL",
    "gn:name":"Douar Baguem",
    "gn:population":0,
    "gn:timezone":"Africa/Casablanca",
    "iso:country":"MA",
    "wof:name":"Douar Baguem",
    "wof:placetype":"locality"
},
  "geometry": {"coordinates":[-3.86562,35.12707],"type":"Point"}
}