{
  "type": "Feature",
  "properties": {
    "gn:admin1_code":"4.0",
    "gn:asciiname":"Lamsada",
    "gn:country_code":"MA",
    "gn:dem":59,
    "gn:feature_class":"P",
    "gn:feature_code":"PPL",
    "gn:name":"Lamsada",
    "gn:population":0,
    "gn:timezone":"Africa/Casablanca",
    "iso:country":"MA",
    "wof:name":"Lamsada",
    "wof:placetype":"locality"
},
  "geometry": {"coordinates":[-6.69802,34.11772],"type":"Point"}
}