{
  "type": "Feature",
  "properties": {
    "gn:admin1_code":"9.0",
    "gn:asciiname":"Aguarti",
    "gn:country_code":"MA",
    "gn:dem":977,
    "gn:feature_class":"P",
    "gn:feature_code":"PPL",
    "gn:name":"Aguarti",
    "gn:population":0,
    "gn:timezone":"Africa/Casablanca",
    "iso:country":"MA",
    "wof:name":"Aguarti",
    "wof:placetype":"locality"
},
  "geometry": {"coordinates":[-7.94449,30.6955],"type":"Point"}
}