{
  "type": "Feature",
  "properties": {
    "gn:admin1_code":"08",
    "gn:admin2_code":"401.0",
    "gn:admin3_code":"440103152.0",
    "gn:asciiname":"Telouet",
    "gn:country_code":"MA",
    "gn:dem":1784,
    "gn:feature_class":"P",
    "gn:feature_code":"PPLA3",
    "gn:name":"Telouet",
    "gn:population":0,
    "gn:timezone":"Africa/Casablanca",
    "iso:country":"MA",
    "name:und_x_variant":[
        "Dar Kaid el Glaoui",
        "Teluet",
        "Telou\u00e8te",
        "Telouet"
    ],
    "wof:name":"Telouet",
    "wof:placetype":"neighbourhood"
},
  "geometry": {"coordinates":[-7.23789,31.28925],"type":"Point"}
}