{
  "type": "Feature",
  "properties": {
    "gn:admin1_code":"01",
    "gn:asciiname":"El Ouesta",
    "gn:country_code":"MA",
    "gn:dem":673,
    "gn:feature_class":"P",
    "gn:feature_code":"PPL",
    "gn:name":"El Ouesta",
    "gn:population":0,
    "gn:timezone":"Africa/Casablanca",
    "iso:country":"MA",
    "name:und_x_variant":[
        "Wasta",
        "El Ouesta"
    ],
    "wof:name":"El Ouesta",
    "wof:placetype":"locality"
},
  "geometry": {"coordinates":[-5.28283,34.98616],"type":"Point"}
}