{
  "type": "Feature",
  "properties": {
    "gn:admin1_code":"03",
    "gn:asciiname":"Douar Ezzaouia Tabouda",
    "gn:country_code":"MA",
    "gn:dem":524,
    "gn:feature_class":"P",
    "gn:feature_code":"PPL",
    "gn:name":"Douar Ezzaouia Tabouda",
    "gn:population":0,
    "gn:timezone":"Africa/Casablanca",
    "iso:country":"MA",
    "name:und_x_variant":[
        "Zaouia Tebouda"
    ],
    "wof:name":"Douar Ezzaouia Tabouda",
    "wof:placetype":"locality"
},
  "geometry": {"coordinates":[-4.72955,33.9878],"type":"Point"}
}