{
  "type": "Feature",
  "properties": {
    "gn:admin1_code":"01",
    "gn:asciiname":"Ouantout",
    "gn:country_code":"MA",
    "gn:dem":632,
    "gn:feature_class":"P",
    "gn:feature_code":"PPL",
    "gn:name":"Ouantout",
    "gn:population":0,
    "gn:timezone":"Africa/Casablanca",
    "iso:country":"MA",
    "name:und_x_variant":[
        "Diar Ouantol",
        "Diar Ouanto\u00fbt",
        "Ouantout"
    ],
    "wof:name":"Ouantout",
    "wof:placetype":"locality"
},
  "geometry": {"coordinates":[-5.54902,35.25354],"type":"Point"}
}