{
  "type": "Feature",
  "properties": {
    "gn:country":"MA",
    "gn:fcode":"ADM3",
    "gn:pop":1694,
    "iso:country":"MA",
    "name:ara_x_preferred":[
        "\u0639\u064a\u0646 \u0627\u0644\u0635\u0641\u0627"
    ],
    "name:ara_x_variant":[
        "\u0631\u0623\u0633 \u0639\u0635\u0641\u0648\u0631"
    ],
    "name:cat_x_preferred":[
        "Ras Asfour"
    ],
    "name:fra_x_preferred":[
        "Ras Asfour"
    ],
    "name:fra_x_variant":[
        "Ras Asfour (CR)",
        "Ras Asfour (Commune Rurale)"
    ],
    "qs:name":"Ras Asfour",
    "qs:photos_9r":0,
    "qs:photos_sr":0,
    "qs:pop_sr":"3",
    "wof:name":"Ras Asfour",
    "wof:placetype":"localadmin",
    "wof:population":1694
},
  "geometry": {"coordinates":[-1.84483,34.51897],"type":"Point"}
}