{
  "type": "Feature",
  "properties": {
    "gn:admin1_code":"2.0",
    "gn:asciiname":"Ouahda Ferme",
    "gn:country_code":"MA",
    "gn:dem":280,
    "gn:feature_class":"P",
    "gn:feature_code":"PPL",
    "gn:name":"Ouahda Ferme",
    "gn:population":0,
    "gn:timezone":"Africa/Casablanca",
    "iso:country":"MA",
    "wof:name":"Ouahda Ferme",
    "wof:placetype":"locality"
},
  "geometry": {"coordinates":[-2.76348,35.01345999999999],"type":"Point"}
}