{
  "type": "Feature",
  "properties": {
    "gn:admin1_code":"6.0",
    "gn:asciiname":"Dar El Haj Mohamed",
    "gn:country_code":"MA",
    "gn:dem":146,
    "gn:feature_class":"P",
    "gn:feature_code":"PPL",
    "gn:name":"Dar El Haj Mohamed",
    "gn:population":0,
    "gn:timezone":"Africa/Casablanca",
    "iso:country":"MA",
    "wof:name":"Dar El Haj Mohamed",
    "wof:placetype":"locality"
},
  "geometry": {"coordinates":[-8.78298,32.55063],"type":"Point"}
}