{
  "type": "Feature",
  "properties": {
    "gn:admin1_code":"07",
    "gn:asciiname":"Douar Lakhlifat",
    "gn:country_code":"MA",
    "gn:dem":416,
    "gn:feature_class":"P",
    "gn:feature_code":"PPL",
    "gn:name":"Douar Lakhlifat",
    "gn:population":0,
    "gn:timezone":"Africa/Casablanca",
    "iso:country":"MA",
    "name:und_x_variant":[
        "Douar Krlifat",
        "Laghlifate",
        "Lakhela\u00effate",
        "Lakhela\u00effat",
        "Douar Lakhlifat"
    ],
    "wof:name":"Douar Lakhlifat",
    "wof:placetype":"locality"
},
  "geometry": {"coordinates":[-9.44504,31.66285],"type":"Point"}
}