{
  "type": "Feature",
  "properties": {
    "gn:admin1_code":"10.0",
    "gn:asciiname":"Id Sidi Mohamed",
    "gn:country_code":"MA",
    "gn:dem":389,
    "gn:feature_class":"P",
    "gn:feature_code":"PPL",
    "gn:name":"Id Sidi Mohamed",
    "gn:population":0,
    "gn:timezone":"Africa/Casablanca",
    "iso:country":"MA",
    "wof:name":"Id Sidi Mohamed",
    "wof:placetype":"locality"
},
  "geometry": {"coordinates":[-9.97149,29.31699],"type":"Point"}
}