{
  "type": "Feature",
  "properties": {
    "gn:admin1_code":"05",
    "gn:asciiname":"Douar Ayt At-Tanji",
    "gn:country_code":"MA",
    "gn:dem":429,
    "gn:feature_class":"P",
    "gn:feature_code":"PPL",
    "gn:name":"Douar Ayt At-Tanji",
    "gn:population":0,
    "gn:timezone":"Africa/Casablanca",
    "iso:country":"MA",
    "name:und_x_variant":[
        "Et Tangui"
    ],
    "wof:name":"Douar Ayt At-Tanji",
    "wof:placetype":"locality"
},
  "geometry": {"coordinates":[-6.74222,32.48376],"type":"Point"}
}