{
  "type": "Feature",
  "properties": {
    "gn:admin1_code":"05",
    "gn:asciiname":"Souq Sebt Oulad Nemma",
    "gn:country_code":"MA",
    "gn:dem":412,
    "gn:feature_class":"P",
    "gn:feature_code":"PPL",
    "gn:name":"Souq Sebt Oulad Nemma",
    "gn:population":0,
    "gn:timezone":"Africa/Casablanca",
    "iso:country":"MA",
    "name:und_x_variant":[
        "Es Sebt",
        "Souk es Sebt",
        "Souq Sebt Oulad Nemma",
        "Souk Sebt des Oulad Nem\u00e2a"
    ],
    "wof:name":"Souq Sebt Oulad Nemma",
    "wof:placetype":"locality"
},
  "geometry": {"coordinates":[-6.70301,32.2973],"type":"Point"}
}