{
  "type": "Feature",
  "properties": {
    "gn:admin1_code":"05",
    "gn:asciiname":"Tazrout",
    "gn:country_code":"MA",
    "gn:dem":1882,
    "gn:elevation":"0.0",
    "gn:feature_class":"P",
    "gn:feature_code":"PPL",
    "gn:name":"Tazrout",
    "gn:population":0,
    "gn:timezone":"Africa/Casablanca",
    "iso:country":"MA",
    "name:und_x_variant":[
        "Taghrout",
        "Tazrout"
    ],
    "wof:name":"Tazrout",
    "wof:placetype":"locality"
},
  "geometry": {"coordinates":[-6.87031,31.54813],"type":"Point"}
}