{
  "type": "Feature",
  "properties": {
    "gn:admin1_code":"4.0",
    "gn:asciiname":"Cooperative Salam",
    "gn:country_code":"MA",
    "gn:dem":9,
    "gn:feature_class":"P",
    "gn:feature_code":"PPLF",
    "gn:name":"Coop\u00e9rative Salam",
    "gn:population":0,
    "gn:timezone":"Africa/Casablanca",
    "iso:country":"MA",
    "wof:name":"Cooperative Salam",
    "wof:placetype":"locality"
},
  "geometry": {"coordinates":[-6.41914,34.41502],"type":"Point"}
}