{
  "type": "Feature",
  "properties": {
    "gn:admin1_code":"9.0",
    "gn:asciiname":"Tanzagour",
    "gn:country_code":"MA",
    "gn:dem":935,
    "gn:feature_class":"P",
    "gn:feature_code":"PPL",
    "gn:name":"Tanzagour",
    "gn:population":0,
    "gn:timezone":"Africa/Casablanca",
    "iso:country":"MA",
    "wof:name":"Tanzagour",
    "wof:placetype":"locality"
},
  "geometry": {"coordinates":[-9.22795,29.81259],"type":"Point"}
}