{
  "type": "Feature",
  "properties": {
    "gn:admin1_code":"9.0",
    "gn:asciiname":"Agouni n'Ali",
    "gn:country_code":"MA",
    "gn:dem":902,
    "gn:feature_class":"P",
    "gn:feature_code":"PPL",
    "gn:name":"Agouni n\u2019Ali",
    "gn:population":0,
    "gn:timezone":"Africa/Casablanca",
    "iso:country":"MA",
    "wof:name":"Agouni n'Ali",
    "wof:placetype":"locality"
},
  "geometry": {"coordinates":[-9.1152,30.02693],"type":"Point"}
}