{
  "type": "Feature",
  "properties": {
    "gn:admin1_code":"05",
    "gn:asciiname":"Zaouia-Taglaout",
    "gn:country_code":"MA",
    "gn:dem":722,
    "gn:feature_class":"P",
    "gn:feature_code":"PPL",
    "gn:name":"Zaou\u00efa-Taglaout",
    "gn:population":0,
    "gn:timezone":"Africa/Casablanca",
    "iso:country":"MA",
    "name:und_x_variant":[
        "Zaouia Taglaout",
        "Zawyat Taglawt",
        "Zouiat Taglaout",
        "Zaou\u00efa-Taglaout"
    ],
    "wof:name":"Zaouia-Taglaout",
    "wof:placetype":"locality"
},
  "geometry": {"coordinates":[-7.27726,31.74005],"type":"Point"}
}