{
  "type": "Feature",
  "properties": {
    "gn:admin1_code":"05",
    "gn:asciiname":"Ait Brahim",
    "gn:country_code":"MA",
    "gn:dem":1214,
    "gn:feature_class":"P",
    "gn:feature_code":"PPL",
    "gn:name":"Ait Brahim",
    "gn:population":0,
    "gn:timezone":"Africa/Casablanca",
    "iso:country":"MA",
    "name:und_x_variant":[
        "A\u00eft Brahim"
    ],
    "wof:name":"Ait Brahim",
    "wof:placetype":"locality"
},
  "geometry": {"coordinates":[-7.08721,31.5288],"type":"Point"}
}