{
  "type": "Feature",
  "properties": {
    "gn:admin1_code":"08",
    "gn:asciiname":"Asgoun",
    "gn:country_code":"MA",
    "gn:dem":1757,
    "gn:feature_class":"P",
    "gn:feature_code":"PPL",
    "gn:name":"Asgoun",
    "gn:population":0,
    "gn:timezone":"Africa/Casablanca",
    "iso:country":"MA",
    "name:und_x_variant":[
        "Agounsi"
    ],
    "wof:name":"Asgoun",
    "wof:placetype":"locality"
},
  "geometry": {"coordinates":[-7.2584,31.27851],"type":"Point"}
}