{
  "type": "Feature",
  "properties": {
    "gn:admin1_code":"4.0",
    "gn:asciiname":"Douar Bni Zrara",
    "gn:country_code":"MA",
    "gn:dem":106,
    "gn:feature_class":"P",
    "gn:feature_code":"PPL",
    "gn:name":"Douar Bni Zrara",
    "gn:population":0,
    "gn:timezone":"Africa/Casablanca",
    "iso:country":"MA",
    "wof:name":"Douar Bni Zrara",
    "wof:placetype":"locality"
},
  "geometry": {"coordinates":[-5.48006,34.50322],"type":"Point"}
}