{
  "type": "Feature",
  "properties": {
    "gn:admin1_code":"8.0",
    "gn:asciiname":"Akhlif",
    "gn:country_code":"MA",
    "gn:dem":1145,
    "gn:feature_class":"P",
    "gn:feature_code":"PPL",
    "gn:name":"Akhlif",
    "gn:population":0,
    "gn:timezone":"Africa/Casablanca",
    "iso:country":"MA",
    "wof:name":"Akhlif",
    "wof:placetype":"locality"
},
  "geometry": {"coordinates":[-6.66799,30.98559],"type":"Point"}
}