{
  "type": "Feature",
  "properties": {
    "gn:admin1_code":"07",
    "gn:asciiname":"Douar Zaouiat El Bousouniya",
    "gn:country_code":"MA",
    "gn:dem":509,
    "gn:feature_class":"P",
    "gn:feature_code":"PPL",
    "gn:name":"Douar Zaouiat El Bousouniya",
    "gn:population":0,
    "gn:timezone":"Africa/Casablanca",
    "iso:country":"MA",
    "name:und_x_variant":[
        "Bou Sounia"
    ],
    "wof:name":"Douar Zaouiat El Bousouniya",
    "wof:placetype":"locality"
},
  "geometry": {"coordinates":[-8.82229,32.02278],"type":"Point"}
}