{
  "type": "Feature",
  "properties": {
    "gn:admin1_code":"08",
    "gn:asciiname":"Ait Haddou-n-Ait Youl",
    "gn:country_code":"MA",
    "gn:dem":1397,
    "gn:feature_class":"P",
    "gn:feature_code":"PPL",
    "gn:name":"A\u00eft Haddou-n-A\u00eft Youl",
    "gn:population":0,
    "gn:timezone":"Africa/Casablanca",
    "iso:country":"MA",
    "name:und_x_variant":[
        "A\u00eft Haddou-n-A\u00eft Youl",
        "A\u00eft Haddou n\u2019A\u00eft Youl"
    ],
    "wof:name":"Ait Haddou-n-Ait Youl",
    "wof:placetype":"neighbourhood"
},
  "geometry": {"coordinates":[-6.14038,31.20385],"type":"Point"}
}