{
  "type": "Feature",
  "properties": {
    "gn:admin1_code":"07",
    "gn:asciiname":"Khyant Redouani",
    "gn:country_code":"MA",
    "gn:dem":443,
    "gn:feature_class":"P",
    "gn:feature_code":"PPL",
    "gn:name":"Khyant Redouani",
    "gn:population":0,
    "gn:timezone":"Africa/Casablanca",
    "iso:country":"MA",
    "name:und_x_variant":[
        "Dar el Groun",
        "Douar el Groun",
        "El Groun",
        "Khyant Redouani"
    ],
    "wof:name":"Khyant Redouani",
    "wof:placetype":"locality"
},
  "geometry": {"coordinates":[-7.94172,32.01295],"type":"Point"}
}