{
  "type": "Feature",
  "properties": {
    "gn:admin1_code":"3.0",
    "gn:asciiname":"Douar Jlayla",
    "gn:country_code":"MA",
    "gn:dem":565,
    "gn:feature_class":"P",
    "gn:feature_code":"PPL",
    "gn:name":"Douar Jlayla",
    "gn:population":0,
    "gn:timezone":"Africa/Casablanca",
    "iso:country":"MA",
    "wof:name":"Douar Jlayla",
    "wof:placetype":"locality"
},
  "geometry": {"coordinates":[-4.41875,34.46547],"type":"Point"}
}