{
  "type": "Feature",
  "properties": {
    "gn:admin1_code":"08",
    "gn:asciiname":"Tabesbess",
    "gn:country_code":"MA",
    "gn:dem":1163,
    "gn:feature_class":"P",
    "gn:feature_code":"PPL",
    "gn:name":"Tabesbess",
    "gn:population":0,
    "gn:timezone":"Africa/Casablanca",
    "iso:country":"MA",
    "name:und_x_variant":[
        "Tabesbaste",
        "Tabesbess"
    ],
    "wof:name":"Tabesbess",
    "wof:placetype":"locality"
},
  "geometry": {"coordinates":[-5.38945,31.45882000000001],"type":"Point"}
}