{
  "type": "Feature",
  "properties": {
    "gn:admin1_code":"03",
    "gn:asciiname":"Douar Debabaa",
    "gn:country_code":"MA",
    "gn:dem":514,
    "gn:feature_class":"P",
    "gn:feature_code":"PPL",
    "gn:name":"Douar Debab\u00e2a",
    "gn:population":0,
    "gn:timezone":"Africa/Casablanca",
    "iso:country":"MA",
    "wof:name":"Douar Debabaa",
    "wof:placetype":"locality"
},
  "geometry": {"coordinates":[-4.99867,34.20667],"type":"Point"}
}