{
  "type": "Feature",
  "properties": {
    "gn:admin1_code":"08",
    "gn:asciiname":"Btatha",
    "gn:country_code":"MA",
    "gn:dem":867,
    "gn:feature_class":"P",
    "gn:feature_code":"PPL",
    "gn:name":"Btatha",
    "gn:population":0,
    "gn:timezone":"Africa/Casablanca",
    "iso:country":"MA",
    "name:und_x_variant":[
        "Zaou\u00efa Jd\u00eeda",
        "Labtatha",
        "El Betatha",
        "Btatha"
    ],
    "wof:name":"Btatha",
    "wof:placetype":"locality"
},
  "geometry": {"coordinates":[-4.21801,31.61535],"type":"Point"}
}