{
  "type": "Feature",
  "properties": {
    "gn:admin1_code":"03",
    "gn:asciiname":"El Amour",
    "gn:country_code":"MA",
    "gn:dem":61,
    "gn:feature_class":"P",
    "gn:feature_code":"PPL",
    "gn:name":"El Amour",
    "gn:population":0,
    "gn:timezone":"Africa/Casablanca",
    "iso:country":"MA",
    "name:und_x_variant":[
        "La\u00e2mour",
        "El Amour"
    ],
    "wof:name":"El Amour",
    "wof:placetype":"locality"
},
  "geometry": {"coordinates":[-5.43568,34.31705],"type":"Point"}
}