{
  "type": "Feature",
  "properties": {
    "gn:country":"MA",
    "gn:fcode":"ADM3",
    "gn:pop":2764,
    "iso:country":"MA",
    "name:ara_x_preferred":[
        "\u0631\u0623\u0633 \u0639\u0635\u0641\u0648\u0631"
    ],
    "name:fra_x_preferred":[
        "Oulad Ftata"
    ],
    "name:fra_x_variant":[
        "Oulad Ftata (CR)",
        "Oulad Ftata (Commune Rurale)"
    ],
    "qs:name":"Oulad Ftata",
    "qs:photos_9r":0,
    "qs:photos_sr":0,
    "qs:pop_sr":"4",
    "wof:name":"Oulad Ftata",
    "wof:placetype":"localadmin",
    "wof:population":2764
},
  "geometry": {"coordinates":[-6.63704,33.18211],"type":"Point"}
}