{
  "type": "Feature",
  "properties": {
    "gn:admin1_code":"8.0",
    "gn:asciiname":"Ait Hammou Ou 'Ali",
    "gn:country_code":"MA",
    "gn:dem":1957,
    "gn:feature_class":"P",
    "gn:feature_code":"PPL",
    "gn:name":"A\u00eft Hammou Ou \u2019Ali",
    "gn:population":0,
    "gn:timezone":"Africa/Casablanca",
    "iso:country":"MA",
    "wof:name":"Ait Hammou Ou 'Ali",
    "wof:placetype":"locality"
},
  "geometry": {"coordinates":[-7.22219,31.31905],"type":"Point"}
}