{
  "type": "Feature",
  "properties": {
    "gn:admin1_code":"09",
    "gn:asciiname":"Agadir-n-Tala",
    "gn:country_code":"MA",
    "gn:dem":1748,
    "gn:feature_class":"P",
    "gn:feature_code":"PPL",
    "gn:name":"Agadir-n-Tala",
    "gn:population":0,
    "gn:timezone":"Africa/Casablanca",
    "iso:country":"MA",
    "name:und_x_variant":[
        "Agadir n\u2019 Tala"
    ],
    "wof:name":"Agadir-n-Tala",
    "wof:placetype":"locality"
},
  "geometry": {"coordinates":[-7.78249,30.32581],"type":"Point"}
}