{
  "type": "Feature",
  "properties": {
    "gn:admin1_code":"7.0",
    "gn:asciiname":"Douar Laaouja",
    "gn:country_code":"MA",
    "gn:dem":608,
    "gn:feature_class":"P",
    "gn:feature_code":"PPL",
    "gn:name":"Douar Laaouja",
    "gn:population":0,
    "gn:timezone":"Africa/Casablanca",
    "iso:country":"MA",
    "wof:name":"Douar Laaouja",
    "wof:placetype":"locality"
},
  "geometry": {"coordinates":[-7.55136,31.98292],"type":"Point"}
}