{
  "type": "Feature",
  "properties": {
    "gn:admin1_code":"6.0",
    "gn:asciiname":"Moulay Mohamed",
    "gn:country_code":"MA",
    "gn:dem":294,
    "gn:feature_class":"P",
    "gn:feature_code":"PPL",
    "gn:name":"Moulay Mohamed",
    "gn:population":0,
    "gn:timezone":"Africa/Casablanca",
    "iso:country":"MA",
    "wof:name":"Moulay Mohamed",
    "wof:placetype":"locality"
},
  "geometry": {"coordinates":[-7.92407,32.97487],"type":"Point"}
}