{
  "type": "Feature",
  "properties": {
    "gn:admin1_code":"6.0",
    "gn:asciiname":"Dhar Lehmar",
    "gn:country_code":"MA",
    "gn:dem":418,
    "gn:feature_class":"P",
    "gn:feature_code":"PPL",
    "gn:name":"Dhar Lehmar",
    "gn:population":0,
    "gn:timezone":"Africa/Casablanca",
    "iso:country":"MA",
    "wof:name":"Dhar Lehmar",
    "wof:placetype":"locality"
},
  "geometry": {"coordinates":[-7.20641,33.27187],"type":"Point"}
}