{
  "type": "Feature",
  "properties": {
    "gn:admin1_code":"09",
    "gn:asciiname":"Sintil",
    "gn:country_code":"MA",
    "gn:dem":313,
    "gn:feature_class":"P",
    "gn:feature_code":"PPL",
    "gn:name":"Sintil",
    "gn:population":0,
    "gn:timezone":"Africa/Casablanca",
    "iso:country":"MA",
    "name:und_x_variant":[
        "Sentil",
        "Sinnt",
        "Sintit",
        "Sintil"
    ],
    "wof:name":"Sintil",
    "wof:placetype":"locality"
},
  "geometry": {"coordinates":[-9.74705,29.62157],"type":"Point"}
}