{
  "type": "Feature",
  "properties": {
    "gn:admin1_code":"9.0",
    "gn:asciiname":"Tagandout",
    "gn:country_code":"MA",
    "gn:dem":1189,
    "gn:feature_class":"P",
    "gn:feature_code":"PPL",
    "gn:name":"Tagandout",
    "gn:population":0,
    "gn:timezone":"Africa/Casablanca",
    "iso:country":"MA",
    "wof:name":"Tagandout",
    "wof:placetype":"locality"
},
  "geometry": {"coordinates":[-8.8583,30.09144],"type":"Point"}
}