{
  "type": "Feature",
  "properties": {
    "gn:admin1_code":"6.0",
    "gn:asciiname":"Oulad Sidi 'Mara",
    "gn:country_code":"MA",
    "gn:dem":191,
    "gn:feature_class":"P",
    "gn:feature_code":"PPL",
    "gn:name":"Oulad Sidi \u2019Mara",
    "gn:population":0,
    "gn:timezone":"Africa/Casablanca",
    "iso:country":"MA",
    "wof:name":"Oulad Sidi 'Mara",
    "wof:placetype":"locality"
},
  "geometry": {"coordinates":[-8.05448,32.86781],"type":"Point"}
}