{
  "type": "Feature",
  "properties": {
    "gn:admin1_code":"9.0",
    "gn:asciiname":"Irgane",
    "gn:country_code":"MA",
    "gn:dem":1118,
    "gn:feature_class":"P",
    "gn:feature_code":"PPL",
    "gn:name":"Irgane",
    "gn:population":0,
    "gn:timezone":"Africa/Casablanca",
    "iso:country":"MA",
    "wof:name":"Irgane",
    "wof:placetype":"locality"
},
  "geometry": {"coordinates":[-8.491,30.78229],"type":"Point"}
}