{
  "type": "Feature",
  "properties": {
    "gn:country":"MA",
    "gn:fcode":"ADM3",
    "gn:population":5690,
    "iso:country":"MA",
    "name:ara_x_preferred":[
        "\u0627\u0646\u0631\u0643\u064a"
    ],
    "name:ara_x_variant":[
        "\u0628\u064a\u0646 \u0648\u064a\u062f\u0627\u0646"
    ],
    "name:ary_x_preferred":[
        "\u0628\u064a\u0646 \u0644\u0648\u064a\u062f\u0627\u0646"
    ],
    "name:cat_x_preferred":[
        "Bin El Ouidane"
    ],
    "name:ceb_x_preferred":[
        "Bin El Ouidane"
    ],
    "name:deu_x_preferred":[
        "Bin El Ouidane"
    ],
    "name:eng_x_preferred":[
        "Bin El Ouidane"
    ],
    "name:fra_x_preferred":[
        "Bin El Ouidane"
    ],
    "name:fra_x_variant":[
        "Bin El Ouidane (CR)",
        "Bin El Ouidane (Commune Rurale)",
        "Bin elouidane",
        "Bin el Ouidane"
    ],
    "name:ita_x_preferred":[
        "Bin elouidane"
    ],
    "name:por_x_preferred":[
        "Bin el Ouidane"
    ],
    "name:swe_x_preferred":[
        "Bin El Ouidane"
    ],
    "qs:name":"Bin El Ouidane",
    "qs:photos_9r":0,
    "qs:photos_sr":0,
    "qs:pop_sr":"5",
    "wd:wordcount":61,
    "wof:name":"Bin El Ouidane",
    "wof:placetype":"localadmin",
    "wof:population":5690
},
  "geometry": {"coordinates":[-6.46331,32.10853],"type":"Point"}
}