{
  "type": "Feature",
  "properties": {
    "gn:admin1_code":"7.0",
    "gn:asciiname":"Lborrat",
    "gn:country_code":"MA",
    "gn:dem":56,
    "gn:feature_class":"P",
    "gn:feature_code":"PPL",
    "gn:name":"Lborrat",
    "gn:population":0,
    "gn:timezone":"Africa/Casablanca",
    "iso:country":"MA",
    "wof:name":"Lborrat",
    "wof:placetype":"locality"
},
  "geometry": {"coordinates":[-9.24042,32.23043],"type":"Point"}
}