{
  "type": "Feature",
  "properties": {
    "gn:admin1_code":"07",
    "gn:asciiname":"El Graa",
    "gn:country_code":"MA",
    "gn:dem":343,
    "gn:feature_class":"P",
    "gn:feature_code":"PPL",
    "gn:name":"El Graa",
    "gn:population":0,
    "gn:timezone":"Africa/Casablanca",
    "iso:country":"MA",
    "name:und_x_variant":[
        "Ouled Khalifa el Gara",
        "El Graa"
    ],
    "wof:name":"El Graa",
    "wof:placetype":"locality"
},
  "geometry": {"coordinates":[-7.75252,32.56661],"type":"Point"}
}