{
  "type": "Feature",
  "properties": {
    "gn:admin1_code":"7.0",
    "gn:asciiname":"Ait El Konnima",
    "gn:country_code":"MA",
    "gn:dem":211,
    "gn:feature_class":"P",
    "gn:feature_code":"PPL",
    "gn:name":"Ait El Konnima",
    "gn:population":0,
    "gn:timezone":"Africa/Casablanca",
    "iso:country":"MA",
    "wof:name":"Ait El Konnima",
    "wof:placetype":"locality"
},
  "geometry": {"coordinates":[-9.52531,31.59503],"type":"Point"}
}