{
  "type": "Feature",
  "properties": {
    "gn:admin1_code":"09",
    "gn:asciiname":"Idamghane",
    "gn:country_code":"MA",
    "gn:dem":1595,
    "gn:feature_class":"P",
    "gn:feature_code":"PPL",
    "gn:name":"Idamghane",
    "gn:population":0,
    "gn:timezone":"Africa/Casablanca",
    "iso:country":"MA",
    "name:und_x_variant":[
        "Idamkh\u00e8n",
        "Idamghne",
        "Idamkhene",
        "Idamghane"
    ],
    "wof:name":"Idamghane",
    "wof:placetype":"locality"
},
  "geometry": {"coordinates":[-7.98248,30.23328],"type":"Point"}
}