{
  "type": "Feature",
  "properties": {
    "gn:admin1_code":"03",
    "gn:asciiname":"Dar Ettaliba",
    "gn:country_code":"MA",
    "gn:dem":245,
    "gn:feature_class":"P",
    "gn:feature_code":"PPL",
    "gn:name":"Dar Ettaliba",
    "gn:population":0,
    "gn:timezone":"Africa/Casablanca",
    "iso:country":"MA",
    "wof:name":"Dar Ettaliba",
    "wof:placetype":"locality"
},
  "geometry": {"coordinates":[-4.68119,34.46572],"type":"Point"}
}