{
  "type": "Feature",
  "properties": {
    "gn:admin1_code":"8.0",
    "gn:asciiname":"Toughza",
    "gn:country_code":"MA",
    "gn:dem":998,
    "gn:feature_class":"P",
    "gn:feature_code":"PPL",
    "gn:name":"Toughza",
    "gn:population":0,
    "gn:timezone":"Africa/Casablanca",
    "iso:country":"MA",
    "name:und_x_variant":[
        "Iournza"
    ],
    "wof:name":"Toughza",
    "wof:placetype":"locality"
},
  "geometry": {"coordinates":[-4.90235,31.67885],"type":"Point"}
}