{
  "type": "Feature",
  "properties": {
    "gn:country":"MA",
    "gn:fcode":"ADM3",
    "gn:pop":6660,
    "iso:country":"MA",
    "name:ara_x_preferred":[
        "\u0623\u0648\u0644\u0627\u062f \u0633\u064a\u062f\u064a \u0639\u0644\u064a \u0628\u0646 \u064a\u0648\u0633\u0641"
    ],
    "name:ara_x_variant":[
        "\u0623\u0648\u0644\u0627\u062f \u0641\u0631\u064a\u062c"
    ],
    "name:cat_x_preferred":[
        "Oulad Frej"
    ],
    "name:ceb_x_preferred":[
        "Oulad Frej"
    ],
    "name:deu_x_preferred":[
        "Oulad Frej"
    ],
    "name:eng_x_preferred":[
        "Oulad Frej"
    ],
    "name:fra_x_preferred":[
        "Oulad Frej"
    ],
    "name:fra_x_variant":[
        "Oulad Frej (CR)",
        "Oulad Frej (Commune Rurale)"
    ],
    "name:ita_x_preferred":[
        "Oulad Frej"
    ],
    "name:nld_x_preferred":[
        "Oulad Frej"
    ],
    "name:swe_x_preferred":[
        "Oulad Frej"
    ],
    "qs:name":"Oulad Frej",
    "qs:photos_9r":0,
    "qs:photos_sr":0,
    "qs:pop_sr":"5",
    "wd:wordcount":78,
    "wof:name":"Oulad Frej",
    "wof:placetype":"localadmin",
    "wof:population":6660
},
  "geometry": {"coordinates":[-8.18087,33.01963],"type":"Point"}
}