{
  "type": "Feature",
  "properties": {
    "gn:admin1_code":"01",
    "gn:asciiname":"Caotina",
    "gn:country_code":"MA",
    "gn:dem":277,
    "gn:feature_class":"P",
    "gn:feature_code":"PPL",
    "gn:name":"Caotina",
    "gn:population":0,
    "gn:timezone":"Africa/Casablanca",
    "iso:country":"MA",
    "name:und_x_variant":[
        "Puento Fomento",
        "Fomento",
        "Puente de Fomento",
        "Caotina"
    ],
    "wof:name":"Caotina",
    "wof:placetype":"locality"
},
  "geometry": {"coordinates":[-5.30888,35.19545],"type":"Point"}
}