{
  "type": "Feature",
  "properties": {
    "gn:admin1_code":"9.0",
    "gn:asciiname":"Aourir",
    "gn:country_code":"MA",
    "gn:dem":872,
    "gn:feature_class":"P",
    "gn:feature_code":"PPL",
    "gn:name":"Aourir",
    "gn:population":0,
    "gn:timezone":"Africa/Casablanca",
    "iso:country":"MA",
    "name:ara_x_preferred":[
        "\u0623\u0648\u0631\u064a\u0631"
    ],
    "name:cat_x_preferred":[
        "Aourir"
    ],
    "name:ceb_x_preferred":[
        "Aourir"
    ],
    "name:eus_x_preferred":[
        "Aourir"
    ],
    "name:fra_x_preferred":[
        "Aourir"
    ],
    "name:ita_x_preferred":[
        "Aourir"
    ],
    "name:pol_x_preferred":[
        "Aurir"
    ],
    "name:por_x_preferred":[
        "Aourir"
    ],
    "name:swe_x_preferred":[
        "Aourir"
    ],
    "wof:name":"Aourir",
    "wof:placetype":"locality"
},
  "geometry": {"coordinates":[-9.08496,30.07506],"type":"Point"}
}