{
  "type": "Feature",
  "properties": {
    "gn:admin1_code":"7.0",
    "gn:asciiname":"Annrar Mellouln",
    "gn:country_code":"MA",
    "gn:dem":925,
    "gn:feature_class":"P",
    "gn:feature_code":"PPL",
    "gn:name":"Annrar Mellouln",
    "gn:population":0,
    "gn:timezone":"Africa/Casablanca",
    "iso:country":"MA",
    "wof:name":"Annrar Mellouln",
    "wof:placetype":"locality"
},
  "geometry": {"coordinates":[-9.22718,31.25413],"type":"Point"}
}