{
  "type": "Feature",
  "properties": {
    "gn:admin1_code":"07",
    "gn:asciiname":"Tasseli",
    "gn:country_code":"MA",
    "gn:dem":1508,
    "gn:feature_class":"P",
    "gn:feature_code":"PPL",
    "gn:name":"Tasseli",
    "gn:population":0,
    "gn:timezone":"Africa/Casablanca",
    "iso:country":"MA",
    "wof:name":"Tasseli",
    "wof:placetype":"locality"
},
  "geometry": {"coordinates":[-8.69861,30.98088],"type":"Point"}
}