{
  "type": "Feature",
  "properties": {
    "gn:country":"MA",
    "gn:fcode":"ADM3",
    "gn:pop":7951,
    "iso:country":"MA",
    "name:ara_x_preferred":[
        "\u0627\u062b\u0646\u064a\u0646 \u0627\u0643\u0644\u0648"
    ],
    "name:ara_x_variant":[
        "\u0623\u0643\u062f\u0632"
    ],
    "name:azb_x_preferred":[
        "\u0627\u06a9\u062f\u0632"
    ],
    "name:aze_x_preferred":[
        "Aqd\u0259z"
    ],
    "name:bul_x_preferred":[
        "\u0410\u0433\u0434\u0435\u0437"
    ],
    "name:cat_x_preferred":[
        "Agdz"
    ],
    "name:ceb_x_preferred":[
        "Agdz"
    ],
    "name:deu_x_preferred":[
        "Agdz"
    ],
    "name:eng_x_preferred":[
        "Agdz"
    ],
    "name:fas_x_preferred":[
        "\u0627\u06a9\u062f\u0632"
    ],
    "name:fra_x_preferred":[
        "Agdz"
    ],
    "name:fra_x_variant":[
        "Agdz (MU)",
        "Agdz (Commune Urbaine)"
    ],
    "name:ita_x_preferred":[
        "Agdz"
    ],
    "name:lit_x_preferred":[
        "Agdezas"
    ],
    "name:nld_x_preferred":[
        "Agdz"
    ],
    "name:pol_x_preferred":[
        "Akdaz"
    ],
    "name:por_x_preferred":[
        "Agdz"
    ],
    "name:swe_x_preferred":[
        "Agdz"
    ],
    "name:urd_x_preferred":[
        "\u0627\u06af\u062f\u0632"
    ],
    "qs:name":"Agdz",
    "qs:photos_9r":0,
    "qs:photos_sr":0,
    "qs:pop_sr":"5",
    "wd:wordcount":310,
    "wof:name":"Agdz",
    "wof:placetype":"localadmin",
    "wof:population":7951
},
  "geometry": {"coordinates":[-6.47287,30.69838],"type":"Point"}
}