{
  "type": "Feature",
  "properties": {
    "gn:admin1_code":"9.0",
    "gn:asciiname":"Ait Hammou",
    "gn:country_code":"MA",
    "gn:dem":631,
    "gn:feature_class":"P",
    "gn:feature_code":"PPL",
    "gn:name":"A\u00eft Hammou",
    "gn:population":0,
    "gn:timezone":"Africa/Casablanca",
    "iso:country":"MA",
    "name:ara_x_preferred":[
        "\u0622\u064a\u062a \u062d\u0645\u0648"
    ],
    "name:azb_x_preferred":[
        "\u0622\u06cc\u062a \u0647\u0627\u0645\u0648"
    ],
    "name:cat_x_preferred":[
        "Ait Hammou"
    ],
    "name:fas_x_preferred":[
        "\u0622\u06cc\u062a \u0647\u0627\u0645\u0648"
    ],
    "name:ita_x_preferred":[
        "Ait Hammou"
    ],
    "wof:name":"Ait Hammou",
    "wof:placetype":"locality"
},
  "geometry": {"coordinates":[-9.0981,30.10065],"type":"Point"}
}