{
  "type": "Feature",
  "properties": {
    "gn:admin1_code":"7.0",
    "gn:asciiname":"Douar El Gouraanc Zouizat",
    "gn:country_code":"MA",
    "gn:dem":341,
    "gn:feature_class":"P",
    "gn:feature_code":"PPL",
    "gn:name":"Douar El Gouraanc Zouizat",
    "gn:population":0,
    "gn:timezone":"Africa/Casablanca",
    "iso:country":"MA",
    "wof:name":"Douar El Gouraanc Zouizat",
    "wof:placetype":"locality"
},
  "geometry": {"coordinates":[-9.10065,32.00113],"type":"Point"}
}