{
  "type": "Feature",
  "properties": {
    "gn:admin1_code":"9.0",
    "gn:asciiname":"Igguie el Ain",
    "gn:country_code":"MA",
    "gn:dem":1244,
    "gn:feature_class":"P",
    "gn:feature_code":"PPL",
    "gn:name":"Igguie el A\u00efn",
    "gn:population":0,
    "gn:timezone":"Africa/Casablanca",
    "iso:country":"MA",
    "wof:name":"Igguie el Ain",
    "wof:placetype":"locality"
},
  "geometry": {"coordinates":[-9.45774,30.66291],"type":"Point"}
}