{
  "type": "Feature",
  "properties": {
    "gn:admin1_code":"07",
    "gn:asciiname":"Ouiskdou",
    "gn:country_code":"MA",
    "gn:dem":1050,
    "gn:feature_class":"P",
    "gn:feature_code":"PPL",
    "gn:name":"Ouiskdou",
    "gn:population":0,
    "gn:timezone":"Africa/Casablanca",
    "iso:country":"MA",
    "name:und_x_variant":[
        "Ouissgado",
        "Ouis Kdou",
        "Ouis Keddou",
        "Ouiskdou"
    ],
    "wof:name":"Ouiskdou",
    "wof:placetype":"locality"
},
  "geometry": {"coordinates":[-7.47363,31.52252],"type":"Point"}
}