{
  "type": "Feature",
  "properties": {
    "gn:admin1_code":"3.0",
    "gn:asciiname":"Douar Oulad Lmenana",
    "gn:country_code":"MA",
    "gn:dem":346,
    "gn:feature_class":"P",
    "gn:feature_code":"PPL",
    "gn:name":"Douar Oulad Lmenana",
    "gn:population":0,
    "gn:timezone":"Africa/Casablanca",
    "iso:country":"MA",
    "wof:name":"Douar Oulad Lmenana",
    "wof:placetype":"locality"
},
  "geometry": {"coordinates":[-5.01999,34.44863],"type":"Point"}
}