{
  "type": "Feature",
  "properties": {
    "gn:admin1_code":"01",
    "gn:asciiname":"Targa",
    "gn:country_code":"MA",
    "gn:dem":29,
    "gn:feature_class":"P",
    "gn:feature_code":"PPL",
    "gn:name":"Targa",
    "gn:population":0,
    "gn:timezone":"Africa/Casablanca",
    "iso:country":"MA",
    "name:und_x_variant":[
        "Targha",
        "Tarerha",
        "Targa"
    ],
    "wof:name":"Targa",
    "wof:placetype":"locality"
},
  "geometry": {"coordinates":[-5.0117,35.39097],"type":"Point"}
}