{
  "type": "Feature",
  "properties": {
    "gn:admin1_code":"07",
    "gn:asciiname":"Ait Moussi",
    "gn:country_code":"MA",
    "gn:dem":436,
    "gn:feature_class":"P",
    "gn:feature_code":"PPL",
    "gn:name":"A\u00eft Moussi",
    "gn:population":0,
    "gn:timezone":"Africa/Casablanca",
    "iso:country":"MA",
    "name:und_x_variant":[
        "Douar A\u00eft Moussi",
        "A\u00eft Moussi Omar",
        "A\u00eft Moussi"
    ],
    "wof:name":"Ait Moussi",
    "wof:placetype":"locality"
},
  "geometry": {"coordinates":[-7.97361,32.04759],"type":"Point"}
}