{
  "type": "Feature",
  "properties": {
    "gn:admin1_code":"4.0",
    "gn:asciiname":"Douar Oulad El Arta",
    "gn:country_code":"MA",
    "gn:dem":607,
    "gn:feature_class":"P",
    "gn:feature_code":"PPL",
    "gn:name":"Douar Oulad El Arta",
    "gn:population":0,
    "gn:timezone":"Africa/Casablanca",
    "iso:country":"MA",
    "wof:name":"Douar Oulad El Arta",
    "wof:placetype":"locality"
},
  "geometry": {"coordinates":[-6.75497,33.35299000000001],"type":"Point"}
}