{
  "type": "Feature",
  "properties": {
    "gn:admin1_code":"4.0",
    "gn:asciiname":"Dar Mohamed Ou Said",
    "gn:country_code":"MA",
    "gn:dem":639,
    "gn:feature_class":"P",
    "gn:feature_code":"PPL",
    "gn:name":"Dar Mohamed Ou Said",
    "gn:population":0,
    "gn:timezone":"Africa/Casablanca",
    "iso:country":"MA",
    "wof:name":"Dar Mohamed Ou Said",
    "wof:placetype":"locality"
},
  "geometry": {"coordinates":[-5.77878,33.72897],"type":"Point"}
}