{
  "type": "Feature",
  "properties": {
    "gn:admin1_code":"5.0",
    "gn:asciiname":"Tassekssout",
    "gn:country_code":"MA",
    "gn:dem":1510,
    "gn:feature_class":"P",
    "gn:feature_code":"PPL",
    "gn:name":"Tassekssout",
    "gn:population":0,
    "gn:timezone":"Africa/Casablanca",
    "iso:country":"MA",
    "wof:name":"Tassekssout",
    "wof:placetype":"locality"
},
  "geometry": {"coordinates":[-6.5088,32.04788],"type":"Point"}
}