{
  "type": "Feature",
  "properties": {
    "gn:admin1_code":"9.0",
    "gn:asciiname":"Ait 'Blla",
    "gn:country_code":"MA",
    "gn:dem":831,
    "gn:feature_class":"P",
    "gn:feature_code":"PPL",
    "gn:name":"A\u00eft \u2019Blla",
    "gn:population":0,
    "gn:timezone":"Africa/Casablanca",
    "iso:country":"MA",
    "wof:name":"Ait 'Blla",
    "wof:placetype":"locality"
},
  "geometry": {"coordinates":[-9.15002,29.66403],"type":"Point"}
}