{
  "type": "Feature",
  "properties": {
    "gn:admin1_code":"6.0",
    "gn:asciiname":"Mesaoud",
    "gn:country_code":"MA",
    "gn:dem":292,
    "gn:feature_class":"P",
    "gn:feature_code":"PPL",
    "gn:name":"Mesaoud",
    "gn:population":0,
    "gn:timezone":"Africa/Casablanca",
    "iso:country":"MA",
    "name:fra_x_preferred":[
        "Mesaoud"
    ],
    "wof:name":"Mesaoud",
    "wof:placetype":"locality"
},
  "geometry": {"coordinates":[-7.95431,32.8608],"type":"Point"}
}