{
  "type": "Feature",
  "properties": {
    "gn:admin1_code":"08",
    "gn:asciiname":"Asrir",
    "gn:country_code":"MA",
    "gn:dem":1014,
    "gn:feature_class":"P",
    "gn:feature_code":"PPL",
    "gn:name":"Asrir",
    "gn:population":0,
    "gn:timezone":"Africa/Casablanca",
    "iso:country":"MA",
    "name:und_x_variant":[
        "Asrir A\u00eft Frah",
        "Asrir",
        "Assat"
    ],
    "wof:name":"Asrir",
    "wof:placetype":"locality"
},
  "geometry": {"coordinates":[-5.07326,31.50968],"type":"Point"}
}