{
  "type": "Feature",
  "properties": {
    "gn:country":"MA",
    "gn:fcode":"ADM3",
    "gn:pop":8380,
    "iso:country":"MA",
    "name:ara_x_preferred":[
        "\u0627\u0642\u0627 \u0627\u064a\u063a\u0627\u0646"
    ],
    "name:fra_x_preferred":[
        "Allougoum"
    ],
    "name:fra_x_variant":[
        "Allougoum (CR)",
        "Allougoum (Commune Rurale)"
    ],
    "qs:name":"Allougoum",
    "qs:photos_9r":0,
    "qs:photos_sr":0,
    "qs:pop_sr":"5",
    "wof:name":"Allougoum",
    "wof:placetype":"localadmin",
    "wof:population":8380
},
  "geometry": {"coordinates":[-6.82941,29.96907],"type":"Point"}
}