{
  "type": "Feature",
  "properties": {
    "gn:admin1_code":"3.0",
    "gn:asciiname":"Douar Ic-ceffahen",
    "gn:country_code":"MA",
    "gn:dem":1217,
    "gn:feature_class":"P",
    "gn:feature_code":"PPL",
    "gn:name":"Douar I\u00e7-\u00e7effahen",
    "gn:population":0,
    "gn:timezone":"Africa/Casablanca",
    "iso:country":"MA",
    "wof:name":"Douar Ic-ceffahen",
    "wof:placetype":"locality"
},
  "geometry": {"coordinates":[-4.10341,33.98842],"type":"Point"}
}