{
  "type": "Feature",
  "properties": {
    "gn:admin1_code":"9.0",
    "gn:asciiname":"Anzg",
    "gn:country_code":"MA",
    "gn:dem":834,
    "gn:feature_class":"P",
    "gn:feature_code":"PPL",
    "gn:name":"Anzg",
    "gn:population":0,
    "gn:timezone":"Africa/Casablanca",
    "iso:country":"MA",
    "wof:name":"Anzg",
    "wof:placetype":"locality"
},
  "geometry": {"coordinates":[-9.10212,29.72361],"type":"Point"}
}