{
  "type": "Feature",
  "properties": {
    "gn:admin1_code":"9.0",
    "gn:asciiname":"Bouskene",
    "gn:country_code":"MA",
    "gn:dem":1072,
    "gn:feature_class":"P",
    "gn:feature_code":"PPL",
    "gn:name":"Bouskene",
    "gn:population":0,
    "gn:timezone":"Africa/Casablanca",
    "iso:country":"MA",
    "name:ara_x_preferred":[
        "\u0628\u0648\u0633\u0643\u0646"
    ],
    "name:azb_x_preferred":[
        "\u0628\u0648\u0633\u06a9\u0646"
    ],
    "name:fas_x_preferred":[
        "\u0628\u0648\u0633\u06a9\u0646"
    ],
    "name:fra_x_preferred":[
        "Bouskene"
    ],
    "name:ita_x_preferred":[
        "Bouskene"
    ],
    "name:msa_x_preferred":[
        "Bouskene"
    ],
    "name:por_x_preferred":[
        "Bouskene"
    ],
    "name:ron_x_preferred":[
        "Bouskene"
    ],
    "name:spa_x_preferred":[
        "Bouskene"
    ],
    "name:vie_x_preferred":[
        "Bouskene"
    ],
    "name:zho_x_preferred":[
        "\u5e03\u65af\u80af"
    ],
    "wof:name":"Bouskene",
    "wof:placetype":"locality"
},
  "geometry": {"coordinates":[-8.79669,30.7408],"type":"Point"}
}