{
  "type": "Feature",
  "properties": {
    "gn:admin1_code":"1.0",
    "gn:asciiname":"Imakhkhoutene",
    "gn:country_code":"MA",
    "gn:dem":167,
    "gn:feature_class":"P",
    "gn:feature_code":"PPL",
    "gn:name":"Imakhkhoutene",
    "gn:population":0,
    "gn:timezone":"Africa/Casablanca",
    "iso:country":"MA",
    "wof:name":"Imakhkhoutene",
    "wof:placetype":"locality"
},
  "geometry": {"coordinates":[-5.15478,35.44531],"type":"Point"}
}