{
  "type": "Feature",
  "properties": {
    "gn:admin1_code":"01",
    "gn:admin2_code":"571.0",
    "gn:admin3_code":"1657101071.0",
    "gn:asciiname":"Oued Laou",
    "gn:country_code":"MA",
    "gn:dem":20,
    "gn:feature_class":"P",
    "gn:feature_code":"PPLA3",
    "gn:name":"Oued Laou",
    "gn:population":0,
    "gn:timezone":"Africa/Casablanca",
    "iso:country":"MA",
    "name:ara_x_preferred":[
        "\u0648\u0627\u062f \u0644\u0648"
    ],
    "name:azb_x_preferred":[
        "\u0648\u0627\u062f \u0644\u0648"
    ],
    "name:cat_x_preferred":[
        "Oued Laou"
    ],
    "name:deu_x_preferred":[
        "Oued Laou"
    ],
    "name:eus_x_preferred":[
        "Oued Laou"
    ],
    "name:fas_x_preferred":[
        "\u0648\u0627\u062f \u0644\u0648"
    ],
    "name:fra_x_preferred":[
        "Oued Laou"
    ],
    "name:spa_x_preferred":[
        "Oued Laou"
    ],
    "name:und_x_variant":[
        "Uad Lau",
        "Oued Lao",
        "Oued Lahou",
        "Oued Lou"
    ],
    "name:urd_x_preferred":[
        "\u0648\u0627\u062f \u0644\u0627\u0648"
    ],
    "wof:name":"Oued Laou",
    "wof:placetype":"locality"
},
  "geometry": {"coordinates":[-5.09627,35.4484],"type":"Point"}
}