{
  "type": "Feature",
  "properties": {
    "gn:admin1_code":"6.0",
    "gn:asciiname":"Nouala",
    "gn:country_code":"MA",
    "gn:dem":190,
    "gn:feature_class":"P",
    "gn:feature_code":"PPL",
    "gn:name":"Nouala",
    "gn:population":0,
    "gn:timezone":"Africa/Casablanca",
    "iso:country":"MA",
    "wof:name":"Nouala",
    "wof:placetype":"locality"
},
  "geometry": {"coordinates":[-8.10014,33.19083],"type":"Point"}
}