{
  "type": "Feature",
  "properties": {
    "gn:admin1_code":"8.0",
    "gn:asciiname":"Ait Mouch Takatar",
    "gn:country_code":"MA",
    "gn:dem":1016,
    "gn:feature_class":"P",
    "gn:feature_code":"PPL",
    "gn:name":"A\u00eft Mouch Takatar",
    "gn:population":0,
    "gn:timezone":"Africa/Casablanca",
    "iso:country":"MA",
    "wof:name":"Ait Mouch Takatar",
    "wof:placetype":"locality"
},
  "geometry": {"coordinates":[-4.93748,31.68914],"type":"Point"}
}