{
  "type": "Feature",
  "properties": {
    "gn:admin1_code":"9.0",
    "gn:asciiname":"Ait Mbarek",
    "gn:country_code":"MA",
    "gn:dem":939,
    "gn:feature_class":"P",
    "gn:feature_code":"PPL",
    "gn:name":"A\u00eft Mbarek",
    "gn:population":0,
    "gn:timezone":"Africa/Casablanca",
    "iso:country":"MA",
    "wof:name":"Ait Mbarek",
    "wof:placetype":"locality"
},
  "geometry": {"coordinates":[-9.26975,30.68609],"type":"Point"}
}