{
  "type": "Feature",
  "properties": {
    "gn:admin1_code":"9.0",
    "gn:asciiname":"Dar Jfard",
    "gn:country_code":"MA",
    "gn:dem":1079,
    "gn:feature_class":"P",
    "gn:feature_code":"PPL",
    "gn:name":"Dar Jfard",
    "gn:population":0,
    "gn:timezone":"Africa/Casablanca",
    "iso:country":"MA",
    "wof:name":"Dar Jfard",
    "wof:placetype":"locality"
},
  "geometry": {"coordinates":[-9.18843,29.91803],"type":"Point"}
}