{
  "type": "Feature",
  "properties": {
    "gn:admin1_code":"9.0",
    "gn:asciiname":"Dou Ganza",
    "gn:country_code":"MA",
    "gn:dem":1344,
    "gn:feature_class":"P",
    "gn:feature_code":"PPL",
    "gn:name":"Dou Ganza",
    "gn:population":0,
    "gn:timezone":"Africa/Casablanca",
    "iso:country":"MA",
    "wof:name":"Dou Ganza",
    "wof:placetype":"locality"
},
  "geometry": {"coordinates":[-8.07704,30.51414],"type":"Point"}
}