{
  "type": "Feature",
  "properties": {
    "gn:admin1_code":"02",
    "gn:asciiname":"Taliouine",
    "gn:country_code":"MA",
    "gn:dem":272,
    "gn:feature_class":"P",
    "gn:feature_code":"PPL",
    "gn:name":"Taliou\u00eene",
    "gn:population":0,
    "gn:timezone":"Africa/Casablanca",
    "iso:country":"MA",
    "name:ara_x_preferred":[
        "\u062a\u0627\u0644\u064a\u0648\u064a\u0646"
    ],
    "name:cat_x_preferred":[
        "Taliouine"
    ],
    "name:ceb_x_preferred":[
        "Taliouine"
    ],
    "name:deu_x_preferred":[
        "Taliouine"
    ],
    "name:fra_x_preferred":[
        "Taliouine"
    ],
    "name:nld_x_preferred":[
        "Taliouine"
    ],
    "name:por_x_preferred":[
        "Taliouine"
    ],
    "name:swe_x_preferred":[
        "Taliouine"
    ],
    "name:und_x_variant":[
        "Taliuin",
        "Taliou\u00eene"
    ],
    "wof:name":"Taliouine",
    "wof:placetype":"locality"
},
  "geometry": {"coordinates":[-3.52428,35.16455],"type":"Point"}
}