{
  "type": "Feature",
  "properties": {
    "gn:admin1_code":"02",
    "gn:asciiname":"Taliouine",
    "gn:country_code":"MA",
    "gn:dem":272,
    "gn:feature_class":"P",
    "gn:feature_code":"PPL",
    "gn:name":"Taliou\u00eene",
    "gn:population":0,
    "gn:timezone":"Africa/Casablanca",
    "iso:country":"MA",
    "name:und_x_variant":[
        "Taliuin",
        "Taliou\u00eene"
    ],
    "wof:name":"Taliouine",
    "wof:placetype":"locality"
},
  "geometry": {"coordinates":[-3.52428,35.16455],"type":"Point"}
}