{
  "type": "Feature",
  "properties": {
    "gn:admin1_code":"4.0",
    "gn:asciiname":"Darqaoua",
    "gn:country_code":"MA",
    "gn:dem":44,
    "gn:feature_class":"P",
    "gn:feature_code":"PPL",
    "gn:name":"Darqaoua",
    "gn:population":0,
    "gn:timezone":"Africa/Casablanca",
    "iso:country":"MA",
    "wof:name":"Darqaoua",
    "wof:placetype":"locality"
},
  "geometry": {"coordinates":[-6.23463,34.77261],"type":"Point"}
}