{
  "type": "Feature",
  "properties": {
    "gn:admin1_code":"7.0",
    "gn:asciiname":"Laqninat",
    "gn:country_code":"MA",
    "gn:dem":184,
    "gn:feature_class":"P",
    "gn:feature_code":"PPL",
    "gn:name":"Laqninat",
    "gn:population":0,
    "gn:timezone":"Africa/Casablanca",
    "iso:country":"MA",
    "wof:name":"Laqninat",
    "wof:placetype":"locality"
},
  "geometry": {"coordinates":[-8.77883,32.28175],"type":"Point"}
}