{
  "type": "Feature",
  "properties": {
    "gn:country":"MA",
    "gn:fcode":"ADM3",
    "gn:population":7609,
    "iso:country":"MA",
    "name:ara_x_preferred":[
        "\u0633\u064a\u062f\u064a \u062d\u0631\u0627\u0632\u0645"
    ],
    "name:fra_x_preferred":[
        "Elorjane"
    ],
    "name:fra_x_variant":[
        "Elorjane (CR)",
        "Elorjane (Commune Rurale)"
    ],
    "qs:name":"Elorjane",
    "qs:photos_9r":0,
    "qs:photos_sr":0,
    "qs:pop_sr":"5",
    "wof:name":"Elorjane",
    "wof:placetype":"localadmin",
    "wof:population":7609
},
  "geometry": {"coordinates":[-3.77287,33.4508],"type":"Point"}
}