{
  "type": "Feature",
  "properties": {
    "gn:admin1_code":"2.0",
    "gn:asciiname":"Douar Ihejjiouene",
    "gn:country_code":"MA",
    "gn:dem":628,
    "gn:feature_class":"P",
    "gn:feature_code":"PPL",
    "gn:name":"Douar Ihejjiouene",
    "gn:population":0,
    "gn:timezone":"Africa/Casablanca",
    "iso:country":"MA",
    "wof:name":"Douar Ihejjiouene",
    "wof:placetype":"locality"
},
  "geometry": {"coordinates":[-3.61637,35.05676],"type":"Point"}
}