{
  "type": "Feature",
  "properties": {
    "gn:admin1_code":"7.0",
    "gn:asciiname":"Sidi Bou Mlik",
    "gn:country_code":"MA",
    "gn:dem":366,
    "gn:feature_class":"P",
    "gn:feature_code":"PPL",
    "gn:name":"Sidi Bou Mlik",
    "gn:population":0,
    "gn:timezone":"Africa/Casablanca",
    "iso:country":"MA",
    "wof:name":"Sidi Bou Mlik",
    "wof:placetype":"locality"
},
  "geometry": {"coordinates":[-7.25868,32.25526],"type":"Point"}
}