{
  "type": "Feature",
  "properties": {
    "gn:admin1_code":"01",
    "gn:asciiname":"Jmedrane",
    "gn:country_code":"MA",
    "gn:dem":420,
    "gn:feature_class":"P",
    "gn:feature_code":"PPL",
    "gn:name":"Jmedrane",
    "gn:population":0,
    "gn:timezone":"Africa/Casablanca",
    "iso:country":"MA",
    "name:und_x_variant":[
        "Ymedran",
        "Jmedrane"
    ],
    "wof:name":"Jmedrane",
    "wof:placetype":"locality"
},
  "geometry": {"coordinates":[-4.779,35.21828],"type":"Point"}
}