{
  "type": "Feature",
  "properties": {
    "gn:admin1_code":"5.0",
    "gn:asciiname":"Douar Barraqa",
    "gn:country_code":"MA",
    "gn:dem":535,
    "gn:feature_class":"P",
    "gn:feature_code":"PPL",
    "gn:name":"Douar Barraqa",
    "gn:population":0,
    "gn:timezone":"Africa/Casablanca",
    "iso:country":"MA",
    "wof:name":"Douar Barraqa",
    "wof:placetype":"locality"
},
  "geometry": {"coordinates":[-6.25694,32.61375],"type":"Point"}
}