{
  "type": "Feature",
  "properties": {
    "gn:admin1_code":"03",
    "gn:asciiname":"Douar el Gaada",
    "gn:country_code":"MA",
    "gn:dem":608,
    "gn:feature_class":"P",
    "gn:feature_code":"PPL",
    "gn:name":"Douar el Gaada",
    "gn:population":0,
    "gn:timezone":"Africa/Casablanca",
    "iso:country":"MA",
    "name:und_x_variant":[
        "Ga\u00e2da",
        "Douar el Gaada",
        "El Gaada"
    ],
    "wof:name":"Douar el Gaada",
    "wof:placetype":"locality"
},
  "geometry": {"coordinates":[-3.90199,34.34948],"type":"Point"}
}