{
  "type": "Feature",
  "properties": {
    "gn:admin1_code":"07",
    "gn:asciiname":"Douar Ben Khalifa",
    "gn:country_code":"MA",
    "gn:dem":540,
    "gn:feature_class":"P",
    "gn:feature_code":"PPL",
    "gn:name":"Douar Ben Khalifa",
    "gn:population":0,
    "gn:timezone":"Africa/Casablanca",
    "iso:country":"MA",
    "name:und_x_variant":[
        "Bel Khalifa"
    ],
    "wof:name":"Douar Ben Khalifa",
    "wof:placetype":"locality"
},
  "geometry": {"coordinates":[-7.64147,31.69063],"type":"Point"}
}