{
  "type": "Feature",
  "properties": {
    "gn:admin1_code":"6.0",
    "gn:asciiname":"Oulad Mekki",
    "gn:country_code":"MA",
    "gn:dem":140,
    "gn:feature_class":"P",
    "gn:feature_code":"PPL",
    "gn:name":"Oulad Mekki",
    "gn:population":0,
    "gn:timezone":"Africa/Casablanca",
    "iso:country":"MA",
    "wof:name":"Oulad Mekki",
    "wof:placetype":"locality"
},
  "geometry": {"coordinates":[-8.21569,32.98409],"type":"Point"}
}