{
  "type": "Feature",
  "properties": {
    "gn:admin1_code":"07",
    "gn:asciiname":"Tiddirht Oudra",
    "gn:country_code":"MA",
    "gn:dem":1432,
    "gn:feature_class":"P",
    "gn:feature_code":"PPL",
    "gn:name":"Tiddirht Oudra",
    "gn:population":0,
    "gn:timezone":"Africa/Casablanca",
    "iso:country":"MA",
    "wof:name":"Tiddirht Oudra",
    "wof:placetype":"locality"
},
  "geometry": {"coordinates":[-9.17918,30.88095],"type":"Point"}
}