{
  "type": "Feature",
  "properties": {
    "gn:admin1_code":"01",
    "gn:asciiname":"Douar Fechkara",
    "gn:country_code":"MA",
    "gn:dem":271,
    "gn:feature_class":"P",
    "gn:feature_code":"PPL",
    "gn:name":"Douar Fechkara",
    "gn:population":0,
    "gn:timezone":"Africa/Casablanca",
    "iso:country":"MA",
    "name:und_x_variant":[
        "Fechkara"
    ],
    "wof:name":"Douar Fechkara",
    "wof:placetype":"locality"
},
  "geometry": {"coordinates":[-5.59861,35.60979000000001],"type":"Point"}
}