{
  "type": "Feature",
  "properties": {
    "gn:admin1_code":"2.0",
    "gn:asciiname":"Amara Harcha",
    "gn:country_code":"MA",
    "gn:dem":457,
    "gn:feature_class":"P",
    "gn:feature_code":"PPL",
    "gn:name":"Amara Harcha",
    "gn:population":0,
    "gn:timezone":"Africa/Casablanca",
    "iso:country":"MA",
    "wof:name":"Amara Harcha",
    "wof:placetype":"locality"
},
  "geometry": {"coordinates":[-3.48508,35.0483],"type":"Point"}
}