{
  "type": "Feature",
  "properties": {
    "gn:admin1_code":"2.0",
    "gn:asciiname":"Taberbourt",
    "gn:country_code":"MA",
    "gn:dem":821,
    "gn:feature_class":"P",
    "gn:feature_code":"PPL",
    "gn:name":"Taberbourt",
    "gn:population":0,
    "gn:timezone":"Africa/Casablanca",
    "iso:country":"MA",
    "wof:name":"Taberbourt",
    "wof:placetype":"locality"
},
  "geometry": {"coordinates":[-2.13014,34.54252],"type":"Point"}
}