{
  "type": "Feature",
  "properties": {
    "gn:admin1_code":"09",
    "gn:asciiname":"Igounjabene",
    "gn:country_code":"MA",
    "gn:dem":1010,
    "gn:feature_class":"P",
    "gn:feature_code":"PPL",
    "gn:name":"Igounjabene",
    "gn:population":0,
    "gn:timezone":"Africa/Casablanca",
    "iso:country":"MA",
    "name:und_x_variant":[
        "Igounjab\u00e8n",
        "Igounjabene"
    ],
    "wof:name":"Igounjabene",
    "wof:placetype":"locality"
},
  "geometry": {"coordinates":[-8.25999,30.45689],"type":"Point"}
}