{
  "type": "Feature",
  "properties": {
    "gn:admin1_code":"7.0",
    "gn:asciiname":"Imachtika",
    "gn:country_code":"MA",
    "gn:dem":309,
    "gn:feature_class":"P",
    "gn:feature_code":"PPL",
    "gn:name":"Imachtika",
    "gn:population":0,
    "gn:timezone":"Africa/Casablanca",
    "iso:country":"MA",
    "wof:name":"Imachtika",
    "wof:placetype":"locality"
},
  "geometry": {"coordinates":[-9.6773,31.29351],"type":"Point"}
}