{
  "type": "Feature",
  "properties": {
    "gn:admin1_code":"1.0",
    "gn:asciiname":"Houmat Beqqacha",
    "gn:country_code":"MA",
    "gn:dem":173,
    "gn:feature_class":"P",
    "gn:feature_code":"PPL",
    "gn:name":"Houmat Beqqacha",
    "gn:population":0,
    "gn:timezone":"Africa/Casablanca",
    "iso:country":"MA",
    "wof:name":"Houmat Beqqacha",
    "wof:placetype":"locality"
},
  "geometry": {"coordinates":[-5.71864,35.71367],"type":"Point"}
}