{
  "type": "Feature",
  "properties": {
    "gn:admin1_code":"7.0",
    "gn:asciiname":"Dar Mahloud",
    "gn:country_code":"MA",
    "gn:dem":534,
    "gn:feature_class":"P",
    "gn:feature_code":"PPL",
    "gn:name":"Dar Mahloud",
    "gn:population":0,
    "gn:timezone":"Africa/Casablanca",
    "iso:country":"MA",
    "wof:name":"Dar Mahloud",
    "wof:placetype":"locality"
},
  "geometry": {"coordinates":[-7.84843,31.56164],"type":"Point"}
}