{
  "type": "Feature",
  "properties": {
    "gn:admin1_code":"01",
    "gn:asciiname":"Selib",
    "gn:country_code":"MA",
    "gn:dem":457,
    "gn:feature_class":"P",
    "gn:feature_code":"PPL",
    "gn:name":"Selib",
    "gn:population":0,
    "gn:timezone":"Africa/Casablanca",
    "iso:country":"MA",
    "name:und_x_variant":[
        "Slib",
        "Salib",
        "Selib"
    ],
    "wof:name":"Selib",
    "wof:placetype":"locality"
},
  "geometry": {"coordinates":[-5.26479,34.95323],"type":"Point"}
}