{
  "type": "Feature",
  "properties": {
    "gn:admin1_code":"08",
    "gn:asciiname":"Abrach",
    "gn:country_code":"MA",
    "gn:dem":1591,
    "gn:feature_class":"P",
    "gn:feature_code":"PPL",
    "gn:name":"Abrach",
    "gn:population":0,
    "gn:timezone":"Africa/Casablanca",
    "iso:country":"MA",
    "name:und_x_variant":[
        "Aberach",
        "Abrach"
    ],
    "wof:name":"Abrach",
    "wof:placetype":"locality"
},
  "geometry": {"coordinates":[-6.68036,31.25904],"type":"Point"}
}