{
  "type": "Feature",
  "properties": {
    "gn:admin1_code":"04",
    "gn:asciiname":"Douar Lahfaya",
    "gn:country_code":"MA",
    "gn:dem":88,
    "gn:feature_class":"P",
    "gn:feature_code":"PPL",
    "gn:name":"Douar Lahfaya",
    "gn:population":0,
    "gn:timezone":"Africa/Casablanca",
    "iso:country":"MA",
    "name:und_x_variant":[
        "Douar el Halaf",
        "El Halaf",
        "Douar Lahfaya"
    ],
    "wof:name":"Douar Lahfaya",
    "wof:placetype":"locality"
},
  "geometry": {"coordinates":[-5.74582,34.64738],"type":"Point"}
}