{
  "type": "Feature",
  "properties": {
    "gn:admin1_code":"6.0",
    "gn:asciiname":"Douar Oulad El Arbe",
    "gn:country_code":"MA",
    "gn:dem":136,
    "gn:feature_class":"P",
    "gn:feature_code":"PPL",
    "gn:name":"Douar Oulad El Arbe",
    "gn:population":0,
    "gn:timezone":"Africa/Casablanca",
    "iso:country":"MA",
    "wof:name":"Douar Oulad El Arbe",
    "wof:placetype":"locality"
},
  "geometry": {"coordinates":[-8.82625,32.55553],"type":"Point"}
}