{
  "type": "Feature",
  "properties": {
    "gn:admin1_code":"7.0",
    "gn:asciiname":"Ait Chtouka",
    "gn:country_code":"MA",
    "gn:dem":223,
    "gn:feature_class":"P",
    "gn:feature_code":"PPL",
    "gn:name":"Ait Chtouka",
    "gn:population":0,
    "gn:timezone":"Africa/Casablanca",
    "iso:country":"MA",
    "wof:name":"Ait Chtouka",
    "wof:placetype":"locality"
},
  "geometry": {"coordinates":[-9.59647,31.53331],"type":"Point"}
}