{
  "type": "Feature",
  "properties": {
    "gn:admin1_code":"1.0",
    "gn:asciiname":"Diouanat Lborj",
    "gn:country_code":"MA",
    "gn:dem":100,
    "gn:feature_class":"P",
    "gn:feature_code":"PPL",
    "gn:name":"Diouanat Lborj",
    "gn:population":0,
    "gn:timezone":"Africa/Casablanca",
    "iso:country":"MA",
    "wof:name":"Diouanat Lborj",
    "wof:placetype":"locality"
},
  "geometry": {"coordinates":[-5.72598,35.69355],"type":"Point"}
}