{
  "type": "Feature",
  "properties": {
    "gn:country":"MA",
    "gn:fcode":"ADM3",
    "gn:pop":9066,
    "iso:country":"MA",
    "name:ara_x_preferred":[
        "\u0648\u0627\u062f\u064a \u0627\u0644\u0645\u062e\u0627\u0632\u0646"
    ],
    "name:ara_x_variant":[
        "\u0645\u0648\u0627\u0644\u064a\u0646 \u0627\u0644\u0648\u0627\u062f"
    ],
    "name:cat_x_preferred":[
        "Moualine el Oued"
    ],
    "name:eng_x_preferred":[
        "Moualine el Oued"
    ],
    "name:fra_x_preferred":[
        "Moualine El Oued"
    ],
    "name:fra_x_variant":[
        "Moualine El Oued (CR)",
        "Moualine El Oued (Commune Rurale)"
    ],
    "name:ita_x_preferred":[
        "Moualine el Oued"
    ],
    "name:nld_x_preferred":[
        "Moualine el Oued"
    ],
    "qs:name":"Moualine El Oued",
    "qs:photos_9r":0,
    "qs:photos_sr":0,
    "qs:pop_sr":"5",
    "wd:wordcount":24,
    "wof:name":"Moualine El Oued",
    "wof:placetype":"localadmin",
    "wof:population":9066
},
  "geometry": {"coordinates":[-7.32051,33.45609],"type":"Point"}
}