{
  "type": "Feature",
  "properties": {
    "gn:admin1_code":"3.0",
    "gn:asciiname":"Seddari Moussa",
    "gn:country_code":"MA",
    "gn:dem":288,
    "gn:feature_class":"P",
    "gn:feature_code":"PPL",
    "gn:name":"Seddari Moussa",
    "gn:population":0,
    "gn:timezone":"Africa/Casablanca",
    "iso:country":"MA",
    "wof:name":"Seddari Moussa",
    "wof:placetype":"locality"
},
  "geometry": {"coordinates":[-4.4615,34.35514000000001],"type":"Point"}
}