{
  "type": "Feature",
  "properties": {
    "gn:admin1_code":"3.0",
    "gn:asciiname":"Almou n-Cherif",
    "gn:country_code":"MA",
    "gn:dem":1089,
    "gn:feature_class":"P",
    "gn:feature_code":"PPL",
    "gn:name":"Almou n-Cherif",
    "gn:population":0,
    "gn:timezone":"Africa/Casablanca",
    "iso:country":"MA",
    "wof:name":"Almou n-Cherif",
    "wof:placetype":"locality"
},
  "geometry": {"coordinates":[-5.73319,33.54697],"type":"Point"}
}