{
  "type": "Feature",
  "properties": {
    "gn:admin1_code":"9.0",
    "gn:asciiname":"Tachikht",
    "gn:country_code":"MA",
    "gn:dem":555,
    "gn:feature_class":"P",
    "gn:feature_code":"PPL",
    "gn:name":"Tachikht",
    "gn:population":0,
    "gn:timezone":"Africa/Casablanca",
    "iso:country":"MA",
    "wof:name":"Tachikht",
    "wof:placetype":"locality"
},
  "geometry": {"coordinates":[-9.77814,30.67537],"type":"Point"}
}