{
  "type": "Feature",
  "properties": {
    "gn:admin1_code":"01",
    "gn:asciiname":"Bine el Ouidane",
    "gn:country_code":"MA",
    "gn:dem":181,
    "gn:feature_class":"P",
    "gn:feature_code":"PPL",
    "gn:name":"Bine el Ouidane",
    "gn:population":0,
    "gn:timezone":"Africa/Casablanca",
    "iso:country":"MA",
    "name:und_x_variant":[
        "Ben el Ouidane",
        "Bine el Ouidane"
    ],
    "wof:name":"Bine el Ouidane",
    "wof:placetype":"locality"
},
  "geometry": {"coordinates":[-5.4938,35.78624],"type":"Point"}
}