{
  "type": "Feature",
  "properties": {
    "gn:admin1_code":"08",
    "gn:asciiname":"Tabarqiyt",
    "gn:country_code":"MA",
    "gn:dem":1393,
    "gn:feature_class":"P",
    "gn:feature_code":"PPL",
    "gn:name":"Tabarqiyt",
    "gn:population":0,
    "gn:timezone":"Africa/Casablanca",
    "iso:country":"MA",
    "name:und_x_variant":[
        "Taberket",
        "Taberkit",
        "Tabarqiyt"
    ],
    "wof:name":"Tabarqiyt",
    "wof:placetype":"locality"
},
  "geometry": {"coordinates":[-4.64293,32.23919],"type":"Point"}
}