{
  "type": "Feature",
  "properties": {
    "gn:admin1_code":"09",
    "gn:asciiname":"Tiguemmi n'Ait Bihi",
    "gn:country_code":"MA",
    "gn:dem":253,
    "gn:feature_class":"P",
    "gn:feature_code":"PPL",
    "gn:name":"Tiguemmi n\u2019A\u00eft Bihi",
    "gn:population":0,
    "gn:timezone":"Africa/Casablanca",
    "iso:country":"MA",
    "name:und_x_variant":[
        "Ait Bihi",
        "Tiguemmi n\u2019A\u00eft Bihi"
    ],
    "wof:name":"Tiguemmi n'Ait Bihi",
    "wof:placetype":"locality"
},
  "geometry": {"coordinates":[-9.71,30.5606],"type":"Point"}
}