{
  "type": "Feature",
  "properties": {
    "gn:admin1_code":"9.0",
    "gn:asciiname":"Tagniyt",
    "gn:country_code":"MA",
    "gn:dem":892,
    "gn:feature_class":"P",
    "gn:feature_code":"PPL",
    "gn:name":"Tagniyt",
    "gn:population":0,
    "gn:timezone":"Africa/Casablanca",
    "iso:country":"MA",
    "wof:name":"Tagniyt",
    "wof:placetype":"locality"
},
  "geometry": {"coordinates":[-9.1027,29.62521],"type":"Point"}
}