{
  "type": "Feature",
  "properties": {
    "gn:admin1_code":"7.0",
    "gn:asciiname":"Ait Ahd ou Bella",
    "gn:country_code":"MA",
    "gn:dem":485,
    "gn:feature_class":"P",
    "gn:feature_code":"PPL",
    "gn:name":"A\u00eft Ahd ou Bella",
    "gn:population":0,
    "gn:timezone":"Africa/Casablanca",
    "iso:country":"MA",
    "wof:name":"Ait Ahd ou Bella",
    "wof:placetype":"locality"
},
  "geometry": {"coordinates":[-9.42753,31.33092000000001],"type":"Point"}
}