{
  "type": "Feature",
  "properties": {
    "gn:admin1_code":"01",
    "gn:asciiname":"Douar Moutti",
    "gn:country_code":"MA",
    "gn:dem":796,
    "gn:feature_class":"P",
    "gn:feature_code":"PPL",
    "gn:name":"Douar Moutti",
    "gn:population":0,
    "gn:timezone":"Africa/Casablanca",
    "iso:country":"MA",
    "name:und_x_variant":[
        "Monti",
        "Motte",
        "Douar Moutti"
    ],
    "wof:name":"Douar Moutti",
    "wof:placetype":"locality"
},
  "geometry": {"coordinates":[-4.85096,35.01522],"type":"Point"}
}