{
  "type": "Feature",
  "properties": {
    "gn:admin1_code":"08",
    "gn:asciiname":"Amgane",
    "gn:country_code":"MA",
    "gn:dem":1091,
    "gn:feature_class":"P",
    "gn:feature_code":"PPL",
    "gn:name":"Amgane",
    "gn:population":0,
    "gn:timezone":"Africa/Casablanca",
    "iso:country":"MA",
    "name:und_x_variant":[
        "Anegane",
        "Amgane"
    ],
    "wof:name":"Amgane",
    "wof:placetype":"locality"
},
  "geometry": {"coordinates":[-4.75471,31.41623],"type":"Point"}
}