{
  "type": "Feature",
  "properties": {
    "gn:admin1_code":"01",
    "gn:asciiname":"Douar Galmet",
    "gn:country_code":"MA",
    "gn:dem":354,
    "gn:feature_class":"P",
    "gn:feature_code":"PPL",
    "gn:name":"Douar Galmet",
    "gn:population":0,
    "gn:timezone":"Africa/Casablanca",
    "iso:country":"MA",
    "name:und_x_variant":[
        "Guelmez"
    ],
    "wof:name":"Douar Galmet",
    "wof:placetype":"locality"
},
  "geometry": {"coordinates":[-5.0251,35.293],"type":"Point"}
}