{
  "type": "Feature",
  "properties": {
    "gn:admin1_code":"06",
    "gn:asciiname":"Douar Laqrafiyine",
    "gn:country_code":"MA",
    "gn:dem":626,
    "gn:feature_class":"P",
    "gn:feature_code":"PPL",
    "gn:name":"Douar Laqrafiyine",
    "gn:population":0,
    "gn:timezone":"Africa/Casablanca",
    "iso:country":"MA",
    "name:und_x_variant":[
        "Kasbet el Maarif"
    ],
    "wof:name":"Douar Laqrafiyine",
    "wof:placetype":"locality"
},
  "geometry": {"coordinates":[-7.11352,33.06795],"type":"Point"}
}