{
  "type": "Feature",
  "properties": {
    "gn:admin1_code":"9.0",
    "gn:asciiname":"Ait Benhar",
    "gn:country_code":"MA",
    "gn:dem":852,
    "gn:feature_class":"P",
    "gn:feature_code":"PPL",
    "gn:name":"A\u00eft Benhar",
    "gn:population":0,
    "gn:timezone":"Africa/Casablanca",
    "iso:country":"MA",
    "wof:name":"Ait Benhar",
    "wof:placetype":"locality"
},
  "geometry": {"coordinates":[-9.24628,30.69705],"type":"Point"}
}