{
  "type": "Feature",
  "properties": {
    "gn:admin1_code":"6.0",
    "gn:asciiname":"Douar El Bakara",
    "gn:country_code":"MA",
    "gn:dem":149,
    "gn:feature_class":"P",
    "gn:feature_code":"PPL",
    "gn:name":"Douar El Bakara",
    "gn:population":0,
    "gn:timezone":"Africa/Casablanca",
    "iso:country":"MA",
    "wof:name":"Douar El Bakara",
    "wof:placetype":"locality"
},
  "geometry": {"coordinates":[-8.53667,32.7748],"type":"Point"}
}