{
  "type": "Feature",
  "properties": {
    "gn:admin1_code":"9.0",
    "gn:asciiname":"Imouglagal",
    "gn:country_code":"MA",
    "gn:dem":1185,
    "gn:feature_class":"P",
    "gn:feature_code":"PPL",
    "gn:name":"Imouglagal",
    "gn:population":0,
    "gn:timezone":"Africa/Casablanca",
    "iso:country":"MA",
    "wof:name":"Imouglagal",
    "wof:placetype":"locality"
},
  "geometry": {"coordinates":[-8.94448,29.92704],"type":"Point"}
}