{
  "type": "Feature",
  "properties": {
    "gn:admin1_code":"3.0",
    "gn:asciiname":"Troussi",
    "gn:country_code":"MA",
    "gn:dem":1587,
    "gn:feature_class":"P",
    "gn:feature_code":"PPLL",
    "gn:name":"Troussi",
    "gn:population":0,
    "gn:timezone":"Africa/Casablanca",
    "iso:country":"MA",
    "wof:name":"Troussi",
    "wof:placetype":"locality"
},
  "geometry": {"coordinates":[-4.97611,33.63055],"type":"Point"}
}