{
  "type": "Feature",
  "properties": {
    "gn:admin1_code":"9.0",
    "gn:asciiname":"Tassiyla-n-Tbnannat",
    "gn:country_code":"MA",
    "gn:dem":1254,
    "gn:feature_class":"P",
    "gn:feature_code":"PPL",
    "gn:name":"Tassiyla-n-Tbnannat",
    "gn:population":0,
    "gn:timezone":"Africa/Casablanca",
    "iso:country":"MA",
    "wof:name":"Tassiyla-n-Tbnannat",
    "wof:placetype":"locality"
},
  "geometry": {"coordinates":[-9.01704,29.91486],"type":"Point"}
}