{
  "type": "Feature",
  "properties": {
    "gn:admin1_code":"02",
    "gn:asciiname":"Oulad Amghar",
    "gn:country_code":"MA",
    "gn:dem":49,
    "gn:feature_class":"P",
    "gn:feature_code":"PPL",
    "gn:name":"Oulad Amghar",
    "gn:population":0,
    "gn:timezone":"Africa/Casablanca",
    "iso:country":"MA",
    "name:ara_x_preferred":[
        "\u0623\u0648\u0644\u0627\u062f \u0623\u0645\u063a\u0627\u0631"
    ],
    "name:cat_x_preferred":[
        "Oulad Amghar"
    ],
    "name:ceb_x_preferred":[
        "Oulad Amghar"
    ],
    "name:swe_x_preferred":[
        "Oulad Amghar"
    ],
    "wof:name":"Oulad Amghar",
    "wof:placetype":"locality"
},
  "geometry": {"coordinates":[-3.65434,35.25841],"type":"Point"}
}