{
  "type": "Feature",
  "properties": {
    "gn:admin1_code":"9.0",
    "gn:asciiname":"Targante",
    "gn:country_code":"MA",
    "gn:dem":853,
    "gn:feature_class":"P",
    "gn:feature_code":"PPL",
    "gn:name":"Targante",
    "gn:population":0,
    "gn:timezone":"Africa/Casablanca",
    "iso:country":"MA",
    "name:ara_x_preferred":[
        "\u062a\u0627\u0631\u0643\u0627\u0646\u062a"
    ],
    "name:cat_x_preferred":[
        "Targante"
    ],
    "name:ceb_x_preferred":[
        "Targante"
    ],
    "name:ita_x_preferred":[
        "Targante"
    ],
    "name:swe_x_preferred":[
        "Targante"
    ],
    "wof:name":"Targante",
    "wof:placetype":"locality"
},
  "geometry": {"coordinates":[-9.06041,30.81306],"type":"Point"}
}