{
  "type": "Feature",
  "properties": {
    "gn:admin1_code":"07",
    "gn:asciiname":"Tanfit",
    "gn:country_code":"MA",
    "gn:dem":1422,
    "gn:feature_class":"P",
    "gn:feature_code":"PPL",
    "gn:name":"Tanfit",
    "gn:population":0,
    "gn:timezone":"Africa/Casablanca",
    "iso:country":"MA",
    "name:und_x_variant":[
        "Tanefit"
    ],
    "wof:name":"Tanfit",
    "wof:placetype":"locality"
},
  "geometry": {"coordinates":[-8.09314,30.95837],"type":"Point"}
}