{
  "type": "Feature",
  "properties": {
    "gn:admin1_code":"7.0",
    "gn:asciiname":"Tigmat N'Tenzelt",
    "gn:country_code":"MA",
    "gn:dem":1340,
    "gn:feature_class":"P",
    "gn:feature_code":"PPL",
    "gn:name":"Tigmat N\u2019Tenzelt",
    "gn:population":0,
    "gn:timezone":"Africa/Casablanca",
    "iso:country":"MA",
    "wof:name":"Tigmat N'Tenzelt",
    "wof:placetype":"locality"
},
  "geometry": {"coordinates":[-9.12884,31.03236],"type":"Point"}
}