{
  "type": "Feature",
  "properties": {
    "gn:admin1_code":"7.0",
    "gn:asciiname":"Azib 'Azzi Bou Jem'a",
    "gn:country_code":"MA",
    "gn:dem":844,
    "gn:feature_class":"P",
    "gn:feature_code":"PPL",
    "gn:name":"Azib \u2019Azzi Bou Jem\u2019a",
    "gn:population":0,
    "gn:timezone":"Africa/Casablanca",
    "iso:country":"MA",
    "wof:name":"Azib 'Azzi Bou Jem'a",
    "wof:placetype":"locality"
},
  "geometry": {"coordinates":[-7.95262,31.38175],"type":"Point"}
}