{
  "type": "Feature",
  "properties": {
    "gn:admin1_code":"07",
    "gn:asciiname":"Douar Jbarat",
    "gn:country_code":"MA",
    "gn:dem":127,
    "gn:feature_class":"P",
    "gn:feature_code":"PPL",
    "gn:name":"Douar Jbarat",
    "gn:population":0,
    "gn:timezone":"Africa/Casablanca",
    "iso:country":"MA",
    "name:und_x_variant":[
        "Douar Jebarat",
        "Jebbarat",
        "Jebarat",
        "Douar Jbarat"
    ],
    "wof:name":"Douar Jbarat",
    "wof:placetype":"locality"
},
  "geometry": {"coordinates":[-9.215,32.34362],"type":"Point"}
}