{
  "type": "Feature",
  "properties": {
    "gn:admin1_code":"6.0",
    "gn:asciiname":"Lemnasra",
    "gn:country_code":"MA",
    "gn:dem":356,
    "gn:feature_class":"P",
    "gn:feature_code":"PPL",
    "gn:name":"Lemnasra",
    "gn:population":0,
    "gn:timezone":"Africa/Casablanca",
    "iso:country":"MA",
    "wof:name":"Lemnasra",
    "wof:placetype":"locality"
},
  "geometry": {"coordinates":[-7.11996,33.36556],"type":"Point"}
}