{
  "type": "Feature",
  "properties": {
    "gn:admin1_code":"2.0",
    "gn:asciiname":"Ibouqayene",
    "gn:country_code":"MA",
    "gn:dem":196,
    "gn:feature_class":"P",
    "gn:feature_code":"PPL",
    "gn:name":"Ibouqayene",
    "gn:population":0,
    "gn:timezone":"Africa/Casablanca",
    "iso:country":"MA",
    "wof:name":"Ibouqayene",
    "wof:placetype":"locality"
},
  "geometry": {"coordinates":[-2.99334,35.09614000000001],"type":"Point"}
}