{
  "type": "Feature",
  "properties": {
    "gn:admin1_code":"1.0",
    "gn:asciiname":"Douar Oulad Baqqal",
    "gn:country_code":"MA",
    "gn:dem":831,
    "gn:feature_class":"P",
    "gn:feature_code":"PPL",
    "gn:name":"Douar Oulad Baqqal",
    "gn:population":0,
    "gn:timezone":"Africa/Casablanca",
    "iso:country":"MA",
    "wof:name":"Douar Oulad Baqqal",
    "wof:placetype":"locality"
},
  "geometry": {"coordinates":[-5.44445,35.28495],"type":"Point"}
}