{
  "type": "Feature",
  "properties": {
    "gn:admin1_code":"07",
    "gn:asciiname":"Ait el Abid",
    "gn:country_code":"MA",
    "gn:dem":527,
    "gn:feature_class":"P",
    "gn:feature_code":"PPL",
    "gn:name":"A\u00eft el Abid",
    "gn:population":0,
    "gn:timezone":"Africa/Casablanca",
    "iso:country":"MA",
    "wof:name":"Ait el Abid",
    "wof:placetype":"locality"
},
  "geometry": {"coordinates":[-9.26,31.51],"type":"Point"}
}