{
  "type": "Feature",
  "properties": {
    "gn:admin1_code":"07",
    "gn:admin2_code":"41.0",
    "gn:admin3_code":"704107112.0",
    "gn:asciiname":"Ouirgane",
    "gn:country_code":"MA",
    "gn:dem":906,
    "gn:feature_class":"P",
    "gn:feature_code":"PPL",
    "gn:name":"Ouirgane",
    "gn:population":0,
    "gn:timezone":"Africa/Casablanca",
    "iso:country":"MA",
    "name:und_x_variant":[
        "Ouirg\u00e2n",
        "Ouirgane"
    ],
    "wof:name":"Ouirgane",
    "wof:placetype":"locality"
},
  "geometry": {"coordinates":[-8.07329,31.17766],"type":"Point"}
}