{
  "type": "Feature",
  "properties": {
    "gn:admin1_code":"07",
    "gn:admin2_code":"41.0",
    "gn:admin3_code":"704107112.0",
    "gn:asciiname":"Ouirgane",
    "gn:country_code":"MA",
    "gn:dem":906,
    "gn:feature_class":"P",
    "gn:feature_code":"PPL",
    "gn:name":"Ouirgane",
    "gn:population":0,
    "gn:timezone":"Africa/Casablanca",
    "iso:country":"MA",
    "name:ara_x_preferred":[
        "\u0648\u064a\u0631\u0643\u0627\u0646"
    ],
    "name:azb_x_preferred":[
        "\u0648\u06cc\u0631\u06a9\u0627\u0646"
    ],
    "name:cat_x_preferred":[
        "Ouirgane"
    ],
    "name:deu_x_preferred":[
        "Ouirgane"
    ],
    "name:fas_x_preferred":[
        "\u0648\u06cc\u0631\u06a9\u0627\u0646"
    ],
    "name:fra_x_preferred":[
        "Ouirgane"
    ],
    "name:ita_x_preferred":[
        "Ouirgane"
    ],
    "name:por_x_preferred":[
        "Ouirgane"
    ],
    "name:und_x_variant":[
        "Ouirg\u00e2n"
    ],
    "name:urd_x_preferred":[
        "\u0648\u06cc\u0631\u06af\u0627\u0646"
    ],
    "wof:name":"Ouirgane",
    "wof:placetype":"locality"
},
  "geometry": {"coordinates":[-8.07329,31.17766],"type":"Point"}
}