{
  "type": "Feature",
  "properties": {
    "gn:admin1_code":"7.0",
    "gn:asciiname":"Rbaat Ben Najma",
    "gn:country_code":"MA",
    "gn:dem":172,
    "gn:feature_class":"P",
    "gn:feature_code":"PPL",
    "gn:name":"Rbaat Ben Najma",
    "gn:population":0,
    "gn:timezone":"Africa/Casablanca",
    "iso:country":"MA",
    "wof:name":"Rbaat Ben Najma",
    "wof:placetype":"locality"
},
  "geometry": {"coordinates":[-9.21736,32.06251],"type":"Point"}
}