{
  "type": "Feature",
  "properties": {
    "gn:admin1_code":"03",
    "gn:asciiname":"Bou Saad",
    "gn:country_code":"MA",
    "gn:dem":1125,
    "gn:feature_class":"P",
    "gn:feature_code":"PPL",
    "gn:name":"Bou Saad",
    "gn:population":0,
    "gn:timezone":"Africa/Casablanca",
    "iso:country":"MA",
    "wof:name":"Bou Saad",
    "wof:placetype":"locality"
},
  "geometry": {"coordinates":[-3.9226,33.86179],"type":"Point"}
}