{
  "type": "Feature",
  "properties": {
    "gn:gn_country":"MA",
    "gn:gn_fcode":"ADM3",
    "gn:gn_pop":4001,
    "gn:population":4001,
    "iso:country":"MA",
    "name:ara_x_preferred":[
        "\u0632\u0627\u0648\u064a\u0629 \u0633\u064a\u062f\u064a \u0642\u0627\u0633\u0645"
    ],
    "name:fra_x_preferred":[
        "Imouzzer Marmoucha"
    ],
    "name:fra_x_variant":[
        "Imouzzer Marmoucha (MU)",
        "Imouzzer Marmoucha (Commune Urbaine)"
    ],
    "qs_pg:aaroncc":"MA",
    "qs_pg:gn_country":"MA",
    "qs_pg:gn_fcode":"ADM3",
    "qs_pg:gn_pop":4001,
    "qs_pg:name":"Imouzzer Marmoucha",
    "qs_pg:photos_9r":0,
    "qs_pg:photos_sr":0,
    "qs_pg:pop_sr":4,
    "qs_pg:qs_pg_placetype":"localadmin",
    "wof:name":"Imouzzer Marmoucha",
    "wof:placetype":"localadmin",
    "wof:population":4001
},
  "geometry": {"coordinates":[-4.29501,33.46277],"type":"Point"}
}