{
  "type": "Feature",
  "properties": {
    "gn:admin1_code":"03",
    "gn:asciiname":"Etmaialt",
    "gn:country_code":"MA",
    "gn:dem":893,
    "gn:feature_class":"P",
    "gn:feature_code":"PPL",
    "gn:name":"Etmaialt",
    "gn:population":0,
    "gn:timezone":"Africa/Casablanca",
    "iso:country":"MA",
    "name:und_x_variant":[
        "Tema\u00eflt"
    ],
    "wof:name":"Etmaialt",
    "wof:placetype":"locality"
},
  "geometry": {"coordinates":[-4.31432,34.71054],"type":"Point"}
}