{
  "type": "Feature",
  "properties": {
    "gn:admin1_code":"08",
    "gn:asciiname":"Tizilit",
    "gn:country_code":"MA",
    "gn:dem":1295,
    "gn:feature_class":"P",
    "gn:feature_code":"PPL",
    "gn:name":"Tizilit",
    "gn:population":0,
    "gn:timezone":"Africa/Casablanca",
    "iso:country":"MA",
    "name:und_x_variant":[
        "Tizilita",
        "Tizilit"
    ],
    "wof:name":"Tizilit",
    "wof:placetype":"locality"
},
  "geometry": {"coordinates":[-5.69047,31.01451],"type":"Point"}
}