{
  "type": "Feature",
  "properties": {
    "gn:admin1_code":"9.0",
    "gn:asciiname":"Agadir Imaizene",
    "gn:country_code":"MA",
    "gn:dem":606,
    "gn:feature_class":"P",
    "gn:feature_code":"PPL",
    "gn:name":"Agadir Imaizene",
    "gn:population":0,
    "gn:timezone":"Africa/Casablanca",
    "iso:country":"MA",
    "wof:name":"Agadir Imaizene",
    "wof:placetype":"locality"
},
  "geometry": {"coordinates":[-9.10958,30.10364],"type":"Point"}
}