{
  "type": "Feature",
  "properties": {
    "gn:admin1_code":"9.0",
    "gn:asciiname":"Tajgaline",
    "gn:country_code":"MA",
    "gn:dem":603,
    "gn:feature_class":"P",
    "gn:feature_code":"PPL",
    "gn:name":"Tajgaline",
    "gn:population":0,
    "gn:timezone":"Africa/Casablanca",
    "iso:country":"MA",
    "wof:name":"Tajgaline",
    "wof:placetype":"locality"
},
  "geometry": {"coordinates":[-9.24672,30.62906],"type":"Point"}
}