{
  "type": "Feature",
  "properties": {
    "gn:admin1_code":"01",
    "gn:asciiname":"Roueda",
    "gn:country_code":"MA",
    "gn:dem":235,
    "gn:feature_class":"P",
    "gn:feature_code":"PPL",
    "gn:name":"Roueda",
    "gn:population":0,
    "gn:timezone":"Africa/Casablanca",
    "iso:country":"MA",
    "wof:name":"Roueda",
    "wof:placetype":"locality"
},
  "geometry": {"coordinates":[-5.47366,35.01485],"type":"Point"}
}