{
  "type": "Feature",
  "properties": {
    "gn:admin1_code":"9.0",
    "gn:asciiname":"Agourgounane",
    "gn:country_code":"MA",
    "gn:dem":1031,
    "gn:feature_class":"P",
    "gn:feature_code":"PPL",
    "gn:name":"Agourgounane",
    "gn:population":0,
    "gn:timezone":"Africa/Casablanca",
    "iso:country":"MA",
    "wof:name":"Agourgounane",
    "wof:placetype":"locality"
},
  "geometry": {"coordinates":[-9.01054,30.03064],"type":"Point"}
}