{
  "type": "Feature",
  "properties": {
    "gn:admin1_code":"5.0",
    "gn:asciiname":"Ighir Nwaza",
    "gn:country_code":"MA",
    "gn:dem":1465,
    "gn:feature_class":"P",
    "gn:feature_code":"PPL",
    "gn:name":"Ighir Nwaza",
    "gn:population":0,
    "gn:timezone":"Africa/Casablanca",
    "iso:country":"MA",
    "wof:name":"Ighir Nwaza",
    "wof:placetype":"locality"
},
  "geometry": {"coordinates":[-6.54508,32.07171],"type":"Point"}
}