{
  "type": "Feature",
  "properties": {
    "gn:admin1_code":"09",
    "gn:asciiname":"Agrd Wwalous",
    "gn:country_code":"MA",
    "gn:dem":1246,
    "gn:feature_class":"P",
    "gn:feature_code":"PPL",
    "gn:name":"Agrd Wwalous",
    "gn:population":0,
    "gn:timezone":"Africa/Casablanca",
    "iso:country":"MA",
    "name:und_x_variant":[
        "Aguerd Oualouss",
        "Aguerd Oualouz",
        "Agrd Wwalous"
    ],
    "wof:name":"Agrd Wwalous",
    "wof:placetype":"locality"
},
  "geometry": {"coordinates":[-9.23731,29.5407],"type":"Point"}
}