{
  "type": "Feature",
  "properties": {
    "gn:admin1_code":"5.0",
    "gn:asciiname":"Ayt Yidir",
    "gn:country_code":"MA",
    "gn:dem":1224,
    "gn:feature_class":"P",
    "gn:feature_code":"PPL",
    "gn:name":"Ayt Yidir",
    "gn:population":0,
    "gn:timezone":"Africa/Casablanca",
    "iso:country":"MA",
    "wof:name":"Ayt Yidir",
    "wof:placetype":"locality"
},
  "geometry": {"coordinates":[-6.66822,32.00077],"type":"Point"}
}