{
  "type": "Feature",
  "properties": {
    "gn:admin1_code":"04",
    "gn:asciiname":"Baabcha",
    "gn:country_code":"MA",
    "gn:dem":32,
    "gn:feature_class":"P",
    "gn:feature_code":"PPL",
    "gn:name":"Baabcha",
    "gn:population":0,
    "gn:timezone":"Africa/Casablanca",
    "iso:country":"MA",
    "name:und_x_variant":[
        "El Bahabicha",
        "Dar el Ba\u00e2bcha",
        "Douar Ba\u00e2bcha",
        "Baabcha"
    ],
    "wof:name":"Baabcha",
    "wof:placetype":"locality"
},
  "geometry": {"coordinates":[-6.00148,34.65401],"type":"Point"}
}