{
  "type": "Feature",
  "properties": {
    "gn:admin1_code":"01",
    "gn:asciiname":"Douar Mlalleh",
    "gn:country_code":"MA",
    "gn:dem":337,
    "gn:feature_class":"P",
    "gn:feature_code":"PPL",
    "gn:name":"Douar Mlalleh",
    "gn:population":0,
    "gn:timezone":"Africa/Casablanca",
    "iso:country":"MA",
    "name:und_x_variant":[
        "Mlalah"
    ],
    "wof:name":"Douar Mlalleh",
    "wof:placetype":"locality"
},
  "geometry": {"coordinates":[-5.54919,35.72737],"type":"Point"}
}