{
  "type": "Feature",
  "properties": {
    "gn:admin1_code":"7.0",
    "gn:asciiname":"Ineflas",
    "gn:country_code":"MA",
    "gn:dem":336,
    "gn:feature_class":"P",
    "gn:feature_code":"PPL",
    "gn:name":"Ineflas",
    "gn:population":0,
    "gn:timezone":"Africa/Casablanca",
    "iso:country":"MA",
    "wof:name":"Ineflas",
    "wof:placetype":"locality"
},
  "geometry": {"coordinates":[-9.71316,31.19436],"type":"Point"}
}