{
  "type": "Feature",
  "properties": {
    "gn:admin1_code":"09",
    "gn:asciiname":"Ait Rehal",
    "gn:country_code":"MA",
    "gn:dem":557,
    "gn:feature_class":"P",
    "gn:feature_code":"PPL",
    "gn:name":"A\u00eft Rehal",
    "gn:population":0,
    "gn:timezone":"Africa/Casablanca",
    "iso:country":"MA",
    "name:und_x_variant":[
        "Zaouia A\u00eft Rabal",
        "A\u00eft-Rahhal",
        "A\u00eft Rehal"
    ],
    "wof:name":"Ait Rehal",
    "wof:placetype":"locality"
},
  "geometry": {"coordinates":[-8.2626,29.43834],"type":"Point"}
}