{
  "type": "Feature",
  "properties": {
    "gn:admin1_code":"09",
    "gn:asciiname":"Aguerd Imelal",
    "gn:country_code":"MA",
    "gn:dem":1118,
    "gn:feature_class":"P",
    "gn:feature_code":"PPL",
    "gn:name":"Aguerd Imelal",
    "gn:population":0,
    "gn:timezone":"Africa/Casablanca",
    "iso:country":"MA",
    "wof:name":"Aguerd Imelal",
    "wof:placetype":"locality"
},
  "geometry": {"coordinates":[-8.82876,29.50821],"type":"Point"}
}