{
  "type": "Feature",
  "properties": {
    "gn:admin1_code":"07",
    "gn:asciiname":"El Raba",
    "gn:country_code":"MA",
    "gn:dem":400,
    "gn:feature_class":"P",
    "gn:feature_code":"PPL",
    "gn:name":"El Raba",
    "gn:population":0,
    "gn:timezone":"Africa/Casablanca",
    "iso:country":"MA",
    "name:und_x_variant":[
        "Al Ghaba",
        "El Raba"
    ],
    "wof:name":"El Raba",
    "wof:placetype":"locality"
},
  "geometry": {"coordinates":[-9.13696,31.56164],"type":"Point"}
}