{
  "type": "Feature",
  "properties": {
    "gn:admin1_code":"08",
    "gn:asciiname":"Marouf",
    "gn:country_code":"MA",
    "gn:dem":1665,
    "gn:feature_class":"P",
    "gn:feature_code":"PPL",
    "gn:name":"Marouf",
    "gn:population":0,
    "gn:timezone":"Africa/Casablanca",
    "iso:country":"MA",
    "name:und_x_variant":[
        "Maarouf"
    ],
    "wof:name":"Marouf",
    "wof:placetype":"locality"
},
  "geometry": {"coordinates":[-7.15247,31.2395],"type":"Point"}
}