{
  "type": "Feature",
  "properties": {
    "gn:admin1_code":"1.0",
    "gn:asciiname":"Souihla",
    "gn:country_code":"MA",
    "gn:dem":25,
    "gn:feature_class":"P",
    "gn:feature_code":"PPL",
    "gn:name":"Souihla",
    "gn:population":0,
    "gn:timezone":"Africa/Casablanca",
    "iso:country":"MA",
    "name:por_x_preferred":[
        "Souihla"
    ],
    "wof:name":"Souihla",
    "wof:placetype":"locality"
},
  "geometry": {"coordinates":[-5.58303,35.82697],"type":"Point"}
}