{
  "type": "Feature",
  "properties": {
    "gn:admin1_code":"9.0",
    "gn:asciiname":"Akhferga",
    "gn:country_code":"MA",
    "gn:dem":1625,
    "gn:feature_class":"P",
    "gn:feature_code":"PPL",
    "gn:name":"Akhferga",
    "gn:population":0,
    "gn:timezone":"Africa/Casablanca",
    "iso:country":"MA",
    "wof:name":"Akhferga",
    "wof:placetype":"locality"
},
  "geometry": {"coordinates":[-8.83225,30.87289],"type":"Point"}
}