{
  "type": "Feature",
  "properties": {
    "gn:admin1_code":"5.0",
    "gn:asciiname":"Sidi Moulay Hsayn",
    "gn:country_code":"MA",
    "gn:dem":852,
    "gn:feature_class":"P",
    "gn:feature_code":"PPL",
    "gn:name":"Sidi Moulay Hsayn",
    "gn:population":0,
    "gn:timezone":"Africa/Casablanca",
    "iso:country":"MA",
    "wof:name":"Sidi Moulay Hsayn",
    "wof:placetype":"locality"
},
  "geometry": {"coordinates":[-7.13519,31.72913],"type":"Point"}
}