{
  "type": "Feature",
  "properties": {
    "gn:admin1_code":"3.0",
    "gn:asciiname":"Oulad Tayeb Hammou",
    "gn:country_code":"MA",
    "gn:dem":949,
    "gn:feature_class":"P",
    "gn:feature_code":"PPL",
    "gn:name":"Oulad Tayeb Hammou",
    "gn:population":0,
    "gn:timezone":"Africa/Casablanca",
    "iso:country":"MA",
    "wof:name":"Oulad Tayeb Hammou",
    "wof:placetype":"locality"
},
  "geometry": {"coordinates":[-4.52316,33.85863],"type":"Point"}
}