{
  "type": "Feature",
  "properties": {
    "gn:admin1_code":"05",
    "gn:asciiname":"Douar Oulad Soltane",
    "gn:country_code":"MA",
    "gn:dem":370,
    "gn:feature_class":"P",
    "gn:feature_code":"PPL",
    "gn:name":"Douar Oulad Soltane",
    "gn:population":0,
    "gn:timezone":"Africa/Casablanca",
    "iso:country":"MA",
    "name:und_x_variant":[
        "Oulad Soltane",
        "Douar Oulad Soltane"
    ],
    "wof:name":"Douar Oulad Soltane",
    "wof:placetype":"locality"
},
  "geometry": {"coordinates":[-6.9481,32.30012],"type":"Point"}
}