{
  "type": "Feature",
  "properties": {
    "gn:admin1_code":"03",
    "gn:asciiname":"Al Mizah",
    "gn:country_code":"MA",
    "gn:dem":739,
    "gn:feature_class":"P",
    "gn:feature_code":"PPL",
    "gn:name":"Al Mizah",
    "gn:population":0,
    "gn:timezone":"Africa/Casablanca",
    "iso:country":"MA",
    "wof:name":"Al Mizah",
    "wof:placetype":"locality"
},
  "geometry": {"coordinates":[-4.66821,34.63919],"type":"Point"}
}