{
  "type": "Feature",
  "properties": {
    "gn:admin1_code":"09",
    "gn:asciiname":"Ait Ms'oud",
    "gn:country_code":"MA",
    "gn:dem":946,
    "gn:feature_class":"P",
    "gn:feature_code":"PPL",
    "gn:name":"A\u00eft Ms\u2019oud",
    "gn:population":0,
    "gn:timezone":"Africa/Casablanca",
    "iso:country":"MA",
    "name:und_x_variant":[
        "A\u00eft Ms\u2019oud",
        "A\u00eft Messaoud"
    ],
    "wof:name":"Ait Ms'oud",
    "wof:placetype":"locality"
},
  "geometry": {"coordinates":[-9.22298,29.67196],"type":"Point"}
}