{
  "type": "Feature",
  "properties": {
    "gn:admin1_code":"6.0",
    "gn:asciiname":"Douar El Haj Brahim",
    "gn:country_code":"MA",
    "gn:dem":185,
    "gn:feature_class":"P",
    "gn:feature_code":"PPL",
    "gn:name":"Douar El Haj Brahim",
    "gn:population":0,
    "gn:timezone":"Africa/Casablanca",
    "iso:country":"MA",
    "wof:name":"Douar El Haj Brahim",
    "wof:placetype":"locality"
},
  "geometry": {"coordinates":[-8.56224,32.6098],"type":"Point"}
}