{
  "type": "Feature",
  "properties": {
    "gn:admin1_code":"08",
    "gn:asciiname":"Sidi Larbi",
    "gn:country_code":"MA",
    "gn:dem":1460,
    "gn:feature_class":"P",
    "gn:feature_code":"PPL",
    "gn:name":"Sidi Larbi",
    "gn:population":0,
    "gn:timezone":"Africa/Casablanca",
    "iso:country":"MA",
    "wof:name":"Sidi Larbi",
    "wof:placetype":"locality"
},
  "geometry": {"coordinates":[-7.26,30.51],"type":"Point"}
}