{
  "type": "Feature",
  "properties": {
    "gn:admin1_code":"09",
    "gn:asciiname":"Anzgarn",
    "gn:country_code":"MA",
    "gn:dem":1178,
    "gn:feature_class":"P",
    "gn:feature_code":"PPL",
    "gn:name":"Anzgarn",
    "gn:population":0,
    "gn:timezone":"Africa/Casablanca",
    "iso:country":"MA",
    "name:und_x_variant":[
        "Ainzgarne",
        "Anzgarn",
        "Anzegarn"
    ],
    "wof:name":"Anzgarn",
    "wof:placetype":"locality"
},
  "geometry": {"coordinates":[-9.1386,29.82892],"type":"Point"}
}