{
  "type": "Feature",
  "properties": {
    "gn:admin1_code":"6.0",
    "gn:asciiname":"Sidi Jalali ben Bou'azza",
    "gn:country_code":"MA",
    "gn:dem":159,
    "gn:feature_class":"P",
    "gn:feature_code":"PPL",
    "gn:name":"Sidi Jalali ben Bou\u2019azza",
    "gn:population":0,
    "gn:timezone":"Africa/Casablanca",
    "iso:country":"MA",
    "wof:name":"Sidi Jalali ben Bou'azza",
    "wof:placetype":"locality"
},
  "geometry": {"coordinates":[-8.16108,32.88003],"type":"Point"}
}