{
  "type": "Feature",
  "properties": {
    "gn:admin1_code":"1.0",
    "gn:asciiname":"Imzourene",
    "gn:country_code":"MA",
    "gn:dem":517,
    "gn:feature_class":"P",
    "gn:feature_code":"PPL",
    "gn:name":"Imzourene",
    "gn:population":0,
    "gn:timezone":"Africa/Casablanca",
    "iso:country":"MA",
    "wof:name":"Imzourene",
    "wof:placetype":"locality"
},
  "geometry": {"coordinates":[-5.18829,35.47522],"type":"Point"}
}