{
  "type": "Feature",
  "properties": {
    "gn:admin1_code":"09",
    "gn:asciiname":"Ait Slimane",
    "gn:country_code":"MA",
    "gn:dem":870,
    "gn:feature_class":"P",
    "gn:feature_code":"PPL",
    "gn:name":"A\u00eft Slimane",
    "gn:population":0,
    "gn:timezone":"Africa/Casablanca",
    "iso:country":"MA",
    "wof:name":"Ait Slimane",
    "wof:placetype":"locality"
},
  "geometry": {"coordinates":[-8.27287,30.7571],"type":"Point"}
}