{
  "type": "Feature",
  "properties": {
    "gn:admin1_code":"01",
    "gn:asciiname":"Asahadene",
    "gn:country_code":"MA",
    "gn:dem":736,
    "gn:feature_class":"P",
    "gn:feature_code":"PPL",
    "gn:name":"Asahadene",
    "gn:population":0,
    "gn:timezone":"Africa/Casablanca",
    "iso:country":"MA",
    "wof:name":"Asahadene",
    "wof:placetype":"locality"
},
  "geometry": {"coordinates":[-5.37719,35.20775],"type":"Point"}
}