{
  "type": "Feature",
  "properties": {
    "gn:gn_country":"MA",
    "gn:gn_fcode":"ADM3",
    "gn:gn_pop":18542,
    "gn:population":20811,
    "iso:country":"MA",
    "name:ara_x_preferred":[
        "\u0627\u0644\u0633\u0648\u0627\u0643\u0646"
    ],
    "name:fra_x_preferred":[
        "Bni Mansour"
    ],
    "name:fra_x_variant":[
        "Bni Mansour (CR)",
        "Bni Mansour (Commune Rurale)"
    ],
    "qs_pg:aaroncc":"MA",
    "qs_pg:gn_country":"MA",
    "qs_pg:gn_fcode":"ADM3",
    "qs_pg:gn_pop":18542,
    "qs_pg:name":"Bni Mansour",
    "qs_pg:photos_9r":0,
    "qs_pg:photos_sr":0,
    "qs_pg:pop_sr":6,
    "qs_pg:qs_pg_placetype":"localadmin",
    "wof:name":"Bni Mansour",
    "wof:placetype":"localadmin",
    "wof:population":20811
},
  "geometry": {"coordinates":[-4.91004,35.15152],"type":"Point"}
}