{
  "type": "Feature",
  "properties": {
    "gn:admin1_code":"01",
    "gn:asciiname":"Haouta",
    "gn:country_code":"MA",
    "gn:dem":1117,
    "gn:feature_class":"P",
    "gn:feature_code":"PPL",
    "gn:name":"Haouta",
    "gn:population":0,
    "gn:timezone":"Africa/Casablanca",
    "iso:country":"MA",
    "wof:name":"Haouta",
    "wof:placetype":"locality"
},
  "geometry": {"coordinates":[-5.13508,35.0713],"type":"Point"}
}