{
  "type": "Feature",
  "properties": {
    "gn:admin1_code":"01",
    "gn:asciiname":"Beni Bou Smour",
    "gn:country_code":"MA",
    "gn:dem":966,
    "gn:feature_class":"P",
    "gn:feature_code":"PPL",
    "gn:name":"Beni Bou Smour",
    "gn:population":0,
    "gn:timezone":"Africa/Casablanca",
    "iso:country":"MA",
    "name:und_x_variant":[
        "Bani Bouzemour",
        "Beni Bou Smour"
    ],
    "wof:name":"Beni Bou Smour",
    "wof:placetype":"locality"
},
  "geometry": {"coordinates":[-4.20442,34.94453],"type":"Point"}
}