{
  "type": "Feature",
  "properties": {
    "gn:gn_country":"MA",
    "gn:gn_fcode":"ADM3",
    "gn:gn_pop":22889,
    "gn:population":22889,
    "iso:country":"MA",
    "name:ara_x_preferred":[
        "\u0632\u0643\u0632\u0644"
    ],
    "name:fra_x_preferred":[
        "Sidi Sliman Echchara"
    ],
    "name:fra_x_variant":[
        "Sidi Sliman Echchara (MU)",
        "Sidi Sliman Echchara (Commune Urbaine)"
    ],
    "qs_pg:aaroncc":"MA",
    "qs_pg:gn_country":"MA",
    "qs_pg:gn_fcode":"ADM3",
    "qs_pg:gn_pop":22889,
    "qs_pg:name":"Sidi Sliman Echchara",
    "qs_pg:photos_9r":0,
    "qs_pg:photos_sr":0,
    "qs_pg:pop_sr":7,
    "qs_pg:qs_pg_placetype":"localadmin",
    "wof:name":"Sidi Sliman Echchara",
    "wof:placetype":"localadmin",
    "wof:population":22889
},
  "geometry": {"coordinates":[-2.36215,34.9097],"type":"Point"}
}