{
  "type": "Feature",
  "properties": {
    "gn:admin1_code":"08",
    "gn:asciiname":"Tarhoulit",
    "gn:country_code":"MA",
    "gn:dem":789,
    "gn:feature_class":"P",
    "gn:feature_code":"PPL",
    "gn:name":"Tarhoulit",
    "gn:population":0,
    "gn:timezone":"Africa/Casablanca",
    "iso:country":"MA",
    "wof:name":"Tarhoulit",
    "wof:placetype":"locality"
},
  "geometry": {"coordinates":[-5.33012,30.622],"type":"Point"}
}