{
  "type": "Feature",
  "properties": {
    "gn:admin1_code":"9.0",
    "gn:asciiname":"Irhirane",
    "gn:country_code":"MA",
    "gn:dem":926,
    "gn:feature_class":"P",
    "gn:feature_code":"PPL",
    "gn:name":"Irhirane",
    "gn:population":0,
    "gn:timezone":"Africa/Casablanca",
    "iso:country":"MA",
    "wof:name":"Irhirane",
    "wof:placetype":"locality"
},
  "geometry": {"coordinates":[-8.7674,30.27839],"type":"Point"}
}