{
  "type": "Feature",
  "properties": {
    "gn:admin1_code":"1.0",
    "gn:asciiname":"Douar Eddouamer",
    "gn:country_code":"MA",
    "gn:dem":45,
    "gn:feature_class":"P",
    "gn:feature_code":"PPL",
    "gn:name":"Douar Eddouamer",
    "gn:population":0,
    "gn:timezone":"Africa/Casablanca",
    "iso:country":"MA",
    "wof:name":"Douar Eddouamer",
    "wof:placetype":"locality"
},
  "geometry": {"coordinates":[-5.88395,34.96903],"type":"Point"}
}