{
  "type": "Feature",
  "properties": {
    "gn:admin1_code":"7.0",
    "gn:asciiname":"Rbaat Hammou",
    "gn:country_code":"MA",
    "gn:dem":343,
    "gn:feature_class":"P",
    "gn:feature_code":"PPL",
    "gn:name":"Rbaat Hammou",
    "gn:population":0,
    "gn:timezone":"Africa/Casablanca",
    "iso:country":"MA",
    "wof:name":"Rbaat Hammou",
    "wof:placetype":"locality"
},
  "geometry": {"coordinates":[-8.82124,31.92282],"type":"Point"}
}