{
  "type": "Feature",
  "properties": {
    "gn:admin1_code":"10.0",
    "gn:asciiname":"Ben Iddar",
    "gn:country_code":"MA",
    "gn:dem":435,
    "gn:feature_class":"P",
    "gn:feature_code":"PPL",
    "gn:name":"Ben Iddar",
    "gn:population":0,
    "gn:timezone":"Africa/Casablanca",
    "iso:country":"MA",
    "wof:name":"Ben Iddar",
    "wof:placetype":"locality"
},
  "geometry": {"coordinates":[-9.94693,29.31049],"type":"Point"}
}