{
  "type": "Feature",
  "properties": {
    "gn:admin1_code":"2.0",
    "gn:asciiname":"Douar Yat Lhadi",
    "gn:country_code":"MA",
    "gn:dem":74,
    "gn:feature_class":"P",
    "gn:feature_code":"PPL",
    "gn:name":"Douar Yat Lhadi",
    "gn:population":0,
    "gn:timezone":"Africa/Casablanca",
    "iso:country":"MA",
    "wof:name":"Douar Yat Lhadi",
    "wof:placetype":"locality"
},
  "geometry": {"coordinates":[-2.58937,35.07925],"type":"Point"}
}