{
  "type": "Feature",
  "properties": {
    "gn:admin1_code":"03",
    "gn:asciiname":"Douar Oulad El Maati",
    "gn:country_code":"MA",
    "gn:dem":169,
    "gn:feature_class":"P",
    "gn:feature_code":"PPL",
    "gn:name":"Douar Oulad El Maati",
    "gn:population":0,
    "gn:timezone":"Africa/Casablanca",
    "iso:country":"MA",
    "name:und_x_variant":[
        "Oulad Ma\u00e2ti",
        "Oulad el Maati",
        "Douar Oulad El Maati"
    ],
    "wof:name":"Douar Oulad El Maati",
    "wof:placetype":"locality"
},
  "geometry": {"coordinates":[-5.25386,34.34708],"type":"Point"}
}