{
  "type": "Feature",
  "properties": {
    "gn:country":"MA",
    "gn:fcode":"ADM3",
    "gn:pop":7480,
    "iso:country":"MA",
    "name:ara_x_preferred":[
        "\u062a\u0627\u0633\u0631\u064a\u0631\u062a"
    ],
    "name:fra_x_preferred":[
        "Arbaa Rasmouka"
    ],
    "name:fra_x_variant":[
        "Arbaa Rasmouka (CR)",
        "Arbaa Rasmouka (Commune Rurale)"
    ],
    "qs:name":"Arbaa Rasmouka",
    "qs:photos_9r":0,
    "qs:photos_sr":0,
    "qs:pop_sr":"5",
    "wd:wordcount":80,
    "wof:name":"Arbaa Rasmouka",
    "wof:placetype":"localadmin",
    "wof:population":7480
},
  "geometry": {"coordinates":[-9.52283,29.80265],"type":"Point"}
}