{
  "type": "Feature",
  "properties": {
    "gn:country":"MA",
    "gn:fcode":"ADM3",
    "gn:population":7480,
    "iso:country":"MA",
    "name:ara_x_preferred":[
        "\u062a\u0627\u0633\u0631\u064a\u0631\u062a"
    ],
    "name:ara_x_variant":[
        "\u0623\u0631\u0628\u0639\u0627\u0621 \u0631\u0633\u0645\u0648\u0643\u0629"
    ],
    "name:ary_x_preferred":[
        "\u0623\u0631\u0628\u0639\u0627\u0621 \u0631\u0633\u0645\u0648\u0643\u0629"
    ],
    "name:cat_x_preferred":[
        "Arbaa Rasmouka"
    ],
    "name:ceb_x_preferred":[
        "Arbaa Rasmouka"
    ],
    "name:eng_x_preferred":[
        "Arbaa Rasmouka"
    ],
    "name:fra_x_preferred":[
        "Arbaa Rasmouka"
    ],
    "name:fra_x_variant":[
        "Arbaa Rasmouka (CR)",
        "Arbaa Rasmouka (Commune Rurale)"
    ],
    "name:ita_x_preferred":[
        "Arbaa Rasmouka"
    ],
    "name:swe_x_preferred":[
        "Arbaa Rasmouka"
    ],
    "qs:name":"Arbaa Rasmouka",
    "qs:photos_9r":0,
    "qs:photos_sr":0,
    "qs:pop_sr":"5",
    "wd:wordcount":80,
    "wof:name":"Arbaa Rasmouka",
    "wof:placetype":"localadmin",
    "wof:population":7480
},
  "geometry": {"coordinates":[-9.52283,29.80265],"type":"Point"}
}