{
  "type": "Feature",
  "properties": {
    "gn:admin1_code":"5.0",
    "gn:asciiname":"Mers Ait Kedada",
    "gn:country_code":"MA",
    "gn:dem":523,
    "gn:feature_class":"P",
    "gn:feature_code":"PPL",
    "gn:name":"Mers A\u00eft Kedada",
    "gn:population":0,
    "gn:timezone":"Africa/Casablanca",
    "iso:country":"MA",
    "wof:name":"Mers Ait Kedada",
    "wof:placetype":"locality"
},
  "geometry": {"coordinates":[-6.22184,32.61405],"type":"Point"}
}