{
  "type": "Feature",
  "properties": {
    "gn:admin1_code":"09",
    "gn:asciiname":"Tagdicht",
    "gn:country_code":"MA",
    "gn:dem":1754,
    "gn:feature_class":"P",
    "gn:feature_code":"PPL",
    "gn:name":"Tagdicht",
    "gn:population":0,
    "gn:timezone":"Africa/Casablanca",
    "iso:country":"MA",
    "name:und_x_variant":[
        "Tagoudicht"
    ],
    "wof:name":"Tagdicht",
    "wof:placetype":"locality"
},
  "geometry": {"coordinates":[-8.3035,30.10242],"type":"Point"}
}