{
  "type": "Feature",
  "properties": {
    "gn:admin1_code":"7.0",
    "gn:asciiname":"Douar Id Ou Mouajeauc",
    "gn:country_code":"MA",
    "gn:dem":367,
    "gn:feature_class":"P",
    "gn:feature_code":"PPL",
    "gn:name":"Douar Id Ou Mouajeauc",
    "gn:population":0,
    "gn:timezone":"Africa/Casablanca",
    "iso:country":"MA",
    "wof:name":"Douar Id Ou Mouajeauc",
    "wof:placetype":"locality"
},
  "geometry": {"coordinates":[-9.63949,31.11925],"type":"Point"}
}