{
  "type": "Feature",
  "properties": {
    "gn:admin1_code":"09",
    "gn:asciiname":"Agadir",
    "gn:country_code":"MA",
    "gn:dem":981,
    "gn:feature_class":"P",
    "gn:feature_code":"PPL",
    "gn:name":"Agadir",
    "gn:population":0,
    "gn:timezone":"Africa/Casablanca",
    "iso:country":"MA",
    "wof:name":"Agadir",
    "wof:placetype":"locality"
},
  "geometry": {"coordinates":[-7.9478,30.69457],"type":"Point"}
}