{
  "type": "Feature",
  "properties": {
    "gn:admin1_code":"08",
    "gn:asciiname":"Bougma",
    "gn:country_code":"MA",
    "gn:dem":1381,
    "gn:feature_class":"P",
    "gn:feature_code":"PPL",
    "gn:name":"Bougma",
    "gn:population":0,
    "gn:timezone":"Africa/Casablanca",
    "iso:country":"MA",
    "wof:name":"Bougma",
    "wof:placetype":"locality"
},
  "geometry": {"coordinates":[-4.55154,32.7041],"type":"Point"}
}