{
  "type": "Feature",
  "properties": {
    "gn:admin1_code":"1.0",
    "gn:asciiname":"Douar Aidene",
    "gn:country_code":"MA",
    "gn:dem":1036,
    "gn:feature_class":"P",
    "gn:feature_code":"PPL",
    "gn:name":"Douar Aidene",
    "gn:population":0,
    "gn:timezone":"Africa/Casablanca",
    "iso:country":"MA",
    "wof:name":"Douar Aidene",
    "wof:placetype":"locality"
},
  "geometry": {"coordinates":[-4.76319,35.07676],"type":"Point"}
}