{
  "type": "Feature",
  "properties": {
    "gn:country":"MA",
    "gn:fcode":"ADM3",
    "gn:population":20695,
    "iso:country":"MA",
    "name:ara_x_preferred":[
        "\u0627\u0644\u0645\u0646\u0632\u0644 (\u0627\u0644\u0628\u0644\u062f\u064a\u0629)"
    ],
    "name:fra_x_preferred":[
        "Sebaa Rouadi"
    ],
    "name:fra_x_variant":[
        "Sebaa Rouadi (CR)",
        "Sebaa Rouadi (Commune Rurale)"
    ],
    "qs:name":"Sebaa Rouadi",
    "qs:photos_9r":0,
    "qs:photos_sr":0,
    "qs:pop_sr":"7",
    "wof:name":"Sebaa Rouadi",
    "wof:placetype":"localadmin",
    "wof:population":20695
},
  "geometry": {"coordinates":[-5.13625,34.07487],"type":"Point"}
}