{
  "type": "Feature",
  "properties": {
    "gn:admin1_code":"3.0",
    "gn:asciiname":"Dar Ris Said",
    "gn:country_code":"MA",
    "gn:dem":608,
    "gn:feature_class":"P",
    "gn:feature_code":"PPL",
    "gn:name":"Dar Ris Said",
    "gn:population":0,
    "gn:timezone":"Africa/Casablanca",
    "iso:country":"MA",
    "wof:name":"Dar Ris Said",
    "wof:placetype":"locality"
},
  "geometry": {"coordinates":[-5.29558,33.90787],"type":"Point"}
}