{
  "type": "Feature",
  "properties": {
    "gn:admin1_code":"2.0",
    "gn:asciiname":"Douar Hidara",
    "gn:country_code":"MA",
    "gn:dem":56,
    "gn:feature_class":"P",
    "gn:feature_code":"PPL",
    "gn:name":"Douar Hidara",
    "gn:population":0,
    "gn:timezone":"Africa/Casablanca",
    "iso:country":"MA",
    "wof:name":"Douar Hidara",
    "wof:placetype":"locality"
},
  "geometry": {"coordinates":[-2.37786,35.07062],"type":"Point"}
}