{
  "type": "Feature",
  "properties": {
    "gn:admin1_code":"5.0",
    "gn:asciiname":"Tanout ou Ahbar",
    "gn:country_code":"MA",
    "gn:dem":842,
    "gn:feature_class":"P",
    "gn:feature_code":"PPL",
    "gn:name":"Tanout ou Ahbar",
    "gn:population":0,
    "gn:timezone":"Africa/Casablanca",
    "iso:country":"MA",
    "wof:name":"Tanout ou Ahbar",
    "wof:placetype":"locality"
},
  "geometry": {"coordinates":[-5.76347,32.96989],"type":"Point"}
}