{
  "type": "Feature",
  "properties": {
    "gn:admin1_code":"5.0",
    "gn:asciiname":"Ait Khnoucha",
    "gn:country_code":"MA",
    "gn:dem":676,
    "gn:feature_class":"P",
    "gn:feature_code":"PPL",
    "gn:name":"A\u00eft Khnoucha",
    "gn:population":0,
    "gn:timezone":"Africa/Casablanca",
    "iso:country":"MA",
    "wof:name":"Ait Khnoucha",
    "wof:placetype":"locality"
},
  "geometry": {"coordinates":[-6.46741,32.77729],"type":"Point"}
}