{
  "type": "Feature",
  "properties": {
    "gn:admin1_code":"09",
    "gn:asciiname":"Ben Jerrar",
    "gn:country_code":"MA",
    "gn:dem":67,
    "gn:feature_class":"P",
    "gn:feature_code":"PPL",
    "gn:name":"Ben Jerrar",
    "gn:population":0,
    "gn:timezone":"Africa/Casablanca",
    "iso:country":"MA",
    "name:und_x_variant":[
        "Zaouia Ben Jerrar",
        "Ben Jarrar A\u00eft Amira",
        "Ben Jerrar",
        "Ben Jerra"
    ],
    "wof:name":"Ben Jerrar",
    "wof:placetype":"locality"
},
  "geometry": {"coordinates":[-9.50377,30.26224],"type":"Point"}
}