{
  "type": "Feature",
  "properties": {
    "gn:admin1_code":"7.0",
    "gn:asciiname":"Sidi 'Ali ou Moussa",
    "gn:country_code":"MA",
    "gn:dem":1588,
    "gn:feature_class":"P",
    "gn:feature_code":"PPL",
    "gn:name":"Sidi \u2019Ali ou Moussa",
    "gn:population":0,
    "gn:timezone":"Africa/Casablanca",
    "iso:country":"MA",
    "wof:name":"Sidi 'Ali ou Moussa",
    "wof:placetype":"locality"
},
  "geometry": {"coordinates":[-7.31942,31.44025],"type":"Point"}
}