{
  "type": "Feature",
  "properties": {
    "gn:admin1_code":"47.0",
    "gn:asciiname":"Tizaoute",
    "gn:country_code":"MA",
    "gn:dem":1731,
    "gn:feature_class":"P",
    "gn:feature_code":"PPL",
    "gn:name":"Tizaoute",
    "gn:population":0,
    "gn:timezone":"Africa/Casablanca",
    "iso:country":"MA",
    "wof:name":"Tizaoute",
    "wof:placetype":"locality"
},
  "geometry": {"coordinates":[-7.88013,31.2382],"type":"Point"}
}