{
  "type": "Feature",
  "properties": {
    "gn:admin1_code":"5.0",
    "gn:asciiname":"Ifard-n-Ougallid",
    "gn:country_code":"MA",
    "gn:dem":1080,
    "gn:feature_class":"P",
    "gn:feature_code":"PPL",
    "gn:name":"Ifard-n-Ougallid",
    "gn:population":0,
    "gn:timezone":"Africa/Casablanca",
    "iso:country":"MA",
    "wof:name":"Ifard-n-Ougallid",
    "wof:placetype":"locality"
},
  "geometry": {"coordinates":[-6.9185,31.9551],"type":"Point"}
}