{
  "type": "Feature",
  "properties": {
    "gn:admin1_code":"6.0",
    "gn:asciiname":"Ech-Chikdanir",
    "gn:country_code":"MA",
    "gn:dem":422,
    "gn:feature_class":"P",
    "gn:feature_code":"PPL",
    "gn:name":"Ech-Chikdanir",
    "gn:population":0,
    "gn:timezone":"Africa/Casablanca",
    "iso:country":"MA",
    "wof:name":"Ech-Chikdanir",
    "wof:placetype":"locality"
},
  "geometry": {"coordinates":[-7.62725,32.97865],"type":"Point"}
}