{
  "type": "Feature",
  "properties": {
    "gn:admin1_code":"7.0",
    "gn:asciiname":"Douar Znba",
    "gn:country_code":"MA",
    "gn:dem":176,
    "gn:feature_class":"P",
    "gn:feature_code":"PPL",
    "gn:name":"Douar Znba",
    "gn:population":0,
    "gn:timezone":"Africa/Casablanca",
    "iso:country":"MA",
    "wof:name":"Douar Znba",
    "wof:placetype":"locality"
},
  "geometry": {"coordinates":[-9.38619,31.88294],"type":"Point"}
}