{
  "type": "Feature",
  "properties": {
    "gn:admin1_code":"01",
    "gn:asciiname":"Tifouta",
    "gn:country_code":"MA",
    "gn:dem":476,
    "gn:feature_class":"P",
    "gn:feature_code":"PPL",
    "gn:name":"Tifouta",
    "gn:population":0,
    "gn:timezone":"Africa/Casablanca",
    "iso:country":"MA",
    "wof:name":"Tifouta",
    "wof:placetype":"locality"
},
  "geometry": {"coordinates":[-5.27607,34.74108],"type":"Point"}
}