{
  "type": "Feature",
  "properties": {
    "gn:country":"MA",
    "gn:fcode":"ADM3",
    "gn:pop":18399,
    "iso:country":"MA",
    "name:ara_x_preferred":[
        "\u0627\u0628\u0644\u064a\u062f\u0629"
    ],
    "name:fra_x_preferred":[
        "Bni Zoli"
    ],
    "name:fra_x_variant":[
        "Bni Zoli (CR)",
        "Bni Zoli (Commune Rurale)"
    ],
    "qs:name":"Bni Zoli",
    "qs:photos_9r":0,
    "qs:photos_sr":0,
    "qs:pop_sr":"6",
    "wof:name":"Bni Zoli",
    "wof:placetype":"localadmin",
    "wof:population":18399
},
  "geometry": {"coordinates":[-5.85629,30.50465],"type":"Point"}
}