{
  "type": "Feature",
  "properties": {
    "gn:admin1_code":"06",
    "gn:asciiname":"Douar Laatoucha",
    "gn:country_code":"MA",
    "gn:dem":435,
    "gn:feature_class":"P",
    "gn:feature_code":"PPL",
    "gn:name":"Douar Laatoucha",
    "gn:population":0,
    "gn:timezone":"Africa/Casablanca",
    "iso:country":"MA",
    "name:und_x_variant":[
        "Douar el Arech",
        "La\u00e2toucha",
        "Douar Laatocha",
        "Douar Laatoucha",
        "Laatocha"
    ],
    "wof:name":"Douar Laatoucha",
    "wof:placetype":"locality"
},
  "geometry": {"coordinates":[-7.37516,32.57084],"type":"Point"}
}