{
  "type": "Feature",
  "properties": {
    "gn:admin1_code":"05",
    "gn:asciiname":"Bou Abbeb",
    "gn:country_code":"MA",
    "gn:dem":696,
    "gn:feature_class":"P",
    "gn:feature_code":"PPL",
    "gn:name":"Bou Abbeb",
    "gn:population":0,
    "gn:timezone":"Africa/Casablanca",
    "iso:country":"MA",
    "name:und_x_variant":[
        "Bou Abbed",
        "Bou Abbeb"
    ],
    "wof:name":"Bou Abbeb",
    "wof:placetype":"locality"
},
  "geometry": {"coordinates":[-6.22947,32.7741],"type":"Point"}
}