{
  "type": "Feature",
  "properties": {
    "gn:admin1_code":"3.0",
    "gn:asciiname":"Douar Lghozlane",
    "gn:country_code":"MA",
    "gn:dem":379,
    "gn:feature_class":"P",
    "gn:feature_code":"PPL",
    "gn:name":"Douar Lghozlane",
    "gn:population":0,
    "gn:timezone":"Africa/Casablanca",
    "iso:country":"MA",
    "wof:name":"Douar Lghozlane",
    "wof:placetype":"locality"
},
  "geometry": {"coordinates":[-5.06609,34.42228],"type":"Point"}
}