{
  "type": "Feature",
  "properties": {
    "gn:admin1_code":"10",
    "gn:asciiname":"Id Ben Yama",
    "gn:country_code":"MA",
    "gn:dem":315,
    "gn:feature_class":"P",
    "gn:feature_code":"PPL",
    "gn:name":"Id Ben Yama",
    "gn:population":0,
    "gn:timezone":"Africa/Casablanca",
    "iso:country":"MA",
    "wof:name":"Id Ben Yama",
    "wof:placetype":"locality"
},
  "geometry": {"coordinates":[-9.95,29.46],"type":"Point"}
}