{
  "type": "Feature",
  "properties": {
    "gn:admin1_code":"6.0",
    "gn:asciiname":"Oulad Ameur",
    "gn:country_code":"MA",
    "gn:dem":391,
    "gn:feature_class":"P",
    "gn:feature_code":"PPL",
    "gn:name":"Oulad Ameur",
    "gn:population":0,
    "gn:timezone":"Africa/Casablanca",
    "iso:country":"MA",
    "wof:name":"Oulad Ameur",
    "wof:placetype":"locality"
},
  "geometry": {"coordinates":[-7.6337,32.68551],"type":"Point"}
}