{
  "type": "Feature",
  "properties": {
    "gn:admin1_code":"10",
    "gn:asciiname":"Id Abdallah",
    "gn:country_code":"MA",
    "gn:dem":1181,
    "gn:feature_class":"P",
    "gn:feature_code":"PPL",
    "gn:name":"Id Abdallah",
    "gn:population":0,
    "gn:timezone":"Africa/Casablanca",
    "iso:country":"MA",
    "name:und_x_variant":[
        "Id Abdellah",
        "Id Abdallah"
    ],
    "wof:name":"Id Abdallah",
    "wof:placetype":"locality"
},
  "geometry": {"coordinates":[-9.42393,29.40314],"type":"Point"}
}