{
  "type": "Feature",
  "properties": {
    "gn:admin1_code":"6.0",
    "gn:asciiname":"Dhoura",
    "gn:country_code":"MA",
    "gn:dem":555,
    "gn:feature_class":"P",
    "gn:feature_code":"PPLL",
    "gn:name":"Dhoura",
    "gn:population":0,
    "gn:timezone":"Africa/Casablanca",
    "iso:country":"MA",
    "wof:name":"Dhoura",
    "wof:placetype":"locality"
},
  "geometry": {"coordinates":[-7.41548,33.03211],"type":"Point"}
}