{
  "type": "Feature",
  "properties": {
    "gn:admin1_code":"07",
    "gn:asciiname":"Zaouiat Echarradi",
    "gn:country_code":"MA",
    "gn:dem":334,
    "gn:feature_class":"P",
    "gn:feature_code":"PPL",
    "gn:name":"Zaouiat Echarradi",
    "gn:population":0,
    "gn:timezone":"Africa/Casablanca",
    "iso:country":"MA",
    "name:und_x_variant":[
        "Zaouiet-ech-Cherradi"
    ],
    "wof:name":"Zaouiat Echarradi",
    "wof:placetype":"locality"
},
  "geometry": {"coordinates":[-8.31921,31.71414],"type":"Point"}
}