{
  "type": "Feature",
  "properties": {
    "gn:admin1_code":"06",
    "gn:asciiname":"Charqawa",
    "gn:country_code":"MA",
    "gn:dem":269,
    "gn:feature_class":"P",
    "gn:feature_code":"PPL",
    "gn:name":"Charqawa",
    "gn:population":0,
    "gn:timezone":"Africa/Casablanca",
    "iso:country":"MA",
    "name:und_x_variant":[
        "Cherkaoua",
        "Charcaoua",
        "Dar ech Cherkaoua",
        "Charqawa"
    ],
    "wof:name":"Charqawa",
    "wof:placetype":"locality"
},
  "geometry": {"coordinates":[-7.38287,33.25585],"type":"Point"}
}