{
  "type": "Feature",
  "properties": {
    "gn:admin1_code":"3.0",
    "gn:asciiname":"Douar Sanhaja",
    "gn:country_code":"MA",
    "gn:dem":1008,
    "gn:feature_class":"P",
    "gn:feature_code":"PPL",
    "gn:name":"Douar Sanhaja",
    "gn:population":0,
    "gn:timezone":"Africa/Casablanca",
    "iso:country":"MA",
    "wof:name":"Douar Sanhaja",
    "wof:placetype":"locality"
},
  "geometry": {"coordinates":[-4.81409,33.78558],"type":"Point"}
}