{
  "type": "Feature",
  "properties": {
    "gn:admin1_code":"01",
    "gn:asciiname":"Khyam Zaynoune",
    "gn:country_code":"MA",
    "gn:dem":85,
    "gn:feature_class":"P",
    "gn:feature_code":"PPL",
    "gn:name":"Khyam Zaynoune",
    "gn:population":0,
    "gn:timezone":"Africa/Casablanca",
    "iso:country":"MA",
    "name:und_x_variant":[
        "Sraoula",
        "Khiam Za\u00efzoun",
        "Khyam Zaynoune"
    ],
    "wof:name":"Khyam Zaynoune",
    "wof:placetype":"locality"
},
  "geometry": {"coordinates":[-5.87764,35.4297],"type":"Point"}
}