{
  "type": "Feature",
  "properties": {
    "gn:admin1_code":"47.0",
    "gn:asciiname":"Tirliite",
    "gn:country_code":"MA",
    "gn:dem":1182,
    "gn:feature_class":"P",
    "gn:feature_code":"PPL",
    "gn:name":"Tirliite",
    "gn:population":0,
    "gn:timezone":"Africa/Casablanca",
    "iso:country":"MA",
    "wof:name":"Tirliite",
    "wof:placetype":"neighbourhood"
},
  "geometry": {"coordinates":[-7.97382,31.24619],"type":"Point"}
}