{
  "type": "Feature",
  "properties": {
    "gn:admin1_code":"04",
    "gn:asciiname":"Labalda",
    "gn:country_code":"MA",
    "gn:dem":10,
    "gn:feature_class":"P",
    "gn:feature_code":"PPL",
    "gn:name":"Labalda",
    "gn:population":0,
    "gn:timezone":"Africa/Casablanca",
    "iso:country":"MA",
    "name:und_x_variant":[
        "Douar Labalda",
        "Abadla",
        "Labalda"
    ],
    "wof:name":"Labalda",
    "wof:placetype":"locality"
},
  "geometry": {"coordinates":[-6.21601,34.43633],"type":"Point"}
}