{
  "type": "Feature",
  "properties": {
    "gn:admin1_code":"08",
    "gn:asciiname":"Ou Aissa",
    "gn:country_code":"MA",
    "gn:dem":1571,
    "gn:feature_class":"P",
    "gn:feature_code":"PPL",
    "gn:name":"Ou A\u00efssa",
    "gn:population":0,
    "gn:timezone":"Africa/Casablanca",
    "iso:country":"MA",
    "wof:name":"Ou Aissa",
    "wof:placetype":"locality"
},
  "geometry": {"coordinates":[-4.89378,32.26834],"type":"Point"}
}