{
  "type": "Feature",
  "properties": {
    "gn:admin1_code":"05",
    "gn:asciiname":"Admadane",
    "gn:country_code":"MA",
    "gn:dem":1652,
    "gn:feature_class":"P",
    "gn:feature_code":"PPL",
    "gn:name":"Admadane",
    "gn:population":0,
    "gn:timezone":"Africa/Casablanca",
    "iso:country":"MA",
    "name:und_x_variant":[
        "Admatene"
    ],
    "wof:name":"Admadane",
    "wof:placetype":"locality"
},
  "geometry": {"coordinates":[-6.37778,31.93819],"type":"Point"}
}