{
  "type": "Feature",
  "properties": {
    "gn:admin1_code":"09",
    "gn:asciiname":"Anzi",
    "gn:country_code":"MA",
    "gn:dem":404,
    "gn:feature_class":"P",
    "gn:feature_code":"PPL",
    "gn:name":"Anzi",
    "gn:population":0,
    "gn:timezone":"Africa/Casablanca",
    "iso:country":"MA",
    "name:ceb_x_preferred":[
        "Anzi"
    ],
    "name:deu_x_preferred":[
        "Anzi"
    ],
    "name:hun_x_preferred":[
        "Anzi"
    ],
    "name:ita_x_preferred":[
        "Anzi"
    ],
    "name:ron_x_preferred":[
        "Anzi"
    ],
    "name:swe_x_preferred":[
        "Anzi"
    ],
    "name:und_x_variant":[
        "Anezi"
    ],
    "wof:name":"Anzi",
    "wof:placetype":"locality"
},
  "geometry": {"coordinates":[-9.36227,29.66203],"type":"Point"}
}