{
  "type": "Feature",
  "properties": {
    "gn:admin1_code":"9.0",
    "gn:asciiname":"Amzarkou",
    "gn:country_code":"MA",
    "gn:dem":1539,
    "gn:feature_class":"P",
    "gn:feature_code":"PPL",
    "gn:name":"Amzarkou",
    "gn:population":0,
    "gn:timezone":"Africa/Casablanca",
    "iso:country":"MA",
    "wof:name":"Amzarkou",
    "wof:placetype":"locality"
},
  "geometry": {"coordinates":[-7.84683,30.949],"type":"Point"}
}