{
  "type": "Feature",
  "properties": {
    "gn:admin1_code":"08",
    "gn:asciiname":"Ait Ouznag",
    "gn:country_code":"MA",
    "gn:dem":1732,
    "gn:feature_class":"P",
    "gn:feature_code":"PPL",
    "gn:name":"A\u00eft Ouznag",
    "gn:population":0,
    "gn:timezone":"Africa/Casablanca",
    "iso:country":"MA",
    "wof:name":"Ait Ouznag",
    "wof:placetype":"locality"
},
  "geometry": {"coordinates":[-6.56571,31.32798],"type":"Point"}
}