{
  "type": "Feature",
  "properties": {
    "gn:admin1_code":"4.0",
    "gn:asciiname":"Karme Laklab",
    "gn:country_code":"MA",
    "gn:dem":93,
    "gn:feature_class":"P",
    "gn:feature_code":"PPL",
    "gn:name":"Karme Laklab",
    "gn:population":0,
    "gn:timezone":"Africa/Casablanca",
    "iso:country":"MA",
    "wof:name":"Karme Laklab",
    "wof:placetype":"locality"
},
  "geometry": {"coordinates":[-6.52295,34.18859],"type":"Point"}
}