{
  "type": "Feature",
  "properties": {
    "gn:admin1_code":"06",
    "gn:asciiname":"Ain Tekki",
    "gn:country_code":"MA",
    "gn:dem":73,
    "gn:feature_class":"P",
    "gn:feature_code":"PPL",
    "gn:name":"A\u00efn Tekki",
    "gn:population":0,
    "gn:timezone":"Africa/Casablanca",
    "iso:country":"MA",
    "wof:name":"Ain Tekki",
    "wof:placetype":"locality"
},
  "geometry": {"coordinates":[-7.35709,33.66576],"type":"Point"}
}