{
  "type": "Feature",
  "properties": {
    "gn:admin1_code":"01",
    "gn:asciiname":"Douar Lakhemissa",
    "gn:country_code":"MA",
    "gn:dem":501,
    "gn:feature_class":"P",
    "gn:feature_code":"PPL",
    "gn:name":"Douar Lakhemissa",
    "gn:population":0,
    "gn:timezone":"Africa/Casablanca",
    "iso:country":"MA",
    "name:und_x_variant":[
        "El Khemissa"
    ],
    "wof:name":"Douar Lakhemissa",
    "wof:placetype":"locality"
},
  "geometry": {"coordinates":[-5.58303,35.52525],"type":"Point"}
}