{
  "type": "Feature",
  "properties": {
    "gn:admin1_code":"07",
    "gn:asciiname":"Alane",
    "gn:country_code":"MA",
    "gn:dem":1531,
    "gn:feature_class":"P",
    "gn:feature_code":"PPL",
    "gn:name":"Alane",
    "gn:population":0,
    "gn:timezone":"Africa/Casablanca",
    "iso:country":"MA",
    "name:deu_x_preferred":[
        "Alane"
    ],
    "name:fra_x_preferred":[
        "Alane"
    ],
    "name:nds_x_preferred":[
        "Alane"
    ],
    "name:und_x_variant":[
        "A\u00e2lane",
        "Allane",
        "Alane"
    ],
    "wof:name":"Alane",
    "wof:placetype":"locality"
},
  "geometry": {"coordinates":[-7.3709,31.51319],"type":"Point"}
}