{
  "type": "Feature",
  "properties": {
    "gn:admin1_code":"7.0",
    "gn:asciiname":"Douar An Chlayba",
    "gn:country_code":"MA",
    "gn:dem":511,
    "gn:feature_class":"P",
    "gn:feature_code":"PPL",
    "gn:name":"Douar An Chlayba",
    "gn:population":0,
    "gn:timezone":"Africa/Casablanca",
    "iso:country":"MA",
    "wof:name":"Douar An Chlayba",
    "wof:placetype":"locality"
},
  "geometry": {"coordinates":[-7.77376,31.63728],"type":"Point"}
}