{
  "type": "Feature",
  "properties": {
    "gn:admin1_code":"9.0",
    "gn:asciiname":"Timyal",
    "gn:country_code":"MA",
    "gn:dem":842,
    "gn:feature_class":"P",
    "gn:feature_code":"PPL",
    "gn:name":"Timyal",
    "gn:population":0,
    "gn:timezone":"Africa/Casablanca",
    "iso:country":"MA",
    "wof:name":"Timyal",
    "wof:placetype":"locality"
},
  "geometry": {"coordinates":[-8.97006,30.03338],"type":"Point"}
}