{
  "type": "Feature",
  "properties": {
    "gn:country":"MA",
    "gn:fcode":"ADM3",
    "gn:population":3716,
    "iso:country":"MA",
    "name:ara_x_preferred":[
        "\u0639\u064a\u0646 \u0643\u0631\u0645\u0629"
    ],
    "name:ara_x_variant":[
        "\u0639\u064a\u0646 \u0639\u0631\u0645\u0629"
    ],
    "name:ary_x_preferred":[
        "\u0639\u064a\u0646 \u0648\u0631\u0645\u0629"
    ],
    "name:azb_x_preferred":[
        "\u0622\u0626\u06cc\u0646 \u0627\u0648\u0631\u0645\u0627"
    ],
    "name:cat_x_preferred":[
        "Ain Orma"
    ],
    "name:ceb_x_preferred":[
        "Ain Orma"
    ],
    "name:eng_x_preferred":[
        "Ain Orma"
    ],
    "name:fas_x_preferred":[
        "\u0622\u0626\u06cc\u0646 \u0627\u0648\u0631\u0645\u0627"
    ],
    "name:fra_x_preferred":[
        "Ain Orma"
    ],
    "name:fra_x_variant":[
        "Ain Orma (CR)",
        "Ain Orma (Commune Rurale)"
    ],
    "name:ita_x_preferred":[
        "Ain Orma"
    ],
    "name:swe_x_preferred":[
        "Ain Orma"
    ],
    "qs:name":"Ain Orma",
    "qs:photos_9r":0,
    "qs:photos_sr":0,
    "qs:pop_sr":"4",
    "wd:wordcount":60,
    "wof:name":"Ain Orma",
    "wof:placetype":"localadmin",
    "wof:population":3716
},
  "geometry": {"coordinates":[-5.72485,33.91334],"type":"Point"}
}