{
  "type": "Feature",
  "properties": {
    "gn:admin1_code":"2.0",
    "gn:asciiname":"Dar Hassan Ettou",
    "gn:country_code":"MA",
    "gn:dem":23,
    "gn:feature_class":"P",
    "gn:feature_code":"PPL",
    "gn:name":"Dar Hassan Ettou",
    "gn:population":0,
    "gn:timezone":"Africa/Casablanca",
    "iso:country":"MA",
    "wof:name":"Dar Hassan Ettou",
    "wof:placetype":"locality"
},
  "geometry": {"coordinates":[-2.82278,35.09156],"type":"Point"}
}