{
  "type": "Feature",
  "properties": {
    "gn:gn_country":"MA",
    "gn:gn_fcode":"ADM3",
    "gn:gn_pop":13691,
    "gn:population":12684,
    "iso:country":"MA",
    "name:ara_x_preferred":[
        "\u062a\u0627\u0641\u0631\u0627\u0646\u062a"
    ],
    "name:fra_x_preferred":[
        "Bouadel"
    ],
    "name:fra_x_variant":[
        "Bouadel (CR)",
        "Bouadel (Commune Rurale)"
    ],
    "qs_pg:aaroncc":"MA",
    "qs_pg:gn_country":"MA",
    "qs_pg:gn_fcode":"ADM3",
    "qs_pg:gn_pop":13691,
    "qs_pg:name":"Bouadel",
    "qs_pg:photos_9r":0,
    "qs_pg:photos_sr":0,
    "qs_pg:pop_sr":6,
    "qs_pg:qs_pg_placetype":"localadmin",
    "wof:name":"Bouadel",
    "wof:placetype":"localadmin",
    "wof:population":12684
},
  "geometry": {"coordinates":[-4.52858,34.54634],"type":"Point"}
}