{
  "type": "Feature",
  "properties": {
    "gn:admin1_code":"05",
    "gn:asciiname":"Assao",
    "gn:country_code":"MA",
    "gn:dem":1421,
    "gn:elevation":"0.0",
    "gn:feature_class":"P",
    "gn:feature_code":"PPL",
    "gn:name":"Assao",
    "gn:population":0,
    "gn:timezone":"Africa/Casablanca",
    "iso:country":"MA",
    "wof:name":"Assao",
    "wof:placetype":"locality"
},
  "geometry": {"coordinates":[-6.68145,31.69565],"type":"Point"}
}