{
  "type": "Feature",
  "properties": {
    "gn:admin1_code":"7.0",
    "gn:asciiname":"Drouar Chhouat",
    "gn:country_code":"MA",
    "gn:dem":385,
    "gn:feature_class":"P",
    "gn:feature_code":"PPL",
    "gn:name":"Drouar Chhouat",
    "gn:population":0,
    "gn:timezone":"Africa/Casablanca",
    "iso:country":"MA",
    "wof:name":"Drouar Chhouat",
    "wof:placetype":"locality"
},
  "geometry": {"coordinates":[-8.8753,32.10708],"type":"Point"}
}