{
  "type": "Feature",
  "properties": {
    "gn:admin1_code":"9.0",
    "gn:asciiname":"El Brieij",
    "gn:country_code":"MA",
    "gn:dem":199,
    "gn:feature_class":"P",
    "gn:feature_code":"PPL",
    "gn:name":"El Brieij",
    "gn:population":0,
    "gn:timezone":"Africa/Casablanca",
    "iso:country":"MA",
    "wof:name":"El Brieij",
    "wof:placetype":"locality"
},
  "geometry": {"coordinates":[-9.17994,30.27481],"type":"Point"}
}