{
  "type": "Feature",
  "properties": {
    "gn:admin1_code":"01",
    "gn:asciiname":"Oulad d'Ajoud",
    "gn:country_code":"MA",
    "gn:dem":996,
    "gn:feature_class":"P",
    "gn:feature_code":"PPL",
    "gn:name":"Oulad d\u2019Ajoud",
    "gn:population":0,
    "gn:timezone":"Africa/Casablanca",
    "iso:country":"MA",
    "name:und_x_variant":[
        "Ulad Aiud",
        "Oulad de Ajoud",
        "Oulad d\u2019Ajoud"
    ],
    "wof:name":"Oulad d'Ajoud",
    "wof:placetype":"locality"
},
  "geometry": {"coordinates":[-5.20164,35.03477],"type":"Point"}
}