{
  "type": "Feature",
  "properties": {
    "iso:country":"MA",
    "name:ara_x_preferred":[
        "\u0648\u0627\u0644\u062f\u064a\u0629"
    ],
    "name:eng_x_preferred":[
        "Walidia"
    ],
    "qs:gn_pop":0,
    "qs:name":"\u0648\u0627\u0644\u062f\u064a\u0629",
    "qs:name_adm0":"\u0627\u0644\u0645\u063a\u0631\u0628",
    "qs:name_adm1":"\u062f\u0643\u0627\u0644\u0629 \u0639\u0628\u062f\u0629",
    "qs:photos":170,
    "qs:photos_1k":34,
    "qs:photos_9k":1,
    "qs:photos_9r":4,
    "qs:photos_all":170,
    "qs:photos_sr":4,
    "qs:placetype":"Town",
    "qs:pop_sr":"0",
    "qs:woe_adm0":23424893,
    "wof:name":"Walidia",
    "wof:placetype":"locality"
},
  "geometry": {"coordinates":[-9.039001,32.735279],"type":"Point"}
}