{
  "type": "Feature",
  "properties": {
    "gn:admin1_code":"10",
    "gn:asciiname":"Id Tikida",
    "gn:country_code":"MA",
    "gn:dem":249,
    "gn:feature_class":"P",
    "gn:feature_code":"PPL",
    "gn:name":"Id Tikida",
    "gn:population":0,
    "gn:timezone":"Africa/Casablanca",
    "iso:country":"MA",
    "name:und_x_variant":[
        "Id Kidda"
    ],
    "wof:name":"Id Tikida",
    "wof:placetype":"locality"
},
  "geometry": {"coordinates":[-9.99179,29.39988],"type":"Point"}
}