{
  "type": "Feature",
  "properties": {
    "gn:admin1_code":"1.0",
    "gn:asciiname":"Douar Iqojan",
    "gn:country_code":"MA",
    "gn:dem":875,
    "gn:feature_class":"P",
    "gn:feature_code":"PPL",
    "gn:name":"Douar Iqojan",
    "gn:population":0,
    "gn:timezone":"Africa/Casablanca",
    "iso:country":"MA",
    "wof:name":"Douar Iqojan",
    "wof:placetype":"locality"
},
  "geometry": {"coordinates":[-4.81436,35.18125999999999],"type":"Point"}
}