{
  "type": "Feature",
  "properties": {
    "gn:admin1_code":"8.0",
    "gn:asciiname":"Oulad 'Addou",
    "gn:country_code":"MA",
    "gn:dem":758,
    "gn:feature_class":"P",
    "gn:feature_code":"PPL",
    "gn:name":"Oulad \u2019Addou",
    "gn:population":0,
    "gn:timezone":"Africa/Casablanca",
    "iso:country":"MA",
    "wof:name":"Oulad 'Addou",
    "wof:placetype":"locality"
},
  "geometry": {"coordinates":[-4.25728,31.26833],"type":"Point"}
}