{
  "type": "Feature",
  "properties": {
    "gn:admin1_code":"7.0",
    "gn:asciiname":"Hamouk",
    "gn:country_code":"MA",
    "gn:dem":835,
    "gn:feature_class":"P",
    "gn:feature_code":"PPL",
    "gn:name":"Hamouk",
    "gn:population":0,
    "gn:timezone":"Africa/Casablanca",
    "iso:country":"MA",
    "wof:name":"Hamouk",
    "wof:placetype":"locality"
},
  "geometry": {"coordinates":[-8.3721,31.27645],"type":"Point"}
}