{
  "type": "Feature",
  "properties": {
    "gn:country":"MA",
    "gn:fcode":"ADM3",
    "gn:population":6464,
    "iso:country":"MA",
    "name:ara_x_preferred":[
        "\u0627\u0644\u0645\u0639\u062f\u0631 \u0627\u0644\u0643\u0628\u064a\u0631"
    ],
    "name:ara_x_variant":[
        "\u0648\u064a\u062c\u0627\u0646"
    ],
    "name:cat_x_preferred":[
        "Ouijjane"
    ],
    "name:eng_x_preferred":[
        "Ouijjane"
    ],
    "name:fra_x_preferred":[
        "Ouijjane"
    ],
    "name:fra_x_variant":[
        "Ouijjane (CR)",
        "Ouijjane (Commune Rurale)"
    ],
    "name:ita_x_preferred":[
        "Ouijjane"
    ],
    "qs:name":"Ouijjane",
    "qs:photos_9r":0,
    "qs:photos_sr":0,
    "qs:pop_sr":"5",
    "wd:wordcount":79,
    "wof:name":"Ouijjane",
    "wof:placetype":"localadmin",
    "wof:population":6464
},
  "geometry": {"coordinates":[-9.56262,29.66136],"type":"Point"}
}