{
  "type": "Feature",
  "properties": {
    "gn:admin1_code":"3.0",
    "gn:asciiname":"Douar Jorf Lahmer",
    "gn:country_code":"MA",
    "gn:dem":342,
    "gn:feature_class":"P",
    "gn:feature_code":"PPL",
    "gn:name":"Douar Jorf Lahmer",
    "gn:population":0,
    "gn:timezone":"Africa/Casablanca",
    "iso:country":"MA",
    "wof:name":"Douar Jorf Lahmer",
    "wof:placetype":"locality"
},
  "geometry": {"coordinates":[-4.25691,34.20542],"type":"Point"}
}