{
  "type": "Feature",
  "properties": {
    "gn:admin1_code":"6.0",
    "gn:asciiname":"Mon. Cantra.",
    "gn:country_code":"MA",
    "gn:dem":7,
    "gn:feature_class":"P",
    "gn:feature_code":"PPL",
    "gn:name":"Mon. Cantra.",
    "gn:population":0,
    "gn:timezone":"Africa/Casablanca",
    "iso:country":"MA",
    "wof:name":"Mon. Cantra.",
    "wof:placetype":"locality"
},
  "geometry": {"coordinates":[-8.87315,32.86136],"type":"Point"}
}