{
  "type": "Feature",
  "properties": {
    "gn:country":"MA",
    "gn:fcode":"ADM3",
    "gn:population":5947,
    "iso:country":"MA",
    "name:ara_x_preferred":[
        "\u0627\u0641\u0644\u0627 \u064a\u0633\u0646"
    ],
    "name:ara_x_variant":[
        "\u0639\u064a\u0646 \u062a\u0632\u064a\u062a\u0648\u0646\u062a"
    ],
    "name:azb_x_preferred":[
        "\u0639\u06cc\u0646 \u062a\u0632\u06cc\u062a\u0648\u0646\u062a"
    ],
    "name:cat_x_preferred":[
        "Ain Tazitounte"
    ],
    "name:ceb_x_preferred":[
        "Ain Tazitounte"
    ],
    "name:eng_x_preferred":[
        "Ain Tazitounte"
    ],
    "name:fas_x_preferred":[
        "\u0639\u06cc\u0646 \u062a\u0632\u06cc\u062a\u0648\u0646\u062a"
    ],
    "name:fra_x_preferred":[
        "Ain Tazitounte"
    ],
    "name:fra_x_variant":[
        "Ain Tazitounte (CR)",
        "Ain Tazitounte (Commune Rurale)"
    ],
    "name:ita_x_preferred":[
        "Ain Tazitounte"
    ],
    "name:swe_x_preferred":[
        "Ain Tazitounte"
    ],
    "qs:name":"Ain Tazitounte",
    "qs:photos_9r":0,
    "qs:photos_sr":0,
    "qs:pop_sr":"5",
    "wd:wordcount":61,
    "wof:name":"Ain Tazitounte",
    "wof:placetype":"localadmin",
    "wof:population":5947
},
  "geometry": {"coordinates":[-8.88576,31.11051],"type":"Point"}
}