{
  "type": "Feature",
  "properties": {
    "gn:country":"MA",
    "gn:fcode":"ADM3",
    "gn:pop":5947,
    "iso:country":"MA",
    "name:ara_x_preferred":[
        "\u0627\u0641\u0644\u0627 \u064a\u0633\u0646"
    ],
    "name:fra_x_preferred":[
        "Ain Tazitounte"
    ],
    "name:fra_x_variant":[
        "Ain Tazitounte (CR)",
        "Ain Tazitounte (Commune Rurale)"
    ],
    "qs:name":"Ain Tazitounte",
    "qs:photos_9r":0,
    "qs:photos_sr":0,
    "qs:pop_sr":"5",
    "wd:wordcount":61,
    "wof:name":"Ain Tazitounte",
    "wof:placetype":"localadmin",
    "wof:population":5947
},
  "geometry": {"coordinates":[-8.88576,31.11051],"type":"Point"}
}