{
  "type": "Feature",
  "properties": {
    "gn:admin1_code":"7.0",
    "gn:asciiname":"Tigliyine",
    "gn:country_code":"MA",
    "gn:dem":603,
    "gn:feature_class":"P",
    "gn:feature_code":"PPL",
    "gn:name":"Tigliyine",
    "gn:population":0,
    "gn:timezone":"Africa/Casablanca",
    "iso:country":"MA",
    "wof:name":"Tigliyine",
    "wof:placetype":"locality"
},
  "geometry": {"coordinates":[-7.70495,31.58833],"type":"Point"}
}