{
  "type": "Feature",
  "properties": {
    "gn:admin1_code":"03",
    "gn:asciiname":"Cooperative El Hammouniya",
    "gn:country_code":"MA",
    "gn:dem":587,
    "gn:feature_class":"P",
    "gn:feature_code":"PPLF",
    "gn:name":"Coop\u00e9rative El Hammouniya",
    "gn:population":0,
    "gn:timezone":"Africa/Casablanca",
    "iso:country":"MA",
    "name:und_x_variant":[
        "Coop\u00e9rative El Hammouniya"
    ],
    "wof:name":"Cooperative El Hammouniya",
    "wof:placetype":"locality"
},
  "geometry": {"coordinates":[-4.94019,33.93101],"type":"Point"}
}