{
  "type": "Feature",
  "properties": {
    "gn:admin1_code":"01",
    "gn:asciiname":"Ait Taa",
    "gn:country_code":"MA",
    "gn:dem":813,
    "gn:feature_class":"P",
    "gn:feature_code":"PPL",
    "gn:name":"A\u00eft Taa",
    "gn:population":0,
    "gn:timezone":"Africa/Casablanca",
    "iso:country":"MA",
    "name:und_x_variant":[
        "A\u00eft Ta\u00e2a",
        "A\u00eft Taa"
    ],
    "wof:name":"Ait Taa",
    "wof:placetype":"locality"
},
  "geometry": {"coordinates":[-3.91596,35.0351],"type":"Point"}
}