{
  "type": "Feature",
  "properties": {
    "gn:admin1_code":"7.0",
    "gn:asciiname":"Douar Ezzouitina",
    "gn:country_code":"MA",
    "gn:dem":219,
    "gn:feature_class":"P",
    "gn:feature_code":"PPL",
    "gn:name":"Douar Ezzouitina",
    "gn:population":0,
    "gn:timezone":"Africa/Casablanca",
    "iso:country":"MA",
    "wof:name":"Douar Ezzouitina",
    "wof:placetype":"locality"
},
  "geometry": {"coordinates":[-9.47511,31.69578],"type":"Point"}
}