{
  "type": "Feature",
  "properties": {
    "gn:admin1_code":"7.0",
    "gn:asciiname":"Douar Lekfamech",
    "gn:country_code":"MA",
    "gn:dem":77,
    "gn:feature_class":"P",
    "gn:feature_code":"PPL",
    "gn:name":"Douar Lekfamech",
    "gn:population":0,
    "gn:timezone":"Africa/Casablanca",
    "iso:country":"MA",
    "wof:name":"Douar Lekfamech",
    "wof:placetype":"locality"
},
  "geometry": {"coordinates":[-9.63735,31.64692],"type":"Point"}
}