{
  "type": "Feature",
  "properties": {
    "gn:gn_country":"MA",
    "gn:gn_fcode":"ADM3",
    "gn:gn_pop":3480,
    "gn:population":2744,
    "iso:country":"MA",
    "name:ara_x_preferred":[
        "\u0633\u064a\u062f\u064a \u0639\u0628\u062f \u0627\u0644\u0644\u0647 \u0627\u0644\u0628\u0648\u0634\u0648\u0627\u0631\u064a"
    ],
    "name:fra_x_preferred":[
        "Tanalt"
    ],
    "name:fra_x_variant":[
        "Tanalt (CR)",
        "Tanalt (Commune Rurale)"
    ],
    "qs_pg:aaroncc":"MA",
    "qs_pg:gn_country":"MA",
    "qs_pg:gn_fcode":"ADM3",
    "qs_pg:gn_pop":3480,
    "qs_pg:name":"Tanalt",
    "qs_pg:photos_9r":0,
    "qs_pg:photos_sr":0,
    "qs_pg:pop_sr":4,
    "qs_pg:qs_pg_placetype":"localadmin",
    "wof:name":"Tanalt",
    "wof:placetype":"localadmin",
    "wof:population":2744
},
  "geometry": {"coordinates":[-9.11168,29.76578],"type":"Point"}
}