{
  "type": "Feature",
  "properties": {
    "gn:admin1_code":"09",
    "gn:asciiname":"Ifrhel",
    "gn:country_code":"MA",
    "gn:dem":832,
    "gn:feature_class":"P",
    "gn:feature_code":"PPL",
    "gn:name":"Ifrhel",
    "gn:population":0,
    "gn:timezone":"Africa/Casablanca",
    "iso:country":"MA",
    "name:und_x_variant":[
        "Ifghel",
        "Ifrhel"
    ],
    "wof:name":"Ifrhel",
    "wof:placetype":"locality"
},
  "geometry": {"coordinates":[-9.00084,30.12455],"type":"Point"}
}