{
  "type": "Feature",
  "properties": {
    "gn:admin1_code":"1.0",
    "gn:asciiname":"Amazouaq",
    "gn:country_code":"MA",
    "gn:dem":338,
    "gn:feature_class":"P",
    "gn:feature_code":"PPL",
    "gn:name":"Amazouaq",
    "gn:population":0,
    "gn:timezone":"Africa/Casablanca",
    "iso:country":"MA",
    "wof:name":"Amazouaq",
    "wof:placetype":"locality"
},
  "geometry": {"coordinates":[-5.59384,35.20729],"type":"Point"}
}