{
  "type": "Feature",
  "properties": {
    "gn:admin1_code":"06",
    "gn:asciiname":"Douar Guerarta",
    "gn:country_code":"MA",
    "gn:dem":137,
    "gn:feature_class":"P",
    "gn:feature_code":"PPL",
    "gn:name":"Douar Guerarta",
    "gn:population":0,
    "gn:timezone":"Africa/Casablanca",
    "iso:country":"MA",
    "wof:name":"Douar Guerarta",
    "wof:placetype":"locality"
},
  "geometry": {"coordinates":[-8.58872,32.88334],"type":"Point"}
}