{
  "type": "Feature",
  "properties": {
    "gn:admin1_code":"9.0",
    "gn:asciiname":"Al Handaq",
    "gn:country_code":"MA",
    "gn:dem":1271,
    "gn:feature_class":"P",
    "gn:feature_code":"PPL",
    "gn:name":"Al Handaq",
    "gn:population":0,
    "gn:timezone":"Africa/Casablanca",
    "iso:country":"MA",
    "wof:name":"Al Handaq",
    "wof:placetype":"locality"
},
  "geometry": {"coordinates":[-8.11383,30.53489],"type":"Point"}
}