{
  "type": "Feature",
  "properties": {
    "gn:admin1_code":"7.0",
    "gn:asciiname":"El Karin",
    "gn:country_code":"MA",
    "gn:dem":132,
    "gn:feature_class":"P",
    "gn:feature_code":"PPL",
    "gn:name":"El Karin",
    "gn:population":0,
    "gn:timezone":"Africa/Casablanca",
    "iso:country":"MA",
    "wof:name":"El Karin",
    "wof:placetype":"locality"
},
  "geometry": {"coordinates":[-9.15073,32.38800000000001],"type":"Point"}
}