{
  "type": "Feature",
  "properties": {
    "gn:admin1_code":"1.0",
    "gn:asciiname":"Douar Abounser",
    "gn:country_code":"MA",
    "gn:dem":686,
    "gn:feature_class":"P",
    "gn:feature_code":"PPL",
    "gn:name":"Douar Abounser",
    "gn:population":0,
    "gn:timezone":"Africa/Casablanca",
    "iso:country":"MA",
    "wof:name":"Douar Abounser",
    "wof:placetype":"locality"
},
  "geometry": {"coordinates":[-4.38659,35.02476],"type":"Point"}
}