{
  "type": "Feature",
  "properties": {
    "gn:admin1_code":"09",
    "gn:asciiname":"Aousift",
    "gn:country_code":"MA",
    "gn:dem":1130,
    "gn:feature_class":"P",
    "gn:feature_code":"PPL",
    "gn:name":"Aousift",
    "gn:population":0,
    "gn:timezone":"Africa/Casablanca",
    "iso:country":"MA",
    "name:und_x_variant":[
        "Aoussift",
        "Aousift"
    ],
    "wof:name":"Aousift",
    "wof:placetype":"locality"
},
  "geometry": {"coordinates":[-8.96093,29.67432],"type":"Point"}
}