{
  "type": "Feature",
  "properties": {
    "gn:admin1_code":"2.0",
    "gn:asciiname":"Dar Kaddouri",
    "gn:country_code":"MA",
    "gn:dem":457,
    "gn:feature_class":"P",
    "gn:feature_code":"PPL",
    "gn:name":"Dar Kaddouri",
    "gn:population":0,
    "gn:timezone":"Africa/Casablanca",
    "iso:country":"MA",
    "wof:name":"Dar Kaddouri",
    "wof:placetype":"locality"
},
  "geometry": {"coordinates":[-1.87445,34.78628],"type":"Point"}
}