{
  "type": "Feature",
  "properties": {
    "gn:admin1_code":"7.0",
    "gn:asciiname":"Douar Oulad Amer",
    "gn:country_code":"MA",
    "gn:dem":549,
    "gn:feature_class":"P",
    "gn:feature_code":"PPL",
    "gn:name":"Douar Oulad Amer",
    "gn:population":0,
    "gn:timezone":"Africa/Casablanca",
    "iso:country":"MA",
    "wof:name":"Douar Oulad Amer",
    "wof:placetype":"locality"
},
  "geometry": {"coordinates":[-8.92628,32.00615],"type":"Point"}
}