{
  "type": "Feature",
  "properties": {
    "gn:admin1_code":"09",
    "gn:asciiname":"Azlim",
    "gn:country_code":"MA",
    "gn:dem":1732,
    "gn:feature_class":"P",
    "gn:feature_code":"PPL",
    "gn:name":"Azlim",
    "gn:population":0,
    "gn:timezone":"Africa/Casablanca",
    "iso:country":"MA",
    "wof:name":"Azlim",
    "wof:placetype":"locality"
},
  "geometry": {"coordinates":[-8.21907,30.13556],"type":"Point"}
}