{
  "type": "Feature",
  "properties": {
    "gn:admin1_code":"3.0",
    "gn:asciiname":"Douar Ait-Rahou",
    "gn:country_code":"MA",
    "gn:dem":1660,
    "gn:feature_class":"P",
    "gn:feature_code":"PPL",
    "gn:name":"Douar Ait-Rahou",
    "gn:population":0,
    "gn:timezone":"Africa/Casablanca",
    "iso:country":"MA",
    "wof:name":"Douar Ait-Rahou",
    "wof:placetype":"locality"
},
  "geometry": {"coordinates":[-4.97556,33.59212],"type":"Point"}
}