{
  "type": "Feature",
  "properties": {
    "gn:admin1_code":"4.0",
    "gn:asciiname":"Douar Dioucha",
    "gn:country_code":"MA",
    "gn:dem":346,
    "gn:feature_class":"P",
    "gn:feature_code":"PPL",
    "gn:name":"Douar Dioucha",
    "gn:population":0,
    "gn:timezone":"Africa/Casablanca",
    "iso:country":"MA",
    "wof:name":"Douar Dioucha",
    "wof:placetype":"locality"
},
  "geometry": {"coordinates":[-6.69011,33.68603],"type":"Point"}
}