{
  "type": "Feature",
  "properties": {
    "gn:admin1_code":"03",
    "gn:asciiname":"Douar Ziadra",
    "gn:country_code":"MA",
    "gn:dem":262,
    "gn:feature_class":"P",
    "gn:feature_code":"PPL",
    "gn:name":"Douar Ziadra",
    "gn:population":0,
    "gn:timezone":"Africa/Casablanca",
    "iso:country":"MA",
    "name:und_x_variant":[
        "Ziadra"
    ],
    "wof:name":"Douar Ziadra",
    "wof:placetype":"locality"
},
  "geometry": {"coordinates":[-4.71477,34.20602],"type":"Point"}
}