{
  "type": "Feature",
  "properties": {
    "gn:admin1_code":"01",
    "gn:asciiname":"Douar El Kifane",
    "gn:country_code":"MA",
    "gn:dem":240,
    "gn:feature_class":"P",
    "gn:feature_code":"PPL",
    "gn:name":"Douar El Kifane",
    "gn:population":0,
    "gn:timezone":"Africa/Casablanca",
    "iso:country":"MA",
    "name:und_x_variant":[
        "Kifane"
    ],
    "wof:name":"Douar El Kifane",
    "wof:placetype":"locality"
},
  "geometry": {"coordinates":[-5.85375,35.30147],"type":"Point"}
}