{
  "type": "Feature",
  "properties": {
    "gn:admin1_code":"6.0",
    "gn:asciiname":"Douar 'Babsa",
    "gn:country_code":"MA",
    "gn:dem":148,
    "gn:feature_class":"P",
    "gn:feature_code":"PPL",
    "gn:name":"Douar \u2019Babsa",
    "gn:population":0,
    "gn:timezone":"Africa/Casablanca",
    "iso:country":"MA",
    "wof:name":"Douar 'Babsa",
    "wof:placetype":"locality"
},
  "geometry": {"coordinates":[-8.21561,32.86136],"type":"Point"}
}