{
  "type": "Feature",
  "properties": {
    "gn:admin1_code":"2.0",
    "gn:asciiname":"Iguerdouaane",
    "gn:country_code":"MA",
    "gn:dem":389,
    "gn:feature_class":"P",
    "gn:feature_code":"PPL",
    "gn:name":"Iguerdouaane",
    "gn:population":0,
    "gn:timezone":"Africa/Casablanca",
    "iso:country":"MA",
    "wof:name":"Iguerdouaane",
    "wof:placetype":"locality"
},
  "geometry": {"coordinates":[-3.40523,35.06464],"type":"Point"}
}