{
  "type": "Feature",
  "properties": {
    "gn:admin1_code":"05",
    "gn:asciiname":"Douar Oulad 'Attou",
    "gn:country_code":"MA",
    "gn:dem":439,
    "gn:feature_class":"P",
    "gn:feature_code":"PPL",
    "gn:name":"Douar Oulad \u2019Attou",
    "gn:population":0,
    "gn:timezone":"Africa/Casablanca",
    "iso:country":"MA",
    "name:und_x_variant":[
        "Douar Oulad \u2019Attou",
        "Oulad Atta"
    ],
    "wof:name":"Douar Oulad 'Attou",
    "wof:placetype":"locality"
},
  "geometry": {"coordinates":[-6.59623,32.25808],"type":"Point"}
}