{
  "type": "Feature",
  "properties": {
    "gn:admin1_code":"1.0",
    "gn:asciiname":"Douar Taourat",
    "gn:country_code":"MA",
    "gn:dem":250,
    "gn:feature_class":"P",
    "gn:feature_code":"PPL",
    "gn:name":"Douar Taourat",
    "gn:population":0,
    "gn:timezone":"Africa/Casablanca",
    "iso:country":"MA",
    "wof:name":"Douar Taourat",
    "wof:placetype":"locality"
},
  "geometry": {"coordinates":[-5.13962,34.78304],"type":"Point"}
}