{
  "type": "Feature",
  "properties": {
    "gn:admin1_code":"10.0",
    "gn:asciiname":"Id Hammou Ou Sa'id",
    "gn:country_code":"MA",
    "gn:dem":764,
    "gn:feature_class":"P",
    "gn:feature_code":"PPL",
    "gn:name":"Id Hammou Ou Sa\u2019id",
    "gn:population":0,
    "gn:timezone":"Africa/Casablanca",
    "iso:country":"MA",
    "wof:name":"Id Hammou Ou Sa'id",
    "wof:placetype":"locality"
},
  "geometry": {"coordinates":[-9.84701,29.36834],"type":"Point"}
}