{
  "type": "Feature",
  "properties": {
    "gn:admin1_code":"6.0",
    "gn:asciiname":"Societe Ecogema",
    "gn:country_code":"MA",
    "gn:dem":58,
    "gn:feature_class":"P",
    "gn:feature_code":"PPL",
    "gn:name":"Soci\u00e9t\u00e9 Ecogema",
    "gn:population":0,
    "gn:timezone":"Africa/Casablanca",
    "iso:country":"MA",
    "wof:name":"Societe Ecogema",
    "wof:placetype":"locality"
},
  "geometry": {"coordinates":[-7.13625,33.78992],"type":"Point"}
}