{
  "type": "Feature",
  "properties": {
    "gn:admin1_code":"7.0",
    "gn:asciiname":"Douar Laassara",
    "gn:country_code":"MA",
    "gn:dem":370,
    "gn:feature_class":"P",
    "gn:feature_code":"PPL",
    "gn:name":"Douar Laassara",
    "gn:population":0,
    "gn:timezone":"Africa/Casablanca",
    "iso:country":"MA",
    "wof:name":"Douar Laassara",
    "wof:placetype":"locality"
},
  "geometry": {"coordinates":[-9.05101,32.01721],"type":"Point"}
}