{
  "type": "Feature",
  "properties": {
    "gn:admin1_code":"9.0",
    "gn:asciiname":"Tarharrabout",
    "gn:country_code":"MA",
    "gn:dem":561,
    "gn:feature_class":"P",
    "gn:feature_code":"PPL",
    "gn:name":"Tarharrabout",
    "gn:population":0,
    "gn:timezone":"Africa/Casablanca",
    "iso:country":"MA",
    "wof:name":"Tarharrabout",
    "wof:placetype":"locality"
},
  "geometry": {"coordinates":[-9.17296,30.02311],"type":"Point"}
}