{
  "type": "Feature",
  "properties": {
    "gn:admin1_code":"1.0",
    "gn:asciiname":"Douar Talantazart",
    "gn:country_code":"MA",
    "gn:dem":962,
    "gn:feature_class":"P",
    "gn:feature_code":"PPL",
    "gn:name":"Douar Talantazart",
    "gn:population":0,
    "gn:timezone":"Africa/Casablanca",
    "iso:country":"MA",
    "wof:name":"Douar Talantazart",
    "wof:placetype":"locality"
},
  "geometry": {"coordinates":[-4.76815,35.13162],"type":"Point"}
}