{
  "type": "Feature",
  "properties": {
    "gn:admin1_code":"5.0",
    "gn:asciiname":"Tirika",
    "gn:country_code":"MA",
    "gn:dem":1077,
    "gn:feature_class":"P",
    "gn:feature_code":"PPL",
    "gn:name":"Tirika",
    "gn:population":0,
    "gn:timezone":"Africa/Casablanca",
    "iso:country":"MA",
    "wof:name":"Tirika",
    "wof:placetype":"locality"
},
  "geometry": {"coordinates":[-6.89639,31.69976],"type":"Point"}
}