{
  "type": "Feature",
  "properties": {
    "gn:admin1_code":"9.0",
    "gn:asciiname":"Bakkou",
    "gn:country_code":"MA",
    "gn:dem":1522,
    "gn:feature_class":"P",
    "gn:feature_code":"PPL",
    "gn:name":"Bakkou",
    "gn:population":0,
    "gn:timezone":"Africa/Casablanca",
    "iso:country":"MA",
    "wof:name":"Bakkou",
    "wof:placetype":"locality"
},
  "geometry": {"coordinates":[-8.74647,29.92029],"type":"Point"}
}