{
  "type": "Feature",
  "properties": {
    "gn:admin1_code":"7.0",
    "gn:asciiname":"Douar Ait Abderrahmane",
    "gn:country_code":"MA",
    "gn:dem":271,
    "gn:feature_class":"P",
    "gn:feature_code":"PPL",
    "gn:name":"Douar Ait Abderrahmane",
    "gn:population":0,
    "gn:timezone":"Africa/Casablanca",
    "iso:country":"MA",
    "wof:name":"Douar Ait Abderrahmane",
    "wof:placetype":"locality"
},
  "geometry": {"coordinates":[-9.52443,31.43602000000001],"type":"Point"}
}