{
  "type": "Feature",
  "properties": {
    "gn:admin1_code":"7.0",
    "gn:asciiname":"Douar N'Khila",
    "gn:country_code":"MA",
    "gn:dem":589,
    "gn:feature_class":"P",
    "gn:feature_code":"PPL",
    "gn:name":"Douar N\u2019Khila",
    "gn:population":0,
    "gn:timezone":"Africa/Casablanca",
    "iso:country":"MA",
    "wof:name":"Douar N'Khila",
    "wof:placetype":"locality"
},
  "geometry": {"coordinates":[-8.15298,31.43344],"type":"Point"}
}