{
  "type": "Feature",
  "properties": {
    "gn:admin1_code":"7.0",
    "gn:asciiname":"Douar Ait Lgout",
    "gn:country_code":"MA",
    "gn:dem":609,
    "gn:feature_class":"P",
    "gn:feature_code":"PPL",
    "gn:name":"Douar Ait Lgout",
    "gn:population":0,
    "gn:timezone":"Africa/Casablanca",
    "iso:country":"MA",
    "wof:name":"Douar Ait Lgout",
    "wof:placetype":"locality"
},
  "geometry": {"coordinates":[-7.84704,31.50173],"type":"Point"}
}