{
  "type": "Feature",
  "properties": {
    "gn:admin1_code":"01",
    "gn:asciiname":"Seffal",
    "gn:country_code":"MA",
    "gn:dem":1231,
    "gn:feature_class":"P",
    "gn:feature_code":"PPL",
    "gn:name":"Seffal",
    "gn:population":0,
    "gn:timezone":"Africa/Casablanca",
    "iso:country":"MA",
    "wof:name":"Seffal",
    "wof:placetype":"locality"
},
  "geometry": {"coordinates":[-4.16,34.81],"type":"Point"}
}