{
  "type": "Feature",
  "properties": {
    "gn:admin1_code":"7.0",
    "gn:asciiname":"Douar Jouabar",
    "gn:country_code":"MA",
    "gn:dem":614,
    "gn:feature_class":"P",
    "gn:feature_code":"PPL",
    "gn:name":"Douar Jouabar",
    "gn:population":0,
    "gn:timezone":"Africa/Casablanca",
    "iso:country":"MA",
    "wof:name":"Douar Jouabar",
    "wof:placetype":"locality"
},
  "geometry": {"coordinates":[-7.80348,31.50664],"type":"Point"}
}