{
  "type": "Feature",
  "properties": {
    "gn:admin1_code":"9.0",
    "gn:asciiname":"Iwwal",
    "gn:country_code":"MA",
    "gn:dem":1172,
    "gn:feature_class":"P",
    "gn:feature_code":"PPL",
    "gn:name":"Iwwal",
    "gn:population":0,
    "gn:timezone":"Africa/Casablanca",
    "iso:country":"MA",
    "wof:name":"Iwwal",
    "wof:placetype":"locality"
},
  "geometry": {"coordinates":[-8.95633,29.9719],"type":"Point"}
}