{
  "type": "Feature",
  "properties": {
    "gn:admin1_code":"2.0",
    "gn:asciiname":"Douar Idouane",
    "gn:country_code":"MA",
    "gn:dem":471,
    "gn:feature_class":"P",
    "gn:feature_code":"PPL",
    "gn:name":"Douar Idouane",
    "gn:population":0,
    "gn:timezone":"Africa/Casablanca",
    "iso:country":"MA",
    "wof:name":"Douar Idouane",
    "wof:placetype":"locality"
},
  "geometry": {"coordinates":[-3.70038,35.05054000000001],"type":"Point"}
}