{
  "type": "Feature",
  "properties": {
    "gn:admin1_code":"1.0",
    "gn:asciiname":"Dar Battioui",
    "gn:country_code":"MA",
    "gn:dem":10,
    "gn:feature_class":"P",
    "gn:feature_code":"PPL",
    "gn:name":"Dar Battioui",
    "gn:population":0,
    "gn:timezone":"Africa/Casablanca",
    "iso:country":"MA",
    "wof:name":"Dar Battioui",
    "wof:placetype":"locality"
},
  "geometry": {"coordinates":[-5.36233,35.78313],"type":"Point"}
}