{
  "type": "Feature",
  "properties": {
    "gn:admin1_code":"3.0",
    "gn:asciiname":"Douar Markouna",
    "gn:country_code":"MA",
    "gn:dem":496,
    "gn:feature_class":"P",
    "gn:feature_code":"PPL",
    "gn:name":"Douar Markouna",
    "gn:population":0,
    "gn:timezone":"Africa/Casablanca",
    "iso:country":"MA",
    "wof:name":"Douar Markouna",
    "wof:placetype":"locality"
},
  "geometry": {"coordinates":[-4.39695,34.34778],"type":"Point"}
}