{
  "type": "Feature",
  "properties": {
    "gn:admin1_code":"2.0",
    "gn:asciiname":"Douar Taddar Jdid",
    "gn:country_code":"MA",
    "gn:dem":805,
    "gn:feature_class":"P",
    "gn:feature_code":"PPL",
    "gn:name":"Douar Taddar Jdid",
    "gn:population":0,
    "gn:timezone":"Africa/Casablanca",
    "iso:country":"MA",
    "wof:name":"Douar Taddar Jdid",
    "wof:placetype":"locality"
},
  "geometry": {"coordinates":[-3.73915,35.07211],"type":"Point"}
}