{
  "type": "Feature",
  "properties": {
    "gn:admin1_code":"09",
    "gn:asciiname":"Alouss",
    "gn:country_code":"MA",
    "gn:dem":1448,
    "gn:feature_class":"P",
    "gn:feature_code":"PPL",
    "gn:name":"Alouss",
    "gn:population":0,
    "gn:timezone":"Africa/Casablanca",
    "iso:country":"MA",
    "wof:name":"Alouss",
    "wof:placetype":"locality"
},
  "geometry": {"coordinates":[-8.30889,30.25681],"type":"Point"}
}