{
  "type": "Feature",
  "properties": {
    "gn:admin1_code":"7.0",
    "gn:asciiname":"Tama",
    "gn:country_code":"MA",
    "gn:dem":669,
    "gn:feature_class":"P",
    "gn:feature_code":"PPL",
    "gn:name":"Tama",
    "gn:population":0,
    "gn:timezone":"Africa/Casablanca",
    "iso:country":"MA",
    "wof:name":"Tama",
    "wof:placetype":"locality"
},
  "geometry": {"coordinates":[-9.37532,31.26525],"type":"Point"}
}