{
  "type": "Feature",
  "properties": {
    "gn:admin1_code":"04",
    "gn:asciiname":"Douar Labrahma",
    "gn:country_code":"MA",
    "gn:dem":51,
    "gn:feature_class":"P",
    "gn:feature_code":"PPL",
    "gn:name":"Douar Labrahma",
    "gn:population":0,
    "gn:timezone":"Africa/Casablanca",
    "iso:country":"MA",
    "wof:name":"Douar Labrahma",
    "wof:placetype":"locality"
},
  "geometry": {"coordinates":[-6.75155,34.09132],"type":"Point"}
}