{
  "type": "Feature",
  "properties": {
    "gn:admin1_code":"08",
    "gn:asciiname":"Magaman",
    "gn:country_code":"MA",
    "gn:dem":1039,
    "gn:feature_class":"P",
    "gn:feature_code":"PPL",
    "gn:name":"Magaman",
    "gn:population":0,
    "gn:timezone":"Africa/Casablanca",
    "iso:country":"MA",
    "name:und_x_variant":[
        "Mgamane",
        "Meggamane",
        "Magaman"
    ],
    "wof:name":"Magaman",
    "wof:placetype":"locality"
},
  "geometry": {"coordinates":[-4.97701,31.71112],"type":"Point"}
}