{
  "type": "Feature",
  "properties": {
    "gn:admin1_code":"03",
    "gn:asciiname":"Douar Tafsest",
    "gn:country_code":"MA",
    "gn:dem":1073,
    "gn:feature_class":"P",
    "gn:feature_code":"PPL",
    "gn:name":"Douar Tafsest",
    "gn:population":0,
    "gn:timezone":"Africa/Casablanca",
    "iso:country":"MA",
    "name:und_x_variant":[
        "Tafsest"
    ],
    "wof:name":"Douar Tafsest",
    "wof:placetype":"locality"
},
  "geometry": {"coordinates":[-3.99433,33.97476],"type":"Point"}
}