{
  "type": "Feature",
  "properties": {
    "gn:admin1_code":"4.0",
    "gn:asciiname":"Laamirat",
    "gn:country_code":"MA",
    "gn:dem":194,
    "gn:feature_class":"P",
    "gn:feature_code":"PPL",
    "gn:name":"Laamirat",
    "gn:population":0,
    "gn:timezone":"Africa/Casablanca",
    "iso:country":"MA",
    "wof:name":"Laamirat",
    "wof:placetype":"locality"
},
  "geometry": {"coordinates":[-5.55562,34.6165],"type":"Point"}
}