{
  "type": "Feature",
  "properties": {
    "gn:admin1_code":"3.0",
    "gn:asciiname":"Douar Bni Mathar",
    "gn:country_code":"MA",
    "gn:dem":359,
    "gn:feature_class":"P",
    "gn:feature_code":"PPL",
    "gn:name":"Douar Bni Mathar",
    "gn:population":0,
    "gn:timezone":"Africa/Casablanca",
    "iso:country":"MA",
    "wof:name":"Douar Bni Mathar",
    "wof:placetype":"locality"
},
  "geometry": {"coordinates":[-5.26082,34.00025],"type":"Point"}
}