{
  "type": "Feature",
  "properties": {
    "gn:admin1_code":"07",
    "gn:asciiname":"Douar Hmara",
    "gn:country_code":"MA",
    "gn:dem":367,
    "gn:feature_class":"P",
    "gn:feature_code":"PPL",
    "gn:name":"Douar Hmara",
    "gn:population":0,
    "gn:timezone":"Africa/Casablanca",
    "iso:country":"MA",
    "name:und_x_variant":[
        "Dour ben Abdallah"
    ],
    "wof:name":"Douar Hmara",
    "wof:placetype":"locality"
},
  "geometry": {"coordinates":[-8.66494,32.06349],"type":"Point"}
}