{
  "type": "Feature",
  "properties": {
    "gn:admin1_code":"4.0",
    "gn:asciiname":"Oulad Sidi Ben Damou",
    "gn:country_code":"MA",
    "gn:dem":548,
    "gn:feature_class":"P",
    "gn:feature_code":"PPL",
    "gn:name":"Oulad Sidi Ben Damou",
    "gn:population":0,
    "gn:timezone":"Africa/Casablanca",
    "iso:country":"MA",
    "wof:name":"Oulad Sidi Ben Damou",
    "wof:placetype":"locality"
},
  "geometry": {"coordinates":[-6.48982,33.50404],"type":"Point"}
}