{
  "type": "Feature",
  "properties": {
    "gn:admin1_code":"05",
    "gn:asciiname":"Igmir",
    "gn:country_code":"MA",
    "gn:dem":771,
    "gn:feature_class":"P",
    "gn:feature_code":"PPL",
    "gn:name":"Igmir",
    "gn:population":0,
    "gn:timezone":"Africa/Casablanca",
    "iso:country":"MA",
    "wof:name":"Igmir",
    "wof:placetype":"locality"
},
  "geometry": {"coordinates":[-7.27837,31.68288],"type":"Point"}
}