{
  "type": "Feature",
  "properties": {
    "gn:admin1_code":"07",
    "gn:asciiname":"Frizem",
    "gn:country_code":"MA",
    "gn:dem":704,
    "gn:feature_class":"P",
    "gn:feature_code":"PPL",
    "gn:name":"Frizem",
    "gn:population":0,
    "gn:timezone":"Africa/Casablanca",
    "iso:country":"MA",
    "name:und_x_variant":[
        "Douar Frizem",
        "Frizim",
        "Frizem"
    ],
    "wof:name":"Frizem",
    "wof:placetype":"locality"
},
  "geometry": {"coordinates":[-8.29528,31.40697],"type":"Point"}
}