{
  "type": "Feature",
  "properties": {
    "gn:admin1_code":"01",
    "gn:asciiname":"Douar Neqaqcha",
    "gn:country_code":"MA",
    "gn:dem":133,
    "gn:feature_class":"P",
    "gn:feature_code":"PPL",
    "gn:name":"Douar Neqaqcha",
    "gn:population":0,
    "gn:timezone":"Africa/Casablanca",
    "iso:country":"MA",
    "name:und_x_variant":[
        "Nakakichat",
        "Nekakcha",
        "Douar Neqaqcha"
    ],
    "wof:name":"Douar Neqaqcha",
    "wof:placetype":"locality"
},
  "geometry": {"coordinates":[-5.96295,35.36494000000001],"type":"Point"}
}