{
  "type": "Feature",
  "properties": {
    "gn:admin1_code":"02",
    "gn:asciiname":"Lamrija Al Fouqania",
    "gn:country_code":"MA",
    "gn:dem":1497,
    "gn:feature_class":"P",
    "gn:feature_code":"PPL",
    "gn:name":"Lamrija Al Fouqania",
    "gn:population":0,
    "gn:timezone":"Africa/Casablanca",
    "iso:country":"MA",
    "name:und_x_variant":[
        "Meridja Foukania",
        "Meridja",
        "Merija Foukania",
        "Lamrija Al Fouqania"
    ],
    "wof:name":"Lamrija Al Fouqania",
    "wof:placetype":"locality"
},
  "geometry": {"coordinates":[-3.59655,32.72967],"type":"Point"}
}