{
  "type": "Feature",
  "properties": {
    "gn:admin1_code":"6.0",
    "gn:asciiname":"Douar Rguibat",
    "gn:country_code":"MA",
    "gn:dem":168,
    "gn:feature_class":"P",
    "gn:feature_code":"PPL",
    "gn:name":"Douar Rguibat",
    "gn:population":0,
    "gn:timezone":"Africa/Casablanca",
    "iso:country":"MA",
    "wof:name":"Douar Rguibat",
    "wof:placetype":"locality"
},
  "geometry": {"coordinates":[-8.46064,32.69611],"type":"Point"}
}