{
  "type": "Feature",
  "properties": {
    "gn:admin1_code":"01",
    "gn:asciiname":"Tiechart",
    "gn:country_code":"MA",
    "gn:dem":428,
    "gn:feature_class":"P",
    "gn:feature_code":"PPL",
    "gn:name":"Tiechart",
    "gn:population":0,
    "gn:timezone":"Africa/Casablanca",
    "iso:country":"MA",
    "name:und_x_variant":[
        "Tiexart",
        "Tiechart"
    ],
    "wof:name":"Tiechart",
    "wof:placetype":"locality"
},
  "geometry": {"coordinates":[-4.63283,35.06995999999999],"type":"Point"}
}