{
  "type": "Feature",
  "properties": {
    "gn:admin1_code":"02",
    "gn:asciiname":"Bouqallal",
    "gn:country_code":"MA",
    "gn:dem":314,
    "gn:feature_class":"P",
    "gn:feature_code":"PPL",
    "gn:name":"Bouqallal",
    "gn:population":0,
    "gn:timezone":"Africa/Casablanca",
    "iso:country":"MA",
    "name:und_x_variant":[
        "Bo\u00fbkell\u00e2",
        "Bo\u00fbkell\u00e2l",
        "Bouqallal"
    ],
    "wof:name":"Bouqallal",
    "wof:placetype":"locality"
},
  "geometry": {"coordinates":[-3.32942,35.14372],"type":"Point"}
}