{
  "type": "Feature",
  "properties": {
    "gn:admin1_code":"1.0",
    "gn:asciiname":"Lemdaouer",
    "gn:country_code":"MA",
    "gn:dem":28,
    "gn:feature_class":"P",
    "gn:feature_code":"PPL",
    "gn:name":"Lemdaouer",
    "gn:population":0,
    "gn:timezone":"Africa/Casablanca",
    "iso:country":"MA",
    "wof:name":"Lemdaouer",
    "wof:placetype":"locality"
},
  "geometry": {"coordinates":[-5.85075,35.49322],"type":"Point"}
}