{
  "type": "Feature",
  "properties": {
    "gn:country":"MA",
    "gn:fcode":"ADM3",
    "gn:population":8382,
    "iso:country":"MA",
    "name:ara_x_preferred":[
        "\u0627\u0644\u062f\u0634\u0631\u0629"
    ],
    "name:fra_x_preferred":[
        "Elaamria"
    ],
    "name:fra_x_variant":[
        "Elaamria (CR)",
        "Elaamria (Commune Rurale)"
    ],
    "qs:name":"Elaamria",
    "qs:photos_9r":0,
    "qs:photos_sr":0,
    "qs:pop_sr":"5",
    "wof:name":"Elaamria",
    "wof:placetype":"localadmin",
    "wof:population":8382
},
  "geometry": {"coordinates":[-7.24169,32.23384],"type":"Point"}
}