{
  "type": "Feature",
  "properties": {
    "gn:admin1_code":"3.0",
    "gn:asciiname":"Sidi 'Ali Bou Khzer",
    "gn:country_code":"MA",
    "gn:dem":980,
    "gn:feature_class":"P",
    "gn:feature_code":"PPL",
    "gn:name":"Sidi \u2019Ali Bou Khzer",
    "gn:population":0,
    "gn:timezone":"Africa/Casablanca",
    "iso:country":"MA",
    "wof:name":"Sidi 'Ali Bou Khzer",
    "wof:placetype":"locality"
},
  "geometry": {"coordinates":[-4.41534,33.88502],"type":"Point"}
}