{
  "type": "Feature",
  "properties": {
    "gn:admin1_code":"6.0",
    "gn:asciiname":"Oulad Abbes Saidi",
    "gn:country_code":"MA",
    "gn:dem":367,
    "gn:feature_class":"P",
    "gn:feature_code":"PPL",
    "gn:name":"Oulad Abb\u00e8s Sa\u00efdi",
    "gn:population":0,
    "gn:timezone":"Africa/Casablanca",
    "iso:country":"MA",
    "wof:name":"Oulad Abbes Saidi",
    "wof:placetype":"locality"
},
  "geometry": {"coordinates":[-7.74764,32.80126],"type":"Point"}
}