{
  "type": "Feature",
  "properties": {
    "gn:admin1_code":"5.0",
    "gn:asciiname":"Ait 'Arfat",
    "gn:country_code":"MA",
    "gn:dem":1319,
    "gn:feature_class":"P",
    "gn:feature_code":"PPL",
    "gn:name":"A\u00eft \u2019Arfat",
    "gn:population":0,
    "gn:timezone":"Africa/Casablanca",
    "iso:country":"MA",
    "wof:name":"Ait 'Arfat",
    "wof:placetype":"locality"
},
  "geometry": {"coordinates":[-6.58404,31.988],"type":"Point"}
}