{
  "type": "Feature",
  "properties": {
    "gn:admin1_code":"8.0",
    "gn:asciiname":"Qcar Lahrar",
    "gn:country_code":"MA",
    "gn:dem":934,
    "gn:feature_class":"P",
    "gn:feature_code":"PPL",
    "gn:name":"Qcar Lahrar",
    "gn:population":0,
    "gn:timezone":"Africa/Casablanca",
    "iso:country":"MA",
    "wof:name":"Qcar Lahrar",
    "wof:placetype":"locality"
},
  "geometry": {"coordinates":[-4.22798,31.76908],"type":"Point"}
}