{
  "type": "Feature",
  "properties": {
    "gn:admin1_code":"01",
    "gn:asciiname":"Douar Lkouf Lfougi",
    "gn:country_code":"MA",
    "gn:dem":279,
    "gn:feature_class":"P",
    "gn:feature_code":"PPL",
    "gn:name":"Douar Lkouf Lfougi",
    "gn:population":0,
    "gn:timezone":"Africa/Casablanca",
    "iso:country":"MA",
    "name:und_x_variant":[
        "Kouf el Fouki"
    ],
    "wof:name":"Douar Lkouf Lfougi",
    "wof:placetype":"locality"
},
  "geometry": {"coordinates":[-5.43595,35.71342],"type":"Point"}
}