{
  "type": "Feature",
  "properties": {
    "gn:admin1_code":"08",
    "gn:asciiname":"El Hazbane",
    "gn:country_code":"MA",
    "gn:dem":786,
    "gn:feature_class":"P",
    "gn:feature_code":"PPL",
    "gn:name":"El Hazbane",
    "gn:population":0,
    "gn:timezone":"Africa/Casablanca",
    "iso:country":"MA",
    "wof:name":"El Hazbane",
    "wof:placetype":"locality"
},
  "geometry": {"coordinates":[-5.23842,30.82227],"type":"Point"}
}