{
  "type": "Feature",
  "properties": {
    "gn:admin1_code":"02",
    "gn:asciiname":"Imaaroufene",
    "gn:country_code":"MA",
    "gn:dem":145,
    "gn:feature_class":"P",
    "gn:feature_code":"PPL",
    "gn:name":"Imaaroufene",
    "gn:population":0,
    "gn:timezone":"Africa/Casablanca",
    "iso:country":"MA",
    "name:und_x_variant":[
        "Ymarufen",
        "Im \u2019arofene",
        "Imarufen",
        "Imaroufene",
        "Imaaroufene"
    ],
    "wof:name":"Imaaroufene",
    "wof:placetype":"locality"
},
  "geometry": {"coordinates":[-3.14905,35.12652],"type":"Point"}
}