{
  "type": "Feature",
  "properties": {
    "gn:admin1_code":"6.0",
    "gn:asciiname":"Douar Bir Jmel",
    "gn:country_code":"MA",
    "gn:dem":134,
    "gn:feature_class":"P",
    "gn:feature_code":"PPL",
    "gn:name":"Douar Bir Jmel",
    "gn:population":0,
    "gn:timezone":"Africa/Casablanca",
    "iso:country":"MA",
    "wof:name":"Douar Bir Jmel",
    "wof:placetype":"locality"
},
  "geometry": {"coordinates":[-8.91868,32.73989],"type":"Point"}
}