{
  "type": "Feature",
  "properties": {
    "gn:admin1_code":"7.0",
    "gn:asciiname":"Lahnich",
    "gn:country_code":"MA",
    "gn:dem":656,
    "gn:feature_class":"P",
    "gn:feature_code":"PPL",
    "gn:name":"Lahnich",
    "gn:population":0,
    "gn:timezone":"Africa/Casablanca",
    "iso:country":"MA",
    "wof:name":"Lahnich",
    "wof:placetype":"locality"
},
  "geometry": {"coordinates":[-7.09929,31.85273],"type":"Point"}
}