{
  "type": "Feature",
  "properties": {
    "gn:admin1_code":"5.0",
    "gn:asciiname":"Ait Wishane",
    "gn:country_code":"MA",
    "gn:dem":1057,
    "gn:feature_class":"P",
    "gn:feature_code":"PPL",
    "gn:name":"Ait Wishane",
    "gn:population":0,
    "gn:timezone":"Africa/Casablanca",
    "iso:country":"MA",
    "wof:name":"Ait Wishane",
    "wof:placetype":"locality"
},
  "geometry": {"coordinates":[-7.1911,31.64348],"type":"Point"}
}