{
  "type": "Feature",
  "properties": {
    "gn:admin1_code":"4.0",
    "gn:asciiname":"Dar Sidi Said",
    "gn:country_code":"MA",
    "gn:dem":341,
    "gn:feature_class":"P",
    "gn:feature_code":"PPL",
    "gn:name":"Dar Sidi Said",
    "gn:population":0,
    "gn:timezone":"Africa/Casablanca",
    "iso:country":"MA",
    "wof:name":"Dar Sidi Said",
    "wof:placetype":"locality"
},
  "geometry": {"coordinates":[-6.8986,33.67590999999999],"type":"Point"}
}