{
  "type": "Feature",
  "properties": {
    "gn:admin1_code":"4.0",
    "gn:asciiname":"Douar Ezhouibuza",
    "gn:country_code":"MA",
    "gn:dem":230,
    "gn:feature_class":"P",
    "gn:feature_code":"PPL",
    "gn:name":"Douar Ezhouibuza",
    "gn:population":0,
    "gn:timezone":"Africa/Casablanca",
    "iso:country":"MA",
    "wof:name":"Douar Ezhouibuza",
    "wof:placetype":"locality"
},
  "geometry": {"coordinates":[-5.63565,34.72223],"type":"Point"}
}