{
  "type": "Feature",
  "properties": {
    "gn:country":"MA",
    "gn:fcode":"ADM3",
    "gn:pop":7330,
    "iso:country":"MA",
    "name:ara_x_preferred":[
        "\u0623\u064a\u062a \u0645\u0632\u0627\u0644"
    ],
    "name:ara_x_variant":[
        "\u0622\u064a\u062a \u0648\u0627\u062f\u0631\u064a\u0645"
    ],
    "name:azb_x_preferred":[
        "\u0622\u06cc\u062a \u0627\u0648\u0627\u062f\u0631\u06cc\u0645"
    ],
    "name:cat_x_preferred":[
        "A\u00eft Ouadrim"
    ],
    "name:eng_x_preferred":[
        "Ait Ouadrim"
    ],
    "name:eus_x_preferred":[
        "Ait Ouadrim"
    ],
    "name:fas_x_preferred":[
        "\u0627\u06cc\u062a \u0627\u0648\u0627\u062f\u0631\u06cc\u0645"
    ],
    "name:fra_x_preferred":[
        "Ait Ouadrim"
    ],
    "name:fra_x_variant":[
        "Ait Ouadrim (CR)",
        "Ait Ouadrim (Commune Rurale)"
    ],
    "name:ita_x_preferred":[
        "Ait Ouadrim"
    ],
    "qs:name":"Ait Ouadrim",
    "qs:photos_9r":0,
    "qs:photos_sr":0,
    "qs:pop_sr":"5",
    "wd:wordcount":63,
    "wof:name":"Ait Ouadrim",
    "wof:placetype":"localadmin",
    "wof:population":7330
},
  "geometry": {"coordinates":[-9.24999,30.01939],"type":"Point"}
}