{
  "type": "Feature",
  "properties": {
    "gn:admin1_code":"4.0",
    "gn:asciiname":"Douar Ghyalsa",
    "gn:country_code":"MA",
    "gn:dem":98,
    "gn:feature_class":"P",
    "gn:feature_code":"PPL",
    "gn:name":"Douar Ghyalsa",
    "gn:population":0,
    "gn:timezone":"Africa/Casablanca",
    "iso:country":"MA",
    "wof:name":"Douar Ghyalsa",
    "wof:placetype":"locality"
},
  "geometry": {"coordinates":[-5.86465,34.71566],"type":"Point"}
}