{
  "type": "Feature",
  "properties": {
    "gn:admin1_code":"7.0",
    "gn:asciiname":"Dar Lehrizi Echaoui",
    "gn:country_code":"MA",
    "gn:dem":399,
    "gn:feature_class":"P",
    "gn:feature_code":"PPL",
    "gn:name":"Dar Lehrizi Echaoui",
    "gn:population":0,
    "gn:timezone":"Africa/Casablanca",
    "iso:country":"MA",
    "wof:name":"Dar Lehrizi Echaoui",
    "wof:placetype":"locality"
},
  "geometry": {"coordinates":[-7.9305,32.53895],"type":"Point"}
}