{
  "type": "Feature",
  "properties": {
    "gn:admin1_code":"04",
    "gn:asciiname":"Douar Lhart",
    "gn:country_code":"MA",
    "gn:dem":80,
    "gn:feature_class":"P",
    "gn:feature_code":"PPL",
    "gn:name":"Douar Lhart",
    "gn:population":0,
    "gn:timezone":"Africa/Casablanca",
    "iso:country":"MA",
    "name:und_x_variant":[
        "El Harte",
        "El Hart",
        "Douar Lhart"
    ],
    "wof:name":"Douar Lhart",
    "wof:placetype":"locality"
},
  "geometry": {"coordinates":[-5.43046,34.53509],"type":"Point"}
}