{
  "type": "Feature",
  "properties": {
    "gn:admin1_code":"5.0",
    "gn:asciiname":"Lamdint-n-Ougard-n-Ait Issimour",
    "gn:country_code":"MA",
    "gn:dem":1005,
    "gn:feature_class":"P",
    "gn:feature_code":"PPL",
    "gn:name":"Lamdint-n-Ougard-n-A\u00eft Issimour",
    "gn:population":0,
    "gn:timezone":"Africa/Casablanca",
    "iso:country":"MA",
    "wof:name":"Lamdint-n-Ougard-n-Ait Issimour",
    "wof:placetype":"locality"
},
  "geometry": {"coordinates":[-6.33249,32.10125],"type":"Point"}
}