{
  "type": "Feature",
  "properties": {
    "gn:admin1_code":"09",
    "gn:asciiname":"Bou Tamert",
    "gn:country_code":"MA",
    "gn:dem":1302,
    "gn:feature_class":"P",
    "gn:feature_code":"PPL",
    "gn:name":"Bou Tamert",
    "gn:population":0,
    "gn:timezone":"Africa/Casablanca",
    "iso:country":"MA",
    "name:und_x_variant":[
        "Bou Tamart",
        "Bou Tamert"
    ],
    "wof:name":"Bou Tamert",
    "wof:placetype":"locality"
},
  "geometry": {"coordinates":[-8.39037,30.46206],"type":"Point"}
}