{
  "type": "Feature",
  "properties": {
    "gn:admin1_code":"9.0",
    "gn:asciiname":"Azrou",
    "gn:country_code":"MA",
    "gn:dem":30,
    "gn:feature_class":"P",
    "gn:feature_code":"PPL",
    "gn:name":"Azrou",
    "gn:population":0,
    "gn:timezone":"Africa/Casablanca",
    "iso:country":"MA",
    "name:ara_x_preferred":[
        "\u0623\u0632\u0631\u0648"
    ],
    "name:azb_x_preferred":[
        "\u0627\u0632\u0631\u0648"
    ],
    "name:cat_x_preferred":[
        "Azrou"
    ],
    "name:ceb_x_preferred":[
        "Azrou"
    ],
    "name:ces_x_preferred":[
        "Azrou"
    ],
    "name:cym_x_preferred":[
        "Azrou"
    ],
    "name:deu_x_preferred":[
        "Azrou"
    ],
    "name:fas_x_preferred":[
        "\u0627\u0632\u0631\u0648"
    ],
    "name:fra_x_preferred":[
        "Azrou"
    ],
    "name:ita_x_preferred":[
        "Azrou"
    ],
    "name:kab_x_preferred":[
        "A\u1e93ru"
    ],
    "name:nld_x_preferred":[
        "Azrou"
    ],
    "name:por_x_preferred":[
        "Azrou"
    ],
    "name:ron_x_preferred":[
        "Azrou"
    ],
    "name:rus_x_preferred":[
        "\u0410\u0437\u0440\u0443"
    ],
    "name:spa_x_preferred":[
        "Azr\u00fa"
    ],
    "name:swe_x_preferred":[
        "Azrou"
    ],
    "name:zho_x_preferred":[
        "\u827e\u8332\u9b6f"
    ],
    "wof:name":"Azrou",
    "wof:placetype":"locality"
},
  "geometry": {"coordinates":[-9.45988,30.36222],"type":"Point"}
}