{
  "type": "Feature",
  "properties": {
    "gn:admin1_code":"07",
    "gn:asciiname":"Douar Drarat Rmel",
    "gn:country_code":"MA",
    "gn:dem":116,
    "gn:feature_class":"P",
    "gn:feature_code":"PPL",
    "gn:name":"Douar Drarat Rmel",
    "gn:population":0,
    "gn:timezone":"Africa/Casablanca",
    "iso:country":"MA",
    "name:und_x_variant":[
        "Rmal"
    ],
    "wof:name":"Douar Drarat Rmel",
    "wof:placetype":"locality"
},
  "geometry": {"coordinates":[-8.97809,32.51017],"type":"Point"}
}