{
  "type": "Feature",
  "properties": {
    "gn:admin1_code":"06",
    "gn:asciiname":"Dlalja",
    "gn:country_code":"MA",
    "gn:dem":276,
    "gn:feature_class":"P",
    "gn:feature_code":"PPL",
    "gn:name":"Dlalja",
    "gn:population":0,
    "gn:timezone":"Africa/Casablanca",
    "iso:country":"MA",
    "wof:name":"Dlalja",
    "wof:placetype":"locality"
},
  "geometry": {"coordinates":[-7.24417,33.36177],"type":"Point"}
}