{
  "type": "Feature",
  "properties": {
    "gn:admin1_code":"07",
    "gn:asciiname":"Oulad Bou Salah",
    "gn:country_code":"MA",
    "gn:dem":184,
    "gn:feature_class":"P",
    "gn:feature_code":"PPL",
    "gn:name":"Oulad Bou Salah",
    "gn:population":0,
    "gn:timezone":"Africa/Casablanca",
    "iso:country":"MA",
    "name:und_x_variant":[
        "Douar Oulad bou Salah",
        "Oulad Bou Salah"
    ],
    "wof:name":"Oulad Bou Salah",
    "wof:placetype":"locality"
},
  "geometry": {"coordinates":[-8.82515,32.35595],"type":"Point"}
}