{
  "type": "Feature",
  "properties": {
    "gn:admin1_code":"10",
    "gn:asciiname":"Dar Tiguigur",
    "gn:country_code":"MA",
    "gn:dem":361,
    "gn:feature_class":"P",
    "gn:feature_code":"PPL",
    "gn:name":"Dar Tiguigur",
    "gn:population":0,
    "gn:timezone":"Africa/Casablanca",
    "iso:country":"MA",
    "wof:name":"Dar Tiguigur",
    "wof:placetype":"locality"
},
  "geometry": {"coordinates":[-10.05,29.48],"type":"Point"}
}