{
  "type": "Feature",
  "properties": {
    "gn:admin1_code":"7.0",
    "gn:asciiname":"Douar Iahsera",
    "gn:country_code":"MA",
    "gn:dem":606,
    "gn:feature_class":"P",
    "gn:feature_code":"PPL",
    "gn:name":"Douar Iahsera",
    "gn:population":0,
    "gn:timezone":"Africa/Casablanca",
    "iso:country":"MA",
    "wof:name":"Douar Iahsera",
    "wof:placetype":"locality"
},
  "geometry": {"coordinates":[-7.84148,31.50385],"type":"Point"}
}