{
  "type": "Feature",
  "properties": {
    "gn:admin1_code":"7.0",
    "gn:asciiname":"Cooperative Teguemine Argane",
    "gn:country_code":"MA",
    "gn:dem":191,
    "gn:feature_class":"P",
    "gn:feature_code":"PPLF",
    "gn:name":"Coop\u00e9rative T\u00e9guemine Argane",
    "gn:population":0,
    "gn:timezone":"Africa/Casablanca",
    "iso:country":"MA",
    "wof:name":"Cooperative Teguemine Argane",
    "wof:placetype":"locality"
},
  "geometry": {"coordinates":[-9.62913,31.52186],"type":"Point"}
}