{
  "type": "Feature",
  "properties": {
    "gn:admin1_code":"01",
    "gn:asciiname":"Douar Ahourchane Lfoqiya",
    "gn:country_code":"MA",
    "gn:dem":340,
    "gn:feature_class":"P",
    "gn:feature_code":"PPL",
    "gn:name":"Douar Ahourchane Lfoqiya",
    "gn:population":0,
    "gn:timezone":"Africa/Casablanca",
    "iso:country":"MA",
    "name:und_x_variant":[
        "Ahouchane"
    ],
    "wof:name":"Douar Ahourchane Lfoqiya",
    "wof:placetype":"locality"
},
  "geometry": {"coordinates":[-5.60243,35.52735999999999],"type":"Point"}
}