{
  "type": "Feature",
  "properties": {
    "gn:admin1_code":"1.0",
    "gn:asciiname":"Douar Taarichane",
    "gn:country_code":"MA",
    "gn:dem":837,
    "gn:feature_class":"P",
    "gn:feature_code":"PPL",
    "gn:name":"Douar Taarichane",
    "gn:population":0,
    "gn:timezone":"Africa/Casablanca",
    "iso:country":"MA",
    "wof:name":"Douar Taarichane",
    "wof:placetype":"locality"
},
  "geometry": {"coordinates":[-5.04997,35.09323],"type":"Point"}
}