{
  "type": "Feature",
  "properties": {
    "gn:admin1_code":"07",
    "gn:asciiname":"Igourhane",
    "gn:country_code":"MA",
    "gn:dem":1552,
    "gn:feature_class":"P",
    "gn:feature_code":"PPL",
    "gn:name":"Igourhane",
    "gn:population":0,
    "gn:timezone":"Africa/Casablanca",
    "iso:country":"MA",
    "name:und_x_variant":[
        "Igourdane",
        "Igourhane"
    ],
    "wof:name":"Igourhane",
    "wof:placetype":"locality"
},
  "geometry": {"coordinates":[-8.66588,31.12348],"type":"Point"}
}