{
  "type": "Feature",
  "properties": {
    "gn:admin1_code":"03",
    "gn:asciiname":"Tellaka",
    "gn:country_code":"MA",
    "gn:dem":200,
    "gn:feature_class":"P",
    "gn:feature_code":"PPL",
    "gn:name":"Tellaka",
    "gn:population":0,
    "gn:timezone":"Africa/Casablanca",
    "iso:country":"MA",
    "wof:name":"Tellaka",
    "wof:placetype":"locality"
},
  "geometry": {"coordinates":[-5.12124,34.74589],"type":"Point"}
}