{
  "type": "Feature",
  "properties": {
    "gn:admin1_code":"10",
    "gn:asciiname":"Id Ou Bellouch",
    "gn:country_code":"MA",
    "gn:dem":817,
    "gn:feature_class":"P",
    "gn:feature_code":"PPL",
    "gn:name":"Id Ou Bellouch",
    "gn:population":0,
    "gn:timezone":"Africa/Casablanca",
    "iso:country":"MA",
    "name:und_x_variant":[
        "Id Harine"
    ],
    "wof:name":"Id Ou Bellouch",
    "wof:placetype":"locality"
},
  "geometry": {"coordinates":[-9.88042,29.30275],"type":"Point"}
}