{
  "type": "Feature",
  "properties": {
    "gn:admin1_code":"02",
    "gn:asciiname":"Dar el Kelaj",
    "gn:country_code":"MA",
    "gn:dem":205,
    "gn:feature_class":"P",
    "gn:feature_code":"PPL",
    "gn:name":"Dar el Kelaj",
    "gn:population":0,
    "gn:timezone":"Africa/Casablanca",
    "iso:country":"MA",
    "wof:name":"Dar el Kelaj",
    "wof:placetype":"locality"
},
  "geometry": {"coordinates":[-3.05043,34.9317],"type":"Point"}
}