{
  "type": "Feature",
  "properties": {
    "gn:admin1_code":"03",
    "gn:asciiname":"Douar Ouled Mimoun",
    "gn:country_code":"MA",
    "gn:dem":707,
    "gn:feature_class":"P",
    "gn:feature_code":"PPL",
    "gn:name":"Douar Ouled Mimoun",
    "gn:population":0,
    "gn:timezone":"Africa/Casablanca",
    "iso:country":"MA",
    "name:und_x_variant":[
        "Oulad Mimoun"
    ],
    "wof:name":"Douar Ouled Mimoun",
    "wof:placetype":"locality"
},
  "geometry": {"coordinates":[-4.24209,34.45595],"type":"Point"}
}