{
  "type": "Feature",
  "properties": {
    "gn:admin1_code":"3.0",
    "gn:asciiname":"Douar Chorfa Lakhrabiya",
    "gn:country_code":"MA",
    "gn:dem":465,
    "gn:feature_class":"P",
    "gn:feature_code":"PPL",
    "gn:name":"Douar Chorfa Lakhrabiya",
    "gn:population":0,
    "gn:timezone":"Africa/Casablanca",
    "iso:country":"MA",
    "wof:name":"Douar Chorfa Lakhrabiya",
    "wof:placetype":"locality"
},
  "geometry": {"coordinates":[-4.62129,34.15596],"type":"Point"}
}