{
  "type": "Feature",
  "properties": {
    "gn:admin1_code":"7.0",
    "gn:asciiname":"Ait Mazouz",
    "gn:country_code":"MA",
    "gn:dem":1197,
    "gn:feature_class":"P",
    "gn:feature_code":"PPL",
    "gn:name":"A\u00eft Mazouz",
    "gn:population":0,
    "gn:timezone":"Africa/Casablanca",
    "iso:country":"MA",
    "wof:name":"Ait Mazouz",
    "wof:placetype":"locality"
},
  "geometry": {"coordinates":[-9.21493,31.06064000000001],"type":"Point"}
}