{
  "type": "Feature",
  "properties": {
    "gn:admin1_code":"7.0",
    "gn:asciiname":"Douar Jdid",
    "gn:country_code":"MA",
    "gn:dem":174,
    "gn:feature_class":"P",
    "gn:feature_code":"PPL",
    "gn:name":"Douar Jdid",
    "gn:population":0,
    "gn:timezone":"Africa/Casablanca",
    "iso:country":"MA",
    "wof:name":"Douar Jdid",
    "wof:placetype":"locality"
},
  "geometry": {"coordinates":[-8.79353,32.33586],"type":"Point"}
}