{
  "type": "Feature",
  "properties": {
    "gn:admin1_code":"3.0",
    "gn:asciiname":"Douar Laqnasra",
    "gn:country_code":"MA",
    "gn:dem":227,
    "gn:feature_class":"P",
    "gn:feature_code":"PPL",
    "gn:name":"Douar Laqnasra",
    "gn:population":0,
    "gn:timezone":"Africa/Casablanca",
    "iso:country":"MA",
    "wof:name":"Douar Laqnasra",
    "wof:placetype":"locality"
},
  "geometry": {"coordinates":[-4.70082,34.22301],"type":"Point"}
}