{
  "type": "Feature",
  "properties": {
    "gn:country":"MA",
    "gn:fcode":"ADM3",
    "gn:population":13852,
    "iso:country":"MA",
    "name:ara_x_preferred":[
        "\u0648\u064a\u0633\u0644\u0627\u0646 (\u0627\u0644\u0628\u0644\u062f\u064a\u0629)"
    ],
    "name:ara_x_variant":[
        "\u062a\u0648\u0644\u0627\u0644"
    ],
    "name:cat_x_preferred":[
        "Toulal"
    ],
    "name:fra_x_preferred":[
        "Toulal"
    ],
    "name:fra_x_variant":[
        "Toulal (MU)",
        "Toulal (Commune Urbaine)"
    ],
    "qs_pg:aaroncc":"MA",
    "qs_pg:gn_country":"MA",
    "qs_pg:gn_fcode":"ADM3",
    "qs_pg:gn_pop":13852,
    "qs_pg:name":"Toulal",
    "qs_pg:photos_9r":0,
    "qs_pg:photos_sr":0,
    "qs_pg:pop_sr":6,
    "qs_pg:qs_pg_placetype":"localadmin",
    "wof:name":"Toulal",
    "wof:placetype":"localadmin",
    "wof:population":13852
},
  "geometry": {"coordinates":[-5.60214,33.89513],"type":"Point"}
}