{
  "type": "Feature",
  "properties": {
    "gn:admin1_code":"2.0",
    "gn:asciiname":"Issoussane",
    "gn:country_code":"MA",
    "gn:dem":605,
    "gn:feature_class":"P",
    "gn:feature_code":"PPL",
    "gn:name":"Issoussane",
    "gn:population":0,
    "gn:timezone":"Africa/Casablanca",
    "iso:country":"MA",
    "wof:name":"Issoussane",
    "wof:placetype":"locality"
},
  "geometry": {"coordinates":[-3.49701,35.11542],"type":"Point"}
}