{
  "type": "Feature",
  "properties": {
    "gn:admin1_code":"05",
    "gn:asciiname":"Ait el Haj",
    "gn:country_code":"MA",
    "gn:dem":812,
    "gn:feature_class":"P",
    "gn:feature_code":"PPL",
    "gn:name":"A\u00eft el Haj",
    "gn:population":0,
    "gn:timezone":"Africa/Casablanca",
    "iso:country":"MA",
    "name:und_x_variant":[
        "A\u00eft el Hajj",
        "A\u00eft el Haj"
    ],
    "wof:name":"Ait el Haj",
    "wof:placetype":"locality"
},
  "geometry": {"coordinates":[-7.24062,31.71218],"type":"Point"}
}