{
  "type": "Feature",
  "properties": {
    "gn:admin1_code":"9.0",
    "gn:asciiname":"Iggi Agdi",
    "gn:country_code":"MA",
    "gn:dem":16,
    "gn:feature_class":"P",
    "gn:feature_code":"PPL",
    "gn:name":"Iggi Agdi",
    "gn:population":0,
    "gn:timezone":"Africa/Casablanca",
    "iso:country":"MA",
    "wof:name":"Iggi Agdi",
    "wof:placetype":"locality"
},
  "geometry": {"coordinates":[-9.52487,30.32244],"type":"Point"}
}