{
  "type": "Feature",
  "properties": {
    "gn:admin1_code":"01",
    "gn:asciiname":"Kouebdana",
    "gn:country_code":"MA",
    "gn:dem":343,
    "gn:feature_class":"P",
    "gn:feature_code":"PPL",
    "gn:name":"Kouebdana",
    "gn:population":0,
    "gn:timezone":"Africa/Casablanca",
    "iso:country":"MA",
    "name:und_x_variant":[
        "Quebdana",
        "Kouebdana"
    ],
    "wof:name":"Kouebdana",
    "wof:placetype":"locality"
},
  "geometry": {"coordinates":[-5.44745,35.79142],"type":"Point"}
}