{
  "type": "Feature",
  "properties": {
    "gn:admin1_code":"7.0",
    "gn:asciiname":"Douar Echeguirine",
    "gn:country_code":"MA",
    "gn:dem":352,
    "gn:feature_class":"P",
    "gn:feature_code":"PPL",
    "gn:name":"Douar Echeguirine",
    "gn:population":0,
    "gn:timezone":"Africa/Casablanca",
    "iso:country":"MA",
    "wof:name":"Douar Echeguirine",
    "wof:placetype":"locality"
},
  "geometry": {"coordinates":[-8.72645,31.54689],"type":"Point"}
}