{
  "type": "Feature",
  "properties": {
    "gn:admin1_code":"01",
    "gn:asciiname":"Douar Aghriyine",
    "gn:country_code":"MA",
    "gn:dem":395,
    "gn:feature_class":"P",
    "gn:feature_code":"PPL",
    "gn:name":"Douar Aghriyine",
    "gn:population":0,
    "gn:timezone":"Africa/Casablanca",
    "iso:country":"MA",
    "name:und_x_variant":[
        "Agral"
    ],
    "wof:name":"Douar Aghriyine",
    "wof:placetype":"locality"
},
  "geometry": {"coordinates":[-5.61781,35.50265],"type":"Point"}
}