{
  "type": "Feature",
  "properties": {
    "gn:admin1_code":"2.0",
    "gn:asciiname":"Aghbal",
    "gn:country_code":"MA",
    "gn:dem":234,
    "gn:feature_class":"P",
    "gn:feature_code":"PPL",
    "gn:name":"Aghbal",
    "gn:population":0,
    "gn:timezone":"Africa/Casablanca",
    "iso:country":"MA",
    "name:ara_x_preferred":[
        "\u0623\u063a\u0628\u0627\u0644"
    ],
    "name:azb_x_preferred":[
        "\u0627\u063a\u0628\u0627\u0644"
    ],
    "name:fas_x_preferred":[
        "\u0627\u063a\u0628\u0627\u0644"
    ],
    "name:fra_x_preferred":[
        "Aghbal"
    ],
    "name:ita_x_preferred":[
        "Aghbal"
    ],
    "name:kab_x_preferred":[
        "A\u0263bal"
    ],
    "name:msa_x_preferred":[
        "Aghbal"
    ],
    "name:por_x_preferred":[
        "Aghbal"
    ],
    "name:ron_x_preferred":[
        "Aghbal"
    ],
    "name:spa_x_preferred":[
        "Aghbal"
    ],
    "name:urd_x_preferred":[
        "\u0627\u0642\u0628\u0627\u0644"
    ],
    "name:vie_x_preferred":[
        "Aghbal"
    ],
    "wof:name":"Aghbal",
    "wof:placetype":"locality"
},
  "geometry": {"coordinates":[-2.12666,34.93955],"type":"Point"}
}