{
  "type": "Feature",
  "properties": {
    "gn:admin1_code":"08",
    "gn:asciiname":"Ait Youl",
    "gn:country_code":"MA",
    "gn:dem":1582,
    "gn:feature_class":"P",
    "gn:feature_code":"PPL",
    "gn:name":"A\u00eft Youl",
    "gn:population":0,
    "gn:timezone":"Africa/Casablanca",
    "iso:country":"MA",
    "name:ara_x_preferred":[
        "\u0622\u064a\u062a \u064a\u0648\u0644"
    ],
    "name:azb_x_preferred":[
        "\u0622\u06cc\u062a \u06cc\u0648\u0644"
    ],
    "name:cat_x_preferred":[
        "Ait Youl"
    ],
    "name:ceb_x_preferred":[
        "Ait Youl"
    ],
    "name:fas_x_preferred":[
        "\u0622\u06cc\u062a \u06cc\u0648\u0644"
    ],
    "name:ita_x_preferred":[
        "Ait Youl"
    ],
    "name:swe_x_preferred":[
        "Ait Youl"
    ],
    "name:und_x_variant":[
        "A\u00eft Yous",
        "A\u00eft Youl"
    ],
    "wof:name":"Ait Youl",
    "wof:placetype":"locality"
},
  "geometry": {"coordinates":[-6.00768,31.41901],"type":"Point"}
}