{
  "type": "Feature",
  "properties": {
    "gn:admin1_code":"03",
    "gn:asciiname":"Douar Eddachra",
    "gn:country_code":"MA",
    "gn:dem":388,
    "gn:feature_class":"P",
    "gn:feature_code":"PPL",
    "gn:name":"Douar Eddachra",
    "gn:population":0,
    "gn:timezone":"Africa/Casablanca",
    "iso:country":"MA",
    "name:und_x_variant":[
        "Dachra",
        "Douar ed Dechra",
        "Douar Eddachra"
    ],
    "wof:name":"Douar Eddachra",
    "wof:placetype":"locality"
},
  "geometry": {"coordinates":[-5.33122,34.32853],"type":"Point"}
}