{
  "type": "Feature",
  "properties": {
    "gn:admin1_code":"7.0",
    "gn:asciiname":"Tabya",
    "gn:country_code":"MA",
    "gn:dem":1140,
    "gn:feature_class":"P",
    "gn:feature_code":"PPL",
    "gn:name":"Tabya",
    "gn:population":0,
    "gn:timezone":"Africa/Casablanca",
    "iso:country":"MA",
    "wof:name":"Tabya",
    "wof:placetype":"locality"
},
  "geometry": {"coordinates":[-8.92139,31.13127],"type":"Point"}
}