{
  "type": "Feature",
  "properties": {
    "gn:admin1_code":"07",
    "gn:asciiname":"Arhbalou",
    "gn:country_code":"MA",
    "gn:dem":1438,
    "gn:feature_class":"P",
    "gn:feature_code":"PPL",
    "gn:name":"Arhbalou",
    "gn:population":0,
    "gn:timezone":"Africa/Casablanca",
    "iso:country":"MA",
    "name:und_x_variant":[
        "Aghballou",
        "Arhbalou"
    ],
    "wof:name":"Arhbalou",
    "wof:placetype":"locality"
},
  "geometry": {"coordinates":[-9.21845,30.81893],"type":"Point"}
}