{
  "type": "Feature",
  "properties": {
    "gn:admin1_code":"7.0",
    "gn:asciiname":"Wadaker",
    "gn:country_code":"MA",
    "gn:dem":1045,
    "gn:feature_class":"P",
    "gn:feature_code":"PPL",
    "gn:name":"Wadaker",
    "gn:population":0,
    "gn:timezone":"Africa/Casablanca",
    "iso:country":"MA",
    "wof:name":"Wadaker",
    "wof:placetype":"locality"
},
  "geometry": {"coordinates":[-8.26814,31.21558],"type":"Point"}
}