{
  "type": "Feature",
  "properties": {
    "gn:admin1_code":"9.0",
    "gn:asciiname":"Taoujgalt",
    "gn:country_code":"MA",
    "gn:dem":893,
    "gn:feature_class":"P",
    "gn:feature_code":"PPL",
    "gn:name":"Taoujgalt",
    "gn:population":0,
    "gn:timezone":"Africa/Casablanca",
    "iso:country":"MA",
    "wof:name":"Taoujgalt",
    "wof:placetype":"locality"
},
  "geometry": {"coordinates":[-8.77832,30.25294],"type":"Point"}
}