{
  "type": "Feature",
  "properties": {
    "gn:admin1_code":"9.0",
    "gn:asciiname":"Tawriyrt Wazlghiwn",
    "gn:country_code":"MA",
    "gn:dem":1002,
    "gn:feature_class":"P",
    "gn:feature_code":"PPL",
    "gn:name":"Tawriyrt Wazlghiwn",
    "gn:population":0,
    "gn:timezone":"Africa/Casablanca",
    "iso:country":"MA",
    "wof:name":"Tawriyrt Wazlghiwn",
    "wof:placetype":"locality"
},
  "geometry": {"coordinates":[-9.18971,29.58933],"type":"Point"}
}