{
  "type": "Feature",
  "properties": {
    "gn:country":"MA",
    "gn:fcode":"ADM3",
    "gn:population":14000,
    "iso:country":"MA",
    "name:ara_x_preferred":[
        "\u0627\u0632\u0646\u0627\u0643\u0646"
    ],
    "name:fra_x_preferred":[
        "Ighrem N Ougdal"
    ],
    "name:fra_x_variant":[
        "Ighrem N Ougdal (CR)",
        "Ighrem N Ougdal (Commune Rurale)"
    ],
    "qs_pg:aaroncc":"MA",
    "qs_pg:gn_country":"MA",
    "qs_pg:gn_fcode":"ADM3",
    "qs_pg:gn_pop":14000,
    "qs_pg:name":"Ighrem N Ougdal",
    "qs_pg:photos_9r":0,
    "qs_pg:photos_sr":0,
    "qs_pg:pop_sr":6,
    "qs_pg:qs_pg_placetype":"localadmin",
    "wof:name":"Ighrem N Ougdal",
    "wof:placetype":"localadmin",
    "wof:population":14000
},
  "geometry": {"coordinates":[-7.41413,31.19393],"type":"Point"}
}