{
  "type": "Feature",
  "properties": {
    "gn:admin1_code":"09",
    "gn:asciiname":"Ddou Dad",
    "gn:country_code":"MA",
    "gn:dem":1518,
    "gn:feature_class":"P",
    "gn:feature_code":"PPL",
    "gn:name":"Ddou Dad",
    "gn:population":0,
    "gn:timezone":"Africa/Casablanca",
    "iso:country":"MA",
    "name:und_x_variant":[
        "Azourane"
    ],
    "wof:name":"Ddou Dad",
    "wof:placetype":"locality"
},
  "geometry": {"coordinates":[-9.11064,29.75749],"type":"Point"}
}