{
  "type": "Feature",
  "properties": {
    "gn:admin1_code":"4.0",
    "gn:asciiname":"Douar El Haytem",
    "gn:country_code":"MA",
    "gn:dem":80,
    "gn:feature_class":"P",
    "gn:feature_code":"PPL",
    "gn:name":"Douar El Haytem",
    "gn:population":0,
    "gn:timezone":"Africa/Casablanca",
    "iso:country":"MA",
    "wof:name":"Douar El Haytem",
    "wof:placetype":"locality"
},
  "geometry": {"coordinates":[-5.75504,34.69266],"type":"Point"}
}