{
  "type": "Feature",
  "properties": {
    "gn:admin1_code":"7.0",
    "gn:asciiname":"Ait Sidi Hammou",
    "gn:country_code":"MA",
    "gn:dem":680,
    "gn:feature_class":"P",
    "gn:feature_code":"PPL",
    "gn:name":"A\u00eft Sidi Hammou",
    "gn:population":0,
    "gn:timezone":"Africa/Casablanca",
    "iso:country":"MA",
    "wof:name":"Ait Sidi Hammou",
    "wof:placetype":"locality"
},
  "geometry": {"coordinates":[-9.1659,31.3819],"type":"Point"}
}