{
  "type": "Feature",
  "properties": {
    "gn:admin1_code":"05",
    "gn:asciiname":"Sidi Ammat",
    "gn:country_code":"MA",
    "gn:dem":900,
    "gn:feature_class":"P",
    "gn:feature_code":"PPL",
    "gn:name":"Sidi Ammat",
    "gn:population":0,
    "gn:timezone":"Africa/Casablanca",
    "iso:country":"MA",
    "wof:name":"Sidi Ammat",
    "wof:placetype":"locality"
},
  "geometry": {"coordinates":[-5.83,32.95],"type":"Point"}
}