{
  "type": "Feature",
  "properties": {
    "gn:admin1_code":"09",
    "gn:asciiname":"Aguerd",
    "gn:country_code":"MA",
    "gn:dem":1306,
    "gn:feature_class":"P",
    "gn:feature_code":"PPL",
    "gn:name":"Aguerd",
    "gn:population":0,
    "gn:timezone":"Africa/Casablanca",
    "iso:country":"MA",
    "name:ara_x_preferred":[
        "\u0623\u0643\u0631\u0636"
    ],
    "name:azb_x_preferred":[
        "\u0627\u0642\u0648\u0631\u062f"
    ],
    "name:cat_x_preferred":[
        "Aguerd"
    ],
    "name:ceb_x_preferred":[
        "Aguerd"
    ],
    "name:fas_x_preferred":[
        "\u0627\u06af\u0648\u0631\u062f"
    ],
    "name:fin_x_preferred":[
        "Aguerd"
    ],
    "name:ita_x_preferred":[
        "Aguerd"
    ],
    "name:swe_x_preferred":[
        "Aguerd"
    ],
    "name:urd_x_preferred":[
        "\u0627\u06af\u0648\u0631\u062f"
    ],
    "wof:name":"Aguerd",
    "wof:placetype":"locality"
},
  "geometry": {"coordinates":[-8.76527,30.77785],"type":"Point"}
}