{
  "type": "Feature",
  "properties": {
    "gn:admin1_code":"2.0",
    "gn:asciiname":"Douar Bou Amoud",
    "gn:country_code":"MA",
    "gn:dem":246,
    "gn:feature_class":"P",
    "gn:feature_code":"PPL",
    "gn:name":"Douar Bou Amoud",
    "gn:population":0,
    "gn:timezone":"Africa/Casablanca",
    "iso:country":"MA",
    "wof:name":"Douar Bou Amoud",
    "wof:placetype":"locality"
},
  "geometry": {"coordinates":[-2.23954,34.91897],"type":"Point"}
}