{
  "type": "Feature",
  "properties": {
    "gn:admin1_code":"06",
    "gn:asciiname":"Bir Louard",
    "gn:country_code":"MA",
    "gn:dem":382,
    "gn:feature_class":"P",
    "gn:feature_code":"PPL",
    "gn:name":"Bir Louard",
    "gn:population":0,
    "gn:timezone":"Africa/Casablanca",
    "iso:country":"MA",
    "name:und_x_variant":[
        "Bir el Ouard"
    ],
    "wof:name":"Bir Louard",
    "wof:placetype":"locality"
},
  "geometry": {"coordinates":[-7.01982,33.3144],"type":"Point"}
}