{
  "type": "Feature",
  "properties": {
    "gn:admin1_code":"7.0",
    "gn:asciiname":"La'wissat",
    "gn:country_code":"MA",
    "gn:dem":58,
    "gn:feature_class":"P",
    "gn:feature_code":"PPL",
    "gn:name":"La\u2019wissat",
    "gn:population":0,
    "gn:timezone":"Africa/Casablanca",
    "iso:country":"MA",
    "wof:name":"La'wissat",
    "wof:placetype":"locality"
},
  "geometry": {"coordinates":[-9.32438,32.08448],"type":"Point"}
}