{
  "type": "Feature",
  "properties": {
    "gn:admin1_code":"1.0",
    "gn:asciiname":"Lemhalla",
    "gn:country_code":"MA",
    "gn:dem":192,
    "gn:feature_class":"P",
    "gn:feature_code":"PPL",
    "gn:name":"Lemhalla",
    "gn:population":0,
    "gn:timezone":"Africa/Casablanca",
    "iso:country":"MA",
    "wof:name":"Lemhalla",
    "wof:placetype":"locality"
},
  "geometry": {"coordinates":[-5.63858,35.73238],"type":"Point"}
}