{
  "type": "Feature",
  "properties": {
    "gn:admin1_code":"07",
    "gn:asciiname":"Douar el Karia",
    "gn:country_code":"MA",
    "gn:dem":618,
    "gn:feature_class":"P",
    "gn:feature_code":"PPL",
    "gn:name":"Douar el Karia",
    "gn:population":0,
    "gn:timezone":"Africa/Casablanca",
    "iso:country":"MA",
    "name:und_x_variant":[
        "El Qariya",
        "Douar el Karia",
        "El Karia"
    ],
    "wof:name":"Douar el Karia",
    "wof:placetype":"locality"
},
  "geometry": {"coordinates":[-8.22819,31.44056],"type":"Point"}
}