{
  "type": "Feature",
  "properties": {
    "gn:admin1_code":"05",
    "gn:admin2_code":"301.0",
    "gn:admin3_code":"1330103112.0",
    "gn:asciiname":"Sidi Yahya Ou Saad",
    "gn:country_code":"MA",
    "gn:dem":1484,
    "gn:feature_class":"P",
    "gn:feature_code":"PPLA3",
    "gn:name":"Sidi Yahya Ou Saad",
    "gn:population":0,
    "gn:timezone":"Africa/Casablanca",
    "iso:country":"MA",
    "name:ara_x_preferred":[
        "\u0633\u064a\u062f\u064a \u064a\u062d\u064a\u0649 \u0623\u0648 \u0633\u0627\u0639\u062f"
    ],
    "name:cat_x_preferred":[
        "Sidi Yahya Ou Saad"
    ],
    "name:ceb_x_preferred":[
        "Sidi Yahya Ou Saad"
    ],
    "name:ita_x_preferred":[
        "Sidi Yahya Ou Saad"
    ],
    "name:swe_x_preferred":[
        "Sidi Yahya Ou Saad"
    ],
    "name:und_x_variant":[
        "Sidi Yahya Ou Saoua",
        "Sidi yahya ou saoud",
        "Sidi Yahya Ou Saad"
    ],
    "wof:name":"Sidi Yahya Ou Saad",
    "wof:placetype":"locality"
},
  "geometry": {"coordinates":[-5.57738,32.68011],"type":"Point"}
}