{
  "type": "Feature",
  "properties": {
    "gn:admin1_code":"4.0",
    "gn:asciiname":"Douar Ain Ogla",
    "gn:country_code":"MA",
    "gn:dem":565,
    "gn:feature_class":"P",
    "gn:feature_code":"PPL",
    "gn:name":"Douar Ain Ogla",
    "gn:population":0,
    "gn:timezone":"Africa/Casablanca",
    "iso:country":"MA",
    "wof:name":"Douar Ain Ogla",
    "wof:placetype":"locality"
},
  "geometry": {"coordinates":[-6.34725,33.56725],"type":"Point"}
}