{
  "type": "Feature",
  "properties": {
    "gn:country":"MA",
    "gn:fcode":"ADM3",
    "gn:population":8042,
    "iso:country":"MA",
    "name:ara_x_preferred":[
        "\u0634\u0643\u0631\u0627\u0646"
    ],
    "name:ara_x_variant":[
        "\u0628\u0627\u0628 \u062a\u064a\u0648\u0643\u0627"
    ],
    "name:cat_x_preferred":[
        "Bab Tiouka"
    ],
    "name:eng_x_preferred":[
        "Bab Tiouka"
    ],
    "name:fra_x_preferred":[
        "Bab Tiouka"
    ],
    "name:fra_x_variant":[
        "Bab Tiouka (CR)",
        "Bab Tiouka (Commune Rurale)"
    ],
    "name:ita_x_preferred":[
        "Bab Tiouka"
    ],
    "qs:name":"Bab Tiouka",
    "qs:photos_9r":0,
    "qs:photos_sr":0,
    "qs:pop_sr":"5",
    "wd:wordcount":63,
    "wof:name":"Bab Tiouka",
    "wof:placetype":"localadmin",
    "wof:population":8042
},
  "geometry": {"coordinates":[-5.62681,34.21395],"type":"Point"}
}