{
  "type": "Feature",
  "properties": {
    "gn:admin1_code":"01",
    "gn:asciiname":"Mouara er Rmel",
    "gn:country_code":"MA",
    "gn:dem":59,
    "gn:feature_class":"P",
    "gn:feature_code":"PPL",
    "gn:name":"Mouara er Rmel",
    "gn:population":0,
    "gn:timezone":"Africa/Casablanca",
    "iso:country":"MA",
    "wof:name":"Mouara er Rmel",
    "wof:placetype":"locality"
},
  "geometry": {"coordinates":[-6.12199,35.06591],"type":"Point"}
}