{
  "type": "Feature",
  "properties": {
    "gn:admin1_code":"7.0",
    "gn:asciiname":"Dar Abdellah Chaker",
    "gn:country_code":"MA",
    "gn:dem":157,
    "gn:feature_class":"P",
    "gn:feature_code":"PPL",
    "gn:name":"Dar Abdellah Chaker",
    "gn:population":0,
    "gn:timezone":"Africa/Casablanca",
    "iso:country":"MA",
    "wof:name":"Dar Abdellah Chaker",
    "wof:placetype":"locality"
},
  "geometry": {"coordinates":[-9.62974,31.54513],"type":"Point"}
}