{
  "type": "Feature",
  "properties": {
    "gn:admin1_code":"09",
    "gn:asciiname":"Agafai",
    "gn:country_code":"MA",
    "gn:dem":211,
    "gn:feature_class":"P",
    "gn:feature_code":"PPL",
    "gn:name":"Agafa\u00ef",
    "gn:population":0,
    "gn:timezone":"Africa/Casablanca",
    "iso:country":"MA",
    "name:und_x_variant":[
        "Agafaye",
        "Agafa\u00ef"
    ],
    "wof:name":"Agafai",
    "wof:placetype":"locality"
},
  "geometry": {"coordinates":[-8.92753,30.39981],"type":"Point"}
}