{
  "type": "Feature",
  "properties": {
    "gn:admin1_code":"05",
    "gn:asciiname":"Ghougoult",
    "gn:country_code":"MA",
    "gn:dem":1888,
    "gn:elevation":"0.0",
    "gn:feature_class":"P",
    "gn:feature_code":"PPL",
    "gn:name":"Ghougoult",
    "gn:population":0,
    "gn:timezone":"Africa/Casablanca",
    "iso:country":"MA",
    "wof:name":"Ghougoult",
    "wof:placetype":"locality"
},
  "geometry": {"coordinates":[-6.59917,31.55435],"type":"Point"}
}