{
  "type": "Feature",
  "properties": {
    "gn:admin1_code":"1.0",
    "gn:asciiname":"Izarchiouene",
    "gn:country_code":"MA",
    "gn:dem":764,
    "gn:feature_class":"P",
    "gn:feature_code":"PPL",
    "gn:name":"Izarchiouene",
    "gn:population":0,
    "gn:timezone":"Africa/Casablanca",
    "iso:country":"MA",
    "wof:name":"Izarchiouene",
    "wof:placetype":"locality"
},
  "geometry": {"coordinates":[-3.88896,35.02984],"type":"Point"}
}