{
  "type": "Feature",
  "properties": {
    "gn:admin1_code":"6.0",
    "gn:asciiname":"Dar Haj El Arbi",
    "gn:country_code":"MA",
    "gn:dem":438,
    "gn:feature_class":"P",
    "gn:feature_code":"PPL",
    "gn:name":"Dar Haj El Arbi",
    "gn:population":0,
    "gn:timezone":"Africa/Casablanca",
    "iso:country":"MA",
    "wof:name":"Dar Haj El Arbi",
    "wof:placetype":"locality"
},
  "geometry": {"coordinates":[-7.70561,32.97629000000001],"type":"Point"}
}