{
  "type": "Feature",
  "properties": {
    "gn:admin1_code":"09",
    "gn:asciiname":"Wawzougart",
    "gn:country_code":"MA",
    "gn:dem":1463,
    "gn:feature_class":"P",
    "gn:feature_code":"PPL",
    "gn:name":"Wawzougart",
    "gn:population":0,
    "gn:timezone":"Africa/Casablanca",
    "iso:country":"MA",
    "name:und_x_variant":[
        "Ouaouzouart",
        "Ouaouzgarte",
        "Ouaouzougart",
        "Wawzougart"
    ],
    "wof:name":"Wawzougart",
    "wof:placetype":"locality"
},
  "geometry": {"coordinates":[-7.84844,30.80058],"type":"Point"}
}