{
  "type": "Feature",
  "properties": {
    "gn:admin1_code":"09",
    "gn:asciiname":"Tamelalt",
    "gn:country_code":"MA",
    "gn:dem":283,
    "gn:feature_class":"P",
    "gn:feature_code":"PPL",
    "gn:name":"Tamelalt",
    "gn:population":0,
    "gn:timezone":"Africa/Casablanca",
    "iso:country":"MA",
    "name:und_x_variant":[
        "Tamlalt",
        "Tamelalt"
    ],
    "wof:name":"Tamelalt",
    "wof:placetype":"locality"
},
  "geometry": {"coordinates":[-9.92271,29.69523],"type":"Point"}
}