{
  "type": "Feature",
  "properties": {
    "gn:admin1_code":"7.0",
    "gn:asciiname":"Sidi Mohamed Ben Ali",
    "gn:country_code":"MA",
    "gn:dem":93,
    "gn:feature_class":"P",
    "gn:feature_code":"PPL",
    "gn:name":"Sidi Mohamed Ben Ali",
    "gn:population":0,
    "gn:timezone":"Africa/Casablanca",
    "iso:country":"MA",
    "wof:name":"Sidi Mohamed Ben Ali",
    "wof:placetype":"locality"
},
  "geometry": {"coordinates":[-9.24174,32.41918],"type":"Point"}
}