{
  "type": "Feature",
  "properties": {
    "gn:admin1_code":"1.0",
    "gn:asciiname":"Douar Aremzane",
    "gn:country_code":"MA",
    "gn:dem":1032,
    "gn:feature_class":"P",
    "gn:feature_code":"PPL",
    "gn:name":"Douar Aremzane",
    "gn:population":0,
    "gn:timezone":"Africa/Casablanca",
    "iso:country":"MA",
    "wof:name":"Douar Aremzane",
    "wof:placetype":"locality"
},
  "geometry": {"coordinates":[-4.24902,35.00605],"type":"Point"}
}