{
  "type": "Feature",
  "properties": {
    "gn:admin1_code":"1.0",
    "gn:asciiname":"Ain Allou",
    "gn:country_code":"MA",
    "gn:dem":303,
    "gn:feature_class":"P",
    "gn:feature_code":"PPL",
    "gn:name":"Ain Allou",
    "gn:population":0,
    "gn:timezone":"Africa/Casablanca",
    "iso:country":"MA",
    "wof:name":"Ain Allou",
    "wof:placetype":"locality"
},
  "geometry": {"coordinates":[-5.51732,35.79744],"type":"Point"}
}