{
  "type": "Feature",
  "properties": {
    "gn:admin1_code":"02",
    "gn:asciiname":"Assaqqif",
    "gn:country_code":"MA",
    "gn:dem":7,
    "gn:feature_class":"P",
    "gn:feature_code":"PPL",
    "gn:name":"Assaqqif",
    "gn:population":0,
    "gn:timezone":"Africa/Casablanca",
    "iso:country":"MA",
    "wof:name":"Assaqqif",
    "wof:placetype":"locality"
},
  "geometry": {"coordinates":[-3.75795,35.26251],"type":"Point"}
}