{
  "type": "Feature",
  "properties": {
    "gn:admin1_code":"9.0",
    "gn:asciiname":"Imzizwi",
    "gn:country_code":"MA",
    "gn:dem":1010,
    "gn:feature_class":"P",
    "gn:feature_code":"PPL",
    "gn:name":"Imzizwi",
    "gn:population":0,
    "gn:timezone":"Africa/Casablanca",
    "iso:country":"MA",
    "wof:name":"Imzizwi",
    "wof:placetype":"locality"
},
  "geometry": {"coordinates":[-7.93866,30.53207],"type":"Point"}
}