{
  "type": "Feature",
  "properties": {
    "gn:admin1_code":"9.0",
    "gn:asciiname":"Tafandt",
    "gn:country_code":"MA",
    "gn:dem":44,
    "gn:feature_class":"P",
    "gn:feature_code":"PPL",
    "gn:name":"Tafandt",
    "gn:population":0,
    "gn:timezone":"Africa/Casablanca",
    "iso:country":"MA",
    "wof:name":"Tafandt",
    "wof:placetype":"locality"
},
  "geometry": {"coordinates":[-9.42186,30.36634],"type":"Point"}
}