{
  "type": "Feature",
  "properties": {
    "gn:admin1_code":"7.0",
    "gn:asciiname":"Oulad Ben Yamna",
    "gn:country_code":"MA",
    "gn:dem":496,
    "gn:feature_class":"P",
    "gn:feature_code":"PPL",
    "gn:name":"Oulad Ben Yamna",
    "gn:population":0,
    "gn:timezone":"Africa/Casablanca",
    "iso:country":"MA",
    "wof:name":"Oulad Ben Yamna",
    "wof:placetype":"locality"
},
  "geometry": {"coordinates":[-9.03759,31.96391],"type":"Point"}
}