{
  "type": "Feature",
  "properties": {
    "gn:admin1_code":"05",
    "gn:asciiname":"Ayt Mansour",
    "gn:country_code":"MA",
    "gn:dem":833,
    "gn:feature_class":"P",
    "gn:feature_code":"PPL",
    "gn:name":"Ayt Mansour",
    "gn:population":0,
    "gn:timezone":"Africa/Casablanca",
    "iso:country":"MA",
    "name:und_x_variant":[
        "A\u00eft Mansour"
    ],
    "wof:name":"Ayt Mansour",
    "wof:placetype":"locality"
},
  "geometry": {"coordinates":[-6.74673,32.08597],"type":"Point"}
}