{
  "type": "Feature",
  "properties": {
    "gn:admin1_code":"01",
    "gn:asciiname":"Oulad Sidi Abdelkader",
    "gn:country_code":"MA",
    "gn:dem":132,
    "gn:feature_class":"P",
    "gn:feature_code":"PPL",
    "gn:name":"Oulad Sidi Abdelkader",
    "gn:population":0,
    "gn:timezone":"Africa/Casablanca",
    "iso:country":"MA",
    "name:und_x_variant":[
        "Kader",
        "Oulad Sidi Abdelkader"
    ],
    "wof:name":"Oulad Sidi Abdelkader",
    "wof:placetype":"locality"
},
  "geometry": {"coordinates":[-5.87812,35.47464],"type":"Point"}
}