{
  "type": "Feature",
  "properties": {
    "gn:admin1_code":"07",
    "gn:asciiname":"Oulad Friha",
    "gn:country_code":"MA",
    "gn:dem":369,
    "gn:feature_class":"P",
    "gn:feature_code":"PPL",
    "gn:name":"Oulad Friha",
    "gn:population":0,
    "gn:timezone":"Africa/Casablanca",
    "iso:country":"MA",
    "wof:name":"Oulad Friha",
    "wof:placetype":"locality"
},
  "geometry": {"coordinates":[-9.18708,31.63741],"type":"Point"}
}