{
  "type": "Feature",
  "properties": {
    "gn:admin1_code":"07",
    "gn:asciiname":"Douar Mreys Errmad",
    "gn:country_code":"MA",
    "gn:dem":485,
    "gn:feature_class":"P",
    "gn:feature_code":"PPL",
    "gn:name":"Douar Mreys Errmad",
    "gn:population":0,
    "gn:timezone":"Africa/Casablanca",
    "iso:country":"MA",
    "name:und_x_variant":[
        "Douar el Hajj el Madani",
        "El Hajj el Madani",
        "El Haj el Madani",
        "Douar Mreys Errmad"
    ],
    "wof:name":"Douar Mreys Errmad",
    "wof:placetype":"locality"
},
  "geometry": {"coordinates":[-8.07,31.94558],"type":"Point"}
}