{
  "type": "Feature",
  "properties": {
    "gn:admin1_code":"04",
    "gn:asciiname":"Douar Lbastyoune",
    "gn:country_code":"MA",
    "gn:dem":170,
    "gn:feature_class":"P",
    "gn:feature_code":"PPL",
    "gn:name":"Douar Lbastyoune",
    "gn:population":0,
    "gn:timezone":"Africa/Casablanca",
    "iso:country":"MA",
    "name:und_x_variant":[
        "Bestioune",
        "Bastioun",
        "Douar Lbastyoune"
    ],
    "wof:name":"Douar Lbastyoune",
    "wof:placetype":"locality"
},
  "geometry": {"coordinates":[-5.86319,34.90244000000001],"type":"Point"}
}