{
  "type": "Feature",
  "properties": {
    "gn:admin1_code":"04",
    "gn:asciiname":"Lemaadga",
    "gn:country_code":"MA",
    "gn:dem":16,
    "gn:feature_class":"P",
    "gn:feature_code":"PPL",
    "gn:name":"Lemaadga",
    "gn:population":0,
    "gn:timezone":"Africa/Casablanca",
    "iso:country":"MA",
    "name:und_x_variant":[
        "Douar el Ma\u00e2tga",
        "Ma\u00e2tga",
        "Lemaadga"
    ],
    "wof:name":"Lemaadga",
    "wof:placetype":"locality"
},
  "geometry": {"coordinates":[-6.10046,34.60308],"type":"Point"}
}