{
  "type": "Feature",
  "properties": {
    "gn:admin1_code":"2.0",
    "gn:asciiname":"Douar Khreb",
    "gn:country_code":"MA",
    "gn:dem":581,
    "gn:feature_class":"P",
    "gn:feature_code":"PPL",
    "gn:name":"Douar Khreb",
    "gn:population":0,
    "gn:timezone":"Africa/Casablanca",
    "iso:country":"MA",
    "wof:name":"Douar Khreb",
    "wof:placetype":"locality"
},
  "geometry": {"coordinates":[-1.79022,34.69432],"type":"Point"}
}