{
  "type": "Feature",
  "properties": {
    "gn:admin1_code":"11",
    "gn:admin2_code":"121.0",
    "gn:asciiname":"Akhfennir",
    "gn:country_code":"MA",
    "gn:dem":15,
    "gn:feature_class":"P",
    "gn:feature_code":"PPL",
    "gn:name":"Akhfennir",
    "gn:population":1583,
    "gn:timezone":"Africa/Casablanca",
    "iso:country":"MA",
    "name:ara_x_preferred":[
        "\u0623\u062e\u0641\u0646\u064a\u0631"
    ],
    "name:cat_x_preferred":[
        "Akhfennir"
    ],
    "name:ita_x_preferred":[
        "Akhfennir"
    ],
    "wof:name":"Akhfennir",
    "wof:placetype":"locality",
    "wof:population":1583
},
  "geometry": {"coordinates":[-12.05157,28.09455],"type":"Point"}
}