{
  "type": "Feature",
  "properties": {
    "gn:admin1_code":"7.0",
    "gn:asciiname":"Douar Lekkir",
    "gn:country_code":"MA",
    "gn:dem":488,
    "gn:feature_class":"P",
    "gn:feature_code":"PPL",
    "gn:name":"Douar Lekkir",
    "gn:population":0,
    "gn:timezone":"Africa/Casablanca",
    "iso:country":"MA",
    "name:und_x_variant":[
        "Douar bel Rhanodour"
    ],
    "wof:name":"Douar Lekkir",
    "wof:placetype":"locality"
},
  "geometry": {"coordinates":[-7.81421,31.63468],"type":"Point"}
}