{
  "type": "Feature",
  "properties": {
    "gn:admin1_code":"07",
    "gn:asciiname":"Toualeb",
    "gn:country_code":"MA",
    "gn:dem":465,
    "gn:feature_class":"P",
    "gn:feature_code":"PPL",
    "gn:name":"Toualeb",
    "gn:population":0,
    "gn:timezone":"Africa/Casablanca",
    "iso:country":"MA",
    "name:und_x_variant":[
        "Douar et Toualeb",
        "Toualeb"
    ],
    "wof:name":"Toualeb",
    "wof:placetype":"locality"
},
  "geometry": {"coordinates":[-8.01629,32.26343],"type":"Point"}
}