{
  "type": "Feature",
  "properties": {
    "gn:admin1_code":"1.0",
    "gn:asciiname":"Moulay Abderrahmane",
    "gn:country_code":"MA",
    "gn:dem":432,
    "gn:feature_class":"P",
    "gn:feature_code":"PPL",
    "gn:name":"Moulay Abderrahmane",
    "gn:population":0,
    "gn:timezone":"Africa/Casablanca",
    "iso:country":"MA",
    "wof:name":"Moulay Abderrahmane",
    "wof:placetype":"locality"
},
  "geometry": {"coordinates":[-5.13381,34.80463],"type":"Point"}
}