{
  "type": "Feature",
  "properties": {
    "gn:admin1_code":"4.0",
    "gn:asciiname":"Ait Mhammed 'Abdallah",
    "gn:country_code":"MA",
    "gn:dem":435,
    "gn:feature_class":"P",
    "gn:feature_code":"PPL",
    "gn:name":"A\u00eft Mhammed \u2019Abdallah",
    "gn:population":0,
    "gn:timezone":"Africa/Casablanca",
    "iso:country":"MA",
    "wof:name":"Ait Mhammed 'Abdallah",
    "wof:placetype":"locality"
},
  "geometry": {"coordinates":[-6.32214,33.78799],"type":"Point"}
}