{
  "type": "Feature",
  "properties": {
    "gn:admin1_code":"7.0",
    "gn:asciiname":"Agouram",
    "gn:country_code":"MA",
    "gn:dem":2059,
    "gn:feature_class":"P",
    "gn:feature_code":"PPL",
    "gn:name":"Agouram",
    "gn:population":0,
    "gn:timezone":"Africa/Casablanca",
    "iso:country":"MA",
    "wof:name":"Agouram",
    "wof:placetype":"locality"
},
  "geometry": {"coordinates":[-7.54552,31.32986],"type":"Point"}
}