{
  "type": "Feature",
  "properties": {
    "gn:admin1_code":"08",
    "gn:asciiname":"Asfalou",
    "gn:country_code":"MA",
    "gn:dem":1302,
    "gn:feature_class":"P",
    "gn:feature_code":"PPL",
    "gn:name":"Asfalou",
    "gn:population":0,
    "gn:timezone":"Africa/Casablanca",
    "iso:country":"MA",
    "wof:name":"Asfalou",
    "wof:placetype":"locality"
},
  "geometry": {"coordinates":[-7.14333,31.06599000000001],"type":"Point"}
}