{
  "type": "Feature",
  "properties": {
    "gn:admin1_code":"01",
    "gn:asciiname":"Aila",
    "gn:country_code":"MA",
    "gn:dem":395,
    "gn:feature_class":"P",
    "gn:feature_code":"PPL",
    "gn:name":"A\u00efla",
    "gn:population":0,
    "gn:timezone":"Africa/Casablanca",
    "iso:country":"MA",
    "name:ceb_x_preferred":[
        "Aila"
    ],
    "name:deu_x_preferred":[
        "Aila"
    ],
    "name:fra_x_preferred":[
        "Aila"
    ],
    "name:nld_x_preferred":[
        "Aila"
    ],
    "name:swe_x_preferred":[
        "Aila"
    ],
    "wof:name":"Aila",
    "wof:placetype":"locality"
},
  "geometry": {"coordinates":[-5.31856,35.02994],"type":"Point"}
}