{
  "type": "Feature",
  "properties": {
    "gn:admin1_code":"5.0",
    "gn:asciiname":"Dar Mser ben Ferich",
    "gn:country_code":"MA",
    "gn:dem":809,
    "gn:feature_class":"P",
    "gn:feature_code":"PPL",
    "gn:name":"Dar Mser ben Ferich",
    "gn:population":0,
    "gn:timezone":"Africa/Casablanca",
    "iso:country":"MA",
    "wof:name":"Dar Mser ben Ferich",
    "wof:placetype":"locality"
},
  "geometry": {"coordinates":[-6.6977,32.93339],"type":"Point"}
}