{
  "type": "Feature",
  "properties": {
    "gn:admin1_code":"7.0",
    "gn:asciiname":"Ayt Ben L'arbi",
    "gn:country_code":"MA",
    "gn:dem":762,
    "gn:feature_class":"P",
    "gn:feature_code":"PPL",
    "gn:name":"Ayt Ben L\u2019arbi",
    "gn:population":0,
    "gn:timezone":"Africa/Casablanca",
    "iso:country":"MA",
    "wof:name":"Ayt Ben L'arbi",
    "wof:placetype":"locality"
},
  "geometry": {"coordinates":[-7.90362,31.40883],"type":"Point"}
}