{
  "type": "Feature",
  "properties": {
    "gn:admin1_code":"4.0",
    "gn:asciiname":"Lagsayaat",
    "gn:country_code":"MA",
    "gn:dem":29,
    "gn:feature_class":"P",
    "gn:feature_code":"PPLL",
    "gn:name":"Lagsayaat",
    "gn:population":0,
    "gn:timezone":"Africa/Casablanca",
    "iso:country":"MA",
    "wof:name":"Lagsayaat",
    "wof:placetype":"locality"
},
  "geometry": {"coordinates":[-6.55137,34.36912],"type":"Point"}
}