{
  "type": "Feature",
  "properties": {
    "gn:admin1_code":"01",
    "gn:asciiname":"Lgour",
    "gn:country_code":"MA",
    "gn:dem":109,
    "gn:feature_class":"P",
    "gn:feature_code":"PPL",
    "gn:name":"Lgour",
    "gn:population":0,
    "gn:timezone":"Africa/Casablanca",
    "iso:country":"MA",
    "name:und_x_variant":[
        "Gour",
        "Kour",
        "El Gour",
        "Lgour"
    ],
    "wof:name":"Lgour",
    "wof:placetype":"locality"
},
  "geometry": {"coordinates":[-5.81407,35.49309],"type":"Point"}
}