{
  "type": "Feature",
  "properties": {
    "gn:admin1_code":"05",
    "gn:asciiname":"Assaka",
    "gn:country_code":"MA",
    "gn:dem":901,
    "gn:feature_class":"P",
    "gn:feature_code":"PPL",
    "gn:name":"Assaka",
    "gn:population":0,
    "gn:timezone":"Africa/Casablanca",
    "iso:country":"MA",
    "name:cat_x_preferred":[
        "Assaka"
    ],
    "name:ces_x_preferred":[
        "A\u0161maka"
    ],
    "name:che_x_preferred":[
        "\u0410\u0441\u0441\u0430\u043a\u0430"
    ],
    "name:hin_x_preferred":[
        "\u0905\u0936\u094d\u092e\u0915"
    ],
    "name:ita_x_preferred":[
        "Assaka"
    ],
    "name:jpn_x_preferred":[
        "\u30a2\u30c3\u30b5\u30ab\u56fd"
    ],
    "name:kor_x_preferred":[
        "\uc544\uc0ac\uce74"
    ],
    "name:lit_x_preferred":[
        "A\u0161maka"
    ],
    "name:mar_x_preferred":[
        "\u0905\u0936\u094d\u092e\u0915"
    ],
    "name:pnb_x_preferred":[
        "\u0627\u0634\u0645\u06a9"
    ],
    "name:rus_x_preferred":[
        "\u0410\u0448\u043c\u0430\u043a\u0430"
    ],
    "name:san_x_preferred":[
        "\u0905\u0936\u094d\u092e\u0915\u0903"
    ],
    "name:tam_x_preferred":[
        "\u0b85\u0bb8\u0bcd\u0bae\u0b95\u0bae\u0bcd"
    ],
    "name:tel_x_preferred":[
        "\u0c05\u0c36\u0c4d\u0c2e\u0c15 \u0c1c\u0c28\u0c2a\u0c26\u0c02"
    ],
    "name:zho_x_preferred":[
        "\u963f\u6e7f\u6ce2"
    ],
    "wof:name":"Assaka",
    "wof:placetype":"locality"
},
  "geometry": {"coordinates":[-5.61582,33.02297],"type":"Point"}
}