{
  "type": "Feature",
  "properties": {
    "gn:admin1_code":"05",
    "gn:asciiname":"Assaka",
    "gn:country_code":"MA",
    "gn:dem":901,
    "gn:feature_class":"P",
    "gn:feature_code":"PPL",
    "gn:name":"Assaka",
    "gn:population":0,
    "gn:timezone":"Africa/Casablanca",
    "iso:country":"MA",
    "wof:name":"Assaka",
    "wof:placetype":"locality"
},
  "geometry": {"coordinates":[-5.61582,33.02297],"type":"Point"}
}