{
  "type": "Feature",
  "properties": {
    "gn:admin1_code":"7.0",
    "gn:asciiname":"Moulay Mustafa",
    "gn:country_code":"MA",
    "gn:dem":728,
    "gn:feature_class":"P",
    "gn:feature_code":"PPL",
    "gn:name":"Moulay Mustafa",
    "gn:population":0,
    "gn:timezone":"Africa/Casablanca",
    "iso:country":"MA",
    "wof:name":"Moulay Mustafa",
    "wof:placetype":"locality"
},
  "geometry": {"coordinates":[-7.91025,31.4251],"type":"Point"}
}