{
  "type": "Feature",
  "properties": {
    "gn:admin1_code":"09",
    "gn:asciiname":"Ait Garri",
    "gn:country_code":"MA",
    "gn:dem":575,
    "gn:feature_class":"P",
    "gn:feature_code":"PPL",
    "gn:name":"A\u00eft Garri",
    "gn:population":0,
    "gn:timezone":"Africa/Casablanca",
    "iso:country":"MA",
    "name:und_x_variant":[
        "A\u00eft Guerry",
        "A\u00eft Guerri",
        "A\u00eft Garri"
    ],
    "wof:name":"Ait Garri",
    "wof:placetype":"locality"
},
  "geometry": {"coordinates":[-8.331,30.56873],"type":"Point"}
}