{
  "type": "Feature",
  "properties": {
    "gn:admin1_code":"2.0",
    "gn:asciiname":"Dar Errachidi Emfi",
    "gn:country_code":"MA",
    "gn:dem":25,
    "gn:feature_class":"P",
    "gn:feature_code":"PPL",
    "gn:name":"Dar Errachidi Emfi",
    "gn:population":0,
    "gn:timezone":"Africa/Casablanca",
    "iso:country":"MA",
    "wof:name":"Dar Errachidi Emfi",
    "wof:placetype":"locality"
},
  "geometry": {"coordinates":[-2.92186,35.11423],"type":"Point"}
}