{
  "type": "Feature",
  "properties": {
    "gn:admin1_code":"05",
    "gn:asciiname":"d'Ait 'Ammar",
    "gn:country_code":"MA",
    "gn:dem":866,
    "gn:feature_class":"P",
    "gn:feature_code":"PPL",
    "gn:name":"d\u2019A\u00eft \u2019Ammar",
    "gn:population":0,
    "gn:timezone":"Africa/Casablanca",
    "iso:country":"MA",
    "name:und_x_variant":[
        "d\u2019A\u00eft \u2019Ammar",
        "A\u00eft Ammar"
    ],
    "wof:name":"d'Ait 'Ammar",
    "wof:placetype":"locality"
},
  "geometry": {"coordinates":[-6.65567,33.06227],"type":"Point"}
}