{
  "type": "Feature",
  "properties": {
    "gn:admin1_code":"1.0",
    "gn:asciiname":"Dar Cala Qasjae",
    "gn:country_code":"MA",
    "gn:dem":327,
    "gn:feature_class":"P",
    "gn:feature_code":"PPL",
    "gn:name":"Dar Cala Qasjae",
    "gn:population":0,
    "gn:timezone":"Africa/Casablanca",
    "iso:country":"MA",
    "wof:name":"Dar Cala Qasjae",
    "wof:placetype":"locality"
},
  "geometry": {"coordinates":[-5.46284,35.72268],"type":"Point"}
}