{
  "type": "Feature",
  "properties": {
    "gn:admin1_code":"9.0",
    "gn:asciiname":"Oulad Alioua",
    "gn:country_code":"MA",
    "gn:dem":109,
    "gn:feature_class":"P",
    "gn:feature_code":"PPL",
    "gn:name":"Oulad Alioua",
    "gn:population":0,
    "gn:timezone":"Africa/Casablanca",
    "iso:country":"MA",
    "wof:name":"Oulad Alioua",
    "wof:placetype":"locality"
},
  "geometry": {"coordinates":[-9.26376,30.37108],"type":"Point"}
}