{
  "type": "Feature",
  "properties": {
    "gn:admin1_code":"5.0",
    "gn:asciiname":"Azlafan",
    "gn:country_code":"MA",
    "gn:dem":1065,
    "gn:feature_class":"P",
    "gn:feature_code":"PPL",
    "gn:name":"Azlafan",
    "gn:population":0,
    "gn:timezone":"Africa/Casablanca",
    "iso:country":"MA",
    "wof:name":"Azlafan",
    "wof:placetype":"locality"
},
  "geometry": {"coordinates":[-6.8624,31.9063],"type":"Point"}
}