{
  "type": "Feature",
  "properties": {
    "gn:admin1_code":"7.0",
    "gn:asciiname":"Lhormat",
    "gn:country_code":"MA",
    "gn:dem":532,
    "gn:feature_class":"P",
    "gn:feature_code":"PPL",
    "gn:name":"Lhormat",
    "gn:population":0,
    "gn:timezone":"Africa/Casablanca",
    "iso:country":"MA",
    "wof:name":"Lhormat",
    "wof:placetype":"locality"
},
  "geometry": {"coordinates":[-8.91047,32.00535],"type":"Point"}
}