{
  "type": "Feature",
  "properties": {
    "gn:admin1_code":"07",
    "gn:asciiname":"Tazougaght",
    "gn:country_code":"MA",
    "gn:dem":1432,
    "gn:feature_class":"P",
    "gn:feature_code":"PPL",
    "gn:name":"Tazougaght",
    "gn:population":0,
    "gn:timezone":"Africa/Casablanca",
    "iso:country":"MA",
    "name:und_x_variant":[
        "Tazourgat",
        "Tazougart",
        "Tazougaght"
    ],
    "wof:name":"Tazougaght",
    "wof:placetype":"locality"
},
  "geometry": {"coordinates":[-8.08336,30.97683],"type":"Point"}
}