{
  "type": "Feature",
  "properties": {
    "gn:admin1_code":"8.0",
    "gn:asciiname":"Akazwy",
    "gn:country_code":"MA",
    "gn:dem":1434,
    "gn:feature_class":"P",
    "gn:feature_code":"PPL",
    "gn:name":"Akazwy",
    "gn:population":0,
    "gn:timezone":"Africa/Casablanca",
    "iso:country":"MA",
    "wof:name":"Akazwy",
    "wof:placetype":"locality"
},
  "geometry": {"coordinates":[-6.15278,31.22459000000001],"type":"Point"}
}