{
  "type": "Feature",
  "properties": {
    "gn:admin1_code":"06",
    "gn:asciiname":"Chelihat",
    "gn:country_code":"MA",
    "gn:dem":317,
    "gn:feature_class":"P",
    "gn:feature_code":"PPL",
    "gn:name":"Chelihat",
    "gn:population":0,
    "gn:timezone":"Africa/Casablanca",
    "iso:country":"MA",
    "name:und_x_variant":[
        "Douar ech Chelihet",
        "Chlihate",
        "Douar Chlihat",
        "Chlihat",
        "Chelihat"
    ],
    "wof:name":"Chelihat",
    "wof:placetype":"locality"
},
  "geometry": {"coordinates":[-7.46387,32.4731],"type":"Point"}
}