{
  "type": "Feature",
  "properties": {
    "gn:admin1_code":"06",
    "gn:asciiname":"El Haddada",
    "gn:country_code":"MA",
    "gn:dem":128,
    "gn:feature_class":"P",
    "gn:feature_code":"PPL",
    "gn:name":"El Haddada",
    "gn:population":0,
    "gn:timezone":"Africa/Casablanca",
    "iso:country":"MA",
    "name:und_x_variant":[
        "El Haddade",
        "El Haddada"
    ],
    "wof:name":"El Haddada",
    "wof:placetype":"locality"
},
  "geometry": {"coordinates":[-8.75763,32.63103],"type":"Point"}
}