{
  "type": "Feature",
  "properties": {
    "gn:admin1_code":"01",
    "gn:asciiname":"Dehar",
    "gn:country_code":"MA",
    "gn:dem":500,
    "gn:feature_class":"P",
    "gn:feature_code":"PPL",
    "gn:name":"Dehar",
    "gn:population":0,
    "gn:timezone":"Africa/Casablanca",
    "iso:country":"MA",
    "wof:name":"Dehar",
    "wof:placetype":"locality"
},
  "geometry": {"coordinates":[-5.37,34.98],"type":"Point"}
}