{
  "type": "Feature",
  "properties": {
    "gn:admin1_code":"08",
    "gn:asciiname":"Bou Irghissene",
    "gn:country_code":"MA",
    "gn:dem":1714,
    "gn:feature_class":"P",
    "gn:feature_code":"PPL",
    "gn:name":"Bou Irghissene",
    "gn:population":0,
    "gn:timezone":"Africa/Casablanca",
    "iso:country":"MA",
    "name:und_x_variant":[
        "Bou Irghissen",
        "Bou Irrhissene",
        "Bou Irghissene"
    ],
    "wof:name":"Bou Irghissene",
    "wof:placetype":"locality"
},
  "geometry": {"coordinates":[-5.44965,32.37499],"type":"Point"}
}