{
  "type": "Feature",
  "properties": {
    "gn:admin1_code":"6.0",
    "gn:asciiname":"Hajj Bouchaib",
    "gn:country_code":"MA",
    "gn:dem":362,
    "gn:feature_class":"P",
    "gn:feature_code":"PPL",
    "gn:name":"Hajj Boucha\u00efb",
    "gn:population":0,
    "gn:timezone":"Africa/Casablanca",
    "iso:country":"MA",
    "wof:name":"Hajj Bouchaib",
    "wof:placetype":"locality"
},
  "geometry": {"coordinates":[-7.85002,32.85447],"type":"Point"}
}