{
  "type": "Feature",
  "properties": {
    "gn:admin1_code":"07",
    "gn:asciiname":"Douar Oulad Sidi Abdellah",
    "gn:country_code":"MA",
    "gn:dem":415,
    "gn:feature_class":"P",
    "gn:feature_code":"PPL",
    "gn:name":"Douar Oulad Sidi Abdellah",
    "gn:population":0,
    "gn:timezone":"Africa/Casablanca",
    "iso:country":"MA",
    "name:und_x_variant":[
        "Oulad Abdallah",
        "Sidi Abdellah",
        "Oulad Sidi Abdallah",
        "Douar Oulad Sidi Abdellah"
    ],
    "wof:name":"Douar Oulad Sidi Abdellah",
    "wof:placetype":"locality"
},
  "geometry": {"coordinates":[-9.07832,31.54517],"type":"Point"}
}