{
  "type": "Feature",
  "properties": {
    "gn:admin1_code":"04",
    "gn:asciiname":"Laararsa",
    "gn:country_code":"MA",
    "gn:dem":113,
    "gn:feature_class":"P",
    "gn:feature_code":"PPL",
    "gn:name":"Laararsa",
    "gn:population":0,
    "gn:timezone":"Africa/Casablanca",
    "iso:country":"MA",
    "name:und_x_variant":[
        "A\u00e2rarsate",
        "Douar el Ararsa",
        "El Arana",
        "El Ararsa",
        "Laararsa"
    ],
    "wof:name":"Laararsa",
    "wof:placetype":"locality"
},
  "geometry": {"coordinates":[-5.60272,34.67065],"type":"Point"}
}