{
  "type": "Feature",
  "properties": {
    "gn:admin1_code":"02",
    "gn:asciiname":"Ayt Mohand",
    "gn:country_code":"MA",
    "gn:dem":1333,
    "gn:feature_class":"P",
    "gn:feature_code":"PPL",
    "gn:name":"Ayt Mohand",
    "gn:population":0,
    "gn:timezone":"Africa/Casablanca",
    "iso:country":"MA",
    "name:und_x_variant":[
        "Ksar des A\u00eft Mohammed",
        "A\u00eft Mohammed",
        "Ayt Mohand"
    ],
    "wof:name":"Ayt Mohand",
    "wof:placetype":"locality"
},
  "geometry": {"coordinates":[-3.76725,32.41051],"type":"Point"}
}