{
  "type": "Feature",
  "properties": {
    "gn:admin1_code":"09",
    "gn:asciiname":"Bounaamane",
    "gn:country_code":"MA",
    "gn:dem":394,
    "gn:feature_class":"P",
    "gn:feature_code":"PPL",
    "gn:name":"Bounaamane",
    "gn:population":0,
    "gn:timezone":"Africa/Casablanca",
    "iso:country":"MA",
    "name:und_x_variant":[
        "Souk ej Jem\u2019a n Bou N\u2019am\u00e2ne",
        "Bou Na\u00e2mane",
        "Souk-Sebt de Bou-Naamane",
        "Souq aj Jam\u2019a n Bou Na\u2019mane",
        "Bou Namane",
        "Bounaamane"
    ],
    "wof:name":"Bounaamane",
    "wof:placetype":"locality"
},
  "geometry": {"coordinates":[-9.81346,29.53128],"type":"Point"}
}