{
  "type": "Feature",
  "properties": {
    "gn:admin1_code":"03",
    "gn:asciiname":"Arhil Oumial",
    "gn:country_code":"MA",
    "gn:dem":1109,
    "gn:feature_class":"P",
    "gn:feature_code":"PPL",
    "gn:name":"Arhil Oumial",
    "gn:population":0,
    "gn:timezone":"Africa/Casablanca",
    "iso:country":"MA",
    "name:und_x_variant":[
        "Douar Arhil Oumial",
        "Aghil Oumial",
        "Aghil Ou Miel",
        "Arhil Oumial"
    ],
    "wof:name":"Arhil Oumial",
    "wof:placetype":"locality"
},
  "geometry": {"coordinates":[-3.98702,34.05202],"type":"Point"}
}