{
  "type": "Feature",
  "properties": {
    "gn:admin1_code":"6.0",
    "gn:asciiname":"Douar Acheddadene",
    "gn:country_code":"MA",
    "gn:dem":266,
    "gn:feature_class":"P",
    "gn:feature_code":"PPL",
    "gn:name":"Douar Acheddadene",
    "gn:population":0,
    "gn:timezone":"Africa/Casablanca",
    "iso:country":"MA",
    "wof:name":"Douar Acheddadene",
    "wof:placetype":"locality"
},
  "geometry": {"coordinates":[-6.89993,33.49253],"type":"Point"}
}