{
  "type": "Feature",
  "properties": {
    "gn:admin1_code":"01",
    "gn:asciiname":"Gharouzim",
    "gn:country_code":"MA",
    "gn:dem":458,
    "gn:feature_class":"P",
    "gn:feature_code":"PPL",
    "gn:name":"Gharouzim",
    "gn:population":0,
    "gn:timezone":"Africa/Casablanca",
    "iso:country":"MA",
    "wof:name":"Gharouzim",
    "wof:placetype":"locality"
},
  "geometry": {"coordinates":[-5.28749,35.15677],"type":"Point"}
}