{
  "type": "Feature",
  "properties": {
    "gn:admin1_code":"7.0",
    "gn:asciiname":"Ac-Cour",
    "gn:country_code":"MA",
    "gn:dem":1381,
    "gn:feature_class":"P",
    "gn:feature_code":"PPL",
    "gn:name":"Ac-\u00c7our",
    "gn:population":0,
    "gn:timezone":"Africa/Casablanca",
    "iso:country":"MA",
    "wof:name":"Ac-Cour",
    "wof:placetype":"locality"
},
  "geometry": {"coordinates":[-7.49833,31.37727000000001],"type":"Point"}
}