{
  "type": "Feature",
  "properties": {
    "gn:admin1_code":"7.0",
    "gn:asciiname":"Ait Lachchain",
    "gn:country_code":"MA",
    "gn:dem":390,
    "gn:feature_class":"P",
    "gn:feature_code":"PPL",
    "gn:name":"Ait Lachchain",
    "gn:population":0,
    "gn:timezone":"Africa/Casablanca",
    "iso:country":"MA",
    "wof:name":"Ait Lachchain",
    "wof:placetype":"locality"
},
  "geometry": {"coordinates":[-9.38664,31.5765],"type":"Point"}
}