{
  "type": "Feature",
  "properties": {
    "gn:admin1_code":"7.0",
    "gn:asciiname":"Douar Leqdadra",
    "gn:country_code":"MA",
    "gn:dem":350,
    "gn:feature_class":"P",
    "gn:feature_code":"PPL",
    "gn:name":"Douar Leqdadra",
    "gn:population":0,
    "gn:timezone":"Africa/Casablanca",
    "iso:country":"MA",
    "wof:name":"Douar Leqdadra",
    "wof:placetype":"locality"
},
  "geometry": {"coordinates":[-8.88498,32.11649],"type":"Point"}
}