{
  "type": "Feature",
  "properties": {
    "gn:admin1_code":"07",
    "gn:asciiname":"Oulad Abbad Ben El Haj",
    "gn:country_code":"MA",
    "gn:dem":501,
    "gn:feature_class":"P",
    "gn:feature_code":"PPL",
    "gn:name":"Oulad Abbad Ben El Haj",
    "gn:population":0,
    "gn:timezone":"Africa/Casablanca",
    "iso:country":"MA",
    "name:und_x_variant":[
        "Ouled Abad bel Haj",
        "Ouled hadj",
        "Douar Abd el Hajj",
        "Oulad Abbad Ben El Haj"
    ],
    "wof:name":"Oulad Abbad Ben El Haj",
    "wof:placetype":"locality"
},
  "geometry": {"coordinates":[-8.91624,31.935],"type":"Point"}
}