{
  "type": "Feature",
  "properties": {
    "gn:admin1_code":"09",
    "gn:asciiname":"Adeqqi",
    "gn:country_code":"MA",
    "gn:dem":1818,
    "gn:feature_class":"P",
    "gn:feature_code":"PPL",
    "gn:name":"Adeqqi",
    "gn:population":0,
    "gn:timezone":"Africa/Casablanca",
    "iso:country":"MA",
    "name:und_x_variant":[
        "Atki",
        "Adki",
        "Adeqqi"
    ],
    "wof:name":"Adeqqi",
    "wof:placetype":"locality"
},
  "geometry": {"coordinates":[-8.61833,30.82936],"type":"Point"}
}