{
  "type": "Feature",
  "properties": {
    "gn:admin1_code":"5.0",
    "gn:asciiname":"Oulad Yahya",
    "gn:country_code":"MA",
    "gn:dem":723,
    "gn:feature_class":"P",
    "gn:feature_code":"PPL",
    "gn:name":"Oulad Yahya",
    "gn:population":0,
    "gn:timezone":"Africa/Casablanca",
    "iso:country":"MA",
    "wof:name":"Oulad Yahya",
    "wof:placetype":"locality"
},
  "geometry": {"coordinates":[-6.26609,32.79385],"type":"Point"}
}