{
  "type": "Feature",
  "properties": {
    "gn:admin1_code":"03",
    "gn:asciiname":"Douar Kalaat Said",
    "gn:country_code":"MA",
    "gn:dem":615,
    "gn:feature_class":"P",
    "gn:feature_code":"PPL",
    "gn:name":"Douar Kalaat Said",
    "gn:population":0,
    "gn:timezone":"Africa/Casablanca",
    "iso:country":"MA",
    "name:und_x_variant":[
        "Kelaa de Sa\u00efd",
        "Kalaat Sa\u00efd",
        "Douar Kalaat Said"
    ],
    "wof:name":"Douar Kalaat Said",
    "wof:placetype":"locality"
},
  "geometry": {"coordinates":[-4.59563,33.77814],"type":"Point"}
}