{
  "type": "Feature",
  "properties": {
    "gn:admin1_code":"05",
    "gn:admin2_code":"301.0",
    "gn:admin3_code":"1330105032.0",
    "gn:asciiname":"Aguelmous",
    "gn:country_code":"MA",
    "gn:dem":1187,
    "gn:feature_class":"P",
    "gn:feature_code":"PPLA3",
    "gn:name":"Aguelmous",
    "gn:population":0,
    "gn:timezone":"Africa/Casablanca",
    "iso:country":"MA",
    "name:und_x_variant":[
        "Aguelmouss",
        "Aguelmous"
    ],
    "wof:name":"Aguelmous",
    "wof:placetype":"locality"
},
  "geometry": {"coordinates":[-5.84626,33.16139],"type":"Point"}
}