{
  "type": "Feature",
  "properties": {
    "gn:admin1_code":"05",
    "gn:admin2_code":"301.0",
    "gn:admin3_code":"1330105032.0",
    "gn:asciiname":"Aguelmous",
    "gn:country_code":"MA",
    "gn:dem":1187,
    "gn:feature_class":"P",
    "gn:feature_code":"PPLA3",
    "gn:name":"Aguelmous",
    "gn:population":0,
    "gn:timezone":"Africa/Casablanca",
    "iso:country":"MA",
    "name:ara_x_preferred":[
        "\u0623\u0643\u0644\u0645\u0648\u0633"
    ],
    "name:azb_x_preferred":[
        "\u0627\u0642\u0648\u0644\u0645\u0627\u0633"
    ],
    "name:cat_x_preferred":[
        "Aguelmous"
    ],
    "name:ceb_x_preferred":[
        "Aguelmous"
    ],
    "name:deu_x_preferred":[
        "Aguelmous"
    ],
    "name:fas_x_preferred":[
        "\u0627\u06af\u0648\u0644\u0645\u0627\u0633"
    ],
    "name:fra_x_preferred":[
        "Aguelmous"
    ],
    "name:ita_x_preferred":[
        "Aguelmous"
    ],
    "name:pol_x_preferred":[
        "Akalmus"
    ],
    "name:swe_x_preferred":[
        "Aguelmous"
    ],
    "name:und_x_variant":[
        "Aguelmouss"
    ],
    "name:urd_x_preferred":[
        "\u0627\u06af\u0648\u0644\u0645\u0627\u0633"
    ],
    "wof:name":"Aguelmous",
    "wof:placetype":"locality"
},
  "geometry": {"coordinates":[-5.84626,33.16139],"type":"Point"}
}