{
  "type": "Feature",
  "properties": {
    "gn:admin1_code":"07",
    "gn:asciiname":"Oulad Sidi Fares",
    "gn:country_code":"MA",
    "gn:dem":63,
    "gn:feature_class":"P",
    "gn:feature_code":"PPL",
    "gn:name":"Oulad Sidi Fares",
    "gn:population":0,
    "gn:timezone":"Africa/Casablanca",
    "iso:country":"MA",
    "name:und_x_variant":[
        "Douar Oulad Sidi Far\u00e8s",
        "Oulad Sidi Fares"
    ],
    "wof:name":"Oulad Sidi Fares",
    "wof:placetype":"locality"
},
  "geometry": {"coordinates":[-9.20369,32.44023],"type":"Point"}
}