{
  "type": "Feature",
  "properties": {
    "gn:admin1_code":"07",
    "gn:asciiname":"Ait Omrhar",
    "gn:country_code":"MA",
    "gn:dem":1346,
    "gn:feature_class":"P",
    "gn:feature_code":"PPL",
    "gn:name":"A\u00eft Omrhar",
    "gn:population":0,
    "gn:timezone":"Africa/Casablanca",
    "iso:country":"MA",
    "name:und_x_variant":[
        "A\u00eft Omrhar",
        "A\u00eft Oumghar"
    ],
    "wof:name":"Ait Omrhar",
    "wof:placetype":"locality"
},
  "geometry": {"coordinates":[-7.26567,31.56794],"type":"Point"}
}