{
  "type": "Feature",
  "properties": {
    "gn:admin1_code":"02",
    "gn:asciiname":"Mechra Klila",
    "gn:country_code":"MA",
    "gn:dem":206,
    "gn:feature_class":"P",
    "gn:feature_code":"PPL",
    "gn:name":"Mechra Klila",
    "gn:population":0,
    "gn:timezone":"Africa/Casablanca",
    "iso:country":"MA",
    "wof:name":"Mechra Klila",
    "wof:placetype":"locality"
},
  "geometry": {"coordinates":[-2.95228,34.64462],"type":"Point"}
}