{
  "type": "Feature",
  "properties": {
    "gn:admin1_code":"7.0",
    "gn:asciiname":"Tigoudert",
    "gn:country_code":"MA",
    "gn:dem":616,
    "gn:feature_class":"P",
    "gn:feature_code":"PPL",
    "gn:name":"Tigoudert",
    "gn:population":0,
    "gn:timezone":"Africa/Casablanca",
    "iso:country":"MA",
    "wof:name":"Tigoudert",
    "wof:placetype":"locality"
},
  "geometry": {"coordinates":[-9.41416,31.29937],"type":"Point"}
}