{
  "type": "Feature",
  "properties": {
    "gn:admin1_code":"9.0",
    "gn:asciiname":"Lalla Zira",
    "gn:country_code":"MA",
    "gn:dem":69,
    "gn:feature_class":"P",
    "gn:feature_code":"PPL",
    "gn:name":"Lalla Zira",
    "gn:population":0,
    "gn:timezone":"Africa/Casablanca",
    "iso:country":"MA",
    "wof:name":"Lalla Zira",
    "wof:placetype":"locality"
},
  "geometry": {"coordinates":[-9.57241,30.08743],"type":"Point"}
}