{
  "type": "Feature",
  "properties": {
    "gn:admin1_code":"7.0",
    "gn:asciiname":"Taberouaguet",
    "gn:country_code":"MA",
    "gn:dem":417,
    "gn:feature_class":"P",
    "gn:feature_code":"PPL",
    "gn:name":"Taberouaguet",
    "gn:population":0,
    "gn:timezone":"Africa/Casablanca",
    "iso:country":"MA",
    "wof:name":"Taberouaguet",
    "wof:placetype":"locality"
},
  "geometry": {"coordinates":[-9.38465,31.47292],"type":"Point"}
}