{
  "type": "Feature",
  "properties": {
    "gn:admin1_code":"08",
    "gn:asciiname":"Ait Ichou Ou Ali",
    "gn:country_code":"MA",
    "gn:dem":1384,
    "gn:feature_class":"P",
    "gn:feature_code":"PPL",
    "gn:name":"A\u00eft Ichou Ou Ali",
    "gn:population":0,
    "gn:timezone":"Africa/Casablanca",
    "iso:country":"MA",
    "name:und_x_variant":[
        "Ait Ichchou Ou\u00e2li",
        "A\u00eft Ichou Ou Ali"
    ],
    "wof:name":"Ait Ichou Ou Ali",
    "wof:placetype":"locality"
},
  "geometry": {"coordinates":[-4.32182,32.67981],"type":"Point"}
}