{
  "type": "Feature",
  "properties": {
    "gn:admin1_code":"4.0",
    "gn:asciiname":"Dar Berrahou Hammou",
    "gn:country_code":"MA",
    "gn:dem":780,
    "gn:feature_class":"P",
    "gn:feature_code":"PPL",
    "gn:name":"Dar Berrahou Hammou",
    "gn:population":0,
    "gn:timezone":"Africa/Casablanca",
    "iso:country":"MA",
    "wof:name":"Dar Berrahou Hammou",
    "wof:placetype":"locality"
},
  "geometry": {"coordinates":[-6.17488,33.50221],"type":"Point"}
}