{
  "type": "Feature",
  "properties": {
    "gn:admin1_code":"09",
    "gn:asciiname":"Tidinghi",
    "gn:country_code":"MA",
    "gn:dem":1591,
    "gn:feature_class":"P",
    "gn:feature_code":"PPL",
    "gn:name":"Tidinghi",
    "gn:population":0,
    "gn:timezone":"Africa/Casablanca",
    "iso:country":"MA",
    "name:und_x_variant":[
        "Tidenrhi"
    ],
    "wof:name":"Tidinghi",
    "wof:placetype":"locality"
},
  "geometry": {"coordinates":[-9.10323,29.87629],"type":"Point"}
}