{
  "type": "Feature",
  "properties": {
    "gn:admin1_code":"03",
    "gn:asciiname":"Douar Ain Qdima",
    "gn:country_code":"MA",
    "gn:dem":442,
    "gn:feature_class":"P",
    "gn:feature_code":"PPL",
    "gn:name":"Douar Ain Qdima",
    "gn:population":0,
    "gn:timezone":"Africa/Casablanca",
    "iso:country":"MA",
    "name:und_x_variant":[
        "A\u00efn Kdima"
    ],
    "wof:name":"Douar Ain Qdima",
    "wof:placetype":"locality"
},
  "geometry": {"coordinates":[-5.12929,34.67261],"type":"Point"}
}