{
  "type": "Feature",
  "properties": {
    "gn:admin1_code":"47.0",
    "gn:asciiname":"Ait Souka",
    "gn:country_code":"MA",
    "gn:dem":1827,
    "gn:feature_class":"P",
    "gn:feature_code":"PPL",
    "gn:name":"A\u00eft Souka",
    "gn:population":0,
    "gn:timezone":"Africa/Casablanca",
    "iso:country":"MA",
    "wof:name":"Ait Souka",
    "wof:placetype":"locality"
},
  "geometry": {"coordinates":[-7.9114,31.14015],"type":"Point"}
}