{
  "type": "Feature",
  "properties": {
    "gn:admin1_code":"07",
    "gn:asciiname":"Ait 'Issa",
    "gn:country_code":"MA",
    "gn:dem":1601,
    "gn:feature_class":"P",
    "gn:feature_code":"PPL",
    "gn:name":"A\u00eft \u2019Issa",
    "gn:population":0,
    "gn:timezone":"Africa/Casablanca",
    "iso:country":"MA",
    "name:und_x_variant":[
        "A\u00eft \u2019Issa",
        "A\u00eft A\u00efssa"
    ],
    "wof:name":"Ait 'Issa",
    "wof:placetype":"locality"
},
  "geometry": {"coordinates":[-7.291,31.45242],"type":"Point"}
}