{
  "type": "Feature",
  "properties": {
    "gn:admin1_code":"03",
    "gn:asciiname":"Tazrout",
    "gn:country_code":"MA",
    "gn:dem":525,
    "gn:feature_class":"P",
    "gn:feature_code":"PPL",
    "gn:name":"Tazrout",
    "gn:population":0,
    "gn:timezone":"Africa/Casablanca",
    "iso:country":"MA",
    "name:und_x_variant":[
        "Tazeroute",
        "Tazrout",
        "Tazerout"
    ],
    "wof:name":"Tazrout",
    "wof:placetype":"locality"
},
  "geometry": {"coordinates":[-5.0192,34.59307],"type":"Point"}
}