{
  "type": "Feature",
  "properties": {
    "gn:admin1_code":"1.0",
    "gn:asciiname":"Abyata",
    "gn:country_code":"MA",
    "gn:dem":255,
    "gn:feature_class":"P",
    "gn:feature_code":"PPL",
    "gn:name":"Abyata",
    "gn:population":0,
    "gn:timezone":"Africa/Casablanca",
    "iso:country":"MA",
    "wof:name":"Abyata",
    "wof:placetype":"locality"
},
  "geometry": {"coordinates":[-5.14972,35.4912],"type":"Point"}
}