{
  "type": "Feature",
  "properties": {
    "gn:admin1_code":"7.0",
    "gn:asciiname":"Douar Qibal",
    "gn:country_code":"MA",
    "gn:dem":576,
    "gn:feature_class":"P",
    "gn:feature_code":"PPL",
    "gn:name":"Douar Qibal",
    "gn:population":0,
    "gn:timezone":"Africa/Casablanca",
    "iso:country":"MA",
    "wof:name":"Douar Qibal",
    "wof:placetype":"locality"
},
  "geometry": {"coordinates":[-7.53673,31.82158],"type":"Point"}
}