{
  "type": "Feature",
  "properties": {
    "gn:admin1_code":"7.0",
    "gn:asciiname":"Oulad Dahhou",
    "gn:country_code":"MA",
    "gn:dem":701,
    "gn:feature_class":"P",
    "gn:feature_code":"PPL",
    "gn:name":"Oulad Dahhou",
    "gn:population":0,
    "gn:timezone":"Africa/Casablanca",
    "iso:country":"MA",
    "wof:name":"Oulad Dahhou",
    "wof:placetype":"locality"
},
  "geometry": {"coordinates":[-7.05612,31.84041],"type":"Point"}
}