{
  "type": "Feature",
  "properties": {
    "gn:admin1_code":"04",
    "gn:asciiname":"Douar Lamaadda",
    "gn:country_code":"MA",
    "gn:dem":167,
    "gn:feature_class":"P",
    "gn:feature_code":"PPL",
    "gn:name":"Douar Lamaadda",
    "gn:population":0,
    "gn:timezone":"Africa/Casablanca",
    "iso:country":"MA",
    "name:und_x_variant":[
        "Douar Maadda",
        "Ma\u2019da",
        "Maadda",
        "Douar Lamaadda"
    ],
    "wof:name":"Douar Lamaadda",
    "wof:placetype":"locality"
},
  "geometry": {"coordinates":[-5.968,34.90117],"type":"Point"}
}