{
  "type": "Feature",
  "properties": {
    "gn:admin1_code":"01",
    "gn:asciiname":"Tafsou",
    "gn:country_code":"MA",
    "gn:dem":1110,
    "gn:feature_class":"P",
    "gn:feature_code":"PPL",
    "gn:name":"Tafsou",
    "gn:population":0,
    "gn:timezone":"Africa/Casablanca",
    "iso:country":"MA",
    "wof:name":"Tafsou",
    "wof:placetype":"locality"
},
  "geometry": {"coordinates":[-4.44907,34.78079],"type":"Point"}
}