{
  "type": "Feature",
  "properties": {
    "iso:country":"MA",
    "name:und_x_variant":[
        "Had Dra\u00e2"
    ],
    "qs:gn_country":"MA",
    "qs:gn_fcode":"PPL",
    "qs:gn_pop":0,
    "qs:name":"Souk El Had du Draa",
    "qs:name_adm0":"\u0627\u0644\u0645\u063a\u0631\u0628",
    "qs:name_adm1":"\u0645\u0631\u0627\u0643\u0634 \u0640 \u062a\u0627\u0646\u0633\u064a\u0641\u062a \u0640 \u0627\u0644\u062d\u0648\u0632",
    "qs:photos":38,
    "qs:photos_1k":8,
    "qs:photos_9k":1,
    "qs:photos_9r":2,
    "qs:photos_all":38,
    "qs:photos_sr":2,
    "qs:placetype":"Town",
    "qs:pop_sr":"4",
    "qs:woe_adm0":23424893,
    "wof:name":"Souk El Had du Draa",
    "wof:placetype":"locality"
},
  "geometry": {"coordinates":[-9.5332,31.57868],"type":"Point"}
}