{
  "type": "Feature",
  "properties": {
    "gn:admin1_code":"07",
    "gn:asciiname":"Oulad El Ain Leqraqra",
    "gn:country_code":"MA",
    "gn:dem":189,
    "gn:feature_class":"P",
    "gn:feature_code":"PPL",
    "gn:name":"Oulad El Ain Leqraqra",
    "gn:population":0,
    "gn:timezone":"Africa/Casablanca",
    "iso:country":"MA",
    "name:und_x_variant":[
        "Oulad Na\u00efn"
    ],
    "wof:name":"Oulad El Ain Leqraqra",
    "wof:placetype":"locality"
},
  "geometry": {"coordinates":[-8.76536,32.4117],"type":"Point"}
}