{
  "type": "Feature",
  "properties": {
    "gn:admin1_code":"7.0",
    "gn:asciiname":"Chrunat El Oued",
    "gn:country_code":"MA",
    "gn:dem":38,
    "gn:feature_class":"P",
    "gn:feature_code":"PPL",
    "gn:name":"Chrunat El Oued",
    "gn:population":0,
    "gn:timezone":"Africa/Casablanca",
    "iso:country":"MA",
    "wof:name":"Chrunat El Oued",
    "wof:placetype":"locality"
},
  "geometry": {"coordinates":[-9.22754,32.56943],"type":"Point"}
}