{
  "type": "Feature",
  "properties": {
    "gn:admin1_code":"03",
    "gn:asciiname":"Ait Belaid",
    "gn:country_code":"MA",
    "gn:dem":1183,
    "gn:feature_class":"P",
    "gn:feature_code":"PPL",
    "gn:name":"A\u00eft Bela\u00efd",
    "gn:population":0,
    "gn:timezone":"Africa/Casablanca",
    "iso:country":"MA",
    "wof:name":"Ait Belaid",
    "wof:placetype":"locality"
},
  "geometry": {"coordinates":[-4.73091,33.74531],"type":"Point"}
}