{
  "type": "Feature",
  "properties": {
    "gn:admin1_code":"08",
    "gn:asciiname":"Ouantkou",
    "gn:country_code":"MA",
    "gn:dem":1577,
    "gn:feature_class":"P",
    "gn:feature_code":"PPL",
    "gn:name":"Ouantkou",
    "gn:population":0,
    "gn:timezone":"Africa/Casablanca",
    "iso:country":"MA",
    "name:und_x_variant":[
        "Wantkou",
        "Ouantkou"
    ],
    "wof:name":"Ouantkou",
    "wof:placetype":"locality"
},
  "geometry": {"coordinates":[-7.33393,30.26988],"type":"Point"}
}