{
  "type": "Feature",
  "properties": {
    "gn:country":"MA",
    "gn:fcode":"ADM3",
    "gn:population":4431,
    "iso:country":"MA",
    "name:ara_x_preferred":[
        "\u0645\u064a\u062f\u0644\u062a (\u0627\u0644\u0628\u0644\u062f\u064a\u0629)"
    ],
    "name:ara_x_variant":[
        "\u0623\u06ad\u0648\u062f\u064a\u0645",
        "\u0623\u062e\u0648\u062f\u0645"
    ],
    "name:ary_x_preferred":[
        "\u0623\u06af\u0648\u062f\u064a\u0645"
    ],
    "name:bul_x_preferred":[
        "\u0410\u0433\u043e\u0443\u0434\u0438\u043c"
    ],
    "name:cat_x_preferred":[
        "Agoudim"
    ],
    "name:ceb_x_preferred":[
        "Agoudim"
    ],
    "name:eng_x_preferred":[
        "Agoudim"
    ],
    "name:fra_x_preferred":[
        "Agoudim"
    ],
    "name:fra_x_variant":[
        "Agoudim (CR)",
        "Agoudim (Commune Rurale)"
    ],
    "name:ita_x_preferred":[
        "Agoudim"
    ],
    "name:swe_x_preferred":[
        "Agoudim"
    ],
    "qs:name":"Agoudim",
    "qs:photos_9r":0,
    "qs:photos_sr":0,
    "qs:pop_sr":"4",
    "wd:wordcount":56,
    "wof:name":"Agoudim",
    "wof:placetype":"localadmin",
    "wof:population":4431
},
  "geometry": {"coordinates":[-5.05277,32.38746],"type":"Point"}
}