{
  "type": "Feature",
  "properties": {
    "gn:admin1_code":"06",
    "gn:asciiname":"Oulad Hamouda",
    "gn:country_code":"MA",
    "gn:dem":43,
    "gn:feature_class":"P",
    "gn:feature_code":"PPL",
    "gn:name":"Oulad Hamouda",
    "gn:population":0,
    "gn:timezone":"Africa/Casablanca",
    "iso:country":"MA",
    "name:und_x_variant":[
        "Douar Oulad Hamouda"
    ],
    "wof:name":"Oulad Hamouda",
    "wof:placetype":"locality"
},
  "geometry": {"coordinates":[-8.50979,33.20557],"type":"Point"}
}