{
  "type": "Feature",
  "properties": {
    "gn:admin1_code":"7.0",
    "gn:asciiname":"Zairia",
    "gn:country_code":"MA",
    "gn:dem":426,
    "gn:feature_class":"P",
    "gn:feature_code":"PPL",
    "gn:name":"Za\u00efria",
    "gn:population":0,
    "gn:timezone":"Africa/Casablanca",
    "iso:country":"MA",
    "wof:name":"Zairia",
    "wof:placetype":"locality"
},
  "geometry": {"coordinates":[-9.39577,31.38459000000001],"type":"Point"}
}