{
  "type": "Feature",
  "properties": {
    "gn:admin1_code":"9.0",
    "gn:asciiname":"El Hallat",
    "gn:country_code":"MA",
    "gn:dem":256,
    "gn:feature_class":"P",
    "gn:feature_code":"PPL",
    "gn:name":"El Hallat",
    "gn:population":0,
    "gn:timezone":"Africa/Casablanca",
    "iso:country":"MA",
    "wof:name":"El Hallat",
    "wof:placetype":"locality"
},
  "geometry": {"coordinates":[-9.68553,30.7557],"type":"Point"}
}