{
  "type": "Feature",
  "properties": {
    "gn:admin1_code":"09",
    "gn:asciiname":"Awrir",
    "gn:country_code":"MA",
    "gn:dem":918,
    "gn:feature_class":"P",
    "gn:feature_code":"PPL",
    "gn:name":"Awrir",
    "gn:population":0,
    "gn:timezone":"Africa/Casablanca",
    "iso:country":"MA",
    "name:und_x_variant":[
        "Aourir"
    ],
    "wof:name":"Awrir",
    "wof:placetype":"locality"
},
  "geometry": {"coordinates":[-8.64747,30.34039000000001],"type":"Point"}
}