{
  "type": "Feature",
  "properties": {
    "gn:admin1_code":"05",
    "gn:asciiname":"Ait Sidi-Bou 'Ali",
    "gn:country_code":"MA",
    "gn:dem":1190,
    "gn:feature_class":"P",
    "gn:feature_code":"PPL",
    "gn:name":"A\u00eft Sidi-Bou \u2019Ali",
    "gn:population":0,
    "gn:timezone":"Africa/Casablanca",
    "iso:country":"MA",
    "name:und_x_variant":[
        "Sidi Bou Ali",
        "A\u00eft Sidi Bou\u2018Li",
        "A\u00eft Sidi Bou Ali",
        "A\u00eft Sidi-Bou \u2019Ali"
    ],
    "wof:name":"Ait Sidi-Bou 'Ali",
    "wof:placetype":"locality"
},
  "geometry": {"coordinates":[-5.63898,32.73887],"type":"Point"}
}