{
  "type": "Feature",
  "properties": {
    "gn:admin1_code":"7.0",
    "gn:asciiname":"Tnine Sakyat",
    "gn:country_code":"MA",
    "gn:dem":302,
    "gn:feature_class":"P",
    "gn:feature_code":"PPL",
    "gn:name":"Tnine Sakyat",
    "gn:population":0,
    "gn:timezone":"Africa/Casablanca",
    "iso:country":"MA",
    "wof:name":"Tnine Sakyat",
    "wof:placetype":"locality"
},
  "geometry": {"coordinates":[-9.22092,31.77288],"type":"Point"}
}