{
  "type": "Feature",
  "properties": {
    "gn:admin1_code":"7.0",
    "gn:asciiname":"Oulad El Haj Abderrahmane",
    "gn:country_code":"MA",
    "gn:dem":403,
    "gn:feature_class":"P",
    "gn:feature_code":"PPL",
    "gn:name":"Oulad El Haj Abderrahmane",
    "gn:population":0,
    "gn:timezone":"Africa/Casablanca",
    "iso:country":"MA",
    "wof:name":"Oulad El Haj Abderrahmane",
    "wof:placetype":"locality"
},
  "geometry": {"coordinates":[-7.83005,32.42874],"type":"Point"}
}