{
  "type": "Feature",
  "properties": {
    "gn:admin1_code":"01",
    "gn:asciiname":"Igzar Aicha",
    "gn:country_code":"MA",
    "gn:dem":1092,
    "gn:feature_class":"P",
    "gn:feature_code":"PPL",
    "gn:name":"Igzar A\u00efcha",
    "gn:population":0,
    "gn:timezone":"Africa/Casablanca",
    "iso:country":"MA",
    "name:und_x_variant":[
        "Arhzar A\u00efssa",
        "Igzar A\u00efcha"
    ],
    "wof:name":"Igzar Aicha",
    "wof:placetype":"locality"
},
  "geometry": {"coordinates":[-4.12077,34.93467],"type":"Point"}
}