{
  "type": "Feature",
  "properties": {
    "gn:admin1_code":"6.0",
    "gn:asciiname":"El Oujaina",
    "gn:country_code":"MA",
    "gn:dem":49,
    "gn:feature_class":"P",
    "gn:feature_code":"PPL",
    "gn:name":"El Ouja\u00efna",
    "gn:population":0,
    "gn:timezone":"Africa/Casablanca",
    "iso:country":"MA",
    "wof:name":"El Oujaina",
    "wof:placetype":"locality"
},
  "geometry": {"coordinates":[-8.51971,33.10517],"type":"Point"}
}