{
  "type": "Feature",
  "properties": {
    "gn:admin1_code":"7.0",
    "gn:asciiname":"Rbaat Oulad Mouki",
    "gn:country_code":"MA",
    "gn:dem":218,
    "gn:feature_class":"P",
    "gn:feature_code":"PPL",
    "gn:name":"Rbaat Oulad Mouki",
    "gn:population":0,
    "gn:timezone":"Africa/Casablanca",
    "iso:country":"MA",
    "wof:name":"Rbaat Oulad Mouki",
    "wof:placetype":"locality"
},
  "geometry": {"coordinates":[-9.1349,32.04455],"type":"Point"}
}