{
  "type": "Feature",
  "properties": {
    "gn:admin1_code":"01",
    "gn:asciiname":"Douar Badaoua Tayf",
    "gn:country_code":"MA",
    "gn:dem":64,
    "gn:feature_class":"P",
    "gn:feature_code":"PPL",
    "gn:name":"Douar Badaoua Tayf",
    "gn:population":0,
    "gn:timezone":"Africa/Casablanca",
    "iso:country":"MA",
    "name:und_x_variant":[
        "Bedaoua",
        "Bdaoua et Ta\u00eff",
        "Douar Badaoua Tayf"
    ],
    "wof:name":"Douar Badaoua Tayf",
    "wof:placetype":"locality"
},
  "geometry": {"coordinates":[-6.02361,35.19888],"type":"Point"}
}