{
  "type": "Feature",
  "properties": {
    "gn:country":"MA",
    "gn:fcode":"ADM3",
    "gn:population":7641,
    "iso:country":"MA",
    "name:ara_x_preferred":[
        "\u0623\u0648\u0644\u0627\u062f \u0639\u0645\u0631\u0627\u0646"
    ],
    "name:ara_x_variant":[
        "\u0623\u0648\u0644\u0627\u062f \u0628\u0648\u0633\u0627\u0643\u0646"
    ],
    "name:ary_x_preferred":[
        "\u0648\u0644\u0627\u062f \u0628\u0648\u0633\u0627\u0643\u0646"
    ],
    "name:azb_x_preferred":[
        "\u0627\u0648\u0644\u0627\u062f \u0628\u0648\u0633\u0627\u06a9\u0646"
    ],
    "name:cat_x_preferred":[
        "Oulad Boussaken"
    ],
    "name:ceb_x_preferred":[
        "Oulad Boussaken"
    ],
    "name:eng_x_preferred":[
        "Oulad Boussaken"
    ],
    "name:fas_x_preferred":[
        "\u0627\u0648\u0644\u0627\u062f \u0628\u0648\u0633\u0627\u06a9\u0646"
    ],
    "name:fra_x_preferred":[
        "Oulad Boussaken"
    ],
    "name:fra_x_variant":[
        "Oulad Boussaken (CR)",
        "Oulad Boussaken (Commune Rurale)"
    ],
    "name:ita_x_preferred":[
        "Oulad Boussaken"
    ],
    "name:swe_x_preferred":[
        "Oulad Boussaken"
    ],
    "qs:name":"Oulad Boussaken",
    "qs:photos_9r":0,
    "qs:photos_sr":0,
    "qs:pop_sr":"5",
    "wd:wordcount":61,
    "wof:name":"Oulad Boussaken",
    "wof:placetype":"localadmin",
    "wof:population":7641
},
  "geometry": {"coordinates":[-8.14417,32.57013],"type":"Point"}
}