{
  "type": "Feature",
  "properties": {
    "gn:country":"MA",
    "gn:fcode":"ADM3",
    "gn:pop":7641,
    "iso:country":"MA",
    "name:ara_x_preferred":[
        "\u0623\u0648\u0644\u0627\u062f \u0639\u0645\u0631\u0627\u0646"
    ],
    "name:fra_x_preferred":[
        "Oulad Boussaken"
    ],
    "name:fra_x_variant":[
        "Oulad Boussaken (CR)",
        "Oulad Boussaken (Commune Rurale)"
    ],
    "qs:name":"Oulad Boussaken",
    "qs:photos_9r":0,
    "qs:photos_sr":0,
    "qs:pop_sr":"5",
    "wd:wordcount":61,
    "wof:name":"Oulad Boussaken",
    "wof:placetype":"localadmin",
    "wof:population":7641
},
  "geometry": {"coordinates":[-8.14417,32.57013],"type":"Point"}
}