{
  "type": "Feature",
  "properties": {
    "gn:admin1_code":"7.0",
    "gn:asciiname":"'Ali ou Hammou",
    "gn:country_code":"MA",
    "gn:dem":732,
    "gn:feature_class":"P",
    "gn:feature_code":"PPL",
    "gn:name":"\u2019Ali ou Hammou",
    "gn:population":0,
    "gn:timezone":"Africa/Casablanca",
    "iso:country":"MA",
    "wof:name":"'Ali ou Hammou",
    "wof:placetype":"locality"
},
  "geometry": {"coordinates":[-8.47915,31.28779],"type":"Point"}
}