{
  "type": "Feature",
  "properties": {
    "gn:admin1_code":"09",
    "gn:asciiname":"Agounsa",
    "gn:country_code":"MA",
    "gn:dem":1595,
    "gn:feature_class":"P",
    "gn:feature_code":"PPL",
    "gn:name":"Agounsa",
    "gn:population":0,
    "gn:timezone":"Africa/Casablanca",
    "iso:country":"MA",
    "name:und_x_variant":[
        "Agoursa",
        "Agounsa"
    ],
    "wof:name":"Agounsa",
    "wof:placetype":"locality"
},
  "geometry": {"coordinates":[-8.86025,30.76809],"type":"Point"}
}