{
  "type": "Feature",
  "properties": {
    "gn:admin1_code":"05",
    "gn:asciiname":"Tafraout",
    "gn:country_code":"MA",
    "gn:dem":2350,
    "gn:feature_class":"P",
    "gn:feature_code":"PPL",
    "gn:name":"Tafraout",
    "gn:population":0,
    "gn:timezone":"Africa/Casablanca",
    "iso:country":"MA",
    "name:ara_x_preferred":[
        "\u062a\u0627\u0641\u0631\u0627\u0648\u062a"
    ],
    "name:cat_x_preferred":[
        "Tafraout"
    ],
    "name:deu_x_preferred":[
        "Tafraoute"
    ],
    "name:fra_x_preferred":[
        "Tafraout"
    ],
    "name:ita_x_preferred":[
        "Tafraout"
    ],
    "name:por_x_preferred":[
        "Tafraout"
    ],
    "wof:name":"Tafraout",
    "wof:placetype":"locality"
},
  "geometry": {"coordinates":[-5.95661,31.84158],"type":"Point"}
}