{
  "type": "Feature",
  "properties": {
    "gn:admin1_code":"7.0",
    "gn:asciiname":"Oulad Zalagh",
    "gn:country_code":"MA",
    "gn:dem":242,
    "gn:feature_class":"P",
    "gn:feature_code":"PPL",
    "gn:name":"Oulad Zalagh",
    "gn:population":0,
    "gn:timezone":"Africa/Casablanca",
    "iso:country":"MA",
    "wof:name":"Oulad Zalagh",
    "wof:placetype":"locality"
},
  "geometry": {"coordinates":[-8.80721,32.22277],"type":"Point"}
}