{
  "type": "Feature",
  "properties": {
    "gn:admin1_code":"1.0",
    "gn:asciiname":"Douar Oulad Lhamdi",
    "gn:country_code":"MA",
    "gn:dem":784,
    "gn:feature_class":"P",
    "gn:feature_code":"PPL",
    "gn:name":"Douar Oulad Lhamdi",
    "gn:population":0,
    "gn:timezone":"Africa/Casablanca",
    "iso:country":"MA",
    "wof:name":"Douar Oulad Lhamdi",
    "wof:placetype":"locality"
},
  "geometry": {"coordinates":[-4.34541,35.02229000000001],"type":"Point"}
}