{
  "type": "Feature",
  "properties": {
    "gn:admin1_code":"54",
    "gn:asciiname":"Talezzert Talezart",
    "gn:country_code":"MA",
    "gn:dem":497,
    "gn:feature_class":"P",
    "gn:feature_code":"PPL",
    "gn:name":"Talezzert Talezart",
    "gn:population":0,
    "gn:timezone":"Africa/Casablanca",
    "iso:country":"MA",
    "wof:name":"Talezzert Talezart",
    "wof:placetype":"locality"
},
  "geometry": {"coordinates":[-2.56,34.78],"type":"Point"}
}