{
  "type": "Feature",
  "properties": {
    "gn:admin1_code":"9.0",
    "gn:asciiname":"Ait Azzouz",
    "gn:country_code":"MA",
    "gn:dem":188,
    "gn:feature_class":"P",
    "gn:feature_code":"PPL",
    "gn:name":"A\u00eft Azzouz",
    "gn:population":0,
    "gn:timezone":"Africa/Casablanca",
    "iso:country":"MA",
    "wof:name":"Ait Azzouz",
    "wof:placetype":"locality"
},
  "geometry": {"coordinates":[-8.96002,30.43001],"type":"Point"}
}