{
  "type": "Feature",
  "properties": {
    "gn:admin1_code":"07",
    "gn:asciiname":"Douar Zaouiat Sidi Said",
    "gn:country_code":"MA",
    "gn:dem":194,
    "gn:feature_class":"P",
    "gn:feature_code":"PPL",
    "gn:name":"Douar Zaouiat Sidi Said",
    "gn:population":0,
    "gn:timezone":"Africa/Casablanca",
    "iso:country":"MA",
    "name:und_x_variant":[
        "Zaouia Sidi Sa\u00efd Bou Chenbour",
        "Sidi Sa\u00efd Bou Khennbour",
        "Zaouia Oulad Sidi Sa\u00efd",
        "Zaouit Sidi Sa\u00efd",
        "Sidi Sa\u00efd Bou Chembour",
        "Douar Zaouiat Sidi Said"
    ],
    "wof:name":"Douar Zaouiat Sidi Said",
    "wof:placetype":"locality"
},
  "geometry": {"coordinates":[-9.16558,32.11923],"type":"Point"}
}