{
  "type": "Feature",
  "properties": {
    "gn:admin1_code":"8.0",
    "gn:asciiname":"Ziyb Tilkriyt",
    "gn:country_code":"MA",
    "gn:dem":2390,
    "gn:feature_class":"P",
    "gn:feature_code":"PPL",
    "gn:name":"Ziyb Tilkriyt",
    "gn:population":0,
    "gn:timezone":"Africa/Casablanca",
    "iso:country":"MA",
    "wof:name":"Ziyb Tilkriyt",
    "wof:placetype":"locality"
},
  "geometry": {"coordinates":[-7.18048,31.33301],"type":"Point"}
}