{
  "type": "Feature",
  "properties": {
    "gn:admin1_code":"7.0",
    "gn:asciiname":"Awsir",
    "gn:country_code":"MA",
    "gn:dem":1465,
    "gn:feature_class":"P",
    "gn:feature_code":"PPL",
    "gn:name":"Awsir",
    "gn:population":0,
    "gn:timezone":"Africa/Casablanca",
    "iso:country":"MA",
    "wof:name":"Awsir",
    "wof:placetype":"locality"
},
  "geometry": {"coordinates":[-8.87368,31.07649],"type":"Point"}
}