{
  "type": "Feature",
  "properties": {
    "gn:admin1_code":"03",
    "gn:asciiname":"As Siouane",
    "gn:country_code":"MA",
    "gn:dem":245,
    "gn:feature_class":"P",
    "gn:feature_code":"PPL",
    "gn:name":"As Siouane",
    "gn:population":0,
    "gn:timezone":"Africa/Casablanca",
    "iso:country":"MA",
    "wof:name":"As Siouane",
    "wof:placetype":"locality"
},
  "geometry": {"coordinates":[-4.93115,34.55368],"type":"Point"}
}