{
  "type": "Feature",
  "properties": {
    "gn:country":"MA",
    "gn:fcode":"ADM3",
    "gn:pop":4301,
    "iso:country":"MA",
    "name:ara_x_preferred":[
        "\u0633\u064a\u062f\u064a \u0627\u062d\u0645\u062f \u0627\u0648 \u0645\u0628\u0627\u0631\u0643"
    ],
    "name:ara_x_variant":[
        "\u0633\u064a\u062f\u064a \u0623\u062d\u0645\u062f \u0623\u0648\u062d\u0627\u0645\u062f"
    ],
    "name:cat_x_preferred":[
        "Sidi Hmad Ou Hamed"
    ],
    "name:ceb_x_preferred":[
        "Sidi Hmad Ou Hamed"
    ],
    "name:eng_x_preferred":[
        "Sidi Hmad Ou Hamed"
    ],
    "name:fra_x_preferred":[
        "Sidi Hmad Ou Hamed"
    ],
    "name:fra_x_variant":[
        "Sidi Hmad Ou Hamed (CR)",
        "Sidi Hmad Ou Hamed (Commune Rurale)"
    ],
    "name:ita_x_preferred":[
        "Sidi Hmad Ou Hamed"
    ],
    "name:swe_x_preferred":[
        "Sidi Hmad Ou Hamed"
    ],
    "qs:name":"Sidi Hmad Ou Hamed",
    "qs:photos_9r":0,
    "qs:photos_sr":0,
    "qs:pop_sr":"4",
    "wd:wordcount":64,
    "wof:name":"Sidi Hmad Ou Hamed",
    "wof:placetype":"localadmin",
    "wof:population":4301
},
  "geometry": {"coordinates":[-9.68174,31.35423],"type":"Point"}
}