{
  "type": "Feature",
  "properties": {
    "gn:admin1_code":"10",
    "gn:asciiname":"Cheikh Sidi Balaid",
    "gn:country_code":"MA",
    "gn:dem":487,
    "gn:feature_class":"P",
    "gn:feature_code":"PPL",
    "gn:name":"Che\u00efkh Sidi Balaid",
    "gn:population":0,
    "gn:timezone":"Africa/Casablanca",
    "iso:country":"MA",
    "name:und_x_variant":[
        "Chej Sidi Belaid",
        "Che\u00efkh Sidi Balaid"
    ],
    "wof:name":"Cheikh Sidi Balaid",
    "wof:placetype":"locality"
},
  "geometry": {"coordinates":[-10.19983,29.20603],"type":"Point"}
}