{
  "type": "Feature",
  "properties": {
    "gn:admin1_code":"9.0",
    "gn:asciiname":"Ait Makhlouf",
    "gn:country_code":"MA",
    "gn:dem":1430,
    "gn:feature_class":"P",
    "gn:feature_code":"PPL",
    "gn:name":"A\u00eft Makhlouf",
    "gn:population":0,
    "gn:timezone":"Africa/Casablanca",
    "iso:country":"MA",
    "name:ara_x_preferred":[
        "\u0622\u064a\u062a \u0645\u062e\u0644\u0648\u0641"
    ],
    "name:cat_x_preferred":[
        "Ait Makhlouf"
    ],
    "name:fas_x_preferred":[
        "\u0622\u06cc\u062a \u0645\u062e\u0644\u0648\u0641"
    ],
    "name:ita_x_preferred":[
        "Ait Makhlouf"
    ],
    "wof:name":"Ait Makhlouf",
    "wof:placetype":"locality"
},
  "geometry": {"coordinates":[-8.55632,30.16091],"type":"Point"}
}