{
  "type": "Feature",
  "properties": {
    "gn:admin1_code":"5.0",
    "gn:asciiname":"Charfa",
    "gn:country_code":"MA",
    "gn:dem":638,
    "gn:feature_class":"P",
    "gn:feature_code":"PPL",
    "gn:name":"Charfa",
    "gn:population":0,
    "gn:timezone":"Africa/Casablanca",
    "iso:country":"MA",
    "wof:name":"Charfa",
    "wof:placetype":"locality"
},
  "geometry": {"coordinates":[-6.88708,32.72392],"type":"Point"}
}