{
  "type": "Feature",
  "properties": {
    "gn:admin1_code":"06",
    "gn:asciiname":"Oulad Sa'id",
    "gn:country_code":"MA",
    "gn:dem":421,
    "gn:feature_class":"P",
    "gn:feature_code":"PPL",
    "gn:name":"Oulad Sa\u2019id",
    "gn:population":0,
    "gn:timezone":"Africa/Casablanca",
    "iso:country":"MA",
    "wof:name":"Oulad Sa'id",
    "wof:placetype":"locality"
},
  "geometry": {"coordinates":[-6.83,33.56],"type":"Point"}
}