{
  "type": "Feature",
  "properties": {
    "gn:admin1_code":"07",
    "gn:asciiname":"Lakrakcha",
    "gn:country_code":"MA",
    "gn:dem":618,
    "gn:feature_class":"P",
    "gn:feature_code":"PPL",
    "gn:name":"Lakrakcha",
    "gn:population":0,
    "gn:timezone":"Africa/Casablanca",
    "iso:country":"MA",
    "name:und_x_variant":[
        "Al Khakcha"
    ],
    "wof:name":"Lakrakcha",
    "wof:placetype":"locality"
},
  "geometry": {"coordinates":[-7.07407,31.96702],"type":"Point"}
}