{
  "type": "Feature",
  "properties": {
    "gn:admin1_code":"08",
    "gn:asciiname":"Boutanfit",
    "gn:country_code":"MA",
    "gn:dem":1010,
    "gn:feature_class":"P",
    "gn:feature_code":"PPL",
    "gn:name":"Boutanfit",
    "gn:population":0,
    "gn:timezone":"Africa/Casablanca",
    "iso:country":"MA",
    "name:und_x_variant":[
        "Boutenfit",
        "Bou Tounfit",
        "Boutanfit"
    ],
    "wof:name":"Boutanfit",
    "wof:placetype":"locality"
},
  "geometry": {"coordinates":[-4.92994,31.68426],"type":"Point"}
}