{
  "type": "Feature",
  "properties": {
    "gn:admin1_code":"3.0",
    "gn:asciiname":"Douar Dhar Lbir",
    "gn:country_code":"MA",
    "gn:dem":741,
    "gn:feature_class":"P",
    "gn:feature_code":"PPL",
    "gn:name":"Douar Dhar Lbir",
    "gn:population":0,
    "gn:timezone":"Africa/Casablanca",
    "iso:country":"MA",
    "name:und_x_variant":[
        "Leghris"
    ],
    "wof:name":"Douar Dhar Lbir",
    "wof:placetype":"locality"
},
  "geometry": {"coordinates":[-4.71395,33.82842],"type":"Point"}
}