{
  "type": "Feature",
  "properties": {
    "gn:admin1_code":"01",
    "gn:asciiname":"Mers Laqouar",
    "gn:country_code":"MA",
    "gn:dem":75,
    "gn:feature_class":"P",
    "gn:feature_code":"PPL",
    "gn:name":"Mers Laqouar",
    "gn:population":0,
    "gn:timezone":"Africa/Casablanca",
    "iso:country":"MA",
    "name:und_x_variant":[
        "Mers el Koar",
        "Mers el Kouar",
        "Mers Laqouar"
    ],
    "wof:name":"Mers Laqouar",
    "wof:placetype":"locality"
},
  "geometry": {"coordinates":[-5.92406,35.47282],"type":"Point"}
}