{
  "type": "Feature",
  "properties": {
    "gn:admin1_code":"09",
    "gn:asciiname":"Bouagrirene",
    "gn:country_code":"MA",
    "gn:dem":682,
    "gn:feature_class":"P",
    "gn:feature_code":"PPL",
    "gn:name":"Bouagrirene",
    "gn:population":0,
    "gn:timezone":"Africa/Casablanca",
    "iso:country":"MA",
    "name:und_x_variant":[
        "Bou Agrizen",
        "Bouagrize Bikgnafne",
        "Bouagrizene",
        "Bouagrirene"
    ],
    "wof:name":"Bouagrirene",
    "wof:placetype":"locality"
},
  "geometry": {"coordinates":[-9.0862,30.08848],"type":"Point"}
}