{
  "type": "Feature",
  "properties": {
    "gn:admin1_code":"4.0",
    "gn:asciiname":"Dar Miloud Shayli",
    "gn:country_code":"MA",
    "gn:dem":381,
    "gn:feature_class":"P",
    "gn:feature_code":"PPL",
    "gn:name":"Dar Miloud Shayli",
    "gn:population":0,
    "gn:timezone":"Africa/Casablanca",
    "iso:country":"MA",
    "wof:name":"Dar Miloud Shayli",
    "wof:placetype":"locality"
},
  "geometry": {"coordinates":[-6.58775,33.67541],"type":"Point"}
}