{
  "type": "Feature",
  "properties": {
    "gn:admin1_code":"09",
    "gn:asciiname":"Bou Safarn",
    "gn:country_code":"MA",
    "gn:dem":719,
    "gn:feature_class":"P",
    "gn:feature_code":"PPL",
    "gn:name":"Bou Safarn",
    "gn:population":0,
    "gn:timezone":"Africa/Casablanca",
    "iso:country":"MA",
    "name:und_x_variant":[
        "Bou Salarn",
        "Bou Selloum",
        "Bou Safarn"
    ],
    "wof:name":"Bou Safarn",
    "wof:placetype":"locality"
},
  "geometry": {"coordinates":[-8.16,30.68],"type":"Point"}
}