{
  "type": "Feature",
  "properties": {
    "gn:admin1_code":"02",
    "gn:asciiname":"Itchinaouiyene",
    "gn:country_code":"MA",
    "gn:dem":402,
    "gn:feature_class":"P",
    "gn:feature_code":"PPL",
    "gn:name":"Itchinaouiyene",
    "gn:population":0,
    "gn:timezone":"Africa/Casablanca",
    "iso:country":"MA",
    "wof:name":"Itchinaouiyene",
    "wof:placetype":"locality"
},
  "geometry": {"coordinates":[-3.36657,35.12621],"type":"Point"}
}