{
  "type": "Feature",
  "properties": {
    "gn:admin1_code":"7.0",
    "gn:asciiname":"Douar Sidi Lafqih",
    "gn:country_code":"MA",
    "gn:dem":466,
    "gn:feature_class":"P",
    "gn:feature_code":"PPL",
    "gn:name":"Douar Sidi Lafqih",
    "gn:population":0,
    "gn:timezone":"Africa/Casablanca",
    "iso:country":"MA",
    "wof:name":"Douar Sidi Lafqih",
    "wof:placetype":"locality"
},
  "geometry": {"coordinates":[-7.84391,31.73495],"type":"Point"}
}