{
  "type": "Feature",
  "properties": {
    "gn:admin1_code":"10",
    "gn:asciiname":"Bouaim",
    "gn:country_code":"MA",
    "gn:dem":790,
    "gn:feature_class":"P",
    "gn:feature_code":"PPL",
    "gn:name":"Boua\u00efm",
    "gn:population":0,
    "gn:timezone":"Africa/Casablanca",
    "iso:country":"MA",
    "wof:name":"Bouaim",
    "wof:placetype":"locality"
},
  "geometry": {"coordinates":[-9.95046,29.20235],"type":"Point"}
}