{
  "type": "Feature",
  "properties": {
    "gn:admin1_code":"01",
    "gn:asciiname":"Douar Adrou",
    "gn:country_code":"MA",
    "gn:dem":775,
    "gn:feature_class":"P",
    "gn:feature_code":"PPL",
    "gn:name":"Douar Adrou",
    "gn:population":0,
    "gn:timezone":"Africa/Casablanca",
    "iso:country":"MA",
    "name:und_x_variant":[
        "Adrou"
    ],
    "wof:name":"Douar Adrou",
    "wof:placetype":"locality"
},
  "geometry": {"coordinates":[-5.45356,35.19795],"type":"Point"}
}