{
  "type": "Feature",
  "properties": {
    "gn:admin1_code":"05",
    "gn:asciiname":"Ikhf-n-Ighil",
    "gn:country_code":"MA",
    "gn:dem":1079,
    "gn:feature_class":"P",
    "gn:feature_code":"PPL",
    "gn:name":"Ikhf-n-Ighil",
    "gn:population":0,
    "gn:timezone":"Africa/Casablanca",
    "iso:country":"MA",
    "name:und_x_variant":[
        "A\u00eft Irhil"
    ],
    "wof:name":"Ikhf-n-Ighil",
    "wof:placetype":"locality"
},
  "geometry": {"coordinates":[-6.74427,32.04116],"type":"Point"}
}