{
  "type": "Feature",
  "properties": {
    "gn:admin1_code":"1.0",
    "gn:asciiname":"Douar Kzira",
    "gn:country_code":"MA",
    "gn:dem":350,
    "gn:feature_class":"P",
    "gn:feature_code":"PPL",
    "gn:name":"Douar Kzira",
    "gn:population":0,
    "gn:timezone":"Africa/Casablanca",
    "iso:country":"MA",
    "wof:name":"Douar Kzira",
    "wof:placetype":"locality"
},
  "geometry": {"coordinates":[-5.65849,35.50476],"type":"Point"}
}