{
  "type": "Feature",
  "properties": {
    "gn:admin1_code":"09",
    "gn:asciiname":"Imjjat",
    "gn:country_code":"MA",
    "gn:dem":95,
    "gn:feature_class":"P",
    "gn:feature_code":"PPL",
    "gn:name":"Imjjat",
    "gn:population":0,
    "gn:timezone":"Africa/Casablanca",
    "iso:country":"MA",
    "name:und_x_variant":[
        "Imijate",
        "Imjjat"
    ],
    "wof:name":"Imjjat",
    "wof:placetype":"locality"
},
  "geometry": {"coordinates":[-9.54727,29.94685],"type":"Point"}
}