{
  "type": "Feature",
  "properties": {
    "gn:admin1_code":"03",
    "gn:asciiname":"Mesrawa Sefliya",
    "gn:country_code":"MA",
    "gn:dem":448,
    "gn:feature_class":"P",
    "gn:feature_code":"PPL",
    "gn:name":"Mesrawa Sefliya",
    "gn:population":0,
    "gn:timezone":"Africa/Casablanca",
    "iso:country":"MA",
    "wof:name":"Mesrawa Sefliya",
    "wof:placetype":"locality"
},
  "geometry": {"coordinates":[-4.72964,34.5424],"type":"Point"}
}