{
  "type": "Feature",
  "properties": {
    "gn:admin1_code":"09",
    "gn:asciiname":"Tizirt",
    "gn:country_code":"MA",
    "gn:dem":1264,
    "gn:feature_class":"P",
    "gn:feature_code":"PPL",
    "gn:name":"Tizirt",
    "gn:population":0,
    "gn:timezone":"Africa/Casablanca",
    "iso:country":"MA",
    "wof:name":"Tizirt",
    "wof:placetype":"locality"
},
  "geometry": {"coordinates":[-8.42599,30.21062],"type":"Point"}
}