{
  "type": "Feature",
  "properties": {
    "gn:admin1_code":"08",
    "gn:asciiname":"Azib",
    "gn:country_code":"MA",
    "gn:dem":1569,
    "gn:feature_class":"P",
    "gn:feature_code":"PPL",
    "gn:name":"Azib",
    "gn:population":0,
    "gn:timezone":"Africa/Casablanca",
    "iso:country":"MA",
    "wof:name":"Azib",
    "wof:placetype":"locality"
},
  "geometry": {"coordinates":[-6.25785,31.2725],"type":"Point"}
}