{
  "type": "Feature",
  "properties": {
    "gn:admin1_code":"3.0",
    "gn:asciiname":"Ait Chaayeb",
    "gn:country_code":"MA",
    "gn:dem":751,
    "gn:feature_class":"P",
    "gn:feature_code":"PPL",
    "gn:name":"Ait Chaayeb",
    "gn:population":0,
    "gn:timezone":"Africa/Casablanca",
    "iso:country":"MA",
    "wof:name":"Ait Chaayeb",
    "wof:placetype":"locality"
},
  "geometry": {"coordinates":[-5.24897,33.82445999999999],"type":"Point"}
}