{
  "type": "Feature",
  "properties": {
    "gn:admin1_code":"9.0",
    "gn:asciiname":"Agueni Ouzdar",
    "gn:country_code":"MA",
    "gn:dem":1099,
    "gn:feature_class":"P",
    "gn:feature_code":"PPL",
    "gn:name":"Agueni Ouzdar",
    "gn:population":0,
    "gn:timezone":"Africa/Casablanca",
    "iso:country":"MA",
    "wof:name":"Agueni Ouzdar",
    "wof:placetype":"locality"
},
  "geometry": {"coordinates":[-9.44458,30.64433],"type":"Point"}
}