{
  "type": "Feature",
  "properties": {
    "gn:admin1_code":"7.0",
    "gn:asciiname":"Oulad 'Abbou",
    "gn:country_code":"MA",
    "gn:dem":551,
    "gn:feature_class":"P",
    "gn:feature_code":"PPL",
    "gn:name":"Oulad \u2019Abbou",
    "gn:population":0,
    "gn:timezone":"Africa/Casablanca",
    "iso:country":"MA",
    "wof:name":"Oulad 'Abbou",
    "wof:placetype":"locality"
},
  "geometry": {"coordinates":[-7.37308,31.93574000000001],"type":"Point"}
}