{
  "type": "Feature",
  "properties": {
    "gn:admin1_code":"02",
    "gn:asciiname":"Oulad Bouazza",
    "gn:country_code":"MA",
    "gn:dem":222,
    "gn:feature_class":"P",
    "gn:feature_code":"PPL",
    "gn:name":"Oulad Bouazza",
    "gn:population":0,
    "gn:timezone":"Africa/Casablanca",
    "iso:country":"MA",
    "name:und_x_variant":[
        "Oulad Bo\u00fb \u2019Azza"
    ],
    "wof:name":"Oulad Bouazza",
    "wof:placetype":"locality"
},
  "geometry": {"coordinates":[-3.10134,35.02899],"type":"Point"}
}