{
  "type": "Feature",
  "properties": {
    "gn:admin1_code":"07",
    "gn:asciiname":"Idarmach",
    "gn:country_code":"MA",
    "gn:dem":797,
    "gn:feature_class":"P",
    "gn:feature_code":"PPL",
    "gn:name":"Idarmach",
    "gn:population":0,
    "gn:timezone":"Africa/Casablanca",
    "iso:country":"MA",
    "name:und_x_variant":[
        "Idermache",
        "Idermach"
    ],
    "wof:name":"Idarmach",
    "wof:placetype":"locality"
},
  "geometry": {"coordinates":[-7.68284,31.49029],"type":"Point"}
}