{
  "type": "Feature",
  "properties": {
    "gn:admin1_code":"3.0",
    "gn:asciiname":"Douar Gharbia",
    "gn:country_code":"MA",
    "gn:dem":138,
    "gn:feature_class":"P",
    "gn:feature_code":"PPL",
    "gn:name":"Douar Gharbia",
    "gn:population":0,
    "gn:timezone":"Africa/Casablanca",
    "iso:country":"MA",
    "wof:name":"Douar Gharbia",
    "wof:placetype":"locality"
},
  "geometry": {"coordinates":[-5.22794,34.49506],"type":"Point"}
}