{
  "type": "Feature",
  "properties": {
    "gn:admin1_code":"7.0",
    "gn:asciiname":"Igroukka",
    "gn:country_code":"MA",
    "gn:dem":1411,
    "gn:feature_class":"P",
    "gn:feature_code":"PPL",
    "gn:name":"Igroukka",
    "gn:population":0,
    "gn:timezone":"Africa/Casablanca",
    "iso:country":"MA",
    "wof:name":"Igroukka",
    "wof:placetype":"locality"
},
  "geometry": {"coordinates":[-7.64562,31.37759],"type":"Point"}
}