{
  "type": "Feature",
  "properties": {
    "gn:admin1_code":"05",
    "gn:asciiname":"Ait 'Abdallah",
    "gn:country_code":"MA",
    "gn:dem":781,
    "gn:elevation":"0.0",
    "gn:feature_class":"P",
    "gn:feature_code":"PPL",
    "gn:name":"A\u00eft \u2019Abdallah",
    "gn:population":0,
    "gn:timezone":"Africa/Casablanca",
    "iso:country":"MA",
    "name:und_x_variant":[
        "A\u00eft Abdellah",
        "Douar Ca\u00efd Abdallah",
        "A\u00eft \u2019Abdallah"
    ],
    "wof:name":"Ait 'Abdallah",
    "wof:placetype":"locality"
},
  "geometry": {"coordinates":[-6.96096,31.83327],"type":"Point"}
}