{
  "type": "Feature",
  "properties": {
    "gn:admin1_code":"01",
    "gn:asciiname":"Er Rif",
    "gn:country_code":"MA",
    "gn:dem":1169,
    "gn:feature_class":"P",
    "gn:feature_code":"PPL",
    "gn:name":"Er Rif",
    "gn:population":0,
    "gn:timezone":"Africa/Casablanca",
    "iso:country":"MA",
    "name:ell_x_preferred":[
        "\u0395\u03c1 \u03a1\u03b9\u03c6"
    ],
    "name:hin_x_preferred":[
        "\u090f\u0930 \u0930\u093f\u092b\u094d"
    ],
    "name:kor_x_preferred":[
        "\uc5b4 \ub9ac\ud504"
    ],
    "name:tur_x_preferred":[
        "Er Rif"
    ],
    "name:vie_x_preferred":[
        "D\u00e3y Er Rif"
    ],
    "wof:name":"Er Rif",
    "wof:placetype":"locality"
},
  "geometry": {"coordinates":[-4.73,34.88],"type":"Point"}
}