{
  "type": "Feature",
  "properties": {
    "gn:admin1_code":"1.0",
    "gn:asciiname":"Mghougha Jdida",
    "gn:country_code":"MA",
    "gn:dem":44,
    "gn:feature_class":"P",
    "gn:feature_code":"PPL",
    "gn:name":"Mghougha Jdida",
    "gn:population":0,
    "gn:timezone":"Africa/Casablanca",
    "iso:country":"MA",
    "wof:name":"Mghougha Jdida",
    "wof:placetype":"locality"
},
  "geometry": {"coordinates":[-5.78247,35.75271],"type":"Point"}
}