{
  "type": "Feature",
  "properties": {
    "gn:admin1_code":"9.0",
    "gn:asciiname":"Ait ou Lahiane",
    "gn:country_code":"MA",
    "gn:dem":724,
    "gn:feature_class":"P",
    "gn:feature_code":"PPL",
    "gn:name":"A\u00eft ou Lahiane",
    "gn:population":0,
    "gn:timezone":"Africa/Casablanca",
    "iso:country":"MA",
    "wof:name":"Ait ou Lahiane",
    "wof:placetype":"locality"
},
  "geometry": {"coordinates":[-9.3523,30.61979],"type":"Point"}
}