{
  "type": "Feature",
  "properties": {
    "gn:admin1_code":"03",
    "gn:asciiname":"Oulad Slama",
    "gn:country_code":"MA",
    "gn:dem":192,
    "gn:feature_class":"P",
    "gn:feature_code":"PPL",
    "gn:name":"Oulad Slama",
    "gn:population":0,
    "gn:timezone":"Africa/Casablanca",
    "iso:country":"MA",
    "name:ara_x_preferred":[
        "\u0623\u0648\u0644\u0627\u062f \u0633\u0644\u0627\u0645\u0629"
    ],
    "name:cat_x_preferred":[
        "Oulad Slama"
    ],
    "name:und_x_variant":[
        "Ouled Slama"
    ],
    "wof:name":"Oulad Slama",
    "wof:placetype":"locality"
},
  "geometry": {"coordinates":[-5.43037,34.38365],"type":"Point"}
}