{
  "type": "Feature",
  "properties": {
    "gn:admin1_code":"55",
    "gn:asciiname":"Talat",
    "gn:cc2":"MA",
    "gn:country_code":"MA",
    "gn:dem":1293,
    "gn:feature_class":"P",
    "gn:feature_code":"PPL",
    "gn:name":"Talat",
    "gn:population":0,
    "gn:timezone":"Africa/Casablanca",
    "iso:country":"MA",
    "name:ceb_x_preferred":[
        "Talat"
    ],
    "name:deu_x_preferred":[
        "Talat"
    ],
    "name:rus_x_preferred":[
        "\u0422\u0430\u043b\u0430\u0442"
    ],
    "name:und_x_variant":[
        "Talate"
    ],
    "wof:name":"Talat",
    "wof:placetype":"locality"
},
  "geometry": {"coordinates":[-8.28,30.03],"type":"Point"}
}