{
  "type": "Feature",
  "properties": {
    "gn:admin1_code":"04",
    "gn:asciiname":"Douar Oulad el Ahmar",
    "gn:country_code":"MA",
    "gn:dem":41,
    "gn:feature_class":"P",
    "gn:feature_code":"PPL",
    "gn:name":"Douar Oulad el Ahmar",
    "gn:population":0,
    "gn:timezone":"Africa/Casablanca",
    "iso:country":"MA",
    "name:und_x_variant":[
        "Oulad Lahmar",
        "Oulad el Ahmar"
    ],
    "wof:name":"Douar Oulad el Ahmar",
    "wof:placetype":"locality"
},
  "geometry": {"coordinates":[-5.56625,34.45452],"type":"Point"}
}