{
  "type": "Feature",
  "properties": {
    "gn:gn_country":"MA",
    "gn:gn_fcode":"ADM3",
    "gn:gn_pop":20541,
    "gn:population":20541,
    "iso:country":"MA",
    "name:ara_x_preferred":[
        "\u0627\u062c\u0648\u0627\u0645\u0639\u0629"
    ],
    "name:fra_x_preferred":[
        "Laaouama"
    ],
    "name:fra_x_variant":[
        "Laaouama (CR)",
        "Laaouama (Commune Rurale)"
    ],
    "qs_pg:aaroncc":"MA",
    "qs_pg:gn_country":"MA",
    "qs_pg:gn_fcode":"ADM3",
    "qs_pg:gn_pop":20541,
    "qs_pg:name":"Laaouama",
    "qs_pg:photos_9r":0,
    "qs_pg:photos_sr":0,
    "qs_pg:pop_sr":7,
    "qs_pg:qs_pg_placetype":"localadmin",
    "wof:name":"Laaouama",
    "wof:placetype":"localadmin",
    "wof:population":20541
},
  "geometry": {"coordinates":[-5.79053,35.69189],"type":"Point"}
}