{
  "type": "Feature",
  "properties": {
    "gn:admin1_code":"09",
    "gn:asciiname":"Annzad",
    "gn:country_code":"MA",
    "gn:dem":378,
    "gn:feature_class":"P",
    "gn:feature_code":"PPL",
    "gn:name":"Annzad",
    "gn:population":0,
    "gn:timezone":"Africa/Casablanca",
    "iso:country":"MA",
    "name:und_x_variant":[
        "Anzad"
    ],
    "wof:name":"Annzad",
    "wof:placetype":"locality"
},
  "geometry": {"coordinates":[-9.1292,30.16053],"type":"Point"}
}