{
  "type": "Feature",
  "properties": {
    "gn:admin1_code":"7.0",
    "gn:asciiname":"Ait Bnidir",
    "gn:country_code":"MA",
    "gn:dem":734,
    "gn:feature_class":"P",
    "gn:feature_code":"PPL",
    "gn:name":"A\u00eft Bnidir",
    "gn:population":0,
    "gn:timezone":"Africa/Casablanca",
    "iso:country":"MA",
    "wof:name":"Ait Bnidir",
    "wof:placetype":"locality"
},
  "geometry": {"coordinates":[-9.44328,31.26011],"type":"Point"}
}