{
  "type": "Feature",
  "properties": {
    "gn:country":"MA",
    "gn:fcode":"PPLA3",
    "gn:population":82518,
    "iso:country":"MA",
    "name:ara_x_preferred":[
        "\u062a\u0627\u0648\u0631\u064a\u0631\u062a"
    ],
    "name:azb_x_preferred":[
        "\u062a\u0627\u0648\u0631\u06cc\u0631\u062a"
    ],
    "name:ben_x_preferred":[
        "\u09a4\u09be\u0993\u09b0\u09bf\u09b0\u09cd\u09a4"
    ],
    "name:cat_x_preferred":[
        "Taourirt"
    ],
    "name:ceb_x_preferred":[
        "Taourirt"
    ],
    "name:dan_x_preferred":[
        "Taourirt"
    ],
    "name:deu_x_preferred":[
        "Taourirt"
    ],
    "name:ell_x_preferred":[
        "\u03a4\u03b1\u03bf\u03c5\u03c1\u03af\u03c1\u03c4"
    ],
    "name:eng_x_preferred":[
        "Taourirt"
    ],
    "name:fas_x_preferred":[
        "\u062a\u0627\u0648\u0631\u06cc\u0631\u062a"
    ],
    "name:fin_x_preferred":[
        "Taourirt"
    ],
    "name:fra_x_preferred":[
        "Taourirt"
    ],
    "name:guj_x_preferred":[
        "\u0a9f\u0abe\u0a89\u0ab0\u0ab0\u0acd\u0a9f"
    ],
    "name:hin_x_preferred":[
        "\u091f\u093e\u092f\u0930\u093f\u0930\u0924"
    ],
    "name:ind_x_preferred":[
        "Taourirt"
    ],
    "name:ita_x_preferred":[
        "Taourirt"
    ],
    "name:jpn_x_preferred":[
        "\u30bf\u30a6\u30ea\u30eb"
    ],
    "name:kan_x_preferred":[
        "\u0c9f\u0ccc\u0cb0\u0ccd\u0c9f\u0ccd"
    ],
    "name:kor_x_preferred":[
        "\ud0c0\uc6b0\ub9ac\ub974\ud2b8"
    ],
    "name:lav_x_preferred":[
        "Taorirta"
    ],
    "name:lit_x_preferred":[
        "Taurirtas"
    ],
    "name:mar_x_preferred":[
        "\u0924\u093e\u0909\u0930\u0930\u094d\u091f"
    ],
    "name:msa_x_preferred":[
        "Taourirt"
    ],
    "name:nld_x_preferred":[
        "Taourirt"
    ],
    "name:nob_x_preferred":[
        "Taourirt"
    ],
    "name:pol_x_preferred":[
        "Taurirt"
    ],
    "name:por_x_preferred":[
        "Taourirt"
    ],
    "name:rus_x_preferred":[
        "\u0422\u0430\u0443\u0440\u0438\u0440\u0442"
    ],
    "name:sin_x_preferred":[
        "\u0da7\u0dcf\u0d94\u0dbb\u0dbb\u0dca\u0da7\u0dca"
    ],
    "name:spa_x_preferred":[
        "Taoririrt"
    ],
    "name:swe_x_preferred":[
        "Taourirt"
    ],
    "name:tam_x_preferred":[
        "\u0b9f\u0bb5\u0bc1\u0bb0\u0bbf\u0bb0\u0bcd\u0b9f\u0bcd"
    ],
    "name:tel_x_preferred":[
        "\u0c24\u0c4c\u0c30\u0c3f\u0c30\u0c4d\u0c1f\u0c4d"
    ],
    "name:tha_x_preferred":[
        "\u0e17\u0e32\u0e40\u0e23\u0e34\u0e17"
    ],
    "name:tur_x_preferred":[
        "Taourirt"
    ],
    "name:ukr_x_preferred":[
        "\u0422\u0430\u0443\u0440\u0456\u0440\u0442"
    ],
    "name:urd_x_preferred":[
        "\u062a\u0627\u0648\u0631\u06cc\u0631\u062a\u060c \u0645\u0631\u0627\u06a9\u0634"
    ],
    "name:urd_x_variant":[
        "\u062a\u0627\u0648\u0631\u06cc\u0631\u062a"
    ],
    "name:vie_x_preferred":[
        "Taourirt"
    ],
    "name:zho_x_preferred":[
        "\u9676\u91cc\u723e\u7279"
    ],
    "qs:name":"Taourirt",
    "qs:photos_9r":0,
    "qs:photos_sr":0,
    "qs:pop_sr":"8",
    "wd:wordcount":25,
    "wof:name":"Taourirt",
    "wof:placetype":"locality",
    "wof:population":82518
},
  "geometry": {"coordinates":[-2.89732,34.4073],"type":"Point"}
}