{
  "type": "Feature",
  "properties": {
    "gn:admin1_code":"3.0",
    "gn:asciiname":"Douar Essadat",
    "gn:country_code":"MA",
    "gn:dem":256,
    "gn:feature_class":"P",
    "gn:feature_code":"PPL",
    "gn:name":"Douar Essadat",
    "gn:population":0,
    "gn:timezone":"Africa/Casablanca",
    "iso:country":"MA",
    "wof:name":"Douar Essadat",
    "wof:placetype":"locality"
},
  "geometry": {"coordinates":[-5.26966,34.09053],"type":"Point"}
}