{
  "type": "Feature",
  "properties": {
    "gn:admin1_code":"1.0",
    "gn:asciiname":"Chouiyekh",
    "gn:country_code":"MA",
    "gn:dem":14,
    "gn:feature_class":"P",
    "gn:feature_code":"PPL",
    "gn:name":"Chouiyekh",
    "gn:population":0,
    "gn:timezone":"Africa/Casablanca",
    "iso:country":"MA",
    "wof:name":"Chouiyekh",
    "wof:placetype":"locality"
},
  "geometry": {"coordinates":[-5.56769,35.8413],"type":"Point"}
}