{
  "type": "Feature",
  "properties": {
    "gn:admin1_code":"08",
    "gn:asciiname":"Oulad 'Arbiya",
    "gn:country_code":"MA",
    "gn:dem":1202,
    "gn:feature_class":"P",
    "gn:feature_code":"PPL",
    "gn:name":"Oulad \u2019Arbiya",
    "gn:population":0,
    "gn:timezone":"Africa/Casablanca",
    "iso:country":"MA",
    "wof:name":"Oulad 'Arbiya",
    "wof:placetype":"locality"
},
  "geometry": {"coordinates":[-6.60567,31.04668],"type":"Point"}
}