{
  "type": "Feature",
  "properties": {
    "gn:country":"MA",
    "gn:fcode":"ADM3",
    "gn:pop":4608,
    "iso:country":"MA",
    "name:ara_x_preferred":[
        "\u062a\u064a\u0632\u0643\u064a\u0646"
    ],
    "name:ara_x_variant":[
        "\u0623\u063a\u0628\u0627\u0631"
    ],
    "name:azb_x_preferred":[
        "\u0627\u0642\u0628\u0627\u0631"
    ],
    "name:cat_x_preferred":[
        "Aghbar"
    ],
    "name:eng_x_preferred":[
        "Aghbar"
    ],
    "name:fas_x_preferred":[
        "\u0627\u0642\u0628\u0627\u0631"
    ],
    "name:fra_x_preferred":[
        "Aghbar"
    ],
    "name:fra_x_variant":[
        "Aghbar (CR)",
        "Aghbar (Commune Rurale)"
    ],
    "name:ita_x_preferred":[
        "Aghbar"
    ],
    "name:urd_x_preferred":[
        "\u0627\u0642\u0628\u0627\u0631"
    ],
    "qs:name":"Aghbar",
    "qs:photos_9r":0,
    "qs:photos_sr":0,
    "qs:pop_sr":"4",
    "wd:wordcount":79,
    "wof:name":"Aghbar",
    "wof:placetype":"localadmin",
    "wof:population":4608
},
  "geometry": {"coordinates":[-8.50186,30.91765],"type":"Point"}
}