{
  "type": "Feature",
  "properties": {
    "gn:admin1_code":"09",
    "gn:asciiname":"Ighir Ida Oumalguis",
    "gn:country_code":"MA",
    "gn:dem":1276,
    "gn:feature_class":"P",
    "gn:feature_code":"PPL",
    "gn:name":"Ighir Ida Oumalguis",
    "gn:population":0,
    "gn:timezone":"Africa/Casablanca",
    "iso:country":"MA",
    "name:und_x_variant":[
        "Ighir Ida Oumaguis",
        "Irhir",
        "Ighir Ida Oumalguis"
    ],
    "wof:name":"Ighir Ida Oumalguis",
    "wof:placetype":"locality"
},
  "geometry": {"coordinates":[-8.69947,30.1563],"type":"Point"}
}