{
  "type": "Feature",
  "properties": {
    "gn:admin1_code":"05",
    "gn:asciiname":"Taglast",
    "gn:country_code":"MA",
    "gn:dem":1663,
    "gn:feature_class":"P",
    "gn:feature_code":"PPL",
    "gn:name":"Taglast",
    "gn:population":0,
    "gn:timezone":"Africa/Casablanca",
    "iso:country":"MA",
    "name:und_x_variant":[
        "Tagoulast"
    ],
    "wof:name":"Taglast",
    "wof:placetype":"locality"
},
  "geometry": {"coordinates":[-6.90693,31.44654],"type":"Point"}
}