{
  "type": "Feature",
  "properties": {
    "gn:admin1_code":"07",
    "gn:asciiname":"Ould Ar Rami",
    "gn:country_code":"MA",
    "gn:dem":471,
    "gn:feature_class":"P",
    "gn:feature_code":"PPL",
    "gn:name":"Ould Ar Rami",
    "gn:population":0,
    "gn:timezone":"Africa/Casablanca",
    "iso:country":"MA",
    "name:und_x_variant":[
        "Ould er Ram"
    ],
    "wof:name":"Ould Ar Rami",
    "wof:placetype":"locality"
},
  "geometry": {"coordinates":[-8.23316,32.16076],"type":"Point"}
}