{
  "type": "Feature",
  "properties": {
    "gn:admin1_code":"7.0",
    "gn:asciiname":"Lkantaoni",
    "gn:country_code":"MA",
    "gn:dem":420,
    "gn:feature_class":"P",
    "gn:feature_code":"PPL",
    "gn:name":"Lkantaoni",
    "gn:population":0,
    "gn:timezone":"Africa/Casablanca",
    "iso:country":"MA",
    "wof:name":"Lkantaoni",
    "wof:placetype":"locality"
},
  "geometry": {"coordinates":[-8.51863,31.53896],"type":"Point"}
}