{
  "type": "Feature",
  "properties": {
    "gn:country":"MA",
    "gn:fcode":"ADM3",
    "gn:population":8224,
    "iso:country":"MA",
    "name:ara_x_preferred":[
        "\u0627\u0643\u0644\u064a"
    ],
    "name:ara_x_variant":[
        "\u0625\u064a\u06ad\u0648\u062f\u0627\u0631 \u0645\u0646\u0627\u0628\u0647\u0629",
        "\u0625\u064a\u06ad\u0648\u062f\u0627\u0631 \u0627\u0645\u0646\u0627\u0628\u0647\u0627"
    ],
    "name:ary_x_preferred":[
        "\u0625\u064a\u06ad\u0648\u062f\u0627\u0631 \u0645\u0646\u0627\u0628\u0647\u0629"
    ],
    "name:cat_x_preferred":[
        "Igoudar Mnabha"
    ],
    "name:ceb_x_preferred":[
        "Igoudar Mnabha"
    ],
    "name:eng_x_preferred":[
        "Igoudar Mnabha"
    ],
    "name:fra_x_preferred":[
        "Igoudar Mnabha"
    ],
    "name:fra_x_variant":[
        "Igoudar Mnabha (CR)",
        "Igoudar Mnabha (Commune Rurale)"
    ],
    "name:ita_x_preferred":[
        "Igoudar Mnabha"
    ],
    "name:swe_x_preferred":[
        "Igoudar Mnabha"
    ],
    "qs:name":"Igoudar Mnabha",
    "qs:photos_9r":0,
    "qs:photos_sr":0,
    "qs:pop_sr":"5",
    "wd:wordcount":61,
    "wof:name":"Igoudar Mnabha",
    "wof:placetype":"localadmin",
    "wof:population":8224
},
  "geometry": {"coordinates":[-8.44138,30.65502],"type":"Point"}
}