{
  "type": "Feature",
  "properties": {
    "gn:country":"MA",
    "gn:fcode":"ADM3",
    "gn:pop":8224,
    "iso:country":"MA",
    "name:ara_x_preferred":[
        "\u0627\u0643\u0644\u064a"
    ],
    "name:fra_x_preferred":[
        "Igoudar Mnabha"
    ],
    "name:fra_x_variant":[
        "Igoudar Mnabha (CR)",
        "Igoudar Mnabha (Commune Rurale)"
    ],
    "qs:name":"Igoudar Mnabha",
    "qs:photos_9r":0,
    "qs:photos_sr":0,
    "qs:pop_sr":"5",
    "wd:wordcount":61,
    "wof:name":"Igoudar Mnabha",
    "wof:placetype":"localadmin",
    "wof:population":8224
},
  "geometry": {"coordinates":[-8.44138,30.65502],"type":"Point"}
}