{
  "type": "Feature",
  "properties": {
    "gn:admin1_code":"1.0",
    "gn:asciiname":"Douar Layyadene",
    "gn:country_code":"MA",
    "gn:dem":762,
    "gn:feature_class":"P",
    "gn:feature_code":"PPL",
    "gn:name":"Douar Layyadene",
    "gn:population":0,
    "gn:timezone":"Africa/Casablanca",
    "iso:country":"MA",
    "wof:name":"Douar Layyadene",
    "wof:placetype":"locality"
},
  "geometry": {"coordinates":[-5.43636,35.28872],"type":"Point"}
}