{
  "type": "Feature",
  "properties": {
    "gn:admin1_code":"4.0",
    "gn:asciiname":"Douar Legdadra",
    "gn:country_code":"MA",
    "gn:dem":293,
    "gn:feature_class":"P",
    "gn:feature_code":"PPL",
    "gn:name":"Douar Legdadra",
    "gn:population":0,
    "gn:timezone":"Africa/Casablanca",
    "iso:country":"MA",
    "wof:name":"Douar Legdadra",
    "wof:placetype":"locality"
},
  "geometry": {"coordinates":[-6.83359,33.72366],"type":"Point"}
}