{
  "type": "Feature",
  "properties": {
    "gn:admin1_code":"7.0",
    "gn:asciiname":"Dar Lcaid Said",
    "gn:country_code":"MA",
    "gn:dem":599,
    "gn:feature_class":"P",
    "gn:feature_code":"PPL",
    "gn:name":"Dar Lcaid Said",
    "gn:population":0,
    "gn:timezone":"Africa/Casablanca",
    "iso:country":"MA",
    "wof:name":"Dar Lcaid Said",
    "wof:placetype":"locality"
},
  "geometry": {"coordinates":[-7.71126,31.58712],"type":"Point"}
}