{
  "type": "Feature",
  "properties": {
    "gn:admin1_code":"1.0",
    "gn:asciiname":"Douar Echebharine",
    "gn:country_code":"MA",
    "gn:dem":550,
    "gn:feature_class":"P",
    "gn:feature_code":"PPL",
    "gn:name":"Douar Echebharine",
    "gn:population":0,
    "gn:timezone":"Africa/Casablanca",
    "iso:country":"MA",
    "wof:name":"Douar Echebharine",
    "wof:placetype":"locality"
},
  "geometry": {"coordinates":[-5.1513,35.04317],"type":"Point"}
}