{
  "type": "Feature",
  "properties": {
    "gn:admin1_code":"08",
    "gn:asciiname":"Tafergalt",
    "gn:country_code":"MA",
    "gn:dem":920,
    "gn:feature_class":"P",
    "gn:feature_code":"PPL",
    "gn:name":"Taferg\u00e2lt",
    "gn:population":0,
    "gn:timezone":"Africa/Casablanca",
    "iso:country":"MA",
    "name:und_x_variant":[
        "Tafougalte",
        "Tafergalt",
        "Taferg\u00e2lt"
    ],
    "wof:name":"Tafergalt",
    "wof:placetype":"locality"
},
  "geometry": {"coordinates":[-6.39815,30.68253],"type":"Point"}
}