{
  "type": "Feature",
  "properties": {
    "gn:admin1_code":"7.0",
    "gn:asciiname":"Ait El Haj Ahmed",
    "gn:country_code":"MA",
    "gn:dem":353,
    "gn:feature_class":"P",
    "gn:feature_code":"PPL",
    "gn:name":"Ait El Haj Ahmed",
    "gn:population":0,
    "gn:timezone":"Africa/Casablanca",
    "iso:country":"MA",
    "wof:name":"Ait El Haj Ahmed",
    "wof:placetype":"locality"
},
  "geometry": {"coordinates":[-9.52074,31.50229],"type":"Point"}
}