{
  "type": "Feature",
  "properties": {
    "gn:admin1_code":"9.0",
    "gn:asciiname":"Hassan Ettahiri",
    "gn:country_code":"MA",
    "gn:dem":537,
    "gn:feature_class":"P",
    "gn:feature_code":"PPL",
    "gn:name":"Hassan Ettahiri",
    "gn:population":0,
    "gn:timezone":"Africa/Casablanca",
    "iso:country":"MA",
    "wof:name":"Hassan Ettahiri",
    "wof:placetype":"locality"
},
  "geometry": {"coordinates":[-9.69547,29.50808],"type":"Point"}
}