{
  "type": "Feature",
  "properties": {
    "gn:admin1_code":"01",
    "gn:asciiname":"Taounza",
    "gn:country_code":"MA",
    "gn:dem":819,
    "gn:feature_class":"P",
    "gn:feature_code":"PPL",
    "gn:name":"Taounza",
    "gn:population":0,
    "gn:timezone":"Africa/Casablanca",
    "iso:country":"MA",
    "name:ara_x_preferred":[
        "\u062a\u0627\u0648\u0646\u0632\u0627"
    ],
    "name:cat_x_preferred":[
        "Taounza"
    ],
    "name:ceb_x_preferred":[
        "Taounza"
    ],
    "name:ita_x_preferred":[
        "Taounza"
    ],
    "name:swe_x_preferred":[
        "Taounza"
    ],
    "wof:name":"Taounza",
    "wof:placetype":"locality"
},
  "geometry": {"coordinates":[-4.33,34.75],"type":"Point"}
}