{
  "type": "Feature",
  "properties": {
    "gn:admin1_code":"01",
    "gn:asciiname":"Taounza",
    "gn:country_code":"MA",
    "gn:dem":819,
    "gn:feature_class":"P",
    "gn:feature_code":"PPL",
    "gn:name":"Taounza",
    "gn:population":0,
    "gn:timezone":"Africa/Casablanca",
    "iso:country":"MA",
    "wof:name":"Taounza",
    "wof:placetype":"locality"
},
  "geometry": {"coordinates":[-4.33,34.75],"type":"Point"}
}