{
  "type": "Feature",
  "properties": {
    "gn:admin1_code":"08",
    "gn:asciiname":"Ihmoudan",
    "gn:country_code":"MA",
    "gn:dem":1288,
    "gn:feature_class":"P",
    "gn:feature_code":"PPL",
    "gn:name":"Ihmoudan",
    "gn:population":0,
    "gn:timezone":"Africa/Casablanca",
    "iso:country":"MA",
    "wof:name":"Ihmoudan",
    "wof:placetype":"locality"
},
  "geometry": {"coordinates":[-7.12809,30.44301],"type":"Point"}
}