{
  "type": "Feature",
  "properties": {
    "gn:admin1_code":"03",
    "gn:asciiname":"Douar Ait Mhand Ou Amer",
    "gn:country_code":"MA",
    "gn:dem":782,
    "gn:feature_class":"P",
    "gn:feature_code":"PPL",
    "gn:name":"Douar Ait Mhand Ou Amer",
    "gn:population":0,
    "gn:timezone":"Africa/Casablanca",
    "iso:country":"MA",
    "name:und_x_variant":[
        "Douar A\u00eft Mohannd Ou Amar",
        "A\u00eft Mohannd Ou Amar",
        "A\u00eft Mohand Ou Amar",
        "Douar Ait Mhand Ou Amer"
    ],
    "wof:name":"Douar Ait Mhand Ou Amer",
    "wof:placetype":"locality"
},
  "geometry": {"coordinates":[-4.40271,33.99909],"type":"Point"}
}