{
  "type": "Feature",
  "properties": {
    "gn:admin1_code":"7.0",
    "gn:asciiname":"Rlhar El Haj Eddua",
    "gn:country_code":"MA",
    "gn:dem":442,
    "gn:feature_class":"P",
    "gn:feature_code":"PPL",
    "gn:name":"Rlhar El Haj Eddua",
    "gn:population":0,
    "gn:timezone":"Africa/Casablanca",
    "iso:country":"MA",
    "wof:name":"Rlhar El Haj Eddua",
    "wof:placetype":"locality"
},
  "geometry": {"coordinates":[-8.73644,32.14236],"type":"Point"}
}