{
  "type": "Feature",
  "properties": {
    "gn:admin1_code":"02",
    "gn:asciiname":"Ichnaiene",
    "gn:country_code":"MA",
    "gn:dem":572,
    "gn:feature_class":"P",
    "gn:feature_code":"PPL",
    "gn:name":"Ichna\u00efene",
    "gn:population":0,
    "gn:timezone":"Africa/Casablanca",
    "iso:country":"MA",
    "name:und_x_variant":[
        "Ichnaien",
        "Ichna\u00efene"
    ],
    "wof:name":"Ichnaiene",
    "wof:placetype":"locality"
},
  "geometry": {"coordinates":[-3.65504,35.04922],"type":"Point"}
}