{
  "type": "Feature",
  "properties": {
    "gn:admin1_code":"03",
    "gn:asciiname":"Oulad Hassoun",
    "gn:country_code":"MA",
    "gn:dem":539,
    "gn:feature_class":"P",
    "gn:feature_code":"PPL",
    "gn:name":"Oulad Hassoun",
    "gn:population":0,
    "gn:timezone":"Africa/Casablanca",
    "iso:country":"MA",
    "wof:name":"Oulad Hassoun",
    "wof:placetype":"locality"
},
  "geometry": {"coordinates":[-5.043,33.94006],"type":"Point"}
}