{
  "type": "Feature",
  "properties": {
    "gn:admin1_code":"10.0",
    "gn:asciiname":"Id Chabour",
    "gn:country_code":"MA",
    "gn:dem":639,
    "gn:feature_class":"P",
    "gn:feature_code":"PPL",
    "gn:name":"Id Chabour",
    "gn:population":0,
    "gn:timezone":"Africa/Casablanca",
    "iso:country":"MA",
    "wof:name":"Id Chabour",
    "wof:placetype":"locality"
},
  "geometry": {"coordinates":[-9.92743,29.28427000000001],"type":"Point"}
}