{
  "type": "Feature",
  "properties": {
    "gn:admin1_code":"05",
    "gn:asciiname":"Talehnat",
    "gn:country_code":"MA",
    "gn:dem":1280,
    "gn:feature_class":"P",
    "gn:feature_code":"PPL",
    "gn:name":"Talehnat",
    "gn:population":0,
    "gn:timezone":"Africa/Casablanca",
    "iso:country":"MA",
    "wof:name":"Talehnat",
    "wof:placetype":"locality"
},
  "geometry": {"coordinates":[-5.47849,32.86829],"type":"Point"}
}