{
  "type": "Feature",
  "properties": {
    "gn:admin1_code":"2.0",
    "gn:asciiname":"Dar Ezzaki",
    "gn:country_code":"MA",
    "gn:dem":88,
    "gn:feature_class":"P",
    "gn:feature_code":"PPL",
    "gn:name":"Dar Ezzaki",
    "gn:population":0,
    "gn:timezone":"Africa/Casablanca",
    "iso:country":"MA",
    "wof:name":"Dar Ezzaki",
    "wof:placetype":"locality"
},
  "geometry": {"coordinates":[-2.34473,34.98489],"type":"Point"}
}