{
  "type": "Feature",
  "properties": {
    "gn:admin1_code":"10",
    "gn:asciiname":"Bizmaouene",
    "gn:country_code":"MA",
    "gn:dem":386,
    "gn:feature_class":"P",
    "gn:feature_code":"PPL",
    "gn:name":"Bizmaouene",
    "gn:population":0,
    "gn:timezone":"Africa/Casablanca",
    "iso:country":"MA",
    "name:und_x_variant":[
        "Bizmaun",
        "Bismaoun",
        "Bizmawane",
        "Bizmaouene"
    ],
    "wof:name":"Bizmaouene",
    "wof:placetype":"locality"
},
  "geometry": {"coordinates":[-10.17526,29.13753],"type":"Point"}
}