{
  "type": "Feature",
  "properties": {
    "gn:admin1_code":"09",
    "gn:asciiname":"Imidar-n-Imargar",
    "gn:country_code":"MA",
    "gn:dem":842,
    "gn:feature_class":"P",
    "gn:feature_code":"PPL",
    "gn:name":"Imidar-n-Imargar",
    "gn:population":0,
    "gn:timezone":"Africa/Casablanca",
    "iso:country":"MA",
    "name:und_x_variant":[
        "Imoujjerne",
        "Dar Imoujir",
        "Imidar-n-Imargar"
    ],
    "wof:name":"Imidar-n-Imargar",
    "wof:placetype":"locality"
},
  "geometry": {"coordinates":[-8.04862,30.6717],"type":"Point"}
}