{
  "type": "Feature",
  "properties": {
    "gn:admin1_code":"7.0",
    "gn:asciiname":"Dyour El Houssine Ben Azzouz",
    "gn:country_code":"MA",
    "gn:dem":381,
    "gn:feature_class":"P",
    "gn:feature_code":"PPL",
    "gn:name":"Dyour El Houssine Ben Azzouz",
    "gn:population":0,
    "gn:timezone":"Africa/Casablanca",
    "iso:country":"MA",
    "wof:name":"Dyour El Houssine Ben Azzouz",
    "wof:placetype":"locality"
},
  "geometry": {"coordinates":[-9.07227,31.59636],"type":"Point"}
}