{
  "type": "Feature",
  "properties": {
    "gn:admin1_code":"9.0",
    "gn:asciiname":"Tou Languer",
    "gn:country_code":"MA",
    "gn:dem":139,
    "gn:feature_class":"P",
    "gn:feature_code":"PPL",
    "gn:name":"Tou Languer",
    "gn:population":0,
    "gn:timezone":"Africa/Casablanca",
    "iso:country":"MA",
    "wof:name":"Tou Languer",
    "wof:placetype":"locality"
},
  "geometry": {"coordinates":[-9.37418,30.11282000000001],"type":"Point"}
}