{
  "type": "Feature",
  "properties": {
    "gn:admin1_code":"7.0",
    "gn:asciiname":"Douar Hrarcha",
    "gn:country_code":"MA",
    "gn:dem":142,
    "gn:feature_class":"P",
    "gn:feature_code":"PPL",
    "gn:name":"Douar Hrarcha",
    "gn:population":0,
    "gn:timezone":"Africa/Casablanca",
    "iso:country":"MA",
    "wof:name":"Douar Hrarcha",
    "wof:placetype":"locality"
},
  "geometry": {"coordinates":[-9.22727,32.05203],"type":"Point"}
}