{
  "type": "Feature",
  "properties": {
    "gn:admin1_code":"05",
    "gn:asciiname":"Chorfa Igouzoulne",
    "gn:country_code":"MA",
    "gn:dem":948,
    "gn:feature_class":"P",
    "gn:feature_code":"PPL",
    "gn:name":"Chorfa Igouzoulne",
    "gn:population":0,
    "gn:timezone":"Africa/Casablanca",
    "iso:country":"MA",
    "name:und_x_variant":[
        "Chorfa n\u2019Igousaoune",
        "Cherfa n\u2019Igousaoune",
        "Chorfa Igouzoulne"
    ],
    "wof:name":"Chorfa Igouzoulne",
    "wof:placetype":"locality"
},
  "geometry": {"coordinates":[-7.15694,31.70406],"type":"Point"}
}