{
  "type": "Feature",
  "properties": {
    "gn:admin1_code":"06",
    "gn:asciiname":"Et Touajna",
    "gn:country_code":"MA",
    "gn:dem":156,
    "gn:feature_class":"P",
    "gn:feature_code":"PPL",
    "gn:name":"Et Touajna",
    "gn:population":0,
    "gn:timezone":"Africa/Casablanca",
    "iso:country":"MA",
    "name:und_x_variant":[
        "Touajna",
        "Douar et Touajna",
        "Et Touajna"
    ],
    "wof:name":"Et Touajna",
    "wof:placetype":"locality"
},
  "geometry": {"coordinates":[-8.7015,32.65674],"type":"Point"}
}