{
  "type": "Feature",
  "properties": {
    "gn:admin1_code":"01",
    "gn:asciiname":"Douar Qbira",
    "gn:country_code":"MA",
    "gn:dem":589,
    "gn:feature_class":"P",
    "gn:feature_code":"PPL",
    "gn:name":"Douar Qbira",
    "gn:population":0,
    "gn:timezone":"Africa/Casablanca",
    "iso:country":"MA",
    "name:und_x_variant":[
        "Ikbira"
    ],
    "wof:name":"Douar Qbira",
    "wof:placetype":"locality"
},
  "geometry": {"coordinates":[-5.4929,35.17696],"type":"Point"}
}