{
  "type": "Feature",
  "properties": {
    "gn:admin1_code":"07",
    "gn:asciiname":"Fkarine",
    "gn:country_code":"MA",
    "gn:dem":684,
    "gn:feature_class":"P",
    "gn:feature_code":"PPL",
    "gn:name":"Fkarine",
    "gn:population":0,
    "gn:timezone":"Africa/Casablanca",
    "iso:country":"MA",
    "name:und_x_variant":[
        "Elfkarine",
        "Fekarine",
        "Fakarine",
        "Fkarine"
    ],
    "wof:name":"Fkarine",
    "wof:placetype":"locality"
},
  "geometry": {"coordinates":[-7.41159,31.68167],"type":"Point"}
}