{
  "type": "Feature",
  "properties": {
    "gn:admin1_code":"06",
    "gn:admin2_code":"111.0",
    "gn:admin3_code":"611103072.0",
    "gn:asciiname":"Mellila",
    "gn:country_code":"MA",
    "gn:dem":326,
    "gn:feature_class":"P",
    "gn:feature_code":"PPLA3",
    "gn:name":"Mellila",
    "gn:population":0,
    "gn:timezone":"Africa/Casablanca",
    "iso:country":"MA",
    "wof:name":"Mellila",
    "wof:placetype":"locality"
},
  "geometry": {"coordinates":[-7.14,33.38],"type":"Point"}
}