{
  "type": "Feature",
  "properties": {
    "gn:admin1_code":"7.0",
    "gn:asciiname":"Zawt",
    "gn:country_code":"MA",
    "gn:dem":2034,
    "gn:feature_class":"P",
    "gn:feature_code":"PPL",
    "gn:name":"Zawt",
    "gn:population":0,
    "gn:timezone":"Africa/Casablanca",
    "iso:country":"MA",
    "wof:name":"Zawt",
    "wof:placetype":"locality"
},
  "geometry": {"coordinates":[-7.9409,30.97572000000001],"type":"Point"}
}