{
  "type": "Feature",
  "properties": {
    "gn:admin1_code":"06",
    "gn:asciiname":"Dar Tibari",
    "gn:country_code":"MA",
    "gn:dem":37,
    "gn:feature_class":"P",
    "gn:feature_code":"PPL",
    "gn:name":"Dar Tibari",
    "gn:population":0,
    "gn:timezone":"Africa/Casablanca",
    "iso:country":"MA",
    "name:und_x_variant":[
        "Ouled Tibari",
        "Douar Tibari",
        "Dar Tibari"
    ],
    "wof:name":"Dar Tibari",
    "wof:placetype":"locality"
},
  "geometry": {"coordinates":[-8.50858,33.13012],"type":"Point"}
}