{
  "type": "Feature",
  "properties": {
    "gn:admin1_code":"07",
    "gn:asciiname":"Tassena",
    "gn:country_code":"MA",
    "gn:dem":857,
    "gn:feature_class":"P",
    "gn:feature_code":"PPL",
    "gn:name":"Tassena",
    "gn:population":0,
    "gn:timezone":"Africa/Casablanca",
    "iso:country":"MA",
    "name:und_x_variant":[
        "Douar Tassena",
        "Tassena"
    ],
    "wof:name":"Tassena",
    "wof:placetype":"locality"
},
  "geometry": {"coordinates":[-8.25128,31.28533],"type":"Point"}
}