{
  "type": "Feature",
  "properties": {
    "gn:admin1_code":"1.0",
    "gn:asciiname":"Douar Assaidene",
    "gn:country_code":"MA",
    "gn:dem":604,
    "gn:feature_class":"P",
    "gn:feature_code":"PPL",
    "gn:name":"Douar Assaidene",
    "gn:population":0,
    "gn:timezone":"Africa/Casablanca",
    "iso:country":"MA",
    "wof:name":"Douar Assaidene",
    "wof:placetype":"locality"
},
  "geometry": {"coordinates":[-5.42078,35.32339],"type":"Point"}
}