{
  "type": "Feature",
  "properties": {
    "gn:admin1_code":"7.0",
    "gn:asciiname":"Ayt Al Houssayne",
    "gn:country_code":"MA",
    "gn:dem":743,
    "gn:feature_class":"P",
    "gn:feature_code":"PPL",
    "gn:name":"Ayt Al Houssayne",
    "gn:population":0,
    "gn:timezone":"Africa/Casablanca",
    "iso:country":"MA",
    "wof:name":"Ayt Al Houssayne",
    "wof:placetype":"locality"
},
  "geometry": {"coordinates":[-7.77595,31.43668],"type":"Point"}
}