{
  "type": "Feature",
  "properties": {
    "gn:admin1_code":"01",
    "gn:asciiname":"Lahdadoua",
    "gn:country_code":"MA",
    "gn:dem":480,
    "gn:feature_class":"P",
    "gn:feature_code":"PPL",
    "gn:name":"Lahdadoua",
    "gn:population":0,
    "gn:timezone":"Africa/Casablanca",
    "iso:country":"MA",
    "name:und_x_variant":[
        "El Haina"
    ],
    "wof:name":"Lahdadoua",
    "wof:placetype":"locality"
},
  "geometry": {"coordinates":[-5.49457,35.47865],"type":"Point"}
}