{
  "type": "Feature",
  "properties": {
    "gn:admin1_code":"03",
    "gn:asciiname":"Douar Ennehirat",
    "gn:country_code":"MA",
    "gn:dem":712,
    "gn:feature_class":"P",
    "gn:feature_code":"PPL",
    "gn:name":"Douar Ennehirat",
    "gn:population":0,
    "gn:timezone":"Africa/Casablanca",
    "iso:country":"MA",
    "name:und_x_variant":[
        "Douar A\u00efn Nhereth",
        "A\u00efn Nhereth",
        "Douar Ennehirat"
    ],
    "wof:name":"Douar Ennehirat",
    "wof:placetype":"locality"
},
  "geometry": {"coordinates":[-4.25779,34.27642],"type":"Point"}
}