{
  "type": "Feature",
  "properties": {
    "gn:admin1_code":"6.0",
    "gn:asciiname":"Ouad Lhahriya",
    "gn:country_code":"MA",
    "gn:dem":300,
    "gn:feature_class":"P",
    "gn:feature_code":"PPL",
    "gn:name":"Ouad Lhahriya",
    "gn:population":0,
    "gn:timezone":"Africa/Casablanca",
    "iso:country":"MA",
    "wof:name":"Ouad Lhahriya",
    "wof:placetype":"locality"
},
  "geometry": {"coordinates":[-7.09312,33.35918],"type":"Point"}
}