{
  "type": "Feature",
  "properties": {
    "gn:admin1_code":"2.0",
    "gn:asciiname":"Zaouia",
    "gn:country_code":"MA",
    "gn:dem":404,
    "gn:feature_class":"P",
    "gn:feature_code":"PPL",
    "gn:name":"Zaouia",
    "gn:population":0,
    "gn:timezone":"Africa/Casablanca",
    "iso:country":"MA",
    "wof:name":"Zaouia",
    "wof:placetype":"locality"
},
  "geometry": {"coordinates":[-2.35592,34.84433],"type":"Point"}
}