{
  "type": "Feature",
  "properties": {
    "gn:admin1_code":"6.0",
    "gn:asciiname":"El 'Aberrat",
    "gn:country_code":"MA",
    "gn:dem":445,
    "gn:feature_class":"P",
    "gn:feature_code":"PPL",
    "gn:name":"El \u2019Aberrat",
    "gn:population":0,
    "gn:timezone":"Africa/Casablanca",
    "iso:country":"MA",
    "wof:name":"El 'Aberrat",
    "wof:placetype":"locality"
},
  "geometry": {"coordinates":[-7.66401,32.81248],"type":"Point"}
}