{
  "type": "Feature",
  "properties": {
    "gn:admin1_code":"5.0",
    "gn:asciiname":"Ighran-n-taghbalout",
    "gn:country_code":"MA",
    "gn:dem":1308,
    "gn:feature_class":"P",
    "gn:feature_code":"PPL",
    "gn:name":"Ighran-n-taghbalout",
    "gn:population":0,
    "gn:timezone":"Africa/Casablanca",
    "iso:country":"MA",
    "wof:name":"Ighran-n-taghbalout",
    "wof:placetype":"locality"
},
  "geometry": {"coordinates":[-7.0503,31.67988],"type":"Point"}
}