{
  "type": "Feature",
  "properties": {
    "gn:admin1_code":"02",
    "gn:asciiname":"Azar",
    "gn:country_code":"MA",
    "gn:dem":1307,
    "gn:feature_class":"P",
    "gn:feature_code":"PPL",
    "gn:name":"Azar",
    "gn:population":0,
    "gn:timezone":"Africa/Casablanca",
    "iso:country":"MA",
    "name:ara_x_preferred":[
        "\u0642\u0648\u0633"
    ],
    "name:azb_x_preferred":[
        "\u0622\u0630\u0631"
    ],
    "name:aze_x_preferred":[
        "Az\u0259r"
    ],
    "name:bul_x_preferred":[
        "\u0410\u0437\u0430\u0440"
    ],
    "name:ckb_x_preferred":[
        "\u0633\u06d5\u0631\u0645\u0627\u0648\u06d5\u0632"
    ],
    "name:fas_x_preferred":[
        "\u0622\u0630\u0631"
    ],
    "name:glk_x_preferred":[
        "\u0622\u0630\u0631"
    ],
    "name:hun_x_preferred":[
        "\u00c1zar"
    ],
    "name:mzn_x_preferred":[
        "\u0622\u0630\u0631"
    ],
    "name:pus_x_preferred":[
        "\u0644\u064a\u0646\u062f\u06cd"
    ],
    "name:rus_x_preferred":[
        "\u0410\u0437\u0430\u0440"
    ],
    "name:snd_x_preferred":[
        "\u0622\u0632\u0631"
    ],
    "name:spa_x_preferred":[
        "Azar"
    ],
    "name:tat_x_preferred":[
        "\u041a\u0430\u0432\u04d9\u0441"
    ],
    "name:tgk_x_preferred":[
        "\u041e\u0437\u0430\u0440"
    ],
    "name:und_x_variant":[
        "Ksar Azer",
        "Azzar"
    ],
    "wof:name":"Azar",
    "wof:placetype":"locality"
},
  "geometry": {"coordinates":[-3.74139,32.39922],"type":"Point"}
}