{
  "type": "Feature",
  "properties": {
    "gn:admin1_code":"02",
    "gn:asciiname":"Azar",
    "gn:country_code":"MA",
    "gn:dem":1307,
    "gn:feature_class":"P",
    "gn:feature_code":"PPL",
    "gn:name":"Azar",
    "gn:population":0,
    "gn:timezone":"Africa/Casablanca",
    "iso:country":"MA",
    "name:und_x_variant":[
        "Ksar Azer",
        "Azzar",
        "Azar"
    ],
    "wof:name":"Azar",
    "wof:placetype":"locality"
},
  "geometry": {"coordinates":[-3.74139,32.39922],"type":"Point"}
}