{
  "type": "Feature",
  "properties": {
    "gn:admin1_code":"07",
    "gn:asciiname":"Douar Chaala Lfoqia",
    "gn:country_code":"MA",
    "gn:dem":136,
    "gn:feature_class":"P",
    "gn:feature_code":"PPL",
    "gn:name":"Douar Chaala Lfoqia",
    "gn:population":0,
    "gn:timezone":"Africa/Casablanca",
    "iso:country":"MA",
    "name:und_x_variant":[
        "Cha\u00e2la",
        "Chaalla",
        "Douar Chaala Lfoqia"
    ],
    "wof:name":"Douar Chaala Lfoqia",
    "wof:placetype":"locality"
},
  "geometry": {"coordinates":[-8.96408,32.4827],"type":"Point"}
}