{
  "type": "Feature",
  "properties": {
    "gn:admin1_code":"4.0",
    "gn:asciiname":"Klabibiyal",
    "gn:country_code":"MA",
    "gn:dem":13,
    "gn:feature_class":"P",
    "gn:feature_code":"PPL",
    "gn:name":"Klabibiyal",
    "gn:population":0,
    "gn:timezone":"Africa/Casablanca",
    "iso:country":"MA",
    "wof:name":"Klabibiyal",
    "wof:placetype":"locality"
},
  "geometry": {"coordinates":[-6.4649,34.46019],"type":"Point"}
}