{
  "type": "Feature",
  "properties": {
    "gn:admin1_code":"08",
    "gn:asciiname":"Imdghar n'Izder",
    "gn:country_code":"MA",
    "gn:dem":1504,
    "gn:feature_class":"P",
    "gn:feature_code":"PPL",
    "gn:name":"Imdghar n\u2019Izder",
    "gn:population":0,
    "gn:timezone":"Africa/Casablanca",
    "iso:country":"MA",
    "name:und_x_variant":[
        "Imdrer n\u2019Izder",
        "Imdghar n\u2019Izder"
    ],
    "wof:name":"Imdghar n'Izder",
    "wof:placetype":"locality"
},
  "geometry": {"coordinates":[-7.33138,30.61408],"type":"Point"}
}