{
  "type": "Feature",
  "properties": {
    "gn:admin1_code":"9.0",
    "gn:asciiname":"Ighiyl Iwrzadn",
    "gn:country_code":"MA",
    "gn:dem":989,
    "gn:feature_class":"P",
    "gn:feature_code":"PPL",
    "gn:name":"Ighiyl Iwrzadn",
    "gn:population":0,
    "gn:timezone":"Africa/Casablanca",
    "iso:country":"MA",
    "wof:name":"Ighiyl Iwrzadn",
    "wof:placetype":"locality"
},
  "geometry": {"coordinates":[-9.22289,29.67843],"type":"Point"}
}