{
  "type": "Feature",
  "properties": {
    "gn:admin1_code":"01",
    "gn:asciiname":"Douar Ait Fares",
    "gn:country_code":"MA",
    "gn:dem":159,
    "gn:feature_class":"P",
    "gn:feature_code":"PPL",
    "gn:name":"Douar Ait Fares",
    "gn:population":0,
    "gn:timezone":"Africa/Casablanca",
    "iso:country":"MA",
    "name:und_x_variant":[
        "A\u00eft Farts"
    ],
    "wof:name":"Douar Ait Fares",
    "wof:placetype":"locality"
},
  "geometry": {"coordinates":[-3.85292,35.09251],"type":"Point"}
}