{
  "type": "Feature",
  "properties": {
    "gn:admin1_code":"9.0",
    "gn:asciiname":"Anammr",
    "gn:country_code":"MA",
    "gn:dem":747,
    "gn:feature_class":"P",
    "gn:feature_code":"PPL",
    "gn:name":"Anammr",
    "gn:population":0,
    "gn:timezone":"Africa/Casablanca",
    "iso:country":"MA",
    "wof:name":"Anammr",
    "wof:placetype":"locality"
},
  "geometry": {"coordinates":[-9.30208,29.61882],"type":"Point"}
}