{
  "type": "Feature",
  "properties": {
    "gn:admin1_code":"09",
    "gn:asciiname":"Ighir-n-Ait Bazziy",
    "gn:country_code":"MA",
    "gn:dem":1240,
    "gn:feature_class":"P",
    "gn:feature_code":"PPL",
    "gn:name":"Ighir-n-A\u00eft Bazziy",
    "gn:population":0,
    "gn:timezone":"Africa/Casablanca",
    "iso:country":"MA",
    "name:und_x_variant":[
        "Ighir-n-A\u00eft Bazziy",
        "Irhir n\u2019A\u00eft el Bazi"
    ],
    "wof:name":"Ighir-n-Ait Bazziy",
    "wof:placetype":"locality"
},
  "geometry": {"coordinates":[-8.31582,30.04048],"type":"Point"}
}