{
  "type": "Feature",
  "properties": {
    "gn:admin1_code":"03",
    "gn:asciiname":"Ait Aboukais",
    "gn:country_code":"MA",
    "gn:dem":1414,
    "gn:feature_class":"P",
    "gn:feature_code":"PPL",
    "gn:name":"A\u00eft Abouka\u00efs",
    "gn:population":0,
    "gn:timezone":"Africa/Casablanca",
    "iso:country":"MA",
    "wof:name":"Ait Aboukais",
    "wof:placetype":"locality"
},
  "geometry": {"coordinates":[-3.99364,33.77269],"type":"Point"}
}