{
  "type": "Feature",
  "properties": {
    "gn:admin1_code":"55",
    "gn:asciiname":"Isdras",
    "gn:cc2":"MA",
    "gn:country_code":"MA",
    "gn:dem":1760,
    "gn:feature_class":"P",
    "gn:feature_code":"PPL",
    "gn:name":"Isdras",
    "gn:population":0,
    "gn:timezone":"Africa/Casablanca",
    "iso:country":"MA",
    "name:und_x_variant":[
        "Isserdas",
        "Isdras"
    ],
    "wof:name":"Isdras",
    "wof:placetype":"locality"
},
  "geometry": {"coordinates":[-8.58,30.06],"type":"Point"}
}