{
  "type": "Feature",
  "properties": {
    "gn:admin1_code":"6.0",
    "gn:asciiname":"La'badla",
    "gn:country_code":"MA",
    "gn:dem":489,
    "gn:feature_class":"P",
    "gn:feature_code":"PPL",
    "gn:name":"La\u2019badla",
    "gn:population":0,
    "gn:timezone":"Africa/Casablanca",
    "iso:country":"MA",
    "wof:name":"La'badla",
    "wof:placetype":"locality"
},
  "geometry": {"coordinates":[-7.08282,32.59546],"type":"Point"}
}