{
  "type": "Feature",
  "properties": {
    "gn:country":"MA",
    "gn:fcode":"ADM3",
    "gn:population":1273,
    "iso:country":"MA",
    "name:ara_x_preferred":[
        "\u0627\u0644\u062f\u0627\u062e\u0644\u0629 (\u0627\u0644\u0628\u0644\u062f\u064a\u0629)"
    ],
    "name:ara_x_variant":[
        "\u0628\u0626\u0631 \u0625\u0646\u0632\u0631\u0627\u0646"
    ],
    "name:cat_x_preferred":[
        "Bir Anzarane"
    ],
    "name:ceb_x_preferred":[
        "Bir Anzarane"
    ],
    "name:fra_x_preferred":[
        "Bir Anzarane"
    ],
    "name:fra_x_variant":[
        "Bir Anzarane (CR)",
        "Bir Anzarane (Commune Rurale)"
    ],
    "name:ita_x_preferred":[
        "Bir Anzarane"
    ],
    "name:swe_x_preferred":[
        "Bir Anzarane"
    ],
    "qs_pg:aaroncc":"MA",
    "qs_pg:gn_country":"MA",
    "qs_pg:gn_fcode":"ADM3",
    "qs_pg:gn_pop":1273,
    "qs_pg:name":"Bir Anzarane",
    "qs_pg:photos_9r":0,
    "qs_pg:photos_sr":0,
    "qs_pg:pop_sr":3,
    "qs_pg:qs_pg_placetype":"localadmin",
    "wof:name":"Bir Anzarane",
    "wof:placetype":"localadmin",
    "wof:population":1273
},
  "geometry": {"coordinates":[-14.66318,24.046],"type":"Point"}
}