{
  "type": "Feature",
  "properties": {
    "gn:country":"MA",
    "gn:fcode":"ADM3",
    "gn:population":1273,
    "iso:country":"MA",
    "name:ara_x_preferred":[
        "\u0627\u0644\u062f\u0627\u062e\u0644\u0629 (\u0627\u0644\u0628\u0644\u062f\u064a\u0629)"
    ],
    "name:ara_x_variant":[
        "\u0628\u0626\u0631 \u0625\u0646\u0632\u0631\u0627\u0646"
    ],
    "name:ben_x_preferred":[
        "\u09ac\u09bf\u09b0 \u0986\u099e\u09cd\u099c\u09be\u09b0\u09be\u09a8\u09c7"
    ],
    "name:cat_x_preferred":[
        "Bir Anzarane"
    ],
    "name:ceb_x_preferred":[
        "Bir Anzarane"
    ],
    "name:deu_x_preferred":[
        "Bir Anzarane"
    ],
    "name:ell_x_preferred":[
        "\u039c\u03c0\u03b9\u03c1 \u0391\u03bd\u03b6\u03b1\u03c1\u03ac\u03bd\u03b5"
    ],
    "name:fas_x_preferred":[
        "\u0628\u06cc\u0631 \u0627\u0646\u0632\u0627\u0631\u0627\u0646"
    ],
    "name:fra_x_preferred":[
        "Bir Anzarane"
    ],
    "name:fra_x_variant":[
        "Bir Anzarane (CR)",
        "Bir Anzarane (Commune Rurale)"
    ],
    "name:heb_x_preferred":[
        "\u05d1\u05d9\u05e8 \u05d0\u05e0\u05d6\u05e8\u05e0\u05d4"
    ],
    "name:hin_x_preferred":[
        "\u092c\u0940\u0930 \u0905\u0902\u091c\u093e\u0930\u093e\u0928\u0947"
    ],
    "name:hun_x_preferred":[
        "Bir Anzarane"
    ],
    "name:ind_x_preferred":[
        "Bir Anzarane"
    ],
    "name:ita_x_preferred":[
        "Bir Anzarane"
    ],
    "name:jpn_x_preferred":[
        "\u30d3\u30eb\u30fb\u30a2\u30f3\u30b6\u30e9\u30fc\u30f3"
    ],
    "name:kor_x_preferred":[
        "\ube44\ub974 \uc548\uc790\ub780"
    ],
    "name:nld_x_preferred":[
        "Bir Anzarane"
    ],
    "name:por_x_preferred":[
        "Bir Anzarane"
    ],
    "name:rus_x_preferred":[
        "\u0411\u0438\u0440-\u0410\u043d\u0437\u0430\u0440\u0430\u043d"
    ],
    "name:swe_x_preferred":[
        "Bir Anzarane"
    ],
    "name:tur_x_preferred":[
        "Bir Anzarane"
    ],
    "name:ukr_x_preferred":[
        "\u0411\u0456\u0440-\u0410\u043d\u0437\u0430\u0440\u0430\u043d\u0435"
    ],
    "name:urd_x_preferred":[
        "\u0628\u06cc\u0631 \u0627\u06cc\u0646\u0632\u0627\u0631\u0627\u0646\u06d2"
    ],
    "name:vie_x_preferred":[
        "Bir Anzarane"
    ],
    "qs_pg:aaroncc":"MA",
    "qs_pg:gn_country":"MA",
    "qs_pg:gn_fcode":"ADM3",
    "qs_pg:gn_pop":1273,
    "qs_pg:name":"Bir Anzarane",
    "qs_pg:photos_9r":0,
    "qs_pg:photos_sr":0,
    "qs_pg:pop_sr":3,
    "qs_pg:qs_pg_placetype":"localadmin",
    "wof:name":"Bir Anzarane",
    "wof:placetype":"localadmin",
    "wof:population":1273
},
  "geometry": {"coordinates":[-14.66318,24.046],"type":"Point"}
}