{
  "type": "Feature",
  "properties": {
    "gn:admin1_code":"6.0",
    "gn:asciiname":"Douar Oudad El Mokhtar",
    "gn:country_code":"MA",
    "gn:dem":478,
    "gn:feature_class":"P",
    "gn:feature_code":"PPL",
    "gn:name":"Douar Oudad El Mokhtar",
    "gn:population":0,
    "gn:timezone":"Africa/Casablanca",
    "iso:country":"MA",
    "wof:name":"Douar Oudad El Mokhtar",
    "wof:placetype":"locality"
},
  "geometry": {"coordinates":[-7.21429,33.17890999999999],"type":"Point"}
}