{
  "type": "Feature",
  "properties": {
    "gn:country":"MA",
    "gn:fcode":"ADM3",
    "gn:population":10406,
    "iso:country":"MA",
    "name:ara_x_preferred":[
        "\u0628\u0646\u064a \u0623\u062d\u0645\u062f \u0627\u0644\u0634\u0631\u0642\u064a\u0629"
    ],
    "name:fra_x_preferred":[
        "Maghraoua"
    ],
    "name:fra_x_variant":[
        "Maghraoua (CR)",
        "Maghraoua (Commune Rurale)"
    ],
    "qs_pg:aaroncc":"MA",
    "qs_pg:gn_country":"MA",
    "qs_pg:gn_fcode":"ADM3",
    "qs_pg:gn_pop":10406,
    "qs_pg:name":"Maghraoua",
    "qs_pg:photos_9r":0,
    "qs_pg:photos_sr":0,
    "qs_pg:pop_sr":6,
    "qs_pg:qs_pg_placetype":"localadmin",
    "wof:name":"Maghraoua",
    "wof:placetype":"localadmin",
    "wof:population":8204
},
  "geometry": {"coordinates":[-4.00947,33.94403],"type":"Point"}
}