{
  "type": "Feature",
  "properties": {
    "gn:admin1_code":"03",
    "gn:asciiname":"Douar Agrane",
    "gn:country_code":"MA",
    "gn:dem":1202,
    "gn:feature_class":"P",
    "gn:feature_code":"PPL",
    "gn:name":"Douar Agrane",
    "gn:population":0,
    "gn:timezone":"Africa/Casablanca",
    "iso:country":"MA",
    "name:und_x_variant":[
        "Agroun",
        "Agrane",
        "Douar Agrane"
    ],
    "wof:name":"Douar Agrane",
    "wof:placetype":"locality"
},
  "geometry": {"coordinates":[-4.15083,34.01143],"type":"Point"}
}