{
  "type": "Feature",
  "properties": {
    "gn:admin1_code":"06",
    "gn:asciiname":"Douar Olad. Rbia",
    "gn:country_code":"MA",
    "gn:dem":109,
    "gn:feature_class":"P",
    "gn:feature_code":"PPL",
    "gn:name":"Douar Olad. Rbia",
    "gn:population":0,
    "gn:timezone":"Africa/Casablanca",
    "iso:country":"MA",
    "name:und_x_variant":[
        "Douar Oulad Rbia"
    ],
    "wof:name":"Douar Olad. Rbia",
    "wof:placetype":"locality"
},
  "geometry": {"coordinates":[-8.93446,32.79548],"type":"Point"}
}