{
  "type": "Feature",
  "properties": {
    "gn:admin1_code":"9.0",
    "gn:asciiname":"Ait Houmane",
    "gn:country_code":"MA",
    "gn:dem":175,
    "gn:feature_class":"P",
    "gn:feature_code":"PPL",
    "gn:name":"A\u00eft Houmane",
    "gn:population":0,
    "gn:timezone":"Africa/Casablanca",
    "iso:country":"MA",
    "wof:name":"Ait Houmane",
    "wof:placetype":"locality"
},
  "geometry": {"coordinates":[-9.23861,30.27549],"type":"Point"}
}