{
  "type": "Feature",
  "properties": {
    "gn:admin1_code":"10.0",
    "gn:asciiname":"Id La'sri",
    "gn:country_code":"MA",
    "gn:dem":1004,
    "gn:feature_class":"P",
    "gn:feature_code":"PPL",
    "gn:name":"Id La\u2019sri",
    "gn:population":0,
    "gn:timezone":"Africa/Casablanca",
    "iso:country":"MA",
    "wof:name":"Id La'sri",
    "wof:placetype":"locality"
},
  "geometry": {"coordinates":[-9.75554,29.2235],"type":"Point"}
}