{
  "type": "Feature",
  "properties": {
    "gn:admin1_code":"01",
    "gn:asciiname":"Iketdreoun",
    "gn:country_code":"MA",
    "gn:dem":201,
    "gn:feature_class":"P",
    "gn:feature_code":"PPL",
    "gn:name":"Iketdreoun",
    "gn:population":0,
    "gn:timezone":"Africa/Casablanca",
    "iso:country":"MA",
    "name:und_x_variant":[
        "Iketdreun",
        "Iketdreoun"
    ],
    "wof:name":"Iketdreoun",
    "wof:placetype":"locality"
},
  "geometry": {"coordinates":[-3.91786,35.17347],"type":"Point"}
}