{
  "type": "Feature",
  "properties": {
    "gn:admin1_code":"09",
    "gn:asciiname":"Takoucht",
    "gn:country_code":"MA",
    "gn:dem":1163,
    "gn:feature_class":"P",
    "gn:feature_code":"PPL",
    "gn:name":"Takoucht",
    "gn:population":0,
    "gn:timezone":"Africa/Casablanca",
    "iso:country":"MA",
    "name:ara_x_preferred":[
        "\u062a\u0627\u0643\u0648\u0634\u062a"
    ],
    "name:cat_x_preferred":[
        "Takoucht"
    ],
    "name:ita_x_preferred":[
        "Takoucht"
    ],
    "wof:name":"Takoucht",
    "wof:placetype":"locality"
},
  "geometry": {"coordinates":[-9.11004,29.95719],"type":"Point"}
}