{
  "type": "Feature",
  "properties": {
    "gn:admin1_code":"09",
    "gn:asciiname":"Aguerd-n-Tassoukt",
    "gn:country_code":"MA",
    "gn:dem":1419,
    "gn:feature_class":"P",
    "gn:feature_code":"PPL",
    "gn:name":"Aguerd-n-Tassoukt",
    "gn:population":0,
    "gn:timezone":"Africa/Casablanca",
    "iso:country":"MA",
    "name:und_x_variant":[
        "Aguerd",
        "Aguerd n\u2019 Tsoukt",
        "Aguerd-n-Tassoukt"
    ],
    "wof:name":"Aguerd-n-Tassoukt",
    "wof:placetype":"locality"
},
  "geometry": {"coordinates":[-8.59545,30.81433],"type":"Point"}
}