{
  "type": "Feature",
  "properties": {
    "gn:admin1_code":"6.0",
    "gn:asciiname":"Douar Cha'ba",
    "gn:country_code":"MA",
    "gn:dem":303,
    "gn:feature_class":"P",
    "gn:feature_code":"PPL",
    "gn:name":"Douar Cha\u2019ba",
    "gn:population":0,
    "gn:timezone":"Africa/Casablanca",
    "iso:country":"MA",
    "wof:name":"Douar Cha'ba",
    "wof:placetype":"locality"
},
  "geometry": {"coordinates":[-8.20775,32.48686],"type":"Point"}
}