{
  "type": "Feature",
  "properties": {
    "gn:admin1_code":"7.0",
    "gn:asciiname":"Iderrazene",
    "gn:country_code":"MA",
    "gn:dem":132,
    "gn:feature_class":"P",
    "gn:feature_code":"PPL",
    "gn:name":"Iderrazene",
    "gn:population":0,
    "gn:timezone":"Africa/Casablanca",
    "iso:country":"MA",
    "wof:name":"Iderrazene",
    "wof:placetype":"locality"
},
  "geometry": {"coordinates":[-9.69767,31.36525],"type":"Point"}
}