{
  "type": "Feature",
  "properties": {
    "gn:admin1_code":"7.0",
    "gn:asciiname":"Lekhrab",
    "gn:country_code":"MA",
    "gn:dem":330,
    "gn:feature_class":"P",
    "gn:feature_code":"PPL",
    "gn:name":"Lekhrab",
    "gn:population":0,
    "gn:timezone":"Africa/Casablanca",
    "iso:country":"MA",
    "wof:name":"Lekhrab",
    "wof:placetype":"locality"
},
  "geometry": {"coordinates":[-8.75792,32.22774],"type":"Point"}
}