{
  "type": "Feature",
  "properties": {
    "gn:admin1_code":"7.0",
    "gn:asciiname":"Douar Ait Sidi Hammou",
    "gn:country_code":"MA",
    "gn:dem":500,
    "gn:feature_class":"P",
    "gn:feature_code":"PPL",
    "gn:name":"Douar Ait Sidi Hammou",
    "gn:population":0,
    "gn:timezone":"Africa/Casablanca",
    "iso:country":"MA",
    "wof:name":"Douar Ait Sidi Hammou",
    "wof:placetype":"locality"
},
  "geometry": {"coordinates":[-7.82012,31.60381],"type":"Point"}
}