{
  "type": "Feature",
  "properties": {
    "gn:admin1_code":"08",
    "gn:asciiname":"Achaywa",
    "gn:country_code":"MA",
    "gn:dem":1463,
    "gn:feature_class":"P",
    "gn:feature_code":"PPL",
    "gn:name":"Achaywa",
    "gn:population":0,
    "gn:timezone":"Africa/Casablanca",
    "iso:country":"MA",
    "name:und_x_variant":[
        "Achaouia"
    ],
    "wof:name":"Achaywa",
    "wof:placetype":"locality"
},
  "geometry": {"coordinates":[-4.86708,31.94775],"type":"Point"}
}