{
  "type": "Feature",
  "properties": {
    "gn:admin1_code":"6.0",
    "gn:asciiname":"Oulad Driss",
    "gn:country_code":"MA",
    "gn:dem":195,
    "gn:feature_class":"P",
    "gn:feature_code":"PPL",
    "gn:name":"Oulad Driss",
    "gn:population":0,
    "gn:timezone":"Africa/Casablanca",
    "iso:country":"MA",
    "wof:name":"Oulad Driss",
    "wof:placetype":"locality"
},
  "geometry": {"coordinates":[-8.1543,32.76286],"type":"Point"}
}