{
  "type": "Feature",
  "properties": {
    "gn:admin1_code":"08",
    "gn:asciiname":"Timountout n'Oufella",
    "gn:country_code":"MA",
    "gn:dem":1668,
    "gn:feature_class":"P",
    "gn:feature_code":"PPL",
    "gn:name":"Timountout n\u2019Oufella",
    "gn:population":0,
    "gn:timezone":"Africa/Casablanca",
    "iso:country":"MA",
    "name:und_x_variant":[
        "Timouritoute n\u2019Oufla",
        "Timountout n\u2019Oufella"
    ],
    "wof:name":"Timountout n'Oufella",
    "wof:placetype":"locality"
},
  "geometry": {"coordinates":[-7.26276,31.21111],"type":"Point"}
}