{
  "type": "Feature",
  "properties": {
    "gn:admin1_code":"1.0",
    "gn:asciiname":"Douar Talamanna",
    "gn:country_code":"MA",
    "gn:dem":1027,
    "gn:feature_class":"P",
    "gn:feature_code":"PPL",
    "gn:name":"Douar Talamanna",
    "gn:population":0,
    "gn:timezone":"Africa/Casablanca",
    "iso:country":"MA",
    "wof:name":"Douar Talamanna",
    "wof:placetype":"locality"
},
  "geometry": {"coordinates":[-4.90333,35.14602],"type":"Point"}
}