{
  "type": "Feature",
  "properties": {
    "gn:admin1_code":"9.0",
    "gn:asciiname":"Tissikit",
    "gn:country_code":"MA",
    "gn:dem":515,
    "gn:feature_class":"P",
    "gn:feature_code":"PPL",
    "gn:name":"Tissikit",
    "gn:population":0,
    "gn:timezone":"Africa/Casablanca",
    "iso:country":"MA",
    "wof:name":"Tissikit",
    "wof:placetype":"locality"
},
  "geometry": {"coordinates":[-9.20478,30.11301],"type":"Point"}
}