{
  "type": "Feature",
  "properties": {
    "gn:admin1_code":"7.0",
    "gn:asciiname":"Ait Addouj",
    "gn:country_code":"MA",
    "gn:dem":427,
    "gn:feature_class":"P",
    "gn:feature_code":"PPL",
    "gn:name":"A\u00eft Addouj",
    "gn:population":0,
    "gn:timezone":"Africa/Casablanca",
    "iso:country":"MA",
    "wof:name":"Ait Addouj",
    "wof:placetype":"locality"
},
  "geometry": {"coordinates":[-9.45514,31.41551],"type":"Point"}
}