{
  "type": "Feature",
  "properties": {
    "gn:admin1_code":"09",
    "gn:asciiname":"Ouintla",
    "gn:country_code":"MA",
    "gn:dem":978,
    "gn:feature_class":"P",
    "gn:feature_code":"PPL",
    "gn:name":"Ouintla",
    "gn:population":0,
    "gn:timezone":"Africa/Casablanca",
    "iso:country":"MA",
    "name:und_x_variant":[
        "Wintha",
        "Ouintla"
    ],
    "wof:name":"Ouintla",
    "wof:placetype":"locality"
},
  "geometry": {"coordinates":[-8.54426,29.53173],"type":"Point"}
}