{
  "type": "Feature",
  "properties": {
    "gn:admin1_code":"9.0",
    "gn:asciiname":"Imi-n-Tanat",
    "gn:country_code":"MA",
    "gn:dem":1072,
    "gn:feature_class":"P",
    "gn:feature_code":"PPL",
    "gn:name":"Imi-n-Tanat",
    "gn:population":0,
    "gn:timezone":"Africa/Casablanca",
    "iso:country":"MA",
    "wof:name":"Imi-n-Tanat",
    "wof:placetype":"locality"
},
  "geometry": {"coordinates":[-9.21958,29.57013],"type":"Point"}
}