{
  "type": "Feature",
  "properties": {
    "gn:admin1_code":"09",
    "gn:asciiname":"Tamaddanst",
    "gn:country_code":"MA",
    "gn:dem":1219,
    "gn:feature_class":"P",
    "gn:feature_code":"PPL",
    "gn:name":"Tamaddanst",
    "gn:population":0,
    "gn:timezone":"Africa/Casablanca",
    "iso:country":"MA",
    "name:und_x_variant":[
        "Tameddenst"
    ],
    "wof:name":"Tamaddanst",
    "wof:placetype":"locality"
},
  "geometry": {"coordinates":[-8.05858,30.76965],"type":"Point"}
}