{
  "type": "Feature",
  "properties": {
    "gn:admin1_code":"02",
    "gn:asciiname":"Msilma Ifis",
    "gn:country_code":"MA",
    "gn:dem":67,
    "gn:feature_class":"P",
    "gn:feature_code":"PPL",
    "gn:name":"Msilma Ifis",
    "gn:population":0,
    "gn:timezone":"Africa/Casablanca",
    "iso:country":"MA",
    "wof:name":"Msilma Ifis",
    "wof:placetype":"locality"
},
  "geometry": {"coordinates":[-3.30147,35.1933],"type":"Point"}
}