{
  "type": "Feature",
  "properties": {
    "gn:admin1_code":"4.0",
    "gn:asciiname":"Oulad Taleb Lgharbiya",
    "gn:country_code":"MA",
    "gn:dem":23,
    "gn:feature_class":"P",
    "gn:feature_code":"PPL",
    "gn:name":"Oulad Taleb Lgharbiya",
    "gn:population":0,
    "gn:timezone":"Africa/Casablanca",
    "iso:country":"MA",
    "wof:name":"Oulad Taleb Lgharbiya",
    "wof:placetype":"locality"
},
  "geometry": {"coordinates":[-6.69687,34.18251],"type":"Point"}
}