{
  "type": "Feature",
  "properties": {
    "gn:admin1_code":"09",
    "gn:asciiname":"Ait 'Ali",
    "gn:country_code":"MA",
    "gn:dem":617,
    "gn:feature_class":"P",
    "gn:feature_code":"PPL",
    "gn:name":"A\u00eft \u2019Ali",
    "gn:population":0,
    "gn:timezone":"Africa/Casablanca",
    "iso:country":"MA",
    "name:und_x_variant":[
        "Ayt Ali",
        "A\u00eft Ali",
        "A\u00eft \u2019Ali",
        "Ichourha",
        "Ichou Lahra"
    ],
    "wof:name":"Ait 'Ali",
    "wof:placetype":"locality"
},
  "geometry": {"coordinates":[-8.30884,30.71887000000001],"type":"Point"}
}