{
  "type": "Feature",
  "properties": {
    "gn:admin1_code":"1.0",
    "gn:asciiname":"Douar Louharna",
    "gn:country_code":"MA",
    "gn:dem":772,
    "gn:feature_class":"P",
    "gn:feature_code":"PPL",
    "gn:name":"Douar Louharna",
    "gn:population":0,
    "gn:timezone":"Africa/Casablanca",
    "iso:country":"MA",
    "wof:name":"Douar Louharna",
    "wof:placetype":"locality"
},
  "geometry": {"coordinates":[-5.63432,35.45569000000001],"type":"Point"}
}