{
  "type": "Feature",
  "properties": {
    "gn:admin1_code":"7.0",
    "gn:asciiname":"Oulad Lahsen El Azzaba",
    "gn:country_code":"MA",
    "gn:dem":528,
    "gn:feature_class":"P",
    "gn:feature_code":"PPL",
    "gn:name":"Oulad Lahsen El Azzaba",
    "gn:population":0,
    "gn:timezone":"Africa/Casablanca",
    "iso:country":"MA",
    "wof:name":"Oulad Lahsen El Azzaba",
    "wof:placetype":"locality"
},
  "geometry": {"coordinates":[-7.85876,32.46666],"type":"Point"}
}