{
  "type": "Feature",
  "properties": {
    "gn:admin1_code":"03",
    "gn:asciiname":"Douar Oulad El Haj Abdellah",
    "gn:country_code":"MA",
    "gn:dem":359,
    "gn:feature_class":"P",
    "gn:feature_code":"PPL",
    "gn:name":"Douar Oulad El Haj Abdellah",
    "gn:population":0,
    "gn:timezone":"Africa/Casablanca",
    "iso:country":"MA",
    "name:und_x_variant":[
        "Douar Oulad el Haj Abdallah",
        "Ouled Hadj Abdallah",
        "Oulad el Haj Abdallah",
        "Oulad el Hajj Abdallah",
        "Douar Oulad El Haj Abdellah"
    ],
    "wof:name":"Douar Oulad El Haj Abdellah",
    "wof:placetype":"locality"
},
  "geometry": {"coordinates":[-5.18544,34.15235999999999],"type":"Point"}
}