{
  "type": "Feature",
  "properties": {
    "gn:admin1_code":"03",
    "gn:asciiname":"Douar Ait Ali Ou Zayed",
    "gn:country_code":"MA",
    "gn:dem":668,
    "gn:feature_class":"P",
    "gn:feature_code":"PPL",
    "gn:name":"Douar Ait Ali Ou Zayed",
    "gn:population":0,
    "gn:timezone":"Africa/Casablanca",
    "iso:country":"MA",
    "wof:name":"Douar Ait Ali Ou Zayed",
    "wof:placetype":"locality"
},
  "geometry": {"coordinates":[-4.98587,33.87791],"type":"Point"}
}