{
  "type": "Feature",
  "properties": {
    "gn:admin1_code":"01",
    "gn:asciiname":"Aich Tebene",
    "gn:country_code":"MA",
    "gn:dem":296,
    "gn:feature_class":"P",
    "gn:feature_code":"PPL",
    "gn:name":"A\u00efch Tebene",
    "gn:population":0,
    "gn:timezone":"Africa/Casablanca",
    "iso:country":"MA",
    "name:und_x_variant":[
        "Aich Teben",
        "A\u00efch Tebene"
    ],
    "wof:name":"Aich Tebene",
    "wof:placetype":"locality"
},
  "geometry": {"coordinates":[-4.03,35.15],"type":"Point"}
}