{
  "type": "Feature",
  "properties": {
    "gn:admin1_code":"3.0",
    "gn:asciiname":"Douar Oulad Berrached",
    "gn:country_code":"MA",
    "gn:dem":761,
    "gn:feature_class":"P",
    "gn:feature_code":"PPL",
    "gn:name":"Douar Oulad Berrached",
    "gn:population":0,
    "gn:timezone":"Africa/Casablanca",
    "iso:country":"MA",
    "wof:name":"Douar Oulad Berrached",
    "wof:placetype":"locality"
},
  "geometry": {"coordinates":[-4.26006,34.31349],"type":"Point"}
}