{
  "type": "Feature",
  "properties": {
    "gn:admin1_code":"8.0",
    "gn:asciiname":"Azib Ighsane",
    "gn:country_code":"MA",
    "gn:dem":1811,
    "gn:feature_class":"P",
    "gn:feature_code":"PPL",
    "gn:name":"Azib Ighsane",
    "gn:population":0,
    "gn:timezone":"Africa/Casablanca",
    "iso:country":"MA",
    "wof:name":"Azib Ighsane",
    "wof:placetype":"locality"
},
  "geometry": {"coordinates":[-7.50158,30.47204],"type":"Point"}
}