{
  "type": "Feature",
  "properties": {
    "gn:admin1_code":"03",
    "gn:asciiname":"Cherfa Beni Oual",
    "gn:country_code":"MA",
    "gn:dem":158,
    "gn:feature_class":"P",
    "gn:feature_code":"PPL",
    "gn:name":"Cherfa Beni Oual",
    "gn:population":0,
    "gn:timezone":"Africa/Casablanca",
    "iso:country":"MA",
    "name:und_x_variant":[
        "Cheurfa Beni Oual",
        "Cherfa Beni Oual"
    ],
    "wof:name":"Cherfa Beni Oual",
    "wof:placetype":"locality"
},
  "geometry": {"coordinates":[-5.12108,34.34364],"type":"Point"}
}