{
  "type": "Feature",
  "properties": {
    "gn:admin1_code":"04",
    "gn:asciiname":"Azib Remiki",
    "gn:country_code":"MA",
    "gn:dem":22,
    "gn:feature_class":"P",
    "gn:feature_code":"PPL",
    "gn:name":"Azib Remiki",
    "gn:population":0,
    "gn:timezone":"Africa/Casablanca",
    "iso:country":"MA",
    "name:und_x_variant":[
        "Azib Ramifi",
        "Azib Remiki"
    ],
    "wof:name":"Azib Remiki",
    "wof:placetype":"locality"
},
  "geometry": {"coordinates":[-6.06497,34.73008],"type":"Point"}
}