{
  "type": "Feature",
  "properties": {
    "gn:admin1_code":"5.0",
    "gn:asciiname":"Ait Aari",
    "gn:country_code":"MA",
    "gn:dem":888,
    "gn:feature_class":"P",
    "gn:feature_code":"PPL",
    "gn:name":"A\u00eft A\u00e2ri",
    "gn:population":0,
    "gn:timezone":"Africa/Casablanca",
    "iso:country":"MA",
    "wof:name":"Ait Aari",
    "wof:placetype":"locality"
},
  "geometry": {"coordinates":[-5.82286,32.95365],"type":"Point"}
}