{
  "type": "Feature",
  "properties": {
    "gn:admin1_code":"9.0",
    "gn:asciiname":"Tiguemmi Lhaj Abed",
    "gn:country_code":"MA",
    "gn:dem":120,
    "gn:feature_class":"P",
    "gn:feature_code":"PPL",
    "gn:name":"Tiguemmi Lhaj Abed",
    "gn:population":0,
    "gn:timezone":"Africa/Casablanca",
    "iso:country":"MA",
    "wof:name":"Tiguemmi Lhaj Abed",
    "wof:placetype":"locality"
},
  "geometry": {"coordinates":[-9.35388,30.26591],"type":"Point"}
}