{
  "type": "Feature",
  "properties": {
    "gn:admin1_code":"2.0",
    "gn:asciiname":"Dar Moumni Loukili",
    "gn:country_code":"MA",
    "gn:dem":625,
    "gn:feature_class":"P",
    "gn:feature_code":"PPL",
    "gn:name":"Dar Moumni Loukili",
    "gn:population":0,
    "gn:timezone":"Africa/Casablanca",
    "iso:country":"MA",
    "wof:name":"Dar Moumni Loukili",
    "wof:placetype":"locality"
},
  "geometry": {"coordinates":[-2.42303,34.55206],"type":"Point"}
}