{
  "type": "Feature",
  "properties": {
    "gn:admin1_code":"1.0",
    "gn:asciiname":"Bni Bou Setta",
    "gn:country_code":"MA",
    "gn:dem":906,
    "gn:feature_class":"P",
    "gn:feature_code":"PPL",
    "gn:name":"Bni Bou Setta",
    "gn:population":0,
    "gn:timezone":"Africa/Casablanca",
    "iso:country":"MA",
    "wof:name":"Bni Bou Setta",
    "wof:placetype":"locality"
},
  "geometry": {"coordinates":[-3.87693,35.00581],"type":"Point"}
}