{
  "type": "Feature",
  "properties": {
    "gn:admin1_code":"04",
    "gn:asciiname":"Labhayriya",
    "gn:country_code":"MA",
    "gn:dem":38,
    "gn:feature_class":"P",
    "gn:feature_code":"PPL",
    "gn:name":"Labhayriya",
    "gn:population":0,
    "gn:timezone":"Africa/Casablanca",
    "iso:country":"MA",
    "wof:name":"Labhayriya",
    "wof:placetype":"locality"
},
  "geometry": {"coordinates":[-6.75551,34.11947],"type":"Point"}
}