{
  "type": "Feature",
  "properties": {
    "gn:admin1_code":"09",
    "gn:asciiname":"Aourga",
    "gn:country_code":"MA",
    "gn:dem":566,
    "gn:feature_class":"P",
    "gn:feature_code":"PPL",
    "gn:name":"Aourga",
    "gn:population":0,
    "gn:timezone":"Africa/Casablanca",
    "iso:country":"MA",
    "wof:name":"Aourga",
    "wof:placetype":"locality"
},
  "geometry": {"coordinates":[-9.51077,30.71824],"type":"Point"}
}