{
  "type": "Feature",
  "properties": {
    "gn:admin1_code":"08",
    "gn:asciiname":"Zouiet Sidi Bou Beker",
    "gn:country_code":"MA",
    "gn:dem":1595,
    "gn:feature_class":"P",
    "gn:feature_code":"PPL",
    "gn:name":"Zouiet Sidi Bou Beker",
    "gn:population":0,
    "gn:timezone":"Africa/Casablanca",
    "iso:country":"MA",
    "name:und_x_variant":[
        "Zaou\u00efet Sidi Bou Beker",
        "Zouiet Sidi Bou Beker"
    ],
    "wof:name":"Zouiet Sidi Bou Beker",
    "wof:placetype":"locality"
},
  "geometry": {"coordinates":[-5.98562,31.44313],"type":"Point"}
}