{
  "type": "Feature",
  "properties": {
    "gn:country":"MA",
    "gn:fcode":"ADM3",
    "gn:population":5619,
    "iso:country":"MA",
    "name:ara_x_preferred":[
        "\u0627\u0644\u0641\u0642\u0631\u0627\u0621"
    ],
    "name:fra_x_preferred":[
        "M Fassis"
    ],
    "name:fra_x_variant":[
        "M Fassis (CR)",
        "M Fassis (Commune Rurale)"
    ],
    "qs:name":"M Fassis",
    "qs:photos_9r":0,
    "qs:photos_sr":0,
    "qs:pop_sr":"5",
    "wof:name":"M Fassis",
    "wof:placetype":"localadmin",
    "wof:population":5619
},
  "geometry": {"coordinates":[-6.81101,32.77393],"type":"Point"}
}