{
  "type": "Feature",
  "properties": {
    "gn:admin1_code":"7.0",
    "gn:asciiname":"Douar El Ain",
    "gn:country_code":"MA",
    "gn:dem":353,
    "gn:feature_class":"P",
    "gn:feature_code":"PPL",
    "gn:name":"Douar El Ain",
    "gn:population":0,
    "gn:timezone":"Africa/Casablanca",
    "iso:country":"MA",
    "wof:name":"Douar El Ain",
    "wof:placetype":"locality"
},
  "geometry": {"coordinates":[-8.38278,31.65556],"type":"Point"}
}