{
  "type": "Feature",
  "properties": {
    "gn:admin1_code":"07",
    "gn:asciiname":"Douar Sagriel",
    "gn:country_code":"MA",
    "gn:dem":234,
    "gn:feature_class":"P",
    "gn:feature_code":"PPL",
    "gn:name":"Douar Sagriel",
    "gn:population":0,
    "gn:timezone":"Africa/Casablanca",
    "iso:country":"MA",
    "wof:name":"Douar Sagriel",
    "wof:placetype":"locality"
},
  "geometry": {"coordinates":[-8.56801,32.30384],"type":"Point"}
}