{
  "type": "Feature",
  "properties": {
    "gn:admin1_code":"4.0",
    "gn:asciiname":"Oulad Assam",
    "gn:country_code":"MA",
    "gn:dem":90,
    "gn:feature_class":"P",
    "gn:feature_code":"PPL",
    "gn:name":"Oulad Assam",
    "gn:population":0,
    "gn:timezone":"Africa/Casablanca",
    "iso:country":"MA",
    "wof:name":"Oulad Assam",
    "wof:placetype":"locality"
},
  "geometry": {"coordinates":[-5.94647,34.76384],"type":"Point"}
}