{
  "type": "Feature",
  "properties": {
    "gn:admin1_code":"07",
    "gn:asciiname":"Oufifes",
    "gn:country_code":"MA",
    "gn:dem":1939,
    "gn:feature_class":"P",
    "gn:feature_code":"PPL",
    "gn:name":"Oufifes",
    "gn:population":0,
    "gn:timezone":"Africa/Casablanca",
    "iso:country":"MA",
    "wof:name":"Oufifes",
    "wof:placetype":"locality"
},
  "geometry": {"coordinates":[-8.49475,30.89305],"type":"Point"}
}