{
  "type": "Feature",
  "properties": {
    "gn:admin1_code":"7.0",
    "gn:asciiname":"La'raj",
    "gn:country_code":"MA",
    "gn:dem":567,
    "gn:feature_class":"P",
    "gn:feature_code":"PPL",
    "gn:name":"La\u2019raj",
    "gn:population":0,
    "gn:timezone":"Africa/Casablanca",
    "iso:country":"MA",
    "wof:name":"La'raj",
    "wof:placetype":"locality"
},
  "geometry": {"coordinates":[-7.34406,31.91134000000001],"type":"Point"}
}