{
  "type": "Feature",
  "properties": {
    "gn:admin1_code":"6.0",
    "gn:asciiname":"Douar Ed-Dchar",
    "gn:country_code":"MA",
    "gn:dem":108,
    "gn:feature_class":"P",
    "gn:feature_code":"PPL",
    "gn:name":"Douar Ed-Dchar",
    "gn:population":0,
    "gn:timezone":"Africa/Casablanca",
    "iso:country":"MA",
    "wof:name":"Douar Ed-Dchar",
    "wof:placetype":"locality"
},
  "geometry": {"coordinates":[-8.65442,32.92351],"type":"Point"}
}