{
  "type": "Feature",
  "properties": {
    "gn:admin1_code":"5.0",
    "gn:asciiname":"Ait Ougaddim",
    "gn:country_code":"MA",
    "gn:dem":638,
    "gn:feature_class":"P",
    "gn:feature_code":"PPL",
    "gn:name":"A\u00eft Ougaddim",
    "gn:population":0,
    "gn:timezone":"Africa/Casablanca",
    "iso:country":"MA",
    "wof:name":"Ait Ougaddim",
    "wof:placetype":"locality"
},
  "geometry": {"coordinates":[-6.76589,32.05286],"type":"Point"}
}