{
  "type": "Feature",
  "properties": {
    "gn:admin1_code":"7.0",
    "gn:asciiname":"Timilt",
    "gn:country_code":"MA",
    "gn:dem":893,
    "gn:feature_class":"P",
    "gn:feature_code":"PPL",
    "gn:name":"Timilt",
    "gn:population":0,
    "gn:timezone":"Africa/Casablanca",
    "iso:country":"MA",
    "wof:name":"Timilt",
    "wof:placetype":"locality"
},
  "geometry": {"coordinates":[-8.45819,31.21501],"type":"Point"}
}