{
  "type": "Feature",
  "properties": {
    "gn:admin1_code":"7.0",
    "gn:asciiname":"Tafaytour",
    "gn:country_code":"MA",
    "gn:dem":1087,
    "gn:feature_class":"P",
    "gn:feature_code":"PPL",
    "gn:name":"Tafaytour",
    "gn:population":0,
    "gn:timezone":"Africa/Casablanca",
    "iso:country":"MA",
    "wof:name":"Tafaytour",
    "wof:placetype":"locality"
},
  "geometry": {"coordinates":[-8.98096,31.11862],"type":"Point"}
}