{
  "type": "Feature",
  "properties": {
    "gn:admin1_code":"1.0",
    "gn:asciiname":"Dar Moulay Ahmed Abdelfdil",
    "gn:country_code":"MA",
    "gn:dem":88,
    "gn:feature_class":"P",
    "gn:feature_code":"PPL",
    "gn:name":"Dar Moulay Ahmed Abdelfdil",
    "gn:population":0,
    "gn:timezone":"Africa/Casablanca",
    "iso:country":"MA",
    "wof:name":"Dar Moulay Ahmed Abdelfdil",
    "wof:placetype":"locality"
},
  "geometry": {"coordinates":[-5.78524,35.4973],"type":"Point"}
}