{
  "type": "Feature",
  "properties": {
    "gn:admin1_code":"07",
    "gn:asciiname":"Sbait",
    "gn:country_code":"MA",
    "gn:dem":544,
    "gn:feature_class":"P",
    "gn:feature_code":"PPL",
    "gn:name":"Sba\u00eft",
    "gn:population":0,
    "gn:timezone":"Africa/Casablanca",
    "iso:country":"MA",
    "name:und_x_variant":[
        "Sbe\u00eft",
        "Sba\u00eft"
    ],
    "wof:name":"Sbait",
    "wof:placetype":"locality"
},
  "geometry": {"coordinates":[-8.48,31.41],"type":"Point"}
}