{
  "type": "Feature",
  "properties": {
    "gn:admin1_code":"9.0",
    "gn:asciiname":"Tizroualme",
    "gn:country_code":"MA",
    "gn:dem":498,
    "gn:feature_class":"P",
    "gn:feature_code":"PPL",
    "gn:name":"Tizroualme",
    "gn:population":0,
    "gn:timezone":"Africa/Casablanca",
    "iso:country":"MA",
    "wof:name":"Tizroualme",
    "wof:placetype":"locality"
},
  "geometry": {"coordinates":[-9.52989,30.79309000000001],"type":"Point"}
}