{
  "type": "Feature",
  "properties": {
    "gn:admin1_code":"09",
    "gn:asciiname":"Ait Mzal",
    "gn:country_code":"MA",
    "gn:dem":192,
    "gn:feature_class":"P",
    "gn:feature_code":"PPL",
    "gn:name":"A\u00eft Mzal",
    "gn:population":0,
    "gn:timezone":"Africa/Casablanca",
    "iso:country":"MA",
    "name:ara_x_preferred":[
        "\u0622\u064a\u062a \u0645\u0632\u0627\u0644"
    ],
    "name:azb_x_preferred":[
        "\u0622\u06cc\u062a \u0645\u0632\u0627\u0644"
    ],
    "name:cat_x_preferred":[
        "A\u00eft Mzal"
    ],
    "name:eus_x_preferred":[
        "Ait Mzal"
    ],
    "name:fas_x_preferred":[
        "\u0622\u06cc\u062a \u0645\u0632\u0627\u0644"
    ],
    "name:ita_x_preferred":[
        "Ait Mzal"
    ],
    "name:und_x_variant":[
        "A\u00eft Amzal"
    ],
    "wof:name":"Ait Mzal",
    "wof:placetype":"locality"
},
  "geometry": {"coordinates":[-9.11,30.28],"type":"Point"}
}