{
  "type": "Feature",
  "properties": {
    "gn:admin1_code":"07",
    "gn:asciiname":"Douar Lebbazda",
    "gn:country_code":"MA",
    "gn:dem":332,
    "gn:feature_class":"P",
    "gn:feature_code":"PPL",
    "gn:name":"Douar Lebbazda",
    "gn:population":0,
    "gn:timezone":"Africa/Casablanca",
    "iso:country":"MA",
    "name:und_x_variant":[
        "Bir Yazid",
        "Douar el Yazid",
        "Ben Yazza",
        "Douar Bel Yazid",
        "Douar Lebbazda"
    ],
    "wof:name":"Douar Lebbazda",
    "wof:placetype":"locality"
},
  "geometry": {"coordinates":[-8.48944,31.64714],"type":"Point"}
}