{
  "type": "Feature",
  "properties": {
    "gn:admin1_code":"02",
    "gn:asciiname":"Sidi Yahya",
    "gn:country_code":"MA",
    "gn:dem":588,
    "gn:feature_class":"P",
    "gn:feature_code":"PPL",
    "gn:name":"Sidi Yahya",
    "gn:population":0,
    "gn:timezone":"Africa/Casablanca",
    "iso:country":"MA",
    "name:und_x_variant":[
        "Sidi Yahia"
    ],
    "wof:name":"Sidi Yahya",
    "wof:placetype":"locality"
},
  "geometry": {"coordinates":[-1.86386,34.66468],"type":"Point"}
}