{
  "type": "Feature",
  "properties": {
    "gn:admin1_code":"10",
    "gn:asciiname":"Ait Yasa Ou Ihia",
    "gn:country_code":"MA",
    "gn:dem":78,
    "gn:feature_class":"P",
    "gn:feature_code":"PPL",
    "gn:name":"A\u00eft Yasa Ou Ihia",
    "gn:population":0,
    "gn:timezone":"Africa/Casablanca",
    "iso:country":"MA",
    "name:und_x_variant":[
        "Ait Iaza U Ihia",
        "A\u00eft Yasa Ou Ihia"
    ],
    "wof:name":"Ait Yasa Ou Ihia",
    "wof:placetype":"locality"
},
  "geometry": {"coordinates":[-10.13339,29.35247],"type":"Point"}
}