{
  "type": "Feature",
  "properties": {
    "gn:admin1_code":"55",
    "gn:asciiname":"Guemoud",
    "gn:cc2":"MA",
    "gn:country_code":"MA",
    "gn:dem":62,
    "gn:feature_class":"P",
    "gn:feature_code":"PPL",
    "gn:name":"Guemoud",
    "gn:population":0,
    "gn:timezone":"Africa/Casablanca",
    "iso:country":"MA",
    "name:und_x_variant":[
        "Guemend",
        "Guemoud"
    ],
    "wof:name":"Guemoud",
    "wof:placetype":"locality"
},
  "geometry": {"coordinates":[-9.38,30.36],"type":"Point"}
}