{
  "type": "Feature",
  "properties": {
    "gn:admin1_code":"7.0",
    "gn:asciiname":"Oulad Shaymda",
    "gn:country_code":"MA",
    "gn:dem":454,
    "gn:feature_class":"P",
    "gn:feature_code":"PPL",
    "gn:name":"Oulad Shaymda",
    "gn:population":0,
    "gn:timezone":"Africa/Casablanca",
    "iso:country":"MA",
    "wof:name":"Oulad Shaymda",
    "wof:placetype":"locality"
},
  "geometry": {"coordinates":[-9.03434,31.98006],"type":"Point"}
}