{
  "type": "Feature",
  "properties": {
    "gn:admin1_code":"6.0",
    "gn:asciiname":"Dar Oulad Zaaria",
    "gn:country_code":"MA",
    "gn:dem":502,
    "gn:feature_class":"P",
    "gn:feature_code":"PPL",
    "gn:name":"Dar Oulad Zaaria",
    "gn:population":0,
    "gn:timezone":"Africa/Casablanca",
    "iso:country":"MA",
    "wof:name":"Dar Oulad Zaaria",
    "wof:placetype":"locality"
},
  "geometry": {"coordinates":[-7.51069,32.99134],"type":"Point"}
}