{
  "type": "Feature",
  "properties": {
    "gn:admin1_code":"03",
    "gn:admin2_code":"561.0",
    "gn:admin3_code":"1556103012.0",
    "gn:asciiname":"Ajdir",
    "gn:country_code":"MA",
    "gn:dem":1060,
    "gn:feature_class":"P",
    "gn:feature_code":"PPLA3",
    "gn:name":"Ajdir",
    "gn:population":0,
    "gn:timezone":"Africa/Casablanca",
    "iso:country":"MA",
    "name:ara_x_preferred":[
        "\u0623\u062c\u062f\u064a\u0631"
    ],
    "name:azb_x_preferred":[
        "\u0627\u062c\u062f\u06cc\u0631"
    ],
    "name:cat_x_preferred":[
        "Ajdir"
    ],
    "name:deu_x_preferred":[
        "Ajdir"
    ],
    "name:est_x_preferred":[
        "Ajdir"
    ],
    "name:eus_x_preferred":[
        "Ajdir"
    ],
    "name:fas_x_preferred":[
        "\u0627\u062c\u062f\u06cc\u0631"
    ],
    "name:fra_x_preferred":[
        "Ajdir"
    ],
    "name:ita_x_preferred":[
        "Ajdir"
    ],
    "name:kab_x_preferred":[
        "Ajdir"
    ],
    "name:nld_x_preferred":[
        "Ajdir"
    ],
    "name:nor_x_preferred":[
        "Ajdir"
    ],
    "name:pol_x_preferred":[
        "Ad\u017cdir"
    ],
    "name:por_x_preferred":[
        "Ajdir"
    ],
    "name:spa_x_preferred":[
        "Axdir"
    ],
    "name:swe_x_preferred":[
        "Ajdir"
    ],
    "name:zho_x_preferred":[
        "\u963f\u6770\u8fea\u5c14"
    ],
    "wof:name":"Ajdir",
    "wof:placetype":"locality"
},
  "geometry": {"coordinates":[-3.97582,34.74347],"type":"Point"}
}