{
  "type": "Feature",
  "properties": {
    "gn:admin1_code":"03",
    "gn:admin2_code":"561.0",
    "gn:admin3_code":"1556103012.0",
    "gn:asciiname":"Ajdir",
    "gn:country_code":"MA",
    "gn:dem":1060,
    "gn:feature_class":"P",
    "gn:feature_code":"PPLA3",
    "gn:name":"Ajdir",
    "gn:population":0,
    "gn:timezone":"Africa/Casablanca",
    "iso:country":"MA",
    "wof:name":"Ajdir",
    "wof:placetype":"locality"
},
  "geometry": {"coordinates":[-3.97582,34.74347],"type":"Point"}
}