{
  "type": "Feature",
  "properties": {
    "gn:admin1_code":"02",
    "gn:asciiname":"Ihijjaouiyyene",
    "gn:country_code":"MA",
    "gn:dem":321,
    "gn:feature_class":"P",
    "gn:feature_code":"PPL",
    "gn:name":"Ihijjaouiyyene",
    "gn:population":0,
    "gn:timezone":"Africa/Casablanca",
    "iso:country":"MA",
    "wof:name":"Ihijjaouiyyene",
    "wof:placetype":"locality"
},
  "geometry": {"coordinates":[-3.32897,35.12787],"type":"Point"}
}