{
  "type": "Feature",
  "properties": {
    "gn:admin1_code":"09",
    "gn:asciiname":"Dousdrem",
    "gn:country_code":"MA",
    "gn:dem":576,
    "gn:feature_class":"P",
    "gn:feature_code":"PPL",
    "gn:name":"Dousdrem",
    "gn:population":0,
    "gn:timezone":"Africa/Casablanca",
    "iso:country":"MA",
    "name:und_x_variant":[
        "Dousderm"
    ],
    "wof:name":"Dousdrem",
    "wof:placetype":"locality"
},
  "geometry": {"coordinates":[-9.5619,30.49235],"type":"Point"}
}