{
  "type": "Feature",
  "properties": {
    "gn:admin1_code":"07",
    "gn:asciiname":"Douar Oulad El Garne",
    "gn:country_code":"MA",
    "gn:dem":527,
    "gn:feature_class":"P",
    "gn:feature_code":"PPL",
    "gn:name":"Douar Oulad El Garne",
    "gn:population":0,
    "gn:timezone":"Africa/Casablanca",
    "iso:country":"MA",
    "name:und_x_variant":[
        "Ouled el guerne",
        "Oulad el Guern",
        "Douar Oulad El Garne"
    ],
    "wof:name":"Douar Oulad El Garne",
    "wof:placetype":"locality"
},
  "geometry": {"coordinates":[-7.79123,31.58685],"type":"Point"}
}