{
  "type": "Feature",
  "properties": {
    "gn:admin1_code":"7.0",
    "gn:asciiname":"Igbil-n-Ougalf",
    "gn:country_code":"MA",
    "gn:dem":1110,
    "gn:feature_class":"P",
    "gn:feature_code":"PPL",
    "gn:name":"Igbil-n-Ougalf",
    "gn:population":0,
    "gn:timezone":"Africa/Casablanca",
    "iso:country":"MA",
    "wof:name":"Igbil-n-Ougalf",
    "wof:placetype":"locality"
},
  "geometry": {"coordinates":[-7.70315,31.39265],"type":"Point"}
}