{
  "type": "Feature",
  "properties": {
    "gn:admin1_code":"7.0",
    "gn:asciiname":"Oulad Lichaoun",
    "gn:country_code":"MA",
    "gn:dem":86,
    "gn:feature_class":"P",
    "gn:feature_code":"PPL",
    "gn:name":"Oulad Lichaoun",
    "gn:population":0,
    "gn:timezone":"Africa/Casablanca",
    "iso:country":"MA",
    "wof:name":"Oulad Lichaoun",
    "wof:placetype":"locality"
},
  "geometry": {"coordinates":[-9.12536,32.45029],"type":"Point"}
}