{
  "type": "Feature",
  "properties": {
    "gn:admin1_code":"06",
    "gn:asciiname":"Dahamna",
    "gn:country_code":"MA",
    "gn:dem":548,
    "gn:feature_class":"P",
    "gn:feature_code":"PPL",
    "gn:name":"Dahamna",
    "gn:population":0,
    "gn:timezone":"Africa/Casablanca",
    "iso:country":"MA",
    "name:und_x_variant":[
        "Dar Dahamna"
    ],
    "wof:name":"Dahamna",
    "wof:placetype":"locality"
},
  "geometry": {"coordinates":[-7.11823,32.6135],"type":"Point"}
}