{
  "type": "Feature",
  "properties": {
    "gn:admin1_code":"03",
    "gn:asciiname":"Douar Ain Adel",
    "gn:country_code":"MA",
    "gn:dem":651,
    "gn:feature_class":"P",
    "gn:feature_code":"PPL",
    "gn:name":"Douar Ain Adel",
    "gn:population":0,
    "gn:timezone":"Africa/Casablanca",
    "iso:country":"MA",
    "name:und_x_variant":[
        "Douar A\u00efn el Adel",
        "A\u00efn el Adel",
        "Douar Ain Adel"
    ],
    "wof:name":"Douar Ain Adel",
    "wof:placetype":"locality"
},
  "geometry": {"coordinates":[-4.59771,34.41253],"type":"Point"}
}