{
  "type": "Feature",
  "properties": {
    "gn:admin1_code":"06",
    "gn:asciiname":"Douar ben Daoui",
    "gn:country_code":"MA",
    "gn:dem":166,
    "gn:feature_class":"P",
    "gn:feature_code":"PPL",
    "gn:name":"Douar ben Daoui",
    "gn:population":0,
    "gn:timezone":"Africa/Casablanca",
    "iso:country":"MA",
    "wof:name":"Douar ben Daoui",
    "wof:placetype":"locality"
},
  "geometry": {"coordinates":[-8.5658,32.66808],"type":"Point"}
}