{
  "type": "Feature",
  "properties": {
    "gn:admin1_code":"10",
    "gn:asciiname":"Id Bou Inine",
    "gn:country_code":"MA",
    "gn:dem":1227,
    "gn:feature_class":"P",
    "gn:feature_code":"PPL",
    "gn:name":"Id Bou Inine",
    "gn:population":0,
    "gn:timezone":"Africa/Casablanca",
    "iso:country":"MA",
    "wof:name":"Id Bou Inine",
    "wof:placetype":"locality"
},
  "geometry": {"coordinates":[-9.52492,29.35319],"type":"Point"}
}