{
  "type": "Feature",
  "properties": {
    "gn:admin1_code":"4.0",
    "gn:asciiname":"Douar Cherfa Bou Ouezzam",
    "gn:country_code":"MA",
    "gn:dem":1019,
    "gn:feature_class":"P",
    "gn:feature_code":"PPL",
    "gn:name":"Douar Cherfa Bou Ouezzam",
    "gn:population":0,
    "gn:timezone":"Africa/Casablanca",
    "iso:country":"MA",
    "wof:name":"Douar Cherfa Bou Ouezzam",
    "wof:placetype":"locality"
},
  "geometry": {"coordinates":[-6.03247,33.5501],"type":"Point"}
}