{
  "type": "Feature",
  "properties": {
    "gn:admin1_code":"10.0",
    "gn:asciiname":"Id Chaka",
    "gn:country_code":"MA",
    "gn:dem":827,
    "gn:feature_class":"P",
    "gn:feature_code":"PPL",
    "gn:name":"Id Chaka",
    "gn:population":0,
    "gn:timezone":"Africa/Casablanca",
    "iso:country":"MA",
    "wof:name":"Id Chaka",
    "wof:placetype":"locality"
},
  "geometry": {"coordinates":[-9.84569,29.30578],"type":"Point"}
}