{
  "type": "Feature",
  "properties": {
    "gn:admin1_code":"47.0",
    "gn:asciiname":"Amskere",
    "gn:country_code":"MA",
    "gn:dem":1841,
    "gn:feature_class":"P",
    "gn:feature_code":"PPL",
    "gn:name":"Amskere",
    "gn:population":0,
    "gn:timezone":"Africa/Casablanca",
    "iso:country":"MA",
    "wof:name":"Amskere",
    "wof:placetype":"locality"
},
  "geometry": {"coordinates":[-7.90012,31.17092],"type":"Point"}
}