{
  "type": "Feature",
  "properties": {
    "gn:admin1_code":"02",
    "gn:asciiname":"Amezri",
    "gn:country_code":"MA",
    "gn:dem":995,
    "gn:feature_class":"P",
    "gn:feature_code":"PPL",
    "gn:name":"Amezri",
    "gn:population":0,
    "gn:timezone":"Africa/Casablanca",
    "iso:country":"MA",
    "wof:name":"Amezri",
    "wof:placetype":"locality"
},
  "geometry": {"coordinates":[-3.802,33.84764000000001],"type":"Point"}
}