{
  "type": "Feature",
  "properties": {
    "gn:admin1_code":"04",
    "gn:asciiname":"Douar Oulad Hamad",
    "gn:country_code":"MA",
    "gn:dem":23,
    "gn:feature_class":"P",
    "gn:feature_code":"PPL",
    "gn:name":"Douar Oulad Hamad",
    "gn:population":0,
    "gn:timezone":"Africa/Casablanca",
    "iso:country":"MA",
    "name:und_x_variant":[
        "Oulad Hamad",
        "Ouled Hamad",
        "Douar Oulad Hamad"
    ],
    "wof:name":"Douar Oulad Hamad",
    "wof:placetype":"locality"
},
  "geometry": {"coordinates":[-5.85966,34.48612],"type":"Point"}
}