{
  "type": "Feature",
  "properties": {
    "gn:country":"MA",
    "gn:fcode":"ADM3",
    "gn:population":4895,
    "iso:country":"MA",
    "name:ara_x_preferred":[
        "\u0628\u0646\u064a \u062d\u0631\u0634\u0646"
    ],
    "name:fra_x_preferred":[
        "Azzinate"
    ],
    "name:fra_x_variant":[
        "Azzinate (CR)",
        "Azzinate (Commune Rurale)"
    ],
    "qs:name":"Azzinate",
    "qs:photos_9r":0,
    "qs:photos_sr":0,
    "qs:pop_sr":"4",
    "wof:name":"Azzinate",
    "wof:placetype":"localadmin",
    "wof:population":4895
},
  "geometry": {"coordinates":[-5.78307,35.63425],"type":"Point"}
}