{
  "type": "Feature",
  "properties": {
    "gn:gn_country":"MA",
    "gn:gn_fcode":"ADM3",
    "gn:gn_pop":14404,
    "gn:population":14485,
    "iso:country":"MA",
    "name:ara_x_preferred":[
        "\u062a\u0627\u0645\u062f\u0629"
    ],
    "name:ara_x_variant":[
        "\u0628\u0648\u0644\u0639\u0648\u0627\u0646"
    ],
    "name:cat_x_preferred":[
        "Boulaouane"
    ],
    "name:ceb_x_preferred":[
        "Boulaouane"
    ],
    "name:deu_x_preferred":[
        "Boulaouane"
    ],
    "name:fra_x_preferred":[
        "Boulaouane"
    ],
    "name:fra_x_variant":[
        "Boulaouane (CR)",
        "Boulaouane (Commune Rurale)"
    ],
    "name:ita_x_preferred":[
        "Boulaouane"
    ],
    "name:swe_x_preferred":[
        "Boulaouane"
    ],
    "qs_pg:aaroncc":"MA",
    "qs_pg:gn_country":"MA",
    "qs_pg:gn_fcode":"ADM3",
    "qs_pg:gn_pop":14404,
    "qs_pg:name":"Boulaouane",
    "qs_pg:photos_9r":0,
    "qs_pg:photos_sr":0,
    "qs_pg:pop_sr":6,
    "qs_pg:qs_pg_placetype":"localadmin",
    "wof:name":"Boulaouane",
    "wof:placetype":"localadmin",
    "wof:population":14485
},
  "geometry": {"coordinates":[-8.07074,32.86374],"type":"Point"}
}