{
  "type": "Feature",
  "properties": {
    "gn:admin1_code":"09",
    "gn:asciiname":"Igharmane",
    "gn:country_code":"MA",
    "gn:dem":1690,
    "gn:feature_class":"P",
    "gn:feature_code":"PPL",
    "gn:name":"Igharmane",
    "gn:population":0,
    "gn:timezone":"Africa/Casablanca",
    "iso:country":"MA",
    "name:und_x_variant":[
        "Igharman",
        "Irhamane",
        "Irharmane",
        "Igharmane"
    ],
    "wof:name":"Igharmane",
    "wof:placetype":"locality"
},
  "geometry": {"coordinates":[-7.88598,30.25415],"type":"Point"}
}