{
  "type": "Feature",
  "properties": {
    "gn:admin1_code":"7.0",
    "gn:asciiname":"Tassila Moussa",
    "gn:country_code":"MA",
    "gn:dem":361,
    "gn:feature_class":"P",
    "gn:feature_code":"PPL",
    "gn:name":"Tassila Moussa",
    "gn:population":0,
    "gn:timezone":"Africa/Casablanca",
    "iso:country":"MA",
    "wof:name":"Tassila Moussa",
    "wof:placetype":"locality"
},
  "geometry": {"coordinates":[-9.63828,31.13311],"type":"Point"}
}