{
  "type": "Feature",
  "properties": {
    "gn:admin1_code":"5.0",
    "gn:asciiname":"Daw Ighil",
    "gn:country_code":"MA",
    "gn:dem":1236,
    "gn:feature_class":"P",
    "gn:feature_code":"PPL",
    "gn:name":"Daw Ighil",
    "gn:population":0,
    "gn:timezone":"Africa/Casablanca",
    "iso:country":"MA",
    "wof:name":"Daw Ighil",
    "wof:placetype":"locality"
},
  "geometry": {"coordinates":[-6.94537,31.69705],"type":"Point"}
}