{
  "type": "Feature",
  "properties": {
    "gn:admin1_code":"01",
    "gn:asciiname":"Rhar el Kais",
    "gn:country_code":"MA",
    "gn:dem":1240,
    "gn:feature_class":"P",
    "gn:feature_code":"PPL",
    "gn:name":"Rhar el Ka\u00efs",
    "gn:population":0,
    "gn:timezone":"Africa/Casablanca",
    "iso:country":"MA",
    "wof:name":"Rhar el Kais",
    "wof:placetype":"locality"
},
  "geometry": {"coordinates":[-4.15,34.76],"type":"Point"}
}