{
  "type": "Feature",
  "properties": {
    "gn:admin1_code":"09",
    "gn:asciiname":"Iwzlit",
    "gn:country_code":"MA",
    "gn:dem":1185,
    "gn:feature_class":"P",
    "gn:feature_code":"PPL",
    "gn:name":"Iwzlit",
    "gn:population":0,
    "gn:timezone":"Africa/Casablanca",
    "iso:country":"MA",
    "name:und_x_variant":[
        "Iouzlit"
    ],
    "wof:name":"Iwzlit",
    "wof:placetype":"locality"
},
  "geometry": {"coordinates":[-8.82897,30.11007],"type":"Point"}
}