{
  "type": "Feature",
  "properties": {
    "gn:admin1_code":"08",
    "gn:asciiname":"Aguerzaka",
    "gn:country_code":"MA",
    "gn:dem":1736,
    "gn:feature_class":"P",
    "gn:feature_code":"PPL",
    "gn:name":"Aguerzaka",
    "gn:population":0,
    "gn:timezone":"Africa/Casablanca",
    "iso:country":"MA",
    "name:und_x_variant":[
        "Aguerzouka",
        "Aguerzga",
        "Aguerzeka",
        "Aguerzaka"
    ],
    "wof:name":"Aguerzaka",
    "wof:placetype":"locality"
},
  "geometry": {"coordinates":[-6.11725,31.4986],"type":"Point"}
}