{
  "type": "Feature",
  "properties": {
    "gn:admin1_code":"08",
    "gn:asciiname":"Tignidart",
    "gn:country_code":"MA",
    "gn:dem":1759,
    "gn:feature_class":"P",
    "gn:feature_code":"PPL",
    "gn:name":"Tignidart",
    "gn:population":0,
    "gn:timezone":"Africa/Casablanca",
    "iso:country":"MA",
    "name:und_x_variant":[
        "Tiguidart",
        "Tiguidert",
        "Tignidart"
    ],
    "wof:name":"Tignidart",
    "wof:placetype":"locality"
},
  "geometry": {"coordinates":[-7.31194,31.25877],"type":"Point"}
}