{
  "type": "Feature",
  "properties": {
    "gn:admin1_code":"4.0",
    "gn:asciiname":"Oulad Kamel",
    "gn:country_code":"MA",
    "gn:dem":183,
    "gn:feature_class":"P",
    "gn:feature_code":"PPL",
    "gn:name":"Oulad Kamel",
    "gn:population":0,
    "gn:timezone":"Africa/Casablanca",
    "iso:country":"MA",
    "wof:name":"Oulad Kamel",
    "wof:placetype":"locality"
},
  "geometry": {"coordinates":[-6.60547,34.0019],"type":"Point"}
}