{
  "type": "Feature",
  "properties": {
    "gn:country":"MA",
    "gn:fcode":"ADM3",
    "gn:population":7478,
    "iso:country":"MA",
    "name:ara_x_preferred":[
        "\u0627\u0644\u062e\u0631\u0648\u0628"
    ],
    "name:ara_x_variant":[
        "\u0648\u0627\u062f \u0644\u0648"
    ],
    "name:azb_x_preferred":[
        "\u0648\u0627\u062f \u0644\u0648"
    ],
    "name:cat_x_preferred":[
        "Oued Laou"
    ],
    "name:deu_x_preferred":[
        "Oued Laou"
    ],
    "name:eng_x_preferred":[
        "Oued Laou"
    ],
    "name:eus_x_preferred":[
        "Oued Laou"
    ],
    "name:fas_x_preferred":[
        "\u0648\u0627\u062f \u0644\u0648"
    ],
    "name:fra_x_preferred":[
        "Oued Laou"
    ],
    "name:fra_x_variant":[
        "Oued Laou (MU)",
        "Oued Laou (Commune Urbaine)"
    ],
    "name:nld_x_preferred":[
        "Oued Laou"
    ],
    "name:nob_x_preferred":[
        "Oued Laou"
    ],
    "name:spa_x_preferred":[
        "Oued Laou"
    ],
    "name:urd_x_preferred":[
        "\u0648\u0627\u062f \u0644\u0627\u0648"
    ],
    "qs:name":"Oued Laou",
    "qs:photos_9r":0,
    "qs:photos_sr":0,
    "qs:pop_sr":"5",
    "wd:wordcount":584,
    "wof:name":"Oued Laou",
    "wof:placetype":"localadmin",
    "wof:population":7478
},
  "geometry": {"coordinates":[-5.12036,35.4557],"type":"Point"}
}