{
  "type": "Feature",
  "properties": {
    "gn:gn_country":"MA",
    "gn:gn_fcode":"ADM3",
    "gn:gn_pop":11896,
    "gn:population":11896,
    "iso:country":"MA",
    "name:ara_x_preferred":[
        "\u0633\u064a\u062f\u064a \u0628\u0646\u0648\u0631 (\u0627\u0644\u0628\u0644\u062f\u064a\u0629)"
    ],
    "name:ara_x_variant":[
        "\u0632\u0645\u0627\u0645\u0631\u0629"
    ],
    "name:azb_x_preferred":[
        "\u0632\u0645\u0627\u0645\u0631\u0647"
    ],
    "name:cat_x_preferred":[
        "Zemamra"
    ],
    "name:fas_x_preferred":[
        "\u0632\u0645\u0627\u0645\u0631\u0647"
    ],
    "name:fra_x_preferred":[
        "Zemamra"
    ],
    "name:fra_x_variant":[
        "Zemamra (MU)",
        "Zemamra (Commune Urbaine)"
    ],
    "qs_pg:aaroncc":"MA",
    "qs_pg:gn_country":"MA",
    "qs_pg:gn_fcode":"ADM3",
    "qs_pg:gn_pop":11896,
    "qs_pg:name":"Zemamra",
    "qs_pg:photos_9r":0,
    "qs_pg:photos_sr":0,
    "qs_pg:pop_sr":6,
    "qs_pg:qs_pg_placetype":"localadmin",
    "wof:name":"Zemamra",
    "wof:placetype":"localadmin",
    "wof:population":11896
},
  "geometry": {"coordinates":[-8.7053,32.62181],"type":"Point"}
}