{
  "type": "Feature",
  "properties": {
    "gn:admin1_code":"9.0",
    "gn:asciiname":"Anct",
    "gn:country_code":"MA",
    "gn:dem":760,
    "gn:feature_class":"P",
    "gn:feature_code":"PPL",
    "gn:name":"Anct",
    "gn:population":0,
    "gn:timezone":"Africa/Casablanca",
    "iso:country":"MA",
    "wof:name":"Anct",
    "wof:placetype":"locality"
},
  "geometry": {"coordinates":[-9.26829,29.73524],"type":"Point"}
}