{
  "type": "Feature",
  "properties": {
    "gn:admin1_code":"09",
    "gn:asciiname":"Imaoun",
    "gn:country_code":"MA",
    "gn:dem":919,
    "gn:feature_class":"P",
    "gn:feature_code":"PPL",
    "gn:name":"Imaoun",
    "gn:population":0,
    "gn:timezone":"Africa/Casablanca",
    "iso:country":"MA",
    "wof:name":"Imaoun",
    "wof:placetype":"locality"
},
  "geometry": {"coordinates":[-8.45,30.48],"type":"Point"}
}