{
  "type": "Feature",
  "properties": {
    "gn:admin1_code":"8.0",
    "gn:asciiname":"Ait Tazarine",
    "gn:country_code":"MA",
    "gn:dem":1370,
    "gn:feature_class":"P",
    "gn:feature_code":"PPL",
    "gn:name":"A\u00eft Tazarine",
    "gn:population":0,
    "gn:timezone":"Africa/Casablanca",
    "iso:country":"MA",
    "wof:name":"Ait Tazarine",
    "wof:placetype":"locality"
},
  "geometry": {"coordinates":[-6.20248,31.18853],"type":"Point"}
}