{
  "type": "Feature",
  "properties": {
    "gn:admin1_code":"08",
    "gn:asciiname":"Tasguit",
    "gn:country_code":"MA",
    "gn:dem":1115,
    "gn:feature_class":"P",
    "gn:feature_code":"PPL",
    "gn:name":"Tasguit",
    "gn:population":0,
    "gn:timezone":"Africa/Casablanca",
    "iso:country":"MA",
    "name:und_x_variant":[
        "Ksar Tazguite",
        "Tasguit"
    ],
    "wof:name":"Tasguit",
    "wof:placetype":"locality"
},
  "geometry": {"coordinates":[-4.96,31.81],"type":"Point"}
}