{
  "type": "Feature",
  "properties": {
    "gn:admin1_code":"7.0",
    "gn:asciiname":"Oulad Essoussi",
    "gn:country_code":"MA",
    "gn:dem":429,
    "gn:feature_class":"P",
    "gn:feature_code":"PPL",
    "gn:name":"Oulad Essoussi",
    "gn:population":0,
    "gn:timezone":"Africa/Casablanca",
    "iso:country":"MA",
    "wof:name":"Oulad Essoussi",
    "wof:placetype":"locality"
},
  "geometry": {"coordinates":[-7.4485,32.12732],"type":"Point"}
}