{
  "type": "Feature",
  "properties": {
    "gn:admin1_code":"7.0",
    "gn:asciiname":"Tizert",
    "gn:country_code":"MA",
    "gn:dem":1222,
    "gn:feature_class":"P",
    "gn:feature_code":"PPL",
    "gn:name":"Tizert",
    "gn:population":0,
    "gn:timezone":"Africa/Casablanca",
    "iso:country":"MA",
    "wof:name":"Tizert",
    "wof:placetype":"locality"
},
  "geometry": {"coordinates":[-7.77211,31.29464],"type":"Point"}
}