{
  "type": "Feature",
  "properties": {
    "gn:country":"MA",
    "gn:fcode":"ADM3",
    "gn:pop":31705,
    "iso:country":"MA",
    "name:ara_x_preferred":[
        "\u0633\u064a\u062f\u064a \u0633\u0644\u064a\u0645\u0627\u0646 (\u0627\u0644\u0628\u0644\u062f\u064a\u0629)"
    ],
    "name:ara_x_variant":[
        "\u0633\u064a\u062f\u064a \u064a\u062d\u064a\u0649 \u0627\u0644\u063a\u0631\u0628"
    ],
    "name:cat_x_preferred":[
        "Sidi Yahya El Gharb"
    ],
    "name:ceb_x_preferred":[
        "Sidi Yahia el Gharb"
    ],
    "name:eng_x_preferred":[
        "Sidi Yahya El Gharb"
    ],
    "name:fra_x_preferred":[
        "Sidi Yahya El Gharb"
    ],
    "name:fra_x_variant":[
        "Sidi Yahya El Gharb (MU)",
        "Sidi Yahya El Gharb (Commune Urbaine)"
    ],
    "name:ita_x_preferred":[
        "Sidi Yahia al Gharb"
    ],
    "name:nld_x_preferred":[
        "Sidi Yahya El Gharb"
    ],
    "name:swe_x_preferred":[
        "Sidi Yahia el Gharb"
    ],
    "qs:name":"Sidi Yahya El Gharb",
    "qs:photos_9r":0,
    "qs:photos_sr":0,
    "qs:pop_sr":"7",
    "wd:wordcount":134,
    "wof:name":"Sidi Yahya El Gharb",
    "wof:placetype":"localadmin",
    "wof:population":31705
},
  "geometry": {"coordinates":[-6.30196,34.30745],"type":"Point"}
}