{
  "type": "Feature",
  "properties": {
    "gn:admin1_code":"04",
    "gn:asciiname":"Karia ed Douadi",
    "gn:country_code":"MA",
    "gn:dem":68,
    "gn:feature_class":"P",
    "gn:feature_code":"PPL",
    "gn:name":"Karia ed Douadi",
    "gn:population":0,
    "gn:timezone":"Africa/Casablanca",
    "iso:country":"MA",
    "name:und_x_variant":[
        "Kariat Daoudi",
        "Karia ed Douadi"
    ],
    "wof:name":"Karia ed Douadi",
    "wof:placetype":"locality"
},
  "geometry": {"coordinates":[-5.69519,34.4604],"type":"Point"}
}