{
  "type": "Feature",
  "properties": {
    "gn:admin1_code":"1.0",
    "gn:asciiname":"Laaroussa Mamsoukha",
    "gn:country_code":"MA",
    "gn:dem":372,
    "gn:feature_class":"P",
    "gn:feature_code":"PPL",
    "gn:name":"Laaroussa Mamsoukha",
    "gn:population":0,
    "gn:timezone":"Africa/Casablanca",
    "iso:country":"MA",
    "wof:name":"Laaroussa Mamsoukha",
    "wof:placetype":"locality"
},
  "geometry": {"coordinates":[-5.59837,35.20043],"type":"Point"}
}