{
  "type": "Feature",
  "properties": {
    "gn:admin1_code":"9.0",
    "gn:asciiname":"Calbarch",
    "gn:country_code":"MA",
    "gn:dem":260,
    "gn:feature_class":"P",
    "gn:feature_code":"PPL",
    "gn:name":"\u00c7albarch",
    "gn:population":0,
    "gn:timezone":"Africa/Casablanca",
    "iso:country":"MA",
    "wof:name":"Calbarch",
    "wof:placetype":"locality"
},
  "geometry": {"coordinates":[-9.4715,29.70196],"type":"Point"}
}