{
  "type": "Feature",
  "properties": {
    "gn:admin1_code":"9.0",
    "gn:asciiname":"Lasakra",
    "gn:country_code":"MA",
    "gn:dem":414,
    "gn:feature_class":"P",
    "gn:feature_code":"PPL",
    "gn:name":"Lasakra",
    "gn:population":0,
    "gn:timezone":"Africa/Casablanca",
    "iso:country":"MA",
    "wof:name":"Lasakra",
    "wof:placetype":"locality"
},
  "geometry": {"coordinates":[-8.51788,30.56817],"type":"Point"}
}