{
  "type": "Feature",
  "properties": {
    "gn:admin1_code":"2.0",
    "gn:asciiname":"Chtayta",
    "gn:country_code":"MA",
    "gn:dem":445,
    "gn:feature_class":"P",
    "gn:feature_code":"PPL",
    "gn:name":"Chtayta",
    "gn:population":0,
    "gn:timezone":"Africa/Casablanca",
    "iso:country":"MA",
    "wof:name":"Chtayta",
    "wof:placetype":"locality"
},
  "geometry": {"coordinates":[-1.98008,34.86612],"type":"Point"}
}