{
  "type": "Feature",
  "properties": {
    "gn:admin1_code":"08",
    "gn:asciiname":"Ait Said Ou Ali",
    "gn:country_code":"MA",
    "gn:dem":2464,
    "gn:feature_class":"P",
    "gn:feature_code":"PPL",
    "gn:name":"A\u00eft Sa\u00efd Ou Ali",
    "gn:population":0,
    "gn:timezone":"Africa/Casablanca",
    "iso:country":"MA",
    "wof:name":"Ait Said Ou Ali",
    "wof:placetype":"locality"
},
  "geometry": {"coordinates":[-5.82631,32.02654],"type":"Point"}
}