{
  "type": "Feature",
  "properties": {
    "gn:admin1_code":"6.0",
    "gn:asciiname":"Lalla Rouahla",
    "gn:country_code":"MA",
    "gn:dem":72,
    "gn:feature_class":"P",
    "gn:feature_code":"PPL",
    "gn:name":"Lalla Rouahla",
    "gn:population":0,
    "gn:timezone":"Africa/Casablanca",
    "iso:country":"MA",
    "wof:name":"Lalla Rouahla",
    "wof:placetype":"locality"
},
  "geometry": {"coordinates":[-8.62145,33.04239],"type":"Point"}
}