{
  "type": "Feature",
  "properties": {
    "gn:admin1_code":"9.0",
    "gn:asciiname":"Douar Bayfri",
    "gn:country_code":"MA",
    "gn:dem":309,
    "gn:feature_class":"P",
    "gn:feature_code":"PPL",
    "gn:name":"Douar Bayfri",
    "gn:population":0,
    "gn:timezone":"Africa/Casablanca",
    "iso:country":"MA",
    "wof:name":"Douar Bayfri",
    "wof:placetype":"locality"
},
  "geometry": {"coordinates":[-9.78597,30.8482],"type":"Point"}
}