{
  "type": "Feature",
  "properties": {
    "gn:admin1_code":"5.0",
    "gn:asciiname":"Tadawt-n-Ighram",
    "gn:country_code":"MA",
    "gn:dem":1314,
    "gn:feature_class":"P",
    "gn:feature_code":"PPL",
    "gn:name":"Tadawt-n-Ighram",
    "gn:population":0,
    "gn:timezone":"Africa/Casablanca",
    "iso:country":"MA",
    "wof:name":"Tadawt-n-Ighram",
    "wof:placetype":"locality"
},
  "geometry": {"coordinates":[-6.62641,31.99466],"type":"Point"}
}