{
  "type": "Feature",
  "properties": {
    "gn:admin1_code":"01",
    "gn:asciiname":"Douar Mangralla",
    "gn:country_code":"MA",
    "gn:dem":312,
    "gn:feature_class":"P",
    "gn:feature_code":"PPL",
    "gn:name":"Douar Mangralla",
    "gn:population":0,
    "gn:timezone":"Africa/Casablanca",
    "iso:country":"MA",
    "name:und_x_variant":[
        "Mengrala"
    ],
    "wof:name":"Douar Mangralla",
    "wof:placetype":"locality"
},
  "geometry": {"coordinates":[-5.56439,35.66208],"type":"Point"}
}