{
  "type": "Feature",
  "properties": {
    "gn:admin1_code":"02",
    "gn:asciiname":"Sidi Marouf",
    "gn:country_code":"MA",
    "gn:dem":465,
    "gn:feature_class":"P",
    "gn:feature_code":"PPL",
    "gn:name":"Sidi Marouf",
    "gn:population":0,
    "gn:timezone":"Africa/Casablanca",
    "iso:country":"MA",
    "wof:name":"Sidi Marouf",
    "wof:placetype":"locality"
},
  "geometry": {"coordinates":[-2.79,34.37],"type":"Point"}
}