{
  "type": "Feature",
  "properties": {
    "gn:admin1_code":"08",
    "gn:asciiname":"Irhir n'Inigane",
    "gn:country_code":"MA",
    "gn:dem":1567,
    "gn:feature_class":"P",
    "gn:feature_code":"PPL",
    "gn:name":"Irhir n\u2019Inigane",
    "gn:population":0,
    "gn:timezone":"Africa/Casablanca",
    "iso:country":"MA",
    "wof:name":"Irhir n'Inigane",
    "wof:placetype":"locality"
},
  "geometry": {"coordinates":[-6.60159,31.24397],"type":"Point"}
}