{
  "type": "Feature",
  "properties": {
    "gn:admin1_code":"06",
    "gn:asciiname":"Zirara",
    "gn:country_code":"MA",
    "gn:dem":241,
    "gn:feature_class":"P",
    "gn:feature_code":"PPL",
    "gn:name":"Zirara",
    "gn:population":0,
    "gn:timezone":"Africa/Casablanca",
    "iso:country":"MA",
    "name:ara_x_preferred":[
        "\u0632\u064a\u0631\u0627\u0631\u0629"
    ],
    "name:cat_x_preferred":[
        "Zirara"
    ],
    "name:ita_x_preferred":[
        "Zirara"
    ],
    "name:urd_x_preferred":[
        "\u0632\u06cc\u0631\u0627\u0631\u06c1"
    ],
    "wof:name":"Zirara",
    "wof:placetype":"locality"
},
  "geometry": {"coordinates":[-8.53539,32.34461],"type":"Point"}
}