{
  "type": "Feature",
  "properties": {
    "gn:admin1_code":"4.0",
    "gn:asciiname":"Sar Omar Salmani",
    "gn:country_code":"MA",
    "gn:dem":300,
    "gn:feature_class":"P",
    "gn:feature_code":"PPL",
    "gn:name":"Sar Omar Salmani",
    "gn:population":0,
    "gn:timezone":"Africa/Casablanca",
    "iso:country":"MA",
    "wof:name":"Sar Omar Salmani",
    "wof:placetype":"locality"
},
  "geometry": {"coordinates":[-6.57618,33.63154],"type":"Point"}
}