{
  "type": "Feature",
  "properties": {
    "gn:admin1_code":"1.0",
    "gn:asciiname":"Douar Hjaa Mlaahi",
    "gn:country_code":"MA",
    "gn:dem":340,
    "gn:feature_class":"P",
    "gn:feature_code":"PPL",
    "gn:name":"Douar Hjaa Mlaahi",
    "gn:population":0,
    "gn:timezone":"Africa/Casablanca",
    "iso:country":"MA",
    "wof:name":"Douar Hjaa Mlaahi",
    "wof:placetype":"locality"
},
  "geometry": {"coordinates":[-5.18732,34.7414],"type":"Point"}
}