{
  "type": "Feature",
  "properties": {
    "gn:admin1_code":"04",
    "gn:asciiname":"Dar el Baraka",
    "gn:country_code":"MA",
    "gn:dem":17,
    "gn:feature_class":"P",
    "gn:feature_code":"PPL",
    "gn:name":"Dar el Baraka",
    "gn:population":0,
    "gn:timezone":"Africa/Casablanca",
    "iso:country":"MA",
    "wof:name":"Dar el Baraka",
    "wof:placetype":"locality"
},
  "geometry": {"coordinates":[-6.12088,34.43153],"type":"Point"}
}