{
  "type": "Feature",
  "properties": {
    "gn:admin1_code":"10",
    "gn:asciiname":"Idufkir",
    "gn:country_code":"MA",
    "gn:dem":19,
    "gn:feature_class":"P",
    "gn:feature_code":"PPL",
    "gn:name":"Idufkir",
    "gn:population":0,
    "gn:timezone":"Africa/Casablanca",
    "iso:country":"MA",
    "wof:name":"Idufkir",
    "wof:placetype":"locality"
},
  "geometry": {"coordinates":[-10.16,29.38],"type":"Point"}
}