{
  "type": "Feature",
  "properties": {
    "gn:admin1_code":"7.0",
    "gn:asciiname":"Rbaat Ahmed Bel Ayachi",
    "gn:country_code":"MA",
    "gn:dem":392,
    "gn:feature_class":"P",
    "gn:feature_code":"PPL",
    "gn:name":"Rbaat Ahmed Bel Ayachi",
    "gn:population":0,
    "gn:timezone":"Africa/Casablanca",
    "iso:country":"MA",
    "wof:name":"Rbaat Ahmed Bel Ayachi",
    "wof:placetype":"locality"
},
  "geometry": {"coordinates":[-9.02591,31.99958],"type":"Point"}
}