{
  "type": "Feature",
  "properties": {
    "gn:admin1_code":"7.0",
    "gn:asciiname":"Nzalat Oulad Moussa",
    "gn:country_code":"MA",
    "gn:dem":425,
    "gn:feature_class":"P",
    "gn:feature_code":"PPL",
    "gn:name":"Nzalat Oulad Moussa",
    "gn:population":0,
    "gn:timezone":"Africa/Casablanca",
    "iso:country":"MA",
    "wof:name":"Nzalat Oulad Moussa",
    "wof:placetype":"locality"
},
  "geometry": {"coordinates":[-7.93487,32.05917],"type":"Point"}
}