{
  "type": "Feature",
  "properties": {
    "gn:admin1_code":"5.0",
    "gn:asciiname":"Ait 'Allal",
    "gn:country_code":"MA",
    "gn:dem":525,
    "gn:feature_class":"P",
    "gn:feature_code":"PPL",
    "gn:name":"A\u00eft \u2019Allal",
    "gn:population":0,
    "gn:timezone":"Africa/Casablanca",
    "iso:country":"MA",
    "wof:name":"Ait 'Allal",
    "wof:placetype":"locality"
},
  "geometry": {"coordinates":[-6.90651,32.08487],"type":"Point"}
}