{
  "type": "Feature",
  "properties": {
    "gn:country":"MA",
    "gn:fcode":"ADM3",
    "gn:population":10298,
    "iso:country":"MA",
    "name:ara_x_preferred":[
        "\u0628\u0646\u064a \u0628\u0648\u0641\u0631\u0627\u062d"
    ],
    "name:cat_x_preferred":[
        "Bni Boufrah"
    ],
    "name:ceb_x_preferred":[
        "Bni Boufrah"
    ],
    "name:eng_x_preferred":[
        "Bni Boufrah"
    ],
    "name:fra_x_preferred":[
        "Bni Boufrah"
    ],
    "name:fra_x_variant":[
        "Bni Boufrah (CR)",
        "Bni Boufrah (Commune Rurale)"
    ],
    "name:ita_x_preferred":[
        "Bni Boufrah"
    ],
    "name:por_x_preferred":[
        "Beni Boufrah"
    ],
    "name:swe_x_preferred":[
        "Bni Boufrah"
    ],
    "name:urd_x_preferred":[
        "\u0628\u0646\u06cc \u0628\u0648\u0641\u0631\u0627\u062d"
    ],
    "qs:name":"Bni Boufrah",
    "qs:photos_9r":0,
    "qs:photos_sr":0,
    "qs:pop_sr":"6",
    "wd:wordcount":80,
    "wof:name":"Bni Boufrah",
    "wof:placetype":"localadmin",
    "wof:population":10298
},
  "geometry": {"coordinates":[-4.32061,35.06761],"type":"Point"}
}