{
  "type": "Feature",
  "properties": {
    "gn:admin1_code":"06",
    "gn:asciiname":"Had Oulad Issa",
    "gn:country_code":"MA",
    "gn:dem":78,
    "gn:feature_class":"P",
    "gn:feature_code":"PPL",
    "gn:name":"Had Oulad Issa",
    "gn:population":0,
    "gn:timezone":"Africa/Casablanca",
    "iso:country":"MA",
    "name:und_x_variant":[
        "Had-des-Oulad-A\u00efssa",
        "Souk el Had",
        "Had Oulad A\u00efssa",
        "El Had Oulad A\u00efssa",
        "El Had des Oulad A\u00efssa",
        "Had Oulad Issa"
    ],
    "wof:name":"Had Oulad Issa",
    "wof:placetype":"locality"
},
  "geometry": {"coordinates":[-8.69759,32.95217],"type":"Point"}
}