{
  "type": "Feature",
  "properties": {
    "gn:admin1_code":"7.0",
    "gn:asciiname":"Id Zenouat",
    "gn:country_code":"MA",
    "gn:dem":279,
    "gn:feature_class":"P",
    "gn:feature_code":"PPL",
    "gn:name":"Id Zenouat",
    "gn:population":0,
    "gn:timezone":"Africa/Casablanca",
    "iso:country":"MA",
    "wof:name":"Id Zenouat",
    "wof:placetype":"locality"
},
  "geometry": {"coordinates":[-9.73674,31.02077],"type":"Point"}
}