{
  "type": "Feature",
  "properties": {
    "gn:admin1_code":"1.0",
    "gn:asciiname":"Douar Zrabha",
    "gn:country_code":"MA",
    "gn:dem":372,
    "gn:feature_class":"P",
    "gn:feature_code":"PPL",
    "gn:name":"Douar Zrabha",
    "gn:population":0,
    "gn:timezone":"Africa/Casablanca",
    "iso:country":"MA",
    "wof:name":"Douar Zrabha",
    "wof:placetype":"locality"
},
  "geometry": {"coordinates":[-5.53702,35.5796],"type":"Point"}
}