{
  "type": "Feature",
  "properties": {
    "gn:admin1_code":"7.0",
    "gn:asciiname":"Douar Dhar Ben El Caid",
    "gn:country_code":"MA",
    "gn:dem":372,
    "gn:feature_class":"P",
    "gn:feature_code":"PPL",
    "gn:name":"Douar Dhar Ben El Caid",
    "gn:population":0,
    "gn:timezone":"Africa/Casablanca",
    "iso:country":"MA",
    "wof:name":"Douar Dhar Ben El Caid",
    "wof:placetype":"locality"
},
  "geometry": {"coordinates":[-9.40098,31.5539],"type":"Point"}
}