{
  "type": "Feature",
  "properties": {
    "gn:admin1_code":"6.0",
    "gn:asciiname":"Douar Aoulad Sidi Ahmed",
    "gn:country_code":"MA",
    "gn:dem":356,
    "gn:feature_class":"P",
    "gn:feature_code":"PPL",
    "gn:name":"Douar Aoulad Sidi Ahmed",
    "gn:population":0,
    "gn:timezone":"Africa/Casablanca",
    "iso:country":"MA",
    "wof:name":"Douar Aoulad Sidi Ahmed",
    "wof:placetype":"locality"
},
  "geometry": {"coordinates":[-6.8788,33.38239],"type":"Point"}
}