{
  "type": "Feature",
  "properties": {
    "gn:admin1_code":"9.0",
    "gn:asciiname":"Taladia",
    "gn:country_code":"MA",
    "gn:dem":1130,
    "gn:feature_class":"P",
    "gn:feature_code":"PPL",
    "gn:name":"Taladia",
    "gn:population":0,
    "gn:timezone":"Africa/Casablanca",
    "iso:country":"MA",
    "wof:name":"Taladia",
    "wof:placetype":"locality"
},
  "geometry": {"coordinates":[-8.0028,30.70142],"type":"Point"}
}