{
  "type": "Feature",
  "properties": {
    "gn:admin1_code":"5.0",
    "gn:asciiname":"Azib Ihadatane",
    "gn:country_code":"MA",
    "gn:dem":1023,
    "gn:feature_class":"P",
    "gn:feature_code":"PPL",
    "gn:name":"Azib Ihadatane",
    "gn:population":0,
    "gn:timezone":"Africa/Casablanca",
    "iso:country":"MA",
    "wof:name":"Azib Ihadatane",
    "wof:placetype":"locality"
},
  "geometry": {"coordinates":[-7.03889,31.7195],"type":"Point"}
}