{
  "type": "Feature",
  "properties": {
    "gn:admin1_code":"05",
    "gn:asciiname":"Imi -n- Isk",
    "gn:country_code":"MA",
    "gn:dem":2076,
    "gn:elevation":"0.0",
    "gn:feature_class":"P",
    "gn:feature_code":"PPL",
    "gn:name":"Imi -n- Isk",
    "gn:population":0,
    "gn:timezone":"Africa/Casablanca",
    "iso:country":"MA",
    "name:und_x_variant":[
        "Imi n\u2019Isk"
    ],
    "wof:name":"Imi -n- Isk",
    "wof:placetype":"locality"
},
  "geometry": {"coordinates":[-6.64246,31.53888],"type":"Point"}
}