{
  "type": "Feature",
  "properties": {
    "gn:admin1_code":"6.0",
    "gn:asciiname":"Fouim Sidi Ben Amer",
    "gn:country_code":"MA",
    "gn:dem":488,
    "gn:feature_class":"P",
    "gn:feature_code":"PPL",
    "gn:name":"Fouim Sidi Ben Amer",
    "gn:population":0,
    "gn:timezone":"Africa/Casablanca",
    "iso:country":"MA",
    "wof:name":"Fouim Sidi Ben Amer",
    "wof:placetype":"locality"
},
  "geometry": {"coordinates":[-7.00431,33.29582],"type":"Point"}
}