{
  "type": "Feature",
  "properties": {
    "gn:admin1_code":"03",
    "gn:asciiname":"Qouassem",
    "gn:country_code":"MA",
    "gn:dem":296,
    "gn:feature_class":"P",
    "gn:feature_code":"PPL",
    "gn:name":"Qouassem",
    "gn:population":0,
    "gn:timezone":"Africa/Casablanca",
    "iso:country":"MA",
    "name:und_x_variant":[
        "El Souahem",
        "Kouassem",
        "Qouassem"
    ],
    "wof:name":"Qouassem",
    "wof:placetype":"locality"
},
  "geometry": {"coordinates":[-5.05952,34.51522],"type":"Point"}
}