{
  "type": "Feature",
  "properties": {
    "gn:admin1_code":"4.0",
    "gn:asciiname":"Souassiyine Laakkal",
    "gn:country_code":"MA",
    "gn:dem":11,
    "gn:feature_class":"P",
    "gn:feature_code":"PPL",
    "gn:name":"Souassiyine Laakkal",
    "gn:population":0,
    "gn:timezone":"Africa/Casablanca",
    "iso:country":"MA",
    "wof:name":"Souassiyine Laakkal",
    "wof:placetype":"locality"
},
  "geometry": {"coordinates":[-6.25438,34.51069],"type":"Point"}
}