{
  "type": "Feature",
  "properties": {
    "gn:admin1_code":"03",
    "gn:asciiname":"El Jemaa el Rheriba",
    "gn:country_code":"MA",
    "gn:dem":548,
    "gn:feature_class":"P",
    "gn:feature_code":"PPL",
    "gn:name":"El Jemaa el Rheriba",
    "gn:population":0,
    "gn:timezone":"Africa/Casablanca",
    "iso:country":"MA",
    "wof:name":"El Jemaa el Rheriba",
    "wof:placetype":"locality"
},
  "geometry": {"coordinates":[-4.91238,34.48829],"type":"Point"}
}