{
  "type": "Feature",
  "properties": {
    "gn:admin1_code":"6.0",
    "gn:asciiname":"Dar El Haj 'Abdallah",
    "gn:country_code":"MA",
    "gn:dem":187,
    "gn:feature_class":"P",
    "gn:feature_code":"PPL",
    "gn:name":"Dar El Haj \u2019Abdallah",
    "gn:population":0,
    "gn:timezone":"Africa/Casablanca",
    "iso:country":"MA",
    "wof:name":"Dar El Haj 'Abdallah",
    "wof:placetype":"locality"
},
  "geometry": {"coordinates":[-8.09754,33.20419],"type":"Point"}
}