{
  "type": "Feature",
  "properties": {
    "gn:admin1_code":"1.0",
    "gn:asciiname":"Douar Amazigh",
    "gn:country_code":"MA",
    "gn:dem":847,
    "gn:feature_class":"P",
    "gn:feature_code":"PPL",
    "gn:name":"Douar Amazigh",
    "gn:population":0,
    "gn:timezone":"Africa/Casablanca",
    "iso:country":"MA",
    "wof:name":"Douar Amazigh",
    "wof:placetype":"locality"
},
  "geometry": {"coordinates":[-5.02993,35.09520999999999],"type":"Point"}
}