{
  "type": "Feature",
  "properties": {
    "gn:admin1_code":"08",
    "gn:asciiname":"Akour",
    "gn:country_code":"MA",
    "gn:dem":1724,
    "gn:feature_class":"P",
    "gn:feature_code":"PPL",
    "gn:name":"Akour",
    "gn:population":0,
    "gn:timezone":"Africa/Casablanca",
    "iso:country":"MA",
    "wof:name":"Akour",
    "wof:placetype":"locality"
},
  "geometry": {"coordinates":[-5.24876,31.71363],"type":"Point"}
}