{
  "type": "Feature",
  "properties": {
    "gn:admin1_code":"09",
    "gn:asciiname":"Tabia",
    "gn:country_code":"MA",
    "gn:dem":858,
    "gn:feature_class":"P",
    "gn:feature_code":"PPL",
    "gn:name":"Tabia",
    "gn:population":0,
    "gn:timezone":"Africa/Casablanca",
    "iso:country":"MA",
    "name:ceb_x_preferred":[
        "Tabia"
    ],
    "name:ita_x_preferred":[
        "Tabia"
    ],
    "name:swe_x_preferred":[
        "Tabia"
    ],
    "wof:name":"Tabia",
    "wof:placetype":"locality"
},
  "geometry": {"coordinates":[-8.01875,30.73075],"type":"Point"}
}