{
  "type": "Feature",
  "properties": {
    "gn:admin1_code":"09",
    "gn:asciiname":"Agmour",
    "gn:country_code":"MA",
    "gn:dem":782,
    "gn:feature_class":"P",
    "gn:feature_code":"PPL",
    "gn:name":"Agmour",
    "gn:population":0,
    "gn:timezone":"Africa/Casablanca",
    "iso:country":"MA",
    "wof:name":"Agmour",
    "wof:placetype":"locality"
},
  "geometry": {"coordinates":[-7.4127,30.07397000000001],"type":"Point"}
}