{
  "type": "Feature",
  "properties": {
    "gn:admin1_code":"7.0",
    "gn:asciiname":"Douar Ait Bou Higoune",
    "gn:country_code":"MA",
    "gn:dem":431,
    "gn:feature_class":"P",
    "gn:feature_code":"PPL",
    "gn:name":"Douar Ait Bou Higoune",
    "gn:population":0,
    "gn:timezone":"Africa/Casablanca",
    "iso:country":"MA",
    "wof:name":"Douar Ait Bou Higoune",
    "wof:placetype":"locality"
},
  "geometry": {"coordinates":[-9.32067,31.52758],"type":"Point"}
}