{
  "type": "Feature",
  "properties": {
    "gn:admin1_code":"7.0",
    "gn:asciiname":"Iggui-Ouach",
    "gn:country_code":"MA",
    "gn:dem":1285,
    "gn:feature_class":"P",
    "gn:feature_code":"PPL",
    "gn:name":"Iggui-Ouach",
    "gn:population":0,
    "gn:timezone":"Africa/Casablanca",
    "iso:country":"MA",
    "wof:name":"Iggui-Ouach",
    "wof:placetype":"locality"
},
  "geometry": {"coordinates":[-9.24615,30.99305],"type":"Point"}
}