{
  "type": "Feature",
  "properties": {
    "gn:admin1_code":"01",
    "gn:asciiname":"Douar Bni Aydoune",
    "gn:country_code":"MA",
    "gn:dem":759,
    "gn:feature_class":"P",
    "gn:feature_code":"PPL",
    "gn:name":"Douar Bni Aydoune",
    "gn:population":0,
    "gn:timezone":"Africa/Casablanca",
    "iso:country":"MA",
    "name:und_x_variant":[
        "Beni A\u00efdoune"
    ],
    "wof:name":"Douar Bni Aydoune",
    "wof:placetype":"locality"
},
  "geometry": {"coordinates":[-5.05326,35.27425],"type":"Point"}
}