{
  "type": "Feature",
  "properties": {
    "gn:admin1_code":"7.0",
    "gn:asciiname":"Id Aissa",
    "gn:country_code":"MA",
    "gn:dem":293,
    "gn:feature_class":"P",
    "gn:feature_code":"PPL",
    "gn:name":"Id Aissa",
    "gn:population":0,
    "gn:timezone":"Africa/Casablanca",
    "iso:country":"MA",
    "wof:name":"Id Aissa",
    "wof:placetype":"locality"
},
  "geometry": {"coordinates":[-9.79586,30.97255],"type":"Point"}
}