{
  "type": "Feature",
  "properties": {
    "gn:admin1_code":"03",
    "gn:asciiname":"Tizourgane",
    "gn:country_code":"MA",
    "gn:dem":540,
    "gn:feature_class":"P",
    "gn:feature_code":"PPL",
    "gn:name":"Tizourgane",
    "gn:population":0,
    "gn:timezone":"Africa/Casablanca",
    "iso:country":"MA",
    "name:und_x_variant":[
        "Tizourghane",
        "Tizaorgane",
        "Tizourgane"
    ],
    "wof:name":"Tizourgane",
    "wof:placetype":"locality"
},
  "geometry": {"coordinates":[-4.73542,34.60388],"type":"Point"}
}