{
  "type": "Feature",
  "properties": {
    "gn:admin1_code":"5.0",
    "gn:asciiname":"Ait Wi 'Lef",
    "gn:country_code":"MA",
    "gn:dem":1138,
    "gn:feature_class":"P",
    "gn:feature_code":"PPL",
    "gn:name":"A\u00eft Wi \u2019Lef",
    "gn:population":0,
    "gn:timezone":"Africa/Casablanca",
    "iso:country":"MA",
    "wof:name":"Ait Wi 'Lef",
    "wof:placetype":"locality"
},
  "geometry": {"coordinates":[-6.23253,32.01015],"type":"Point"}
}