{
  "type": "Feature",
  "properties": {
    "iso:country":"MA",
    "qs:gn_country":"MA",
    "qs:gn_fcode":"PPL",
    "qs:gn_pop":0,
    "qs:name":"Ait Ridi",
    "qs:name_adm0":"\u0627\u0644\u0645\u063a\u0631\u0628",
    "qs:name_adm1":"\u0633\u0648\u0633 \u0640 \u0645\u0627\u0633\u0629 \u0640 \u062f\u0631\u0639\u0629",
    "qs:photos":25,
    "qs:photos_1k":5,
    "qs:photos_9k":1,
    "qs:photos_9r":1,
    "qs:photos_all":25,
    "qs:photos_sr":1,
    "qs:placetype":"Town",
    "qs:pop_sr":"0",
    "qs:woe_adm0":23424893,
    "wof:name":"Ait Ridi",
    "wof:placetype":"locality"
},
  "geometry": {"coordinates":[-6.19238,31.19088],"type":"Point"}
}