{
  "type": "Feature",
  "properties": {
    "gn:admin1_code":"02",
    "gn:asciiname":"Ali Ouzinib",
    "gn:country_code":"MA",
    "gn:dem":128,
    "gn:feature_class":"P",
    "gn:feature_code":"PPL",
    "gn:name":"Ali Ouzinib",
    "gn:population":0,
    "gn:timezone":"Africa/Casablanca",
    "iso:country":"MA",
    "name:und_x_variant":[
        "Ali Uzinib",
        "Ali Ouzinib"
    ],
    "wof:name":"Ali Ouzinib",
    "wof:placetype":"locality"
},
  "geometry": {"coordinates":[-3.21001,35.10515],"type":"Point"}
}