{
  "type": "Feature",
  "properties": {
    "gn:admin1_code":"05",
    "gn:asciiname":"Zawyat Askar",
    "gn:country_code":"MA",
    "gn:dem":1179,
    "gn:feature_class":"P",
    "gn:feature_code":"PPL",
    "gn:name":"Zawyat Askar",
    "gn:population":0,
    "gn:timezone":"Africa/Casablanca",
    "iso:country":"MA",
    "name:und_x_variant":[
        "Zaouia Asker"
    ],
    "wof:name":"Zawyat Askar",
    "wof:placetype":"locality"
},
  "geometry": {"coordinates":[-6.15019,32.16638],"type":"Point"}
}