{
  "type": "Feature",
  "properties": {
    "gn:admin1_code":"6.0",
    "gn:asciiname":"Tnaja",
    "gn:country_code":"MA",
    "gn:dem":185,
    "gn:feature_class":"P",
    "gn:feature_code":"PPL",
    "gn:name":"Tnaja",
    "gn:population":0,
    "gn:timezone":"Africa/Casablanca",
    "iso:country":"MA",
    "wof:name":"Tnaja",
    "wof:placetype":"locality"
},
  "geometry": {"coordinates":[-8.16511,33.15131],"type":"Point"}
}