{
  "type": "Feature",
  "properties": {
    "gn:admin1_code":"10",
    "gn:asciiname":"Amzloug",
    "gn:country_code":"MA",
    "gn:dem":641,
    "gn:feature_class":"P",
    "gn:feature_code":"PPL",
    "gn:name":"Amzloug",
    "gn:population":0,
    "gn:timezone":"Africa/Casablanca",
    "iso:country":"MA",
    "name:und_x_variant":[
        "Id Bocoto",
        "Id Bokoto",
        "Irhgradene",
        "Amzloug"
    ],
    "wof:name":"Amzloug",
    "wof:placetype":"locality"
},
  "geometry": {"coordinates":[-9.90069,29.38821],"type":"Point"}
}