{
  "type": "Feature",
  "properties": {
    "gn:admin1_code":"2.0",
    "gn:asciiname":"Sidi Mimoune",
    "gn:country_code":"MA",
    "gn:dem":455,
    "gn:feature_class":"P",
    "gn:feature_code":"PPL",
    "gn:name":"Sidi Mimoune",
    "gn:population":0,
    "gn:timezone":"Africa/Casablanca",
    "iso:country":"MA",
    "wof:name":"Sidi Mimoune",
    "wof:placetype":"locality"
},
  "geometry": {"coordinates":[-3.03972,35.19713],"type":"Point"}
}