{
  "type": "Feature",
  "properties": {
    "gn:admin1_code":"01",
    "gn:asciiname":"Beni Oualal",
    "gn:country_code":"MA",
    "gn:dem":465,
    "gn:feature_class":"P",
    "gn:feature_code":"PPL",
    "gn:name":"Beni Oualal",
    "gn:population":0,
    "gn:timezone":"Africa/Casablanca",
    "iso:country":"MA",
    "name:und_x_variant":[
        "Beni Ouallal",
        "Bani Oualal",
        "Beni Oualal"
    ],
    "wof:name":"Beni Oualal",
    "wof:placetype":"locality"
},
  "geometry": {"coordinates":[-5.34143,35.06929],"type":"Point"}
}