{
  "type": "Feature",
  "properties": {
    "gn:admin1_code":"3.0",
    "gn:asciiname":"Oued Jdida",
    "gn:country_code":"MA",
    "gn:dem":525,
    "gn:feature_class":"P",
    "gn:feature_code":"PPL",
    "gn:name":"Oued Jdida",
    "gn:population":0,
    "gn:timezone":"Africa/Casablanca",
    "iso:country":"MA",
    "name:ara_x_preferred":[
        "\u0648\u0627\u062f \u0627\u0644\u062c\u062f\u064a\u062f\u0629"
    ],
    "name:cat_x_preferred":[
        "Oued Jdida"
    ],
    "name:ceb_x_preferred":[
        "Oued Jdida"
    ],
    "name:ita_x_preferred":[
        "Oued Jdida"
    ],
    "name:swe_x_preferred":[
        "Oued Jdida"
    ],
    "wof:name":"Oued Jdida",
    "wof:placetype":"locality"
},
  "geometry": {"coordinates":[-5.36643,33.92557],"type":"Point"}
}