{
  "type": "Feature",
  "properties": {
    "gn:admin1_code":"7.0",
    "gn:asciiname":"Douar Omar",
    "gn:country_code":"MA",
    "gn:dem":534,
    "gn:feature_class":"P",
    "gn:feature_code":"PPL",
    "gn:name":"Douar Omar",
    "gn:population":0,
    "gn:timezone":"Africa/Casablanca",
    "iso:country":"MA",
    "wof:name":"Douar Omar",
    "wof:placetype":"locality"
},
  "geometry": {"coordinates":[-8.03424,31.89371],"type":"Point"}
}