{
  "type": "Feature",
  "properties": {
    "gn:admin1_code":"08",
    "gn:asciiname":"Ait Abd el Fadit",
    "gn:country_code":"MA",
    "gn:dem":1850,
    "gn:feature_class":"P",
    "gn:feature_code":"PPL",
    "gn:name":"A\u00eft Abd el Fadit",
    "gn:population":0,
    "gn:timezone":"Africa/Casablanca",
    "iso:country":"MA",
    "name:und_x_variant":[
        "A\u00eft Abde el Fadel",
        "A\u00eft Abd el Fadit"
    ],
    "wof:name":"Ait Abd el Fadit",
    "wof:placetype":"locality"
},
  "geometry": {"coordinates":[-5.09862,32.42890999999999],"type":"Point"}
}