{
  "type": "Feature",
  "properties": {
    "gn:admin1_code":"7.0",
    "gn:asciiname":"Taguenntourt",
    "gn:country_code":"MA",
    "gn:dem":1430,
    "gn:feature_class":"P",
    "gn:feature_code":"PPL",
    "gn:name":"Taguenntourt",
    "gn:population":0,
    "gn:timezone":"Africa/Casablanca",
    "iso:country":"MA",
    "wof:name":"Taguenntourt",
    "wof:placetype":"locality"
},
  "geometry": {"coordinates":[-7.81103,31.27568],"type":"Point"}
}