{
  "type": "Feature",
  "properties": {
    "gn:admin1_code":"2.0",
    "gn:asciiname":"Oulad Saleh",
    "gn:country_code":"MA",
    "gn:dem":433,
    "gn:feature_class":"P",
    "gn:feature_code":"PPL",
    "gn:name":"Oulad Saleh",
    "gn:population":0,
    "gn:timezone":"Africa/Casablanca",
    "iso:country":"MA",
    "wof:name":"Oulad Saleh",
    "wof:placetype":"locality"
},
  "geometry": {"coordinates":[-1.94453,34.85847],"type":"Point"}
}