{
  "type": "Feature",
  "properties": {
    "gn:admin1_code":"6.0",
    "gn:asciiname":"Laatatra",
    "gn:country_code":"MA",
    "gn:dem":182,
    "gn:feature_class":"P",
    "gn:feature_code":"PPL",
    "gn:name":"Laatatra",
    "gn:population":0,
    "gn:timezone":"Africa/Casablanca",
    "iso:country":"MA",
    "wof:name":"Laatatra",
    "wof:placetype":"locality"
},
  "geometry": {"coordinates":[-8.4158,32.63041],"type":"Point"}
}