{
  "type": "Feature",
  "properties": {
    "gn:admin1_code":"7.0",
    "gn:asciiname":"Oulad 'Ali",
    "gn:country_code":"MA",
    "gn:dem":665,
    "gn:feature_class":"P",
    "gn:feature_code":"PPL",
    "gn:name":"Oulad \u2019Ali",
    "gn:population":0,
    "gn:timezone":"Africa/Casablanca",
    "iso:country":"MA",
    "wof:name":"Oulad 'Ali",
    "wof:placetype":"locality"
},
  "geometry": {"coordinates":[-7.30515,31.79814],"type":"Point"}
}