{
  "type": "Feature",
  "properties": {
    "gn:admin1_code":"09",
    "gn:asciiname":"Tamtalt",
    "gn:country_code":"MA",
    "gn:dem":1545,
    "gn:feature_class":"P",
    "gn:feature_code":"PPL",
    "gn:name":"Tamtalt",
    "gn:population":0,
    "gn:timezone":"Africa/Casablanca",
    "iso:country":"MA",
    "name:und_x_variant":[
        "Tamtelte",
        "Tamtelt",
        "Tamtalt"
    ],
    "wof:name":"Tamtalt",
    "wof:placetype":"locality"
},
  "geometry": {"coordinates":[-7.99694,30.24687],"type":"Point"}
}