{
  "type": "Feature",
  "properties": {
    "gn:admin1_code":"7.0",
    "gn:asciiname":"Id Boudrarene",
    "gn:country_code":"MA",
    "gn:dem":596,
    "gn:feature_class":"P",
    "gn:feature_code":"PPL",
    "gn:name":"Id Boudrarene",
    "gn:population":0,
    "gn:timezone":"Africa/Casablanca",
    "iso:country":"MA",
    "wof:name":"Id Boudrarene",
    "wof:placetype":"locality"
},
  "geometry": {"coordinates":[-9.65752,31.27507],"type":"Point"}
}