{
  "type": "Feature",
  "properties": {
    "gn:country":"MA",
    "gn:fcode":"ADM3",
    "gn:pop":13314,
    "iso:country":"MA",
    "name:ara_x_preferred":[
        "\u0644\u0639\u0643\u0627\u0643\u0634\u0629"
    ],
    "name:ara_x_variant":[
        "\u0627\u0644\u0639\u0627\u0645\u0631\u064a\u0629"
    ],
    "name:azb_x_preferred":[
        "\u0627\u0644\u0639\u0627\u0645\u0631\u06cc\u0647"
    ],
    "name:bul_x_preferred":[
        "\u041b\u0430\u043c\u0440\u0438\u0430"
    ],
    "name:cat_x_preferred":[
        "Laamria"
    ],
    "name:ceb_x_preferred":[
        "Laamria"
    ],
    "name:eng_x_preferred":[
        "Laamria"
    ],
    "name:fas_x_preferred":[
        "\u0627\u0644\u0639\u0627\u0645\u0631\u06cc\u0647"
    ],
    "name:fra_x_preferred":[
        "Laamria"
    ],
    "name:fra_x_variant":[
        "Laamria (CR)",
        "Laamria (Commune Rurale)"
    ],
    "name:ita_x_preferred":[
        "Laamria"
    ],
    "name:swe_x_preferred":[
        "Laamria"
    ],
    "name:urd_x_preferred":[
        "\u0644\u0627\u0645\u0631\u06cc\u0627"
    ],
    "qs:name":"Laamria",
    "qs:photos_9r":0,
    "qs:photos_sr":0,
    "qs:pop_sr":"6",
    "wd:wordcount":60,
    "wof:name":"Laamria",
    "wof:placetype":"localadmin",
    "wof:population":13314
},
  "geometry": {"coordinates":[-8.23631,32.82742],"type":"Point"}
}