{
  "type": "Feature",
  "properties": {
    "gn:country":"MA",
    "gn:fcode":"ADM3",
    "gn:pop":13314,
    "iso:country":"MA",
    "name:ara_x_preferred":[
        "\u0644\u0639\u0643\u0627\u0643\u0634\u0629"
    ],
    "name:fra_x_preferred":[
        "Laamria"
    ],
    "name:fra_x_variant":[
        "Laamria (CR)",
        "Laamria (Commune Rurale)"
    ],
    "qs:name":"Laamria",
    "qs:photos_9r":0,
    "qs:photos_sr":0,
    "qs:pop_sr":"6",
    "wd:wordcount":60,
    "wof:name":"Laamria",
    "wof:placetype":"localadmin",
    "wof:population":13314
},
  "geometry": {"coordinates":[-8.23631,32.82742],"type":"Point"}
}