{
  "type": "Feature",
  "properties": {
    "gn:admin1_code":"08",
    "gn:asciiname":"Timdras",
    "gn:country_code":"MA",
    "gn:dem":1951,
    "gn:feature_class":"P",
    "gn:feature_code":"PPL",
    "gn:name":"Timdras",
    "gn:population":0,
    "gn:timezone":"Africa/Casablanca",
    "iso:country":"MA",
    "name:und_x_variant":[
        "Timdghas",
        "Timedrhas",
        "Timdrhas",
        "Timdras"
    ],
    "wof:name":"Timdras",
    "wof:placetype":"locality"
},
  "geometry": {"coordinates":[-6.13601,30.95231],"type":"Point"}
}