{
  "type": "Feature",
  "properties": {
    "gn:country":"MA",
    "gn:fcode":"ADM3",
    "gn:pop":11076,
    "iso:country":"MA",
    "name:ara_x_preferred":[
        "\u0633\u064a\u062f\u064a \u0631\u0636\u0648\u0627\u0646"
    ],
    "name:fra_x_preferred":[
        "Oulad Nouel"
    ],
    "name:fra_x_variant":[
        "Oulad Nouel (CR)",
        "Oulad Nouel (Commune Rurale)"
    ],
    "qs:name":"Oulad Nouel",
    "qs:photos_9r":0,
    "qs:photos_sr":0,
    "qs:pop_sr":"6",
    "wd:wordcount":63,
    "wof:name":"Oulad Nouel",
    "wof:placetype":"localadmin",
    "wof:population":11076
},
  "geometry": {"coordinates":[-5.65774,34.49896],"type":"Point"}
}