{
  "type": "Feature",
  "properties": {
    "gn:admin1_code":"7.0",
    "gn:asciiname":"I'karine",
    "gn:country_code":"MA",
    "gn:dem":695,
    "gn:feature_class":"P",
    "gn:feature_code":"PPL",
    "gn:name":"I\u2019karine",
    "gn:population":0,
    "gn:timezone":"Africa/Casablanca",
    "iso:country":"MA",
    "wof:name":"I'karine",
    "wof:placetype":"locality"
},
  "geometry": {"coordinates":[-7.838,31.44654],"type":"Point"}
}