{
  "type": "Feature",
  "properties": {
    "gn:admin1_code":"2.0",
    "gn:asciiname":"Douar Lbekakra",
    "gn:country_code":"MA",
    "gn:dem":654,
    "gn:feature_class":"P",
    "gn:feature_code":"PPL",
    "gn:name":"Douar Lbekakra",
    "gn:population":0,
    "gn:timezone":"Africa/Casablanca",
    "iso:country":"MA",
    "wof:name":"Douar Lbekakra",
    "wof:placetype":"locality"
},
  "geometry": {"coordinates":[-2.00385,34.60704],"type":"Point"}
}