{
  "type": "Feature",
  "properties": {
    "gn:admin1_code":"3.0",
    "gn:asciiname":"Dar El Houssine Amantich",
    "gn:country_code":"MA",
    "gn:dem":1072,
    "gn:feature_class":"P",
    "gn:feature_code":"PPL",
    "gn:name":"Dar El Houssine Amantich",
    "gn:population":0,
    "gn:timezone":"Africa/Casablanca",
    "iso:country":"MA",
    "wof:name":"Dar El Houssine Amantich",
    "wof:placetype":"locality"
},
  "geometry": {"coordinates":[-5.27698,33.70335],"type":"Point"}
}