{
  "type": "Feature",
  "properties": {
    "gn:admin1_code":"07",
    "gn:asciiname":"Iguer n'Kouris",
    "gn:country_code":"MA",
    "gn:dem":1094,
    "gn:feature_class":"P",
    "gn:feature_code":"PPL",
    "gn:name":"Iguer n\u2019Kouris",
    "gn:population":0,
    "gn:timezone":"Africa/Casablanca",
    "iso:country":"MA",
    "wof:name":"Iguer n'Kouris",
    "wof:placetype":"locality"
},
  "geometry": {"coordinates":[-8.137,31.05111],"type":"Point"}
}