{
  "type": "Feature",
  "properties": {
    "gn:admin1_code":"02",
    "gn:asciiname":"Timguerdine",
    "gn:country_code":"MA",
    "gn:dem":1067,
    "gn:feature_class":"P",
    "gn:feature_code":"PPL",
    "gn:name":"Timguerdine",
    "gn:population":0,
    "gn:timezone":"Africa/Casablanca",
    "iso:country":"MA",
    "wof:name":"Timguerdine",
    "wof:placetype":"locality"
},
  "geometry": {"coordinates":[-3.66237,33.87410999999999],"type":"Point"}
}