{
  "type": "Feature",
  "properties": {
    "gn:admin1_code":"5.0",
    "gn:asciiname":"Adrar-n-Souq Aqdim",
    "gn:country_code":"MA",
    "gn:dem":1706,
    "gn:feature_class":"P",
    "gn:feature_code":"PPL",
    "gn:name":"Adrar-n-Souq Aqdim",
    "gn:population":0,
    "gn:timezone":"Africa/Casablanca",
    "iso:country":"MA",
    "wof:name":"Adrar-n-Souq Aqdim",
    "wof:placetype":"locality"
},
  "geometry": {"coordinates":[-6.48038,31.88836],"type":"Point"}
}