{
  "type": "Feature",
  "properties": {
    "gn:admin1_code":"7.0",
    "gn:asciiname":"Sidi El Arbi",
    "gn:country_code":"MA",
    "gn:dem":225,
    "gn:feature_class":"P",
    "gn:feature_code":"PPL",
    "gn:name":"Sidi El Arbi",
    "gn:population":0,
    "gn:timezone":"Africa/Casablanca",
    "iso:country":"MA",
    "wof:name":"Sidi El Arbi",
    "wof:placetype":"locality"
},
  "geometry": {"coordinates":[-8.66614,32.33705],"type":"Point"}
}