{
  "type": "Feature",
  "properties": {
    "gn:admin1_code":"7.0",
    "gn:asciiname":"Douar Ad-Dahra",
    "gn:country_code":"MA",
    "gn:dem":54,
    "gn:feature_class":"P",
    "gn:feature_code":"PPL",
    "gn:name":"Douar Ad-Dahra",
    "gn:population":0,
    "gn:timezone":"Africa/Casablanca",
    "iso:country":"MA",
    "wof:name":"Douar Ad-Dahra",
    "wof:placetype":"locality"
},
  "geometry": {"coordinates":[-9.32835,32.02496],"type":"Point"}
}