{
  "type": "Feature",
  "properties": {
    "gn:admin1_code":"07",
    "gn:asciiname":"Bou Zammour",
    "gn:country_code":"MA",
    "gn:dem":112,
    "gn:feature_class":"P",
    "gn:feature_code":"PPL",
    "gn:name":"Bou Zammour",
    "gn:population":0,
    "gn:timezone":"Africa/Casablanca",
    "iso:country":"MA",
    "name:und_x_variant":[
        "Bou Zemmour",
        "Bou Zammour"
    ],
    "wof:name":"Bou Zammour",
    "wof:placetype":"locality"
},
  "geometry": {"coordinates":[-9.71026,31.38862],"type":"Point"}
}