{
  "type": "Feature",
  "properties": {
    "gn:admin1_code":"7.0",
    "gn:asciiname":"Sidi Bouknadel",
    "gn:country_code":"MA",
    "gn:dem":542,
    "gn:feature_class":"P",
    "gn:feature_code":"PPL",
    "gn:name":"Sidi Bouknadel",
    "gn:population":0,
    "gn:timezone":"Africa/Casablanca",
    "iso:country":"MA",
    "wof:name":"Sidi Bouknadel",
    "wof:placetype":"locality"
},
  "geometry": {"coordinates":[-9.21318,31.72267],"type":"Point"}
}