{
  "type": "Feature",
  "properties": {
    "gn:admin1_code":"6.0",
    "gn:asciiname":"Douar Drarga",
    "gn:country_code":"MA",
    "gn:dem":186,
    "gn:feature_class":"P",
    "gn:feature_code":"PPL",
    "gn:name":"Douar Drarga",
    "gn:population":0,
    "gn:timezone":"Africa/Casablanca",
    "iso:country":"MA",
    "wof:name":"Douar Drarga",
    "wof:placetype":"locality"
},
  "geometry": {"coordinates":[-8.41064,32.66021],"type":"Point"}
}