{
  "type": "Feature",
  "properties": {
    "gn:admin1_code":"7.0",
    "gn:asciiname":"Douar Dhamna",
    "gn:country_code":"MA",
    "gn:dem":417,
    "gn:feature_class":"P",
    "gn:feature_code":"PPL",
    "gn:name":"Douar Dhamna",
    "gn:population":0,
    "gn:timezone":"Africa/Casablanca",
    "iso:country":"MA",
    "wof:name":"Douar Dhamna",
    "wof:placetype":"locality"
},
  "geometry": {"coordinates":[-8.75967,32.10835],"type":"Point"}
}