{
  "type": "Feature",
  "properties": {
    "gn:admin1_code":"07",
    "gn:asciiname":"Angoukht",
    "gn:country_code":"MA",
    "gn:dem":1811,
    "gn:feature_class":"P",
    "gn:feature_code":"PPL",
    "gn:name":"Angoukht",
    "gn:population":0,
    "gn:timezone":"Africa/Casablanca",
    "iso:country":"MA",
    "name:und_x_variant":[
        "Angourt",
        "Angoukot"
    ],
    "wof:name":"Angoukht",
    "wof:placetype":"locality"
},
  "geometry": {"coordinates":[-8.534,30.99629],"type":"Point"}
}