{
  "type": "Feature",
  "properties": {
    "gn:admin1_code":"03",
    "gn:asciiname":"Oulad Ayad",
    "gn:country_code":"MA",
    "gn:dem":323,
    "gn:feature_class":"P",
    "gn:feature_code":"PPLL",
    "gn:name":"Oulad Ayad",
    "gn:population":0,
    "gn:timezone":"Africa/Casablanca",
    "iso:country":"MA",
    "name:und_x_variant":[
        "Oulad Aiyad"
    ],
    "wof:name":"Oulad Ayad",
    "wof:placetype":"locality"
},
  "geometry": {"coordinates":[-4.61159,34.08017],"type":"Point"}
}