{
  "type": "Feature",
  "properties": {
    "gn:admin1_code":"03",
    "gn:asciiname":"Oulad Ayad",
    "gn:country_code":"MA",
    "gn:dem":323,
    "gn:feature_class":"P",
    "gn:feature_code":"PPLL",
    "gn:name":"Oulad Ayad",
    "gn:population":0,
    "gn:timezone":"Africa/Casablanca",
    "iso:country":"MA",
    "name:ara_x_preferred":[
        "\u0623\u0648\u0644\u0627\u062f \u0639\u064a\u0627\u062f"
    ],
    "name:azb_x_preferred":[
        "\u0627\u0648\u0644\u0627\u062f \u0639\u06cc\u0627\u062f"
    ],
    "name:cat_x_preferred":[
        "Oulad Ayad"
    ],
    "name:fas_x_preferred":[
        "\u0627\u0648\u0644\u0627\u062f \u0639\u06cc\u0627\u062f"
    ],
    "name:fra_x_preferred":[
        "Oulad Ayad"
    ],
    "name:ita_x_preferred":[
        "Oulad Ayad"
    ],
    "name:und_x_variant":[
        "Oulad Aiyad"
    ],
    "wof:name":"Oulad Ayad",
    "wof:placetype":"locality"
},
  "geometry": {"coordinates":[-4.61159,34.08017],"type":"Point"}
}