{
  "type": "Feature",
  "properties": {
    "gn:admin1_code":"5.0",
    "gn:asciiname":"Ait Wabout",
    "gn:country_code":"MA",
    "gn:dem":803,
    "gn:feature_class":"P",
    "gn:feature_code":"PPL",
    "gn:name":"Ait Wabout",
    "gn:population":0,
    "gn:timezone":"Africa/Casablanca",
    "iso:country":"MA",
    "wof:name":"Ait Wabout",
    "wof:placetype":"locality"
},
  "geometry": {"coordinates":[-7.19128,31.72605],"type":"Point"}
}