{
  "type": "Feature",
  "properties": {
    "gn:country":"MA",
    "gn:fcode":"ADM3",
    "gn:population":11283,
    "iso:country":"MA",
    "name:ara_x_preferred":[
        "\u0639\u064a\u0646 \u062a\u0645\u0643\u0646\u0627\u064a"
    ],
    "name:fra_x_preferred":[
        "Louadaine"
    ],
    "name:fra_x_variant":[
        "Louadaine (CR)",
        "Louadaine (Commune Rurale)"
    ],
    "qs:name":"Louadaine",
    "qs:photos_9r":0,
    "qs:photos_sr":0,
    "qs:pop_sr":"6",
    "wof:name":"Louadaine",
    "wof:placetype":"localadmin",
    "wof:population":11283
},
  "geometry": {"coordinates":[-4.92071,34.22478],"type":"Point"}
}