{
  "type": "Feature",
  "properties": {
    "gn:admin1_code":"09",
    "gn:asciiname":"Bou Kdir",
    "gn:country_code":"MA",
    "gn:dem":1197,
    "gn:feature_class":"P",
    "gn:feature_code":"PPL",
    "gn:name":"Bou Kdir",
    "gn:population":0,
    "gn:timezone":"Africa/Casablanca",
    "iso:country":"MA",
    "name:und_x_variant":[
        "Ouled Boukdir",
        "Bou Kdir"
    ],
    "wof:name":"Bou Kdir",
    "wof:placetype":"locality"
},
  "geometry": {"coordinates":[-6.85,30.11],"type":"Point"}
}