{
  "type": "Feature",
  "properties": {
    "gn:admin1_code":"7.0",
    "gn:asciiname":"Bizourane",
    "gn:country_code":"MA",
    "gn:dem":1279,
    "gn:feature_class":"P",
    "gn:feature_code":"PPL",
    "gn:name":"Bizourane",
    "gn:population":0,
    "gn:timezone":"Africa/Casablanca",
    "iso:country":"MA",
    "wof:name":"Bizourane",
    "wof:placetype":"locality"
},
  "geometry": {"coordinates":[-9.00263,31.0897],"type":"Point"}
}