{
  "type": "Feature",
  "properties": {
    "gn:admin1_code":"04",
    "gn:asciiname":"Anabsa el Hadaj",
    "gn:country_code":"MA",
    "gn:dem":14,
    "gn:feature_class":"P",
    "gn:feature_code":"PPL",
    "gn:name":"Anabsa el Hadaj",
    "gn:population":0,
    "gn:timezone":"Africa/Casablanca",
    "iso:country":"MA",
    "name:und_x_variant":[
        "El ma\u00e2rif dahr el hdaj",
        "Anasba-el-Hadaj",
        "Anabsa el Hadaj"
    ],
    "wof:name":"Anabsa el Hadaj",
    "wof:placetype":"locality"
},
  "geometry": {"coordinates":[-6.12271,34.84887],"type":"Point"}
}