{
  "type": "Feature",
  "properties": {
    "gn:admin1_code":"6.0",
    "gn:asciiname":"Douar Sidi Ahmed",
    "gn:country_code":"MA",
    "gn:dem":75,
    "gn:feature_class":"P",
    "gn:feature_code":"PPL",
    "gn:name":"Douar Sidi Ahmed",
    "gn:population":0,
    "gn:timezone":"Africa/Casablanca",
    "iso:country":"MA",
    "wof:name":"Douar Sidi Ahmed",
    "wof:placetype":"locality"
},
  "geometry": {"coordinates":[-8.70714,32.91298],"type":"Point"}
}