{
  "type": "Feature",
  "properties": {
    "gn:admin1_code":"09",
    "gn:asciiname":"Assif El Hjad",
    "gn:country_code":"MA",
    "gn:dem":712,
    "gn:feature_class":"P",
    "gn:feature_code":"PPL",
    "gn:name":"Assif El Hjad",
    "gn:population":0,
    "gn:timezone":"Africa/Casablanca",
    "iso:country":"MA",
    "name:und_x_variant":[
        "Assif el Hard",
        "Assif el Had",
        "Assif El Hjad"
    ],
    "wof:name":"Assif El Hjad",
    "wof:placetype":"locality"
},
  "geometry": {"coordinates":[-9.48021,30.74579],"type":"Point"}
}