{
  "type": "Feature",
  "properties": {
    "gn:admin1_code":"10.0",
    "gn:asciiname":"Tousdine",
    "gn:country_code":"MA",
    "gn:dem":884,
    "gn:feature_class":"P",
    "gn:feature_code":"PPL",
    "gn:name":"Tousdine",
    "gn:population":0,
    "gn:timezone":"Africa/Casablanca",
    "iso:country":"MA",
    "wof:name":"Tousdine",
    "wof:placetype":"locality"
},
  "geometry": {"coordinates":[-9.80039,29.29826],"type":"Point"}
}