{
  "type": "Feature",
  "properties": {
    "gn:admin1_code":"4.0",
    "gn:asciiname":"Obidib",
    "gn:country_code":"MA",
    "gn:dem":144,
    "gn:feature_class":"P",
    "gn:feature_code":"PPL",
    "gn:name":"Obidib",
    "gn:population":0,
    "gn:timezone":"Africa/Casablanca",
    "iso:country":"MA",
    "wof:name":"Obidib",
    "wof:placetype":"locality"
},
  "geometry": {"coordinates":[-7.02159,33.77605],"type":"Point"}
}