{
  "type": "Feature",
  "properties": {
    "gn:admin1_code":"09",
    "gn:asciiname":"Agoujgal",
    "gn:country_code":"MA",
    "gn:dem":1205,
    "gn:feature_class":"P",
    "gn:feature_code":"PPL",
    "gn:name":"Agoujgal",
    "gn:population":0,
    "gn:timezone":"Africa/Casablanca",
    "iso:country":"MA",
    "name:und_x_variant":[
        "Aguejgal",
        "Agoujgal"
    ],
    "wof:name":"Agoujgal",
    "wof:placetype":"locality"
},
  "geometry": {"coordinates":[-9.03494,29.41577],"type":"Point"}
}