{
  "type": "Feature",
  "properties": {
    "gn:admin1_code":"03",
    "gn:asciiname":"Issidane",
    "gn:country_code":"MA",
    "gn:dem":1066,
    "gn:feature_class":"P",
    "gn:feature_code":"PPL",
    "gn:name":"Issidane",
    "gn:population":0,
    "gn:timezone":"Africa/Casablanca",
    "iso:country":"MA",
    "name:und_x_variant":[
        "Douar Issidane",
        "Issidane"
    ],
    "wof:name":"Issidane",
    "wof:placetype":"locality"
},
  "geometry": {"coordinates":[-3.95249,34.06559],"type":"Point"}
}