{
  "type": "Feature",
  "properties": {
    "gn:admin1_code":"7.0",
    "gn:asciiname":"Douar Lemsakna",
    "gn:country_code":"MA",
    "gn:dem":222,
    "gn:feature_class":"P",
    "gn:feature_code":"PPL",
    "gn:name":"Douar Lemsakna",
    "gn:population":0,
    "gn:timezone":"Africa/Casablanca",
    "iso:country":"MA",
    "wof:name":"Douar Lemsakna",
    "wof:placetype":"locality"
},
  "geometry": {"coordinates":[-9.05415,31.75863],"type":"Point"}
}