{
  "type": "Feature",
  "properties": {
    "gn:admin1_code":"03",
    "gn:asciiname":"Boudra'",
    "gn:country_code":"MA",
    "gn:dem":1423,
    "gn:feature_class":"P",
    "gn:feature_code":"PPL",
    "gn:name":"Boudra\u2019",
    "gn:population":0,
    "gn:timezone":"Africa/Casablanca",
    "iso:country":"MA",
    "name:und_x_variant":[
        "Boudra\u2019",
        "Bou Dra"
    ],
    "wof:name":"Boudra'",
    "wof:placetype":"locality"
},
  "geometry": {"coordinates":[-5.36622,33.26449],"type":"Point"}
}