{
  "type": "Feature",
  "properties": {
    "gn:admin1_code":"09",
    "gn:asciiname":"Timichcha",
    "gn:country_code":"MA",
    "gn:dem":1759,
    "gn:feature_class":"P",
    "gn:feature_code":"PPL",
    "gn:name":"Timichcha",
    "gn:population":0,
    "gn:timezone":"Africa/Casablanca",
    "iso:country":"MA",
    "name:und_x_variant":[
        "Tmichcha",
        "Timicha",
        "Timichcha"
    ],
    "wof:name":"Timichcha",
    "wof:placetype":"locality"
},
  "geometry": {"coordinates":[-8.45247,30.10575],"type":"Point"}
}