{
  "type": "Feature",
  "properties": {
    "gn:admin1_code":"09",
    "gn:asciiname":"Taourirt",
    "gn:country_code":"MA",
    "gn:dem":659,
    "gn:feature_class":"P",
    "gn:feature_code":"PPL",
    "gn:name":"Taourirt",
    "gn:population":0,
    "gn:timezone":"Africa/Casablanca",
    "iso:country":"MA",
    "name:ceb_x_preferred":[
        "Taourirt"
    ],
    "name:fra_x_preferred":[
        "Taourirt"
    ],
    "name:nld_x_preferred":[
        "Taourirt"
    ],
    "name:pol_x_preferred":[
        "Taurirt"
    ],
    "name:swe_x_preferred":[
        "Taourirt"
    ],
    "wof:name":"Taourirt",
    "wof:placetype":"locality"
},
  "geometry": {"coordinates":[-7.99386,29.72914],"type":"Point"}
}