{
  "type": "Feature",
  "properties": {
    "gn:admin1_code":"08",
    "gn:asciiname":"Ksebt Ait Hamed Ben Ali",
    "gn:country_code":"MA",
    "gn:dem":790,
    "gn:feature_class":"P",
    "gn:feature_code":"PPL",
    "gn:name":"Ksebt A\u00eft Hamed Ben Ali",
    "gn:population":0,
    "gn:timezone":"Africa/Casablanca",
    "iso:country":"MA",
    "name:und_x_variant":[
        "Kasbat ouled ahmed ben ali",
        "Ksebt el Kaaba",
        "Ksebt A\u00eft Hamed Ben Ali"
    ],
    "wof:name":"Ksebt Ait Hamed Ben Ali",
    "wof:placetype":"locality"
},
  "geometry": {"coordinates":[-6.0313,30.46905],"type":"Point"}
}