{
  "type": "Feature",
  "properties": {
    "gn:admin1_code":"02",
    "gn:asciiname":"Douar Sidi Mou",
    "gn:country_code":"MA",
    "gn:dem":758,
    "gn:feature_class":"P",
    "gn:feature_code":"PPL",
    "gn:name":"Douar Sidi Mou",
    "gn:population":0,
    "gn:timezone":"Africa/Casablanca",
    "iso:country":"MA",
    "name:und_x_variant":[
        "Sidi Mou"
    ],
    "wof:name":"Douar Sidi Mou",
    "wof:placetype":"locality"
},
  "geometry": {"coordinates":[-3.8302,33.96112],"type":"Point"}
}