{
  "type": "Feature",
  "properties": {
    "gn:admin1_code":"1.0",
    "gn:asciiname":"Ben Slimane",
    "gn:country_code":"MA",
    "gn:dem":418,
    "gn:feature_class":"P",
    "gn:feature_code":"PPL",
    "gn:name":"Ben Slimane",
    "gn:population":0,
    "gn:timezone":"Africa/Casablanca",
    "iso:country":"MA",
    "wof:name":"Ben Slimane",
    "wof:placetype":"locality"
},
  "geometry": {"coordinates":[-5.5525,35.13504],"type":"Point"}
}