{
  "type": "Feature",
  "properties": {
    "gn:country":"MA",
    "gn:fcode":"ADM3",
    "gn:population":12924,
    "iso:country":"MA",
    "name:ara_x_preferred":[
        "\u0627\u0644\u0635\u0647\u0631\u064a\u062c"
    ],
    "name:ara_x_variant":[
        "\u0628\u0648\u064a\u0627 \u0639\u0645\u0631"
    ],
    "name:ary_x_preferred":[
        "\u0628\u0648\u064a\u0627 \u0639\u0645\u0631"
    ],
    "name:azb_x_preferred":[
        "\u0628\u0648\u06cc\u0627 \u0639\u0645\u0631"
    ],
    "name:cat_x_preferred":[
        "Bouya Omar"
    ],
    "name:ceb_x_preferred":[
        "Bouya Omar"
    ],
    "name:eng_x_preferred":[
        "Bouya Omar"
    ],
    "name:fas_x_preferred":[
        "\u0628\u0648\u06cc\u0627 \u0639\u0645\u0631"
    ],
    "name:fra_x_preferred":[
        "Bouya Omar"
    ],
    "name:fra_x_variant":[
        "Bouya Omar (CR)",
        "Bouya Omar (Commune Rurale)"
    ],
    "name:ita_x_preferred":[
        "Bouya Omar"
    ],
    "name:swe_x_preferred":[
        "Bouya Omar"
    ],
    "qs:name":"Bouya Omar",
    "qs:photos_9r":0,
    "qs:photos_sr":0,
    "qs:pop_sr":"6",
    "wd:wordcount":65,
    "wof:name":"Bouya Omar",
    "wof:placetype":"localadmin",
    "wof:population":12924
},
  "geometry": {"coordinates":[-7.21373,31.7794],"type":"Point"}
}