{
  "type": "Feature",
  "properties": {
    "gn:admin1_code":"6.0",
    "gn:asciiname":"Soualha",
    "gn:country_code":"MA",
    "gn:dem":506,
    "gn:feature_class":"P",
    "gn:feature_code":"PPL",
    "gn:name":"Soualha",
    "gn:population":0,
    "gn:timezone":"Africa/Casablanca",
    "iso:country":"MA",
    "wof:name":"Soualha",
    "wof:placetype":"locality"
},
  "geometry": {"coordinates":[-7.14844,32.56295],"type":"Point"}
}