{
  "type": "Feature",
  "properties": {
    "gn:admin1_code":"3.0",
    "gn:asciiname":"Lqachla",
    "gn:country_code":"MA",
    "gn:dem":735,
    "gn:feature_class":"P",
    "gn:feature_code":"PPL",
    "gn:name":"Lqachla",
    "gn:population":0,
    "gn:timezone":"Africa/Casablanca",
    "iso:country":"MA",
    "wof:name":"Lqachla",
    "wof:placetype":"locality"
},
  "geometry": {"coordinates":[-5.65781,33.71550999999999],"type":"Point"}
}