{
  "type": "Feature",
  "properties": {
    "gn:admin1_code":"7.0",
    "gn:asciiname":"Taougjgalt",
    "gn:country_code":"MA",
    "gn:dem":589,
    "gn:feature_class":"P",
    "gn:feature_code":"PPL",
    "gn:name":"Taougjgalt",
    "gn:population":0,
    "gn:timezone":"Africa/Casablanca",
    "iso:country":"MA",
    "wof:name":"Taougjgalt",
    "wof:placetype":"locality"
},
  "geometry": {"coordinates":[-9.52115,30.94648],"type":"Point"}
}