{
  "type": "Feature",
  "properties": {
    "gn:admin1_code":"5.0",
    "gn:asciiname":"Taliwine",
    "gn:country_code":"MA",
    "gn:dem":2013,
    "gn:feature_class":"P",
    "gn:feature_code":"PPL",
    "gn:name":"Taliwine",
    "gn:population":0,
    "gn:timezone":"Africa/Casablanca",
    "iso:country":"MA",
    "wof:name":"Taliwine",
    "wof:placetype":"locality"
},
  "geometry": {"coordinates":[-6.34695,31.83073],"type":"Point"}
}