{
  "type": "Feature",
  "properties": {
    "gn:admin1_code":"9.0",
    "gn:asciiname":"Id Bitirgane",
    "gn:country_code":"MA",
    "gn:dem":671,
    "gn:feature_class":"P",
    "gn:feature_code":"PPL",
    "gn:name":"Id Bitirgane",
    "gn:population":0,
    "gn:timezone":"Africa/Casablanca",
    "iso:country":"MA",
    "wof:name":"Id Bitirgane",
    "wof:placetype":"locality"
},
  "geometry": {"coordinates":[-9.84862,29.44983],"type":"Point"}
}