{
  "type": "Feature",
  "properties": {
    "gn:admin1_code":"07",
    "gn:asciiname":"Douar Jbourat",
    "gn:country_code":"MA",
    "gn:dem":417,
    "gn:feature_class":"P",
    "gn:feature_code":"PPL",
    "gn:name":"Douar Jbourat",
    "gn:population":0,
    "gn:timezone":"Africa/Casablanca",
    "iso:country":"MA",
    "name:und_x_variant":[
        "Douar Jebourat",
        "Douar Djebourat",
        "Jebourat",
        "Douar Jbourat"
    ],
    "wof:name":"Douar Jbourat",
    "wof:placetype":"locality"
},
  "geometry": {"coordinates":[-8.58105,32.14248],"type":"Point"}
}