{
  "type": "Feature",
  "properties": {
    "gn:admin1_code":"07",
    "gn:asciiname":"Douar Erroucha",
    "gn:country_code":"MA",
    "gn:dem":602,
    "gn:feature_class":"P",
    "gn:feature_code":"PPL",
    "gn:name":"Douar Erroucha",
    "gn:population":0,
    "gn:timezone":"Africa/Casablanca",
    "iso:country":"MA",
    "name:und_x_variant":[
        "Roha",
        "Rocha",
        "Douar Erroucha"
    ],
    "wof:name":"Douar Erroucha",
    "wof:placetype":"locality"
},
  "geometry": {"coordinates":[-7.50462,31.76196],"type":"Point"}
}