{
  "type": "Feature",
  "properties": {
    "gn:admin1_code":"09",
    "gn:asciiname":"Agni Hrach",
    "gn:country_code":"MA",
    "gn:dem":944,
    "gn:feature_class":"P",
    "gn:feature_code":"PPL",
    "gn:name":"Agni Hrach",
    "gn:population":0,
    "gn:timezone":"Africa/Casablanca",
    "iso:country":"MA",
    "name:und_x_variant":[
        "Agouni Areuch",
        "Agouni Ihrichen",
        "Agouni Arech",
        "Agni Hrach"
    ],
    "wof:name":"Agni Hrach",
    "wof:placetype":"locality"
},
  "geometry": {"coordinates":[-9.15881,29.6309],"type":"Point"}
}