{
  "type": "Feature",
  "properties": {
    "gn:admin1_code":"6.0",
    "gn:asciiname":"Dar Haj Ahmed",
    "gn:country_code":"MA",
    "gn:dem":241,
    "gn:feature_class":"P",
    "gn:feature_code":"PPL",
    "gn:name":"Dar Haj Ahmed",
    "gn:population":0,
    "gn:timezone":"Africa/Casablanca",
    "iso:country":"MA",
    "wof:name":"Dar Haj Ahmed",
    "wof:placetype":"locality"
},
  "geometry": {"coordinates":[-7.79378,33.1423],"type":"Point"}
}