{
  "type": "Feature",
  "properties": {
    "gn:admin1_code":"09",
    "gn:asciiname":"Imniy",
    "gn:country_code":"MA",
    "gn:dem":1770,
    "gn:feature_class":"P",
    "gn:feature_code":"PPL",
    "gn:name":"Imniy",
    "gn:population":0,
    "gn:timezone":"Africa/Casablanca",
    "iso:country":"MA",
    "name:und_x_variant":[
        "Imni"
    ],
    "wof:name":"Imniy",
    "wof:placetype":"locality"
},
  "geometry": {"coordinates":[-8.4105,30.1349],"type":"Point"}
}