{
  "type": "Feature",
  "properties": {
    "gn:admin1_code":"03",
    "gn:asciiname":"Ain Lorma",
    "gn:country_code":"MA",
    "gn:dem":482,
    "gn:feature_class":"P",
    "gn:feature_code":"PPL",
    "gn:name":"A\u00efn Lorma",
    "gn:population":0,
    "gn:timezone":"Africa/Casablanca",
    "iso:country":"MA",
    "name:und_x_variant":[
        "A\u00eft Orma",
        "A\u00efn el Orma",
        "A\u00efn Lorma"
    ],
    "wof:name":"Ain Lorma",
    "wof:placetype":"locality"
},
  "geometry": {"coordinates":[-5.74723,33.89349],"type":"Point"}
}