{
  "type": "Feature",
  "properties": {
    "gn:admin1_code":"07",
    "gn:asciiname":"Igriffoudn",
    "gn:country_code":"MA",
    "gn:dem":1126,
    "gn:feature_class":"P",
    "gn:feature_code":"PPL",
    "gn:name":"Igriffoudn",
    "gn:population":0,
    "gn:timezone":"Africa/Casablanca",
    "iso:country":"MA",
    "name:und_x_variant":[
        "Igrif Foud\u00e8n",
        "Igri Foudene",
        "Igrif Foudene",
        "Igriffoudn"
    ],
    "wof:name":"Igriffoudn",
    "wof:placetype":"locality"
},
  "geometry": {"coordinates":[-7.71654,31.29485],"type":"Point"}
}