{
  "type": "Feature",
  "properties": {
    "gn:admin1_code":"6.0",
    "gn:asciiname":"Douar Lebrakta Ain Rabeh",
    "gn:country_code":"MA",
    "gn:dem":647,
    "gn:feature_class":"P",
    "gn:feature_code":"PPL",
    "gn:name":"Douar Lebrakta Ain Rabeh",
    "gn:population":0,
    "gn:timezone":"Africa/Casablanca",
    "iso:country":"MA",
    "wof:name":"Douar Lebrakta Ain Rabeh",
    "wof:placetype":"locality"
},
  "geometry": {"coordinates":[-7.29164,33.02202],"type":"Point"}
}