{
  "type": "Feature",
  "properties": {
    "gn:admin1_code":"08",
    "gn:asciiname":"Ait Melk",
    "gn:country_code":"MA",
    "gn:dem":917,
    "gn:feature_class":"P",
    "gn:feature_code":"PPL",
    "gn:name":"A\u00eft Melk",
    "gn:population":0,
    "gn:timezone":"Africa/Casablanca",
    "iso:country":"MA",
    "name:und_x_variant":[
        "A\u00eft Melkt",
        "A\u00eft Melk"
    ],
    "wof:name":"Ait Melk",
    "wof:placetype":"locality"
},
  "geometry": {"coordinates":[-6.25528,30.70793],"type":"Point"}
}