{
  "type": "Feature",
  "properties": {
    "gn:admin1_code":"8.0",
    "gn:asciiname":"Mjarcha",
    "gn:country_code":"MA",
    "gn:dem":770,
    "gn:feature_class":"P",
    "gn:feature_code":"PPL",
    "gn:name":"Mjarcha",
    "gn:population":0,
    "gn:timezone":"Africa/Casablanca",
    "iso:country":"MA",
    "wof:name":"Mjarcha",
    "wof:placetype":"locality"
},
  "geometry": {"coordinates":[-4.30424,31.31184],"type":"Point"}
}