{
  "type": "Feature",
  "properties": {
    "gn:admin1_code":"1.0",
    "gn:asciiname":"Douar Bni Chiker",
    "gn:country_code":"MA",
    "gn:dem":397,
    "gn:feature_class":"P",
    "gn:feature_code":"PPL",
    "gn:name":"Douar Bni Chiker",
    "gn:population":0,
    "gn:timezone":"Africa/Casablanca",
    "iso:country":"MA",
    "wof:name":"Douar Bni Chiker",
    "wof:placetype":"locality"
},
  "geometry": {"coordinates":[-4.22333,35.05192],"type":"Point"}
}