{
  "type": "Feature",
  "properties": {
    "gn:admin1_code":"03",
    "gn:asciiname":"Douar Ait Said Ou Moussa",
    "gn:country_code":"MA",
    "gn:dem":700,
    "gn:feature_class":"P",
    "gn:feature_code":"PPL",
    "gn:name":"Douar Ait Said Ou Moussa",
    "gn:population":0,
    "gn:timezone":"Africa/Casablanca",
    "iso:country":"MA",
    "wof:name":"Douar Ait Said Ou Moussa",
    "wof:placetype":"locality"
},
  "geometry": {"coordinates":[-5.61899,33.7412],"type":"Point"}
}