{
  "type": "Feature",
  "properties": {
    "gn:admin1_code":"1.0",
    "gn:asciiname":"Douar Errochah",
    "gn:country_code":"MA",
    "gn:dem":370,
    "gn:feature_class":"P",
    "gn:feature_code":"PPL",
    "gn:name":"Douar Errochah",
    "gn:population":0,
    "gn:timezone":"Africa/Casablanca",
    "iso:country":"MA",
    "wof:name":"Douar Errochah",
    "wof:placetype":"locality"
},
  "geometry": {"coordinates":[-5.5958,35.53129000000001],"type":"Point"}
}