{
  "type": "Feature",
  "properties": {
    "iso:country":"MA",
    "name:ara_x_preferred":[
        "\u0628\u0646 \u0633\u0644\u064a\u0645\u0627\u0646"
    ],
    "name:cat_x_preferred":[
        "Benslimane"
    ],
    "name:chi_x_preferred":[
        "\u672c\u8607\u840a\u66fc"
    ],
    "name:cym_x_preferred":[
        "Ben Slimane"
    ],
    "name:deu_x_preferred":[
        "Benslimane"
    ],
    "name:dut_x_preferred":[
        "Ben Slimane"
    ],
    "name:eng_x_preferred":[
        "Ben Slimane"
    ],
    "name:fra_x_preferred":[
        "Benslimane"
    ],
    "name:fre_x_preferred":[
        "Ben Slimane"
    ],
    "name:ger_x_preferred":[
        "Ben Slimane"
    ],
    "name:ita_x_preferred":[
        "Ben Slimane"
    ],
    "name:jpn_x_preferred":[
        "\u30d9\u30f3\u30fb\u30b9\u30ea\u30de\u30f3"
    ],
    "name:nld_x_preferred":[
        "Benslimane"
    ],
    "name:por_x_preferred":[
        "Benslimane"
    ],
    "name:rus_x_preferred":[
        "\u0411\u0435\u043d-\u0421\u043b\u0438\u043c\u0430\u043d"
    ],
    "name:spa_x_preferred":[
        "Provincia de Benslimane"
    ],
    "name:swe_x_preferred":[
        "Benslimane"
    ],
    "name:unk_x_variant":[
        "Bouhault"
    ],
    "name:urd_x_preferred":[
        "\u0628\u0646 \u0633\u0644\u06cc\u0645\u0627\u0646"
    ],
    "name:wel_x_preferred":[
        "Ben Slimane"
    ],
    "name:zho_x_preferred":[
        "\u672c\u8607\u840a\u66fc"
    ],
    "qs:gn_country":"MA",
    "qs:gn_fcode":"PPL",
    "qs:gn_pop":0,
    "qs:name":"Ben Sliman",
    "qs:name_adm0":"\u0627\u0644\u0645\u063a\u0631\u0628",
    "qs:name_adm1":"\u0627\u0644\u0634\u0627\u0648\u064a\u0629",
    "qs:photos":51,
    "qs:photos_1k":10,
    "qs:photos_9k":1,
    "qs:photos_9r":2,
    "qs:photos_all":51,
    "qs:photos_sr":2,
    "qs:placetype":"Town",
    "qs:pop_sr":"7",
    "qs:woe_adm0":23424893,
    "wd:wordcount":99,
    "wof:name":"Ben Sliman",
    "wof:placetype":"locality"
},
  "geometry": {"coordinates":[-7.12079,33.61297],"type":"Point"}
}