{
  "type": "Feature",
  "properties": {
    "gn:admin1_code":"7.0",
    "gn:asciiname":"Znazene",
    "gn:country_code":"MA",
    "gn:dem":419,
    "gn:feature_class":"P",
    "gn:feature_code":"PPL",
    "gn:name":"Znazene",
    "gn:population":0,
    "gn:timezone":"Africa/Casablanca",
    "iso:country":"MA",
    "wof:name":"Znazene",
    "wof:placetype":"locality"
},
  "geometry": {"coordinates":[-9.04063,31.97873],"type":"Point"}
}