{
  "type": "Feature",
  "properties": {
    "gn:admin1_code":"03",
    "gn:asciiname":"Archidyene",
    "gn:country_code":"MA",
    "gn:dem":1234,
    "gn:feature_class":"P",
    "gn:feature_code":"PPL",
    "gn:name":"Archidyene",
    "gn:population":0,
    "gn:timezone":"Africa/Casablanca",
    "iso:country":"MA",
    "name:und_x_variant":[
        "Archidiene"
    ],
    "wof:name":"Archidyene",
    "wof:placetype":"locality"
},
  "geometry": {"coordinates":[-3.77523,34.61176],"type":"Point"}
}