{
  "type": "Feature",
  "properties": {
    "gn:admin1_code":"6.0",
    "gn:asciiname":"Dar Sidi Allal",
    "gn:country_code":"MA",
    "gn:dem":135,
    "gn:feature_class":"P",
    "gn:feature_code":"PPL",
    "gn:name":"Dar Sidi Allal",
    "gn:population":0,
    "gn:timezone":"Africa/Casablanca",
    "iso:country":"MA",
    "wof:name":"Dar Sidi Allal",
    "wof:placetype":"neighbourhood"
},
  "geometry": {"coordinates":[-8.51342,32.87721],"type":"Point"}
}