{
  "type": "Feature",
  "properties": {
    "gn:admin1_code":"1.0",
    "gn:asciiname":"Barriqch",
    "gn:country_code":"MA",
    "gn:dem":40,
    "gn:feature_class":"P",
    "gn:feature_code":"PPL",
    "gn:name":"Barriqch",
    "gn:population":0,
    "gn:timezone":"Africa/Casablanca",
    "iso:country":"MA",
    "wof:name":"Barriqch",
    "wof:placetype":"locality"
},
  "geometry": {"coordinates":[-4.80318,35.24795],"type":"Point"}
}