{
  "type": "Feature",
  "properties": {
    "gn:admin1_code":"08",
    "gn:asciiname":"Taddi",
    "gn:country_code":"MA",
    "gn:dem":1688,
    "gn:feature_class":"P",
    "gn:feature_code":"PPL",
    "gn:name":"Taddi",
    "gn:population":0,
    "gn:timezone":"Africa/Casablanca",
    "iso:country":"MA",
    "wof:name":"Taddi",
    "wof:placetype":"locality"
},
  "geometry": {"coordinates":[-5.64485,31.26928],"type":"Point"}
}