{
  "type": "Feature",
  "properties": {
    "gn:admin1_code":"01",
    "gn:asciiname":"Boughamboub",
    "gn:country_code":"MA",
    "gn:dem":290,
    "gn:feature_class":"P",
    "gn:feature_code":"PPL",
    "gn:name":"Bo\u00fbghambo\u00fbb",
    "gn:population":0,
    "gn:timezone":"Africa/Casablanca",
    "iso:country":"MA",
    "name:und_x_variant":[
        "Bo\u00fbrhambo\u00fbb",
        "Bouchamboub",
        "Bo\u00fbghambo\u00fbb"
    ],
    "wof:name":"Boughamboub",
    "wof:placetype":"locality"
},
  "geometry": {"coordinates":[-4.18696,35.13982],"type":"Point"}
}