{
  "type": "Feature",
  "properties": {
    "gn:admin1_code":"04",
    "gn:asciiname":"Douar Oulad Hlal",
    "gn:country_code":"MA",
    "gn:dem":88,
    "gn:feature_class":"P",
    "gn:feature_code":"PPL",
    "gn:name":"Douar Oulad Hlal",
    "gn:population":0,
    "gn:timezone":"Africa/Casablanca",
    "iso:country":"MA",
    "name:und_x_variant":[
        "Ouled Allal",
        "Oulad Allal",
        "Douar Oulad Allal",
        "Douar Oulad Hlal"
    ],
    "wof:name":"Douar Oulad Hlal",
    "wof:placetype":"locality"
},
  "geometry": {"coordinates":[-5.85553,34.69206],"type":"Point"}
}