{
  "type": "Feature",
  "properties": {
    "gn:admin1_code":"02",
    "gn:asciiname":"Oulad Daoud",
    "gn:country_code":"MA",
    "gn:dem":183,
    "gn:feature_class":"P",
    "gn:feature_code":"PPL",
    "gn:name":"Oulad Daoud",
    "gn:population":0,
    "gn:timezone":"Africa/Casablanca",
    "iso:country":"MA",
    "name:ara_x_preferred":[
        "\u0623\u0648\u0644\u0627\u062f \u062f\u0627\u0648\u062f"
    ],
    "name:cat_x_preferred":[
        "Oulad Daoud"
    ],
    "name:fra_x_preferred":[
        "Ouled Daoud"
    ],
    "wof:name":"Oulad Daoud",
    "wof:placetype":"locality"
},
  "geometry": {"coordinates":[-2.81728,34.94521],"type":"Point"}
}