{
  "type": "Feature",
  "properties": {
    "gn:admin1_code":"06",
    "gn:asciiname":"Douar ba Hamada",
    "gn:country_code":"MA",
    "gn:dem":352,
    "gn:feature_class":"P",
    "gn:feature_code":"PPL",
    "gn:name":"Douar ba Hamada",
    "gn:population":0,
    "gn:timezone":"Africa/Casablanca",
    "iso:country":"MA",
    "name:und_x_variant":[
        "Ouled Bahamada",
        "Douar Ba Hammada",
        "Douar ba Hamada"
    ],
    "wof:name":"Douar ba Hamada",
    "wof:placetype":"locality"
},
  "geometry": {"coordinates":[-7.1575,32.40748],"type":"Point"}
}