{
  "type": "Feature",
  "properties": {
    "gn:admin1_code":"3.0",
    "gn:asciiname":"Douar Madrad",
    "gn:country_code":"MA",
    "gn:dem":1314,
    "gn:feature_class":"P",
    "gn:feature_code":"PPL",
    "gn:name":"Douar Madrad",
    "gn:population":0,
    "gn:timezone":"Africa/Casablanca",
    "iso:country":"MA",
    "wof:name":"Douar Madrad",
    "wof:placetype":"locality"
},
  "geometry": {"coordinates":[-4.22894,33.95014],"type":"Point"}
}