{
  "type": "Feature",
  "properties": {
    "gn:admin1_code":"05",
    "gn:asciiname":"Douar Oulad Sidi Dris",
    "gn:country_code":"MA",
    "gn:dem":347,
    "gn:feature_class":"P",
    "gn:feature_code":"PPL",
    "gn:name":"Douar Oulad Sidi Dris",
    "gn:population":0,
    "gn:timezone":"Africa/Casablanca",
    "iso:country":"MA",
    "name:und_x_variant":[
        "Oulad Sidi Driss"
    ],
    "wof:name":"Douar Oulad Sidi Dris",
    "wof:placetype":"locality"
},
  "geometry": {"coordinates":[-7.11672,32.32882],"type":"Point"}
}