{
  "type": "Feature",
  "properties": {
    "gn:admin1_code":"4.0",
    "gn:asciiname":"Zouayriya",
    "gn:country_code":"MA",
    "gn:dem":500,
    "gn:feature_class":"P",
    "gn:feature_code":"PPL",
    "gn:name":"Zouayriya",
    "gn:population":0,
    "gn:timezone":"Africa/Casablanca",
    "iso:country":"MA",
    "wof:name":"Zouayriya",
    "wof:placetype":"locality"
},
  "geometry": {"coordinates":[-6.4817,33.57671],"type":"Point"}
}