{
  "type": "Feature",
  "properties": {
    "gn:admin1_code":"2.0",
    "gn:asciiname":"Ikharouidene",
    "gn:country_code":"MA",
    "gn:dem":561,
    "gn:feature_class":"P",
    "gn:feature_code":"PPL",
    "gn:name":"Ikharouidene",
    "gn:population":0,
    "gn:timezone":"Africa/Casablanca",
    "iso:country":"MA",
    "wof:name":"Ikharouidene",
    "wof:placetype":"locality"
},
  "geometry": {"coordinates":[-3.41879,35.10381],"type":"Point"}
}