{
  "type": "Feature",
  "properties": {
    "gn:admin1_code":"7.0",
    "gn:asciiname":"Douar Id Ou Malek",
    "gn:country_code":"MA",
    "gn:dem":265,
    "gn:feature_class":"P",
    "gn:feature_code":"PPL",
    "gn:name":"Douar Id Ou Malek",
    "gn:population":0,
    "gn:timezone":"Africa/Casablanca",
    "iso:country":"MA",
    "wof:name":"Douar Id Ou Malek",
    "wof:placetype":"locality"
},
  "geometry": {"coordinates":[-9.53007,31.35882],"type":"Point"}
}