{
  "type": "Feature",
  "properties": {
    "gn:admin1_code":"07",
    "gn:asciiname":"Douar Essaidat",
    "gn:country_code":"MA",
    "gn:dem":302,
    "gn:feature_class":"P",
    "gn:feature_code":"PPL",
    "gn:name":"Douar Essaidat",
    "gn:population":0,
    "gn:timezone":"Africa/Casablanca",
    "iso:country":"MA",
    "name:und_x_variant":[
        "Dar Saidate",
        "Saidate",
        "Douar Sa\u00efdat",
        "Sa\u00efdat",
        "Douar Essaidat"
    ],
    "wof:name":"Douar Essaidat",
    "wof:placetype":"locality"
},
  "geometry": {"coordinates":[-8.48303,31.70585],"type":"Point"}
}