{
  "type": "Feature",
  "properties": {
    "gn:admin1_code":"1.0",
    "gn:asciiname":"Douar Ain Laassel",
    "gn:country_code":"MA",
    "gn:dem":150,
    "gn:feature_class":"P",
    "gn:feature_code":"PPL",
    "gn:name":"Douar Ain Laassel",
    "gn:population":0,
    "gn:timezone":"Africa/Casablanca",
    "iso:country":"MA",
    "wof:name":"Douar Ain Laassel",
    "wof:placetype":"locality"
},
  "geometry": {"coordinates":[-5.85322,35.69014],"type":"Point"}
}