{
  "type": "Feature",
  "properties": {
    "gn:admin1_code":"7.0",
    "gn:asciiname":"Dar Salem Ould as Salek",
    "gn:country_code":"MA",
    "gn:dem":623,
    "gn:feature_class":"P",
    "gn:feature_code":"PPL",
    "gn:name":"Dar Salem Ould as Salek",
    "gn:population":0,
    "gn:timezone":"Africa/Casablanca",
    "iso:country":"MA",
    "wof:name":"Dar Salem Ould as Salek",
    "wof:placetype":"locality"
},
  "geometry": {"coordinates":[-8.35556,31.40919],"type":"Point"}
}