{
  "type": "Feature",
  "properties": {
    "gn:admin1_code":"8.0",
    "gn:asciiname":"Timaskalt",
    "gn:country_code":"MA",
    "gn:dem":1426,
    "gn:feature_class":"P",
    "gn:feature_code":"PPL",
    "gn:name":"Timaskalt",
    "gn:population":0,
    "gn:timezone":"Africa/Casablanca",
    "iso:country":"MA",
    "wof:name":"Timaskalt",
    "wof:placetype":"locality"
},
  "geometry": {"coordinates":[-6.09861,31.23545],"type":"Point"}
}