{
  "type": "Feature",
  "properties": {
    "gn:admin1_code":"7.0",
    "gn:asciiname":"Jaddi Bou Ghanbour",
    "gn:country_code":"MA",
    "gn:dem":111,
    "gn:feature_class":"P",
    "gn:feature_code":"PPL",
    "gn:name":"Jaddi Bou Ghanbour",
    "gn:population":0,
    "gn:timezone":"Africa/Casablanca",
    "iso:country":"MA",
    "wof:name":"Jaddi Bou Ghanbour",
    "wof:placetype":"locality"
},
  "geometry": {"coordinates":[-9.68226,31.58261],"type":"Point"}
}