{
  "type": "Feature",
  "properties": {
    "gn:asciiname":"Dar el mouelda",
    "gn:country_code":"MA",
    "gn:dem":260,
    "gn:feature_class":"P",
    "gn:feature_code":"PPL",
    "gn:name":"Dar el mouelda",
    "gn:population":0,
    "gn:timezone":"Africa/Casablanca",
    "iso:country":"MA",
    "wof:name":"Dar el mouelda",
    "wof:placetype":"locality"
},
  "geometry": {"coordinates":[-4.68089,34.10673],"type":"Point"}
}