{
  "type": "Feature",
  "properties": {
    "gn:admin1_code":"09",
    "gn:asciiname":"Ighram",
    "gn:country_code":"MA",
    "gn:dem":1723,
    "gn:feature_class":"P",
    "gn:feature_code":"PPL",
    "gn:name":"Ighram",
    "gn:population":0,
    "gn:timezone":"Africa/Casablanca",
    "iso:country":"MA",
    "name:ara_x_preferred":[
        "\u0625\u064a\u063a\u0631\u0645"
    ],
    "name:cat_x_preferred":[
        "Irherm"
    ],
    "name:deu_x_preferred":[
        "Igherm"
    ],
    "name:fra_x_preferred":[
        "Irherm"
    ],
    "name:por_x_preferred":[
        "Irherm"
    ],
    "name:und_x_variant":[
        "Ighram"
    ],
    "wof:name":"Ighram",
    "wof:placetype":"locality"
},
  "geometry": {"coordinates":[-8.46023,30.08928],"type":"Point"}
}