{
  "type": "Feature",
  "properties": {
    "gn:admin1_code":"03",
    "gn:asciiname":"Douar Gnites",
    "gn:country_code":"MA",
    "gn:dem":717,
    "gn:feature_class":"P",
    "gn:feature_code":"PPL",
    "gn:name":"Douar Gnites",
    "gn:population":0,
    "gn:timezone":"Africa/Casablanca",
    "iso:country":"MA",
    "name:und_x_variant":[
        "Guenitess",
        "Douar Gnites"
    ],
    "wof:name":"Douar Gnites",
    "wof:placetype":"locality"
},
  "geometry": {"coordinates":[-4.16865,34.29229],"type":"Point"}
}