{
  "type": "Feature",
  "properties": {
    "gn:admin1_code":"7.0",
    "gn:asciiname":"Oulad Bouchta",
    "gn:country_code":"MA",
    "gn:dem":127,
    "gn:feature_class":"P",
    "gn:feature_code":"PPL",
    "gn:name":"Oulad Bouchta",
    "gn:population":0,
    "gn:timezone":"Africa/Casablanca",
    "iso:country":"MA",
    "wof:name":"Oulad Bouchta",
    "wof:placetype":"locality"
},
  "geometry": {"coordinates":[-9.04372,32.33581],"type":"Point"}
}