{
  "type": "Feature",
  "properties": {
    "gn:admin1_code":"7.0",
    "gn:asciiname":"Douar ben Nasser",
    "gn:country_code":"MA",
    "gn:dem":540,
    "gn:feature_class":"P",
    "gn:feature_code":"PPL",
    "gn:name":"Douar ben Nasser",
    "gn:population":0,
    "gn:timezone":"Africa/Casablanca",
    "iso:country":"MA",
    "wof:name":"Douar ben Nasser",
    "wof:placetype":"locality"
},
  "geometry": {"coordinates":[-8.14142,31.44909],"type":"Point"}
}