{
  "type": "Feature",
  "properties": {
    "gn:admin1_code":"01",
    "gn:asciiname":"Bou Safi",
    "gn:country_code":"MA",
    "gn:dem":47,
    "gn:feature_class":"P",
    "gn:feature_code":"PPL",
    "gn:name":"Bou Safi",
    "gn:population":0,
    "gn:timezone":"Africa/Casablanca",
    "iso:country":"MA",
    "wof:name":"Bou Safi",
    "wof:placetype":"locality"
},
  "geometry": {"coordinates":[-6.03432,35.18871],"type":"Point"}
}