{
  "type": "Feature",
  "properties": {
    "gn:admin1_code":"09",
    "gn:asciiname":"Tagragra",
    "gn:country_code":"MA",
    "gn:dem":953,
    "gn:feature_class":"P",
    "gn:feature_code":"PPL",
    "gn:name":"Tagragra",
    "gn:population":0,
    "gn:timezone":"Africa/Casablanca",
    "iso:country":"MA",
    "wof:name":"Tagragra",
    "wof:placetype":"locality"
},
  "geometry": {"coordinates":[-8.44983,30.36503],"type":"Point"}
}