{
  "type": "Feature",
  "properties": {
    "gn:admin1_code":"7.0",
    "gn:asciiname":"Kbaat Ben Raleh",
    "gn:country_code":"MA",
    "gn:dem":530,
    "gn:feature_class":"P",
    "gn:feature_code":"PPL",
    "gn:name":"Kbaat Ben Raleh",
    "gn:population":0,
    "gn:timezone":"Africa/Casablanca",
    "iso:country":"MA",
    "wof:name":"Kbaat Ben Raleh",
    "wof:placetype":"locality"
},
  "geometry": {"coordinates":[-8.96539,31.96917],"type":"Point"}
}