{
  "type": "Feature",
  "properties": {
    "gn:admin1_code":"01",
    "gn:asciiname":"Douar Adyaz",
    "gn:country_code":"MA",
    "gn:dem":788,
    "gn:feature_class":"P",
    "gn:feature_code":"PPL",
    "gn:name":"Douar Adyaz",
    "gn:population":0,
    "gn:timezone":"Africa/Casablanca",
    "iso:country":"MA",
    "name:und_x_variant":[
        "Adyaz",
        "Adiaz",
        "Douar Adyaz"
    ],
    "wof:name":"Douar Adyaz",
    "wof:placetype":"locality"
},
  "geometry": {"coordinates":[-5.51649,35.34511],"type":"Point"}
}