{
  "type": "Feature",
  "properties": {
    "gn:admin1_code":"7.0",
    "gn:asciiname":"Oulad El Ayachi",
    "gn:country_code":"MA",
    "gn:dem":354,
    "gn:feature_class":"P",
    "gn:feature_code":"PPL",
    "gn:name":"Oulad El Ayachi",
    "gn:population":0,
    "gn:timezone":"Africa/Casablanca",
    "iso:country":"MA",
    "wof:name":"Oulad El Ayachi",
    "wof:placetype":"locality"
},
  "geometry": {"coordinates":[-8.55898,31.59755],"type":"Point"}
}