{
  "type": "Feature",
  "properties": {
    "gn:admin1_code":"7.0",
    "gn:asciiname":"Oulad Aichouch",
    "gn:country_code":"MA",
    "gn:dem":153,
    "gn:feature_class":"P",
    "gn:feature_code":"PPL",
    "gn:name":"Oulad Aichouch",
    "gn:population":0,
    "gn:timezone":"Africa/Casablanca",
    "iso:country":"MA",
    "wof:name":"Oulad Aichouch",
    "wof:placetype":"locality"
},
  "geometry": {"coordinates":[-8.94589,32.36868],"type":"Point"}
}