{
  "type": "Feature",
  "properties": {
    "gn:admin1_code":"3.0",
    "gn:asciiname":"Oulad Alla",
    "gn:country_code":"MA",
    "gn:dem":547,
    "gn:feature_class":"P",
    "gn:feature_code":"PPL",
    "gn:name":"Oulad Alla",
    "gn:population":0,
    "gn:timezone":"Africa/Casablanca",
    "iso:country":"MA",
    "wof:name":"Oulad Alla",
    "wof:placetype":"locality"
},
  "geometry": {"coordinates":[-4.56292,33.97324],"type":"Point"}
}