{
  "type": "Feature",
  "properties": {
    "gn:admin1_code":"5.0",
    "gn:asciiname":"Arboua",
    "gn:country_code":"MA",
    "gn:dem":1057,
    "gn:feature_class":"P",
    "gn:feature_code":"PPL",
    "gn:name":"Arbou\u00e2",
    "gn:population":0,
    "gn:timezone":"Africa/Casablanca",
    "iso:country":"MA",
    "wof:name":"Arboua",
    "wof:placetype":"locality"
},
  "geometry": {"coordinates":[-5.59379,32.9417],"type":"Point"}
}