{
  "type": "Feature",
  "properties": {
    "gn:admin1_code":"5.0",
    "gn:asciiname":"Tagzirt-n-Ait I'zza",
    "gn:country_code":"MA",
    "gn:dem":834,
    "gn:feature_class":"P",
    "gn:feature_code":"PPL",
    "gn:name":"Tagzirt-n-A\u00eft I\u2019zza",
    "gn:population":0,
    "gn:timezone":"Africa/Casablanca",
    "iso:country":"MA",
    "wof:name":"Tagzirt-n-Ait I'zza",
    "wof:placetype":"locality"
},
  "geometry": {"coordinates":[-6.44743,32.08385999999999],"type":"Point"}
}