{
  "type": "Feature",
  "properties": {
    "gn:admin1_code":"1.0",
    "gn:asciiname":"Douar Kaf Lghoul",
    "gn:country_code":"MA",
    "gn:dem":391,
    "gn:feature_class":"P",
    "gn:feature_code":"PPL",
    "gn:name":"Douar Kaf Lghoul",
    "gn:population":0,
    "gn:timezone":"Africa/Casablanca",
    "iso:country":"MA",
    "wof:name":"Douar Kaf Lghoul",
    "wof:placetype":"locality"
},
  "geometry": {"coordinates":[-5.18407,34.74992],"type":"Point"}
}