{
  "type": "Feature",
  "properties": {
    "gn:admin1_code":"9.0",
    "gn:asciiname":"Ait 'Ali Ou Dawd",
    "gn:country_code":"MA",
    "gn:dem":906,
    "gn:feature_class":"P",
    "gn:feature_code":"PPL",
    "gn:name":"A\u00eft \u2019Ali Ou Dawd",
    "gn:population":0,
    "gn:timezone":"Africa/Casablanca",
    "iso:country":"MA",
    "wof:name":"Ait 'Ali Ou Dawd",
    "wof:placetype":"locality"
},
  "geometry": {"coordinates":[-9.21362,29.80531],"type":"Point"}
}