{
  "type": "Feature",
  "properties": {
    "gn:admin1_code":"9.0",
    "gn:asciiname":"Ilbdi",
    "gn:country_code":"MA",
    "gn:dem":405,
    "gn:feature_class":"P",
    "gn:feature_code":"PPL",
    "gn:name":"Ilbdi",
    "gn:population":0,
    "gn:timezone":"Africa/Casablanca",
    "iso:country":"MA",
    "wof:name":"Ilbdi",
    "wof:placetype":"locality"
},
  "geometry": {"coordinates":[-9.45468,30.56592],"type":"Point"}
}