{
  "type": "Feature",
  "properties": {
    "gn:admin1_code":"07",
    "gn:asciiname":"Tachguelt",
    "gn:country_code":"MA",
    "gn:dem":1548,
    "gn:feature_class":"P",
    "gn:feature_code":"PPL",
    "gn:name":"Tachguelt",
    "gn:population":0,
    "gn:timezone":"Africa/Casablanca",
    "iso:country":"MA",
    "name:und_x_variant":[
        "Techguelt",
        "Tacheguelt",
        "Tachguelt"
    ],
    "wof:name":"Tachguelt",
    "wof:placetype":"locality"
},
  "geometry": {"coordinates":[-8.0981,31.01395],"type":"Point"}
}