{
  "type": "Feature",
  "properties": {
    "gn:admin1_code":"2.0",
    "gn:asciiname":"Douar Imarchouhet",
    "gn:country_code":"MA",
    "gn:dem":592,
    "gn:feature_class":"P",
    "gn:feature_code":"PPL",
    "gn:name":"Douar Imarchouhet",
    "gn:population":0,
    "gn:timezone":"Africa/Casablanca",
    "iso:country":"MA",
    "wof:name":"Douar Imarchouhet",
    "wof:placetype":"locality"
},
  "geometry": {"coordinates":[-3.75145,35.09454],"type":"Point"}
}