{
  "type": "Feature",
  "properties": {
    "gn:admin1_code":"5.0",
    "gn:asciiname":"Ighiyr-n-Tamdroust",
    "gn:country_code":"MA",
    "gn:dem":1558,
    "gn:feature_class":"P",
    "gn:feature_code":"PPL",
    "gn:name":"Ighiyr-n-Tamdroust",
    "gn:population":0,
    "gn:timezone":"Africa/Casablanca",
    "iso:country":"MA",
    "wof:name":"Ighiyr-n-Tamdroust",
    "wof:placetype":"locality"
},
  "geometry": {"coordinates":[-7.01429,31.44611],"type":"Point"}
}