{
  "type": "Feature",
  "properties": {
    "gn:admin1_code":"2.0",
    "gn:asciiname":"Oulad Bou Chlaghem",
    "gn:country_code":"MA",
    "gn:dem":38,
    "gn:feature_class":"P",
    "gn:feature_code":"PPL",
    "gn:name":"Oulad Bou Chlaghem",
    "gn:population":0,
    "gn:timezone":"Africa/Casablanca",
    "iso:country":"MA",
    "wof:name":"Oulad Bou Chlaghem",
    "wof:placetype":"locality"
},
  "geometry": {"coordinates":[-2.87234,35.07632],"type":"Point"}
}