{
  "type": "Feature",
  "properties": {
    "gn:admin1_code":"9.0",
    "gn:asciiname":"Idargane",
    "gn:country_code":"MA",
    "gn:dem":869,
    "gn:feature_class":"P",
    "gn:feature_code":"PPL",
    "gn:name":"Idargane",
    "gn:population":0,
    "gn:timezone":"Africa/Casablanca",
    "iso:country":"MA",
    "wof:name":"Idargane",
    "wof:placetype":"locality"
},
  "geometry": {"coordinates":[-7.99357,30.73537],"type":"Point"}
}