{
  "type": "Feature",
  "properties": {
    "gn:admin1_code":"7.0",
    "gn:asciiname":"Imzilene",
    "gn:country_code":"MA",
    "gn:dem":185,
    "gn:feature_class":"P",
    "gn:feature_code":"PPL",
    "gn:name":"Imzilene",
    "gn:population":0,
    "gn:timezone":"Africa/Casablanca",
    "iso:country":"MA",
    "wof:name":"Imzilene",
    "wof:placetype":"locality"
},
  "geometry": {"coordinates":[-9.72245,31.2727],"type":"Point"}
}