{
  "type": "Feature",
  "properties": {
    "gn:admin1_code":"3.0",
    "gn:asciiname":"Douar Jirat",
    "gn:country_code":"MA",
    "gn:dem":313,
    "gn:feature_class":"P",
    "gn:feature_code":"PPL",
    "gn:name":"Douar Jirat",
    "gn:population":0,
    "gn:timezone":"Africa/Casablanca",
    "iso:country":"MA",
    "wof:name":"Douar Jirat",
    "wof:placetype":"locality"
},
  "geometry": {"coordinates":[-4.69141,34.09213],"type":"Point"}
}