{
  "type": "Feature",
  "properties": {
    "gn:admin1_code":"07",
    "gn:asciiname":"Ibelay",
    "gn:country_code":"MA",
    "gn:dem":858,
    "gn:feature_class":"P",
    "gn:feature_code":"PPL",
    "gn:name":"Ibelay",
    "gn:population":0,
    "gn:timezone":"Africa/Casablanca",
    "iso:country":"MA",
    "wof:name":"Ibelay",
    "wof:placetype":"locality"
},
  "geometry": {"coordinates":[-9.34318,31.16539],"type":"Point"}
}