{
  "type": "Feature",
  "properties": {
    "gn:admin1_code":"2.0",
    "gn:asciiname":"Douar Ibouamanene",
    "gn:country_code":"MA",
    "gn:dem":210,
    "gn:feature_class":"P",
    "gn:feature_code":"PPL",
    "gn:name":"Douar Ibouamanene",
    "gn:population":0,
    "gn:timezone":"Africa/Casablanca",
    "iso:country":"MA",
    "wof:name":"Douar Ibouamanene",
    "wof:placetype":"locality"
},
  "geometry": {"coordinates":[-3.7997,35.08322],"type":"Point"}
}