{
  "type": "Feature",
  "properties": {
    "gn:admin1_code":"09",
    "gn:asciiname":"Ait Mhand-ou-Yous",
    "gn:country_code":"MA",
    "gn:dem":531,
    "gn:feature_class":"P",
    "gn:feature_code":"PPL",
    "gn:name":"A\u00eft Mhand-ou-Yous",
    "gn:population":0,
    "gn:timezone":"Africa/Casablanca",
    "iso:country":"MA",
    "name:und_x_variant":[
        "A\u00eft Mhand-ou-Yous",
        "A\u00eft Yous"
    ],
    "wof:name":"Ait Mhand-ou-Yous",
    "wof:placetype":"locality"
},
  "geometry": {"coordinates":[-8.328,30.62514],"type":"Point"}
}