{
  "type": "Feature",
  "properties": {
    "gn:admin1_code":"1.0",
    "gn:asciiname":"Lanziri",
    "gn:country_code":"MA",
    "gn:dem":469,
    "gn:feature_class":"P",
    "gn:feature_code":"PPL",
    "gn:name":"Lanziri",
    "gn:population":0,
    "gn:timezone":"Africa/Casablanca",
    "iso:country":"MA",
    "wof:name":"Lanziri",
    "wof:placetype":"locality"
},
  "geometry": {"coordinates":[-5.20224,35.48166],"type":"Point"}
}