{
  "type": "Feature",
  "properties": {
    "gn:admin1_code":"09",
    "gn:asciiname":"Ifarkhane-n-Oufella",
    "gn:country_code":"MA",
    "gn:dem":591,
    "gn:feature_class":"P",
    "gn:feature_code":"PPL",
    "gn:name":"Ifarkhane-n-Oufella",
    "gn:population":0,
    "gn:timezone":"Africa/Casablanca",
    "iso:country":"MA",
    "name:und_x_variant":[
        "Ifirkhane Douar Oujella",
        "Iferkane n\u2019Oufella",
        "Ifarkhane-n-Oufella"
    ],
    "wof:name":"Ifarkhane-n-Oufella",
    "wof:placetype":"locality"
},
  "geometry": {"coordinates":[-8.3524,30.55973],"type":"Point"}
}