{
  "type": "Feature",
  "properties": {
    "gn:admin1_code":"09",
    "gn:asciiname":"El Gara",
    "gn:country_code":"MA",
    "gn:dem":101,
    "gn:feature_class":"P",
    "gn:feature_code":"PPL",
    "gn:name":"El Gara",
    "gn:population":0,
    "gn:timezone":"Africa/Casablanca",
    "iso:country":"MA",
    "name:ara_x_preferred":[
        "\u0627\u0644\u0643\u0627\u0631\u0629"
    ],
    "name:azb_x_preferred":[
        "\u0627\u0644\u06a9\u0627\u0631\u0647"
    ],
    "name:cat_x_preferred":[
        "El Gara"
    ],
    "name:fas_x_preferred":[
        "\u0627\u0644\u06a9\u0627\u0631\u0647"
    ],
    "name:fra_x_preferred":[
        "El Gara"
    ],
    "name:ita_x_preferred":[
        "El Gara"
    ],
    "name:und_x_variant":[
        "Grara",
        "El Grarat",
        "El Grara"
    ],
    "wof:name":"El Gara",
    "wof:placetype":"locality"
},
  "geometry": {"coordinates":[-9.70696,29.8523],"type":"Point"}
}