{
  "type": "Feature",
  "properties": {
    "gn:admin1_code":"1.0",
    "gn:asciiname":"Lemchirae",
    "gn:country_code":"MA",
    "gn:dem":152,
    "gn:feature_class":"P",
    "gn:feature_code":"PPLL",
    "gn:name":"Lemchirae",
    "gn:population":0,
    "gn:timezone":"Africa/Casablanca",
    "iso:country":"MA",
    "wof:name":"Lemchirae",
    "wof:placetype":"locality"
},
  "geometry": {"coordinates":[-6.06481,35.25190999999999],"type":"Point"}
}