{
  "type": "Feature",
  "properties": {
    "gn:admin1_code":"7.0",
    "gn:asciiname":"Dar Jlal Ben Erranu",
    "gn:country_code":"MA",
    "gn:dem":489,
    "gn:feature_class":"P",
    "gn:feature_code":"PPL",
    "gn:name":"Dar Jlal Ben Erranu",
    "gn:population":0,
    "gn:timezone":"Africa/Casablanca",
    "iso:country":"MA",
    "wof:name":"Dar Jlal Ben Erranu",
    "wof:placetype":"locality"
},
  "geometry": {"coordinates":[-7.85761,31.61102],"type":"Point"}
}