{
  "type": "Feature",
  "properties": {
    "gn:admin1_code":"08",
    "gn:asciiname":"Aira n'Ait Sedrat",
    "gn:country_code":"MA",
    "gn:dem":881,
    "gn:feature_class":"P",
    "gn:feature_code":"PPL",
    "gn:name":"A\u00efra n\u2019A\u00eft Sedrat",
    "gn:population":0,
    "gn:timezone":"Africa/Casablanca",
    "iso:country":"MA",
    "wof:name":"Aira n'Ait Sedrat",
    "wof:placetype":"locality"
},
  "geometry": {"coordinates":[-6.2445,30.70943],"type":"Point"}
}