{
  "type": "Feature",
  "properties": {
    "gn:admin1_code":"9.0",
    "gn:asciiname":"Berkous",
    "gn:country_code":"MA",
    "gn:dem":2064,
    "gn:feature_class":"P",
    "gn:feature_code":"PPL",
    "gn:name":"Berkous",
    "gn:population":0,
    "gn:timezone":"Africa/Casablanca",
    "iso:country":"MA",
    "wof:name":"Berkous",
    "wof:placetype":"locality"
},
  "geometry": {"coordinates":[-8.81804,30.95191],"type":"Point"}
}