{
  "type": "Feature",
  "properties": {
    "gn:admin1_code":"7.0",
    "gn:asciiname":"Douar Said El Qadim",
    "gn:country_code":"MA",
    "gn:dem":436,
    "gn:feature_class":"P",
    "gn:feature_code":"PPL",
    "gn:name":"Douar Said El Qadim",
    "gn:population":0,
    "gn:timezone":"Africa/Casablanca",
    "iso:country":"MA",
    "wof:name":"Douar Said El Qadim",
    "wof:placetype":"locality"
},
  "geometry": {"coordinates":[-8.36825,32.19035],"type":"Point"}
}