{
  "type": "Feature",
  "properties": {
    "gn:admin1_code":"2.0",
    "gn:asciiname":"Douar Iheqqounene",
    "gn:country_code":"MA",
    "gn:dem":800,
    "gn:feature_class":"P",
    "gn:feature_code":"PPL",
    "gn:name":"Douar Iheqqounene",
    "gn:population":0,
    "gn:timezone":"Africa/Casablanca",
    "iso:country":"MA",
    "wof:name":"Douar Iheqqounene",
    "wof:placetype":"locality"
},
  "geometry": {"coordinates":[-3.51762,35.06387],"type":"Point"}
}