{
  "type": "Feature",
  "properties": {
    "gn:admin1_code":"04",
    "gn:asciiname":"Maison Cantonniere d'Ouled Azouz",
    "gn:country_code":"MA",
    "gn:dem":11,
    "gn:feature_class":"P",
    "gn:feature_code":"PPL",
    "gn:name":"Maison Cantonni\u00e8re d\u2019Ouled Azouz",
    "gn:population":0,
    "gn:timezone":"Africa/Casablanca",
    "iso:country":"MA",
    "wof:name":"Maison Cantonniere d'Ouled Azouz",
    "wof:placetype":"locality"
},
  "geometry": {"coordinates":[-6.47,34.45],"type":"Point"}
}