{
  "type": "Feature",
  "properties": {
    "gn:admin1_code":"8.0",
    "gn:asciiname":"Zawyat Moulay 'Adbalmalk",
    "gn:country_code":"MA",
    "gn:dem":1369,
    "gn:feature_class":"P",
    "gn:feature_code":"PPL",
    "gn:name":"Zawyat Moulay \u2019Adbalmalk",
    "gn:population":0,
    "gn:timezone":"Africa/Casablanca",
    "iso:country":"MA",
    "wof:name":"Zawyat Moulay 'Adbalmalk",
    "wof:placetype":"locality"
},
  "geometry": {"coordinates":[-6.20284,31.19378],"type":"Point"}
}