{
  "type": "Feature",
  "properties": {
    "gn:admin1_code":"9.0",
    "gn:asciiname":"Tifiyrassiyn",
    "gn:country_code":"MA",
    "gn:dem":752,
    "gn:feature_class":"P",
    "gn:feature_code":"PPL",
    "gn:name":"Tifiyrassiyn",
    "gn:population":0,
    "gn:timezone":"Africa/Casablanca",
    "iso:country":"MA",
    "wof:name":"Tifiyrassiyn",
    "wof:placetype":"locality"
},
  "geometry": {"coordinates":[-9.17057,29.97901],"type":"Point"}
}