{
  "type": "Feature",
  "properties": {
    "gn:admin1_code":"01",
    "gn:asciiname":"Sidi Kasem",
    "gn:country_code":"MA",
    "gn:dem":693,
    "gn:feature_class":"P",
    "gn:feature_code":"PPL",
    "gn:name":"Sidi Kasem",
    "gn:population":0,
    "gn:timezone":"Africa/Casablanca",
    "iso:country":"MA",
    "name:und_x_variant":[
        "Zouia Sidi Kacem",
        "Zou\u00efet Sidi Kacem",
        "Sidi Kasem"
    ],
    "wof:name":"Sidi Kasem",
    "wof:placetype":"locality"
},
  "geometry": {"coordinates":[-5.2163,35.47287],"type":"Point"}
}