{
  "type": "Feature",
  "properties": {
    "gn:admin1_code":"08",
    "gn:asciiname":"Igdaoun",
    "gn:country_code":"MA",
    "gn:dem":843,
    "gn:feature_class":"P",
    "gn:feature_code":"PPL",
    "gn:name":"Igdaoun",
    "gn:population":0,
    "gn:timezone":"Africa/Casablanca",
    "iso:country":"MA",
    "name:und_x_variant":[
        "Igdourane",
        "Igdaoun"
    ],
    "wof:name":"Igdaoun",
    "wof:placetype":"locality"
},
  "geometry": {"coordinates":[-6.15031,30.58156],"type":"Point"}
}