{
  "type": "Feature",
  "properties": {
    "gn:country":"MA",
    "gn:fcode":"ADM3",
    "gn:pop":44730,
    "iso:country":"MA",
    "name:ara_x_preferred":[
        "\u0627\u0648\u062a\u0631\u0628\u0627\u062a"
    ],
    "name:fra_x_preferred":[
        "Midelt"
    ],
    "name:fra_x_variant":[
        "Midelt (MU)",
        "Midelt (Commune Urbaine)"
    ],
    "qs:name":"Midelt",
    "qs:photos_9r":0,
    "qs:photos_sr":0,
    "qs:pop_sr":"7",
    "wd:wordcount":819,
    "wof:name":"Midelt",
    "wof:placetype":"localadmin",
    "wof:population":44730
},
  "geometry": {"coordinates":[-4.74077,32.6828],"type":"Point"}
}