{
  "type": "Feature",
  "properties": {
    "gn:country":"MA",
    "gn:fcode":"ADM3",
    "gn:population":44730,
    "iso:country":"MA",
    "name:ara_x_preferred":[
        "\u0627\u0648\u062a\u0631\u0628\u0627\u062a"
    ],
    "name:ara_x_variant":[
        "\u0645\u064a\u062f\u0644\u062a"
    ],
    "name:ary_x_preferred":[
        "\u0645\u064a\u062f\u0644\u062a"
    ],
    "name:azb_x_preferred":[
        "\u0645\u06cc\u062f\u0644\u062a"
    ],
    "name:cat_x_preferred":[
        "Midelt"
    ],
    "name:ceb_x_preferred":[
        "Midelt"
    ],
    "name:dan_x_preferred":[
        "Midelt"
    ],
    "name:deu_x_preferred":[
        "Midelt"
    ],
    "name:eng_x_preferred":[
        "Midelt"
    ],
    "name:fas_x_preferred":[
        "\u0645\u06cc\u062f\u0644\u062a"
    ],
    "name:fra_x_preferred":[
        "Midelt"
    ],
    "name:fra_x_variant":[
        "Midelt (MU)",
        "Midelt (Commune Urbaine)"
    ],
    "name:heb_x_preferred":[
        "\u05de\u05d9\u05d3\u05dc\u05ea"
    ],
    "name:ita_x_preferred":[
        "Midelt"
    ],
    "name:jpn_x_preferred":[
        "\u30df\u30c7\u30eb\u30c8"
    ],
    "name:nld_x_preferred":[
        "Midelt"
    ],
    "name:pol_x_preferred":[
        "Midalt"
    ],
    "name:por_x_preferred":[
        "Midelt"
    ],
    "name:rus_x_preferred":[
        "\u041c\u0438\u0434\u0435\u043b\u044c\u0442"
    ],
    "name:spa_x_preferred":[
        "Midelt"
    ],
    "name:swe_x_preferred":[
        "Midelt"
    ],
    "name:zho_x_preferred":[
        "\u7c73\u5fb7\u52d2\u7279"
    ],
    "qs:name":"Midelt",
    "qs:photos_9r":0,
    "qs:photos_sr":0,
    "qs:pop_sr":"7",
    "wd:wordcount":819,
    "wof:name":"Midelt",
    "wof:placetype":"localadmin",
    "wof:population":44730
},
  "geometry": {"coordinates":[-4.74077,32.6828],"type":"Point"}
}