{
  "type": "Feature",
  "properties": {
    "gn:admin1_code":"2.0",
    "gn:asciiname":"Douar Basri",
    "gn:country_code":"MA",
    "gn:dem":230,
    "gn:feature_class":"P",
    "gn:feature_code":"PPL",
    "gn:name":"Douar Basri",
    "gn:population":0,
    "gn:timezone":"Africa/Casablanca",
    "iso:country":"MA",
    "wof:name":"Douar Basri",
    "wof:placetype":"locality"
},
  "geometry": {"coordinates":[-2.61586,35.05025999999999],"type":"Point"}
}