{
  "type": "Feature",
  "properties": {
    "gn:admin1_code":"6.0",
    "gn:asciiname":"Douar Jouaoula",
    "gn:country_code":"MA",
    "gn:dem":76,
    "gn:feature_class":"P",
    "gn:feature_code":"PPL",
    "gn:name":"Douar Jouaoula",
    "gn:population":0,
    "gn:timezone":"Africa/Casablanca",
    "iso:country":"MA",
    "wof:name":"Douar Jouaoula",
    "wof:placetype":"locality"
},
  "geometry": {"coordinates":[-8.41915,33.15798],"type":"Point"}
}