{
  "type": "Feature",
  "properties": {
    "gn:admin1_code":"10",
    "gn:asciiname":"Id Mbarek",
    "gn:country_code":"MA",
    "gn:dem":546,
    "gn:feature_class":"P",
    "gn:feature_code":"PPL",
    "gn:name":"Id Mbarek",
    "gn:population":0,
    "gn:timezone":"Africa/Casablanca",
    "iso:country":"MA",
    "name:und_x_variant":[
        "Izerban",
        "Id Embarec",
        "Id Embare"
    ],
    "wof:name":"Id Mbarek",
    "wof:placetype":"locality"
},
  "geometry": {"coordinates":[-9.97873,29.22378],"type":"Point"}
}