{
  "type": "Feature",
  "properties": {
    "gn:admin1_code":"09",
    "gn:asciiname":"Tamernout",
    "gn:country_code":"MA",
    "gn:dem":928,
    "gn:feature_class":"P",
    "gn:feature_code":"PPL",
    "gn:name":"Tamernout",
    "gn:population":0,
    "gn:timezone":"Africa/Casablanca",
    "iso:country":"MA",
    "name:und_x_variant":[
        "Timernoute",
        "Tamernoute",
        "Tamernout"
    ],
    "wof:name":"Tamernout",
    "wof:placetype":"locality"
},
  "geometry": {"coordinates":[-9.25681,29.81482],"type":"Point"}
}