{
  "type": "Feature",
  "properties": {
    "gn:admin1_code":"07",
    "gn:admin2_code":"191.0",
    "gn:admin3_code":"719103372.0",
    "gn:asciiname":"Sidi Moussa",
    "gn:country_code":"MA",
    "gn:dem":354,
    "gn:feature_class":"P",
    "gn:feature_code":"PPLA3",
    "gn:name":"Sidi Moussa",
    "gn:population":0,
    "gn:timezone":"Africa/Casablanca",
    "iso:country":"MA",
    "name:ceb_x_preferred":[
        "Sidi Moussa"
    ],
    "name:swe_x_preferred":[
        "Sidi Moussa"
    ],
    "wof:name":"Sidi Moussa",
    "wof:placetype":"locality"
},
  "geometry": {"coordinates":[-7.20095,32.27209000000001],"type":"Point"}
}