{
  "type": "Feature",
  "properties": {
    "gn:admin1_code":"03",
    "gn:asciiname":"Douar Dehara",
    "gn:country_code":"MA",
    "gn:dem":415,
    "gn:feature_class":"P",
    "gn:feature_code":"PPL",
    "gn:name":"Douar Dehara",
    "gn:population":0,
    "gn:timezone":"Africa/Casablanca",
    "iso:country":"MA",
    "name:und_x_variant":[
        "Douar Dechra",
        "Dechra",
        "Douar Dehara"
    ],
    "wof:name":"Douar Dehara",
    "wof:placetype":"locality"
},
  "geometry": {"coordinates":[-4.73806,34.45565999999999],"type":"Point"}
}