{
  "type": "Feature",
  "properties": {
    "gn:admin1_code":"2.0",
    "gn:asciiname":"Douar Oulad Taleb",
    "gn:country_code":"MA",
    "gn:dem":25,
    "gn:feature_class":"P",
    "gn:feature_code":"PPL",
    "gn:name":"Douar Oulad Taleb",
    "gn:population":0,
    "gn:timezone":"Africa/Casablanca",
    "iso:country":"MA",
    "wof:name":"Douar Oulad Taleb",
    "wof:placetype":"locality"
},
  "geometry": {"coordinates":[-2.76802,35.09035],"type":"Point"}
}