{
  "type": "Feature",
  "properties": {
    "gn:admin1_code":"01",
    "gn:asciiname":"Kelalba",
    "gn:country_code":"MA",
    "gn:dem":447,
    "gn:feature_class":"P",
    "gn:feature_code":"PPL",
    "gn:name":"Kelalba",
    "gn:population":0,
    "gn:timezone":"Africa/Casablanca",
    "iso:country":"MA",
    "name:und_x_variant":[
        "Kelabla",
        "Kelalba"
    ],
    "wof:name":"Kelalba",
    "wof:placetype":"locality"
},
  "geometry": {"coordinates":[-5.23391,34.6431],"type":"Point"}
}