{
  "type": "Feature",
  "properties": {
    "gn:admin1_code":"03",
    "gn:admin2_code":"531.0",
    "gn:admin3_code":"1553103112.0",
    "gn:asciiname":"Ratba",
    "gn:country_code":"MA",
    "gn:dem":590,
    "gn:feature_class":"P",
    "gn:feature_code":"PPLA3",
    "gn:name":"Ratba",
    "gn:population":0,
    "gn:timezone":"Africa/Casablanca",
    "iso:country":"MA",
    "name:ara_x_preferred":[
        "\u0627\u0644\u0631\u062a\u0628\u0629"
    ],
    "name:cat_x_preferred":[
        "Ratba"
    ],
    "name:ceb_x_preferred":[
        "Ratba"
    ],
    "name:ita_x_preferred":[
        "Ratba"
    ],
    "name:swe_x_preferred":[
        "Ratba"
    ],
    "wof:name":"Ratba",
    "wof:placetype":"locality"
},
  "geometry": {"coordinates":[-4.93989,34.77772],"type":"Point"}
}