{
  "type": "Feature",
  "properties": {
    "gn:admin1_code":"7.0",
    "gn:asciiname":"Jerf Dbaa",
    "gn:country_code":"MA",
    "gn:dem":474,
    "gn:feature_class":"P",
    "gn:feature_code":"PPL",
    "gn:name":"Jerf Dbaa",
    "gn:population":0,
    "gn:timezone":"Africa/Casablanca",
    "iso:country":"MA",
    "wof:name":"Jerf Dbaa",
    "wof:placetype":"locality"
},
  "geometry": {"coordinates":[-9.17244,31.49788],"type":"Point"}
}