{
  "type": "Feature",
  "properties": {
    "gn:admin1_code":"07",
    "gn:asciiname":"Bellat Jbel",
    "gn:country_code":"MA",
    "gn:dem":417,
    "gn:feature_class":"P",
    "gn:feature_code":"PPL",
    "gn:name":"Bellat Jbel",
    "gn:population":0,
    "gn:timezone":"Africa/Casablanca",
    "iso:country":"MA",
    "name:und_x_variant":[
        "Douar Bellat",
        "Bellat Jbel",
        "Bellat"
    ],
    "wof:name":"Bellat Jbel",
    "wof:placetype":"locality"
},
  "geometry": {"coordinates":[-8.75148,32.19733],"type":"Point"}
}