{
  "type": "Feature",
  "properties": {
    "gn:admin1_code":"1.0",
    "gn:asciiname":"Taoukart",
    "gn:country_code":"MA",
    "gn:dem":877,
    "gn:feature_class":"P",
    "gn:feature_code":"PPL",
    "gn:name":"Taoukart",
    "gn:population":0,
    "gn:timezone":"Africa/Casablanca",
    "iso:country":"MA",
    "wof:name":"Taoukart",
    "wof:placetype":"locality"
},
  "geometry": {"coordinates":[-4.78909,35.0072],"type":"Point"}
}