{
  "type": "Feature",
  "properties": {
    "gn:admin1_code":"01",
    "gn:asciiname":"Douar Bani Gueddour",
    "gn:country_code":"MA",
    "gn:dem":164,
    "gn:feature_class":"P",
    "gn:feature_code":"PPL",
    "gn:name":"Douar Bani Gueddour",
    "gn:population":0,
    "gn:timezone":"Africa/Casablanca",
    "iso:country":"MA",
    "name:und_x_variant":[
        "Beni Gueddaour",
        "Beni Gdour",
        "Beni Gueddour",
        "Douar Bani Gueddour"
    ],
    "wof:name":"Douar Bani Gueddour",
    "wof:placetype":"locality"
},
  "geometry": {"coordinates":[-5.72825,34.9731],"type":"Point"}
}