{
  "type": "Feature",
  "properties": {
    "gn:admin1_code":"6.0",
    "gn:asciiname":"Douar Leqouab Ghouaouta",
    "gn:country_code":"MA",
    "gn:dem":279,
    "gn:feature_class":"P",
    "gn:feature_code":"PPL",
    "gn:name":"Douar Leqouab Ghouaouta",
    "gn:population":0,
    "gn:timezone":"Africa/Casablanca",
    "iso:country":"MA",
    "wof:name":"Douar Leqouab Ghouaouta",
    "wof:placetype":"locality"
},
  "geometry": {"coordinates":[-8.23378,32.53085],"type":"Point"}
}