{
  "type": "Feature",
  "properties": {
    "gn:admin1_code":"7.0",
    "gn:asciiname":"Oulad Zhirou",
    "gn:country_code":"MA",
    "gn:dem":184,
    "gn:feature_class":"P",
    "gn:feature_code":"PPL",
    "gn:name":"Oulad Zhirou",
    "gn:population":0,
    "gn:timezone":"Africa/Casablanca",
    "iso:country":"MA",
    "wof:name":"Oulad Zhirou",
    "wof:placetype":"locality"
},
  "geometry": {"coordinates":[-9.03486,31.77684],"type":"Point"}
}