{
  "type": "Feature",
  "properties": {
    "gn:admin1_code":"01",
    "gn:asciiname":"Douar Lemaazza",
    "gn:country_code":"MA",
    "gn:dem":864,
    "gn:feature_class":"P",
    "gn:feature_code":"PPL",
    "gn:name":"Douar Lemaazza",
    "gn:population":0,
    "gn:timezone":"Africa/Casablanca",
    "iso:country":"MA",
    "name:und_x_variant":[
        "Maaza",
        "El Marhza",
        "El Maghza",
        "Douar Lemaazza"
    ],
    "wof:name":"Douar Lemaazza",
    "wof:placetype":"locality"
},
  "geometry": {"coordinates":[-5.43934,35.19361],"type":"Point"}
}