{
  "type": "Feature",
  "properties": {
    "gn:admin1_code":"01",
    "gn:asciiname":"Douar Khandeq Lkebch",
    "gn:country_code":"MA",
    "gn:dem":165,
    "gn:feature_class":"P",
    "gn:feature_code":"PPL",
    "gn:name":"Douar Khandeq Lkebch",
    "gn:population":0,
    "gn:timezone":"Africa/Casablanca",
    "iso:country":"MA",
    "name:und_x_variant":[
        "Khandak el Kabch",
        "Khandak el Kebch",
        "Douar Khandeq Lkebch"
    ],
    "wof:name":"Douar Khandeq Lkebch",
    "wof:placetype":"locality"
},
  "geometry": {"coordinates":[-5.62621,35.61476],"type":"Point"}
}