{
  "type": "Feature",
  "properties": {
    "gn:admin1_code":"07",
    "gn:asciiname":"Douar Dhar Ouiffini",
    "gn:country_code":"MA",
    "gn:dem":100,
    "gn:feature_class":"P",
    "gn:feature_code":"PPL",
    "gn:name":"Douar Dhar Ouiffini",
    "gn:population":0,
    "gn:timezone":"Africa/Casablanca",
    "iso:country":"MA",
    "name:und_x_variant":[
        "Douar Debra"
    ],
    "wof:name":"Douar Dhar Ouiffini",
    "wof:placetype":"locality"
},
  "geometry": {"coordinates":[-9.24637,32.32582],"type":"Point"}
}