{
  "type": "Feature",
  "properties": {
    "gn:admin1_code":"07",
    "gn:asciiname":"Mzaiouate",
    "gn:country_code":"MA",
    "gn:dem":409,
    "gn:feature_class":"P",
    "gn:feature_code":"PPL",
    "gn:name":"Mzaiouate",
    "gn:population":0,
    "gn:timezone":"Africa/Casablanca",
    "iso:country":"MA",
    "wof:name":"Mzaiouate",
    "wof:placetype":"locality"
},
  "geometry": {"coordinates":[-9.10671,31.89604000000001],"type":"Point"}
}