{
  "type": "Feature",
  "properties": {
    "gn:admin1_code":"09",
    "gn:asciiname":"Ifri Iderdar",
    "gn:country_code":"MA",
    "gn:dem":992,
    "gn:feature_class":"P",
    "gn:feature_code":"PPL",
    "gn:name":"Ifri Iderdar",
    "gn:population":0,
    "gn:timezone":"Africa/Casablanca",
    "iso:country":"MA",
    "wof:name":"Ifri Iderdar",
    "wof:placetype":"locality"
},
  "geometry": {"coordinates":[-8.46,30.38],"type":"Point"}
}