{
  "type": "Feature",
  "properties": {
    "gn:country":"MA",
    "gn:fcode":"ADM3",
    "gn:population":75239,
    "iso:country":"MA",
    "name:ara_x_preferred":[
        "\u0628\u0648\u0630\u0646\u064a\u0628 (\u0627\u0644\u0628\u0644\u062f\u064a\u0629)"
    ],
    "name:ara_x_variant":[
        "\u0627\u0644\u0631\u0634\u064a\u062f\u064a\u0629"
    ],
    "name:azb_x_preferred":[
        "\u0631\u0634\u06cc\u062f\u06cc\u0647"
    ],
    "name:cat_x_preferred":[
        "Rachidia"
    ],
    "name:ceb_x_preferred":[
        "Errachidia"
    ],
    "name:deu_x_preferred":[
        "Errachidia"
    ],
    "name:eng_x_preferred":[
        "Errachidia"
    ],
    "name:fas_x_preferred":[
        "\u0631\u0634\u06cc\u062f\u06cc\u0647"
    ],
    "name:fra_x_preferred":[
        "Errachidia"
    ],
    "name:fra_x_variant":[
        "Errachidia (MU)",
        "Errachidia (Commune Urbaine)"
    ],
    "name:heb_x_preferred":[
        "\u05d0-\u05e8\u05e9\u05d9\u05d3\u05d9\u05d4"
    ],
    "name:ita_x_preferred":[
        "Al-Rashidiyya"
    ],
    "name:jpn_x_preferred":[
        "\u30a8\u30eb\u30e9\u30b7\u30c7\u30a3\u30a2"
    ],
    "name:kab_x_preferred":[
        "Imet\u0263aren"
    ],
    "name:kor_x_preferred":[
        "\uc5d0\ub77c\uc2dc\ub514\uc544"
    ],
    "name:lav_x_preferred":[
        "R\u0101\u0161\u012bd\u012bja"
    ],
    "name:lit_x_preferred":[
        "Er Ra\u0161idija"
    ],
    "name:nld_x_preferred":[
        "Errachidia"
    ],
    "name:pol_x_preferred":[
        "Ar-Raszidija"
    ],
    "name:por_x_preferred":[
        "Errachidia"
    ],
    "name:ron_x_preferred":[
        "Er Rachidia"
    ],
    "name:rus_x_preferred":[
        "\u042d\u0440-\u0420\u0430\u0448\u0438\u0434\u0438\u044f"
    ],
    "name:spa_x_preferred":[
        "Er-Rachid\u00eda"
    ],
    "name:swe_x_preferred":[
        "Errachidia"
    ],
    "name:urd_x_preferred":[
        "\u0627\u0644\u0631\u0634\u06cc\u062f\u06cc\u06c1"
    ],
    "name:zho_x_preferred":[
        "\u62c9\u5e0c\u8fea\u8036"
    ],
    "qs:name":"Errachidia",
    "qs:photos_9r":0,
    "qs:photos_sr":0,
    "qs:pop_sr":"8",
    "wd:wordcount":106,
    "wof:name":"Errachidia",
    "wof:placetype":"localadmin",
    "wof:population":75239
},
  "geometry": {"coordinates":[-4.43588,31.93055],"type":"Point"}
}