{
  "type": "Feature",
  "properties": {
    "gn:country":"MA",
    "gn:fcode":"ADM3",
    "gn:pop":75239,
    "iso:country":"MA",
    "name:ara_x_preferred":[
        "\u0628\u0648\u0630\u0646\u064a\u0628 (\u0627\u0644\u0628\u0644\u062f\u064a\u0629)"
    ],
    "name:fra_x_preferred":[
        "Errachidia"
    ],
    "name:fra_x_variant":[
        "Errachidia (MU)",
        "Errachidia (Commune Urbaine)"
    ],
    "qs:name":"Errachidia",
    "qs:photos_9r":0,
    "qs:photos_sr":0,
    "qs:pop_sr":"8",
    "wd:wordcount":106,
    "wof:name":"Errachidia",
    "wof:placetype":"localadmin",
    "wof:population":75239
},
  "geometry": {"coordinates":[-4.43588,31.93055],"type":"Point"}
}