{
  "type": "Feature",
  "properties": {
    "gn:admin1_code":"9.0",
    "gn:asciiname":"Amigdoul",
    "gn:country_code":"MA",
    "gn:dem":925,
    "gn:feature_class":"P",
    "gn:feature_code":"PPL",
    "gn:name":"Amigdoul",
    "gn:population":0,
    "gn:timezone":"Africa/Casablanca",
    "iso:country":"MA",
    "wof:name":"Amigdoul",
    "wof:placetype":"locality"
},
  "geometry": {"coordinates":[-8.9285,30.673],"type":"Point"}
}