{
  "type": "Feature",
  "properties": {
    "gn:admin1_code":"7.0",
    "gn:asciiname":"Idou Mnail",
    "gn:country_code":"MA",
    "gn:dem":343,
    "gn:feature_class":"P",
    "gn:feature_code":"PPL",
    "gn:name":"Idou Mna\u00efl",
    "gn:population":0,
    "gn:timezone":"Africa/Casablanca",
    "iso:country":"MA",
    "wof:name":"Idou Mnail",
    "wof:placetype":"locality"
},
  "geometry": {"coordinates":[-9.67761,30.95208],"type":"Point"}
}