{
  "type": "Feature",
  "properties": {
    "gn:admin1_code":"8.0",
    "gn:asciiname":"Zawia",
    "gn:country_code":"MA",
    "gn:dem":761,
    "gn:feature_class":"P",
    "gn:feature_code":"PPL",
    "gn:name":"Zawia",
    "gn:population":0,
    "gn:timezone":"Africa/Casablanca",
    "iso:country":"MA",
    "wof:name":"Zawia",
    "wof:placetype":"locality"
},
  "geometry": {"coordinates":[-4.28472,31.25723],"type":"Point"}
}