{
  "type": "Feature",
  "properties": {
    "gn:admin1_code":"08",
    "gn:asciiname":"Timekkit",
    "gn:country_code":"MA",
    "gn:dem":1290,
    "gn:feature_class":"P",
    "gn:feature_code":"PPL",
    "gn:name":"Timekkit",
    "gn:population":0,
    "gn:timezone":"Africa/Casablanca",
    "iso:country":"MA",
    "name:und_x_variant":[
        "Timka\u00efte",
        "Timkete",
        "Timekkit"
    ],
    "wof:name":"Timekkit",
    "wof:placetype":"locality"
},
  "geometry": {"coordinates":[-5.31886,31.63628],"type":"Point"}
}