{
  "type": "Feature",
  "properties": {
    "gn:admin1_code":"9.0",
    "gn:asciiname":"Izwirry",
    "gn:country_code":"MA",
    "gn:dem":1358,
    "gn:feature_class":"P",
    "gn:feature_code":"PPL",
    "gn:name":"Izwirry",
    "gn:population":0,
    "gn:timezone":"Africa/Casablanca",
    "iso:country":"MA",
    "wof:name":"Izwirry",
    "wof:placetype":"locality"
},
  "geometry": {"coordinates":[-8.81138,30.04867],"type":"Point"}
}