{
  "type": "Feature",
  "properties": {
    "gn:admin1_code":"6.0",
    "gn:asciiname":"Douar Laqwadra",
    "gn:country_code":"MA",
    "gn:dem":139,
    "gn:feature_class":"P",
    "gn:feature_code":"PPL",
    "gn:name":"Douar Laqwadra",
    "gn:population":0,
    "gn:timezone":"Africa/Casablanca",
    "iso:country":"MA",
    "wof:name":"Douar Laqwadra",
    "wof:placetype":"locality"
},
  "geometry": {"coordinates":[-8.64016,32.74988],"type":"Point"}
}