{
  "type": "Feature",
  "properties": {
    "gn:admin1_code":"09",
    "gn:asciiname":"Ait Soummane",
    "gn:country_code":"MA",
    "gn:dem":427,
    "gn:feature_class":"P",
    "gn:feature_code":"PPL",
    "gn:name":"A\u00eft Soummane",
    "gn:population":0,
    "gn:timezone":"Africa/Casablanca",
    "iso:country":"MA",
    "name:und_x_variant":[
        "A\u00eft Soummane",
        "A\u00eft Soumouane"
    ],
    "wof:name":"Ait Soummane",
    "wof:placetype":"locality"
},
  "geometry": {"coordinates":[-8.5735,30.62444],"type":"Point"}
}