{
  "type": "Feature",
  "properties": {
    "gn:admin1_code":"7.0",
    "gn:asciiname":"Cooperative Ibrahimia",
    "gn:country_code":"MA",
    "gn:dem":140,
    "gn:feature_class":"P",
    "gn:feature_code":"PPL",
    "gn:name":"Coop\u00e8rative Ibrahimia",
    "gn:population":0,
    "gn:timezone":"Africa/Casablanca",
    "iso:country":"MA",
    "wof:name":"Cooperative Ibrahimia",
    "wof:placetype":"locality"
},
  "geometry": {"coordinates":[-8.90608,32.47958],"type":"Point"}
}