{
  "type": "Feature",
  "properties": {
    "gn:admin1_code":"03",
    "gn:asciiname":"Douar Chtatoua",
    "gn:country_code":"MA",
    "gn:dem":521,
    "gn:feature_class":"P",
    "gn:feature_code":"PPL",
    "gn:name":"Douar Chtatoua",
    "gn:population":0,
    "gn:timezone":"Africa/Casablanca",
    "iso:country":"MA",
    "name:und_x_variant":[
        "Chtatoua"
    ],
    "wof:name":"Douar Chtatoua",
    "wof:placetype":"locality"
},
  "geometry": {"coordinates":[-4.298,34.30932],"type":"Point"}
}