{
  "type": "Feature",
  "properties": {
    "gn:admin1_code":"01",
    "gn:asciiname":"Lafriyyene",
    "gn:country_code":"MA",
    "gn:dem":61,
    "gn:feature_class":"P",
    "gn:feature_code":"PPLL",
    "gn:name":"Lafriyyene",
    "gn:population":0,
    "gn:timezone":"Africa/Casablanca",
    "iso:country":"MA",
    "wof:name":"Lafriyyene",
    "wof:placetype":"locality"
},
  "geometry": {"coordinates":[-6.00433,35.44162],"type":"Point"}
}