{
  "type": "Feature",
  "properties": {
    "gn:admin1_code":"4.0",
    "gn:asciiname":"Douar Tizi Mouka",
    "gn:country_code":"MA",
    "gn:dem":295,
    "gn:feature_class":"P",
    "gn:feature_code":"PPL",
    "gn:name":"Douar Tizi Mouka",
    "gn:population":0,
    "gn:timezone":"Africa/Casablanca",
    "iso:country":"MA",
    "wof:name":"Douar Tizi Mouka",
    "wof:placetype":"locality"
},
  "geometry": {"coordinates":[-6.34717,33.62085],"type":"Point"}
}