{
  "type": "Feature",
  "properties": {
    "gn:admin1_code":"9.0",
    "gn:asciiname":"Amdrous",
    "gn:country_code":"MA",
    "gn:dem":1186,
    "gn:feature_class":"P",
    "gn:feature_code":"PPL",
    "gn:name":"Amdrous",
    "gn:population":0,
    "gn:timezone":"Africa/Casablanca",
    "iso:country":"MA",
    "wof:name":"Amdrous",
    "wof:placetype":"locality"
},
  "geometry": {"coordinates":[-9.28526,29.55379000000001],"type":"Point"}
}