{
  "type": "Feature",
  "properties": {
    "gn:admin1_code":"10.0",
    "gn:asciiname":"Id Bibi",
    "gn:country_code":"MA",
    "gn:dem":804,
    "gn:feature_class":"P",
    "gn:feature_code":"PPL",
    "gn:name":"Id Bibi",
    "gn:population":0,
    "gn:timezone":"Africa/Casablanca",
    "iso:country":"MA",
    "wof:name":"Id Bibi",
    "wof:placetype":"locality"
},
  "geometry": {"coordinates":[-9.78971,29.40762],"type":"Point"}
}