{
  "type": "Feature",
  "properties": {
    "gn:admin1_code":"7.0",
    "gn:asciiname":"Ancien Cafe",
    "gn:country_code":"MA",
    "gn:dem":45,
    "gn:feature_class":"P",
    "gn:feature_code":"PPL",
    "gn:name":"Ancien Cafe",
    "gn:population":0,
    "gn:timezone":"Africa/Casablanca",
    "iso:country":"MA",
    "wof:name":"Ancien Cafe",
    "wof:placetype":"locality"
},
  "geometry": {"coordinates":[-9.26066,32.17284],"type":"Point"}
}