{
  "type": "Feature",
  "properties": {
    "gn:country":"MA",
    "gn:fcode":"ADM3",
    "gn:population":404,
    "iso:country":"MA",
    "name:ara_x_preferred":[
        "\u0645\u064a\u062c\u064a\u0643"
    ],
    "name:ara_x_variant":[
        "\u0623\u0645 \u0627\u062f\u0631\u064a\u0643\u0629"
    ],
    "name:cat_x_preferred":[
        "Oum Dreyga"
    ],
    "name:ceb_x_preferred":[
        "Oum Dreyga"
    ],
    "name:epo_x_preferred":[
        "Umm Dreiga"
    ],
    "name:fra_x_preferred":[
        "Oum Dreyga"
    ],
    "name:fra_x_variant":[
        "Oum Dreyga (CR)",
        "Oum Dreyga (Commune Rurale)"
    ],
    "name:ita_x_preferred":[
        "Umm Dreiga"
    ],
    "name:swe_x_preferred":[
        "Oum Dreyga"
    ],
    "qs_pg:aaroncc":"MA",
    "qs_pg:gn_country":"MA",
    "qs_pg:gn_fcode":"ADM3",
    "qs_pg:gn_pop":404,
    "qs_pg:name":"Oum Dreyga",
    "qs_pg:photos_9r":0,
    "qs_pg:photos_sr":0,
    "qs_pg:pop_sr":2,
    "qs_pg:qs_pg_placetype":"localadmin",
    "wof:name":"Oum Dreyga",
    "wof:placetype":"localadmin",
    "wof:population":404
},
  "geometry": {"coordinates":[-13.50212,24.15433],"type":"Point"}
}