{
  "type": "Feature",
  "properties": {
    "gn:admin1_code":"04",
    "gn:asciiname":"Laassala",
    "gn:country_code":"MA",
    "gn:dem":13,
    "gn:feature_class":"P",
    "gn:feature_code":"PPL",
    "gn:name":"Laassala",
    "gn:population":0,
    "gn:timezone":"Africa/Casablanca",
    "iso:country":"MA",
    "name:und_x_variant":[
        "Assala",
        "Douar el Assala",
        "El Assala",
        "Laassala"
    ],
    "wof:name":"Laassala",
    "wof:placetype":"locality"
},
  "geometry": {"coordinates":[-6.20315,34.58662],"type":"Point"}
}