{
  "type": "Feature",
  "properties": {
    "gn:admin1_code":"08",
    "gn:asciiname":"Ait Ben Mohammed",
    "gn:country_code":"MA",
    "gn:dem":601,
    "gn:feature_class":"P",
    "gn:feature_code":"PPL",
    "gn:name":"A\u00eft Ben Mohammed",
    "gn:population":0,
    "gn:timezone":"Africa/Casablanca",
    "iso:country":"MA",
    "name:und_x_variant":[
        "A\u00eft Bo\u00fb Mhamed",
        "A\u00eft Ben Mohammed"
    ],
    "wof:name":"Ait Ben Mohammed",
    "wof:placetype":"locality"
},
  "geometry": {"coordinates":[-5.56,29.96],"type":"Point"}
}