{
  "type": "Feature",
  "properties": {
    "gn:admin1_code":"2.0",
    "gn:asciiname":"Jaddi Hssayene",
    "gn:country_code":"MA",
    "gn:dem":573,
    "gn:feature_class":"P",
    "gn:feature_code":"PPL",
    "gn:name":"Jaddi Hssayene",
    "gn:population":0,
    "gn:timezone":"Africa/Casablanca",
    "iso:country":"MA",
    "wof:name":"Jaddi Hssayene",
    "wof:placetype":"locality"
},
  "geometry": {"coordinates":[-3.5872,35.05928],"type":"Point"}
}