{
  "type": "Feature",
  "properties": {
    "gn:admin1_code":"7.0",
    "gn:asciiname":"Douar Jnane Lahrach",
    "gn:country_code":"MA",
    "gn:dem":33,
    "gn:feature_class":"P",
    "gn:feature_code":"PPL",
    "gn:name":"Douar Jnane Lahrach",
    "gn:population":0,
    "gn:timezone":"Africa/Casablanca",
    "iso:country":"MA",
    "wof:name":"Douar Jnane Lahrach",
    "wof:placetype":"locality"
},
  "geometry": {"coordinates":[-9.64932,31.66822],"type":"Point"}
}