{
  "type": "Feature",
  "properties": {
    "gn:admin1_code":"07",
    "gn:asciiname":"Tawrirt",
    "gn:country_code":"MA",
    "gn:dem":926,
    "gn:feature_class":"P",
    "gn:feature_code":"PPL",
    "gn:name":"Tawrirt",
    "gn:population":0,
    "gn:timezone":"Africa/Casablanca",
    "iso:country":"MA",
    "name:und_x_variant":[
        "Tamarirt"
    ],
    "wof:name":"Tawrirt",
    "wof:placetype":"locality"
},
  "geometry": {"coordinates":[-8.61035,31.22487000000001],"type":"Point"}
}