{
  "type": "Feature",
  "properties": {
    "gn:admin1_code":"2.0",
    "gn:asciiname":"Taghilast",
    "gn:country_code":"MA",
    "gn:dem":434,
    "gn:feature_class":"P",
    "gn:feature_code":"PPL",
    "gn:name":"Taghilast",
    "gn:population":0,
    "gn:timezone":"Africa/Casablanca",
    "iso:country":"MA",
    "wof:name":"Taghilast",
    "wof:placetype":"locality"
},
  "geometry": {"coordinates":[-3.4816,35.04391],"type":"Point"}
}