{
  "type": "Feature",
  "properties": {
    "gn:admin1_code":"09",
    "gn:asciiname":"Irhir",
    "gn:country_code":"MA",
    "gn:dem":1173,
    "gn:feature_class":"P",
    "gn:feature_code":"PPL",
    "gn:name":"Irhir",
    "gn:population":0,
    "gn:timezone":"Africa/Casablanca",
    "iso:country":"MA",
    "wof:name":"Irhir",
    "wof:placetype":"locality"
},
  "geometry": {"coordinates":[-8.36,30.33],"type":"Point"}
}