{
  "type": "Feature",
  "properties": {
    "gn:admin1_code":"03",
    "gn:asciiname":"Olad. Daoud",
    "gn:country_code":"MA",
    "gn:dem":632,
    "gn:feature_class":"P",
    "gn:feature_code":"PPL",
    "gn:name":"Olad. Daoud",
    "gn:population":0,
    "gn:timezone":"Africa/Casablanca",
    "iso:country":"MA",
    "name:und_x_variant":[
        "Oulad Daoud"
    ],
    "wof:name":"Olad. Daoud",
    "wof:placetype":"locality"
},
  "geometry": {"coordinates":[-4.09773,34.26213],"type":"Point"}
}