{
  "type": "Feature",
  "properties": {
    "gn:admin1_code":"5.0",
    "gn:asciiname":"Irherm Abalya",
    "gn:country_code":"MA",
    "gn:dem":803,
    "gn:feature_class":"P",
    "gn:feature_code":"PPL",
    "gn:name":"Irherm Abalya",
    "gn:population":0,
    "gn:timezone":"Africa/Casablanca",
    "iso:country":"MA",
    "wof:name":"Irherm Abalya",
    "wof:placetype":"locality"
},
  "geometry": {"coordinates":[-5.98733,32.86218],"type":"Point"}
}