{
  "type": "Feature",
  "properties": {
    "gn:gn_country":"MA",
    "gn:gn_fcode":"ADM3",
    "gn:gn_pop":398131,
    "gn:population":398131,
    "iso:country":"MA",
    "name:ara_x_preferred":[
        "\u0623\u0648\u0644\u0627\u062f \u0627\u0645\u062d\u0645\u062f"
    ],
    "name:ara_x_variant":[
        "\u0648\u062c\u062f\u0629"
    ],
    "name:azb_x_preferred":[
        "\u0648\u062c\u062f\u0647"
    ],
    "name:bel_x_preferred":[
        "\u0423\u0434\u0436\u0434\u0430"
    ],
    "name:bre_x_preferred":[
        "Oujda"
    ],
    "name:bul_x_preferred":[
        "\u0423\u0434\u0436\u0434\u0430"
    ],
    "name:cat_x_preferred":[
        "Oujda"
    ],
    "name:ceb_x_preferred":[
        "Oujda"
    ],
    "name:ces_x_preferred":[
        "Ud\u017eda"
    ],
    "name:cym_x_preferred":[
        "Oujda"
    ],
    "name:dan_x_preferred":[
        "Oujda"
    ],
    "name:deu_x_preferred":[
        "Oujda"
    ],
    "name:epo_x_preferred":[
        "U\u011dda"
    ],
    "name:eus_x_preferred":[
        "Ujda"
    ],
    "name:fas_x_preferred":[
        "\u0648\u062c\u062f\u0647"
    ],
    "name:fin_x_preferred":[
        "Oujda"
    ],
    "name:fra_x_preferred":[
        "Oujda"
    ],
    "name:fra_x_variant":[
        "Oujda (MU)",
        "Oujda (Commune Urbaine)"
    ],
    "name:glg_x_preferred":[
        "Oujda"
    ],
    "name:heb_x_preferred":[
        "\u05d0\u05d5\u05d2'\u05d3\u05d4"
    ],
    "name:hrv_x_preferred":[
        "Oujda"
    ],
    "name:hun_x_preferred":[
        "Oujda"
    ],
    "name:ile_x_preferred":[
        "Oujda"
    ],
    "name:ind_x_preferred":[
        "Oujda"
    ],
    "name:ita_x_preferred":[
        "Oujda"
    ],
    "name:jpn_x_preferred":[
        "\u30a6\u30b8\u30c0"
    ],
    "name:kab_x_preferred":[
        "Wejdet"
    ],
    "name:kaz_x_preferred":[
        "\u0423\u0434\u0436\u0434\u0430"
    ],
    "name:kor_x_preferred":[
        "\uc6b0\uc9c0\ub2e4"
    ],
    "name:kur_x_preferred":[
        "Oujda"
    ],
    "name:lit_x_preferred":[
        "Ud\u017eda"
    ],
    "name:mkd_x_preferred":[
        "\u0423\u045f\u0434\u0430"
    ],
    "name:nld_x_preferred":[
        "Oujda"
    ],
    "name:nor_x_preferred":[
        "Oujda"
    ],
    "name:pol_x_preferred":[
        "Wad\u017cda"
    ],
    "name:por_x_preferred":[
        "Ujda"
    ],
    "name:ron_x_preferred":[
        "Oujda"
    ],
    "name:rus_x_preferred":[
        "\u0423\u0434\u0436\u0434\u0430"
    ],
    "name:sco_x_preferred":[
        "Oujda"
    ],
    "name:spa_x_preferred":[
        "Uchda"
    ],
    "name:sqi_x_preferred":[
        "Uxhda"
    ],
    "name:swe_x_preferred":[
        "Oujda"
    ],
    "name:tur_x_preferred":[
        "Ucda"
    ],
    "name:twi_x_preferred":[
        "Oujda"
    ],
    "name:ukr_x_preferred":[
        "\u0423\u0434\u0436\u0434\u0430"
    ],
    "name:urd_x_preferred":[
        "\u0648\u062c\u062f\u06c1"
    ],
    "name:vie_x_preferred":[
        "Oujda"
    ],
    "name:war_x_preferred":[
        "Oujda"
    ],
    "name:zho_x_preferred":[
        "\u4e4c\u5b63\u8fbe"
    ],
    "qs_pg:aaroncc":"MA",
    "qs_pg:gn_country":"MA",
    "qs_pg:gn_fcode":"ADM3",
    "qs_pg:gn_pop":398131,
    "qs_pg:name":"Oujda",
    "qs_pg:photos_9r":0,
    "qs_pg:photos_sr":0,
    "qs_pg:pop_sr":10,
    "qs_pg:qs_pg_placetype":"localadmin",
    "wof:name":"Oujda",
    "wof:placetype":"localadmin",
    "wof:population":398131
},
  "geometry": {"coordinates":[-1.9108,34.68288],"type":"Point"}
}