{
  "type": "Feature",
  "properties": {
    "gn:gn_country":"MA",
    "gn:gn_fcode":"ADM3",
    "gn:gn_pop":398131,
    "gn:population":398131,
    "iso:country":"MA",
    "name:ara_x_preferred":[
        "\u0623\u0648\u0644\u0627\u062f \u0627\u0645\u062d\u0645\u062f"
    ],
    "name:fra_x_preferred":[
        "Oujda"
    ],
    "name:fra_x_variant":[
        "Oujda (MU)",
        "Oujda (Commune Urbaine)"
    ],
    "qs_pg:aaroncc":"MA",
    "qs_pg:gn_country":"MA",
    "qs_pg:gn_fcode":"ADM3",
    "qs_pg:gn_pop":398131,
    "qs_pg:name":"Oujda",
    "qs_pg:photos_9r":0,
    "qs_pg:photos_sr":0,
    "qs_pg:pop_sr":10,
    "qs_pg:qs_pg_placetype":"localadmin",
    "wof:name":"Oujda",
    "wof:placetype":"localadmin",
    "wof:population":398131
},
  "geometry": {"coordinates":[-1.9108,34.68288],"type":"Point"}
}