{
  "type": "Feature",
  "properties": {
    "gn:admin1_code":"09",
    "gn:asciiname":"Sinns",
    "gn:country_code":"MA",
    "gn:dem":592,
    "gn:feature_class":"P",
    "gn:feature_code":"PPL",
    "gn:name":"Sinns",
    "gn:population":0,
    "gn:timezone":"Africa/Casablanca",
    "iso:country":"MA",
    "name:und_x_variant":[
        "Sins"
    ],
    "wof:name":"Sinns",
    "wof:placetype":"locality"
},
  "geometry": {"coordinates":[-8.54339,30.70133],"type":"Point"}
}