{
  "type": "Feature",
  "properties": {
    "iso:country":"MA",
    "name:ara_x_preferred":[
        "\u0627\u0644\u0641\u0646\u064a\u062f\u0642"
    ],
    "name:arg_x_preferred":[
        "Fnideq"
    ],
    "name:azb_x_preferred":[
        "\u0641\u0646\u06cc\u062f\u0642"
    ],
    "name:bul_x_preferred":[
        "\u0424\u043d\u0438\u0434\u0435\u043a"
    ],
    "name:cat_x_preferred":[
        "Fnideq"
    ],
    "name:ceb_x_preferred":[
        "Fnidek"
    ],
    "name:deu_x_preferred":[
        "Fnideq"
    ],
    "name:eng_x_preferred":[
        "Fnideq"
    ],
    "name:eus_x_preferred":[
        "Fnideq"
    ],
    "name:fas_x_preferred":[
        "\u0641\u0646\u06cc\u062f\u0642"
    ],
    "name:fra_x_preferred":[
        "Fnideq"
    ],
    "name:ita_x_preferred":[
        "Fnidq"
    ],
    "name:jpn_x_preferred":[
        "\u30d5\u30cb\u30c7\u30af"
    ],
    "name:kab_x_preferred":[
        "Fnideq"
    ],
    "name:nld_x_preferred":[
        "Fnideq"
    ],
    "name:pol_x_preferred":[
        "Al-Funajdik"
    ],
    "name:por_x_preferred":[
        "Fnideq"
    ],
    "name:rus_x_preferred":[
        "\u0424\u043d\u0438\u0434\u043a"
    ],
    "name:spa_x_preferred":[
        "Castillejos"
    ],
    "name:srd_x_preferred":[
        "Fnideq"
    ],
    "name:swe_x_preferred":[
        "Fnideq"
    ],
    "name:unk_x_variant":[
        "Los Castillejos"
    ],
    "name:urd_x_preferred":[
        "\u0641\u0646\u06cc\u062f\u0642"
    ],
    "qs:gn_country":"MA",
    "qs:gn_fcode":"PPL",
    "qs:gn_pop":0,
    "qs:name":"Fnideq",
    "qs:name_adm0":"\u0627\u0644\u0645\u063a\u0631\u0628",
    "qs:name_adm1":"\u0637\u0646\u062c\u0629\u0640 \u062a\u0637\u0648\u0627\u0646",
    "qs:photos":163,
    "qs:photos_1k":33,
    "qs:photos_9k":1,
    "qs:photos_9r":4,
    "qs:photos_all":163,
    "qs:photos_sr":4,
    "qs:placetype":"Town",
    "qs:pop_sr":"0",
    "qs:woe_adm0":23424893,
    "wd:wordcount":60,
    "wof:name":"Fnideq",
    "wof:placetype":"locality"
},
  "geometry": {"coordinates":[-5.35747,35.84906],"type":"Point"}
}