{
  "type": "Feature",
  "properties": {
    "gn:admin1_code":"55",
    "gn:asciiname":"Sidi Mimoun",
    "gn:country_code":"MA",
    "gn:dem":18,
    "gn:feature_class":"P",
    "gn:feature_code":"PPL",
    "gn:name":"Sidi Mimoun",
    "gn:population":0,
    "gn:timezone":"Africa/Casablanca",
    "iso:country":"MA",
    "wof:name":"Sidi Mimoun",
    "wof:placetype":"locality"
},
  "geometry": {"coordinates":[-9.51,30.33],"type":"Point"}
}