{
  "type": "Feature",
  "properties": {
    "gn:admin1_code":"07",
    "gn:asciiname":"Oulad Mbarek",
    "gn:country_code":"MA",
    "gn:dem":176,
    "gn:feature_class":"P",
    "gn:feature_code":"PPL",
    "gn:name":"Oulad Mbarek",
    "gn:population":0,
    "gn:timezone":"Africa/Casablanca",
    "iso:country":"MA",
    "name:und_x_variant":[
        "Douar Oulad Mbarek",
        "Ouled M\u2019barek Chedmi",
        "Oulad Mbarek"
    ],
    "wof:name":"Oulad Mbarek",
    "wof:placetype":"locality"
},
  "geometry": {"coordinates":[-8.84364,32.42126],"type":"Point"}
}