{
  "type": "Feature",
  "properties": {
    "gn:admin1_code":"9.0",
    "gn:asciiname":"Taourirt Id ben Sras",
    "gn:country_code":"MA",
    "gn:dem":232,
    "gn:feature_class":"P",
    "gn:feature_code":"PPL",
    "gn:name":"Taourirt Id ben Sras",
    "gn:population":0,
    "gn:timezone":"Africa/Casablanca",
    "iso:country":"MA",
    "wof:name":"Taourirt Id ben Sras",
    "wof:placetype":"locality"
},
  "geometry": {"coordinates":[-9.6795,30.77502],"type":"Point"}
}