{
  "type": "Feature",
  "properties": {
    "gn:admin1_code":"03",
    "gn:asciiname":"Kasba Mohammed Ameziane",
    "gn:country_code":"MA",
    "gn:dem":1222,
    "gn:feature_class":"P",
    "gn:feature_code":"PPL",
    "gn:name":"Kasba Mohammed Ameziane",
    "gn:population":0,
    "gn:timezone":"Africa/Casablanca",
    "iso:country":"MA",
    "name:und_x_variant":[
        "A\u00eft M\u2019hamed Im\u00e9ziane",
        "Kasba Mohammed Ameziane"
    ],
    "wof:name":"Kasba Mohammed Ameziane",
    "wof:placetype":"locality"
},
  "geometry": {"coordinates":[-4.39605,33.52014],"type":"Point"}
}