{
  "type": "Feature",
  "properties": {
    "gn:admin1_code":"09",
    "gn:asciiname":"Taddart",
    "gn:country_code":"MA",
    "gn:dem":1040,
    "gn:feature_class":"P",
    "gn:feature_code":"PPL",
    "gn:name":"Taddart",
    "gn:population":0,
    "gn:timezone":"Africa/Casablanca",
    "iso:country":"MA",
    "name:und_x_variant":[
        "Tadarte",
        "Zaouia Taddert",
        "Taddart"
    ],
    "wof:name":"Taddart",
    "wof:placetype":"locality"
},
  "geometry": {"coordinates":[-8.0815,30.67035],"type":"Point"}
}