{
  "type": "Feature",
  "properties": {
    "gn:admin1_code":"9.0",
    "gn:asciiname":"Doutirourt",
    "gn:country_code":"MA",
    "gn:dem":604,
    "gn:feature_class":"P",
    "gn:feature_code":"PPL",
    "gn:name":"Doutirourt",
    "gn:population":0,
    "gn:timezone":"Africa/Casablanca",
    "iso:country":"MA",
    "wof:name":"Doutirourt",
    "wof:placetype":"locality"
},
  "geometry": {"coordinates":[-9.8731,29.45922],"type":"Point"}
}