{
  "type": "Feature",
  "properties": {
    "gn:admin1_code":"1.0",
    "gn:asciiname":"Douar Dhar Rmel Alouanech",
    "gn:country_code":"MA",
    "gn:dem":75,
    "gn:feature_class":"P",
    "gn:feature_code":"PPL",
    "gn:name":"Douar Dhar Rmel Alouanech",
    "gn:population":0,
    "gn:timezone":"Africa/Casablanca",
    "iso:country":"MA",
    "wof:name":"Douar Dhar Rmel Alouanech",
    "wof:placetype":"locality"
},
  "geometry": {"coordinates":[-5.67619,35.61124],"type":"Point"}
}