{
  "type": "Feature",
  "properties": {
    "gn:country":"MA",
    "gn:fcode":"ADM3",
    "gn:pop":1138,
    "iso:country":"MA",
    "name:ara_x_preferred":[
        "\u062a\u0644\u0648\u064a\u0646 \u0627\u0633\u0627\u0643\u0627"
    ],
    "name:fra_x_preferred":[
        "Targa Wassay"
    ],
    "name:fra_x_variant":[
        "Targa Wassay (CR)",
        "Targa Wassay (Commune Rurale)"
    ],
    "qs:name":"Targa Wassay",
    "qs:photos_9r":0,
    "qs:photos_sr":0,
    "qs:pop_sr":"3",
    "wof:name":"Targa Wassay",
    "wof:placetype":"localadmin",
    "wof:population":1138
},
  "geometry": {"coordinates":[-10.26197,29.05663],"type":"Point"}
}