{
  "type": "Feature",
  "properties": {
    "gn:admin1_code":"2.0",
    "gn:asciiname":"Ellayl",
    "gn:country_code":"MA",
    "gn:dem":68,
    "gn:feature_class":"P",
    "gn:feature_code":"PPL",
    "gn:name":"Ellayl",
    "gn:population":0,
    "gn:timezone":"Africa/Casablanca",
    "iso:country":"MA",
    "wof:name":"Ellayl",
    "wof:placetype":"locality"
},
  "geometry": {"coordinates":[-2.94557,35.08208],"type":"Point"}
}