{
  "type": "Feature",
  "properties": {
    "gn:admin1_code":"1.0",
    "gn:asciiname":"Ahriq Lousli",
    "gn:country_code":"MA",
    "gn:dem":56,
    "gn:feature_class":"P",
    "gn:feature_code":"PPL",
    "gn:name":"Ahriq Lousli",
    "gn:population":0,
    "gn:timezone":"Africa/Casablanca",
    "iso:country":"MA",
    "wof:name":"Ahriq Lousli",
    "wof:placetype":"locality"
},
  "geometry": {"coordinates":[-5.36436,35.55202],"type":"Point"}
}