{
  "type": "Feature",
  "properties": {
    "gn:admin1_code":"3.0",
    "gn:asciiname":"Douar Dinanat",
    "gn:country_code":"MA",
    "gn:dem":582,
    "gn:feature_class":"P",
    "gn:feature_code":"PPL",
    "gn:name":"Douar Dinanat",
    "gn:population":0,
    "gn:timezone":"Africa/Casablanca",
    "iso:country":"MA",
    "wof:name":"Douar Dinanat",
    "wof:placetype":"locality"
},
  "geometry": {"coordinates":[-4.55795,34.20611],"type":"Point"}
}