{
  "type": "Feature",
  "properties": {
    "gn:admin1_code":"7.0",
    "gn:asciiname":"H'ritiers El Ghandour Abdeljalil",
    "gn:country_code":"MA",
    "gn:dem":384,
    "gn:feature_class":"P",
    "gn:feature_code":"PPL",
    "gn:name":"H\u2019ritiers El Ghandour Abdeljalil",
    "gn:population":0,
    "gn:timezone":"Africa/Casablanca",
    "iso:country":"MA",
    "wof:name":"H'ritiers El Ghandour Abdeljalil",
    "wof:placetype":"locality"
},
  "geometry": {"coordinates":[-8.38824,31.60883],"type":"Point"}
}