{
  "type": "Feature",
  "properties": {
    "gn:admin1_code":"7.0",
    "gn:asciiname":"Khyam Oulad Essifer",
    "gn:country_code":"MA",
    "gn:dem":333,
    "gn:feature_class":"P",
    "gn:feature_code":"PPL",
    "gn:name":"Khyam Oulad Essifer",
    "gn:population":0,
    "gn:timezone":"Africa/Casablanca",
    "iso:country":"MA",
    "wof:name":"Khyam Oulad Essifer",
    "wof:placetype":"locality"
},
  "geometry": {"coordinates":[-8.25711,31.73409],"type":"Point"}
}