{
  "type": "Feature",
  "properties": {
    "gn:admin1_code":"01",
    "gn:asciiname":"Haoutiene",
    "gn:country_code":"MA",
    "gn:dem":1270,
    "gn:feature_class":"P",
    "gn:feature_code":"PPL",
    "gn:name":"Haoutiene",
    "gn:population":0,
    "gn:timezone":"Africa/Casablanca",
    "iso:country":"MA",
    "wof:name":"Haoutiene",
    "wof:placetype":"locality"
},
  "geometry": {"coordinates":[-5.15496,35.20303],"type":"Point"}
}