{
  "type": "Feature",
  "properties": {
    "gn:admin1_code":"06",
    "gn:asciiname":"El Maalmine",
    "gn:country_code":"MA",
    "gn:dem":432,
    "gn:feature_class":"P",
    "gn:feature_code":"PPL",
    "gn:name":"El Maalmine",
    "gn:population":0,
    "gn:timezone":"Africa/Casablanca",
    "iso:country":"MA",
    "wof:name":"El Maalmine",
    "wof:placetype":"locality"
},
  "geometry": {"coordinates":[-7.60065,32.63108],"type":"Point"}
}