{
  "type": "Feature",
  "properties": {
    "gn:admin1_code":"3.0",
    "gn:asciiname":"Douar Ait Said Ou Abderralureine",
    "gn:country_code":"MA",
    "gn:dem":1572,
    "gn:feature_class":"P",
    "gn:feature_code":"PPL",
    "gn:name":"Douar Ait Said Ou Abderralureine",
    "gn:population":0,
    "gn:timezone":"Africa/Casablanca",
    "iso:country":"MA",
    "wof:name":"Douar Ait Said Ou Abderralureine",
    "wof:placetype":"locality"
},
  "geometry": {"coordinates":[-4.96921,33.63362],"type":"Point"}
}