{
  "type": "Feature",
  "properties": {
    "gn:admin1_code":"09",
    "gn:asciiname":"Tagoudicht",
    "gn:country_code":"MA",
    "gn:dem":1477,
    "gn:feature_class":"P",
    "gn:feature_code":"PPL",
    "gn:name":"Tagoudicht",
    "gn:population":0,
    "gn:timezone":"Africa/Casablanca",
    "iso:country":"MA",
    "name:und_x_variant":[
        "Tagodacht",
        "Tagoudicht"
    ],
    "wof:name":"Tagoudicht",
    "wof:placetype":"locality"
},
  "geometry": {"coordinates":[-8.63007,30.77675],"type":"Point"}
}