{
  "type": "Feature",
  "properties": {
    "gn:admin1_code":"04",
    "gn:asciiname":"Douar Sefyane",
    "gn:country_code":"MA",
    "gn:dem":296,
    "gn:feature_class":"P",
    "gn:feature_code":"PPL",
    "gn:name":"Douar Sefyane",
    "gn:population":0,
    "gn:timezone":"Africa/Casablanca",
    "iso:country":"MA",
    "name:und_x_variant":[
        "Douar Sefiane",
        "Sefian",
        "Sefiane",
        "Douar Sefyane"
    ],
    "wof:name":"Douar Sefyane",
    "wof:placetype":"locality"
},
  "geometry": {"coordinates":[-5.81525,34.78898],"type":"Point"}
}