{
  "type": "Feature",
  "properties": {
    "gn:admin1_code":"08",
    "gn:asciiname":"Ait 'Issi",
    "gn:country_code":"MA",
    "gn:dem":1371,
    "gn:feature_class":"P",
    "gn:feature_code":"PPL",
    "gn:name":"A\u00eft \u2019Issi",
    "gn:population":0,
    "gn:timezone":"Africa/Casablanca",
    "iso:country":"MA",
    "name:und_x_variant":[
        "A\u00eft \u2019Issi",
        "A\u00eft A\u00efssi"
    ],
    "wof:name":"Ait 'Issi",
    "wof:placetype":"locality"
},
  "geometry": {"coordinates":[-6.19847,31.17922],"type":"Point"}
}