{
  "type": "Feature",
  "properties": {
    "gn:admin1_code":"6.0",
    "gn:asciiname":"Daour El Qrawcha",
    "gn:country_code":"MA",
    "gn:dem":180,
    "gn:feature_class":"P",
    "gn:feature_code":"PPL",
    "gn:name":"Daour El Qrawcha",
    "gn:population":0,
    "gn:timezone":"Africa/Casablanca",
    "iso:country":"MA",
    "wof:name":"Daour El Qrawcha",
    "wof:placetype":"locality"
},
  "geometry": {"coordinates":[-8.62408,32.59619],"type":"Point"}
}