{
  "type": "Feature",
  "properties": {
    "gn:admin1_code":"7.0",
    "gn:asciiname":"Douar Azadous Id Ou Massoud",
    "gn:country_code":"MA",
    "gn:dem":365,
    "gn:feature_class":"P",
    "gn:feature_code":"PPL",
    "gn:name":"Douar Azadous Id Ou Massoud",
    "gn:population":0,
    "gn:timezone":"Africa/Casablanca",
    "iso:country":"MA",
    "wof:name":"Douar Azadous Id Ou Massoud",
    "wof:placetype":"locality"
},
  "geometry": {"coordinates":[-9.65994,31.01853],"type":"Point"}
}