{
  "type": "Feature",
  "properties": {
    "gn:admin1_code":"7.0",
    "gn:asciiname":"Douar Azib Chorfa",
    "gn:country_code":"MA",
    "gn:dem":521,
    "gn:feature_class":"P",
    "gn:feature_code":"PPL",
    "gn:name":"Douar Azib Chorfa",
    "gn:population":0,
    "gn:timezone":"Africa/Casablanca",
    "iso:country":"MA",
    "wof:name":"Douar Azib Chorfa",
    "wof:placetype":"locality"
},
  "geometry": {"coordinates":[-7.69305,31.69103],"type":"Point"}
}