{
  "type": "Feature",
  "properties": {
    "gn:admin1_code":"9.0",
    "gn:asciiname":"Zawyat-n-Wawoust",
    "gn:country_code":"MA",
    "gn:dem":1513,
    "gn:feature_class":"P",
    "gn:feature_code":"PPL",
    "gn:name":"Zawyat-n-Wawoust",
    "gn:population":0,
    "gn:timezone":"Africa/Casablanca",
    "iso:country":"MA",
    "wof:name":"Zawyat-n-Wawoust",
    "wof:placetype":"locality"
},
  "geometry": {"coordinates":[-7.89929,30.42947],"type":"Point"}
}