{
  "type": "Feature",
  "properties": {
    "gn:admin1_code":"03",
    "gn:asciiname":"Ait Omar Ou Abid",
    "gn:country_code":"MA",
    "gn:dem":1495,
    "gn:feature_class":"P",
    "gn:feature_code":"PPL",
    "gn:name":"A\u00eft Omar Ou Abid",
    "gn:population":0,
    "gn:timezone":"Africa/Casablanca",
    "iso:country":"MA",
    "name:und_x_variant":[
        "A\u00eft Amer Ou Abid",
        "Ait Amrou Abid",
        "A\u00eft Omar Ou Abid"
    ],
    "wof:name":"Ait Omar Ou Abid",
    "wof:placetype":"locality"
},
  "geometry": {"coordinates":[-4.82559,33.35819],"type":"Point"}
}