{
  "type": "Feature",
  "properties": {
    "gn:admin1_code":"9.0",
    "gn:asciiname":"Chwattat",
    "gn:country_code":"MA",
    "gn:dem":493,
    "gn:feature_class":"P",
    "gn:feature_code":"PPL",
    "gn:name":"Chwattat",
    "gn:population":0,
    "gn:timezone":"Africa/Casablanca",
    "iso:country":"MA",
    "wof:name":"Chwattat",
    "wof:placetype":"locality"
},
  "geometry": {"coordinates":[-8.48767,30.64099],"type":"Point"}
}