{
  "type": "Feature",
  "properties": {
    "gn:admin1_code":"10",
    "gn:asciiname":"Taskala",
    "gn:country_code":"MA",
    "gn:dem":827,
    "gn:feature_class":"P",
    "gn:feature_code":"PPL",
    "gn:name":"Taskala",
    "gn:population":0,
    "gn:timezone":"Africa/Casablanca",
    "iso:country":"MA",
    "name:ell_x_preferred":[
        "\u03a4\u03b1\u03c3\u03ba\u03ac\u03bb\u03b1"
    ],
    "name:kaz_x_preferred":[
        "\u0422\u0430\u0441\u049b\u0430\u043b\u0430"
    ],
    "name:rus_x_preferred":[
        "\u0422\u0430\u0441\u043a\u0430\u043b\u0430"
    ],
    "name:ukr_x_preferred":[
        "\u0422\u0430\u0441\u043a\u0430\u043b\u0430"
    ],
    "wof:name":"Taskala",
    "wof:placetype":"locality"
},
  "geometry": {"coordinates":[-9.49012,29.22302],"type":"Point"}
}