{
  "type": "Feature",
  "properties": {
    "gn:admin1_code":"10",
    "gn:asciiname":"Taskala",
    "gn:country_code":"MA",
    "gn:dem":827,
    "gn:feature_class":"P",
    "gn:feature_code":"PPL",
    "gn:name":"Taskala",
    "gn:population":0,
    "gn:timezone":"Africa/Casablanca",
    "iso:country":"MA",
    "wof:name":"Taskala",
    "wof:placetype":"locality"
},
  "geometry": {"coordinates":[-9.49012,29.22302],"type":"Point"}
}