{
  "type": "Feature",
  "properties": {
    "gn:admin1_code":"7.0",
    "gn:asciiname":"Azib el Caid",
    "gn:country_code":"MA",
    "gn:dem":770,
    "gn:feature_class":"P",
    "gn:feature_code":"PPL",
    "gn:name":"Azib el Ca\u00efd",
    "gn:population":0,
    "gn:timezone":"Africa/Casablanca",
    "iso:country":"MA",
    "wof:name":"Azib el Caid",
    "wof:placetype":"locality"
},
  "geometry": {"coordinates":[-8.10575,31.31114],"type":"Point"}
}