{
  "type": "Feature",
  "properties": {
    "gn:admin1_code":"6.0",
    "gn:asciiname":"Laabadliya Oulad Essahni",
    "gn:country_code":"MA",
    "gn:dem":567,
    "gn:feature_class":"P",
    "gn:feature_code":"PPL",
    "gn:name":"Laabadliya Oulad Essahni",
    "gn:population":0,
    "gn:timezone":"Africa/Casablanca",
    "iso:country":"MA",
    "wof:name":"Laabadliya Oulad Essahni",
    "wof:placetype":"locality"
},
  "geometry": {"coordinates":[-7.27799,33.12097],"type":"Point"}
}