{
  "type": "Feature",
  "properties": {
    "gn:admin1_code":"08",
    "gn:asciiname":"Ait Aissa",
    "gn:country_code":"MA",
    "gn:dem":1008,
    "gn:feature_class":"P",
    "gn:feature_code":"PPL",
    "gn:name":"A\u00eft A\u00efssa",
    "gn:population":0,
    "gn:timezone":"Africa/Casablanca",
    "iso:country":"MA",
    "name:und_x_variant":[
        "A\u00eft \u2018Issa",
        "A\u00eft A\u00efssa"
    ],
    "wof:name":"Ait Aissa",
    "wof:placetype":"locality"
},
  "geometry": {"coordinates":[-6.93235,30.43726],"type":"Point"}
}