{
  "type": "Feature",
  "properties": {
    "gn:admin1_code":"2.0",
    "gn:asciiname":"Douar Ait Rahhou",
    "gn:country_code":"MA",
    "gn:dem":624,
    "gn:feature_class":"P",
    "gn:feature_code":"PPL",
    "gn:name":"Douar Ait Rahhou",
    "gn:population":0,
    "gn:timezone":"Africa/Casablanca",
    "iso:country":"MA",
    "wof:name":"Douar Ait Rahhou",
    "wof:placetype":"locality"
},
  "geometry": {"coordinates":[-3.52696,35.0955],"type":"Point"}
}