{
  "type": "Feature",
  "properties": {
    "gn:admin1_code":"08",
    "gn:asciiname":"Tadiaght",
    "gn:country_code":"MA",
    "gn:dem":1835,
    "gn:feature_class":"P",
    "gn:feature_code":"PPL",
    "gn:name":"Tadiaght",
    "gn:population":0,
    "gn:timezone":"Africa/Casablanca",
    "iso:country":"MA",
    "name:und_x_variant":[
        "Tadiarht",
        "Tagadirt",
        "Tadiakhte",
        "Tachdirt",
        "Tadiaght"
    ],
    "wof:name":"Tadiaght",
    "wof:placetype":"locality"
},
  "geometry": {"coordinates":[-7.51405,31.16083],"type":"Point"}
}