{
  "type": "Feature",
  "properties": {
    "gn:admin1_code":"9.0",
    "gn:asciiname":"Ib'rarn",
    "gn:country_code":"MA",
    "gn:dem":561,
    "gn:feature_class":"P",
    "gn:feature_code":"PPL",
    "gn:name":"Ib\u2019rarn",
    "gn:population":0,
    "gn:timezone":"Africa/Casablanca",
    "iso:country":"MA",
    "wof:name":"Ib'rarn",
    "wof:placetype":"locality"
},
  "geometry": {"coordinates":[-9.40042,29.64243],"type":"Point"}
}