{
  "type": "Feature",
  "properties": {
    "gn:country":"MA",
    "gn:fcode":"ADM3",
    "gn:population":2217,
    "iso:country":"MA",
    "name:ara_x_preferred":[
        "\u0623\u0648\u0644\u0627\u062f \u0639\u0644\u064a \u064a\u0648\u0633\u0641"
    ],
    "name:bul_x_preferred":[
        "\u0422\u0438\u0433\u0445\u0437\u0430"
    ],
    "name:cat_x_preferred":[
        "Tighza"
    ],
    "name:ceb_x_preferred":[
        "Tighza"
    ],
    "name:eng_x_preferred":[
        "Tighza"
    ],
    "name:fra_x_preferred":[
        "Tighza"
    ],
    "name:fra_x_variant":[
        "Tighza (AC)",
        "Tighza (Agglomeration Communale)"
    ],
    "name:swe_x_preferred":[
        "Tighza"
    ],
    "qs:name":"Tighza",
    "qs:photos_9r":0,
    "qs:photos_sr":0,
    "qs:pop_sr":"4",
    "wd:wordcount":51,
    "wof:name":"Tighza",
    "wof:placetype":"localadmin",
    "wof:population":2217
},
  "geometry": {"coordinates":[-5.62646,33.18557],"type":"Point"}
}