{
  "type": "Feature",
  "properties": {
    "gn:admin1_code":"3.0",
    "gn:asciiname":"Cooperative Essahra",
    "gn:country_code":"MA",
    "gn:dem":345,
    "gn:feature_class":"P",
    "gn:feature_code":"PPLF",
    "gn:name":"Coop\u00e8rative Essahra",
    "gn:population":0,
    "gn:timezone":"Africa/Casablanca",
    "iso:country":"MA",
    "wof:name":"Cooperative Essahra",
    "wof:placetype":"locality"
},
  "geometry": {"coordinates":[-4.47805,34.15933],"type":"Point"}
}