{
  "type": "Feature",
  "properties": {
    "gn:admin1_code":"07",
    "gn:asciiname":"Iguedmioun",
    "gn:country_code":"MA",
    "gn:dem":1445,
    "gn:feature_class":"P",
    "gn:feature_code":"PPL",
    "gn:name":"Iguedmioun",
    "gn:population":0,
    "gn:timezone":"Africa/Casablanca",
    "iso:country":"MA",
    "wof:name":"Iguedmioun",
    "wof:placetype":"locality"
},
  "geometry": {"coordinates":[-8.96409,30.92075],"type":"Point"}
}