{
  "type": "Feature",
  "properties": {
    "gn:admin1_code":"09",
    "gn:asciiname":"Banoun",
    "gn:country_code":"MA",
    "gn:dem":320,
    "gn:feature_class":"P",
    "gn:feature_code":"PPL",
    "gn:name":"Banoun",
    "gn:population":0,
    "gn:timezone":"Africa/Casablanca",
    "iso:country":"MA",
    "wof:name":"Banoun",
    "wof:placetype":"locality"
},
  "geometry": {"coordinates":[-9.04169,30.20746],"type":"Point"}
}