{
  "type": "Feature",
  "properties": {
    "gn:admin1_code":"01",
    "gn:asciiname":"Douar Imenza",
    "gn:country_code":"MA",
    "gn:dem":514,
    "gn:feature_class":"P",
    "gn:feature_code":"PPL",
    "gn:name":"Douar Imenza",
    "gn:population":0,
    "gn:timezone":"Africa/Casablanca",
    "iso:country":"MA",
    "name:und_x_variant":[
        "Ymenya",
        "Jmenja",
        "Douar Imenza"
    ],
    "wof:name":"Douar Imenza",
    "wof:placetype":"locality"
},
  "geometry": {"coordinates":[-4.48246,35.10196],"type":"Point"}
}