{
  "type": "Feature",
  "properties": {
    "gn:admin1_code":"7.0",
    "gn:asciiname":"Oulad Taher Boubker",
    "gn:country_code":"MA",
    "gn:dem":169,
    "gn:feature_class":"P",
    "gn:feature_code":"PPL",
    "gn:name":"Oulad Taher Boubker",
    "gn:population":0,
    "gn:timezone":"Africa/Casablanca",
    "iso:country":"MA",
    "wof:name":"Oulad Taher Boubker",
    "wof:placetype":"locality"
},
  "geometry": {"coordinates":[-8.82975,32.30954000000001],"type":"Point"}
}