{
  "type": "Feature",
  "properties": {
    "gn:admin1_code":"04",
    "gn:asciiname":"Douar Bouchouk",
    "gn:country_code":"MA",
    "gn:dem":32,
    "gn:feature_class":"P",
    "gn:feature_code":"PPL",
    "gn:name":"Douar Bouchouk",
    "gn:population":0,
    "gn:timezone":"Africa/Casablanca",
    "iso:country":"MA",
    "name:und_x_variant":[
        "Dr. Bouchouk"
    ],
    "wof:name":"Douar Bouchouk",
    "wof:placetype":"locality"
},
  "geometry": {"coordinates":[-6.78516,34.08806],"type":"Point"}
}