{
  "type": "Feature",
  "properties": {
    "gn:admin1_code":"9.0",
    "gn:asciiname":"Asguine",
    "gn:country_code":"MA",
    "gn:dem":1465,
    "gn:feature_class":"P",
    "gn:feature_code":"PPL",
    "gn:name":"Asguine",
    "gn:population":0,
    "gn:timezone":"Africa/Casablanca",
    "iso:country":"MA",
    "wof:name":"Asguine",
    "wof:placetype":"locality"
},
  "geometry": {"coordinates":[-8.89766,30.73461],"type":"Point"}
}