{
  "type": "Feature",
  "properties": {
    "gn:admin1_code":"07",
    "gn:asciiname":"Douar Chehda",
    "gn:country_code":"MA",
    "gn:dem":156,
    "gn:feature_class":"P",
    "gn:feature_code":"PPL",
    "gn:name":"Douar Chehda",
    "gn:population":0,
    "gn:timezone":"Africa/Casablanca",
    "iso:country":"MA",
    "name:und_x_variant":[
        "Chehada"
    ],
    "wof:name":"Douar Chehda",
    "wof:placetype":"locality"
},
  "geometry": {"coordinates":[-8.89584,32.30422],"type":"Point"}
}