{
  "type": "Feature",
  "properties": {
    "gn:admin1_code":"02",
    "gn:asciiname":"Fadel Allah",
    "gn:country_code":"MA",
    "gn:dem":1259,
    "gn:feature_class":"P",
    "gn:feature_code":"PPL",
    "gn:name":"Fadel Allah",
    "gn:population":0,
    "gn:timezone":"Africa/Casablanca",
    "iso:country":"MA",
    "wof:name":"Fadel Allah",
    "wof:placetype":"locality"
},
  "geometry": {"coordinates":[-3.66835,32.38408],"type":"Point"}
}