{
  "type": "Feature",
  "properties": {
    "gn:admin1_code":"10",
    "gn:asciiname":"Auleg",
    "gn:country_code":"MA",
    "gn:dem":1413,
    "gn:feature_class":"P",
    "gn:feature_code":"PPL",
    "gn:name":"Auleg",
    "gn:population":0,
    "gn:timezone":"Africa/Casablanca",
    "iso:country":"MA",
    "wof:name":"Auleg",
    "wof:placetype":"locality"
},
  "geometry": {"coordinates":[-9.23263,29.41292],"type":"Point"}
}