{
  "type": "Feature",
  "properties": {
    "gn:admin1_code":"7.0",
    "gn:asciiname":"Dar Mohamed Al Guadiri",
    "gn:country_code":"MA",
    "gn:dem":41,
    "gn:feature_class":"P",
    "gn:feature_code":"PPL",
    "gn:name":"Dar Mohamed Al Guadiri",
    "gn:population":0,
    "gn:timezone":"Africa/Casablanca",
    "iso:country":"MA",
    "wof:name":"Dar Mohamed Al Guadiri",
    "wof:placetype":"locality"
},
  "geometry": {"coordinates":[-9.3278,32.01267],"type":"Point"}
}