{
  "type": "Feature",
  "properties": {
    "gn:admin1_code":"2.0",
    "gn:asciiname":"Aarabene",
    "gn:country_code":"MA",
    "gn:dem":460,
    "gn:feature_class":"P",
    "gn:feature_code":"PPL",
    "gn:name":"Aarabene",
    "gn:population":0,
    "gn:timezone":"Africa/Casablanca",
    "iso:country":"MA",
    "wof:name":"Aarabene",
    "wof:placetype":"locality"
},
  "geometry": {"coordinates":[-3.39523,35.10978],"type":"Point"}
}