{
  "type": "Feature",
  "properties": {
    "gn:country":"MA",
    "gn:fcode":"ADM3",
    "gn:population":6378,
    "iso:country":"MA",
    "name:ara_x_preferred":[
        "\u0645\u0634\u0631\u0639 \u062d\u0645\u0627\u062f\u064a"
    ],
    "name:ara_x_variant":[
        "\u0645\u0633\u062a\u063a\u0645\u0631"
    ],
    "name:ary_x_preferred":[
        "\u0645\u0633\u062a\u06af\u0645\u0631"
    ],
    "name:bul_x_preferred":[
        "\u041c\u0435\u0441\u0442\u0435\u0433\u043c\u0435\u0440"
    ],
    "name:cat_x_preferred":[
        "Mestegmer"
    ],
    "name:ceb_x_preferred":[
        "Mestegmer"
    ],
    "name:eng_x_preferred":[
        "Mestegmer"
    ],
    "name:fra_x_preferred":[
        "Mestegmer"
    ],
    "name:fra_x_variant":[
        "Mestegmer (CR)",
        "Mestegmer (Commune Rurale)"
    ],
    "name:ita_x_preferred":[
        "Mestegmer"
    ],
    "name:swe_x_preferred":[
        "Mestegmer"
    ],
    "qs:name":"Mestegmer",
    "qs:photos_9r":0,
    "qs:photos_sr":0,
    "qs:pop_sr":"5",
    "wd:wordcount":77,
    "wof:name":"Mestegmer",
    "wof:placetype":"localadmin",
    "wof:population":6378
},
  "geometry": {"coordinates":[-2.7939,34.51425],"type":"Point"}
}