{
  "type": "Feature",
  "properties": {
    "gn:admin1_code":"8.0",
    "gn:asciiname":"Moulav Lahcen",
    "gn:country_code":"MA",
    "gn:dem":1059,
    "gn:feature_class":"P",
    "gn:feature_code":"PPL",
    "gn:name":"Moulav Lahcen",
    "gn:population":0,
    "gn:timezone":"Africa/Casablanca",
    "iso:country":"MA",
    "wof:name":"Moulav Lahcen",
    "wof:placetype":"locality"
},
  "geometry": {"coordinates":[-4.45574,31.97198],"type":"Point"}
}