{
  "type": "Feature",
  "properties": {
    "gn:admin1_code":"6.0",
    "gn:asciiname":"Lakhmalcha",
    "gn:country_code":"MA",
    "gn:dem":256,
    "gn:feature_class":"P",
    "gn:feature_code":"PPL",
    "gn:name":"Lakhmalcha",
    "gn:population":0,
    "gn:timezone":"Africa/Casablanca",
    "iso:country":"MA",
    "wof:name":"Lakhmalcha",
    "wof:placetype":"locality"
},
  "geometry": {"coordinates":[-7.17927,33.48275],"type":"Point"}
}