{
  "type": "Feature",
  "properties": {
    "gn:admin1_code":"08",
    "gn:asciiname":"Bou Zemou",
    "gn:country_code":"MA",
    "gn:dem":2252,
    "gn:feature_class":"P",
    "gn:feature_code":"PPL",
    "gn:name":"Bou Zemou",
    "gn:population":0,
    "gn:timezone":"Africa/Casablanca",
    "iso:country":"MA",
    "name:und_x_variant":[
        "Ksar Bou Ouezmou",
        "Bou Ouzemou des A\u00eft Ouarzef",
        "Bou Zemou"
    ],
    "wof:name":"Bou Zemou",
    "wof:placetype":"locality"
},
  "geometry": {"coordinates":[-5.53268,32.09839],"type":"Point"}
}