{
  "type": "Feature",
  "properties": {
    "gn:admin1_code":"08",
    "gn:asciiname":"Jorf Lahman",
    "gn:country_code":"MA",
    "gn:dem":827,
    "gn:feature_class":"P",
    "gn:feature_code":"PPL",
    "gn:name":"Jorf Lahman",
    "gn:population":0,
    "gn:timezone":"Africa/Casablanca",
    "iso:country":"MA",
    "name:und_x_variant":[
        "Jorf el Ham\u00e2m"
    ],
    "wof:name":"Jorf Lahman",
    "wof:placetype":"locality"
},
  "geometry": {"coordinates":[-4.18691,31.52687],"type":"Point"}
}