{
  "type": "Feature",
  "properties": {
    "gn:admin1_code":"02",
    "gn:asciiname":"Ijehhouhene",
    "gn:country_code":"MA",
    "gn:dem":334,
    "gn:feature_class":"P",
    "gn:feature_code":"PPL",
    "gn:name":"Ijehhouhene",
    "gn:population":0,
    "gn:timezone":"Africa/Casablanca",
    "iso:country":"MA",
    "name:und_x_variant":[
        "Ijchhouhene"
    ],
    "wof:name":"Ijehhouhene",
    "wof:placetype":"locality"
},
  "geometry": {"coordinates":[-3.32591,35.17119],"type":"Point"}
}