{
  "type": "Feature",
  "properties": {
    "gn:admin1_code":"02",
    "gn:asciiname":"Mahirija",
    "gn:country_code":"MA",
    "gn:dem":670,
    "gn:feature_class":"P",
    "gn:feature_code":"PPL",
    "gn:name":"Mahirija",
    "gn:population":0,
    "gn:timezone":"Africa/Casablanca",
    "iso:country":"MA",
    "name:und_x_variant":[
        "Mahiridja",
        "Mahirija"
    ],
    "wof:name":"Mahirija",
    "wof:placetype":"locality"
},
  "geometry": {"coordinates":[-3.27789,33.99051],"type":"Point"}
}