{
  "type": "Feature",
  "properties": {
    "gn:admin1_code":"5.0",
    "gn:asciiname":"Timratine",
    "gn:country_code":"MA",
    "gn:dem":767,
    "gn:feature_class":"P",
    "gn:feature_code":"PPL",
    "gn:name":"Timratine",
    "gn:population":0,
    "gn:timezone":"Africa/Casablanca",
    "iso:country":"MA",
    "wof:name":"Timratine",
    "wof:placetype":"locality"
},
  "geometry": {"coordinates":[-5.8576,32.79053],"type":"Point"}
}