{
  "type": "Feature",
  "properties": {
    "gn:admin1_code":"9.0",
    "gn:asciiname":"Ait 'Ddi ou Ms 'oud",
    "gn:country_code":"MA",
    "gn:dem":1225,
    "gn:feature_class":"P",
    "gn:feature_code":"PPL",
    "gn:name":"A\u00eft \u2019Ddi ou Ms \u2019oud",
    "gn:population":0,
    "gn:timezone":"Africa/Casablanca",
    "iso:country":"MA",
    "wof:name":"Ait 'Ddi ou Ms 'oud",
    "wof:placetype":"locality"
},
  "geometry": {"coordinates":[-9.23593,29.53435],"type":"Point"}
}