{
  "type": "Feature",
  "properties": {
    "gn:admin1_code":"10",
    "gn:asciiname":"Dar el Haithat",
    "gn:country_code":"MA",
    "gn:dem":335,
    "gn:feature_class":"P",
    "gn:feature_code":"PPL",
    "gn:name":"Dar el Haithat",
    "gn:population":0,
    "gn:timezone":"Africa/Casablanca",
    "iso:country":"MA",
    "name:und_x_variant":[
        "Dar Ainetad",
        "Dar el Haithat"
    ],
    "wof:name":"Dar el Haithat",
    "wof:placetype":"locality"
},
  "geometry": {"coordinates":[-10.31115,29.18147],"type":"Point"}
}