{
  "type": "Feature",
  "properties": {
    "gn:admin1_code":"1.0",
    "gn:asciiname":"Douar El Khoms",
    "gn:country_code":"MA",
    "gn:dem":426,
    "gn:feature_class":"P",
    "gn:feature_code":"PPL",
    "gn:name":"Douar El Khoms",
    "gn:population":0,
    "gn:timezone":"Africa/Casablanca",
    "iso:country":"MA",
    "wof:name":"Douar El Khoms",
    "wof:placetype":"locality"
},
  "geometry": {"coordinates":[-5.66716,35.49042],"type":"Point"}
}