{
  "type": "Feature",
  "properties": {
    "gn:admin1_code":"01",
    "gn:asciiname":"Kitane",
    "gn:country_code":"MA",
    "gn:dem":60,
    "gn:feature_class":"P",
    "gn:feature_code":"PPL",
    "gn:name":"Kitane",
    "gn:population":0,
    "gn:timezone":"Africa/Casablanca",
    "iso:country":"MA",
    "wof:name":"Kitane",
    "wof:placetype":"locality"
},
  "geometry": {"coordinates":[-5.33946,35.54112],"type":"Point"}
}