{
  "type": "Feature",
  "properties": {
    "gn:admin1_code":"01",
    "gn:asciiname":"Douar Bouslama",
    "gn:country_code":"MA",
    "gn:dem":97,
    "gn:feature_class":"P",
    "gn:feature_code":"PPL",
    "gn:name":"Douar Bouslama",
    "gn:population":0,
    "gn:timezone":"Africa/Casablanca",
    "iso:country":"MA",
    "name:und_x_variant":[
        "Buselama",
        "Bouselama",
        "Douar Bouslama"
    ],
    "wof:name":"Douar Bouslama",
    "wof:placetype":"neighbourhood"
},
  "geometry": {"coordinates":[-3.8495,35.13094],"type":"Point"}
}