{
  "type": "Feature",
  "properties": {
    "gn:admin1_code":"07",
    "gn:asciiname":"Douar Msabeh",
    "gn:country_code":"MA",
    "gn:dem":220,
    "gn:feature_class":"P",
    "gn:feature_code":"PPL",
    "gn:name":"Douar Msabeh",
    "gn:population":0,
    "gn:timezone":"Africa/Casablanca",
    "iso:country":"MA",
    "name:und_x_variant":[
        "Lam Sabih",
        "Msabeh"
    ],
    "wof:name":"Douar Msabeh",
    "wof:placetype":"locality"
},
  "geometry": {"coordinates":[-8.6325,32.36601],"type":"Point"}
}