{
  "type": "Feature",
  "properties": {
    "gn:admin1_code":"7.0",
    "gn:asciiname":"Douar Dkara Oulad El Haj Mohamed",
    "gn:country_code":"MA",
    "gn:dem":474,
    "gn:feature_class":"P",
    "gn:feature_code":"PPL",
    "gn:name":"Douar Dkara Oulad El Haj Mohamed",
    "gn:population":0,
    "gn:timezone":"Africa/Casablanca",
    "iso:country":"MA",
    "wof:name":"Douar Dkara Oulad El Haj Mohamed",
    "wof:placetype":"locality"
},
  "geometry": {"coordinates":[-8.46834,32.21346],"type":"Point"}
}