{
  "type": "Feature",
  "properties": {
    "gn:admin1_code":"7.0",
    "gn:asciiname":"Zaouit-Bezaioud",
    "gn:country_code":"MA",
    "gn:dem":953,
    "gn:feature_class":"P",
    "gn:feature_code":"PPL",
    "gn:name":"Zaouit-Beza\u00efoud",
    "gn:population":0,
    "gn:timezone":"Africa/Casablanca",
    "iso:country":"MA",
    "wof:name":"Zaouit-Bezaioud",
    "wof:placetype":"locality"
},
  "geometry": {"coordinates":[-9.00224,31.15763],"type":"Point"}
}