{
  "type": "Feature",
  "properties": {
    "gn:admin1_code":"09",
    "gn:asciiname":"Agouni",
    "gn:country_code":"MA",
    "gn:dem":1423,
    "gn:feature_class":"P",
    "gn:feature_code":"PPL",
    "gn:name":"Agouni",
    "gn:population":0,
    "gn:timezone":"Africa/Casablanca",
    "iso:country":"MA",
    "name:azb_x_preferred":[
        "\u0627\u0642\u0648\u0646\u06cc"
    ],
    "name:fas_x_preferred":[
        "\u0627\u06af\u0648\u0646\u06cc"
    ],
    "name:nor_x_preferred":[
        "Agouni"
    ],
    "name:urd_x_preferred":[
        "\u0627\u06af\u0648\u0646\u06cc"
    ],
    "wof:name":"Agouni",
    "wof:placetype":"locality"
},
  "geometry": {"coordinates":[-8.97385,30.77338],"type":"Point"}
}