{
  "type": "Feature",
  "properties": {
    "gn:admin1_code":"09",
    "gn:asciiname":"Anou-n-Addi",
    "gn:country_code":"MA",
    "gn:dem":115,
    "gn:feature_class":"P",
    "gn:feature_code":"PPL",
    "gn:name":"Anou-n-Addi",
    "gn:population":0,
    "gn:timezone":"Africa/Casablanca",
    "iso:country":"MA",
    "name:und_x_variant":[
        "Amou n\u2019Addi A\u00eft Amar",
        "Anou n\u2019Addi",
        "Anou-n-Addi"
    ],
    "wof:name":"Anou-n-Addi",
    "wof:placetype":"locality"
},
  "geometry": {"coordinates":[-9.47087,30.05892],"type":"Point"}
}