{
  "type": "Feature",
  "properties": {
    "gn:admin1_code":"7.0",
    "gn:asciiname":"Douar Ghzaouna Oulad Safi",
    "gn:country_code":"MA",
    "gn:dem":151,
    "gn:feature_class":"P",
    "gn:feature_code":"PPL",
    "gn:name":"Douar Ghzaouna Oulad Safi",
    "gn:population":0,
    "gn:timezone":"Africa/Casablanca",
    "iso:country":"MA",
    "wof:name":"Douar Ghzaouna Oulad Safi",
    "wof:placetype":"locality"
},
  "geometry": {"coordinates":[-8.9285,32.46100999999999],"type":"Point"}
}