{
  "type": "Feature",
  "properties": {
    "gn:admin1_code":"1.0",
    "gn:asciiname":"Douar Feddal",
    "gn:country_code":"MA",
    "gn:dem":211,
    "gn:feature_class":"P",
    "gn:feature_code":"PPL",
    "gn:name":"Douar Feddal",
    "gn:population":0,
    "gn:timezone":"Africa/Casablanca",
    "iso:country":"MA",
    "wof:name":"Douar Feddal",
    "wof:placetype":"locality"
},
  "geometry": {"coordinates":[-4.4341,35.08593],"type":"Point"}
}