{
  "type": "Feature",
  "properties": {
    "gn:admin1_code":"10.0",
    "gn:asciiname":"Id Bou Sa'id",
    "gn:country_code":"MA",
    "gn:dem":814,
    "gn:feature_class":"P",
    "gn:feature_code":"PPL",
    "gn:name":"Id Bou Sa\u2019id",
    "gn:population":0,
    "gn:timezone":"Africa/Casablanca",
    "iso:country":"MA",
    "wof:name":"Id Bou Sa'id",
    "wof:placetype":"locality"
},
  "geometry": {"coordinates":[-9.79002,29.40561],"type":"Point"}
}