{
  "type": "Feature",
  "properties": {
    "gn:admin1_code":"05",
    "gn:asciiname":"Ait Aissa",
    "gn:country_code":"MA",
    "gn:dem":1767,
    "gn:feature_class":"P",
    "gn:feature_code":"PPL",
    "gn:name":"A\u00eft A\u00efssa",
    "gn:population":0,
    "gn:timezone":"Africa/Casablanca",
    "iso:country":"MA",
    "wof:name":"Ait Aissa",
    "wof:placetype":"locality"
},
  "geometry": {"coordinates":[-5.93523,32.08023],"type":"Point"}
}