{
  "type": "Feature",
  "properties": {
    "gn:admin1_code":"02",
    "gn:asciiname":"Douar Ijetta",
    "gn:country_code":"MA",
    "gn:dem":598,
    "gn:feature_class":"P",
    "gn:feature_code":"PPL",
    "gn:name":"Douar Ijetta",
    "gn:population":0,
    "gn:timezone":"Africa/Casablanca",
    "iso:country":"MA",
    "wof:name":"Douar Ijetta",
    "wof:placetype":"locality"
},
  "geometry": {"coordinates":[-3.7266,35.16694],"type":"Point"}
}