{
  "type": "Feature",
  "properties": {
    "gn:admin1_code":"03",
    "gn:asciiname":"Kasba du Dir",
    "gn:country_code":"MA",
    "gn:dem":1169,
    "gn:feature_class":"P",
    "gn:feature_code":"PPL",
    "gn:name":"Kasba du Dir",
    "gn:population":0,
    "gn:timezone":"Africa/Casablanca",
    "iso:country":"MA",
    "wof:name":"Kasba du Dir",
    "wof:placetype":"locality"
},
  "geometry": {"coordinates":[-4.3682,33.68979],"type":"Point"}
}