{
  "type": "Feature",
  "properties": {
    "gn:admin1_code":"4.0",
    "gn:asciiname":"Oulad Ghanem",
    "gn:country_code":"MA",
    "gn:dem":97,
    "gn:feature_class":"P",
    "gn:feature_code":"PPL",
    "gn:name":"Oulad Ghanem",
    "gn:population":0,
    "gn:timezone":"Africa/Casablanca",
    "iso:country":"MA",
    "name:ara_x_preferred":[
        "\u0623\u0648\u0644\u0627\u062f \u063a\u0627\u0646\u0645"
    ],
    "name:cat_x_preferred":[
        "Oulad Ghanem"
    ],
    "name:ceb_x_preferred":[
        "Oulad Ghanem"
    ],
    "name:ita_x_preferred":[
        "Ouled Ghanem"
    ],
    "name:swe_x_preferred":[
        "Oulad Ghanem"
    ],
    "wof:name":"Oulad Ghanem",
    "wof:placetype":"locality"
},
  "geometry": {"coordinates":[-7.01112,33.8343],"type":"Point"}
}