{
  "type": "Feature",
  "properties": {
    "gn:admin1_code":"01",
    "gn:admin2_code":"51.0",
    "gn:admin3_code":"1505105212.0",
    "gn:asciiname":"Rouadi",
    "gn:country_code":"MA",
    "gn:dem":399,
    "gn:feature_class":"P",
    "gn:feature_code":"PPLA3",
    "gn:name":"Rouadi",
    "gn:population":0,
    "gn:timezone":"Africa/Casablanca",
    "iso:country":"MA",
    "wof:name":"Rouadi",
    "wof:placetype":"locality"
},
  "geometry": {"coordinates":[-4.13631,35.14119],"type":"Point"}
}