{
  "type": "Feature",
  "properties": {
    "gn:admin1_code":"9.0",
    "gn:asciiname":"Ggui'az",
    "gn:country_code":"MA",
    "gn:dem":871,
    "gn:feature_class":"P",
    "gn:feature_code":"PPL",
    "gn:name":"Ggui\u2019az",
    "gn:population":0,
    "gn:timezone":"Africa/Casablanca",
    "iso:country":"MA",
    "wof:name":"Ggui'az",
    "wof:placetype":"locality"
},
  "geometry": {"coordinates":[-9.17931,29.99068],"type":"Point"}
}