{
  "type": "Feature",
  "properties": {
    "gn:admin1_code":"9.0",
    "gn:asciiname":"Touriyrt",
    "gn:country_code":"MA",
    "gn:dem":779,
    "gn:feature_class":"P",
    "gn:feature_code":"PPL",
    "gn:name":"Touriyrt",
    "gn:population":0,
    "gn:timezone":"Africa/Casablanca",
    "iso:country":"MA",
    "wof:name":"Touriyrt",
    "wof:placetype":"locality"
},
  "geometry": {"coordinates":[-9.35388,29.55894],"type":"Point"}
}