{
  "type": "Feature",
  "properties": {
    "gn:admin1_code":"6.0",
    "gn:asciiname":"Ouled Sidi Chenane",
    "gn:country_code":"MA",
    "gn:dem":362,
    "gn:feature_class":"P",
    "gn:feature_code":"PPL",
    "gn:name":"Ouled Sidi Chenane",
    "gn:population":0,
    "gn:timezone":"Africa/Casablanca",
    "iso:country":"MA",
    "wof:name":"Ouled Sidi Chenane",
    "wof:placetype":"locality"
},
  "geometry": {"coordinates":[-7.79518,32.82696],"type":"Point"}
}