{
  "type": "Feature",
  "properties": {
    "gn:admin1_code":"01",
    "gn:asciiname":"Touansa",
    "gn:country_code":"MA",
    "gn:dem":77,
    "gn:feature_class":"P",
    "gn:feature_code":"PPL",
    "gn:name":"Touansa",
    "gn:population":0,
    "gn:timezone":"Africa/Casablanca",
    "iso:country":"MA",
    "name:und_x_variant":[
        "Touanza"
    ],
    "wof:name":"Touansa",
    "wof:placetype":"locality"
},
  "geometry": {"coordinates":[-5.9156,35.48723],"type":"Point"}
}