{
  "type": "Feature",
  "properties": {
    "gn:admin1_code":"7.0",
    "gn:asciiname":"Tanrhourt",
    "gn:country_code":"MA",
    "gn:dem":412,
    "gn:feature_class":"P",
    "gn:feature_code":"PPL",
    "gn:name":"Tanrhourt",
    "gn:population":0,
    "gn:timezone":"Africa/Casablanca",
    "iso:country":"MA",
    "wof:name":"Tanrhourt",
    "wof:placetype":"locality"
},
  "geometry": {"coordinates":[-9.67542,30.90528],"type":"Point"}
}