{
  "type": "Feature",
  "properties": {
    "gn:admin1_code":"10.0",
    "gn:asciiname":"Ihabarine",
    "gn:country_code":"MA",
    "gn:dem":590,
    "gn:feature_class":"P",
    "gn:feature_code":"PPL",
    "gn:name":"Ihabarine",
    "gn:population":0,
    "gn:timezone":"Africa/Casablanca",
    "iso:country":"MA",
    "wof:name":"Ihabarine",
    "wof:placetype":"locality"
},
  "geometry": {"coordinates":[-9.93741,29.27819],"type":"Point"}
}