{
  "type": "Feature",
  "properties": {
    "gn:admin1_code":"7.0",
    "gn:asciiname":"Iggui Ouanou",
    "gn:country_code":"MA",
    "gn:dem":293,
    "gn:feature_class":"P",
    "gn:feature_code":"PPL",
    "gn:name":"Iggui Ouanou",
    "gn:population":0,
    "gn:timezone":"Africa/Casablanca",
    "iso:country":"MA",
    "wof:name":"Iggui Ouanou",
    "wof:placetype":"locality"
},
  "geometry": {"coordinates":[-9.69037,31.02669],"type":"Point"}
}