{
  "type": "Feature",
  "properties": {
    "gn:admin1_code":"1.0",
    "gn:asciiname":"Oulad Ahmed",
    "gn:country_code":"MA",
    "gn:dem":555,
    "gn:feature_class":"P",
    "gn:feature_code":"PPL",
    "gn:name":"Oulad Ahmed",
    "gn:population":0,
    "gn:timezone":"Africa/Casablanca",
    "iso:country":"MA",
    "wof:name":"Oulad Ahmed",
    "wof:placetype":"locality"
},
  "geometry": {"coordinates":[-3.95584,35.03993],"type":"Point"}
}