{
  "type": "Feature",
  "properties": {
    "gn:admin1_code":"7.0",
    "gn:asciiname":"Askour",
    "gn:country_code":"MA",
    "gn:dem":1073,
    "gn:feature_class":"P",
    "gn:feature_code":"PPL",
    "gn:name":"Askour",
    "gn:population":0,
    "gn:timezone":"Africa/Casablanca",
    "iso:country":"MA",
    "wof:name":"Askour",
    "wof:placetype":"locality"
},
  "geometry": {"coordinates":[-7.51681,31.47704],"type":"Point"}
}