{
  "type": "Feature",
  "properties": {
    "gn:admin1_code":"10",
    "gn:asciiname":"Boused",
    "gn:country_code":"MA",
    "gn:dem":346,
    "gn:feature_class":"P",
    "gn:feature_code":"PPL",
    "gn:name":"Boused",
    "gn:population":0,
    "gn:timezone":"Africa/Casablanca",
    "iso:country":"MA",
    "name:und_x_variant":[
        "Ahel Buxait",
        "Boused"
    ],
    "wof:name":"Boused",
    "wof:placetype":"locality"
},
  "geometry": {"coordinates":[-10.28785,29.17468],"type":"Point"}
}