{
  "type": "Feature",
  "properties": {
    "gn:admin1_code":"01",
    "gn:asciiname":"Tleta Rissana",
    "gn:country_code":"MA",
    "gn:dem":24,
    "gn:feature_class":"P",
    "gn:feature_code":"PPL",
    "gn:name":"Tleta Rissana",
    "gn:population":0,
    "gn:timezone":"Africa/Casablanca",
    "iso:country":"MA",
    "name:und_x_variant":[
        "Et Tleta de Reissana",
        "Telata de Raisana",
        "Soko el Tzelatza",
        "Zoco Telata",
        "Et Tleta Ghana",
        "Et Tleta",
        "Tleta Rissana"
    ],
    "wof:name":"Tleta Rissana",
    "wof:placetype":"locality"
},
  "geometry": {"coordinates":[-5.94333,35.22015],"type":"Point"}
}