{
  "type": "Feature",
  "properties": {
    "gn:admin1_code":"2.0",
    "gn:asciiname":"Douar Taqarboust Echorfa",
    "gn:country_code":"MA",
    "gn:dem":347,
    "gn:feature_class":"P",
    "gn:feature_code":"PPL",
    "gn:name":"Douar Taqarboust Echorfa",
    "gn:population":0,
    "gn:timezone":"Africa/Casablanca",
    "iso:country":"MA",
    "wof:name":"Douar Taqarboust Echorfa",
    "wof:placetype":"locality"
},
  "geometry": {"coordinates":[-2.36511,34.86049000000001],"type":"Point"}
}