{
  "type": "Feature",
  "properties": {
    "gn:admin1_code":"03",
    "gn:asciiname":"Douar Lamtahene",
    "gn:country_code":"MA",
    "gn:dem":319,
    "gn:feature_class":"P",
    "gn:feature_code":"PPL",
    "gn:name":"Douar Lamtahene",
    "gn:population":0,
    "gn:timezone":"Africa/Casablanca",
    "iso:country":"MA",
    "name:und_x_variant":[
        "Douar Refda el Hamra",
        "Refda el Hamra",
        "Douar Lamtahene"
    ],
    "wof:name":"Douar Lamtahene",
    "wof:placetype":"locality"
},
  "geometry": {"coordinates":[-4.31811,34.16289],"type":"Point"}
}