{
  "type": "Feature",
  "properties": {
    "gn:admin1_code":"2.0",
    "gn:asciiname":"Bouodour",
    "gn:country_code":"MA",
    "gn:dem":433,
    "gn:feature_class":"P",
    "gn:feature_code":"PPL",
    "gn:name":"Bouodour",
    "gn:population":0,
    "gn:timezone":"Africa/Casablanca",
    "iso:country":"MA",
    "wof:name":"Bouodour",
    "wof:placetype":"locality"
},
  "geometry": {"coordinates":[-3.07775,35.20656],"type":"Point"}
}