{
  "type": "Feature",
  "properties": {
    "gn:admin1_code":"03",
    "gn:asciiname":"Douar el Boudaoudia",
    "gn:country_code":"MA",
    "gn:dem":868,
    "gn:feature_class":"P",
    "gn:feature_code":"PPL",
    "gn:name":"Douar el Boudaoudia",
    "gn:population":0,
    "gn:timezone":"Africa/Casablanca",
    "iso:country":"MA",
    "name:und_x_variant":[
        "Boudoudia",
        "Douar el Boudaoudia",
        "El Boudaoudia"
    ],
    "wof:name":"Douar el Boudaoudia",
    "wof:placetype":"locality"
},
  "geometry": {"coordinates":[-3.89087,34.34135],"type":"Point"}
}