{
  "type": "Feature",
  "properties": {
    "gn:admin1_code":"06",
    "gn:asciiname":"Sidi Muhammed ben Ahmed",
    "gn:country_code":"MA",
    "gn:dem":136,
    "gn:feature_class":"P",
    "gn:feature_code":"PPL",
    "gn:name":"Sidi Muhammed ben Ahmed",
    "gn:population":0,
    "gn:timezone":"Africa/Casablanca",
    "iso:country":"MA",
    "name:und_x_variant":[
        "Mohammed ben Ahmed"
    ],
    "wof:name":"Sidi Muhammed ben Ahmed",
    "wof:placetype":"locality"
},
  "geometry": {"coordinates":[-8.52983,32.93814],"type":"Point"}
}