{
  "type": "Feature",
  "properties": {
    "gn:admin1_code":"6.0",
    "gn:asciiname":"Mar'awd",
    "gn:country_code":"MA",
    "gn:dem":230,
    "gn:feature_class":"P",
    "gn:feature_code":"PPL",
    "gn:name":"Mar\u2019awd",
    "gn:population":0,
    "gn:timezone":"Africa/Casablanca",
    "iso:country":"MA",
    "wof:name":"Mar'awd",
    "wof:placetype":"locality"
},
  "geometry": {"coordinates":[-7.77659,33.17557],"type":"Point"}
}