{
  "type": "Feature",
  "properties": {
    "gn:admin1_code":"09",
    "gn:asciiname":"Miggarn",
    "gn:country_code":"MA",
    "gn:dem":1240,
    "gn:feature_class":"P",
    "gn:feature_code":"PPL",
    "gn:name":"Miggarn",
    "gn:population":0,
    "gn:timezone":"Africa/Casablanca",
    "iso:country":"MA",
    "name:und_x_variant":[
        "Imiguerne",
        "Imiguern",
        "Miggarn"
    ],
    "wof:name":"Miggarn",
    "wof:placetype":"locality"
},
  "geometry": {"coordinates":[-7.805,30.5075],"type":"Point"}
}