{
  "type": "Feature",
  "properties": {
    "gn:admin1_code":"9.0",
    "gn:asciiname":"Taguennza",
    "gn:country_code":"MA",
    "gn:dem":720,
    "gn:feature_class":"P",
    "gn:feature_code":"PPL",
    "gn:name":"Taguennza",
    "gn:population":0,
    "gn:timezone":"Africa/Casablanca",
    "iso:country":"MA",
    "wof:name":"Taguennza",
    "wof:placetype":"locality"
},
  "geometry": {"coordinates":[-9.14862,30.04596],"type":"Point"}
}