{
  "type": "Feature",
  "properties": {
    "gn:admin1_code":"09",
    "gn:asciiname":"Oulad Amira",
    "gn:country_code":"MA",
    "gn:dem":253,
    "gn:feature_class":"P",
    "gn:feature_code":"PPL",
    "gn:name":"Oulad Amira",
    "gn:population":0,
    "gn:timezone":"Africa/Casablanca",
    "iso:country":"MA",
    "name:und_x_variant":[
        "Oulad Aamira",
        "Oulad Amira"
    ],
    "wof:name":"Oulad Amira",
    "wof:placetype":"locality"
},
  "geometry": {"coordinates":[-8.80674,30.47082],"type":"Point"}
}