{
  "type": "Feature",
  "properties": {
    "gn:gn_country":"MA",
    "gn:gn_fcode":"ADM3",
    "gn:gn_pop":7084,
    "gn:population":6597,
    "iso:country":"MA",
    "name:ara_x_preferred":[
        "\u0639\u064a\u0646 \u0642\u064a\u0634\u0631"
    ],
    "name:fra_x_preferred":[
        "Bni Zrantel"
    ],
    "name:fra_x_variant":[
        "Bni Zrantel (CR)",
        "Bni Zrantel (Commune Rurale)"
    ],
    "qs_pg:aaroncc":"MA",
    "qs_pg:gn_country":"MA",
    "qs_pg:gn_fcode":"ADM3",
    "qs_pg:gn_pop":7084,
    "qs_pg:name":"Bni Zrantel",
    "qs_pg:photos_9r":0,
    "qs_pg:photos_sr":0,
    "qs_pg:pop_sr":5,
    "qs_pg:qs_pg_placetype":"localadmin",
    "wof:name":"Bni Zrantel",
    "wof:placetype":"localadmin",
    "wof:population":6597
},
  "geometry": {"coordinates":[-6.15226,32.77302],"type":"Point"}
}