{
  "type": "Feature",
  "properties": {
    "gn:admin1_code":"3.0",
    "gn:asciiname":"Douar Smissil",
    "gn:country_code":"MA",
    "gn:dem":458,
    "gn:feature_class":"P",
    "gn:feature_code":"PPL",
    "gn:name":"Douar Smissil",
    "gn:population":0,
    "gn:timezone":"Africa/Casablanca",
    "iso:country":"MA",
    "wof:name":"Douar Smissil",
    "wof:placetype":"locality"
},
  "geometry": {"coordinates":[-4.81633,34.40634],"type":"Point"}
}