{
  "type": "Feature",
  "properties": {
    "gn:admin1_code":"7.0",
    "gn:asciiname":"Douar Agadir Oumghar",
    "gn:country_code":"MA",
    "gn:dem":256,
    "gn:feature_class":"P",
    "gn:feature_code":"PPL",
    "gn:name":"Douar Agadir Oumghar",
    "gn:population":0,
    "gn:timezone":"Africa/Casablanca",
    "iso:country":"MA",
    "wof:name":"Douar Agadir Oumghar",
    "wof:placetype":"locality"
},
  "geometry": {"coordinates":[-9.53408,31.4379],"type":"Point"}
}