{
  "type": "Feature",
  "properties": {
    "gn:admin1_code":"09",
    "gn:asciiname":"Taskra",
    "gn:country_code":"MA",
    "gn:dem":1432,
    "gn:feature_class":"P",
    "gn:feature_code":"PPL",
    "gn:name":"Taskra",
    "gn:population":0,
    "gn:timezone":"Africa/Casablanca",
    "iso:country":"MA",
    "name:und_x_variant":[
        "Tassekra"
    ],
    "wof:name":"Taskra",
    "wof:placetype":"locality"
},
  "geometry": {"coordinates":[-9.08586,29.91662],"type":"Point"}
}