{
  "type": "Feature",
  "properties": {
    "gn:admin1_code":"05",
    "gn:asciiname":"Ammarghoud",
    "gn:country_code":"MA",
    "gn:dem":1528,
    "gn:feature_class":"P",
    "gn:feature_code":"PPL",
    "gn:name":"Ammarghoud",
    "gn:population":0,
    "gn:timezone":"Africa/Casablanca",
    "iso:country":"MA",
    "name:und_x_variant":[
        "Wamirgout"
    ],
    "wof:name":"Ammarghoud",
    "wof:placetype":"locality"
},
  "geometry": {"coordinates":[-6.95613,31.46297],"type":"Point"}
}