{
  "type": "Feature",
  "properties": {
    "gn:admin1_code":"01",
    "gn:asciiname":"Douar Ouaoussif",
    "gn:country_code":"MA",
    "gn:dem":254,
    "gn:feature_class":"P",
    "gn:feature_code":"PPL",
    "gn:name":"Douar Ouaoussif",
    "gn:population":0,
    "gn:timezone":"Africa/Casablanca",
    "iso:country":"MA",
    "name:und_x_variant":[
        "Daousif",
        "Dausif",
        "Ouass\u00eef",
        "Douar Ouaoussif"
    ],
    "wof:name":"Douar Ouaoussif",
    "wof:placetype":"locality"
},
  "geometry": {"coordinates":[-4.41519,35.08284],"type":"Point"}
}