{
  "type": "Feature",
  "properties": {
    "gn:admin1_code":"9.0",
    "gn:asciiname":"Ait bou Laich",
    "gn:country_code":"MA",
    "gn:dem":697,
    "gn:feature_class":"P",
    "gn:feature_code":"PPL",
    "gn:name":"A\u00eft bou La\u00efch",
    "gn:population":0,
    "gn:timezone":"Africa/Casablanca",
    "iso:country":"MA",
    "wof:name":"Ait bou Laich",
    "wof:placetype":"locality"
},
  "geometry": {"coordinates":[-9.05086,30.12435],"type":"Point"}
}