{
  "type": "Feature",
  "properties": {
    "gn:admin1_code":"8.0",
    "gn:asciiname":"Dar Alberj",
    "gn:country_code":"MA",
    "gn:dem":1342,
    "gn:feature_class":"P",
    "gn:feature_code":"PPL",
    "gn:name":"Dar Alberj",
    "gn:population":0,
    "gn:timezone":"Africa/Casablanca",
    "iso:country":"MA",
    "wof:name":"Dar Alberj",
    "wof:placetype":"locality"
},
  "geometry": {"coordinates":[-6.92659,30.53117],"type":"Point"}
}