{
  "type": "Feature",
  "properties": {
    "gn:admin1_code":"01",
    "gn:asciiname":"Tazroutene",
    "gn:country_code":"MA",
    "gn:dem":260,
    "gn:feature_class":"P",
    "gn:feature_code":"PPL",
    "gn:name":"Tazroutene",
    "gn:population":0,
    "gn:timezone":"Africa/Casablanca",
    "iso:country":"MA",
    "name:und_x_variant":[
        "Tazroute",
        "Tazroutane",
        "Tazroutene"
    ],
    "wof:name":"Tazroutene",
    "wof:placetype":"locality"
},
  "geometry": {"coordinates":[-5.76334,35.42418],"type":"Point"}
}