{
  "type": "Feature",
  "properties": {
    "gn:admin1_code":"7.0",
    "gn:asciiname":"Rbaat Ben Khalija",
    "gn:country_code":"MA",
    "gn:dem":316,
    "gn:feature_class":"P",
    "gn:feature_code":"PPL",
    "gn:name":"Rbaat Ben Khalija",
    "gn:population":0,
    "gn:timezone":"Africa/Casablanca",
    "iso:country":"MA",
    "wof:name":"Rbaat Ben Khalija",
    "wof:placetype":"locality"
},
  "geometry": {"coordinates":[-8.66876,32.24514],"type":"Point"}
}