{
  "type": "Feature",
  "properties": {
    "gn:admin1_code":"07",
    "gn:asciiname":"Douar Oulad Amer Leqliaa",
    "gn:country_code":"MA",
    "gn:dem":350,
    "gn:feature_class":"P",
    "gn:feature_code":"PPL",
    "gn:name":"Douar Oulad Amer Leqliaa",
    "gn:population":0,
    "gn:timezone":"Africa/Casablanca",
    "iso:country":"MA",
    "name:und_x_variant":[
        "Oulad Amer Tizmarine",
        "Douar Oulad Ameur",
        "Oulad Ameur",
        "Douar Oulad Amer",
        "Douar Oulad Amer Leqliaa"
    ],
    "wof:name":"Douar Oulad Amer Leqliaa",
    "wof:placetype":"locality"
},
  "geometry": {"coordinates":[-8.34403,32.23748],"type":"Point"}
}