{
  "type": "Feature",
  "properties": {
    "gn:admin1_code":"7.0",
    "gn:asciiname":"Douar Oulad Ali El Hamri",
    "gn:country_code":"MA",
    "gn:dem":133,
    "gn:feature_class":"P",
    "gn:feature_code":"PPL",
    "gn:name":"Douar Oulad Ali El Hamri",
    "gn:population":0,
    "gn:timezone":"Africa/Casablanca",
    "iso:country":"MA",
    "wof:name":"Douar Oulad Ali El Hamri",
    "wof:placetype":"locality"
},
  "geometry": {"coordinates":[-9.1533,32.18897],"type":"Point"}
}