{
  "type": "Feature",
  "properties": {
    "gn:country":"MA",
    "gn:fcode":"ADM3",
    "gn:pop":15050,
    "iso:country":"MA",
    "name:ara_x_preferred":[
        "\u0645\u062a\u0648\u062d"
    ],
    "name:ara_x_variant":[
        "\u0645\u06ad\u0631\u0633"
    ],
    "name:bul_x_preferred":[
        "\u041c\u043e\u0433\u0440\u0435\u0441"
    ],
    "name:cat_x_preferred":[
        "Mogress"
    ],
    "name:ceb_x_preferred":[
        "Mogress"
    ],
    "name:eng_x_preferred":[
        "Mogress"
    ],
    "name:fra_x_preferred":[
        "Mogress"
    ],
    "name:fra_x_variant":[
        "Mogress (CR)",
        "Mogress (Commune Rurale)"
    ],
    "name:ita_x_preferred":[
        "Mogress"
    ],
    "name:swe_x_preferred":[
        "Mogress"
    ],
    "qs:name":"Mogress",
    "qs:photos_9r":0,
    "qs:photos_sr":0,
    "qs:pop_sr":"6",
    "wd:wordcount":60,
    "wof:name":"Mogress",
    "wof:placetype":"localadmin",
    "wof:population":15050
},
  "geometry": {"coordinates":[-8.44971,32.90096],"type":"Point"}
}