{
  "type": "Feature",
  "properties": {
    "gn:admin1_code":"5.0",
    "gn:asciiname":"Gouwfri",
    "gn:country_code":"MA",
    "gn:dem":1671,
    "gn:feature_class":"P",
    "gn:feature_code":"PPL",
    "gn:name":"Gouwfri",
    "gn:population":0,
    "gn:timezone":"Africa/Casablanca",
    "iso:country":"MA",
    "wof:name":"Gouwfri",
    "wof:placetype":"locality"
},
  "geometry": {"coordinates":[-6.52917,31.93803],"type":"Point"}
}