{
  "type": "Feature",
  "properties": {
    "gn:admin1_code":"4.0",
    "gn:asciiname":"Douar Lahlaya",
    "gn:country_code":"MA",
    "gn:dem":90,
    "gn:feature_class":"P",
    "gn:feature_code":"PPL",
    "gn:name":"Douar Lahlaya",
    "gn:population":0,
    "gn:timezone":"Africa/Casablanca",
    "iso:country":"MA",
    "wof:name":"Douar Lahlaya",
    "wof:placetype":"locality"
},
  "geometry": {"coordinates":[-5.78221,34.50675],"type":"Point"}
}