{
  "type": "Feature",
  "properties": {
    "gn:admin1_code":"7.0",
    "gn:asciiname":"Iminogoug",
    "gn:country_code":"MA",
    "gn:dem":1246,
    "gn:feature_class":"P",
    "gn:feature_code":"PPL",
    "gn:name":"Iminogoug",
    "gn:population":0,
    "gn:timezone":"Africa/Casablanca",
    "iso:country":"MA",
    "wof:name":"Iminogoug",
    "wof:placetype":"locality"
},
  "geometry": {"coordinates":[-7.29696,31.56498],"type":"Point"}
}