{
  "type": "Feature",
  "properties": {
    "gn:admin1_code":"08",
    "gn:asciiname":"Khlil",
    "gn:country_code":"MA",
    "gn:dem":999,
    "gn:feature_class":"P",
    "gn:feature_code":"PPL",
    "gn:name":"Khlil",
    "gn:population":0,
    "gn:timezone":"Africa/Casablanca",
    "iso:country":"MA",
    "wof:name":"Khlil",
    "wof:placetype":"locality"
},
  "geometry": {"coordinates":[-4.90742,31.67732],"type":"Point"}
}