{
  "type": "Feature",
  "properties": {
    "gn:admin1_code":"4.0",
    "gn:asciiname":"Douar Goula",
    "gn:country_code":"MA",
    "gn:dem":380,
    "gn:feature_class":"P",
    "gn:feature_code":"PPL",
    "gn:name":"Douar Goula",
    "gn:population":0,
    "gn:timezone":"Africa/Casablanca",
    "iso:country":"MA",
    "wof:name":"Douar Goula",
    "wof:placetype":"locality"
},
  "geometry": {"coordinates":[-6.63606,33.7019],"type":"Point"}
}