{
  "type": "Feature",
  "properties": {
    "gn:admin1_code":"09",
    "gn:asciiname":"Imouchchiywn",
    "gn:country_code":"MA",
    "gn:dem":1193,
    "gn:feature_class":"P",
    "gn:feature_code":"PPL",
    "gn:name":"Imouchchiywn",
    "gn:population":0,
    "gn:timezone":"Africa/Casablanca",
    "iso:country":"MA",
    "name:und_x_variant":[
        "Imachchioun"
    ],
    "wof:name":"Imouchchiywn",
    "wof:placetype":"locality"
},
  "geometry": {"coordinates":[-9.31823,29.51434],"type":"Point"}
}