{
  "type": "Feature",
  "properties": {
    "gn:admin1_code":"5.0",
    "gn:asciiname":"Ayt Jilali",
    "gn:country_code":"MA",
    "gn:dem":591,
    "gn:feature_class":"P",
    "gn:feature_code":"PPL",
    "gn:name":"Ayt Jilali",
    "gn:population":0,
    "gn:timezone":"Africa/Casablanca",
    "iso:country":"MA",
    "wof:name":"Ayt Jilali",
    "wof:placetype":"locality"
},
  "geometry": {"coordinates":[-6.60527,32.71881],"type":"Point"}
}