{
  "type": "Feature",
  "properties": {
    "gn:admin1_code":"01",
    "gn:asciiname":"Dahar Sarfine",
    "gn:country_code":"MA",
    "gn:dem":1097,
    "gn:feature_class":"P",
    "gn:feature_code":"PPL",
    "gn:name":"Dahar Sarfine",
    "gn:population":0,
    "gn:timezone":"Africa/Casablanca",
    "iso:country":"MA",
    "name:und_x_variant":[
        "Dahar Sabfine",
        "Dahar Sarfine"
    ],
    "wof:name":"Dahar Sarfine",
    "wof:placetype":"locality"
},
  "geometry": {"coordinates":[-4.11,34.96],"type":"Point"}
}