{
  "type": "Feature",
  "properties": {
    "gn:admin1_code":"01",
    "gn:asciiname":"Zarqa",
    "gn:country_code":"MA",
    "gn:dem":648,
    "gn:feature_class":"P",
    "gn:feature_code":"PPL",
    "gn:name":"Zarqa",
    "gn:population":0,
    "gn:timezone":"Africa/Casablanca",
    "iso:country":"MA",
    "name:und_x_variant":[
        "Zerka"
    ],
    "wof:name":"Zarqa",
    "wof:placetype":"locality"
},
  "geometry": {"coordinates":[-5.4088,35.39897],"type":"Point"}
}