{
  "type": "Feature",
  "properties": {
    "gn:admin1_code":"01",
    "gn:asciiname":"Zarqa",
    "gn:country_code":"MA",
    "gn:dem":648,
    "gn:feature_class":"P",
    "gn:feature_code":"PPL",
    "gn:name":"Zarqa",
    "gn:population":0,
    "gn:timezone":"Africa/Casablanca",
    "iso:country":"MA",
    "name:ara_x_preferred":[
        "\u0627\u0644\u0632\u0631\u0642\u0627\u0621"
    ],
    "name:arz_x_preferred":[
        "\u0627\u0644\u0632\u0631\u0642\u0627"
    ],
    "name:bel_x_preferred":[
        "\u042d\u0437-\u0417\u0430\u0440\u043a\u0430"
    ],
    "name:bul_x_preferred":[
        "\u0417\u0430\u0440\u043a\u0430"
    ],
    "name:cat_x_preferred":[
        "Zarqa"
    ],
    "name:ceb_x_preferred":[
        "Zarqa"
    ],
    "name:ces_x_preferred":[
        "Zark\u00e1"
    ],
    "name:che_x_preferred":[
        "\u042d\u0437-\u0417\u0430\u0440\u043a\u044a\u0430"
    ],
    "name:cym_x_preferred":[
        "Zarqa"
    ],
    "name:dan_x_preferred":[
        "Zarqa"
    ],
    "name:deu_x_preferred":[
        "Zarqa"
    ],
    "name:epo_x_preferred":[
        "Zarkao"
    ],
    "name:eus_x_preferred":[
        "Zarqa"
    ],
    "name:fas_x_preferred":[
        "\u0632\u0631\u0642\u0627\u0621"
    ],
    "name:fin_x_preferred":[
        "Zarqa"
    ],
    "name:fra_x_preferred":[
        "Zarka"
    ],
    "name:gle_x_preferred":[
        "Zarqa"
    ],
    "name:heb_x_preferred":[
        "\u05d6\u05e8\u05e7\u05d0"
    ],
    "name:ile_x_preferred":[
        "Zarqa"
    ],
    "name:ind_x_preferred":[
        "Zarqa"
    ],
    "name:ita_x_preferred":[
        "Al-Zarqa"
    ],
    "name:jpn_x_preferred":[
        "\u30b6\u30eb\u30ab"
    ],
    "name:kal_x_preferred":[
        "Zarqa"
    ],
    "name:kaz_x_preferred":[
        "\u042d\u0437-\u0417\u0430\u0440\u043a\u0430 \u049b\u0430\u043b\u0430\u0441\u044b"
    ],
    "name:kor_x_preferred":[
        "\uc790\ub974\uce74"
    ],
    "name:lat_x_preferred":[
        "Zarqa"
    ],
    "name:lit_x_preferred":[
        "Zarka"
    ],
    "name:mal_x_preferred":[
        "\u0d38\u0d7c\u0d16"
    ],
    "name:msa_x_preferred":[
        "Zarqa"
    ],
    "name:mzn_x_preferred":[
        "\u0632\u0631\u0642\u0627"
    ],
    "name:nld_x_preferred":[
        "Zarka"
    ],
    "name:nno_x_preferred":[
        "Zarqa"
    ],
    "name:nor_x_preferred":[
        "Zarqa"
    ],
    "name:pnb_x_preferred":[
        "\u0632\u0631\u0642\u0627"
    ],
    "name:pol_x_preferred":[
        "Az-Zarka"
    ],
    "name:por_x_preferred":[
        "Zarqa"
    ],
    "name:rus_x_preferred":[
        "\u042d\u0437-\u0417\u0430\u0440\u043a\u0430"
    ],
    "name:sco_x_preferred":[
        "Zarqa"
    ],
    "name:spa_x_preferred":[
        "Zarqa"
    ],
    "name:sqi_x_preferred":[
        "Zarqa"
    ],
    "name:swe_x_preferred":[
        "Zarqa"
    ],
    "name:tha_x_preferred":[
        "\u0e0b\u0e32\u0e23\u0e4c\u0e01\u0e32"
    ],
    "name:tur_x_preferred":[
        "Zerka"
    ],
    "name:ukr_x_preferred":[
        "\u0415\u0437-\u0417\u0430\u0440\u043a\u0430"
    ],
    "name:urd_x_preferred":[
        "\u0632\u0631\u0642\u0627\u0621"
    ],
    "name:vie_x_preferred":[
        "Zarqa"
    ],
    "name:war_x_preferred":[
        "Zarqa"
    ],
    "name:zho_x_preferred":[
        "\u624e\u5c14\u5361"
    ],
    "wof:name":"Zarqa",
    "wof:placetype":"locality"
},
  "geometry": {"coordinates":[-5.4088,35.39897],"type":"Point"}
}