{
  "type": "Feature",
  "properties": {
    "gn:admin1_code":"55",
    "gn:asciiname":"Agoudas",
    "gn:country_code":"MA",
    "gn:dem":1710,
    "gn:feature_class":"P",
    "gn:feature_code":"PPL",
    "gn:name":"Agoudas",
    "gn:population":0,
    "gn:timezone":"Africa/Casablanca",
    "iso:country":"MA",
    "wof:name":"Agoudas",
    "wof:placetype":"locality"
},
  "geometry": {"coordinates":[-7.73,30.46],"type":"Point"}
}