{
  "type": "Feature",
  "properties": {
    "gn:admin1_code":"01",
    "gn:asciiname":"El Koudia",
    "gn:country_code":"MA",
    "gn:dem":341,
    "gn:feature_class":"P",
    "gn:feature_code":"PPL",
    "gn:name":"El Koudia",
    "gn:population":0,
    "gn:timezone":"Africa/Casablanca",
    "iso:country":"MA",
    "name:und_x_variant":[
        "Koudia",
        "El Koudia"
    ],
    "wof:name":"El Koudia",
    "wof:placetype":"locality"
},
  "geometry": {"coordinates":[-5.25391,34.72044],"type":"Point"}
}