{
  "type": "Feature",
  "properties": {
    "gn:admin1_code":"08",
    "gn:asciiname":"Irhem Akdim",
    "gn:country_code":"MA",
    "gn:dem":1180,
    "gn:feature_class":"P",
    "gn:feature_code":"PPL",
    "gn:name":"Irhem Akdim",
    "gn:population":0,
    "gn:timezone":"Africa/Casablanca",
    "iso:country":"MA",
    "name:und_x_variant":[
        "Igham akdim",
        "Irhem Akdim"
    ],
    "wof:name":"Irhem Akdim",
    "wof:placetype":"locality"
},
  "geometry": {"coordinates":[-5.41261,31.47055],"type":"Point"}
}