{
  "type": "Feature",
  "properties": {
    "gn:admin1_code":"07",
    "gn:asciiname":"Al Maharad",
    "gn:country_code":"MA",
    "gn:dem":811,
    "gn:feature_class":"P",
    "gn:feature_code":"PPL",
    "gn:name":"Al Maharad",
    "gn:population":0,
    "gn:timezone":"Africa/Casablanca",
    "iso:country":"MA",
    "name:und_x_variant":[
        "Douar el Maharad",
        "El Meharad",
        "Al Maharad"
    ],
    "wof:name":"Al Maharad",
    "wof:placetype":"locality"
},
  "geometry": {"coordinates":[-8.40475,31.27719],"type":"Point"}
}