{
  "type": "Feature",
  "properties": {
    "gn:admin1_code":"9.0",
    "gn:asciiname":"Ouitkrazene",
    "gn:country_code":"MA",
    "gn:dem":920,
    "gn:feature_class":"P",
    "gn:feature_code":"PPL",
    "gn:name":"Ouitkrazene",
    "gn:population":0,
    "gn:timezone":"Africa/Casablanca",
    "iso:country":"MA",
    "wof:name":"Ouitkrazene",
    "wof:placetype":"locality"
},
  "geometry": {"coordinates":[-8.80919,30.72766],"type":"Point"}
}