{
  "type": "Feature",
  "properties": {
    "gn:admin1_code":"02",
    "gn:asciiname":"Dar Ben Khsied",
    "gn:country_code":"MA",
    "gn:dem":450,
    "gn:feature_class":"P",
    "gn:feature_code":"PPL",
    "gn:name":"Dar Ben Khsied",
    "gn:population":0,
    "gn:timezone":"Africa/Casablanca",
    "iso:country":"MA",
    "wof:name":"Dar Ben Khsied",
    "wof:placetype":"locality"
},
  "geometry": {"coordinates":[-1.96,34.82],"type":"Point"}
}