{
  "type": "Feature",
  "properties": {
    "gn:admin1_code":"01",
    "gn:asciiname":"Oulad Laayyachi",
    "gn:country_code":"MA",
    "gn:dem":89,
    "gn:feature_class":"P",
    "gn:feature_code":"PPL",
    "gn:name":"Oulad Laayyachi",
    "gn:population":0,
    "gn:timezone":"Africa/Casablanca",
    "iso:country":"MA",
    "name:und_x_variant":[
        "Laiacha",
        "Aulad Laiachi",
        "Oulad La\u00efacha",
        "Oulad Laayyachi"
    ],
    "wof:name":"Oulad Laayyachi",
    "wof:placetype":"locality"
},
  "geometry": {"coordinates":[-5.9321,35.52010999999999],"type":"Point"}
}