{
  "type": "Feature",
  "properties": {
    "gn:admin1_code":"06",
    "gn:asciiname":"Douar Laina",
    "gn:country_code":"MA",
    "gn:dem":249,
    "gn:feature_class":"P",
    "gn:feature_code":"PPL",
    "gn:name":"Douar La\u00efna",
    "gn:population":0,
    "gn:timezone":"Africa/Casablanca",
    "iso:country":"MA",
    "wof:name":"Douar Laina",
    "wof:placetype":"locality"
},
  "geometry": {"coordinates":[-8.5045,32.33934],"type":"Point"}
}