{
  "type": "Feature",
  "properties": {
    "gn:admin1_code":"03",
    "gn:asciiname":"Douar Moussat",
    "gn:country_code":"MA",
    "gn:dem":193,
    "gn:feature_class":"P",
    "gn:feature_code":"PPL",
    "gn:name":"Douar Moussat",
    "gn:population":0,
    "gn:timezone":"Africa/Casablanca",
    "iso:country":"MA",
    "name:und_x_variant":[
        "Douar Oulad Moussa",
        "Moussatt",
        "Oulad Moussa",
        "Douar Moussat"
    ],
    "wof:name":"Douar Moussat",
    "wof:placetype":"locality"
},
  "geometry": {"coordinates":[-5.23143,34.3426],"type":"Point"}
}