{
  "type": "Feature",
  "properties": {
    "gn:admin1_code":"08",
    "gn:asciiname":"Tafrout",
    "gn:country_code":"MA",
    "gn:dem":1711,
    "gn:feature_class":"P",
    "gn:feature_code":"PPL",
    "gn:name":"Tafrout",
    "gn:population":0,
    "gn:timezone":"Africa/Casablanca",
    "iso:country":"MA",
    "wof:name":"Tafrout",
    "wof:placetype":"locality"
},
  "geometry": {"coordinates":[-6.55333,31.32512],"type":"Point"}
}