{
  "type": "Feature",
  "properties": {
    "gn:admin1_code":"10.0",
    "gn:asciiname":"Id 'Addi",
    "gn:country_code":"MA",
    "gn:dem":789,
    "gn:feature_class":"P",
    "gn:feature_code":"PPL",
    "gn:name":"Id \u2019Addi",
    "gn:population":0,
    "gn:timezone":"Africa/Casablanca",
    "iso:country":"MA",
    "wof:name":"Id 'Addi",
    "wof:placetype":"locality"
},
  "geometry": {"coordinates":[-9.88102,29.28176],"type":"Point"}
}