{
  "type": "Feature",
  "properties": {
    "gn:admin1_code":"03",
    "gn:asciiname":"Ifrane n-Terjan",
    "gn:country_code":"MA",
    "gn:dem":1318,
    "gn:feature_class":"P",
    "gn:feature_code":"PPL",
    "gn:name":"Ifrane n-Terjan",
    "gn:population":0,
    "gn:timezone":"Africa/Casablanca",
    "iso:country":"MA",
    "name:und_x_variant":[
        "Ifrane Ntourjou",
        "Ifrane n\u2019 Tourjou",
        "Ifrane n-Terjan"
    ],
    "wof:name":"Ifrane n-Terjan",
    "wof:placetype":"locality"
},
  "geometry": {"coordinates":[-4.61759,33.59134],"type":"Point"}
}