{
  "type": "Feature",
  "properties": {
    "gn:admin1_code":"9.0",
    "gn:asciiname":"Ilmatene",
    "gn:country_code":"MA",
    "gn:dem":887,
    "gn:feature_class":"P",
    "gn:feature_code":"PPL",
    "gn:name":"Ilmatene",
    "gn:population":0,
    "gn:timezone":"Africa/Casablanca",
    "iso:country":"MA",
    "wof:name":"Ilmatene",
    "wof:placetype":"locality"
},
  "geometry": {"coordinates":[-9.1116,30.01201],"type":"Point"}
}