{
  "type": "Feature",
  "properties": {
    "gn:admin1_code":"03",
    "gn:asciiname":"Douar Jemaa",
    "gn:country_code":"MA",
    "gn:dem":383,
    "gn:feature_class":"P",
    "gn:feature_code":"PPL",
    "gn:name":"Douar Jemaa",
    "gn:population":0,
    "gn:timezone":"Africa/Casablanca",
    "iso:country":"MA",
    "name:und_x_variant":[
        "Jemaa",
        "Douar Oulad Jemar",
        "Douar Jemaa"
    ],
    "wof:name":"Douar Jemaa",
    "wof:placetype":"locality"
},
  "geometry": {"coordinates":[-4.76,34.3262],"type":"Point"}
}