{
  "type": "Feature",
  "properties": {
    "gn:admin1_code":"02",
    "gn:asciiname":"Douar Ihemmoudane",
    "gn:country_code":"MA",
    "gn:dem":342,
    "gn:feature_class":"P",
    "gn:feature_code":"PPL",
    "gn:name":"Douar Ihemmoudane",
    "gn:population":0,
    "gn:timezone":"Africa/Casablanca",
    "iso:country":"MA",
    "name:und_x_variant":[
        "Douar Ihemmoudene"
    ],
    "wof:name":"Douar Ihemmoudane",
    "wof:placetype":"locality"
},
  "geometry": {"coordinates":[-3.67486,35.14076],"type":"Point"}
}