{
  "type": "Feature",
  "properties": {
    "gn:admin1_code":"7.0",
    "gn:asciiname":"Oulad Laaroussi",
    "gn:country_code":"MA",
    "gn:dem":461,
    "gn:feature_class":"P",
    "gn:feature_code":"PPL",
    "gn:name":"Oulad Laaroussi",
    "gn:population":0,
    "gn:timezone":"Africa/Casablanca",
    "iso:country":"MA",
    "wof:name":"Oulad Laaroussi",
    "wof:placetype":"locality"
},
  "geometry": {"coordinates":[-9.09731,31.9545],"type":"Point"}
}