{
  "type": "Feature",
  "properties": {
    "gn:admin1_code":"9.0",
    "gn:asciiname":"Agadir Woul",
    "gn:country_code":"MA",
    "gn:dem":1183,
    "gn:feature_class":"P",
    "gn:feature_code":"PPL",
    "gn:name":"Agadir Woul",
    "gn:population":0,
    "gn:timezone":"Africa/Casablanca",
    "iso:country":"MA",
    "wof:name":"Agadir Woul",
    "wof:placetype":"locality"
},
  "geometry": {"coordinates":[-9.02921,29.55904],"type":"Point"}
}