{
  "type": "Feature",
  "properties": {
    "gn:admin1_code":"7.0",
    "gn:asciiname":"Tahfriygt",
    "gn:country_code":"MA",
    "gn:dem":1483,
    "gn:feature_class":"P",
    "gn:feature_code":"PPL",
    "gn:name":"Tahfriygt",
    "gn:population":0,
    "gn:timezone":"Africa/Casablanca",
    "iso:country":"MA",
    "wof:name":"Tahfriygt",
    "wof:placetype":"locality"
},
  "geometry": {"coordinates":[-7.18236,31.48914000000001],"type":"Point"}
}