{
  "type": "Feature",
  "properties": {
    "gn:admin1_code":"7.0",
    "gn:asciiname":"Douar Rja Fellah",
    "gn:country_code":"MA",
    "gn:dem":130,
    "gn:feature_class":"P",
    "gn:feature_code":"PPL",
    "gn:name":"Douar Rja Fellah",
    "gn:population":0,
    "gn:timezone":"Africa/Casablanca",
    "iso:country":"MA",
    "wof:name":"Douar Rja Fellah",
    "wof:placetype":"locality"
},
  "geometry": {"coordinates":[-8.98071,32.25297],"type":"Point"}
}