{
  "type": "Feature",
  "properties": {
    "gn:admin1_code":"01",
    "gn:asciiname":"Douar Tandert",
    "gn:country_code":"MA",
    "gn:dem":829,
    "gn:feature_class":"P",
    "gn:feature_code":"PPL",
    "gn:name":"Douar Tandert",
    "gn:population":0,
    "gn:timezone":"Africa/Casablanca",
    "iso:country":"MA",
    "name:und_x_variant":[
        "Tendret",
        "Tamderetz",
        "Tamderets",
        "Douar Tandert"
    ],
    "wof:name":"Douar Tandert",
    "wof:placetype":"locality"
},
  "geometry": {"coordinates":[-4.85727,35.06702],"type":"Point"}
}