{
  "type": "Feature",
  "properties": {
    "gn:admin1_code":"1.0",
    "gn:asciiname":"Douar Ihemmoutene",
    "gn:country_code":"MA",
    "gn:dem":729,
    "gn:feature_class":"P",
    "gn:feature_code":"PPL",
    "gn:name":"Douar Ihemmoutene",
    "gn:population":0,
    "gn:timezone":"Africa/Casablanca",
    "iso:country":"MA",
    "wof:name":"Douar Ihemmoutene",
    "wof:placetype":"locality"
},
  "geometry": {"coordinates":[-4.37386,35.01698],"type":"Point"}
}