{
  "type": "Feature",
  "properties": {
    "gn:admin1_code":"03",
    "gn:asciiname":"Douar Ait Laachor",
    "gn:country_code":"MA",
    "gn:dem":480,
    "gn:feature_class":"P",
    "gn:feature_code":"PPL",
    "gn:name":"Douar Ait Laachor",
    "gn:population":0,
    "gn:timezone":"Africa/Casablanca",
    "iso:country":"MA",
    "name:und_x_variant":[
        "Douar Bou Kennfoud",
        "Douar Bou Kenfoud",
        "Douar Ait Laachor"
    ],
    "wof:name":"Douar Ait Laachor",
    "wof:placetype":"locality"
},
  "geometry": {"coordinates":[-5.53262,34.12971],"type":"Point"}
}