{
  "type": "Feature",
  "properties": {
    "gn:admin1_code":"1.0",
    "gn:asciiname":"Douar Bouskene",
    "gn:country_code":"MA",
    "gn:dem":111,
    "gn:feature_class":"P",
    "gn:feature_code":"PPL",
    "gn:name":"Douar Bouskene",
    "gn:population":0,
    "gn:timezone":"Africa/Casablanca",
    "iso:country":"MA",
    "wof:name":"Douar Bouskene",
    "wof:placetype":"locality"
},
  "geometry": {"coordinates":[-4.95363,35.30467],"type":"Point"}
}