{
  "type": "Feature",
  "properties": {
    "gn:admin1_code":"3.0",
    "gn:asciiname":"Douar Ayt Ahmed",
    "gn:country_code":"MA",
    "gn:dem":1108,
    "gn:feature_class":"P",
    "gn:feature_code":"PPL",
    "gn:name":"Douar Ayt Ahmed",
    "gn:population":0,
    "gn:timezone":"Africa/Casablanca",
    "iso:country":"MA",
    "wof:name":"Douar Ayt Ahmed",
    "wof:placetype":"locality"
},
  "geometry": {"coordinates":[-4.42109,33.80953],"type":"Point"}
}