{
  "type": "Feature",
  "properties": {
    "gn:admin1_code":"7.0",
    "gn:asciiname":"Oulad Miloud Ben Ali",
    "gn:country_code":"MA",
    "gn:dem":420,
    "gn:feature_class":"P",
    "gn:feature_code":"PPL",
    "gn:name":"Oulad Miloud Ben Ali",
    "gn:population":0,
    "gn:timezone":"Africa/Casablanca",
    "iso:country":"MA",
    "wof:name":"Oulad Miloud Ben Ali",
    "wof:placetype":"locality"
},
  "geometry": {"coordinates":[-7.75655,32.3152],"type":"Point"}
}