{
  "type": "Feature",
  "properties": {
    "gn:admin1_code":"10.0",
    "gn:asciiname":"Izwawn",
    "gn:country_code":"MA",
    "gn:dem":823,
    "gn:feature_class":"P",
    "gn:feature_code":"PPL",
    "gn:name":"Izwawn",
    "gn:population":0,
    "gn:timezone":"Africa/Casablanca",
    "iso:country":"MA",
    "wof:name":"Izwawn",
    "wof:placetype":"locality"
},
  "geometry": {"coordinates":[-9.80132,29.36986],"type":"Point"}
}