{
  "type": "Feature",
  "properties": {
    "gn:admin1_code":"7.0",
    "gn:asciiname":"Dar Tahar Ben Hammadi",
    "gn:country_code":"MA",
    "gn:dem":395,
    "gn:feature_class":"P",
    "gn:feature_code":"PPL",
    "gn:name":"Dar Tahar Ben Hammadi",
    "gn:population":0,
    "gn:timezone":"Africa/Casablanca",
    "iso:country":"MA",
    "wof:name":"Dar Tahar Ben Hammadi",
    "wof:placetype":"locality"
},
  "geometry": {"coordinates":[-8.40111,31.59052],"type":"Point"}
}