{
  "type": "Feature",
  "properties": {
    "gn:admin1_code":"5.0",
    "gn:asciiname":"Anllatf",
    "gn:country_code":"MA",
    "gn:dem":1443,
    "gn:feature_class":"P",
    "gn:feature_code":"PPL",
    "gn:name":"Anllatf",
    "gn:population":0,
    "gn:timezone":"Africa/Casablanca",
    "iso:country":"MA",
    "wof:name":"Anllatf",
    "wof:placetype":"locality"
},
  "geometry": {"coordinates":[-6.70402,31.76828],"type":"Point"}
}