{
  "type": "Feature",
  "properties": {
    "gn:admin1_code":"01",
    "gn:asciiname":"Douar Chrif",
    "gn:country_code":"MA",
    "gn:dem":44,
    "gn:feature_class":"P",
    "gn:feature_code":"PPL",
    "gn:name":"Douar Chrif",
    "gn:population":0,
    "gn:timezone":"Africa/Casablanca",
    "iso:country":"MA",
    "wof:name":"Douar Chrif",
    "wof:placetype":"locality"
},
  "geometry": {"coordinates":[-5.99861,35.53455],"type":"Point"}
}