{
  "type": "Feature",
  "properties": {
    "gn:admin1_code":"07",
    "gn:asciiname":"Sebt Gzoula",
    "gn:country_code":"MA",
    "gn:dem":197,
    "gn:feature_class":"P",
    "gn:feature_code":"PPL",
    "gn:name":"Sebt Gzoula",
    "gn:population":0,
    "gn:timezone":"Africa/Casablanca",
    "iso:country":"MA",
    "name:ara_x_preferred":[
        "\u0633\u0628\u062a \u0643\u0632\u0648\u0644\u0629"
    ],
    "name:cat_x_preferred":[
        "Sebt Gzoula"
    ],
    "name:ceb_x_preferred":[
        "Sebt Gzoula"
    ],
    "name:fra_x_preferred":[
        "Sebt Gzoula"
    ],
    "name:ita_x_preferred":[
        "Sebt Gzoula"
    ],
    "name:swe_x_preferred":[
        "Sebt Gzoula"
    ],
    "name:und_x_variant":[
        "Es Sebt",
        "Sebt-Gzoula",
        "Es Sebt Gzoula",
        "Gzoula",
        "Sebt des Gzoula"
    ],
    "wof:name":"Sebt Gzoula",
    "wof:placetype":"locality"
},
  "geometry": {"coordinates":[-9.08366,32.10779],"type":"Point"}
}