{
  "type": "Feature",
  "properties": {
    "gn:admin1_code":"08",
    "gn:asciiname":"Talmouda",
    "gn:country_code":"MA",
    "gn:dem":1741,
    "gn:feature_class":"P",
    "gn:feature_code":"PPL",
    "gn:name":"Talmouda",
    "gn:population":0,
    "gn:timezone":"Africa/Casablanca",
    "iso:country":"MA",
    "wof:name":"Talmouda",
    "wof:placetype":"locality"
},
  "geometry": {"coordinates":[-7.49785,30.60679],"type":"Point"}
}