{
  "type": "Feature",
  "properties": {
    "gn:admin1_code":"3.0",
    "gn:asciiname":"Cooperative Salima",
    "gn:country_code":"MA",
    "gn:dem":824,
    "gn:feature_class":"P",
    "gn:feature_code":"PPLF",
    "gn:name":"Coop\u00e9rative Salima",
    "gn:population":0,
    "gn:timezone":"Africa/Casablanca",
    "iso:country":"MA",
    "name:und_x_variant":[
        "Coop\u00e9rative Salima",
        "Sous Centre"
    ],
    "wof:name":"Cooperative Salima",
    "wof:placetype":"locality"
},
  "geometry": {"coordinates":[-5.63238,33.66353],"type":"Point"}
}