{
  "type": "Feature",
  "properties": {
    "gn:admin1_code":"06",
    "gn:asciiname":"Douar Labsaylat",
    "gn:country_code":"MA",
    "gn:dem":122,
    "gn:feature_class":"P",
    "gn:feature_code":"PPL",
    "gn:name":"Douar Labsaylat",
    "gn:population":0,
    "gn:timezone":"Africa/Casablanca",
    "iso:country":"MA",
    "name:und_x_variant":[
        "Douar el Absailat"
    ],
    "wof:name":"Douar Labsaylat",
    "wof:placetype":"locality"
},
  "geometry": {"coordinates":[-8.63105,32.82621],"type":"Point"}
}