{
  "type": "Feature",
  "properties": {
    "gn:asciiname":"Ait Mansour",
    "gn:country_code":"MA",
    "gn:dem":1274,
    "gn:feature_class":"P",
    "gn:feature_code":"PPL",
    "gn:name":"Ait Mansour",
    "gn:population":0,
    "gn:timezone":"Africa/Casablanca",
    "iso:country":"MA",
    "wof:name":"Ait Mansour",
    "wof:placetype":"locality"
},
  "geometry": {"coordinates":[-8.87724,29.54799],"type":"Point"}
}