{
  "type": "Feature",
  "properties": {
    "gn:gn_country":"MA",
    "gn:gn_fcode":"ADM3",
    "gn:gn_pop":11133,
    "gn:population":12461,
    "iso:country":"MA",
    "name:ara_x_preferred":[
        "\u0623\u0648\u0644\u0627\u062f \u0627\u0645\u0631\u0627\u0628\u0637"
    ],
    "name:ara_x_variant":[
        "\u0623\u0648\u0646\u0627\u063a\u0629"
    ],
    "name:cat_x_preferred":[
        "Ounagha"
    ],
    "name:ceb_x_preferred":[
        "Ounara"
    ],
    "name:fin_x_preferred":[
        "Ounagha"
    ],
    "name:fra_x_preferred":[
        "Ounagha"
    ],
    "name:fra_x_variant":[
        "Ounagha (CR)",
        "Ounagha (Commune Rurale)"
    ],
    "name:ita_x_preferred":[
        "Ounagha"
    ],
    "name:por_x_preferred":[
        "Ounagha"
    ],
    "name:swe_x_preferred":[
        "Ounara"
    ],
    "qs_pg:aaroncc":"MA",
    "qs_pg:gn_country":"MA",
    "qs_pg:gn_fcode":"ADM3",
    "qs_pg:gn_pop":11133,
    "qs_pg:name":"Ounagha",
    "qs_pg:photos_9r":0,
    "qs_pg:photos_sr":0,
    "qs_pg:pop_sr":6,
    "qs_pg:qs_pg_placetype":"localadmin",
    "wof:name":"Ounagha",
    "wof:placetype":"localadmin",
    "wof:population":12461
},
  "geometry": {"coordinates":[-9.62981,31.50436],"type":"Point"}
}