{
  "type": "Feature",
  "properties": {
    "gn:admin1_code":"08",
    "gn:asciiname":"Ait Hamad",
    "gn:country_code":"MA",
    "gn:dem":1600,
    "gn:feature_class":"P",
    "gn:feature_code":"PPL",
    "gn:name":"A\u00eft Hamad",
    "gn:population":0,
    "gn:timezone":"Africa/Casablanca",
    "iso:country":"MA",
    "wof:name":"Ait Hamad",
    "wof:placetype":"locality"
},
  "geometry": {"coordinates":[-7.40647,31.14343],"type":"Point"}
}