{
  "type": "Feature",
  "properties": {
    "gn:admin1_code":"6.0",
    "gn:asciiname":"Jenanat",
    "gn:country_code":"MA",
    "gn:dem":364,
    "gn:feature_class":"P",
    "gn:feature_code":"PPL",
    "gn:name":"Jenanat",
    "gn:population":0,
    "gn:timezone":"Africa/Casablanca",
    "iso:country":"MA",
    "wof:name":"Jenanat",
    "wof:placetype":"locality"
},
  "geometry": {"coordinates":[-7.77035,32.7626],"type":"Point"}
}