{
  "type": "Feature",
  "properties": {
    "gn:admin1_code":"6.0",
    "gn:asciiname":"Aguib Lahrich",
    "gn:country_code":"MA",
    "gn:dem":505,
    "gn:feature_class":"P",
    "gn:feature_code":"PPL",
    "gn:name":"Aguib Lahrich",
    "gn:population":0,
    "gn:timezone":"Africa/Casablanca",
    "iso:country":"MA",
    "wof:name":"Aguib Lahrich",
    "wof:placetype":"locality"
},
  "geometry": {"coordinates":[-7.09322,33.22123],"type":"Point"}
}