{
  "type": "Feature",
  "properties": {
    "gn:admin1_code":"07",
    "gn:asciiname":"El Rhouiba",
    "gn:country_code":"MA",
    "gn:dem":101,
    "gn:feature_class":"P",
    "gn:feature_code":"PPL",
    "gn:name":"El Rhouiba",
    "gn:population":0,
    "gn:timezone":"Africa/Casablanca",
    "iso:country":"MA",
    "name:und_x_variant":[
        "Douar el Rhou\u00efba",
        "El Rhouiba"
    ],
    "wof:name":"El Rhouiba",
    "wof:placetype":"locality"
},
  "geometry": {"coordinates":[-9.03959,32.62062],"type":"Point"}
}