{
  "type": "Feature",
  "properties": {
    "gn:admin1_code":"01",
    "gn:admin2_code":"151.0",
    "gn:admin3_code":"1615109052.0",
    "gn:asciiname":"Brikcha",
    "gn:country_code":"MA",
    "gn:dem":307,
    "gn:feature_class":"P",
    "gn:feature_code":"PPLA3",
    "gn:name":"Brikcha",
    "gn:population":0,
    "gn:timezone":"Africa/Casablanca",
    "iso:country":"MA",
    "name:ara_x_preferred":[
        "\u0628\u0631\u064a\u0643\u0634\u0629"
    ],
    "name:cat_x_preferred":[
        "Brikcha"
    ],
    "name:fra_x_preferred":[
        "Brikcha"
    ],
    "name:ita_x_preferred":[
        "Brikcha"
    ],
    "name:pol_x_preferred":[
        "Bariksza"
    ],
    "name:und_x_variant":[
        "Douar Brikcha",
        "Brickcha"
    ],
    "name:urd_x_preferred":[
        "\u0628\u0631\u06cc\u06a9\u0634\u06c1"
    ],
    "wof:name":"Brikcha",
    "wof:placetype":"locality"
},
  "geometry": {"coordinates":[-5.57295,34.96732],"type":"Point"}
}