{
  "type": "Feature",
  "properties": {
    "gn:admin1_code":"01",
    "gn:admin2_code":"151.0",
    "gn:admin3_code":"1615109052.0",
    "gn:asciiname":"Brikcha",
    "gn:country_code":"MA",
    "gn:dem":307,
    "gn:feature_class":"P",
    "gn:feature_code":"PPLA3",
    "gn:name":"Brikcha",
    "gn:population":0,
    "gn:timezone":"Africa/Casablanca",
    "iso:country":"MA",
    "name:und_x_variant":[
        "Douar Brikcha",
        "Brickcha",
        "Brikcha"
    ],
    "wof:name":"Brikcha",
    "wof:placetype":"locality"
},
  "geometry": {"coordinates":[-5.57295,34.96732],"type":"Point"}
}