{
  "type": "Feature",
  "properties": {
    "gn:admin1_code":"08",
    "gn:asciiname":"Ksebt n'Ourhi",
    "gn:country_code":"MA",
    "gn:dem":683,
    "gn:feature_class":"P",
    "gn:feature_code":"PPL",
    "gn:name":"Ksebt n\u2019Ourhi",
    "gn:population":0,
    "gn:timezone":"Africa/Casablanca",
    "iso:country":"MA",
    "wof:name":"Ksebt n'Ourhi",
    "wof:placetype":"locality"
},
  "geometry": {"coordinates":[-5.68,30.25],"type":"Point"}
}