{
  "type": "Feature",
  "properties": {
    "gn:admin1_code":"05",
    "gn:asciiname":"Ait Wa'ziq",
    "gn:country_code":"MA",
    "gn:dem":1124,
    "gn:feature_class":"P",
    "gn:feature_code":"PPL",
    "gn:name":"A\u00eft Wa\u2019ziq",
    "gn:population":0,
    "gn:timezone":"Africa/Casablanca",
    "iso:country":"MA",
    "name:und_x_variant":[
        "A\u00eft Wa\u2019ziq",
        "A\u00eft Ou Azik"
    ],
    "wof:name":"Ait Wa'ziq",
    "wof:placetype":"locality"
},
  "geometry": {"coordinates":[-6.37395,32.18225],"type":"Point"}
}