{
  "type": "Feature",
  "properties": {
    "gn:admin1_code":"7.0",
    "gn:asciiname":"Iznagn",
    "gn:country_code":"MA",
    "gn:dem":954,
    "gn:feature_class":"P",
    "gn:feature_code":"PPL",
    "gn:name":"Iznagn",
    "gn:population":0,
    "gn:timezone":"Africa/Casablanca",
    "iso:country":"MA",
    "wof:name":"Iznagn",
    "wof:placetype":"locality"
},
  "geometry": {"coordinates":[-9.01252,31.20409],"type":"Point"}
}