{
  "type": "Feature",
  "properties": {
    "gn:admin1_code":"09",
    "gn:asciiname":"Ait Bouzmane",
    "gn:country_code":"MA",
    "gn:dem":726,
    "gn:feature_class":"P",
    "gn:feature_code":"PPL",
    "gn:name":"A\u00eft Bouzmane",
    "gn:population":0,
    "gn:timezone":"Africa/Casablanca",
    "iso:country":"MA",
    "wof:name":"Ait Bouzmane",
    "wof:placetype":"locality"
},
  "geometry": {"coordinates":[-8.36761,30.51089],"type":"Point"}
}