{
  "type": "Feature",
  "properties": {
    "gn:admin1_code":"9.0",
    "gn:asciiname":"Tiymkhca",
    "gn:country_code":"MA",
    "gn:dem":945,
    "gn:feature_class":"P",
    "gn:feature_code":"PPL",
    "gn:name":"Tiymkhca",
    "gn:population":0,
    "gn:timezone":"Africa/Casablanca",
    "iso:country":"MA",
    "wof:name":"Tiymkhca",
    "wof:placetype":"locality"
},
  "geometry": {"coordinates":[-9.16991,29.6181],"type":"Point"}
}