{
  "type": "Feature",
  "properties": {
    "gn:admin1_code":"4.0",
    "gn:asciiname":"Douar Ait Ali Lahsene",
    "gn:country_code":"MA",
    "gn:dem":189,
    "gn:feature_class":"P",
    "gn:feature_code":"PPL",
    "gn:name":"Douar Ait Ali Lahsene",
    "gn:population":0,
    "gn:timezone":"Africa/Casablanca",
    "iso:country":"MA",
    "wof:name":"Douar Ait Ali Lahsene",
    "wof:placetype":"locality"
},
  "geometry": {"coordinates":[-6.51265,34.01081],"type":"Point"}
}