{
  "type": "Feature",
  "properties": {
    "gn:admin1_code":"6.0",
    "gn:asciiname":"Douar El Gharbaouiyine",
    "gn:country_code":"MA",
    "gn:dem":232,
    "gn:feature_class":"P",
    "gn:feature_code":"PPL",
    "gn:name":"Douar El Gharbaouiyine",
    "gn:population":0,
    "gn:timezone":"Africa/Casablanca",
    "iso:country":"MA",
    "wof:name":"Douar El Gharbaouiyine",
    "wof:placetype":"locality"
},
  "geometry": {"coordinates":[-8.16957,32.67769000000001],"type":"Point"}
}