{
  "type": "Feature",
  "properties": {
    "gn:admin1_code":"7.0",
    "gn:asciiname":"Douar Itlil",
    "gn:country_code":"MA",
    "gn:dem":525,
    "gn:feature_class":"P",
    "gn:feature_code":"PPL",
    "gn:name":"Douar Itlil",
    "gn:population":0,
    "gn:timezone":"Africa/Casablanca",
    "iso:country":"MA",
    "wof:name":"Douar Itlil",
    "wof:placetype":"locality"
},
  "geometry": {"coordinates":[-7.8773,32.32372],"type":"Point"}
}