{
  "type": "Feature",
  "properties": {
    "gn:admin1_code":"03",
    "gn:asciiname":"Dar Menaiad",
    "gn:country_code":"MA",
    "gn:dem":905,
    "gn:feature_class":"P",
    "gn:feature_code":"PPL",
    "gn:name":"Dar Mena\u00efad",
    "gn:population":0,
    "gn:timezone":"Africa/Casablanca",
    "iso:country":"MA",
    "name:und_x_variant":[
        "Douar Dar Mena\u00efad",
        "Dar Mena\u00efad"
    ],
    "wof:name":"Dar Menaiad",
    "wof:placetype":"locality"
},
  "geometry": {"coordinates":[-4.27637,34.36145],"type":"Point"}
}