{
  "type": "Feature",
  "properties": {
    "gn:admin1_code":"07",
    "gn:asciiname":"Toulkine",
    "gn:country_code":"MA",
    "gn:dem":1726,
    "gn:feature_class":"P",
    "gn:feature_code":"PPL",
    "gn:name":"Toulkine",
    "gn:population":0,
    "gn:timezone":"Africa/Casablanca",
    "iso:country":"MA",
    "wof:name":"Toulkine",
    "wof:placetype":"locality"
},
  "geometry": {"coordinates":[-8.32987,31.16182],"type":"Point"}
}