{
  "type": "Feature",
  "properties": {
    "gn:admin1_code":"07",
    "gn:asciiname":"Douar Errouabza",
    "gn:country_code":"MA",
    "gn:dem":512,
    "gn:feature_class":"P",
    "gn:feature_code":"PPL",
    "gn:name":"Douar Errouabza",
    "gn:population":0,
    "gn:timezone":"Africa/Casablanca",
    "iso:country":"MA",
    "name:und_x_variant":[
        "Oulad Abb\u00e8s",
        "Douar Abbes",
        "Dar Oulad La\u00efrabas",
        "Douar Errouabza"
    ],
    "wof:name":"Douar Errouabza",
    "wof:placetype":"locality"
},
  "geometry": {"coordinates":[-8.3216,31.95881],"type":"Point"}
}