{
  "type": "Feature",
  "properties": {
    "gn:admin1_code":"6.0",
    "gn:asciiname":"Douar El Mouissat",
    "gn:country_code":"MA",
    "gn:dem":187,
    "gn:feature_class":"P",
    "gn:feature_code":"PPL",
    "gn:name":"Douar El Mouissat",
    "gn:population":0,
    "gn:timezone":"Africa/Casablanca",
    "iso:country":"MA",
    "wof:name":"Douar El Mouissat",
    "wof:placetype":"locality"
},
  "geometry": {"coordinates":[-8.26854,33.04733],"type":"Point"}
}