{
  "type": "Feature",
  "properties": {
    "gn:admin1_code":"7.0",
    "gn:asciiname":"Douar Lakbir",
    "gn:country_code":"MA",
    "gn:dem":405,
    "gn:feature_class":"P",
    "gn:feature_code":"PPL",
    "gn:name":"Douar Lakbir",
    "gn:population":0,
    "gn:timezone":"Africa/Casablanca",
    "iso:country":"MA",
    "wof:name":"Douar Lakbir",
    "wof:placetype":"locality"
},
  "geometry": {"coordinates":[-8.82307,31.98283],"type":"Point"}
}