{
  "type": "Feature",
  "properties": {
    "gn:admin1_code":"09",
    "gn:asciiname":"Id Aissa",
    "gn:country_code":"MA",
    "gn:dem":286,
    "gn:feature_class":"P",
    "gn:feature_code":"PPL",
    "gn:name":"Id A\u00efssa",
    "gn:population":0,
    "gn:timezone":"Africa/Casablanca",
    "iso:country":"MA",
    "name:und_x_variant":[
        "Id \u2019Issa",
        "Id A\u00efssa"
    ],
    "wof:name":"Id Aissa",
    "wof:placetype":"locality"
},
  "geometry": {"coordinates":[-9.83938,29.74767],"type":"Point"}
}