{
  "type": "Feature",
  "properties": {
    "gn:admin1_code":"1.0",
    "gn:asciiname":"Essikha",
    "gn:country_code":"MA",
    "gn:dem":366,
    "gn:feature_class":"P",
    "gn:feature_code":"PPL",
    "gn:name":"Essikha",
    "gn:population":0,
    "gn:timezone":"Africa/Casablanca",
    "iso:country":"MA",
    "wof:name":"Essikha",
    "wof:placetype":"locality"
},
  "geometry": {"coordinates":[-5.12726,34.78463],"type":"Point"}
}