{
  "type": "Feature",
  "properties": {
    "gn:admin1_code":"4.0",
    "gn:asciiname":"Dar Mohamed Ben Ali",
    "gn:country_code":"MA",
    "gn:dem":49,
    "gn:feature_class":"P",
    "gn:feature_code":"PPL",
    "gn:name":"Dar Mohamed Ben Ali",
    "gn:population":0,
    "gn:timezone":"Africa/Casablanca",
    "iso:country":"MA",
    "wof:name":"Dar Mohamed Ben Ali",
    "wof:placetype":"locality"
},
  "geometry": {"coordinates":[-6.22144,34.80713],"type":"Point"}
}