{
  "type": "Feature",
  "properties": {
    "gn:admin1_code":"7.0",
    "gn:asciiname":"El Azzaba",
    "gn:country_code":"MA",
    "gn:dem":506,
    "gn:feature_class":"P",
    "gn:feature_code":"PPL",
    "gn:name":"El Azzaba",
    "gn:population":0,
    "gn:timezone":"Africa/Casablanca",
    "iso:country":"MA",
    "wof:name":"El Azzaba",
    "wof:placetype":"locality"
},
  "geometry": {"coordinates":[-7.93149,32.41642],"type":"Point"}
}