{
  "type": "Feature",
  "properties": {
    "gn:admin1_code":"04",
    "gn:asciiname":"Douar Lehmoumiine",
    "gn:country_code":"MA",
    "gn:dem":35,
    "gn:feature_class":"P",
    "gn:feature_code":"PPL",
    "gn:name":"Douar Lehmoumiine",
    "gn:population":0,
    "gn:timezone":"Africa/Casablanca",
    "iso:country":"MA",
    "name:und_x_variant":[
        "Lehmouniine",
        "Lahminine",
        "Douar Lehmoumiine"
    ],
    "wof:name":"Douar Lehmoumiine",
    "wof:placetype":"locality"
},
  "geometry": {"coordinates":[-5.68326,34.57471],"type":"Point"}
}