{
  "type": "Feature",
  "properties": {
    "gn:admin1_code":"01",
    "gn:asciiname":"Oulad el Haj",
    "gn:country_code":"MA",
    "gn:dem":1171,
    "gn:feature_class":"P",
    "gn:feature_code":"PPL",
    "gn:name":"Oulad el Haj",
    "gn:population":0,
    "gn:timezone":"Africa/Casablanca",
    "iso:country":"MA",
    "name:und_x_variant":[
        "Ulad el Hach",
        "Oulad el Hach",
        "Oulad el Haj"
    ],
    "wof:name":"Oulad el Haj",
    "wof:placetype":"locality"
},
  "geometry": {"coordinates":[-5.16255,35.17055999999999],"type":"Point"}
}