{
  "type": "Feature",
  "properties": {
    "gn:country":"MA",
    "gn:fcode":"ADM3",
    "gn:population":2817,
    "iso:country":"MA",
    "name:ara_x_preferred":[
        "\u062a\u0632\u0645\u0648\u0631\u062a"
    ],
    "name:ceb_x_preferred":[
        "Tiout"
    ],
    "name:fra_x_preferred":[
        "Tiout"
    ],
    "name:fra_x_variant":[
        "Tiout (CR)",
        "Tiout (Commune Rurale)"
    ],
    "name:msa_x_preferred":[
        "Tiout"
    ],
    "name:swe_x_preferred":[
        "Tiout"
    ],
    "qs:name":"Tiout",
    "qs:photos_9r":0,
    "qs:photos_sr":0,
    "qs:pop_sr":"4",
    "wd:wordcount":8,
    "wof:name":"Tiout",
    "wof:placetype":"localadmin",
    "wof:population":2817
},
  "geometry": {"coordinates":[-8.66904,30.41342],"type":"Point"}
}