{
  "type": "Feature",
  "properties": {
    "gn:admin1_code":"2.0",
    "gn:asciiname":"Douar Zkhanine",
    "gn:country_code":"MA",
    "gn:dem":31,
    "gn:feature_class":"P",
    "gn:feature_code":"PPL",
    "gn:name":"Douar Zkhanine",
    "gn:population":0,
    "gn:timezone":"Africa/Casablanca",
    "iso:country":"MA",
    "wof:name":"Douar Zkhanine",
    "wof:placetype":"locality"
},
  "geometry": {"coordinates":[-2.41792,35.04906],"type":"Point"}
}