{
  "type": "Feature",
  "properties": {
    "gn:admin1_code":"07",
    "gn:asciiname":"Mesdi",
    "gn:country_code":"MA",
    "gn:dem":1245,
    "gn:feature_class":"P",
    "gn:feature_code":"PPL",
    "gn:name":"Mesdi",
    "gn:population":0,
    "gn:timezone":"Africa/Casablanca",
    "iso:country":"MA",
    "wof:name":"Mesdi",
    "wof:placetype":"locality"
},
  "geometry": {"coordinates":[-9.09706,31.18227000000001],"type":"Point"}
}