{
  "type": "Feature",
  "properties": {
    "gn:admin1_code":"8.0",
    "gn:asciiname":"Bni Moussi",
    "gn:country_code":"MA",
    "gn:dem":984,
    "gn:feature_class":"P",
    "gn:feature_code":"PPL",
    "gn:name":"Bni Moussi",
    "gn:population":0,
    "gn:timezone":"Africa/Casablanca",
    "iso:country":"MA",
    "wof:name":"Bni Moussi",
    "wof:placetype":"locality"
},
  "geometry": {"coordinates":[-4.32249,31.88796],"type":"Point"}
}