{
  "type": "Feature",
  "properties": {
    "gn:admin1_code":"7.0",
    "gn:asciiname":"Laqwam",
    "gn:country_code":"MA",
    "gn:dem":628,
    "gn:feature_class":"P",
    "gn:feature_code":"PPL",
    "gn:name":"Laqwam",
    "gn:population":0,
    "gn:timezone":"Africa/Casablanca",
    "iso:country":"MA",
    "wof:name":"Laqwam",
    "wof:placetype":"locality"
},
  "geometry": {"coordinates":[-7.45948,31.75156],"type":"Point"}
}