{
  "type": "Feature",
  "properties": {
    "gn:admin1_code":"9.0",
    "gn:asciiname":"Ait Al Moudn",
    "gn:country_code":"MA",
    "gn:dem":623,
    "gn:feature_class":"P",
    "gn:feature_code":"PPL",
    "gn:name":"Ait Al Moudn",
    "gn:population":0,
    "gn:timezone":"Africa/Casablanca",
    "iso:country":"MA",
    "wof:name":"Ait Al Moudn",
    "wof:placetype":"locality"
},
  "geometry": {"coordinates":[-9.219,29.99455],"type":"Point"}
}