{
  "type": "Feature",
  "properties": {
    "gn:admin1_code":"7.0",
    "gn:asciiname":"Oulad Ba Rahhal",
    "gn:country_code":"MA",
    "gn:dem":581,
    "gn:feature_class":"P",
    "gn:feature_code":"PPL",
    "gn:name":"Oulad Ba Rahhal",
    "gn:population":0,
    "gn:timezone":"Africa/Casablanca",
    "iso:country":"MA",
    "wof:name":"Oulad Ba Rahhal",
    "wof:placetype":"locality"
},
  "geometry": {"coordinates":[-7.44295,31.86584],"type":"Point"}
}