{
  "type": "Feature",
  "properties": {
    "gn:country":"MA",
    "gn:fcode":"ADM3",
    "gn:population":8830,
    "iso:country":"MA",
    "name:ara_x_preferred":[
        "\u062a\u0648\u0632\u064a\u0646\u062a"
    ],
    "name:ara_x_variant":[
        "\u0627\u0632\u0646\u0627\u062f\u0629"
    ],
    "name:cat_x_preferred":[
        "Znada"
    ],
    "name:ceb_x_preferred":[
        "Znada"
    ],
    "name:eng_x_preferred":[
        "Znada"
    ],
    "name:fas_x_preferred":[
        "\u0632\u0646\u0627\u062f\u0627"
    ],
    "name:fra_x_preferred":[
        "Znada"
    ],
    "name:fra_x_variant":[
        "Znada (CR)",
        "Znada (Commune Rurale)"
    ],
    "name:ita_x_preferred":[
        "Znada"
    ],
    "name:swe_x_preferred":[
        "Znada"
    ],
    "qs:name":"Znada",
    "qs:photos_9r":0,
    "qs:photos_sr":0,
    "qs:pop_sr":"5",
    "wd:wordcount":81,
    "wof:name":"Znada",
    "wof:placetype":"localadmin",
    "wof:population":8830
},
  "geometry": {"coordinates":[-7.37165,32.05329],"type":"Point"}
}