{
  "type": "Feature",
  "properties": {
    "gn:admin1_code":"3.0",
    "gn:asciiname":"Douar Kseb",
    "gn:country_code":"MA",
    "gn:dem":409,
    "gn:feature_class":"P",
    "gn:feature_code":"PPL",
    "gn:name":"Douar Kseb",
    "gn:population":0,
    "gn:timezone":"Africa/Casablanca",
    "iso:country":"MA",
    "wof:name":"Douar Kseb",
    "wof:placetype":"locality"
},
  "geometry": {"coordinates":[-5.15934,34.48714],"type":"Point"}
}