{
  "type": "Feature",
  "properties": {
    "gn:admin1_code":"3.0",
    "gn:asciiname":"Douar Doumat Zmim",
    "gn:country_code":"MA",
    "gn:dem":316,
    "gn:feature_class":"P",
    "gn:feature_code":"PPL",
    "gn:name":"Douar Doumat Zmim",
    "gn:population":0,
    "gn:timezone":"Africa/Casablanca",
    "iso:country":"MA",
    "wof:name":"Douar Doumat Zmim",
    "wof:placetype":"locality"
},
  "geometry": {"coordinates":[-4.3538,34.17074],"type":"Point"}
}