{
  "type": "Feature",
  "properties": {
    "gn:admin1_code":"10",
    "gn:asciiname":"Id Boubker",
    "gn:country_code":"MA",
    "gn:dem":1309,
    "gn:feature_class":"P",
    "gn:feature_code":"PPL",
    "gn:name":"Id Boubker",
    "gn:population":0,
    "gn:timezone":"Africa/Casablanca",
    "iso:country":"MA",
    "name:und_x_variant":[
        "Id Boubaker",
        "Id Boubker"
    ],
    "wof:name":"Id Boubker",
    "wof:placetype":"locality"
},
  "geometry": {"coordinates":[-9.39576,29.34577],"type":"Point"}
}