{
  "type": "Feature",
  "properties": {
    "gn:admin1_code":"02",
    "gn:asciiname":"Douar Imarchouchene",
    "gn:country_code":"MA",
    "gn:dem":53,
    "gn:feature_class":"P",
    "gn:feature_code":"PPL",
    "gn:name":"Douar Imarchouchene",
    "gn:population":0,
    "gn:timezone":"Africa/Casablanca",
    "iso:country":"MA",
    "wof:name":"Douar Imarchouchene",
    "wof:placetype":"locality"
},
  "geometry": {"coordinates":[-3.78113,35.17871],"type":"Point"}
}