{
  "type": "Feature",
  "properties": {
    "gn:admin1_code":"02",
    "gn:asciiname":"Douar 'Ali Jdid",
    "gn:country_code":"MA",
    "gn:dem":1433,
    "gn:feature_class":"P",
    "gn:feature_code":"PPL",
    "gn:name":"Douar \u2019Ali Jdid",
    "gn:population":0,
    "gn:timezone":"Africa/Casablanca",
    "iso:country":"MA",
    "name:und_x_variant":[
        "Douar \u2019Ali Jdid",
        "Ali Ou Jdid"
    ],
    "wof:name":"Douar 'Ali Jdid",
    "wof:placetype":"locality"
},
  "geometry": {"coordinates":[-3.30894,32.69517],"type":"Point"}
}