{
  "type": "Feature",
  "properties": {
    "gn:admin1_code":"03",
    "gn:asciiname":"Beni Ammer",
    "gn:country_code":"MA",
    "gn:dem":315,
    "gn:feature_class":"P",
    "gn:feature_code":"PPL",
    "gn:name":"Beni Ammer",
    "gn:population":0,
    "gn:timezone":"Africa/Casablanca",
    "iso:country":"MA",
    "name:und_x_variant":[
        "Douar Oulad Beni Amar",
        "Oulad Beni Ammar",
        "Beni Ammer"
    ],
    "wof:name":"Beni Ammer",
    "wof:placetype":"locality"
},
  "geometry": {"coordinates":[-4.99847,34.44352],"type":"Point"}
}