{
  "type": "Feature",
  "properties": {
    "gn:country":"MA",
    "gn:fcode":"ADM3",
    "gn:population":8319,
    "iso:country":"MA",
    "name:ara_x_preferred":[
        "\u0627\u0644\u0635\u0641\u0627\u0641\u0639\u0629"
    ],
    "name:ara_x_variant":[
        "\u0632\u064a\u0631\u0627\u0631\u0629"
    ],
    "name:cat_x_preferred":[
        "Zirara"
    ],
    "name:fra_x_preferred":[
        "Zirara"
    ],
    "name:fra_x_variant":[
        "Zirara (CR)",
        "Zirara (Commune Rurale)"
    ],
    "name:ita_x_preferred":[
        "Zirara"
    ],
    "name:urd_x_preferred":[
        "\u0632\u06cc\u0631\u0627\u0631\u06c1"
    ],
    "qs:name":"Zirara",
    "qs:photos_9r":0,
    "qs:photos_sr":0,
    "qs:pop_sr":"5",
    "wd:wordcount":50,
    "wof:name":"Zirara",
    "wof:placetype":"localadmin",
    "wof:population":8319
},
  "geometry": {"coordinates":[-5.74727,34.22791],"type":"Point"}
}