{
  "type": "Feature",
  "properties": {
    "gn:admin1_code":"7.0",
    "gn:asciiname":"Laqtib",
    "gn:country_code":"MA",
    "gn:dem":458,
    "gn:feature_class":"P",
    "gn:feature_code":"PPL",
    "gn:name":"Laqtib",
    "gn:population":0,
    "gn:timezone":"Africa/Casablanca",
    "iso:country":"MA",
    "wof:name":"Laqtib",
    "wof:placetype":"locality"
},
  "geometry": {"coordinates":[-8.00928,32.2081],"type":"Point"}
}