{
  "type": "Feature",
  "properties": {
    "gn:country":"MA",
    "gn:fcode":"ADM3",
    "gn:population":4773,
    "iso:country":"MA",
    "name:ara_x_preferred":[
        "\u062a\u0627\u0644\u0643\u062c\u0648\u0646\u062a"
    ],
    "name:ara_x_variant":[
        "\u062a\u064a\u06ad\u0648\u06ad\u0629"
    ],
    "name:cat_x_preferred":[
        "Tigouga"
    ],
    "name:eng_x_preferred":[
        "Tigouga"
    ],
    "name:fra_x_preferred":[
        "Tigouga"
    ],
    "name:fra_x_variant":[
        "Tigouga (CR)",
        "Tigouga (Commune Rurale)"
    ],
    "name:ita_x_preferred":[
        "Tigouga"
    ],
    "qs:name":"Tigouga",
    "qs:photos_9r":0,
    "qs:photos_sr":0,
    "qs:pop_sr":"4",
    "wd:wordcount":60,
    "wof:name":"Tigouga",
    "wof:placetype":"localadmin",
    "wof:population":4773
},
  "geometry": {"coordinates":[-8.61251,30.83539],"type":"Point"}
}