{
  "type": "Feature",
  "properties": {
    "gn:country":"MA",
    "gn:fcode":"ADM3",
    "gn:population":5020,
    "iso:country":"MA",
    "name:ara_x_preferred":[
        "\u0623\u0645 \u0627\u062f\u0631\u064a\u0643\u0629"
    ],
    "name:ara_x_variant":[
        "\u0627\u0644\u0639\u0631\u0643\u0648\u0628"
    ],
    "name:bar_x_preferred":[
        "El Argoub"
    ],
    "name:bul_x_preferred":[
        "\u0410\u0440\u0433\u0443\u0431"
    ],
    "name:cat_x_preferred":[
        "Argub"
    ],
    "name:deu_x_preferred":[
        "El Argoub"
    ],
    "name:fra_x_preferred":[
        "El Argoub"
    ],
    "name:fra_x_variant":[
        "El Argoub (CR)",
        "El Argoub (Commune Rurale)"
    ],
    "name:ita_x_preferred":[
        "El Argoub"
    ],
    "qs_pg:aaroncc":"MA",
    "qs_pg:gn_country":"MA",
    "qs_pg:gn_fcode":"ADM3",
    "qs_pg:gn_pop":5020,
    "qs_pg:name":"El Argoub",
    "qs_pg:photos_9r":0,
    "qs_pg:photos_sr":0,
    "qs_pg:pop_sr":5,
    "qs_pg:qs_pg_placetype":"localadmin",
    "wof:name":"El Argoub",
    "wof:placetype":"localadmin",
    "wof:population":5020
},
  "geometry": {"coordinates":[-15.26972,23.71008],"type":"Point"}
}