{
  "type": "Feature",
  "properties": {
    "gn:admin1_code":"09",
    "gn:asciiname":"Ait Yahya",
    "gn:country_code":"MA",
    "gn:dem":530,
    "gn:feature_class":"P",
    "gn:feature_code":"PPL",
    "gn:name":"A\u00eft Yahya",
    "gn:population":0,
    "gn:timezone":"Africa/Casablanca",
    "iso:country":"MA",
    "wof:name":"Ait Yahya",
    "wof:placetype":"locality"
},
  "geometry": {"coordinates":[-9.24108,29.91194],"type":"Point"}
}