{
  "type": "Feature",
  "properties": {
    "gn:admin1_code":"1.0",
    "gn:asciiname":"Cooperative Louafaa",
    "gn:country_code":"MA",
    "gn:dem":67,
    "gn:feature_class":"P",
    "gn:feature_code":"PPLF",
    "gn:name":"Coop\u00e9rative Louafaa",
    "gn:population":0,
    "gn:timezone":"Africa/Casablanca",
    "iso:country":"MA",
    "wof:name":"Cooperative Louafaa",
    "wof:placetype":"locality"
},
  "geometry": {"coordinates":[-6.14553,35.05599],"type":"Point"}
}