{
  "type": "Feature",
  "properties": {
    "gn:admin1_code":"3.0",
    "gn:asciiname":"Mechraa Lahmir",
    "gn:country_code":"MA",
    "gn:dem":1678,
    "gn:feature_class":"P",
    "gn:feature_code":"PPL",
    "gn:name":"Mechraa Lahmir",
    "gn:population":0,
    "gn:timezone":"Africa/Casablanca",
    "iso:country":"MA",
    "wof:name":"Mechraa Lahmir",
    "wof:placetype":"locality"
},
  "geometry": {"coordinates":[-4.98966,33.55876],"type":"Point"}
}