{
  "type": "Feature",
  "properties": {
    "gn:admin1_code":"7.0",
    "gn:asciiname":"Ait Bouyzakdane",
    "gn:country_code":"MA",
    "gn:dem":1223,
    "gn:feature_class":"P",
    "gn:feature_code":"PPL",
    "gn:name":"A\u00eft Bouyzakdane",
    "gn:population":0,
    "gn:timezone":"Africa/Casablanca",
    "iso:country":"MA",
    "wof:name":"Ait Bouyzakdane",
    "wof:placetype":"locality"
},
  "geometry": {"coordinates":[-7.63787,31.42252],"type":"Point"}
}