{
  "type": "Feature",
  "properties": {
    "gn:admin1_code":"1.0",
    "gn:asciiname":"Douar Ben Hallou Essoufli",
    "gn:country_code":"MA",
    "gn:dem":89,
    "gn:feature_class":"P",
    "gn:feature_code":"PPL",
    "gn:name":"Douar Ben Hallou Essoufli",
    "gn:population":0,
    "gn:timezone":"Africa/Casablanca",
    "iso:country":"MA",
    "wof:name":"Douar Ben Hallou Essoufli",
    "wof:placetype":"locality"
},
  "geometry": {"coordinates":[-5.51595,35.65368],"type":"Point"}
}