{
  "type": "Feature",
  "properties": {
    "gn:admin1_code":"03",
    "gn:asciiname":"Douar Labrareq",
    "gn:country_code":"MA",
    "gn:dem":385,
    "gn:feature_class":"P",
    "gn:feature_code":"PPL",
    "gn:name":"Douar Labrareq",
    "gn:population":0,
    "gn:timezone":"Africa/Casablanca",
    "iso:country":"MA",
    "name:und_x_variant":[
        "Douar Brarak",
        "Brarak",
        "Douar Labrareq"
    ],
    "wof:name":"Douar Labrareq",
    "wof:placetype":"locality"
},
  "geometry": {"coordinates":[-4.26787,34.17177],"type":"Point"}
}