{
  "type": "Feature",
  "properties": {
    "gn:admin1_code":"05",
    "gn:asciiname":"Assmanda",
    "gn:country_code":"MA",
    "gn:dem":620,
    "gn:feature_class":"P",
    "gn:feature_code":"PPL",
    "gn:name":"Assmanda",
    "gn:population":0,
    "gn:timezone":"Africa/Casablanca",
    "iso:country":"MA",
    "name:und_x_variant":[
        "Es Smamra"
    ],
    "wof:name":"Assmanda",
    "wof:placetype":"locality"
},
  "geometry": {"coordinates":[-6.95897,32.73664],"type":"Point"}
}