{
  "type": "Feature",
  "properties": {
    "gn:admin1_code":"10",
    "gn:asciiname":"Ioutlane",
    "gn:country_code":"MA",
    "gn:dem":179,
    "gn:feature_class":"P",
    "gn:feature_code":"PPL",
    "gn:name":"Ioutlane",
    "gn:population":0,
    "gn:timezone":"Africa/Casablanca",
    "iso:country":"MA",
    "name:und_x_variant":[
        "Iutlar",
        "Iutlan",
        "Ioutlane"
    ],
    "wof:name":"Ioutlane",
    "wof:placetype":"locality"
},
  "geometry": {"coordinates":[-10.23379,29.01431],"type":"Point"}
}