{
  "type": "Feature",
  "properties": {
    "gn:admin1_code":"06",
    "gn:asciiname":"Douar Slamna",
    "gn:country_code":"MA",
    "gn:dem":87,
    "gn:feature_class":"P",
    "gn:feature_code":"PPL",
    "gn:name":"Douar Slamna",
    "gn:population":0,
    "gn:timezone":"Africa/Casablanca",
    "iso:country":"MA",
    "name:und_x_variant":[
        "Slamna",
        "Douar Slama",
        "Douar Slamna"
    ],
    "wof:name":"Douar Slamna",
    "wof:placetype":"locality"
},
  "geometry": {"coordinates":[-8.29082,33.22527],"type":"Point"}
}