{
  "type": "Feature",
  "properties": {
    "gn:admin1_code":"9.0",
    "gn:asciiname":"Amalou",
    "gn:country_code":"MA",
    "gn:dem":576,
    "gn:feature_class":"P",
    "gn:feature_code":"PPL",
    "gn:name":"Amalou",
    "gn:population":0,
    "gn:timezone":"Africa/Casablanca",
    "iso:country":"MA",
    "wof:name":"Amalou",
    "wof:placetype":"locality"
},
  "geometry": {"coordinates":[-9.87552,29.46128],"type":"Point"}
}