{
  "type": "Feature",
  "properties": {
    "gn:country":"MA",
    "gn:fcode":"ADM3",
    "gn:population":13931,
    "iso:country":"MA",
    "name:ara_x_preferred":[
        "\u0639\u062f\u0631\u062c"
    ],
    "name:fra_x_preferred":[
        "Laajajra"
    ],
    "name:fra_x_variant":[
        "Laajajra (CR)",
        "Laajajra (Commune Rurale)"
    ],
    "qs:name":"Laajajra",
    "qs:photos_9r":0,
    "qs:photos_sr":0,
    "qs:pop_sr":"6",
    "wof:name":"Laajajra",
    "wof:placetype":"localadmin",
    "wof:population":13931
},
  "geometry": {"coordinates":[-5.15385,34.18527],"type":"Point"}
}