{
  "type": "Feature",
  "properties": {
    "gn:admin1_code":"9.0",
    "gn:asciiname":"Taourirt Ou Jbara",
    "gn:country_code":"MA",
    "gn:dem":522,
    "gn:feature_class":"P",
    "gn:feature_code":"PPL",
    "gn:name":"Taourirt Ou Jbara",
    "gn:population":0,
    "gn:timezone":"Africa/Casablanca",
    "iso:country":"MA",
    "wof:name":"Taourirt Ou Jbara",
    "wof:placetype":"locality"
},
  "geometry": {"coordinates":[-9.20416,30.07391],"type":"Point"}
}