{
  "type": "Feature",
  "properties": {
    "gn:admin1_code":"09",
    "gn:asciiname":"Ibakizene",
    "gn:country_code":"MA",
    "gn:dem":1857,
    "gn:feature_class":"P",
    "gn:feature_code":"PPL",
    "gn:name":"Ibakizene",
    "gn:population":0,
    "gn:timezone":"Africa/Casablanca",
    "iso:country":"MA",
    "name:und_x_variant":[
        "Ibakiz\u00e8n",
        "Ibakizene"
    ],
    "wof:name":"Ibakizene",
    "wof:placetype":"locality"
},
  "geometry": {"coordinates":[-8.16065,30.17102],"type":"Point"}
}