{
  "type": "Feature",
  "properties": {
    "gn:admin1_code":"4.0",
    "gn:asciiname":"Bahharet Oulad Moussa",
    "gn:country_code":"MA",
    "gn:dem":10,
    "gn:feature_class":"P",
    "gn:feature_code":"PPL",
    "gn:name":"Bahharet Oulad Moussa",
    "gn:population":0,
    "gn:timezone":"Africa/Casablanca",
    "iso:country":"MA",
    "wof:name":"Bahharet Oulad Moussa",
    "wof:placetype":"locality"
},
  "geometry": {"coordinates":[-6.3685,34.70406],"type":"Point"}
}