{
  "type": "Feature",
  "properties": {
    "gn:admin1_code":"1.0",
    "gn:asciiname":"Zedmet El Oulya",
    "gn:country_code":"MA",
    "gn:dem":404,
    "gn:feature_class":"P",
    "gn:feature_code":"PPL",
    "gn:name":"Zedmet El Oulya",
    "gn:population":0,
    "gn:timezone":"Africa/Casablanca",
    "iso:country":"MA",
    "wof:name":"Zedmet El Oulya",
    "wof:placetype":"locality"
},
  "geometry": {"coordinates":[-4.71411,35.12601],"type":"Point"}
}