{
  "type": "Feature",
  "properties": {
    "gn:admin1_code":"7.0",
    "gn:asciiname":"Oulad El Houssine",
    "gn:country_code":"MA",
    "gn:dem":430,
    "gn:feature_class":"P",
    "gn:feature_code":"PPL",
    "gn:name":"Oulad El Houssine",
    "gn:population":0,
    "gn:timezone":"Africa/Casablanca",
    "iso:country":"MA",
    "wof:name":"Oulad El Houssine",
    "wof:placetype":"locality"
},
  "geometry": {"coordinates":[-8.80271,32.16342],"type":"Point"}
}