{
  "type": "Feature",
  "properties": {
    "gn:gn_country":"MA",
    "gn:gn_fcode":"ADM3",
    "gn:gn_pop":11113,
    "gn:population":11113,
    "iso:country":"MA",
    "name:ara_x_preferred":[
        "\u0643\u062f\u064a\u0629 \u0628\u0646\u064a \u062f\u063a\u0648\u063a"
    ],
    "name:ara_x_variant":[
        "\u0643\u0631\u062f\u064a\u062f"
    ],
    "name:azb_x_preferred":[
        "\u06a9\u0631\u062f\u06cc\u062f"
    ],
    "name:cat_x_preferred":[
        "Kridid"
    ],
    "name:ceb_x_preferred":[
        "Kridid"
    ],
    "name:fas_x_preferred":[
        "\u06a9\u0631\u062f\u06cc\u062f"
    ],
    "name:fra_x_preferred":[
        "Kridid"
    ],
    "name:fra_x_variant":[
        "Kridid (CR)",
        "Kridid (Commune Rurale)"
    ],
    "name:ita_x_preferred":[
        "Kridid"
    ],
    "name:swe_x_preferred":[
        "Kridid"
    ],
    "qs_pg:aaroncc":"MA",
    "qs_pg:gn_country":"MA",
    "qs_pg:gn_fcode":"ADM3",
    "qs_pg:gn_pop":11113,
    "qs_pg:name":"Kridid",
    "qs_pg:photos_9r":0,
    "qs_pg:photos_sr":0,
    "qs_pg:pop_sr":6,
    "qs_pg:qs_pg_placetype":"localadmin",
    "wof:name":"Kridid",
    "wof:placetype":"localadmin",
    "wof:population":11113
},
  "geometry": {"coordinates":[-8.60015,32.49701],"type":"Point"}
}