{
  "type": "Feature",
  "properties": {
    "gn:admin1_code":"02",
    "gn:asciiname":"Beni Bou Mediene",
    "gn:country_code":"MA",
    "gn:dem":281,
    "gn:feature_class":"P",
    "gn:feature_code":"PPL",
    "gn:name":"Beni Bou Mediene",
    "gn:population":0,
    "gn:timezone":"Africa/Casablanca",
    "iso:country":"MA",
    "name:und_x_variant":[
        "Beni bou Mediena",
        "Beni-Bu-Medien",
        "Beni Bou Mediene"
    ],
    "wof:name":"Beni Bou Mediene",
    "wof:placetype":"locality"
},
  "geometry": {"coordinates":[-3.66061,35.12524000000001],"type":"Point"}
}