{
  "type": "Feature",
  "properties": {
    "gn:admin1_code":"7.0",
    "gn:asciiname":"Dar Mohamed Chakli",
    "gn:country_code":"MA",
    "gn:dem":427,
    "gn:feature_class":"P",
    "gn:feature_code":"PPL",
    "gn:name":"Dar Mohamed Chakli",
    "gn:population":0,
    "gn:timezone":"Africa/Casablanca",
    "iso:country":"MA",
    "wof:name":"Dar Mohamed Chakli",
    "wof:placetype":"locality"
},
  "geometry": {"coordinates":[-7.73714,32.16409],"type":"Point"}
}