{
  "type": "Feature",
  "properties": {
    "gn:country":"MA",
    "gn:fcode":"ADM3",
    "gn:pop":14706,
    "iso:country":"MA",
    "name:ara_x_preferred":[
        "\u0632\u0648\u0645\u064a"
    ],
    "name:fra_x_preferred":[
        "Anjra"
    ],
    "name:fra_x_variant":[
        "Anjra (CR)",
        "Anjra (Commune Rurale)"
    ],
    "qs:name":"Anjra",
    "qs:photos_9r":0,
    "qs:photos_sr":0,
    "qs:pop_sr":"6",
    "wd:wordcount":78,
    "wof:name":"Anjra",
    "wof:placetype":"localadmin",
    "wof:population":14706
},
  "geometry": {"coordinates":[-5.53814,35.69254],"type":"Point"}
}