{
  "type": "Feature",
  "properties": {
    "gn:country":"MA",
    "gn:fcode":"ADM3",
    "gn:population":14706,
    "iso:country":"MA",
    "name:ara_x_preferred":[
        "\u0632\u0648\u0645\u064a"
    ],
    "name:ara_x_variant":[
        "\u0623\u0646\u062c\u0631\u0629"
    ],
    "name:azb_x_preferred":[
        "\u0627\u0646\u062c\u0631\u0647"
    ],
    "name:cat_x_preferred":[
        "Anjra"
    ],
    "name:eng_x_preferred":[
        "Anjra"
    ],
    "name:fas_x_preferred":[
        "\u0627\u0646\u062c\u0631\u0647"
    ],
    "name:fra_x_preferred":[
        "Anjra"
    ],
    "name:fra_x_variant":[
        "Anjra (CR)",
        "Anjra (Commune Rurale)"
    ],
    "name:ita_x_preferred":[
        "Anjra"
    ],
    "name:jpn_x_preferred":[
        "\u30a2\u30f3\u30b8\u30e5\u30e9"
    ],
    "name:spa_x_preferred":[
        "Anjra"
    ],
    "name:swe_x_preferred":[
        "Anjra"
    ],
    "name:urd_x_preferred":[
        "\u0627\u0646\u062c\u0631\u06c1"
    ],
    "name:zho_x_preferred":[
        "\u5b89\u5091\u62c9_(\u6469\u6d1b\u54e5)"
    ],
    "qs:name":"Anjra",
    "qs:photos_9r":0,
    "qs:photos_sr":0,
    "qs:pop_sr":"6",
    "wd:wordcount":78,
    "wof:name":"Anjra",
    "wof:placetype":"localadmin",
    "wof:population":14706
},
  "geometry": {"coordinates":[-5.53814,35.69254],"type":"Point"}
}