{
  "type": "Feature",
  "properties": {
    "gn:admin1_code":"07",
    "gn:asciiname":"Douar Oulad Abdellah",
    "gn:country_code":"MA",
    "gn:dem":266,
    "gn:feature_class":"P",
    "gn:feature_code":"PPL",
    "gn:name":"Douar Oulad Abdellah",
    "gn:population":0,
    "gn:timezone":"Africa/Casablanca",
    "iso:country":"MA",
    "name:und_x_variant":[
        "Oulad Abdallah"
    ],
    "wof:name":"Douar Oulad Abdellah",
    "wof:placetype":"locality"
},
  "geometry": {"coordinates":[-8.60596,31.78205],"type":"Point"}
}