{
  "type": "Feature",
  "properties": {
    "gn:admin1_code":"2.0",
    "gn:asciiname":"Station des Essais M.V.A.",
    "gn:country_code":"MA",
    "gn:dem":89,
    "gn:feature_class":"P",
    "gn:feature_code":"PPL",
    "gn:name":"Station des Essais M.V.A.",
    "gn:population":0,
    "gn:timezone":"Africa/Casablanca",
    "iso:country":"MA",
    "name:und_x_variant":[
        "Boughriba"
    ],
    "wof:name":"Station des Essais M.V.A.",
    "wof:placetype":"locality"
},
  "geometry": {"coordinates":[-2.4923,34.90654],"type":"Point"}
}