{
  "type": "Feature",
  "properties": {
    "gn:admin1_code":"07",
    "gn:asciiname":"Oulad Tagra",
    "gn:country_code":"MA",
    "gn:dem":209,
    "gn:feature_class":"P",
    "gn:feature_code":"PPL",
    "gn:name":"Oulad Tagra",
    "gn:population":0,
    "gn:timezone":"Africa/Casablanca",
    "iso:country":"MA",
    "name:und_x_variant":[
        "Douar Oulad Sidi Tahar",
        "Oulad Sidi Tahar",
        "Oulad Tagra"
    ],
    "wof:name":"Oulad Tagra",
    "wof:placetype":"locality"
},
  "geometry": {"coordinates":[-8.64798,32.40222],"type":"Point"}
}