{
  "type": "Feature",
  "properties": {
    "gn:country":"MA",
    "gn:fcode":"ADM3",
    "gn:population":9449,
    "iso:country":"MA",
    "name:ara_x_preferred":[
        "\u0643\u062f\u0627\u0646\u0629"
    ],
    "name:ara_x_variant":[
        "\u0643\u064a\u0633\u0631"
    ],
    "name:bul_x_preferred":[
        "\u0413\u0443\u0438\u0441\u0435\u0440"
    ],
    "name:cat_x_preferred":[
        "Guisser"
    ],
    "name:ceb_x_preferred":[
        "Guisser"
    ],
    "name:eng_x_preferred":[
        "Guisser"
    ],
    "name:fra_x_preferred":[
        "Guisser"
    ],
    "name:fra_x_variant":[
        "Guisser (CR)",
        "Guisser (Commune Rurale)"
    ],
    "name:ita_x_preferred":[
        "Guisser"
    ],
    "name:nld_x_preferred":[
        "Guisser"
    ],
    "name:swe_x_preferred":[
        "Guisser"
    ],
    "qs:name":"Guisser",
    "qs:photos_9r":0,
    "qs:photos_sr":0,
    "qs:pop_sr":"5",
    "wd:wordcount":48,
    "wof:name":"Guisser",
    "wof:placetype":"localadmin",
    "wof:population":9449
},
  "geometry": {"coordinates":[-7.49419,32.77205],"type":"Point"}
}