{
  "type": "Feature",
  "properties": {
    "gn:admin1_code":"7.0",
    "gn:asciiname":"Ait Ta'allat",
    "gn:country_code":"MA",
    "gn:dem":1451,
    "gn:feature_class":"P",
    "gn:feature_code":"PPL",
    "gn:name":"A\u00eft Ta\u2019allat",
    "gn:population":0,
    "gn:timezone":"Africa/Casablanca",
    "iso:country":"MA",
    "wof:name":"Ait Ta'allat",
    "wof:placetype":"locality"
},
  "geometry": {"coordinates":[-7.49439,31.37377],"type":"Point"}
}