{
  "type": "Feature",
  "properties": {
    "gn:admin1_code":"5.0",
    "gn:asciiname":"Oulad Ach. Chawi",
    "gn:country_code":"MA",
    "gn:dem":635,
    "gn:feature_class":"P",
    "gn:feature_code":"PPL",
    "gn:name":"Oulad Ach. Chawi",
    "gn:population":0,
    "gn:timezone":"Africa/Casablanca",
    "iso:country":"MA",
    "wof:name":"Oulad Ach. Chawi",
    "wof:placetype":"locality"
},
  "geometry": {"coordinates":[-6.76226,32.7431],"type":"Point"}
}