{
  "type": "Feature",
  "properties": {
    "gn:admin1_code":"09",
    "gn:asciiname":"Tafraout",
    "gn:country_code":"MA",
    "gn:dem":1295,
    "gn:feature_class":"P",
    "gn:feature_code":"PPL",
    "gn:name":"Tafraout",
    "gn:population":0,
    "gn:timezone":"Africa/Casablanca",
    "iso:country":"MA",
    "wof:name":"Tafraout",
    "wof:placetype":"locality"
},
  "geometry": {"coordinates":[-9.08553,29.46021],"type":"Point"}
}