{
  "type": "Feature",
  "properties": {
    "gn:admin1_code":"5.0",
    "gn:asciiname":"Bougal",
    "gn:country_code":"MA",
    "gn:dem":1744,
    "gn:feature_class":"P",
    "gn:feature_code":"PPL",
    "gn:name":"Bougal",
    "gn:population":0,
    "gn:timezone":"Africa/Casablanca",
    "iso:country":"MA",
    "wof:name":"Bougal",
    "wof:placetype":"locality"
},
  "geometry": {"coordinates":[-6.57726,31.61177],"type":"Point"}
}