{
  "type": "Feature",
  "properties": {
    "gn:admin1_code":"9.0",
    "gn:asciiname":"Tissili",
    "gn:country_code":"MA",
    "gn:dem":1468,
    "gn:feature_class":"P",
    "gn:feature_code":"PPL",
    "gn:name":"Tissili",
    "gn:population":0,
    "gn:timezone":"Africa/Casablanca",
    "iso:country":"MA",
    "wof:name":"Tissili",
    "wof:placetype":"locality"
},
  "geometry": {"coordinates":[-8.68996,30.82559],"type":"Point"}
}