{
  "type": "Feature",
  "properties": {
    "gn:country":"MA",
    "gn:fcode":"ADM3",
    "gn:pop":2213,
    "iso:country":"MA",
    "name:ara_x_preferred":[
        "\u062c\u0645\u0639\u0629 \u0645\u0648\u0644 \u0627\u0644\u0628\u0644\u0627\u062f"
    ],
    "name:ara_x_variant":[
        "\u0622\u064a\u062a \u0625\u064a\u0634\u0648"
    ],
    "name:cat_x_preferred":[
        "Ait Ichou"
    ],
    "name:ceb_x_preferred":[
        "Ait Ichou"
    ],
    "name:eng_x_preferred":[
        "Ait Ichou"
    ],
    "name:fra_x_preferred":[
        "Ait Ichou"
    ],
    "name:fra_x_variant":[
        "Ait Ichou (CR)",
        "Ait Ichou (Commune Rurale)"
    ],
    "name:ita_x_preferred":[
        "Ait Ichou"
    ],
    "name:swe_x_preferred":[
        "Ait Ichou"
    ],
    "qs:name":"Ait Ichou",
    "qs:photos_9r":0,
    "qs:photos_sr":0,
    "qs:pop_sr":"4",
    "wd:wordcount":60,
    "wof:name":"Ait Ichou",
    "wof:placetype":"localadmin",
    "wof:population":2213
},
  "geometry": {"coordinates":[-6.03526,33.53363],"type":"Point"}
}