{
  "type": "Feature",
  "properties": {
    "gn:admin1_code":"6.0",
    "gn:asciiname":"Lebbakra",
    "gn:country_code":"MA",
    "gn:dem":467,
    "gn:feature_class":"P",
    "gn:feature_code":"PPL",
    "gn:name":"Lebbakra",
    "gn:population":0,
    "gn:timezone":"Africa/Casablanca",
    "iso:country":"MA",
    "wof:name":"Lebbakra",
    "wof:placetype":"locality"
},
  "geometry": {"coordinates":[-7.14571,33.25774000000001],"type":"Point"}
}