{
  "type": "Feature",
  "properties": {
    "gn:admin1_code":"1.0",
    "gn:asciiname":"Dar Abdellah Hamacud",
    "gn:country_code":"MA",
    "gn:dem":5,
    "gn:feature_class":"P",
    "gn:feature_code":"PPL",
    "gn:name":"Dar Abdellah Hamacud",
    "gn:population":0,
    "gn:timezone":"Africa/Casablanca",
    "iso:country":"MA",
    "wof:name":"Dar Abdellah Hamacud",
    "wof:placetype":"locality"
},
  "geometry": {"coordinates":[-5.32832,35.63768],"type":"Point"}
}