{
  "type": "Feature",
  "properties": {
    "gn:admin1_code":"06",
    "gn:asciiname":"El Houaza",
    "gn:country_code":"MA",
    "gn:dem":408,
    "gn:feature_class":"P",
    "gn:feature_code":"PPL",
    "gn:name":"El Houaza",
    "gn:population":0,
    "gn:timezone":"Africa/Casablanca",
    "iso:country":"MA",
    "name:und_x_variant":[
        "El Haouazza"
    ],
    "wof:name":"El Houaza",
    "wof:placetype":"locality"
},
  "geometry": {"coordinates":[-7.7018,32.91389],"type":"Point"}
}