{
  "type": "Feature",
  "properties": {
    "gn:admin1_code":"01",
    "gn:asciiname":"Douar Zitouna",
    "gn:country_code":"MA",
    "gn:dem":222,
    "gn:feature_class":"P",
    "gn:feature_code":"PPL",
    "gn:name":"Douar Zitouna",
    "gn:population":0,
    "gn:timezone":"Africa/Casablanca",
    "iso:country":"MA",
    "name:und_x_variant":[
        "Zitouna",
        "Zeituna",
        "Ze\u00eftouna",
        "Douar Zitouna"
    ],
    "wof:name":"Douar Zitouna",
    "wof:placetype":"locality"
},
  "geometry": {"coordinates":[-4.28098,35.13094],"type":"Point"}
}