{
  "type": "Feature",
  "properties": {
    "gn:admin1_code":"08",
    "gn:asciiname":"Tiwiyyine",
    "gn:country_code":"MA",
    "gn:dem":1280,
    "gn:feature_class":"P",
    "gn:feature_code":"PPL",
    "gn:name":"Tiwiyyine",
    "gn:population":0,
    "gn:timezone":"Africa/Casablanca",
    "iso:country":"MA",
    "name:und_x_variant":[
        "Ksar Tiouine",
        "Tiouiyne",
        "Tiyouine",
        "Tiouine",
        "Tiwiyyine"
    ],
    "wof:name":"Tiwiyyine",
    "wof:placetype":"locality"
},
  "geometry": {"coordinates":[-7.21409,30.9321],"type":"Point"}
}