{
  "type": "Feature",
  "properties": {
    "gn:admin1_code":"1.0",
    "gn:asciiname":"Douar Ain Alaq",
    "gn:country_code":"MA",
    "gn:dem":257,
    "gn:feature_class":"P",
    "gn:feature_code":"PPL",
    "gn:name":"Douar Ain Alaq",
    "gn:population":0,
    "gn:timezone":"Africa/Casablanca",
    "iso:country":"MA",
    "wof:name":"Douar Ain Alaq",
    "wof:placetype":"locality"
},
  "geometry": {"coordinates":[-5.40439,34.72517],"type":"Point"}
}