{
  "type": "Feature",
  "properties": {
    "gn:admin1_code":"03",
    "gn:asciiname":"Douar Khelifa Ben Aissa",
    "gn:country_code":"MA",
    "gn:dem":770,
    "gn:feature_class":"P",
    "gn:feature_code":"PPL",
    "gn:name":"Douar Khelifa Ben Aissa",
    "gn:population":0,
    "gn:timezone":"Africa/Casablanca",
    "iso:country":"MA",
    "name:und_x_variant":[
        "Dar Khalifa Ben A\u00efssa"
    ],
    "wof:name":"Douar Khelifa Ben Aissa",
    "wof:placetype":"locality"
},
  "geometry": {"coordinates":[-5.60693,33.70433],"type":"Point"}
}