{
  "type": "Feature",
  "properties": {
    "gn:admin1_code":"05",
    "gn:asciiname":"Tamkaydout",
    "gn:country_code":"MA",
    "gn:dem":1716,
    "gn:feature_class":"P",
    "gn:feature_code":"PPL",
    "gn:name":"Tamkaydout",
    "gn:population":0,
    "gn:timezone":"Africa/Casablanca",
    "iso:country":"MA",
    "name:und_x_variant":[
        "A\u00eft Zolit-Tamakaydout",
        "Tamka\u00efdout",
        "Tamkaydout"
    ],
    "wof:name":"Tamkaydout",
    "wof:placetype":"locality"
},
  "geometry": {"coordinates":[-5.35177,32.66082],"type":"Point"}
}