{
  "type": "Feature",
  "properties": {
    "gn:admin1_code":"6.0",
    "gn:asciiname":"Douar Legouarba Oulad Laaribi",
    "gn:country_code":"MA",
    "gn:dem":230,
    "gn:feature_class":"P",
    "gn:feature_code":"PPL",
    "gn:name":"Douar Legouarba Oulad Laaribi",
    "gn:population":0,
    "gn:timezone":"Africa/Casablanca",
    "iso:country":"MA",
    "wof:name":"Douar Legouarba Oulad Laaribi",
    "wof:placetype":"locality"
},
  "geometry": {"coordinates":[-8.12587,32.73157],"type":"Point"}
}