{
  "type": "Feature",
  "properties": {
    "gn:admin1_code":"7.0",
    "gn:asciiname":"Eddouiouat",
    "gn:country_code":"MA",
    "gn:dem":354,
    "gn:feature_class":"P",
    "gn:feature_code":"PPL",
    "gn:name":"Eddouiouat",
    "gn:population":0,
    "gn:timezone":"Africa/Casablanca",
    "iso:country":"MA",
    "wof:name":"Eddouiouat",
    "wof:placetype":"locality"
},
  "geometry": {"coordinates":[-8.60773,32.18329],"type":"Point"}
}