{
  "type": "Feature",
  "properties": {
    "gn:admin1_code":"5.0",
    "gn:asciiname":"Ait Affaiko",
    "gn:country_code":"MA",
    "gn:dem":1432,
    "gn:feature_class":"P",
    "gn:feature_code":"PPL",
    "gn:name":"Ait Affaiko",
    "gn:population":0,
    "gn:timezone":"Africa/Casablanca",
    "iso:country":"MA",
    "wof:name":"Ait Affaiko",
    "wof:placetype":"locality"
},
  "geometry": {"coordinates":[-7.03883,31.64585],"type":"Point"}
}