{
  "type": "Feature",
  "properties": {
    "gn:admin1_code":"1.0",
    "gn:asciiname":"Douar Aghil Asnous",
    "gn:country_code":"MA",
    "gn:dem":40,
    "gn:feature_class":"P",
    "gn:feature_code":"PPL",
    "gn:name":"Douar Aghil Asnous",
    "gn:population":0,
    "gn:timezone":"Africa/Casablanca",
    "iso:country":"MA",
    "wof:name":"Douar Aghil Asnous",
    "wof:placetype":"locality"
},
  "geometry": {"coordinates":[-4.97792,35.32003],"type":"Point"}
}