{
  "type": "Feature",
  "properties": {
    "gn:admin1_code":"3.0",
    "gn:asciiname":"Imma Henna",
    "gn:country_code":"MA",
    "gn:dem":1647,
    "gn:feature_class":"P",
    "gn:feature_code":"PPL",
    "gn:name":"Imma Henna",
    "gn:population":0,
    "gn:timezone":"Africa/Casablanca",
    "iso:country":"MA",
    "wof:name":"Imma Henna",
    "wof:placetype":"locality"
},
  "geometry": {"coordinates":[-4.97541,33.59623],"type":"Point"}
}