{
  "type": "Feature",
  "properties": {
    "gn:admin1_code":"01",
    "gn:asciiname":"Souk Khmis Bni Arouss",
    "gn:country_code":"MA",
    "gn:dem":188,
    "gn:feature_class":"P",
    "gn:feature_code":"PPL",
    "gn:name":"Souk Khmis Bni Arouss",
    "gn:population":0,
    "gn:timezone":"Africa/Casablanca",
    "iso:country":"MA",
    "name:und_x_variant":[
        "Beni Ar\u00f3s",
        "El Jemis de Beni Ar\u00e1s",
        "Bni Aarouss",
        "Soko El Jemis",
        "Zoco el Jemis",
        "El Khemis des Beni Aros",
        "Zoco el Jemis de Beni Aros",
        "Souq Khemis des Beni Arouss",
        "Souk Khemis des Beni Arouss",
        "Souk Khmis Bni Arouss"
    ],
    "wof:name":"Souk Khmis Bni Arouss",
    "wof:placetype":"locality"
},
  "geometry": {"coordinates":[-5.62939,35.30707],"type":"Point"}
}