{
  "type": "Feature",
  "properties": {
    "gn:admin1_code":"09",
    "gn:asciiname":"Zaouia Ait Cherif",
    "gn:country_code":"MA",
    "gn:dem":456,
    "gn:feature_class":"P",
    "gn:feature_code":"PPL",
    "gn:name":"Zaouia A\u00eft Cherif",
    "gn:population":0,
    "gn:timezone":"Africa/Casablanca",
    "iso:country":"MA",
    "name:und_x_variant":[
        "Zaouia A\u00eftcheri",
        "Zaouia A\u00eft Cherif"
    ],
    "wof:name":"Zaouia Ait Cherif",
    "wof:placetype":"locality"
},
  "geometry": {"coordinates":[-8.69307,30.62343],"type":"Point"}
}