{
  "type": "Feature",
  "properties": {
    "gn:admin1_code":"06",
    "gn:asciiname":"Douar Laalichat",
    "gn:country_code":"MA",
    "gn:dem":169,
    "gn:feature_class":"P",
    "gn:feature_code":"PPL",
    "gn:name":"Douar Laalichat",
    "gn:population":0,
    "gn:timezone":"Africa/Casablanca",
    "iso:country":"MA",
    "name:und_x_variant":[
        "Douar Alachat Mohammed ben Sma\u00efl"
    ],
    "wof:name":"Douar Laalichat",
    "wof:placetype":"locality"
},
  "geometry": {"coordinates":[-8.6782,32.53931],"type":"Point"}
}