{
  "type": "Feature",
  "properties": {
    "gn:admin1_code":"7.0",
    "gn:asciiname":"Dar Bou Ider",
    "gn:country_code":"MA",
    "gn:dem":879,
    "gn:feature_class":"P",
    "gn:feature_code":"PPL",
    "gn:name":"Dar Bou Ider",
    "gn:population":0,
    "gn:timezone":"Africa/Casablanca",
    "iso:country":"MA",
    "wof:name":"Dar Bou Ider",
    "wof:placetype":"locality"
},
  "geometry": {"coordinates":[-7.96571,31.37455],"type":"Point"}
}