{
  "type": "Feature",
  "properties": {
    "gn:admin1_code":"7.0",
    "gn:asciiname":"Dar El Hajial",
    "gn:country_code":"MA",
    "gn:dem":526,
    "gn:feature_class":"P",
    "gn:feature_code":"PPL",
    "gn:name":"Dar El Hajial",
    "gn:population":0,
    "gn:timezone":"Africa/Casablanca",
    "iso:country":"MA",
    "wof:name":"Dar El Hajial",
    "wof:placetype":"locality"
},
  "geometry": {"coordinates":[-7.93601,32.31726],"type":"Point"}
}