{
  "type": "Feature",
  "properties": {
    "gn:admin1_code":"04",
    "gn:asciiname":"Douar Ennchal",
    "gn:country_code":"MA",
    "gn:dem":308,
    "gn:feature_class":"P",
    "gn:feature_code":"PPL",
    "gn:name":"Douar Ennchal",
    "gn:population":0,
    "gn:timezone":"Africa/Casablanca",
    "iso:country":"MA",
    "name:und_x_variant":[
        "N\u2019hal",
        "Nehal",
        "Douar Ennchal"
    ],
    "wof:name":"Douar Ennchal",
    "wof:placetype":"locality"
},
  "geometry": {"coordinates":[-5.80052,34.8876],"type":"Point"}
}