{
  "type": "Feature",
  "properties": {
    "gn:admin1_code":"6.0",
    "gn:asciiname":"Leabadla",
    "gn:country_code":"MA",
    "gn:dem":233,
    "gn:feature_class":"P",
    "gn:feature_code":"PPL",
    "gn:name":"Leabadla",
    "gn:population":0,
    "gn:timezone":"Africa/Casablanca",
    "iso:country":"MA",
    "wof:name":"Leabadla",
    "wof:placetype":"locality"
},
  "geometry": {"coordinates":[-7.22081,33.36139],"type":"Point"}
}