{
  "type": "Feature",
  "properties": {
    "gn:admin1_code":"07",
    "gn:asciiname":"Zawyat Tassaft",
    "gn:country_code":"MA",
    "gn:dem":1498,
    "gn:feature_class":"P",
    "gn:feature_code":"PPL",
    "gn:name":"Zawyat Tassaft",
    "gn:population":0,
    "gn:timezone":"Africa/Casablanca",
    "iso:country":"MA",
    "name:und_x_variant":[
        "Zaouia de Tassaft",
        "Tasseft",
        "Zawyat Tassaft"
    ],
    "wof:name":"Zawyat Tassaft",
    "wof:placetype":"locality"
},
  "geometry": {"coordinates":[-8.21699,30.9598],"type":"Point"}
}