{
  "type": "Feature",
  "properties": {
    "gn:admin1_code":"09",
    "gn:asciiname":"Tiwjgaline",
    "gn:country_code":"MA",
    "gn:dem":1714,
    "gn:feature_class":"P",
    "gn:feature_code":"PPL",
    "gn:name":"Tiwjgaline",
    "gn:population":0,
    "gn:timezone":"Africa/Casablanca",
    "iso:country":"MA",
    "name:und_x_variant":[
        "Tiouijgaline",
        "Tioujgaline"
    ],
    "wof:name":"Tiwjgaline",
    "wof:placetype":"locality"
},
  "geometry": {"coordinates":[-8.40513,30.08416],"type":"Point"}
}