{
  "type": "Feature",
  "properties": {
    "gn:admin1_code":"9.0",
    "gn:asciiname":"Id Dilguif",
    "gn:country_code":"MA",
    "gn:dem":689,
    "gn:feature_class":"P",
    "gn:feature_code":"PPL",
    "gn:name":"Id Dilguif",
    "gn:population":0,
    "gn:timezone":"Africa/Casablanca",
    "iso:country":"MA",
    "wof:name":"Id Dilguif",
    "wof:placetype":"locality"
},
  "geometry": {"coordinates":[-9.82459,29.45269],"type":"Point"}
}