{
  "type": "Feature",
  "properties": {
    "gn:admin1_code":"4.0",
    "gn:asciiname":"Oulad Marzoug",
    "gn:country_code":"MA",
    "gn:dem":121,
    "gn:feature_class":"P",
    "gn:feature_code":"PPL",
    "gn:name":"Oulad Marzoug",
    "gn:population":0,
    "gn:timezone":"Africa/Casablanca",
    "iso:country":"MA",
    "wof:name":"Oulad Marzoug",
    "wof:placetype":"locality"
},
  "geometry": {"coordinates":[-6.71509,33.75889],"type":"Point"}
}