{
  "type": "Feature",
  "properties": {
    "gn:admin1_code":"55.0",
    "gn:asciiname":"Inegouadine",
    "gn:country_code":"MA",
    "gn:dem":1820,
    "gn:feature_class":"P",
    "gn:feature_code":"PPL",
    "gn:name":"Inegouadine",
    "gn:population":0,
    "gn:timezone":"Africa/Casablanca",
    "iso:country":"MA",
    "wof:name":"Inegouadine",
    "wof:placetype":"locality"
},
  "geometry": {"coordinates":[-7.83246,31.01714],"type":"Point"}
}