{
  "type": "Feature",
  "properties": {
    "gn:admin1_code":"6.0",
    "gn:asciiname":"Douar Oulad Daouya",
    "gn:country_code":"MA",
    "gn:dem":560,
    "gn:feature_class":"P",
    "gn:feature_code":"PPL",
    "gn:name":"Douar Oulad Daouya",
    "gn:population":0,
    "gn:timezone":"Africa/Casablanca",
    "iso:country":"MA",
    "wof:name":"Douar Oulad Daouya",
    "wof:placetype":"locality"
},
  "geometry": {"coordinates":[-7.13127,33.12915],"type":"Point"}
}