{
  "type": "Feature",
  "properties": {
    "gn:admin1_code":"7.0",
    "gn:asciiname":"Rgamna",
    "gn:country_code":"MA",
    "gn:dem":130,
    "gn:feature_class":"P",
    "gn:feature_code":"PPL",
    "gn:name":"Rgamna",
    "gn:population":0,
    "gn:timezone":"Africa/Casablanca",
    "iso:country":"MA",
    "wof:name":"Rgamna",
    "wof:placetype":"locality"
},
  "geometry": {"coordinates":[-9.12961,32.49054],"type":"Point"}
}