{
  "type": "Feature",
  "properties": {
    "gn:admin1_code":"07",
    "gn:asciiname":"Tbab'a Dra' Twil",
    "gn:country_code":"MA",
    "gn:dem":569,
    "gn:feature_class":"P",
    "gn:feature_code":"PPL",
    "gn:name":"Tbab\u2019a Dra\u2019 Twil",
    "gn:population":0,
    "gn:timezone":"Africa/Casablanca",
    "iso:country":"MA",
    "name:und_x_variant":[
        "Taba\u00e2 Drame Teouil",
        "Tebaba\u2019a Dra\u2019twil",
        "Douar Tebab\u00e2a Draa Touil",
        "Tbeba",
        "Tebab\u00e2a",
        "Tebab\u2018a",
        "Tbab\u2019a Dra\u2019 Twil"
    ],
    "wof:name":"Tbab'a Dra' Twil",
    "wof:placetype":"locality"
},
  "geometry": {"coordinates":[-7.43396,31.91826],"type":"Point"}
}