{
  "type": "Feature",
  "properties": {
    "gn:admin1_code":"1.0",
    "gn:asciiname":"Talat Toufalene",
    "gn:country_code":"MA",
    "gn:dem":712,
    "gn:feature_class":"P",
    "gn:feature_code":"PPL",
    "gn:name":"Talat Toufalene",
    "gn:population":0,
    "gn:timezone":"Africa/Casablanca",
    "iso:country":"MA",
    "wof:name":"Talat Toufalene",
    "wof:placetype":"locality"
},
  "geometry": {"coordinates":[-4.80117,35.01199],"type":"Point"}
}