{
  "type": "Feature",
  "properties": {
    "gn:admin1_code":"7.0",
    "gn:asciiname":"Douar Oulad Lemaachi",
    "gn:country_code":"MA",
    "gn:dem":101,
    "gn:feature_class":"P",
    "gn:feature_code":"PPL",
    "gn:name":"Douar Oulad Lemaachi",
    "gn:population":0,
    "gn:timezone":"Africa/Casablanca",
    "iso:country":"MA",
    "wof:name":"Douar Oulad Lemaachi",
    "wof:placetype":"locality"
},
  "geometry": {"coordinates":[-9.1687,32.33129],"type":"Point"}
}