{
  "type": "Feature",
  "properties": {
    "gn:admin1_code":"7.0",
    "gn:asciiname":"Tighmartane",
    "gn:country_code":"MA",
    "gn:dem":1428,
    "gn:feature_class":"P",
    "gn:feature_code":"PPL",
    "gn:name":"Tighmartane",
    "gn:population":0,
    "gn:timezone":"Africa/Casablanca",
    "iso:country":"MA",
    "wof:name":"Tighmartane",
    "wof:placetype":"locality"
},
  "geometry": {"coordinates":[-7.32958,31.46923],"type":"Point"}
}