{
  "type": "Feature",
  "properties": {
    "gn:admin1_code":"07",
    "gn:asciiname":"Kourimat",
    "gn:country_code":"MA",
    "gn:dem":460,
    "gn:feature_class":"P",
    "gn:feature_code":"PPL",
    "gn:name":"Kourimat",
    "gn:population":0,
    "gn:timezone":"Africa/Casablanca",
    "iso:country":"MA",
    "name:ara_x_preferred":[
        "\u0627\u0644\u0643\u0631\u064a\u0645\u0627\u062a"
    ],
    "name:cat_x_preferred":[
        "Korimate"
    ],
    "name:ita_x_preferred":[
        "Korimate"
    ],
    "name:und_x_variant":[
        "El Djem\u00e2",
        "Korimate",
        "El Jem\u00e2",
        "Kourimate",
        "Sebt-Korimate",
        "Kourimat"
    ],
    "wof:name":"Kourimat",
    "wof:placetype":"locality"
},
  "geometry": {"coordinates":[-9.31638,31.46047],"type":"Point"}
}