{
  "type": "Feature",
  "properties": {
    "gn:admin1_code":"03",
    "gn:asciiname":"Douar Ifatna",
    "gn:country_code":"MA",
    "gn:dem":642,
    "gn:feature_class":"P",
    "gn:feature_code":"PPL",
    "gn:name":"Douar Ifatna",
    "gn:population":0,
    "gn:timezone":"Africa/Casablanca",
    "iso:country":"MA",
    "name:und_x_variant":[
        "Ifatna"
    ],
    "wof:name":"Douar Ifatna",
    "wof:placetype":"locality"
},
  "geometry": {"coordinates":[-4.01187,34.36296],"type":"Point"}
}