{
  "type": "Feature",
  "properties": {
    "gn:admin1_code":"01",
    "gn:asciiname":"Chrouda Lfouqiya",
    "gn:country_code":"MA",
    "gn:dem":126,
    "gn:feature_class":"P",
    "gn:feature_code":"PPL",
    "gn:name":"Chrouda Lfouqiya",
    "gn:population":0,
    "gn:timezone":"Africa/Casablanca",
    "iso:country":"MA",
    "name:und_x_variant":[
        "Chrouda"
    ],
    "wof:name":"Chrouda Lfouqiya",
    "wof:placetype":"locality"
},
  "geometry": {"coordinates":[-5.17683,35.38930999999999],"type":"Point"}
}