{
  "type": "Feature",
  "properties": {
    "gn:admin1_code":"7.0",
    "gn:asciiname":"Rahhal Ben 'Ali",
    "gn:country_code":"MA",
    "gn:dem":559,
    "gn:feature_class":"P",
    "gn:feature_code":"PPL",
    "gn:name":"Rahhal Ben \u2019Ali",
    "gn:population":0,
    "gn:timezone":"Africa/Casablanca",
    "iso:country":"MA",
    "wof:name":"Rahhal Ben 'Ali",
    "wof:placetype":"locality"
},
  "geometry": {"coordinates":[-7.25464,31.92358],"type":"Point"}
}