{
  "type": "Feature",
  "properties": {
    "gn:admin1_code":"4.0",
    "gn:asciiname":"Douar Sahraoua",
    "gn:country_code":"MA",
    "gn:dem":19,
    "gn:feature_class":"P",
    "gn:feature_code":"PPL",
    "gn:name":"Douar Sahraoua",
    "gn:population":0,
    "gn:timezone":"Africa/Casablanca",
    "iso:country":"MA",
    "wof:name":"Douar Sahraoua",
    "wof:placetype":"locality"
},
  "geometry": {"coordinates":[-5.95078,34.55132],"type":"Point"}
}