{
  "type": "Feature",
  "properties": {
    "gn:admin1_code":"06",
    "gn:asciiname":"Douar Freyakh",
    "gn:country_code":"MA",
    "gn:dem":365,
    "gn:feature_class":"P",
    "gn:feature_code":"PPL",
    "gn:name":"Douar Freyakh",
    "gn:population":0,
    "gn:timezone":"Africa/Casablanca",
    "iso:country":"MA",
    "wof:name":"Douar Freyakh",
    "wof:placetype":"locality"
},
  "geometry": {"coordinates":[-7.46,32.51],"type":"Point"}
}