{
  "type": "Feature",
  "properties": {
    "gn:admin1_code":"2.0",
    "gn:asciiname":"Caryane Taarabt",
    "gn:country_code":"MA",
    "gn:dem":45,
    "gn:feature_class":"P",
    "gn:feature_code":"PPL",
    "gn:name":"Caryane Taarabt",
    "gn:population":0,
    "gn:timezone":"Africa/Casablanca",
    "iso:country":"MA",
    "wof:name":"Caryane Taarabt",
    "wof:placetype":"locality"
},
  "geometry": {"coordinates":[-2.4226,35.12006],"type":"Point"}
}