{
  "type": "Feature",
  "properties": {
    "gn:admin1_code":"05",
    "gn:asciiname":"Ait Lahsene Ou Ali",
    "gn:country_code":"MA",
    "gn:dem":1615,
    "gn:elevation":"0.0",
    "gn:feature_class":"P",
    "gn:feature_code":"PPL",
    "gn:name":"A\u00eft Lahsene Ou Ali",
    "gn:population":0,
    "gn:timezone":"Africa/Casablanca",
    "iso:country":"MA",
    "wof:name":"Ait Lahsene Ou Ali",
    "wof:placetype":"locality"
},
  "geometry": {"coordinates":[-6.71016,31.68518],"type":"Point"}
}