{
  "type": "Feature",
  "properties": {
    "gn:admin1_code":"7.0",
    "gn:asciiname":"Ayt Ahmed Ou 'Ali",
    "gn:country_code":"MA",
    "gn:dem":831,
    "gn:feature_class":"P",
    "gn:feature_code":"PPL",
    "gn:name":"Ayt Ahmed Ou \u2019Ali",
    "gn:population":0,
    "gn:timezone":"Africa/Casablanca",
    "iso:country":"MA",
    "wof:name":"Ayt Ahmed Ou 'Ali",
    "wof:placetype":"locality"
},
  "geometry": {"coordinates":[-7.79565,31.3869],"type":"Point"}
}