{
  "type": "Feature",
  "properties": {
    "gn:admin1_code":"6.0",
    "gn:asciiname":"Chouala",
    "gn:country_code":"MA",
    "gn:dem":166,
    "gn:feature_class":"P",
    "gn:feature_code":"PPL",
    "gn:name":"Chouala",
    "gn:population":0,
    "gn:timezone":"Africa/Casablanca",
    "iso:country":"MA",
    "wof:name":"Chouala",
    "wof:placetype":"locality"
},
  "geometry": {"coordinates":[-8.10128,32.95291],"type":"Point"}
}