{
  "type": "Feature",
  "properties": {
    "gn:admin1_code":"7.0",
    "gn:asciiname":"Oulad Mansour",
    "gn:country_code":"MA",
    "gn:dem":575,
    "gn:feature_class":"P",
    "gn:feature_code":"PPL",
    "gn:name":"Oulad Mansour",
    "gn:population":0,
    "gn:timezone":"Africa/Casablanca",
    "iso:country":"MA",
    "wof:name":"Oulad Mansour",
    "wof:placetype":"locality"
},
  "geometry": {"coordinates":[-9.18124,31.70919],"type":"Point"}
}