{
  "type": "Feature",
  "properties": {
    "gn:admin1_code":"07",
    "gn:asciiname":"Taws",
    "gn:country_code":"MA",
    "gn:dem":1346,
    "gn:feature_class":"P",
    "gn:feature_code":"PPL",
    "gn:name":"Taws",
    "gn:population":0,
    "gn:timezone":"Africa/Casablanca",
    "iso:country":"MA",
    "name:und_x_variant":[
        "Taous"
    ],
    "wof:name":"Taws",
    "wof:placetype":"locality"
},
  "geometry": {"coordinates":[-8.27177,30.94361],"type":"Point"}
}