{
  "type": "Feature",
  "properties": {
    "gn:admin1_code":"6.0",
    "gn:asciiname":"Douar Lbousra",
    "gn:country_code":"MA",
    "gn:dem":216,
    "gn:feature_class":"P",
    "gn:feature_code":"PPL",
    "gn:name":"Douar Lbousra",
    "gn:population":0,
    "gn:timezone":"Africa/Casablanca",
    "iso:country":"MA",
    "wof:name":"Douar Lbousra",
    "wof:placetype":"locality"
},
  "geometry": {"coordinates":[-8.16489,32.71471],"type":"Point"}
}