{
  "type": "Feature",
  "properties": {
    "gn:admin1_code":"8.0",
    "gn:asciiname":"Oulad ' Aycha",
    "gn:country_code":"MA",
    "gn:dem":759,
    "gn:feature_class":"P",
    "gn:feature_code":"PPL",
    "gn:name":"Oulad \u2019 Aycha",
    "gn:population":0,
    "gn:timezone":"Africa/Casablanca",
    "iso:country":"MA",
    "wof:name":"Oulad ' Aycha",
    "wof:placetype":"locality"
},
  "geometry": {"coordinates":[-4.24566,31.26725],"type":"Point"}
}