{
  "type": "Feature",
  "properties": {
    "gn:admin1_code":"7.0",
    "gn:asciiname":"Iraqene",
    "gn:country_code":"MA",
    "gn:dem":739,
    "gn:feature_class":"P",
    "gn:feature_code":"PPL",
    "gn:name":"Iraqene",
    "gn:population":0,
    "gn:timezone":"Africa/Casablanca",
    "iso:country":"MA",
    "wof:name":"Iraqene",
    "wof:placetype":"locality"
},
  "geometry": {"coordinates":[-7.64154,31.53505],"type":"Point"}
}