{
  "type": "Feature",
  "properties": {
    "gn:admin1_code":"5.0",
    "gn:asciiname":"Assaklou",
    "gn:country_code":"MA",
    "gn:dem":1843,
    "gn:feature_class":"P",
    "gn:feature_code":"PPL",
    "gn:name":"Assaklou",
    "gn:population":0,
    "gn:timezone":"Africa/Casablanca",
    "iso:country":"MA",
    "wof:name":"Assaklou",
    "wof:placetype":"locality"
},
  "geometry": {"coordinates":[-6.0666,31.81608],"type":"Point"}
}