{
  "type": "Feature",
  "properties": {
    "gn:admin1_code":"09",
    "gn:asciiname":"Agardane",
    "gn:country_code":"MA",
    "gn:dem":1325,
    "gn:feature_class":"P",
    "gn:feature_code":"PPL",
    "gn:name":"Agardane",
    "gn:population":0,
    "gn:timezone":"Africa/Casablanca",
    "iso:country":"MA",
    "name:und_x_variant":[
        "Aguerdane"
    ],
    "wof:name":"Agardane",
    "wof:placetype":"locality"
},
  "geometry": {"coordinates":[-8.83401,29.94176],"type":"Point"}
}