{
  "type": "Feature",
  "properties": {
    "gn:admin1_code":"9.0",
    "gn:asciiname":"Lahfert",
    "gn:country_code":"MA",
    "gn:dem":170,
    "gn:feature_class":"P",
    "gn:feature_code":"PPL",
    "gn:name":"Lahfert",
    "gn:population":0,
    "gn:timezone":"Africa/Casablanca",
    "iso:country":"MA",
    "wof:name":"Lahfert",
    "wof:placetype":"locality"
},
  "geometry": {"coordinates":[-9.29959,30.13978],"type":"Point"}
}