{
  "type": "Feature",
  "properties": {
    "gn:admin1_code":"4.0",
    "gn:asciiname":"Cooperative Ouidad",
    "gn:country_code":"MA",
    "gn:dem":398,
    "gn:feature_class":"P",
    "gn:feature_code":"PPLF",
    "gn:name":"Coop\u00e9rative Ouidad",
    "gn:population":0,
    "gn:timezone":"Africa/Casablanca",
    "iso:country":"MA",
    "wof:name":"Cooperative Ouidad",
    "wof:placetype":"locality"
},
  "geometry": {"coordinates":[-6.68867,33.622],"type":"Point"}
}