{
  "type": "Feature",
  "properties": {
    "gn:admin1_code":"2.0",
    "gn:asciiname":"Jaddi Mhamed",
    "gn:country_code":"MA",
    "gn:dem":557,
    "gn:feature_class":"P",
    "gn:feature_code":"PPL",
    "gn:name":"Jaddi Mhamed",
    "gn:population":0,
    "gn:timezone":"Africa/Casablanca",
    "iso:country":"MA",
    "wof:name":"Jaddi Mhamed",
    "wof:placetype":"locality"
},
  "geometry": {"coordinates":[-3.40557,35.11636],"type":"Point"}
}