{
  "type": "Feature",
  "properties": {
    "gn:admin1_code":"10",
    "gn:asciiname":"Timezguida de Jemaa",
    "gn:country_code":"MA",
    "gn:dem":951,
    "gn:feature_class":"P",
    "gn:feature_code":"PPL",
    "gn:name":"Timezguida de Jemaa",
    "gn:population":0,
    "gn:timezone":"Africa/Casablanca",
    "iso:country":"MA",
    "name:und_x_variant":[
        "Timzguida el Jem\u00e2a",
        "Timezguida de Jemaa"
    ],
    "wof:name":"Timezguida de Jemaa",
    "wof:placetype":"locality"
},
  "geometry": {"coordinates":[-9.44212,29.23791],"type":"Point"}
}