{
  "type": "Feature",
  "properties": {
    "gn:admin1_code":"02",
    "gn:asciiname":"Douar Oulad Jaber Tehata",
    "gn:country_code":"MA",
    "gn:dem":620,
    "gn:feature_class":"P",
    "gn:feature_code":"PPL",
    "gn:name":"Douar Oulad Jaber Tehata",
    "gn:population":0,
    "gn:timezone":"Africa/Casablanca",
    "iso:country":"MA",
    "name:und_x_variant":[
        "Ouled el Man Tahata",
        "Oulad el Mane Tahata",
        "Douar Oulad Jaber Tehata",
        "Ouled Bou Jem\u00e2a Louffagar Thata",
        "Oulad Boujemaa Tahata",
        "Oulad Boujema\u00e2 Fouaga"
    ],
    "wof:name":"Douar Oulad Jaber Tehata",
    "wof:placetype":"locality"
},
  "geometry": {"coordinates":[-2.12583,34.78824],"type":"Point"}
}