{
  "type": "Feature",
  "properties": {
    "gn:admin1_code":"2.0",
    "gn:asciiname":"Tizi",
    "gn:country_code":"MA",
    "gn:dem":234,
    "gn:feature_class":"P",
    "gn:feature_code":"PPL",
    "gn:name":"Tizi",
    "gn:population":0,
    "gn:timezone":"Africa/Casablanca",
    "iso:country":"MA",
    "name:ara_x_preferred":[
        "\u062a\u064a\u0632\u064a"
    ],
    "name:azb_x_preferred":[
        "\u062a\u06cc\u0632\u06cc"
    ],
    "name:fas_x_preferred":[
        "\u062a\u06cc\u0632\u06cc"
    ],
    "name:fra_x_preferred":[
        "Tizi"
    ],
    "name:ita_x_preferred":[
        "Tizi"
    ],
    "name:kab_x_preferred":[
        "Tizi"
    ],
    "name:msa_x_preferred":[
        "Tizi"
    ],
    "name:por_x_preferred":[
        "Tizi"
    ],
    "name:ron_x_preferred":[
        "Tizi"
    ],
    "name:spa_x_preferred":[
        "Tizi"
    ],
    "name:vie_x_preferred":[
        "Tizi"
    ],
    "wof:name":"Tizi",
    "wof:placetype":"locality"
},
  "geometry": {"coordinates":[-3.0828,35.12818],"type":"Point"}
}