{
  "type": "Feature",
  "properties": {
    "gn:admin1_code":"55",
    "gn:asciiname":"Ait Said",
    "gn:country_code":"MA",
    "gn:dem":1341,
    "gn:feature_class":"P",
    "gn:feature_code":"PPL",
    "gn:name":"A\u00eft Sa\u00efd",
    "gn:population":0,
    "gn:timezone":"Africa/Casablanca",
    "iso:country":"MA",
    "name:ara_x_preferred":[
        "\u0622\u064a\u062a \u0633\u0639\u064a\u062f"
    ],
    "name:azb_x_preferred":[
        "\u0622\u06cc\u062a \u0633\u062f"
    ],
    "name:cat_x_preferred":[
        "Ait Said"
    ],
    "name:fas_x_preferred":[
        "\u0622\u06cc\u062a \u0633\u062f"
    ],
    "name:ita_x_preferred":[
        "Ait Said"
    ],
    "wof:name":"Ait Said",
    "wof:placetype":"locality"
},
  "geometry": {"coordinates":[-6.61,31.13],"type":"Point"}
}