{
  "type": "Feature",
  "properties": {
    "gn:admin1_code":"7.0",
    "gn:asciiname":"Ait Mirane",
    "gn:country_code":"MA",
    "gn:dem":488,
    "gn:feature_class":"P",
    "gn:feature_code":"PPL",
    "gn:name":"A\u00eft Mirane",
    "gn:population":0,
    "gn:timezone":"Africa/Casablanca",
    "iso:country":"MA",
    "wof:name":"Ait Mirane",
    "wof:placetype":"locality"
},
  "geometry": {"coordinates":[-9.37503,31.37595],"type":"Point"}
}