{
  "type": "Feature",
  "properties": {
    "gn:admin1_code":"9.0",
    "gn:asciiname":"Imi Ougchtiym",
    "gn:country_code":"MA",
    "gn:dem":1046,
    "gn:feature_class":"P",
    "gn:feature_code":"PPL",
    "gn:name":"Imi Ougchtiym",
    "gn:population":0,
    "gn:timezone":"Africa/Casablanca",
    "iso:country":"MA",
    "wof:name":"Imi Ougchtiym",
    "wof:placetype":"locality"
},
  "geometry": {"coordinates":[-8.92364,29.74942],"type":"Point"}
}