{
  "type": "Feature",
  "properties": {
    "gn:admin1_code":"10.0",
    "gn:asciiname":"Id Oufqir",
    "gn:country_code":"MA",
    "gn:dem":630,
    "gn:feature_class":"P",
    "gn:feature_code":"PPL",
    "gn:name":"Id Oufqir",
    "gn:population":0,
    "gn:timezone":"Africa/Casablanca",
    "iso:country":"MA",
    "wof:name":"Id Oufqir",
    "wof:placetype":"locality"
},
  "geometry": {"coordinates":[-9.93496,29.27461],"type":"Point"}
}