{
  "type": "Feature",
  "properties": {
    "gn:admin1_code":"1.0",
    "gn:asciiname":"Douar Tamzazkout",
    "gn:country_code":"MA",
    "gn:dem":401,
    "gn:feature_class":"P",
    "gn:feature_code":"PPL",
    "gn:name":"Douar Tamzazkout",
    "gn:population":0,
    "gn:timezone":"Africa/Casablanca",
    "iso:country":"MA",
    "wof:name":"Douar Tamzazkout",
    "wof:placetype":"locality"
},
  "geometry": {"coordinates":[-3.82513,34.99757],"type":"Point"}
}