{
  "type": "Feature",
  "properties": {
    "gn:admin1_code":"3.0",
    "gn:asciiname":"Douar Ait Ayyoub",
    "gn:country_code":"MA",
    "gn:dem":701,
    "gn:feature_class":"P",
    "gn:feature_code":"PPL",
    "gn:name":"Douar Ait Ayyoub",
    "gn:population":0,
    "gn:timezone":"Africa/Casablanca",
    "iso:country":"MA",
    "wof:name":"Douar Ait Ayyoub",
    "wof:placetype":"locality"
},
  "geometry": {"coordinates":[-4.66099,33.95468],"type":"Point"}
}