{
  "type": "Feature",
  "properties": {
    "gn:admin1_code":"8.0",
    "gn:asciiname":"Tawzout",
    "gn:country_code":"MA",
    "gn:dem":1776,
    "gn:feature_class":"P",
    "gn:feature_code":"PPL",
    "gn:name":"Tawzout",
    "gn:population":0,
    "gn:timezone":"Africa/Casablanca",
    "iso:country":"MA",
    "wof:name":"Tawzout",
    "wof:placetype":"locality"
},
  "geometry": {"coordinates":[-7.51704,30.60457],"type":"Point"}
}