{
  "type": "Feature",
  "properties": {
    "gn:admin1_code":"08",
    "gn:asciiname":"Ait Aouch",
    "gn:country_code":"MA",
    "gn:dem":1725,
    "gn:feature_class":"P",
    "gn:feature_code":"PPL",
    "gn:name":"A\u00eft Aouch",
    "gn:population":0,
    "gn:timezone":"Africa/Casablanca",
    "iso:country":"MA",
    "name:und_x_variant":[
        "N\u2019A\u00eft Aouch",
        "A\u00eft Aouch"
    ],
    "wof:name":"Ait Aouch",
    "wof:placetype":"locality"
},
  "geometry": {"coordinates":[-4.94387,32.30982],"type":"Point"}
}