{
  "type": "Feature",
  "properties": {
    "gn:admin1_code":"9.0",
    "gn:asciiname":"Id Mansour",
    "gn:country_code":"MA",
    "gn:dem":284,
    "gn:feature_class":"P",
    "gn:feature_code":"PPL",
    "gn:name":"Id Mansour",
    "gn:population":0,
    "gn:timezone":"Africa/Casablanca",
    "iso:country":"MA",
    "wof:name":"Id Mansour",
    "wof:placetype":"locality"
},
  "geometry": {"coordinates":[-9.7814,30.77605],"type":"Point"}
}