{
  "type": "Feature",
  "properties": {
    "gn:admin1_code":"03",
    "gn:asciiname":"Bou Mahrouf",
    "gn:country_code":"MA",
    "gn:dem":1297,
    "gn:feature_class":"P",
    "gn:feature_code":"PPL",
    "gn:name":"Bou Mahrouf",
    "gn:population":0,
    "gn:timezone":"Africa/Casablanca",
    "iso:country":"MA",
    "name:und_x_variant":[
        "Dar Bou Marouf",
        "Bou Mahrouf"
    ],
    "wof:name":"Bou Mahrouf",
    "wof:placetype":"locality"
},
  "geometry": {"coordinates":[-3.8069,34.74529],"type":"Point"}
}