{
  "type": "Feature",
  "properties": {
    "gn:admin1_code":"3.0",
    "gn:asciiname":"Oulad Bou Ades",
    "gn:country_code":"MA",
    "gn:dem":672,
    "gn:feature_class":"P",
    "gn:feature_code":"PPL",
    "gn:name":"Oulad Bou Ades",
    "gn:population":0,
    "gn:timezone":"Africa/Casablanca",
    "iso:country":"MA",
    "wof:name":"Oulad Bou Ades",
    "wof:placetype":"locality"
},
  "geometry": {"coordinates":[-4.58863,33.88691],"type":"Point"}
}