{
  "type": "Feature",
  "properties": {
    "gn:admin1_code":"8.0",
    "gn:asciiname":"Alighane",
    "gn:country_code":"MA",
    "gn:dem":2057,
    "gn:feature_class":"P",
    "gn:feature_code":"PPL",
    "gn:name":"Alighane",
    "gn:population":0,
    "gn:timezone":"Africa/Casablanca",
    "iso:country":"MA",
    "wof:name":"Alighane",
    "wof:placetype":"locality"
},
  "geometry": {"coordinates":[-7.41009,31.26196],"type":"Point"}
}