{
  "type": "Feature",
  "properties": {
    "gn:admin1_code":"07",
    "gn:asciiname":"Oulad Ali",
    "gn:country_code":"MA",
    "gn:dem":425,
    "gn:feature_class":"P",
    "gn:feature_code":"PPL",
    "gn:name":"Oulad Ali",
    "gn:population":0,
    "gn:timezone":"Africa/Casablanca",
    "iso:country":"MA",
    "name:und_x_variant":[
        "Oulad Jaber",
        "Oulad Jeber",
        "Douar Oulad Jaber",
        "Oulad Ali"
    ],
    "wof:name":"Oulad Ali",
    "wof:placetype":"locality"
},
  "geometry": {"coordinates":[-7.43254,32.22966],"type":"Point"}
}