{
  "type": "Feature",
  "properties": {
    "gn:admin1_code":"6.0",
    "gn:asciiname":"Cooperative Sehb Laasel",
    "gn:country_code":"MA",
    "gn:dem":305,
    "gn:feature_class":"P",
    "gn:feature_code":"PPLF",
    "gn:name":"Coop\u00e9rative Sehb Laasel",
    "gn:population":0,
    "gn:timezone":"Africa/Casablanca",
    "iso:country":"MA",
    "wof:name":"Cooperative Sehb Laasel",
    "wof:placetype":"locality"
},
  "geometry": {"coordinates":[-7.06556,33.58178],"type":"Point"}
}