{
  "type": "Feature",
  "properties": {
    "gn:admin1_code":"03",
    "gn:asciiname":"Douar Bni Hameline",
    "gn:country_code":"MA",
    "gn:dem":393,
    "gn:feature_class":"P",
    "gn:feature_code":"PPL",
    "gn:name":"Douar Bni Hameline",
    "gn:population":0,
    "gn:timezone":"Africa/Casablanca",
    "iso:country":"MA",
    "name:und_x_variant":[
        "Douar Beni Hameline",
        "Beni Hameline",
        "Douar Bni Hameline"
    ],
    "wof:name":"Douar Bni Hameline",
    "wof:placetype":"locality"
},
  "geometry": {"coordinates":[-4.81475,34.14911],"type":"Point"}
}