{
  "type": "Feature",
  "properties": {
    "gn:admin1_code":"7.0",
    "gn:asciiname":"Azrou-n-Souq",
    "gn:country_code":"MA",
    "gn:dem":1187,
    "gn:feature_class":"P",
    "gn:feature_code":"PPL",
    "gn:name":"Azrou-n-Souq",
    "gn:population":0,
    "gn:timezone":"Africa/Casablanca",
    "iso:country":"MA",
    "wof:name":"Azrou-n-Souq",
    "wof:placetype":"locality"
},
  "geometry": {"coordinates":[-8.16817,30.99766],"type":"Point"}
}