{
  "type": "Feature",
  "properties": {
    "gn:admin1_code":"9.0",
    "gn:asciiname":"Hassi Lebgar",
    "gn:country_code":"MA",
    "gn:dem":76,
    "gn:feature_class":"P",
    "gn:feature_code":"PPL",
    "gn:name":"Hassi Lebgar",
    "gn:population":0,
    "gn:timezone":"Africa/Casablanca",
    "iso:country":"MA",
    "wof:name":"Hassi Lebgar",
    "wof:placetype":"locality"
},
  "geometry": {"coordinates":[-9.49631,30.23167],"type":"Point"}
}