{
  "type": "Feature",
  "properties": {
    "gn:admin1_code":"07",
    "gn:asciiname":"Bouazda",
    "gn:country_code":"MA",
    "gn:dem":163,
    "gn:feature_class":"P",
    "gn:feature_code":"PPL",
    "gn:name":"Bouazda",
    "gn:population":0,
    "gn:timezone":"Africa/Casablanca",
    "iso:country":"MA",
    "name:und_x_variant":[
        "Douar el Bouazda",
        "El Bouazda"
    ],
    "wof:name":"Bouazda",
    "wof:placetype":"locality"
},
  "geometry": {"coordinates":[-8.86793,32.26768],"type":"Point"}
}