{
  "type": "Feature",
  "properties": {
    "gn:admin1_code":"9.0",
    "gn:asciiname":"Id Ben Addi",
    "gn:country_code":"MA",
    "gn:dem":282,
    "gn:feature_class":"P",
    "gn:feature_code":"PPL",
    "gn:name":"Id Ben Addi",
    "gn:population":0,
    "gn:timezone":"Africa/Casablanca",
    "iso:country":"MA",
    "wof:name":"Id Ben Addi",
    "wof:placetype":"locality"
},
  "geometry": {"coordinates":[-9.78419,30.77996],"type":"Point"}
}