{
  "type": "Feature",
  "properties": {
    "gn:admin1_code":"3.0",
    "gn:asciiname":"Talaint Tamellalt",
    "gn:country_code":"MA",
    "gn:dem":1676,
    "gn:feature_class":"P",
    "gn:feature_code":"PPL",
    "gn:name":"Talaint Tamellalt",
    "gn:population":0,
    "gn:timezone":"Africa/Casablanca",
    "iso:country":"MA",
    "wof:name":"Talaint Tamellalt",
    "wof:placetype":"locality"
},
  "geometry": {"coordinates":[-4.99547,33.54692],"type":"Point"}
}