{
  "type": "Feature",
  "properties": {
    "gn:admin1_code":"1.0",
    "gn:asciiname":"Oulad Ben Ifou",
    "gn:country_code":"MA",
    "gn:dem":57,
    "gn:feature_class":"P",
    "gn:feature_code":"PPL",
    "gn:name":"Oulad Ben Ifou",
    "gn:population":0,
    "gn:timezone":"Africa/Casablanca",
    "iso:country":"MA",
    "wof:name":"Oulad Ben Ifou",
    "wof:placetype":"locality"
},
  "geometry": {"coordinates":[-5.95803,35.46165],"type":"Point"}
}