{
  "type": "Feature",
  "properties": {
    "gn:admin1_code":"9.0",
    "gn:asciiname":"Imraouhine",
    "gn:country_code":"MA",
    "gn:dem":168,
    "gn:feature_class":"P",
    "gn:feature_code":"PPL",
    "gn:name":"Imraouhine",
    "gn:population":0,
    "gn:timezone":"Africa/Casablanca",
    "iso:country":"MA",
    "wof:name":"Imraouhine",
    "wof:placetype":"locality"
},
  "geometry": {"coordinates":[-9.40032,29.95399],"type":"Point"}
}