{
  "type": "Feature",
  "properties": {
    "gn:admin1_code":"08",
    "gn:asciiname":"Zakar",
    "gn:country_code":"MA",
    "gn:dem":2019,
    "gn:feature_class":"P",
    "gn:feature_code":"PPL",
    "gn:name":"Zakar",
    "gn:population":0,
    "gn:timezone":"Africa/Casablanca",
    "iso:country":"MA",
    "name:ind_x_preferred":[
        "Zakar"
    ],
    "name:und_x_variant":[
        "Taker",
        "Zaker",
        "Zake"
    ],
    "wof:name":"Zakar",
    "wof:placetype":"locality"
},
  "geometry": {"coordinates":[-5.65355,31.11673],"type":"Point"}
}