{
  "type": "Feature",
  "properties": {
    "gn:admin1_code":"07",
    "gn:asciiname":"Douar Ait Ben Allal",
    "gn:country_code":"MA",
    "gn:dem":394,
    "gn:feature_class":"P",
    "gn:feature_code":"PPL",
    "gn:name":"Douar Ait Ben Allal",
    "gn:population":0,
    "gn:timezone":"Africa/Casablanca",
    "iso:country":"MA",
    "name:und_x_variant":[
        "Achouaker",
        "Douar Abdallah",
        "Chouaker",
        "Douar Ait Ben Allal"
    ],
    "wof:name":"Douar Ait Ben Allal",
    "wof:placetype":"locality"
},
  "geometry": {"coordinates":[-9.34642,31.54322],"type":"Point"}
}