{
  "type": "Feature",
  "properties": {
    "gn:admin1_code":"08",
    "gn:asciiname":"Amassine",
    "gn:country_code":"MA",
    "gn:dem":1897,
    "gn:feature_class":"P",
    "gn:feature_code":"PPL",
    "gn:name":"Amassine",
    "gn:population":0,
    "gn:timezone":"Africa/Casablanca",
    "iso:country":"MA",
    "wof:name":"Amassine",
    "wof:placetype":"locality"
},
  "geometry": {"coordinates":[-7.18233,31.2879],"type":"Point"}
}