{
  "type": "Feature",
  "properties": {
    "gn:admin1_code":"01",
    "gn:asciiname":"Ba Hamed",
    "gn:country_code":"MA",
    "gn:dem":1289,
    "gn:feature_class":"P",
    "gn:feature_code":"PPL",
    "gn:name":"Ba Hamed",
    "gn:population":0,
    "gn:timezone":"Africa/Casablanca",
    "iso:country":"MA",
    "name:und_x_variant":[
        "Tachka",
        "Ba Hamed"
    ],
    "wof:name":"Ba Hamed",
    "wof:placetype":"locality"
},
  "geometry": {"coordinates":[-4.93662,35.04474],"type":"Point"}
}