{
  "type": "Feature",
  "properties": {
    "gn:admin1_code":"7.0",
    "gn:asciiname":"Douar Dar Amar",
    "gn:country_code":"MA",
    "gn:dem":359,
    "gn:feature_class":"P",
    "gn:feature_code":"PPL",
    "gn:name":"Douar Dar Amar",
    "gn:population":0,
    "gn:timezone":"Africa/Casablanca",
    "iso:country":"MA",
    "wof:name":"Douar Dar Amar",
    "wof:placetype":"locality"
},
  "geometry": {"coordinates":[-8.39404,31.64068],"type":"Point"}
}