{
  "type": "Feature",
  "properties": {
    "gn:admin1_code":"6.0",
    "gn:asciiname":"Douar Blidiyine",
    "gn:country_code":"MA",
    "gn:dem":399,
    "gn:feature_class":"P",
    "gn:feature_code":"PPL",
    "gn:name":"Douar Blidiyine",
    "gn:population":0,
    "gn:timezone":"Africa/Casablanca",
    "iso:country":"MA",
    "wof:name":"Douar Blidiyine",
    "wof:placetype":"locality"
},
  "geometry": {"coordinates":[-7.22575,33.22931],"type":"Point"}
}