{
  "type": "Feature",
  "properties": {
    "gn:admin1_code":"3.0",
    "gn:asciiname":"Douar Arrachal",
    "gn:country_code":"MA",
    "gn:dem":328,
    "gn:feature_class":"P",
    "gn:feature_code":"PPL",
    "gn:name":"Douar Arrachal",
    "gn:population":0,
    "gn:timezone":"Africa/Casablanca",
    "iso:country":"MA",
    "wof:name":"Douar Arrachal",
    "wof:placetype":"locality"
},
  "geometry": {"coordinates":[-4.60831,34.07247],"type":"Point"}
}