{
  "type": "Feature",
  "properties": {
    "gn:admin1_code":"7.0",
    "gn:asciiname":"Dar Bou Rouayne",
    "gn:country_code":"MA",
    "gn:dem":414,
    "gn:feature_class":"P",
    "gn:feature_code":"PPL",
    "gn:name":"Dar Bou Rouayne",
    "gn:population":0,
    "gn:timezone":"Africa/Casablanca",
    "iso:country":"MA",
    "wof:name":"Dar Bou Rouayne",
    "wof:placetype":"locality"
},
  "geometry": {"coordinates":[-7.79032,32.10451],"type":"Point"}
}