{
  "type": "Feature",
  "properties": {
    "gn:admin1_code":"07",
    "gn:asciiname":"El Aonafra",
    "gn:country_code":"MA",
    "gn:dem":543,
    "gn:feature_class":"P",
    "gn:feature_code":"PPL",
    "gn:name":"El Aonafra",
    "gn:population":0,
    "gn:timezone":"Africa/Casablanca",
    "iso:country":"MA",
    "name:und_x_variant":[
        "Dar Lanafra",
        "El Aanafra",
        "El Aonafra"
    ],
    "wof:name":"El Aonafra",
    "wof:placetype":"locality"
},
  "geometry": {"coordinates":[-8.75398,31.36115],"type":"Point"}
}