{
  "type": "Feature",
  "properties": {
    "gn:admin1_code":"1.0",
    "gn:asciiname":"Dar Abdelhaq Oueld Lagnaouiya",
    "gn:country_code":"MA",
    "gn:dem":55,
    "gn:feature_class":"P",
    "gn:feature_code":"PPL",
    "gn:name":"Dar Abdelhaq Oueld Lagnaouiya",
    "gn:population":0,
    "gn:timezone":"Africa/Casablanca",
    "iso:country":"MA",
    "wof:name":"Dar Abdelhaq Oueld Lagnaouiya",
    "wof:placetype":"locality"
},
  "geometry": {"coordinates":[-5.89619,35.04212],"type":"Point"}
}