{
  "type": "Feature",
  "properties": {
    "gn:admin1_code":"07",
    "gn:asciiname":"Douar Touggana",
    "gn:country_code":"MA",
    "gn:dem":416,
    "gn:feature_class":"P",
    "gn:feature_code":"PPL",
    "gn:name":"Douar Touggana",
    "gn:population":0,
    "gn:timezone":"Africa/Casablanca",
    "iso:country":"MA",
    "name:und_x_variant":[
        "Tou Goane",
        "Touggana",
        "Douar Touggana"
    ],
    "wof:name":"Douar Touggana",
    "wof:placetype":"locality"
},
  "geometry": {"coordinates":[-8.53956,32.03463],"type":"Point"}
}