{
  "type": "Feature",
  "properties": {
    "gn:admin1_code":"03",
    "gn:asciiname":"Imouzzer Kandar",
    "gn:country_code":"MA",
    "gn:dem":1352,
    "gn:feature_class":"P",
    "gn:feature_code":"PPL",
    "gn:name":"Imouzzer Kandar",
    "gn:population":0,
    "gn:timezone":"Africa/Casablanca",
    "iso:country":"MA",
    "name:ara_x_preferred":[
        "\u0625\u064a\u0645\u0648\u0632\u0627\u0631 \u0643\u0646\u062f\u0631"
    ],
    "name:cat_x_preferred":[
        "Imouzzer Kandar"
    ],
    "name:ceb_x_preferred":[
        "Imouzzer Kandar"
    ],
    "name:cym_x_preferred":[
        "Imouzzer Kandar"
    ],
    "name:fra_x_preferred":[
        "Imouzzer Kandar"
    ],
    "name:ita_x_preferred":[
        "Imouzzer Kandar"
    ],
    "name:por_x_preferred":[
        "Imouzzer Kandar"
    ],
    "name:swe_x_preferred":[
        "Imouzzer Kandar"
    ],
    "name:und_x_variant":[
        "Imouzzer du Kandar",
        "Imouzzer",
        "Immouzer"
    ],
    "wof:name":"Imouzzer Kandar",
    "wof:placetype":"locality"
},
  "geometry": {"coordinates":[-5.01092,33.72871],"type":"Point"}
}