{
  "type": "Feature",
  "properties": {
    "gn:admin1_code":"03",
    "gn:asciiname":"Imouzzer Kandar",
    "gn:country_code":"MA",
    "gn:dem":1352,
    "gn:feature_class":"P",
    "gn:feature_code":"PPL",
    "gn:name":"Imouzzer Kandar",
    "gn:population":0,
    "gn:timezone":"Africa/Casablanca",
    "iso:country":"MA",
    "name:und_x_variant":[
        "Imouzzer du Kandar",
        "Imouzzer",
        "Immouzer",
        "Imouzzer Kandar"
    ],
    "wof:name":"Imouzzer Kandar",
    "wof:placetype":"locality"
},
  "geometry": {"coordinates":[-5.01092,33.72871],"type":"Point"}
}