{
  "type": "Feature",
  "properties": {
    "gn:admin1_code":"9.0",
    "gn:asciiname":"Ait Warhmane",
    "gn:country_code":"MA",
    "gn:dem":1095,
    "gn:feature_class":"P",
    "gn:feature_code":"PPL",
    "gn:name":"A\u00eft Warhmane",
    "gn:population":0,
    "gn:timezone":"Africa/Casablanca",
    "iso:country":"MA",
    "wof:name":"Ait Warhmane",
    "wof:placetype":"locality"
},
  "geometry": {"coordinates":[-9.21119,29.57862],"type":"Point"}
}