{
  "type": "Feature",
  "properties": {
    "gn:admin1_code":"07",
    "gn:asciiname":"Douar Oulad Bella",
    "gn:country_code":"MA",
    "gn:dem":396,
    "gn:feature_class":"P",
    "gn:feature_code":"PPL",
    "gn:name":"Douar Oulad Bella",
    "gn:population":0,
    "gn:timezone":"Africa/Casablanca",
    "iso:country":"MA",
    "name:und_x_variant":[
        "Oulad Bella",
        "Douar Oulad Bella"
    ],
    "wof:name":"Douar Oulad Bella",
    "wof:placetype":"locality"
},
  "geometry": {"coordinates":[-8.57201,32.00517],"type":"Point"}
}