{
  "type": "Feature",
  "properties": {
    "gn:admin1_code":"5.0",
    "gn:asciiname":"Dad'a",
    "gn:country_code":"MA",
    "gn:dem":412,
    "gn:feature_class":"P",
    "gn:feature_code":"PPLL",
    "gn:name":"Dad\u2019a",
    "gn:population":0,
    "gn:timezone":"Africa/Casablanca",
    "iso:country":"MA",
    "wof:name":"Dad'a",
    "wof:placetype":"locality"
},
  "geometry": {"coordinates":[-6.67928,32.39193],"type":"Point"}
}