{
  "type": "Feature",
  "properties": {
    "gn:admin1_code":"05",
    "gn:asciiname":"Bou Idaki",
    "gn:country_code":"MA",
    "gn:dem":795,
    "gn:feature_class":"P",
    "gn:feature_code":"PPL",
    "gn:name":"Bou Idaki",
    "gn:population":0,
    "gn:timezone":"Africa/Casablanca",
    "iso:country":"MA",
    "name:und_x_variant":[
        "Bou Idki"
    ],
    "wof:name":"Bou Idaki",
    "wof:placetype":"locality"
},
  "geometry": {"coordinates":[-5.96889,32.86677],"type":"Point"}
}