{
  "type": "Feature",
  "properties": {
    "gn:admin1_code":"10",
    "gn:asciiname":"Tiderguit",
    "gn:country_code":"MA",
    "gn:dem":210,
    "gn:elevation":"0.0",
    "gn:feature_class":"P",
    "gn:feature_code":"PPL",
    "gn:name":"Tiderguit",
    "gn:population":0,
    "gn:timezone":"Africa/Casablanca",
    "iso:country":"MA",
    "name:und_x_variant":[
        "Tidergit",
        "Tiderguit"
    ],
    "wof:name":"Tiderguit",
    "wof:placetype":"locality"
},
  "geometry": {"coordinates":[-10.7936,28.55555],"type":"Point"}
}