{
  "type": "Feature",
  "properties": {
    "gn:admin1_code":"5.0",
    "gn:asciiname":"Er Rfija",
    "gn:country_code":"MA",
    "gn:dem":926,
    "gn:feature_class":"P",
    "gn:feature_code":"PPL",
    "gn:name":"Er Rfija",
    "gn:population":0,
    "gn:timezone":"Africa/Casablanca",
    "iso:country":"MA",
    "wof:name":"Er Rfija",
    "wof:placetype":"locality"
},
  "geometry": {"coordinates":[-5.71199,32.93057],"type":"Point"}
}