{
  "type": "Feature",
  "properties": {
    "gn:admin1_code":"09",
    "gn:asciiname":"Ait Messaoud",
    "gn:country_code":"MA",
    "gn:dem":650,
    "gn:feature_class":"P",
    "gn:feature_code":"PPL",
    "gn:name":"A\u00eft Messaoud",
    "gn:population":0,
    "gn:timezone":"Africa/Casablanca",
    "iso:country":"MA",
    "wof:name":"Ait Messaoud",
    "wof:placetype":"locality"
},
  "geometry": {"coordinates":[-8.2099,30.68769],"type":"Point"}
}