{
  "type": "Feature",
  "properties": {
    "gn:admin1_code":"7.0",
    "gn:asciiname":"Dar Sana",
    "gn:country_code":"MA",
    "gn:dem":222,
    "gn:feature_class":"P",
    "gn:feature_code":"PPL",
    "gn:name":"Dar Sana",
    "gn:population":0,
    "gn:timezone":"Africa/Casablanca",
    "iso:country":"MA",
    "wof:name":"Dar Sana",
    "wof:placetype":"locality"
},
  "geometry": {"coordinates":[-9.73049,31.11666],"type":"Point"}
}