{
  "type": "Feature",
  "properties": {
    "gn:admin1_code":"09",
    "gn:asciiname":"Awzart",
    "gn:country_code":"MA",
    "gn:dem":1119,
    "gn:feature_class":"P",
    "gn:feature_code":"PPL",
    "gn:name":"Awzart",
    "gn:population":0,
    "gn:timezone":"Africa/Casablanca",
    "iso:country":"MA",
    "name:und_x_variant":[
        "Touzart",
        "Aouzert",
        "Aouzart"
    ],
    "wof:name":"Awzart",
    "wof:placetype":"locality"
},
  "geometry": {"coordinates":[-9.1162,29.56835],"type":"Point"}
}