{
  "type": "Feature",
  "properties": {
    "gn:admin1_code":"3.0",
    "gn:asciiname":"Douar Leghouiba",
    "gn:country_code":"MA",
    "gn:dem":322,
    "gn:feature_class":"P",
    "gn:feature_code":"PPL",
    "gn:name":"Douar Leghouiba",
    "gn:population":0,
    "gn:timezone":"Africa/Casablanca",
    "iso:country":"MA",
    "wof:name":"Douar Leghouiba",
    "wof:placetype":"locality"
},
  "geometry": {"coordinates":[-5.13057,34.46225],"type":"Point"}
}