{
  "type": "Feature",
  "properties": {
    "gn:admin1_code":"3.0",
    "gn:asciiname":"Douar Lamhajja",
    "gn:country_code":"MA",
    "gn:dem":665,
    "gn:feature_class":"P",
    "gn:feature_code":"PPL",
    "gn:name":"Douar Lamhajja",
    "gn:population":0,
    "gn:timezone":"Africa/Casablanca",
    "iso:country":"MA",
    "wof:name":"Douar Lamhajja",
    "wof:placetype":"locality"
},
  "geometry": {"coordinates":[-4.27182,34.09070999999999],"type":"Point"}
}