{
  "type": "Feature",
  "properties": {
    "gn:admin1_code":"09",
    "gn:asciiname":"Assaka",
    "gn:country_code":"MA",
    "gn:dem":938,
    "gn:feature_class":"P",
    "gn:feature_code":"PPL",
    "gn:name":"Assaka",
    "gn:population":0,
    "gn:timezone":"Africa/Casablanca",
    "iso:country":"MA",
    "wof:name":"Assaka",
    "wof:placetype":"locality"
},
  "geometry": {"coordinates":[-6.71541,30.35726],"type":"Point"}
}