{
  "type": "Feature",
  "properties": {
    "gn:admin1_code":"7.0",
    "gn:asciiname":"Toughiyn",
    "gn:country_code":"MA",
    "gn:dem":1416,
    "gn:feature_class":"P",
    "gn:feature_code":"PPL",
    "gn:name":"Toughiyn",
    "gn:population":0,
    "gn:timezone":"Africa/Casablanca",
    "iso:country":"MA",
    "wof:name":"Toughiyn",
    "wof:placetype":"locality"
},
  "geometry": {"coordinates":[-7.32457,31.46574],"type":"Point"}
}