{
  "type": "Feature",
  "properties": {
    "gn:admin1_code":"09",
    "gn:asciiname":"Aid Said",
    "gn:country_code":"MA",
    "gn:dem":963,
    "gn:feature_class":"P",
    "gn:feature_code":"PPL",
    "gn:name":"A\u00efd Sa\u00efd",
    "gn:population":0,
    "gn:timezone":"Africa/Casablanca",
    "iso:country":"MA",
    "name:und_x_variant":[
        "A\u00efd Sa\u00efd",
        "A\u00eft Sa\u00efd"
    ],
    "wof:name":"Aid Said",
    "wof:placetype":"locality"
},
  "geometry": {"coordinates":[-8.77224,30.65925],"type":"Point"}
}