{
  "type": "Feature",
  "properties": {
    "gn:admin1_code":"09",
    "gn:asciiname":"Fiirhil",
    "gn:country_code":"MA",
    "gn:dem":1143,
    "gn:feature_class":"P",
    "gn:feature_code":"PPL",
    "gn:name":"Fiirhil",
    "gn:population":0,
    "gn:timezone":"Africa/Casablanca",
    "iso:country":"MA",
    "name:und_x_variant":[
        "Fighil",
        "Firhil",
        "Fiirhil"
    ],
    "wof:name":"Fiirhil",
    "wof:placetype":"locality"
},
  "geometry": {"coordinates":[-8.83902,29.52366],"type":"Point"}
}