{
  "type": "Feature",
  "properties": {
    "gn:admin1_code":"1.0",
    "gn:asciiname":"Douar Lakhouabi",
    "gn:country_code":"MA",
    "gn:dem":621,
    "gn:feature_class":"P",
    "gn:feature_code":"PPL",
    "gn:name":"Douar Lakhouabi",
    "gn:population":0,
    "gn:timezone":"Africa/Casablanca",
    "iso:country":"MA",
    "wof:name":"Douar Lakhouabi",
    "wof:placetype":"locality"
},
  "geometry": {"coordinates":[-4.99289,35.24265],"type":"Point"}
}