{
  "type": "Feature",
  "properties": {
    "gn:admin1_code":"01",
    "gn:asciiname":"Douar Azaghar",
    "gn:country_code":"MA",
    "gn:dem":873,
    "gn:feature_class":"P",
    "gn:feature_code":"PPL",
    "gn:name":"Douar Azaghar",
    "gn:population":0,
    "gn:timezone":"Africa/Casablanca",
    "iso:country":"MA",
    "name:und_x_variant":[
        "Azghare",
        "Azagar",
        "Douar Azaghar"
    ],
    "wof:name":"Douar Azaghar",
    "wof:placetype":"locality"
},
  "geometry": {"coordinates":[-4.89019,35.14248],"type":"Point"}
}