{
  "type": "Feature",
  "properties": {
    "gn:admin1_code":"10.0",
    "gn:asciiname":"Oubayrouk",
    "gn:country_code":"MA",
    "gn:dem":288,
    "gn:feature_class":"P",
    "gn:feature_code":"PPL",
    "gn:name":"Oubayrouk",
    "gn:population":0,
    "gn:timezone":"Africa/Casablanca",
    "iso:country":"MA",
    "wof:name":"Oubayrouk",
    "wof:placetype":"locality"
},
  "geometry": {"coordinates":[-9.98605,29.47641],"type":"Point"}
}