{
  "type": "Feature",
  "properties": {
    "gn:admin1_code":"01",
    "gn:asciiname":"Douar Tassift",
    "gn:country_code":"MA",
    "gn:dem":59,
    "gn:feature_class":"P",
    "gn:feature_code":"PPL",
    "gn:name":"Douar Tassift",
    "gn:population":0,
    "gn:timezone":"Africa/Casablanca",
    "iso:country":"MA",
    "name:ara_x_preferred":[
        "\u062a\u0627\u0633\u064a\u0641\u062a"
    ],
    "name:cat_x_preferred":[
        "Tassift"
    ],
    "name:ceb_x_preferred":[
        "Tassift"
    ],
    "name:ita_x_preferred":[
        "Tassift"
    ],
    "name:swe_x_preferred":[
        "Tassift"
    ],
    "name:und_x_variant":[
        "Douar Tassift"
    ],
    "name:urd_x_preferred":[
        "\u062a\u0627\u0633\u06cc\u0641\u062a"
    ],
    "wof:name":"Douar Tassift",
    "wof:placetype":"locality"
},
  "geometry": {"coordinates":[-5.22553,35.51002000000001],"type":"Point"}
}