{
  "type": "Feature",
  "properties": {
    "gn:admin1_code":"01",
    "gn:asciiname":"Douar Tassift",
    "gn:country_code":"MA",
    "gn:dem":59,
    "gn:feature_class":"P",
    "gn:feature_code":"PPL",
    "gn:name":"Douar Tassift",
    "gn:population":0,
    "gn:timezone":"Africa/Casablanca",
    "iso:country":"MA",
    "name:und_x_variant":[
        "Tassift",
        "Douar Tassift"
    ],
    "wof:name":"Douar Tassift",
    "wof:placetype":"locality"
},
  "geometry": {"coordinates":[-5.22553,35.51002000000001],"type":"Point"}
}