{
  "type": "Feature",
  "properties": {
    "gn:admin1_code":"4.0",
    "gn:asciiname":"Lqitna",
    "gn:country_code":"MA",
    "gn:dem":15,
    "gn:feature_class":"P",
    "gn:feature_code":"PPL",
    "gn:name":"Lqitna",
    "gn:population":0,
    "gn:timezone":"Africa/Casablanca",
    "iso:country":"MA",
    "wof:name":"Lqitna",
    "wof:placetype":"locality"
},
  "geometry": {"coordinates":[-6.04126,34.60563],"type":"Point"}
}