{
  "type": "Feature",
  "properties": {
    "gn:admin1_code":"1.0",
    "gn:asciiname":"Ighlitene",
    "gn:country_code":"MA",
    "gn:dem":1209,
    "gn:feature_class":"P",
    "gn:feature_code":"PPL",
    "gn:name":"Ighlitene",
    "gn:population":0,
    "gn:timezone":"Africa/Casablanca",
    "iso:country":"MA",
    "wof:name":"Ighlitene",
    "wof:placetype":"locality"
},
  "geometry": {"coordinates":[-5.10636,35.09876],"type":"Point"}
}