{
  "type": "Feature",
  "properties": {
    "gn:country":"MA",
    "gn:fcode":"ADM3",
    "gn:population":1089,
    "iso:country":"MA",
    "name:ara_x_preferred":[
        "\u062f\u0648\u0631\u0629"
    ],
    "name:fra_x_preferred":[
        "Elhagounia"
    ],
    "name:fra_x_variant":[
        "Elhagounia (CR)",
        "Elhagounia (Commune Rurale)"
    ],
    "qs:name":"Elhagounia",
    "qs:photos_9r":0,
    "qs:photos_sr":0,
    "qs:pop_sr":"3",
    "wof:name":"Elhagounia",
    "wof:placetype":"localadmin",
    "wof:population":1089
},
  "geometry": {"coordinates":[-12.30246,27.29105],"type":"Point"}
}