{
  "type": "Feature",
  "properties": {
    "gn:admin1_code":"09",
    "gn:asciiname":"Talat Mmous",
    "gn:country_code":"MA",
    "gn:dem":1351,
    "gn:feature_class":"P",
    "gn:feature_code":"PPL",
    "gn:name":"Talat Mmous",
    "gn:population":0,
    "gn:timezone":"Africa/Casablanca",
    "iso:country":"MA",
    "name:und_x_variant":[
        "Talat Mousse"
    ],
    "wof:name":"Talat Mmous",
    "wof:placetype":"locality"
},
  "geometry": {"coordinates":[-8.95956,29.95211],"type":"Point"}
}