{
  "type": "Feature",
  "properties": {
    "gn:admin1_code":"4.0",
    "gn:asciiname":"Ait Bou Ikhaouene",
    "gn:country_code":"MA",
    "gn:dem":432,
    "gn:feature_class":"P",
    "gn:feature_code":"PPL",
    "gn:name":"Ait Bou Ikhaouene",
    "gn:population":0,
    "gn:timezone":"Africa/Casablanca",
    "iso:country":"MA",
    "wof:name":"Ait Bou Ikhaouene",
    "wof:placetype":"locality"
},
  "geometry": {"coordinates":[-6.14438,33.64894],"type":"Point"}
}