{
  "type": "Feature",
  "properties": {
    "gn:admin1_code":"2.0",
    "gn:asciiname":"Douar Iabdellatene",
    "gn:country_code":"MA",
    "gn:dem":582,
    "gn:feature_class":"P",
    "gn:feature_code":"PPL",
    "gn:name":"Douar Iabdellatene",
    "gn:population":0,
    "gn:timezone":"Africa/Casablanca",
    "iso:country":"MA",
    "wof:name":"Douar Iabdellatene",
    "wof:placetype":"locality"
},
  "geometry": {"coordinates":[-3.70541,35.06641],"type":"Point"}
}