{
  "type": "Feature",
  "properties": {
    "gn:admin1_code":"1.0",
    "gn:asciiname":"Tazrout",
    "gn:country_code":"MA",
    "gn:dem":9,
    "gn:feature_class":"P",
    "gn:feature_code":"PPL",
    "gn:name":"Tazrout",
    "gn:population":0,
    "gn:timezone":"Africa/Casablanca",
    "iso:country":"MA",
    "wof:name":"Tazrout",
    "wof:placetype":"locality"
},
  "geometry": {"coordinates":[-5.32297,35.5643],"type":"Point"}
}