{
  "type": "Feature",
  "properties": {
    "gn:admin1_code":"05",
    "gn:asciiname":"Mellah",
    "gn:country_code":"MA",
    "gn:dem":736,
    "gn:elevation":"0.0",
    "gn:feature_class":"P",
    "gn:feature_code":"PPL",
    "gn:name":"Mellah",
    "gn:population":0,
    "gn:timezone":"Africa/Casablanca",
    "iso:country":"MA",
    "wof:name":"Mellah",
    "wof:placetype":"locality"
},
  "geometry": {"coordinates":[-6.80925,31.99461],"type":"Point"}
}