{
  "type": "Feature",
  "properties": {
    "gn:admin1_code":"05",
    "gn:asciiname":"Mellah",
    "gn:country_code":"MA",
    "gn:dem":736,
    "gn:elevation":"0.0",
    "gn:feature_class":"P",
    "gn:feature_code":"PPL",
    "gn:name":"Mellah",
    "gn:population":0,
    "gn:timezone":"Africa/Casablanca",
    "iso:country":"MA",
    "name:ara_x_preferred":[
        "\u0627\u0644\u0645\u0644\u0627\u062d"
    ],
    "name:cat_x_preferred":[
        "Mallah"
    ],
    "name:deu_x_preferred":[
        "Mellah"
    ],
    "name:est_x_preferred":[
        "Mellah"
    ],
    "name:fin_x_preferred":[
        "Mellah"
    ],
    "name:fra_x_preferred":[
        "Mellah"
    ],
    "name:heb_x_preferred":[
        "\u05de\u05dc\u05d0\u05d7"
    ],
    "name:ind_x_preferred":[
        "Mellah"
    ],
    "name:ita_x_preferred":[
        "Mellah"
    ],
    "name:por_x_preferred":[
        "Mellah"
    ],
    "name:rus_x_preferred":[
        "\u041c\u0435\u043b\u043b\u0430"
    ],
    "name:spa_x_preferred":[
        "Mellah"
    ],
    "name:urd_x_preferred":[
        "\u0645\u0644\u0627\u062d"
    ],
    "name:wln_x_preferred":[
        "Mellah"
    ],
    "wof:name":"Mellah",
    "wof:placetype":"locality"
},
  "geometry": {"coordinates":[-6.80925,31.99461],"type":"Point"}
}