{
  "type": "Feature",
  "properties": {
    "gn:admin1_code":"2.0",
    "gn:asciiname":"Douar Imenouhene",
    "gn:country_code":"MA",
    "gn:dem":708,
    "gn:feature_class":"P",
    "gn:feature_code":"PPL",
    "gn:name":"Douar Imenouhene",
    "gn:population":0,
    "gn:timezone":"Africa/Casablanca",
    "iso:country":"MA",
    "wof:name":"Douar Imenouhene",
    "wof:placetype":"locality"
},
  "geometry": {"coordinates":[-3.6962,35.09024],"type":"Point"}
}