{
  "type": "Feature",
  "properties": {
    "gn:admin1_code":"09",
    "gn:asciiname":"Tiliwa",
    "gn:country_code":"MA",
    "gn:dem":1051,
    "gn:feature_class":"P",
    "gn:feature_code":"PPL",
    "gn:name":"Tiliwa",
    "gn:population":0,
    "gn:timezone":"Africa/Casablanca",
    "iso:country":"MA",
    "name:und_x_variant":[
        "Tiliona",
        "Tilioua",
        "Tiliwa"
    ],
    "wof:name":"Tiliwa",
    "wof:placetype":"locality"
},
  "geometry": {"coordinates":[-8.60919,30.33105],"type":"Point"}
}