{
  "type": "Feature",
  "properties": {
    "gn:admin1_code":"7.0",
    "gn:asciiname":"Douar Naimiyine",
    "gn:country_code":"MA",
    "gn:dem":140,
    "gn:feature_class":"P",
    "gn:feature_code":"PPL",
    "gn:name":"Douar Naimiyine",
    "gn:population":0,
    "gn:timezone":"Africa/Casablanca",
    "iso:country":"MA",
    "wof:name":"Douar Naimiyine",
    "wof:placetype":"locality"
},
  "geometry": {"coordinates":[-9.22034,32.16118],"type":"Point"}
}