{
  "type": "Feature",
  "properties": {
    "gn:admin1_code":"07",
    "gn:asciiname":"Zriba",
    "gn:country_code":"MA",
    "gn:dem":217,
    "gn:feature_class":"P",
    "gn:feature_code":"PPL",
    "gn:name":"Zriba",
    "gn:population":0,
    "gn:timezone":"Africa/Casablanca",
    "iso:country":"MA",
    "name:ara_x_preferred":[
        "\u0627\u0644\u0632\u0631\u064a\u0628\u0629"
    ],
    "name:cat_x_preferred":[
        "Zriba"
    ],
    "name:ceb_x_preferred":[
        "Zriba-Village"
    ],
    "name:fra_x_preferred":[
        "Zriba"
    ],
    "name:sco_x_preferred":[
        "Zriba"
    ],
    "name:spa_x_preferred":[
        "Zriba"
    ],
    "name:ukr_x_preferred":[
        "\u0417\u0440\u0456\u0431\u0430"
    ],
    "name:und_x_variant":[
        "Douar Azrib",
        "Zriba"
    ],
    "wof:name":"Zriba",
    "wof:placetype":"locality"
},
  "geometry": {"coordinates":[-9.51,31.66],"type":"Point"}
}