{
  "type": "Feature",
  "properties": {
    "gn:admin1_code":"01",
    "gn:asciiname":"Douar Izouljam",
    "gn:country_code":"MA",
    "gn:dem":1196,
    "gn:feature_class":"P",
    "gn:feature_code":"PPL",
    "gn:name":"Douar Izouljam",
    "gn:population":0,
    "gn:timezone":"Africa/Casablanca",
    "iso:country":"MA",
    "name:und_x_variant":[
        "Isulgan",
        "Isoulgane",
        "Douar Izouljam"
    ],
    "wof:name":"Douar Izouljam",
    "wof:placetype":"locality"
},
  "geometry": {"coordinates":[-5.00483,35.04928],"type":"Point"}
}