{
  "type": "Feature",
  "properties": {
    "gn:admin1_code":"5.0",
    "gn:asciiname":"Ait Boulmane",
    "gn:country_code":"MA",
    "gn:dem":1074,
    "gn:feature_class":"P",
    "gn:feature_code":"PPL",
    "gn:name":"A\u00eft Boulmane",
    "gn:population":0,
    "gn:timezone":"Africa/Casablanca",
    "iso:country":"MA",
    "wof:name":"Ait Boulmane",
    "wof:placetype":"locality"
},
  "geometry": {"coordinates":[-6.78076,31.73442],"type":"Point"}
}