{
  "type": "Feature",
  "properties": {
    "gn:admin1_code":"7.0",
    "gn:asciiname":"Senais",
    "gn:country_code":"MA",
    "gn:dem":1339,
    "gn:feature_class":"P",
    "gn:feature_code":"PPL",
    "gn:name":"S\u00e9na\u00efs",
    "gn:population":0,
    "gn:timezone":"Africa/Casablanca",
    "iso:country":"MA",
    "wof:name":"Senais",
    "wof:placetype":"locality"
},
  "geometry": {"coordinates":[-9.16043,31.04335],"type":"Point"}
}