{
  "type": "Feature",
  "properties": {
    "gn:admin1_code":"08",
    "gn:asciiname":"Ajmou n'Ait Ali Ou Hasso",
    "gn:country_code":"MA",
    "gn:dem":771,
    "gn:feature_class":"P",
    "gn:feature_code":"PPL",
    "gn:name":"Ajmou n\u2019A\u00eft Ali Ou Hasso",
    "gn:population":0,
    "gn:timezone":"Africa/Casablanca",
    "iso:country":"MA",
    "name:und_x_variant":[
        "A\u00eft Ali Ou Hassoua",
        "Ajmou",
        "Ajmou n\u2019A\u00eft Ali Ou Hasso"
    ],
    "wof:name":"Ajmou n'Ait Ali Ou Hasso",
    "wof:placetype":"locality"
},
  "geometry": {"coordinates":[-5.42586,30.6094],"type":"Point"}
}