{
  "type": "Feature",
  "properties": {
    "gn:country":"MA",
    "gn:fcode":"ADM3",
    "gn:population":5673,
    "iso:country":"MA",
    "name:ara_x_preferred":[
        "\u0627\u0645\u0633\u0643\u0631\u0648\u0636"
    ],
    "name:ara_x_variant":[
        "\u0623\u0648\u0631\u064a\u0631"
    ],
    "name:cat_x_preferred":[
        "Aourir"
    ],
    "name:ceb_x_preferred":[
        "Aourir"
    ],
    "name:eus_x_preferred":[
        "Aourir"
    ],
    "name:fra_x_preferred":[
        "Aourir"
    ],
    "name:fra_x_variant":[
        "Aourir (CR)",
        "Aourir (Commune Rurale)"
    ],
    "name:ita_x_preferred":[
        "Aourir"
    ],
    "name:pol_x_preferred":[
        "Aurir"
    ],
    "name:por_x_preferred":[
        "Aourir"
    ],
    "name:swe_x_preferred":[
        "Aourir"
    ],
    "qs_pg:aaroncc":"MA",
    "qs_pg:gn_country":"MA",
    "qs_pg:gn_fcode":"ADM3",
    "qs_pg:gn_pop":5673,
    "qs_pg:name":"Aourir",
    "qs_pg:photos_9r":0,
    "qs_pg:photos_sr":0,
    "qs_pg:pop_sr":5,
    "qs_pg:qs_pg_placetype":"localadmin",
    "wof:name":"Aourir",
    "wof:placetype":"localadmin",
    "wof:population":5673
},
  "geometry": {"coordinates":[-9.61163,30.52521],"type":"Point"}
}