{
  "type": "Feature",
  "properties": {
    "gn:admin1_code":"7.0",
    "gn:asciiname":"Id Ziou",
    "gn:country_code":"MA",
    "gn:dem":338,
    "gn:feature_class":"P",
    "gn:feature_code":"PPL",
    "gn:name":"Id Ziou",
    "gn:population":0,
    "gn:timezone":"Africa/Casablanca",
    "iso:country":"MA",
    "wof:name":"Id Ziou",
    "wof:placetype":"locality"
},
  "geometry": {"coordinates":[-9.68552,31.05221],"type":"Point"}
}