{
  "type": "Feature",
  "properties": {
    "gn:admin1_code":"05",
    "gn:asciiname":"Timi N'Outine",
    "gn:country_code":"MA",
    "gn:dem":857,
    "gn:feature_class":"P",
    "gn:feature_code":"PPL",
    "gn:name":"Timi N\u2019Outine",
    "gn:population":0,
    "gn:timezone":"Africa/Casablanca",
    "iso:country":"MA",
    "name:und_x_variant":[
        "Timin-n-Outine",
        "Timi N\u2019Outine"
    ],
    "wof:name":"Timi N'Outine",
    "wof:placetype":"locality"
},
  "geometry": {"coordinates":[-7.26366,31.65111],"type":"Point"}
}