{
  "type": "Feature",
  "properties": {
    "gn:admin1_code":"3.0",
    "gn:asciiname":"Douar Oulad Yaaqoub",
    "gn:country_code":"MA",
    "gn:dem":903,
    "gn:feature_class":"P",
    "gn:feature_code":"PPL",
    "gn:name":"Douar Oulad Yaaqoub",
    "gn:population":0,
    "gn:timezone":"Africa/Casablanca",
    "iso:country":"MA",
    "wof:name":"Douar Oulad Yaaqoub",
    "wof:placetype":"locality"
},
  "geometry": {"coordinates":[-4.3227,34.34727],"type":"Point"}
}