{
  "type": "Feature",
  "properties": {
    "gn:admin1_code":"10",
    "gn:asciiname":"Igourramene",
    "gn:country_code":"MA",
    "gn:dem":1174,
    "gn:feature_class":"P",
    "gn:feature_code":"PPL",
    "gn:name":"Igourramene",
    "gn:population":0,
    "gn:timezone":"Africa/Casablanca",
    "iso:country":"MA",
    "name:und_x_variant":[
        "Igourramen",
        "Igourramene"
    ],
    "wof:name":"Igourramene",
    "wof:placetype":"locality"
},
  "geometry": {"coordinates":[-9.59175,29.30375],"type":"Point"}
}