{
  "type": "Feature",
  "properties": {
    "gn:admin1_code":"07",
    "gn:asciiname":"Douar Oulad Jouabra",
    "gn:country_code":"MA",
    "gn:dem":162,
    "gn:feature_class":"P",
    "gn:feature_code":"PPL",
    "gn:name":"Douar Oulad Jouabra",
    "gn:population":0,
    "gn:timezone":"Africa/Casablanca",
    "iso:country":"MA",
    "name:und_x_variant":[
        "Jouagra"
    ],
    "wof:name":"Douar Oulad Jouabra",
    "wof:placetype":"locality"
},
  "geometry": {"coordinates":[-8.89771,32.26291],"type":"Point"}
}