{
  "type": "Feature",
  "properties": {
    "gn:admin1_code":"04",
    "gn:asciiname":"Douar Echyabna",
    "gn:country_code":"MA",
    "gn:dem":132,
    "gn:feature_class":"P",
    "gn:feature_code":"PPL",
    "gn:name":"Douar Echyabna",
    "gn:population":0,
    "gn:timezone":"Africa/Casablanca",
    "iso:country":"MA",
    "name:und_x_variant":[
        "Douar Chiabna",
        "Chiabna",
        "Douar Echyabna"
    ],
    "wof:name":"Douar Echyabna",
    "wof:placetype":"locality"
},
  "geometry": {"coordinates":[-5.90515,34.90575],"type":"Point"}
}