{
  "type": "Feature",
  "properties": {
    "gn:admin1_code":"03",
    "gn:asciiname":"Douar Ain Gouza",
    "gn:country_code":"MA",
    "gn:dem":964,
    "gn:feature_class":"P",
    "gn:feature_code":"PPL",
    "gn:name":"Douar A\u00efn Gouza",
    "gn:population":0,
    "gn:timezone":"Africa/Casablanca",
    "iso:country":"MA",
    "name:und_x_variant":[
        "Douar A\u00efn Gouza",
        "A\u00efn Gouza"
    ],
    "wof:name":"Douar Ain Gouza",
    "wof:placetype":"locality"
},
  "geometry": {"coordinates":[-4.20778,34.36253],"type":"Point"}
}