{
  "type": "Feature",
  "properties": {
    "gn:admin1_code":"03",
    "gn:asciiname":"Ait S'aid",
    "gn:country_code":"MA",
    "gn:dem":1763,
    "gn:feature_class":"P",
    "gn:feature_code":"PPL",
    "gn:name":"A\u00eft S\u2019aid",
    "gn:population":0,
    "gn:timezone":"Africa/Casablanca",
    "iso:country":"MA",
    "name:und_x_variant":[
        "A\u00eft S\u2019aid",
        "A\u00eft Sa\u00efd"
    ],
    "wof:name":"Ait S'aid",
    "wof:placetype":"locality"
},
  "geometry": {"coordinates":[-4.6695,33.24287],"type":"Point"}
}