{
  "type": "Feature",
  "properties": {
    "gn:admin1_code":"07",
    "gn:asciiname":"Douar Lemaizat",
    "gn:country_code":"MA",
    "gn:dem":157,
    "gn:feature_class":"P",
    "gn:feature_code":"PPL",
    "gn:name":"Douar Lemaizat",
    "gn:population":0,
    "gn:timezone":"Africa/Casablanca",
    "iso:country":"MA",
    "name:und_x_variant":[
        "El Mahizate"
    ],
    "wof:name":"Douar Lemaizat",
    "wof:placetype":"locality"
},
  "geometry": {"coordinates":[-9.06066,31.80922],"type":"Point"}
}