{
  "type": "Feature",
  "properties": {
    "gn:admin1_code":"6.0",
    "gn:asciiname":"Khefanncha",
    "gn:country_code":"MA",
    "gn:dem":269,
    "gn:feature_class":"P",
    "gn:feature_code":"PPL",
    "gn:name":"Khefanncha",
    "gn:population":0,
    "gn:timezone":"Africa/Casablanca",
    "iso:country":"MA",
    "wof:name":"Khefanncha",
    "wof:placetype":"locality"
},
  "geometry": {"coordinates":[-7.96173,32.93588],"type":"Point"}
}