{
  "type": "Feature",
  "properties": {
    "gn:admin1_code":"03",
    "gn:asciiname":"Tirnest",
    "gn:country_code":"MA",
    "gn:dem":1297,
    "gn:feature_class":"P",
    "gn:feature_code":"PPL",
    "gn:name":"Tirnest",
    "gn:population":0,
    "gn:timezone":"Africa/Casablanca",
    "iso:country":"MA",
    "wof:name":"Tirnest",
    "wof:placetype":"locality"
},
  "geometry": {"coordinates":[-3.8115,33.4876],"type":"Point"}
}