{
  "type": "Feature",
  "properties": {
    "gn:admin1_code":"07",
    "gn:asciiname":"Douar Alouarg",
    "gn:country_code":"MA",
    "gn:dem":1180,
    "gn:feature_class":"P",
    "gn:feature_code":"PPL",
    "gn:name":"Douar Alouarg",
    "gn:population":0,
    "gn:timezone":"Africa/Casablanca",
    "iso:country":"MA",
    "name:und_x_variant":[
        "Alouarg"
    ],
    "wof:name":"Douar Alouarg",
    "wof:placetype":"locality"
},
  "geometry": {"coordinates":[-8.02435,31.33096],"type":"Point"}
}