{
  "type": "Feature",
  "properties": {
    "gn:admin1_code":"7.0",
    "gn:asciiname":"Dyar",
    "gn:country_code":"MA",
    "gn:dem":431,
    "gn:feature_class":"P",
    "gn:feature_code":"PPL",
    "gn:name":"Dyar",
    "gn:population":0,
    "gn:timezone":"Africa/Casablanca",
    "iso:country":"MA",
    "wof:name":"Dyar",
    "wof:placetype":"locality"
},
  "geometry": {"coordinates":[-8.84387,31.99921],"type":"Point"}
}