{
  "type": "Feature",
  "properties": {
    "gn:admin1_code":"4.0",
    "gn:asciiname":"Ait Ben Abbou",
    "gn:country_code":"MA",
    "gn:dem":445,
    "gn:feature_class":"P",
    "gn:feature_code":"PPL",
    "gn:name":"Ait Ben Abbou",
    "gn:population":0,
    "gn:timezone":"Africa/Casablanca",
    "iso:country":"MA",
    "wof:name":"Ait Ben Abbou",
    "wof:placetype":"locality"
},
  "geometry": {"coordinates":[-6.10033,33.64642],"type":"Point"}
}