{
  "type": "Feature",
  "properties": {
    "gn:admin1_code":"01",
    "gn:asciiname":"Douar Amersane",
    "gn:country_code":"MA",
    "gn:dem":315,
    "gn:feature_class":"P",
    "gn:feature_code":"PPL",
    "gn:name":"Douar Amersane",
    "gn:population":0,
    "gn:timezone":"Africa/Casablanca",
    "iso:country":"MA",
    "name:und_x_variant":[
        "Amersane"
    ],
    "wof:name":"Douar Amersane",
    "wof:placetype":"locality"
},
  "geometry": {"coordinates":[-5.55036,35.61282],"type":"Point"}
}