{
  "type": "Feature",
  "properties": {
    "gn:admin1_code":"09",
    "gn:asciiname":"Ait Kassem",
    "gn:country_code":"MA",
    "gn:dem":194,
    "gn:feature_class":"P",
    "gn:feature_code":"PPL",
    "gn:name":"A\u00eft Kassem",
    "gn:population":0,
    "gn:timezone":"Africa/Casablanca",
    "iso:country":"MA",
    "name:und_x_variant":[
        "A\u00eft Kassem",
        "A\u00eft Kacem"
    ],
    "wof:name":"Ait Kassem",
    "wof:placetype":"locality"
},
  "geometry": {"coordinates":[-9.05258,30.30831],"type":"Point"}
}