{
  "type": "Feature",
  "properties": {
    "gn:admin1_code":"02",
    "gn:asciiname":"Iamourane",
    "gn:country_code":"MA",
    "gn:dem":47,
    "gn:feature_class":"P",
    "gn:feature_code":"PPL",
    "gn:name":"Iamourane",
    "gn:population":0,
    "gn:timezone":"Africa/Casablanca",
    "iso:country":"MA",
    "name:und_x_variant":[
        "Audain",
        "Aoudaine",
        "Ayadane",
        "Aouda\u00efn",
        "Iamourane"
    ],
    "wof:name":"Iamourane",
    "wof:placetype":"locality"
},
  "geometry": {"coordinates":[-3.16379,35.16721],"type":"Point"}
}