{
  "type": "Feature",
  "properties": {
    "gn:admin1_code":"6.0",
    "gn:asciiname":"Oulad Zekkak Ben Ahmed",
    "gn:country_code":"MA",
    "gn:dem":512,
    "gn:feature_class":"P",
    "gn:feature_code":"PPL",
    "gn:name":"Oulad Zekkak Ben Ahmed",
    "gn:population":0,
    "gn:timezone":"Africa/Casablanca",
    "iso:country":"MA",
    "wof:name":"Oulad Zekkak Ben Ahmed",
    "wof:placetype":"locality"
},
  "geometry": {"coordinates":[-7.52709,32.77958],"type":"Point"}
}