{
  "type": "Feature",
  "properties": {
    "gn:admin1_code":"08",
    "gn:asciiname":"Sountat",
    "gn:country_code":"MA",
    "gn:dem":2222,
    "gn:feature_class":"P",
    "gn:feature_code":"PPL",
    "gn:name":"Sountat",
    "gn:population":0,
    "gn:timezone":"Africa/Casablanca",
    "iso:country":"MA",
    "wof:name":"Sountat",
    "wof:placetype":"locality"
},
  "geometry": {"coordinates":[-5.55559,32.12286],"type":"Point"}
}