{
  "type": "Feature",
  "properties": {
    "gn:admin1_code":"08",
    "gn:asciiname":"Rbat",
    "gn:country_code":"MA",
    "gn:dem":945,
    "gn:feature_class":"P",
    "gn:feature_code":"PPL",
    "gn:name":"Rb\u00e2t",
    "gn:population":0,
    "gn:timezone":"Africa/Casablanca",
    "iso:country":"MA",
    "name:und_x_variant":[
        "Rb\u00e2t",
        "Rebat"
    ],
    "wof:name":"Rbat",
    "wof:placetype":"locality"
},
  "geometry": {"coordinates":[-6.44578,30.73812],"type":"Point"}
}