{
  "type": "Feature",
  "properties": {
    "gn:admin1_code":"08",
    "gn:asciiname":"Ayt Sfoul",
    "gn:country_code":"MA",
    "gn:dem":904,
    "gn:feature_class":"P",
    "gn:feature_code":"PPL",
    "gn:name":"Ayt Sfoul",
    "gn:population":0,
    "gn:timezone":"Africa/Casablanca",
    "iso:country":"MA",
    "name:und_x_variant":[
        "A\u00eft Sfo\u00fbl",
        "A\u00eft Isfoul",
        "Ayt Sfoul"
    ],
    "wof:name":"Ayt Sfoul",
    "wof:placetype":"locality"
},
  "geometry": {"coordinates":[-4.1874,31.69908],"type":"Point"}
}