{
  "type": "Feature",
  "properties": {
    "gn:admin1_code":"9.0",
    "gn:asciiname":"Anammar",
    "gn:country_code":"MA",
    "gn:dem":704,
    "gn:feature_class":"P",
    "gn:feature_code":"PPL",
    "gn:name":"Anammar",
    "gn:population":0,
    "gn:timezone":"Africa/Casablanca",
    "iso:country":"MA",
    "wof:name":"Anammar",
    "wof:placetype":"locality"
},
  "geometry": {"coordinates":[-8.26385,30.5529],"type":"Point"}
}