{
  "type": "Feature",
  "properties": {
    "gn:admin1_code":"09",
    "gn:asciiname":"Tinzourine",
    "gn:country_code":"MA",
    "gn:dem":1280,
    "gn:feature_class":"P",
    "gn:feature_code":"PPL",
    "gn:name":"Tinzourine",
    "gn:population":0,
    "gn:timezone":"Africa/Casablanca",
    "iso:country":"MA",
    "name:und_x_variant":[
        "Timzourine",
        "Tinzourine"
    ],
    "wof:name":"Tinzourine",
    "wof:placetype":"locality"
},
  "geometry": {"coordinates":[-8.19931,30.25847000000001],"type":"Point"}
}