{
  "type": "Feature",
  "properties": {
    "gn:admin1_code":"3.0",
    "gn:asciiname":"Douar Lehouafed",
    "gn:country_code":"MA",
    "gn:dem":94,
    "gn:feature_class":"P",
    "gn:feature_code":"PPL",
    "gn:name":"Douar Lehouafed",
    "gn:population":0,
    "gn:timezone":"Africa/Casablanca",
    "iso:country":"MA",
    "wof:name":"Douar Lehouafed",
    "wof:placetype":"locality"
},
  "geometry": {"coordinates":[-5.11887,34.28740999999999],"type":"Point"}
}