{
  "type": "Feature",
  "properties": {
    "gn:admin1_code":"07",
    "gn:asciiname":"Zaouit n'ou-Amane Meloulnine",
    "gn:country_code":"MA",
    "gn:dem":795,
    "gn:feature_class":"P",
    "gn:feature_code":"PPL",
    "gn:name":"Zaouit n\u2019ou-Amane Meloulnine",
    "gn:population":0,
    "gn:timezone":"Africa/Casablanca",
    "iso:country":"MA",
    "name:und_x_variant":[
        "Zaouit n\u2019ou-Amane Meloulnine",
        "Zaouia Amane Mellouline"
    ],
    "wof:name":"Zaouit n'ou-Amane Meloulnine",
    "wof:placetype":"locality"
},
  "geometry": {"coordinates":[-7.35774,31.67164],"type":"Point"}
}