{
  "type": "Feature",
  "properties": {
    "gn:admin1_code":"6.0",
    "gn:asciiname":"Legtaba",
    "gn:country_code":"MA",
    "gn:dem":208,
    "gn:feature_class":"P",
    "gn:feature_code":"PPL",
    "gn:name":"Legtaba",
    "gn:population":0,
    "gn:timezone":"Africa/Casablanca",
    "iso:country":"MA",
    "wof:name":"Legtaba",
    "wof:placetype":"locality"
},
  "geometry": {"coordinates":[-7.04086,33.70219],"type":"Point"}
}