{
  "type": "Feature",
  "properties": {
    "gn:admin1_code":"4.0",
    "gn:asciiname":"Qiyyada",
    "gn:country_code":"MA",
    "gn:dem":173,
    "gn:feature_class":"P",
    "gn:feature_code":"PPL",
    "gn:name":"Qiyyada",
    "gn:population":0,
    "gn:timezone":"Africa/Casablanca",
    "iso:country":"MA",
    "wof:name":"Qiyyada",
    "wof:placetype":"locality"
},
  "geometry": {"coordinates":[-6.78501,33.88105],"type":"Point"}
}