{
  "type": "Feature",
  "properties": {
    "gn:admin1_code":"05",
    "gn:asciiname":"Timddiwgha",
    "gn:country_code":"MA",
    "gn:dem":1169,
    "gn:elevation":"0.0",
    "gn:feature_class":"P",
    "gn:feature_code":"PPL",
    "gn:name":"Timddiwgha",
    "gn:population":0,
    "gn:timezone":"Africa/Casablanca",
    "iso:country":"MA",
    "name:und_x_variant":[
        "Timadouygha"
    ],
    "wof:name":"Timddiwgha",
    "wof:placetype":"locality"
},
  "geometry": {"coordinates":[-6.93741,31.73479],"type":"Point"}
}