{
  "type": "Feature",
  "properties": {
    "gn:admin1_code":"03",
    "gn:asciiname":"Douar Dhar Chayyab",
    "gn:country_code":"MA",
    "gn:dem":511,
    "gn:feature_class":"P",
    "gn:feature_code":"PPL",
    "gn:name":"Douar Dhar Chayyab",
    "gn:population":0,
    "gn:timezone":"Africa/Casablanca",
    "iso:country":"MA",
    "name:und_x_variant":[
        "Douar Dhar Chiyyab"
    ],
    "wof:name":"Douar Dhar Chayyab",
    "wof:placetype":"locality"
},
  "geometry": {"coordinates":[-4.6355,34.41455999999999],"type":"Point"}
}