{
  "type": "Feature",
  "properties": {
    "gn:admin1_code":"02",
    "gn:asciiname":"Hassi Touil",
    "gn:country_code":"MA",
    "gn:dem":266,
    "gn:feature_class":"P",
    "gn:feature_code":"PPL",
    "gn:name":"Hassi Touil",
    "gn:population":0,
    "gn:timezone":"Africa/Casablanca",
    "iso:country":"MA",
    "wof:name":"Hassi Touil",
    "wof:placetype":"locality"
},
  "geometry": {"coordinates":[-3.00882,34.9277],"type":"Point"}
}