{
  "type": "Feature",
  "properties": {
    "gn:admin1_code":"6.0",
    "gn:asciiname":"Lekrifat",
    "gn:country_code":"MA",
    "gn:dem":128,
    "gn:feature_class":"P",
    "gn:feature_code":"PPL",
    "gn:name":"Lekrifat",
    "gn:population":0,
    "gn:timezone":"Africa/Casablanca",
    "iso:country":"MA",
    "wof:name":"Lekrifat",
    "wof:placetype":"locality"
},
  "geometry": {"coordinates":[-8.19451,32.96231],"type":"Point"}
}