{
  "type": "Feature",
  "properties": {
    "gn:admin1_code":"7.0",
    "gn:asciiname":"Lhajra Lboda",
    "gn:country_code":"MA",
    "gn:dem":368,
    "gn:feature_class":"P",
    "gn:feature_code":"PPL",
    "gn:name":"Lhajra Lboda",
    "gn:population":0,
    "gn:timezone":"Africa/Casablanca",
    "iso:country":"MA",
    "wof:name":"Lhajra Lboda",
    "wof:placetype":"locality"
},
  "geometry": {"coordinates":[-8.81594,31.96658],"type":"Point"}
}