{
  "type": "Feature",
  "properties": {
    "gn:admin1_code":"2.0",
    "gn:asciiname":"Hay Oulad Ramdane",
    "gn:country_code":"MA",
    "gn:dem":514,
    "gn:feature_class":"P",
    "gn:feature_code":"PPL",
    "gn:name":"Hay Oulad Ramdane",
    "gn:population":0,
    "gn:timezone":"Africa/Casablanca",
    "iso:country":"MA",
    "wof:name":"Hay Oulad Ramdane",
    "wof:placetype":"locality"
},
  "geometry": {"coordinates":[-1.85936,34.70986],"type":"Point"}
}