{
  "type": "Feature",
  "properties": {
    "gn:admin1_code":"4.0",
    "gn:asciiname":"Laarjat",
    "gn:country_code":"MA",
    "gn:dem":130,
    "gn:feature_class":"P",
    "gn:feature_code":"PPL",
    "gn:name":"Laarjat",
    "gn:population":0,
    "gn:timezone":"Africa/Casablanca",
    "iso:country":"MA",
    "wof:name":"Laarjat",
    "wof:placetype":"locality"
},
  "geometry": {"coordinates":[-6.65192,34.02701],"type":"Point"}
}