{
  "type": "Feature",
  "properties": {
    "gn:admin1_code":"7.0",
    "gn:asciiname":"Douar El Kana",
    "gn:country_code":"MA",
    "gn:dem":459,
    "gn:feature_class":"P",
    "gn:feature_code":"PPL",
    "gn:name":"Douar El Kana",
    "gn:population":0,
    "gn:timezone":"Africa/Casablanca",
    "iso:country":"MA",
    "wof:name":"Douar El Kana",
    "wof:placetype":"locality"
},
  "geometry": {"coordinates":[-8.21111,32.31289],"type":"Point"}
}