{
  "type": "Feature",
  "properties": {
    "gn:admin1_code":"02",
    "gn:asciiname":"Douar Chehalfa Kouchet",
    "gn:country_code":"MA",
    "gn:dem":866,
    "gn:feature_class":"P",
    "gn:feature_code":"PPL",
    "gn:name":"Douar Chehalfa Kouchet",
    "gn:population":0,
    "gn:timezone":"Africa/Casablanca",
    "iso:country":"MA",
    "name:und_x_variant":[
        "Chahalta Kouchete",
        "Chehalfa Tkouchette",
        "Chahalta Kouchet",
        "Douar Chehalfa Kouchet"
    ],
    "wof:name":"Douar Chehalfa Kouchet",
    "wof:placetype":"locality"
},
  "geometry": {"coordinates":[-2.19136,34.80273],"type":"Point"}
}