{
  "type": "Feature",
  "properties": {
    "gn:admin1_code":"07",
    "gn:asciiname":"Frarha",
    "gn:country_code":"MA",
    "gn:dem":476,
    "gn:feature_class":"P",
    "gn:feature_code":"PPL",
    "gn:name":"Frarha",
    "gn:population":0,
    "gn:timezone":"Africa/Casablanca",
    "iso:country":"MA",
    "name:und_x_variant":[
        "Ferareha"
    ],
    "wof:name":"Frarha",
    "wof:placetype":"locality"
},
  "geometry": {"coordinates":[-8.02865,32.38892],"type":"Point"}
}