{
  "type": "Feature",
  "properties": {
    "gn:admin1_code":"9.0",
    "gn:asciiname":"Zaouia Sidi Dahmane",
    "gn:country_code":"MA",
    "gn:dem":279,
    "gn:feature_class":"P",
    "gn:feature_code":"PPL",
    "gn:name":"Zaouia Sidi Dahmane",
    "gn:population":0,
    "gn:timezone":"Africa/Casablanca",
    "iso:country":"MA",
    "wof:name":"Zaouia Sidi Dahmane",
    "wof:placetype":"locality"
},
  "geometry": {"coordinates":[-8.76109,30.51927],"type":"Point"}
}