{
  "type": "Feature",
  "properties": {
    "gn:admin1_code":"02",
    "gn:asciiname":"Ksar Megrane",
    "gn:country_code":"MA",
    "gn:dem":811,
    "gn:feature_class":"P",
    "gn:feature_code":"PPL",
    "gn:name":"Ksar Megrane",
    "gn:population":0,
    "gn:timezone":"Africa/Casablanca",
    "iso:country":"MA",
    "name:und_x_variant":[
        "Mayiane",
        "Megrane",
        "Ksar Megrane"
    ],
    "wof:name":"Ksar Megrane",
    "wof:placetype":"locality"
},
  "geometry": {"coordinates":[-3.11,31.93],"type":"Point"}
}