{
  "type": "Feature",
  "properties": {
    "gn:admin1_code":"05",
    "gn:asciiname":"Tarhia",
    "gn:country_code":"MA",
    "gn:dem":1866,
    "gn:elevation":"0.0",
    "gn:feature_class":"P",
    "gn:feature_code":"PPL",
    "gn:name":"Tarhia",
    "gn:population":0,
    "gn:timezone":"Africa/Casablanca",
    "iso:country":"MA",
    "name:und_x_variant":[
        "Taghria",
        "Tarhia"
    ],
    "wof:name":"Tarhia",
    "wof:placetype":"locality"
},
  "geometry": {"coordinates":[-6.62244,31.61953],"type":"Point"}
}