{
  "type": "Feature",
  "properties": {
    "gn:admin1_code":"9.0",
    "gn:asciiname":"Imouchchjoun",
    "gn:country_code":"MA",
    "gn:dem":378,
    "gn:feature_class":"P",
    "gn:feature_code":"PPL",
    "gn:name":"Imouchchjoun",
    "gn:population":0,
    "gn:timezone":"Africa/Casablanca",
    "iso:country":"MA",
    "wof:name":"Imouchchjoun",
    "wof:placetype":"locality"
},
  "geometry": {"coordinates":[-9.12822,30.15868],"type":"Point"}
}