{
  "type": "Feature",
  "properties": {
    "gn:admin1_code":"06",
    "gn:asciiname":"Laaroussine",
    "gn:country_code":"MA",
    "gn:dem":229,
    "gn:feature_class":"P",
    "gn:feature_code":"PPL",
    "gn:name":"Laaroussine",
    "gn:population":0,
    "gn:timezone":"Africa/Casablanca",
    "iso:country":"MA",
    "wof:name":"Laaroussine",
    "wof:placetype":"locality"
},
  "geometry": {"coordinates":[-7.98151,32.82968],"type":"Point"}
}