{
  "type": "Feature",
  "properties": {
    "gn:admin1_code":"01",
    "gn:asciiname":"Senadla",
    "gn:country_code":"MA",
    "gn:dem":27,
    "gn:feature_class":"P",
    "gn:feature_code":"PPL",
    "gn:name":"Senadla",
    "gn:population":0,
    "gn:timezone":"Africa/Casablanca",
    "iso:country":"MA",
    "wof:name":"Senadla",
    "wof:placetype":"locality"
},
  "geometry": {"coordinates":[-5.84301,35.06299],"type":"Point"}
}