{
  "type": "Feature",
  "properties": {
    "gn:admin1_code":"07",
    "gn:asciiname":"Douar Oulad El Hachya",
    "gn:country_code":"MA",
    "gn:dem":455,
    "gn:feature_class":"P",
    "gn:feature_code":"PPL",
    "gn:name":"Douar Oulad El Hachya",
    "gn:population":0,
    "gn:timezone":"Africa/Casablanca",
    "iso:country":"MA",
    "name:und_x_variant":[
        "Oulad Ya\u00efch"
    ],
    "wof:name":"Douar Oulad El Hachya",
    "wof:placetype":"locality"
},
  "geometry": {"coordinates":[-8.37079,32.06675],"type":"Point"}
}