{
  "type": "Feature",
  "properties": {
    "gn:admin1_code":"09",
    "gn:asciiname":"El Menizla",
    "gn:country_code":"MA",
    "gn:dem":367,
    "gn:feature_class":"P",
    "gn:feature_code":"PPL",
    "gn:name":"El Menizla",
    "gn:population":0,
    "gn:timezone":"Africa/Casablanca",
    "iso:country":"MA",
    "name:und_x_variant":[
        "Menizla",
        "El Mnizla",
        "El Had Mnzila",
        "El Menizla"
    ],
    "wof:name":"El Menizla",
    "wof:placetype":"locality"
},
  "geometry": {"coordinates":[-9.07805,30.61145],"type":"Point"}
}