{
  "type": "Feature",
  "properties": {
    "gn:admin1_code":"1.0",
    "gn:asciiname":"Lhamma",
    "gn:country_code":"MA",
    "gn:dem":357,
    "gn:feature_class":"P",
    "gn:feature_code":"PPL",
    "gn:name":"Lhamma",
    "gn:population":0,
    "gn:timezone":"Africa/Casablanca",
    "iso:country":"MA",
    "wof:name":"Lhamma",
    "wof:placetype":"locality"
},
  "geometry": {"coordinates":[-5.51399,35.38342],"type":"Point"}
}