{
  "type": "Feature",
  "properties": {
    "gn:country":"MA",
    "gn:fcode":"ADM3",
    "gn:population":1497,
    "iso:country":"MA",
    "name:ara_x_preferred":[
        "\u062a\u0627\u0644\u0633\u064a\u0646\u062a"
    ],
    "name:fra_x_preferred":[
        "Abbou Lakhal"
    ],
    "name:fra_x_variant":[
        "Abbou Lakhal (CR)",
        "Abbou Lakhal (Commune Rurale)"
    ],
    "qs:name":"Abbou Lakhal",
    "qs:photos_9r":0,
    "qs:photos_sr":0,
    "qs:pop_sr":"3",
    "wof:name":"Abbou Lakhal",
    "wof:placetype":"localadmin",
    "wof:population":1497
},
  "geometry": {"coordinates":[-1.54034,32.24432],"type":"Point"}
}