{
  "type": "Feature",
  "properties": {
    "gn:admin1_code":"55",
    "gn:asciiname":"Guertsdar",
    "gn:country_code":"MA",
    "gn:dem":142,
    "gn:feature_class":"P",
    "gn:feature_code":"PPL",
    "gn:name":"Guertsdar",
    "gn:population":0,
    "gn:timezone":"Africa/Casablanca",
    "iso:country":"MA",
    "wof:name":"Guertsdar",
    "wof:placetype":"locality"
},
  "geometry": {"coordinates":[-9.27,30.49],"type":"Point"}
}