{
  "type": "Feature",
  "properties": {
    "gn:admin1_code":"6.0",
    "gn:asciiname":"Cooperative Smamra",
    "gn:country_code":"MA",
    "gn:dem":95,
    "gn:feature_class":"P",
    "gn:feature_code":"PPLF",
    "gn:name":"Coop\u00e9rative Smamra",
    "gn:population":0,
    "gn:timezone":"Africa/Casablanca",
    "iso:country":"MA",
    "wof:name":"Cooperative Smamra",
    "wof:placetype":"locality"
},
  "geometry": {"coordinates":[-8.98863,32.62537],"type":"Point"}
}