{
  "type": "Feature",
  "properties": {
    "gn:admin1_code":"8.0",
    "gn:asciiname":"Oulad Ma'tallah",
    "gn:country_code":"MA",
    "gn:dem":802,
    "gn:feature_class":"P",
    "gn:feature_code":"PPL",
    "gn:name":"Oulad Ma\u2019tallah",
    "gn:population":0,
    "gn:timezone":"Africa/Casablanca",
    "iso:country":"MA",
    "wof:name":"Oulad Ma'tallah",
    "wof:placetype":"locality"
},
  "geometry": {"coordinates":[-4.25917,31.44387],"type":"Point"}
}