{
  "type": "Feature",
  "properties": {
    "gn:admin1_code":"01",
    "gn:asciiname":"Ed Dechriyine",
    "gn:country_code":"MA",
    "gn:dem":298,
    "gn:feature_class":"P",
    "gn:feature_code":"PPL",
    "gn:name":"Ed Dechriyine",
    "gn:population":0,
    "gn:timezone":"Africa/Casablanca",
    "iso:country":"MA",
    "wof:name":"Ed Dechriyine",
    "wof:placetype":"locality"
},
  "geometry": {"coordinates":[-5.34918,35.03909],"type":"Point"}
}