{
  "type": "Feature",
  "properties": {
    "gn:admin1_code":"7.0",
    "gn:asciiname":"Amzdarn",
    "gn:country_code":"MA",
    "gn:dem":1301,
    "gn:feature_class":"P",
    "gn:feature_code":"PPL",
    "gn:name":"Amzdarn",
    "gn:population":0,
    "gn:timezone":"Africa/Casablanca",
    "iso:country":"MA",
    "wof:name":"Amzdarn",
    "wof:placetype":"locality"
},
  "geometry": {"coordinates":[-9.14922,31.07349],"type":"Point"}
}