{
  "type": "Feature",
  "properties": {
    "gn:admin1_code":"08",
    "gn:asciiname":"Ait Khelafa",
    "gn:country_code":"MA",
    "gn:dem":1061,
    "gn:feature_class":"P",
    "gn:feature_code":"PPL",
    "gn:name":"A\u00eft Khelafa",
    "gn:population":0,
    "gn:timezone":"Africa/Casablanca",
    "iso:country":"MA",
    "name:und_x_variant":[
        "Ait Relafa",
        "A\u00eft-Khalifa",
        "A\u00eft Khelafa"
    ],
    "wof:name":"Ait Khelafa",
    "wof:placetype":"locality"
},
  "geometry": {"coordinates":[-4.80714,31.43857],"type":"Point"}
}