{
  "type": "Feature",
  "properties": {
    "gn:admin1_code":"7.0",
    "gn:asciiname":"'Azib al Haj Manncour",
    "gn:country_code":"MA",
    "gn:dem":541,
    "gn:feature_class":"P",
    "gn:feature_code":"PPL",
    "gn:name":"\u2019Azib al Haj Mann\u00e7our",
    "gn:population":0,
    "gn:timezone":"Africa/Casablanca",
    "iso:country":"MA",
    "wof:name":"'Azib al Haj Manncour",
    "wof:placetype":"locality"
},
  "geometry": {"coordinates":[-8.31955,31.46238],"type":"Point"}
}