{
  "type": "Feature",
  "properties": {
    "gn:admin1_code":"2.0",
    "gn:asciiname":"Societe Agro-Alimentaire",
    "gn:country_code":"MA",
    "gn:dem":81,
    "gn:feature_class":"P",
    "gn:feature_code":"PPL",
    "gn:name":"Societe Agro-Alimentaire",
    "gn:population":0,
    "gn:timezone":"Africa/Casablanca",
    "iso:country":"MA",
    "wof:name":"Societe Agro-Alimentaire",
    "wof:placetype":"locality"
},
  "geometry": {"coordinates":[-2.34605,34.99285],"type":"Point"}
}