{
  "type": "Feature",
  "properties": {
    "gn:admin1_code":"01",
    "gn:asciiname":"Jamaa Zhar",
    "gn:country_code":"MA",
    "gn:dem":561,
    "gn:feature_class":"P",
    "gn:feature_code":"PPL",
    "gn:name":"Jamaa Zhar",
    "gn:population":0,
    "gn:timezone":"Africa/Casablanca",
    "iso:country":"MA",
    "name:und_x_variant":[
        "Yama Ashar",
        "Jama\u00e2 ez Zhar",
        "Jamaa Zhar"
    ],
    "wof:name":"Jamaa Zhar",
    "wof:placetype":"locality"
},
  "geometry": {"coordinates":[-5.19553,35.43097],"type":"Point"}
}