{
  "type": "Feature",
  "properties": {
    "gn:admin1_code":"01",
    "gn:asciiname":"Douar Assaous",
    "gn:country_code":"MA",
    "gn:dem":190,
    "gn:feature_class":"P",
    "gn:feature_code":"PPL",
    "gn:name":"Douar Assaous",
    "gn:population":0,
    "gn:timezone":"Africa/Casablanca",
    "iso:country":"MA",
    "name:und_x_variant":[
        "Aassaouss",
        "Douar Oulad Ben Asses",
        "Oulad Ben Asses",
        "Douar Assaous"
    ],
    "wof:name":"Douar Assaous",
    "wof:placetype":"locality"
},
  "geometry": {"coordinates":[-5.70647,34.89856],"type":"Point"}
}