{
  "type": "Feature",
  "properties": {
    "gn:admin1_code":"7.0",
    "gn:asciiname":"Tounine",
    "gn:country_code":"MA",
    "gn:dem":1292,
    "gn:feature_class":"P",
    "gn:feature_code":"PPL",
    "gn:name":"Tounine",
    "gn:population":0,
    "gn:timezone":"Africa/Casablanca",
    "iso:country":"MA",
    "wof:name":"Tounine",
    "wof:placetype":"locality"
},
  "geometry": {"coordinates":[-9.1795,31.0372],"type":"Point"}
}