{
  "type": "Feature",
  "properties": {
    "gn:admin1_code":"7.0",
    "gn:asciiname":"Douar Lebsoulat",
    "gn:country_code":"MA",
    "gn:dem":277,
    "gn:feature_class":"P",
    "gn:feature_code":"PPL",
    "gn:name":"Douar Lebsoulat",
    "gn:population":0,
    "gn:timezone":"Africa/Casablanca",
    "iso:country":"MA",
    "wof:name":"Douar Lebsoulat",
    "wof:placetype":"locality"
},
  "geometry": {"coordinates":[-9.09071,32.01212],"type":"Point"}
}