{
  "type": "Feature",
  "properties": {
    "gn:admin1_code":"03",
    "gn:asciiname":"El Khemis du Zrizer",
    "gn:country_code":"MA",
    "gn:dem":349,
    "gn:feature_class":"P",
    "gn:feature_code":"PPL",
    "gn:name":"El Khemis du Zrizer",
    "gn:population":0,
    "gn:timezone":"Africa/Casablanca",
    "iso:country":"MA",
    "name:und_x_variant":[
        "El-Khemis-de-Zrizar",
        "El Khemis du Zrizer"
    ],
    "wof:name":"El Khemis du Zrizer",
    "wof:placetype":"locality"
},
  "geometry": {"coordinates":[-4.61809,34.58665999999999],"type":"Point"}
}