{
  "type": "Feature",
  "properties": {
    "gn:admin1_code":"02",
    "gn:asciiname":"Oulad Mohammed Ou Ammar",
    "gn:country_code":"MA",
    "gn:dem":402,
    "gn:feature_class":"P",
    "gn:feature_code":"PPL",
    "gn:name":"Oulad Mohammed Ou Ammar",
    "gn:population":0,
    "gn:timezone":"Africa/Casablanca",
    "iso:country":"MA",
    "wof:name":"Oulad Mohammed Ou Ammar",
    "wof:placetype":"locality"
},
  "geometry": {"coordinates":[-2.97747,34.91225],"type":"Point"}
}