{
  "type": "Feature",
  "properties": {
    "gn:admin1_code":"3.0",
    "gn:asciiname":"Ait Yahya",
    "gn:country_code":"MA",
    "gn:dem":812,
    "gn:feature_class":"P",
    "gn:feature_code":"PPL",
    "gn:name":"Ait Yahya",
    "gn:population":0,
    "gn:timezone":"Africa/Casablanca",
    "iso:country":"MA",
    "wof:name":"Ait Yahya",
    "wof:placetype":"locality"
},
  "geometry": {"coordinates":[-5.72243,33.65278],"type":"Point"}
}