{
  "type": "Feature",
  "properties": {
    "gn:admin1_code":"2.0",
    "gn:asciiname":"Dar Ben Legzouli Mohamed Ben Lekbir",
    "gn:country_code":"MA",
    "gn:dem":591,
    "gn:feature_class":"P",
    "gn:feature_code":"PPL",
    "gn:name":"Dar Ben Legzouli Mohamed Ben Lekbir",
    "gn:population":0,
    "gn:timezone":"Africa/Casablanca",
    "iso:country":"MA",
    "wof:name":"Dar Ben Legzouli Mohamed Ben Lekbir",
    "wof:placetype":"locality"
},
  "geometry": {"coordinates":[-2.46685,34.59931],"type":"Point"}
}