{
  "type": "Feature",
  "properties": {
    "gn:admin1_code":"01",
    "gn:asciiname":"Amesougane",
    "gn:country_code":"MA",
    "gn:dem":1201,
    "gn:feature_class":"P",
    "gn:feature_code":"PPL",
    "gn:name":"Amesougane",
    "gn:population":0,
    "gn:timezone":"Africa/Casablanca",
    "iso:country":"MA",
    "wof:name":"Amesougane",
    "wof:placetype":"locality"
},
  "geometry": {"coordinates":[-4.73,34.95],"type":"Point"}
}