{
  "type": "Feature",
  "properties": {
    "gn:admin1_code":"09",
    "gn:asciiname":"Amadghar",
    "gn:country_code":"MA",
    "gn:dem":1790,
    "gn:feature_class":"P",
    "gn:feature_code":"PPL",
    "gn:name":"Amadghar",
    "gn:population":0,
    "gn:timezone":"Africa/Casablanca",
    "iso:country":"MA",
    "name:und_x_variant":[
        "Amdrar",
        "Amdrar n\u2019 Oumdras",
        "Amadghar"
    ],
    "wof:name":"Amadghar",
    "wof:placetype":"locality"
},
  "geometry": {"coordinates":[-7.75679,30.31942],"type":"Point"}
}