{
  "type": "Feature",
  "properties": {
    "gn:admin1_code":"2.0",
    "gn:asciiname":"Douar Oulad Ennasser",
    "gn:country_code":"MA",
    "gn:dem":482,
    "gn:feature_class":"P",
    "gn:feature_code":"PPL",
    "gn:name":"Douar Oulad Ennasser",
    "gn:population":0,
    "gn:timezone":"Africa/Casablanca",
    "iso:country":"MA",
    "wof:name":"Douar Oulad Ennasser",
    "wof:placetype":"locality"
},
  "geometry": {"coordinates":[-1.86083,34.75179],"type":"Point"}
}