{
  "type": "Feature",
  "properties": {
    "gn:admin1_code":"10.0",
    "gn:asciiname":"Id Boujm'a",
    "gn:country_code":"MA",
    "gn:dem":402,
    "gn:feature_class":"P",
    "gn:feature_code":"PPL",
    "gn:name":"Id Boujm\u2019a",
    "gn:population":0,
    "gn:timezone":"Africa/Casablanca",
    "iso:country":"MA",
    "wof:name":"Id Boujm'a",
    "wof:placetype":"locality"
},
  "geometry": {"coordinates":[-9.97487,29.31116],"type":"Point"}
}