{
  "type": "Feature",
  "properties": {
    "gn:admin1_code":"09",
    "gn:asciiname":"Tikida",
    "gn:country_code":"MA",
    "gn:dem":1129,
    "gn:feature_class":"P",
    "gn:feature_code":"PPL",
    "gn:name":"Tikida",
    "gn:population":0,
    "gn:timezone":"Africa/Casablanca",
    "iso:country":"MA",
    "wof:name":"Tikida",
    "wof:placetype":"locality"
},
  "geometry": {"coordinates":[-8.44085,30.35483],"type":"Point"}
}