{
  "type": "Feature",
  "properties": {
    "gn:admin1_code":"7.0",
    "gn:asciiname":"Ayt Lahsene ou S'aid",
    "gn:country_code":"MA",
    "gn:dem":654,
    "gn:feature_class":"P",
    "gn:feature_code":"PPL",
    "gn:name":"Ayt Lahsene ou S\u2019aid",
    "gn:population":0,
    "gn:timezone":"Africa/Casablanca",
    "iso:country":"MA",
    "wof:name":"Ayt Lahsene ou S'aid",
    "wof:placetype":"locality"
},
  "geometry": {"coordinates":[-7.7732,31.48128],"type":"Point"}
}