{
  "type": "Feature",
  "properties": {
    "gn:admin1_code":"4.0",
    "gn:asciiname":"Laaouija",
    "gn:country_code":"MA",
    "gn:dem":153,
    "gn:feature_class":"P",
    "gn:feature_code":"PPL",
    "gn:name":"Laaouija",
    "gn:population":0,
    "gn:timezone":"Africa/Casablanca",
    "iso:country":"MA",
    "wof:name":"Laaouija",
    "wof:placetype":"locality"
},
  "geometry": {"coordinates":[-7.03263,33.76808],"type":"Point"}
}