{
  "type": "Feature",
  "properties": {
    "gn:admin1_code":"6.0",
    "gn:asciiname":"Charqawa",
    "gn:country_code":"MA",
    "gn:dem":205,
    "gn:feature_class":"P",
    "gn:feature_code":"PPL",
    "gn:name":"Charqawa",
    "gn:population":0,
    "gn:timezone":"Africa/Casablanca",
    "iso:country":"MA",
    "wof:name":"Charqawa",
    "wof:placetype":"locality"
},
  "geometry": {"coordinates":[-7.97686,33.10258],"type":"Point"}
}