{
  "type": "Feature",
  "properties": {
    "gn:admin1_code":"08",
    "gn:asciiname":"Ait Kherdi",
    "gn:country_code":"MA",
    "gn:dem":607,
    "gn:feature_class":"P",
    "gn:feature_code":"PPL",
    "gn:name":"A\u00eft Kherdi",
    "gn:population":0,
    "gn:timezone":"Africa/Casablanca",
    "iso:country":"MA",
    "wof:name":"Ait Kherdi",
    "wof:placetype":"locality"
},
  "geometry": {"coordinates":[-5.56,29.98],"type":"Point"}
}