{
  "type": "Feature",
  "properties": {
    "gn:admin1_code":"04",
    "gn:asciiname":"Douar Oulad Yahya",
    "gn:country_code":"MA",
    "gn:dem":138,
    "gn:feature_class":"P",
    "gn:feature_code":"PPL",
    "gn:name":"Douar Oulad Yahya",
    "gn:population":0,
    "gn:timezone":"Africa/Casablanca",
    "iso:country":"MA",
    "name:und_x_variant":[
        "Douar Oulad Yahia",
        "Ouled Yahia",
        "Oulad Yahia",
        "Douar Oulad Yahya"
    ],
    "wof:name":"Douar Oulad Yahya",
    "wof:placetype":"locality"
},
  "geometry": {"coordinates":[-5.89922,34.85628],"type":"Point"}
}