{
  "type": "Feature",
  "properties": {
    "gn:admin1_code":"3.0",
    "gn:asciiname":"Douar Essennoune",
    "gn:country_code":"MA",
    "gn:dem":321,
    "gn:feature_class":"P",
    "gn:feature_code":"PPL",
    "gn:name":"Douar Essennoune",
    "gn:population":0,
    "gn:timezone":"Africa/Casablanca",
    "iso:country":"MA",
    "wof:name":"Douar Essennoune",
    "wof:placetype":"locality"
},
  "geometry": {"coordinates":[-4.87582,34.46664000000001],"type":"Point"}
}