{
  "type": "Feature",
  "properties": {
    "gn:admin1_code":"03",
    "gn:asciiname":"Douar Lemsibih",
    "gn:country_code":"MA",
    "gn:dem":519,
    "gn:feature_class":"P",
    "gn:feature_code":"PPL",
    "gn:name":"Douar Lemsibih",
    "gn:population":0,
    "gn:timezone":"Africa/Casablanca",
    "iso:country":"MA",
    "name:und_x_variant":[
        "Douar Sta\u00efl",
        "Sta\u00efl",
        "Douar Lemsibih"
    ],
    "wof:name":"Douar Lemsibih",
    "wof:placetype":"locality"
},
  "geometry": {"coordinates":[-5.08367,34.0736],"type":"Point"}
}