{
  "type": "Feature",
  "properties": {
    "gn:gn_country":"MA",
    "gn:gn_fcode":"ADM3",
    "gn:gn_pop":9623,
    "gn:population":8930,
    "iso:country":"MA",
    "name:ara_x_preferred":[
        "\u0628\u0646\u064a \u0633\u064a\u062f\u0627\u0644 \u0644\u0648\u0637\u0627"
    ],
    "name:fra_x_preferred":[
        "Bni Sidel Jbel"
    ],
    "name:fra_x_variant":[
        "Bni Sidel Jbel (CR)",
        "Bni Sidel Jbel (Commune Rurale)"
    ],
    "qs_pg:aaroncc":"MA",
    "qs_pg:gn_country":"MA",
    "qs_pg:gn_fcode":"ADM3",
    "qs_pg:gn_pop":9623,
    "qs_pg:name":"Bni Sidel Jbel",
    "qs_pg:photos_9r":0,
    "qs_pg:photos_sr":0,
    "qs_pg:pop_sr":5,
    "qs_pg:qs_pg_placetype":"localadmin",
    "wof:name":"Bni Sidel Jbel",
    "wof:placetype":"localadmin",
    "wof:population":8930
},
  "geometry": {"coordinates":[-3.08011,35.21563],"type":"Point"}
}