{
  "type": "Feature",
  "properties": {
    "gn:admin1_code":"04",
    "gn:asciiname":"Douar Rouala",
    "gn:country_code":"MA",
    "gn:dem":11,
    "gn:feature_class":"P",
    "gn:feature_code":"PPL",
    "gn:name":"Douar Rouala",
    "gn:population":0,
    "gn:timezone":"Africa/Casablanca",
    "iso:country":"MA",
    "name:und_x_variant":[
        "Douar Rouata",
        "Rouata",
        "Douar Rouala"
    ],
    "wof:name":"Douar Rouala",
    "wof:placetype":"locality"
},
  "geometry": {"coordinates":[-6.22237,34.58235],"type":"Point"}
}