{
  "type": "Feature",
  "properties": {
    "gn:admin1_code":"1.0",
    "gn:asciiname":"Douar Ben Amer",
    "gn:country_code":"MA",
    "gn:dem":308,
    "gn:feature_class":"P",
    "gn:feature_code":"PPL",
    "gn:name":"Douar Ben Amer",
    "gn:population":0,
    "gn:timezone":"Africa/Casablanca",
    "iso:country":"MA",
    "wof:name":"Douar Ben Amer",
    "wof:placetype":"locality"
},
  "geometry": {"coordinates":[-3.95807,35.10671],"type":"Point"}
}