{
  "type": "Feature",
  "properties": {
    "gn:admin1_code":"6.0",
    "gn:asciiname":"Herkaoua",
    "gn:country_code":"MA",
    "gn:dem":506,
    "gn:feature_class":"P",
    "gn:feature_code":"PPL",
    "gn:name":"Herkaoua",
    "gn:population":0,
    "gn:timezone":"Africa/Casablanca",
    "iso:country":"MA",
    "wof:name":"Herkaoua",
    "wof:placetype":"locality"
},
  "geometry": {"coordinates":[-7.54701,32.91913],"type":"Point"}
}