{
  "type": "Feature",
  "properties": {
    "gn:admin1_code":"05",
    "gn:asciiname":"Rbat",
    "gn:country_code":"MA",
    "gn:dem":1966,
    "gn:feature_class":"P",
    "gn:feature_code":"PPL",
    "gn:name":"Rbat",
    "gn:population":0,
    "gn:timezone":"Africa/Casablanca",
    "iso:country":"MA",
    "wof:name":"Rbat",
    "wof:placetype":"locality"
},
  "geometry": {"coordinates":[-6.36813,31.66637],"type":"Point"}
}