{
  "type": "Feature",
  "properties": {
    "gn:admin1_code":"5.0",
    "gn:asciiname":"Douar Ayt Al Miloudi",
    "gn:country_code":"MA",
    "gn:dem":483,
    "gn:feature_class":"P",
    "gn:feature_code":"PPL",
    "gn:name":"Douar Ayt Al Miloudi",
    "gn:population":0,
    "gn:timezone":"Africa/Casablanca",
    "iso:country":"MA",
    "wof:name":"Douar Ayt Al Miloudi",
    "wof:placetype":"locality"
},
  "geometry": {"coordinates":[-6.54111,32.5658],"type":"Point"}
}