{
  "type": "Feature",
  "properties": {
    "gn:admin1_code":"8.0",
    "gn:asciiname":"Igharm N-Chrif",
    "gn:country_code":"MA",
    "gn:dem":945,
    "gn:feature_class":"P",
    "gn:feature_code":"PPL",
    "gn:name":"Igharm N-Chrif",
    "gn:population":0,
    "gn:timezone":"Africa/Casablanca",
    "iso:country":"MA",
    "wof:name":"Igharm N-Chrif",
    "wof:placetype":"locality"
},
  "geometry": {"coordinates":[-4.1281,31.77167],"type":"Point"}
}