{
  "type": "Feature",
  "properties": {
    "gn:admin1_code":"9.0",
    "gn:asciiname":"Tagadirt Oufella",
    "gn:country_code":"MA",
    "gn:dem":212,
    "gn:feature_class":"P",
    "gn:feature_code":"PPL",
    "gn:name":"Tagadirt Oufella",
    "gn:population":0,
    "gn:timezone":"Africa/Casablanca",
    "iso:country":"MA",
    "wof:name":"Tagadirt Oufella",
    "wof:placetype":"locality"
},
  "geometry": {"coordinates":[-9.38788,30.47761],"type":"Point"}
}