{
  "type": "Feature",
  "properties": {
    "gn:admin1_code":"03",
    "gn:asciiname":"Douar 'Ayn Dfali",
    "gn:country_code":"MA",
    "gn:dem":767,
    "gn:feature_class":"P",
    "gn:feature_code":"PPL",
    "gn:name":"Douar \u2019Ayn Dfali",
    "gn:population":0,
    "gn:timezone":"Africa/Casablanca",
    "iso:country":"MA",
    "name:ara_x_preferred":[
        "\u0639\u064a\u0646 \u0627\u0644\u062f\u0641\u0627\u0644\u064a"
    ],
    "name:azb_x_preferred":[
        "\u0639\u06cc\u0646 \u0627\u0644\u062f\u0641\u0627\u0644\u06cc"
    ],
    "name:cat_x_preferred":[
        "Ain Dfali"
    ],
    "name:fas_x_preferred":[
        "\u0639\u06cc\u0646 \u0627\u0644\u062f\u0641\u0627\u0644\u06cc"
    ],
    "name:fra_x_preferred":[
        "A\u00efn Dfali"
    ],
    "name:ita_x_preferred":[
        "Ain Dfali"
    ],
    "name:und_x_variant":[
        "A\u00efne \u00c9fa\u00efli",
        "Douar \u2019Ayn Dfali"
    ],
    "wof:name":"Douar 'Ayn Dfali",
    "wof:placetype":"locality"
},
  "geometry": {"coordinates":[-4.45274,33.95363],"type":"Point"}
}