{
  "type": "Feature",
  "properties": {
    "gn:gn_country":"MA",
    "gn:gn_fcode":"ADM3",
    "gn:gn_pop":9533,
    "gn:population":10256,
    "iso:country":"MA",
    "name:ara_x_preferred":[
        "\u0627\u062d\u0645\u0631  \u0644\u0643\u0644\u0627\u0644\u0634\u0629"
    ],
    "name:fra_x_preferred":[
        "Ait Igas"
    ],
    "name:fra_x_variant":[
        "Ait Igas (CR)",
        "Ait Igas (Commune Rurale)"
    ],
    "qs_pg:aaroncc":"MA",
    "qs_pg:gn_country":"MA",
    "qs_pg:gn_fcode":"ADM3",
    "qs_pg:gn_pop":9533,
    "qs_pg:name":"Ait Igas",
    "qs_pg:photos_9r":0,
    "qs_pg:photos_sr":0,
    "qs_pg:pop_sr":5,
    "qs_pg:qs_pg_placetype":"localadmin",
    "wof:name":"Ait Igas",
    "wof:placetype":"localadmin",
    "wof:population":10256
},
  "geometry": {"coordinates":[-8.72323,30.59133],"type":"Point"}
}