{
  "type": "Feature",
  "properties": {
    "gn:admin1_code":"01",
    "gn:asciiname":"Douar Kherbennayine",
    "gn:country_code":"MA",
    "gn:dem":272,
    "gn:feature_class":"P",
    "gn:feature_code":"PPL",
    "gn:name":"Douar Kherbennayine",
    "gn:population":0,
    "gn:timezone":"Africa/Casablanca",
    "iso:country":"MA",
    "name:und_x_variant":[
        "Kherbana\u00efn",
        "Kherbenna\u00efn",
        "Douar Kherbennayine"
    ],
    "wof:name":"Douar Kherbennayine",
    "wof:placetype":"locality"
},
  "geometry": {"coordinates":[-5.32673,34.54245],"type":"Point"}
}