{
  "type": "Feature",
  "properties": {
    "gn:admin1_code":"55.0",
    "gn:asciiname":"Ouaounzourt",
    "gn:country_code":"MA",
    "gn:dem":1924,
    "gn:feature_class":"P",
    "gn:feature_code":"PPL",
    "gn:name":"Ouaounzourt",
    "gn:population":0,
    "gn:timezone":"Africa/Casablanca",
    "iso:country":"MA",
    "wof:name":"Ouaounzourt",
    "wof:placetype":"locality"
},
  "geometry": {"coordinates":[-7.83164,31.00103],"type":"Point"}
}