{
  "type": "Feature",
  "properties": {
    "gn:admin1_code":"09",
    "gn:asciiname":"Tirhermt",
    "gn:country_code":"MA",
    "gn:dem":703,
    "gn:feature_class":"P",
    "gn:feature_code":"PPL",
    "gn:name":"Tirhermt",
    "gn:population":0,
    "gn:timezone":"Africa/Casablanca",
    "iso:country":"MA",
    "wof:name":"Tirhermt",
    "wof:placetype":"locality"
},
  "geometry": {"coordinates":[-7.97137,29.76569000000001],"type":"Point"}
}