{
  "type": "Feature",
  "properties": {
    "gn:admin1_code":"6.0",
    "gn:asciiname":"Douar Oulad Ben Ben Daoud Oulad Bihi",
    "gn:country_code":"MA",
    "gn:dem":300,
    "gn:feature_class":"P",
    "gn:feature_code":"PPL",
    "gn:name":"Douar Oulad Ben Ben Daoud Oulad Bihi",
    "gn:population":0,
    "gn:timezone":"Africa/Casablanca",
    "iso:country":"MA",
    "wof:name":"Douar Oulad Ben Ben Daoud Oulad Bihi",
    "wof:placetype":"locality"
},
  "geometry": {"coordinates":[-6.89515,33.46477],"type":"Point"}
}