{
  "type": "Feature",
  "properties": {
    "gn:admin1_code":"1.0",
    "gn:asciiname":"Houmat Tayenza",
    "gn:country_code":"MA",
    "gn:dem":805,
    "gn:feature_class":"P",
    "gn:feature_code":"PPL",
    "gn:name":"Houmat Tayenza",
    "gn:population":0,
    "gn:timezone":"Africa/Casablanca",
    "iso:country":"MA",
    "wof:name":"Houmat Tayenza",
    "wof:placetype":"locality"
},
  "geometry": {"coordinates":[-4.80617,35.06838],"type":"Point"}
}