{
  "type": "Feature",
  "properties": {
    "gn:admin1_code":"07",
    "gn:asciiname":"Ibaloulene",
    "gn:country_code":"MA",
    "gn:dem":1558,
    "gn:feature_class":"P",
    "gn:feature_code":"PPL",
    "gn:name":"Ibaloulene",
    "gn:population":0,
    "gn:timezone":"Africa/Casablanca",
    "iso:country":"MA",
    "name:und_x_variant":[
        "Ibaloul\u00e8n",
        "Ibaloulene"
    ],
    "wof:name":"Ibaloulene",
    "wof:placetype":"locality"
},
  "geometry": {"coordinates":[-8.91232,30.94203],"type":"Point"}
}