{
  "type": "Feature",
  "properties": {
    "gn:admin1_code":"10",
    "gn:asciiname":"Tannadine",
    "gn:country_code":"MA",
    "gn:dem":1202,
    "gn:feature_class":"P",
    "gn:feature_code":"PPL",
    "gn:name":"Tannadine",
    "gn:population":0,
    "gn:timezone":"Africa/Casablanca",
    "iso:country":"MA",
    "name:und_x_variant":[
        "Tanadine",
        "Tannadine"
    ],
    "wof:name":"Tannadine",
    "wof:placetype":"locality"
},
  "geometry": {"coordinates":[-9.43187,29.32474],"type":"Point"}
}