{
  "type": "Feature",
  "properties": {
    "gn:admin1_code":"6.0",
    "gn:asciiname":"Sibanat",
    "gn:country_code":"MA",
    "gn:dem":141,
    "gn:feature_class":"P",
    "gn:feature_code":"PPL",
    "gn:name":"Sibanat",
    "gn:population":0,
    "gn:timezone":"Africa/Casablanca",
    "iso:country":"MA",
    "wof:name":"Sibanat",
    "wof:placetype":"locality"
},
  "geometry": {"coordinates":[-8.35697,33.02255],"type":"Point"}
}