{
  "type": "Feature",
  "properties": {
    "gn:admin1_code":"07",
    "gn:asciiname":"Lahmadat",
    "gn:country_code":"MA",
    "gn:dem":89,
    "gn:feature_class":"P",
    "gn:feature_code":"PPL",
    "gn:name":"Lahmadat",
    "gn:population":0,
    "gn:timezone":"Africa/Casablanca",
    "iso:country":"MA",
    "name:und_x_variant":[
        "Douar el Hamadat",
        "El Hamadat"
    ],
    "wof:name":"Lahmadat",
    "wof:placetype":"locality"
},
  "geometry": {"coordinates":[-9.16954,32.4541],"type":"Point"}
}