{
  "type": "Feature",
  "properties": {
    "gn:admin1_code":"7.0",
    "gn:asciiname":"Widkennt",
    "gn:country_code":"MA",
    "gn:dem":976,
    "gn:feature_class":"P",
    "gn:feature_code":"PPL",
    "gn:name":"Widkennt",
    "gn:population":0,
    "gn:timezone":"Africa/Casablanca",
    "iso:country":"MA",
    "wof:name":"Widkennt",
    "wof:placetype":"locality"
},
  "geometry": {"coordinates":[-7.8268,31.33653],"type":"Point"}
}