{
  "type": "Feature",
  "properties": {
    "gn:admin1_code":"02",
    "gn:asciiname":"Kasba et Torch",
    "gn:country_code":"MA",
    "gn:dem":348,
    "gn:feature_class":"P",
    "gn:feature_code":"PPL",
    "gn:name":"Kasba et Torch",
    "gn:population":0,
    "gn:timezone":"Africa/Casablanca",
    "iso:country":"MA",
    "name:und_x_variant":[
        "Oasbat at Torch",
        "Kasba Torch"
    ],
    "wof:name":"Kasba et Torch",
    "wof:placetype":"locality"
},
  "geometry": {"coordinates":[-3.30727,34.26],"type":"Point"}
}