{
  "type": "Feature",
  "properties": {
    "gn:admin1_code":"08",
    "gn:asciiname":"Sammoure",
    "gn:country_code":"MA",
    "gn:dem":1499,
    "gn:feature_class":"P",
    "gn:feature_code":"PPL",
    "gn:name":"Sammoure",
    "gn:population":0,
    "gn:timezone":"Africa/Casablanca",
    "iso:country":"MA",
    "name:und_x_variant":[
        "Ksar de Samora",
        "Semmoura",
        "Semoura",
        "Sammoure"
    ],
    "wof:name":"Sammoure",
    "wof:placetype":"locality"
},
  "geometry": {"coordinates":[-4.75828,32.66779],"type":"Point"}
}