{
  "type": "Feature",
  "properties": {
    "gn:admin1_code":"3.0",
    "gn:asciiname":"Ait Abdellah",
    "gn:country_code":"MA",
    "gn:dem":1418,
    "gn:feature_class":"P",
    "gn:feature_code":"PPL",
    "gn:name":"Ait Abdellah",
    "gn:population":0,
    "gn:timezone":"Africa/Casablanca",
    "iso:country":"MA",
    "wof:name":"Ait Abdellah",
    "wof:placetype":"locality"
},
  "geometry": {"coordinates":[-4.75942,33.66496],"type":"Point"}
}