{
  "type": "Feature",
  "properties": {
    "gn:admin1_code":"10",
    "gn:asciiname":"Agourout",
    "gn:country_code":"MA",
    "gn:dem":504,
    "gn:feature_class":"P",
    "gn:feature_code":"PPL",
    "gn:name":"Agourout",
    "gn:population":0,
    "gn:timezone":"Africa/Casablanca",
    "iso:country":"MA",
    "name:und_x_variant":[
        "Agurru",
        "Agourout"
    ],
    "wof:name":"Agourout",
    "wof:placetype":"locality"
},
  "geometry": {"coordinates":[-10.19462,29.22106],"type":"Point"}
}