{
  "type": "Feature",
  "properties": {
    "gn:admin1_code":"7.0",
    "gn:asciiname":"Anc. C.M.V.A.",
    "gn:country_code":"MA",
    "gn:dem":572,
    "gn:feature_class":"P",
    "gn:feature_code":"PPL",
    "gn:name":"Anc. C.M.V.A.",
    "gn:population":0,
    "gn:timezone":"Africa/Casablanca",
    "iso:country":"MA",
    "wof:name":"Anc. C.M.V.A.",
    "wof:placetype":"locality"
},
  "geometry": {"coordinates":[-7.57425,31.71387],"type":"Point"}
}