{
  "type": "Feature",
  "properties": {
    "gn:admin1_code":"9.0",
    "gn:asciiname":"Izenaguene",
    "gn:country_code":"MA",
    "gn:dem":390,
    "gn:feature_class":"P",
    "gn:feature_code":"PPL",
    "gn:name":"Izenaguene",
    "gn:population":0,
    "gn:timezone":"Africa/Casablanca",
    "iso:country":"MA",
    "wof:name":"Izenaguene",
    "wof:placetype":"locality"
},
  "geometry": {"coordinates":[-9.1548,30.19153],"type":"Point"}
}