{
  "type": "Feature",
  "properties": {
    "gn:admin1_code":"07",
    "gn:asciiname":"Tidourine",
    "gn:country_code":"MA",
    "gn:dem":198,
    "gn:feature_class":"P",
    "gn:feature_code":"PPL",
    "gn:name":"Tidourine",
    "gn:population":0,
    "gn:timezone":"Africa/Casablanca",
    "iso:country":"MA",
    "wof:name":"Tidourine",
    "wof:placetype":"locality"
},
  "geometry": {"coordinates":[-9.73469,31.26656],"type":"Point"}
}