{
  "type": "Feature",
  "properties": {
    "gn:admin1_code":"04",
    "gn:asciiname":"Douar Zahriyine",
    "gn:country_code":"MA",
    "gn:dem":192,
    "gn:feature_class":"P",
    "gn:feature_code":"PPL",
    "gn:name":"Douar Zahriyine",
    "gn:population":0,
    "gn:timezone":"Africa/Casablanca",
    "iso:country":"MA",
    "name:und_x_variant":[
        "Ezhiry\u00e8ne",
        "Zehriyne",
        "Zehriine",
        "Zehriyine",
        "Douar Zahriyine"
    ],
    "wof:name":"Douar Zahriyine",
    "wof:placetype":"locality"
},
  "geometry": {"coordinates":[-5.35335,34.51887],"type":"Point"}
}