{
  "type": "Feature",
  "properties": {
    "gn:admin1_code":"3.0",
    "gn:asciiname":"Douar Ait Amer",
    "gn:country_code":"MA",
    "gn:dem":652,
    "gn:feature_class":"P",
    "gn:feature_code":"PPL",
    "gn:name":"Douar Ait Amer",
    "gn:population":0,
    "gn:timezone":"Africa/Casablanca",
    "iso:country":"MA",
    "wof:name":"Douar Ait Amer",
    "wof:placetype":"locality"
},
  "geometry": {"coordinates":[-5.49744,33.80462],"type":"Point"}
}