{
  "type": "Feature",
  "properties": {
    "gn:admin1_code":"05",
    "gn:asciiname":"Bou'aziyer",
    "gn:country_code":"MA",
    "gn:dem":468,
    "gn:feature_class":"P",
    "gn:feature_code":"PPL",
    "gn:name":"Bou\u2019aziyer",
    "gn:population":0,
    "gn:timezone":"Africa/Casablanca",
    "iso:country":"MA",
    "name:und_x_variant":[
        "Bou\u2019aziyer",
        "Bou Azir"
    ],
    "wof:name":"Bou'aziyer",
    "wof:placetype":"locality"
},
  "geometry": {"coordinates":[-6.92532,32.17617],"type":"Point"}
}