{
  "type": "Feature",
  "properties": {
    "gn:admin1_code":"1.0",
    "gn:asciiname":"Douar Ibarhounine",
    "gn:country_code":"MA",
    "gn:dem":1080,
    "gn:feature_class":"P",
    "gn:feature_code":"PPL",
    "gn:name":"Douar Ibarhounine",
    "gn:population":0,
    "gn:timezone":"Africa/Casablanca",
    "iso:country":"MA",
    "wof:name":"Douar Ibarhounine",
    "wof:placetype":"locality"
},
  "geometry": {"coordinates":[-5.39921,35.14195],"type":"Point"}
}