{
  "type": "Feature",
  "properties": {
    "gn:admin1_code":"02",
    "gn:asciiname":"Douar Hziyeme-n-Nej",
    "gn:country_code":"MA",
    "gn:dem":589,
    "gn:feature_class":"P",
    "gn:feature_code":"PPL",
    "gn:name":"Douar Hziyeme-n-Nej",
    "gn:population":0,
    "gn:timezone":"Africa/Casablanca",
    "iso:country":"MA",
    "wof:name":"Douar Hziyeme-n-Nej",
    "wof:placetype":"locality"
},
  "geometry": {"coordinates":[-3.71352,35.15035],"type":"Point"}
}