{
  "type": "Feature",
  "properties": {
    "gn:admin1_code":"02",
    "gn:asciiname":"Dhar n-Tbedjaaine",
    "gn:country_code":"MA",
    "gn:dem":661,
    "gn:feature_class":"P",
    "gn:feature_code":"PPLL",
    "gn:name":"Dhar n-Tbedjaaine",
    "gn:population":0,
    "gn:timezone":"Africa/Casablanca",
    "iso:country":"MA",
    "wof:name":"Dhar n-Tbedjaaine",
    "wof:placetype":"locality"
},
  "geometry": {"coordinates":[-3.72479,35.13709],"type":"Point"}
}