{
  "type": "Feature",
  "properties": {
    "gn:admin1_code":"2.0",
    "gn:asciiname":"Douar Tanout",
    "gn:country_code":"MA",
    "gn:dem":83,
    "gn:feature_class":"P",
    "gn:feature_code":"PPL",
    "gn:name":"Douar Tanout",
    "gn:population":0,
    "gn:timezone":"Africa/Casablanca",
    "iso:country":"MA",
    "name:und_x_variant":[
        "Lemharga"
    ],
    "wof:name":"Douar Tanout",
    "wof:placetype":"locality"
},
  "geometry": {"coordinates":[-2.38649,34.96858],"type":"Point"}
}