{
  "type": "Feature",
  "properties": {
    "gn:admin1_code":"7.0",
    "gn:asciiname":"Oulad Ben Jilah",
    "gn:country_code":"MA",
    "gn:dem":299,
    "gn:feature_class":"P",
    "gn:feature_code":"PPL",
    "gn:name":"Oulad Ben Jilah",
    "gn:population":0,
    "gn:timezone":"Africa/Casablanca",
    "iso:country":"MA",
    "wof:name":"Oulad Ben Jilah",
    "wof:placetype":"locality"
},
  "geometry": {"coordinates":[-8.65385,32.28740999999999],"type":"Point"}
}