{
  "type": "Feature",
  "properties": {
    "gn:admin1_code":"7.0",
    "gn:asciiname":"Ait Ouwahmane",
    "gn:country_code":"MA",
    "gn:dem":734,
    "gn:feature_class":"P",
    "gn:feature_code":"PPL",
    "gn:name":"A\u00eft Ouwahmane",
    "gn:population":0,
    "gn:timezone":"Africa/Casablanca",
    "iso:country":"MA",
    "wof:name":"Ait Ouwahmane",
    "wof:placetype":"locality"
},
  "geometry": {"coordinates":[-7.73681,31.45709],"type":"Point"}
}