{
  "type": "Feature",
  "properties": {
    "gn:admin1_code":"1.0",
    "gn:asciiname":"Lakouicha",
    "gn:country_code":"MA",
    "gn:dem":2,
    "gn:feature_class":"P",
    "gn:feature_code":"PPL",
    "gn:name":"Lakouicha",
    "gn:population":0,
    "gn:timezone":"Africa/Casablanca",
    "iso:country":"MA",
    "wof:name":"Lakouicha",
    "wof:placetype":"locality"
},
  "geometry": {"coordinates":[-5.64878,35.82638],"type":"Point"}
}