{
  "type": "Feature",
  "properties": {
    "gn:country":"MA",
    "gn:fcode":"ADM3",
    "gn:population":7219,
    "iso:country":"MA",
    "name:ara_x_preferred":[
        "\u0627\u0633\u062c\u0646"
    ],
    "name:ara_x_variant":[
        "\u062a\u0627\u0646\u0642\u0648\u0628"
    ],
    "name:ary_x_preferred":[
        "\u062a\u0627\u0646\u0642\u0648\u0628"
    ],
    "name:cat_x_preferred":[
        "Tanaqoub"
    ],
    "name:ceb_x_preferred":[
        "Tanaqoub"
    ],
    "name:eng_x_preferred":[
        "Tanaqoub"
    ],
    "name:fra_x_preferred":[
        "Tanaqoub"
    ],
    "name:fra_x_variant":[
        "Tanaqoub (CR)",
        "Tanaqoub (Commune Rurale)"
    ],
    "name:ita_x_preferred":[
        "Tanaqoub"
    ],
    "name:spa_x_preferred":[
        "Tanacob"
    ],
    "name:swe_x_preferred":[
        "Tanaqoub"
    ],
    "name:urd_x_preferred":[
        "\u062a\u0627\u0646\u0642\u0648\u0628"
    ],
    "qs:name":"Tanaqoub",
    "qs:photos_9r":0,
    "qs:photos_sr":0,
    "qs:pop_sr":"5",
    "wd:wordcount":59,
    "wof:name":"Tanaqoub",
    "wof:placetype":"localadmin",
    "wof:population":7219
},
  "geometry": {"coordinates":[-5.47288,35.15628],"type":"Point"}
}