{
  "type": "Feature",
  "properties": {
    "gn:admin1_code":"03",
    "gn:asciiname":"Lhachiya Lhamra",
    "gn:country_code":"MA",
    "gn:dem":848,
    "gn:feature_class":"P",
    "gn:feature_code":"PPL",
    "gn:name":"Lhachiya Lhamra",
    "gn:population":0,
    "gn:timezone":"Africa/Casablanca",
    "iso:country":"MA",
    "name:und_x_variant":[
        "El Habat el Hamra"
    ],
    "wof:name":"Lhachiya Lhamra",
    "wof:placetype":"locality"
},
  "geometry": {"coordinates":[-3.89963,33.11634],"type":"Point"}
}