{
  "type": "Feature",
  "properties": {
    "gn:admin1_code":"9.0",
    "gn:asciiname":"Dar Imzilane",
    "gn:country_code":"MA",
    "gn:dem":1820,
    "gn:feature_class":"P",
    "gn:feature_code":"PPL",
    "gn:name":"Dar Imzilane",
    "gn:population":0,
    "gn:timezone":"Africa/Casablanca",
    "iso:country":"MA",
    "wof:name":"Dar Imzilane",
    "wof:placetype":"locality"
},
  "geometry": {"coordinates":[-7.6504,30.60706],"type":"Point"}
}