{
  "type": "Feature",
  "properties": {
    "gn:admin1_code":"7.0",
    "gn:asciiname":"Arrwida",
    "gn:country_code":"MA",
    "gn:dem":615,
    "gn:feature_class":"P",
    "gn:feature_code":"PPL",
    "gn:name":"Arrwida",
    "gn:population":0,
    "gn:timezone":"Africa/Casablanca",
    "iso:country":"MA",
    "wof:name":"Arrwida",
    "wof:placetype":"locality"
},
  "geometry": {"coordinates":[-7.44102,31.81203],"type":"Point"}
}