{
  "type": "Feature",
  "properties": {
    "gn:admin1_code":"47",
    "gn:asciiname":"Ech Chidmia",
    "gn:cc2":"MA",
    "gn:country_code":"MA",
    "gn:dem":910,
    "gn:feature_class":"P",
    "gn:feature_code":"PPL",
    "gn:name":"Ech Chidmia",
    "gn:population":0,
    "gn:timezone":"Africa/Casablanca",
    "iso:country":"MA",
    "name:und_x_variant":[
        "Douar el Chidmia",
        "Ech Chidmia"
    ],
    "wof:name":"Ech Chidmia",
    "wof:placetype":"locality"
},
  "geometry": {"coordinates":[-7.58,31.96],"type":"Point"}
}