{
  "type": "Feature",
  "properties": {
    "gn:admin1_code":"07",
    "gn:asciiname":"Ed-Dehour",
    "gn:country_code":"MA",
    "gn:dem":370,
    "gn:feature_class":"P",
    "gn:feature_code":"PPL",
    "gn:name":"Ed-Dehour",
    "gn:population":0,
    "gn:timezone":"Africa/Casablanca",
    "iso:country":"MA",
    "name:und_x_variant":[
        "Douar ed Dohor",
        "Ed Dehour",
        "Dohor",
        "Ed-Dehour"
    ],
    "wof:name":"Ed-Dehour",
    "wof:placetype":"locality"
},
  "geometry": {"coordinates":[-7.73261,32.52016],"type":"Point"}
}