{
  "type": "Feature",
  "properties": {
    "gn:admin1_code":"4.0",
    "gn:asciiname":"Azib Harakat",
    "gn:country_code":"MA",
    "gn:dem":46,
    "gn:feature_class":"P",
    "gn:feature_code":"PPL",
    "gn:name":"Azib Harakat",
    "gn:population":0,
    "gn:timezone":"Africa/Casablanca",
    "iso:country":"MA",
    "wof:name":"Azib Harakat",
    "wof:placetype":"locality"
},
  "geometry": {"coordinates":[-5.81572,34.52781],"type":"Point"}
}