{
  "type": "Feature",
  "properties": {
    "gn:admin1_code":"10",
    "gn:asciiname":"Id Amiz",
    "gn:country_code":"MA",
    "gn:dem":862,
    "gn:feature_class":"P",
    "gn:feature_code":"PPL",
    "gn:name":"Id Amiz",
    "gn:population":0,
    "gn:timezone":"Africa/Casablanca",
    "iso:country":"MA",
    "name:und_x_variant":[
        "Hamza",
        "Id Hamza",
        "Id Amiz"
    ],
    "wof:name":"Id Amiz",
    "wof:placetype":"locality"
},
  "geometry": {"coordinates":[-9.79134,29.34855],"type":"Point"}
}