{
  "type": "Feature",
  "properties": {
    "gn:admin1_code":"55",
    "gn:asciiname":"Tamazirt",
    "gn:country_code":"MA",
    "gn:dem":1009,
    "gn:feature_class":"P",
    "gn:feature_code":"PPL",
    "gn:name":"Tamazirt",
    "gn:population":0,
    "gn:timezone":"Africa/Casablanca",
    "iso:country":"MA",
    "wof:name":"Tamazirt",
    "wof:placetype":"locality"
},
  "geometry": {"coordinates":[-9.38,30.64],"type":"Point"}
}