{
  "type": "Feature",
  "properties": {
    "gn:admin1_code":"9.0",
    "gn:asciiname":"Azantou",
    "gn:country_code":"MA",
    "gn:dem":710,
    "gn:feature_class":"P",
    "gn:feature_code":"PPL",
    "gn:name":"Azantou",
    "gn:population":0,
    "gn:timezone":"Africa/Casablanca",
    "iso:country":"MA",
    "wof:name":"Azantou",
    "wof:placetype":"locality"
},
  "geometry": {"coordinates":[-9.21737,29.98235],"type":"Point"}
}