{
  "type": "Feature",
  "properties": {
    "gn:admin1_code":"08",
    "gn:asciiname":"Issil",
    "gn:country_code":"MA",
    "gn:dem":1502,
    "gn:feature_class":"P",
    "gn:feature_code":"PPL",
    "gn:name":"Issil",
    "gn:population":0,
    "gn:timezone":"Africa/Casablanca",
    "iso:country":"MA",
    "wof:name":"Issil",
    "wof:placetype":"locality"
},
  "geometry": {"coordinates":[-7.28512,30.29345],"type":"Point"}
}