{
  "type": "Feature",
  "properties": {
    "gn:admin1_code":"6.0",
    "gn:asciiname":"Douar Oulad Ben Aicha",
    "gn:country_code":"MA",
    "gn:dem":132,
    "gn:feature_class":"P",
    "gn:feature_code":"PPL",
    "gn:name":"Douar Oulad Ben Aicha",
    "gn:population":0,
    "gn:timezone":"Africa/Casablanca",
    "iso:country":"MA",
    "wof:name":"Douar Oulad Ben Aicha",
    "wof:placetype":"locality"
},
  "geometry": {"coordinates":[-8.85293,32.56636],"type":"Point"}
}