{
  "type": "Feature",
  "properties": {
    "gn:admin1_code":"6.0",
    "gn:asciiname":"Khechecha",
    "gn:country_code":"MA",
    "gn:dem":418,
    "gn:feature_class":"P",
    "gn:feature_code":"PPL",
    "gn:name":"Khechecha",
    "gn:population":0,
    "gn:timezone":"Africa/Casablanca",
    "iso:country":"MA",
    "wof:name":"Khechecha",
    "wof:placetype":"locality"
},
  "geometry": {"coordinates":[-7.72164,32.78254],"type":"Point"}
}