{
  "type": "Feature",
  "properties": {
    "gn:gn_country":"MA",
    "gn:gn_fcode":"ADM3",
    "gn:gn_pop":4070,
    "gn:population":3890,
    "iso:country":"MA",
    "name:ara_x_preferred":[
        "\u0645\u0643\u0646\u0627\u0633\u0629 \u0627\u0644\u0634\u0631\u0642\u064a\u0629"
    ],
    "name:ara_x_variant":[
        "\u0645\u0643\u0646\u0627\u0633\u0629 \u0627\u0644\u063a\u0631\u0628\u064a\u0629"
    ],
    "name:cat_x_preferred":[
        "Meknassa Al Gharbia"
    ],
    "name:ceb_x_preferred":[
        "Meknassa Al Gharbia"
    ],
    "name:fra_x_preferred":[
        "Meknassa Al Gharbia"
    ],
    "name:fra_x_variant":[
        "Meknassa Al Gharbia (CR)",
        "Meknassa Al Gharbia (Commune Rurale)"
    ],
    "name:swe_x_preferred":[
        "Meknassa Al Gharbia"
    ],
    "qs_pg:aaroncc":"MA",
    "qs_pg:gn_country":"MA",
    "qs_pg:gn_fcode":"ADM3",
    "qs_pg:gn_pop":4070,
    "qs_pg:name":"Meknassa Al Gharbia",
    "qs_pg:photos_9r":0,
    "qs_pg:photos_sr":0,
    "qs_pg:pop_sr":4,
    "qs_pg:qs_pg_placetype":"localadmin",
    "wof:name":"Meknassa Al Gharbia",
    "wof:placetype":"localadmin",
    "wof:population":3890
},
  "geometry": {"coordinates":[-4.06907,34.26809],"type":"Point"}
}