{
  "type": "Feature",
  "properties": {
    "gn:admin1_code":"6.0",
    "gn:asciiname":"Laaciybiya Oulad Aicha",
    "gn:country_code":"MA",
    "gn:dem":514,
    "gn:feature_class":"P",
    "gn:feature_code":"PPL",
    "gn:name":"Laaciybiya Oulad Aicha",
    "gn:population":0,
    "gn:timezone":"Africa/Casablanca",
    "iso:country":"MA",
    "wof:name":"Laaciybiya Oulad Aicha",
    "wof:placetype":"locality"
},
  "geometry": {"coordinates":[-7.3202,33.11806],"type":"Point"}
}