{
  "type": "Feature",
  "properties": {
    "gn:admin1_code":"7.0",
    "gn:asciiname":"Douar Abadou",
    "gn:country_code":"MA",
    "gn:dem":461,
    "gn:feature_class":"P",
    "gn:feature_code":"PPL",
    "gn:name":"Douar Abadou",
    "gn:population":0,
    "gn:timezone":"Africa/Casablanca",
    "iso:country":"MA",
    "wof:name":"Douar Abadou",
    "wof:placetype":"locality"
},
  "geometry": {"coordinates":[-9.3658,31.67324],"type":"Point"}
}