{
  "type": "Feature",
  "properties": {
    "gn:admin1_code":"9.0",
    "gn:asciiname":"Iguera-n-addi",
    "gn:country_code":"MA",
    "gn:dem":34,
    "gn:feature_class":"P",
    "gn:feature_code":"PPL",
    "gn:name":"Iguera-n-addi",
    "gn:population":0,
    "gn:timezone":"Africa/Casablanca",
    "iso:country":"MA",
    "wof:name":"Iguera-n-addi",
    "wof:placetype":"locality"
},
  "geometry": {"coordinates":[-9.45406,30.368],"type":"Point"}
}