{
  "type": "Feature",
  "properties": {
    "gn:admin1_code":"07",
    "gn:asciiname":"Douar Draana",
    "gn:country_code":"MA",
    "gn:dem":599,
    "gn:feature_class":"P",
    "gn:feature_code":"PPL",
    "gn:name":"Douar Draana",
    "gn:population":0,
    "gn:timezone":"Africa/Casablanca",
    "iso:country":"MA",
    "name:und_x_variant":[
        "Draa",
        "Douar Dr\u00e2a",
        "Douar Draana"
    ],
    "wof:name":"Douar Draana",
    "wof:placetype":"locality"
},
  "geometry": {"coordinates":[-7.83005,31.5128],"type":"Point"}
}