{
  "type": "Feature",
  "properties": {
    "gn:admin1_code":"6.0",
    "gn:asciiname":"Caid Mohamed",
    "gn:country_code":"MA",
    "gn:dem":50,
    "gn:feature_class":"P",
    "gn:feature_code":"PPL",
    "gn:name":"Ca\u00efd Mohamed",
    "gn:population":0,
    "gn:timezone":"Africa/Casablanca",
    "iso:country":"MA",
    "wof:name":"Caid Mohamed",
    "wof:placetype":"locality"
},
  "geometry": {"coordinates":[-8.54522,33.17375],"type":"Point"}
}