{
  "type": "Feature",
  "properties": {
    "gn:admin1_code":"08",
    "gn:asciiname":"Ammar",
    "gn:country_code":"MA",
    "gn:dem":927,
    "gn:feature_class":"P",
    "gn:feature_code":"PPL",
    "gn:name":"Ammar",
    "gn:population":0,
    "gn:timezone":"Africa/Casablanca",
    "iso:country":"MA",
    "name:ara_x_preferred":[
        "\u0639\u0645\u0627\u0631"
    ],
    "name:deu_x_preferred":[
        "Ammar"
    ],
    "name:fra_x_preferred":[
        "Ammar"
    ],
    "name:ita_x_preferred":[
        "Ammar"
    ],
    "name:rus_x_preferred":[
        "\u0410\u043c\u043c\u0430\u0440"
    ],
    "name:sqi_x_preferred":[
        "Ammar"
    ],
    "name:und_x_variant":[
        "Ksar Amar"
    ],
    "wof:name":"Ammar",
    "wof:placetype":"locality"
},
  "geometry": {"coordinates":[-5.22312,31.18247],"type":"Point"}
}