{
  "type": "Feature",
  "properties": {
    "gn:admin1_code":"08",
    "gn:asciiname":"Ammar",
    "gn:country_code":"MA",
    "gn:dem":927,
    "gn:feature_class":"P",
    "gn:feature_code":"PPL",
    "gn:name":"Ammar",
    "gn:population":0,
    "gn:timezone":"Africa/Casablanca",
    "iso:country":"MA",
    "name:und_x_variant":[
        "Ksar Amar",
        "Ammar"
    ],
    "wof:name":"Ammar",
    "wof:placetype":"locality"
},
  "geometry": {"coordinates":[-5.22312,31.18247],"type":"Point"}
}