{
  "type": "Feature",
  "properties": {
    "gn:admin1_code":"4.0",
    "gn:asciiname":"Sfirj",
    "gn:country_code":"MA",
    "gn:dem":68,
    "gn:feature_class":"P",
    "gn:feature_code":"PPL",
    "gn:name":"Sfirj",
    "gn:population":0,
    "gn:timezone":"Africa/Casablanca",
    "iso:country":"MA",
    "wof:name":"Sfirj",
    "wof:placetype":"neighbourhood"
},
  "geometry": {"coordinates":[-6.74273,34.07776],"type":"Point"}
}