{
  "type": "Feature",
  "properties": {
    "gn:admin1_code":"07",
    "gn:asciiname":"Douar Belaid Labbaara",
    "gn:country_code":"MA",
    "gn:dem":308,
    "gn:feature_class":"P",
    "gn:feature_code":"PPL",
    "gn:name":"Douar Belaid Labbaara",
    "gn:population":0,
    "gn:timezone":"Africa/Casablanca",
    "iso:country":"MA",
    "name:und_x_variant":[
        "Bela\u00efd ben Bouara",
        "Ben A\u00efd Boua\u00efra",
        "Douar A\u00efd Ben Boua\u00efra",
        "Douar Belaid Labbaara"
    ],
    "wof:name":"Douar Belaid Labbaara",
    "wof:placetype":"locality"
},
  "geometry": {"coordinates":[-8.50699,31.68597],"type":"Point"}
}