{
  "type": "Feature",
  "properties": {
    "gn:admin1_code":"1.0",
    "gn:asciiname":"Douar Ain Zitoune",
    "gn:country_code":"MA",
    "gn:dem":50,
    "gn:feature_class":"P",
    "gn:feature_code":"PPL",
    "gn:name":"Douar Ain Zitoune",
    "gn:population":0,
    "gn:timezone":"Africa/Casablanca",
    "iso:country":"MA",
    "wof:name":"Douar Ain Zitoune",
    "wof:placetype":"locality"
},
  "geometry": {"coordinates":[-5.91821,35.65004000000001],"type":"Point"}
}