{
  "type": "Feature",
  "properties": {
    "gn:admin1_code":"9.0",
    "gn:asciiname":"Takalilt",
    "gn:country_code":"MA",
    "gn:dem":1514,
    "gn:feature_class":"P",
    "gn:feature_code":"PPL",
    "gn:name":"Takalilt",
    "gn:population":0,
    "gn:timezone":"Africa/Casablanca",
    "iso:country":"MA",
    "wof:name":"Takalilt",
    "wof:placetype":"locality"
},
  "geometry": {"coordinates":[-8.33318,30.84697],"type":"Point"}
}