{
  "type": "Feature",
  "properties": {
    "gn:admin1_code":"06",
    "gn:asciiname":"Oulad Amara",
    "gn:country_code":"MA",
    "gn:dem":17,
    "gn:feature_class":"P",
    "gn:feature_code":"PPL",
    "gn:name":"Oulad Amara",
    "gn:population":0,
    "gn:timezone":"Africa/Casablanca",
    "iso:country":"MA",
    "name:und_x_variant":[
        "Qa\u00e7hat al Hmira",
        "Qasbat ben Hamira",
        "Kasba Bou Hamira",
        "Oulad Amara"
    ],
    "wof:name":"Oulad Amara",
    "wof:placetype":"locality"
},
  "geometry": {"coordinates":[-7.15492,33.8087],"type":"Point"}
}