{
  "type": "Feature",
  "properties": {
    "gn:admin1_code":"7.0",
    "gn:asciiname":"Ibidarene",
    "gn:country_code":"MA",
    "gn:dem":322,
    "gn:feature_class":"P",
    "gn:feature_code":"PPL",
    "gn:name":"Ibidarene",
    "gn:population":0,
    "gn:timezone":"Africa/Casablanca",
    "iso:country":"MA",
    "wof:name":"Ibidarene",
    "wof:placetype":"locality"
},
  "geometry": {"coordinates":[-9.67312,31.13061],"type":"Point"}
}