{
  "type": "Feature",
  "properties": {
    "gn:admin1_code":"08",
    "gn:asciiname":"Irherm",
    "gn:country_code":"MA",
    "gn:dem":1649,
    "gn:feature_class":"P",
    "gn:feature_code":"PPL",
    "gn:name":"Irherm",
    "gn:population":0,
    "gn:timezone":"Africa/Casablanca",
    "iso:country":"MA",
    "name:und_x_variant":[
        "Tazadot",
        "Ighrem",
        "Irherm"
    ],
    "wof:name":"Irherm",
    "wof:placetype":"locality"
},
  "geometry": {"coordinates":[-7.42815,31.15101],"type":"Point"}
}