{
  "type": "Feature",
  "properties": {
    "gn:admin1_code":"08",
    "gn:asciiname":"Irherm",
    "gn:country_code":"MA",
    "gn:dem":1649,
    "gn:feature_class":"P",
    "gn:feature_code":"PPL",
    "gn:name":"Irherm",
    "gn:population":0,
    "gn:timezone":"Africa/Casablanca",
    "iso:country":"MA",
    "name:ara_x_preferred":[
        "\u0625\u064a\u063a\u0631\u0645"
    ],
    "name:cat_x_preferred":[
        "Irherm"
    ],
    "name:deu_x_preferred":[
        "Igherm"
    ],
    "name:fra_x_preferred":[
        "Irherm"
    ],
    "name:por_x_preferred":[
        "Irherm"
    ],
    "name:und_x_variant":[
        "Tazadot",
        "Ighrem"
    ],
    "wof:name":"Irherm",
    "wof:placetype":"locality"
},
  "geometry": {"coordinates":[-7.42815,31.15101],"type":"Point"}
}