{
  "type": "Feature",
  "properties": {
    "gn:admin1_code":"5.0",
    "gn:asciiname":"Oulad Charef",
    "gn:country_code":"MA",
    "gn:dem":870,
    "gn:feature_class":"P",
    "gn:feature_code":"PPL",
    "gn:name":"Oulad Charef",
    "gn:population":0,
    "gn:timezone":"Africa/Casablanca",
    "iso:country":"MA",
    "wof:name":"Oulad Charef",
    "wof:placetype":"locality"
},
  "geometry": {"coordinates":[-6.6308,32.99878],"type":"Point"}
}