{
  "type": "Feature",
  "properties": {
    "gn:admin1_code":"7.0",
    "gn:asciiname":"Dar Abdarrahim Bel Ghali",
    "gn:country_code":"MA",
    "gn:dem":501,
    "gn:feature_class":"P",
    "gn:feature_code":"PPL",
    "gn:name":"Dar Abdarrahim Bel Ghali",
    "gn:population":0,
    "gn:timezone":"Africa/Casablanca",
    "iso:country":"MA",
    "wof:name":"Dar Abdarrahim Bel Ghali",
    "wof:placetype":"locality"
},
  "geometry": {"coordinates":[-7.86795,31.59953],"type":"Point"}
}