{
  "type": "Feature",
  "properties": {
    "gn:country":"MA",
    "gn:fcode":"ADM3",
    "gn:population":11365,
    "iso:country":"MA",
    "name:ara_x_preferred":[
        "\u0627\u062c\u0628\u064a\u0644"
    ],
    "name:ara_x_variant":[
        "\u0627\u0644\u062c\u0648\u0627\u0644\u0629"
    ],
    "name:azb_x_preferred":[
        "\u0627\u0644\u062c\u0648\u0627\u0644\u0647"
    ],
    "name:cat_x_preferred":[
        "Jouala"
    ],
    "name:ceb_x_preferred":[
        "Jouala"
    ],
    "name:fas_x_preferred":[
        "\u0627\u0644\u062c\u0648\u0627\u0644\u0647"
    ],
    "name:fra_x_preferred":[
        "Jouala"
    ],
    "name:fra_x_variant":[
        "Jouala (CR)",
        "Jouala (Commune Rurale)"
    ],
    "name:ita_x_preferred":[
        "Jouala"
    ],
    "name:swe_x_preferred":[
        "Jouala"
    ],
    "qs_pg:aaroncc":"MA",
    "qs_pg:gn_country":"MA",
    "qs_pg:gn_fcode":"ADM3",
    "qs_pg:gn_pop":11365,
    "qs_pg:name":"Jouala",
    "qs_pg:photos_9r":0,
    "qs_pg:photos_sr":0,
    "qs_pg:pop_sr":6,
    "qs_pg:qs_pg_placetype":"localadmin",
    "wof:name":"Jouala",
    "wof:placetype":"localadmin",
    "wof:population":11168
},
  "geometry": {"coordinates":[-7.47137,31.90507],"type":"Point"}
}