{
  "type": "Feature",
  "properties": {
    "gn:admin1_code":"6.0",
    "gn:asciiname":"Sidi El Bettache",
    "gn:country_code":"MA",
    "gn:dem":42,
    "gn:feature_class":"P",
    "gn:feature_code":"PPL",
    "gn:name":"Sidi El Bettache",
    "gn:population":0,
    "gn:timezone":"Africa/Casablanca",
    "iso:country":"MA",
    "wof:name":"Sidi El Bettache",
    "wof:placetype":"locality"
},
  "geometry": {"coordinates":[-8.54753,33.1959],"type":"Point"}
}