{
  "type": "Feature",
  "properties": {
    "gn:admin1_code":"01",
    "gn:asciiname":"El Knatene",
    "gn:country_code":"MA",
    "gn:dem":1181,
    "gn:feature_class":"P",
    "gn:feature_code":"PPL",
    "gn:name":"El Knatene",
    "gn:population":0,
    "gn:timezone":"Africa/Casablanca",
    "iso:country":"MA",
    "name:und_x_variant":[
        "El Knatel",
        "El Knatene"
    ],
    "wof:name":"El Knatene",
    "wof:placetype":"locality"
},
  "geometry": {"coordinates":[-4.41,34.85],"type":"Point"}
}