{
  "type": "Feature",
  "properties": {
    "gn:admin1_code":"05",
    "gn:asciiname":"Tit-n-Blal",
    "gn:country_code":"MA",
    "gn:dem":1634,
    "gn:feature_class":"P",
    "gn:feature_code":"PPL",
    "gn:name":"Tit-n-Blal",
    "gn:population":0,
    "gn:timezone":"Africa/Casablanca",
    "iso:country":"MA",
    "name:und_x_variant":[
        "Titon Belal",
        "Tit\u00e8n Bellel",
        "Titene Bellel",
        "Tit-n-Blal"
    ],
    "wof:name":"Tit-n-Blal",
    "wof:placetype":"locality"
},
  "geometry": {"coordinates":[-5.62901,32.45122],"type":"Point"}
}