{
  "type": "Feature",
  "properties": {
    "gn:admin1_code":"10",
    "gn:asciiname":"Id Rhami",
    "gn:country_code":"MA",
    "gn:dem":1334,
    "gn:feature_class":"P",
    "gn:feature_code":"PPL",
    "gn:name":"Id Rhami",
    "gn:population":0,
    "gn:timezone":"Africa/Casablanca",
    "iso:country":"MA",
    "wof:name":"Id Rhami",
    "wof:placetype":"locality"
},
  "geometry": {"coordinates":[-9.36723,29.37313],"type":"Point"}
}