{
  "type": "Feature",
  "properties": {
    "gn:admin1_code":"1.0",
    "gn:asciiname":"Qoubie Lfouqi",
    "gn:country_code":"MA",
    "gn:dem":473,
    "gn:feature_class":"P",
    "gn:feature_code":"PPL",
    "gn:name":"Qoubie Lfouqi",
    "gn:population":0,
    "gn:timezone":"Africa/Casablanca",
    "iso:country":"MA",
    "wof:name":"Qoubie Lfouqi",
    "wof:placetype":"locality"
},
  "geometry": {"coordinates":[-4.32309,35.02255],"type":"Point"}
}