{
  "type": "Feature",
  "properties": {
    "gn:admin1_code":"7.0",
    "gn:asciiname":"Bou Tazert",
    "gn:country_code":"MA",
    "gn:dem":619,
    "gn:feature_class":"P",
    "gn:feature_code":"PPL",
    "gn:name":"Bou Tazert",
    "gn:population":0,
    "gn:timezone":"Africa/Casablanca",
    "iso:country":"MA",
    "wof:name":"Bou Tazert",
    "wof:placetype":"locality"
},
  "geometry": {"coordinates":[-7.88964,31.48686],"type":"Point"}
}