{
  "type": "Feature",
  "properties": {
    "gn:admin1_code":"9.0",
    "gn:asciiname":"Ljort",
    "gn:country_code":"MA",
    "gn:dem":60,
    "gn:feature_class":"P",
    "gn:feature_code":"PPL",
    "gn:name":"Ljort",
    "gn:population":0,
    "gn:timezone":"Africa/Casablanca",
    "iso:country":"MA",
    "wof:name":"Ljort",
    "wof:placetype":"locality"
},
  "geometry": {"coordinates":[-9.35431,30.3751],"type":"Point"}
}