{
  "type": "Feature",
  "properties": {
    "gn:admin1_code":"1.0",
    "gn:asciiname":"Douar Ennachcharine",
    "gn:country_code":"MA",
    "gn:dem":285,
    "gn:feature_class":"P",
    "gn:feature_code":"PPL",
    "gn:name":"Douar Ennachcharine",
    "gn:population":0,
    "gn:timezone":"Africa/Casablanca",
    "iso:country":"MA",
    "wof:name":"Douar Ennachcharine",
    "wof:placetype":"locality"
},
  "geometry": {"coordinates":[-5.61821,34.9142],"type":"Point"}
}