{
  "type": "Feature",
  "properties": {
    "gn:admin1_code":"9.0",
    "gn:asciiname":"Ait El Cadi",
    "gn:country_code":"MA",
    "gn:dem":147,
    "gn:feature_class":"P",
    "gn:feature_code":"PPL",
    "gn:name":"A\u00eft El Cadi",
    "gn:population":0,
    "gn:timezone":"Africa/Casablanca",
    "iso:country":"MA",
    "wof:name":"Ait El Cadi",
    "wof:placetype":"locality"
},
  "geometry": {"coordinates":[-9.14642,30.48018],"type":"Point"}
}