{
  "type": "Feature",
  "properties": {
    "gn:admin1_code":"01",
    "gn:admin2_code":"51.0",
    "gn:admin3_code":"1505101071.0",
    "gn:asciiname":"Targuist",
    "gn:country_code":"MA",
    "gn:dem":1029,
    "gn:feature_class":"P",
    "gn:feature_code":"PPLA3",
    "gn:name":"Targuist",
    "gn:population":11560,
    "gn:timezone":"Africa/Casablanca",
    "iso:country":"MA",
    "name:ara_x_preferred":[
        "\u062a\u0627\u0631\u062c\u064a\u0633\u062a"
    ],
    "name:cat_x_preferred":[
        "Targuist"
    ],
    "name:ceb_x_preferred":[
        "Targuist"
    ],
    "name:deu_x_preferred":[
        "Targuist"
    ],
    "name:fra_x_preferred":[
        "Targuist"
    ],
    "name:ita_x_preferred":[
        "Targuist"
    ],
    "name:kab_x_preferred":[
        "Targist"
    ],
    "name:nld_x_preferred":[
        "Targuist"
    ],
    "name:rus_x_preferred":[
        "\u0422\u0430\u0440\u0433\u0432\u0438\u0441\u0442"
    ],
    "name:spa_x_preferred":[
        "Targuist"
    ],
    "name:swe_x_preferred":[
        "Targuist"
    ],
    "name:urd_x_preferred":[
        "\u062a\u0627\u0631\u062c\u06cc\u0633\u062a"
    ],
    "name:zho_x_preferred":[
        "\u5854\u723e\u5409\u65af\u7279"
    ],
    "wof:name":"Targuist",
    "wof:placetype":"locality",
    "wof:population":11560
},
  "geometry": {"coordinates":[-4.31856,34.93769],"type":"Point"}
}