{
  "type": "Feature",
  "properties": {
    "gn:admin1_code":"5.0",
    "gn:asciiname":"Lakdadra",
    "gn:country_code":"MA",
    "gn:dem":838,
    "gn:feature_class":"P",
    "gn:feature_code":"PPL",
    "gn:name":"Lakdadra",
    "gn:population":0,
    "gn:timezone":"Africa/Casablanca",
    "iso:country":"MA",
    "wof:name":"Lakdadra",
    "wof:placetype":"locality"
},
  "geometry": {"coordinates":[-6.33828,32.87522],"type":"Point"}
}