{
  "type": "Feature",
  "properties": {
    "gn:admin1_code":"1.0",
    "gn:asciiname":"Douar Laazaba",
    "gn:country_code":"MA",
    "gn:dem":211,
    "gn:feature_class":"P",
    "gn:feature_code":"PPL",
    "gn:name":"Douar Laazaba",
    "gn:population":0,
    "gn:timezone":"Africa/Casablanca",
    "iso:country":"MA",
    "wof:name":"Douar Laazaba",
    "wof:placetype":"locality"
},
  "geometry": {"coordinates":[-5.30206,34.60889],"type":"Point"}
}