{
  "type": "Feature",
  "properties": {
    "gn:country":"MA",
    "gn:fcode":"ADM3",
    "gn:pop":9554,
    "iso:country":"MA",
    "name:ara_x_preferred":[
        "\u0623\u064a\u062a \u0628\u0644\u0642\u0627\u0633\u0645"
    ],
    "name:ceb_x_preferred":[
        "Oulmes"
    ],
    "name:fra_x_preferred":[
        "Oulmes"
    ],
    "name:fra_x_variant":[
        "Oulmes (CR)",
        "Oulmes (Commune Rurale)"
    ],
    "name:nld_x_preferred":[
        "Oulmes"
    ],
    "name:swe_x_preferred":[
        "Oulmes"
    ],
    "qs:name":"Oulmes",
    "qs:photos_9r":0,
    "qs:photos_sr":0,
    "qs:pop_sr":"5",
    "wd:wordcount":29,
    "wof:name":"Oulmes",
    "wof:placetype":"localadmin",
    "wof:population":9554
},
  "geometry": {"coordinates":[-6.00291,33.42349],"type":"Point"}
}