{
  "type": "Feature",
  "properties": {
    "gn:admin1_code":"2.0",
    "gn:asciiname":"Ibou Halil",
    "gn:country_code":"MA",
    "gn:dem":171,
    "gn:feature_class":"P",
    "gn:feature_code":"PPL",
    "gn:name":"Ibou Halil",
    "gn:population":0,
    "gn:timezone":"Africa/Casablanca",
    "iso:country":"MA",
    "wof:name":"Ibou Halil",
    "wof:placetype":"locality"
},
  "geometry": {"coordinates":[-3.79271,35.10052],"type":"Point"}
}