{
  "type": "Feature",
  "properties": {
    "gn:admin1_code":"05",
    "gn:asciiname":"Douar el Koribis",
    "gn:country_code":"MA",
    "gn:dem":784,
    "gn:feature_class":"P",
    "gn:feature_code":"PPL",
    "gn:name":"Douar el Koribis",
    "gn:population":0,
    "gn:timezone":"Africa/Casablanca",
    "iso:country":"MA",
    "wof:name":"Douar el Koribis",
    "wof:placetype":"locality"
},
  "geometry": {"coordinates":[-7.13356,31.74936],"type":"Point"}
}