{
  "type": "Feature",
  "properties": {
    "gn:admin1_code":"7.0",
    "gn:asciiname":"Ayt Athami",
    "gn:country_code":"MA",
    "gn:dem":657,
    "gn:feature_class":"P",
    "gn:feature_code":"PPL",
    "gn:name":"Ayt Athami",
    "gn:population":0,
    "gn:timezone":"Africa/Casablanca",
    "iso:country":"MA",
    "wof:name":"Ayt Athami",
    "wof:placetype":"locality"
},
  "geometry": {"coordinates":[-7.41941,31.74839],"type":"Point"}
}