{
  "type": "Feature",
  "properties": {
    "gn:admin1_code":"9.0",
    "gn:asciiname":"Ighil-n-Igguia",
    "gn:country_code":"MA",
    "gn:dem":1064,
    "gn:feature_class":"P",
    "gn:feature_code":"PPL",
    "gn:name":"Ighil-n-Igguia",
    "gn:population":0,
    "gn:timezone":"Africa/Casablanca",
    "iso:country":"MA",
    "wof:name":"Ighil-n-Igguia",
    "wof:placetype":"locality"
},
  "geometry": {"coordinates":[-8.63565,30.26399],"type":"Point"}
}