{
  "type": "Feature",
  "properties": {
    "gn:admin1_code":"08",
    "gn:asciiname":"Ksar el Borj",
    "gn:country_code":"MA",
    "gn:dem":1115,
    "gn:feature_class":"P",
    "gn:feature_code":"PPL",
    "gn:name":"Ksar el Borj",
    "gn:population":0,
    "gn:timezone":"Africa/Casablanca",
    "iso:country":"MA",
    "name:und_x_variant":[
        "El Bordj",
        "Ksar el Borj"
    ],
    "wof:name":"Ksar el Borj",
    "wof:placetype":"locality"
},
  "geometry": {"coordinates":[-4.96,31.81],"type":"Point"}
}