{
  "type": "Feature",
  "properties": {
    "gn:admin1_code":"3.0",
    "gn:asciiname":"Douar Ain Ereommane",
    "gn:country_code":"MA",
    "gn:dem":418,
    "gn:feature_class":"P",
    "gn:feature_code":"PPL",
    "gn:name":"Douar Ain Ereommane",
    "gn:population":0,
    "gn:timezone":"Africa/Casablanca",
    "iso:country":"MA",
    "wof:name":"Douar Ain Ereommane",
    "wof:placetype":"locality"
},
  "geometry": {"coordinates":[-5.06222,34.10988],"type":"Point"}
}