{
  "type": "Feature",
  "properties": {
    "gn:admin1_code":"01",
    "gn:admin2_code":"571.0",
    "gn:admin3_code":"1657105072.0",
    "gn:asciiname":"Azla",
    "gn:country_code":"MA",
    "gn:dem":9,
    "gn:feature_class":"P",
    "gn:feature_code":"PPLA3",
    "gn:name":"Azla",
    "gn:population":0,
    "gn:timezone":"Africa/Casablanca",
    "iso:country":"MA",
    "wof:name":"Azla",
    "wof:placetype":"locality"
},
  "geometry": {"coordinates":[-5.24472,35.55303],"type":"Point"}
}