{
  "type": "Feature",
  "properties": {
    "gn:country":"MA",
    "gn:fcode":"ADM3",
    "gn:pop":16258,
    "iso:country":"MA",
    "name:ara_x_preferred":[
        "\u062a\u064a\u0646\u0632\u0648\u0644\u064a\u0646"
    ],
    "name:fra_x_preferred":[
        "Mehdya"
    ],
    "name:fra_x_variant":[
        "Mehdya (MU)",
        "Mehdya (Commune Urbaine)"
    ],
    "qs:name":"Mehdya",
    "qs:photos_9r":0,
    "qs:photos_sr":0,
    "qs:pop_sr":"6",
    "wd:wordcount":634,
    "wof:name":"Mehdya",
    "wof:placetype":"localadmin",
    "wof:population":16258
},
  "geometry": {"coordinates":[-6.66193,34.26234],"type":"Point"}
}