{
  "type": "Feature",
  "properties": {
    "gn:country":"MA",
    "gn:fcode":"ADM3",
    "gn:population":16258,
    "iso:country":"MA",
    "name:ara_x_preferred":[
        "\u062a\u064a\u0646\u0632\u0648\u0644\u064a\u0646"
    ],
    "name:ara_x_variant":[
        "\u0627\u0644\u0645\u0647\u062f\u064a\u0629"
    ],
    "name:ary_x_preferred":[
        "\u0645\u0647\u062f\u064a\u0629"
    ],
    "name:bul_x_preferred":[
        "\u041c\u0435\u0445\u0434\u044f"
    ],
    "name:cat_x_preferred":[
        "Mehdya"
    ],
    "name:ceb_x_preferred":[
        "Mehdya"
    ],
    "name:deu_x_preferred":[
        "Mehdia"
    ],
    "name:eng_x_preferred":[
        "Mehdya"
    ],
    "name:eus_x_preferred":[
        "Mehdia"
    ],
    "name:fas_x_preferred":[
        "\u0627\u0644\u0645\u0647\u062f\u064a\u0647"
    ],
    "name:fra_x_preferred":[
        "Mehdya"
    ],
    "name:fra_x_variant":[
        "Mehdya (MU)",
        "Mehdya (Commune Urbaine)",
        "Mehdia"
    ],
    "name:ita_x_preferred":[
        "Mehdya"
    ],
    "name:jpn_x_preferred":[
        "\u30de\u30cf\u30c7\u30a3\u30a2"
    ],
    "name:por_x_preferred":[
        "Mehdia"
    ],
    "name:rus_x_preferred":[
        "\u041c\u0435\u0445\u0434\u0438\u044f"
    ],
    "name:spa_x_preferred":[
        "Mehd\u00eda"
    ],
    "name:swe_x_preferred":[
        "Mehdya"
    ],
    "name:ukr_x_preferred":[
        "\u041c\u0435\u0445\u0434\u0456\u044f"
    ],
    "qs:name":"Mehdya",
    "qs:photos_9r":0,
    "qs:photos_sr":0,
    "qs:pop_sr":"6",
    "wd:wordcount":634,
    "wof:name":"Mehdya",
    "wof:placetype":"localadmin",
    "wof:population":16258
},
  "geometry": {"coordinates":[-6.66193,34.26234],"type":"Point"}
}