{
  "type": "Feature",
  "properties": {
    "gn:admin1_code":"7.0",
    "gn:asciiname":"Takoucht",
    "gn:country_code":"MA",
    "gn:dem":1374,
    "gn:feature_class":"P",
    "gn:feature_code":"PPL",
    "gn:name":"Takoucht",
    "gn:population":0,
    "gn:timezone":"Africa/Casablanca",
    "iso:country":"MA",
    "wof:name":"Takoucht",
    "wof:placetype":"locality"
},
  "geometry": {"coordinates":[-7.82262,31.29222],"type":"Point"}
}