{
  "type": "Feature",
  "properties": {
    "gn:admin1_code":"3.0",
    "gn:asciiname":"Dar Hdidioui Mohamed",
    "gn:country_code":"MA",
    "gn:dem":1218,
    "gn:feature_class":"P",
    "gn:feature_code":"PPL",
    "gn:name":"Dar Hdidioui Mohamed",
    "gn:population":0,
    "gn:timezone":"Africa/Casablanca",
    "iso:country":"MA",
    "wof:name":"Dar Hdidioui Mohamed",
    "wof:placetype":"locality"
},
  "geometry": {"coordinates":[-5.61167,33.53927],"type":"Point"}
}