{
  "type": "Feature",
  "properties": {
    "gn:admin1_code":"01",
    "gn:asciiname":"Douar Gzira",
    "gn:country_code":"MA",
    "gn:dem":280,
    "gn:feature_class":"P",
    "gn:feature_code":"PPL",
    "gn:name":"Douar Gzira",
    "gn:population":0,
    "gn:timezone":"Africa/Casablanca",
    "iso:country":"MA",
    "name:und_x_variant":[
        "Gzira",
        "Guezira",
        "Douar Gzira"
    ],
    "wof:name":"Douar Gzira",
    "wof:placetype":"locality"
},
  "geometry": {"coordinates":[-5.38802,34.71867],"type":"Point"}
}