{
  "type": "Feature",
  "properties": {
    "gn:admin1_code":"2.0",
    "gn:asciiname":"Dar El Haj Ahmed",
    "gn:country_code":"MA",
    "gn:dem":606,
    "gn:feature_class":"P",
    "gn:feature_code":"PPL",
    "gn:name":"Dar El Haj Ahmed",
    "gn:population":0,
    "gn:timezone":"Africa/Casablanca",
    "iso:country":"MA",
    "wof:name":"Dar El Haj Ahmed",
    "wof:placetype":"locality"
},
  "geometry": {"coordinates":[-1.98369,34.67435],"type":"Point"}
}