{
  "type": "Feature",
  "properties": {
    "gn:admin1_code":"09",
    "gn:asciiname":"Agadir Laghdir",
    "gn:country_code":"MA",
    "gn:dem":613,
    "gn:feature_class":"P",
    "gn:feature_code":"PPL",
    "gn:name":"Agadir Laghdir",
    "gn:population":0,
    "gn:timezone":"Africa/Casablanca",
    "iso:country":"MA",
    "name:und_x_variant":[
        "Agadir Oudir"
    ],
    "wof:name":"Agadir Laghdir",
    "wof:placetype":"locality"
},
  "geometry": {"coordinates":[-8.46241,30.71079000000001],"type":"Point"}
}