{
  "type": "Feature",
  "properties": {
    "gn:admin1_code":"8.0",
    "gn:asciiname":"Aning",
    "gn:country_code":"MA",
    "gn:dem":1260,
    "gn:feature_class":"P",
    "gn:feature_code":"PPL",
    "gn:name":"Aning",
    "gn:population":0,
    "gn:timezone":"Africa/Casablanca",
    "iso:country":"MA",
    "wof:name":"Aning",
    "wof:placetype":"locality"
},
  "geometry": {"coordinates":[-6.87382,30.77846],"type":"Point"}
}