{
  "type": "Feature",
  "properties": {
    "gn:admin1_code":"06",
    "gn:asciiname":"Dar El Kouassem",
    "gn:country_code":"MA",
    "gn:dem":61,
    "gn:feature_class":"P",
    "gn:feature_code":"PPL",
    "gn:name":"Dar El Kouassem",
    "gn:population":0,
    "gn:timezone":"Africa/Casablanca",
    "iso:country":"MA",
    "name:und_x_variant":[
        "Abbas bel Kassem",
        "Douar Abbas bel Kassem",
        "Dar El Kouassem"
    ],
    "wof:name":"Dar El Kouassem",
    "wof:placetype":"locality"
},
  "geometry": {"coordinates":[-8.61235,33.06414],"type":"Point"}
}