{
  "type": "Feature",
  "properties": {
    "gn:admin1_code":"01",
    "gn:asciiname":"Douar Anzagh",
    "gn:country_code":"MA",
    "gn:dem":177,
    "gn:feature_class":"P",
    "gn:feature_code":"PPL",
    "gn:name":"Douar Anzagh",
    "gn:population":0,
    "gn:timezone":"Africa/Casablanca",
    "iso:country":"MA",
    "name:und_x_variant":[
        "Anzarh",
        "Anzagh",
        "Douar Anzagh"
    ],
    "wof:name":"Douar Anzagh",
    "wof:placetype":"locality"
},
  "geometry": {"coordinates":[-4.40669,35.09108],"type":"Point"}
}