{
  "type": "Feature",
  "properties": {
    "gn:gn_country":"MA",
    "gn:gn_fcode":"ADM3",
    "gn:gn_pop":7402,
    "gn:population":7023,
    "iso:country":"MA",
    "name:ara_x_preferred":[
        "\u0628\u0648\u0639\u0628\u0648\u0637 \u0627\u0645\u062f\u0644\u0627\u0646"
    ],
    "name:ara_x_variant":[
        "\u0625\u0634\u0645\u0631\u0627\u0631\u0646"
    ],
    "name:cat_x_preferred":[
        "Ichamraren"
    ],
    "name:ceb_x_preferred":[
        "Ichamraren"
    ],
    "name:fra_x_preferred":[
        "Ichamraren"
    ],
    "name:fra_x_variant":[
        "Ichamraren (CR)",
        "Ichamraren (Commune Rurale)"
    ],
    "name:ita_x_preferred":[
        "Ichamraren"
    ],
    "name:swe_x_preferred":[
        "Ichamraren"
    ],
    "qs_pg:aaroncc":"MA",
    "qs_pg:gn_country":"MA",
    "qs_pg:gn_fcode":"ADM3",
    "qs_pg:gn_pop":7402,
    "qs_pg:name":"Ichamraren",
    "qs_pg:photos_9r":0,
    "qs_pg:photos_sr":0,
    "qs_pg:pop_sr":5,
    "qs_pg:qs_pg_placetype":"localadmin",
    "wof:name":"Ichamraren",
    "wof:placetype":"localadmin",
    "wof:population":7023
},
  "geometry": {"coordinates":[-9.12858,31.12821],"type":"Point"}
}