{
  "type": "Feature",
  "properties": {
    "gn:admin1_code":"6.0",
    "gn:asciiname":"Zawyat Moulay ac Cadiq",
    "gn:country_code":"MA",
    "gn:dem":87,
    "gn:feature_class":"P",
    "gn:feature_code":"PPL",
    "gn:name":"Zawyat Moulay a\u00e7 \u00c7adiq",
    "gn:population":0,
    "gn:timezone":"Africa/Casablanca",
    "iso:country":"MA",
    "wof:name":"Zawyat Moulay ac Cadiq",
    "wof:placetype":"locality"
},
  "geometry": {"coordinates":[-8.26419,33.25234],"type":"Point"}
}