{
  "type": "Feature",
  "properties": {
    "gn:admin1_code":"09",
    "gn:asciiname":"Tagouzoult",
    "gn:country_code":"MA",
    "gn:dem":428,
    "gn:feature_class":"P",
    "gn:feature_code":"PPL",
    "gn:name":"Tagouzoult",
    "gn:population":0,
    "gn:timezone":"Africa/Casablanca",
    "iso:country":"MA",
    "name:und_x_variant":[
        "Tagaouzoult"
    ],
    "wof:name":"Tagouzoult",
    "wof:placetype":"locality"
},
  "geometry": {"coordinates":[-8.47598,30.54734],"type":"Point"}
}