{
  "type": "Feature",
  "properties": {
    "gn:admin1_code":"07",
    "gn:asciiname":"Douar Lemharet",
    "gn:country_code":"MA",
    "gn:dem":226,
    "gn:feature_class":"P",
    "gn:feature_code":"PPL",
    "gn:name":"Douar Lemharet",
    "gn:population":0,
    "gn:timezone":"Africa/Casablanca",
    "iso:country":"MA",
    "name:und_x_variant":[
        "Douar el Meharat",
        "El Meharat",
        "Douar Lemharet"
    ],
    "wof:name":"Douar Lemharet",
    "wof:placetype":"locality"
},
  "geometry": {"coordinates":[-8.65468,32.34696],"type":"Point"}
}