{
  "type": "Feature",
  "properties": {
    "gn:admin1_code":"3.0",
    "gn:asciiname":"Hajjiyine",
    "gn:country_code":"MA",
    "gn:dem":509,
    "gn:feature_class":"P",
    "gn:feature_code":"PPL",
    "gn:name":"Hajjiyine",
    "gn:population":0,
    "gn:timezone":"Africa/Casablanca",
    "iso:country":"MA",
    "wof:name":"Hajjiyine",
    "wof:placetype":"locality"
},
  "geometry": {"coordinates":[-5.05804,34.58693],"type":"Point"}
}