{
  "type": "Feature",
  "properties": {
    "gn:admin1_code":"7.0",
    "gn:asciiname":"Oulad Jemaa",
    "gn:country_code":"MA",
    "gn:dem":415,
    "gn:feature_class":"P",
    "gn:feature_code":"PPL",
    "gn:name":"Oulad Jemaa",
    "gn:population":0,
    "gn:timezone":"Africa/Casablanca",
    "iso:country":"MA",
    "wof:name":"Oulad Jemaa",
    "wof:placetype":"locality"
},
  "geometry": {"coordinates":[-8.99597,31.92316],"type":"Point"}
}