{
  "type": "Feature",
  "properties": {
    "gn:admin1_code":"07",
    "gn:asciiname":"Assoul",
    "gn:country_code":"MA",
    "gn:dem":1391,
    "gn:feature_class":"P",
    "gn:feature_code":"PPL",
    "gn:name":"Assoul",
    "gn:population":0,
    "gn:timezone":"Africa/Casablanca",
    "iso:country":"MA",
    "name:ara_x_preferred":[
        "\u0623\u0633\u0648\u0644"
    ],
    "name:azb_x_preferred":[
        "\u0627\u0633\u0648\u0644"
    ],
    "name:cat_x_preferred":[
        "Assoul"
    ],
    "name:ceb_x_preferred":[
        "Assoul"
    ],
    "name:fas_x_preferred":[
        "\u0627\u0633\u0648\u0644"
    ],
    "name:fra_x_preferred":[
        "Assoul"
    ],
    "name:ita_x_preferred":[
        "Assoul"
    ],
    "name:swe_x_preferred":[
        "Assoul"
    ],
    "wof:name":"Assoul",
    "wof:placetype":"locality"
},
  "geometry": {"coordinates":[-8.28745,30.92861],"type":"Point"}
}