{
  "type": "Feature",
  "properties": {
    "gn:admin1_code":"09",
    "gn:asciiname":"Izguigh",
    "gn:country_code":"MA",
    "gn:dem":1166,
    "gn:feature_class":"P",
    "gn:feature_code":"PPL",
    "gn:name":"Izguigh",
    "gn:population":0,
    "gn:timezone":"Africa/Casablanca",
    "iso:country":"MA",
    "name:und_x_variant":[
        "Izgouir",
        "Izougouir",
        "Izguigh"
    ],
    "wof:name":"Izguigh",
    "wof:placetype":"locality"
},
  "geometry": {"coordinates":[-7.7866,30.57322000000001],"type":"Point"}
}