{
  "type": "Feature",
  "properties": {
    "gn:admin1_code":"55",
    "gn:asciiname":"Igihl",
    "gn:country_code":"MA",
    "gn:dem":1356,
    "gn:feature_class":"P",
    "gn:feature_code":"PPL",
    "gn:name":"Igihl",
    "gn:population":0,
    "gn:timezone":"Africa/Casablanca",
    "iso:country":"MA",
    "wof:name":"Igihl",
    "wof:placetype":"locality"
},
  "geometry": {"coordinates":[-7.25,31.05],"type":"Point"}
}