{
  "type": "Feature",
  "properties": {
    "gn:admin1_code":"7.0",
    "gn:asciiname":"Oulad Sidi Taibi",
    "gn:country_code":"MA",
    "gn:dem":116,
    "gn:feature_class":"P",
    "gn:feature_code":"PPL",
    "gn:name":"Oulad Sidi Taibi",
    "gn:population":0,
    "gn:timezone":"Africa/Casablanca",
    "iso:country":"MA",
    "wof:name":"Oulad Sidi Taibi",
    "wof:placetype":"locality"
},
  "geometry": {"coordinates":[-9.17808,32.3988],"type":"Point"}
}