{
  "type": "Feature",
  "properties": {
    "gn:admin1_code":"01",
    "gn:asciiname":"Chouijra",
    "gn:country_code":"MA",
    "gn:dem":26,
    "gn:feature_class":"P",
    "gn:feature_code":"PPL",
    "gn:name":"Chouijra",
    "gn:population":0,
    "gn:timezone":"Africa/Casablanca",
    "iso:country":"MA",
    "wof:name":"Chouijra",
    "wof:placetype":"locality"
},
  "geometry": {"coordinates":[-6.01244,35.44837000000001],"type":"Point"}
}