{
  "type": "Feature",
  "properties": {
    "gn:admin1_code":"03",
    "gn:asciiname":"Iabboudene",
    "gn:country_code":"MA",
    "gn:dem":973,
    "gn:feature_class":"P",
    "gn:feature_code":"PPL",
    "gn:name":"Iabboudene",
    "gn:population":0,
    "gn:timezone":"Africa/Casablanca",
    "iso:country":"MA",
    "name:und_x_variant":[
        "Douar Iabboudene",
        "Iabboudene"
    ],
    "wof:name":"Iabboudene",
    "wof:placetype":"locality"
},
  "geometry": {"coordinates":[-3.94987,34.1075],"type":"Point"}
}