{
  "type": "Feature",
  "properties": {
    "gn:admin1_code":"04",
    "gn:asciiname":"Douar Khelaif",
    "gn:country_code":"MA",
    "gn:dem":25,
    "gn:feature_class":"P",
    "gn:feature_code":"PPL",
    "gn:name":"Douar Khela\u00eff",
    "gn:population":0,
    "gn:timezone":"Africa/Casablanca",
    "iso:country":"MA",
    "name:und_x_variant":[
        "Khela\u00eff",
        "Douar Khela\u00eff"
    ],
    "wof:name":"Douar Khelaif",
    "wof:placetype":"locality"
},
  "geometry": {"coordinates":[-5.85574,34.34679000000001],"type":"Point"}
}