{
  "type": "Feature",
  "properties": {
    "gn:admin1_code":"05",
    "gn:asciiname":"Douar Tarmast",
    "gn:country_code":"MA",
    "gn:dem":354,
    "gn:feature_class":"P",
    "gn:feature_code":"PPL",
    "gn:name":"Douar Tarmast",
    "gn:population":0,
    "gn:timezone":"Africa/Casablanca",
    "iso:country":"MA",
    "name:und_x_variant":[
        "Tarmest",
        "Talmest",
        "Douar Tarmast"
    ],
    "wof:name":"Douar Tarmast",
    "wof:placetype":"locality"
},
  "geometry": {"coordinates":[-7.04227,32.3049],"type":"Point"}
}