{
  "type": "Feature",
  "properties": {
    "gn:admin1_code":"04",
    "gn:asciiname":"Douar Ait Moussa",
    "gn:country_code":"MA",
    "gn:dem":245,
    "gn:feature_class":"P",
    "gn:feature_code":"PPL",
    "gn:name":"Douar A\u00eft Moussa",
    "gn:population":0,
    "gn:timezone":"Africa/Casablanca",
    "iso:country":"MA",
    "wof:name":"Douar Ait Moussa",
    "wof:placetype":"locality"
},
  "geometry": {"coordinates":[-6.48665,33.92649],"type":"Point"}
}