{
  "type": "Feature",
  "properties": {
    "gn:admin1_code":"7.0",
    "gn:asciiname":"Amaz Difassene",
    "gn:country_code":"MA",
    "gn:dem":1399,
    "gn:feature_class":"P",
    "gn:feature_code":"PPL",
    "gn:name":"Amaz Difassene",
    "gn:population":0,
    "gn:timezone":"Africa/Casablanca",
    "iso:country":"MA",
    "wof:name":"Amaz Difassene",
    "wof:placetype":"locality"
},
  "geometry": {"coordinates":[-7.33286,31.53226],"type":"Point"}
}