{
  "type": "Feature",
  "properties": {
    "gn:admin1_code":"7.0",
    "gn:asciiname":"Douar Ftanis",
    "gn:country_code":"MA",
    "gn:dem":380,
    "gn:feature_class":"P",
    "gn:feature_code":"PPL",
    "gn:name":"Douar Ftanis",
    "gn:population":0,
    "gn:timezone":"Africa/Casablanca",
    "iso:country":"MA",
    "wof:name":"Douar Ftanis",
    "wof:placetype":"locality"
},
  "geometry": {"coordinates":[-8.61926,32.10177],"type":"Point"}
}