{
  "type": "Feature",
  "properties": {
    "gn:admin1_code":"7.0",
    "gn:asciiname":"Douar Tyayba",
    "gn:country_code":"MA",
    "gn:dem":526,
    "gn:feature_class":"P",
    "gn:feature_code":"PPL",
    "gn:name":"Douar Tyayba",
    "gn:population":0,
    "gn:timezone":"Africa/Casablanca",
    "iso:country":"MA",
    "name:und_x_variant":[
        "Tahara"
    ],
    "wof:name":"Douar Tyayba",
    "wof:placetype":"locality"
},
  "geometry": {"coordinates":[-8.95624,32.02614000000001],"type":"Point"}
}