{
  "type": "Feature",
  "properties": {
    "gn:admin1_code":"9.0",
    "gn:asciiname":"Tassila Ouakrim",
    "gn:country_code":"MA",
    "gn:dem":431,
    "gn:feature_class":"P",
    "gn:feature_code":"PPL",
    "gn:name":"Tassila Ouakrim",
    "gn:population":0,
    "gn:timezone":"Africa/Casablanca",
    "iso:country":"MA",
    "wof:name":"Tassila Ouakrim",
    "wof:placetype":"locality"
},
  "geometry": {"coordinates":[-9.5546,30.8281],"type":"Point"}
}