{
  "type": "Feature",
  "properties": {
    "gn:admin1_code":"10",
    "gn:asciiname":"Ait Buhucu",
    "gn:country_code":"MA",
    "gn:dem":490,
    "gn:feature_class":"P",
    "gn:feature_code":"PPL",
    "gn:name":"Ait Buhucu",
    "gn:population":0,
    "gn:timezone":"Africa/Casablanca",
    "iso:country":"MA",
    "name:und_x_variant":[
        "Ait Buhokku",
        "Ait Buhucu"
    ],
    "wof:name":"Ait Buhucu",
    "wof:placetype":"locality"
},
  "geometry": {"coordinates":[-10.21,29.13],"type":"Point"}
}