{
  "type": "Feature",
  "properties": {
    "gn:admin1_code":"05",
    "gn:asciiname":"Douar Ayt Moucatine",
    "gn:country_code":"MA",
    "gn:dem":473,
    "gn:feature_class":"P",
    "gn:feature_code":"PPL",
    "gn:name":"Douar Ayt Mou\u00e7atine",
    "gn:population":0,
    "gn:timezone":"Africa/Casablanca",
    "iso:country":"MA",
    "name:und_x_variant":[
        "Douar A\u00eft Moussatine",
        "A\u00eft Moussatine",
        "Douar Ayt Mou\u00e7atine"
    ],
    "wof:name":"Douar Ayt Moucatine",
    "wof:placetype":"locality"
},
  "geometry": {"coordinates":[-6.30905,32.5805],"type":"Point"}
}