{
  "type": "Feature",
  "properties": {
    "gn:admin1_code":"07",
    "gn:asciiname":"Azariyf",
    "gn:country_code":"MA",
    "gn:dem":1661,
    "gn:feature_class":"P",
    "gn:feature_code":"PPL",
    "gn:name":"Azariyf",
    "gn:population":0,
    "gn:timezone":"Africa/Casablanca",
    "iso:country":"MA",
    "name:und_x_variant":[
        "Azarif"
    ],
    "wof:name":"Azariyf",
    "wof:placetype":"locality"
},
  "geometry": {"coordinates":[-7.27858,31.44794000000001],"type":"Point"}
}