{
  "type": "Feature",
  "properties": {
    "gn:admin1_code":"09",
    "gn:asciiname":"Ben Lefdil",
    "gn:country_code":"MA",
    "gn:dem":472,
    "gn:feature_class":"P",
    "gn:feature_code":"PPL",
    "gn:name":"Ben Lefdil",
    "gn:population":0,
    "gn:timezone":"Africa/Casablanca",
    "iso:country":"MA",
    "name:und_x_variant":[
        "Boulfdaile",
        "Bou Zfde\u00efl",
        "Bou Zfede\u00efl",
        "Ben Lefdil"
    ],
    "wof:name":"Ben Lefdil",
    "wof:placetype":"locality"
},
  "geometry": {"coordinates":[-9.62478,29.56557],"type":"Point"}
}