{
  "type": "Feature",
  "properties": {
    "gn:admin1_code":"09",
    "gn:asciiname":"Tamarckhant",
    "gn:country_code":"MA",
    "gn:dem":968,
    "gn:feature_class":"P",
    "gn:feature_code":"PPL",
    "gn:name":"Tamarckhant",
    "gn:population":0,
    "gn:timezone":"Africa/Casablanca",
    "iso:country":"MA",
    "name:und_x_variant":[
        "Tamarkhsent"
    ],
    "wof:name":"Tamarckhant",
    "wof:placetype":"locality"
},
  "geometry": {"coordinates":[-7.93572,30.725],"type":"Point"}
}