{
  "type": "Feature",
  "properties": {
    "gn:admin1_code":"2.0",
    "gn:asciiname":"Iaadalene",
    "gn:country_code":"MA",
    "gn:dem":206,
    "gn:feature_class":"P",
    "gn:feature_code":"PPL",
    "gn:name":"Iaadalene",
    "gn:population":0,
    "gn:timezone":"Africa/Casablanca",
    "iso:country":"MA",
    "wof:name":"Iaadalene",
    "wof:placetype":"locality"
},
  "geometry": {"coordinates":[-3.10498,35.22968],"type":"Point"}
}