{
  "type": "Feature",
  "properties": {
    "gn:admin1_code":"4.0",
    "gn:asciiname":"Douar Leghnaderra",
    "gn:country_code":"MA",
    "gn:dem":348,
    "gn:feature_class":"P",
    "gn:feature_code":"PPL",
    "gn:name":"Douar Leghnaderra",
    "gn:population":0,
    "gn:timezone":"Africa/Casablanca",
    "iso:country":"MA",
    "wof:name":"Douar Leghnaderra",
    "wof:placetype":"locality"
},
  "geometry": {"coordinates":[-6.83941,33.6228],"type":"Point"}
}