{
  "type": "Feature",
  "properties": {
    "gn:admin1_code":"5.0",
    "gn:asciiname":"Aouddim",
    "gn:country_code":"MA",
    "gn:dem":902,
    "gn:feature_class":"P",
    "gn:feature_code":"PPL",
    "gn:name":"Aouddim",
    "gn:population":0,
    "gn:timezone":"Africa/Casablanca",
    "iso:country":"MA",
    "wof:name":"Aouddim",
    "wof:placetype":"locality"
},
  "geometry": {"coordinates":[-5.5879,32.84107],"type":"Point"}
}