{
  "type": "Feature",
  "properties": {
    "gn:admin1_code":"08",
    "gn:asciiname":"Tabougamt",
    "gn:country_code":"MA",
    "gn:dem":1861,
    "gn:feature_class":"P",
    "gn:feature_code":"PPL",
    "gn:name":"Tabougamt",
    "gn:population":0,
    "gn:timezone":"Africa/Casablanca",
    "iso:country":"MA",
    "name:und_x_variant":[
        "Tabougount"
    ],
    "wof:name":"Tabougamt",
    "wof:placetype":"locality"
},
  "geometry": {"coordinates":[-7.21205,31.30438],"type":"Point"}
}