{
  "type": "Feature",
  "properties": {
    "gn:admin1_code":"9.0",
    "gn:asciiname":"Ait Oujart",
    "gn:country_code":"MA",
    "gn:dem":363,
    "gn:feature_class":"P",
    "gn:feature_code":"PPL",
    "gn:name":"A\u00eft Oujart",
    "gn:population":0,
    "gn:timezone":"Africa/Casablanca",
    "iso:country":"MA",
    "wof:name":"Ait Oujart",
    "wof:placetype":"locality"
},
  "geometry": {"coordinates":[-8.76346,30.59653],"type":"Point"}
}