{
  "type": "Feature",
  "properties": {
    "gn:admin1_code":"6.0",
    "gn:asciiname":"Douar Oulad Assri",
    "gn:country_code":"MA",
    "gn:dem":322,
    "gn:feature_class":"P",
    "gn:feature_code":"PPL",
    "gn:name":"Douar Oulad Assri",
    "gn:population":0,
    "gn:timezone":"Africa/Casablanca",
    "iso:country":"MA",
    "wof:name":"Douar Oulad Assri",
    "wof:placetype":"locality"
},
  "geometry": {"coordinates":[-7.00605,33.55876],"type":"Point"}
}