{
  "type": "Feature",
  "properties": {
    "gn:admin1_code":"7.0",
    "gn:asciiname":"Laagada",
    "gn:country_code":"MA",
    "gn:dem":394,
    "gn:feature_class":"P",
    "gn:feature_code":"PPL",
    "gn:name":"Laagada",
    "gn:population":0,
    "gn:timezone":"Africa/Casablanca",
    "iso:country":"MA",
    "wof:name":"Laagada",
    "wof:placetype":"locality"
},
  "geometry": {"coordinates":[-8.7536,32.17869],"type":"Point"}
}