{
  "type": "Feature",
  "properties": {
    "gn:admin1_code":"3.0",
    "gn:asciiname":"Dar Abargui Mohamed",
    "gn:country_code":"MA",
    "gn:dem":817,
    "gn:feature_class":"P",
    "gn:feature_code":"PPL",
    "gn:name":"Dar Abargui Mohamed",
    "gn:population":0,
    "gn:timezone":"Africa/Casablanca",
    "iso:country":"MA",
    "wof:name":"Dar Abargui Mohamed",
    "wof:placetype":"locality"
},
  "geometry": {"coordinates":[-4.78774,33.82048],"type":"Point"}
}