{
  "type": "Feature",
  "properties": {
    "gn:admin1_code":"01",
    "gn:asciiname":"Douar Tahjort",
    "gn:country_code":"MA",
    "gn:dem":25,
    "gn:feature_class":"P",
    "gn:feature_code":"PPL",
    "gn:name":"Douar Tahjort",
    "gn:population":0,
    "gn:timezone":"Africa/Casablanca",
    "iso:country":"MA",
    "wof:name":"Douar Tahjort",
    "wof:placetype":"locality"
},
  "geometry": {"coordinates":[-3.81102,35.16885],"type":"Point"}
}