{
  "type": "Feature",
  "properties": {
    "gn:country":"MA",
    "gn:fcode":"ADM3",
    "gn:population":25066,
    "iso:country":"MA",
    "name:ara_x_preferred":[
        "\u0623\u0648\u0644\u0627\u062f \u0631\u062d\u0645\u0648\u0646"
    ],
    "name:fra_x_preferred":[
        "Sidi Ali Ben Hamdouc"
    ],
    "name:fra_x_variant":[
        "Sidi Ali Ben Hamdouc (CR)",
        "Sidi Ali Ben Hamdouc (Commune Rurale)"
    ],
    "qs_pg:aaroncc":"MA",
    "qs_pg:gn_country":"MA",
    "qs_pg:gn_fcode":"ADM3",
    "qs_pg:gn_pop":25066,
    "qs_pg:name":"Sidi Ali Ben Hamdouc",
    "qs_pg:photos_9r":0,
    "qs_pg:photos_sr":0,
    "qs_pg:pop_sr":7,
    "qs_pg:qs_pg_placetype":"localadmin",
    "wof:name":"Sidi Ali Ben Hamdouc",
    "wof:placetype":"localadmin",
    "wof:population":25066
},
  "geometry": {"coordinates":[-8.27227,33.31031],"type":"Point"}
}