{
  "type": "Feature",
  "properties": {
    "gn:admin1_code":"9.0",
    "gn:asciiname":"Agadir Ouzir",
    "gn:country_code":"MA",
    "gn:dem":703,
    "gn:feature_class":"P",
    "gn:feature_code":"PPL",
    "gn:name":"Agadir Ouzir",
    "gn:population":0,
    "gn:timezone":"Africa/Casablanca",
    "iso:country":"MA",
    "wof:name":"Agadir Ouzir",
    "wof:placetype":"locality"
},
  "geometry": {"coordinates":[-8.90871,30.64787],"type":"Point"}
}