{
  "type": "Feature",
  "properties": {
    "gn:asciiname":"Stehat",
    "gn:country_code":"MA",
    "gn:dem":19,
    "gn:feature_class":"P",
    "gn:feature_code":"PPL",
    "gn:name":"Stehat",
    "gn:population":0,
    "gn:timezone":"Africa/Casablanca",
    "iso:country":"MA",
    "wof:name":"Stehat",
    "wof:placetype":"locality"
},
  "geometry": {"coordinates":[-4.95904,35.34068],"type":"Point"}
}