{
  "type": "Feature",
  "properties": {
    "gn:admin1_code":"09",
    "gn:asciiname":"Afaghniy",
    "gn:country_code":"MA",
    "gn:dem":972,
    "gn:feature_class":"P",
    "gn:feature_code":"PPL",
    "gn:name":"Afaghniy",
    "gn:population":0,
    "gn:timezone":"Africa/Casablanca",
    "iso:country":"MA",
    "name:und_x_variant":[
        "Aferni"
    ],
    "wof:name":"Afaghniy",
    "wof:placetype":"locality"
},
  "geometry": {"coordinates":[-8.88693,30.14652],"type":"Point"}
}