{
  "type": "Feature",
  "properties": {
    "gn:admin1_code":"4.0",
    "gn:asciiname":"Douar Oulad Yaich",
    "gn:country_code":"MA",
    "gn:dem":21,
    "gn:feature_class":"P",
    "gn:feature_code":"PPL",
    "gn:name":"Douar Oulad Yaich",
    "gn:population":0,
    "gn:timezone":"Africa/Casablanca",
    "iso:country":"MA",
    "wof:name":"Douar Oulad Yaich",
    "wof:placetype":"locality"
},
  "geometry": {"coordinates":[-5.96556,34.60743],"type":"Point"}
}