{
  "type": "Feature",
  "properties": {
    "gn:admin1_code":"4.0",
    "gn:asciiname":"Douar Mestaoua",
    "gn:country_code":"MA",
    "gn:dem":23,
    "gn:feature_class":"P",
    "gn:feature_code":"PPL",
    "gn:name":"Douar Mestaoua",
    "gn:population":0,
    "gn:timezone":"Africa/Casablanca",
    "iso:country":"MA",
    "wof:name":"Douar Mestaoua",
    "wof:placetype":"neighbourhood"
},
  "geometry": {"coordinates":[-6.79462,33.98087],"type":"Point"}
}