{
  "type": "Feature",
  "properties": {
    "gn:admin1_code":"07",
    "gn:asciiname":"Douar Yakoubi",
    "gn:country_code":"MA",
    "gn:dem":725,
    "gn:feature_class":"P",
    "gn:feature_code":"PPL",
    "gn:name":"Douar Yakoubi",
    "gn:population":0,
    "gn:timezone":"Africa/Casablanca",
    "iso:country":"MA",
    "name:und_x_variant":[
        "Ouled Ya\u00e2koub",
        "Douar Yakoub",
        "Douar Yakoubi"
    ],
    "wof:name":"Douar Yakoubi",
    "wof:placetype":"locality"
},
  "geometry": {"coordinates":[-7.17718,31.76336],"type":"Point"}
}