{
  "type": "Feature",
  "properties": {
    "gn:gn_country":"MA",
    "gn:gn_fcode":"ADM3",
    "gn:gn_pop":27972,
    "gn:population":27972,
    "iso:country":"MA",
    "name:ara_x_preferred":[
        "\u0628\u0646\u064a \u0648\u0627\u0644"
    ],
    "name:fra_x_preferred":[
        "Oulad H Cine"
    ],
    "name:fra_x_variant":[
        "Oulad H Cine (CR)",
        "Oulad H Cine (Commune Rurale)"
    ],
    "qs_pg:aaroncc":"MA",
    "qs_pg:gn_country":"MA",
    "qs_pg:gn_fcode":"ADM3",
    "qs_pg:gn_pop":27972,
    "qs_pg:name":"Oulad H Cine",
    "qs_pg:photos_9r":0,
    "qs_pg:photos_sr":0,
    "qs_pg:pop_sr":7,
    "qs_pg:qs_pg_placetype":"localadmin",
    "wof:name":"Oulad H Cine",
    "wof:placetype":"localadmin",
    "wof:population":27972
},
  "geometry": {"coordinates":[-5.79697,34.41068],"type":"Point"}
}