{
  "type": "Feature",
  "properties": {
    "gn:admin1_code":"9.0",
    "gn:asciiname":"Ikhsayn",
    "gn:country_code":"MA",
    "gn:dem":1005,
    "gn:feature_class":"P",
    "gn:feature_code":"PPL",
    "gn:name":"Ikhsayn",
    "gn:population":0,
    "gn:timezone":"Africa/Casablanca",
    "iso:country":"MA",
    "wof:name":"Ikhsayn",
    "wof:placetype":"locality"
},
  "geometry": {"coordinates":[-9.15822,29.77723],"type":"Point"}
}