{
  "type": "Feature",
  "properties": {
    "gn:admin1_code":"07",
    "gn:asciiname":"Amzri",
    "gn:country_code":"MA",
    "gn:dem":1095,
    "gn:feature_class":"P",
    "gn:feature_code":"PPL",
    "gn:name":"Amzri",
    "gn:population":0,
    "gn:timezone":"Africa/Casablanca",
    "iso:country":"MA",
    "name:und_x_variant":[
        "Amezri",
        "Amzra",
        "Amzri"
    ],
    "wof:name":"Amzri",
    "wof:placetype":"locality"
},
  "geometry": {"coordinates":[-9.04474,30.97186],"type":"Point"}
}