{
  "type": "Feature",
  "properties": {
    "gn:admin1_code":"09",
    "gn:asciiname":"Zdine",
    "gn:country_code":"MA",
    "gn:dem":1486,
    "gn:feature_class":"P",
    "gn:feature_code":"PPL",
    "gn:name":"Zdine",
    "gn:population":0,
    "gn:timezone":"Africa/Casablanca",
    "iso:country":"MA",
    "wof:name":"Zdine",
    "wof:placetype":"locality"
},
  "geometry": {"coordinates":[-8.30556,30.42006],"type":"Point"}
}