{
  "type": "Feature",
  "properties": {
    "gn:admin1_code":"4.0",
    "gn:asciiname":"Souq at Tnine",
    "gn:country_code":"MA",
    "gn:dem":252,
    "gn:feature_class":"P",
    "gn:feature_code":"PPL",
    "gn:name":"Souq at Tnine",
    "gn:population":0,
    "gn:timezone":"Africa/Casablanca",
    "iso:country":"MA",
    "wof:name":"Souq at Tnine",
    "wof:placetype":"locality"
},
  "geometry": {"coordinates":[-6.4606,33.93871],"type":"Point"}
}