{
  "type": "Feature",
  "properties": {
    "gn:admin1_code":"7.0",
    "gn:asciiname":"Id El Aouni",
    "gn:country_code":"MA",
    "gn:dem":191,
    "gn:feature_class":"P",
    "gn:feature_code":"PPL",
    "gn:name":"Id El Aouni",
    "gn:population":0,
    "gn:timezone":"Africa/Casablanca",
    "iso:country":"MA",
    "wof:name":"Id El Aouni",
    "wof:placetype":"locality"
},
  "geometry": {"coordinates":[-9.64968,31.37077],"type":"Point"}
}