{
  "type": "Feature",
  "properties": {
    "gn:admin1_code":"7.0",
    "gn:asciiname":"Lalla Tach'out",
    "gn:country_code":"MA",
    "gn:dem":1180,
    "gn:feature_class":"P",
    "gn:feature_code":"PPL",
    "gn:name":"Lalla Tach\u2019out",
    "gn:population":0,
    "gn:timezone":"Africa/Casablanca",
    "iso:country":"MA",
    "wof:name":"Lalla Tach'out",
    "wof:placetype":"locality"
},
  "geometry": {"coordinates":[-7.66851,31.40551],"type":"Point"}
}