{
  "type": "Feature",
  "properties": {
    "gn:admin1_code":"3.0",
    "gn:asciiname":"Douar Ait El Haj El Houssine",
    "gn:country_code":"MA",
    "gn:dem":1624,
    "gn:feature_class":"P",
    "gn:feature_code":"PPL",
    "gn:name":"Douar Ait El Haj El Houssine",
    "gn:population":0,
    "gn:timezone":"Africa/Casablanca",
    "iso:country":"MA",
    "wof:name":"Douar Ait El Haj El Houssine",
    "wof:placetype":"locality"
},
  "geometry": {"coordinates":[-4.78436,33.50647],"type":"Point"}
}