{
  "type": "Feature",
  "properties": {
    "gn:admin1_code":"5.0",
    "gn:asciiname":"Lahbab",
    "gn:country_code":"MA",
    "gn:dem":1746,
    "gn:feature_class":"P",
    "gn:feature_code":"PPL",
    "gn:name":"Lahbab",
    "gn:population":0,
    "gn:timezone":"Africa/Casablanca",
    "iso:country":"MA",
    "name:nno_x_preferred":[
        "Lehbab"
    ],
    "wof:name":"Lahbab",
    "wof:placetype":"locality"
},
  "geometry": {"coordinates":[-6.45918,31.86536],"type":"Point"}
}