{
  "type": "Feature",
  "properties": {
    "gn:admin1_code":"9.0",
    "gn:asciiname":"Fouadouz",
    "gn:country_code":"MA",
    "gn:dem":1763,
    "gn:feature_class":"P",
    "gn:feature_code":"PPL",
    "gn:name":"Fouadouz",
    "gn:population":0,
    "gn:timezone":"Africa/Casablanca",
    "iso:country":"MA",
    "wof:name":"Fouadouz",
    "wof:placetype":"locality"
},
  "geometry": {"coordinates":[-8.70393,30.83408],"type":"Point"}
}