{
  "type": "Feature",
  "properties": {
    "gn:country":"MA",
    "gn:fcode":"ADM3",
    "gn:pop":15216,
    "iso:country":"MA",
    "name:ara_x_preferred":[
        "\u0627\u0631\u063a\u064a\u0648\u0629"
    ],
    "name:ara_x_variant":[
        "\u0623\u0648\u0631\u062a\u0632\u0627\u063a"
    ],
    "name:cat_x_preferred":[
        "Ourtzagh"
    ],
    "name:ceb_x_preferred":[
        "Ourtzagh"
    ],
    "name:eng_x_preferred":[
        "Ourtzagh"
    ],
    "name:fra_x_preferred":[
        "Ourtzagh"
    ],
    "name:fra_x_variant":[
        "Ourtzagh (CR)",
        "Ourtzagh (Commune Rurale)"
    ],
    "name:ita_x_preferred":[
        "Ourtzagh"
    ],
    "name:nld_x_preferred":[
        "Ourtzagh"
    ],
    "name:swe_x_preferred":[
        "Ourtzagh"
    ],
    "qs:name":"Ourtzagh",
    "qs:photos_9r":0,
    "qs:photos_sr":0,
    "qs:pop_sr":"6",
    "wd:wordcount":61,
    "wof:name":"Ourtzagh",
    "wof:placetype":"localadmin",
    "wof:population":15216
},
  "geometry": {"coordinates":[-4.9474,34.5076],"type":"Point"}
}