{
  "type": "Feature",
  "properties": {
    "gn:admin1_code":"9.0",
    "gn:asciiname":"Tamarzagou",
    "gn:country_code":"MA",
    "gn:dem":1345,
    "gn:feature_class":"P",
    "gn:feature_code":"PPL",
    "gn:name":"Tamarzagou",
    "gn:population":0,
    "gn:timezone":"Africa/Casablanca",
    "iso:country":"MA",
    "wof:name":"Tamarzagou",
    "wof:placetype":"locality"
},
  "geometry": {"coordinates":[-7.98853,30.63672],"type":"Point"}
}