{
  "type": "Feature",
  "properties": {
    "gn:admin1_code":"4.0",
    "gn:asciiname":"Douar Dhour Lakbar",
    "gn:country_code":"MA",
    "gn:dem":14,
    "gn:feature_class":"P",
    "gn:feature_code":"PPL",
    "gn:name":"Douar Dhour Lakbar",
    "gn:population":0,
    "gn:timezone":"Africa/Casablanca",
    "iso:country":"MA",
    "wof:name":"Douar Dhour Lakbar",
    "wof:placetype":"locality"
},
  "geometry": {"coordinates":[-6.42473,34.29732],"type":"Point"}
}