{
  "type": "Feature",
  "properties": {
    "gn:admin1_code":"08",
    "gn:asciiname":"Zawia Sidi 'Abdellah Boubker",
    "gn:country_code":"MA",
    "gn:dem":770,
    "gn:feature_class":"P",
    "gn:feature_code":"PPL",
    "gn:name":"Zawia Sidi \u2019Abdellah Boubker",
    "gn:population":0,
    "gn:timezone":"Africa/Casablanca",
    "iso:country":"MA",
    "name:und_x_variant":[
        "Sidi Abdallah Ben Boubkour",
        "Sidi Abdallah Ben Boubkeur",
        "Sidi Abdallah Ben Boubker",
        "Zawia Sidi \u2019Abdellah Boubker"
    ],
    "wof:name":"Zawia Sidi 'Abdellah Boubker",
    "wof:placetype":"locality"
},
  "geometry": {"coordinates":[-4.30852,31.3226],"type":"Point"}
}