{
  "type": "Feature",
  "properties": {
    "gn:admin1_code":"07",
    "gn:asciiname":"Agadir-n-Igourramene",
    "gn:country_code":"MA",
    "gn:dem":1022,
    "gn:feature_class":"P",
    "gn:feature_code":"PPL",
    "gn:name":"Agadir-n-Igourramene",
    "gn:population":0,
    "gn:timezone":"Africa/Casablanca",
    "iso:country":"MA",
    "name:und_x_variant":[
        "Agadir n Ougrramene",
        "Agadir n\u2019Igourram\u00e8n",
        "Agadir n\u2019Igourramene",
        "Agadir-n-Igourramene"
    ],
    "wof:name":"Agadir-n-Igourramene",
    "wof:placetype":"locality"
},
  "geometry": {"coordinates":[-7.9295,31.33138],"type":"Point"}
}