{
  "type": "Feature",
  "properties": {
    "gn:admin1_code":"9.0",
    "gn:asciiname":"Igourar",
    "gn:country_code":"MA",
    "gn:dem":137,
    "gn:feature_class":"P",
    "gn:feature_code":"PPL",
    "gn:name":"Igourar",
    "gn:population":0,
    "gn:timezone":"Africa/Casablanca",
    "iso:country":"MA",
    "wof:name":"Igourar",
    "wof:placetype":"locality"
},
  "geometry": {"coordinates":[-9.41117,30.01027],"type":"Point"}
}