{
  "type": "Feature",
  "properties": {
    "gn:admin1_code":"9.0",
    "gn:asciiname":"Anammr-n-Touni",
    "gn:country_code":"MA",
    "gn:dem":1216,
    "gn:feature_class":"P",
    "gn:feature_code":"PPL",
    "gn:name":"Anammr-n-Touni",
    "gn:population":0,
    "gn:timezone":"Africa/Casablanca",
    "iso:country":"MA",
    "wof:name":"Anammr-n-Touni",
    "wof:placetype":"locality"
},
  "geometry": {"coordinates":[-9.1751,29.52178],"type":"Point"}
}