{
  "type": "Feature",
  "properties": {
    "gn:admin1_code":"09",
    "gn:asciiname":"Tine Said",
    "gn:country_code":"MA",
    "gn:dem":124,
    "gn:feature_class":"P",
    "gn:feature_code":"PPL",
    "gn:name":"Tine Said",
    "gn:population":0,
    "gn:timezone":"Africa/Casablanca",
    "iso:country":"MA",
    "name:und_x_variant":[
        "Tnine Sa\u00efd",
        "Tine Sa\u00efd",
        "Ti n\u2019 Sa\u00efd",
        "Tine Said"
    ],
    "wof:name":"Tine Said",
    "wof:placetype":"locality"
},
  "geometry": {"coordinates":[-9.35118,30.2636],"type":"Point"}
}