{
  "type": "Feature",
  "properties": {
    "gn:admin1_code":"03",
    "gn:asciiname":"Oulad Fryakh",
    "gn:country_code":"MA",
    "gn:dem":789,
    "gn:feature_class":"P",
    "gn:feature_code":"PPL",
    "gn:name":"Oulad Fryakh",
    "gn:population":0,
    "gn:timezone":"Africa/Casablanca",
    "iso:country":"MA",
    "wof:name":"Oulad Fryakh",
    "wof:placetype":"locality"
},
  "geometry": {"coordinates":[-4.26234,34.63921],"type":"Point"}
}