{
  "type": "Feature",
  "properties": {
    "gn:admin1_code":"7.0",
    "gn:asciiname":"Bou Klal",
    "gn:country_code":"MA",
    "gn:dem":644,
    "gn:feature_class":"P",
    "gn:feature_code":"PPL",
    "gn:name":"Bou Klal",
    "gn:population":0,
    "gn:timezone":"Africa/Casablanca",
    "iso:country":"MA",
    "wof:name":"Bou Klal",
    "wof:placetype":"locality"
},
  "geometry": {"coordinates":[-9.61332,30.88722000000001],"type":"Point"}
}