{
  "type": "Feature",
  "properties": {
    "gn:admin1_code":"9.0",
    "gn:asciiname":"Moktar",
    "gn:country_code":"MA",
    "gn:dem":245,
    "gn:feature_class":"P",
    "gn:feature_code":"PPL",
    "gn:name":"Moktar",
    "gn:population":0,
    "gn:timezone":"Africa/Casablanca",
    "iso:country":"MA",
    "wof:name":"Moktar",
    "wof:placetype":"locality"
},
  "geometry": {"coordinates":[-9.34225,29.98349],"type":"Point"}
}