{
  "type": "Feature",
  "properties": {
    "gn:admin1_code":"7.0",
    "gn:asciiname":"Douar Leqoussma",
    "gn:country_code":"MA",
    "gn:dem":451,
    "gn:feature_class":"P",
    "gn:feature_code":"PPL",
    "gn:name":"Douar Leqoussma",
    "gn:population":0,
    "gn:timezone":"Africa/Casablanca",
    "iso:country":"MA",
    "wof:name":"Douar Leqoussma",
    "wof:placetype":"locality"
},
  "geometry": {"coordinates":[-9.2722,31.65094],"type":"Point"}
}