{
  "type": "Feature",
  "properties": {
    "gn:admin1_code":"9.0",
    "gn:asciiname":"Iguiyliyz",
    "gn:country_code":"MA",
    "gn:dem":1258,
    "gn:feature_class":"P",
    "gn:feature_code":"PPL",
    "gn:name":"Iguiyliyz",
    "gn:population":0,
    "gn:timezone":"Africa/Casablanca",
    "iso:country":"MA",
    "wof:name":"Iguiyliyz",
    "wof:placetype":"locality"
},
  "geometry": {"coordinates":[-9.19214,29.50604],"type":"Point"}
}