{
  "type": "Feature",
  "properties": {
    "gn:admin1_code":"3.0",
    "gn:asciiname":"Ait Ou Sahla",
    "gn:country_code":"MA",
    "gn:dem":718,
    "gn:feature_class":"P",
    "gn:feature_code":"PPL",
    "gn:name":"Ait Ou Sahla",
    "gn:population":0,
    "gn:timezone":"Africa/Casablanca",
    "iso:country":"MA",
    "wof:name":"Ait Ou Sahla",
    "wof:placetype":"locality"
},
  "geometry": {"coordinates":[-5.68729,33.63437],"type":"Point"}
}