{
  "type": "Feature",
  "properties": {
    "gn:admin1_code":"8.0",
    "gn:asciiname":"Tayfast",
    "gn:country_code":"MA",
    "gn:dem":1838,
    "gn:feature_class":"P",
    "gn:feature_code":"PPL",
    "gn:name":"Tayfast",
    "gn:population":0,
    "gn:timezone":"Africa/Casablanca",
    "iso:country":"MA",
    "wof:name":"Tayfast",
    "wof:placetype":"locality"
},
  "geometry": {"coordinates":[-5.60343,31.17362],"type":"Point"}
}