{
  "type": "Feature",
  "properties": {
    "gn:admin1_code":"1.0",
    "gn:asciiname":"Azrou Lbaz",
    "gn:country_code":"MA",
    "gn:dem":825,
    "gn:feature_class":"P",
    "gn:feature_code":"PPL",
    "gn:name":"Azrou Lbaz",
    "gn:population":0,
    "gn:timezone":"Africa/Casablanca",
    "iso:country":"MA",
    "wof:name":"Azrou Lbaz",
    "wof:placetype":"locality"
},
  "geometry": {"coordinates":[-4.85598,35.07437],"type":"Point"}
}