{
  "type": "Feature",
  "properties": {
    "gn:admin1_code":"05",
    "gn:asciiname":"Douar Oulad Mess'oud",
    "gn:country_code":"MA",
    "gn:dem":447,
    "gn:feature_class":"P",
    "gn:feature_code":"PPL",
    "gn:name":"Douar Oulad Mess\u2019oud",
    "gn:population":0,
    "gn:timezone":"Africa/Casablanca",
    "iso:country":"MA",
    "name:und_x_variant":[
        "Douar Oulad Mess\u2019oud",
        "Oulad Messaoud"
    ],
    "wof:name":"Douar Oulad Mess'oud",
    "wof:placetype":"locality"
},
  "geometry": {"coordinates":[-6.51517,32.48037],"type":"Point"}
}