{
  "type": "Feature",
  "properties": {
    "gn:admin1_code":"7.0",
    "gn:asciiname":"Ibahharene",
    "gn:country_code":"MA",
    "gn:dem":323,
    "gn:feature_class":"P",
    "gn:feature_code":"PPL",
    "gn:name":"Ibahharene",
    "gn:population":0,
    "gn:timezone":"Africa/Casablanca",
    "iso:country":"MA",
    "wof:name":"Ibahharene",
    "wof:placetype":"locality"
},
  "geometry": {"coordinates":[-9.68632,31.13046],"type":"Point"}
}