{
  "type": "Feature",
  "properties": {
    "gn:admin1_code":"7.0",
    "gn:asciiname":"Toughmirt",
    "gn:country_code":"MA",
    "gn:dem":788,
    "gn:feature_class":"P",
    "gn:feature_code":"PPL",
    "gn:name":"Toughmirt",
    "gn:population":0,
    "gn:timezone":"Africa/Casablanca",
    "iso:country":"MA",
    "wof:name":"Toughmirt",
    "wof:placetype":"locality"
},
  "geometry": {"coordinates":[-7.96458,31.40371],"type":"Point"}
}