{
  "type": "Feature",
  "properties": {
    "gn:admin1_code":"09",
    "gn:asciiname":"Tamaayt Oufella",
    "gn:country_code":"MA",
    "gn:dem":199,
    "gn:feature_class":"P",
    "gn:feature_code":"PPL",
    "gn:name":"Tamaayt Oufella",
    "gn:population":0,
    "gn:timezone":"Africa/Casablanca",
    "iso:country":"MA",
    "name:und_x_variant":[
        "Tama\u00eft Ou Fella"
    ],
    "wof:name":"Tamaayt Oufella",
    "wof:placetype":"locality"
},
  "geometry": {"coordinates":[-9.39314,30.47558],"type":"Point"}
}