{
  "type": "Feature",
  "properties": {
    "gn:admin1_code":"8.0",
    "gn:asciiname":"Ftamda",
    "gn:country_code":"MA",
    "gn:dem":1805,
    "gn:feature_class":"P",
    "gn:feature_code":"PPL",
    "gn:name":"Ftamda",
    "gn:population":0,
    "gn:timezone":"Africa/Casablanca",
    "iso:country":"MA",
    "wof:name":"Ftamda",
    "wof:placetype":"locality"
},
  "geometry": {"coordinates":[-7.59778,30.31346],"type":"Point"}
}