{
  "type": "Feature",
  "properties": {
    "gn:admin1_code":"7.0",
    "gn:asciiname":"Icharmioun",
    "gn:country_code":"MA",
    "gn:dem":549,
    "gn:feature_class":"P",
    "gn:feature_code":"PPL",
    "gn:name":"Icharmioun",
    "gn:population":0,
    "gn:timezone":"Africa/Casablanca",
    "iso:country":"MA",
    "wof:name":"Icharmioun",
    "wof:placetype":"locality"
},
  "geometry": {"coordinates":[-9.47082,31.31826],"type":"Point"}
}