{
  "type": "Feature",
  "properties": {
    "gn:admin1_code":"6.0",
    "gn:asciiname":"Douar Chnatwa",
    "gn:country_code":"MA",
    "gn:dem":78,
    "gn:feature_class":"P",
    "gn:feature_code":"PPL",
    "gn:name":"Douar Chnatwa",
    "gn:population":0,
    "gn:timezone":"Africa/Casablanca",
    "iso:country":"MA",
    "wof:name":"Douar Chnatwa",
    "wof:placetype":"locality"
},
  "geometry": {"coordinates":[-8.72129,32.93830999999999],"type":"Point"}
}