{
  "type": "Feature",
  "properties": {
    "gn:country":"MA",
    "gn:fcode":"ADM3",
    "gn:population":17708,
    "iso:country":"MA",
    "name:ara_x_preferred":[
        "\u0633\u0628\u062a\u0629"
    ],
    "name:fra_x_preferred":[
        "Sidi Aissa Ben Slim"
    ],
    "name:fra_x_variant":[
        "Sidi Aissa Ben Slim (CR)",
        "Sidi Aissa Ben Slim (Commune Rurale)"
    ],
    "qs_pg:aaroncc":"MA",
    "qs_pg:gn_country":"MA",
    "qs_pg:gn_fcode":"ADM3",
    "qs_pg:gn_pop":17708,
    "qs_pg:name":"Sidi Aissa Ben  Slim",
    "qs_pg:photos_9r":0,
    "qs_pg:photos_sr":0,
    "qs_pg:pop_sr":6,
    "qs_pg:qs_pg_placetype":"localadmin",
    "wof:name":"Sidi Aissa Ben Slim",
    "wof:placetype":"localadmin",
    "wof:population":17708
},
  "geometry": {"coordinates":[-7.17382,31.9543],"type":"Point"}
}