{
  "type": "Feature",
  "properties": {
    "gn:admin1_code":"7.0",
    "gn:asciiname":"Oumwachfal",
    "gn:country_code":"MA",
    "gn:dem":820,
    "gn:feature_class":"P",
    "gn:feature_code":"PPL",
    "gn:name":"Oumwachfal",
    "gn:population":0,
    "gn:timezone":"Africa/Casablanca",
    "iso:country":"MA",
    "wof:name":"Oumwachfal",
    "wof:placetype":"locality"
},
  "geometry": {"coordinates":[-8.84352,31.20758],"type":"Point"}
}