{
  "type": "Feature",
  "properties": {
    "gn:admin1_code":"09",
    "gn:asciiname":"Timjicht",
    "gn:country_code":"MA",
    "gn:dem":1685,
    "gn:feature_class":"P",
    "gn:feature_code":"PPL",
    "gn:name":"Timjicht",
    "gn:population":0,
    "gn:timezone":"Africa/Casablanca",
    "iso:country":"MA",
    "name:und_x_variant":[
        "Timjich",
        "Timjicht"
    ],
    "wof:name":"Timjicht",
    "wof:placetype":"locality"
},
  "geometry": {"coordinates":[-8.11923,30.24042],"type":"Point"}
}