{
  "type": "Feature",
  "properties": {
    "gn:admin1_code":"01",
    "gn:asciiname":"Jbila",
    "gn:country_code":"MA",
    "gn:dem":598,
    "gn:feature_class":"P",
    "gn:feature_code":"PPL",
    "gn:name":"Jbila",
    "gn:population":0,
    "gn:timezone":"Africa/Casablanca",
    "iso:country":"MA",
    "name:und_x_variant":[
        "Douar Jibila",
        "El Yebila",
        "Jibila",
        "Jbila"
    ],
    "wof:name":"Jbila",
    "wof:placetype":"locality"
},
  "geometry": {"coordinates":[-5.61838,35.15098],"type":"Point"}
}