{
  "type": "Feature",
  "properties": {
    "gn:country":"MA",
    "gn:fcode":"ADM3",
    "gn:population":16602,
    "iso:country":"MA",
    "name:ara_x_preferred":[
        "\u0627\u063a\u0648\u0627\u0632\u064a"
    ],
    "name:ara_x_variant":[
        "\u0645\u0648\u0644\u0627\u064a \u0628\u0648\u0634\u062a\u0649"
    ],
    "name:cat_x_preferred":[
        "Moulay Bouchta"
    ],
    "name:fra_x_preferred":[
        "Moulay Bouchta"
    ],
    "name:fra_x_variant":[
        "Moulay Bouchta (CR)",
        "Moulay Bouchta (Commune Rurale)"
    ],
    "name:ita_x_preferred":[
        "Moulay Bouchta"
    ],
    "name:spa_x_preferred":[
        "Moulay Bouchta"
    ],
    "qs_pg:aaroncc":"MA",
    "qs_pg:gn_country":"MA",
    "qs_pg:gn_fcode":"ADM3",
    "qs_pg:gn_pop":16602,
    "qs_pg:name":"Moulay Bouchta",
    "qs_pg:photos_9r":0,
    "qs_pg:photos_sr":0,
    "qs_pg:pop_sr":6,
    "qs_pg:qs_pg_placetype":"localadmin",
    "wof:name":"Moulay Bouchta",
    "wof:placetype":"localadmin",
    "wof:population":14347
},
  "geometry": {"coordinates":[-5.14018,34.50962],"type":"Point"}
}