{
  "type": "Feature",
  "properties": {
    "gn:admin1_code":"5.0",
    "gn:asciiname":"Ighil-n-Ait Halwane",
    "gn:country_code":"MA",
    "gn:dem":1357,
    "gn:feature_class":"P",
    "gn:feature_code":"PPL",
    "gn:name":"Ighil-n-A\u00eft Halwane",
    "gn:population":0,
    "gn:timezone":"Africa/Casablanca",
    "iso:country":"MA",
    "wof:name":"Ighil-n-Ait Halwane",
    "wof:placetype":"locality"
},
  "geometry": {"coordinates":[-6.42207,32.16151],"type":"Point"}
}