{
  "type": "Feature",
  "properties": {
    "gn:admin1_code":"6.0",
    "gn:asciiname":"Douar Cheikh Smail",
    "gn:country_code":"MA",
    "gn:dem":58,
    "gn:feature_class":"P",
    "gn:feature_code":"PPL",
    "gn:name":"Douar Che\u00efkh Smail",
    "gn:population":0,
    "gn:timezone":"Africa/Casablanca",
    "iso:country":"MA",
    "wof:name":"Douar Cheikh Smail",
    "wof:placetype":"locality"
},
  "geometry": {"coordinates":[-8.48251,33.06973],"type":"Point"}
}