{
  "type": "Feature",
  "properties": {
    "gn:admin1_code":"5.0",
    "gn:asciiname":"Ait Slimane",
    "gn:country_code":"MA",
    "gn:dem":1045,
    "gn:feature_class":"P",
    "gn:feature_code":"PPL",
    "gn:name":"A\u00eft Slimane",
    "gn:population":0,
    "gn:timezone":"Africa/Casablanca",
    "iso:country":"MA",
    "wof:name":"Ait Slimane",
    "wof:placetype":"locality"
},
  "geometry": {"coordinates":[-5.60753,32.7527],"type":"Point"}
}