{
  "type": "Feature",
  "properties": {
    "gn:admin1_code":"9.0",
    "gn:asciiname":"Takerkourt",
    "gn:country_code":"MA",
    "gn:dem":270,
    "gn:feature_class":"P",
    "gn:feature_code":"PPL",
    "gn:name":"Takerkourt",
    "gn:population":0,
    "gn:timezone":"Africa/Casablanca",
    "iso:country":"MA",
    "wof:name":"Takerkourt",
    "wof:placetype":"locality"
},
  "geometry": {"coordinates":[-8.79353,30.50452],"type":"Point"}
}