{
  "type": "Feature",
  "properties": {
    "gn:admin1_code":"05",
    "gn:asciiname":"Iroutane",
    "gn:country_code":"MA",
    "gn:dem":1079,
    "gn:elevation":"0.0",
    "gn:feature_class":"P",
    "gn:feature_code":"PPL",
    "gn:name":"Iroutane",
    "gn:population":0,
    "gn:timezone":"Africa/Casablanca",
    "iso:country":"MA",
    "name:und_x_variant":[
        "Irhoutane"
    ],
    "wof:name":"Iroutane",
    "wof:placetype":"locality"
},
  "geometry": {"coordinates":[-6.91042,31.73049],"type":"Point"}
}