{
  "type": "Feature",
  "properties": {
    "gn:admin1_code":"9.0",
    "gn:asciiname":"Ait Izimer",
    "gn:country_code":"MA",
    "gn:dem":626,
    "gn:feature_class":"P",
    "gn:feature_code":"PPL",
    "gn:name":"A\u00eft Izimer",
    "gn:population":0,
    "gn:timezone":"Africa/Casablanca",
    "iso:country":"MA",
    "wof:name":"Ait Izimer",
    "wof:placetype":"locality"
},
  "geometry": {"coordinates":[-9.11771,30.10054],"type":"Point"}
}