{
  "type": "Feature",
  "properties": {
    "gn:admin1_code":"08",
    "gn:asciiname":"Izbiatine",
    "gn:country_code":"MA",
    "gn:dem":1138,
    "gn:feature_class":"P",
    "gn:feature_code":"PPL",
    "gn:name":"Izbiatine",
    "gn:population":0,
    "gn:timezone":"Africa/Casablanca",
    "iso:country":"MA",
    "name:und_x_variant":[
        "Inzebiatene"
    ],
    "wof:name":"Izbiatine",
    "wof:placetype":"locality"
},
  "geometry": {"coordinates":[-6.92372,30.902],"type":"Point"}
}