{
  "type": "Feature",
  "properties": {
    "gn:admin1_code":"1.0",
    "gn:asciiname":"Douar Lebchirryine",
    "gn:country_code":"MA",
    "gn:dem":61,
    "gn:feature_class":"P",
    "gn:feature_code":"PPL",
    "gn:name":"Douar Lebchirryine",
    "gn:population":0,
    "gn:timezone":"Africa/Casablanca",
    "iso:country":"MA",
    "wof:name":"Douar Lebchirryine",
    "wof:placetype":"locality"
},
  "geometry": {"coordinates":[-6.05088,35.32182],"type":"Point"}
}