{
  "type": "Feature",
  "properties": {
    "gn:admin1_code":"7.0",
    "gn:asciiname":"Douar Oulad Mohamed Ben Tahar",
    "gn:country_code":"MA",
    "gn:dem":514,
    "gn:feature_class":"P",
    "gn:feature_code":"PPL",
    "gn:name":"Douar Oulad Mohamed Ben Tahar",
    "gn:population":0,
    "gn:timezone":"Africa/Casablanca",
    "iso:country":"MA",
    "wof:name":"Douar Oulad Mohamed Ben Tahar",
    "wof:placetype":"locality"
},
  "geometry": {"coordinates":[-8.86486,32.06976],"type":"Point"}
}