{
  "type": "Feature",
  "properties": {
    "gn:admin1_code":"6.0",
    "gn:asciiname":"Nkheila",
    "gn:country_code":"MA",
    "gn:dem":780,
    "gn:feature_class":"P",
    "gn:feature_code":"PPL",
    "gn:name":"Nkheila",
    "gn:population":0,
    "gn:timezone":"Africa/Casablanca",
    "iso:country":"MA",
    "wof:name":"Nkheila",
    "wof:placetype":"locality"
},
  "geometry": {"coordinates":[-7.07671,32.95834],"type":"Point"}
}