{
  "type": "Feature",
  "properties": {
    "gn:admin1_code":"1.0",
    "gn:asciiname":"Moulay Abdellah Cherif",
    "gn:country_code":"MA",
    "gn:dem":866,
    "gn:feature_class":"P",
    "gn:feature_code":"PPL",
    "gn:name":"Moulay Abdellah Cherif",
    "gn:population":0,
    "gn:timezone":"Africa/Casablanca",
    "iso:country":"MA",
    "wof:name":"Moulay Abdellah Cherif",
    "wof:placetype":"locality"
},
  "geometry": {"coordinates":[-5.08315,35.02663],"type":"Point"}
}