{
  "type": "Feature",
  "properties": {
    "gn:admin1_code":"08",
    "gn:asciiname":"Tiflit",
    "gn:country_code":"MA",
    "gn:dem":1274,
    "gn:feature_class":"P",
    "gn:feature_code":"PPL",
    "gn:name":"Tiflit",
    "gn:population":0,
    "gn:timezone":"Africa/Casablanca",
    "iso:country":"MA",
    "name:und_x_variant":[
        "Tiflet A\u00eft Ougrour",
        "Tiflit"
    ],
    "wof:name":"Tiflit",
    "wof:placetype":"locality"
},
  "geometry": {"coordinates":[-6.82297,31.08053],"type":"Point"}
}