{
  "type": "Feature",
  "properties": {
    "gn:admin1_code":"10",
    "gn:asciiname":"Ali Ou Ali",
    "gn:country_code":"MA",
    "gn:dem":371,
    "gn:feature_class":"P",
    "gn:feature_code":"PPL",
    "gn:name":"Ali Ou Ali",
    "gn:population":0,
    "gn:timezone":"Africa/Casablanca",
    "iso:country":"MA",
    "name:und_x_variant":[
        "Ali U Ali",
        "Ali Ou Ali"
    ],
    "wof:name":"Ali Ou Ali",
    "wof:placetype":"locality"
},
  "geometry": {"coordinates":[-10.17577,29.14064],"type":"Point"}
}