{
  "type": "Feature",
  "properties": {
    "gn:admin1_code":"4.0",
    "gn:asciiname":"Douar Douales",
    "gn:country_code":"MA",
    "gn:dem":169,
    "gn:feature_class":"P",
    "gn:feature_code":"PPL",
    "gn:name":"Douar Douales",
    "gn:population":0,
    "gn:timezone":"Africa/Casablanca",
    "iso:country":"MA",
    "wof:name":"Douar Douales",
    "wof:placetype":"locality"
},
  "geometry": {"coordinates":[-5.46934,34.55214],"type":"Point"}
}