{
  "type": "Feature",
  "properties": {
    "gn:admin1_code":"08",
    "gn:asciiname":"Ait Bouchboud",
    "gn:country_code":"MA",
    "gn:dem":1446,
    "gn:feature_class":"P",
    "gn:feature_code":"PPL",
    "gn:name":"A\u00eft Bouchboud",
    "gn:population":0,
    "gn:timezone":"Africa/Casablanca",
    "iso:country":"MA",
    "name:und_x_variant":[
        "A\u00eft Bouchebout",
        "A\u00eft-Bouchboud",
        "A\u00eft Bouchbout",
        "A\u00eft Bouchboud"
    ],
    "wof:name":"Ait Bouchboud",
    "wof:placetype":"locality"
},
  "geometry": {"coordinates":[-4.61445,32.34208],"type":"Point"}
}