{
  "type": "Feature",
  "properties": {
    "gn:admin1_code":"3.0",
    "gn:asciiname":"Ait El Houssine Ou Amar",
    "gn:country_code":"MA",
    "gn:dem":1309,
    "gn:feature_class":"P",
    "gn:feature_code":"PPL",
    "gn:name":"Ait El Houssine Ou Amar",
    "gn:population":0,
    "gn:timezone":"Africa/Casablanca",
    "iso:country":"MA",
    "wof:name":"Ait El Houssine Ou Amar",
    "wof:placetype":"locality"
},
  "geometry": {"coordinates":[-5.37284,33.62125],"type":"Point"}
}