{
  "type": "Feature",
  "properties": {
    "gn:admin1_code":"9.0",
    "gn:asciiname":"Tazka",
    "gn:country_code":"MA",
    "gn:dem":1208,
    "gn:feature_class":"P",
    "gn:feature_code":"PPL",
    "gn:name":"Tazka",
    "gn:population":0,
    "gn:timezone":"Africa/Casablanca",
    "iso:country":"MA",
    "wof:name":"Tazka",
    "wof:placetype":"locality"
},
  "geometry": {"coordinates":[-8.70996,30.13174],"type":"Point"}
}