{
  "type": "Feature",
  "properties": {
    "gn:admin1_code":"7.0",
    "gn:asciiname":"Oulad Ahmed ben Ihia",
    "gn:country_code":"MA",
    "gn:dem":665,
    "gn:feature_class":"P",
    "gn:feature_code":"PPL",
    "gn:name":"Oulad Ahmed ben Ihia",
    "gn:population":0,
    "gn:timezone":"Africa/Casablanca",
    "iso:country":"MA",
    "wof:name":"Oulad Ahmed ben Ihia",
    "wof:placetype":"locality"
},
  "geometry": {"coordinates":[-7.40794,31.7444],"type":"Point"}
}