{
  "type": "Feature",
  "properties": {
    "gn:admin1_code":"08",
    "gn:asciiname":"Timassirine",
    "gn:country_code":"MA",
    "gn:dem":1654,
    "gn:feature_class":"P",
    "gn:feature_code":"PPL",
    "gn:name":"Timassirine",
    "gn:population":0,
    "gn:timezone":"Africa/Casablanca",
    "iso:country":"MA",
    "wof:name":"Timassirine",
    "wof:placetype":"locality"
},
  "geometry": {"coordinates":[-6.57011,31.2906],"type":"Point"}
}