{
  "type": "Feature",
  "properties": {
    "gn:admin1_code":"9.0",
    "gn:asciiname":"Ait Ikhlafn-n-Oufalla",
    "gn:country_code":"MA",
    "gn:dem":1739,
    "gn:feature_class":"P",
    "gn:feature_code":"PPL",
    "gn:name":"A\u00eft Ikhlafn-n-Oufalla",
    "gn:population":0,
    "gn:timezone":"Africa/Casablanca",
    "iso:country":"MA",
    "wof:name":"Ait Ikhlafn-n-Oufalla",
    "wof:placetype":"locality"
},
  "geometry": {"coordinates":[-7.87896,30.22392],"type":"Point"}
}