{
  "type": "Feature",
  "properties": {
    "gn:admin1_code":"09",
    "gn:asciiname":"Tisgui",
    "gn:country_code":"MA",
    "gn:dem":1676,
    "gn:feature_class":"P",
    "gn:feature_code":"PPL",
    "gn:name":"Tisgui",
    "gn:population":0,
    "gn:timezone":"Africa/Casablanca",
    "iso:country":"MA",
    "name:und_x_variant":[
        "Tizguit",
        "Tisgui"
    ],
    "wof:name":"Tisgui",
    "wof:placetype":"locality"
},
  "geometry": {"coordinates":[-8.97209,29.52867],"type":"Point"}
}