{
  "type": "Feature",
  "properties": {
    "gn:admin1_code":"7.0",
    "gn:asciiname":"Ijaane",
    "gn:country_code":"MA",
    "gn:dem":1403,
    "gn:feature_class":"P",
    "gn:feature_code":"PPL",
    "gn:name":"Ijaane",
    "gn:population":0,
    "gn:timezone":"Africa/Casablanca",
    "iso:country":"MA",
    "wof:name":"Ijaane",
    "wof:placetype":"locality"
},
  "geometry": {"coordinates":[-7.20936,31.50153],"type":"Point"}
}