{
  "type": "Feature",
  "properties": {
    "gn:admin1_code":"4.0",
    "gn:asciiname":"Dar Abdeslam Oueld Taher",
    "gn:country_code":"MA",
    "gn:dem":81,
    "gn:feature_class":"P",
    "gn:feature_code":"PPL",
    "gn:name":"Dar Abdeslam Oueld Taher",
    "gn:population":0,
    "gn:timezone":"Africa/Casablanca",
    "iso:country":"MA",
    "wof:name":"Dar Abdeslam Oueld Taher",
    "wof:placetype":"locality"
},
  "geometry": {"coordinates":[-6.20988,34.78937],"type":"Point"}
}