{
  "type": "Feature",
  "properties": {
    "gn:admin1_code":"01",
    "gn:asciiname":"Talamkrene",
    "gn:country_code":"MA",
    "gn:dem":393,
    "gn:feature_class":"P",
    "gn:feature_code":"PPL",
    "gn:name":"Talamkrene",
    "gn:population":0,
    "gn:timezone":"Africa/Casablanca",
    "iso:country":"MA",
    "wof:name":"Talamkrene",
    "wof:placetype":"locality"
},
  "geometry": {"coordinates":[-5.26894,35.26558],"type":"Point"}
}