{
  "type": "Feature",
  "properties": {
    "gn:admin1_code":"1.0",
    "gn:asciiname":"El Kasba",
    "gn:country_code":"MA",
    "gn:dem":97,
    "gn:feature_class":"P",
    "gn:feature_code":"PPL",
    "gn:name":"El Kasba",
    "gn:population":0,
    "gn:timezone":"Africa/Casablanca",
    "iso:country":"MA",
    "wof:name":"El Kasba",
    "wof:placetype":"locality"
},
  "geometry": {"coordinates":[-5.70703,35.52814],"type":"Point"}
}