{
  "type": "Feature",
  "properties": {
    "gn:admin1_code":"2.0",
    "gn:asciiname":"Ouardana",
    "gn:country_code":"MA",
    "gn:dem":456,
    "gn:feature_class":"P",
    "gn:feature_code":"PPL",
    "gn:name":"Ouardana",
    "gn:population":0,
    "gn:timezone":"Africa/Casablanca",
    "iso:country":"MA",
    "name:ara_x_preferred":[
        "\u0648\u0631\u062f\u0627\u0646\u0629"
    ],
    "name:cat_x_preferred":[
        "Ouardana"
    ],
    "name:ceb_x_preferred":[
        "Ouardana"
    ],
    "name:swe_x_preferred":[
        "Ouardana"
    ],
    "wof:name":"Ouardana",
    "wof:placetype":"locality"
},
  "geometry": {"coordinates":[-3.43954,35.05858],"type":"Point"}
}