{
  "type": "Feature",
  "properties": {
    "gn:admin1_code":"2.0",
    "gn:asciiname":"Ouardana",
    "gn:country_code":"MA",
    "gn:dem":456,
    "gn:feature_class":"P",
    "gn:feature_code":"PPL",
    "gn:name":"Ouardana",
    "gn:population":0,
    "gn:timezone":"Africa/Casablanca",
    "iso:country":"MA",
    "wof:name":"Ouardana",
    "wof:placetype":"locality"
},
  "geometry": {"coordinates":[-3.43954,35.05858],"type":"Point"}
}