{
  "type": "Feature",
  "properties": {
    "gn:country":"MA",
    "gn:fcode":"ADM3",
    "gn:population":3413,
    "iso:country":"MA",
    "name:ara_x_preferred":[
        "\u0633\u0644\u0648\u0627\u0646"
    ],
    "name:ara_x_variant":[
        "\u0623\u0641\u0633\u0648"
    ],
    "name:azb_x_preferred":[
        "\u0627\u0641\u0633\u0648"
    ],
    "name:cat_x_preferred":[
        "Afsou"
    ],
    "name:ceb_x_preferred":[
        "Afsou"
    ],
    "name:fas_x_preferred":[
        "\u0627\u0641\u0633\u0648"
    ],
    "name:fra_x_preferred":[
        "Afsou"
    ],
    "name:fra_x_variant":[
        "Afsou (CR)",
        "Afsou (Commune Rurale)"
    ],
    "name:swe_x_preferred":[
        "Afsou"
    ],
    "qs_pg:aaroncc":"MA",
    "qs_pg:gn_country":"MA",
    "qs_pg:gn_fcode":"ADM3",
    "qs_pg:gn_pop":3413,
    "qs_pg:name":"Afsou",
    "qs_pg:photos_9r":0,
    "qs_pg:photos_sr":0,
    "qs_pg:pop_sr":4,
    "qs_pg:qs_pg_placetype":"localadmin",
    "wof:name":"Afsou",
    "wof:placetype":"localadmin",
    "wof:population":2932
},
  "geometry": {"coordinates":[-3.14224,34.82392],"type":"Point"}
}