{
  "type": "Feature",
  "properties": {
    "gn:admin1_code":"7.0",
    "gn:asciiname":"Oulad Ben Lahlub",
    "gn:country_code":"MA",
    "gn:dem":70,
    "gn:feature_class":"P",
    "gn:feature_code":"PPL",
    "gn:name":"Oulad Ben Lahlub",
    "gn:population":0,
    "gn:timezone":"Africa/Casablanca",
    "iso:country":"MA",
    "wof:name":"Oulad Ben Lahlub",
    "wof:placetype":"locality"
},
  "geometry": {"coordinates":[-9.19774,32.55885],"type":"Point"}
}