{
  "type": "Feature",
  "properties": {
    "gn:admin1_code":"9.0",
    "gn:asciiname":"Ougougane",
    "gn:country_code":"MA",
    "gn:dem":1342,
    "gn:feature_class":"P",
    "gn:feature_code":"PPL",
    "gn:name":"Ougougane",
    "gn:population":0,
    "gn:timezone":"Africa/Casablanca",
    "iso:country":"MA",
    "wof:name":"Ougougane",
    "wof:placetype":"locality"
},
  "geometry": {"coordinates":[-7.88331,30.89599],"type":"Point"}
}