{
  "type": "Feature",
  "properties": {
    "gn:admin1_code":"09",
    "gn:asciiname":"Tazmmout",
    "gn:country_code":"MA",
    "gn:dem":1276,
    "gn:feature_class":"P",
    "gn:feature_code":"PPL",
    "gn:name":"Tazmmout",
    "gn:population":0,
    "gn:timezone":"Africa/Casablanca",
    "iso:country":"MA",
    "name:und_x_variant":[
        "Tasmout"
    ],
    "wof:name":"Tazmmout",
    "wof:placetype":"locality"
},
  "geometry": {"coordinates":[-9.23591,29.62197],"type":"Point"}
}