{
  "type": "Feature",
  "properties": {
    "gn:admin1_code":"08",
    "gn:asciiname":"El Borj",
    "gn:country_code":"MA",
    "gn:dem":1632,
    "gn:feature_class":"P",
    "gn:feature_code":"PPL",
    "gn:name":"El Borj",
    "gn:population":0,
    "gn:timezone":"Africa/Casablanca",
    "iso:country":"MA",
    "name:ara_x_preferred":[
        "\u0627\u0644\u0628\u0631\u062c"
    ],
    "name:cat_x_preferred":[
        "El Borj"
    ],
    "name:ita_x_preferred":[
        "El Borj"
    ],
    "name:und_x_variant":[
        "Ksar el Borj",
        "El Bordj"
    ],
    "wof:name":"El Borj",
    "wof:placetype":"locality"
},
  "geometry": {"coordinates":[-4.96338,32.276],"type":"Point"}
}