{
  "type": "Feature",
  "properties": {
    "gn:admin1_code":"2.0",
    "gn:asciiname":"Sidi Allal Mjahed",
    "gn:country_code":"MA",
    "gn:dem":630,
    "gn:feature_class":"P",
    "gn:feature_code":"PPL",
    "gn:name":"Sidi Allal Mjahed",
    "gn:population":0,
    "gn:timezone":"Africa/Casablanca",
    "iso:country":"MA",
    "wof:name":"Sidi Allal Mjahed",
    "wof:placetype":"locality"
},
  "geometry": {"coordinates":[-3.51698,35.08648],"type":"Point"}
}