{
  "type": "Feature",
  "properties": {
    "gn:admin1_code":"1.0",
    "gn:asciiname":"Oulad Ayyachi",
    "gn:country_code":"MA",
    "gn:dem":164,
    "gn:feature_class":"P",
    "gn:feature_code":"PPL",
    "gn:name":"Oulad Ayyachi",
    "gn:population":0,
    "gn:timezone":"Africa/Casablanca",
    "iso:country":"MA",
    "wof:name":"Oulad Ayyachi",
    "wof:placetype":"locality"
},
  "geometry": {"coordinates":[-5.96631,35.38061],"type":"Point"}
}