{
  "type": "Feature",
  "properties": {
    "gn:admin1_code":"3.0",
    "gn:asciiname":"Bou Maiz",
    "gn:country_code":"MA",
    "gn:dem":1549,
    "gn:feature_class":"P",
    "gn:feature_code":"PPLL",
    "gn:name":"Bou Maiz",
    "gn:population":0,
    "gn:timezone":"Africa/Casablanca",
    "iso:country":"MA",
    "wof:name":"Bou Maiz",
    "wof:placetype":"locality"
},
  "geometry": {"coordinates":[-4.96257,33.64861],"type":"Point"}
}