{
  "type": "Feature",
  "properties": {
    "gn:admin1_code":"2.0",
    "gn:asciiname":"Douar Oulad Amer Ben Moussa",
    "gn:country_code":"MA",
    "gn:dem":703,
    "gn:feature_class":"P",
    "gn:feature_code":"PPL",
    "gn:name":"Douar Oulad Amer Ben Moussa",
    "gn:population":0,
    "gn:timezone":"Africa/Casablanca",
    "iso:country":"MA",
    "wof:name":"Douar Oulad Amer Ben Moussa",
    "wof:placetype":"locality"
},
  "geometry": {"coordinates":[-2.43234,34.50079],"type":"Point"}
}