{
  "type": "Feature",
  "properties": {
    "gn:admin1_code":"09",
    "gn:asciiname":"Bou Guir",
    "gn:country_code":"MA",
    "gn:dem":641,
    "gn:feature_class":"P",
    "gn:feature_code":"PPL",
    "gn:name":"Bou Guir",
    "gn:population":0,
    "gn:timezone":"Africa/Casablanca",
    "iso:country":"MA",
    "wof:name":"Bou Guir",
    "wof:placetype":"locality"
},
  "geometry": {"coordinates":[-6.88654,30.07714],"type":"Point"}
}