{
  "type": "Feature",
  "properties": {
    "gn:admin1_code":"01",
    "gn:asciiname":"Douar Tazayert",
    "gn:country_code":"MA",
    "gn:dem":191,
    "gn:feature_class":"P",
    "gn:feature_code":"PPL",
    "gn:name":"Douar Tazayert",
    "gn:population":0,
    "gn:timezone":"Africa/Casablanca",
    "iso:country":"MA",
    "name:und_x_variant":[
        "Taz\u00e2yart"
    ],
    "wof:name":"Douar Tazayert",
    "wof:placetype":"locality"
},
  "geometry": {"coordinates":[-4.45598,35.11765],"type":"Point"}
}