{
  "type": "Feature",
  "properties": {
    "gn:admin1_code":"03",
    "gn:asciiname":"Siaira",
    "gn:country_code":"MA",
    "gn:dem":816,
    "gn:feature_class":"P",
    "gn:feature_code":"PPL",
    "gn:name":"Sia\u00efra",
    "gn:population":0,
    "gn:timezone":"Africa/Casablanca",
    "iso:country":"MA",
    "name:und_x_variant":[
        "Jira",
        "Sia\u00efra"
    ],
    "wof:name":"Siaira",
    "wof:placetype":"locality"
},
  "geometry": {"coordinates":[-4.03161,34.50431],"type":"Point"}
}