{
  "type": "Feature",
  "properties": {
    "gn:country":"MA",
    "gn:fcode":"ADM3",
    "gn:population":3910,
    "iso:country":"MA",
    "name:ara_x_preferred":[
        "\u0633\u064a\u062f\u064a \u0639\u064a\u0633\u0649 \u0628\u0646 \u0633\u0644\u064a\u0645\u0627\u0646"
    ],
    "name:ara_x_variant":[
        "\u0633\u0648\u0631 \u0627\u0644\u0639\u0632"
    ],
    "name:cat_x_preferred":[
        "Sour El Aaz"
    ],
    "name:ceb_x_preferred":[
        "Sour El Aaz"
    ],
    "name:fra_x_preferred":[
        "Sour El Aaz"
    ],
    "name:fra_x_variant":[
        "Sour El Aaz (CR)",
        "Sour El Aaz (Commune Rurale)"
    ],
    "name:ita_x_preferred":[
        "Sour El Aaz"
    ],
    "name:swe_x_preferred":[
        "Sour El Aaz"
    ],
    "qs_pg:aaroncc":"MA",
    "qs_pg:gn_country":"MA",
    "qs_pg:gn_fcode":"ADM3",
    "qs_pg:gn_pop":3910,
    "qs_pg:name":"Sour El Aaz",
    "qs_pg:photos_9r":0,
    "qs_pg:photos_sr":0,
    "qs_pg:pop_sr":4,
    "qs_pg:qs_pg_placetype":"localadmin",
    "wof:name":"Sour El Aaz",
    "wof:placetype":"localadmin",
    "wof:population":3850
},
  "geometry": {"coordinates":[-7.0506,31.85484],"type":"Point"}
}