{
  "type": "Feature",
  "properties": {
    "gn:admin1_code":"2.0",
    "gn:asciiname":"Oulad Ben Said",
    "gn:country_code":"MA",
    "gn:dem":629,
    "gn:feature_class":"P",
    "gn:feature_code":"PPL",
    "gn:name":"Oulad Ben Said",
    "gn:population":0,
    "gn:timezone":"Africa/Casablanca",
    "iso:country":"MA",
    "wof:name":"Oulad Ben Said",
    "wof:placetype":"locality"
},
  "geometry": {"coordinates":[-2.12885,34.78471],"type":"Point"}
}