{
  "type": "Feature",
  "properties": {
    "gn:admin1_code":"7.0",
    "gn:asciiname":"Ouankerra",
    "gn:country_code":"MA",
    "gn:dem":538,
    "gn:feature_class":"P",
    "gn:feature_code":"PPL",
    "gn:name":"Ouankerra",
    "gn:population":0,
    "gn:timezone":"Africa/Casablanca",
    "iso:country":"MA",
    "wof:name":"Ouankerra",
    "wof:placetype":"locality"
},
  "geometry": {"coordinates":[-9.51184,30.92185],"type":"Point"}
}