{
  "type": "Feature",
  "properties": {
    "gn:admin1_code":"01",
    "gn:asciiname":"Douar Khandeq Lhad",
    "gn:country_code":"MA",
    "gn:dem":204,
    "gn:feature_class":"P",
    "gn:feature_code":"PPL",
    "gn:name":"Douar Khandeq Lhad",
    "gn:population":0,
    "gn:timezone":"Africa/Casablanca",
    "iso:country":"MA",
    "name:und_x_variant":[
        "Khandak el Had"
    ],
    "wof:name":"Douar Khandeq Lhad",
    "wof:placetype":"locality"
},
  "geometry": {"coordinates":[-5.63481,35.55594],"type":"Point"}
}