{
  "type": "Feature",
  "properties": {
    "gn:admin1_code":"4.0",
    "gn:asciiname":"Lamhamid",
    "gn:country_code":"MA",
    "gn:dem":33,
    "gn:feature_class":"P",
    "gn:feature_code":"PPL",
    "gn:name":"Lamhamid",
    "gn:population":0,
    "gn:timezone":"Africa/Casablanca",
    "iso:country":"MA",
    "wof:name":"Lamhamid",
    "wof:placetype":"locality"
},
  "geometry": {"coordinates":[-6.23686,34.99267],"type":"Point"}
}