{
  "type": "Feature",
  "properties": {
    "gn:admin1_code":"08",
    "gn:asciiname":"Tine Iouarkane",
    "gn:country_code":"MA",
    "gn:dem":1740,
    "gn:feature_class":"P",
    "gn:feature_code":"PPL",
    "gn:name":"Tine Iouarkane",
    "gn:population":0,
    "gn:timezone":"Africa/Casablanca",
    "iso:country":"MA",
    "name:und_x_variant":[
        "Tine Iourkane",
        "Tiniourkane",
        "Tine Iouarkane"
    ],
    "wof:name":"Tine Iouarkane",
    "wof:placetype":"locality"
},
  "geometry": {"coordinates":[-5.56388,31.25317],"type":"Point"}
}