{
  "type": "Feature",
  "properties": {
    "gn:admin1_code":"06",
    "gn:asciiname":"Jem'at Oulad 'Abbou",
    "gn:country_code":"MA",
    "gn:dem":220,
    "gn:feature_class":"P",
    "gn:feature_code":"PPL",
    "gn:name":"Jem\u2019at Oulad \u2019Abbou",
    "gn:population":0,
    "gn:timezone":"Africa/Casablanca",
    "iso:country":"MA",
    "name:und_x_variant":[
        "Foucauld",
        "Souk-Jemad-Oulad-Abbou",
        "Foucald",
        "S\u016bq Jum\u2018ah Awl\u0101d \u2018Abb\u016b",
        "Foucault",
        "Souk-Jema\u00e2-Oulad-Abbou",
        "Souk Jemaa des Oulad Arbou",
        "Souk Jemaa des Oulad Abbou",
        "Jem\u2019at Oulad \u2019Abbou"
    ],
    "wof:name":"Jem'at Oulad 'Abbou",
    "wof:placetype":"locality"
},
  "geometry": {"coordinates":[-7.9336,33.1148],"type":"Point"}
}