{
  "type": "Feature",
  "properties": {
    "gn:admin1_code":"09",
    "gn:asciiname":"Tazermant",
    "gn:country_code":"MA",
    "gn:dem":1167,
    "gn:feature_class":"P",
    "gn:feature_code":"PPL",
    "gn:name":"Tazermant",
    "gn:population":0,
    "gn:timezone":"Africa/Casablanca",
    "iso:country":"MA",
    "name:und_x_variant":[
        "Tazermannt",
        "Tazermant"
    ],
    "wof:name":"Tazermant",
    "wof:placetype":"locality"
},
  "geometry": {"coordinates":[-8.4928,30.34023],"type":"Point"}
}