{
  "type": "Feature",
  "properties": {
    "gn:admin1_code":"7.0",
    "gn:asciiname":"Douar Raqouane",
    "gn:country_code":"MA",
    "gn:dem":477,
    "gn:feature_class":"P",
    "gn:feature_code":"PPL",
    "gn:name":"Douar Raqouane",
    "gn:population":0,
    "gn:timezone":"Africa/Casablanca",
    "iso:country":"MA",
    "wof:name":"Douar Raqouane",
    "wof:placetype":"locality"
},
  "geometry": {"coordinates":[-7.85843,31.62727000000001],"type":"Point"}
}