{
  "type": "Feature",
  "properties": {
    "gn:admin1_code":"07",
    "gn:asciiname":"Douar Laarissa",
    "gn:country_code":"MA",
    "gn:dem":695,
    "gn:feature_class":"P",
    "gn:feature_code":"PPL",
    "gn:name":"Douar Laarissa",
    "gn:population":0,
    "gn:timezone":"Africa/Casablanca",
    "iso:country":"MA",
    "name:und_x_variant":[
        "El hrissa",
        "Douar Larissa",
        "Larissa",
        "Douar Laarissa"
    ],
    "wof:name":"Douar Laarissa",
    "wof:placetype":"locality"
},
  "geometry": {"coordinates":[-7.68498,31.92478],"type":"Point"}
}