{
  "type": "Feature",
  "properties": {
    "gn:admin1_code":"01",
    "gn:asciiname":"Ait Messaoud",
    "gn:country_code":"MA",
    "gn:dem":1355,
    "gn:feature_class":"P",
    "gn:feature_code":"PPL",
    "gn:name":"A\u00eft Messaoud",
    "gn:population":0,
    "gn:timezone":"Africa/Casablanca",
    "iso:country":"MA",
    "name:und_x_variant":[
        "A\u00eft Ali Moussa",
        "A\u00eft Messaoud"
    ],
    "wof:name":"Ait Messaoud",
    "wof:placetype":"locality"
},
  "geometry": {"coordinates":[-3.96482,34.96087],"type":"Point"}
}