{
  "type": "Feature",
  "properties": {
    "gn:admin1_code":"01",
    "gn:asciiname":"Mzara",
    "gn:country_code":"MA",
    "gn:dem":47,
    "gn:feature_class":"P",
    "gn:feature_code":"PPL",
    "gn:name":"Mzara",
    "gn:population":0,
    "gn:timezone":"Africa/Casablanca",
    "iso:country":"MA",
    "wof:name":"Mzara",
    "wof:placetype":"locality"
},
  "geometry": {"coordinates":[-6.00748,35.46906],"type":"Point"}
}