{
  "type": "Feature",
  "properties": {
    "gn:admin1_code":"03",
    "gn:asciiname":"Douar Kalaat Fechtala",
    "gn:country_code":"MA",
    "gn:dem":266,
    "gn:feature_class":"P",
    "gn:feature_code":"PPL",
    "gn:name":"Douar Kalaat Fechtala",
    "gn:population":0,
    "gn:timezone":"Africa/Casablanca",
    "iso:country":"MA",
    "name:und_x_variant":[
        "Qal\u2019at Fichtala",
        "Lfachilote",
        "Qal\u2019at Fiehtala",
        "Kalla Fichtala",
        "Kalaa Fichtala",
        "Douar Lkalaa",
        "Douar Kalaat Fechtala"
    ],
    "wof:name":"Douar Kalaat Fechtala",
    "wof:placetype":"locality"
},
  "geometry": {"coordinates":[-5.20245,34.49806],"type":"Point"}
}