{
  "type": "Feature",
  "properties": {
    "gn:country":"MA",
    "gn:fcode":"ADM3",
    "gn:population":7710,
    "iso:country":"MA",
    "name:ara_x_preferred":[
        "\u0628\u0631\u0627\u0631\u062d\u0629"
    ],
    "name:fra_x_preferred":[
        "Elgouzate"
    ],
    "name:fra_x_variant":[
        "Elgouzate (CR)",
        "Elgouzate (Commune Rurale)"
    ],
    "qs:name":"Elgouzate",
    "qs:photos_9r":0,
    "qs:photos_sr":0,
    "qs:pop_sr":"5",
    "wof:name":"Elgouzate",
    "wof:placetype":"localadmin",
    "wof:population":7710
},
  "geometry": {"coordinates":[-4.12677,34.49718],"type":"Point"}
}