{
  "type": "Feature",
  "properties": {
    "gn:admin1_code":"02",
    "gn:asciiname":"Iqdimene Oulad Lafqih",
    "gn:country_code":"MA",
    "gn:dem":442,
    "gn:feature_class":"P",
    "gn:feature_code":"PPL",
    "gn:name":"Iqdimene Oulad Lafqih",
    "gn:population":0,
    "gn:timezone":"Africa/Casablanca",
    "iso:country":"MA",
    "wof:name":"Iqdimene Oulad Lafqih",
    "wof:placetype":"locality"
},
  "geometry": {"coordinates":[-3.35143,35.15837],"type":"Point"}
}