{
  "type": "Feature",
  "properties": {
    "gn:admin1_code":"2.0",
    "gn:asciiname":"Afras Issebbanene",
    "gn:country_code":"MA",
    "gn:dem":55,
    "gn:feature_class":"P",
    "gn:feature_code":"PPL",
    "gn:name":"Afras Issebbanene",
    "gn:population":0,
    "gn:timezone":"Africa/Casablanca",
    "iso:country":"MA",
    "wof:name":"Afras Issebbanene",
    "wof:placetype":"locality"
},
  "geometry": {"coordinates":[-2.53113,35.085],"type":"Point"}
}