{
  "type": "Feature",
  "properties": {
    "gn:admin1_code":"07",
    "gn:asciiname":"Tagadirt",
    "gn:country_code":"MA",
    "gn:dem":1248,
    "gn:feature_class":"P",
    "gn:feature_code":"PPL",
    "gn:name":"Tagadirt",
    "gn:population":0,
    "gn:timezone":"Africa/Casablanca",
    "iso:country":"MA",
    "wof:name":"Tagadirt",
    "wof:placetype":"locality"
},
  "geometry": {"coordinates":[-7.98489,31.23514],"type":"Point"}
}