{
  "type": "Feature",
  "properties": {
    "gn:admin1_code":"06",
    "gn:asciiname":"Oulad Chebene",
    "gn:country_code":"MA",
    "gn:dem":245,
    "gn:feature_class":"P",
    "gn:feature_code":"PPL",
    "gn:name":"Oulad Chebene",
    "gn:population":0,
    "gn:timezone":"Africa/Casablanca",
    "iso:country":"MA",
    "name:und_x_variant":[
        "Douar Ouled Chebene",
        "Oulad-Cheb\u00e8n",
        "Douar Oulad Ahmed Ben Meddi Cheba\u00efa",
        "Ouled Chbane",
        "Douar Oulad Ahmed ben Heddi Cheba\u00efa",
        "Oulad Chebene"
    ],
    "wof:name":"Oulad Chebene",
    "wof:placetype":"locality"
},
  "geometry": {"coordinates":[-8.52677,32.33612],"type":"Point"}
}