{
  "type": "Feature",
  "properties": {
    "gn:admin1_code":"07",
    "gn:asciiname":"Tazouggart",
    "gn:country_code":"MA",
    "gn:dem":1379,
    "gn:feature_class":"P",
    "gn:feature_code":"PPL",
    "gn:name":"Tazouggart",
    "gn:population":0,
    "gn:timezone":"Africa/Casablanca",
    "iso:country":"MA",
    "name:und_x_variant":[
        "Tazouguerte",
        "Tazzouguert",
        "Tazouggart"
    ],
    "wof:name":"Tazouggart",
    "wof:placetype":"locality"
},
  "geometry": {"coordinates":[-7.39265,31.40097],"type":"Point"}
}