{
  "type": "Feature",
  "properties": {
    "gn:admin1_code":"7.0",
    "gn:asciiname":"Ftala",
    "gn:country_code":"MA",
    "gn:dem":1776,
    "gn:feature_class":"P",
    "gn:feature_code":"PPL",
    "gn:name":"Ftala",
    "gn:population":0,
    "gn:timezone":"Africa/Casablanca",
    "iso:country":"MA",
    "wof:name":"Ftala",
    "wof:placetype":"locality"
},
  "geometry": {"coordinates":[-7.88527,31.25305],"type":"Point"}
}