{
  "type": "Feature",
  "properties": {
    "gn:admin1_code":"09",
    "gn:asciiname":"Id 'Omar",
    "gn:country_code":"MA",
    "gn:dem":307,
    "gn:feature_class":"P",
    "gn:feature_code":"PPL",
    "gn:name":"Id \u2019Omar",
    "gn:population":0,
    "gn:timezone":"Africa/Casablanca",
    "iso:country":"MA",
    "name:und_x_variant":[
        "Id \u2019Omar",
        "Id Aomar"
    ],
    "wof:name":"Id 'Omar",
    "wof:placetype":"locality"
},
  "geometry": {"coordinates":[-9.46961,29.69559000000001],"type":"Point"}
}