{
  "type": "Feature",
  "properties": {
    "gn:admin1_code":"9.0",
    "gn:asciiname":"Ait Yahya",
    "gn:country_code":"MA",
    "gn:dem":1255,
    "gn:feature_class":"P",
    "gn:feature_code":"PPL",
    "gn:name":"A\u00eft Yahya",
    "gn:population":0,
    "gn:timezone":"Africa/Casablanca",
    "iso:country":"MA",
    "wof:name":"Ait Yahya",
    "wof:placetype":"locality"
},
  "geometry": {"coordinates":[-8.2555,30.85071],"type":"Point"}
}