{
  "type": "Feature",
  "properties": {
    "gn:admin1_code":"9.0",
    "gn:asciiname":"Id al Haj",
    "gn:country_code":"MA",
    "gn:dem":1260,
    "gn:feature_class":"P",
    "gn:feature_code":"PPL",
    "gn:name":"Id al Haj",
    "gn:population":0,
    "gn:timezone":"Africa/Casablanca",
    "iso:country":"MA",
    "wof:name":"Id al Haj",
    "wof:placetype":"locality"
},
  "geometry": {"coordinates":[-9.31178,29.53923],"type":"Point"}
}