{
  "type": "Feature",
  "properties": {
    "gn:admin1_code":"9.0",
    "gn:asciiname":"Witdndan",
    "gn:country_code":"MA",
    "gn:dem":1288,
    "gn:feature_class":"P",
    "gn:feature_code":"PPL",
    "gn:name":"Witdndan",
    "gn:population":0,
    "gn:timezone":"Africa/Casablanca",
    "iso:country":"MA",
    "wof:name":"Witdndan",
    "wof:placetype":"locality"
},
  "geometry": {"coordinates":[-8.96257,29.91544],"type":"Point"}
}