{
  "type": "Feature",
  "properties": {
    "gn:admin1_code":"08",
    "gn:asciiname":"Ait Brahim",
    "gn:country_code":"MA",
    "gn:dem":1192,
    "gn:feature_class":"P",
    "gn:feature_code":"PPL",
    "gn:name":"A\u00eft Brahim",
    "gn:population":0,
    "gn:timezone":"Africa/Casablanca",
    "iso:country":"MA",
    "name:und_x_variant":[
        "A\u00eft Ou Brahim",
        "A\u00eft Brahim"
    ],
    "wof:name":"Ait Brahim",
    "wof:placetype":"locality"
},
  "geometry": {"coordinates":[-4.94598,31.90173],"type":"Point"}
}