{
  "type": "Feature",
  "properties": {
    "gn:admin1_code":"09",
    "gn:asciiname":"Imentass",
    "gn:country_code":"MA",
    "gn:dem":909,
    "gn:feature_class":"P",
    "gn:feature_code":"PPL",
    "gn:name":"Imentass",
    "gn:population":0,
    "gn:timezone":"Africa/Casablanca",
    "iso:country":"MA",
    "name:und_x_variant":[
        "Imantas",
        "Imentas",
        "Imentass"
    ],
    "wof:name":"Imentass",
    "wof:placetype":"locality"
},
  "geometry": {"coordinates":[-9.65,29.45],"type":"Point"}
}