{
  "type": "Feature",
  "properties": {
    "gn:country":"MA",
    "gn:fcode":"ADM3",
    "gn:population":9701,
    "iso:country":"MA",
    "name:ara_x_preferred":[
        "\u0623\u0648\u0644\u0627\u062f \u0633\u064a \u0628\u0648\u062d\u064a\u0649"
    ],
    "name:ara_x_variant":[
        "\u062a\u0627\u0645\u062f\u0627"
    ],
    "name:ary_x_preferred":[
        "\u062a\u0627\u0645\u062f\u0627"
    ],
    "name:azb_x_preferred":[
        "\u062a\u0627\u0645\u062f\u0627"
    ],
    "name:cat_x_preferred":[
        "Tamda"
    ],
    "name:ceb_x_preferred":[
        "Tamda"
    ],
    "name:cym_x_preferred":[
        "Tamda"
    ],
    "name:eng_x_preferred":[
        "Tamda"
    ],
    "name:fas_x_preferred":[
        "\u062a\u0627\u0645\u062f\u0627"
    ],
    "name:fra_x_preferred":[
        "Tamda"
    ],
    "name:fra_x_variant":[
        "Tamda (CR)",
        "Tamda (Commune Rurale)"
    ],
    "name:ita_x_preferred":[
        "Tamda"
    ],
    "qs:name":"Tamda",
    "qs:photos_9r":0,
    "qs:photos_sr":0,
    "qs:pop_sr":"5",
    "wd:wordcount":60,
    "wof:name":"Tamda",
    "wof:placetype":"localadmin",
    "wof:population":9701
},
  "geometry": {"coordinates":[-8.34645,32.43963],"type":"Point"}
}