{
  "type": "Feature",
  "properties": {
    "gn:admin1_code":"5.0",
    "gn:asciiname":"Tigoutit",
    "gn:country_code":"MA",
    "gn:dem":1255,
    "gn:feature_class":"P",
    "gn:feature_code":"PPL",
    "gn:name":"Tigoutit",
    "gn:population":0,
    "gn:timezone":"Africa/Casablanca",
    "iso:country":"MA",
    "wof:name":"Tigoutit",
    "wof:placetype":"locality"
},
  "geometry": {"coordinates":[-6.2247,32.03452],"type":"Point"}
}