{
  "type": "Feature",
  "properties": {
    "gn:admin1_code":"3.0",
    "gn:asciiname":"Oulad Moumene",
    "gn:country_code":"MA",
    "gn:dem":489,
    "gn:feature_class":"P",
    "gn:feature_code":"PPL",
    "gn:name":"Oulad Moumene",
    "gn:population":0,
    "gn:timezone":"Africa/Casablanca",
    "iso:country":"MA",
    "wof:name":"Oulad Moumene",
    "wof:placetype":"locality"
},
  "geometry": {"coordinates":[-5.36882,33.94012],"type":"Point"}
}