{
  "type": "Feature",
  "properties": {
    "gn:admin1_code":"7.0",
    "gn:asciiname":"Id Laaraj",
    "gn:country_code":"MA",
    "gn:dem":170,
    "gn:feature_class":"P",
    "gn:feature_code":"PPL",
    "gn:name":"Id Laaraj",
    "gn:population":0,
    "gn:timezone":"Africa/Casablanca",
    "iso:country":"MA",
    "wof:name":"Id Laaraj",
    "wof:placetype":"locality"
},
  "geometry": {"coordinates":[-9.62243,31.4961],"type":"Point"}
}