{
  "type": "Feature",
  "properties": {
    "gn:admin1_code":"4.0",
    "gn:asciiname":"Ain Laabanat",
    "gn:country_code":"MA",
    "gn:dem":15,
    "gn:feature_class":"P",
    "gn:feature_code":"PPL",
    "gn:name":"Ain Laabanat",
    "gn:population":0,
    "gn:timezone":"Africa/Casablanca",
    "iso:country":"MA",
    "wof:name":"Ain Laabanat",
    "wof:placetype":"locality"
},
  "geometry": {"coordinates":[-7.05294,33.86061],"type":"Point"}
}