{
  "type": "Feature",
  "properties": {
    "gn:admin1_code":"07",
    "gn:asciiname":"Tadrart",
    "gn:country_code":"MA",
    "gn:dem":1969,
    "gn:feature_class":"P",
    "gn:feature_code":"PPL",
    "gn:name":"Tadrart",
    "gn:population":0,
    "gn:timezone":"Africa/Casablanca",
    "iso:country":"MA",
    "name:ceb_x_preferred":[
        "Tadrart"
    ],
    "name:swe_x_preferred":[
        "Tadrart"
    ],
    "name:und_x_variant":[
        "Tadraret"
    ],
    "wof:name":"Tadrart",
    "wof:placetype":"locality"
},
  "geometry": {"coordinates":[-7.73392,31.20571],"type":"Point"}
}