{
  "type": "Feature",
  "properties": {
    "gn:admin1_code":"02",
    "gn:asciiname":"Rotba",
    "gn:country_code":"MA",
    "gn:dem":378,
    "gn:feature_class":"P",
    "gn:feature_code":"PPL",
    "gn:name":"Rotba",
    "gn:population":0,
    "gn:timezone":"Africa/Casablanca",
    "iso:country":"MA",
    "name:und_x_variant":[
        "Arrutbet",
        "Radbet",
        "Arroutbet",
        "Rodbet",
        "Rotba"
    ],
    "wof:name":"Rotba",
    "wof:placetype":"locality"
},
  "geometry": {"coordinates":[-3.3799,35.06111],"type":"Point"}
}