{
  "type": "Feature",
  "properties": {
    "gn:admin1_code":"03",
    "gn:asciiname":"Douar El Hajjarine",
    "gn:country_code":"MA",
    "gn:dem":281,
    "gn:feature_class":"P",
    "gn:feature_code":"PPL",
    "gn:name":"Douar El Hajjarine",
    "gn:population":0,
    "gn:timezone":"Africa/Casablanca",
    "iso:country":"MA",
    "name:und_x_variant":[
        "El Hajirine",
        "El Hajarine",
        "Douar El Hajjarine"
    ],
    "wof:name":"Douar El Hajjarine",
    "wof:placetype":"locality"
},
  "geometry": {"coordinates":[-5.16729,34.70842],"type":"Point"}
}