{
  "type": "Feature",
  "properties": {
    "gn:admin1_code":"09",
    "gn:asciiname":"Tagamout",
    "gn:country_code":"MA",
    "gn:dem":1260,
    "gn:feature_class":"P",
    "gn:feature_code":"PPL",
    "gn:name":"Tagamout",
    "gn:population":0,
    "gn:timezone":"Africa/Casablanca",
    "iso:country":"MA",
    "name:und_x_variant":[
        "Tagmout",
        "Tagmo\u00fbt n\u2019 A\u00eft Paout"
    ],
    "wof:name":"Tagamout",
    "wof:placetype":"locality"
},
  "geometry": {"coordinates":[-8.91073,29.82057],"type":"Point"}
}