{
  "type": "Feature",
  "properties": {
    "gn:admin1_code":"07",
    "gn:asciiname":"Douar Zaouiat Louda",
    "gn:country_code":"MA",
    "gn:dem":288,
    "gn:feature_class":"P",
    "gn:feature_code":"PPL",
    "gn:name":"Douar Zaouiat Louda",
    "gn:population":0,
    "gn:timezone":"Africa/Casablanca",
    "iso:country":"MA",
    "name:und_x_variant":[
        "Zaouiete Loudai",
        "Zawit Louda",
        "Zaouit Louda",
        "Douar Zaouiat Louda"
    ],
    "wof:name":"Douar Zaouiat Louda",
    "wof:placetype":"locality"
},
  "geometry": {"coordinates":[-9.78232,30.95353],"type":"Point"}
}