{
  "type": "Feature",
  "properties": {
    "gn:admin1_code":"09",
    "gn:asciiname":"Douar Ali Ou Brahim",
    "gn:country_code":"MA",
    "gn:dem":75,
    "gn:feature_class":"P",
    "gn:feature_code":"PPL",
    "gn:name":"Douar Ali Ou Brahim",
    "gn:population":0,
    "gn:timezone":"Africa/Casablanca",
    "iso:country":"MA",
    "name:und_x_variant":[
        "Dar Ali Ou Brahim",
        "Ali Ou Brahim",
        "Douar Ali Ou Brahim"
    ],
    "wof:name":"Douar Ali Ou Brahim",
    "wof:placetype":"locality"
},
  "geometry": {"coordinates":[-9.33699,30.36663],"type":"Point"}
}