{
  "type": "Feature",
  "properties": {
    "gn:country":"MA",
    "gn:fcode":"ADM3",
    "gn:pop":30286,
    "iso:country":"MA",
    "name:ara_x_preferred":[
        "\u0623\u0648\u0644\u0627\u062f \u0633\u0628\u064a\u0637\u0629"
    ],
    "name:fra_x_preferred":[
        "Saniat Berguig"
    ],
    "name:fra_x_variant":[
        "Saniat Berguig (CR)",
        "Saniat Berguig (Commune Rurale)"
    ],
    "qs:name":"Saniat Berguig",
    "qs:photos_9r":0,
    "qs:photos_sr":0,
    "qs:pop_sr":"7",
    "wd:wordcount":61,
    "wof:name":"Saniat Berguig",
    "wof:placetype":"localadmin",
    "wof:population":30286
},
  "geometry": {"coordinates":[-8.60733,32.6991],"type":"Point"}
}