{
  "type": "Feature",
  "properties": {
    "gn:country":"MA",
    "gn:fcode":"ADM3",
    "gn:population":30286,
    "iso:country":"MA",
    "name:ara_x_preferred":[
        "\u0623\u0648\u0644\u0627\u062f \u0633\u0628\u064a\u0637\u0629"
    ],
    "name:ara_x_variant":[
        "\u0633\u0627\u0646\u064a\u0629 \u0628\u0631\u0643\u064a\u0643"
    ],
    "name:azb_x_preferred":[
        "\u0633\u0627\u0646\u06cc\u0647 \u0628\u0631\u06a9\u06cc\u06a9"
    ],
    "name:cat_x_preferred":[
        "Saniat Berguig"
    ],
    "name:ceb_x_preferred":[
        "Saniat Berguig"
    ],
    "name:eng_x_preferred":[
        "Saniat Berguig"
    ],
    "name:fas_x_preferred":[
        "\u0633\u0627\u0646\u06cc\u0647 \u0628\u0631\u06a9\u06cc\u06a9"
    ],
    "name:fra_x_preferred":[
        "Saniat Berguig"
    ],
    "name:fra_x_variant":[
        "Saniat Berguig (CR)",
        "Saniat Berguig (Commune Rurale)"
    ],
    "name:ita_x_preferred":[
        "Saniat Berguig"
    ],
    "name:swe_x_preferred":[
        "Saniat Berguig"
    ],
    "qs:name":"Saniat Berguig",
    "qs:photos_9r":0,
    "qs:photos_sr":0,
    "qs:pop_sr":"7",
    "wd:wordcount":61,
    "wof:name":"Saniat Berguig",
    "wof:placetype":"localadmin",
    "wof:population":30286
},
  "geometry": {"coordinates":[-8.60733,32.6991],"type":"Point"}
}