{
  "type": "Feature",
  "properties": {
    "gn:admin1_code":"10",
    "gn:asciiname":"Id Mouloud",
    "gn:country_code":"MA",
    "gn:dem":1275,
    "gn:feature_class":"P",
    "gn:feature_code":"PPL",
    "gn:name":"Id Mouloud",
    "gn:population":0,
    "gn:timezone":"Africa/Casablanca",
    "iso:country":"MA",
    "name:und_x_variant":[
        "Id Mouloudi",
        "Id Mouloud"
    ],
    "wof:name":"Id Mouloud",
    "wof:placetype":"locality"
},
  "geometry": {"coordinates":[-9.3533,29.40759000000001],"type":"Point"}
}