{
  "type": "Feature",
  "properties": {
    "gn:admin1_code":"7.0",
    "gn:asciiname":"Gwilmat",
    "gn:country_code":"MA",
    "gn:dem":659,
    "gn:feature_class":"P",
    "gn:feature_code":"PPL",
    "gn:name":"Gwilmat",
    "gn:population":0,
    "gn:timezone":"Africa/Casablanca",
    "iso:country":"MA",
    "wof:name":"Gwilmat",
    "wof:placetype":"locality"
},
  "geometry": {"coordinates":[-7.18258,31.80109],"type":"Point"}
}