{
  "type": "Feature",
  "properties": {
    "gn:admin1_code":"9.0",
    "gn:asciiname":"Imoussawl",
    "gn:country_code":"MA",
    "gn:dem":1246,
    "gn:feature_class":"P",
    "gn:feature_code":"PPL",
    "gn:name":"Imoussawl",
    "gn:population":0,
    "gn:timezone":"Africa/Casablanca",
    "iso:country":"MA",
    "wof:name":"Imoussawl",
    "wof:placetype":"locality"
},
  "geometry": {"coordinates":[-8.84615,29.96822],"type":"Point"}
}