{
  "type": "Feature",
  "properties": {
    "gn:admin1_code":"02",
    "gn:asciiname":"Et Tleta Bou Beker",
    "gn:country_code":"MA",
    "gn:dem":496,
    "gn:feature_class":"P",
    "gn:feature_code":"PPL",
    "gn:name":"Et Tleta Bou Beker",
    "gn:population":0,
    "gn:timezone":"Africa/Casablanca",
    "iso:country":"MA",
    "name:und_x_variant":[
        "Soko Tzelatza de Bu Beker",
        "Zoco et Telata Ulad Bubquer",
        "Telata bu Beker",
        "Zoco Tzelatza Bu-Beker",
        "Et Tleta Bou Beker"
    ],
    "wof:name":"Et Tleta Bou Beker",
    "wof:placetype":"locality"
},
  "geometry": {"coordinates":[-3.40646,34.82612],"type":"Point"}
}