{
  "type": "Feature",
  "properties": {
    "gn:admin1_code":"07",
    "gn:asciiname":"Douar Oulad Lahsen",
    "gn:country_code":"MA",
    "gn:dem":476,
    "gn:feature_class":"P",
    "gn:feature_code":"PPL",
    "gn:name":"Douar Oulad Lahsen",
    "gn:population":0,
    "gn:timezone":"Africa/Casablanca",
    "iso:country":"MA",
    "name:und_x_variant":[
        "Douar Oulad Hasene",
        "Oulad Lahssene",
        "Ouled Lahc\u00e8ne",
        "Oulad Lahcen",
        "Oulad Lahsene",
        "Douar Oulad Lahsen"
    ],
    "wof:name":"Douar Oulad Lahsen",
    "wof:placetype":"locality"
},
  "geometry": {"coordinates":[-7.86646,32.48607],"type":"Point"}
}