{
  "type": "Feature",
  "properties": {
    "gn:admin1_code":"2.0",
    "gn:asciiname":"Douar Oulad El Haj Ali Bou Abdellah",
    "gn:country_code":"MA",
    "gn:dem":941,
    "gn:feature_class":"P",
    "gn:feature_code":"PPL",
    "gn:name":"Douar Oulad El Haj Ali Bou Abdellah",
    "gn:population":0,
    "gn:timezone":"Africa/Casablanca",
    "iso:country":"MA",
    "wof:name":"Douar Oulad El Haj Ali Bou Abdellah",
    "wof:placetype":"locality"
},
  "geometry": {"coordinates":[-2.15617,34.84075],"type":"Point"}
}