{
  "type": "Feature",
  "properties": {
    "gn:admin1_code":"06",
    "gn:asciiname":"Douar Moulay Echgagne",
    "gn:country_code":"MA",
    "gn:dem":144,
    "gn:feature_class":"P",
    "gn:feature_code":"PPL",
    "gn:name":"Douar Moulay Echgagne",
    "gn:population":0,
    "gn:timezone":"Africa/Casablanca",
    "iso:country":"MA",
    "name:und_x_variant":[
        "Douar Moulay Achafgane"
    ],
    "wof:name":"Douar Moulay Echgagne",
    "wof:placetype":"locality"
},
  "geometry": {"coordinates":[-8.93837,32.72022],"type":"Point"}
}