{
  "type": "Feature",
  "properties": {
    "gn:country":"MA",
    "gn:fcode":"ADM3",
    "gn:population":11251,
    "iso:country":"MA",
    "name:ara_x_preferred":[
        "\u062f\u0627\u0631 \u0623\u0645 \u0627\u0644\u0633\u0644\u0637\u0627\u0646"
    ],
    "name:ara_x_variant":[
        "\u0633\u064a\u062f\u064a \u0644\u0627\u0645\u064a\u0646"
    ],
    "name:cat_x_preferred":[
        "Sidi Lamine"
    ],
    "name:ceb_x_preferred":[
        "Sidi Lamine"
    ],
    "name:fra_x_preferred":[
        "Sidi Lamine"
    ],
    "name:fra_x_variant":[
        "Sidi Lamine (CR)",
        "Sidi Lamine (Commune Rurale)"
    ],
    "name:ita_x_preferred":[
        "Sidi Lamine"
    ],
    "name:swe_x_preferred":[
        "Sidi Lamine"
    ],
    "qs_pg:aaroncc":"MA",
    "qs_pg:gn_country":"MA",
    "qs_pg:gn_fcode":"ADM3",
    "qs_pg:gn_pop":11251,
    "qs_pg:name":"Sidi Lamine",
    "qs_pg:photos_9r":0,
    "qs_pg:photos_sr":0,
    "qs_pg:pop_sr":6,
    "qs_pg:qs_pg_placetype":"localadmin",
    "wof:name":"Sidi Lamine",
    "wof:placetype":"localadmin",
    "wof:population":16808
},
  "geometry": {"coordinates":[-5.98048,32.88321],"type":"Point"}
}