{
  "type": "Feature",
  "properties": {
    "gn:admin1_code":"6.0",
    "gn:asciiname":"Behora",
    "gn:country_code":"MA",
    "gn:dem":382,
    "gn:feature_class":"P",
    "gn:feature_code":"PPL",
    "gn:name":"Behora",
    "gn:population":0,
    "gn:timezone":"Africa/Casablanca",
    "iso:country":"MA",
    "wof:name":"Behora",
    "wof:placetype":"locality"
},
  "geometry": {"coordinates":[-7.75273,32.77047],"type":"Point"}
}