{
  "type": "Feature",
  "properties": {
    "gn:admin1_code":"03",
    "gn:asciiname":"Tem bou Zid",
    "gn:country_code":"MA",
    "gn:dem":1085,
    "gn:feature_class":"P",
    "gn:feature_code":"PPL",
    "gn:name":"Tem bou Zid",
    "gn:population":0,
    "gn:timezone":"Africa/Casablanca",
    "iso:country":"MA",
    "name:und_x_variant":[
        "Tiberranine",
        "Tibberrarine",
        "Tembouzid",
        "Tem bou Zid"
    ],
    "wof:name":"Tem bou Zid",
    "wof:placetype":"locality"
},
  "geometry": {"coordinates":[-4.42968,34.68113],"type":"Point"}
}