{
  "type": "Feature",
  "properties": {
    "gn:admin1_code":"01",
    "gn:asciiname":"Douar Lkherba Chnatta",
    "gn:country_code":"MA",
    "gn:dem":367,
    "gn:feature_class":"P",
    "gn:feature_code":"PPL",
    "gn:name":"Douar Lkherba Chnatta",
    "gn:population":0,
    "gn:timezone":"Africa/Casablanca",
    "iso:country":"MA",
    "name:und_x_variant":[
        "Kherba",
        "El Kherba Chen\u00e2tta",
        "El Kherba",
        "El Kherba Chenatfa",
        "Douar Lkherba Chnatta"
    ],
    "wof:name":"Douar Lkherba Chnatta",
    "wof:placetype":"locality"
},
  "geometry": {"coordinates":[-5.72109,35.2792],"type":"Point"}
}