{
  "type": "Feature",
  "properties": {
    "gn:admin1_code":"08",
    "gn:asciiname":"Talat-n-Ou 'Arab",
    "gn:country_code":"MA",
    "gn:dem":1728,
    "gn:feature_class":"P",
    "gn:feature_code":"PPL",
    "gn:name":"Talat-n-Ou \u2019Arab",
    "gn:population":0,
    "gn:timezone":"Africa/Casablanca",
    "iso:country":"MA",
    "name:und_x_variant":[
        "Talat Ou Arab",
        "Talat Ou Arabe",
        "Talat n\u2019Ouarab",
        "Talat n\u2019Ou Arab",
        "Talat-n-Ou \u2019Arab"
    ],
    "wof:name":"Talat-n-Ou 'Arab",
    "wof:placetype":"locality"
},
  "geometry": {"coordinates":[-5.47518,32.37648],"type":"Point"}
}