{
  "type": "Feature",
  "properties": {
    "gn:admin1_code":"07",
    "gn:asciiname":"Douar Zaakna",
    "gn:country_code":"MA",
    "gn:dem":291,
    "gn:feature_class":"P",
    "gn:feature_code":"PPL",
    "gn:name":"Douar Zaakna",
    "gn:population":0,
    "gn:timezone":"Africa/Casablanca",
    "iso:country":"MA",
    "name:und_x_variant":[
        "Zaakna"
    ],
    "wof:name":"Douar Zaakna",
    "wof:placetype":"locality"
},
  "geometry": {"coordinates":[-8.65357,32.28937],"type":"Point"}
}