{
  "type": "Feature",
  "properties": {
    "gn:admin1_code":"08",
    "gn:asciiname":"Ait el Fkih",
    "gn:country_code":"MA",
    "gn:dem":1292,
    "gn:feature_class":"P",
    "gn:feature_code":"PPL",
    "gn:name":"A\u00eft el Fkih",
    "gn:population":0,
    "gn:timezone":"Africa/Casablanca",
    "iso:country":"MA",
    "name:und_x_variant":[
        "A\u00eft Lfekik",
        "A\u00eft el Fkih"
    ],
    "wof:name":"Ait el Fkih",
    "wof:placetype":"locality"
},
  "geometry": {"coordinates":[-4.43046,32.25583],"type":"Point"}
}