{
  "type": "Feature",
  "properties": {
    "gn:admin1_code":"08",
    "gn:asciiname":"Tastlift",
    "gn:country_code":"MA",
    "gn:dem":889,
    "gn:feature_class":"P",
    "gn:feature_code":"PPL",
    "gn:name":"Tastlift",
    "gn:population":0,
    "gn:timezone":"Africa/Casablanca",
    "iso:country":"MA",
    "name:und_x_variant":[
        "Tastifte",
        "Tastif",
        "Tastlift"
    ],
    "wof:name":"Tastlift",
    "wof:placetype":"locality"
},
  "geometry": {"coordinates":[-6.87109,30.37529],"type":"Point"}
}