{
  "type": "Feature",
  "properties": {
    "gn:admin1_code":"09",
    "gn:admin2_code":"581.0",
    "gn:admin3_code":"458111112.0",
    "gn:asciiname":"Reggada",
    "gn:country_code":"MA",
    "gn:dem":387,
    "gn:feature_class":"P",
    "gn:feature_code":"PPLA3",
    "gn:name":"Reggada",
    "gn:population":0,
    "gn:timezone":"Africa/Casablanca",
    "iso:country":"MA",
    "name:fra_x_preferred":[
        "Reggada"
    ],
    "name:und_x_variant":[
        "Souk-el-Had de Reggada",
        "Er Reggada",
        "Reggada"
    ],
    "wof:name":"Reggada",
    "wof:placetype":"locality"
},
  "geometry": {"coordinates":[-9.70086,29.58016],"type":"Point"}
}