{
  "type": "Feature",
  "properties": {
    "gn:admin1_code":"6.0",
    "gn:asciiname":"Oulad Sidi Mohammed",
    "gn:country_code":"MA",
    "gn:dem":327,
    "gn:feature_class":"P",
    "gn:feature_code":"PPL",
    "gn:name":"Oulad Sidi Mohammed",
    "gn:population":0,
    "gn:timezone":"Africa/Casablanca",
    "iso:country":"MA",
    "wof:name":"Oulad Sidi Mohammed",
    "wof:placetype":"locality"
},
  "geometry": {"coordinates":[-7.62379,32.53625],"type":"Point"}
}