{
  "type": "Feature",
  "properties": {
    "gn:admin1_code":"07",
    "gn:asciiname":"Ait Yassine Brayka",
    "gn:country_code":"MA",
    "gn:dem":447,
    "gn:feature_class":"P",
    "gn:feature_code":"PPL",
    "gn:name":"A\u00eft Yassine Brayka",
    "gn:population":0,
    "gn:timezone":"Africa/Casablanca",
    "iso:country":"MA",
    "name:und_x_variant":[
        "A\u00eft Yassine Brayka",
        "A\u00eft Yassine"
    ],
    "wof:name":"Ait Yassine Brayka",
    "wof:placetype":"locality"
},
  "geometry": {"coordinates":[-8.01098,32.02488],"type":"Point"}
}