{
  "type": "Feature",
  "properties": {
    "gn:admin1_code":"01",
    "gn:asciiname":"Douar Dchayer",
    "gn:country_code":"MA",
    "gn:dem":220,
    "gn:feature_class":"P",
    "gn:feature_code":"PPL",
    "gn:name":"Douar Dchayer",
    "gn:population":0,
    "gn:timezone":"Africa/Casablanca",
    "iso:country":"MA",
    "name:und_x_variant":[
        "Dchiar",
        "Dechiar",
        "Douar Dechiar",
        "Douar Dchayer"
    ],
    "wof:name":"Douar Dchayer",
    "wof:placetype":"locality"
},
  "geometry": {"coordinates":[-5.65036,34.88672],"type":"Point"}
}