{
  "type": "Feature",
  "properties": {
    "gn:admin1_code":"9.0",
    "gn:asciiname":"Anrouz",
    "gn:country_code":"MA",
    "gn:dem":1903,
    "gn:feature_class":"P",
    "gn:feature_code":"PPL",
    "gn:name":"Anrouz",
    "gn:population":0,
    "gn:timezone":"Africa/Casablanca",
    "iso:country":"MA",
    "wof:name":"Anrouz",
    "wof:placetype":"locality"
},
  "geometry": {"coordinates":[-7.77213,30.80128],"type":"Point"}
}