{
  "type": "Feature",
  "properties": {
    "gn:admin1_code":"08",
    "gn:asciiname":"Tioujdal",
    "gn:country_code":"MA",
    "gn:dem":1594,
    "gn:feature_class":"P",
    "gn:feature_code":"PPL",
    "gn:name":"Tioujdal",
    "gn:population":0,
    "gn:timezone":"Africa/Casablanca",
    "iso:country":"MA",
    "name:und_x_variant":[
        "Tiourjdale",
        "Tiourjdal",
        "Tioujdal"
    ],
    "wof:name":"Tioujdal",
    "wof:placetype":"locality"
},
  "geometry": {"coordinates":[-7.3768,31.13298],"type":"Point"}
}