{
  "type": "Feature",
  "properties": {
    "gn:admin1_code":"7.0",
    "gn:asciiname":"Tameurzagt",
    "gn:country_code":"MA",
    "gn:dem":968,
    "gn:feature_class":"P",
    "gn:feature_code":"PPL",
    "gn:name":"Tameurzagt",
    "gn:population":0,
    "gn:timezone":"Africa/Casablanca",
    "iso:country":"MA",
    "wof:name":"Tameurzagt",
    "wof:placetype":"locality"
},
  "geometry": {"coordinates":[-9.14868,31.25613],"type":"Point"}
}