{
  "type": "Feature",
  "properties": {
    "gn:admin1_code":"03",
    "gn:asciiname":"Douar Marbat",
    "gn:country_code":"MA",
    "gn:dem":865,
    "gn:feature_class":"P",
    "gn:feature_code":"PPL",
    "gn:name":"Douar Marbat",
    "gn:population":0,
    "gn:timezone":"Africa/Casablanca",
    "iso:country":"MA",
    "name:und_x_variant":[
        "Merbat",
        "Merbate",
        "Douar Merbat",
        "Douar Marbat"
    ],
    "wof:name":"Douar Marbat",
    "wof:placetype":"locality"
},
  "geometry": {"coordinates":[-4.25426,34.00826],"type":"Point"}
}