{
  "type": "Feature",
  "properties": {
    "gn:admin1_code":"7.0",
    "gn:asciiname":"Ouaderzane",
    "gn:country_code":"MA",
    "gn:dem":454,
    "gn:feature_class":"P",
    "gn:feature_code":"PPL",
    "gn:name":"Ouaderzane",
    "gn:population":0,
    "gn:timezone":"Africa/Casablanca",
    "iso:country":"MA",
    "wof:name":"Ouaderzane",
    "wof:placetype":"locality"
},
  "geometry": {"coordinates":[-9.69005,30.84609],"type":"Point"}
}