{
  "type": "Feature",
  "properties": {
    "gn:admin1_code":"9.0",
    "gn:asciiname":"Ait At Talb",
    "gn:country_code":"MA",
    "gn:dem":883,
    "gn:feature_class":"P",
    "gn:feature_code":"PPL",
    "gn:name":"A\u00eft At Talb",
    "gn:population":0,
    "gn:timezone":"Africa/Casablanca",
    "iso:country":"MA",
    "wof:name":"Ait At Talb",
    "wof:placetype":"locality"
},
  "geometry": {"coordinates":[-9.04291,29.74454],"type":"Point"}
}