{
  "type": "Feature",
  "properties": {
    "gn:admin1_code":"07",
    "gn:asciiname":"Oulad Souam",
    "gn:country_code":"MA",
    "gn:dem":176,
    "gn:feature_class":"P",
    "gn:feature_code":"PPL",
    "gn:name":"Oulad Souam",
    "gn:population":0,
    "gn:timezone":"Africa/Casablanca",
    "iso:country":"MA",
    "name:und_x_variant":[
        "Souam"
    ],
    "wof:name":"Oulad Souam",
    "wof:placetype":"locality"
},
  "geometry": {"coordinates":[-8.85684,32.4069],"type":"Point"}
}