{
  "type": "Feature",
  "properties": {
    "gn:admin1_code":"04",
    "gn:asciiname":"Dar Cheikh Ahmed",
    "gn:country_code":"MA",
    "gn:dem":392,
    "gn:feature_class":"P",
    "gn:feature_code":"PPL",
    "gn:name":"Dar Cheikh Ahmed",
    "gn:population":0,
    "gn:timezone":"Africa/Casablanca",
    "iso:country":"MA",
    "name:und_x_variant":[
        "Dar Ahmed"
    ],
    "wof:name":"Dar Cheikh Ahmed",
    "wof:placetype":"locality"
},
  "geometry": {"coordinates":[-6.15679,33.89443],"type":"Point"}
}