{
  "type": "Feature",
  "properties": {
    "gn:admin1_code":"09",
    "gn:asciiname":"Zaouiat Sidi Lahsene Ali",
    "gn:country_code":"MA",
    "gn:dem":766,
    "gn:feature_class":"P",
    "gn:feature_code":"PPL",
    "gn:name":"Zaouiat Sidi Lahsene Ali",
    "gn:population":0,
    "gn:timezone":"Africa/Casablanca",
    "iso:country":"MA",
    "name:und_x_variant":[
        "Zaouia Sidi Lahsene",
        "Zaouia Sidi Lahsen",
        "Zawit Sidi Lahsene \u2019Ali",
        "Zaouiat Sidi Lahsene Ali"
    ],
    "wof:name":"Zaouiat Sidi Lahsene Ali",
    "wof:placetype":"locality"
},
  "geometry": {"coordinates":[-7.37111,30.07095],"type":"Point"}
}