{
  "type": "Feature",
  "properties": {
    "gn:admin1_code":"5.0",
    "gn:asciiname":"Aouinet Akziz",
    "gn:country_code":"MA",
    "gn:dem":975,
    "gn:feature_class":"P",
    "gn:feature_code":"PPL",
    "gn:name":"Aouinet Akziz",
    "gn:population":0,
    "gn:timezone":"Africa/Casablanca",
    "iso:country":"MA",
    "wof:name":"Aouinet Akziz",
    "wof:placetype":"locality"
},
  "geometry": {"coordinates":[-5.62872,32.96345],"type":"Point"}
}