{
  "type": "Feature",
  "properties": {
    "gn:admin1_code":"3.0",
    "gn:asciiname":"Dar Ali Oussadene",
    "gn:country_code":"MA",
    "gn:dem":559,
    "gn:feature_class":"P",
    "gn:feature_code":"PPL",
    "gn:name":"Dar Ali Oussadene",
    "gn:population":0,
    "gn:timezone":"Africa/Casablanca",
    "iso:country":"MA",
    "wof:name":"Dar Ali Oussadene",
    "wof:placetype":"locality"
},
  "geometry": {"coordinates":[-4.74361,33.96304],"type":"Point"}
}