{
  "type": "Feature",
  "properties": {
    "gn:admin1_code":"6.0",
    "gn:asciiname":"La'marna",
    "gn:country_code":"MA",
    "gn:dem":479,
    "gn:feature_class":"P",
    "gn:feature_code":"PPL",
    "gn:name":"La\u2019marna",
    "gn:population":0,
    "gn:timezone":"Africa/Casablanca",
    "iso:country":"MA",
    "wof:name":"La'marna",
    "wof:placetype":"locality"
},
  "geometry": {"coordinates":[-7.02688,32.57366],"type":"Point"}
}