{
  "type": "Feature",
  "properties": {
    "gn:admin1_code":"05",
    "gn:asciiname":"Zwayad",
    "gn:country_code":"MA",
    "gn:dem":452,
    "gn:feature_class":"P",
    "gn:feature_code":"PPL",
    "gn:name":"Zwayad",
    "gn:population":0,
    "gn:timezone":"Africa/Casablanca",
    "iso:country":"MA",
    "name:und_x_variant":[
        "Douar Zoua\u00efd"
    ],
    "wof:name":"Zwayad",
    "wof:placetype":"locality"
},
  "geometry": {"coordinates":[-6.81665,32.53379],"type":"Point"}
}