{
  "type": "Feature",
  "properties": {
    "gn:admin1_code":"5.0",
    "gn:asciiname":"Dar Pacha",
    "gn:country_code":"MA",
    "gn:dem":545,
    "gn:feature_class":"P",
    "gn:feature_code":"PPL",
    "gn:name":"Dar Pacha",
    "gn:population":0,
    "gn:timezone":"Africa/Casablanca",
    "iso:country":"MA",
    "wof:name":"Dar Pacha",
    "wof:placetype":"locality"
},
  "geometry": {"coordinates":[-6.19085,32.50832],"type":"Point"}
}