{
  "type": "Feature",
  "properties": {
    "gn:admin1_code":"7.0",
    "gn:asciiname":"Anazza",
    "gn:country_code":"MA",
    "gn:dem":1050,
    "gn:feature_class":"P",
    "gn:feature_code":"PPL",
    "gn:name":"Anazza",
    "gn:population":0,
    "gn:timezone":"Africa/Casablanca",
    "iso:country":"MA",
    "wof:name":"Anazza",
    "wof:placetype":"locality"
},
  "geometry": {"coordinates":[-7.68663,31.42946],"type":"Point"}
}