{
  "type": "Feature",
  "properties": {
    "gn:admin1_code":"1.0",
    "gn:asciiname":"Ait Boubaouene",
    "gn:country_code":"MA",
    "gn:dem":229,
    "gn:feature_class":"P",
    "gn:feature_code":"PPL",
    "gn:name":"Ait Boubaouene",
    "gn:population":0,
    "gn:timezone":"Africa/Casablanca",
    "iso:country":"MA",
    "wof:name":"Ait Boubaouene",
    "wof:placetype":"locality"
},
  "geometry": {"coordinates":[-3.93777,35.10431],"type":"Point"}
}