{
  "type": "Feature",
  "properties": {
    "gn:admin1_code":"3.0",
    "gn:asciiname":"Douar Ait Ben Ali",
    "gn:country_code":"MA",
    "gn:dem":546,
    "gn:feature_class":"P",
    "gn:feature_code":"PPL",
    "gn:name":"Douar Ait Ben Ali",
    "gn:population":0,
    "gn:timezone":"Africa/Casablanca",
    "iso:country":"MA",
    "wof:name":"Douar Ait Ben Ali",
    "wof:placetype":"locality"
},
  "geometry": {"coordinates":[-4.49274,34.01712],"type":"Point"}
}