{
  "type": "Feature",
  "properties": {
    "gn:admin1_code":"6.0",
    "gn:asciiname":"'Winat",
    "gn:country_code":"MA",
    "gn:dem":151,
    "gn:feature_class":"P",
    "gn:feature_code":"PPL",
    "gn:name":"\u2019Winat",
    "gn:population":0,
    "gn:timezone":"Africa/Casablanca",
    "iso:country":"MA",
    "wof:name":"'Winat",
    "wof:placetype":"locality"
},
  "geometry": {"coordinates":[-8.09855,33.05273],"type":"Point"}
}