{
  "type": "Feature",
  "properties": {
    "gn:admin1_code":"7.0",
    "gn:asciiname":"Tahouda",
    "gn:country_code":"MA",
    "gn:dem":349,
    "gn:feature_class":"P",
    "gn:feature_code":"PPL",
    "gn:name":"Tahouda",
    "gn:population":0,
    "gn:timezone":"Africa/Casablanca",
    "iso:country":"MA",
    "wof:name":"Tahouda",
    "wof:placetype":"locality"
},
  "geometry": {"coordinates":[-9.68006,30.99111],"type":"Point"}
}