{
  "type": "Feature",
  "properties": {
    "gn:admin1_code":"02",
    "gn:asciiname":"Tafssassine",
    "gn:country_code":"MA",
    "gn:dem":1639,
    "gn:feature_class":"P",
    "gn:feature_code":"PPL",
    "gn:name":"Tafssassine",
    "gn:population":0,
    "gn:timezone":"Africa/Casablanca",
    "iso:country":"MA",
    "name:und_x_variant":[
        "Tafsasine",
        "Tafsassine",
        "Tafssassine"
    ],
    "wof:name":"Tafssassine",
    "wof:placetype":"locality"
},
  "geometry": {"coordinates":[-3.91555,32.45865],"type":"Point"}
}