{
  "type": "Feature",
  "properties": {
    "gn:admin1_code":"3.0",
    "gn:asciiname":"Douar Bou Mlal",
    "gn:country_code":"MA",
    "gn:dem":720,
    "gn:feature_class":"P",
    "gn:feature_code":"PPL",
    "gn:name":"Douar Bou Mlal",
    "gn:population":0,
    "gn:timezone":"Africa/Casablanca",
    "iso:country":"MA",
    "wof:name":"Douar Bou Mlal",
    "wof:placetype":"locality"
},
  "geometry": {"coordinates":[-4.50366,33.9312],"type":"Point"}
}