{
  "type": "Feature",
  "properties": {
    "gn:admin1_code":"03",
    "gn:asciiname":"Sidi el Mokhfi",
    "gn:country_code":"MA",
    "gn:dem":356,
    "gn:feature_class":"P",
    "gn:feature_code":"PPL",
    "gn:name":"Sidi el Mokhfi",
    "gn:population":0,
    "gn:timezone":"Africa/Casablanca",
    "iso:country":"MA",
    "name:und_x_variant":[
        "Sidi al Makhfi",
        "Sidi el Mekfi",
        "Sidi el Mokhfi"
    ],
    "wof:name":"Sidi el Mokhfi",
    "wof:placetype":"locality"
},
  "geometry": {"coordinates":[-4.7893,34.60375],"type":"Point"}
}