{
  "type": "Feature",
  "properties": {
    "gn:admin1_code":"09",
    "gn:asciiname":"Anebdour",
    "gn:country_code":"MA",
    "gn:dem":1305,
    "gn:feature_class":"P",
    "gn:feature_code":"PPL",
    "gn:name":"Anebdour",
    "gn:population":0,
    "gn:timezone":"Africa/Casablanca",
    "iso:country":"MA",
    "wof:name":"Anebdour",
    "wof:placetype":"locality"
},
  "geometry": {"coordinates":[-8.91,29.75],"type":"Point"}
}