{
  "type": "Feature",
  "properties": {
    "gn:admin1_code":"08",
    "gn:asciiname":"Targoua n el Mal",
    "gn:country_code":"MA",
    "gn:dem":895,
    "gn:feature_class":"P",
    "gn:feature_code":"PPL",
    "gn:name":"Targoua n el M\u00e2l",
    "gn:population":0,
    "gn:timezone":"Africa/Casablanca",
    "iso:country":"MA",
    "name:und_x_variant":[
        "Targoua n el M\u00e2l",
        "Targoua n\u2019el Mal"
    ],
    "wof:name":"Targoua n el Mal",
    "wof:placetype":"locality"
},
  "geometry": {"coordinates":[-6.27518,30.68691],"type":"Point"}
}