{
  "type": "Feature",
  "properties": {
    "gn:admin1_code":"2.0",
    "gn:asciiname":"Douar Sidi Ali Ben Yakhlef",
    "gn:country_code":"MA",
    "gn:dem":224,
    "gn:feature_class":"P",
    "gn:feature_code":"PPL",
    "gn:name":"Douar Sidi Ali Ben Yakhlef",
    "gn:population":0,
    "gn:timezone":"Africa/Casablanca",
    "iso:country":"MA",
    "wof:name":"Douar Sidi Ali Ben Yakhlef",
    "wof:placetype":"locality"
},
  "geometry": {"coordinates":[-2.3029,34.9062],"type":"Point"}
}