{
  "type": "Feature",
  "properties": {
    "gn:admin1_code":"46",
    "gn:asciiname":"El Menzel",
    "gn:cc2":"MA",
    "gn:country_code":"MA",
    "gn:dem":1012,
    "gn:feature_class":"P",
    "gn:feature_code":"PPL",
    "gn:name":"El Menzel",
    "gn:population":0,
    "gn:timezone":"Africa/Casablanca",
    "iso:country":"MA",
    "name:und_x_variant":[
        "El Mennzel",
        "El Menzel"
    ],
    "wof:name":"El Menzel",
    "wof:placetype":"locality"
},
  "geometry": {"coordinates":[-4.53,33.83],"type":"Point"}
}