{
  "type": "Feature",
  "properties": {
    "gn:admin1_code":"5.0",
    "gn:asciiname":"Al Krarma",
    "gn:country_code":"MA",
    "gn:dem":449,
    "gn:feature_class":"P",
    "gn:feature_code":"PPL",
    "gn:name":"Al Krarma",
    "gn:population":0,
    "gn:timezone":"Africa/Casablanca",
    "iso:country":"MA",
    "wof:name":"Al Krarma",
    "wof:placetype":"locality"
},
  "geometry": {"coordinates":[-6.94193,32.54636],"type":"Point"}
}