{
  "type": "Feature",
  "properties": {
    "gn:admin1_code":"5.0",
    "gn:asciiname":"Igouzouln",
    "gn:country_code":"MA",
    "gn:dem":1419,
    "gn:feature_class":"P",
    "gn:feature_code":"PPL",
    "gn:name":"Igouzouln",
    "gn:population":0,
    "gn:timezone":"Africa/Casablanca",
    "iso:country":"MA",
    "wof:name":"Igouzouln",
    "wof:placetype":"locality"
},
  "geometry": {"coordinates":[-7.15458,31.62873],"type":"Point"}
}