{
  "type": "Feature",
  "properties": {
    "gn:admin1_code":"7.0",
    "gn:asciiname":"Douar Leghoual",
    "gn:country_code":"MA",
    "gn:dem":158,
    "gn:feature_class":"P",
    "gn:feature_code":"PPL",
    "gn:name":"Douar Leghoual",
    "gn:population":0,
    "gn:timezone":"Africa/Casablanca",
    "iso:country":"MA",
    "name:und_x_variant":[
        "El Roual Bel Kaaba",
        "El Roual",
        "Douar el Rhoual Bel Kabaa"
    ],
    "wof:name":"Douar Leghoual",
    "wof:placetype":"locality"
},
  "geometry": {"coordinates":[-8.90567,32.44336],"type":"Point"}
}