{
  "type": "Feature",
  "properties": {
    "gn:admin1_code":"09",
    "gn:asciiname":"Ifoullousn",
    "gn:country_code":"MA",
    "gn:dem":1209,
    "gn:feature_class":"P",
    "gn:feature_code":"PPL",
    "gn:name":"Ifoullousn",
    "gn:population":0,
    "gn:timezone":"Africa/Casablanca",
    "iso:country":"MA",
    "name:und_x_variant":[
        "Ifoulloussn",
        "Ifoullousene",
        "Ifoullousn"
    ],
    "wof:name":"Ifoullousn",
    "wof:placetype":"locality"
},
  "geometry": {"coordinates":[-9.00995,29.86535],"type":"Point"}
}