{
  "type": "Feature",
  "properties": {
    "gn:admin1_code":"9.0",
    "gn:asciiname":"Id Birouk",
    "gn:country_code":"MA",
    "gn:dem":387,
    "gn:feature_class":"P",
    "gn:feature_code":"PPL",
    "gn:name":"Id Birouk",
    "gn:population":0,
    "gn:timezone":"Africa/Casablanca",
    "iso:country":"MA",
    "wof:name":"Id Birouk",
    "wof:placetype":"locality"
},
  "geometry": {"coordinates":[-9.71487,29.57767],"type":"Point"}
}