{
  "type": "Feature",
  "properties": {
    "gn:admin1_code":"2.0",
    "gn:asciiname":"Ifjjiouan",
    "gn:country_code":"MA",
    "gn:dem":205,
    "gn:feature_class":"P",
    "gn:feature_code":"PPL",
    "gn:name":"Ifjjiouan",
    "gn:population":0,
    "gn:timezone":"Africa/Casablanca",
    "iso:country":"MA",
    "wof:name":"Ifjjiouan",
    "wof:placetype":"locality"
},
  "geometry": {"coordinates":[-3.13532,35.15865],"type":"Point"}
}