{
  "type": "Feature",
  "properties": {
    "gn:admin1_code":"4.0",
    "gn:asciiname":"Labbatla",
    "gn:country_code":"MA",
    "gn:dem":22,
    "gn:feature_class":"P",
    "gn:feature_code":"PPL",
    "gn:name":"Labbatla",
    "gn:population":0,
    "gn:timezone":"Africa/Casablanca",
    "iso:country":"MA",
    "wof:name":"Labbatla",
    "wof:placetype":"locality"
},
  "geometry": {"coordinates":[-6.58444,34.31242],"type":"Point"}
}