{
  "type": "Feature",
  "properties": {
    "gn:admin1_code":"7.0",
    "gn:asciiname":"Douar Dhar Nzala",
    "gn:country_code":"MA",
    "gn:dem":416,
    "gn:feature_class":"P",
    "gn:feature_code":"PPL",
    "gn:name":"Douar Dhar Nzala",
    "gn:population":0,
    "gn:timezone":"Africa/Casablanca",
    "iso:country":"MA",
    "wof:name":"Douar Dhar Nzala",
    "wof:placetype":"locality"
},
  "geometry": {"coordinates":[-7.68683,32.16445],"type":"Point"}
}