{
  "type": "Feature",
  "properties": {
    "gn:admin1_code":"2.0",
    "gn:asciiname":"Douar Tijouine El Madmer",
    "gn:country_code":"MA",
    "gn:dem":662,
    "gn:feature_class":"P",
    "gn:feature_code":"PPL",
    "gn:name":"Douar Tijouine El Madmer",
    "gn:population":0,
    "gn:timezone":"Africa/Casablanca",
    "iso:country":"MA",
    "wof:name":"Douar Tijouine El Madmer",
    "wof:placetype":"locality"
},
  "geometry": {"coordinates":[-2.42176,34.71686],"type":"Point"}
}