{
  "type": "Feature",
  "properties": {
    "gn:admin1_code":"7.0",
    "gn:asciiname":"Douar Ida Ou Tanane",
    "gn:country_code":"MA",
    "gn:dem":254,
    "gn:feature_class":"P",
    "gn:feature_code":"PPL",
    "gn:name":"Douar Ida Ou Tanane",
    "gn:population":0,
    "gn:timezone":"Africa/Casablanca",
    "iso:country":"MA",
    "wof:name":"Douar Ida Ou Tanane",
    "wof:placetype":"locality"
},
  "geometry": {"coordinates":[-9.56953,31.47627],"type":"Point"}
}