{
  "type": "Feature",
  "properties": {
    "gn:admin1_code":"03",
    "gn:asciiname":"Beni Raham",
    "gn:country_code":"MA",
    "gn:dem":1038,
    "gn:feature_class":"P",
    "gn:feature_code":"PPL",
    "gn:name":"Beni Raham",
    "gn:population":0,
    "gn:timezone":"Africa/Casablanca",
    "iso:country":"MA",
    "name:und_x_variant":[
        "Douar Beni Raham",
        "Beni Raham"
    ],
    "wof:name":"Beni Raham",
    "wof:placetype":"locality"
},
  "geometry": {"coordinates":[-4.08019,33.94478],"type":"Point"}
}