{
  "type": "Feature",
  "properties": {
    "gn:admin1_code":"6.0",
    "gn:asciiname":"Oulad Yazza",
    "gn:country_code":"MA",
    "gn:dem":52,
    "gn:feature_class":"P",
    "gn:feature_code":"PPL",
    "gn:name":"Oulad Yazza",
    "gn:population":0,
    "gn:timezone":"Africa/Casablanca",
    "iso:country":"MA",
    "wof:name":"Oulad Yazza",
    "wof:placetype":"locality"
},
  "geometry": {"coordinates":[-8.51486,33.0945],"type":"Point"}
}