{
  "type": "Feature",
  "properties": {
    "gn:admin1_code":"07",
    "gn:asciiname":"Tilniyf",
    "gn:country_code":"MA",
    "gn:dem":1501,
    "gn:feature_class":"P",
    "gn:feature_code":"PPL",
    "gn:name":"Tilniyf",
    "gn:population":0,
    "gn:timezone":"Africa/Casablanca",
    "iso:country":"MA",
    "name:und_x_variant":[
        "Tilnif"
    ],
    "wof:name":"Tilniyf",
    "wof:placetype":"locality"
},
  "geometry": {"coordinates":[-7.41301,31.37289],"type":"Point"}
}