{
  "type": "Feature",
  "properties": {
    "gn:admin1_code":"3.0",
    "gn:asciiname":"Douar Boubiyad",
    "gn:country_code":"MA",
    "gn:dem":274,
    "gn:feature_class":"P",
    "gn:feature_code":"PPL",
    "gn:name":"Douar Boubiyad",
    "gn:population":0,
    "gn:timezone":"Africa/Casablanca",
    "iso:country":"MA",
    "wof:name":"Douar Boubiyad",
    "wof:placetype":"locality"
},
  "geometry": {"coordinates":[-5.42826,34.14202],"type":"Point"}
}