{
  "type": "Feature",
  "properties": {
    "gn:admin1_code":"07",
    "gn:asciiname":"Tassila Iattarn",
    "gn:country_code":"MA",
    "gn:dem":852,
    "gn:feature_class":"P",
    "gn:feature_code":"PPL",
    "gn:name":"Tassila I\u00e2ttarn",
    "gn:population":0,
    "gn:timezone":"Africa/Casablanca",
    "iso:country":"MA",
    "name:und_x_variant":[
        "Tisal Atarene",
        "Tassila n\u2019Iattarn",
        "Tassila I\u00e2ttarn"
    ],
    "wof:name":"Tassila Iattarn",
    "wof:placetype":"locality"
},
  "geometry": {"coordinates":[-9.43,30.88],"type":"Point"}
}