{
  "type": "Feature",
  "properties": {
    "gn:admin1_code":"09",
    "gn:asciiname":"Dou Ouzrou",
    "gn:country_code":"MA",
    "gn:dem":1081,
    "gn:feature_class":"P",
    "gn:feature_code":"PPL",
    "gn:name":"Dou Ouzrou",
    "gn:population":0,
    "gn:timezone":"Africa/Casablanca",
    "iso:country":"MA",
    "name:und_x_variant":[
        "Ouzrou",
        "Dou Ouzrou"
    ],
    "wof:name":"Dou Ouzrou",
    "wof:placetype":"locality"
},
  "geometry": {"coordinates":[-8.52202,29.70858],"type":"Point"}
}