{
  "type": "Feature",
  "properties": {
    "gn:admin1_code":"9.0",
    "gn:asciiname":"Imi-n-Tizguiy",
    "gn:country_code":"MA",
    "gn:dem":1361,
    "gn:feature_class":"P",
    "gn:feature_code":"PPL",
    "gn:name":"Imi-n-Tizguiy",
    "gn:population":0,
    "gn:timezone":"Africa/Casablanca",
    "iso:country":"MA",
    "wof:name":"Imi-n-Tizguiy",
    "wof:placetype":"locality"
},
  "geometry": {"coordinates":[-8.49654,30.21063],"type":"Point"}
}