{
  "type": "Feature",
  "properties": {
    "gn:country":"MA",
    "gn:fcode":"ADM3",
    "gn:pop":4767,
    "iso:country":"MA",
    "name:fra_x_preferred":[
        "Ait Baha"
    ],
    "name:fra_x_variant":[
        "Ait Baha (MU)",
        "Ait Baha (Commune Urbaine)"
    ],
    "qs:name":"Ait Baha",
    "qs:photos_9r":0,
    "qs:photos_sr":0,
    "qs:pop_sr":"4",
    "wd:wordcount":45,
    "wof:name":"Ait Baha",
    "wof:placetype":"localadmin",
    "wof:population":4767
},
  "geometry": {"coordinates":[-9.15775,30.07121],"type":"Point"}
}