{
  "type": "Feature",
  "properties": {
    "gn:country":"MA",
    "gn:fcode":"ADM3",
    "gn:population":4767,
    "iso:country":"MA",
    "name:ara_x_preferred":[
        "\u0622\u064a\u062a \u0628\u0627\u0647\u0627"
    ],
    "name:ary_x_preferred":[
        "\u0622\u064a\u062a \u0628\u0627\u0647\u0627"
    ],
    "name:azb_x_preferred":[
        "\u0622\u06cc\u062a \u0628\u0627\u0647\u0627"
    ],
    "name:cat_x_preferred":[
        "A\u00eft Baha"
    ],
    "name:ceb_x_preferred":[
        "Ait Baha"
    ],
    "name:deu_x_preferred":[
        "A\u00eft Baha"
    ],
    "name:eng_x_preferred":[
        "Ait Baha"
    ],
    "name:eus_x_preferred":[
        "Ait Baha"
    ],
    "name:fas_x_preferred":[
        "\u0622\u06cc\u062a \u0628\u0627\u0647\u0627"
    ],
    "name:fra_x_preferred":[
        "Ait Baha"
    ],
    "name:fra_x_variant":[
        "Ait Baha (MU)",
        "Ait Baha (Commune Urbaine)",
        "A\u00eft Baha"
    ],
    "name:kab_x_preferred":[
        "Ayt Baha"
    ],
    "name:nld_x_preferred":[
        "Ait Baha"
    ],
    "name:por_x_preferred":[
        "Ait Baha"
    ],
    "name:shi_x_preferred":[
        "Ayt Baha"
    ],
    "name:swe_x_preferred":[
        "A\u00eft Baha"
    ],
    "name:zho_x_preferred":[
        "\u963f\u4f0a\u7279\u5df4\u54c8"
    ],
    "qs:name":"Ait Baha",
    "qs:photos_9r":0,
    "qs:photos_sr":0,
    "qs:pop_sr":"4",
    "wd:wordcount":45,
    "wof:name":"Ait Baha",
    "wof:placetype":"localadmin",
    "wof:population":4767
},
  "geometry": {"coordinates":[-9.15775,30.07121],"type":"Point"}
}