{
  "type": "Feature",
  "properties": {
    "gn:admin1_code":"02",
    "gn:asciiname":"El Rhlel",
    "gn:country_code":"MA",
    "gn:dem":476,
    "gn:feature_class":"P",
    "gn:feature_code":"PPL",
    "gn:name":"El Rhlel",
    "gn:population":0,
    "gn:timezone":"Africa/Casablanca",
    "iso:country":"MA",
    "name:und_x_variant":[
        "Al Ghlel",
        "El Rhlel"
    ],
    "wof:name":"El Rhlel",
    "wof:placetype":"locality"
},
  "geometry": {"coordinates":[-2.63756,34.55174],"type":"Point"}
}