{
  "type": "Feature",
  "properties": {
    "gn:admin1_code":"6.0",
    "gn:asciiname":"Essafa",
    "gn:country_code":"MA",
    "gn:dem":522,
    "gn:feature_class":"P",
    "gn:feature_code":"PPL",
    "gn:name":"Essafa",
    "gn:population":0,
    "gn:timezone":"Africa/Casablanca",
    "iso:country":"MA",
    "wof:name":"Essafa",
    "wof:placetype":"locality"
},
  "geometry": {"coordinates":[-6.84542,33.45164],"type":"Point"}
}