{
  "type": "Feature",
  "properties": {
    "gn:admin1_code":"2.0",
    "gn:asciiname":"Douar Oulad Ezzoufri Mohamed",
    "gn:country_code":"MA",
    "gn:dem":59,
    "gn:feature_class":"P",
    "gn:feature_code":"PPL",
    "gn:name":"Douar Oulad Ezzoufri Mohamed",
    "gn:population":0,
    "gn:timezone":"Africa/Casablanca",
    "iso:country":"MA",
    "wof:name":"Douar Oulad Ezzoufri Mohamed",
    "wof:placetype":"locality"
},
  "geometry": {"coordinates":[-2.82923,35.07259000000001],"type":"Point"}
}