{
  "type": "Feature",
  "properties": {
    "gn:admin1_code":"01",
    "gn:admin2_code":"511.0",
    "gn:admin3_code":"1651103072.0",
    "gn:asciiname":"Dar Chaoui",
    "gn:country_code":"MA",
    "gn:dem":112,
    "gn:feature_class":"P",
    "gn:feature_code":"PPLA3",
    "gn:name":"Dar Chaoui",
    "gn:population":0,
    "gn:timezone":"Africa/Casablanca",
    "iso:country":"MA",
    "name:und_x_variant":[
        "Xauia",
        "Dar ech Chaui",
        "Dar Chaui",
        "Dar Xaui",
        "Der Xaui",
        "Dar Chaoui"
    ],
    "wof:name":"Dar Chaoui",
    "wof:placetype":"locality"
},
  "geometry": {"coordinates":[-5.71742,35.5377],"type":"Point"}
}