{
  "type": "Feature",
  "properties": {
    "gn:admin1_code":"7.0",
    "gn:asciiname":"Douar Lakhouadra El Koudia",
    "gn:country_code":"MA",
    "gn:dem":330,
    "gn:feature_class":"P",
    "gn:feature_code":"PPL",
    "gn:name":"Douar Lakhouadra El Koudia",
    "gn:population":0,
    "gn:timezone":"Africa/Casablanca",
    "iso:country":"MA",
    "wof:name":"Douar Lakhouadra El Koudia",
    "wof:placetype":"locality"
},
  "geometry": {"coordinates":[-8.594,31.89409],"type":"Point"}
}