{
  "type": "Feature",
  "properties": {
    "gn:admin1_code":"09",
    "gn:asciiname":"Agoumadane",
    "gn:country_code":"MA",
    "gn:dem":808,
    "gn:feature_class":"P",
    "gn:feature_code":"PPL",
    "gn:name":"Agoumadane",
    "gn:population":0,
    "gn:timezone":"Africa/Casablanca",
    "iso:country":"MA",
    "wof:name":"Agoumadane",
    "wof:placetype":"locality"
},
  "geometry": {"coordinates":[-8.88551,30.67764],"type":"Point"}
}