{
  "type": "Feature",
  "properties": {
    "gn:admin1_code":"4.0",
    "gn:asciiname":"Lehjafna Bougdour",
    "gn:country_code":"MA",
    "gn:dem":125,
    "gn:feature_class":"P",
    "gn:feature_code":"PPL",
    "gn:name":"Lehjafna Bougdour",
    "gn:population":0,
    "gn:timezone":"Africa/Casablanca",
    "iso:country":"MA",
    "wof:name":"Lehjafna Bougdour",
    "wof:placetype":"locality"
},
  "geometry": {"coordinates":[-5.52872,34.56582],"type":"Point"}
}