{
  "type": "Feature",
  "properties": {
    "gn:admin1_code":"09",
    "gn:asciiname":"Imerguene",
    "gn:country_code":"MA",
    "gn:dem":1009,
    "gn:feature_class":"P",
    "gn:feature_code":"PPL",
    "gn:name":"Imerguene",
    "gn:population":0,
    "gn:timezone":"Africa/Casablanca",
    "iso:country":"MA",
    "name:und_x_variant":[
        "Imeadjarne",
        "Imerguene"
    ],
    "wof:name":"Imerguene",
    "wof:placetype":"locality"
},
  "geometry": {"coordinates":[-8.27398,30.82704],"type":"Point"}
}