{
  "type": "Feature",
  "properties": {
    "gn:admin1_code":"9.0",
    "gn:asciiname":"Tagtwalt",
    "gn:country_code":"MA",
    "gn:dem":1235,
    "gn:feature_class":"P",
    "gn:feature_code":"PPL",
    "gn:name":"Tagtwalt",
    "gn:population":0,
    "gn:timezone":"Africa/Casablanca",
    "iso:country":"MA",
    "wof:name":"Tagtwalt",
    "wof:placetype":"locality"
},
  "geometry": {"coordinates":[-9.31067,29.51647],"type":"Point"}
}