{
  "type": "Feature",
  "properties": {
    "gn:admin1_code":"03",
    "gn:asciiname":"Oulad Draoui",
    "gn:country_code":"MA",
    "gn:dem":694,
    "gn:feature_class":"P",
    "gn:feature_code":"PPL",
    "gn:name":"Oulad Draoui",
    "gn:population":0,
    "gn:timezone":"Africa/Casablanca",
    "iso:country":"MA",
    "wof:name":"Oulad Draoui",
    "wof:placetype":"locality"
},
  "geometry": {"coordinates":[-3.63863,33.54293],"type":"Point"}
}