{
  "type": "Feature",
  "properties": {
    "gn:admin1_code":"07",
    "gn:asciiname":"Douar Oulad Cheikh",
    "gn:country_code":"MA",
    "gn:dem":467,
    "gn:feature_class":"P",
    "gn:feature_code":"PPL",
    "gn:name":"Douar Oulad Cheikh",
    "gn:population":0,
    "gn:timezone":"Africa/Casablanca",
    "iso:country":"MA",
    "name:und_x_variant":[
        "Oulad-Che\u00efkh"
    ],
    "wof:name":"Douar Oulad Cheikh",
    "wof:placetype":"locality"
},
  "geometry": {"coordinates":[-8.07746,31.97777],"type":"Point"}
}