{
  "type": "Feature",
  "properties": {
    "gn:admin1_code":"01",
    "gn:asciiname":"Sayyoufa",
    "gn:country_code":"MA",
    "gn:dem":272,
    "gn:feature_class":"P",
    "gn:feature_code":"PPL",
    "gn:name":"Sayyoufa",
    "gn:population":0,
    "gn:timezone":"Africa/Casablanca",
    "iso:country":"MA",
    "name:und_x_variant":[
        "Sayoufa",
        "Sejoufa",
        "Sayyoufa"
    ],
    "wof:name":"Sayyoufa",
    "wof:placetype":"locality"
},
  "geometry": {"coordinates":[-5.71064,35.65377],"type":"Point"}
}