{
  "type": "Feature",
  "properties": {
    "gn:admin1_code":"01",
    "gn:asciiname":"Amtar",
    "gn:country_code":"MA",
    "gn:dem":17,
    "gn:feature_class":"P",
    "gn:feature_code":"PPL",
    "gn:name":"Amtar",
    "gn:population":0,
    "gn:timezone":"Africa/Casablanca",
    "iso:country":"MA",
    "name:ara_x_preferred":[
        "\u0623\u0645\u062a\u0627\u0631"
    ],
    "name:azb_x_preferred":[
        "\u0627\u0645\u062a\u0627\u0631"
    ],
    "name:cat_x_preferred":[
        "Amtar"
    ],
    "name:ceb_x_preferred":[
        "Amtar"
    ],
    "name:fas_x_preferred":[
        "\u0627\u0645\u062a\u0627\u0631"
    ],
    "name:ita_x_preferred":[
        "Amtar"
    ],
    "name:swe_x_preferred":[
        "Amtar"
    ],
    "name:und_x_variant":[
        "Amter",
        "M\u2019Ter",
        "Dar Mter"
    ],
    "name:urd_x_preferred":[
        "\u0627\u0645\u062a\u0627\u0631"
    ],
    "wof:name":"Amtar",
    "wof:placetype":"locality"
},
  "geometry": {"coordinates":[-4.79248,35.2425],"type":"Point"}
}