{
  "type": "Feature",
  "properties": {
    "gn:admin1_code":"7.0",
    "gn:asciiname":"Laabarda",
    "gn:country_code":"MA",
    "gn:dem":411,
    "gn:feature_class":"P",
    "gn:feature_code":"PPL",
    "gn:name":"Laabarda",
    "gn:population":0,
    "gn:timezone":"Africa/Casablanca",
    "iso:country":"MA",
    "wof:name":"Laabarda",
    "wof:placetype":"locality"
},
  "geometry": {"coordinates":[-7.75977,32.11702],"type":"Point"}
}