{
  "type": "Feature",
  "properties": {
    "gn:admin1_code":"7.0",
    "gn:asciiname":"Hit Legrini",
    "gn:country_code":"MA",
    "gn:dem":264,
    "gn:feature_class":"P",
    "gn:feature_code":"PPL",
    "gn:name":"Hit Legrini",
    "gn:population":0,
    "gn:timezone":"Africa/Casablanca",
    "iso:country":"MA",
    "wof:name":"Hit Legrini",
    "wof:placetype":"locality"
},
  "geometry": {"coordinates":[-8.48334,32.31217],"type":"Point"}
}