{
  "type": "Feature",
  "properties": {
    "gn:admin1_code":"09",
    "gn:asciiname":"Tidili",
    "gn:country_code":"MA",
    "gn:dem":1188,
    "gn:feature_class":"P",
    "gn:feature_code":"PPL",
    "gn:name":"Tidili",
    "gn:population":0,
    "gn:timezone":"Africa/Casablanca",
    "iso:country":"MA",
    "name:und_x_variant":[
        "Tiditi",
        "Tidili"
    ],
    "wof:name":"Tidili",
    "wof:placetype":"locality"
},
  "geometry": {"coordinates":[-8.57373,29.68914],"type":"Point"}
}