{
  "type": "Feature",
  "properties": {
    "gn:admin1_code":"9.0",
    "gn:asciiname":"Ait Daoud",
    "gn:country_code":"MA",
    "gn:dem":509,
    "gn:feature_class":"P",
    "gn:feature_code":"PPL",
    "gn:name":"A\u00eft Daoud",
    "gn:population":0,
    "gn:timezone":"Africa/Casablanca",
    "iso:country":"MA",
    "name:ara_x_preferred":[
        "\u0622\u064a\u062a \u062f\u0627\u0648\u0648\u062f"
    ],
    "name:azb_x_preferred":[
        "\u0622\u06cc\u062a \u062f\u0627\u0648\u0648\u062f"
    ],
    "name:cat_x_preferred":[
        "Ait Daoud"
    ],
    "name:ceb_x_preferred":[
        "Ait Daoud"
    ],
    "name:fas_x_preferred":[
        "\u0622\u06cc\u062a \u062f\u0627\u0648\u0648\u062f"
    ],
    "name:fra_x_preferred":[
        "A\u00eft Daoud"
    ],
    "name:swe_x_preferred":[
        "Ait Daoud"
    ],
    "wof:name":"Ait Daoud",
    "wof:placetype":"locality"
},
  "geometry": {"coordinates":[-9.11075,30.18187],"type":"Point"}
}