{
  "type": "Feature",
  "properties": {
    "gn:admin1_code":"5.0",
    "gn:asciiname":"Oulad Abbou",
    "gn:country_code":"MA",
    "gn:dem":819,
    "gn:feature_class":"P",
    "gn:feature_code":"PPL",
    "gn:name":"Oulad Abbou",
    "gn:population":0,
    "gn:timezone":"Africa/Casablanca",
    "iso:country":"MA",
    "name:ara_x_preferred":[
        "\u0623\u0648\u0644\u0627\u062f \u0639\u0628\u0648"
    ],
    "name:azb_x_preferred":[
        "\u0627\u0648\u0644\u0627\u062f \u0639\u0628\u0648"
    ],
    "name:cat_x_preferred":[
        "Oulad Abbou"
    ],
    "name:fas_x_preferred":[
        "\u0627\u0648\u0644\u0627\u062f \u0639\u0628\u0648"
    ],
    "name:fra_x_preferred":[
        "Oulad Abbou"
    ],
    "name:ita_x_preferred":[
        "Oulad Abbou"
    ],
    "wof:name":"Oulad Abbou",
    "wof:placetype":"locality"
},
  "geometry": {"coordinates":[-6.48313,32.86828],"type":"Point"}
}