{
  "type": "Feature",
  "properties": {
    "gn:admin1_code":"1.0",
    "gn:asciiname":"Douar Ihajjamene",
    "gn:country_code":"MA",
    "gn:dem":628,
    "gn:feature_class":"P",
    "gn:feature_code":"PPL",
    "gn:name":"Douar Ihajjamene",
    "gn:population":0,
    "gn:timezone":"Africa/Casablanca",
    "iso:country":"MA",
    "wof:name":"Douar Ihajjamene",
    "wof:placetype":"locality"
},
  "geometry": {"coordinates":[-4.9216,35.20457000000001],"type":"Point"}
}