{
  "type": "Feature",
  "properties": {
    "gn:admin1_code":"01",
    "gn:asciiname":"Douar Hammer",
    "gn:country_code":"MA",
    "gn:dem":345,
    "gn:feature_class":"P",
    "gn:feature_code":"PPL",
    "gn:name":"Douar Hammer",
    "gn:population":0,
    "gn:timezone":"Africa/Casablanca",
    "iso:country":"MA",
    "name:und_x_variant":[
        "Hammar",
        "Ahammar",
        "Douar Ahammar",
        "Douar Hammer"
    ],
    "wof:name":"Douar Hammer",
    "wof:placetype":"locality"
},
  "geometry": {"coordinates":[-5.52756,34.8384],"type":"Point"}
}