{
  "type": "Feature",
  "properties": {
    "gn:country":"MA",
    "gn:fcode":"ADM3",
    "gn:pop":1820,
    "iso:country":"MA",
    "name:ara_x_preferred":[
        "\u0627\u062c\u062f\u064a\u0631\u064a\u0629"
    ],
    "name:fra_x_preferred":[
        "Sidi Ahmed Laaroussi"
    ],
    "name:fra_x_variant":[
        "Sidi Ahmed Laaroussi (CR)",
        "Sidi Ahmed Laaroussi (Commune Rurale)"
    ],
    "qs:name":"Sidi Ahmed Laaroussi",
    "qs:photos_9r":0,
    "qs:photos_sr":0,
    "qs:pop_sr":"3",
    "wof:name":"Sidi Ahmed Laaroussi",
    "wof:placetype":"localadmin",
    "wof:population":1820
},
  "geometry": {"coordinates":[-11.99975,27.04662],"type":"Point"}
}