{
  "type": "Feature",
  "properties": {
    "gn:admin1_code":"01",
    "gn:asciiname":"Egsanene",
    "gn:country_code":"MA",
    "gn:dem":1173,
    "gn:feature_class":"P",
    "gn:feature_code":"PPL",
    "gn:name":"Egsanene",
    "gn:population":0,
    "gn:timezone":"Africa/Casablanca",
    "iso:country":"MA",
    "name:und_x_variant":[
        "Igsanen",
        "Egaanene",
        "Egsanen",
        "Egsanene"
    ],
    "wof:name":"Egsanene",
    "wof:placetype":"locality"
},
  "geometry": {"coordinates":[-4.41,34.95],"type":"Point"}
}