{
  "type": "Feature",
  "properties": {
    "gn:admin1_code":"3.0",
    "gn:asciiname":"Douar Ait Kacem Ou Haddou",
    "gn:country_code":"MA",
    "gn:dem":1164,
    "gn:feature_class":"P",
    "gn:feature_code":"PPL",
    "gn:name":"Douar Ait Kacem Ou Haddou",
    "gn:population":0,
    "gn:timezone":"Africa/Casablanca",
    "iso:country":"MA",
    "wof:name":"Douar Ait Kacem Ou Haddou",
    "wof:placetype":"locality"
},
  "geometry": {"coordinates":[-5.53395,33.50024000000001],"type":"Point"}
}