{
  "type": "Feature",
  "properties": {
    "gn:admin1_code":"05",
    "gn:asciiname":"Ait Mama",
    "gn:country_code":"MA",
    "gn:dem":2166,
    "gn:feature_class":"P",
    "gn:feature_code":"PPL",
    "gn:name":"A\u00eft Mama",
    "gn:population":0,
    "gn:timezone":"Africa/Casablanca",
    "iso:country":"MA",
    "name:und_x_variant":[
        "A\u00eft Mama",
        "A\u00eft M\u2018ammar"
    ],
    "wof:name":"Ait Mama",
    "wof:placetype":"locality"
},
  "geometry": {"coordinates":[-6.47931,31.76311],"type":"Point"}
}