{
  "type": "Feature",
  "properties": {
    "gn:admin1_code":"07",
    "gn:asciiname":"Taguanza",
    "gn:country_code":"MA",
    "gn:dem":1115,
    "gn:feature_class":"P",
    "gn:feature_code":"PPL",
    "gn:name":"Taguanza",
    "gn:population":0,
    "gn:timezone":"Africa/Casablanca",
    "iso:country":"MA",
    "name:und_x_variant":[
        "Taguenza"
    ],
    "wof:name":"Taguanza",
    "wof:placetype":"locality"
},
  "geometry": {"coordinates":[-9.06041,31.20478],"type":"Point"}
}