{
  "type": "Feature",
  "properties": {
    "gn:admin1_code":"6.0",
    "gn:asciiname":"Oulad Sidi Bourahhou",
    "gn:country_code":"MA",
    "gn:dem":165,
    "gn:feature_class":"P",
    "gn:feature_code":"PPL",
    "gn:name":"Oulad Sidi Bourahhou",
    "gn:population":0,
    "gn:timezone":"Africa/Casablanca",
    "iso:country":"MA",
    "wof:name":"Oulad Sidi Bourahhou",
    "wof:placetype":"locality"
},
  "geometry": {"coordinates":[-8.16718,32.83392],"type":"Point"}
}