{
  "type": "Feature",
  "properties": {
    "gn:admin1_code":"1.0",
    "gn:asciiname":"Houmat Lamrabtiyine",
    "gn:country_code":"MA",
    "gn:dem":664,
    "gn:feature_class":"P",
    "gn:feature_code":"PPL",
    "gn:name":"Houmat Lamrabtiyine",
    "gn:population":0,
    "gn:timezone":"Africa/Casablanca",
    "iso:country":"MA",
    "wof:name":"Houmat Lamrabtiyine",
    "wof:placetype":"locality"
},
  "geometry": {"coordinates":[-5.21356,35.08701],"type":"Point"}
}