{
  "type": "Feature",
  "properties": {
    "gn:admin1_code":"01",
    "gn:asciiname":"Aghnouri Lfouqiyyine",
    "gn:country_code":"MA",
    "gn:dem":102,
    "gn:feature_class":"P",
    "gn:feature_code":"PPL",
    "gn:name":"Aghnouri Lfouqiyyine",
    "gn:population":0,
    "gn:timezone":"Africa/Casablanca",
    "iso:country":"MA",
    "name:und_x_variant":[
        "El Foukiyine"
    ],
    "wof:name":"Aghnouri Lfouqiyyine",
    "wof:placetype":"locality"
},
  "geometry": {"coordinates":[-5.12842,35.45179],"type":"Point"}
}