{
  "type": "Feature",
  "properties": {
    "gn:country":"MA",
    "gn:fcode":"ADM3",
    "gn:population":13635,
    "iso:country":"MA",
    "name:ara_x_preferred":[
        "\u0623\u062d\u062f \u0628\u0648\u0645\u0648\u0633\u0649"
    ],
    "name:ara_x_variant":[
        "\u0623\u0648\u0644\u0627\u062f \u0628\u0648\u0631\u062d\u0645\u0648\u0646"
    ],
    "name:ary_x_preferred":[
        "\u0648\u0644\u0627\u062f \u0628\u0648\u0631\u062d\u0645\u0648\u0646"
    ],
    "name:azb_x_preferred":[
        "\u0627\u0648\u0644\u0627\u062f \u0628\u0648\u0631\u062d\u0645\u0648\u0646"
    ],
    "name:cat_x_preferred":[
        "Oulad Bourahmoune"
    ],
    "name:ceb_x_preferred":[
        "Oulad Bourahmoune"
    ],
    "name:eng_x_preferred":[
        "Oulad Bourahmoune"
    ],
    "name:fas_x_preferred":[
        "\u0627\u0648\u0644\u0627\u062f \u0628\u0648\u0631\u062d\u0645\u0648\u0646"
    ],
    "name:fra_x_preferred":[
        "Oulad Bourahmoune"
    ],
    "name:fra_x_variant":[
        "Oulad Bourahmoune (CR)",
        "Oulad Bourahmoune (Commune Rurale)"
    ],
    "name:ita_x_preferred":[
        "Oulad Bourahmoune"
    ],
    "name:swe_x_preferred":[
        "Oulad Bourahmoune"
    ],
    "qs:name":"Oulad Bourahmoune",
    "qs:photos_9r":0,
    "qs:photos_sr":0,
    "qs:pop_sr":"6",
    "wd:wordcount":60,
    "wof:name":"Oulad Bourahmoune",
    "wof:placetype":"localadmin",
    "wof:population":13635
},
  "geometry": {"coordinates":[-6.68837,32.29857],"type":"Point"}
}