{
  "type": "Feature",
  "properties": {
    "gn:admin1_code":"07",
    "gn:asciiname":"Tiguimi Jdid",
    "gn:country_code":"MA",
    "gn:dem":710,
    "gn:feature_class":"P",
    "gn:feature_code":"PPL",
    "gn:name":"Tiguimi Jdid",
    "gn:population":0,
    "gn:timezone":"Africa/Casablanca",
    "iso:country":"MA",
    "name:und_x_variant":[
        "Tigammi Jdid",
        "Tiguemmi Idid",
        "Tigmi Jdid",
        "Tiguimi Jdid"
    ],
    "wof:name":"Tiguimi Jdid",
    "wof:placetype":"locality"
},
  "geometry": {"coordinates":[-8.77606,31.22661],"type":"Point"}
}