{
  "type": "Feature",
  "properties": {
    "gn:admin1_code":"01",
    "gn:asciiname":"Zitanes",
    "gn:country_code":"MA",
    "gn:dem":436,
    "gn:feature_class":"P",
    "gn:feature_code":"PPL",
    "gn:name":"Zitanes",
    "gn:population":0,
    "gn:timezone":"Africa/Casablanca",
    "iso:country":"MA",
    "name:und_x_variant":[
        "Zitanse",
        "Zitanes"
    ],
    "wof:name":"Zitanes",
    "wof:placetype":"locality"
},
  "geometry": {"coordinates":[-5.40694,35.06895],"type":"Point"}
}