{
  "type": "Feature",
  "properties": {
    "gn:admin1_code":"05",
    "gn:asciiname":"Ali Ou Zaid",
    "gn:country_code":"MA",
    "gn:dem":1231,
    "gn:elevation":"0.0",
    "gn:feature_class":"P",
    "gn:feature_code":"PPL",
    "gn:name":"Ali Ou Za\u00efd",
    "gn:population":0,
    "gn:timezone":"Africa/Casablanca",
    "iso:country":"MA",
    "wof:name":"Ali Ou Zaid",
    "wof:placetype":"locality"
},
  "geometry": {"coordinates":[-6.72188,31.95276],"type":"Point"}
}