{
  "type": "Feature",
  "properties": {
    "gn:admin1_code":"7.0",
    "gn:asciiname":"Hamid bel Medjoul",
    "gn:country_code":"MA",
    "gn:dem":509,
    "gn:feature_class":"P",
    "gn:feature_code":"PPL",
    "gn:name":"Hamid bel Medjoul",
    "gn:population":0,
    "gn:timezone":"Africa/Casablanca",
    "iso:country":"MA",
    "wof:name":"Hamid bel Medjoul",
    "wof:placetype":"locality"
},
  "geometry": {"coordinates":[-8.6175,31.42686],"type":"Point"}
}