{
  "type": "Feature",
  "properties": {
    "gn:admin1_code":"3.0",
    "gn:asciiname":"Dada El Haj Lahsen",
    "gn:country_code":"MA",
    "gn:dem":1610,
    "gn:feature_class":"P",
    "gn:feature_code":"PPL",
    "gn:name":"Dada El Haj Lahsen",
    "gn:population":0,
    "gn:timezone":"Africa/Casablanca",
    "iso:country":"MA",
    "wof:name":"Dada El Haj Lahsen",
    "wof:placetype":"locality"
},
  "geometry": {"coordinates":[-4.97782,33.62207],"type":"Point"}
}