{
  "type": "Feature",
  "properties": {
    "gn:admin1_code":"07",
    "gn:asciiname":"Laararja",
    "gn:country_code":"MA",
    "gn:dem":90,
    "gn:feature_class":"P",
    "gn:feature_code":"PPL",
    "gn:name":"Laararja",
    "gn:population":0,
    "gn:timezone":"Africa/Casablanca",
    "iso:country":"MA",
    "name:und_x_variant":[
        "Lararja",
        "Douar el Anabja",
        "El Anabja",
        "Laararja"
    ],
    "wof:name":"Laararja",
    "wof:placetype":"locality"
},
  "geometry": {"coordinates":[-9.14246,32.5708],"type":"Point"}
}