{
  "type": "Feature",
  "properties": {
    "gn:admin1_code":"3.0",
    "gn:asciiname":"Douar Ait Ou Berkane",
    "gn:country_code":"MA",
    "gn:dem":584,
    "gn:feature_class":"P",
    "gn:feature_code":"PPL",
    "gn:name":"Douar Ait Ou Berkane",
    "gn:population":0,
    "gn:timezone":"Africa/Casablanca",
    "iso:country":"MA",
    "wof:name":"Douar Ait Ou Berkane",
    "wof:placetype":"locality"
},
  "geometry": {"coordinates":[-4.70031,33.98223],"type":"Point"}
}