{
  "type": "Feature",
  "properties": {
    "gn:admin1_code":"7.0",
    "gn:asciiname":"Ait Sidi Bihi",
    "gn:country_code":"MA",
    "gn:dem":197,
    "gn:feature_class":"P",
    "gn:feature_code":"PPL",
    "gn:name":"Ait Sidi Bihi",
    "gn:population":0,
    "gn:timezone":"Africa/Casablanca",
    "iso:country":"MA",
    "wof:name":"Ait Sidi Bihi",
    "wof:placetype":"locality"
},
  "geometry": {"coordinates":[-9.53609,31.59467],"type":"Point"}
}