{
  "type": "Feature",
  "properties": {
    "gn:admin1_code":"03",
    "gn:asciiname":"L'Oulja",
    "gn:country_code":"MA",
    "gn:dem":184,
    "gn:feature_class":"P",
    "gn:feature_code":"PPL",
    "gn:name":"L\u2019Oulja",
    "gn:population":0,
    "gn:timezone":"Africa/Casablanca",
    "iso:country":"MA",
    "wof:name":"L'Oulja",
    "wof:placetype":"locality"
},
  "geometry": {"coordinates":[-4.94172,34.2899],"type":"Point"}
}