{
  "type": "Feature",
  "properties": {
    "gn:country":"MA",
    "gn:fcode":"ADM3",
    "gn:population":234690,
    "iso:country":"MA",
    "name:ara_x_preferred":[
        "\u0627\u0644\u0639\u064a\u0627\u064a\u062f\u0629  (\u0627\u0644\u0645\u0642\u0627\u0637\u0639\u0629)"
    ],
    "name:fra_x_preferred":[
        "Tabriquet"
    ],
    "name:fra_x_variant":[
        "Tabriquet (AR)",
        "Tabriquet (Arrondissement)"
    ],
    "qs_pg:aaroncc":"MA",
    "qs_pg:gn_country":"MA",
    "qs_pg:gn_fcode":"ADM3",
    "qs_pg:gn_pop":234690,
    "qs_pg:name":"Tabriquet",
    "qs_pg:photos_9r":0,
    "qs_pg:photos_sr":0,
    "qs_pg:pop_sr":10,
    "qs_pg:qs_pg_placetype":"localadmin",
    "wof:name":"Tabriquet",
    "wof:placetype":"localadmin",
    "wof:population":234690
},
  "geometry": {"coordinates":[-6.79459,34.05795],"type":"Point"}
}