{
  "type": "Feature",
  "properties": {
    "gn:admin1_code":"7.0",
    "gn:asciiname":"Douar Arichat",
    "gn:country_code":"MA",
    "gn:dem":165,
    "gn:feature_class":"P",
    "gn:feature_code":"PPL",
    "gn:name":"Douar Arichat",
    "gn:population":0,
    "gn:timezone":"Africa/Casablanca",
    "iso:country":"MA",
    "wof:name":"Douar Arichat",
    "wof:placetype":"locality"
},
  "geometry": {"coordinates":[-9.2218,32.1009],"type":"Point"}
}