{
  "type": "Feature",
  "properties": {
    "gn:admin1_code":"01",
    "gn:asciiname":"Douar Oulad Lahsene",
    "gn:country_code":"MA",
    "gn:dem":309,
    "gn:feature_class":"P",
    "gn:feature_code":"PPL",
    "gn:name":"Douar Oulad Lahsene",
    "gn:population":0,
    "gn:timezone":"Africa/Casablanca",
    "iso:country":"MA",
    "name:und_x_variant":[
        "Oulad Lahsene"
    ],
    "wof:name":"Douar Oulad Lahsene",
    "wof:placetype":"locality"
},
  "geometry": {"coordinates":[-5.23666,34.71612],"type":"Point"}
}