{
  "type": "Feature",
  "properties": {
    "gn:admin1_code":"04",
    "gn:asciiname":"Douar Oulad Khrais",
    "gn:country_code":"MA",
    "gn:dem":35,
    "gn:feature_class":"P",
    "gn:feature_code":"PPL",
    "gn:name":"Douar Oulad Khra\u00efs",
    "gn:population":0,
    "gn:timezone":"Africa/Casablanca",
    "iso:country":"MA",
    "name:und_x_variant":[
        "Douar Oulad Khra\u00efs",
        "Oulad Khra\u00efs"
    ],
    "wof:name":"Douar Oulad Khrais",
    "wof:placetype":"locality"
},
  "geometry": {"coordinates":[-5.64189,34.4462],"type":"Point"}
}