{
  "type": "Feature",
  "properties": {
    "gn:admin1_code":"7.0",
    "gn:asciiname":"Douar El Haj El Bachir",
    "gn:country_code":"MA",
    "gn:dem":388,
    "gn:feature_class":"P",
    "gn:feature_code":"PPL",
    "gn:name":"Douar El Haj El Bachir",
    "gn:population":0,
    "gn:timezone":"Africa/Casablanca",
    "iso:country":"MA",
    "wof:name":"Douar El Haj El Bachir",
    "wof:placetype":"locality"
},
  "geometry": {"coordinates":[-8.86214,32.09117],"type":"Point"}
}