{
  "type": "Feature",
  "properties": {
    "gn:admin1_code":"9.0",
    "gn:asciiname":"Agardane",
    "gn:country_code":"MA",
    "gn:dem":1288,
    "gn:feature_class":"P",
    "gn:feature_code":"PPL",
    "gn:name":"Agardane",
    "gn:population":0,
    "gn:timezone":"Africa/Casablanca",
    "iso:country":"MA",
    "wof:name":"Agardane",
    "wof:placetype":"locality"
},
  "geometry": {"coordinates":[-8.1565,30.85606],"type":"Point"}
}