{
  "type": "Feature",
  "properties": {
    "gn:admin1_code":"9.0",
    "gn:asciiname":"Imraouhin",
    "gn:country_code":"MA",
    "gn:dem":163,
    "gn:feature_class":"P",
    "gn:feature_code":"PPL",
    "gn:name":"Imraouhin",
    "gn:population":0,
    "gn:timezone":"Africa/Casablanca",
    "iso:country":"MA",
    "wof:name":"Imraouhin",
    "wof:placetype":"locality"
},
  "geometry": {"coordinates":[-9.39341,29.97325],"type":"Point"}
}