{
  "type": "Feature",
  "properties": {
    "gn:admin1_code":"07",
    "gn:asciiname":"Tiwyaline",
    "gn:country_code":"MA",
    "gn:dem":2004,
    "gn:feature_class":"P",
    "gn:feature_code":"PPL",
    "gn:name":"Tiwyaline",
    "gn:population":0,
    "gn:timezone":"Africa/Casablanca",
    "iso:country":"MA",
    "name:und_x_variant":[
        "Tiouiyaline",
        "Tiouyaline",
        "Tiouialine",
        "Tiwyaline"
    ],
    "wof:name":"Tiwyaline",
    "wof:placetype":"locality"
},
  "geometry": {"coordinates":[-8.49497,30.90268],"type":"Point"}
}