{
  "type": "Feature",
  "properties": {
    "gn:admin1_code":"7.0",
    "gn:asciiname":"Sidi El Makhfi",
    "gn:country_code":"MA",
    "gn:dem":395,
    "gn:feature_class":"P",
    "gn:feature_code":"PPL",
    "gn:name":"Sidi El Makhfi",
    "gn:population":0,
    "gn:timezone":"Africa/Casablanca",
    "iso:country":"MA",
    "wof:name":"Sidi El Makhfi",
    "wof:placetype":"locality"
},
  "geometry": {"coordinates":[-9.46502,31.60981],"type":"Point"}
}