{
  "type": "Feature",
  "properties": {
    "gn:admin1_code":"1.0",
    "gn:asciiname":"Douar Lahouarta",
    "gn:country_code":"MA",
    "gn:dem":76,
    "gn:feature_class":"P",
    "gn:feature_code":"PPL",
    "gn:name":"Douar Lahouarta",
    "gn:population":0,
    "gn:timezone":"Africa/Casablanca",
    "iso:country":"MA",
    "wof:name":"Douar Lahouarta",
    "wof:placetype":"locality"
},
  "geometry": {"coordinates":[-5.84708,35.62394000000001],"type":"Point"}
}