{
  "type": "Feature",
  "properties": {
    "gn:admin1_code":"01",
    "gn:asciiname":"Amazzar",
    "gn:country_code":"MA",
    "gn:dem":976,
    "gn:feature_class":"P",
    "gn:feature_code":"PPL",
    "gn:name":"Amazzar",
    "gn:population":0,
    "gn:timezone":"Africa/Casablanca",
    "iso:country":"MA",
    "name:und_x_variant":[
        "Amaz\u00e1",
        "Amesar",
        "Amezar",
        "Amazzar"
    ],
    "wof:name":"Amazzar",
    "wof:placetype":"locality"
},
  "geometry": {"coordinates":[-5.1689,35.18455],"type":"Point"}
}