{
  "type": "Feature",
  "properties": {
    "gn:admin1_code":"05",
    "gn:asciiname":"Agard-n-Isghane",
    "gn:country_code":"MA",
    "gn:dem":1695,
    "gn:feature_class":"P",
    "gn:feature_code":"PPL",
    "gn:name":"Agard-n-Isghane",
    "gn:population":0,
    "gn:timezone":"Africa/Casablanca",
    "iso:country":"MA",
    "name:und_x_variant":[
        "Aguerd n\u2019 Irhissine",
        "Aguerd n\u2019 Irhissane",
        "Agard-n-Isghane"
    ],
    "wof:name":"Agard-n-Isghane",
    "wof:placetype":"locality"
},
  "geometry": {"coordinates":[-6.21081,32.08028],"type":"Point"}
}