{
  "type": "Feature",
  "properties": {
    "gn:admin1_code":"9.0",
    "gn:asciiname":"Rouif",
    "gn:country_code":"MA",
    "gn:dem":159,
    "gn:feature_class":"P",
    "gn:feature_code":"PPL",
    "gn:name":"Rouif",
    "gn:population":0,
    "gn:timezone":"Africa/Casablanca",
    "iso:country":"MA",
    "wof:name":"Rouif",
    "wof:placetype":"locality"
},
  "geometry": {"coordinates":[-9.08265,30.43305],"type":"Point"}
}