{
  "type": "Feature",
  "properties": {
    "gn:admin1_code":"7.0",
    "gn:asciiname":"Douar Ait Ben Said",
    "gn:country_code":"MA",
    "gn:dem":156,
    "gn:feature_class":"P",
    "gn:feature_code":"PPL",
    "gn:name":"Douar Ait Ben Said",
    "gn:population":0,
    "gn:timezone":"Africa/Casablanca",
    "iso:country":"MA",
    "wof:name":"Douar Ait Ben Said",
    "wof:placetype":"locality"
},
  "geometry": {"coordinates":[-9.24352,31.81662],"type":"Point"}
}