{
  "type": "Feature",
  "properties": {
    "gn:admin1_code":"8.0",
    "gn:asciiname":"Bou Ihangar",
    "gn:country_code":"MA",
    "gn:dem":2326,
    "gn:feature_class":"P",
    "gn:feature_code":"PPL",
    "gn:name":"Bou Ihangar",
    "gn:population":0,
    "gn:timezone":"Africa/Casablanca",
    "iso:country":"MA",
    "wof:name":"Bou Ihangar",
    "wof:placetype":"locality"
},
  "geometry": {"coordinates":[-6.94972,31.32178],"type":"Point"}
}