{
  "type": "Feature",
  "properties": {
    "gn:admin1_code":"07",
    "gn:asciiname":"Douar Oulad Said",
    "gn:country_code":"MA",
    "gn:dem":498,
    "gn:feature_class":"P",
    "gn:feature_code":"PPL",
    "gn:name":"Douar Oulad Said",
    "gn:population":0,
    "gn:timezone":"Africa/Casablanca",
    "iso:country":"MA",
    "name:und_x_variant":[
        "Oulad Sa\u00efd"
    ],
    "wof:name":"Douar Oulad Said",
    "wof:placetype":"locality"
},
  "geometry": {"coordinates":[-7.71168,31.98324],"type":"Point"}
}