{
  "type": "Feature",
  "properties": {
    "gn:admin1_code":"3.0",
    "gn:asciiname":"Gharbaous",
    "gn:country_code":"MA",
    "gn:dem":731,
    "gn:feature_class":"P",
    "gn:feature_code":"PPL",
    "gn:name":"Gharbaous",
    "gn:population":0,
    "gn:timezone":"Africa/Casablanca",
    "iso:country":"MA",
    "wof:name":"Gharbaous",
    "wof:placetype":"locality"
},
  "geometry": {"coordinates":[-5.26131,33.83238],"type":"Point"}
}