{
  "type": "Feature",
  "properties": {
    "gn:admin1_code":"7.0",
    "gn:asciiname":"Had Essoualma",
    "gn:country_code":"MA",
    "gn:dem":221,
    "gn:feature_class":"P",
    "gn:feature_code":"PPL",
    "gn:name":"Had Essoualma",
    "gn:population":0,
    "gn:timezone":"Africa/Casablanca",
    "iso:country":"MA",
    "wof:name":"Had Essoualma",
    "wof:placetype":"locality"
},
  "geometry": {"coordinates":[-9.04743,31.85804000000001],"type":"Point"}
}