{
  "type": "Feature",
  "properties": {
    "gn:admin1_code":"4.0",
    "gn:asciiname":"Mechraa Lamdaz",
    "gn:country_code":"MA",
    "gn:dem":8,
    "gn:feature_class":"P",
    "gn:feature_code":"PPLL",
    "gn:name":"Mechraa Lamdaz",
    "gn:population":0,
    "gn:timezone":"Africa/Casablanca",
    "iso:country":"MA",
    "wof:name":"Mechraa Lamdaz",
    "wof:placetype":"locality"
},
  "geometry": {"coordinates":[-6.77322,33.959],"type":"Point"}
}