{
  "type": "Feature",
  "properties": {
    "gn:admin1_code":"07",
    "gn:asciiname":"Tannsrhart",
    "gn:country_code":"MA",
    "gn:dem":1312,
    "gn:feature_class":"P",
    "gn:feature_code":"PPL",
    "gn:name":"Tannsrhart",
    "gn:population":0,
    "gn:timezone":"Africa/Casablanca",
    "iso:country":"MA",
    "name:und_x_variant":[
        "Tansghart"
    ],
    "wof:name":"Tannsrhart",
    "wof:placetype":"locality"
},
  "geometry": {"coordinates":[-7.96591,31.22589],"type":"Point"}
}