{
  "type": "Feature",
  "properties": {
    "gn:admin1_code":"9.0",
    "gn:asciiname":"Ait Walane",
    "gn:country_code":"MA",
    "gn:dem":1445,
    "gn:feature_class":"P",
    "gn:feature_code":"PPL",
    "gn:name":"A\u00eft Walane",
    "gn:population":0,
    "gn:timezone":"Africa/Casablanca",
    "iso:country":"MA",
    "wof:name":"Ait Walane",
    "wof:placetype":"locality"
},
  "geometry": {"coordinates":[-8.54752,30.16455],"type":"Point"}
}