{
  "type": "Feature",
  "properties": {
    "gn:admin1_code":"9.0",
    "gn:asciiname":"Tamlalt",
    "gn:country_code":"MA",
    "gn:dem":783,
    "gn:feature_class":"P",
    "gn:feature_code":"PPL",
    "gn:name":"Tamlalt",
    "gn:population":0,
    "gn:timezone":"Africa/Casablanca",
    "iso:country":"MA",
    "wof:name":"Tamlalt",
    "wof:placetype":"locality"
},
  "geometry": {"coordinates":[-9.28782,29.61126],"type":"Point"}
}