{
  "type": "Feature",
  "properties": {
    "gn:admin1_code":"08",
    "gn:asciiname":"Carghine",
    "gn:country_code":"MA",
    "gn:dem":1458,
    "gn:feature_class":"P",
    "gn:feature_code":"PPL",
    "gn:name":"Carghine",
    "gn:population":0,
    "gn:timezone":"Africa/Casablanca",
    "iso:country":"MA",
    "wof:name":"Carghine",
    "wof:placetype":"locality"
},
  "geometry": {"coordinates":[-6.04752,31.2676],"type":"Point"}
}