{
  "type": "Feature",
  "properties": {
    "gn:admin1_code":"7.0",
    "gn:asciiname":"Ben Ach-chikh",
    "gn:country_code":"MA",
    "gn:dem":609,
    "gn:feature_class":"P",
    "gn:feature_code":"PPL",
    "gn:name":"Ben Ach-chikh",
    "gn:population":0,
    "gn:timezone":"Africa/Casablanca",
    "iso:country":"MA",
    "wof:name":"Ben Ach-chikh",
    "wof:placetype":"locality"
},
  "geometry": {"coordinates":[-7.13919,31.88314],"type":"Point"}
}