{
  "type": "Feature",
  "properties": {
    "gn:admin1_code":"4.0",
    "gn:asciiname":"Oulad Amer",
    "gn:country_code":"MA",
    "gn:dem":13,
    "gn:feature_class":"P",
    "gn:feature_code":"PPL",
    "gn:name":"Oulad Amer",
    "gn:population":0,
    "gn:timezone":"Africa/Casablanca",
    "iso:country":"MA",
    "name:ara_x_preferred":[
        "\u0623\u0648\u0644\u0627\u062f \u0639\u0627\u0645\u0631"
    ],
    "name:cat_x_preferred":[
        "Oulad Amer"
    ],
    "name:ita_x_preferred":[
        "Oulad Amer"
    ],
    "wof:name":"Oulad Amer",
    "wof:placetype":"locality"
},
  "geometry": {"coordinates":[-6.46777,34.33213],"type":"Point"}
}