{
  "type": "Feature",
  "properties": {
    "gn:admin1_code":"01",
    "gn:asciiname":"Bouaouene",
    "gn:country_code":"MA",
    "gn:dem":936,
    "gn:feature_class":"P",
    "gn:feature_code":"PPL",
    "gn:name":"Bouaouene",
    "gn:population":0,
    "gn:timezone":"Africa/Casablanca",
    "iso:country":"MA",
    "name:und_x_variant":[
        "Boua\u00e2nne",
        "Bouaouene"
    ],
    "wof:name":"Bouaouene",
    "wof:placetype":"locality"
},
  "geometry": {"coordinates":[-5.30365,35.28651],"type":"Point"}
}