{
  "type": "Feature",
  "properties": {
    "gn:admin1_code":"9.0",
    "gn:asciiname":"Tine Mohamed Ou Mohand",
    "gn:country_code":"MA",
    "gn:dem":116,
    "gn:feature_class":"P",
    "gn:feature_code":"PPL",
    "gn:name":"Tine Mohamed Ou Mohand",
    "gn:population":0,
    "gn:timezone":"Africa/Casablanca",
    "iso:country":"MA",
    "wof:name":"Tine Mohamed Ou Mohand",
    "wof:placetype":"locality"
},
  "geometry": {"coordinates":[-9.43655,30.10689],"type":"Point"}
}