{
  "type": "Feature",
  "properties": {
    "gn:admin1_code":"04",
    "gn:asciiname":"Mghiten Oulad Slimane",
    "gn:country_code":"MA",
    "gn:dem":17,
    "gn:feature_class":"P",
    "gn:feature_code":"PPL",
    "gn:name":"Mghiten Oulad Slimane",
    "gn:population":0,
    "gn:timezone":"Africa/Casablanca",
    "iso:country":"MA",
    "name:und_x_variant":[
        "Douar Merhitene",
        "Oulad Slimane",
        "Mghiten Ouled Msellem",
        "Merhitene Oulad Slimane",
        "Mghiten Oulad Slimane"
    ],
    "wof:name":"Mghiten Oulad Slimane",
    "wof:placetype":"locality"
},
  "geometry": {"coordinates":[-6.06884,34.60446],"type":"Point"}
}