{
  "type": "Feature",
  "properties": {
    "gn:admin1_code":"6.0",
    "gn:asciiname":"Rerharhoua",
    "gn:country_code":"MA",
    "gn:dem":374,
    "gn:feature_class":"P",
    "gn:feature_code":"PPL",
    "gn:name":"Rerharhoua",
    "gn:population":0,
    "gn:timezone":"Africa/Casablanca",
    "iso:country":"MA",
    "wof:name":"Rerharhoua",
    "wof:placetype":"locality"
},
  "geometry": {"coordinates":[-7.73496,32.749],"type":"Point"}
}