{
  "type": "Feature",
  "properties": {
    "gn:admin1_code":"07",
    "gn:asciiname":"Bou 'Azza",
    "gn:country_code":"MA",
    "gn:dem":611,
    "gn:feature_class":"P",
    "gn:feature_code":"PPL",
    "gn:name":"Bou \u2019Azza",
    "gn:population":0,
    "gn:timezone":"Africa/Casablanca",
    "iso:country":"MA",
    "name:und_x_variant":[
        "Douar bou Azza",
        "Bou Azza",
        "Bou \u2019Azza"
    ],
    "wof:name":"Bou 'Azza",
    "wof:placetype":"locality"
},
  "geometry": {"coordinates":[-7.91766,31.48912],"type":"Point"}
}