{
  "type": "Feature",
  "properties": {
    "gn:admin1_code":"3.0",
    "gn:asciiname":"Dar Mekouar",
    "gn:country_code":"MA",
    "gn:dem":1170,
    "gn:feature_class":"P",
    "gn:feature_code":"PPL",
    "gn:name":"Dar Mekouar",
    "gn:population":0,
    "gn:timezone":"Africa/Casablanca",
    "iso:country":"MA",
    "wof:name":"Dar Mekouar",
    "wof:placetype":"locality"
},
  "geometry": {"coordinates":[-5.01177,33.74985],"type":"Point"}
}