{
  "type": "Feature",
  "properties": {
    "gn:admin1_code":"02",
    "gn:asciiname":"Oulad Yrhoud",
    "gn:country_code":"MA",
    "gn:dem":607,
    "gn:feature_class":"P",
    "gn:feature_code":"PPL",
    "gn:name":"Oulad Yrhoud",
    "gn:population":0,
    "gn:timezone":"Africa/Casablanca",
    "iso:country":"MA",
    "name:und_x_variant":[
        "Oulad Irhoud"
    ],
    "wof:name":"Oulad Yrhoud",
    "wof:placetype":"locality"
},
  "geometry": {"coordinates":[-3.90574,34.29339],"type":"Point"}
}