{
  "type": "Feature",
  "properties": {
    "gn:admin1_code":"8.0",
    "gn:asciiname":"Oulad Bou 'Ali",
    "gn:country_code":"MA",
    "gn:dem":757,
    "gn:feature_class":"P",
    "gn:feature_code":"PPL",
    "gn:name":"Oulad Bou \u2019Ali",
    "gn:population":0,
    "gn:timezone":"Africa/Casablanca",
    "iso:country":"MA",
    "wof:name":"Oulad Bou 'Ali",
    "wof:placetype":"locality"
},
  "geometry": {"coordinates":[-4.30815,31.26794000000001],"type":"Point"}
}