{
  "type": "Feature",
  "properties": {
    "gn:admin1_code":"09",
    "gn:asciiname":"Ait Bouziane",
    "gn:country_code":"MA",
    "gn:dem":949,
    "gn:feature_class":"P",
    "gn:feature_code":"PPL",
    "gn:name":"A\u00eft Bouziane",
    "gn:population":0,
    "gn:timezone":"Africa/Casablanca",
    "iso:country":"MA",
    "wof:name":"Ait Bouziane",
    "wof:placetype":"locality"
},
  "geometry": {"coordinates":[-8.78418,30.23521],"type":"Point"}
}