{
  "type": "Feature",
  "properties": {
    "gn:admin1_code":"10",
    "gn:asciiname":"Alhehi",
    "gn:country_code":"MA",
    "gn:dem":339,
    "gn:feature_class":"P",
    "gn:feature_code":"PPL",
    "gn:name":"Alhehi",
    "gn:population":0,
    "gn:timezone":"Africa/Casablanca",
    "iso:country":"MA",
    "name:und_x_variant":[
        "Ahel Hehe",
        "Alhehi"
    ],
    "wof:name":"Alhehi",
    "wof:placetype":"locality"
},
  "geometry": {"coordinates":[-10.29714,29.17631],"type":"Point"}
}