{
  "type": "Feature",
  "properties": {
    "gn:admin1_code":"6.0",
    "gn:asciiname":"Douar Laqwasme",
    "gn:country_code":"MA",
    "gn:dem":129,
    "gn:feature_class":"P",
    "gn:feature_code":"PPL",
    "gn:name":"Douar Laqwasme",
    "gn:population":0,
    "gn:timezone":"Africa/Casablanca",
    "iso:country":"MA",
    "wof:name":"Douar Laqwasme",
    "wof:placetype":"locality"
},
  "geometry": {"coordinates":[-8.56464,32.94712],"type":"Point"}
}