{
  "type": "Feature",
  "properties": {
    "gn:admin1_code":"04",
    "gn:asciiname":"Douar Hamamcha",
    "gn:country_code":"MA",
    "gn:dem":28,
    "gn:feature_class":"P",
    "gn:feature_code":"PPL",
    "gn:name":"Douar Hamamcha",
    "gn:population":0,
    "gn:timezone":"Africa/Casablanca",
    "iso:country":"MA",
    "name:und_x_variant":[
        "Lahmamcha",
        "Dar Hamamcha",
        "Douar Hamamcha"
    ],
    "wof:name":"Douar Hamamcha",
    "wof:placetype":"locality"
},
  "geometry": {"coordinates":[-5.78672,34.34675],"type":"Point"}
}