{
  "type": "Feature",
  "properties": {
    "gn:admin1_code":"07",
    "gn:asciiname":"Douar Oulad Hajj Mohammed",
    "gn:country_code":"MA",
    "gn:dem":815,
    "gn:feature_class":"P",
    "gn:feature_code":"PPL",
    "gn:name":"Douar Oulad Hajj Mohammed",
    "gn:population":0,
    "gn:timezone":"Africa/Casablanca",
    "iso:country":"MA",
    "name:und_x_variant":[
        "Douar Oulad Haj Mohammed",
        "Douar Oulad Hajj Mohammed"
    ],
    "wof:name":"Douar Oulad Hajj Mohammed",
    "wof:placetype":"locality"
},
  "geometry": {"coordinates":[-8.96181,31.21486],"type":"Point"}
}