{
  "type": "Feature",
  "properties": {
    "gn:admin1_code":"1.0",
    "gn:asciiname":"Douar Tazat",
    "gn:country_code":"MA",
    "gn:dem":159,
    "gn:feature_class":"P",
    "gn:feature_code":"PPL",
    "gn:name":"Douar Tazat",
    "gn:population":0,
    "gn:timezone":"Africa/Casablanca",
    "iso:country":"MA",
    "wof:name":"Douar Tazat",
    "wof:placetype":"locality"
},
  "geometry": {"coordinates":[-4.81598,35.23432000000001],"type":"Point"}
}