{
  "type": "Feature",
  "properties": {
    "gn:admin1_code":"7.0",
    "gn:asciiname":"El Atoug",
    "gn:country_code":"MA",
    "gn:dem":523,
    "gn:feature_class":"P",
    "gn:feature_code":"PPL",
    "gn:name":"El Atoug",
    "gn:population":0,
    "gn:timezone":"Africa/Casablanca",
    "iso:country":"MA",
    "wof:name":"El Atoug",
    "wof:placetype":"locality"
},
  "geometry": {"coordinates":[-9.28801,31.43307],"type":"Point"}
}