{
  "type": "Feature",
  "properties": {
    "gn:admin1_code":"2.0",
    "gn:asciiname":"Ibou Ajajene Jbel",
    "gn:country_code":"MA",
    "gn:dem":463,
    "gn:feature_class":"P",
    "gn:feature_code":"PPL",
    "gn:name":"Ibou Ajajene Jbel",
    "gn:population":0,
    "gn:timezone":"Africa/Casablanca",
    "iso:country":"MA",
    "wof:name":"Ibou Ajajene Jbel",
    "wof:placetype":"locality"
},
  "geometry": {"coordinates":[-3.01038,35.21154],"type":"Point"}
}