{
  "type": "Feature",
  "properties": {
    "gn:admin1_code":"10",
    "gn:asciiname":"Id Roufa",
    "gn:country_code":"MA",
    "gn:dem":311,
    "gn:feature_class":"P",
    "gn:feature_code":"PPL",
    "gn:name":"Id Roufa",
    "gn:population":0,
    "gn:timezone":"Africa/Casablanca",
    "iso:country":"MA",
    "name:und_x_variant":[
        "Idrufa",
        "Id Roufa"
    ],
    "wof:name":"Id Roufa",
    "wof:placetype":"locality"
},
  "geometry": {"coordinates":[-10.1165,29.2512],"type":"Point"}
}