{
  "type": "Feature",
  "properties": {
    "gn:admin1_code":"05",
    "gn:asciiname":"Tamarout",
    "gn:country_code":"MA",
    "gn:dem":946,
    "gn:elevation":"0.0",
    "gn:feature_class":"P",
    "gn:feature_code":"PPL",
    "gn:name":"Tamarout",
    "gn:population":0,
    "gn:timezone":"Africa/Casablanca",
    "iso:country":"MA",
    "name:und_x_variant":[
        "Tamarioute",
        "Tamarout"
    ],
    "wof:name":"Tamarout",
    "wof:placetype":"locality"
},
  "geometry": {"coordinates":[-6.79596,31.82156],"type":"Point"}
}