{
  "type": "Feature",
  "properties": {
    "gn:admin1_code":"07",
    "gn:asciiname":"Oulad Rahhou",
    "gn:country_code":"MA",
    "gn:dem":752,
    "gn:feature_class":"P",
    "gn:feature_code":"PPL",
    "gn:name":"Oulad Rahhou",
    "gn:population":0,
    "gn:timezone":"Africa/Casablanca",
    "iso:country":"MA",
    "name:und_x_variant":[
        "Oulad Raho"
    ],
    "wof:name":"Oulad Rahhou",
    "wof:placetype":"locality"
},
  "geometry": {"coordinates":[-7.14641,31.76192],"type":"Point"}
}