{
  "type": "Feature",
  "properties": {
    "gn:admin1_code":"6.0",
    "gn:asciiname":"Douar Lhaj Taher",
    "gn:country_code":"MA",
    "gn:dem":323,
    "gn:feature_class":"P",
    "gn:feature_code":"PPL",
    "gn:name":"Douar Lhaj Taher",
    "gn:population":0,
    "gn:timezone":"Africa/Casablanca",
    "iso:country":"MA",
    "wof:name":"Douar Lhaj Taher",
    "wof:placetype":"locality"
},
  "geometry": {"coordinates":[-7.12486,33.42249],"type":"Point"}
}