{
  "type": "Feature",
  "properties": {
    "gn:admin1_code":"7.0",
    "gn:asciiname":"Ait Douar Ali",
    "gn:country_code":"MA",
    "gn:dem":448,
    "gn:feature_class":"P",
    "gn:feature_code":"PPL",
    "gn:name":"Ait Douar Ali",
    "gn:population":0,
    "gn:timezone":"Africa/Casablanca",
    "iso:country":"MA",
    "wof:name":"Ait Douar Ali",
    "wof:placetype":"locality"
},
  "geometry": {"coordinates":[-9.37504,31.59299],"type":"Point"}
}