{
  "type": "Feature",
  "properties": {
    "gn:admin1_code":"10.0",
    "gn:asciiname":"Id Barrouchid",
    "gn:country_code":"MA",
    "gn:dem":685,
    "gn:feature_class":"P",
    "gn:feature_code":"PPL",
    "gn:name":"Id Barrouchid",
    "gn:population":0,
    "gn:timezone":"Africa/Casablanca",
    "iso:country":"MA",
    "wof:name":"Id Barrouchid",
    "wof:placetype":"locality"
},
  "geometry": {"coordinates":[-9.89215,29.332],"type":"Point"}
}