{
  "type": "Feature",
  "properties": {
    "gn:admin1_code":"1.0",
    "gn:asciiname":"Douar Tonet",
    "gn:country_code":"MA",
    "gn:dem":639,
    "gn:feature_class":"P",
    "gn:feature_code":"PPL",
    "gn:name":"Douar Tonet",
    "gn:population":0,
    "gn:timezone":"Africa/Casablanca",
    "iso:country":"MA",
    "name:und_x_variant":[
        "Tonet"
    ],
    "wof:name":"Douar Tonet",
    "wof:placetype":"locality"
},
  "geometry": {"coordinates":[-5.43837,35.37086],"type":"Point"}
}