{
  "type": "Feature",
  "properties": {
    "gn:admin1_code":"7.0",
    "gn:asciiname":"Tinwaline",
    "gn:country_code":"MA",
    "gn:dem":1153,
    "gn:feature_class":"P",
    "gn:feature_code":"PPL",
    "gn:name":"Tinwaline",
    "gn:population":0,
    "gn:timezone":"Africa/Casablanca",
    "iso:country":"MA",
    "wof:name":"Tinwaline",
    "wof:placetype":"locality"
},
  "geometry": {"coordinates":[-8.68799,31.08432],"type":"Point"}
}