{
  "type": "Feature",
  "properties": {
    "gn:admin1_code":"9.0",
    "gn:asciiname":"Iyrnad",
    "gn:country_code":"MA",
    "gn:dem":554,
    "gn:feature_class":"P",
    "gn:feature_code":"PPL",
    "gn:name":"Iyrnad",
    "gn:population":0,
    "gn:timezone":"Africa/Casablanca",
    "iso:country":"MA",
    "wof:name":"Iyrnad",
    "wof:placetype":"locality"
},
  "geometry": {"coordinates":[-9.33775,29.70716],"type":"Point"}
}