{
  "type": "Feature",
  "properties": {
    "gn:admin1_code":"05",
    "gn:asciiname":"Hamed Ou Aissa",
    "gn:country_code":"MA",
    "gn:dem":1956,
    "gn:elevation":"0.0",
    "gn:feature_class":"P",
    "gn:feature_code":"PPL",
    "gn:name":"Hamed Ou A\u00efssa",
    "gn:population":0,
    "gn:timezone":"Africa/Casablanca",
    "iso:country":"MA",
    "wof:name":"Hamed Ou Aissa",
    "wof:placetype":"locality"
},
  "geometry": {"coordinates":[-6.84762,31.57233],"type":"Point"}
}