{
  "type": "Feature",
  "properties": {
    "gn:admin1_code":"01",
    "gn:asciiname":"Haiata",
    "gn:country_code":"MA",
    "gn:dem":508,
    "gn:feature_class":"P",
    "gn:feature_code":"PPL",
    "gn:name":"Ha\u00efata",
    "gn:population":0,
    "gn:timezone":"Africa/Casablanca",
    "iso:country":"MA",
    "wof:name":"Haiata",
    "wof:placetype":"locality"
},
  "geometry": {"coordinates":[-5.66905,35.2459],"type":"Point"}
}