{
  "type": "Feature",
  "properties": {
    "gn:country":"MA",
    "gn:fcode":"ADM3",
    "gn:pop":10325,
    "iso:country":"MA",
    "name:ara_x_preferred":[
        "\u0633\u064a\u062f\u064a \u0639\u0628\u062f \u0627\u0644\u0644\u0647 \u063a\u064a\u0627\u062a"
    ],
    "name:ara_x_variant":[
        "\u062a\u0645\u0643\u0631\u062a"
    ],
    "name:azb_x_preferred":[
        "\u062a\u0645\u06a9\u0631\u062a"
    ],
    "name:bul_x_preferred":[
        "\u0422\u0430\u043c\u0430\u0433\u0443\u0435\u0440\u0442"
    ],
    "name:cat_x_preferred":[
        "Tamaguert"
    ],
    "name:ceb_x_preferred":[
        "Tamaguert"
    ],
    "name:eng_x_preferred":[
        "Tamaguert"
    ],
    "name:fas_x_preferred":[
        "\u062a\u0645\u06a9\u0631\u062a"
    ],
    "name:fra_x_preferred":[
        "Tamaguert"
    ],
    "name:fra_x_variant":[
        "Tamaguert (CR)",
        "Tamaguert (Commune Rurale)"
    ],
    "name:ita_x_preferred":[
        "Tamaguert"
    ],
    "name:swe_x_preferred":[
        "Tamaguert"
    ],
    "name:urd_x_preferred":[
        "\u062a\u0645\u06af\u0631\u062a"
    ],
    "qs:name":"Tamaguert",
    "qs:photos_9r":0,
    "qs:photos_sr":0,
    "qs:pop_sr":"6",
    "wd:wordcount":62,
    "wof:name":"Tamaguert",
    "wof:placetype":"localadmin",
    "wof:population":10325
},
  "geometry": {"coordinates":[-7.54046,31.54196],"type":"Point"}
}