{
  "type": "Feature",
  "properties": {
    "gn:admin1_code":"07",
    "gn:asciiname":"Al Bioutat",
    "gn:country_code":"MA",
    "gn:dem":431,
    "gn:feature_class":"P",
    "gn:feature_code":"PPL",
    "gn:name":"Al Bioutat",
    "gn:population":0,
    "gn:timezone":"Africa/Casablanca",
    "iso:country":"MA",
    "wof:name":"Al Bioutat",
    "wof:placetype":"locality"
},
  "geometry": {"coordinates":[-8.97532,31.47296],"type":"Point"}
}