{
  "type": "Feature",
  "properties": {
    "gn:admin1_code":"7.0",
    "gn:asciiname":"Takatert",
    "gn:country_code":"MA",
    "gn:dem":831,
    "gn:feature_class":"P",
    "gn:feature_code":"PPL",
    "gn:name":"Takatert",
    "gn:population":0,
    "gn:timezone":"Africa/Casablanca",
    "iso:country":"MA",
    "wof:name":"Takatert",
    "wof:placetype":"locality"
},
  "geometry": {"coordinates":[-7.43064,31.57926],"type":"Point"}
}