{
  "type": "Feature",
  "properties": {
    "gn:admin1_code":"07",
    "gn:asciiname":"Oulad Kheia",
    "gn:country_code":"MA",
    "gn:dem":83,
    "gn:feature_class":"P",
    "gn:feature_code":"PPL",
    "gn:name":"Oulad Khe\u00efa",
    "gn:population":0,
    "gn:timezone":"Africa/Casablanca",
    "iso:country":"MA",
    "name:und_x_variant":[
        "Douar Oulad Khe\u00efa",
        "Oulad Khe\u00efa"
    ],
    "wof:name":"Oulad Kheia",
    "wof:placetype":"locality"
},
  "geometry": {"coordinates":[-9.15747,32.31723],"type":"Point"}
}