{
  "type": "Feature",
  "properties": {
    "gn:admin1_code":"2.0",
    "gn:asciiname":"Bou Chfari",
    "gn:country_code":"MA",
    "gn:dem":42,
    "gn:feature_class":"P",
    "gn:feature_code":"PPL",
    "gn:name":"Bou Chfari",
    "gn:population":0,
    "gn:timezone":"Africa/Casablanca",
    "iso:country":"MA",
    "wof:name":"Bou Chfari",
    "wof:placetype":"locality"
},
  "geometry": {"coordinates":[-3.20206,35.21680999999999],"type":"Point"}
}