{
  "type": "Feature",
  "properties": {
    "gn:admin1_code":"6.0",
    "gn:asciiname":"Dar El Haj Lekbir",
    "gn:country_code":"MA",
    "gn:dem":387,
    "gn:feature_class":"P",
    "gn:feature_code":"PPL",
    "gn:name":"Dar El Haj Lekbir",
    "gn:population":0,
    "gn:timezone":"Africa/Casablanca",
    "iso:country":"MA",
    "wof:name":"Dar El Haj Lekbir",
    "wof:placetype":"locality"
},
  "geometry": {"coordinates":[-6.94344,33.25827],"type":"Point"}
}