{
  "type": "Feature",
  "properties": {
    "gn:admin1_code":"7.0",
    "gn:asciiname":"Amadaln",
    "gn:country_code":"MA",
    "gn:dem":1198,
    "gn:feature_class":"P",
    "gn:feature_code":"PPL",
    "gn:name":"Amadaln",
    "gn:population":0,
    "gn:timezone":"Africa/Casablanca",
    "iso:country":"MA",
    "wof:name":"Amadaln",
    "wof:placetype":"locality"
},
  "geometry": {"coordinates":[-9.24261,31.19543],"type":"Point"}
}