{
  "type": "Feature",
  "properties": {
    "gn:admin1_code":"09",
    "gn:asciiname":"Alaggou",
    "gn:country_code":"MA",
    "gn:dem":1554,
    "gn:feature_class":"P",
    "gn:feature_code":"PPL",
    "gn:name":"Alaggou",
    "gn:population":0,
    "gn:timezone":"Africa/Casablanca",
    "iso:country":"MA",
    "name:und_x_variant":[
        "Algou"
    ],
    "wof:name":"Alaggou",
    "wof:placetype":"locality"
},
  "geometry": {"coordinates":[-7.86216,30.42301],"type":"Point"}
}