{
  "type": "Feature",
  "properties": {
    "gn:admin1_code":"10.0",
    "gn:asciiname":"Tazarout",
    "gn:country_code":"MA",
    "gn:dem":707,
    "gn:feature_class":"P",
    "gn:feature_code":"PPL",
    "gn:name":"Tazarout",
    "gn:population":0,
    "gn:timezone":"Africa/Casablanca",
    "iso:country":"MA",
    "wof:name":"Tazarout",
    "wof:placetype":"locality"
},
  "geometry": {"coordinates":[-9.89196,29.32057],"type":"Point"}
}