{
  "type": "Feature",
  "properties": {
    "gn:admin1_code":"06",
    "gn:asciiname":"Douar el Biaida",
    "gn:country_code":"MA",
    "gn:dem":559,
    "gn:feature_class":"P",
    "gn:feature_code":"PPL",
    "gn:name":"Douar el Bia\u00efda",
    "gn:population":0,
    "gn:timezone":"Africa/Casablanca",
    "iso:country":"MA",
    "wof:name":"Douar el Biaida",
    "wof:placetype":"locality"
},
  "geometry": {"coordinates":[-7.35494,32.66059],"type":"Point"}
}