{
  "type": "Feature",
  "properties": {
    "gn:admin1_code":"6.0",
    "gn:asciiname":"Leqouader",
    "gn:country_code":"MA",
    "gn:dem":361,
    "gn:feature_class":"P",
    "gn:feature_code":"PPL",
    "gn:name":"Leqouader",
    "gn:population":0,
    "gn:timezone":"Africa/Casablanca",
    "iso:country":"MA",
    "wof:name":"Leqouader",
    "wof:placetype":"locality"
},
  "geometry": {"coordinates":[-7.10058,33.19863],"type":"Point"}
}