{
  "type": "Feature",
  "properties": {
    "gn:admin1_code":"7.0",
    "gn:asciiname":"Drae Essahel",
    "gn:country_code":"MA",
    "gn:dem":195,
    "gn:feature_class":"P",
    "gn:feature_code":"PPL",
    "gn:name":"Drae Essahel",
    "gn:population":0,
    "gn:timezone":"Africa/Casablanca",
    "iso:country":"MA",
    "wof:name":"Drae Essahel",
    "wof:placetype":"locality"
},
  "geometry": {"coordinates":[-9.61061,31.54556],"type":"Point"}
}