{
  "type": "Feature",
  "properties": {
    "gn:admin1_code":"7.0",
    "gn:asciiname":"Oulad Haddad",
    "gn:country_code":"MA",
    "gn:dem":621,
    "gn:feature_class":"P",
    "gn:feature_code":"PPL",
    "gn:name":"Oulad Haddad",
    "gn:population":0,
    "gn:timezone":"Africa/Casablanca",
    "iso:country":"MA",
    "wof:name":"Oulad Haddad",
    "wof:placetype":"locality"
},
  "geometry": {"coordinates":[-7.20531,31.83183],"type":"Point"}
}