{
  "type": "Feature",
  "properties": {
    "gn:country":"MA",
    "gn:fcode":"ADM3",
    "gn:pop":5514,
    "iso:country":"MA",
    "name:ara_x_preferred":[
        "\u0627\u0644\u0645\u0646\u0632\u0647"
    ],
    "name:fra_x_preferred":[
        "Ait Bouyahya  El Haj"
    ],
    "name:fra_x_variant":[
        "Ait Bouyahya  El Haj (CR)",
        "Ait Bouyahya  El Haj (Commune Rurale)"
    ],
    "qs:name":"Ait Bouyahya  El Haj",
    "qs:photos_9r":0,
    "qs:photos_sr":0,
    "qs:pop_sr":"5",
    "wof:name":"Ait Bouyahya  El Haj",
    "wof:placetype":"localadmin",
    "wof:population":5514
},
  "geometry": {"coordinates":[-6.29392,33.88129],"type":"Point"}
}