{
  "type": "Feature",
  "properties": {
    "gn:admin1_code":"7.0",
    "gn:asciiname":"Dar Hassan Lebhour",
    "gn:country_code":"MA",
    "gn:dem":313,
    "gn:feature_class":"P",
    "gn:feature_code":"PPL",
    "gn:name":"Dar Hassan Lebhour",
    "gn:population":0,
    "gn:timezone":"Africa/Casablanca",
    "iso:country":"MA",
    "wof:name":"Dar Hassan Lebhour",
    "wof:placetype":"locality"
},
  "geometry": {"coordinates":[-8.42059,31.69548],"type":"Point"}
}