{
  "type": "Feature",
  "properties": {
    "gn:admin1_code":"2.0",
    "gn:asciiname":"Hay Cooperative El Fath",
    "gn:country_code":"MA",
    "gn:dem":10,
    "gn:feature_class":"P",
    "gn:feature_code":"PPL",
    "gn:name":"Hay Cooperative El Fath",
    "gn:population":0,
    "gn:timezone":"Africa/Casablanca",
    "iso:country":"MA",
    "wof:name":"Hay Cooperative El Fath",
    "wof:placetype":"locality"
},
  "geometry": {"coordinates":[-2.73831,35.10169],"type":"Point"}
}