{
  "type": "Feature",
  "properties": {
    "gn:admin1_code":"01",
    "gn:asciiname":"Yarghit",
    "gn:country_code":"MA",
    "gn:dem":159,
    "gn:feature_class":"P",
    "gn:feature_code":"PPL",
    "gn:name":"Yarghit",
    "gn:population":0,
    "gn:timezone":"Africa/Casablanca",
    "iso:country":"MA",
    "name:und_x_variant":[
        "Jarguit",
        "Yarghite",
        "Yarghit"
    ],
    "wof:name":"Yarghit",
    "wof:placetype":"locality"
},
  "geometry": {"coordinates":[-5.33994,35.5214],"type":"Point"}
}