{
  "type": "Feature",
  "properties": {
    "gn:admin1_code":"05",
    "gn:asciiname":"Foum el Anser",
    "gn:country_code":"MA",
    "gn:dem":651,
    "gn:feature_class":"P",
    "gn:feature_code":"PPL",
    "gn:name":"Foum el Anser",
    "gn:population":0,
    "gn:timezone":"Africa/Casablanca",
    "iso:country":"MA",
    "name:und_x_variant":[
        "Foum el Annseur",
        "Foum el Anseur",
        "Foum el Anser"
    ],
    "wof:name":"Foum el Anser",
    "wof:placetype":"locality"
},
  "geometry": {"coordinates":[-6.25967,32.37309],"type":"Point"}
}