{
  "type": "Feature",
  "properties": {
    "gn:admin1_code":"2.0",
    "gn:asciiname":"Douar Tiourar",
    "gn:country_code":"MA",
    "gn:dem":204,
    "gn:feature_class":"P",
    "gn:feature_code":"PPL",
    "gn:name":"Douar Tiourar",
    "gn:population":0,
    "gn:timezone":"Africa/Casablanca",
    "iso:country":"MA",
    "wof:name":"Douar Tiourar",
    "wof:placetype":"locality"
},
  "geometry": {"coordinates":[-2.3001,34.92984000000001],"type":"Point"}
}