{
  "type": "Feature",
  "properties": {
    "gn:admin1_code":"9.0",
    "gn:asciiname":"Ait ou Guerd",
    "gn:country_code":"MA",
    "gn:dem":457,
    "gn:feature_class":"P",
    "gn:feature_code":"PPL",
    "gn:name":"A\u00eft ou Guerd",
    "gn:population":0,
    "gn:timezone":"Africa/Casablanca",
    "iso:country":"MA",
    "wof:name":"Ait ou Guerd",
    "wof:placetype":"locality"
},
  "geometry": {"coordinates":[-9.36386,29.83022],"type":"Point"}
}