{
  "type": "Feature",
  "properties": {
    "gn:admin1_code":"08",
    "gn:asciiname":"'Arbane",
    "gn:country_code":"MA",
    "gn:dem":1533,
    "gn:feature_class":"P",
    "gn:feature_code":"PPL",
    "gn:name":"\u2019Arbane",
    "gn:population":0,
    "gn:timezone":"Africa/Casablanca",
    "iso:country":"MA",
    "name:und_x_variant":[
        "A\u00e2rbane",
        "Arbane",
        "\u2019Arbane"
    ],
    "wof:name":"'Arbane",
    "wof:placetype":"locality"
},
  "geometry": {"coordinates":[-4.87563,32.97558],"type":"Point"}
}