{
  "type": "Feature",
  "properties": {
    "gn:admin1_code":"09",
    "gn:asciiname":"Tounkrim",
    "gn:country_code":"MA",
    "gn:dem":474,
    "gn:feature_class":"P",
    "gn:feature_code":"PPL",
    "gn:name":"Tounkrim",
    "gn:population":0,
    "gn:timezone":"Africa/Casablanca",
    "iso:country":"MA",
    "wof:name":"Tounkrim",
    "wof:placetype":"locality"
},
  "geometry": {"coordinates":[-9.51219,30.49159],"type":"Point"}
}