{
  "type": "Feature",
  "properties": {
    "gn:admin1_code":"04",
    "gn:asciiname":"Douar Oulad Salem",
    "gn:country_code":"MA",
    "gn:dem":41,
    "gn:feature_class":"P",
    "gn:feature_code":"PPL",
    "gn:name":"Douar Oulad Salem",
    "gn:population":0,
    "gn:timezone":"Africa/Casablanca",
    "iso:country":"MA",
    "name:und_x_variant":[
        "Oulad Salem",
        "Ouled Salem",
        "Douar Oulad Salem"
    ],
    "wof:name":"Douar Oulad Salem",
    "wof:placetype":"locality"
},
  "geometry": {"coordinates":[-5.77067,34.56519],"type":"Point"}
}