{
  "type": "Feature",
  "properties": {
    "gn:admin1_code":"10.0",
    "gn:asciiname":"Id Wassa",
    "gn:country_code":"MA",
    "gn:dem":587,
    "gn:feature_class":"P",
    "gn:feature_code":"PPL",
    "gn:name":"Id Wassa",
    "gn:population":0,
    "gn:timezone":"Africa/Casablanca",
    "iso:country":"MA",
    "wof:name":"Id Wassa",
    "wof:placetype":"locality"
},
  "geometry": {"coordinates":[-9.93902,29.27343],"type":"Point"}
}