{
  "type": "Feature",
  "properties": {
    "gn:admin1_code":"04",
    "gn:asciiname":"Douar Skara",
    "gn:country_code":"MA",
    "gn:dem":202,
    "gn:feature_class":"P",
    "gn:feature_code":"PPL",
    "gn:name":"Douar Skara",
    "gn:population":0,
    "gn:timezone":"Africa/Casablanca",
    "iso:country":"MA",
    "wof:name":"Douar Skara",
    "wof:placetype":"locality"
},
  "geometry": {"coordinates":[-5.64112,34.1747],"type":"Point"}
}