{
  "type": "Feature",
  "properties": {
    "gn:admin1_code":"03",
    "gn:asciiname":"Douar Lemtinner",
    "gn:country_code":"MA",
    "gn:dem":261,
    "gn:feature_class":"P",
    "gn:feature_code":"PPL",
    "gn:name":"Douar Lemtinner",
    "gn:population":0,
    "gn:timezone":"Africa/Casablanca",
    "iso:country":"MA",
    "name:und_x_variant":[
        "Douar el Mtimra",
        "El Mtimra",
        "Douar Lemtinner",
        "Douar Lemtuner"
    ],
    "wof:name":"Douar Lemtinner",
    "wof:placetype":"locality"
},
  "geometry": {"coordinates":[-4.62964,34.4856],"type":"Point"}
}