{
  "type": "Feature",
  "properties": {
    "gn:country":"MA",
    "gn:fcode":"ADM3",
    "gn:pop":3027,
    "iso:country":"MA",
    "name:ara_x_preferred":[
        "\u0646\u064a\u062d\u064a\u062a"
    ],
    "name:fra_x_preferred":[
        "Oualqadi"
    ],
    "name:fra_x_variant":[
        "Oualqadi (CR)",
        "Oualqadi (Commune Rurale)"
    ],
    "qs:name":"Oualqadi",
    "qs:photos_9r":0,
    "qs:photos_sr":0,
    "qs:pop_sr":"4",
    "wd:wordcount":60,
    "wof:name":"Oualqadi",
    "wof:placetype":"localadmin",
    "wof:population":3027
},
  "geometry": {"coordinates":[-8.4964,30.20496],"type":"Point"}
}