{
  "type": "Feature",
  "properties": {
    "gn:admin1_code":"6.0",
    "gn:asciiname":"Tbatba",
    "gn:country_code":"MA",
    "gn:dem":129,
    "gn:feature_class":"P",
    "gn:feature_code":"PPL",
    "gn:name":"Tbatba",
    "gn:population":0,
    "gn:timezone":"Africa/Casablanca",
    "iso:country":"MA",
    "wof:name":"Tbatba",
    "wof:placetype":"locality"
},
  "geometry": {"coordinates":[-8.12121,33.04542],"type":"Point"}
}