{
  "type": "Feature",
  "properties": {
    "gn:admin1_code":"07",
    "gn:asciiname":"Douar Arabat",
    "gn:country_code":"MA",
    "gn:dem":493,
    "gn:feature_class":"P",
    "gn:feature_code":"PPL",
    "gn:name":"Douar Arabat",
    "gn:population":0,
    "gn:timezone":"Africa/Casablanca",
    "iso:country":"MA",
    "name:und_x_variant":[
        "Arabate",
        "Arabat",
        "Douar Arabat"
    ],
    "wof:name":"Douar Arabat",
    "wof:placetype":"locality"
},
  "geometry": {"coordinates":[-7.97028,32.29393],"type":"Point"}
}