{
  "type": "Feature",
  "properties": {
    "gn:admin1_code":"04",
    "gn:asciiname":"Sidi Allal",
    "gn:country_code":"MA",
    "gn:dem":284,
    "gn:feature_class":"P",
    "gn:feature_code":"PPL",
    "gn:name":"Sidi Allal",
    "gn:population":0,
    "gn:timezone":"Africa/Casablanca",
    "iso:country":"MA",
    "name:und_x_variant":[
        "A\u00eft Allal",
        "Sidi Allal"
    ],
    "wof:name":"Sidi Allal",
    "wof:placetype":"locality"
},
  "geometry": {"coordinates":[-5.85934,33.80833],"type":"Point"}
}