{
  "type": "Feature",
  "properties": {
    "gn:admin1_code":"01",
    "gn:asciiname":"Alalech",
    "gn:country_code":"MA",
    "gn:dem":436,
    "gn:feature_class":"P",
    "gn:feature_code":"PPL",
    "gn:name":"Alalech",
    "gn:population":0,
    "gn:timezone":"Africa/Casablanca",
    "iso:country":"MA",
    "name:und_x_variant":[
        "Ahlalech",
        "Aalalech",
        "Alalech"
    ],
    "wof:name":"Alalech",
    "wof:placetype":"locality"
},
  "geometry": {"coordinates":[-5.03303,34.94342],"type":"Point"}
}