{
  "type": "Feature",
  "properties": {
    "gn:admin1_code":"08",
    "gn:asciiname":"Ouriouroug",
    "gn:country_code":"MA",
    "gn:dem":2583,
    "gn:feature_class":"P",
    "gn:feature_code":"PPL",
    "gn:name":"Ouriouroug",
    "gn:population":0,
    "gn:timezone":"Africa/Casablanca",
    "iso:country":"MA",
    "name:und_x_variant":[
        "Duriouroug"
    ],
    "wof:name":"Ouriouroug",
    "wof:placetype":"locality"
},
  "geometry": {"coordinates":[-6.60455,31.39544],"type":"Point"}
}