{
  "type": "Feature",
  "properties": {
    "gn:admin1_code":"5.0",
    "gn:asciiname":"Ait Wakrim",
    "gn:country_code":"MA",
    "gn:dem":1069,
    "gn:feature_class":"P",
    "gn:feature_code":"PPL",
    "gn:name":"A\u00eft Wakrim",
    "gn:population":0,
    "gn:timezone":"Africa/Casablanca",
    "iso:country":"MA",
    "wof:name":"Ait Wakrim",
    "wof:placetype":"locality"
},
  "geometry": {"coordinates":[-6.88774,31.69225],"type":"Point"}
}