{
  "type": "Feature",
  "properties": {
    "gn:gn_country":"MA",
    "gn:gn_fcode":"ADM3",
    "gn:gn_pop":5324,
    "gn:population":5324,
    "iso:country":"MA",
    "name:ara_x_preferred":[
        "\u0644\u0643\u062f\u0627\u062f\u0631\u0629"
    ],
    "name:ara_x_variant":[
        "\u0644\u062d\u0633\u064a\u0646\u0627\u062a"
    ],
    "name:cat_x_preferred":[
        "Lahsinate"
    ],
    "name:ceb_x_preferred":[
        "Lahsinate"
    ],
    "name:fra_x_preferred":[
        "Lahsinate"
    ],
    "name:fra_x_variant":[
        "Lahsinate (CR)",
        "Lahsinate (Commune Rurale)"
    ],
    "name:ita_x_preferred":[
        "Lahsinate"
    ],
    "name:swe_x_preferred":[
        "Lahsinate"
    ],
    "name:urd_x_preferred":[
        "\u0644\u0627\u06c1\u0633\u06cc\u0646\u0627\u0679\u06cc"
    ],
    "qs_pg:aaroncc":"MA",
    "qs_pg:gn_country":"MA",
    "qs_pg:gn_fcode":"ADM3",
    "qs_pg:gn_pop":5324,
    "qs_pg:name":"Lahsinate",
    "qs_pg:photos_9r":0,
    "qs_pg:photos_sr":0,
    "qs_pg:pop_sr":5,
    "qs_pg:qs_pg_placetype":"localadmin",
    "wof:name":"Lahsinate",
    "wof:placetype":"localadmin",
    "wof:population":5324
},
  "geometry": {"coordinates":[-9.48798,31.5383],"type":"Point"}
}