{
  "type": "Feature",
  "properties": {
    "gn:admin1_code":"07",
    "gn:asciiname":"Douar Nouama",
    "gn:country_code":"MA",
    "gn:dem":181,
    "gn:feature_class":"P",
    "gn:feature_code":"PPL",
    "gn:name":"Douar Nouama",
    "gn:population":0,
    "gn:timezone":"Africa/Casablanca",
    "iso:country":"MA",
    "name:und_x_variant":[
        "Douar Sidi Kaddour",
        "Nouama",
        "Douar Nouama"
    ],
    "wof:name":"Douar Nouama",
    "wof:placetype":"locality"
},
  "geometry": {"coordinates":[-9.25145,31.81476],"type":"Point"}
}