{
  "type": "Feature",
  "properties": {
    "gn:admin1_code":"03",
    "gn:asciiname":"Beni Mansour",
    "gn:country_code":"MA",
    "gn:dem":679,
    "gn:feature_class":"P",
    "gn:feature_code":"PPL",
    "gn:name":"Beni Mansour",
    "gn:population":0,
    "gn:timezone":"Africa/Casablanca",
    "iso:country":"MA",
    "wof:name":"Beni Mansour",
    "wof:placetype":"locality"
},
  "geometry": {"coordinates":[-5.4071,34.0607],"type":"Point"}
}