{
  "type": "Feature",
  "properties": {
    "gn:admin1_code":"07",
    "gn:asciiname":"Douar Chelhaouiyine",
    "gn:country_code":"MA",
    "gn:dem":357,
    "gn:feature_class":"P",
    "gn:feature_code":"PPL",
    "gn:name":"Douar Chelhaouiyine",
    "gn:population":0,
    "gn:timezone":"Africa/Casablanca",
    "iso:country":"MA",
    "name:und_x_variant":[
        "Rguibat Chlihaouia",
        "Douar Reguibet",
        "Chlehalouya",
        "Douar Chelhaouiyine",
        "Ar Rguibat"
    ],
    "wof:name":"Douar Chelhaouiyine",
    "wof:placetype":"locality"
},
  "geometry": {"coordinates":[-8.24618,32.23532],"type":"Point"}
}