{
  "type": "Feature",
  "properties": {
    "gn:admin1_code":"1.0",
    "gn:asciiname":"Chouikhene",
    "gn:country_code":"MA",
    "gn:dem":600,
    "gn:feature_class":"P",
    "gn:feature_code":"PPL",
    "gn:name":"Chouikhene",
    "gn:population":0,
    "gn:timezone":"Africa/Casablanca",
    "iso:country":"MA",
    "wof:name":"Chouikhene",
    "wof:placetype":"locality"
},
  "geometry": {"coordinates":[-5.22634,35.45828],"type":"Point"}
}