{
  "type": "Feature",
  "properties": {
    "gn:admin1_code":"01",
    "gn:asciiname":"Ifartane Fouqiya",
    "gn:country_code":"MA",
    "gn:dem":246,
    "gn:feature_class":"P",
    "gn:feature_code":"PPL",
    "gn:name":"Ifartane Fouqiya",
    "gn:population":0,
    "gn:timezone":"Africa/Casablanca",
    "iso:country":"MA",
    "name:und_x_variant":[
        "Afertane"
    ],
    "wof:name":"Ifartane Fouqiya",
    "wof:placetype":"locality"
},
  "geometry": {"coordinates":[-5.19368,35.34743],"type":"Point"}
}