{
  "type": "Feature",
  "properties": {
    "gn:admin1_code":"9.0",
    "gn:asciiname":"Agadir Oujgal",
    "gn:country_code":"MA",
    "gn:dem":1310,
    "gn:feature_class":"P",
    "gn:feature_code":"PPL",
    "gn:name":"Agadir Oujgal",
    "gn:population":0,
    "gn:timezone":"Africa/Casablanca",
    "iso:country":"MA",
    "name:und_x_variant":[
        "Agadir"
    ],
    "wof:name":"Agadir Oujgal",
    "wof:placetype":"locality"
},
  "geometry": {"coordinates":[-9.28816,29.74801],"type":"Point"}
}