{
  "type": "Feature",
  "properties": {
    "gn:admin1_code":"9.0",
    "gn:asciiname":"Id Abdellah",
    "gn:country_code":"MA",
    "gn:dem":291,
    "gn:feature_class":"P",
    "gn:feature_code":"PPL",
    "gn:name":"Id Abdellah",
    "gn:population":0,
    "gn:timezone":"Africa/Casablanca",
    "iso:country":"MA",
    "wof:name":"Id Abdellah",
    "wof:placetype":"locality"
},
  "geometry": {"coordinates":[-9.77906,30.78763],"type":"Point"}
}