{
  "type": "Feature",
  "properties": {
    "gn:admin1_code":"10",
    "gn:asciiname":"Ifadadene",
    "gn:country_code":"MA",
    "gn:dem":1172,
    "gn:feature_class":"P",
    "gn:feature_code":"PPL",
    "gn:name":"Ifadadene",
    "gn:population":0,
    "gn:timezone":"Africa/Casablanca",
    "iso:country":"MA",
    "wof:name":"Ifadadene",
    "wof:placetype":"locality"
},
  "geometry": {"coordinates":[-9.62457,29.30183],"type":"Point"}
}