{
  "type": "Feature",
  "properties": {
    "gn:admin1_code":"09",
    "gn:asciiname":"Za Sidi Ouaggag",
    "gn:country_code":"MA",
    "gn:dem":100,
    "gn:feature_class":"P",
    "gn:feature_code":"PPL",
    "gn:name":"Za Sidi Ouaggag",
    "gn:population":0,
    "gn:timezone":"Africa/Casablanca",
    "iso:country":"MA",
    "name:eng_x_historical":[
        "Agulha"
    ],
    "name:eng_x_preferred":[
        "Agulha"
    ],
    "name:und_x_variant":[
        "Zaouit sidi ouagag",
        "Zaouia Sidi Ouaggag",
        "Zaouit Aglou",
        "Za Sidi Ouaggag"
    ],
    "wof:name":"Za Sidi Ouaggag",
    "wof:placetype":"locality"
},
  "geometry": {"coordinates":[-9.81063,29.78844],"type":"Point"}
}