{
  "type": "Feature",
  "properties": {
    "gn:admin1_code":"2.0",
    "gn:asciiname":"Douar Iqoubaene",
    "gn:country_code":"MA",
    "gn:dem":32,
    "gn:feature_class":"P",
    "gn:feature_code":"PPL",
    "gn:name":"Douar Iqoubaene",
    "gn:population":0,
    "gn:timezone":"Africa/Casablanca",
    "iso:country":"MA",
    "wof:name":"Douar Iqoubaene",
    "wof:placetype":"locality"
},
  "geometry": {"coordinates":[-2.66286,35.09200999999999],"type":"Point"}
}