{
  "type": "Feature",
  "properties": {
    "gn:admin1_code":"08",
    "gn:asciiname":"Tizouat",
    "gn:country_code":"MA",
    "gn:dem":1847,
    "gn:feature_class":"P",
    "gn:feature_code":"PPL",
    "gn:name":"Tizouat",
    "gn:population":0,
    "gn:timezone":"Africa/Casablanca",
    "iso:country":"MA",
    "name:und_x_variant":[
        "Tizwat",
        "A\u00eft Touzoud",
        "Tizouad",
        "Tezoued",
        "Tinzouad",
        "Tizouat"
    ],
    "wof:name":"Tizouat",
    "wof:placetype":"locality"
},
  "geometry": {"coordinates":[-7.46944,30.73623],"type":"Point"}
}