{
  "type": "Feature",
  "properties": {
    "gn:admin1_code":"9.0",
    "gn:asciiname":"Ait Ouakrim",
    "gn:country_code":"MA",
    "gn:dem":533,
    "gn:feature_class":"P",
    "gn:feature_code":"PPL",
    "gn:name":"A\u00eft Ouakrim",
    "gn:population":0,
    "gn:timezone":"Africa/Casablanca",
    "iso:country":"MA",
    "wof:name":"Ait Ouakrim",
    "wof:placetype":"locality"
},
  "geometry": {"coordinates":[-9.20053,30.10374],"type":"Point"}
}