{
  "type": "Feature",
  "properties": {
    "gn:admin1_code":"07",
    "gn:asciiname":"Oulad Snoussine",
    "gn:country_code":"MA",
    "gn:dem":583,
    "gn:feature_class":"P",
    "gn:feature_code":"PPL",
    "gn:name":"Oulad Snoussine",
    "gn:population":0,
    "gn:timezone":"Africa/Casablanca",
    "iso:country":"MA",
    "name:und_x_variant":[
        "Snousiyne",
        "Douar Snoussiyne",
        "Snoussiyne",
        "Oulad Snoussine"
    ],
    "wof:name":"Oulad Snoussine",
    "wof:placetype":"locality"
},
  "geometry": {"coordinates":[-7.49949,31.98282],"type":"Point"}
}