{
  "type": "Feature",
  "properties": {
    "gn:admin1_code":"7.0",
    "gn:asciiname":"Ibouzidane",
    "gn:country_code":"MA",
    "gn:dem":633,
    "gn:feature_class":"P",
    "gn:feature_code":"PPL",
    "gn:name":"Ibouzidane",
    "gn:population":0,
    "gn:timezone":"Africa/Casablanca",
    "iso:country":"MA",
    "wof:name":"Ibouzidane",
    "wof:placetype":"locality"
},
  "geometry": {"coordinates":[-9.52868,31.23215],"type":"Point"}
}