{
  "type": "Feature",
  "properties": {
    "gn:admin1_code":"04",
    "gn:asciiname":"Lataouna",
    "gn:country_code":"MA",
    "gn:dem":15,
    "gn:feature_class":"P",
    "gn:feature_code":"PPL",
    "gn:name":"Lataouna",
    "gn:population":0,
    "gn:timezone":"Africa/Casablanca",
    "iso:country":"MA",
    "name:und_x_variant":[
        "Al \u2018Atawna",
        "Lataouna"
    ],
    "wof:name":"Lataouna",
    "wof:placetype":"locality"
},
  "geometry": {"coordinates":[-6.07913,34.46285],"type":"Point"}
}