{
  "type": "Feature",
  "properties": {
    "gn:admin1_code":"02",
    "gn:admin2_code":"381.0",
    "gn:admin3_code":"838107053.0",
    "gn:asciiname":"Kariat Arkmane",
    "gn:country_code":"MA",
    "gn:dem":3,
    "gn:feature_class":"P",
    "gn:feature_code":"PPLA3",
    "gn:name":"Kariat Arkmane",
    "gn:population":0,
    "gn:timezone":"Africa/Casablanca",
    "iso:country":"MA",
    "name:und_x_variant":[
        "Soko el Arbaa",
        "Zoco el Arbaa",
        "El Arbaa Soko",
        "Kariat Arekmam",
        "Souk-el-Arb\u00e2a",
        "Karia Arkeman",
        "El Arba",
        "Karia-Arakmane-Afso",
        "Karia de Arkeman",
        "Kariet Arkmane",
        "Karia de Arken\u00e1n",
        "Karia da Arkeman",
        "Kariat akmane",
        "Karia d\u2019Arkemane",
        "Kariat Arkmane",
        "El Arb\u00e2a"
    ],
    "wof:name":"Kariat Arkmane",
    "wof:placetype":"locality"
},
  "geometry": {"coordinates":[-2.74693,35.1071],"type":"Point"}
}