{
  "type": "Feature",
  "properties": {
    "gn:admin1_code":"48",
    "gn:asciiname":"Hassilabied",
    "gn:country_code":"MA",
    "gn:dem":710,
    "gn:feature_class":"P",
    "gn:feature_code":"PPL",
    "gn:name":"Hassilabied",
    "gn:population":150,
    "gn:timezone":"Africa/Casablanca",
    "iso:country":"MA",
    "name:eng_x_preferred":[
        "Hassi Labied"
    ],
    "name:rus_x_preferred":[
        "\u0425\u0430\u0441\u0441\u0438\u043b\u0430\u0431\u0438\u0435\u0434"
    ],
    "wof:name":"Hassilabied",
    "wof:placetype":"locality",
    "wof:population":150
},
  "geometry": {"coordinates":[-4.02623,31.13448],"type":"Point"}
}