{
  "type": "Feature",
  "properties": {
    "gn:admin1_code":"9.0",
    "gn:asciiname":"Ighil",
    "gn:country_code":"MA",
    "gn:dem":1587,
    "gn:feature_class":"P",
    "gn:feature_code":"PPL",
    "gn:name":"Ighil",
    "gn:population":0,
    "gn:timezone":"Africa/Casablanca",
    "iso:country":"MA",
    "wof:name":"Ighil",
    "wof:placetype":"locality"
},
  "geometry": {"coordinates":[-8.82116,30.76271],"type":"Point"}
}