{
  "type": "Feature",
  "properties": {
    "gn:admin1_code":"7.0",
    "gn:asciiname":"Douar Ait Laarej",
    "gn:country_code":"MA",
    "gn:dem":444,
    "gn:feature_class":"P",
    "gn:feature_code":"PPL",
    "gn:name":"Douar Ait Laarej",
    "gn:population":0,
    "gn:timezone":"Africa/Casablanca",
    "iso:country":"MA",
    "wof:name":"Douar Ait Laarej",
    "wof:placetype":"locality"
},
  "geometry": {"coordinates":[-9.30747,31.52777],"type":"Point"}
}