{
  "type": "Feature",
  "properties": {
    "gn:admin1_code":"7.0",
    "gn:asciiname":"Wizammarn",
    "gn:country_code":"MA",
    "gn:dem":1730,
    "gn:feature_class":"P",
    "gn:feature_code":"PPL",
    "gn:name":"Wizammarn",
    "gn:population":0,
    "gn:timezone":"Africa/Casablanca",
    "iso:country":"MA",
    "wof:name":"Wizammarn",
    "wof:placetype":"locality"
},
  "geometry": {"coordinates":[-8.42752,30.90076],"type":"Point"}
}