{
  "type": "Feature",
  "properties": {
    "gn:admin1_code":"7.0",
    "gn:asciiname":"Gounaidila",
    "gn:country_code":"MA",
    "gn:dem":798,
    "gn:feature_class":"P",
    "gn:feature_code":"PPL",
    "gn:name":"Gouna\u00efdila",
    "gn:population":0,
    "gn:timezone":"Africa/Casablanca",
    "iso:country":"MA",
    "wof:name":"Gounaidila",
    "wof:placetype":"locality"
},
  "geometry": {"coordinates":[-9.19816,31.33252],"type":"Point"}
}