{
  "type": "Feature",
  "properties": {
    "gn:admin1_code":"05",
    "gn:asciiname":"Douar Tazzoumt",
    "gn:country_code":"MA",
    "gn:dem":1242,
    "gn:elevation":"0.0",
    "gn:feature_class":"P",
    "gn:feature_code":"PPL",
    "gn:name":"Douar Tazzoumt",
    "gn:population":0,
    "gn:timezone":"Africa/Casablanca",
    "iso:country":"MA",
    "wof:name":"Douar Tazzoumt",
    "wof:placetype":"locality"
},
  "geometry": {"coordinates":[-6.78155,31.75321],"type":"Point"}
}