{
  "type": "Feature",
  "properties": {
    "gn:admin1_code":"07",
    "gn:asciiname":"Oubdir",
    "gn:country_code":"MA",
    "gn:dem":896,
    "gn:feature_class":"P",
    "gn:feature_code":"PPL",
    "gn:name":"Oubdir",
    "gn:population":0,
    "gn:timezone":"Africa/Casablanca",
    "iso:country":"MA",
    "wof:name":"Oubdir",
    "wof:placetype":"locality"
},
  "geometry": {"coordinates":[-7.60206,31.4954],"type":"Point"}
}