{
  "type": "Feature",
  "properties": {
    "gn:admin1_code":"9.0",
    "gn:asciiname":"Id Ba Aissa",
    "gn:country_code":"MA",
    "gn:dem":80,
    "gn:feature_class":"P",
    "gn:feature_code":"PPL",
    "gn:name":"Id Ba Aissa",
    "gn:population":0,
    "gn:timezone":"Africa/Casablanca",
    "iso:country":"MA",
    "wof:name":"Id Ba Aissa",
    "wof:placetype":"locality"
},
  "geometry": {"coordinates":[-9.82981,30.68694],"type":"Point"}
}