{
  "type": "Feature",
  "properties": {
    "gn:admin1_code":"2.0",
    "gn:asciiname":"Oulad Loqbani Louffaqa",
    "gn:country_code":"MA",
    "gn:dem":1096,
    "gn:feature_class":"P",
    "gn:feature_code":"PPL",
    "gn:name":"Oulad Loqbani Louffaqa",
    "gn:population":0,
    "gn:timezone":"Africa/Casablanca",
    "iso:country":"MA",
    "wof:name":"Oulad Loqbani Louffaqa",
    "wof:placetype":"locality"
},
  "geometry": {"coordinates":[-1.79099,34.50019],"type":"Point"}
}