{
  "type": "Feature",
  "properties": {
    "gn:admin1_code":"09",
    "gn:asciiname":"Tanfit",
    "gn:country_code":"MA",
    "gn:dem":1142,
    "gn:feature_class":"P",
    "gn:feature_code":"PPL",
    "gn:name":"Tanfit",
    "gn:population":0,
    "gn:timezone":"Africa/Casablanca",
    "iso:country":"MA",
    "name:und_x_variant":[
        "Tinlaf",
        "Tanfist",
        "Tanfit"
    ],
    "wof:name":"Tanfit",
    "wof:placetype":"locality"
},
  "geometry": {"coordinates":[-8.14221,30.78044],"type":"Point"}
}