{
  "type": "Feature",
  "properties": {
    "gn:admin1_code":"9.0",
    "gn:asciiname":"Ait bel Aid",
    "gn:country_code":"MA",
    "gn:dem":390,
    "gn:feature_class":"P",
    "gn:feature_code":"PPL",
    "gn:name":"A\u00eft bel A\u00efd",
    "gn:population":0,
    "gn:timezone":"Africa/Casablanca",
    "iso:country":"MA",
    "wof:name":"Ait bel Aid",
    "wof:placetype":"locality"
},
  "geometry": {"coordinates":[-9.07866,30.61527],"type":"Point"}
}