{
  "type": "Feature",
  "properties": {
    "gn:admin1_code":"3.0",
    "gn:asciiname":"Kizi Legih",
    "gn:country_code":"MA",
    "gn:dem":1017,
    "gn:feature_class":"P",
    "gn:feature_code":"PPL",
    "gn:name":"Kizi Legih",
    "gn:population":0,
    "gn:timezone":"Africa/Casablanca",
    "iso:country":"MA",
    "wof:name":"Kizi Legih",
    "wof:placetype":"locality"
},
  "geometry": {"coordinates":[-4.56584,33.51416],"type":"Point"}
}