{
  "type": "Feature",
  "properties": {
    "gn:admin1_code":"3.0",
    "gn:asciiname":"Douar Zaara",
    "gn:country_code":"MA",
    "gn:dem":133,
    "gn:feature_class":"P",
    "gn:feature_code":"PPL",
    "gn:name":"Douar Zaara",
    "gn:population":0,
    "gn:timezone":"Africa/Casablanca",
    "iso:country":"MA",
    "wof:name":"Douar Zaara",
    "wof:placetype":"locality"
},
  "geometry": {"coordinates":[-5.23595,34.4267],"type":"Point"}
}