{
  "type": "Feature",
  "properties": {
    "gn:admin1_code":"07",
    "gn:asciiname":"Douar Eaeratra",
    "gn:country_code":"MA",
    "gn:dem":569,
    "gn:feature_class":"P",
    "gn:feature_code":"PPL",
    "gn:name":"Douar Eaeratra",
    "gn:population":0,
    "gn:timezone":"Africa/Casablanca",
    "iso:country":"MA",
    "name:und_x_variant":[
        "Douar Tretna",
        "Tratra",
        "Et Tratra",
        "Douar Eaeratra"
    ],
    "wof:name":"Douar Eaeratra",
    "wof:placetype":"locality"
},
  "geometry": {"coordinates":[-7.60669,31.82246],"type":"Point"}
}