{
  "type": "Feature",
  "properties": {
    "gn:admin1_code":"04",
    "gn:asciiname":"Dar es Salam",
    "gn:country_code":"MA",
    "gn:dem":113,
    "gn:feature_class":"P",
    "gn:feature_code":"PPL",
    "gn:name":"Dar es Salam",
    "gn:population":0,
    "gn:timezone":"Africa/Casablanca",
    "iso:country":"MA",
    "name:und_x_variant":[
        "Dar as Salame",
        "Dar as Salam",
        "Dar es Salam"
    ],
    "wof:name":"Dar es Salam",
    "wof:placetype":"locality"
},
  "geometry": {"coordinates":[-6.83262,33.93852],"type":"Point"}
}