{
  "type": "Feature",
  "properties": {
    "gn:admin1_code":"05",
    "gn:asciiname":"Imzayn",
    "gn:country_code":"MA",
    "gn:dem":2262,
    "gn:elevation":"0.0",
    "gn:feature_class":"P",
    "gn:feature_code":"PPL",
    "gn:name":"Imzayn",
    "gn:population":0,
    "gn:timezone":"Africa/Casablanca",
    "iso:country":"MA",
    "name:und_x_variant":[
        "Imazayn"
    ],
    "wof:name":"Imzayn",
    "wof:placetype":"locality"
},
  "geometry": {"coordinates":[-6.81412,31.52044],"type":"Point"}
}