{
  "type": "Feature",
  "properties": {
    "gn:admin1_code":"09",
    "gn:asciiname":"Tirkou",
    "gn:country_code":"MA",
    "gn:dem":485,
    "gn:feature_class":"P",
    "gn:feature_code":"PPL",
    "gn:name":"Tirkou",
    "gn:population":0,
    "gn:timezone":"Africa/Casablanca",
    "iso:country":"MA",
    "wof:name":"Tirkou",
    "wof:placetype":"locality"
},
  "geometry": {"coordinates":[-9.19556,30.63946],"type":"Point"}
}