{
  "type": "Feature",
  "properties": {
    "gn:admin1_code":"08",
    "gn:asciiname":"Ait Lahsene Ou Bouzid",
    "gn:country_code":"MA",
    "gn:dem":1429,
    "gn:feature_class":"P",
    "gn:feature_code":"PPL",
    "gn:name":"A\u00eft Lahsene Ou Bouzid",
    "gn:population":0,
    "gn:timezone":"Africa/Casablanca",
    "iso:country":"MA",
    "name:und_x_variant":[
        "A\u00eft Lhasen",
        "A\u00eft Lhassene",
        "A\u00eft Lahsene Ou Bouzid"
    ],
    "wof:name":"Ait Lahsene Ou Bouzid",
    "wof:placetype":"locality"
},
  "geometry": {"coordinates":[-6.10857,31.23381],"type":"Point"}
}