{
  "type": "Feature",
  "properties": {
    "gn:admin1_code":"03",
    "gn:asciiname":"Bab Mareklo",
    "gn:country_code":"MA",
    "gn:dem":1130,
    "gn:feature_class":"P",
    "gn:feature_code":"PPL",
    "gn:name":"Bab Mareklo",
    "gn:population":0,
    "gn:timezone":"Africa/Casablanca",
    "iso:country":"MA",
    "wof:name":"Bab Mareklo",
    "wof:placetype":"locality"
},
  "geometry": {"coordinates":[-4.78034,34.75286],"type":"Point"}
}