{
  "type": "Feature",
  "properties": {
    "gn:admin1_code":"09",
    "gn:asciiname":"Ait Ou Hssayn",
    "gn:country_code":"MA",
    "gn:dem":289,
    "gn:feature_class":"P",
    "gn:feature_code":"PPL",
    "gn:name":"Ait Ou Hssayn",
    "gn:population":0,
    "gn:timezone":"Africa/Casablanca",
    "iso:country":"MA",
    "wof:name":"Ait Ou Hssayn",
    "wof:placetype":"locality"
},
  "geometry": {"coordinates":[-9.59745,30.47017],"type":"Point"}
}