{
  "type": "Feature",
  "properties": {
    "gn:admin1_code":"1.0",
    "gn:asciiname":"Douar Abdelhamid",
    "gn:country_code":"MA",
    "gn:dem":696,
    "gn:feature_class":"P",
    "gn:feature_code":"PPL",
    "gn:name":"Douar Abdelhamid",
    "gn:population":0,
    "gn:timezone":"Africa/Casablanca",
    "iso:country":"MA",
    "wof:name":"Douar Abdelhamid",
    "wof:placetype":"locality"
},
  "geometry": {"coordinates":[-4.75592,35.16439],"type":"Point"}
}