{
  "type": "Feature",
  "properties": {
    "gn:admin1_code":"3.0",
    "gn:asciiname":"Douar Oulab Bou Taleb",
    "gn:country_code":"MA",
    "gn:dem":818,
    "gn:feature_class":"P",
    "gn:feature_code":"PPL",
    "gn:name":"Douar Oulab Bou Taleb",
    "gn:population":0,
    "gn:timezone":"Africa/Casablanca",
    "iso:country":"MA",
    "wof:name":"Douar Oulab Bou Taleb",
    "wof:placetype":"locality"
},
  "geometry": {"coordinates":[-4.35503,34.36735],"type":"Point"}
}