{
  "type": "Feature",
  "properties": {
    "gn:admin1_code":"7.0",
    "gn:asciiname":"Douar Majat",
    "gn:country_code":"MA",
    "gn:dem":348,
    "gn:feature_class":"P",
    "gn:feature_code":"PPL",
    "gn:name":"Douar Majat",
    "gn:population":0,
    "gn:timezone":"Africa/Casablanca",
    "iso:country":"MA",
    "wof:name":"Douar Majat",
    "wof:placetype":"locality"
},
  "geometry": {"coordinates":[-7.21234,32.28457],"type":"Point"}
}