{
  "type": "Feature",
  "properties": {
    "iso:country":"MA",
    "name:ara_x_preferred":[
        "\u0641\u0645 \u0632\u06ad\u064a\u062f"
    ],
    "name:cat_x_preferred":[
        "Foum Zguid"
    ],
    "name:ceb_x_preferred":[
        "Foum Zguid"
    ],
    "name:deu_x_preferred":[
        "Foum-Zguid"
    ],
    "name:eng_x_preferred":[
        "Foum Zguid"
    ],
    "name:fra_x_preferred":[
        "Foum Zguid"
    ],
    "name:nld_x_preferred":[
        "Foum Zguid"
    ],
    "name:por_x_preferred":[
        "Foum Zguid"
    ],
    "name:swe_x_preferred":[
        "Foum Zguid"
    ],
    "name:zho_x_preferred":[
        "\u5bcc\u59c6\u5bb0\u5409\u5fb7"
    ],
    "qs:gn_country":"MA",
    "qs:gn_fcode":"PPL",
    "qs:gn_pop":0,
    "qs:name":"Foum Zguid",
    "qs:name_adm0":"\u0627\u0644\u0645\u063a\u0631\u0628",
    "qs:name_adm1":"\u0643\u0644\u0645\u064a\u0645 \u0640 \u0627\u0644\u0633\u0645\u0627\u0631\u0629",
    "qs:photos":22,
    "qs:photos_1k":4,
    "qs:photos_9k":1,
    "qs:photos_9r":1,
    "qs:photos_all":22,
    "qs:photos_sr":1,
    "qs:placetype":"Town",
    "qs:pop_sr":"0",
    "qs:woe_adm0":23424893,
    "wd:wordcount":100,
    "wof:name":"Foum Zguid",
    "wof:placetype":"locality"
},
  "geometry": {"coordinates":[-6.87119,30.08792],"type":"Point"}
}