{
  "type": "Feature",
  "properties": {
    "gn:admin1_code":"7.0",
    "gn:asciiname":"Moro",
    "gn:country_code":"MA",
    "gn:dem":782,
    "gn:feature_class":"P",
    "gn:feature_code":"PPL",
    "gn:name":"Moro",
    "gn:population":0,
    "gn:timezone":"Africa/Casablanca",
    "iso:country":"MA",
    "wof:name":"Moro",
    "wof:placetype":"locality"
},
  "geometry": {"coordinates":[-7.34264,31.67781],"type":"Point"}
}