{
  "type": "Feature",
  "properties": {
    "gn:admin1_code":"9.0",
    "gn:asciiname":"Tou Janna",
    "gn:country_code":"MA",
    "gn:dem":100,
    "gn:feature_class":"P",
    "gn:feature_code":"PPL",
    "gn:name":"Tou Janna",
    "gn:population":0,
    "gn:timezone":"Africa/Casablanca",
    "iso:country":"MA",
    "wof:name":"Tou Janna",
    "wof:placetype":"locality"
},
  "geometry": {"coordinates":[-9.4474,30.19895],"type":"Point"}
}