{
  "type": "Feature",
  "properties": {
    "gn:admin1_code":"7.0",
    "gn:asciiname":"Al Foqra",
    "gn:country_code":"MA",
    "gn:dem":680,
    "gn:feature_class":"P",
    "gn:feature_code":"PPL",
    "gn:name":"Al Foqra",
    "gn:population":0,
    "gn:timezone":"Africa/Casablanca",
    "iso:country":"MA",
    "wof:name":"Al Foqra",
    "wof:placetype":"locality"
},
  "geometry": {"coordinates":[-7.06826,31.88016],"type":"Point"}
}