{
  "type": "Feature",
  "properties": {
    "gn:admin1_code":"02",
    "gn:asciiname":"Sehb",
    "gn:country_code":"MA",
    "gn:dem":36,
    "gn:feature_class":"P",
    "gn:feature_code":"PPL",
    "gn:name":"Sehb",
    "gn:population":0,
    "gn:timezone":"Africa/Casablanca",
    "iso:country":"MA",
    "wof:name":"Sehb",
    "wof:placetype":"locality"
},
  "geometry": {"coordinates":[-3.00398,35.39126],"type":"Point"}
}