{
  "type": "Feature",
  "properties": {
    "gn:admin1_code":"6.0",
    "gn:asciiname":"Dar El Haj S'id Ben 'Abbou",
    "gn:country_code":"MA",
    "gn:dem":155,
    "gn:feature_class":"P",
    "gn:feature_code":"PPL",
    "gn:name":"Dar El Haj S\u2019id Ben \u2019Abbou",
    "gn:population":0,
    "gn:timezone":"Africa/Casablanca",
    "iso:country":"MA",
    "wof:name":"Dar El Haj S'id Ben 'Abbou",
    "wof:placetype":"locality"
},
  "geometry": {"coordinates":[-8.1248,33.22922],"type":"Point"}
}