{
  "type": "Feature",
  "properties": {
    "gn:admin1_code":"5.0",
    "gn:asciiname":"Ait Ibourk",
    "gn:country_code":"MA",
    "gn:dem":1142,
    "gn:feature_class":"P",
    "gn:feature_code":"PPL",
    "gn:name":"A\u00eft Ibourk",
    "gn:population":0,
    "gn:timezone":"Africa/Casablanca",
    "iso:country":"MA",
    "wof:name":"Ait Ibourk",
    "wof:placetype":"locality"
},
  "geometry": {"coordinates":[-6.77612,31.73259],"type":"Point"}
}