{
  "type": "Feature",
  "properties": {
    "gn:admin1_code":"07",
    "gn:asciiname":"Douar Abdallah Ben Laroussi",
    "gn:country_code":"MA",
    "gn:dem":329,
    "gn:feature_class":"P",
    "gn:feature_code":"PPL",
    "gn:name":"Douar Abdallah Ben Laroussi",
    "gn:population":0,
    "gn:timezone":"Africa/Casablanca",
    "iso:country":"MA",
    "wof:name":"Douar Abdallah Ben Laroussi",
    "wof:placetype":"locality"
},
  "geometry": {"coordinates":[-8.93,31.83],"type":"Point"}
}