{
  "type": "Feature",
  "properties": {
    "gn:admin1_code":"3.0",
    "gn:asciiname":"Douar Laaouada",
    "gn:country_code":"MA",
    "gn:dem":281,
    "gn:feature_class":"P",
    "gn:feature_code":"PPL",
    "gn:name":"Douar Laaouada",
    "gn:population":0,
    "gn:timezone":"Africa/Casablanca",
    "iso:country":"MA",
    "wof:name":"Douar Laaouada",
    "wof:placetype":"locality"
},
  "geometry": {"coordinates":[-5.31382,34.30447],"type":"Point"}
}