{
  "type": "Feature",
  "properties": {
    "gn:admin1_code":"01",
    "gn:asciiname":"Douar Techar",
    "gn:country_code":"MA",
    "gn:dem":163,
    "gn:feature_class":"P",
    "gn:feature_code":"PPL",
    "gn:name":"Douar Techar",
    "gn:population":0,
    "gn:timezone":"Africa/Casablanca",
    "iso:country":"MA",
    "wof:name":"Douar Techar",
    "wof:placetype":"locality"
},
  "geometry": {"coordinates":[-5.38122,35.75972],"type":"Point"}
}