{
  "type": "Feature",
  "properties": {
    "gn:admin1_code":"02",
    "gn:asciiname":"Safsafat",
    "gn:country_code":"MA",
    "gn:dem":472,
    "gn:feature_class":"P",
    "gn:feature_code":"PPL",
    "gn:name":"Safsafat",
    "gn:population":0,
    "gn:timezone":"Africa/Casablanca",
    "iso:country":"MA",
    "name:und_x_variant":[
        "Douar Safsafat",
        "Safsafate",
        "Safsafat"
    ],
    "wof:name":"Safsafat",
    "wof:placetype":"locality"
},
  "geometry": {"coordinates":[-3.61808,34.14380999999999],"type":"Point"}
}