{
  "type": "Feature",
  "properties": {
    "gn:admin1_code":"01",
    "gn:asciiname":"Douar Guemfis",
    "gn:country_code":"MA",
    "gn:dem":920,
    "gn:feature_class":"P",
    "gn:feature_code":"PPL",
    "gn:name":"Douar Guemfis",
    "gn:population":0,
    "gn:timezone":"Africa/Casablanca",
    "iso:country":"MA",
    "name:und_x_variant":[
        "Guenfich"
    ],
    "wof:name":"Douar Guemfis",
    "wof:placetype":"locality"
},
  "geometry": {"coordinates":[-5.24425,35.36831],"type":"Point"}
}