{
  "type": "Feature",
  "properties": {
    "gn:admin1_code":"3.0",
    "gn:asciiname":"Commune Sidi Youssef Ben Ahmed",
    "gn:country_code":"MA",
    "gn:dem":838,
    "gn:feature_class":"P",
    "gn:feature_code":"PPLF",
    "gn:name":"Commune Sidi Youssef Ben Ahmed",
    "gn:population":0,
    "gn:timezone":"Africa/Casablanca",
    "iso:country":"MA",
    "wof:name":"Commune Sidi Youssef Ben Ahmed",
    "wof:placetype":"locality"
},
  "geometry": {"coordinates":[-4.79757,33.81825],"type":"Point"}
}