{
  "type": "Feature",
  "properties": {
    "gn:admin1_code":"09",
    "gn:asciiname":"Wadiz",
    "gn:country_code":"MA",
    "gn:dem":591,
    "gn:feature_class":"P",
    "gn:feature_code":"PPL",
    "gn:name":"Wadiz",
    "gn:population":0,
    "gn:timezone":"Africa/Casablanca",
    "iso:country":"MA",
    "name:und_x_variant":[
        "Odaiz",
        "Ouddiz",
        "Wadiz"
    ],
    "wof:name":"Wadiz",
    "wof:placetype":"locality"
},
  "geometry": {"coordinates":[-8.27753,30.66938],"type":"Point"}
}