{
  "type": "Feature",
  "properties": {
    "gn:admin1_code":"08",
    "gn:asciiname":"Oulad Massad",
    "gn:country_code":"MA",
    "gn:dem":820,
    "gn:feature_class":"P",
    "gn:feature_code":"PPL",
    "gn:name":"Oulad Massad",
    "gn:population":0,
    "gn:timezone":"Africa/Casablanca",
    "iso:country":"MA",
    "name:und_x_variant":[
        "Oulad Msa\u00e2d",
        "Oulad M\u2019Sad",
        "Oulad Msa\u2018ad",
        "Oulad Massad"
    ],
    "wof:name":"Oulad Massad",
    "wof:placetype":"locality"
},
  "geometry": {"coordinates":[-6.12509,30.54626],"type":"Point"}
}