{
  "type": "Feature",
  "properties": {
    "gn:admin1_code":"7.0",
    "gn:asciiname":"Dar Bidah Mohamed",
    "gn:country_code":"MA",
    "gn:dem":398,
    "gn:feature_class":"P",
    "gn:feature_code":"PPL",
    "gn:name":"Dar Bidah Mohamed",
    "gn:population":0,
    "gn:timezone":"Africa/Casablanca",
    "iso:country":"MA",
    "wof:name":"Dar Bidah Mohamed",
    "wof:placetype":"locality"
},
  "geometry": {"coordinates":[-8.40058,31.58419],"type":"Point"}
}