{
  "type": "Feature",
  "properties": {
    "gn:admin1_code":"08",
    "gn:asciiname":"Inedar",
    "gn:country_code":"MA",
    "gn:dem":1044,
    "gn:feature_class":"P",
    "gn:feature_code":"PPL",
    "gn:name":"Inedar",
    "gn:population":0,
    "gn:timezone":"Africa/Casablanca",
    "iso:country":"MA",
    "name:und_x_variant":[
        "Ihanndar",
        "Ihandar",
        "Ihamdar",
        "Inedar"
    ],
    "wof:name":"Inedar",
    "wof:placetype":"locality"
},
  "geometry": {"coordinates":[-5.01726,31.43047],"type":"Point"}
}