{
  "type": "Feature",
  "properties": {
    "gn:admin1_code":"9.0",
    "gn:asciiname":"Id Barka",
    "gn:country_code":"MA",
    "gn:dem":714,
    "gn:feature_class":"P",
    "gn:feature_code":"PPL",
    "gn:name":"Id Barka",
    "gn:population":0,
    "gn:timezone":"Africa/Casablanca",
    "iso:country":"MA",
    "wof:name":"Id Barka",
    "wof:placetype":"locality"
},
  "geometry": {"coordinates":[-9.79672,29.46209],"type":"Point"}
}