{
  "type": "Feature",
  "properties": {
    "gn:admin1_code":"9.0",
    "gn:asciiname":"Ait Abouad",
    "gn:country_code":"MA",
    "gn:dem":155,
    "gn:feature_class":"P",
    "gn:feature_code":"PPL",
    "gn:name":"A\u00eft Abouad",
    "gn:population":0,
    "gn:timezone":"Africa/Casablanca",
    "iso:country":"MA",
    "wof:name":"Ait Abouad",
    "wof:placetype":"locality"
},
  "geometry": {"coordinates":[-9.19955,30.33487],"type":"Point"}
}