{
  "type": "Feature",
  "properties": {
    "gn:admin1_code":"7.0",
    "gn:asciiname":"Oulad Kehayl",
    "gn:country_code":"MA",
    "gn:dem":544,
    "gn:feature_class":"P",
    "gn:feature_code":"PPL",
    "gn:name":"Oulad Kehayl",
    "gn:population":0,
    "gn:timezone":"Africa/Casablanca",
    "iso:country":"MA",
    "wof:name":"Oulad Kehayl",
    "wof:placetype":"locality"
},
  "geometry": {"coordinates":[-8.9079,31.98837],"type":"Point"}
}