{
  "type": "Feature",
  "properties": {
    "gn:admin1_code":"1.0",
    "gn:asciiname":"Douar Ennonayel Damoud",
    "gn:country_code":"MA",
    "gn:dem":336,
    "gn:feature_class":"P",
    "gn:feature_code":"PPL",
    "gn:name":"Douar Ennonayel Damoud",
    "gn:population":0,
    "gn:timezone":"Africa/Casablanca",
    "iso:country":"MA",
    "wof:name":"Douar Ennonayel Damoud",
    "wof:placetype":"locality"
},
  "geometry": {"coordinates":[-5.22685,34.84899],"type":"Point"}
}