{
  "type": "Feature",
  "properties": {
    "gn:admin1_code":"01",
    "gn:asciiname":"Douar Zoua",
    "gn:country_code":"MA",
    "gn:dem":197,
    "gn:feature_class":"P",
    "gn:feature_code":"PPL",
    "gn:name":"Douar Zoua",
    "gn:population":0,
    "gn:timezone":"Africa/Casablanca",
    "iso:country":"MA",
    "name:und_x_variant":[
        "Zoua"
    ],
    "wof:name":"Douar Zoua",
    "wof:placetype":"locality"
},
  "geometry": {"coordinates":[-5.83104,35.27573],"type":"Point"}
}