{
  "type": "Feature",
  "properties": {
    "gn:admin1_code":"7.0",
    "gn:asciiname":"Oukoun",
    "gn:country_code":"MA",
    "gn:dem":1525,
    "gn:feature_class":"P",
    "gn:feature_code":"PPL",
    "gn:name":"Oukoun",
    "gn:population":0,
    "gn:timezone":"Africa/Casablanca",
    "iso:country":"MA",
    "wof:name":"Oukoun",
    "wof:placetype":"locality"
},
  "geometry": {"coordinates":[-8.34421,30.91384],"type":"Point"}
}