{
  "type": "Feature",
  "properties": {
    "gn:admin1_code":"6.0",
    "gn:asciiname":"Douar Laatatra",
    "gn:country_code":"MA",
    "gn:dem":360,
    "gn:feature_class":"P",
    "gn:feature_code":"PPL",
    "gn:name":"Douar Laatatra",
    "gn:population":0,
    "gn:timezone":"Africa/Casablanca",
    "iso:country":"MA",
    "wof:name":"Douar Laatatra",
    "wof:placetype":"locality"
},
  "geometry": {"coordinates":[-6.93411,33.29972],"type":"Point"}
}