{
  "type": "Feature",
  "properties": {
    "gn:admin1_code":"7.0",
    "gn:asciiname":"Anou Amrhar",
    "gn:country_code":"MA",
    "gn:dem":861,
    "gn:feature_class":"P",
    "gn:feature_code":"PPL",
    "gn:name":"Anou Amrhar",
    "gn:population":0,
    "gn:timezone":"Africa/Casablanca",
    "iso:country":"MA",
    "wof:name":"Anou Amrhar",
    "wof:placetype":"locality"
},
  "geometry": {"coordinates":[-9.25108,31.26226],"type":"Point"}
}