{
  "type": "Feature",
  "properties": {
    "gn:admin1_code":"08",
    "gn:asciiname":"Ait Ounrhi Assamer",
    "gn:country_code":"MA",
    "gn:dem":2046,
    "gn:feature_class":"P",
    "gn:feature_code":"PPL",
    "gn:name":"A\u00eft Ounrhi Assamer",
    "gn:population":0,
    "gn:timezone":"Africa/Casablanca",
    "iso:country":"MA",
    "wof:name":"Ait Ounrhi Assamer",
    "wof:placetype":"locality"
},
  "geometry": {"coordinates":[-5.88303,31.69366],"type":"Point"}
}