{
  "type": "Feature",
  "properties": {
    "gn:admin1_code":"7.0",
    "gn:asciiname":"'Ali Ou Abrik",
    "gn:country_code":"MA",
    "gn:dem":568,
    "gn:feature_class":"P",
    "gn:feature_code":"PPL",
    "gn:name":"\u2019Ali Ou Abrik",
    "gn:population":0,
    "gn:timezone":"Africa/Casablanca",
    "iso:country":"MA",
    "wof:name":"'Ali Ou Abrik",
    "wof:placetype":"locality"
},
  "geometry": {"coordinates":[-8.46001,31.39017],"type":"Point"}
}