{
  "type": "Feature",
  "properties": {
    "gn:country":"MA",
    "gn:fcode":"ADM3",
    "gn:population":13738,
    "iso:country":"MA",
    "name:ara_x_preferred":[
        "\u0645\u0634\u0631\u0639 \u0627\u0644\u0639\u064a\u0646"
    ],
    "name:ara_x_variant":[
        "\u0633\u064a\u062f\u064a \u0623\u062d\u0645\u062f \u0623\u0648 \u0639\u0645\u0631\u0648"
    ],
    "name:ary_x_preferred":[
        "\u0633\u064a\u062f\u064a \u0623\u062d\u0645\u062f \u0623\u0648\u0639\u0645\u0631"
    ],
    "name:cat_x_preferred":[
        "Sidi Ahmed Ou Amar"
    ],
    "name:ceb_x_preferred":[
        "Sidi Ahmed Ou Amar"
    ],
    "name:eng_x_preferred":[
        "Sidi Ahmed Ou Amar"
    ],
    "name:fra_x_preferred":[
        "Sidi Ahmed Ou Amar"
    ],
    "name:fra_x_variant":[
        "Sidi Ahmed Ou Amar (CR)",
        "Sidi Ahmed Ou Amar (Commune Rurale)"
    ],
    "name:ita_x_preferred":[
        "Sidi Ahmed Ou Amar"
    ],
    "name:swe_x_preferred":[
        "Sidi Ahmed Ou Amar"
    ],
    "qs:name":"Sidi Ahmed Ou Amar",
    "qs:photos_9r":0,
    "qs:photos_sr":0,
    "qs:pop_sr":"6",
    "wd:wordcount":63,
    "wof:name":"Sidi Ahmed Ou Amar",
    "wof:placetype":"localadmin",
    "wof:population":13738
},
  "geometry": {"coordinates":[-9.12464,30.4119],"type":"Point"}
}