{
  "type": "Feature",
  "properties": {
    "gn:admin1_code":"7.0",
    "gn:asciiname":"Tabout Ait Raho",
    "gn:country_code":"MA",
    "gn:dem":1597,
    "gn:feature_class":"P",
    "gn:feature_code":"PPL",
    "gn:name":"Tabout A\u00eft Raho",
    "gn:population":0,
    "gn:timezone":"Africa/Casablanca",
    "iso:country":"MA",
    "wof:name":"Tabout Ait Raho",
    "wof:placetype":"locality"
},
  "geometry": {"coordinates":[-7.25442,31.50536],"type":"Point"}
}