{
  "type": "Feature",
  "properties": {
    "gn:admin1_code":"07",
    "gn:asciiname":"Douar Lebrinat",
    "gn:country_code":"MA",
    "gn:dem":256,
    "gn:feature_class":"P",
    "gn:feature_code":"PPL",
    "gn:name":"Douar Lebrinat",
    "gn:population":0,
    "gn:timezone":"Africa/Casablanca",
    "iso:country":"MA",
    "name:und_x_variant":[
        "Douar Brinat",
        "Brinat",
        "Douar Lebrinat"
    ],
    "wof:name":"Douar Lebrinat",
    "wof:placetype":"locality"
},
  "geometry": {"coordinates":[-9.09895,32.05316],"type":"Point"}
}