{
  "type": "Feature",
  "properties": {
    "gn:admin1_code":"02",
    "gn:asciiname":"Douar Ijattarene",
    "gn:country_code":"MA",
    "gn:dem":413,
    "gn:feature_class":"P",
    "gn:feature_code":"PPL",
    "gn:name":"Douar Ijattarene",
    "gn:population":0,
    "gn:timezone":"Africa/Casablanca",
    "iso:country":"MA",
    "wof:name":"Douar Ijattarene",
    "wof:placetype":"locality"
},
  "geometry": {"coordinates":[-3.75608,35.14969],"type":"Point"}
}