{
  "type": "Feature",
  "properties": {
    "gn:admin1_code":"08",
    "gn:asciiname":"Tazoult n'Oumradou",
    "gn:country_code":"MA",
    "gn:dem":1569,
    "gn:feature_class":"P",
    "gn:feature_code":"PPL",
    "gn:name":"Tazoult n\u2019Oumradou",
    "gn:population":0,
    "gn:timezone":"Africa/Casablanca",
    "iso:country":"MA",
    "name:und_x_variant":[
        "Tazalt nommadou",
        "Tazoult n\u2019 Oumradoua",
        "Tazoult n\u2019Oumradou"
    ],
    "wof:name":"Tazoult n'Oumradou",
    "wof:placetype":"locality"
},
  "geometry": {"coordinates":[-7.45458,31.03243],"type":"Point"}
}