{
  "type": "Feature",
  "properties": {
    "gn:admin1_code":"03",
    "gn:asciiname":"El Marsa",
    "gn:country_code":"MA",
    "gn:dem":861,
    "gn:feature_class":"P",
    "gn:feature_code":"PPL",
    "gn:name":"El Marsa",
    "gn:population":0,
    "gn:timezone":"Africa/Casablanca",
    "iso:country":"MA",
    "name:ara_x_preferred":[
        "\u0627\u0644\u0645\u0631\u0633\u0649"
    ],
    "name:fra_x_preferred":[
        "El Marsa"
    ],
    "name:ita_x_preferred":[
        "El Marsa"
    ],
    "name:ron_x_preferred":[
        "El Marsa"
    ],
    "wof:name":"El Marsa",
    "wof:placetype":"locality"
},
  "geometry": {"coordinates":[-3.7715,33.35249],"type":"Point"}
}