{
  "type": "Feature",
  "properties": {
    "gn:admin1_code":"07",
    "gn:asciiname":"Adar",
    "gn:country_code":"MA",
    "gn:dem":861,
    "gn:feature_class":"P",
    "gn:feature_code":"PPL",
    "gn:name":"Adar",
    "gn:population":0,
    "gn:timezone":"Africa/Casablanca",
    "iso:country":"MA",
    "name:ara_x_preferred":[
        "\u0622\u0630\u0627\u0631"
    ],
    "name:bel_x_preferred":[
        "\u0410\u0434\u0430\u0440"
    ],
    "name:cat_x_preferred":[
        "Adar"
    ],
    "name:ceb_x_preferred":[
        "Adar"
    ],
    "name:ces_x_preferred":[
        "Adar"
    ],
    "name:deu_x_preferred":[
        "Adar"
    ],
    "name:epo_x_preferred":[
        "Adaro"
    ],
    "name:est_x_preferred":[
        "Adar"
    ],
    "name:eus_x_preferred":[
        "Adar"
    ],
    "name:fas_x_preferred":[
        "\u0622\u0630\u0627\u0631"
    ],
    "name:fra_x_preferred":[
        "Adar"
    ],
    "name:glg_x_preferred":[
        "Adar"
    ],
    "name:heb_x_preferred":[
        "\u05d0\u05d3\u05e8"
    ],
    "name:ina_x_preferred":[
        "Adar"
    ],
    "name:ind_x_preferred":[
        "Adar"
    ],
    "name:ita_x_preferred":[
        "Adar"
    ],
    "name:lad_x_preferred":[
        "Adar"
    ],
    "name:mkd_x_preferred":[
        "\u0410\u0434\u0430\u0440"
    ],
    "name:msa_x_preferred":[
        "Adar"
    ],
    "name:nld_x_preferred":[
        "Adar"
    ],
    "name:nno_x_preferred":[
        "Ad\u00e1r"
    ],
    "name:nor_x_preferred":[
        "Ad\u00e1r"
    ],
    "name:pol_x_preferred":[
        "Adar"
    ],
    "name:por_x_preferred":[
        "Adar"
    ],
    "name:ron_x_preferred":[
        "Adar"
    ],
    "name:rus_x_preferred":[
        "\u0410\u0434\u0430\u0440"
    ],
    "name:slk_x_preferred":[
        "Adar"
    ],
    "name:spa_x_preferred":[
        "Adar"
    ],
    "name:tgl_x_preferred":[
        "Adar"
    ],
    "name:tur_x_preferred":[
        "Adar"
    ],
    "name:ukr_x_preferred":[
        "\u0410\u0434\u0430\u0440"
    ],
    "name:und_x_variant":[
        "Haddar"
    ],
    "name:yid_x_preferred":[
        "\u05d0\u05d3\u05e8"
    ],
    "name:zho_x_preferred":[
        "\u4e9a\u8fbe\u6708"
    ],
    "wof:name":"Adar",
    "wof:placetype":"locality"
},
  "geometry": {"coordinates":[-9.17515,31.30518],"type":"Point"}
}