{
  "type": "Feature",
  "properties": {
    "gn:admin1_code":"7.0",
    "gn:asciiname":"Ihoum",
    "gn:country_code":"MA",
    "gn:dem":229,
    "gn:feature_class":"P",
    "gn:feature_code":"PPL",
    "gn:name":"Ihoum",
    "gn:population":0,
    "gn:timezone":"Africa/Casablanca",
    "iso:country":"MA",
    "wof:name":"Ihoum",
    "wof:placetype":"locality"
},
  "geometry": {"coordinates":[-9.68601,31.3102],"type":"Point"}
}