{
  "type": "Feature",
  "properties": {
    "gn:admin1_code":"9.0",
    "gn:asciiname":"Sidi Al Kouch",
    "gn:country_code":"MA",
    "gn:dem":1600,
    "gn:feature_class":"P",
    "gn:feature_code":"PPL",
    "gn:name":"Sidi Al Kouch",
    "gn:population":0,
    "gn:timezone":"Africa/Casablanca",
    "iso:country":"MA",
    "wof:name":"Sidi Al Kouch",
    "wof:placetype":"locality"
},
  "geometry": {"coordinates":[-7.83871,30.71279],"type":"Point"}
}