{
  "type": "Feature",
  "properties": {
    "gn:admin1_code":"6.0",
    "gn:asciiname":"Beni Khelef",
    "gn:country_code":"MA",
    "gn:dem":357,
    "gn:feature_class":"P",
    "gn:feature_code":"PPL",
    "gn:name":"Beni Khelef",
    "gn:population":0,
    "gn:timezone":"Africa/Casablanca",
    "iso:country":"MA",
    "wof:name":"Beni Khelef",
    "wof:placetype":"locality"
},
  "geometry": {"coordinates":[-7.79767,32.81974],"type":"Point"}
}