{
  "type": "Feature",
  "properties": {
    "gn:country":"MA",
    "gn:fcode":"ADM3",
    "gn:population":7499,
    "iso:country":"MA",
    "name:ara_x_preferred":[
        "\u0632\u0645\u0631\u0627\u0646 \u0627\u0644\u0634\u0631\u0642\u064a\u0629"
    ],
    "name:ara_x_variant":[
        "\u0622\u064a\u062a \u062d\u0645\u0648"
    ],
    "name:ary_x_preferred":[
        "\u0622\u064a\u062a \u062d\u0645\u0648"
    ],
    "name:azb_x_preferred":[
        "\u0622\u06cc\u062a \u0647\u0627\u0645\u0648"
    ],
    "name:cat_x_preferred":[
        "Ait Hammou"
    ],
    "name:eng_x_preferred":[
        "Ait Hammou"
    ],
    "name:fas_x_preferred":[
        "\u0627\u06cc\u062a \u0647\u0627\u0645\u0648"
    ],
    "name:fra_x_preferred":[
        "Ait Hammou"
    ],
    "name:fra_x_variant":[
        "Ait Hammou (CR)",
        "Ait Hammou (Commune Rurale)"
    ],
    "name:heb_x_preferred":[
        "\u05d0\u05d9\u05d9\u05d8 \u05d7\u05de\u05d5"
    ],
    "name:ita_x_preferred":[
        "Ait Hammou"
    ],
    "qs:name":"Ait Hammou",
    "qs:photos_9r":0,
    "qs:photos_sr":0,
    "qs:pop_sr":"5",
    "wd:wordcount":65,
    "wof:name":"Ait Hammou",
    "wof:placetype":"localadmin",
    "wof:population":7499
},
  "geometry": {"coordinates":[-8.23118,32.21624],"type":"Point"}
}