{
  "type": "Feature",
  "properties": {
    "gn:admin1_code":"01",
    "gn:asciiname":"Mrah el Bacha",
    "gn:country_code":"MA",
    "gn:dem":13,
    "gn:feature_class":"P",
    "gn:feature_code":"PPL",
    "gn:name":"Mrah el Bacha",
    "gn:population":0,
    "gn:timezone":"Africa/Casablanca",
    "iso:country":"MA",
    "wof:name":"Mrah el Bacha",
    "wof:placetype":"locality"
},
  "geometry": {"coordinates":[-5.34048,35.72683],"type":"Point"}
}