{
  "type": "Feature",
  "properties": {
    "gn:admin1_code":"3.0",
    "gn:asciiname":"Dar Mohamed Ben Salem",
    "gn:country_code":"MA",
    "gn:dem":197,
    "gn:feature_class":"P",
    "gn:feature_code":"PPL",
    "gn:name":"Dar Mohamed Ben Salem",
    "gn:population":0,
    "gn:timezone":"Africa/Casablanca",
    "iso:country":"MA",
    "wof:name":"Dar Mohamed Ben Salem",
    "wof:placetype":"locality"
},
  "geometry": {"coordinates":[-4.95124,34.41085],"type":"Point"}
}