{
  "type": "Feature",
  "properties": {
    "gn:admin1_code":"2.0",
    "gn:asciiname":"Douar Imekhloufene",
    "gn:country_code":"MA",
    "gn:dem":423,
    "gn:feature_class":"P",
    "gn:feature_code":"PPL",
    "gn:name":"Douar Imekhloufene",
    "gn:population":0,
    "gn:timezone":"Africa/Casablanca",
    "iso:country":"MA",
    "wof:name":"Douar Imekhloufene",
    "wof:placetype":"locality"
},
  "geometry": {"coordinates":[-3.60972,35.10496],"type":"Point"}
}