{
  "type": "Feature",
  "properties": {
    "gn:admin1_code":"7.0",
    "gn:asciiname":"Ait el Khiat",
    "gn:country_code":"MA",
    "gn:dem":505,
    "gn:feature_class":"P",
    "gn:feature_code":"PPL",
    "gn:name":"A\u00eft el Khiat",
    "gn:population":0,
    "gn:timezone":"Africa/Casablanca",
    "iso:country":"MA",
    "wof:name":"Ait el Khiat",
    "wof:placetype":"locality"
},
  "geometry": {"coordinates":[-9.27728,31.47005],"type":"Point"}
}