{
  "type": "Feature",
  "properties": {
    "gn:admin1_code":"01",
    "gn:asciiname":"Douar Lakhyame",
    "gn:country_code":"MA",
    "gn:dem":259,
    "gn:feature_class":"P",
    "gn:feature_code":"PPL",
    "gn:name":"Douar Lakhyame",
    "gn:population":0,
    "gn:timezone":"Africa/Casablanca",
    "iso:country":"MA",
    "name:und_x_variant":[
        "El Khoaine"
    ],
    "wof:name":"Douar Lakhyame",
    "wof:placetype":"locality"
},
  "geometry": {"coordinates":[-5.08172,35.33924000000001],"type":"Point"}
}