{
  "type": "Feature",
  "properties": {
    "gn:gn_country":"MA",
    "gn:gn_fcode":"ADM3",
    "gn:gn_pop":3476,
    "gn:population":3200,
    "iso:country":"MA",
    "name:ara_x_preferred":[
        "\u0633\u064a\u062f\u064a \u0623\u062d\u0645\u062f \u0623\u0648 \u0645\u0648\u0633\u0649"
    ],
    "name:fra_x_preferred":[
        "Tafraout El Mouloud"
    ],
    "name:fra_x_variant":[
        "Tafraout El Mouloud (CR)",
        "Tafraout El Mouloud (Commune Rurale)"
    ],
    "qs_pg:aaroncc":"MA",
    "qs_pg:gn_country":"MA",
    "qs_pg:gn_fcode":"ADM3",
    "qs_pg:gn_pop":3476,
    "qs_pg:name":"Tafraout El Mouloud",
    "qs_pg:photos_9r":0,
    "qs_pg:photos_sr":0,
    "qs_pg:pop_sr":4,
    "qs_pg:qs_pg_placetype":"localadmin",
    "wof:name":"Tafraout El Mouloud",
    "wof:placetype":"localadmin",
    "wof:population":3200
},
  "geometry": {"coordinates":[-9.21768,29.67385],"type":"Point"}
}