{
  "type": "Feature",
  "properties": {
    "gn:admin1_code":"9.0",
    "gn:asciiname":"Tizi Ounbad",
    "gn:country_code":"MA",
    "gn:dem":881,
    "gn:feature_class":"P",
    "gn:feature_code":"PPL",
    "gn:name":"Tizi Ounbad",
    "gn:population":0,
    "gn:timezone":"Africa/Casablanca",
    "iso:country":"MA",
    "wof:name":"Tizi Ounbad",
    "wof:placetype":"locality"
},
  "geometry": {"coordinates":[-9.22063,29.7119],"type":"Point"}
}