{
  "type": "Feature",
  "properties": {
    "gn:admin1_code":"6.0",
    "gn:asciiname":"Moulay Abdellah",
    "gn:country_code":"MA",
    "gn:dem":613,
    "gn:feature_class":"P",
    "gn:feature_code":"PPL",
    "gn:name":"Moulay Abdellah",
    "gn:population":0,
    "gn:timezone":"Africa/Casablanca",
    "iso:country":"MA",
    "wof:name":"Moulay Abdellah",
    "wof:placetype":"locality"
},
  "geometry": {"coordinates":[-7.06369,33.09183],"type":"Point"}
}