{
  "type": "Feature",
  "properties": {
    "gn:admin1_code":"07",
    "gn:asciiname":"Tassila Amert",
    "gn:country_code":"MA",
    "gn:dem":722,
    "gn:feature_class":"P",
    "gn:feature_code":"PPL",
    "gn:name":"Tassila Amert",
    "gn:population":0,
    "gn:timezone":"Africa/Casablanca",
    "iso:country":"MA",
    "wof:name":"Tassila Amert",
    "wof:placetype":"locality"
},
  "geometry": {"coordinates":[-9.46302,30.99388],"type":"Point"}
}