{
  "type": "Feature",
  "properties": {
    "gn:admin1_code":"07",
    "gn:asciiname":"Imi n-Tlit",
    "gn:country_code":"MA",
    "gn:dem":550,
    "gn:feature_class":"P",
    "gn:feature_code":"PPL",
    "gn:name":"Imi n-Tlit",
    "gn:population":0,
    "gn:timezone":"Africa/Casablanca",
    "iso:country":"MA",
    "name:und_x_variant":[
        "Et Tnine",
        "Tnine Imi n\u2019Tlif",
        "Tnine",
        "Imi n\u2019Tlit",
        "Imi n-Tlit"
    ],
    "wof:name":"Imi n-Tlit",
    "wof:placetype":"locality"
},
  "geometry": {"coordinates":[-9.5458,31.21634],"type":"Point"}
}