{
  "type": "Feature",
  "properties": {
    "gn:admin1_code":"6.0",
    "gn:asciiname":"El Abarka",
    "gn:country_code":"MA",
    "gn:dem":190,
    "gn:feature_class":"P",
    "gn:feature_code":"PPL",
    "gn:name":"El Abarka",
    "gn:population":0,
    "gn:timezone":"Africa/Casablanca",
    "iso:country":"MA",
    "wof:name":"El Abarka",
    "wof:placetype":"locality"
},
  "geometry": {"coordinates":[-8.0681,32.89581],"type":"Point"}
}