{
  "type": "Feature",
  "properties": {
    "gn:admin1_code":"5.0",
    "gn:asciiname":"Ait-Ali-ou-Nacer",
    "gn:country_code":"MA",
    "gn:dem":1157,
    "gn:feature_class":"P",
    "gn:feature_code":"PPL",
    "gn:name":"A\u00eft-Ali-ou-Nacer",
    "gn:population":0,
    "gn:timezone":"Africa/Casablanca",
    "iso:country":"MA",
    "wof:name":"Ait-Ali-ou-Nacer",
    "wof:placetype":"locality"
},
  "geometry": {"coordinates":[-7.09873,31.68662],"type":"Point"}
}