{
  "type": "Feature",
  "properties": {
    "gn:admin1_code":"1.0",
    "gn:asciiname":"Douar Ihemmichene",
    "gn:country_code":"MA",
    "gn:dem":716,
    "gn:feature_class":"P",
    "gn:feature_code":"PPL",
    "gn:name":"Douar Ihemmichene",
    "gn:population":0,
    "gn:timezone":"Africa/Casablanca",
    "iso:country":"MA",
    "wof:name":"Douar Ihemmichene",
    "wof:placetype":"locality"
},
  "geometry": {"coordinates":[-3.93479,35.01868],"type":"Point"}
}