{
  "type": "Feature",
  "properties": {
    "gn:admin1_code":"09",
    "gn:asciiname":"Tazoult",
    "gn:country_code":"MA",
    "gn:dem":1032,
    "gn:feature_class":"P",
    "gn:feature_code":"PPL",
    "gn:name":"Tazoult",
    "gn:population":0,
    "gn:timezone":"Africa/Casablanca",
    "iso:country":"MA",
    "name:ara_x_preferred":[
        "\u062a\u0627\u0632\u0648\u0644\u062a"
    ],
    "name:azb_x_preferred":[
        "\u062a\u0627\u0632\u0648\u0644\u062a"
    ],
    "name:deu_x_preferred":[
        "Tazoult-Lamb\u00e8se"
    ],
    "name:fas_x_preferred":[
        "\u062a\u0627\u0632\u0648\u0644\u062a"
    ],
    "name:fra_x_preferred":[
        "Tazoult"
    ],
    "name:ita_x_preferred":[
        "Tazoult"
    ],
    "name:kab_x_preferred":[
        "Ta\u1e93ult"
    ],
    "name:msa_x_preferred":[
        "Tazoult"
    ],
    "name:por_x_preferred":[
        "Tazoult"
    ],
    "name:ron_x_preferred":[
        "Tazoult"
    ],
    "name:vie_x_preferred":[
        "Tazoult"
    ],
    "name:zho_x_preferred":[
        "\u5854\u7956\u723e\u7279"
    ],
    "wof:name":"Tazoult",
    "wof:placetype":"locality"
},
  "geometry": {"coordinates":[-8.55582,29.5556],"type":"Point"}
}