{
  "type": "Feature",
  "properties": {
    "gn:admin1_code":"08",
    "gn:asciiname":"Tazrouft",
    "gn:country_code":"MA",
    "gn:dem":1678,
    "gn:feature_class":"P",
    "gn:feature_code":"PPL",
    "gn:name":"Tazrouft",
    "gn:population":0,
    "gn:timezone":"Africa/Casablanca",
    "iso:country":"MA",
    "name:und_x_variant":[
        "Tazerouft",
        "Tazrouft"
    ],
    "wof:name":"Tazrouft",
    "wof:placetype":"locality"
},
  "geometry": {"coordinates":[-4.73041,32.44091],"type":"Point"}
}