{
  "type": "Feature",
  "properties": {
    "gn:admin1_code":"4.0",
    "gn:asciiname":"Douar Miyassa",
    "gn:country_code":"MA",
    "gn:dem":46,
    "gn:feature_class":"P",
    "gn:feature_code":"PPL",
    "gn:name":"Douar Miyassa",
    "gn:population":0,
    "gn:timezone":"Africa/Casablanca",
    "iso:country":"MA",
    "wof:name":"Douar Miyassa",
    "wof:placetype":"locality"
},
  "geometry": {"coordinates":[-5.82149,34.53324],"type":"Point"}
}