{
  "type": "Feature",
  "properties": {
    "gn:admin1_code":"6.0",
    "gn:asciiname":"Oulad Mes'oud",
    "gn:country_code":"MA",
    "gn:dem":525,
    "gn:feature_class":"P",
    "gn:feature_code":"PPL",
    "gn:name":"Oulad Mes\u2019oud",
    "gn:population":0,
    "gn:timezone":"Africa/Casablanca",
    "iso:country":"MA",
    "wof:name":"Oulad Mes'oud",
    "wof:placetype":"locality"
},
  "geometry": {"coordinates":[-7.08261,32.6208],"type":"Point"}
}