{
  "type": "Feature",
  "properties": {
    "gn:admin1_code":"02",
    "gn:asciiname":"Zenaga",
    "gn:country_code":"MA",
    "gn:dem":865,
    "gn:feature_class":"P",
    "gn:feature_code":"PPL",
    "gn:name":"Zenaga",
    "gn:population":0,
    "gn:timezone":"Africa/Casablanca",
    "iso:country":"MA",
    "name:ita_x_preferred":[
        "Zenaga"
    ],
    "name:und_x_variant":[
        "Zenag"
    ],
    "wof:name":"Zenaga",
    "wof:placetype":"locality"
},
  "geometry": {"coordinates":[-1.23628,32.09993],"type":"Point"}
}