{
  "type": "Feature",
  "properties": {
    "gn:admin1_code":"03",
    "gn:asciiname":"Douar Lehrarcha",
    "gn:country_code":"MA",
    "gn:dem":225,
    "gn:feature_class":"P",
    "gn:feature_code":"PPL",
    "gn:name":"Douar Lehrarcha",
    "gn:population":0,
    "gn:timezone":"Africa/Casablanca",
    "iso:country":"MA",
    "name:und_x_variant":[
        "Douar Lehraarcha"
    ],
    "wof:name":"Douar Lehrarcha",
    "wof:placetype":"locality"
},
  "geometry": {"coordinates":[-4.70962,34.48723],"type":"Point"}
}