{
  "type": "Feature",
  "properties": {
    "gn:country":"MA",
    "gn:fcode":"ADM3",
    "gn:population":8465,
    "iso:country":"MA",
    "name:ara_x_preferred":[
        "\u0644\u0628\u062e\u0627\u062a\u0629"
    ],
    "name:fra_x_preferred":[
        "Oulad Fennane"
    ],
    "name:fra_x_variant":[
        "Oulad Fennane (CR)",
        "Oulad Fennane (Commune Rurale)"
    ],
    "qs:name":"Oulad Fennane",
    "qs:photos_9r":0,
    "qs:photos_sr":0,
    "qs:pop_sr":"5",
    "wof:name":"Oulad Fennane",
    "wof:placetype":"localadmin",
    "wof:population":8465
},
  "geometry": {"coordinates":[-6.51435,33.09495],"type":"Point"}
}