{
  "type": "Feature",
  "properties": {
    "gn:asciiname":"Daoudiate",
    "gn:country_code":"MA",
    "gn:dem":449,
    "gn:feature_class":"P",
    "gn:feature_code":"PPL",
    "gn:name":"Daoudiate",
    "gn:population":0,
    "gn:timezone":"Africa/Casablanca",
    "iso:country":"MA",
    "wof:name":"Daoudiate",
    "wof:placetype":"locality"
},
  "geometry": {"coordinates":[-7.99487,31.64852],"type":"Point"}
}