{
  "type": "Feature",
  "properties": {
    "gn:admin1_code":"7.0",
    "gn:asciiname":"Douar Souarha",
    "gn:country_code":"MA",
    "gn:dem":429,
    "gn:feature_class":"P",
    "gn:feature_code":"PPL",
    "gn:name":"Douar Souarha",
    "gn:population":0,
    "gn:timezone":"Africa/Casablanca",
    "iso:country":"MA",
    "wof:name":"Douar Souarha",
    "wof:placetype":"locality"
},
  "geometry": {"coordinates":[-8.98743,31.93154],"type":"Point"}
}