{
  "type": "Feature",
  "properties": {
    "gn:admin1_code":"8.0",
    "gn:asciiname":"Timarggoussine",
    "gn:country_code":"MA",
    "gn:dem":1760,
    "gn:feature_class":"P",
    "gn:feature_code":"PPL",
    "gn:name":"Timarggoussine",
    "gn:population":0,
    "gn:timezone":"Africa/Casablanca",
    "iso:country":"MA",
    "wof:name":"Timarggoussine",
    "wof:placetype":"locality"
},
  "geometry": {"coordinates":[-7.26202,31.27757],"type":"Point"}
}