{
  "type": "Feature",
  "properties": {
    "gn:admin1_code":"2.0",
    "gn:asciiname":"Douar Ighanouyene",
    "gn:country_code":"MA",
    "gn:dem":875,
    "gn:feature_class":"P",
    "gn:feature_code":"PPL",
    "gn:name":"Douar Ighanouyene",
    "gn:population":0,
    "gn:timezone":"Africa/Casablanca",
    "iso:country":"MA",
    "wof:name":"Douar Ighanouyene",
    "wof:placetype":"locality"
},
  "geometry": {"coordinates":[-2.19979,34.52412],"type":"Point"}
}