{
  "type": "Feature",
  "properties": {
    "gn:country":"MA",
    "gn:fcode":"ADM3",
    "gn:population":5032,
    "iso:country":"MA",
    "name:ara_x_preferred":[
        "\u0623\u0648\u0644\u0627\u062f \u0628\u0648\u0628\u0643\u0631"
    ],
    "name:ara_x_variant":[
        "\u062a\u0627\u0632\u0627\u063a\u064a\u0646"
    ],
    "name:ary_x_preferred":[
        "\u062a\u0627\u0632\u0627\u063a\u064a\u0646"
    ],
    "name:bul_x_preferred":[
        "\u0422\u0430\u0437\u0430\u0433\u0445\u0438\u043d\u0435"
    ],
    "name:cat_x_preferred":[
        "Tazaghine"
    ],
    "name:ceb_x_preferred":[
        "Tazaghine"
    ],
    "name:eng_x_preferred":[
        "Tazaghine"
    ],
    "name:fra_x_preferred":[
        "Tazaghine"
    ],
    "name:fra_x_variant":[
        "Tazaghine (CR)",
        "Tazaghine (Commune Rurale)"
    ],
    "name:ita_x_preferred":[
        "Tazaghine"
    ],
    "name:nld_x_preferred":[
        "Tazaghine"
    ],
    "name:spa_x_preferred":[
        "Tasagu\u00edn"
    ],
    "name:swe_x_preferred":[
        "Tazaghine"
    ],
    "qs:name":"Tazaghine",
    "qs:photos_9r":0,
    "qs:photos_sr":0,
    "qs:pop_sr":"5",
    "wd:wordcount":84,
    "wof:name":"Tazaghine",
    "wof:placetype":"localadmin",
    "wof:population":5032
},
  "geometry": {"coordinates":[-3.47277,35.17497],"type":"Point"}
}