{
  "type": "Feature",
  "properties": {
    "gn:country":"MA",
    "gn:fcode":"ADM3",
    "gn:population":4014,
    "iso:country":"MA",
    "name:ara_x_preferred":[
        "\u0627\u0648\u0632\u064a\u0648\u0629"
    ],
    "name:fra_x_preferred":[
        "Sidi Abdellah Ou Sai"
    ],
    "name:fra_x_variant":[
        "Sidi Abdellah Ou Sai (CR)",
        "Sidi Abdellah Ou Sai (Commune Rurale)"
    ],
    "qs:name":"Sidi Abdellah Ou Sai",
    "qs:photos_9r":0,
    "qs:photos_sr":0,
    "qs:pop_sr":"4",
    "wof:name":"Sidi Abdellah Ou Sai",
    "wof:placetype":"localadmin",
    "wof:population":4014
},
  "geometry": {"coordinates":[-8.6926,30.80859],"type":"Point"}
}