{
  "type": "Feature",
  "properties": {
    "gn:admin1_code":"01",
    "gn:asciiname":"Iqarbassene",
    "gn:country_code":"MA",
    "gn:dem":323,
    "gn:feature_class":"P",
    "gn:feature_code":"PPL",
    "gn:name":"Iqarbassene",
    "gn:population":0,
    "gn:timezone":"Africa/Casablanca",
    "iso:country":"MA",
    "name:und_x_variant":[
        "Ehandanene"
    ],
    "wof:name":"Iqarbassene",
    "wof:placetype":"locality"
},
  "geometry": {"coordinates":[-5.20755,35.49446],"type":"Point"}
}