{
  "type": "Feature",
  "properties": {
    "gn:admin1_code":"09",
    "gn:asciiname":"Oulad Krim",
    "gn:country_code":"MA",
    "gn:dem":599,
    "gn:feature_class":"P",
    "gn:feature_code":"PPL",
    "gn:name":"Oulad Krim",
    "gn:population":0,
    "gn:timezone":"Africa/Casablanca",
    "iso:country":"MA",
    "wof:name":"Oulad Krim",
    "wof:placetype":"locality"
},
  "geometry": {"coordinates":[-8.45801,30.70361],"type":"Point"}
}