{
  "type": "Feature",
  "properties": {
    "gn:admin1_code":"1.0",
    "gn:asciiname":"Nouader Bni Ansar",
    "gn:country_code":"MA",
    "gn:dem":1194,
    "gn:feature_class":"P",
    "gn:feature_code":"PPL",
    "gn:name":"Nouader Bni Ansar",
    "gn:population":0,
    "gn:timezone":"Africa/Casablanca",
    "iso:country":"MA",
    "wof:name":"Nouader Bni Ansar",
    "wof:placetype":"locality"
},
  "geometry": {"coordinates":[-4.87473,35.0881],"type":"Point"}
}