{
  "type": "Feature",
  "properties": {
    "gn:admin1_code":"02",
    "gn:asciiname":"Oulad Snoussi",
    "gn:country_code":"MA",
    "gn:dem":523,
    "gn:feature_class":"P",
    "gn:feature_code":"PPL",
    "gn:name":"Oulad Snoussi",
    "gn:population":0,
    "gn:timezone":"Africa/Casablanca",
    "iso:country":"MA",
    "name:und_x_variant":[
        "Ouled Snoussi",
        "Oulad Senoussi",
        "Oulad Snoussi"
    ],
    "wof:name":"Oulad Snoussi",
    "wof:placetype":"locality"
},
  "geometry": {"coordinates":[-2.05531,34.79924],"type":"Point"}
}