{
  "type": "Feature",
  "properties": {
    "gn:admin1_code":"07",
    "gn:asciiname":"Zaouia Nouasser",
    "gn:country_code":"MA",
    "gn:dem":419,
    "gn:feature_class":"P",
    "gn:feature_code":"PPL",
    "gn:name":"Zaouia Nouasser",
    "gn:population":0,
    "gn:timezone":"Africa/Casablanca",
    "iso:country":"MA",
    "name:und_x_variant":[
        "Nouaceur Kebla",
        "Koudia Nouaser",
        "Zawya Nwa\u00e7er",
        "Zaouia Nouasser"
    ],
    "wof:name":"Zaouia Nouasser",
    "wof:placetype":"locality"
},
  "geometry": {"coordinates":[-8.77088,31.48556],"type":"Point"}
}