{
  "type": "Feature",
  "properties": {
    "gn:admin1_code":"1.0",
    "gn:asciiname":"Douar Chbiya",
    "gn:country_code":"MA",
    "gn:dem":194,
    "gn:feature_class":"P",
    "gn:feature_code":"PPL",
    "gn:name":"Douar Chbiya",
    "gn:population":0,
    "gn:timezone":"Africa/Casablanca",
    "iso:country":"MA",
    "wof:name":"Douar Chbiya",
    "wof:placetype":"locality"
},
  "geometry": {"coordinates":[-5.52786,35.59142999999999],"type":"Point"}
}