{
  "type": "Feature",
  "properties": {
    "gn:admin1_code":"01",
    "gn:asciiname":"Ait Handou Hias",
    "gn:country_code":"MA",
    "gn:dem":109,
    "gn:feature_class":"P",
    "gn:feature_code":"PPL",
    "gn:name":"A\u00eft Handou Hias",
    "gn:population":0,
    "gn:timezone":"Africa/Casablanca",
    "iso:country":"MA",
    "name:und_x_variant":[
        "Ait Handu Hias",
        "A\u00eft Handou Hias"
    ],
    "wof:name":"Ait Handou Hias",
    "wof:placetype":"locality"
},
  "geometry": {"coordinates":[-3.87049,35.16341],"type":"Point"}
}