{
  "type": "Feature",
  "properties": {
    "gn:country":"MA",
    "gn:fcode":"ADM3",
    "gn:pop":10445,
    "iso:country":"MA",
    "name:ara_x_preferred":[
        "\u062a\u063a\u0632\u0648\u062a \u0646\u0627\u064a\u062a \u0639\u0637\u0649"
    ],
    "name:fra_x_preferred":[
        "Tilmi"
    ],
    "name:fra_x_variant":[
        "Tilmi (CR)",
        "Tilmi (Commune Rurale)"
    ],
    "qs:name":"Tilmi",
    "qs:photos_9r":0,
    "qs:photos_sr":0,
    "qs:pop_sr":"6",
    "wd:wordcount":77,
    "wof:name":"Tilmi",
    "wof:placetype":"localadmin",
    "wof:population":10445
},
  "geometry": {"coordinates":[-5.72919,31.85202],"type":"Point"}
}