{
  "type": "Feature",
  "properties": {
    "gn:country":"MA",
    "gn:fcode":"ADM3",
    "gn:population":10445,
    "iso:country":"MA",
    "name:ara_x_preferred":[
        "\u062a\u063a\u0632\u0648\u062a \u0646\u0627\u064a\u062a \u0639\u0637\u0649"
    ],
    "name:ara_x_variant":[
        "\u062a\u064a\u0644\u0645\u064a"
    ],
    "name:ary_x_preferred":[
        "\u062a\u064a\u0644\u0645\u064a"
    ],
    "name:azb_x_preferred":[
        "\u062a\u06cc\u0644\u0645\u06cc"
    ],
    "name:bul_x_preferred":[
        "\u0422\u0438\u043b\u043c\u0438"
    ],
    "name:cat_x_preferred":[
        "Tilmi"
    ],
    "name:ceb_x_preferred":[
        "Tilmi"
    ],
    "name:deu_x_preferred":[
        "Tilmi"
    ],
    "name:eng_x_preferred":[
        "Tilmi"
    ],
    "name:fas_x_preferred":[
        "\u062a\u06cc\u0644\u0645\u06cc"
    ],
    "name:fra_x_preferred":[
        "Tilmi"
    ],
    "name:fra_x_variant":[
        "Tilmi (CR)",
        "Tilmi (Commune Rurale)"
    ],
    "name:ita_x_preferred":[
        "Tilmi"
    ],
    "name:swe_x_preferred":[
        "Tilmi"
    ],
    "qs:name":"Tilmi",
    "qs:photos_9r":0,
    "qs:photos_sr":0,
    "qs:pop_sr":"6",
    "wd:wordcount":77,
    "wof:name":"Tilmi",
    "wof:placetype":"localadmin",
    "wof:population":10445
},
  "geometry": {"coordinates":[-5.72919,31.85202],"type":"Point"}
}