{
  "type": "Feature",
  "properties": {
    "gn:admin1_code":"2.0",
    "gn:asciiname":"Douar Ennejajra",
    "gn:country_code":"MA",
    "gn:dem":105,
    "gn:feature_class":"P",
    "gn:feature_code":"PPL",
    "gn:name":"Douar Ennejajra",
    "gn:population":0,
    "gn:timezone":"Africa/Casablanca",
    "iso:country":"MA",
    "wof:name":"Douar Ennejajra",
    "wof:placetype":"locality"
},
  "geometry": {"coordinates":[-2.37173,34.93919],"type":"Point"}
}