{
  "type": "Feature",
  "properties": {
    "gn:admin1_code":"9.0",
    "gn:asciiname":"Assa-n-tawyirt",
    "gn:country_code":"MA",
    "gn:dem":1321,
    "gn:feature_class":"P",
    "gn:feature_code":"PPL",
    "gn:name":"Assa-n-tawyirt",
    "gn:population":0,
    "gn:timezone":"Africa/Casablanca",
    "iso:country":"MA",
    "wof:name":"Assa-n-tawyirt",
    "wof:placetype":"locality"
},
  "geometry": {"coordinates":[-9.16247,29.53518],"type":"Point"}
}