{
  "type": "Feature",
  "properties": {
    "gn:admin1_code":"02",
    "gn:asciiname":"Aklim",
    "gn:country_code":"MA",
    "gn:dem":102,
    "gn:feature_class":"P",
    "gn:feature_code":"PPL",
    "gn:name":"Aklim",
    "gn:population":0,
    "gn:timezone":"Africa/Casablanca",
    "iso:country":"MA",
    "wof:name":"Aklim",
    "wof:placetype":"locality"
},
  "geometry": {"coordinates":[-2.43,34.92],"type":"Point"}
}