{
  "type": "Feature",
  "properties": {
    "gn:admin1_code":"02",
    "gn:asciiname":"Aklim",
    "gn:country_code":"MA",
    "gn:dem":102,
    "gn:feature_class":"P",
    "gn:feature_code":"PPL",
    "gn:name":"Aklim",
    "gn:population":0,
    "gn:timezone":"Africa/Casablanca",
    "iso:country":"MA",
    "name:ara_x_preferred":[
        "\u0623\u0643\u0644\u064a\u0645"
    ],
    "name:azb_x_preferred":[
        "\u0627\u06a9\u0644\u0644\u06cc\u0645"
    ],
    "name:cat_x_preferred":[
        "Aklim"
    ],
    "name:ceb_x_preferred":[
        "Aklim"
    ],
    "name:fas_x_preferred":[
        "\u0627\u06a9\u0644\u0644\u06cc\u0645"
    ],
    "name:fra_x_preferred":[
        "Aklim"
    ],
    "name:nld_x_preferred":[
        "Aklim"
    ],
    "name:pol_x_preferred":[
        "Aklim"
    ],
    "name:swe_x_preferred":[
        "Aklim"
    ],
    "wof:name":"Aklim",
    "wof:placetype":"locality"
},
  "geometry": {"coordinates":[-2.43,34.92],"type":"Point"}
}