{
  "type": "Feature",
  "properties": {
    "gn:admin1_code":"09",
    "gn:asciiname":"Tamalout",
    "gn:country_code":"MA",
    "gn:dem":1267,
    "gn:feature_class":"P",
    "gn:feature_code":"PPL",
    "gn:name":"Tamalout",
    "gn:population":0,
    "gn:timezone":"Africa/Casablanca",
    "iso:country":"MA",
    "wof:name":"Tamalout",
    "wof:placetype":"locality"
},
  "geometry": {"coordinates":[-8.87497,29.54764],"type":"Point"}
}