{
  "type": "Feature",
  "properties": {
    "gn:admin1_code":"06",
    "gn:asciiname":"Douar Oulad Mbarek",
    "gn:country_code":"MA",
    "gn:dem":18,
    "gn:feature_class":"P",
    "gn:feature_code":"PPL",
    "gn:name":"Douar Oulad Mbarek",
    "gn:population":0,
    "gn:timezone":"Africa/Casablanca",
    "iso:country":"MA",
    "name:und_x_variant":[
        "Oulad Mbarek",
        "Douar Oulad Mbarek"
    ],
    "wof:name":"Douar Oulad Mbarek",
    "wof:placetype":"locality"
},
  "geometry": {"coordinates":[-8.53848,33.23061],"type":"Point"}
}