{
  "type": "Feature",
  "properties": {
    "gn:admin1_code":"01",
    "gn:asciiname":"Chtaouna",
    "gn:country_code":"MA",
    "gn:dem":449,
    "gn:feature_class":"P",
    "gn:feature_code":"PPL",
    "gn:name":"Chtaouna",
    "gn:population":0,
    "gn:timezone":"Africa/Casablanca",
    "iso:country":"MA",
    "name:und_x_variant":[
        "Staouna"
    ],
    "wof:name":"Chtaouna",
    "wof:placetype":"locality"
},
  "geometry": {"coordinates":[-5.60301,35.4715],"type":"Point"}
}