{
  "type": "Feature",
  "properties": {
    "gn:admin1_code":"04",
    "gn:asciiname":"Oulad Ziyane",
    "gn:country_code":"MA",
    "gn:dem":14,
    "gn:feature_class":"P",
    "gn:feature_code":"PPL",
    "gn:name":"Oulad Ziyane",
    "gn:population":0,
    "gn:timezone":"Africa/Casablanca",
    "iso:country":"MA",
    "name:und_x_variant":[
        "Douar Oulad Ziane",
        "Oulad Ziane",
        "Oulad Ziyane"
    ],
    "wof:name":"Oulad Ziyane",
    "wof:placetype":"locality"
},
  "geometry": {"coordinates":[-6.37412,34.55071],"type":"Point"}
}