{
  "type": "Feature",
  "properties": {
    "gn:admin1_code":"1.0",
    "gn:asciiname":"Bled Ghdira",
    "gn:country_code":"MA",
    "gn:dem":36,
    "gn:feature_class":"P",
    "gn:feature_code":"PPLL",
    "gn:name":"Bled Ghdira",
    "gn:population":0,
    "gn:timezone":"Africa/Casablanca",
    "iso:country":"MA",
    "wof:name":"Bled Ghdira",
    "wof:placetype":"neighbourhood"
},
  "geometry": {"coordinates":[-6.17782,35.14367],"type":"Point"}
}