{
  "type": "Feature",
  "properties": {
    "gn:admin1_code":"02",
    "gn:asciiname":"Ayt Ya'qoub",
    "gn:country_code":"MA",
    "gn:dem":1163,
    "gn:feature_class":"P",
    "gn:feature_code":"PPL",
    "gn:name":"Ayt Ya\u2019qoub",
    "gn:population":0,
    "gn:timezone":"Africa/Casablanca",
    "iso:country":"MA",
    "name:und_x_variant":[
        "Ayt Ya\u2019qoub",
        "A\u00eft Yakoub"
    ],
    "wof:name":"Ayt Ya'qoub",
    "wof:placetype":"locality"
},
  "geometry": {"coordinates":[-3.41561,32.39357],"type":"Point"}
}