{
  "type": "Feature",
  "properties": {
    "gn:admin1_code":"6.0",
    "gn:asciiname":"Bousroutane",
    "gn:country_code":"MA",
    "gn:dem":344,
    "gn:feature_class":"P",
    "gn:feature_code":"PPL",
    "gn:name":"Bousroutane",
    "gn:population":0,
    "gn:timezone":"Africa/Casablanca",
    "iso:country":"MA",
    "wof:name":"Bousroutane",
    "wof:placetype":"locality"
},
  "geometry": {"coordinates":[-7.77664,33.02247],"type":"Point"}
}