{
  "type": "Feature",
  "properties": {
    "gn:admin1_code":"7.0",
    "gn:asciiname":"Rbaat El Bam",
    "gn:country_code":"MA",
    "gn:dem":308,
    "gn:feature_class":"P",
    "gn:feature_code":"PPL",
    "gn:name":"Rbaat El Bam",
    "gn:population":0,
    "gn:timezone":"Africa/Casablanca",
    "iso:country":"MA",
    "wof:name":"Rbaat El Bam",
    "wof:placetype":"locality"
},
  "geometry": {"coordinates":[-8.86671,31.86634],"type":"Point"}
}