{
  "type": "Feature",
  "properties": {
    "gn:admin1_code":"07",
    "gn:asciiname":"Allous",
    "gn:country_code":"MA",
    "gn:dem":1881,
    "gn:feature_class":"P",
    "gn:feature_code":"PPL",
    "gn:name":"Allous",
    "gn:population":0,
    "gn:timezone":"Africa/Casablanca",
    "iso:country":"MA",
    "wof:name":"Allous",
    "wof:placetype":"locality"
},
  "geometry": {"coordinates":[-8.64491,30.93559],"type":"Point"}
}