{
  "type": "Feature",
  "properties": {
    "gn:admin1_code":"9.0",
    "gn:asciiname":"Ait Moulay Lahsene",
    "gn:country_code":"MA",
    "gn:dem":479,
    "gn:feature_class":"P",
    "gn:feature_code":"PPL",
    "gn:name":"A\u00eft Moulay Lahsene",
    "gn:population":0,
    "gn:timezone":"Africa/Casablanca",
    "iso:country":"MA",
    "wof:name":"Ait Moulay Lahsene",
    "wof:placetype":"locality"
},
  "geometry": {"coordinates":[-8.42652,30.60903],"type":"Point"}
}