{
  "type": "Feature",
  "properties": {
    "gn:admin1_code":"01",
    "gn:asciiname":"Hofret ez Zeitoune",
    "gn:country_code":"MA",
    "gn:dem":45,
    "gn:feature_class":"P",
    "gn:feature_code":"PPL",
    "gn:name":"Hofret ez Ze\u00eftoune",
    "gn:population":0,
    "gn:timezone":"Africa/Casablanca",
    "iso:country":"MA",
    "name:und_x_variant":[
        "Ez Ze\u00eftoune",
        "Hofret ez Ze\u00eftoune"
    ],
    "wof:name":"Hofret ez Zeitoune",
    "wof:placetype":"locality"
},
  "geometry": {"coordinates":[-5.38728,35.79858],"type":"Point"}
}