{
  "type": "Feature",
  "properties": {
    "gn:admin1_code":"7.0",
    "gn:asciiname":"Ait Oukrim",
    "gn:country_code":"MA",
    "gn:dem":654,
    "gn:feature_class":"P",
    "gn:feature_code":"PPL",
    "gn:name":"Ait Oukrim",
    "gn:population":0,
    "gn:timezone":"Africa/Casablanca",
    "iso:country":"MA",
    "wof:name":"Ait Oukrim",
    "wof:placetype":"locality"
},
  "geometry": {"coordinates":[-7.62547,31.57795],"type":"Point"}
}