{
  "type": "Feature",
  "properties": {
    "gn:admin1_code":"3.0",
    "gn:asciiname":"Douar Sidi Allal",
    "gn:country_code":"MA",
    "gn:dem":677,
    "gn:feature_class":"P",
    "gn:feature_code":"PPL",
    "gn:name":"Douar Sidi Allal",
    "gn:population":0,
    "gn:timezone":"Africa/Casablanca",
    "iso:country":"MA",
    "wof:name":"Douar Sidi Allal",
    "wof:placetype":"locality"
},
  "geometry": {"coordinates":[-5.32825,33.83412],"type":"Point"}
}