{
  "type": "Feature",
  "properties": {
    "gn:admin1_code":"9.0",
    "gn:asciiname":"Lamaasser",
    "gn:country_code":"MA",
    "gn:dem":185,
    "gn:feature_class":"P",
    "gn:feature_code":"PPL",
    "gn:name":"Lamaasser",
    "gn:population":0,
    "gn:timezone":"Africa/Casablanca",
    "iso:country":"MA",
    "name:und_x_variant":[
        "El Maasser"
    ],
    "wof:name":"Lamaasser",
    "wof:placetype":"locality"
},
  "geometry": {"coordinates":[-9.48742,30.41959],"type":"Point"}
}