{
  "type": "Feature",
  "properties": {
    "gn:gn_country":"MA",
    "gn:gn_fcode":"ADM3",
    "gn:gn_pop":352058,
    "gn:population":352058,
    "iso:country":"MA",
    "name:ara_x_preferred":[
        "\u0627\u0644\u0637\u0644\u0648\u062d"
    ],
    "name:fra_x_preferred":[
        "Kenitra"
    ],
    "name:fra_x_variant":[
        "Kenitra (MU)",
        "Kenitra (Commune Urbaine)"
    ],
    "qs_pg:aaroncc":"MA",
    "qs_pg:gn_country":"MA",
    "qs_pg:gn_fcode":"ADM3",
    "qs_pg:gn_pop":352058,
    "qs_pg:name":"Kenitra",
    "qs_pg:photos_9r":0,
    "qs_pg:photos_sr":0,
    "qs_pg:pop_sr":10,
    "qs_pg:qs_pg_placetype":"localadmin",
    "wof:name":"Kenitra",
    "wof:placetype":"localadmin",
    "wof:population":352058
},
  "geometry": {"coordinates":[-6.57719,34.26593],"type":"Point"}
}