{
  "type": "Feature",
  "properties": {
    "gn:country":"MA",
    "gn:fcode":"ADM3",
    "gn:population":352058,
    "iso:country":"MA",
    "name:ara_x_preferred":[
        "\u0627\u0644\u0637\u0644\u0648\u062d"
    ],
    "name:ara_x_variant":[
        "\u0627\u0644\u0642\u0646\u064a\u0637\u0631\u0629"
    ],
    "name:azb_x_preferred":[
        "\u0642\u0646\u06cc\u0637\u0631\u0647"
    ],
    "name:bel_x_preferred":[
        "\u041a\u0435\u043d\u0456\u0442\u0440\u0430"
    ],
    "name:cat_x_preferred":[
        "Kenitra"
    ],
    "name:ceb_x_preferred":[
        "Kenitra"
    ],
    "name:ces_x_preferred":[
        "Kenitra"
    ],
    "name:cym_x_preferred":[
        "K\u00e9nitra"
    ],
    "name:dan_x_preferred":[
        "K\u00e9nitra"
    ],
    "name:deu_x_preferred":[
        "Kenitra"
    ],
    "name:epo_x_preferred":[
        "Kenitro"
    ],
    "name:eus_x_preferred":[
        "Kenitra"
    ],
    "name:fas_x_preferred":[
        "\u0642\u0646\u06cc\u0637\u0631\u0647"
    ],
    "name:fra_x_preferred":[
        "Kenitra"
    ],
    "name:fra_x_variant":[
        "Kenitra (MU)",
        "Kenitra (Commune Urbaine)",
        "K\u00e9nitra"
    ],
    "name:heb_x_preferred":[
        "\u05d0\u05dc-\u05e7\u05e0\u05d9\u05d8\u05e8\u05d4"
    ],
    "name:hrv_x_preferred":[
        "Kenitra"
    ],
    "name:hun_x_preferred":[
        "Kenitra"
    ],
    "name:ita_x_preferred":[
        "Kenitra"
    ],
    "name:jpn_x_preferred":[
        "\u30b1\u30cb\u30c8\u30e9"
    ],
    "name:kab_x_preferred":[
        "Qni\u1e6dra"
    ],
    "name:kat_x_preferred":[
        "\u10d9\u10d4\u10dc\u10d8\u10e2\u10e0\u10d0"
    ],
    "name:kaz_x_preferred":[
        "\u041a\u0435\u043d\u0438\u0442\u0440\u0430"
    ],
    "name:kor_x_preferred":[
        "\ucf00\ub2c8\ud2b8\ub77c"
    ],
    "name:lit_x_preferred":[
        "Kenitra"
    ],
    "name:mkd_x_preferred":[
        "\u041a\u0435\u043d\u0438\u0442\u0440\u0430"
    ],
    "name:nld_x_preferred":[
        "Kenitra"
    ],
    "name:nor_x_preferred":[
        "K\u00e9nitra"
    ],
    "name:pol_x_preferred":[
        "Al-Kunajtira"
    ],
    "name:por_x_preferred":[
        "Kenitra"
    ],
    "name:ron_x_preferred":[
        "Kenitra"
    ],
    "name:rus_x_preferred":[
        "\u041a\u0435\u043d\u0438\u0442\u0440\u0430"
    ],
    "name:spa_x_preferred":[
        "Kenitra"
    ],
    "name:sqi_x_preferred":[
        "Kenitra"
    ],
    "name:swe_x_preferred":[
        "K\u00e9nitra"
    ],
    "name:ukr_x_preferred":[
        "\u041a\u0435\u043d\u0456\u0442\u0440\u0430"
    ],
    "name:uzb_x_preferred":[
        "Kenitra"
    ],
    "name:vie_x_preferred":[
        "Kenitra"
    ],
    "name:war_x_preferred":[
        "Kenitra"
    ],
    "name:zho_x_preferred":[
        "\u84cb\u5c3c\u7279\u62c9"
    ],
    "qs_pg:aaroncc":"MA",
    "qs_pg:gn_country":"MA",
    "qs_pg:gn_fcode":"ADM3",
    "qs_pg:gn_pop":352058,
    "qs_pg:name":"Kenitra",
    "qs_pg:photos_9r":0,
    "qs_pg:photos_sr":0,
    "qs_pg:pop_sr":10,
    "qs_pg:qs_pg_placetype":"localadmin",
    "wof:name":"Kenitra",
    "wof:placetype":"localadmin",
    "wof:population":352058
},
  "geometry": {"coordinates":[-6.57719,34.26593],"type":"Point"}
}