{
  "type": "Feature",
  "properties": {
    "gn:admin1_code":"05",
    "gn:asciiname":"Amzerlou",
    "gn:country_code":"MA",
    "gn:dem":2468,
    "gn:feature_class":"P",
    "gn:feature_code":"PPL",
    "gn:name":"Amzerlou",
    "gn:population":0,
    "gn:timezone":"Africa/Casablanca",
    "iso:country":"MA",
    "wof:name":"Amzerlou",
    "wof:placetype":"locality"
},
  "geometry": {"coordinates":[-5.85427,31.88929000000001],"type":"Point"}
}