{
  "type": "Feature",
  "properties": {
    "gn:country":"MA",
    "gn:fcode":"ADM3",
    "gn:population":3666,
    "iso:country":"MA",
    "name:ara_x_preferred":[
        "\u062d\u0627\u0633\u064a \u0628\u0631\u0643\u0627\u0646"
    ],
    "name:ara_x_variant":[
        "\u0628\u0648\u0634\u0641\u0627\u0639\u0629",
        "\u0623\u0648\u0644\u0627\u062f \u062f\u0627\u0648\u0648\u062f \u0627\u0632\u062e\u0627\u0646\u064a\u0646"
    ],
    "name:ary_x_preferred":[
        "\u0648\u0644\u0627\u062f \u062f\u0627\u0648\u062f \u0632\u062e\u0627\u0646\u064a\u0646"
    ],
    "name:cat_x_preferred":[
        "Oulad Daoud Zkhanine"
    ],
    "name:ceb_x_preferred":[
        "Oulad Daoud Zkhanine"
    ],
    "name:eng_x_preferred":[
        "Oulad Daoud Zkhanine"
    ],
    "name:fra_x_preferred":[
        "Oulad Daoud Zkhanine"
    ],
    "name:fra_x_variant":[
        "Oulad Daoud Zkhanine (CR)",
        "Oulad Daoud Zkhanine (Commune Rurale)",
        "Oulad Daoud",
        "Oulad Daoud (CR)",
        "Oulad Daoud (Commune Rurale)"
    ],
    "name:ita_x_preferred":[
        "Oulad Daoud Zkhanine"
    ],
    "name:por_x_preferred":[
        "Oulad Daoud Zkhanine"
    ],
    "name:spa_x_preferred":[
        "Ulad Da\u00fad"
    ],
    "name:swe_x_preferred":[
        "Oulad Daoud Zkhanine"
    ],
    "qs:name":"Oulad Daoud Zkhanine",
    "qs:photos_9r":0,
    "qs:photos_sr":0,
    "qs:pop_sr":"4",
    "wd:wordcount":58,
    "wof:name":"Oulad Daoud Zkhanine",
    "wof:placetype":"localadmin",
    "wof:population":3666
},
  "geometry": {"coordinates":[-2.60141,34.98106],"type":"Point"}
}