{
  "type": "Feature",
  "properties": {
    "gn:admin1_code":"06",
    "gn:asciiname":"Dar El Caid Mohamed",
    "gn:country_code":"MA",
    "gn:dem":418,
    "gn:feature_class":"P",
    "gn:feature_code":"PPL",
    "gn:name":"Dar El Caid Mohamed",
    "gn:population":0,
    "gn:timezone":"Africa/Casablanca",
    "iso:country":"MA",
    "name:und_x_variant":[
        "Dar Ca\u00efd Mohammed"
    ],
    "wof:name":"Dar El Caid Mohamed",
    "wof:placetype":"locality"
},
  "geometry": {"coordinates":[-7.19637,33.29153],"type":"Point"}
}