{
  "type": "Feature",
  "properties": {
    "gn:admin1_code":"09",
    "gn:asciiname":"Tirine",
    "gn:country_code":"MA",
    "gn:dem":1289,
    "gn:feature_class":"P",
    "gn:feature_code":"PPL",
    "gn:name":"Tirine",
    "gn:population":0,
    "gn:timezone":"Africa/Casablanca",
    "iso:country":"MA",
    "name:und_x_variant":[
        "Tizhine"
    ],
    "wof:name":"Tirine",
    "wof:placetype":"locality"
},
  "geometry": {"coordinates":[-8.72009,30.15085],"type":"Point"}
}