{
  "type": "Feature",
  "properties": {
    "gn:admin1_code":"07",
    "gn:asciiname":"Talkaft",
    "gn:country_code":"MA",
    "gn:dem":647,
    "gn:feature_class":"P",
    "gn:feature_code":"PPL",
    "gn:name":"Talkaft",
    "gn:population":0,
    "gn:timezone":"Africa/Casablanca",
    "iso:country":"MA",
    "name:und_x_variant":[
        "Talkeft"
    ],
    "wof:name":"Talkaft",
    "wof:placetype":"locality"
},
  "geometry": {"coordinates":[-7.77955,31.4867],"type":"Point"}
}