{
  "type": "Feature",
  "properties": {
    "gn:admin1_code":"07",
    "gn:asciiname":"Douar Chouifat",
    "gn:country_code":"MA",
    "gn:dem":102,
    "gn:feature_class":"P",
    "gn:feature_code":"PPL",
    "gn:name":"Douar Chouifat",
    "gn:population":0,
    "gn:timezone":"Africa/Casablanca",
    "iso:country":"MA",
    "name:und_x_variant":[
        "Achouifat",
        "Douar Haoussine Ben Chleuh",
        "Chouifat",
        "Douar Chouifat"
    ],
    "wof:name":"Douar Chouifat",
    "wof:placetype":"locality"
},
  "geometry": {"coordinates":[-9.19001,31.8392],"type":"Point"}
}