{
  "type": "Feature",
  "properties": {
    "gn:admin1_code":"07",
    "gn:asciiname":"Tigdit",
    "gn:country_code":"MA",
    "gn:dem":218,
    "gn:feature_class":"P",
    "gn:feature_code":"PPL",
    "gn:name":"Tigdit",
    "gn:population":0,
    "gn:timezone":"Africa/Casablanca",
    "iso:country":"MA",
    "name:und_x_variant":[
        "Tigdif"
    ],
    "wof:name":"Tigdit",
    "wof:placetype":"locality"
},
  "geometry": {"coordinates":[-9.76228,31.19574],"type":"Point"}
}