{
  "type": "Feature",
  "properties": {
    "gn:country":"MA",
    "gn:fcode":"ADM3",
    "gn:pop":39593,
    "iso:country":"MA",
    "name:ara_x_preferred":[
        "\u0644\u0628\u064a\u0631 \u0627\u0644\u062c\u062f\u064a\u062f (\u0627\u0644\u0628\u0644\u062f\u064a\u0629)"
    ],
    "name:fra_x_preferred":[
        "Sidi Bennour"
    ],
    "name:fra_x_variant":[
        "Sidi Bennour (MU)",
        "Sidi Bennour (Commune Urbaine)"
    ],
    "qs:name":"Sidi Bennour",
    "qs:photos_9r":0,
    "qs:photos_sr":0,
    "qs:pop_sr":"7",
    "wd:wordcount":207,
    "wof:name":"Sidi Bennour",
    "wof:placetype":"localadmin",
    "wof:population":39593
},
  "geometry": {"coordinates":[-8.42819,32.66136],"type":"Point"}
}