{
  "type": "Feature",
  "properties": {
    "gn:country":"MA",
    "gn:fcode":"ADM3",
    "gn:pop":39593,
    "iso:country":"MA",
    "name:ara_x_preferred":[
        "\u0644\u0628\u064a\u0631 \u0627\u0644\u062c\u062f\u064a\u062f (\u0627\u0644\u0628\u0644\u062f\u064a\u0629)"
    ],
    "name:ara_x_variant":[
        "\u0633\u064a\u062f\u064a \u0628\u0646\u0648\u0631"
    ],
    "name:azb_x_preferred":[
        "\u0633\u06cc\u062f\u06cc \u0628\u0646\u0648\u0631"
    ],
    "name:cat_x_preferred":[
        "Sidi Bennour"
    ],
    "name:ceb_x_preferred":[
        "Sidi Bennour"
    ],
    "name:cym_x_preferred":[
        "Sidi Bennour"
    ],
    "name:deu_x_preferred":[
        "Sidi Bennour"
    ],
    "name:eng_x_preferred":[
        "Sidi Bennour"
    ],
    "name:fas_x_preferred":[
        "\u0633\u06cc\u062f\u06cc \u0628\u0646\u0648\u0631"
    ],
    "name:fra_x_preferred":[
        "Sidi Bennour"
    ],
    "name:fra_x_variant":[
        "Sidi Bennour (MU)",
        "Sidi Bennour (Commune Urbaine)"
    ],
    "name:ita_x_preferred":[
        "Sidi Bennour"
    ],
    "name:jpn_x_preferred":[
        "\u30b7\u30c7\u30a3\u30fb\u30d9\u30cc\u30fc\u30eb"
    ],
    "name:nld_x_preferred":[
        "Sidi Bennour"
    ],
    "name:por_x_preferred":[
        "Sidi Bennour"
    ],
    "name:rus_x_preferred":[
        "\u0421\u0438\u0434\u0438-\u0411\u0435\u043d\u043d\u0443\u0440"
    ],
    "name:spa_x_preferred":[
        "Sidi Bennour"
    ],
    "name:swe_x_preferred":[
        "Sidi Bennour"
    ],
    "name:urd_x_preferred":[
        "\u0633\u06cc\u062f\u06cc \u0628\u0646\u0648\u0631"
    ],
    "name:zho_x_preferred":[
        "\u897f\u8fea\u672c\u52aa\u723e"
    ],
    "qs:name":"Sidi Bennour",
    "qs:photos_9r":0,
    "qs:photos_sr":0,
    "qs:pop_sr":"7",
    "wd:wordcount":207,
    "wof:name":"Sidi Bennour",
    "wof:placetype":"localadmin",
    "wof:population":39593
},
  "geometry": {"coordinates":[-8.42819,32.66136],"type":"Point"}
}