{
  "type": "Feature",
  "properties": {
    "gn:country":"MA",
    "gn:fcode":"ADM3",
    "gn:population":39593,
    "iso:country":"MA",
    "name:ara_x_preferred":[
        "\u0644\u0628\u064a\u0631 \u0627\u0644\u062c\u062f\u064a\u062f (\u0627\u0644\u0628\u0644\u062f\u064a\u0629)"
    ],
    "name:ara_x_variant":[
        "\u0633\u064a\u062f\u064a \u0628\u0646\u0648\u0631"
    ],
    "name:ary_x_preferred":[
        "\u0633\u064a\u062f\u064a \u0628\u0646\u0648\u0631"
    ],
    "name:arz_x_preferred":[
        "\u0633\u064a\u062f\u0649 \u0628\u0646\u0648\u0631"
    ],
    "name:ast_x_preferred":[
        "Sidi Bennour"
    ],
    "name:azb_x_preferred":[
        "\u0633\u06cc\u062f\u06cc \u0628\u0646\u0648\u0631"
    ],
    "name:azb_x_variant":[
        "Sidi Bennour"
    ],
    "name:bel_x_preferred":[
        "\u0421\u0456\u0434\u0437\u0456-\u0411\u0435\u043d\u0443\u0440"
    ],
    "name:cat_x_preferred":[
        "Sidi Bennour"
    ],
    "name:ceb_x_preferred":[
        "Sidi Bennour"
    ],
    "name:cym_x_preferred":[
        "Sidi Bennour"
    ],
    "name:deu_x_preferred":[
        "Sidi Bennour"
    ],
    "name:ell_x_preferred":[
        "\u03a3\u03af\u03bd\u03c4\u03b9 \u039c\u03c0\u03b5\u03bd\u03bf\u03cd\u03c1"
    ],
    "name:eng_x_preferred":[
        "Sidi Bennour"
    ],
    "name:eng_x_variant":[
        "el jadida"
    ],
    "name:fas_x_preferred":[
        "\u0633\u06cc\u062f\u06cc \u0628\u0646\u0648\u0631"
    ],
    "name:fra_x_preferred":[
        "Sidi Bennour"
    ],
    "name:fra_x_variant":[
        "Sidi Bennour (MU)",
        "Sidi Bennour (Commune Urbaine)"
    ],
    "name:gle_x_preferred":[
        "Sidi Bennour"
    ],
    "name:heb_x_preferred":[
        "\u05e1\u05d9\u05d3\u05d9 \u05d1\u05e0\u05d5\u05e8"
    ],
    "name:ita_x_preferred":[
        "Sidi Bennour"
    ],
    "name:jpn_x_preferred":[
        "\u30b7\u30c7\u30a3\u30fb\u30d9\u30cc\u30fc\u30eb"
    ],
    "name:jpn_x_variant":[
        "\u30b7\u30c7\u30a3 \u30d9\u30ce\u30fc\u30eb"
    ],
    "name:mlt_x_preferred":[
        "Sidi Bennour"
    ],
    "name:msa_x_preferred":[
        "Sidi Bennour"
    ],
    "name:nan_x_preferred":[
        "Sidi Bennour"
    ],
    "name:nld_x_preferred":[
        "Sidi Bennour"
    ],
    "name:nob_x_preferred":[
        "Sidi Bennour"
    ],
    "name:por_x_preferred":[
        "Sidi Bennour"
    ],
    "name:rus_x_preferred":[
        "\u0421\u0438\u0434\u0438-\u0411\u0435\u043d\u043d\u0443\u0440"
    ],
    "name:rus_x_variant":[
        "\u0421\u0438\u0434\u0438 \u0411\u0435\u043d\u043d\u0443\u0440"
    ],
    "name:shi_x_preferred":[
        "Sidi Bnnur"
    ],
    "name:spa_x_preferred":[
        "Sidi Bennour"
    ],
    "name:swe_x_preferred":[
        "Sidi Bennour"
    ],
    "name:urd_x_preferred":[
        "\u0633\u06cc\u062f\u06cc \u0628\u0646\u0648\u0631"
    ],
    "name:vec_x_preferred":[
        "Sidi Bennour"
    ],
    "name:zho_x_preferred":[
        "\u897f\u8fea\u672c\u52aa\u723e"
    ],
    "name:zho_x_variant":[
        "\u897f\u8fea \u672c\u52aa\u5c14"
    ],
    "qs:name":"Sidi Bennour",
    "qs:photos_9r":0,
    "qs:photos_sr":0,
    "qs:pop_sr":"7",
    "wd:wordcount":207,
    "wof:name":"Sidi Bennour",
    "wof:placetype":"localadmin",
    "wof:population":39593
},
  "geometry": {"coordinates":[-8.42819,32.66136],"type":"Point"}
}