{
  "type": "Feature",
  "properties": {
    "gn:admin1_code":"08",
    "gn:asciiname":"Azdal",
    "gn:country_code":"MA",
    "gn:dem":1871,
    "gn:feature_class":"P",
    "gn:feature_code":"PPL",
    "gn:name":"Azdal",
    "gn:population":0,
    "gn:timezone":"Africa/Casablanca",
    "iso:country":"MA",
    "name:und_x_variant":[
        "Azel",
        "Azdel",
        "Azdal"
    ],
    "wof:name":"Azdal",
    "wof:placetype":"locality"
},
  "geometry": {"coordinates":[-6.60205,31.31535],"type":"Point"}
}