{
  "type": "Feature",
  "properties": {
    "gn:admin1_code":"05",
    "gn:asciiname":"Awinat",
    "gn:country_code":"MA",
    "gn:dem":918,
    "gn:feature_class":"P",
    "gn:feature_code":"PPL",
    "gn:name":"Awinat",
    "gn:population":0,
    "gn:timezone":"Africa/Casablanca",
    "iso:country":"MA",
    "name:und_x_variant":[
        "Aouinat"
    ],
    "wof:name":"Awinat",
    "wof:placetype":"locality"
},
  "geometry": {"coordinates":[-6.02909,33.1846],"type":"Point"}
}