{
  "type": "Feature",
  "properties": {
    "gn:admin1_code":"01",
    "gn:asciiname":"Tamoukoutz",
    "gn:country_code":"MA",
    "gn:dem":902,
    "gn:feature_class":"P",
    "gn:feature_code":"PPL",
    "gn:name":"Tamoukoutz",
    "gn:population":0,
    "gn:timezone":"Africa/Casablanca",
    "iso:country":"MA",
    "name:und_x_variant":[
        "Tamaccut",
        "Tamkout",
        "Tamoukoutz"
    ],
    "wof:name":"Tamoukoutz",
    "wof:placetype":"locality"
},
  "geometry": {"coordinates":[-5.19902,34.95922],"type":"Point"}
}