{
  "type": "Feature",
  "properties": {
    "gn:country":"MA",
    "gn:fcode":"ADM3",
    "gn:population":69640,
    "iso:country":"MA",
    "name:ara_x_preferred":[
        "\u0623\u064a\u062a \u0627\u064a\u0634\u0648"
    ],
    "name:fra_x_preferred":[
        "Tiflet"
    ],
    "name:fra_x_variant":[
        "Tiflet (MU)",
        "Tiflet (Commune Urbaine)"
    ],
    "qs_pg:aaroncc":"MA",
    "qs_pg:gn_country":"MA",
    "qs_pg:gn_fcode":"ADM3",
    "qs_pg:gn_pop":69640,
    "qs_pg:name":"Tiflet",
    "qs_pg:photos_9r":0,
    "qs_pg:photos_sr":0,
    "qs_pg:pop_sr":8,
    "qs_pg:qs_pg_placetype":"localadmin",
    "wof:name":"Tiflet",
    "wof:placetype":"localadmin",
    "wof:population":69640
},
  "geometry": {"coordinates":[-6.31519,33.89517],"type":"Point"}
}