{
  "type": "Feature",
  "properties": {
    "gn:admin1_code":"10.0",
    "gn:asciiname":"Oubir",
    "gn:country_code":"MA",
    "gn:dem":807,
    "gn:feature_class":"P",
    "gn:feature_code":"PPL",
    "gn:name":"Oubir",
    "gn:population":0,
    "gn:timezone":"Africa/Casablanca",
    "iso:country":"MA",
    "wof:name":"Oubir",
    "wof:placetype":"locality"
},
  "geometry": {"coordinates":[-9.87269,29.35735],"type":"Point"}
}