{
  "type": "Feature",
  "properties": {
    "gn:admin1_code":"5.0",
    "gn:asciiname":"Agard",
    "gn:country_code":"MA",
    "gn:dem":2307,
    "gn:feature_class":"P",
    "gn:feature_code":"PPL",
    "gn:name":"Agard",
    "gn:population":0,
    "gn:timezone":"Africa/Casablanca",
    "iso:country":"MA",
    "name:fra_x_preferred":[
        "Agard"
    ],
    "wof:name":"Agard",
    "wof:placetype":"locality"
},
  "geometry": {"coordinates":[-6.57621,31.56651],"type":"Point"}
}