{
  "type": "Feature",
  "properties": {
    "gn:admin1_code":"2.0",
    "gn:asciiname":"Douar Ouaouzart",
    "gn:country_code":"MA",
    "gn:dem":1007,
    "gn:feature_class":"P",
    "gn:feature_code":"PPL",
    "gn:name":"Douar Ouaouzart",
    "gn:population":0,
    "gn:timezone":"Africa/Casablanca",
    "iso:country":"MA",
    "wof:name":"Douar Ouaouzart",
    "wof:placetype":"locality"
},
  "geometry": {"coordinates":[-3.7143,35.0096],"type":"Point"}
}