{
  "type": "Feature",
  "properties": {
    "gn:gn_country":"MA",
    "gn:gn_fcode":"PPLA3",
    "gn:gn_pop":187708,
    "gn:population":187708,
    "iso:country":"MA",
    "name:ara_x_preferred":[
        "\u0627\u0644\u0647\u0631\u0627\u0648\u064a\u064a\u0646"
    ],
    "name:ara_x_variant":[
        "\u0627\u0644\u0645\u062d\u0645\u062f\u064a\u0629"
    ],
    "name:azb_x_preferred":[
        "\u0645\u062d\u0645\u062f\u06cc\u0647"
    ],
    "name:aze_x_preferred":[
        "M\u0259h\u0259mm\u0259diyy\u0259"
    ],
    "name:cat_x_preferred":[
        "Mohammedia"
    ],
    "name:ceb_x_preferred":[
        "Mohammedia"
    ],
    "name:cym_x_preferred":[
        "Mohamm\u00e9dia"
    ],
    "name:dan_x_preferred":[
        "Mohamm\u00e9dia"
    ],
    "name:deu_x_preferred":[
        "Mohammedia"
    ],
    "name:epo_x_preferred":[
        "Mohamedio"
    ],
    "name:eus_x_preferred":[
        "Mohammedia"
    ],
    "name:fas_x_preferred":[
        "\u0645\u062d\u0645\u062f\u06cc\u0647"
    ],
    "name:fin_x_preferred":[
        "Mohammedia"
    ],
    "name:fra_x_preferred":[
        "Mohamm\u00e9dia"
    ],
    "name:ind_x_preferred":[
        "Mohammedia"
    ],
    "name:ita_x_preferred":[
        "Mohammedia"
    ],
    "name:kab_x_preferred":[
        "Mu\u1e25emmedeyya"
    ],
    "name:kor_x_preferred":[
        "\ubaa8\ud558\uba54\ub514\uc544"
    ],
    "name:lit_x_preferred":[
        "Mohamedija"
    ],
    "name:nld_x_preferred":[
        "Mohammedia"
    ],
    "name:nor_x_preferred":[
        "Mohammedia"
    ],
    "name:pol_x_preferred":[
        "Al-Muhammadijja"
    ],
    "name:por_x_preferred":[
        "Mohammedia"
    ],
    "name:ron_x_preferred":[
        "Mohammedia"
    ],
    "name:rus_x_preferred":[
        "\u041c\u043e\u0445\u0430\u043c\u043c\u0435\u0434\u0438\u044f"
    ],
    "name:sco_x_preferred":[
        "Mohammedia"
    ],
    "name:sqi_x_preferred":[
        "Mohammedia"
    ],
    "name:swe_x_preferred":[
        "Mohammedia"
    ],
    "name:tur_x_preferred":[
        "Muhammediye"
    ],
    "name:unk_x_variant":[
        "Fedhala"
    ],
    "name:urd_x_preferred":[
        "\u0645\u062d\u0645\u062f\u06cc\u06c1"
    ],
    "name:zho_x_preferred":[
        "\u7a46\u7f55\u9ed8\u8fea\u8036"
    ],
    "qs_pg:aaroncc":"MA",
    "qs_pg:gn_country":"MA",
    "qs_pg:gn_fcode":"PPLA3",
    "qs_pg:gn_pop":187708,
    "qs_pg:name":"Mohammedia",
    "qs_pg:photos_9r":0,
    "qs_pg:photos_sr":0,
    "qs_pg:pop_sr":9,
    "qs_pg:qs_pg_placetype":"locality",
    "wof:name":"Mohammedia",
    "wof:placetype":"locality",
    "wof:population":187708
},
  "geometry": {"coordinates":[-7.38298,33.68607],"type":"Point"}
}