{
  "type": "Feature",
  "properties": {
    "gn:admin1_code":"01",
    "gn:asciiname":"Cherouta",
    "gn:country_code":"MA",
    "gn:dem":560,
    "gn:feature_class":"P",
    "gn:feature_code":"PPL",
    "gn:name":"Cherouta",
    "gn:population":0,
    "gn:timezone":"Africa/Casablanca",
    "iso:country":"MA",
    "wof:name":"Cherouta",
    "wof:placetype":"locality"
},
  "geometry": {"coordinates":[-5.32944,35.27202],"type":"Point"}
}