{
  "type": "Feature",
  "properties": {
    "gn:admin1_code":"1.0",
    "gn:asciiname":"Houmat Mae Izidi",
    "gn:country_code":"MA",
    "gn:dem":1257,
    "gn:feature_class":"P",
    "gn:feature_code":"PPL",
    "gn:name":"Houmat Mae Izidi",
    "gn:population":0,
    "gn:timezone":"Africa/Casablanca",
    "iso:country":"MA",
    "wof:name":"Houmat Mae Izidi",
    "wof:placetype":"locality"
},
  "geometry": {"coordinates":[-5.02079,35.03566],"type":"Point"}
}