{
  "type": "Feature",
  "properties": {
    "gn:admin1_code":"02",
    "gn:asciiname":"Douar Errabda",
    "gn:country_code":"MA",
    "gn:dem":18,
    "gn:feature_class":"P",
    "gn:feature_code":"PPL",
    "gn:name":"Douar Errabda",
    "gn:population":0,
    "gn:timezone":"Africa/Casablanca",
    "iso:country":"MA",
    "wof:name":"Douar Errabda",
    "wof:placetype":"locality"
},
  "geometry": {"coordinates":[-3.76316,35.23911],"type":"Point"}
}