{
  "type": "Feature",
  "properties": {
    "gn:admin1_code":"08",
    "gn:asciiname":"Taourirt n'Ait Arji",
    "gn:country_code":"MA",
    "gn:dem":1428,
    "gn:feature_class":"P",
    "gn:feature_code":"PPL",
    "gn:name":"Taourirt n\u2019A\u00eft Arji",
    "gn:population":0,
    "gn:timezone":"Africa/Casablanca",
    "iso:country":"MA",
    "wof:name":"Taourirt n'Ait Arji",
    "wof:placetype":"locality"
},
  "geometry": {"coordinates":[-5.41,31.64],"type":"Point"}
}