{
  "type": "Feature",
  "properties": {
    "gn:country":"MA",
    "gn:fcode":"ADM3",
    "gn:population":15151,
    "iso:country":"MA",
    "name:ara_x_preferred":[
        "\u0645\u062c\u0627\u0637"
    ],
    "name:ara_x_variant":[
        "\u0623\u0645\u0632\u0648\u0636\u0629"
    ],
    "name:cat_x_preferred":[
        "M'Zouda"
    ],
    "name:eng_x_preferred":[
        "M'Zouda"
    ],
    "name:fra_x_preferred":[
        "M Zouda"
    ],
    "name:fra_x_variant":[
        "M Zouda (CR)",
        "M Zouda (Commune Rurale)"
    ],
    "name:ita_x_preferred":[
        "M'Zouda"
    ],
    "name:urd_x_preferred":[
        "\u0645'\u0632\u0648\u062f\u0627"
    ],
    "qs:name":"M Zouda",
    "qs:photos_9r":0,
    "qs:photos_sr":0,
    "qs:pop_sr":"6",
    "wd:wordcount":60,
    "wof:name":"M Zouda",
    "wof:placetype":"localadmin",
    "wof:population":15151
},
  "geometry": {"coordinates":[-8.55443,31.23549],"type":"Point"}
}