{
  "type": "Feature",
  "properties": {
    "gn:admin1_code":"08",
    "gn:asciiname":"Taferghoust",
    "gn:country_code":"MA",
    "gn:dem":1190,
    "gn:feature_class":"P",
    "gn:feature_code":"PPL",
    "gn:name":"Taferghoust",
    "gn:population":0,
    "gn:timezone":"Africa/Casablanca",
    "iso:country":"MA",
    "name:und_x_variant":[
        "Tafergoust",
        "Taferghoust"
    ],
    "wof:name":"Taferghoust",
    "wof:placetype":"locality"
},
  "geometry": {"coordinates":[-6.80566,31.02689],"type":"Point"}
}