{
  "type": "Feature",
  "properties": {
    "gn:admin1_code":"02",
    "gn:asciiname":"Douar Tajjakhet",
    "gn:country_code":"MA",
    "gn:dem":29,
    "gn:feature_class":"P",
    "gn:feature_code":"PPL",
    "gn:name":"Douar Tajjakhet",
    "gn:population":0,
    "gn:timezone":"Africa/Casablanca",
    "iso:country":"MA",
    "wof:name":"Douar Tajjakhet",
    "wof:placetype":"locality"
},
  "geometry": {"coordinates":[-3.804,35.16064],"type":"Point"}
}