{
  "type": "Feature",
  "properties": {
    "gn:admin1_code":"04",
    "gn:asciiname":"Bou Hzitat Tirs",
    "gn:country_code":"MA",
    "gn:dem":89,
    "gn:feature_class":"P",
    "gn:feature_code":"PPL",
    "gn:name":"Bou Hzitat Tirs",
    "gn:population":0,
    "gn:timezone":"Africa/Casablanca",
    "iso:country":"MA",
    "name:und_x_variant":[
        "Ben Zitat et Tirs",
        "Ouled Ben Sbar Tarss",
        "Douar Ben Zitat et Tirs",
        "Bou Hzitat Tirs"
    ],
    "wof:name":"Bou Hzitat Tirs",
    "wof:placetype":"locality"
},
  "geometry": {"coordinates":[-5.93629,34.66970999999999],"type":"Point"}
}