{
  "type": "Feature",
  "properties": {
    "gn:admin1_code":"01",
    "gn:asciiname":"Rouiyef",
    "gn:country_code":"MA",
    "gn:dem":168,
    "gn:feature_class":"P",
    "gn:feature_code":"PPL",
    "gn:name":"Rouiyef",
    "gn:population":0,
    "gn:timezone":"Africa/Casablanca",
    "iso:country":"MA",
    "name:und_x_variant":[
        "Rauif",
        "Roulef",
        "Ruief",
        "Er Rouief",
        "Rouiyef"
    ],
    "wof:name":"Rouiyef",
    "wof:placetype":"locality"
},
  "geometry": {"coordinates":[-5.78961,35.61874],"type":"Point"}
}