{
  "type": "Feature",
  "properties": {
    "gn:admin1_code":"9.0",
    "gn:asciiname":"Awriyr",
    "gn:country_code":"MA",
    "gn:dem":652,
    "gn:feature_class":"P",
    "gn:feature_code":"PPL",
    "gn:name":"Awriyr",
    "gn:population":0,
    "gn:timezone":"Africa/Casablanca",
    "iso:country":"MA",
    "wof:name":"Awriyr",
    "wof:placetype":"locality"
},
  "geometry": {"coordinates":[-9.23967,29.84902],"type":"Point"}
}