{
  "type": "Feature",
  "properties": {
    "gn:admin1_code":"7.0",
    "gn:asciiname":"Dar El Haj Hassan",
    "gn:country_code":"MA",
    "gn:dem":539,
    "gn:feature_class":"P",
    "gn:feature_code":"PPL",
    "gn:name":"Dar El Haj Hassan",
    "gn:population":0,
    "gn:timezone":"Africa/Casablanca",
    "iso:country":"MA",
    "wof:name":"Dar El Haj Hassan",
    "wof:placetype":"locality"
},
  "geometry": {"coordinates":[-7.80501,31.56486],"type":"Point"}
}