{
  "type": "Feature",
  "properties": {
    "gn:admin1_code":"06",
    "gn:asciiname":"Oulad S'aidane",
    "gn:country_code":"MA",
    "gn:dem":407,
    "gn:feature_class":"P",
    "gn:feature_code":"PPL",
    "gn:name":"Oulad S\u2019a\u00efdane",
    "gn:population":0,
    "gn:timezone":"Africa/Casablanca",
    "iso:country":"MA",
    "name:und_x_variant":[
        "Oulad S\u2019a\u00efdane",
        "Oulad Saadane"
    ],
    "wof:name":"Oulad S'aidane",
    "wof:placetype":"locality"
},
  "geometry": {"coordinates":[-7.59943,32.65309],"type":"Point"}
}