{
  "type": "Feature",
  "properties": {
    "gn:admin1_code":"02",
    "gn:asciiname":"Touissite",
    "gn:country_code":"MA",
    "gn:dem":1124,
    "gn:feature_class":"P",
    "gn:feature_code":"PPL",
    "gn:name":"Touissite",
    "gn:population":0,
    "gn:timezone":"Africa/Casablanca",
    "iso:country":"MA",
    "name:ara_x_preferred":[
        "\u062a\u0648\u064a\u0633\u064a\u062a"
    ],
    "name:azb_x_preferred":[
        "\u062a\u0648\u06cc\u0633\u06cc\u062a"
    ],
    "name:cat_x_preferred":[
        "Touissit"
    ],
    "name:ceb_x_preferred":[
        "Touissit"
    ],
    "name:fas_x_preferred":[
        "\u062a\u0648\u06cc\u0633\u06cc\u062a"
    ],
    "name:fra_x_preferred":[
        "Touissit"
    ],
    "name:ita_x_preferred":[
        "Touissit"
    ],
    "name:swe_x_preferred":[
        "Touissit"
    ],
    "name:und_x_variant":[
        "Touissite"
    ],
    "wof:name":"Touissite",
    "wof:placetype":"locality"
},
  "geometry": {"coordinates":[-1.7685,34.47857],"type":"Point"}
}