{
  "type": "Feature",
  "properties": {
    "gn:admin1_code":"02",
    "gn:asciiname":"Touissite",
    "gn:country_code":"MA",
    "gn:dem":1124,
    "gn:feature_class":"P",
    "gn:feature_code":"PPL",
    "gn:name":"Touissite",
    "gn:population":0,
    "gn:timezone":"Africa/Casablanca",
    "iso:country":"MA",
    "name:und_x_variant":[
        "Touissit",
        "Touissite"
    ],
    "wof:name":"Touissite",
    "wof:placetype":"locality"
},
  "geometry": {"coordinates":[-1.7685,34.47857],"type":"Point"}
}