{
  "type": "Feature",
  "properties": {
    "gn:admin1_code":"07",
    "gn:asciiname":"Laanakir Labhira",
    "gn:country_code":"MA",
    "gn:dem":510,
    "gn:feature_class":"P",
    "gn:feature_code":"PPL",
    "gn:name":"Laanakir Labhira",
    "gn:population":0,
    "gn:timezone":"Africa/Casablanca",
    "iso:country":"MA",
    "name:und_x_variant":[
        "Douar Anaguir",
        "El Anakir Haj Aomar",
        "El Anakir Hajj Aomar",
        "Laanakir Labhira"
    ],
    "wof:name":"Laanakir Labhira",
    "wof:placetype":"locality"
},
  "geometry": {"coordinates":[-7.84405,31.92637],"type":"Point"}
}