{
  "type": "Feature",
  "properties": {
    "gn:admin1_code":"02",
    "gn:asciiname":"Bou Reggane",
    "gn:country_code":"MA",
    "gn:dem":345,
    "gn:feature_class":"P",
    "gn:feature_code":"PPL",
    "gn:name":"Bou Reggane",
    "gn:population":0,
    "gn:timezone":"Africa/Casablanca",
    "iso:country":"MA",
    "wof:name":"Bou Reggane",
    "wof:placetype":"locality"
},
  "geometry": {"coordinates":[-3.34419,35.13257],"type":"Point"}
}