{
  "type": "Feature",
  "properties": {
    "gn:admin1_code":"10",
    "gn:asciiname":"Id Ben Adda",
    "gn:country_code":"MA",
    "gn:dem":927,
    "gn:feature_class":"P",
    "gn:feature_code":"PPL",
    "gn:name":"Id Ben Adda",
    "gn:population":0,
    "gn:timezone":"Africa/Casablanca",
    "iso:country":"MA",
    "name:und_x_variant":[
        "Id Ali Ou Addi",
        "Id Salah Ou Addi",
        "Id Ben Adda"
    ],
    "wof:name":"Id Ben Adda",
    "wof:placetype":"locality"
},
  "geometry": {"coordinates":[-9.76483,29.30093],"type":"Point"}
}