{
  "type": "Feature",
  "properties": {
    "gn:admin1_code":"5.0",
    "gn:asciiname":"Ait Messaad",
    "gn:country_code":"MA",
    "gn:dem":874,
    "gn:feature_class":"P",
    "gn:feature_code":"PPL",
    "gn:name":"A\u00eft Mess\u00e2ad",
    "gn:population":0,
    "gn:timezone":"Africa/Casablanca",
    "iso:country":"MA",
    "wof:name":"Ait Messaad",
    "wof:placetype":"locality"
},
  "geometry": {"coordinates":[-5.91919,32.90961],"type":"Point"}
}