{
  "type": "Feature",
  "properties": {
    "gn:admin1_code":"2.0",
    "gn:asciiname":"Douar Ihemmitene",
    "gn:country_code":"MA",
    "gn:dem":189,
    "gn:feature_class":"P",
    "gn:feature_code":"PPL",
    "gn:name":"Douar Ihemmitene",
    "gn:population":0,
    "gn:timezone":"Africa/Casablanca",
    "iso:country":"MA",
    "wof:name":"Douar Ihemmitene",
    "wof:placetype":"locality"
},
  "geometry": {"coordinates":[-2.57479,35.06104000000001],"type":"Point"}
}