{
  "type": "Feature",
  "properties": {
    "gn:admin1_code":"05",
    "gn:asciiname":"Klabou",
    "gn:country_code":"MA",
    "gn:dem":1350,
    "gn:elevation":"0.0",
    "gn:feature_class":"P",
    "gn:feature_code":"PPL",
    "gn:name":"Klabou",
    "gn:population":0,
    "gn:timezone":"Africa/Casablanca",
    "iso:country":"MA",
    "name:und_x_variant":[
        "Klabo"
    ],
    "wof:name":"Klabou",
    "wof:placetype":"locality"
},
  "geometry": {"coordinates":[-6.56455,31.69795],"type":"Point"}
}