{
  "type": "Feature",
  "properties": {
    "gn:admin1_code":"07",
    "gn:asciiname":"Douar Echidmiya",
    "gn:country_code":"MA",
    "gn:dem":709,
    "gn:feature_class":"P",
    "gn:feature_code":"PPL",
    "gn:name":"Douar Echidmiya",
    "gn:population":0,
    "gn:timezone":"Africa/Casablanca",
    "iso:country":"MA",
    "name:und_x_variant":[
        "Ech Chidmia",
        "Douar el Chidmia"
    ],
    "wof:name":"Douar Echidmiya",
    "wof:placetype":"locality"
},
  "geometry": {"coordinates":[-7.57247,31.97348],"type":"Point"}
}