{
  "type": "Feature",
  "properties": {
    "gn:admin1_code":"08",
    "gn:asciiname":"Ouaklim Oukider",
    "gn:country_code":"MA",
    "gn:dem":1258,
    "gn:feature_class":"P",
    "gn:feature_code":"PPL",
    "gn:name":"Ouaklim Oukider",
    "gn:population":0,
    "gn:timezone":"Africa/Casablanca",
    "iso:country":"MA",
    "name:ara_x_preferred":[
        "\u0648\u0627\u0643\u0644\u064a\u0645"
    ],
    "name:azb_x_preferred":[
        "\u0648\u0627\u06a9\u0644\u06cc\u0645"
    ],
    "name:cat_x_preferred":[
        "Ouaklim"
    ],
    "name:ceb_x_preferred":[
        "Ouaklim"
    ],
    "name:fas_x_preferred":[
        "\u0648\u0627\u06a9\u0644\u06cc\u0645"
    ],
    "name:ita_x_preferred":[
        "Ouaklim"
    ],
    "name:swe_x_preferred":[
        "Ouaklim"
    ],
    "name:und_x_variant":[
        "Wakline",
        "Ouaklim Oukider"
    ],
    "wof:name":"Ouaklim Oukider",
    "wof:placetype":"locality"
},
  "geometry": {"coordinates":[-5.54954,31.44537],"type":"Point"}
}