{
  "type": "Feature",
  "properties": {
    "gn:admin1_code":"2.0",
    "gn:asciiname":"Ifsi",
    "gn:country_code":"MA",
    "gn:dem":776,
    "gn:feature_class":"P",
    "gn:feature_code":"PPL",
    "gn:name":"Ifsi",
    "gn:population":0,
    "gn:timezone":"Africa/Casablanca",
    "iso:country":"MA",
    "wof:name":"Ifsi",
    "wof:placetype":"locality"
},
  "geometry": {"coordinates":[-2.38038,34.77759],"type":"Point"}
}