{
  "type": "Feature",
  "properties": {
    "gn:admin1_code":"05",
    "gn:asciiname":"Ait 'Amir",
    "gn:country_code":"MA",
    "gn:dem":648,
    "gn:feature_class":"P",
    "gn:feature_code":"PPL",
    "gn:name":"A\u00eft \u2019Amir",
    "gn:population":0,
    "gn:timezone":"Africa/Casablanca",
    "iso:country":"MA",
    "name:und_x_variant":[
        "A\u00eft \u2019Amir",
        "A\u00eft Amir"
    ],
    "wof:name":"Ait 'Amir",
    "wof:placetype":"locality"
},
  "geometry": {"coordinates":[-6.44156,32.22437],"type":"Point"}
}