{
  "type": "Feature",
  "properties": {
    "gn:admin1_code":"9.0",
    "gn:asciiname":"Id Az Za'iym",
    "gn:country_code":"MA",
    "gn:dem":1199,
    "gn:feature_class":"P",
    "gn:feature_code":"PPL",
    "gn:name":"Id Az Za\u2019iym",
    "gn:population":0,
    "gn:timezone":"Africa/Casablanca",
    "iso:country":"MA",
    "wof:name":"Id Az Za'iym",
    "wof:placetype":"locality"
},
  "geometry": {"coordinates":[-9.32251,29.51376],"type":"Point"}
}