{
  "type": "Feature",
  "properties": {
    "gn:admin1_code":"08",
    "gn:asciiname":"Gaouz",
    "gn:country_code":"MA",
    "gn:dem":749,
    "gn:feature_class":"P",
    "gn:feature_code":"PPL",
    "gn:name":"Gaouz",
    "gn:population":0,
    "gn:timezone":"Africa/Casablanca",
    "iso:country":"MA",
    "name:und_x_variant":[
        "Ksar Gaouz",
        "Gaouz"
    ],
    "wof:name":"Gaouz",
    "wof:placetype":"locality"
},
  "geometry": {"coordinates":[-4.29774,31.20398],"type":"Point"}
}