{
  "type": "Feature",
  "properties": {
    "gn:country":"MA",
    "gn:fcode":"ADM3",
    "gn:population":10352,
    "iso:country":"MA",
    "name:ara_x_preferred":[
        "\u0633\u064a\u062f\u064a \u0628\u064a\u0628\u064a"
    ],
    "name:ara_x_variant":[
        "\u0633\u064a\u062f\u064a \u0628\u0648\u0633\u062d\u0627\u0628"
    ],
    "name:ary_x_preferred":[
        "\u0633\u064a\u062f\u064a \u0628\u0648\u0633\u062d\u0627\u0628"
    ],
    "name:cat_x_preferred":[
        "Sidi Boushab"
    ],
    "name:ceb_x_preferred":[
        "Sidi Boushab"
    ],
    "name:deu_x_preferred":[
        "Sidi Boushab"
    ],
    "name:eng_x_preferred":[
        "Sidi Boushab"
    ],
    "name:fra_x_preferred":[
        "Sidi Boushab"
    ],
    "name:fra_x_variant":[
        "Sidi Boushab (Commune Rurale)"
    ],
    "name:ita_x_preferred":[
        "Sidi Boushab"
    ],
    "name:nld_x_preferred":[
        "Sidi Boushab"
    ],
    "name:nob_x_preferred":[
        "Sidi Boushab"
    ],
    "name:por_x_preferred":[
        "Sidi Boushab"
    ],
    "name:spa_x_preferred":[
        "Sidi Boushab"
    ],
    "name:swe_x_preferred":[
        "Sidi Boushab"
    ],
    "qs:name":"Sidi Boushab",
    "qs:photos_9r":0,
    "qs:photos_sr":0,
    "qs:pop_sr":"6",
    "wd:wordcount":82,
    "wof:name":"Sidi Boushab",
    "wof:placetype":"localadmin",
    "wof:population":10352
},
  "geometry": {"coordinates":[-9.30529,30.08692],"type":"Point"}
}