{
  "type": "Feature",
  "properties": {
    "gn:admin1_code":"4.0",
    "gn:asciiname":"Cooperative Lamiya",
    "gn:country_code":"MA",
    "gn:dem":218,
    "gn:feature_class":"P",
    "gn:feature_code":"PPLF",
    "gn:name":"Coop\u00e9rative Lamiya",
    "gn:population":0,
    "gn:timezone":"Africa/Casablanca",
    "iso:country":"MA",
    "wof:name":"Cooperative Lamiya",
    "wof:placetype":"locality"
},
  "geometry": {"coordinates":[-5.63121,34.72078],"type":"Point"}
}