{
  "type": "Feature",
  "properties": {
    "gn:admin1_code":"08",
    "gn:asciiname":"Timidart",
    "gn:country_code":"MA",
    "gn:dem":901,
    "gn:feature_class":"P",
    "gn:feature_code":"PPL",
    "gn:name":"Timidart",
    "gn:population":0,
    "gn:timezone":"Africa/Casablanca",
    "iso:country":"MA",
    "name:und_x_variant":[
        "Timiderte",
        "Timidert",
        "Timidart"
    ],
    "wof:name":"Timidart",
    "wof:placetype":"locality"
},
  "geometry": {"coordinates":[-6.29807,30.68248],"type":"Point"}
}