{
  "type": "Feature",
  "properties": {
    "gn:admin1_code":"05",
    "gn:asciiname":"Tassalnt",
    "gn:country_code":"MA",
    "gn:dem":1686,
    "gn:elevation":"0.0",
    "gn:feature_class":"P",
    "gn:feature_code":"PPL",
    "gn:name":"Tassalnt",
    "gn:population":0,
    "gn:timezone":"Africa/Casablanca",
    "iso:country":"MA",
    "name:und_x_variant":[
        "Tasselnt"
    ],
    "wof:name":"Tassalnt",
    "wof:placetype":"locality"
},
  "geometry": {"coordinates":[-6.84551,31.61951],"type":"Point"}
}