{
  "type": "Feature",
  "properties": {
    "gn:admin1_code":"09",
    "gn:asciiname":"Tinzad",
    "gn:country_code":"MA",
    "gn:dem":1050,
    "gn:feature_class":"P",
    "gn:feature_code":"PPL",
    "gn:name":"Tinzad",
    "gn:population":0,
    "gn:timezone":"Africa/Casablanca",
    "iso:country":"MA",
    "name:und_x_variant":[
        "Timzad",
        "Tinzad"
    ],
    "wof:name":"Tinzad",
    "wof:placetype":"locality"
},
  "geometry": {"coordinates":[-9.04104,29.9684],"type":"Point"}
}