{
  "type": "Feature",
  "properties": {
    "gn:admin1_code":"6.0",
    "gn:asciiname":"Oulad El Bouzzaoui",
    "gn:country_code":"MA",
    "gn:dem":253,
    "gn:feature_class":"P",
    "gn:feature_code":"PPL",
    "gn:name":"Oulad El Bouzzaoui",
    "gn:population":0,
    "gn:timezone":"Africa/Casablanca",
    "iso:country":"MA",
    "wof:name":"Oulad El Bouzzaoui",
    "wof:placetype":"locality"
},
  "geometry": {"coordinates":[-7.44699,33.23370999999999],"type":"Point"}
}