{
  "type": "Feature",
  "properties": {
    "gn:admin1_code":"07",
    "gn:asciiname":"Baragha",
    "gn:country_code":"MA",
    "gn:dem":820,
    "gn:feature_class":"P",
    "gn:feature_code":"PPL",
    "gn:name":"Baragha",
    "gn:population":0,
    "gn:timezone":"Africa/Casablanca",
    "iso:country":"MA",
    "name:und_x_variant":[
        "Douar Bararha",
        "Bararha",
        "Baragha"
    ],
    "wof:name":"Baragha",
    "wof:placetype":"locality"
},
  "geometry": {"coordinates":[-8.34358,31.28082],"type":"Point"}
}