{
  "type": "Feature",
  "properties": {
    "gn:admin1_code":"9.0",
    "gn:asciiname":"Id Boujoua",
    "gn:country_code":"MA",
    "gn:dem":556,
    "gn:feature_class":"P",
    "gn:feature_code":"PPL",
    "gn:name":"Id Boujoua",
    "gn:population":0,
    "gn:timezone":"Africa/Casablanca",
    "iso:country":"MA",
    "wof:name":"Id Boujoua",
    "wof:placetype":"locality"
},
  "geometry": {"coordinates":[-9.86704,29.50006],"type":"Point"}
}