{
  "type": "Feature",
  "properties": {
    "gn:admin1_code":"03",
    "gn:asciiname":"Douar Ain Essikh",
    "gn:country_code":"MA",
    "gn:dem":531,
    "gn:feature_class":"P",
    "gn:feature_code":"PPL",
    "gn:name":"Douar Ain Essikh",
    "gn:population":0,
    "gn:timezone":"Africa/Casablanca",
    "iso:country":"MA",
    "name:und_x_variant":[
        "A\u00efn Sikh"
    ],
    "wof:name":"Douar Ain Essikh",
    "wof:placetype":"locality"
},
  "geometry": {"coordinates":[-5.06248,34.07886],"type":"Point"}
}