{
  "type": "Feature",
  "properties": {
    "gn:admin1_code":"7.0",
    "gn:asciiname":"Oulad Dar",
    "gn:country_code":"MA",
    "gn:dem":400,
    "gn:feature_class":"P",
    "gn:feature_code":"PPL",
    "gn:name":"Oulad Dar",
    "gn:population":0,
    "gn:timezone":"Africa/Casablanca",
    "iso:country":"MA",
    "wof:name":"Oulad Dar",
    "wof:placetype":"locality"
},
  "geometry": {"coordinates":[-8.7032,32.11868],"type":"Point"}
}