{
  "type": "Feature",
  "properties": {
    "gn:admin1_code":"7.0",
    "gn:asciiname":"Tamlalt",
    "gn:country_code":"MA",
    "gn:dem":72,
    "gn:feature_class":"P",
    "gn:feature_code":"PPL",
    "gn:name":"Tamlalt",
    "gn:population":0,
    "gn:timezone":"Africa/Casablanca",
    "iso:country":"MA",
    "wof:name":"Tamlalt",
    "wof:placetype":"locality"
},
  "geometry": {"coordinates":[-9.81361,31.18222],"type":"Point"}
}