{
  "type": "Feature",
  "properties": {
    "gn:admin1_code":"7.0",
    "gn:asciiname":"Agadir-n Ait Lahssen",
    "gn:country_code":"MA",
    "gn:dem":745,
    "gn:feature_class":"P",
    "gn:feature_code":"PPL",
    "gn:name":"Agadir-n Ait Lahssen",
    "gn:population":0,
    "gn:timezone":"Africa/Casablanca",
    "iso:country":"MA",
    "wof:name":"Agadir-n Ait Lahssen",
    "wof:placetype":"locality"
},
  "geometry": {"coordinates":[-7.63071,31.54555],"type":"Point"}
}