{
  "type": "Feature",
  "properties": {
    "gn:admin1_code":"01",
    "gn:asciiname":"Lahrarsa Chammakha",
    "gn:country_code":"MA",
    "gn:dem":11,
    "gn:feature_class":"P",
    "gn:feature_code":"PPL",
    "gn:name":"Lahrarsa Chammakha",
    "gn:population":0,
    "gn:timezone":"Africa/Casablanca",
    "iso:country":"MA",
    "name:und_x_variant":[
        "El Hararsa",
        "El Herarsa",
        "Lahrarsa Chammakha"
    ],
    "wof:name":"Lahrarsa Chammakha",
    "wof:placetype":"locality"
},
  "geometry": {"coordinates":[-5.92295,35.08215999999999],"type":"Point"}
}