{
  "type": "Feature",
  "properties": {
    "gn:admin1_code":"09",
    "gn:asciiname":"Ait Tammennt",
    "gn:country_code":"MA",
    "gn:dem":319,
    "gn:feature_class":"P",
    "gn:feature_code":"PPL",
    "gn:name":"A\u00eft Tammennt",
    "gn:population":0,
    "gn:timezone":"Africa/Casablanca",
    "iso:country":"MA",
    "name:und_x_variant":[
        "A\u00eft Tammennt",
        "A\u00eft Tamment"
    ],
    "wof:name":"Ait Tammennt",
    "wof:placetype":"locality"
},
  "geometry": {"coordinates":[-8.71045,30.55079000000001],"type":"Point"}
}