{
  "type": "Feature",
  "properties": {
    "gn:admin1_code":"06",
    "gn:asciiname":"Douar El Khemamla",
    "gn:country_code":"MA",
    "gn:dem":58,
    "gn:feature_class":"P",
    "gn:feature_code":"PPL",
    "gn:name":"Douar El Khemamla",
    "gn:population":0,
    "gn:timezone":"Africa/Casablanca",
    "iso:country":"MA",
    "name:und_x_variant":[
        "Lakmamla Alssakak",
        "Douar el Khermoula",
        "Douar El Khemamla"
    ],
    "wof:name":"Douar El Khemamla",
    "wof:placetype":"locality"
},
  "geometry": {"coordinates":[-8.7167,32.99709],"type":"Point"}
}