{
  "type": "Feature",
  "properties": {
    "gn:admin1_code":"09",
    "gn:asciiname":"Tabad'ant",
    "gn:country_code":"MA",
    "gn:dem":1457,
    "gn:feature_class":"P",
    "gn:feature_code":"PPL",
    "gn:name":"Tabad\u2019ant",
    "gn:population":0,
    "gn:timezone":"Africa/Casablanca",
    "iso:country":"MA",
    "name:und_x_variant":[
        "Tabbada\u00e2nte A\u00eft Fanzar",
        "Tabadannt",
        "Tabadant",
        "Tabad\u2019ant"
    ],
    "wof:name":"Tabad'ant",
    "wof:placetype":"locality"
},
  "geometry": {"coordinates":[-7.94897,30.42898],"type":"Point"}
}