{
  "type": "Feature",
  "properties": {
    "gn:admin1_code":"08",
    "gn:asciiname":"Timesla",
    "gn:country_code":"MA",
    "gn:dem":828,
    "gn:feature_class":"P",
    "gn:feature_code":"PPL",
    "gn:name":"Timesla",
    "gn:population":0,
    "gn:timezone":"Africa/Casablanca",
    "iso:country":"MA",
    "name:und_x_variant":[
        "Timasla",
        "Timsla",
        "Timesla"
    ],
    "wof:name":"Timesla",
    "wof:placetype":"locality"
},
  "geometry": {"coordinates":[-6.13313,30.58036],"type":"Point"}
}