{
  "type": "Feature",
  "properties": {
    "gn:admin1_code":"07",
    "gn:asciiname":"Tioughza",
    "gn:country_code":"MA",
    "gn:dem":840,
    "gn:feature_class":"P",
    "gn:feature_code":"PPL",
    "gn:name":"Tioughza",
    "gn:population":0,
    "gn:timezone":"Africa/Casablanca",
    "iso:country":"MA",
    "name:ara_x_preferred":[
        "\u062a\u064a\u0648\u063a\u0632\u0629"
    ],
    "name:cat_x_preferred":[
        "Tioughza"
    ],
    "name:ceb_x_preferred":[
        "Tioughza"
    ],
    "name:fra_x_preferred":[
        "Tioughza"
    ],
    "name:ita_x_preferred":[
        "Tioughza"
    ],
    "name:swe_x_preferred":[
        "Tioughza"
    ],
    "name:und_x_variant":[
        "Douar Tiourhza",
        "Tizourit",
        "Tiourhza"
    ],
    "wof:name":"Tioughza",
    "wof:placetype":"locality"
},
  "geometry": {"coordinates":[-7.91025,31.37287],"type":"Point"}
}