{
  "type": "Feature",
  "properties": {
    "gn:admin1_code":"07",
    "gn:asciiname":"Tioughza",
    "gn:country_code":"MA",
    "gn:dem":840,
    "gn:feature_class":"P",
    "gn:feature_code":"PPL",
    "gn:name":"Tioughza",
    "gn:population":0,
    "gn:timezone":"Africa/Casablanca",
    "iso:country":"MA",
    "name:und_x_variant":[
        "Douar Tiourhza",
        "Tizourit",
        "Tiourhza",
        "Tioughza"
    ],
    "wof:name":"Tioughza",
    "wof:placetype":"locality"
},
  "geometry": {"coordinates":[-7.91025,31.37287],"type":"Point"}
}