{
  "type": "Feature",
  "properties": {
    "gn:admin1_code":"9.0",
    "gn:asciiname":"Zaouiat Sidi Mohammed Ouchine",
    "gn:country_code":"MA",
    "gn:dem":300,
    "gn:feature_class":"P",
    "gn:feature_code":"PPL",
    "gn:name":"Zaouiat Sidi Mohammed Ouchine",
    "gn:population":0,
    "gn:timezone":"Africa/Casablanca",
    "iso:country":"MA",
    "wof:name":"Zaouiat Sidi Mohammed Ouchine",
    "wof:placetype":"locality"
},
  "geometry": {"coordinates":[-9.78616,30.83444],"type":"Point"}
}