{
  "type": "Feature",
  "properties": {
    "gn:admin1_code":"6.0",
    "gn:asciiname":"Oulad Charqi",
    "gn:country_code":"MA",
    "gn:dem":71,
    "gn:feature_class":"P",
    "gn:feature_code":"PPL",
    "gn:name":"Oulad Charqi",
    "gn:population":0,
    "gn:timezone":"Africa/Casablanca",
    "iso:country":"MA",
    "wof:name":"Oulad Charqi",
    "wof:placetype":"locality"
},
  "geometry": {"coordinates":[-7.33915,33.54048],"type":"Point"}
}