{
  "type": "Feature",
  "properties": {
    "gn:admin1_code":"7.0",
    "gn:asciiname":"Tawnrast",
    "gn:country_code":"MA",
    "gn:dem":1337,
    "gn:feature_class":"P",
    "gn:feature_code":"PPL",
    "gn:name":"Tawnrast",
    "gn:population":0,
    "gn:timezone":"Africa/Casablanca",
    "iso:country":"MA",
    "wof:name":"Tawnrast",
    "wof:placetype":"locality"
},
  "geometry": {"coordinates":[-8.53467,31.06268],"type":"Point"}
}