{
  "type": "Feature",
  "properties": {
    "gn:gn_country":"MA",
    "gn:gn_fcode":"ADM3",
    "gn:gn_pop":1365,
    "gn:population":1365,
    "iso:country":"MA",
    "name:ara_x_preferred":[
        "\u0645\u0631\u0643\u0632 \u0628\u0648\u0639\u0646\u0627\u0646"
    ],
    "name:fra_x_preferred":[
        "Kettara"
    ],
    "name:fra_x_variant":[
        "Kettara (AC)",
        "Kettara (Agglomeration Communale)"
    ],
    "qs_pg:aaroncc":"MA",
    "qs_pg:gn_country":"MA",
    "qs_pg:gn_fcode":"ADM3",
    "qs_pg:gn_pop":1365,
    "qs_pg:name":"Kettara",
    "qs_pg:photos_9r":0,
    "qs_pg:photos_sr":0,
    "qs_pg:pop_sr":3,
    "qs_pg:qs_pg_placetype":"localadmin",
    "wof:name":"Kettara",
    "wof:placetype":"localadmin",
    "wof:population":1365
},
  "geometry": {"coordinates":[-8.17436,31.8723],"type":"Point"}
}