{
  "type": "Feature",
  "properties": {
    "gn:admin1_code":"9.0",
    "gn:asciiname":"Ait ou Aziz",
    "gn:country_code":"MA",
    "gn:dem":531,
    "gn:feature_class":"P",
    "gn:feature_code":"PPL",
    "gn:name":"A\u00eft ou Aziz",
    "gn:population":0,
    "gn:timezone":"Africa/Casablanca",
    "iso:country":"MA",
    "wof:name":"Ait ou Aziz",
    "wof:placetype":"locality"
},
  "geometry": {"coordinates":[-9.6082,30.78846],"type":"Point"}
}