{
  "type": "Feature",
  "properties": {
    "gn:admin1_code":"9.0",
    "gn:asciiname":"Ait Ahmad Ou Sa'id",
    "gn:country_code":"MA",
    "gn:dem":1087,
    "gn:feature_class":"P",
    "gn:feature_code":"PPL",
    "gn:name":"A\u00eft Ahmad Ou Sa\u2019id",
    "gn:population":0,
    "gn:timezone":"Africa/Casablanca",
    "iso:country":"MA",
    "wof:name":"Ait Ahmad Ou Sa'id",
    "wof:placetype":"locality"
},
  "geometry": {"coordinates":[-9.23726,29.81058],"type":"Point"}
}