{
  "type": "Feature",
  "properties": {
    "gn:admin1_code":"03",
    "gn:asciiname":"Ait Said Ou Heddou",
    "gn:country_code":"MA",
    "gn:dem":1483,
    "gn:feature_class":"P",
    "gn:feature_code":"PPL",
    "gn:name":"A\u00eft Sa\u00efd Ou Heddou",
    "gn:population":0,
    "gn:timezone":"Africa/Casablanca",
    "iso:country":"MA",
    "name:und_x_variant":[
        "A\u00eft Sa\u00efd Ou Hadou",
        "A\u00eft Sa\u00efd Ou Heddou"
    ],
    "wof:name":"Ait Said Ou Heddou",
    "wof:placetype":"locality"
},
  "geometry": {"coordinates":[-4.8212,33.41117],"type":"Point"}
}