{
  "type": "Feature",
  "properties": {
    "gn:admin1_code":"09",
    "gn:asciiname":"Tagadirt Iysiyl",
    "gn:country_code":"MA",
    "gn:dem":1275,
    "gn:feature_class":"P",
    "gn:feature_code":"PPL",
    "gn:name":"Tagadirt Iysiyl",
    "gn:population":0,
    "gn:timezone":"Africa/Casablanca",
    "iso:country":"MA",
    "name:und_x_variant":[
        "Tagadirt",
        "Tagadir Issil"
    ],
    "wof:name":"Tagadirt Iysiyl",
    "wof:placetype":"locality"
},
  "geometry": {"coordinates":[-8.53317,29.90155],"type":"Point"}
}