{
  "type": "Feature",
  "properties": {
    "gn:admin1_code":"03",
    "gn:asciiname":"Ben Khadra",
    "gn:country_code":"MA",
    "gn:dem":668,
    "gn:feature_class":"P",
    "gn:feature_code":"PPL",
    "gn:name":"Ben Khadra",
    "gn:population":0,
    "gn:timezone":"Africa/Casablanca",
    "iso:country":"MA",
    "wof:name":"Ben Khadra",
    "wof:placetype":"locality"
},
  "geometry": {"coordinates":[-5.35,33.83],"type":"Point"}
}