{
  "type": "Feature",
  "properties": {
    "gn:admin1_code":"10.0",
    "gn:asciiname":"Id Sa'id Ou 'Ali",
    "gn:country_code":"MA",
    "gn:dem":926,
    "gn:feature_class":"P",
    "gn:feature_code":"PPL",
    "gn:name":"Id Sa\u2019id Ou \u2019Ali",
    "gn:population":0,
    "gn:timezone":"Africa/Casablanca",
    "iso:country":"MA",
    "wof:name":"Id Sa'id Ou 'Ali",
    "wof:placetype":"locality"
},
  "geometry": {"coordinates":[-9.76947,29.27026],"type":"Point"}
}