{
  "type": "Feature",
  "properties": {
    "gn:admin1_code":"03",
    "gn:asciiname":"Refuge de Taffert",
    "gn:country_code":"MA",
    "gn:dem":1900,
    "gn:feature_class":"P",
    "gn:feature_code":"PPL",
    "gn:name":"Refuge de Taffert",
    "gn:population":0,
    "gn:timezone":"Africa/Casablanca",
    "iso:country":"MA",
    "wof:name":"Refuge de Taffert",
    "wof:placetype":"locality"
},
  "geometry": {"coordinates":[-4.16748,33.64977],"type":"Point"}
}