{
  "type": "Feature",
  "properties": {
    "gn:admin1_code":"10",
    "gn:asciiname":"Id L'arba",
    "gn:country_code":"MA",
    "gn:dem":647,
    "gn:feature_class":"P",
    "gn:feature_code":"PPL",
    "gn:name":"Id L\u2019arba",
    "gn:population":0,
    "gn:timezone":"Africa/Casablanca",
    "iso:country":"MA",
    "name:und_x_variant":[
        "Zoco El Arba de Ait Abdallah",
        "El Arba",
        "Zoco el Arbaa",
        "El Arba n\u2019A\u00eft Abdallah",
        "Id L\u2019arba"
    ],
    "wof:name":"Id L'arba",
    "wof:placetype":"locality"
},
  "geometry": {"coordinates":[-9.9043,29.3419],"type":"Point"}
}