{
  "type": "Feature",
  "properties": {
    "gn:admin1_code":"01",
    "gn:asciiname":"Douar Bou Khalifa",
    "gn:country_code":"MA",
    "gn:dem":480,
    "gn:feature_class":"P",
    "gn:feature_code":"PPL",
    "gn:name":"Douar Bou Khalifa",
    "gn:population":0,
    "gn:timezone":"Africa/Casablanca",
    "iso:country":"MA",
    "name:und_x_variant":[
        "Bo\u00fbkhl\u00eefa"
    ],
    "wof:name":"Douar Bou Khalifa",
    "wof:placetype":"locality"
},
  "geometry": {"coordinates":[-4.02946,35.06999],"type":"Point"}
}