{
  "type": "Feature",
  "properties": {
    "gn:admin1_code":"07",
    "gn:asciiname":"Layaida",
    "gn:country_code":"MA",
    "gn:dem":477,
    "gn:feature_class":"P",
    "gn:feature_code":"PPL",
    "gn:name":"Laya\u00efda",
    "gn:population":0,
    "gn:timezone":"Africa/Casablanca",
    "iso:country":"MA",
    "wof:name":"Layaida",
    "wof:placetype":"locality"
},
  "geometry": {"coordinates":[-8.86,31.98],"type":"Point"}
}