{
  "type": "Feature",
  "properties": {
    "gn:admin1_code":"09",
    "gn:asciiname":"Tingliane",
    "gn:country_code":"MA",
    "gn:dem":1248,
    "gn:feature_class":"P",
    "gn:feature_code":"PPL",
    "gn:name":"Tingliane",
    "gn:population":0,
    "gn:timezone":"Africa/Casablanca",
    "iso:country":"MA",
    "name:und_x_variant":[
        "Tinglian",
        "Tin Gliane",
        "Tingliane"
    ],
    "wof:name":"Tingliane",
    "wof:placetype":"locality"
},
  "geometry": {"coordinates":[-8.3513,30.82801],"type":"Point"}
}