{
  "type": "Feature",
  "properties": {
    "gn:admin1_code":"3.0",
    "gn:asciiname":"Douar Ait Bel Kacem",
    "gn:country_code":"MA",
    "gn:dem":649,
    "gn:feature_class":"P",
    "gn:feature_code":"PPL",
    "gn:name":"Douar Ait Bel Kacem",
    "gn:population":0,
    "gn:timezone":"Africa/Casablanca",
    "iso:country":"MA",
    "wof:name":"Douar Ait Bel Kacem",
    "wof:placetype":"locality"
},
  "geometry": {"coordinates":[-4.55443,33.93795],"type":"Point"}
}