{
  "type": "Feature",
  "properties": {
    "gn:admin1_code":"7.0",
    "gn:asciiname":"Tassekra",
    "gn:country_code":"MA",
    "gn:dem":121,
    "gn:feature_class":"P",
    "gn:feature_code":"PPL",
    "gn:name":"Tassekra",
    "gn:population":0,
    "gn:timezone":"Africa/Casablanca",
    "iso:country":"MA",
    "wof:name":"Tassekra",
    "wof:placetype":"locality"
},
  "geometry": {"coordinates":[-9.77557,31.24586],"type":"Point"}
}