{
  "type": "Feature",
  "properties": {
    "gn:admin1_code":"03",
    "gn:asciiname":"Douar Oulad Bel Kaab",
    "gn:country_code":"MA",
    "gn:dem":341,
    "gn:feature_class":"P",
    "gn:feature_code":"PPL",
    "gn:name":"Douar Oulad Bel Kaab",
    "gn:population":0,
    "gn:timezone":"Africa/Casablanca",
    "iso:country":"MA",
    "name:und_x_variant":[
        "Ouled Ben Lekka\u00e2b",
        "Oulad Bel Kaab"
    ],
    "wof:name":"Douar Oulad Bel Kaab",
    "wof:placetype":"locality"
},
  "geometry": {"coordinates":[-4.88773,34.40579],"type":"Point"}
}