{
  "type": "Feature",
  "properties": {
    "gn:admin1_code":"01",
    "gn:asciiname":"Douar Mchichouene",
    "gn:country_code":"MA",
    "gn:dem":603,
    "gn:feature_class":"P",
    "gn:feature_code":"PPL",
    "gn:name":"Douar Mchichouene",
    "gn:population":0,
    "gn:timezone":"Africa/Casablanca",
    "iso:country":"MA",
    "name:und_x_variant":[
        "Amsisouane",
        "El Ouas"
    ],
    "wof:name":"Douar Mchichouene",
    "wof:placetype":"locality"
},
  "geometry": {"coordinates":[-5.47207,35.32841],"type":"Point"}
}