{
  "type": "Feature",
  "properties": {
    "gn:admin1_code":"6.0",
    "gn:asciiname":"Douar Lemlureg Lebsasla",
    "gn:country_code":"MA",
    "gn:dem":384,
    "gn:feature_class":"P",
    "gn:feature_code":"PPL",
    "gn:name":"Douar Lemlureg Lebsasla",
    "gn:population":0,
    "gn:timezone":"Africa/Casablanca",
    "iso:country":"MA",
    "wof:name":"Douar Lemlureg Lebsasla",
    "wof:placetype":"locality"
},
  "geometry": {"coordinates":[-6.98291,33.49518],"type":"Point"}
}