{
  "type": "Feature",
  "properties": {
    "gn:admin1_code":"07",
    "gn:asciiname":"Habbou",
    "gn:country_code":"MA",
    "gn:dem":901,
    "gn:feature_class":"P",
    "gn:feature_code":"PPL",
    "gn:name":"Habbou",
    "gn:population":0,
    "gn:timezone":"Africa/Casablanca",
    "iso:country":"MA",
    "name:und_x_variant":[
        "Habbo",
        "Habbou"
    ],
    "wof:name":"Habbou",
    "wof:placetype":"locality"
},
  "geometry": {"coordinates":[-8.99162,31.17755],"type":"Point"}
}