{
  "type": "Feature",
  "properties": {
    "gn:gn_country":"MA",
    "gn:gn_fcode":"ADM3",
    "gn:gn_pop":3361,
    "gn:population":3570,
    "iso:country":"MA",
    "name:ara_x_preferred":[
        "\u0623\u064a\u062a \u0627\u0648\u0642\u0628\u0644\u064a"
    ],
    "name:fra_x_preferred":[
        "Anergui"
    ],
    "name:fra_x_variant":[
        "Anergui (CR)",
        "Anergui (Commune Rurale)"
    ],
    "qs_pg:aaroncc":"MA",
    "qs_pg:gn_country":"MA",
    "qs_pg:gn_fcode":"ADM3",
    "qs_pg:gn_pop":3361,
    "qs_pg:name":"Anergui",
    "qs_pg:photos_9r":0,
    "qs_pg:photos_sr":0,
    "qs_pg:pop_sr":4,
    "qs_pg:qs_pg_placetype":"localadmin",
    "wof:name":"Anergui",
    "wof:placetype":"localadmin",
    "wof:population":3570
},
  "geometry": {"coordinates":[-5.94857,32.06981],"type":"Point"}
}