{
  "type": "Feature",
  "properties": {
    "gn:admin1_code":"3.0",
    "gn:asciiname":"Dar Chaib Addi",
    "gn:country_code":"MA",
    "gn:dem":723,
    "gn:feature_class":"P",
    "gn:feature_code":"PPL",
    "gn:name":"Dar Chaib Addi",
    "gn:population":0,
    "gn:timezone":"Africa/Casablanca",
    "iso:country":"MA",
    "wof:name":"Dar Chaib Addi",
    "wof:placetype":"locality"
},
  "geometry": {"coordinates":[-5.68617,33.64294],"type":"Point"}
}