{
  "type": "Feature",
  "properties": {
    "gn:admin1_code":"09",
    "gn:asciiname":"Timicha",
    "gn:country_code":"MA",
    "gn:dem":1113,
    "gn:feature_class":"P",
    "gn:feature_code":"PPL",
    "gn:name":"Timicha",
    "gn:population":0,
    "gn:timezone":"Africa/Casablanca",
    "iso:country":"MA",
    "name:und_x_variant":[
        "Timichte",
        "Timicht",
        "Timicha"
    ],
    "wof:name":"Timicha",
    "wof:placetype":"locality"
},
  "geometry": {"coordinates":[-7.81562,30.56027000000001],"type":"Point"}
}