{
  "type": "Feature",
  "properties": {
    "gn:admin1_code":"07",
    "gn:asciiname":"Douar El Koudia",
    "gn:country_code":"MA",
    "gn:dem":434,
    "gn:feature_class":"P",
    "gn:feature_code":"PPL",
    "gn:name":"Douar El Koudia",
    "gn:population":0,
    "gn:timezone":"Africa/Casablanca",
    "iso:country":"MA",
    "name:und_x_variant":[
        "El-Koudia"
    ],
    "wof:name":"Douar El Koudia",
    "wof:placetype":"locality"
},
  "geometry": {"coordinates":[-8.95306,32.10151],"type":"Point"}
}