{
  "type": "Feature",
  "properties": {
    "gn:admin1_code":"3.0",
    "gn:asciiname":"Sidi de Sanie",
    "gn:country_code":"MA",
    "gn:dem":1063,
    "gn:feature_class":"P",
    "gn:feature_code":"PPL",
    "gn:name":"Sidi de Sanie",
    "gn:population":0,
    "gn:timezone":"Africa/Casablanca",
    "iso:country":"MA",
    "wof:name":"Sidi de Sanie",
    "wof:placetype":"locality"
},
  "geometry": {"coordinates":[-4.54927,33.52097],"type":"Point"}
}