{
  "type": "Feature",
  "properties": {
    "gn:admin1_code":"1.0",
    "gn:asciiname":"Douar Tighellane",
    "gn:country_code":"MA",
    "gn:dem":468,
    "gn:feature_class":"P",
    "gn:feature_code":"PPL",
    "gn:name":"Douar Tighellane",
    "gn:population":0,
    "gn:timezone":"Africa/Casablanca",
    "iso:country":"MA",
    "wof:name":"Douar Tighellane",
    "wof:placetype":"locality"
},
  "geometry": {"coordinates":[-5.05351,35.34799],"type":"Point"}
}