{
  "type": "Feature",
  "properties": {
    "gn:admin1_code":"04",
    "gn:asciiname":"Dar Slim",
    "gn:country_code":"MA",
    "gn:dem":195,
    "gn:feature_class":"P",
    "gn:feature_code":"PPL",
    "gn:name":"Dar Slim",
    "gn:population":0,
    "gn:timezone":"Africa/Casablanca",
    "iso:country":"MA",
    "name:und_x_variant":[
        "Salim",
        "Slim",
        "Dar Slim"
    ],
    "wof:name":"Dar Slim",
    "wof:placetype":"locality"
},
  "geometry": {"coordinates":[-5.48659,34.61096],"type":"Point"}
}