{
  "type": "Feature",
  "properties": {
    "gn:admin1_code":"55.0",
    "gn:asciiname":"Limouda",
    "gn:country_code":"MA",
    "gn:dem":2026,
    "gn:feature_class":"P",
    "gn:feature_code":"PPL",
    "gn:name":"Limouda",
    "gn:population":0,
    "gn:timezone":"Africa/Casablanca",
    "iso:country":"MA",
    "wof:name":"Limouda",
    "wof:placetype":"locality"
},
  "geometry": {"coordinates":[-7.77762,31.01197],"type":"Point"}
}