{
  "type": "Feature",
  "properties": {
    "gn:admin1_code":"07",
    "gn:asciiname":"Lemnaysrat",
    "gn:country_code":"MA",
    "gn:dem":194,
    "gn:feature_class":"P",
    "gn:feature_code":"PPL",
    "gn:name":"Lemnaysrat",
    "gn:population":0,
    "gn:timezone":"Africa/Casablanca",
    "iso:country":"MA",
    "name:und_x_variant":[
        "Douar Menisrat",
        "Menisrat",
        "Lemnaysrat"
    ],
    "wof:name":"Lemnaysrat",
    "wof:placetype":"locality"
},
  "geometry": {"coordinates":[-8.76108,32.28391],"type":"Point"}
}