{
  "type": "Feature",
  "properties": {
    "gn:admin1_code":"6.0",
    "gn:asciiname":"Dar Zeroual Said",
    "gn:country_code":"MA",
    "gn:dem":141,
    "gn:feature_class":"P",
    "gn:feature_code":"PPL",
    "gn:name":"Dar Zeroual Said",
    "gn:population":0,
    "gn:timezone":"Africa/Casablanca",
    "iso:country":"MA",
    "wof:name":"Dar Zeroual Said",
    "wof:placetype":"locality"
},
  "geometry": {"coordinates":[-8.79421,32.58475],"type":"Point"}
}