{
  "type": "Feature",
  "properties": {
    "gn:admin1_code":"5.0",
    "gn:asciiname":"Asegwar",
    "gn:country_code":"MA",
    "gn:dem":902,
    "gn:feature_class":"P",
    "gn:feature_code":"PPL",
    "gn:name":"Asegwar",
    "gn:population":0,
    "gn:timezone":"Africa/Casablanca",
    "iso:country":"MA",
    "wof:name":"Asegwar",
    "wof:placetype":"neighbourhood"
},
  "geometry": {"coordinates":[-7.02286,31.73824],"type":"Point"}
}