{
  "type": "Feature",
  "properties": {
    "gn:admin1_code":"09",
    "gn:asciiname":"Imi-n-Tislit",
    "gn:country_code":"MA",
    "gn:dem":1624,
    "gn:feature_class":"P",
    "gn:feature_code":"PPL",
    "gn:name":"Imi-n-Tislit",
    "gn:population":0,
    "gn:timezone":"Africa/Casablanca",
    "iso:country":"MA",
    "name:und_x_variant":[
        "Imi Ou Tislit"
    ],
    "wof:name":"Imi-n-Tislit",
    "wof:placetype":"locality"
},
  "geometry": {"coordinates":[-8.0789,30.88919000000001],"type":"Point"}
}