{
  "type": "Feature",
  "properties": {
    "gn:admin1_code":"4.0",
    "gn:asciiname":"Domaine Sbou",
    "gn:country_code":"MA",
    "gn:dem":11,
    "gn:feature_class":"P",
    "gn:feature_code":"PPL",
    "gn:name":"Domaine Sbou",
    "gn:population":0,
    "gn:timezone":"Africa/Casablanca",
    "iso:country":"MA",
    "wof:name":"Domaine Sbou",
    "wof:placetype":"locality"
},
  "geometry": {"coordinates":[-6.22936,34.56812],"type":"Point"}
}