{
  "type": "Feature",
  "properties": {
    "gn:admin1_code":"7.0",
    "gn:asciiname":"Lamsabih",
    "gn:country_code":"MA",
    "gn:dem":159,
    "gn:feature_class":"P",
    "gn:feature_code":"PPL",
    "gn:name":"Lamsabih",
    "gn:population":0,
    "gn:timezone":"Africa/Casablanca",
    "iso:country":"MA",
    "wof:name":"Lamsabih",
    "wof:placetype":"locality"
},
  "geometry": {"coordinates":[-8.86612,32.28213],"type":"Point"}
}