{
  "type": "Feature",
  "properties": {
    "gn:admin1_code":"09",
    "gn:asciiname":"Tamsaloumt",
    "gn:country_code":"MA",
    "gn:dem":1207,
    "gn:feature_class":"P",
    "gn:feature_code":"PPL",
    "gn:name":"Tamsaloumt",
    "gn:population":0,
    "gn:timezone":"Africa/Casablanca",
    "iso:country":"MA",
    "name:und_x_variant":[
        "Tamselloumt"
    ],
    "wof:name":"Tamsaloumt",
    "wof:placetype":"locality"
},
  "geometry": {"coordinates":[-8.1556,30.88586],"type":"Point"}
}