{
  "type": "Feature",
  "properties": {
    "gn:admin1_code":"09",
    "gn:asciiname":"Tayssa",
    "gn:country_code":"MA",
    "gn:dem":1014,
    "gn:feature_class":"P",
    "gn:feature_code":"PPL",
    "gn:name":"Tayssa",
    "gn:population":0,
    "gn:timezone":"Africa/Casablanca",
    "iso:country":"MA",
    "name:und_x_variant":[
        "Ta\u00efssa"
    ],
    "wof:name":"Tayssa",
    "wof:placetype":"locality"
},
  "geometry": {"coordinates":[-7.9265,30.74668],"type":"Point"}
}