{
  "type": "Feature",
  "properties": {
    "gn:admin1_code":"7.0",
    "gn:asciiname":"Id Bergounni",
    "gn:country_code":"MA",
    "gn:dem":397,
    "gn:feature_class":"P",
    "gn:feature_code":"PPL",
    "gn:name":"Id Bergounni",
    "gn:population":0,
    "gn:timezone":"Africa/Casablanca",
    "iso:country":"MA",
    "wof:name":"Id Bergounni",
    "wof:placetype":"locality"
},
  "geometry": {"coordinates":[-9.62979,31.12661],"type":"Point"}
}