{
  "type": "Feature",
  "properties": {
    "gn:admin1_code":"1.0",
    "gn:asciiname":"Douar Iziouane",
    "gn:country_code":"MA",
    "gn:dem":815,
    "gn:feature_class":"P",
    "gn:feature_code":"PPL",
    "gn:name":"Douar Iziouane",
    "gn:population":0,
    "gn:timezone":"Africa/Casablanca",
    "iso:country":"MA",
    "wof:name":"Douar Iziouane",
    "wof:placetype":"locality"
},
  "geometry": {"coordinates":[-4.87695,35.23454],"type":"Point"}
}