{
  "type": "Feature",
  "properties": {
    "gn:admin1_code":"4.0",
    "gn:asciiname":"Douar Echqaqfa Ettahtiya",
    "gn:country_code":"MA",
    "gn:dem":68,
    "gn:feature_class":"P",
    "gn:feature_code":"PPL",
    "gn:name":"Douar Echqaqfa Ettahtiya",
    "gn:population":0,
    "gn:timezone":"Africa/Casablanca",
    "iso:country":"MA",
    "wof:name":"Douar Echqaqfa Ettahtiya",
    "wof:placetype":"locality"
},
  "geometry": {"coordinates":[-5.65096,34.57400999999999],"type":"Point"}
}