{
  "type": "Feature",
  "properties": {
    "gn:admin1_code":"05",
    "gn:asciiname":"Ait Wayour",
    "gn:country_code":"MA",
    "gn:dem":1599,
    "gn:feature_class":"P",
    "gn:feature_code":"PPL",
    "gn:name":"Ait Wayour",
    "gn:population":0,
    "gn:timezone":"Africa/Casablanca",
    "iso:country":"MA",
    "name:und_x_variant":[
        "A\u00eft Oua\u00efour"
    ],
    "wof:name":"Ait Wayour",
    "wof:placetype":"locality"
},
  "geometry": {"coordinates":[-7.13155,31.59041],"type":"Point"}
}