{
  "type": "Feature",
  "properties": {
    "gn:admin1_code":"04",
    "gn:asciiname":"Oulad Bouazza",
    "gn:country_code":"MA",
    "gn:dem":147,
    "gn:feature_class":"P",
    "gn:feature_code":"PPL",
    "gn:name":"Oulad Bouazza",
    "gn:population":0,
    "gn:timezone":"Africa/Casablanca",
    "iso:country":"MA",
    "name:und_x_variant":[
        "Ouled Bouazza",
        "El Harrak",
        "Douar Oulad Bou Azza",
        "Oulad Bouazza"
    ],
    "wof:name":"Oulad Bouazza",
    "wof:placetype":"locality"
},
  "geometry": {"coordinates":[-6.12688,34.97633],"type":"Point"}
}