{
  "type": "Feature",
  "properties": {
    "gn:admin1_code":"3.0",
    "gn:asciiname":"Cooperative Ettaoufiq",
    "gn:country_code":"MA",
    "gn:dem":366,
    "gn:feature_class":"P",
    "gn:feature_code":"PPLF",
    "gn:name":"Coop\u00e9rative Ettaoufiq",
    "gn:population":0,
    "gn:timezone":"Africa/Casablanca",
    "iso:country":"MA",
    "wof:name":"Cooperative Ettaoufiq",
    "wof:placetype":"locality"
},
  "geometry": {"coordinates":[-4.30107,34.24973],"type":"Point"}
}