{
  "type": "Feature",
  "properties": {
    "gn:admin1_code":"09",
    "gn:asciiname":"Myal",
    "gn:country_code":"MA",
    "gn:dem":1929,
    "gn:feature_class":"P",
    "gn:feature_code":"PPL",
    "gn:name":"Myal",
    "gn:population":0,
    "gn:timezone":"Africa/Casablanca",
    "iso:country":"MA",
    "name:und_x_variant":[
        "Miyal"
    ],
    "wof:name":"Myal",
    "wof:placetype":"locality"
},
  "geometry": {"coordinates":[-7.76208,30.77962],"type":"Point"}
}