{
  "type": "Feature",
  "properties": {
    "gn:admin1_code":"7.0",
    "gn:asciiname":"Douar Ait Jmiai",
    "gn:country_code":"MA",
    "gn:dem":460,
    "gn:feature_class":"P",
    "gn:feature_code":"PPL",
    "gn:name":"Douar Ait Jmiai",
    "gn:population":0,
    "gn:timezone":"Africa/Casablanca",
    "iso:country":"MA",
    "wof:name":"Douar Ait Jmiai",
    "wof:placetype":"locality"
},
  "geometry": {"coordinates":[-9.26784,31.55052],"type":"Point"}
}