{
  "type": "Feature",
  "properties": {
    "gn:admin1_code":"1.0",
    "gn:asciiname":"Cooperative Sidi Essafi",
    "gn:country_code":"MA",
    "gn:dem":95,
    "gn:feature_class":"P",
    "gn:feature_code":"PPLF",
    "gn:name":"Coop\u00e9rative Sidi Essafi",
    "gn:population":0,
    "gn:timezone":"Africa/Casablanca",
    "iso:country":"MA",
    "wof:name":"Cooperative Sidi Essafi",
    "wof:placetype":"locality"
},
  "geometry": {"coordinates":[-5.25895,34.56614],"type":"Point"}
}