{
  "type": "Feature",
  "properties": {
    "gn:admin1_code":"5.0",
    "gn:asciiname":"Tazouwlt",
    "gn:country_code":"MA",
    "gn:dem":1937,
    "gn:feature_class":"P",
    "gn:feature_code":"PPL",
    "gn:name":"Tazouwlt",
    "gn:population":0,
    "gn:timezone":"Africa/Casablanca",
    "iso:country":"MA",
    "wof:name":"Tazouwlt",
    "wof:placetype":"locality"
},
  "geometry": {"coordinates":[-6.61732,31.61948],"type":"Point"}
}