{
  "type": "Feature",
  "properties": {
    "gn:admin1_code":"7.0",
    "gn:asciiname":"Igounane",
    "gn:country_code":"MA",
    "gn:dem":641,
    "gn:feature_class":"P",
    "gn:feature_code":"PPL",
    "gn:name":"Igounane",
    "gn:population":0,
    "gn:timezone":"Africa/Casablanca",
    "iso:country":"MA",
    "wof:name":"Igounane",
    "wof:placetype":"locality"
},
  "geometry": {"coordinates":[-9.46861,31.26618],"type":"Point"}
}