{
  "type": "Feature",
  "properties": {
    "gn:admin1_code":"03",
    "gn:asciiname":"Ed Demna",
    "gn:country_code":"MA",
    "gn:dem":479,
    "gn:feature_class":"P",
    "gn:feature_code":"PPL",
    "gn:name":"Ed Demna",
    "gn:population":0,
    "gn:timezone":"Africa/Casablanca",
    "iso:country":"MA",
    "wof:name":"Ed Demna",
    "wof:placetype":"locality"
},
  "geometry": {"coordinates":[-4.72196,34.56054],"type":"Point"}
}