{
  "type": "Feature",
  "properties": {
    "gn:admin1_code":"10",
    "gn:asciiname":"Ait Brahim",
    "gn:country_code":"MA",
    "gn:dem":290,
    "gn:feature_class":"P",
    "gn:feature_code":"PPL",
    "gn:name":"A\u00eft Brahim",
    "gn:population":0,
    "gn:timezone":"Africa/Casablanca",
    "iso:country":"MA",
    "wof:name":"Ait Brahim",
    "wof:placetype":"locality"
},
  "geometry": {"coordinates":[-10.07539,29.34719],"type":"Point"}
}