{
  "type": "Feature",
  "properties": {
    "gn:admin1_code":"04",
    "gn:asciiname":"Nouasser Ben Nacer",
    "gn:country_code":"MA",
    "gn:dem":8,
    "gn:feature_class":"P",
    "gn:feature_code":"PPL",
    "gn:name":"Nouasser Ben Nacer",
    "gn:population":0,
    "gn:timezone":"Africa/Casablanca",
    "iso:country":"MA",
    "name:und_x_variant":[
        "Douar Nouasseur",
        "Anoicer",
        "Nouasseur",
        "Nouasser",
        "Nouasser Ben Nacer"
    ],
    "wof:name":"Nouasser Ben Nacer",
    "wof:placetype":"locality"
},
  "geometry": {"coordinates":[-6.22196,34.62121],"type":"Point"}
}