{
  "type": "Feature",
  "properties": {
    "gn:admin1_code":"6.0",
    "gn:asciiname":"Laaroussiyne",
    "gn:country_code":"MA",
    "gn:dem":37,
    "gn:feature_class":"P",
    "gn:feature_code":"PPL",
    "gn:name":"Laaroussiyne",
    "gn:population":0,
    "gn:timezone":"Africa/Casablanca",
    "iso:country":"MA",
    "wof:name":"Laaroussiyne",
    "wof:placetype":"locality"
},
  "geometry": {"coordinates":[-8.54114,33.16278],"type":"Point"}
}