{
  "type": "Feature",
  "properties": {
    "gn:admin1_code":"10",
    "gn:asciiname":"Souk el Had",
    "gn:country_code":"MA",
    "gn:dem":314,
    "gn:feature_class":"P",
    "gn:feature_code":"PPL",
    "gn:name":"Souk el Had",
    "gn:population":0,
    "gn:timezone":"Africa/Casablanca",
    "iso:country":"MA",
    "name:und_x_variant":[
        "El Had",
        "Souk el Had"
    ],
    "wof:name":"Souk el Had",
    "wof:placetype":"locality"
},
  "geometry": {"coordinates":[-9.93269,29.50422],"type":"Point"}
}