{
  "type": "Feature",
  "properties": {
    "gn:admin1_code":"09",
    "gn:asciiname":"Tanit",
    "gn:country_code":"MA",
    "gn:dem":439,
    "gn:feature_class":"P",
    "gn:feature_code":"PPL",
    "gn:name":"Tanit",
    "gn:population":0,
    "gn:timezone":"Africa/Casablanca",
    "iso:country":"MA",
    "name:ara_x_preferred":[
        "\u062a\u0627\u0646\u064a\u062a"
    ],
    "name:ast_x_preferred":[
        "Tanit"
    ],
    "name:bel_x_preferred":[
        "\u0422\u0430\u043d\u0456\u0442"
    ],
    "name:cat_x_preferred":[
        "Tanit"
    ],
    "name:cym_x_preferred":[
        "Tanit"
    ],
    "name:deu_x_preferred":[
        "Tanit"
    ],
    "name:epo_x_preferred":[
        "Tanit"
    ],
    "name:eus_x_preferred":[
        "Tanit"
    ],
    "name:fin_x_preferred":[
        "Tanit"
    ],
    "name:fra_x_preferred":[
        "Tanit"
    ],
    "name:glg_x_preferred":[
        "Tanit"
    ],
    "name:heb_x_preferred":[
        "\u05ea\u05e0\u05d9\u05ea"
    ],
    "name:hun_x_preferred":[
        "Tanit"
    ],
    "name:ind_x_preferred":[
        "Tanit"
    ],
    "name:ita_x_preferred":[
        "Tanit"
    ],
    "name:kor_x_preferred":[
        "\ud0c0\ub2c8\ud2b8"
    ],
    "name:nld_x_preferred":[
        "Tanit"
    ],
    "name:nor_x_preferred":[
        "Tanit"
    ],
    "name:pol_x_preferred":[
        "Tanit"
    ],
    "name:por_x_preferred":[
        "Tanit"
    ],
    "name:ron_x_preferred":[
        "Tanit"
    ],
    "name:rus_x_preferred":[
        "\u0422\u0430\u043d\u0438\u0442"
    ],
    "name:spa_x_preferred":[
        "Tanit"
    ],
    "name:swe_x_preferred":[
        "Tanit"
    ],
    "name:ukr_x_preferred":[
        "\u0422\u0430\u043d\u0456\u0442"
    ],
    "name:zho_x_preferred":[
        "\u5854\u5c3c\u7279"
    ],
    "wof:name":"Tanit",
    "wof:placetype":"locality"
},
  "geometry": {"coordinates":[-9.42906,30.56713],"type":"Point"}
}