{
  "type": "Feature",
  "properties": {
    "gn:admin1_code":"09",
    "gn:asciiname":"Tanit",
    "gn:country_code":"MA",
    "gn:dem":439,
    "gn:feature_class":"P",
    "gn:feature_code":"PPL",
    "gn:name":"Tanit",
    "gn:population":0,
    "gn:timezone":"Africa/Casablanca",
    "iso:country":"MA",
    "wof:name":"Tanit",
    "wof:placetype":"locality"
},
  "geometry": {"coordinates":[-9.42906,30.56713],"type":"Point"}
}