{
  "type": "Feature",
  "properties": {
    "gn:admin1_code":"02",
    "gn:asciiname":"Douar Ouled Ben Mohamed Ben Abdallah",
    "gn:country_code":"MA",
    "gn:dem":682,
    "gn:feature_class":"P",
    "gn:feature_code":"PPL",
    "gn:name":"Douar Ouled Ben Mohamed Ben Abdallah",
    "gn:population":0,
    "gn:timezone":"Africa/Casablanca",
    "iso:country":"MA",
    "name:und_x_variant":[
        "Oulad Ben Mohammed Ben Abdallah"
    ],
    "wof:name":"Douar Ouled Ben Mohamed Ben Abdallah",
    "wof:placetype":"locality"
},
  "geometry": {"coordinates":[-3.75913,34.47756],"type":"Point"}
}