{
  "type": "Feature",
  "properties": {
    "gn:admin1_code":"01",
    "gn:asciiname":"Douar Bouqiya",
    "gn:country_code":"MA",
    "gn:dem":299,
    "gn:feature_class":"P",
    "gn:feature_code":"PPL",
    "gn:name":"Douar Bouqiya",
    "gn:population":0,
    "gn:timezone":"Africa/Casablanca",
    "iso:country":"MA",
    "name:und_x_variant":[
        "Bouquia",
        "Boukia",
        "Douar Bouqiya"
    ],
    "wof:name":"Douar Bouqiya",
    "wof:placetype":"locality"
},
  "geometry": {"coordinates":[-5.47467,34.67624],"type":"Point"}
}