{
  "type": "Feature",
  "properties": {
    "gn:admin1_code":"02",
    "gn:asciiname":"Douar Tissekkoumine",
    "gn:country_code":"MA",
    "gn:dem":604,
    "gn:feature_class":"P",
    "gn:feature_code":"PPL",
    "gn:name":"Douar Tissekkoumine",
    "gn:population":0,
    "gn:timezone":"Africa/Casablanca",
    "iso:country":"MA",
    "wof:name":"Douar Tissekkoumine",
    "wof:placetype":"locality"
},
  "geometry": {"coordinates":[-3.72222,35.13189000000001],"type":"Point"}
}