{
  "type": "Feature",
  "properties": {
    "gn:admin1_code":"7.0",
    "gn:asciiname":"Oulad El Faip",
    "gn:country_code":"MA",
    "gn:dem":404,
    "gn:feature_class":"P",
    "gn:feature_code":"PPL",
    "gn:name":"Oulad El Faip",
    "gn:population":0,
    "gn:timezone":"Africa/Casablanca",
    "iso:country":"MA",
    "wof:name":"Oulad El Faip",
    "wof:placetype":"locality"
},
  "geometry": {"coordinates":[-8.92207,31.88363],"type":"Point"}
}