{
  "type": "Feature",
  "properties": {
    "gn:admin1_code":"09",
    "gn:asciiname":"Sriy",
    "gn:country_code":"MA",
    "gn:dem":1350,
    "gn:feature_class":"P",
    "gn:feature_code":"PPL",
    "gn:name":"Sriy",
    "gn:population":0,
    "gn:timezone":"Africa/Casablanca",
    "iso:country":"MA",
    "name:und_x_variant":[
        "Agadir n\u2019 Sri",
        "Sri",
        "Sriy"
    ],
    "wof:name":"Sriy",
    "wof:placetype":"locality"
},
  "geometry": {"coordinates":[-8.79463,30.03824],"type":"Point"}
}