{
  "type": "Feature",
  "properties": {
    "gn:admin1_code":"09",
    "gn:asciiname":"Iguidar-n-Tatalt",
    "gn:country_code":"MA",
    "gn:dem":476,
    "gn:feature_class":"P",
    "gn:feature_code":"PPL",
    "gn:name":"Iguidar-n-Tatalt",
    "gn:population":0,
    "gn:timezone":"Africa/Casablanca",
    "iso:country":"MA",
    "name:und_x_variant":[
        "Iguidar n\u2019Talelt",
        "Igoudar"
    ],
    "wof:name":"Iguidar-n-Tatalt",
    "wof:placetype":"locality"
},
  "geometry": {"coordinates":[-8.39927,30.57603],"type":"Point"}
}