{
  "type": "Feature",
  "properties": {
    "gn:admin1_code":"5.0",
    "gn:asciiname":"Ait Slilou",
    "gn:country_code":"MA",
    "gn:dem":1044,
    "gn:feature_class":"P",
    "gn:feature_code":"PPL",
    "gn:name":"A\u00eft Slilou",
    "gn:population":0,
    "gn:timezone":"Africa/Casablanca",
    "iso:country":"MA",
    "wof:name":"Ait Slilou",
    "wof:placetype":"locality"
},
  "geometry": {"coordinates":[-6.41906,32.20186],"type":"Point"}
}