{
  "type": "Feature",
  "properties": {
    "gn:admin1_code":"7.0",
    "gn:asciiname":"Ait Oulahyane",
    "gn:country_code":"MA",
    "gn:dem":675,
    "gn:feature_class":"P",
    "gn:feature_code":"PPL",
    "gn:name":"Ait Oulahyane",
    "gn:population":0,
    "gn:timezone":"Africa/Casablanca",
    "iso:country":"MA",
    "wof:name":"Ait Oulahyane",
    "wof:placetype":"locality"
},
  "geometry": {"coordinates":[-7.69823,31.5169],"type":"Point"}
}