{
  "type": "Feature",
  "properties": {
    "gn:admin1_code":"03",
    "gn:asciiname":"Oulad Bou Soltane",
    "gn:country_code":"MA",
    "gn:dem":499,
    "gn:feature_class":"P",
    "gn:feature_code":"PPL",
    "gn:name":"Oulad Bou Soltane",
    "gn:population":0,
    "gn:timezone":"Africa/Casablanca",
    "iso:country":"MA",
    "name:und_x_variant":[
        "Ouled Boussoultane",
        "Oulad Bou Soltane"
    ],
    "wof:name":"Oulad Bou Soltane",
    "wof:placetype":"locality"
},
  "geometry": {"coordinates":[-4.69982,34.55062],"type":"Point"}
}