{
  "type": "Feature",
  "properties": {
    "gn:admin1_code":"03",
    "gn:asciiname":"Douar Beni Khalifa",
    "gn:country_code":"MA",
    "gn:dem":710,
    "gn:feature_class":"P",
    "gn:feature_code":"PPL",
    "gn:name":"Douar Beni Khalifa",
    "gn:population":0,
    "gn:timezone":"Africa/Casablanca",
    "iso:country":"MA",
    "name:und_x_variant":[
        "Beni Khalifa"
    ],
    "wof:name":"Douar Beni Khalifa",
    "wof:placetype":"locality"
},
  "geometry": {"coordinates":[-4.15749,34.3263],"type":"Point"}
}