{
  "type": "Feature",
  "properties": {
    "gn:admin1_code":"09",
    "gn:asciiname":"Tisnassamine",
    "gn:country_code":"MA",
    "gn:dem":1151,
    "gn:feature_class":"P",
    "gn:feature_code":"PPL",
    "gn:name":"Tisnassamine",
    "gn:population":0,
    "gn:timezone":"Africa/Casablanca",
    "iso:country":"MA",
    "name:und_x_variant":[
        "Tisenasamine",
        "Tisenna Sidi Amine",
        "Tisnassamine"
    ],
    "wof:name":"Tisnassamine",
    "wof:placetype":"locality"
},
  "geometry": {"coordinates":[-7.7986,30.02034],"type":"Point"}
}