{
  "type": "Feature",
  "properties": {
    "gn:gn_country":"MA",
    "gn:gn_fcode":"ADM3",
    "gn:gn_pop":11815,
    "gn:population":11976,
    "iso:country":"MA",
    "name:ara_x_preferred":[
        "\u062a\u0627\u0645\u062f\u0631\u0648\u0633\u062a"
    ],
    "name:ara_x_variant":[
        "\u0627\u0644\u062b\u0648\u0627\u0644\u062b"
    ],
    "name:cat_x_preferred":[
        "Toualet"
    ],
    "name:ceb_x_preferred":[
        "Toualet"
    ],
    "name:fra_x_preferred":[
        "Toualet"
    ],
    "name:fra_x_variant":[
        "Toualet (CR)",
        "Toualet (Commune Rurale)"
    ],
    "name:ita_x_preferred":[
        "Toualet"
    ],
    "name:swe_x_preferred":[
        "Toualet"
    ],
    "qs_pg:aaroncc":"MA",
    "qs_pg:gn_country":"MA",
    "qs_pg:gn_fcode":"ADM3",
    "qs_pg:gn_pop":11815,
    "qs_pg:name":"Toualet",
    "qs_pg:photos_9r":0,
    "qs_pg:photos_sr":0,
    "qs_pg:pop_sr":6,
    "qs_pg:qs_pg_placetype":"localadmin",
    "wof:name":"Toualet",
    "wof:placetype":"localadmin",
    "wof:population":11976
},
  "geometry": {"coordinates":[-7.65828,32.76784],"type":"Point"}
}