{
  "type": "Feature",
  "properties": {
    "gn:admin1_code":"6.0",
    "gn:asciiname":"Gouitat Leqsabi",
    "gn:country_code":"MA",
    "gn:dem":573,
    "gn:feature_class":"P",
    "gn:feature_code":"PPL",
    "gn:name":"Gouitat Leqsabi",
    "gn:population":0,
    "gn:timezone":"Africa/Casablanca",
    "iso:country":"MA",
    "wof:name":"Gouitat Leqsabi",
    "wof:placetype":"locality"
},
  "geometry": {"coordinates":[-7.07172,33.12857],"type":"Point"}
}