{
  "type": "Feature",
  "properties": {
    "gn:admin1_code":"07",
    "gn:asciiname":"Dar Moulay Ahmed",
    "gn:country_code":"MA",
    "gn:dem":817,
    "gn:feature_class":"P",
    "gn:feature_code":"PPL",
    "gn:name":"Dar Moulay Ahmed",
    "gn:population":0,
    "gn:timezone":"Africa/Casablanca",
    "iso:country":"MA",
    "name:und_x_variant":[
        "Douar Moulay Ahmed",
        "Moulay Ahmed",
        "Dar Moulay Ahmed"
    ],
    "wof:name":"Dar Moulay Ahmed",
    "wof:placetype":"locality"
},
  "geometry": {"coordinates":[-7.81169,31.38804],"type":"Point"}
}