{
  "type": "Feature",
  "properties": {
    "gn:admin1_code":"6.0",
    "gn:asciiname":"Oulad Bouazza",
    "gn:country_code":"MA",
    "gn:dem":228,
    "gn:feature_class":"P",
    "gn:feature_code":"PPL",
    "gn:name":"Oulad Bouazza",
    "gn:population":0,
    "gn:timezone":"Africa/Casablanca",
    "iso:country":"MA",
    "wof:name":"Oulad Bouazza",
    "wof:placetype":"locality"
},
  "geometry": {"coordinates":[-7.09168,33.67064],"type":"Point"}
}