{
  "type": "Feature",
  "properties": {
    "gn:admin1_code":"08",
    "gn:asciiname":"Ait Haddou Amer",
    "gn:country_code":"MA",
    "gn:dem":2272,
    "gn:feature_class":"P",
    "gn:feature_code":"PPL",
    "gn:name":"A\u00eft Haddou Amer",
    "gn:population":0,
    "gn:timezone":"Africa/Casablanca",
    "iso:country":"MA",
    "name:und_x_variant":[
        "A\u00eft Haddou Ameur",
        "A\u00eft Haddou Amer"
    ],
    "wof:name":"Ait Haddou Amer",
    "wof:placetype":"locality"
},
  "geometry": {"coordinates":[-5.48584,32.07966],"type":"Point"}
}