{
  "type": "Feature",
  "properties": {
    "gn:admin1_code":"08",
    "gn:asciiname":"Tameskourt",
    "gn:country_code":"MA",
    "gn:dem":2293,
    "gn:feature_class":"P",
    "gn:feature_code":"PPL",
    "gn:name":"Tameskourt",
    "gn:population":0,
    "gn:timezone":"Africa/Casablanca",
    "iso:country":"MA",
    "wof:name":"Tameskourt",
    "wof:placetype":"locality"
},
  "geometry": {"coordinates":[-5.43144,32.28696],"type":"Point"}
}