{
  "type": "Feature",
  "properties": {
    "gn:admin1_code":"7.0",
    "gn:asciiname":"Douar Blilat Eddalaa",
    "gn:country_code":"MA",
    "gn:dem":360,
    "gn:feature_class":"P",
    "gn:feature_code":"PPL",
    "gn:name":"Douar Blilat Eddalaa",
    "gn:population":0,
    "gn:timezone":"Africa/Casablanca",
    "iso:country":"MA",
    "wof:name":"Douar Blilat Eddalaa",
    "wof:placetype":"locality"
},
  "geometry": {"coordinates":[-8.58534,31.93138],"type":"Point"}
}