{
  "type": "Feature",
  "properties": {
    "gn:admin1_code":"08",
    "gn:asciiname":"Ahmed ben Ali",
    "gn:country_code":"MA",
    "gn:dem":791,
    "gn:feature_class":"P",
    "gn:feature_code":"PPL",
    "gn:name":"Ahmed ben Ali",
    "gn:population":0,
    "gn:timezone":"Africa/Casablanca",
    "iso:country":"MA",
    "wof:name":"Ahmed ben Ali",
    "wof:placetype":"locality"
},
  "geometry": {"coordinates":[-6.03048,30.46702],"type":"Point"}
}