{
  "type": "Feature",
  "properties": {
    "gn:admin1_code":"7.0",
    "gn:asciiname":"Douar Cheikh Brahim",
    "gn:country_code":"MA",
    "gn:dem":477,
    "gn:feature_class":"P",
    "gn:feature_code":"PPL",
    "gn:name":"Douar Cheikh Brahim",
    "gn:population":0,
    "gn:timezone":"Africa/Casablanca",
    "iso:country":"MA",
    "wof:name":"Douar Cheikh Brahim",
    "wof:placetype":"locality"
},
  "geometry": {"coordinates":[-8.36744,31.99079],"type":"Point"}
}