{
  "type": "Feature",
  "properties": {
    "gn:admin1_code":"02",
    "gn:asciiname":"Tazagouin",
    "gn:country_code":"MA",
    "gn:dem":136,
    "gn:feature_class":"P",
    "gn:feature_code":"PPL",
    "gn:name":"Tazagouin",
    "gn:population":0,
    "gn:timezone":"Africa/Casablanca",
    "iso:country":"MA",
    "name:und_x_variant":[
        "Tasagouine",
        "Tasaguin",
        "Tazagouin"
    ],
    "wof:name":"Tazagouin",
    "wof:placetype":"locality"
},
  "geometry": {"coordinates":[-2.45249,35.07575],"type":"Point"}
}