{
  "type": "Feature",
  "properties": {
    "gn:admin1_code":"9.0",
    "gn:asciiname":"Tagnit",
    "gn:country_code":"MA",
    "gn:dem":1721,
    "gn:feature_class":"P",
    "gn:feature_code":"PPL",
    "gn:name":"Tagnit",
    "gn:population":0,
    "gn:timezone":"Africa/Casablanca",
    "iso:country":"MA",
    "wof:name":"Tagnit",
    "wof:placetype":"locality"
},
  "geometry": {"coordinates":[-8.50735,30.09526],"type":"Point"}
}