{
  "type": "Feature",
  "properties": {
    "gn:admin1_code":"7.0",
    "gn:asciiname":"Douar Oulad El Arbi Ben Kaddour",
    "gn:country_code":"MA",
    "gn:dem":144,
    "gn:feature_class":"P",
    "gn:feature_code":"PPL",
    "gn:name":"Douar Oulad El Arbi Ben Kaddour",
    "gn:population":0,
    "gn:timezone":"Africa/Casablanca",
    "iso:country":"MA",
    "wof:name":"Douar Oulad El Arbi Ben Kaddour",
    "wof:placetype":"locality"
},
  "geometry": {"coordinates":[-9.2255,32.05475999999999],"type":"Point"}
}