{
  "type": "Feature",
  "properties": {
    "gn:admin1_code":"01",
    "gn:asciiname":"Amechaji",
    "gn:country_code":"MA",
    "gn:dem":415,
    "gn:feature_class":"P",
    "gn:feature_code":"PPL",
    "gn:name":"Amechaji",
    "gn:population":0,
    "gn:timezone":"Africa/Casablanca",
    "iso:country":"MA",
    "name:und_x_variant":[
        "Amexayi",
        "Amechaji"
    ],
    "wof:name":"Amechaji",
    "wof:placetype":"locality"
},
  "geometry": {"coordinates":[-4.71645,35.20088],"type":"Point"}
}