{
  "type": "Feature",
  "properties": {
    "gn:admin1_code":"10",
    "gn:asciiname":"Oughrane",
    "gn:country_code":"MA",
    "gn:dem":437,
    "gn:feature_class":"P",
    "gn:feature_code":"PPL",
    "gn:name":"Oughrane",
    "gn:population":0,
    "gn:timezone":"Africa/Casablanca",
    "iso:country":"MA",
    "name:und_x_variant":[
        "Ourhrane",
        "Ugran",
        "Ogran",
        "Ougrane",
        "Oughrane"
    ],
    "wof:name":"Oughrane",
    "wof:placetype":"locality"
},
  "geometry": {"coordinates":[-10.1273,29.14862],"type":"Point"}
}