{
  "type": "Feature",
  "properties": {
    "gn:admin1_code":"09",
    "gn:asciiname":"Wawrgout",
    "gn:country_code":"MA",
    "gn:dem":1364,
    "gn:feature_class":"P",
    "gn:feature_code":"PPL",
    "gn:name":"Wawrgout",
    "gn:population":0,
    "gn:timezone":"Africa/Casablanca",
    "iso:country":"MA",
    "name:und_x_variant":[
        "Anaouargoute",
        "Ouaourgout",
        "Wawrgout"
    ],
    "wof:name":"Wawrgout",
    "wof:placetype":"locality"
},
  "geometry": {"coordinates":[-7.73464,30.58742],"type":"Point"}
}