{
  "type": "Feature",
  "properties": {
    "gn:admin1_code":"5.0",
    "gn:asciiname":"Ighrem-n-Imdyane",
    "gn:country_code":"MA",
    "gn:dem":2034,
    "gn:feature_class":"P",
    "gn:feature_code":"PPL",
    "gn:name":"Ighrem-n-Imdyane",
    "gn:population":0,
    "gn:timezone":"Africa/Casablanca",
    "iso:country":"MA",
    "wof:name":"Ighrem-n-Imdyane",
    "wof:placetype":"locality"
},
  "geometry": {"coordinates":[-6.4265,31.81921],"type":"Point"}
}