{
  "type": "Feature",
  "properties": {
    "gn:admin1_code":"7.0",
    "gn:asciiname":"Tijaddant",
    "gn:country_code":"MA",
    "gn:dem":1139,
    "gn:feature_class":"P",
    "gn:feature_code":"PPL",
    "gn:name":"Tijaddant",
    "gn:population":0,
    "gn:timezone":"Africa/Casablanca",
    "iso:country":"MA",
    "wof:name":"Tijaddant",
    "wof:placetype":"locality"
},
  "geometry": {"coordinates":[-7.38713,31.45615],"type":"Point"}
}