{
  "type": "Feature",
  "properties": {
    "gn:admin1_code":"5.0",
    "gn:asciiname":"Ait Ben Nacar",
    "gn:country_code":"MA",
    "gn:dem":1114,
    "gn:feature_class":"P",
    "gn:feature_code":"PPL",
    "gn:name":"A\u00eft Ben Na\u00e7ar",
    "gn:population":0,
    "gn:timezone":"Africa/Casablanca",
    "iso:country":"MA",
    "wof:name":"Ait Ben Nacar",
    "wof:placetype":"locality"
},
  "geometry": {"coordinates":[-6.75177,31.93198],"type":"Point"}
}