{
  "type": "Feature",
  "properties": {
    "gn:admin1_code":"9.0",
    "gn:asciiname":"Douar Issil Ouzeddar",
    "gn:country_code":"MA",
    "gn:dem":339,
    "gn:feature_class":"P",
    "gn:feature_code":"PPL",
    "gn:name":"Douar Issil Ouzeddar",
    "gn:population":0,
    "gn:timezone":"Africa/Casablanca",
    "iso:country":"MA",
    "wof:name":"Douar Issil Ouzeddar",
    "wof:placetype":"locality"
},
  "geometry": {"coordinates":[-9.82232,29.56651],"type":"Point"}
}