{
  "type": "Feature",
  "properties": {
    "gn:admin1_code":"2.0",
    "gn:asciiname":"Douar Igharafene",
    "gn:country_code":"MA",
    "gn:dem":567,
    "gn:feature_class":"P",
    "gn:feature_code":"PPL",
    "gn:name":"Douar Igharafene",
    "gn:population":0,
    "gn:timezone":"Africa/Casablanca",
    "iso:country":"MA",
    "wof:name":"Douar Igharafene",
    "wof:placetype":"locality"
},
  "geometry": {"coordinates":[-2.38176,34.83424],"type":"Point"}
}