{
  "type": "Feature",
  "properties": {
    "gn:admin1_code":"07",
    "gn:asciiname":"Afra",
    "gn:country_code":"MA",
    "gn:dem":939,
    "gn:feature_class":"P",
    "gn:feature_code":"PPL",
    "gn:name":"Afra",
    "gn:population":0,
    "gn:timezone":"Africa/Casablanca",
    "iso:country":"MA",
    "wof:name":"Afra",
    "wof:placetype":"locality"
},
  "geometry": {"coordinates":[-9.38754,30.90762],"type":"Point"}
}