{
  "type": "Feature",
  "properties": {
    "gn:admin1_code":"6.0",
    "gn:asciiname":"Oulad Mahjouba",
    "gn:country_code":"MA",
    "gn:dem":51,
    "gn:feature_class":"P",
    "gn:feature_code":"PPL",
    "gn:name":"Oulad Mahjouba",
    "gn:population":0,
    "gn:timezone":"Africa/Casablanca",
    "iso:country":"MA",
    "wof:name":"Oulad Mahjouba",
    "wof:placetype":"locality"
},
  "geometry": {"coordinates":[-7.14405,33.79007],"type":"Point"}
}