{
  "type": "Feature",
  "properties": {
    "gn:admin1_code":"9.0",
    "gn:asciiname":"Chninet",
    "gn:country_code":"MA",
    "gn:dem":107,
    "gn:feature_class":"P",
    "gn:feature_code":"PPL",
    "gn:name":"Chninet",
    "gn:population":0,
    "gn:timezone":"Africa/Casablanca",
    "iso:country":"MA",
    "wof:name":"Chninet",
    "wof:placetype":"locality"
},
  "geometry": {"coordinates":[-9.21775,30.40701],"type":"Point"}
}