{
  "type": "Feature",
  "properties": {
    "gn:admin1_code":"6.0",
    "gn:asciiname":"Douar Lemjaouline",
    "gn:country_code":"MA",
    "gn:dem":183,
    "gn:feature_class":"P",
    "gn:feature_code":"PPL",
    "gn:name":"Douar Lemjaouline",
    "gn:population":0,
    "gn:timezone":"Africa/Casablanca",
    "iso:country":"MA",
    "wof:name":"Douar Lemjaouline",
    "wof:placetype":"locality"
},
  "geometry": {"coordinates":[-8.603,32.58264],"type":"Point"}
}