{
  "type": "Feature",
  "properties": {
    "gn:country":"MA",
    "gn:fcode":"ADM3",
    "gn:pop":4310,
    "iso:country":"MA",
    "name:ara_x_preferred":[
        "\u0627\u0644\u062f\u062e\u064a\u0633\u0629"
    ],
    "name:fra_x_preferred":[
        "Ait Ben Yacoub"
    ],
    "name:fra_x_variant":[
        "Ait Ben Yacoub (CR)",
        "Ait Ben Yacoub (Commune Rurale)"
    ],
    "qs:name":"Ait Ben Yacoub",
    "qs:photos_9r":0,
    "qs:photos_sr":0,
    "qs:pop_sr":"4",
    "wd:wordcount":58,
    "wof:name":"Ait Ben Yacoub",
    "wof:placetype":"localadmin",
    "wof:population":4310
},
  "geometry": {"coordinates":[-4.87052,33.01053],"type":"Point"}
}