{
  "type": "Feature",
  "properties": {
    "gn:admin1_code":"7.0",
    "gn:asciiname":"Ait bel Fkih",
    "gn:country_code":"MA",
    "gn:dem":515,
    "gn:feature_class":"P",
    "gn:feature_code":"PPL",
    "gn:name":"A\u00eft bel Fkih",
    "gn:population":0,
    "gn:timezone":"Africa/Casablanca",
    "iso:country":"MA",
    "wof:name":"Ait bel Fkih",
    "wof:placetype":"locality"
},
  "geometry": {"coordinates":[-9.423,31.32002],"type":"Point"}
}