{
  "type": "Feature",
  "properties": {
    "gn:admin1_code":"09",
    "gn:asciiname":"Ait Yazza",
    "gn:country_code":"MA",
    "gn:dem":268,
    "gn:feature_class":"P",
    "gn:feature_code":"PPL",
    "gn:name":"Ait Yazza",
    "gn:population":0,
    "gn:timezone":"Africa/Casablanca",
    "iso:country":"MA",
    "name:und_x_variant":[
        "Yazza",
        "A\u00eft Lazza",
        "A\u00eft Yazza",
        "Ait Yazza"
    ],
    "wof:name":"Ait Yazza",
    "wof:placetype":"locality"
},
  "geometry": {"coordinates":[-8.79917,30.50188],"type":"Point"}
}