{
  "type": "Feature",
  "properties": {
    "gn:admin1_code":"7.0",
    "gn:asciiname":"Douar Ifarkhas",
    "gn:country_code":"MA",
    "gn:dem":363,
    "gn:feature_class":"P",
    "gn:feature_code":"PPL",
    "gn:name":"Douar Ifarkhas",
    "gn:population":0,
    "gn:timezone":"Africa/Casablanca",
    "iso:country":"MA",
    "wof:name":"Douar Ifarkhas",
    "wof:placetype":"locality"
},
  "geometry": {"coordinates":[-9.72447,31.05315],"type":"Point"}
}