{
  "type": "Feature",
  "properties": {
    "gn:admin1_code":"02",
    "gn:asciiname":"Ibenadene",
    "gn:country_code":"MA",
    "gn:dem":579,
    "gn:feature_class":"P",
    "gn:feature_code":"PPL",
    "gn:name":"Ibenadene",
    "gn:population":0,
    "gn:timezone":"Africa/Casablanca",
    "iso:country":"MA",
    "name:und_x_variant":[
        "Benadene",
        "Ibennadene",
        "Ibenadene"
    ],
    "wof:name":"Ibenadene",
    "wof:placetype":"locality"
},
  "geometry": {"coordinates":[-3.56,34.85],"type":"Point"}
}