{
  "type": "Feature",
  "properties": {
    "gn:admin1_code":"09",
    "gn:asciiname":"Naouji Et Tahtaniine",
    "gn:country_code":"MA",
    "gn:dem":162,
    "gn:feature_class":"P",
    "gn:feature_code":"PPL",
    "gn:name":"Naouji Et Tahtaniine",
    "gn:population":0,
    "gn:timezone":"Africa/Casablanca",
    "iso:country":"MA",
    "name:und_x_variant":[
        "Nouaji",
        "Najaji el Ghrartigne",
        "Naouji Et Tahtaniine"
    ],
    "wof:name":"Naouji Et Tahtaniine",
    "wof:placetype":"locality"
},
  "geometry": {"coordinates":[-9.09976,30.48761],"type":"Point"}
}