{
  "type": "Feature",
  "properties": {
    "gn:admin1_code":"6.0",
    "gn:asciiname":"Douar Lahmira",
    "gn:country_code":"MA",
    "gn:dem":422,
    "gn:feature_class":"P",
    "gn:feature_code":"PPL",
    "gn:name":"Douar Lahmira",
    "gn:population":0,
    "gn:timezone":"Africa/Casablanca",
    "iso:country":"MA",
    "wof:name":"Douar Lahmira",
    "wof:placetype":"locality"
},
  "geometry": {"coordinates":[-7.22908,33.22534],"type":"Point"}
}