{
  "type": "Feature",
  "properties": {
    "gn:admin1_code":"07",
    "gn:asciiname":"Douar Oulad Kaddour",
    "gn:country_code":"MA",
    "gn:dem":216,
    "gn:feature_class":"P",
    "gn:feature_code":"PPL",
    "gn:name":"Douar Oulad Kaddour",
    "gn:population":0,
    "gn:timezone":"Africa/Casablanca",
    "iso:country":"MA",
    "name:und_x_variant":[
        "Oulad Kaddour",
        "Ouled-Kaddour",
        "Dar Oulad Kaddour",
        "Douar Oulad Kaddour"
    ],
    "wof:name":"Douar Oulad Kaddour",
    "wof:placetype":"locality"
},
  "geometry": {"coordinates":[-8.77021,31.73485],"type":"Point"}
}