{
  "type": "Feature",
  "properties": {
    "gn:admin1_code":"2.0",
    "gn:asciiname":"Douar Oulad Ghanem Ben Kaddour",
    "gn:country_code":"MA",
    "gn:dem":618,
    "gn:feature_class":"P",
    "gn:feature_code":"PPL",
    "gn:name":"Douar Oulad Ghanem Ben Kaddour",
    "gn:population":0,
    "gn:timezone":"Africa/Casablanca",
    "iso:country":"MA",
    "wof:name":"Douar Oulad Ghanem Ben Kaddour",
    "wof:placetype":"locality"
},
  "geometry": {"coordinates":[-2.43389,34.5974],"type":"Point"}
}