{
  "type": "Feature",
  "properties": {
    "gn:admin1_code":"6.0",
    "gn:asciiname":"Barrhout",
    "gn:country_code":"MA",
    "gn:dem":321,
    "gn:feature_class":"P",
    "gn:feature_code":"PPL",
    "gn:name":"Barrhout",
    "gn:population":0,
    "gn:timezone":"Africa/Casablanca",
    "iso:country":"MA",
    "wof:name":"Barrhout",
    "wof:placetype":"locality"
},
  "geometry": {"coordinates":[-7.85251,32.97150999999999],"type":"Point"}
}