{
  "type": "Feature",
  "properties": {
    "gn:admin1_code":"05",
    "gn:asciiname":"Ait Amer",
    "gn:country_code":"MA",
    "gn:dem":1262,
    "gn:elevation":"0.0",
    "gn:feature_class":"P",
    "gn:feature_code":"PPL",
    "gn:name":"A\u00eft Amer",
    "gn:population":0,
    "gn:timezone":"Africa/Casablanca",
    "iso:country":"MA",
    "name:und_x_variant":[
        "A\u00eft Ameur",
        "A\u00eft Amer"
    ],
    "wof:name":"Ait Amer",
    "wof:placetype":"locality"
},
  "geometry": {"coordinates":[-6.69632,31.94157],"type":"Point"}
}