{
  "type": "Feature",
  "properties": {
    "iso:country":"MA",
    "name:ara_x_preferred":[
        "Dradeb"
    ],
    "name:ara_x_variant":[
        "Drades"
    ],
    "qs:gn_adm0_cc":"MA",
    "qs:gn_fcode":"PPLX",
    "qs:gn_local":2530335,
    "qs:gn_namadm1":"57",
    "qs:gn_name":"Dradeb",
    "qs:local_max":5563,
    "qs:local_sum":5563,
    "qs:localhoods":1,
    "qs:name":"Dradeb",
    "qs:name_adm0":"\u0627\u0644\u0645\u063a\u0631\u0628",
    "qs:name_adm1":"\u0637\u0646\u062c\u0629\u0640 \u062a\u0637\u0648\u0627\u0646",
    "qs:name_adm2":"\u0637\u0646\u062c\u0629 \u0623\u0635\u064a\u0644\u0629",
    "qs:name_lau":"\u0637\u0646\u062c\u0629",
    "qs:name_local":"\u0637\u0646\u062c\u0629",
    "qs:photo_max":895,
    "qs:photo_sum":5563,
    "qs:placetype":"Suburb",
    "qs:quad_count":99,
    "qs:woe_adm0":23424893,
    "qs:woe_adm1":56120062,
    "qs:woe_adm2":56120064,
    "qs:woe_lau":56439610,
    "qs:woe_local":1540935,
    "qs:woe_ver":"7.10.0",
    "wof:lang":[
        "ara"
    ],
    "wof:name":"Dradeb",
    "wof:placetype":"neighbourhood"
},
  "geometry": {"coordinates":[-5.811609,35.787175],"type":"Point"}
}