{
  "type": "Feature",
  "properties": {
    "gn:admin1_code":"09",
    "gn:asciiname":"Adad",
    "gn:country_code":"MA",
    "gn:dem":2230,
    "gn:feature_class":"P",
    "gn:feature_code":"PPL",
    "gn:name":"Adad",
    "gn:population":0,
    "gn:timezone":"Africa/Casablanca",
    "iso:country":"MA",
    "name:und_x_variant":[
        "Idad",
        "Adad"
    ],
    "wof:name":"Adad",
    "wof:placetype":"locality"
},
  "geometry": {"coordinates":[-7.75509,31.03042],"type":"Point"}
}