{
  "type": "Feature",
  "properties": {
    "gn:admin1_code":"7.0",
    "gn:asciiname":"Ech Chouihia",
    "gn:country_code":"MA",
    "gn:dem":644,
    "gn:feature_class":"P",
    "gn:feature_code":"PPL",
    "gn:name":"Ech Chouihia",
    "gn:population":0,
    "gn:timezone":"Africa/Casablanca",
    "iso:country":"MA",
    "wof:name":"Ech Chouihia",
    "wof:placetype":"locality"
},
  "geometry": {"coordinates":[-8.53748,31.31102000000001],"type":"Point"}
}