{
  "type": "Feature",
  "properties": {
    "gn:admin1_code":"10",
    "gn:asciiname":"Tihuma Ou Senag",
    "gn:country_code":"MA",
    "gn:dem":444,
    "gn:feature_class":"P",
    "gn:feature_code":"PPL",
    "gn:name":"Tihuma Ou Senag",
    "gn:population":0,
    "gn:timezone":"Africa/Casablanca",
    "iso:country":"MA",
    "name:und_x_variant":[
        "Tihouma ou Senag",
        "Tihuna U Senag",
        "Tihuma Ou Senag"
    ],
    "wof:name":"Tihuma Ou Senag",
    "wof:placetype":"locality"
},
  "geometry": {"coordinates":[-10.09375,29.19238],"type":"Point"}
}