{
  "type": "Feature",
  "properties": {
    "gn:admin1_code":"9.0",
    "gn:asciiname":"Ouagga",
    "gn:country_code":"MA",
    "gn:dem":424,
    "gn:feature_class":"P",
    "gn:feature_code":"PPL",
    "gn:name":"Ouagga",
    "gn:population":0,
    "gn:timezone":"Africa/Casablanca",
    "iso:country":"MA",
    "wof:name":"Ouagga",
    "wof:placetype":"locality"
},
  "geometry": {"coordinates":[-9.69467,30.78623],"type":"Point"}
}