{
  "type": "Feature",
  "properties": {
    "gn:admin1_code":"3.0",
    "gn:asciiname":"Lqallahne",
    "gn:country_code":"MA",
    "gn:dem":483,
    "gn:feature_class":"P",
    "gn:feature_code":"PPL",
    "gn:name":"Lqallahne",
    "gn:population":0,
    "gn:timezone":"Africa/Casablanca",
    "iso:country":"MA",
    "wof:name":"Lqallahne",
    "wof:placetype":"locality"
},
  "geometry": {"coordinates":[-5.05326,34.58377],"type":"Point"}
}