{
  "type": "Feature",
  "properties": {
    "gn:admin1_code":"3.0",
    "gn:asciiname":"Douar Leqbib Echarqi",
    "gn:country_code":"MA",
    "gn:dem":249,
    "gn:feature_class":"P",
    "gn:feature_code":"PPL",
    "gn:name":"Douar Leqbib Echarqi",
    "gn:population":0,
    "gn:timezone":"Africa/Casablanca",
    "iso:country":"MA",
    "wof:name":"Douar Leqbib Echarqi",
    "wof:placetype":"locality"
},
  "geometry": {"coordinates":[-4.67534,34.32216],"type":"Point"}
}