{
  "type": "Feature",
  "properties": {
    "gn:admin1_code":"7.0",
    "gn:asciiname":"Sbabha",
    "gn:country_code":"MA",
    "gn:dem":262,
    "gn:feature_class":"P",
    "gn:feature_code":"PPL",
    "gn:name":"Sbabha",
    "gn:population":0,
    "gn:timezone":"Africa/Casablanca",
    "iso:country":"MA",
    "wof:name":"Sbabha",
    "wof:placetype":"locality"
},
  "geometry": {"coordinates":[-8.78038,31.88716],"type":"Point"}
}