{
  "type": "Feature",
  "properties": {
    "gn:admin1_code":"9.0",
    "gn:asciiname":"Tinghriyt",
    "gn:country_code":"MA",
    "gn:dem":1022,
    "gn:feature_class":"P",
    "gn:feature_code":"PPL",
    "gn:name":"Tinghriyt",
    "gn:population":0,
    "gn:timezone":"Africa/Casablanca",
    "iso:country":"MA",
    "wof:name":"Tinghriyt",
    "wof:placetype":"locality"
},
  "geometry": {"coordinates":[-9.22124,29.73934],"type":"Point"}
}