{
  "type": "Feature",
  "properties": {
    "gn:admin1_code":"05",
    "gn:asciiname":"Techoued",
    "gn:country_code":"MA",
    "gn:dem":1310,
    "gn:feature_class":"P",
    "gn:feature_code":"PPL",
    "gn:name":"Techoued",
    "gn:population":0,
    "gn:timezone":"Africa/Casablanca",
    "iso:country":"MA",
    "wof:name":"Techoued",
    "wof:placetype":"locality"
},
  "geometry": {"coordinates":[-5.48731,32.81837],"type":"Point"}
}