{
  "type": "Feature",
  "properties": {
    "gn:admin1_code":"9.0",
    "gn:asciiname":"Douar Bou Ghandane Izeddour",
    "gn:country_code":"MA",
    "gn:dem":110,
    "gn:feature_class":"P",
    "gn:feature_code":"PPL",
    "gn:name":"Douar Bou Ghandane Izeddour",
    "gn:population":0,
    "gn:timezone":"Africa/Casablanca",
    "iso:country":"MA",
    "wof:name":"Douar Bou Ghandane Izeddour",
    "wof:placetype":"locality"
},
  "geometry": {"coordinates":[-9.98447,29.61794],"type":"Point"}
}