{
  "type": "Feature",
  "properties": {
    "gn:admin1_code":"3.0",
    "gn:asciiname":"Douar Mellaha Sidi Youssef",
    "gn:country_code":"MA",
    "gn:dem":705,
    "gn:feature_class":"P",
    "gn:feature_code":"PPL",
    "gn:name":"Douar Mellaha Sidi Youssef",
    "gn:population":0,
    "gn:timezone":"Africa/Casablanca",
    "iso:country":"MA",
    "wof:name":"Douar Mellaha Sidi Youssef",
    "wof:placetype":"locality"
},
  "geometry": {"coordinates":[-4.56324,33.75368],"type":"Point"}
}