{
  "type": "Feature",
  "properties": {
    "gn:admin1_code":"05",
    "gn:asciiname":"Imi-n Ta'abdiyt",
    "gn:country_code":"MA",
    "gn:dem":1566,
    "gn:elevation":"0.0",
    "gn:feature_class":"P",
    "gn:feature_code":"PPL",
    "gn:name":"Imi-n Ta\u2019abdiyt",
    "gn:population":0,
    "gn:timezone":"Africa/Casablanca",
    "iso:country":"MA",
    "name:und_x_variant":[
        "Imi-n Ta\u2019abdiyt",
        "Ta\u2018bdit"
    ],
    "wof:name":"Imi-n Ta'abdiyt",
    "wof:placetype":"locality"
},
  "geometry": {"coordinates":[-6.52488,31.96348],"type":"Point"}
}