{
  "type": "Feature",
  "properties": {
    "gn:admin1_code":"10",
    "gn:asciiname":"Id Abdallah Ou Said",
    "gn:country_code":"MA",
    "gn:dem":1086,
    "gn:feature_class":"P",
    "gn:feature_code":"PPL",
    "gn:name":"Id Abdallah Ou Sa\u00efd",
    "gn:population":0,
    "gn:timezone":"Africa/Casablanca",
    "iso:country":"MA",
    "wof:name":"Id Abdallah Ou Said",
    "wof:placetype":"locality"
},
  "geometry": {"coordinates":[-9.72336,29.26566],"type":"Point"}
}