{
  "type": "Feature",
  "properties": {
    "gn:admin1_code":"7.0",
    "gn:asciiname":"H'ritiers Ammiguina Mohamed Ben Ayyouch",
    "gn:country_code":"MA",
    "gn:dem":363,
    "gn:feature_class":"P",
    "gn:feature_code":"PPL",
    "gn:name":"H\u2019ritiers Ammiguina Mohamed Ben Ayyouch",
    "gn:population":0,
    "gn:timezone":"Africa/Casablanca",
    "iso:country":"MA",
    "wof:name":"H'ritiers Ammiguina Mohamed Ben Ayyouch",
    "wof:placetype":"locality"
},
  "geometry": {"coordinates":[-8.47875,31.60644000000001],"type":"Point"}
}