{
  "type": "Feature",
  "properties": {
    "gn:admin1_code":"09",
    "gn:asciiname":"Ait Ben 'Issa",
    "gn:country_code":"MA",
    "gn:dem":1135,
    "gn:feature_class":"P",
    "gn:feature_code":"PPL",
    "gn:name":"A\u00eft Ben \u2019Issa",
    "gn:population":0,
    "gn:timezone":"Africa/Casablanca",
    "iso:country":"MA",
    "name:und_x_variant":[
        "A\u00eft Bou A\u00efss",
        "A\u00eft Ben A\u00efss",
        "A\u00eft Ben \u2019Issa"
    ],
    "wof:name":"Ait Ben 'Issa",
    "wof:placetype":"locality"
},
  "geometry": {"coordinates":[-8.95856,29.8605],"type":"Point"}
}