{
  "type": "Feature",
  "properties": {
    "gn:admin1_code":"3.0",
    "gn:asciiname":"Douar Ait Aissa Addi",
    "gn:country_code":"MA",
    "gn:dem":553,
    "gn:feature_class":"P",
    "gn:feature_code":"PPL",
    "gn:name":"Douar Ait Aissa Addi",
    "gn:population":0,
    "gn:timezone":"Africa/Casablanca",
    "iso:country":"MA",
    "wof:name":"Douar Ait Aissa Addi",
    "wof:placetype":"locality"
},
  "geometry": {"coordinates":[-5.68088,33.83341],"type":"Point"}
}