{
  "type": "Feature",
  "properties": {
    "gn:admin1_code":"7.0",
    "gn:asciiname":"Oulad Ben Laaroussi",
    "gn:country_code":"MA",
    "gn:dem":149,
    "gn:feature_class":"P",
    "gn:feature_code":"PPL",
    "gn:name":"Oulad Ben Laaroussi",
    "gn:population":0,
    "gn:timezone":"Africa/Casablanca",
    "iso:country":"MA",
    "wof:name":"Oulad Ben Laaroussi",
    "wof:placetype":"locality"
},
  "geometry": {"coordinates":[-8.95984,32.2962],"type":"Point"}
}