{
  "type": "Feature",
  "properties": {
    "gn:admin1_code":"6.0",
    "gn:asciiname":"Cooperative Lhassaniya",
    "gn:country_code":"MA",
    "gn:dem":274,
    "gn:feature_class":"P",
    "gn:feature_code":"PPLF",
    "gn:name":"Coop\u00e9rative Lhassaniya",
    "gn:population":0,
    "gn:timezone":"Africa/Casablanca",
    "iso:country":"MA",
    "wof:name":"Cooperative Lhassaniya",
    "wof:placetype":"neighbourhood"
},
  "geometry": {"coordinates":[-7.11264,33.58203],"type":"Point"}
}