{
  "type": "Feature",
  "properties": {
    "gn:admin1_code":"09",
    "gn:asciiname":"Aguerdane",
    "gn:country_code":"MA",
    "gn:dem":1351,
    "gn:feature_class":"P",
    "gn:feature_code":"PPL",
    "gn:name":"Aguerdane",
    "gn:population":0,
    "gn:timezone":"Africa/Casablanca",
    "iso:country":"MA",
    "name:und_x_variant":[
        "Agardane",
        "Aguerdane"
    ],
    "wof:name":"Aguerdane",
    "wof:placetype":"locality"
},
  "geometry": {"coordinates":[-8.2921,30.29421],"type":"Point"}
}