{
  "type": "Feature",
  "properties": {
    "gn:admin1_code":"01",
    "gn:asciiname":"Ayaouach",
    "gn:country_code":"MA",
    "gn:dem":345,
    "gn:feature_class":"P",
    "gn:feature_code":"PPL",
    "gn:name":"Ayaouach",
    "gn:population":0,
    "gn:timezone":"Africa/Casablanca",
    "iso:country":"MA",
    "name:und_x_variant":[
        "Aiaouech"
    ],
    "wof:name":"Ayaouach",
    "wof:placetype":"locality"
},
  "geometry": {"coordinates":[-5.46121,35.39415],"type":"Point"}
}