{
  "type": "Feature",
  "properties": {
    "gn:admin1_code":"1.0",
    "gn:asciiname":"Nounyech",
    "gn:country_code":"MA",
    "gn:dem":485,
    "gn:feature_class":"P",
    "gn:feature_code":"PPL",
    "gn:name":"Nounyech",
    "gn:population":0,
    "gn:timezone":"Africa/Casablanca",
    "iso:country":"MA",
    "wof:name":"Nounyech",
    "wof:placetype":"locality"
},
  "geometry": {"coordinates":[-5.49401,35.49249000000001],"type":"Point"}
}