{
  "type": "Feature",
  "properties": {
    "gn:admin1_code":"09",
    "gn:asciiname":"Zawyat Sidi 'Abdallah Bourjg",
    "gn:country_code":"MA",
    "gn:dem":1217,
    "gn:feature_class":"P",
    "gn:feature_code":"PPL",
    "gn:name":"Zawyat Sidi \u2019Abdallah Bourjg",
    "gn:population":0,
    "gn:timezone":"Africa/Casablanca",
    "iso:country":"MA",
    "name:und_x_variant":[
        "Zawyat Sidi \u2019Abdallah Bourjg",
        "Sidi Abdallah Ou Bourzig"
    ],
    "wof:name":"Zawyat Sidi 'Abdallah Bourjg",
    "wof:placetype":"locality"
},
  "geometry": {"coordinates":[-8.01097,30.68711],"type":"Point"}
}