{
  "type": "Feature",
  "properties": {
    "gn:admin1_code":"7.0",
    "gn:asciiname":"Dar Oulad Braham",
    "gn:country_code":"MA",
    "gn:dem":442,
    "gn:feature_class":"P",
    "gn:feature_code":"PPL",
    "gn:name":"Dar Oulad Braham",
    "gn:population":0,
    "gn:timezone":"Africa/Casablanca",
    "iso:country":"MA",
    "wof:name":"Dar Oulad Braham",
    "wof:placetype":"locality"
},
  "geometry": {"coordinates":[-7.85582,32.16238],"type":"Point"}
}