{
  "type": "Feature",
  "properties": {
    "gn:country":"MA",
    "gn:fcode":"ADM3",
    "gn:population":11916,
    "iso:country":"MA",
    "name:ara_x_preferred":[
        "\u0643\u0631\u0627\u0645\u0629"
    ],
    "name:fra_x_preferred":[
        "Guers Tiaallaline"
    ],
    "name:fra_x_variant":[
        "Guers Tiaallaline (CR)",
        "Guers Tiaallaline (Commune Rurale)"
    ],
    "qs:name":"Guers Tiaallaline",
    "qs:photos_9r":0,
    "qs:photos_sr":0,
    "qs:pop_sr":"6",
    "wof:name":"Guers Tiaallaline",
    "wof:placetype":"localadmin",
    "wof:population":11916
},
  "geometry": {"coordinates":[-4.45538,32.22416],"type":"Point"}
}