{
  "type": "Feature",
  "properties": {
    "gn:admin1_code":"9.0",
    "gn:asciiname":"Douar Iragragume",
    "gn:country_code":"MA",
    "gn:dem":306,
    "gn:feature_class":"P",
    "gn:feature_code":"PPL",
    "gn:name":"Douar Iragragume",
    "gn:population":0,
    "gn:timezone":"Africa/Casablanca",
    "iso:country":"MA",
    "wof:name":"Douar Iragragume",
    "wof:placetype":"locality"
},
  "geometry": {"coordinates":[-9.77881,30.7814],"type":"Point"}
}