{
  "type": "Feature",
  "properties": {
    "gn:admin1_code":"01",
    "gn:asciiname":"Douar El Mellaliyine",
    "gn:country_code":"MA",
    "gn:dem":68,
    "gn:feature_class":"P",
    "gn:feature_code":"PPL",
    "gn:name":"Douar El Mellaliyine",
    "gn:population":0,
    "gn:timezone":"Africa/Casablanca",
    "iso:country":"MA",
    "name:und_x_variant":[
        "Malalien",
        "El Melalien",
        "Malalene",
        "El Mellaliyine",
        "El Mellaliyene",
        "El Malaliyine",
        "Douar El Mellaliyine"
    ],
    "wof:name":"Douar El Mellaliyine",
    "wof:placetype":"locality"
},
  "geometry": {"coordinates":[-5.3406,35.62605],"type":"Point"}
}