{
  "type": "Feature",
  "properties": {
    "gn:country":"MA",
    "gn:fcode":"ADM3",
    "gn:population":9759,
    "iso:country":"MA",
    "name:ara_x_preferred":[
        "\u0623\u064a\u062a \u0645\u064a\u0645\u0648\u0646"
    ],
    "name:ara_x_variant":[
        "\u0633\u064a\u062f\u064a \u0644\u062d\u0633\u0646"
    ],
    "name:ary_x_preferred":[
        "\u0633\u064a\u062f\u064a \u0644\u062d\u0633\u0646"
    ],
    "name:cat_x_preferred":[
        "Sidi Lahsen"
    ],
    "name:ceb_x_preferred":[
        "Sidi Lahsen"
    ],
    "name:eng_x_preferred":[
        "Sidi Lahsen"
    ],
    "name:fra_x_preferred":[
        "Sidi Lahsen"
    ],
    "name:fra_x_variant":[
        "Sidi Lahsen (CR)",
        "Sidi Lahsen (Commune Rurale)",
        "Sidi Lahcen"
    ],
    "name:ita_x_preferred":[
        "Sidi Lahcen"
    ],
    "name:swe_x_preferred":[
        "Sidi Lahsen"
    ],
    "qs:name":"Sidi Lahsen",
    "qs:photos_9r":0,
    "qs:photos_sr":0,
    "qs:pop_sr":"5",
    "wd:wordcount":78,
    "wof:name":"Sidi Lahsen",
    "wof:placetype":"localadmin",
    "wof:population":9759
},
  "geometry": {"coordinates":[-2.66973,34.02856],"type":"Point"}
}