{
  "type": "Feature",
  "properties": {
    "gn:admin1_code":"01",
    "gn:asciiname":"El Blat",
    "gn:country_code":"MA",
    "gn:dem":615,
    "gn:feature_class":"P",
    "gn:feature_code":"PPL",
    "gn:name":"El Blat",
    "gn:population":0,
    "gn:timezone":"Africa/Casablanca",
    "iso:country":"MA",
    "name:und_x_variant":[
        "El Blate",
        "El Blat"
    ],
    "wof:name":"El Blat",
    "wof:placetype":"locality"
},
  "geometry": {"coordinates":[-4.98572,34.90783],"type":"Point"}
}