{
  "type": "Feature",
  "properties": {
    "gn:country":"MA",
    "gn:fcode":"ADM3",
    "gn:pop":29851,
    "iso:country":"MA",
    "name:ara_x_preferred":[
        "\u0627\u0644\u0646\u0627\u0636\u0648\u0631 (\u0627\u0644\u0628\u0644\u062f\u064a\u0629)"
    ],
    "name:ara_x_variant":[
        "\u0632\u0627\u064a\u0648"
    ],
    "name:azb_x_preferred":[
        "\u0632\u0627\u06cc\u0648"
    ],
    "name:cat_x_preferred":[
        "Zaio"
    ],
    "name:ceb_x_preferred":[
        "Za\u00efo"
    ],
    "name:deu_x_preferred":[
        "Zaio"
    ],
    "name:eng_x_preferred":[
        "Zaio"
    ],
    "name:eus_x_preferred":[
        "Zaio"
    ],
    "name:fas_x_preferred":[
        "\u0632\u0627\u06cc\u0648"
    ],
    "name:fra_x_preferred":[
        "Zaio"
    ],
    "name:fra_x_variant":[
        "Zaio (MU)",
        "Zaio (Commune Urbaine)",
        "Za\u00efo"
    ],
    "name:ita_x_preferred":[
        "Zaio"
    ],
    "name:nld_x_preferred":[
        "Zaio"
    ],
    "name:swe_x_preferred":[
        "Za\u00efo"
    ],
    "qs:name":"Zaio",
    "qs:photos_9r":0,
    "qs:photos_sr":0,
    "qs:pop_sr":"7",
    "wd:population":35806,
    "wd:wordcount":95,
    "wof:name":"Zaio",
    "wof:placetype":"localadmin",
    "wof:population":35806
},
  "geometry": {"coordinates":[-2.74358,34.93681],"type":"Point"}
}