{
  "type": "Feature",
  "properties": {
    "gn:admin1_code":"4.0",
    "gn:asciiname":"Zhourat",
    "gn:country_code":"MA",
    "gn:dem":7,
    "gn:feature_class":"P",
    "gn:feature_code":"PPL",
    "gn:name":"Zhourat",
    "gn:population":0,
    "gn:timezone":"Africa/Casablanca",
    "iso:country":"MA",
    "wof:name":"Zhourat",
    "wof:placetype":"locality"
},
  "geometry": {"coordinates":[-6.505,34.37394],"type":"Point"}
}