{
  "type": "Feature",
  "properties": {
    "gn:admin1_code":"7.0",
    "gn:asciiname":"Ighdas",
    "gn:country_code":"MA",
    "gn:dem":539,
    "gn:feature_class":"P",
    "gn:feature_code":"PPL",
    "gn:name":"Ighdas",
    "gn:population":0,
    "gn:timezone":"Africa/Casablanca",
    "iso:country":"MA",
    "wof:name":"Ighdas",
    "wof:placetype":"locality"
},
  "geometry": {"coordinates":[-9.5152,31.24436],"type":"Point"}
}