{
  "type": "Feature",
  "properties": {
    "gn:admin1_code":"1.0",
    "gn:asciiname":"Sidi Ahmed El Bakkar",
    "gn:country_code":"MA",
    "gn:dem":390,
    "gn:feature_class":"P",
    "gn:feature_code":"PPL",
    "gn:name":"Sidi Ahmed El Bakkar",
    "gn:population":0,
    "gn:timezone":"Africa/Casablanca",
    "iso:country":"MA",
    "wof:name":"Sidi Ahmed El Bakkar",
    "wof:placetype":"locality"
},
  "geometry": {"coordinates":[-4.71767,35.12622],"type":"Point"}
}