{
  "type": "Feature",
  "properties": {
    "gn:admin1_code":"2.0",
    "gn:asciiname":"Debboura",
    "gn:country_code":"MA",
    "gn:dem":875,
    "gn:feature_class":"P",
    "gn:feature_code":"PPL",
    "gn:name":"Debboura",
    "gn:population":0,
    "gn:timezone":"Africa/Casablanca",
    "iso:country":"MA",
    "wof:name":"Debboura",
    "wof:placetype":"locality"
},
  "geometry": {"coordinates":[-2.14713,34.53695],"type":"Point"}
}