{
  "type": "Feature",
  "properties": {
    "gn:admin1_code":"07",
    "gn:asciiname":"Douar Mrimdat",
    "gn:country_code":"MA",
    "gn:dem":551,
    "gn:feature_class":"P",
    "gn:feature_code":"PPL",
    "gn:name":"Douar Mrimdat",
    "gn:population":0,
    "gn:timezone":"Africa/Casablanca",
    "iso:country":"MA",
    "name:und_x_variant":[
        "Douar Oulad Ahmida"
    ],
    "wof:name":"Douar Mrimdat",
    "wof:placetype":"locality"
},
  "geometry": {"coordinates":[-8.29354,31.8972],"type":"Point"}
}