{
  "type": "Feature",
  "properties": {
    "gn:admin1_code":"09",
    "gn:asciiname":"Douar Agadi",
    "gn:country_code":"MA",
    "gn:dem":235,
    "gn:feature_class":"P",
    "gn:feature_code":"PPL",
    "gn:name":"Douar Agadi",
    "gn:population":0,
    "gn:timezone":"Africa/Casablanca",
    "iso:country":"MA",
    "name:und_x_variant":[
        "Agadir Ikechrane",
        "Iguechrane"
    ],
    "wof:name":"Douar Agadi",
    "wof:placetype":"locality"
},
  "geometry": {"coordinates":[-9.9207,29.57348],"type":"Point"}
}