{
  "type": "Feature",
  "properties": {
    "gn:admin1_code":"07",
    "gn:asciiname":"Douar Chrabli",
    "gn:country_code":"MA",
    "gn:dem":578,
    "gn:feature_class":"P",
    "gn:feature_code":"PPL",
    "gn:name":"Douar Chrabli",
    "gn:population":0,
    "gn:timezone":"Africa/Casablanca",
    "iso:country":"MA",
    "name:und_x_variant":[
        "Chrabli"
    ],
    "wof:name":"Douar Chrabli",
    "wof:placetype":"locality"
},
  "geometry": {"coordinates":[-7.84687,31.52409],"type":"Point"}
}