{
  "type": "Feature",
  "properties": {
    "gn:admin1_code":"01",
    "gn:asciiname":"Douar Tioueghza",
    "gn:country_code":"MA",
    "gn:dem":89,
    "gn:feature_class":"P",
    "gn:feature_code":"PPL",
    "gn:name":"Douar Tioueghza",
    "gn:population":0,
    "gn:timezone":"Africa/Casablanca",
    "iso:country":"MA",
    "name:und_x_variant":[
        "Tugsa",
        "Tioughzat",
        "Tiougsa",
        "Douar Tioueghza"
    ],
    "wof:name":"Douar Tioueghza",
    "wof:placetype":"locality"
},
  "geometry": {"coordinates":[-4.98106,35.26954],"type":"Point"}
}