{
  "type": "Feature",
  "properties": {
    "gn:admin1_code":"6.0",
    "gn:asciiname":"Dar Caid El Houari",
    "gn:country_code":"MA",
    "gn:dem":67,
    "gn:feature_class":"P",
    "gn:feature_code":"PPL",
    "gn:name":"Dar Ca\u00efd El Houari",
    "gn:population":0,
    "gn:timezone":"Africa/Casablanca",
    "iso:country":"MA",
    "wof:name":"Dar Caid El Houari",
    "wof:placetype":"locality"
},
  "geometry": {"coordinates":[-8.48576,33.03371],"type":"Point"}
}