{
  "type": "Feature",
  "properties": {
    "gn:admin1_code":"01",
    "gn:asciiname":"Bni Hdayene",
    "gn:country_code":"MA",
    "gn:dem":141,
    "gn:feature_class":"P",
    "gn:feature_code":"PPL",
    "gn:name":"Bni Hdayene",
    "gn:population":0,
    "gn:timezone":"Africa/Casablanca",
    "iso:country":"MA",
    "name:und_x_variant":[
        "Beni Hada\u00efne",
        "Beni Hadene",
        "Beni Hada\u00efn",
        "Bni Hdayene"
    ],
    "wof:name":"Bni Hdayene",
    "wof:placetype":"locality"
},
  "geometry": {"coordinates":[-5.79436,35.43131],"type":"Point"}
}