{
  "type": "Feature",
  "properties": {
    "gn:admin1_code":"9.0",
    "gn:asciiname":"Barguenna",
    "gn:country_code":"MA",
    "gn:dem":107,
    "gn:feature_class":"P",
    "gn:feature_code":"PPL",
    "gn:name":"Barguenna",
    "gn:population":0,
    "gn:timezone":"Africa/Casablanca",
    "iso:country":"MA",
    "wof:name":"Barguenna",
    "wof:placetype":"locality"
},
  "geometry": {"coordinates":[-9.75652,30.72014],"type":"Point"}
}