{
  "type": "Feature",
  "properties": {
    "gn:admin1_code":"5.0",
    "gn:asciiname":"Tassa-n-Ouzaddiyr",
    "gn:country_code":"MA",
    "gn:dem":1599,
    "gn:feature_class":"P",
    "gn:feature_code":"PPL",
    "gn:name":"Tassa-n-Ouzaddiyr",
    "gn:population":0,
    "gn:timezone":"Africa/Casablanca",
    "iso:country":"MA",
    "wof:name":"Tassa-n-Ouzaddiyr",
    "wof:placetype":"locality"
},
  "geometry": {"coordinates":[-6.53056,31.92499],"type":"Point"}
}