{
  "type": "Feature",
  "properties": {
    "gn:admin1_code":"07",
    "gn:asciiname":"Oulad Salem",
    "gn:country_code":"MA",
    "gn:dem":406,
    "gn:feature_class":"P",
    "gn:feature_code":"PPL",
    "gn:name":"Oulad Salem",
    "gn:population":0,
    "gn:timezone":"Africa/Casablanca",
    "iso:country":"MA",
    "name:und_x_variant":[
        "Oulad-Sellam"
    ],
    "wof:name":"Oulad Salem",
    "wof:placetype":"locality"
},
  "geometry": {"coordinates":[-8.72572,32.05294],"type":"Point"}
}