{
  "type": "Feature",
  "properties": {
    "gn:admin1_code":"56",
    "gn:asciiname":"Oulad Slimane",
    "gn:country_code":"MA",
    "gn:dem":393,
    "gn:feature_class":"P",
    "gn:feature_code":"PPL",
    "gn:name":"Oulad Slimane",
    "gn:population":0,
    "gn:timezone":"Africa/Casablanca",
    "iso:country":"MA",
    "wof:name":"Oulad Slimane",
    "wof:placetype":"locality"
},
  "geometry": {"coordinates":[-6.75,32.33],"type":"Point"}
}