{
  "type": "Feature",
  "properties": {
    "gn:admin1_code":"7.0",
    "gn:asciiname":"Douar Ait Laadraoui",
    "gn:country_code":"MA",
    "gn:dem":593,
    "gn:feature_class":"P",
    "gn:feature_code":"PPL",
    "gn:name":"Douar Ait Laadraoui",
    "gn:population":0,
    "gn:timezone":"Africa/Casablanca",
    "iso:country":"MA",
    "wof:name":"Douar Ait Laadraoui",
    "wof:placetype":"locality"
},
  "geometry": {"coordinates":[-7.55123,31.70081],"type":"Point"}
}