{
  "type": "Feature",
  "properties": {
    "gn:admin1_code":"02",
    "gn:asciiname":"Tirni",
    "gn:country_code":"MA",
    "gn:dem":1458,
    "gn:feature_class":"P",
    "gn:feature_code":"PPL",
    "gn:name":"Tirni",
    "gn:population":0,
    "gn:timezone":"Africa/Casablanca",
    "iso:country":"MA",
    "name:und_x_variant":[
        "Et Terni ou Ouaouerni",
        "Tirni"
    ],
    "wof:name":"Tirni",
    "wof:placetype":"locality"
},
  "geometry": {"coordinates":[-3.57305,34.56095999999999],"type":"Point"}
}