{
  "type": "Feature",
  "properties": {
    "gn:admin1_code":"06",
    "gn:asciiname":"Douar Oulad Youssef",
    "gn:country_code":"MA",
    "gn:dem":86,
    "gn:feature_class":"P",
    "gn:feature_code":"PPL",
    "gn:name":"Douar Oulad Youssef",
    "gn:population":0,
    "gn:timezone":"Africa/Casablanca",
    "iso:country":"MA",
    "name:und_x_variant":[
        "Oulad Youssef"
    ],
    "wof:name":"Douar Oulad Youssef",
    "wof:placetype":"locality"
},
  "geometry": {"coordinates":[-8.99764,32.74683],"type":"Point"}
}