{
  "type": "Feature",
  "properties": {
    "gn:admin1_code":"9.0",
    "gn:asciiname":"Ezzeganine",
    "gn:country_code":"MA",
    "gn:dem":388,
    "gn:feature_class":"P",
    "gn:feature_code":"PPL",
    "gn:name":"Ezzeganine",
    "gn:population":0,
    "gn:timezone":"Africa/Casablanca",
    "iso:country":"MA",
    "wof:name":"Ezzeganine",
    "wof:placetype":"locality"
},
  "geometry": {"coordinates":[-9.62636,29.60292],"type":"Point"}
}