{
  "type": "Feature",
  "properties": {
    "gn:admin1_code":"6.0",
    "gn:asciiname":"Douar Lekhdar",
    "gn:country_code":"MA",
    "gn:dem":221,
    "gn:feature_class":"P",
    "gn:feature_code":"PPL",
    "gn:name":"Douar Lekhdar",
    "gn:population":0,
    "gn:timezone":"Africa/Casablanca",
    "iso:country":"MA",
    "wof:name":"Douar Lekhdar",
    "wof:placetype":"locality"
},
  "geometry": {"coordinates":[-8.41569,32.52765],"type":"Point"}
}