{
  "type": "Feature",
  "properties": {
    "gn:admin1_code":"1.0",
    "gn:asciiname":"Aqmoumene",
    "gn:country_code":"MA",
    "gn:dem":143,
    "gn:feature_class":"P",
    "gn:feature_code":"PPL",
    "gn:name":"Aqmoumene",
    "gn:population":0,
    "gn:timezone":"Africa/Casablanca",
    "iso:country":"MA",
    "wof:name":"Aqmoumene",
    "wof:placetype":"locality"
},
  "geometry": {"coordinates":[-5.13196,35.44999],"type":"Point"}
}