{
  "type": "Feature",
  "properties": {
    "gn:admin1_code":"9.0",
    "gn:asciiname":"Ait Ben Kourt",
    "gn:country_code":"MA",
    "gn:dem":190,
    "gn:feature_class":"P",
    "gn:feature_code":"PPL",
    "gn:name":"A\u00eft Ben Kourt",
    "gn:population":0,
    "gn:timezone":"Africa/Casablanca",
    "iso:country":"MA",
    "wof:name":"Ait Ben Kourt",
    "wof:placetype":"locality"
},
  "geometry": {"coordinates":[-9.09012,30.28052000000001],"type":"Point"}
}