{
  "type": "Feature",
  "properties": {
    "gn:admin1_code":"4.0",
    "gn:asciiname":"Douar Lemkhalif",
    "gn:country_code":"MA",
    "gn:dem":207,
    "gn:feature_class":"P",
    "gn:feature_code":"PPL",
    "gn:name":"Douar Lemkhalif",
    "gn:population":0,
    "gn:timezone":"Africa/Casablanca",
    "iso:country":"MA",
    "wof:name":"Douar Lemkhalif",
    "wof:placetype":"locality"
},
  "geometry": {"coordinates":[-6.96096,33.74281],"type":"Point"}
}