{
  "type": "Feature",
  "properties": {
    "gn:admin1_code":"05",
    "gn:asciiname":"Tamatsift",
    "gn:country_code":"MA",
    "gn:dem":1736,
    "gn:elevation":"0.0",
    "gn:feature_class":"P",
    "gn:feature_code":"PPL",
    "gn:name":"Tamatsift",
    "gn:population":0,
    "gn:timezone":"Africa/Casablanca",
    "iso:country":"MA",
    "name:und_x_variant":[
        "Tametsift"
    ],
    "wof:name":"Tamatsift",
    "wof:placetype":"locality"
},
  "geometry": {"coordinates":[-6.64315,31.68313],"type":"Point"}
}