{
  "type": "Feature",
  "properties": {
    "gn:admin1_code":"03",
    "gn:asciiname":"Beni Izzou",
    "gn:country_code":"MA",
    "gn:dem":394,
    "gn:feature_class":"P",
    "gn:feature_code":"PPL",
    "gn:name":"Beni Izzou",
    "gn:population":0,
    "gn:timezone":"Africa/Casablanca",
    "iso:country":"MA",
    "name:und_x_variant":[
        "Beni Izou",
        "Beni Izzou"
    ],
    "wof:name":"Beni Izzou",
    "wof:placetype":"locality"
},
  "geometry": {"coordinates":[-4.88286,34.65456],"type":"Point"}
}