{
  "type": "Feature",
  "properties": {
    "gn:admin1_code":"8.0",
    "gn:asciiname":"Awjja-n-Wizargane",
    "gn:country_code":"MA",
    "gn:dem":1505,
    "gn:feature_class":"P",
    "gn:feature_code":"PPL",
    "gn:name":"Awjja-n-Wizargane",
    "gn:population":0,
    "gn:timezone":"Africa/Casablanca",
    "iso:country":"MA",
    "wof:name":"Awjja-n-Wizargane",
    "wof:placetype":"locality"
},
  "geometry": {"coordinates":[-6.08734,31.16767],"type":"Point"}
}