{
  "type": "Feature",
  "properties": {
    "gn:admin1_code":"6.0",
    "gn:asciiname":"Douar Santia",
    "gn:country_code":"MA",
    "gn:dem":466,
    "gn:feature_class":"P",
    "gn:feature_code":"PPL",
    "gn:name":"Douar Santia",
    "gn:population":0,
    "gn:timezone":"Africa/Casablanca",
    "iso:country":"MA",
    "wof:name":"Douar Santia",
    "wof:placetype":"locality"
},
  "geometry": {"coordinates":[-7.45581,32.60385],"type":"Point"}
}