{
  "type": "Feature",
  "properties": {
    "gn:admin1_code":"04",
    "gn:asciiname":"Syakka",
    "gn:country_code":"MA",
    "gn:dem":105,
    "gn:feature_class":"P",
    "gn:feature_code":"PPL",
    "gn:name":"Syakka",
    "gn:population":0,
    "gn:timezone":"Africa/Casablanca",
    "iso:country":"MA",
    "name:und_x_variant":[
        "Siaka"
    ],
    "wof:name":"Syakka",
    "wof:placetype":"locality"
},
  "geometry": {"coordinates":[-5.89695,34.64624],"type":"Point"}
}