{
  "type": "Feature",
  "properties": {
    "gn:admin1_code":"9.0",
    "gn:asciiname":"Bou Zouggar",
    "gn:country_code":"MA",
    "gn:dem":149,
    "gn:feature_class":"P",
    "gn:feature_code":"PPL",
    "gn:name":"Bou Zouggar",
    "gn:population":0,
    "gn:timezone":"Africa/Casablanca",
    "iso:country":"MA",
    "wof:name":"Bou Zouggar",
    "wof:placetype":"locality"
},
  "geometry": {"coordinates":[-9.29612,30.4824],"type":"Point"}
}