{
  "type": "Feature",
  "properties": {
    "gn:admin1_code":"6.0",
    "gn:asciiname":"Douar Mlalka",
    "gn:country_code":"MA",
    "gn:dem":181,
    "gn:feature_class":"P",
    "gn:feature_code":"PPL",
    "gn:name":"Douar Mlalka",
    "gn:population":0,
    "gn:timezone":"Africa/Casablanca",
    "iso:country":"MA",
    "wof:name":"Douar Mlalka",
    "wof:placetype":"locality"
},
  "geometry": {"coordinates":[-7.28213,33.59571],"type":"Point"}
}