{
  "type": "Feature",
  "properties": {
    "gn:admin1_code":"7.0",
    "gn:asciiname":"Al Houmri",
    "gn:country_code":"MA",
    "gn:dem":406,
    "gn:feature_class":"P",
    "gn:feature_code":"PPL",
    "gn:name":"Al Houmri",
    "gn:population":0,
    "gn:timezone":"Africa/Casablanca",
    "iso:country":"MA",
    "wof:name":"Al Houmri",
    "wof:placetype":"neighbourhood"
},
  "geometry": {"coordinates":[-8.04209,31.67846],"type":"Point"}
}