{
  "type": "Feature",
  "properties": {
    "gn:admin1_code":"3.0",
    "gn:asciiname":"Erreggada",
    "gn:country_code":"MA",
    "gn:dem":1721,
    "gn:feature_class":"P",
    "gn:feature_code":"PPL",
    "gn:name":"Erreggada",
    "gn:population":0,
    "gn:timezone":"Africa/Casablanca",
    "iso:country":"MA",
    "wof:name":"Erreggada",
    "wof:placetype":"locality"
},
  "geometry": {"coordinates":[-4.95603,33.53667],"type":"Point"}
}