{
  "type": "Feature",
  "properties": {
    "gn:admin1_code":"10",
    "gn:asciiname":"Aguechgal",
    "gn:country_code":"MA",
    "gn:dem":219,
    "gn:feature_class":"P",
    "gn:feature_code":"PPL",
    "gn:name":"Aguechgal",
    "gn:population":0,
    "gn:timezone":"Africa/Casablanca",
    "iso:country":"MA",
    "name:und_x_variant":[
        "Aguejsgal",
        "Aguechgal"
    ],
    "wof:name":"Aguechgal",
    "wof:placetype":"locality"
},
  "geometry": {"coordinates":[-10.263,29.18691],"type":"Point"}
}