{
  "type": "Feature",
  "properties": {
    "gn:admin1_code":"2.0",
    "gn:asciiname":"Douar Iheyyatene",
    "gn:country_code":"MA",
    "gn:dem":699,
    "gn:feature_class":"P",
    "gn:feature_code":"PPL",
    "gn:name":"Douar Iheyyatene",
    "gn:population":0,
    "gn:timezone":"Africa/Casablanca",
    "iso:country":"MA",
    "wof:name":"Douar Iheyyatene",
    "wof:placetype":"locality"
},
  "geometry": {"coordinates":[-3.52886,35.08828],"type":"Point"}
}