{
  "type": "Feature",
  "properties": {
    "gn:admin1_code":"08",
    "gn:asciiname":"Imin-n-Ougdal",
    "gn:country_code":"MA",
    "gn:dem":1955,
    "gn:feature_class":"P",
    "gn:feature_code":"PPL",
    "gn:name":"Imin-n-Ougdal",
    "gn:population":0,
    "gn:timezone":"Africa/Casablanca",
    "iso:country":"MA",
    "name:und_x_variant":[
        "Imi n\u2019Tugdoul"
    ],
    "wof:name":"Imin-n-Ougdal",
    "wof:placetype":"locality"
},
  "geometry": {"coordinates":[-7.22699,31.31838],"type":"Point"}
}