{
  "type": "Feature",
  "properties": {
    "gn:admin1_code":"3.0",
    "gn:asciiname":"Douar Jbel Madane",
    "gn:country_code":"MA",
    "gn:dem":249,
    "gn:feature_class":"P",
    "gn:feature_code":"PPL",
    "gn:name":"Douar Jbel Madane",
    "gn:population":0,
    "gn:timezone":"Africa/Casablanca",
    "iso:country":"MA",
    "wof:name":"Douar Jbel Madane",
    "wof:placetype":"locality"
},
  "geometry": {"coordinates":[-4.8763,34.47119],"type":"Point"}
}