{
  "type": "Feature",
  "properties": {
    "gn:admin1_code":"08",
    "gn:asciiname":"Ikhfraouene n'Iraouene",
    "gn:country_code":"MA",
    "gn:dem":737,
    "gn:feature_class":"P",
    "gn:feature_code":"PPL",
    "gn:name":"Ikhfraouene n\u2019Iraouene",
    "gn:population":0,
    "gn:timezone":"Africa/Casablanca",
    "iso:country":"MA",
    "name:und_x_variant":[
        "Ikhf n\u2019Ouaroun",
        "Ifraouene n\u2019Naouene",
        "Ikhfraouene n\u2019Iraouene"
    ],
    "wof:name":"Ikhfraouene n'Iraouene",
    "wof:placetype":"locality"
},
  "geometry": {"coordinates":[-5.32133,30.29881],"type":"Point"}
}