{
  "type": "Feature",
  "properties": {
    "gn:admin1_code":"8.0",
    "gn:asciiname":"Ghrifat",
    "gn:country_code":"MA",
    "gn:dem":1144,
    "gn:feature_class":"P",
    "gn:feature_code":"PPL",
    "gn:name":"Ghrifat",
    "gn:population":0,
    "gn:timezone":"Africa/Casablanca",
    "iso:country":"MA",
    "wof:name":"Ghrifat",
    "wof:placetype":"locality"
},
  "geometry": {"coordinates":[-6.69178,30.98643],"type":"Point"}
}