{
  "type": "Feature",
  "properties": {
    "gn:admin1_code":"6.0",
    "gn:asciiname":"Chorfa El Kouassem",
    "gn:country_code":"MA",
    "gn:dem":53,
    "gn:feature_class":"P",
    "gn:feature_code":"PPL",
    "gn:name":"Chorfa El Kouassem",
    "gn:population":0,
    "gn:timezone":"Africa/Casablanca",
    "iso:country":"MA",
    "wof:name":"Chorfa El Kouassem",
    "wof:placetype":"locality"
},
  "geometry": {"coordinates":[-8.50208,33.11533],"type":"Point"}
}