{
  "type": "Feature",
  "properties": {
    "gn:admin1_code":"7.0",
    "gn:asciiname":"Tafrawt",
    "gn:country_code":"MA",
    "gn:dem":1194,
    "gn:feature_class":"P",
    "gn:feature_code":"PPL",
    "gn:name":"Tafrawt",
    "gn:population":0,
    "gn:timezone":"Africa/Casablanca",
    "iso:country":"MA",
    "wof:name":"Tafrawt",
    "wof:placetype":"locality"
},
  "geometry": {"coordinates":[-7.54543,31.40849],"type":"Point"}
}