{
  "type": "Feature",
  "properties": {
    "gn:admin1_code":"07",
    "gn:asciiname":"Douar El Maalmine",
    "gn:country_code":"MA",
    "gn:dem":479,
    "gn:feature_class":"P",
    "gn:feature_code":"PPL",
    "gn:name":"Douar El Maalmine",
    "gn:population":0,
    "gn:timezone":"Africa/Casablanca",
    "iso:country":"MA",
    "name:und_x_variant":[
        "El Maallemine"
    ],
    "wof:name":"Douar El Maalmine",
    "wof:placetype":"locality"
},
  "geometry": {"coordinates":[-8.19987,32.29919],"type":"Point"}
}