{
  "type": "Feature",
  "properties": {
    "gn:admin1_code":"07",
    "gn:asciiname":"Assaka",
    "gn:country_code":"MA",
    "gn:dem":1158,
    "gn:feature_class":"P",
    "gn:feature_code":"PPL",
    "gn:name":"Assaka",
    "gn:population":0,
    "gn:timezone":"Africa/Casablanca",
    "iso:country":"MA",
    "wof:name":"Assaka",
    "wof:placetype":"locality"
},
  "geometry": {"coordinates":[-7.21168,31.53781],"type":"Point"}
}