{
  "type": "Feature",
  "properties": {
    "gn:admin1_code":"09",
    "gn:asciiname":"Tamdjwat",
    "gn:country_code":"MA",
    "gn:dem":1805,
    "gn:feature_class":"P",
    "gn:feature_code":"PPL",
    "gn:name":"Tamdjwat",
    "gn:population":0,
    "gn:timezone":"Africa/Casablanca",
    "iso:country":"MA",
    "name:und_x_variant":[
        "Tamedjaout",
        "Tamz",
        "Tamdjwat"
    ],
    "wof:name":"Tamdjwat",
    "wof:placetype":"locality"
},
  "geometry": {"coordinates":[-8.32549,30.1086],"type":"Point"}
}