{
  "type": "Feature",
  "properties": {
    "gn:admin1_code":"09",
    "gn:asciiname":"Timinoun",
    "gn:country_code":"MA",
    "gn:dem":675,
    "gn:feature_class":"P",
    "gn:feature_code":"PPL",
    "gn:name":"Timinoun",
    "gn:population":0,
    "gn:timezone":"Africa/Casablanca",
    "iso:country":"MA",
    "wof:name":"Timinoun",
    "wof:placetype":"locality"
},
  "geometry": {"coordinates":[-8.79065,30.6771],"type":"Point"}
}