{
  "type": "Feature",
  "properties": {
    "gn:admin1_code":"7.0",
    "gn:asciiname":"Talmadannt",
    "gn:country_code":"MA",
    "gn:dem":723,
    "gn:feature_class":"P",
    "gn:feature_code":"PPL",
    "gn:name":"Talmadannt",
    "gn:population":0,
    "gn:timezone":"Africa/Casablanca",
    "iso:country":"MA",
    "wof:name":"Talmadannt",
    "wof:placetype":"locality"
},
  "geometry": {"coordinates":[-8.46452,31.28548],"type":"Point"}
}