{
  "type": "Feature",
  "properties": {
    "gn:admin1_code":"4.0",
    "gn:asciiname":"Douar El Haj Qajja",
    "gn:country_code":"MA",
    "gn:dem":726,
    "gn:feature_class":"P",
    "gn:feature_code":"PPL",
    "gn:name":"Douar El Haj Qajja",
    "gn:population":0,
    "gn:timezone":"Africa/Casablanca",
    "iso:country":"MA",
    "wof:name":"Douar El Haj Qajja",
    "wof:placetype":"locality"
},
  "geometry": {"coordinates":[-6.0502,33.61957],"type":"Point"}
}