{
  "type": "Feature",
  "properties": {
    "gn:admin1_code":"4.0",
    "gn:asciiname":"Douar Ait Said",
    "gn:country_code":"MA",
    "gn:dem":324,
    "gn:feature_class":"P",
    "gn:feature_code":"PPL",
    "gn:name":"Douar Ait Said",
    "gn:population":0,
    "gn:timezone":"Africa/Casablanca",
    "iso:country":"MA",
    "wof:name":"Douar Ait Said",
    "wof:placetype":"locality"
},
  "geometry": {"coordinates":[-6.09467,33.74763],"type":"Point"}
}