{
  "type": "Feature",
  "properties": {
    "gn:admin1_code":"2.0",
    "gn:asciiname":"Douar Issallanene",
    "gn:country_code":"MA",
    "gn:dem":239,
    "gn:feature_class":"P",
    "gn:feature_code":"PPL",
    "gn:name":"Douar Issallanene",
    "gn:population":0,
    "gn:timezone":"Africa/Casablanca",
    "iso:country":"MA",
    "wof:name":"Douar Issallanene",
    "wof:placetype":"locality"
},
  "geometry": {"coordinates":[-2.23184,34.91941],"type":"Point"}
}