{
  "type": "Feature",
  "properties": {
    "gn:admin1_code":"4.0",
    "gn:asciiname":"Ait Hmama",
    "gn:country_code":"MA",
    "gn:dem":402,
    "gn:feature_class":"P",
    "gn:feature_code":"PPL",
    "gn:name":"Ait Hmama",
    "gn:population":0,
    "gn:timezone":"Africa/Casablanca",
    "iso:country":"MA",
    "wof:name":"Ait Hmama",
    "wof:placetype":"locality"
},
  "geometry": {"coordinates":[-6.10137,33.70026],"type":"Point"}
}