{
  "type": "Feature",
  "properties": {
    "gn:admin1_code":"5.0",
    "gn:asciiname":"Ait Lahnida",
    "gn:country_code":"MA",
    "gn:dem":936,
    "gn:feature_class":"P",
    "gn:feature_code":"PPL",
    "gn:name":"Ait Lahnida",
    "gn:population":0,
    "gn:timezone":"Africa/Casablanca",
    "iso:country":"MA",
    "wof:name":"Ait Lahnida",
    "wof:placetype":"locality"
},
  "geometry": {"coordinates":[-7.18339,31.68755],"type":"Point"}
}