{
  "type": "Feature",
  "properties": {
    "gn:admin1_code":"09",
    "gn:asciiname":"Tagnit-n-'Abdiy",
    "gn:country_code":"MA",
    "gn:dem":1328,
    "gn:feature_class":"P",
    "gn:feature_code":"PPL",
    "gn:name":"Tagnit-n-\u2019Abdiy",
    "gn:population":0,
    "gn:timezone":"Africa/Casablanca",
    "iso:country":"MA",
    "name:und_x_variant":[
        "Tagnit-n-\u2019Abdiy",
        "Tagounit n\u2019A\u00eft Abdi"
    ],
    "wof:name":"Tagnit-n-'Abdiy",
    "wof:placetype":"locality"
},
  "geometry": {"coordinates":[-8.21852,30.33946],"type":"Point"}
}