{
  "type": "Feature",
  "properties": {
    "gn:admin1_code":"1.0",
    "gn:asciiname":"Villas Marina Smir",
    "gn:country_code":"MA",
    "gn:dem":5,
    "gn:feature_class":"P",
    "gn:feature_code":"PPL",
    "gn:name":"Villas Marina Smir",
    "gn:population":0,
    "gn:timezone":"Africa/Casablanca",
    "iso:country":"MA",
    "wof:name":"Villas Marina Smir",
    "wof:placetype":"locality"
},
  "geometry": {"coordinates":[-5.34191,35.73990999999999],"type":"Point"}
}