{
  "type": "Feature",
  "properties": {
    "gn:admin1_code":"01",
    "gn:asciiname":"Douar Touilach",
    "gn:country_code":"MA",
    "gn:dem":371,
    "gn:feature_class":"P",
    "gn:feature_code":"PPL",
    "gn:name":"Douar Touilach",
    "gn:population":0,
    "gn:timezone":"Africa/Casablanca",
    "iso:country":"MA",
    "name:und_x_variant":[
        "Dar Touilech"
    ],
    "wof:name":"Douar Touilach",
    "wof:placetype":"locality"
},
  "geometry": {"coordinates":[-5.57737,35.66918],"type":"Point"}
}