{
  "type": "Feature",
  "properties": {
    "gn:admin1_code":"1.0",
    "gn:asciiname":"Azib Tassiff",
    "gn:country_code":"MA",
    "gn:dem":32,
    "gn:feature_class":"P",
    "gn:feature_code":"PPL",
    "gn:name":"Azib Tassiff",
    "gn:population":0,
    "gn:timezone":"Africa/Casablanca",
    "iso:country":"MA",
    "wof:name":"Azib Tassiff",
    "wof:placetype":"locality"
},
  "geometry": {"coordinates":[-5.13832,35.4096],"type":"Point"}
}