{
  "type": "Feature",
  "properties": {
    "gn:admin1_code":"03",
    "gn:asciiname":"Douar Kheliaa",
    "gn:country_code":"MA",
    "gn:dem":699,
    "gn:feature_class":"P",
    "gn:feature_code":"PPL",
    "gn:name":"Douar Kheliaa",
    "gn:population":0,
    "gn:timezone":"Africa/Casablanca",
    "iso:country":"MA",
    "name:und_x_variant":[
        "Darhlia"
    ],
    "wof:name":"Douar Kheliaa",
    "wof:placetype":"locality"
},
  "geometry": {"coordinates":[-4.3596,34.34359],"type":"Point"}
}