{
  "type": "Feature",
  "properties": {
    "gn:admin1_code":"3.0",
    "gn:asciiname":"Dyour Driss Fourjouni",
    "gn:country_code":"MA",
    "gn:dem":536,
    "gn:feature_class":"P",
    "gn:feature_code":"PPL",
    "gn:name":"Dyour Driss Fourjouni",
    "gn:population":0,
    "gn:timezone":"Africa/Casablanca",
    "iso:country":"MA",
    "wof:name":"Dyour Driss Fourjouni",
    "wof:placetype":"locality"
},
  "geometry": {"coordinates":[-5.65683,33.85333],"type":"Point"}
}