{
  "type": "Feature",
  "properties": {
    "gn:admin1_code":"08",
    "gn:asciiname":"Toulal",
    "gn:country_code":"MA",
    "gn:dem":1282,
    "gn:feature_class":"P",
    "gn:feature_code":"PPL",
    "gn:name":"Toulal",
    "gn:population":0,
    "gn:timezone":"Africa/Casablanca",
    "iso:country":"MA",
    "name:ara_x_preferred":[
        "\u062a\u0648\u0644\u0627\u0644"
    ],
    "name:cat_x_preferred":[
        "Toulal"
    ],
    "name:fra_x_preferred":[
        "Toulal"
    ],
    "name:und_x_variant":[
        "Toula"
    ],
    "wof:name":"Toulal",
    "wof:placetype":"locality"
},
  "geometry": {"coordinates":[-3.98449,32.30158],"type":"Point"}
}