{
  "type": "Feature",
  "properties": {
    "gn:admin1_code":"7.0",
    "gn:asciiname":"Timditene",
    "gn:country_code":"MA",
    "gn:dem":1215,
    "gn:feature_class":"P",
    "gn:feature_code":"PPL",
    "gn:name":"Timditene",
    "gn:population":0,
    "gn:timezone":"Africa/Casablanca",
    "iso:country":"MA",
    "wof:name":"Timditene",
    "wof:placetype":"locality"
},
  "geometry": {"coordinates":[-7.28505,31.5765],"type":"Point"}
}