{
  "type": "Feature",
  "properties": {
    "gn:admin1_code":"9.0",
    "gn:asciiname":"Tiwwiyst",
    "gn:country_code":"MA",
    "gn:dem":929,
    "gn:feature_class":"P",
    "gn:feature_code":"PPL",
    "gn:name":"Tiwwiyst",
    "gn:population":0,
    "gn:timezone":"Africa/Casablanca",
    "iso:country":"MA",
    "wof:name":"Tiwwiyst",
    "wof:placetype":"locality"
},
  "geometry": {"coordinates":[-9.2941,29.59369],"type":"Point"}
}