{
  "type": "Feature",
  "properties": {
    "gn:admin1_code":"9.0",
    "gn:asciiname":"Tiqqiy",
    "gn:country_code":"MA",
    "gn:dem":1893,
    "gn:feature_class":"P",
    "gn:feature_code":"PPL",
    "gn:name":"Tiqqiy",
    "gn:population":0,
    "gn:timezone":"Africa/Casablanca",
    "iso:country":"MA",
    "wof:name":"Tiqqiy",
    "wof:placetype":"locality"
},
  "geometry": {"coordinates":[-7.93565,30.9592],"type":"Point"}
}