{
  "type": "Feature",
  "properties": {
    "gn:admin1_code":"03",
    "gn:asciiname":"Douar Tmarkemt",
    "gn:country_code":"MA",
    "gn:dem":803,
    "gn:feature_class":"P",
    "gn:feature_code":"PPL",
    "gn:name":"Douar Tmarkemt",
    "gn:population":0,
    "gn:timezone":"Africa/Casablanca",
    "iso:country":"MA",
    "name:und_x_variant":[
        "Tmarkemt"
    ],
    "wof:name":"Douar Tmarkemt",
    "wof:placetype":"locality"
},
  "geometry": {"coordinates":[-3.90905,33.91353],"type":"Point"}
}