{
  "type": "Feature",
  "properties": {
    "gn:admin1_code":"6.0",
    "gn:asciiname":"Douar Chmaimes",
    "gn:country_code":"MA",
    "gn:dem":223,
    "gn:feature_class":"P",
    "gn:feature_code":"PPL",
    "gn:name":"Douar Chmaimes",
    "gn:population":0,
    "gn:timezone":"Africa/Casablanca",
    "iso:country":"MA",
    "wof:name":"Douar Chmaimes",
    "wof:placetype":"locality"
},
  "geometry": {"coordinates":[-8.37205,32.54411],"type":"Point"}
}