{
  "type": "Feature",
  "properties": {
    "gn:admin1_code":"7.0",
    "gn:asciiname":"Ait el Maatig",
    "gn:country_code":"MA",
    "gn:dem":775,
    "gn:feature_class":"P",
    "gn:feature_code":"PPL",
    "gn:name":"A\u00eft el Maatig",
    "gn:population":0,
    "gn:timezone":"Africa/Casablanca",
    "iso:country":"MA",
    "wof:name":"Ait el Maatig",
    "wof:placetype":"locality"
},
  "geometry": {"coordinates":[-9.30048,31.27504],"type":"Point"}
}