{
  "type": "Feature",
  "properties": {
    "gn:admin1_code":"9.0",
    "gn:asciiname":"Tikitar",
    "gn:country_code":"MA",
    "gn:dem":1153,
    "gn:feature_class":"P",
    "gn:feature_code":"PPL",
    "gn:name":"Tikitar",
    "gn:population":0,
    "gn:timezone":"Africa/Casablanca",
    "iso:country":"MA",
    "wof:name":"Tikitar",
    "wof:placetype":"locality"
},
  "geometry": {"coordinates":[-8.81296,30.15077],"type":"Point"}
}