{
  "type": "Feature",
  "properties": {
    "gn:country":"MA",
    "gn:fcode":"ADM3",
    "gn:population":4066,
    "iso:country":"MA",
    "name:ara_x_preferred":[
        "\u0627\u0643\u0646\u0648\u0644 (\u0627\u0644\u0628\u0644\u062f\u064a\u0629)"
    ],
    "name:ara_x_variant":[
        "\u0623\u0643\u0646\u0648\u0644"
    ],
    "name:ary_x_preferred":[
        "\u0623\u0643\u0646\u0648\u0644"
    ],
    "name:azb_x_preferred":[
        "\u0627\u06a9\u0646\u0648\u0644"
    ],
    "name:cat_x_preferred":[
        "Aknoul"
    ],
    "name:ceb_x_preferred":[
        "Aknoul"
    ],
    "name:eng_x_preferred":[
        "Aknoul"
    ],
    "name:fas_x_preferred":[
        "\u0627\u06a9\u0646\u0648\u0644"
    ],
    "name:fra_x_preferred":[
        "Aknoul"
    ],
    "name:fra_x_variant":[
        "Aknoul (MU)",
        "Aknoul (Commune Urbaine)"
    ],
    "name:ita_x_preferred":[
        "Aknoul"
    ],
    "name:kab_x_preferred":[
        "Aknul"
    ],
    "name:nld_x_preferred":[
        "Aknoul"
    ],
    "name:por_x_preferred":[
        "Aknoul"
    ],
    "name:swe_x_preferred":[
        "Aknoul"
    ],
    "qs:name":"Aknoul",
    "qs:photos_9r":0,
    "qs:photos_sr":0,
    "qs:pop_sr":"4",
    "wd:wordcount":48,
    "wof:name":"Aknoul",
    "wof:placetype":"localadmin",
    "wof:population":4066
},
  "geometry": {"coordinates":[-3.86795,34.6513],"type":"Point"}
}