{
  "type": "Feature",
  "properties": {
    "gn:admin1_code":"07",
    "gn:asciiname":"Tiourar",
    "gn:country_code":"MA",
    "gn:dem":637,
    "gn:feature_class":"P",
    "gn:feature_code":"PPL",
    "gn:name":"Tiourar",
    "gn:population":0,
    "gn:timezone":"Africa/Casablanca",
    "iso:country":"MA",
    "wof:name":"Tiourar",
    "wof:placetype":"locality"
},
  "geometry": {"coordinates":[-9.61478,30.95348],"type":"Point"}
}