{
  "type": "Feature",
  "properties": {
    "gn:admin1_code":"01",
    "gn:asciiname":"Cheiba",
    "gn:country_code":"MA",
    "gn:dem":175,
    "gn:feature_class":"P",
    "gn:feature_code":"PPL",
    "gn:name":"Che\u00efba",
    "gn:population":0,
    "gn:timezone":"Africa/Casablanca",
    "iso:country":"MA",
    "name:und_x_variant":[
        "Mraa Chetba",
        "Che\u00efba"
    ],
    "wof:name":"Cheiba",
    "wof:placetype":"locality"
},
  "geometry": {"coordinates":[-5.9078,35.79379],"type":"Point"}
}