{
  "type": "Feature",
  "properties": {
    "gn:country":"MA",
    "gn:fcode":"ADM3",
    "gn:pop":28120,
    "iso:country":"MA",
    "name:ara_x_preferred":[
        "\u0627\u0644\u0633\u0627\u062d\u0644"
    ],
    "name:fra_x_preferred":[
        "Assilah"
    ],
    "name:fra_x_variant":[
        "Assilah (MU)",
        "Assilah (Commune Urbaine)"
    ],
    "qs:name":"Assilah",
    "qs:photos_9r":0,
    "qs:photos_sr":0,
    "qs:pop_sr":"7",
    "wd:wordcount":343,
    "wof:name":"Assilah",
    "wof:placetype":"localadmin",
    "wof:population":28120
},
  "geometry": {"coordinates":[-6.02372,35.47833],"type":"Point"}
}