{
  "type": "Feature",
  "properties": {
    "gn:admin1_code":"08",
    "gn:asciiname":"Imaghoudene",
    "gn:country_code":"MA",
    "gn:dem":1811,
    "gn:feature_class":"P",
    "gn:feature_code":"PPL",
    "gn:name":"Imaghoudene",
    "gn:population":0,
    "gn:timezone":"Africa/Casablanca",
    "iso:country":"MA",
    "name:und_x_variant":[
        "Imarhoudene",
        "Imaghoud\u00e8ne Adki",
        "Imarhoud\u00e8n",
        "Imaghoudene"
    ],
    "wof:name":"Imaghoudene",
    "wof:placetype":"locality"
},
  "geometry": {"coordinates":[-7.59167,31.08869],"type":"Point"}
}