{
  "type": "Feature",
  "properties": {
    "gn:admin1_code":"08",
    "gn:asciiname":"Tabassamt",
    "gn:country_code":"MA",
    "gn:dem":763,
    "gn:feature_class":"P",
    "gn:feature_code":"PPL",
    "gn:name":"Tabassamt",
    "gn:population":0,
    "gn:timezone":"Africa/Casablanca",
    "iso:country":"MA",
    "name:und_x_variant":[
        "Ksar Tabouassant",
        "Tabassamt",
        "Tabouasamt"
    ],
    "wof:name":"Tabassamt",
    "wof:placetype":"locality"
},
  "geometry": {"coordinates":[-4.27509,31.24013],"type":"Point"}
}