{
  "type": "Feature",
  "properties": {
    "gn:admin1_code":"10",
    "gn:asciiname":"Ait Abdallah Ou Messaoud",
    "gn:country_code":"MA",
    "gn:dem":276,
    "gn:feature_class":"P",
    "gn:feature_code":"PPL",
    "gn:name":"A\u00eft Abdallah Ou Messaoud",
    "gn:population":0,
    "gn:timezone":"Africa/Casablanca",
    "iso:country":"MA",
    "name:und_x_variant":[
        "Ait Abdalah U Mesaud",
        "A\u00eft Abdallah Ou Messaoud"
    ],
    "wof:name":"Ait Abdallah Ou Messaoud",
    "wof:placetype":"locality"
},
  "geometry": {"coordinates":[-10.09371,29.33076],"type":"Point"}
}