{
  "type": "Feature",
  "properties": {
    "gn:admin1_code":"04",
    "gn:asciiname":"Dar Oulad Daouya",
    "gn:country_code":"MA",
    "gn:dem":14,
    "gn:feature_class":"P",
    "gn:feature_code":"PPL",
    "gn:name":"Dar Oulad Daouya",
    "gn:population":0,
    "gn:timezone":"Africa/Casablanca",
    "iso:country":"MA",
    "name:und_x_variant":[
        "Dar daou\u00efa",
        "Karja Oulad Daou\u00efa",
        "Dar Oulad Daou\u00efa",
        "Karia Daouia",
        "Karia Oulad Daouia",
        "Dar Oulad Daouya"
    ],
    "wof:name":"Dar Oulad Daouya",
    "wof:placetype":"locality"
},
  "geometry": {"coordinates":[-6.20913,34.73931],"type":"Point"}
}