{
  "type": "Feature",
  "properties": {
    "gn:admin1_code":"07",
    "gn:asciiname":"Al Gaida",
    "gn:country_code":"MA",
    "gn:dem":802,
    "gn:feature_class":"P",
    "gn:feature_code":"PPL",
    "gn:name":"Al Gaida",
    "gn:population":0,
    "gn:timezone":"Africa/Casablanca",
    "iso:country":"MA",
    "name:und_x_variant":[
        "Lague\u00efada",
        "Douar el Ga\u00efda",
        "El Ga\u00efda",
        "Al Gaida"
    ],
    "wof:name":"Al Gaida",
    "wof:placetype":"locality"
},
  "geometry": {"coordinates":[-8.27277,31.37185],"type":"Point"}
}