{
  "type": "Feature",
  "properties": {
    "gn:admin1_code":"02",
    "gn:asciiname":"Douar Rbia Louta",
    "gn:country_code":"MA",
    "gn:dem":26,
    "gn:feature_class":"P",
    "gn:feature_code":"PPL",
    "gn:name":"Douar Rbia Louta",
    "gn:population":0,
    "gn:timezone":"Africa/Casablanca",
    "iso:country":"MA",
    "wof:name":"Douar Rbia Louta",
    "wof:placetype":"locality"
},
  "geometry": {"coordinates":[-3.77269,35.20304],"type":"Point"}
}