{
  "type": "Feature",
  "properties": {
    "gn:admin1_code":"7.0",
    "gn:asciiname":"Douirhil",
    "gn:country_code":"MA",
    "gn:dem":788,
    "gn:feature_class":"P",
    "gn:feature_code":"PPL",
    "gn:name":"Douirhil",
    "gn:population":0,
    "gn:timezone":"Africa/Casablanca",
    "iso:country":"MA",
    "wof:name":"Douirhil",
    "wof:placetype":"locality"
},
  "geometry": {"coordinates":[-8.51184,31.2547],"type":"Point"}
}