{
  "type": "Feature",
  "properties": {
    "gn:admin1_code":"55",
    "gn:asciiname":"Assafid",
    "gn:country_code":"MA",
    "gn:dem":1011,
    "gn:feature_class":"P",
    "gn:feature_code":"PPL",
    "gn:name":"Assafid",
    "gn:population":0,
    "gn:timezone":"Africa/Casablanca",
    "iso:country":"MA",
    "wof:name":"Assafid",
    "wof:placetype":"locality"
},
  "geometry": {"coordinates":[-9.36,30.65],"type":"Point"}
}