{
  "type": "Feature",
  "properties": {
    "gn:admin1_code":"2.0",
    "gn:asciiname":"Cooperative El Fath",
    "gn:country_code":"MA",
    "gn:dem":65,
    "gn:feature_class":"P",
    "gn:feature_code":"PPLF",
    "gn:name":"Coop\u00e9rative El Fath",
    "gn:population":0,
    "gn:timezone":"Africa/Casablanca",
    "iso:country":"MA",
    "wof:name":"Cooperative El Fath",
    "wof:placetype":"locality"
},
  "geometry": {"coordinates":[-2.48775,34.97307],"type":"Point"}
}