{
  "type": "Feature",
  "properties": {
    "gn:admin1_code":"08",
    "gn:asciiname":"Taggourt Amellil",
    "gn:country_code":"MA",
    "gn:dem":1257,
    "gn:feature_class":"P",
    "gn:feature_code":"PPL",
    "gn:name":"Taggourt Amellil",
    "gn:population":0,
    "gn:timezone":"Africa/Casablanca",
    "iso:country":"MA",
    "wof:name":"Taggourt Amellil",
    "wof:placetype":"locality"
},
  "geometry": {"coordinates":[-4.49962,32.75193],"type":"Point"}
}