{
  "type": "Feature",
  "properties": {
    "gn:admin1_code":"9.0",
    "gn:asciiname":"Tou Achchak",
    "gn:country_code":"MA",
    "gn:dem":616,
    "gn:feature_class":"P",
    "gn:feature_code":"PPL",
    "gn:name":"Tou Achchak",
    "gn:population":0,
    "gn:timezone":"Africa/Casablanca",
    "iso:country":"MA",
    "wof:name":"Tou Achchak",
    "wof:placetype":"locality"
},
  "geometry": {"coordinates":[-9.10728,30.05004000000001],"type":"Point"}
}