{
  "type": "Feature",
  "properties": {
    "gn:admin1_code":"6.0",
    "gn:asciiname":"Oulad En-Nayem",
    "gn:country_code":"MA",
    "gn:dem":231,
    "gn:feature_class":"P",
    "gn:feature_code":"PPL",
    "gn:name":"Oulad En-Nayem",
    "gn:population":0,
    "gn:timezone":"Africa/Casablanca",
    "iso:country":"MA",
    "wof:name":"Oulad En-Nayem",
    "wof:placetype":"locality"
},
  "geometry": {"coordinates":[-8.08493,32.75842],"type":"Point"}
}