{
  "type": "Feature",
  "properties": {
    "gn:admin1_code":"7.0",
    "gn:asciiname":"Azilal Slimane",
    "gn:country_code":"MA",
    "gn:dem":809,
    "gn:feature_class":"P",
    "gn:feature_code":"PPL",
    "gn:name":"Azilal Slimane",
    "gn:population":0,
    "gn:timezone":"Africa/Casablanca",
    "iso:country":"MA",
    "wof:name":"Azilal Slimane",
    "wof:placetype":"locality"
},
  "geometry": {"coordinates":[-8.41332,31.28051],"type":"Point"}
}