{
  "type": "Feature",
  "properties": {
    "gn:admin1_code":"08",
    "gn:asciiname":"Ait Mrabet",
    "gn:country_code":"MA",
    "gn:dem":947,
    "gn:feature_class":"P",
    "gn:feature_code":"PPL",
    "gn:name":"A\u00eft Mrabet",
    "gn:population":0,
    "gn:timezone":"Africa/Casablanca",
    "iso:country":"MA",
    "name:und_x_variant":[
        "A\u00eft M\u2019 Rabt",
        "A\u00eft Mrabet"
    ],
    "wof:name":"Ait Mrabet",
    "wof:placetype":"locality"
},
  "geometry": {"coordinates":[-6.91385,30.40673],"type":"Point"}
}