{
  "type": "Feature",
  "properties": {
    "gn:admin1_code":"09",
    "gn:admin2_code":"1.0",
    "gn:admin3_code":"400105232.0",
    "gn:asciiname":"Taghazout",
    "gn:country_code":"MA",
    "gn:dem":1,
    "gn:feature_class":"P",
    "gn:feature_code":"PPLA3",
    "gn:name":"Taghazout",
    "gn:population":0,
    "gn:timezone":"Africa/Casablanca",
    "iso:country":"MA",
    "name:und_x_variant":[
        "Tarhazoute",
        "Taghazout"
    ],
    "wof:name":"Taghazout",
    "wof:placetype":"locality"
},
  "geometry": {"coordinates":[-9.71115,30.54259],"type":"Point"}
}