{
  "type": "Feature",
  "properties": {
    "gn:admin1_code":"03",
    "gn:asciiname":"Douar Addala",
    "gn:country_code":"MA",
    "gn:dem":443,
    "gn:feature_class":"P",
    "gn:feature_code":"PPL",
    "gn:name":"Douar Addala",
    "gn:population":0,
    "gn:timezone":"Africa/Casablanca",
    "iso:country":"MA",
    "name:und_x_variant":[
        "Adala",
        "Addala"
    ],
    "wof:name":"Douar Addala",
    "wof:placetype":"locality"
},
  "geometry": {"coordinates":[-4.5735,34.41931],"type":"Point"}
}