{
  "type": "Feature",
  "properties": {
    "gn:country":"MA",
    "gn:fcode":"ADM3",
    "gn:population":19275,
    "iso:country":"MA",
    "name:ara_x_preferred":[
        "\u0623\u064a\u062a \u0641\u0627\u0633\u0643\u0627"
    ],
    "name:ara_x_variant":[
        "\u062a\u0645\u0644\u064a\u0644\u062a",
        "\u0622\u064a\u062a \u0633\u064a\u062f\u064a \u062f\u0627\u0648\u062f"
    ],
    "name:ary_x_preferred":[
        "\u0622\u064a\u062a \u0633\u064a\u062f\u064a \u062f\u0627\u0648\u062f"
    ],
    "name:azb_x_preferred":[
        "\u0622\u06cc\u062a \u0633\u06cc\u062f\u06cc \u062f\u0627\u0648\u0648\u062f"
    ],
    "name:cat_x_preferred":[
        "Ait Sidi Daoud"
    ],
    "name:ceb_x_preferred":[
        "Ait Sidi Daoud"
    ],
    "name:eng_x_preferred":[
        "Ait Sidi Daoud"
    ],
    "name:fas_x_preferred":[
        "\u0627\u06cc\u062a \u0633\u06cc\u062f\u06cc \u062f\u0627\u0648\u062f"
    ],
    "name:fra_x_preferred":[
        "Ait Sidi Daoud"
    ],
    "name:fra_x_variant":[
        "Ait Sidi Daoud (CR)",
        "Ait Sidi Daoud (Commune Rurale)",
        "Ait Daoud",
        "Ait Daoud (MU)",
        "Ait Daoud (Commune Urbaine)",
        "A\u00eft Sidi Daoud"
    ],
    "name:ita_x_preferred":[
        "A\u00eft Sidi Daoud"
    ],
    "name:swe_x_preferred":[
        "Ait Sidi Daoud"
    ],
    "name:urd_x_preferred":[
        "\u0622\u06cc\u062a \u0633\u06cc\u062f\u06cc \u062f\u0627\u0648\u062f"
    ],
    "qs:name":"Ait Sidi Daoud",
    "qs:photos_9r":0,
    "qs:photos_sr":0,
    "qs:pop_sr":"6",
    "wd:wordcount":64,
    "wof:name":"Ait Sidi Daoud",
    "wof:placetype":"localadmin",
    "wof:population":19275
},
  "geometry": {"coordinates":[-7.67566,31.61548],"type":"Point"}
}