{
  "type": "Feature",
  "properties": {
    "gn:admin1_code":"5.0",
    "gn:asciiname":"Imzilane",
    "gn:country_code":"MA",
    "gn:dem":1152,
    "gn:feature_class":"P",
    "gn:feature_code":"PPL",
    "gn:name":"Imzilane",
    "gn:population":0,
    "gn:timezone":"Africa/Casablanca",
    "iso:country":"MA",
    "wof:name":"Imzilane",
    "wof:placetype":"locality"
},
  "geometry": {"coordinates":[-6.3657,32.18648],"type":"Point"}
}