{
  "type": "Feature",
  "properties": {
    "gn:admin1_code":"05",
    "gn:asciiname":"Ait Bouhamza",
    "gn:country_code":"MA",
    "gn:dem":537,
    "gn:feature_class":"P",
    "gn:feature_code":"PPL",
    "gn:name":"A\u00eft Bouhamza",
    "gn:population":0,
    "gn:timezone":"Africa/Casablanca",
    "iso:country":"MA",
    "name:und_x_variant":[
        "A\u00eft Bouhamza",
        "A\u00eft Bou Hamza"
    ],
    "wof:name":"Ait Bouhamza",
    "wof:placetype":"locality"
},
  "geometry": {"coordinates":[-6.83629,32.17297],"type":"Point"}
}