{
  "type": "Feature",
  "properties": {
    "gn:admin1_code":"3.0",
    "gn:asciiname":"Moulay Abdelkader",
    "gn:country_code":"MA",
    "gn:dem":408,
    "gn:feature_class":"P",
    "gn:feature_code":"PPL",
    "gn:name":"Moulay Abdelkader",
    "gn:population":0,
    "gn:timezone":"Africa/Casablanca",
    "iso:country":"MA",
    "wof:name":"Moulay Abdelkader",
    "wof:placetype":"locality"
},
  "geometry": {"coordinates":[-4.86159,34.24456],"type":"Point"}
}