{
  "type": "Feature",
  "properties": {
    "gn:admin1_code":"07",
    "gn:asciiname":"Skikine",
    "gn:country_code":"MA",
    "gn:dem":445,
    "gn:feature_class":"P",
    "gn:feature_code":"PPL",
    "gn:name":"Skikine",
    "gn:population":0,
    "gn:timezone":"Africa/Casablanca",
    "iso:country":"MA",
    "wof:name":"Skikine",
    "wof:placetype":"locality"
},
  "geometry": {"coordinates":[-8.81414,31.46793],"type":"Point"}
}