{
  "type": "Feature",
  "properties": {
    "gn:admin1_code":"09",
    "gn:asciiname":"Irherrharene",
    "gn:country_code":"MA",
    "gn:dem":1184,
    "gn:feature_class":"P",
    "gn:feature_code":"PPL",
    "gn:name":"Irherrharene",
    "gn:population":0,
    "gn:timezone":"Africa/Casablanca",
    "iso:country":"MA",
    "name:und_x_variant":[
        "Ighargharen",
        "Irherrharene"
    ],
    "wof:name":"Irherrharene",
    "wof:placetype":"locality"
},
  "geometry": {"coordinates":[-9.44399,30.6505],"type":"Point"}
}