{
  "type": "Feature",
  "properties": {
    "gn:admin1_code":"07",
    "gn:asciiname":"Ait Wiyksane",
    "gn:country_code":"MA",
    "gn:dem":1605,
    "gn:feature_class":"P",
    "gn:feature_code":"PPL",
    "gn:name":"A\u00eft Wiyksane",
    "gn:population":0,
    "gn:timezone":"Africa/Casablanca",
    "iso:country":"MA",
    "name:und_x_variant":[
        "A\u00eft Wiksen",
        "A\u00eft Ouiksene",
        "A\u00eft Wiyksane"
    ],
    "wof:name":"Ait Wiyksane",
    "wof:placetype":"locality"
},
  "geometry": {"coordinates":[-7.46764,31.41771],"type":"Point"}
}