{
  "type": "Feature",
  "properties": {
    "gn:admin1_code":"4.0",
    "gn:asciiname":"Lahratza",
    "gn:country_code":"MA",
    "gn:dem":18,
    "gn:feature_class":"P",
    "gn:feature_code":"PPL",
    "gn:name":"Lahratza",
    "gn:population":0,
    "gn:timezone":"Africa/Casablanca",
    "iso:country":"MA",
    "wof:name":"Lahratza",
    "wof:placetype":"locality"
},
  "geometry": {"coordinates":[-6.71357,34.1519],"type":"Point"}
}