{
  "type": "Feature",
  "properties": {
    "gn:admin1_code":"4.0",
    "gn:asciiname":"Oulad Bou Rahla",
    "gn:country_code":"MA",
    "gn:dem":11,
    "gn:feature_class":"P",
    "gn:feature_code":"PPL",
    "gn:name":"Oulad Bou Rahla",
    "gn:population":0,
    "gn:timezone":"Africa/Casablanca",
    "iso:country":"MA",
    "wof:name":"Oulad Bou Rahla",
    "wof:placetype":"locality"
},
  "geometry": {"coordinates":[-6.51336,34.31278],"type":"Point"}
}