{
  "type": "Feature",
  "properties": {
    "gn:admin1_code":"6.0",
    "gn:asciiname":"Dar Ben Jouwa",
    "gn:country_code":"MA",
    "gn:dem":172,
    "gn:feature_class":"P",
    "gn:feature_code":"PPL",
    "gn:name":"Dar Ben Jouwa",
    "gn:population":0,
    "gn:timezone":"Africa/Casablanca",
    "iso:country":"MA",
    "wof:name":"Dar Ben Jouwa",
    "wof:placetype":"locality"
},
  "geometry": {"coordinates":[-8.14715,32.84086],"type":"Point"}
}