{
  "type": "Feature",
  "properties": {
    "gn:admin1_code":"9.0",
    "gn:asciiname":"Talbourjt",
    "gn:country_code":"MA",
    "gn:dem":145,
    "gn:feature_class":"P",
    "gn:feature_code":"PPL",
    "gn:name":"Talbourjt",
    "gn:population":0,
    "gn:timezone":"Africa/Casablanca",
    "iso:country":"MA",
    "wof:name":"Talbourjt",
    "wof:placetype":"locality"
},
  "geometry": {"coordinates":[-9.33153,30.21928],"type":"Point"}
}