{
  "type": "Feature",
  "properties": {
    "gn:admin1_code":"04",
    "gn:asciiname":"Mehdya Plage",
    "gn:country_code":"MA",
    "gn:dem":15,
    "gn:feature_class":"P",
    "gn:feature_code":"PPL",
    "gn:name":"Mehdya Plage",
    "gn:population":0,
    "gn:timezone":"Africa/Casablanca",
    "iso:country":"MA",
    "name:und_x_variant":[
        "Mehdiya-Plage"
    ],
    "wof:name":"Mehdya Plage",
    "wof:placetype":"locality"
},
  "geometry": {"coordinates":[-6.67904,34.25137],"type":"Point"}
}