{
  "type": "Feature",
  "properties": {
    "gn:admin1_code":"4.0",
    "gn:asciiname":"Douar Drissa",
    "gn:country_code":"MA",
    "gn:dem":191,
    "gn:feature_class":"P",
    "gn:feature_code":"PPL",
    "gn:name":"Douar Drissa",
    "gn:population":0,
    "gn:timezone":"Africa/Casablanca",
    "iso:country":"MA",
    "wof:name":"Douar Drissa",
    "wof:placetype":"locality"
},
  "geometry": {"coordinates":[-5.98761,34.86594],"type":"Point"}
}