{
  "type": "Feature",
  "properties": {
    "gn:admin1_code":"4.0",
    "gn:asciiname":"Oulad Sidi Lhadi",
    "gn:country_code":"MA",
    "gn:dem":13,
    "gn:feature_class":"P",
    "gn:feature_code":"PPL",
    "gn:name":"Oulad Sidi Lhadi",
    "gn:population":0,
    "gn:timezone":"Africa/Casablanca",
    "iso:country":"MA",
    "wof:name":"Oulad Sidi Lhadi",
    "wof:placetype":"locality"
},
  "geometry": {"coordinates":[-6.2869,34.50479],"type":"Point"}
}