{
  "type": "Feature",
  "properties": {
    "gn:admin1_code":"09",
    "gn:asciiname":"Ida Ou Kess Oufella",
    "gn:country_code":"MA",
    "gn:dem":832,
    "gn:feature_class":"P",
    "gn:feature_code":"PPL",
    "gn:name":"Ida Ou Kess Oufella",
    "gn:population":0,
    "gn:timezone":"Africa/Casablanca",
    "iso:country":"MA",
    "wof:name":"Ida Ou Kess Oufella",
    "wof:placetype":"locality"
},
  "geometry": {"coordinates":[-9.16781,30.64036],"type":"Point"}
}