{
  "type": "Feature",
  "properties": {
    "iso:country":"MA",
    "name:ara_x_preferred":[
        "\u0641\u0643\u064a\u0643"
    ],
    "name:ben_x_preferred":[
        "\u09ab\u09bf\u0997\u09c1\u0987\u0997"
    ],
    "name:cat_x_preferred":[
        "Figuig"
    ],
    "name:cym_x_preferred":[
        "Figuig"
    ],
    "name:dan_x_preferred":[
        "Figuig"
    ],
    "name:deu_x_preferred":[
        "Figuig"
    ],
    "name:ell_x_preferred":[
        "\u03a6\u03af\u03b3\u03ba\u03bf\u03c5\u03b9\u03b3\u03ba"
    ],
    "name:eng_x_preferred":[
        "Figuig"
    ],
    "name:eus_x_preferred":[
        "Figuig"
    ],
    "name:fas_x_preferred":[
        "\u0641\u06a9\u06cc\u06a9"
    ],
    "name:fin_x_preferred":[
        "Figuig"
    ],
    "name:fra_x_preferred":[
        "Figuig"
    ],
    "name:guj_x_preferred":[
        "\u0aab\u0abf\u0a97\u0ac1\u0a88\u0a97"
    ],
    "name:hin_x_preferred":[
        "\u092b\u093f\u0917\u094d\u092f\u0941\u0907\u0917"
    ],
    "name:ind_x_preferred":[
        "Figuig"
    ],
    "name:ita_x_preferred":[
        "Figuig"
    ],
    "name:jpn_x_preferred":[
        "\u30d5\u30a1\u30ad\u30af"
    ],
    "name:kan_x_preferred":[
        "\u0cab\u0cbf\u0c97\u0cc1\u0caf\u0cbf\u0c97\u0ccd"
    ],
    "name:kor_x_preferred":[
        "\ud53c\uae30\uadf8"
    ],
    "name:lav_x_preferred":[
        "Figiga"
    ],
    "name:lit_x_preferred":[
        "Figigas"
    ],
    "name:mar_x_preferred":[
        "\u092b\u0940\u0917\u0941\u0907\u0917"
    ],
    "name:msa_x_preferred":[
        "Figuig"
    ],
    "name:nld_x_preferred":[
        "Figuig"
    ],
    "name:nob_x_preferred":[
        "Figuig"
    ],
    "name:pol_x_preferred":[
        "Fid\u017cid\u017c"
    ],
    "name:por_x_preferred":[
        "Figuig"
    ],
    "name:ron_x_preferred":[
        "Figuig"
    ],
    "name:rus_x_preferred":[
        "\u0424\u0438\u0433\u0438\u0433"
    ],
    "name:sin_x_preferred":[
        "\u0dc6\u0dd2\u0d9c\u0dd4\u0d89\u0d9c\u0dca"
    ],
    "name:spa_x_preferred":[
        "Figuig"
    ],
    "name:swe_x_preferred":[
        "Figuig"
    ],
    "name:tam_x_preferred":[
        "\u0baa\u0bbf\u0b95\u0bc1\u0baf\u0bbf\u0b99\u0bcd"
    ],
    "name:tel_x_preferred":[
        "\u0c2b\u0c3f\u0c17\u0c4d\u0c07\u0c17\u0c4d"
    ],
    "name:tha_x_preferred":[
        "\u0e1f\u0e34\u0e01\u0e34\u0e01"
    ],
    "name:tur_x_preferred":[
        "Figuig"
    ],
    "name:ukr_x_preferred":[
        "\u0424\u0456\u0433\u0456\u0433"
    ],
    "name:unk_x_variant":[
        "Figuiq"
    ],
    "name:urd_x_preferred":[
        "\u0641\u06a9\u06cc\u06a9"
    ],
    "name:vie_x_preferred":[
        "Figuig"
    ],
    "name:zho_x_preferred":[
        "\u83f2\u5409\u683c"
    ],
    "qs:gn_country":"MA",
    "qs:gn_fcode":"PPL",
    "qs:gn_pop":12516,
    "qs:name":"Figuig",
    "qs:name_adm0":"\u0627\u0644\u0645\u063a\u0631\u0628",
    "qs:name_adm1":"\u0627\u0644\u062c\u0647\u0629 \u0627\u0644\u0634\u0631\u0642\u064a\u0629",
    "qs:photos":66,
    "qs:photos_1k":13,
    "qs:photos_9k":1,
    "qs:photos_9r":2,
    "qs:photos_all":66,
    "qs:photos_sr":2,
    "qs:placetype":"Town",
    "qs:pop_sr":"6",
    "qs:woe_adm0":23424893,
    "wd:wordcount":844,
    "wof:name":"Figuig",
    "wof:placetype":"locality",
    "wof:population":12516
},
  "geometry": {"coordinates":[-1.22855,32.10891],"type":"Point"}
}