{
  "type": "Feature",
  "properties": {
    "gn:admin1_code":"01",
    "gn:asciiname":"Douar Timizar",
    "gn:country_code":"MA",
    "gn:dem":739,
    "gn:feature_class":"P",
    "gn:feature_code":"PPL",
    "gn:name":"Douar Timizar",
    "gn:population":0,
    "gn:timezone":"Africa/Casablanca",
    "iso:country":"MA",
    "name:und_x_variant":[
        "Timizar"
    ],
    "wof:name":"Douar Timizar",
    "wof:placetype":"locality"
},
  "geometry": {"coordinates":[-5.40105,35.2903],"type":"Point"}
}