{
  "type": "Feature",
  "properties": {
    "gn:admin1_code":"07",
    "gn:asciiname":"Ait Ballahsane",
    "gn:country_code":"MA",
    "gn:dem":787,
    "gn:feature_class":"P",
    "gn:feature_code":"PPL",
    "gn:name":"A\u00eft Ballahsane",
    "gn:population":0,
    "gn:timezone":"Africa/Casablanca",
    "iso:country":"MA",
    "name:und_x_variant":[
        "A\u00eft Bel Lahs\u00e8n",
        "A\u00eft Bel Lahsene",
        "A\u00eft Ballahsane"
    ],
    "wof:name":"Ait Ballahsane",
    "wof:placetype":"locality"
},
  "geometry": {"coordinates":[-7.71793,31.45825],"type":"Point"}
}