{
  "type": "Feature",
  "properties": {
    "gn:admin1_code":"1.0",
    "gn:asciiname":"Sidi Qanqouch",
    "gn:country_code":"MA",
    "gn:dem":11,
    "gn:feature_class":"P",
    "gn:feature_code":"PPL",
    "gn:name":"Sidi Qanqouch",
    "gn:population":0,
    "gn:timezone":"Africa/Casablanca",
    "iso:country":"MA",
    "wof:name":"Sidi Qanqouch",
    "wof:placetype":"locality"
},
  "geometry": {"coordinates":[-5.69786,35.82558],"type":"Point"}
}