{
  "type": "Feature",
  "properties": {
    "gn:admin1_code":"01",
    "gn:asciiname":"Bou Salah",
    "gn:country_code":"MA",
    "gn:dem":419,
    "gn:feature_class":"P",
    "gn:feature_code":"PPL",
    "gn:name":"Bou Salah",
    "gn:population":0,
    "gn:timezone":"Africa/Casablanca",
    "iso:country":"MA",
    "wof:name":"Bou Salah",
    "wof:placetype":"locality"
},
  "geometry": {"coordinates":[-5.38572,34.75568],"type":"Point"}
}