{
  "type": "Feature",
  "properties": {
    "gn:admin1_code":"07",
    "gn:asciiname":"Douar Jaidate Mghinya",
    "gn:country_code":"MA",
    "gn:dem":538,
    "gn:feature_class":"P",
    "gn:feature_code":"PPL",
    "gn:name":"Douar Jaidate Mghinya",
    "gn:population":0,
    "gn:timezone":"Africa/Casablanca",
    "iso:country":"MA",
    "name:und_x_variant":[
        "Douar Chorfa Ja\u00efdat",
        "Chorfa Ja\u00efdat",
        "Douar Jaidate Mghinya"
    ],
    "wof:name":"Douar Jaidate Mghinya",
    "wof:placetype":"locality"
},
  "geometry": {"coordinates":[-7.63368,31.70841],"type":"Point"}
}