{
  "type": "Feature",
  "properties": {
    "gn:admin1_code":"6.0",
    "gn:asciiname":"Douar Bouamer",
    "gn:country_code":"MA",
    "gn:dem":308,
    "gn:feature_class":"P",
    "gn:feature_code":"PPL",
    "gn:name":"Douar Bouamer",
    "gn:population":0,
    "gn:timezone":"Africa/Casablanca",
    "iso:country":"MA",
    "wof:name":"Douar Bouamer",
    "wof:placetype":"locality"
},
  "geometry": {"coordinates":[-7.10775,33.515],"type":"Point"}
}