{
  "type": "Feature",
  "properties": {
    "gn:admin1_code":"09",
    "gn:asciiname":"Ait Ouenla",
    "gn:country_code":"MA",
    "gn:dem":142,
    "gn:feature_class":"P",
    "gn:feature_code":"PPL",
    "gn:name":"A\u00eft Ouenla",
    "gn:population":0,
    "gn:timezone":"Africa/Casablanca",
    "iso:country":"MA",
    "wof:name":"Ait Ouenla",
    "wof:placetype":"locality"
},
  "geometry": {"coordinates":[-9.45022,29.86526],"type":"Point"}
}