{
  "type": "Feature",
  "properties": {
    "gn:admin1_code":"06",
    "gn:asciiname":"Dar El Haj Bou Chaib Bel Kbiar",
    "gn:country_code":"MA",
    "gn:dem":84,
    "gn:feature_class":"P",
    "gn:feature_code":"PPL",
    "gn:name":"Dar El Haj Bou Cha\u00efb Bel Kbiar",
    "gn:population":0,
    "gn:timezone":"Africa/Casablanca",
    "iso:country":"MA",
    "name:und_x_variant":[
        "Ouled Boucha\u00efb Ben Ca\u00efd",
        "Dar-Ca\u00efd-Bouch\u00e2\u00efb",
        "Douar el Ca\u00efd Boucha\u00efb",
        "Dar El Haj Bou Cha\u00efb Bel Kbiar"
    ],
    "wof:name":"Dar El Haj Bou Chaib Bel Kbiar",
    "wof:placetype":"locality"
},
  "geometry": {"coordinates":[-8.42196,33.07906],"type":"Point"}
}