{
  "type": "Feature",
  "properties": {
    "gn:admin1_code":"9.0",
    "gn:asciiname":"Ibarzizane",
    "gn:country_code":"MA",
    "gn:dem":2203,
    "gn:feature_class":"P",
    "gn:feature_code":"PPL",
    "gn:name":"Ibarzizane",
    "gn:population":0,
    "gn:timezone":"Africa/Casablanca",
    "iso:country":"MA",
    "wof:name":"Ibarzizane",
    "wof:placetype":"locality"
},
  "geometry": {"coordinates":[-8.05331,30.86588],"type":"Point"}
}