{
  "type": "Feature",
  "properties": {
    "gn:admin1_code":"7.0",
    "gn:asciiname":"Douar Arabat",
    "gn:country_code":"MA",
    "gn:dem":451,
    "gn:feature_class":"P",
    "gn:feature_code":"PPL",
    "gn:name":"Douar Arabat",
    "gn:population":0,
    "gn:timezone":"Africa/Casablanca",
    "iso:country":"MA",
    "wof:name":"Douar Arabat",
    "wof:placetype":"locality"
},
  "geometry": {"coordinates":[-8.20366,32.35624],"type":"Point"}
}