{
  "type": "Feature",
  "properties": {
    "gn:admin1_code":"9.0",
    "gn:asciiname":"Tigammi-n-Tallakht",
    "gn:country_code":"MA",
    "gn:dem":612,
    "gn:feature_class":"P",
    "gn:feature_code":"PPL",
    "gn:name":"Tigammi-n-Tallakht",
    "gn:population":0,
    "gn:timezone":"Africa/Casablanca",
    "iso:country":"MA",
    "wof:name":"Tigammi-n-Tallakht",
    "wof:placetype":"locality"
},
  "geometry": {"coordinates":[-8.25758,30.70243],"type":"Point"}
}