{
  "type": "Feature",
  "properties": {
    "gn:admin1_code":"6.0",
    "gn:asciiname":"Laouta",
    "gn:country_code":"MA",
    "gn:dem":48,
    "gn:feature_class":"P",
    "gn:feature_code":"PPL",
    "gn:name":"Laouta",
    "gn:population":0,
    "gn:timezone":"Africa/Casablanca",
    "iso:country":"MA",
    "wof:name":"Laouta",
    "wof:placetype":"locality"
},
  "geometry": {"coordinates":[-8.51378,33.10174],"type":"Point"}
}