{
  "type": "Feature",
  "properties": {
    "gn:admin1_code":"6.0",
    "gn:asciiname":"Loudadna",
    "gn:country_code":"MA",
    "gn:dem":213,
    "gn:feature_class":"P",
    "gn:feature_code":"PPL",
    "gn:name":"Loudadna",
    "gn:population":0,
    "gn:timezone":"Africa/Casablanca",
    "iso:country":"MA",
    "wof:name":"Loudadna",
    "wof:placetype":"locality"
},
  "geometry": {"coordinates":[-7.9265,33.17232],"type":"Point"}
}