{
  "type": "Feature",
  "properties": {
    "gn:admin1_code":"1.0",
    "gn:asciiname":"Houmet Lhatba",
    "gn:country_code":"MA",
    "gn:dem":272,
    "gn:feature_class":"P",
    "gn:feature_code":"PPL",
    "gn:name":"Houmet Lhatba",
    "gn:population":0,
    "gn:timezone":"Africa/Casablanca",
    "iso:country":"MA",
    "wof:name":"Houmet Lhatba",
    "wof:placetype":"locality"
},
  "geometry": {"coordinates":[-5.42269,35.88724000000001],"type":"Point"}
}