{
  "type": "Feature",
  "properties": {
    "gn:admin1_code":"2.0",
    "gn:asciiname":"Douar Essebbab",
    "gn:country_code":"MA",
    "gn:dem":154,
    "gn:feature_class":"P",
    "gn:feature_code":"PPL",
    "gn:name":"Douar Essebbab",
    "gn:population":0,
    "gn:timezone":"Africa/Casablanca",
    "iso:country":"MA",
    "wof:name":"Douar Essebbab",
    "wof:placetype":"locality"
},
  "geometry": {"coordinates":[-2.75903,35.04495],"type":"Point"}
}