{
  "type": "Feature",
  "properties": {
    "gn:admin1_code":"04",
    "gn:asciiname":"Chougrane",
    "gn:country_code":"MA",
    "gn:dem":194,
    "gn:feature_class":"P",
    "gn:feature_code":"PPL",
    "gn:name":"Chougrane",
    "gn:population":0,
    "gn:timezone":"Africa/Casablanca",
    "iso:country":"MA",
    "name:und_x_variant":[
        "Chograne",
        "Douar Chograne"
    ],
    "wof:name":"Chougrane",
    "wof:placetype":"locality"
},
  "geometry": {"coordinates":[-6.01899,34.9152],"type":"Point"}
}