{
  "type": "Feature",
  "properties": {
    "gn:admin1_code":"7.0",
    "gn:asciiname":"Bou Tziki",
    "gn:country_code":"MA",
    "gn:dem":378,
    "gn:feature_class":"P",
    "gn:feature_code":"PPL",
    "gn:name":"Bou Tziki",
    "gn:population":0,
    "gn:timezone":"Africa/Casablanca",
    "iso:country":"MA",
    "wof:name":"Bou Tziki",
    "wof:placetype":"locality"
},
  "geometry": {"coordinates":[-9.72212,31.17064],"type":"Point"}
}