{
  "type": "Feature",
  "properties": {
    "gn:admin1_code":"9.0",
    "gn:asciiname":"Errays Mohamed",
    "gn:country_code":"MA",
    "gn:dem":449,
    "gn:feature_class":"P",
    "gn:feature_code":"PPL",
    "gn:name":"Errays Mohamed",
    "gn:population":0,
    "gn:timezone":"Africa/Casablanca",
    "iso:country":"MA",
    "wof:name":"Errays Mohamed",
    "wof:placetype":"locality"
},
  "geometry": {"coordinates":[-9.70613,29.53773],"type":"Point"}
}