{
  "type": "Feature",
  "properties": {
    "gn:admin1_code":"04",
    "gn:asciiname":"Douar Ghzalat",
    "gn:country_code":"MA",
    "gn:dem":324,
    "gn:feature_class":"P",
    "gn:feature_code":"PPL",
    "gn:name":"Douar Ghzalat",
    "gn:population":0,
    "gn:timezone":"Africa/Casablanca",
    "iso:country":"MA",
    "name:und_x_variant":[
        "Douar el Khzalat",
        "Al Khzalat",
        "Lakzalat",
        "El Khzalat",
        "Douar Ghzalat"
    ],
    "wof:name":"Douar Ghzalat",
    "wof:placetype":"locality"
},
  "geometry": {"coordinates":[-5.86606,34.78605],"type":"Point"}
}