{
  "type": "Feature",
  "properties": {
    "gn:admin1_code":"1.0",
    "gn:asciiname":"Houmat Ihammoudene",
    "gn:country_code":"MA",
    "gn:dem":617,
    "gn:feature_class":"P",
    "gn:feature_code":"PPL",
    "gn:name":"Houmat Ihammoudene",
    "gn:population":0,
    "gn:timezone":"Africa/Casablanca",
    "iso:country":"MA",
    "wof:name":"Houmat Ihammoudene",
    "wof:placetype":"locality"
},
  "geometry": {"coordinates":[-4.79227,35.03046],"type":"Point"}
}