{
  "type": "Feature",
  "properties": {
    "gn:admin1_code":"10",
    "gn:asciiname":"Ikem",
    "gn:country_code":"MA",
    "gn:dem":557,
    "gn:feature_class":"P",
    "gn:feature_code":"PPL",
    "gn:name":"Ikem",
    "gn:population":0,
    "gn:timezone":"Africa/Casablanca",
    "iso:country":"MA",
    "name:und_x_variant":[
        "Ikm",
        "Ikem"
    ],
    "wof:name":"Ikem",
    "wof:placetype":"locality"
},
  "geometry": {"coordinates":[-9.60132,29.10187],"type":"Point"}
}