{
  "type": "Feature",
  "properties": {
    "gn:admin1_code":"08",
    "gn:asciiname":"Tamsoult",
    "gn:country_code":"MA",
    "gn:dem":1623,
    "gn:feature_class":"P",
    "gn:feature_code":"PPL",
    "gn:name":"Tamsoult",
    "gn:population":0,
    "gn:timezone":"Africa/Casablanca",
    "iso:country":"MA",
    "name:und_x_variant":[
        "Tamesoult",
        "Tamssoulte",
        "Tamsoult"
    ],
    "wof:name":"Tamsoult",
    "wof:placetype":"locality"
},
  "geometry": {"coordinates":[-6.67571,31.26857],"type":"Point"}
}