{
  "type": "Feature",
  "properties": {
    "gn:admin1_code":"02",
    "gn:asciiname":"Ifqirene",
    "gn:country_code":"MA",
    "gn:dem":425,
    "gn:feature_class":"P",
    "gn:feature_code":"PPL",
    "gn:name":"Ifqirene",
    "gn:population":0,
    "gn:timezone":"Africa/Casablanca",
    "iso:country":"MA",
    "wof:name":"Ifqirene",
    "wof:placetype":"locality"
},
  "geometry": {"coordinates":[-3.35766,35.14829],"type":"Point"}
}