{
  "type": "Feature",
  "properties": {
    "gn:admin1_code":"07",
    "gn:asciiname":"Oulad Mazour",
    "gn:country_code":"MA",
    "gn:dem":642,
    "gn:feature_class":"P",
    "gn:feature_code":"PPL",
    "gn:name":"Oulad Mazour",
    "gn:population":0,
    "gn:timezone":"Africa/Casablanca",
    "iso:country":"MA",
    "wof:name":"Oulad Mazour",
    "wof:placetype":"locality"
},
  "geometry": {"coordinates":[-7.44,31.74914],"type":"Point"}
}