{
  "type": "Feature",
  "properties": {
    "gn:admin1_code":"7.0",
    "gn:asciiname":"Ouchene",
    "gn:country_code":"MA",
    "gn:dem":260,
    "gn:feature_class":"P",
    "gn:feature_code":"PPL",
    "gn:name":"Ouchene",
    "gn:population":0,
    "gn:timezone":"Africa/Casablanca",
    "iso:country":"MA",
    "wof:name":"Ouchene",
    "wof:placetype":"locality"
},
  "geometry": {"coordinates":[-9.80457,31.12502000000001],"type":"Point"}
}