{
  "type": "Feature",
  "properties": {
    "gn:admin1_code":"4.0",
    "gn:asciiname":"Douar Oulad Ziyyane",
    "gn:country_code":"MA",
    "gn:dem":392,
    "gn:feature_class":"P",
    "gn:feature_code":"PPL",
    "gn:name":"Douar Oulad Ziyyane",
    "gn:population":0,
    "gn:timezone":"Africa/Casablanca",
    "iso:country":"MA",
    "wof:name":"Douar Oulad Ziyyane",
    "wof:placetype":"locality"
},
  "geometry": {"coordinates":[-5.53591,34.19439000000001],"type":"Point"}
}