{
  "type": "Feature",
  "properties": {
    "gn:admin1_code":"01",
    "gn:asciiname":"Douar Igueddourene",
    "gn:country_code":"MA",
    "gn:dem":672,
    "gn:feature_class":"P",
    "gn:feature_code":"PPL",
    "gn:name":"Douar Igueddourene",
    "gn:population":0,
    "gn:timezone":"Africa/Casablanca",
    "iso:country":"MA",
    "name:und_x_variant":[
        "Ikdduren",
        "Ikddourene",
        "Douar Igueddourene",
        "Garday",
        "Igues Ibeharene",
        "Igues Ibeharen"
    ],
    "wof:name":"Douar Igueddourene",
    "wof:placetype":"locality"
},
  "geometry": {"coordinates":[-4.30015,35.00527],"type":"Point"}
}