{
  "type": "Feature",
  "properties": {
    "gn:admin1_code":"01",
    "gn:asciiname":"Haidous",
    "gn:country_code":"MA",
    "gn:dem":382,
    "gn:feature_class":"P",
    "gn:feature_code":"PPL",
    "gn:name":"Ha\u00efdous",
    "gn:population":0,
    "gn:timezone":"Africa/Casablanca",
    "iso:country":"MA",
    "name:und_x_variant":[
        "Haidus",
        "Ha\u00efdous"
    ],
    "wof:name":"Haidous",
    "wof:placetype":"locality"
},
  "geometry": {"coordinates":[-4.05,35.08],"type":"Point"}
}