{
  "type": "Feature",
  "properties": {
    "gn:admin1_code":"2.0",
    "gn:asciiname":"Dar Lebrahmi Mohamed Ben Cheikh",
    "gn:country_code":"MA",
    "gn:dem":611,
    "gn:feature_class":"P",
    "gn:feature_code":"PPL",
    "gn:name":"Dar Lebrahmi Mohamed Ben Cheikh",
    "gn:population":0,
    "gn:timezone":"Africa/Casablanca",
    "iso:country":"MA",
    "wof:name":"Dar Lebrahmi Mohamed Ben Cheikh",
    "wof:placetype":"locality"
},
  "geometry": {"coordinates":[-2.44412,34.56634],"type":"Point"}
}