{
  "type": "Feature",
  "properties": {
    "gn:admin1_code":"01",
    "gn:asciiname":"Douar Tarrilane",
    "gn:country_code":"MA",
    "gn:dem":1226,
    "gn:feature_class":"P",
    "gn:feature_code":"PPL",
    "gn:name":"Douar Tarrilane",
    "gn:population":0,
    "gn:timezone":"Africa/Casablanca",
    "iso:country":"MA",
    "name:und_x_variant":[
        "Taourat",
        "Taourart",
        "Taourarte",
        "Douar Tarrilane"
    ],
    "wof:name":"Douar Tarrilane",
    "wof:placetype":"locality"
},
  "geometry": {"coordinates":[-4.90169,35.1236],"type":"Point"}
}