{
  "type": "Feature",
  "properties": {
    "gn:admin1_code":"07",
    "gn:asciiname":"Douar Oulad Boukhliq",
    "gn:country_code":"MA",
    "gn:dem":412,
    "gn:feature_class":"P",
    "gn:feature_code":"PPL",
    "gn:name":"Douar Oulad Boukhliq",
    "gn:population":0,
    "gn:timezone":"Africa/Casablanca",
    "iso:country":"MA",
    "name:und_x_variant":[
        "Boukhliq",
        "Ahel Ch\u00e2b",
        "Douar Oulad Boukhlik",
        "Oulad Boukhlik",
        "Douar Oulad Boukhliq"
    ],
    "wof:name":"Douar Oulad Boukhliq",
    "wof:placetype":"locality"
},
  "geometry": {"coordinates":[-7.65579,32.15919],"type":"Point"}
}