{
  "type": "Feature",
  "properties": {
    "gn:admin1_code":"2.0",
    "gn:asciiname":"Douar Tzayast Laalya",
    "gn:country_code":"MA",
    "gn:dem":161,
    "gn:feature_class":"P",
    "gn:feature_code":"PPL",
    "gn:name":"Douar Tzayast Laalya",
    "gn:population":0,
    "gn:timezone":"Africa/Casablanca",
    "iso:country":"MA",
    "wof:name":"Douar Tzayast Laalya",
    "wof:placetype":"locality"
},
  "geometry": {"coordinates":[-2.44095,34.91105],"type":"Point"}
}