{
  "type": "Feature",
  "properties": {
    "gn:admin1_code":"7.0",
    "gn:asciiname":"Lafqih",
    "gn:country_code":"MA",
    "gn:dem":654,
    "gn:feature_class":"P",
    "gn:feature_code":"PPL",
    "gn:name":"Lafqih",
    "gn:population":0,
    "gn:timezone":"Africa/Casablanca",
    "iso:country":"MA",
    "wof:name":"Lafqih",
    "wof:placetype":"locality"
},
  "geometry": {"coordinates":[-7.29767,31.80844],"type":"Point"}
}