{
  "type": "Feature",
  "properties": {
    "gn:admin1_code":"2.0",
    "gn:asciiname":"Bou Hraoua",
    "gn:country_code":"MA",
    "gn:dem":124,
    "gn:feature_class":"P",
    "gn:feature_code":"PPL",
    "gn:name":"Bou Hraoua",
    "gn:population":0,
    "gn:timezone":"Africa/Casablanca",
    "iso:country":"MA",
    "wof:name":"Bou Hraoua",
    "wof:placetype":"locality"
},
  "geometry": {"coordinates":[-2.97072,35.09467],"type":"Point"}
}