{
  "type": "Feature",
  "properties": {
    "gn:admin1_code":"05",
    "gn:asciiname":"Almou-n-Ait Issimour",
    "gn:country_code":"MA",
    "gn:dem":1571,
    "gn:feature_class":"P",
    "gn:feature_code":"PPL",
    "gn:name":"Almou-n-A\u00eft Issimour",
    "gn:population":0,
    "gn:timezone":"Africa/Casablanca",
    "iso:country":"MA",
    "name:und_x_variant":[
        "Almou-n-A\u00eft Issimour",
        "A\u00eft Issimour"
    ],
    "wof:name":"Almou-n-Ait Issimour",
    "wof:placetype":"locality"
},
  "geometry": {"coordinates":[-6.30104,32.08444],"type":"Point"}
}