{
  "type": "Feature",
  "properties": {
    "gn:admin1_code":"9.0",
    "gn:asciiname":"Adouwwar",
    "gn:country_code":"MA",
    "gn:dem":1234,
    "gn:feature_class":"P",
    "gn:feature_code":"PPL",
    "gn:name":"Adouwwar",
    "gn:population":0,
    "gn:timezone":"Africa/Casablanca",
    "iso:country":"MA",
    "wof:name":"Adouwwar",
    "wof:placetype":"locality"
},
  "geometry": {"coordinates":[-9.00026,29.85361],"type":"Point"}
}