{
  "type": "Feature",
  "properties": {
    "gn:admin1_code":"1.0",
    "gn:asciiname":"Douar Talentaleb",
    "gn:country_code":"MA",
    "gn:dem":992,
    "gn:feature_class":"P",
    "gn:feature_code":"PPL",
    "gn:name":"Douar Talentaleb",
    "gn:population":0,
    "gn:timezone":"Africa/Casablanca",
    "iso:country":"MA",
    "name:und_x_variant":[
        "Douar Talanttalb"
    ],
    "wof:name":"Douar Talentaleb",
    "wof:placetype":"locality"
},
  "geometry": {"coordinates":[-4.74596,35.151],"type":"Point"}
}