{
  "type": "Feature",
  "properties": {
    "gn:admin1_code":"4.0",
    "gn:asciiname":"Haddada",
    "gn:country_code":"MA",
    "gn:dem":19,
    "gn:feature_class":"P",
    "gn:feature_code":"PPL",
    "gn:name":"Haddada",
    "gn:population":0,
    "gn:timezone":"Africa/Casablanca",
    "iso:country":"MA",
    "wof:name":"Haddada",
    "wof:placetype":"locality"
},
  "geometry": {"coordinates":[-6.50788,34.25294],"type":"Point"}
}