{
  "type": "Feature",
  "properties": {
    "gn:admin1_code":"07",
    "gn:asciiname":"El Amarna",
    "gn:country_code":"MA",
    "gn:dem":96,
    "gn:feature_class":"P",
    "gn:feature_code":"PPL",
    "gn:name":"El Amarna",
    "gn:population":0,
    "gn:timezone":"Africa/Casablanca",
    "iso:country":"MA",
    "name:und_x_variant":[
        "Laamarna",
        "Douar El Amarna",
        "El Amarna"
    ],
    "wof:name":"El Amarna",
    "wof:placetype":"locality"
},
  "geometry": {"coordinates":[-9.09749,32.63994],"type":"Point"}
}