{
  "type": "Feature",
  "properties": {
    "gn:admin1_code":"06",
    "gn:asciiname":"Douar Regaa Oulad Sidi Hanine",
    "gn:country_code":"MA",
    "gn:dem":136,
    "gn:feature_class":"P",
    "gn:feature_code":"PPL",
    "gn:name":"Douar Regaa Oulad Sidi Hanine",
    "gn:population":0,
    "gn:timezone":"Africa/Casablanca",
    "iso:country":"MA",
    "wof:name":"Douar Regaa Oulad Sidi Hanine",
    "wof:placetype":"locality"
},
  "geometry": {"coordinates":[-8.23,32.98],"type":"Point"}
}