{
  "type": "Feature",
  "properties": {
    "gn:admin1_code":"09",
    "gn:asciiname":"Talekjount",
    "gn:country_code":"MA",
    "gn:dem":414,
    "gn:feature_class":"P",
    "gn:feature_code":"PPL",
    "gn:name":"Talekjount",
    "gn:population":0,
    "gn:timezone":"Africa/Casablanca",
    "iso:country":"MA",
    "wof:name":"Talekjount",
    "wof:placetype":"locality"
},
  "geometry": {"coordinates":[-9.56502,30.45957000000001],"type":"Point"}
}