{
  "type": "Feature",
  "properties": {
    "gn:admin1_code":"03",
    "gn:asciiname":"Maicha",
    "gn:country_code":"MA",
    "gn:dem":236,
    "gn:feature_class":"P",
    "gn:feature_code":"PPL",
    "gn:name":"Ma\u00efcha",
    "gn:population":0,
    "gn:timezone":"Africa/Casablanca",
    "iso:country":"MA",
    "name:und_x_variant":[
        "Lahmoucha",
        "Ma\u00efcha"
    ],
    "wof:name":"Maicha",
    "wof:placetype":"locality"
},
  "geometry": {"coordinates":[-5.11852,34.25114],"type":"Point"}
}