{
  "type": "Feature",
  "properties": {
    "gn:admin1_code":"03",
    "gn:asciiname":"Ain el Haiz",
    "gn:country_code":"MA",
    "gn:dem":1512,
    "gn:feature_class":"P",
    "gn:feature_code":"PPL",
    "gn:name":"A\u00efn el Ha\u00efz",
    "gn:population":0,
    "gn:timezone":"Africa/Casablanca",
    "iso:country":"MA",
    "name:und_x_variant":[
        "A\u00eft el Ha\u00efz",
        "A\u00efn el Ha\u00efz"
    ],
    "wof:name":"Ain el Haiz",
    "wof:placetype":"locality"
},
  "geometry": {"coordinates":[-4.24716,33.52924],"type":"Point"}
}