{
  "type": "Feature",
  "properties": {
    "gn:admin1_code":"3.0",
    "gn:asciiname":"Dar Ait Said Ou Moussa",
    "gn:country_code":"MA",
    "gn:dem":1226,
    "gn:feature_class":"P",
    "gn:feature_code":"PPL",
    "gn:name":"Dar Ait Said Ou Moussa",
    "gn:population":0,
    "gn:timezone":"Africa/Casablanca",
    "iso:country":"MA",
    "wof:name":"Dar Ait Said Ou Moussa",
    "wof:placetype":"locality"
},
  "geometry": {"coordinates":[-5.58575,33.51748],"type":"Point"}
}