{
  "type": "Feature",
  "properties": {
    "gn:admin1_code":"6.0",
    "gn:asciiname":"Douar Laassilat",
    "gn:country_code":"MA",
    "gn:dem":502,
    "gn:feature_class":"P",
    "gn:feature_code":"PPL",
    "gn:name":"Douar Laassilat",
    "gn:population":0,
    "gn:timezone":"Africa/Casablanca",
    "iso:country":"MA",
    "wof:name":"Douar Laassilat",
    "wof:placetype":"locality"
},
  "geometry": {"coordinates":[-7.23303,33.12534],"type":"Point"}
}