{
  "type": "Feature",
  "properties": {
    "gn:admin1_code":"1.0",
    "gn:asciiname":"Haoumet Lmoujahidine",
    "gn:country_code":"MA",
    "gn:dem":52,
    "gn:feature_class":"P",
    "gn:feature_code":"PPL",
    "gn:name":"Haoumet Lmoujahidine",
    "gn:population":0,
    "gn:timezone":"Africa/Casablanca",
    "iso:country":"MA",
    "wof:name":"Haoumet Lmoujahidine",
    "wof:placetype":"locality"
},
  "geometry": {"coordinates":[-5.84593,35.76874],"type":"Point"}
}