{
  "type": "Feature",
  "properties": {
    "gn:admin1_code":"3.0",
    "gn:asciiname":"Douar Ben Tahrat",
    "gn:country_code":"MA",
    "gn:dem":175,
    "gn:feature_class":"P",
    "gn:feature_code":"PPL",
    "gn:name":"Douar Ben Tahrat",
    "gn:population":0,
    "gn:timezone":"Africa/Casablanca",
    "iso:country":"MA",
    "wof:name":"Douar Ben Tahrat",
    "wof:placetype":"locality"
},
  "geometry": {"coordinates":[-5.29857,34.32438],"type":"Point"}
}