{
  "type": "Feature",
  "properties": {
    "gn:admin1_code":"8.0",
    "gn:asciiname":"Timzoughine",
    "gn:country_code":"MA",
    "gn:dem":1023,
    "gn:feature_class":"P",
    "gn:feature_code":"PPL",
    "gn:name":"Timzoughine",
    "gn:population":0,
    "gn:timezone":"Africa/Casablanca",
    "iso:country":"MA",
    "wof:name":"Timzoughine",
    "wof:placetype":"locality"
},
  "geometry": {"coordinates":[-4.41848,31.89507],"type":"Point"}
}