{
  "type": "Feature",
  "properties": {
    "gn:admin1_code":"4.0",
    "gn:asciiname":"Mahallen Jlal Oueld Corta",
    "gn:country_code":"MA",
    "gn:dem":37,
    "gn:feature_class":"P",
    "gn:feature_code":"PPL",
    "gn:name":"Mahallen Jlal Oueld Corta",
    "gn:population":0,
    "gn:timezone":"Africa/Casablanca",
    "iso:country":"MA",
    "wof:name":"Mahallen Jlal Oueld Corta",
    "wof:placetype":"locality"
},
  "geometry": {"coordinates":[-6.56209,34.23178],"type":"Point"}
}