{
  "type": "Feature",
  "properties": {
    "gn:admin1_code":"3.0",
    "gn:asciiname":"Cooperative Lbouzidia",
    "gn:country_code":"MA",
    "gn:dem":464,
    "gn:feature_class":"P",
    "gn:feature_code":"PPLF",
    "gn:name":"Coop\u00e9rative Lbouzidia",
    "gn:population":0,
    "gn:timezone":"Africa/Casablanca",
    "iso:country":"MA",
    "wof:name":"Cooperative Lbouzidia",
    "wof:placetype":"locality"
},
  "geometry": {"coordinates":[-4.91699,34.01815999999999],"type":"Point"}
}