{
  "type": "Feature",
  "properties": {
    "gn:admin1_code":"09",
    "gn:asciiname":"Imhilene",
    "gn:country_code":"MA",
    "gn:dem":2038,
    "gn:feature_class":"P",
    "gn:feature_code":"PPL",
    "gn:name":"Imhilene",
    "gn:population":0,
    "gn:timezone":"Africa/Casablanca",
    "iso:country":"MA",
    "name:und_x_variant":[
        "Imhilem",
        "Imhilene"
    ],
    "wof:name":"Imhilene",
    "wof:placetype":"locality"
},
  "geometry": {"coordinates":[-7.86106,31.0203],"type":"Point"}
}