{
  "type": "Feature",
  "properties": {
    "gn:gn_country":"MA",
    "gn:gn_fcode":"ADM3",
    "gn:gn_pop":7297,
    "gn:population":6724,
    "iso:country":"MA",
    "name:ara_x_preferred":[
        "\u062a\u0627\u0648\u064a\u0627\u0644\u062a"
    ],
    "name:ara_x_variant":[
        "\u062a\u0633\u0648\u0633\u0641\u064a"
    ],
    "name:cat_x_preferred":[
        "Tassousfi"
    ],
    "name:ceb_x_preferred":[
        "Tassousfi"
    ],
    "name:fra_x_preferred":[
        "Tassousfi"
    ],
    "name:fra_x_variant":[
        "Tassousfi (CR)",
        "Tassousfi (Commune Rurale)"
    ],
    "name:ita_x_preferred":[
        "Tassousfi"
    ],
    "name:swe_x_preferred":[
        "Tassousfi"
    ],
    "qs_pg:aaroncc":"MA",
    "qs_pg:gn_country":"MA",
    "qs_pg:gn_fcode":"ADM3",
    "qs_pg:gn_pop":7297,
    "qs_pg:name":"Tassousfi",
    "qs_pg:photos_9r":0,
    "qs_pg:photos_sr":0,
    "qs_pg:pop_sr":5,
    "qs_pg:qs_pg_placetype":"localadmin",
    "wof:name":"Tassousfi",
    "wof:placetype":"localadmin",
    "wof:population":6724
},
  "geometry": {"coordinates":[-7.89546,30.45218],"type":"Point"}
}