{
  "type": "Feature",
  "properties": {
    "gn:admin1_code":"10",
    "gn:asciiname":"Indichene",
    "gn:country_code":"MA",
    "gn:dem":906,
    "gn:feature_class":"P",
    "gn:feature_code":"PPL",
    "gn:name":"Indichene",
    "gn:population":0,
    "gn:timezone":"Africa/Casablanca",
    "iso:country":"MA",
    "name:und_x_variant":[
        "Imdichne",
        "Indichene"
    ],
    "wof:name":"Indichene",
    "wof:placetype":"locality"
},
  "geometry": {"coordinates":[-9.77433,29.22514],"type":"Point"}
}