{
  "type": "Feature",
  "properties": {
    "gn:admin1_code":"8.0",
    "gn:asciiname":"Taswit",
    "gn:country_code":"MA",
    "gn:dem":1436,
    "gn:feature_class":"P",
    "gn:feature_code":"PPL",
    "gn:name":"Taswit",
    "gn:population":0,
    "gn:timezone":"Africa/Casablanca",
    "iso:country":"MA",
    "wof:name":"Taswit",
    "wof:placetype":"locality"
},
  "geometry": {"coordinates":[-6.08717,31.22532],"type":"Point"}
}