{
  "type": "Feature",
  "properties": {
    "gn:admin1_code":"01",
    "gn:asciiname":"Etchea",
    "gn:country_code":"MA",
    "gn:dem":318,
    "gn:feature_class":"P",
    "gn:feature_code":"PPL",
    "gn:name":"Etchea",
    "gn:population":0,
    "gn:timezone":"Africa/Casablanca",
    "iso:country":"MA",
    "wof:name":"Etchea",
    "wof:placetype":"locality"
},
  "geometry": {"coordinates":[-3.94841,35.18182],"type":"Point"}
}