{
  "type": "Feature",
  "properties": {
    "gn:admin1_code":"10.0",
    "gn:asciiname":"Icwabane",
    "gn:country_code":"MA",
    "gn:dem":997,
    "gn:feature_class":"P",
    "gn:feature_code":"PPL",
    "gn:name":"I\u00e7wabane",
    "gn:population":0,
    "gn:timezone":"Africa/Casablanca",
    "iso:country":"MA",
    "wof:name":"Icwabane",
    "wof:placetype":"locality"
},
  "geometry": {"coordinates":[-9.75621,29.31787000000001],"type":"Point"}
}