{
  "type": "Feature",
  "properties": {
    "gn:admin1_code":"07",
    "gn:asciiname":"Lehouamda",
    "gn:country_code":"MA",
    "gn:dem":86,
    "gn:feature_class":"P",
    "gn:feature_code":"PPL",
    "gn:name":"Lehouamda",
    "gn:population":0,
    "gn:timezone":"Africa/Casablanca",
    "iso:country":"MA",
    "name:und_x_variant":[
        "Houamda",
        "Douar Krouamda",
        "Khouamda",
        "Lehouamda"
    ],
    "wof:name":"Lehouamda",
    "wof:placetype":"locality"
},
  "geometry": {"coordinates":[-9.21922,32.55689],"type":"Point"}
}