{
  "type": "Feature",
  "properties": {
    "gn:admin1_code":"09",
    "gn:asciiname":"Tagmou-n-Ait Oumziyl",
    "gn:country_code":"MA",
    "gn:dem":1267,
    "gn:feature_class":"P",
    "gn:feature_code":"PPL",
    "gn:name":"Tagmou-n-A\u00eft Oumziyl",
    "gn:population":0,
    "gn:timezone":"Africa/Casablanca",
    "iso:country":"MA",
    "name:und_x_variant":[
        "Taguimoute",
        "Tagmout",
        "Tagmou-n-A\u00eft Oumziyl"
    ],
    "wof:name":"Tagmou-n-Ait Oumziyl",
    "wof:placetype":"locality"
},
  "geometry": {"coordinates":[-9.07659,29.74586],"type":"Point"}
}