{
  "type": "Feature",
  "properties": {
    "gn:admin1_code":"9.0",
    "gn:asciiname":"Azrou n'Ait I'zza ou Yassine",
    "gn:country_code":"MA",
    "gn:dem":192,
    "gn:feature_class":"P",
    "gn:feature_code":"PPL",
    "gn:name":"Azrou n\u2019A\u00eft I\u2019zza ou Yassine",
    "gn:population":0,
    "gn:timezone":"Africa/Casablanca",
    "iso:country":"MA",
    "wof:name":"Azrou n'Ait I'zza ou Yassine",
    "wof:placetype":"locality"
},
  "geometry": {"coordinates":[-9.49286,29.86922],"type":"Point"}
}