{
  "type": "Feature",
  "properties": {
    "gn:admin1_code":"8.0",
    "gn:asciiname":"Khouttart Azag N-ouchchane",
    "gn:country_code":"MA",
    "gn:dem":1079,
    "gn:feature_class":"P",
    "gn:feature_code":"PPL",
    "gn:name":"Khouttart Azag N-ouchchane",
    "gn:population":0,
    "gn:timezone":"Africa/Casablanca",
    "iso:country":"MA",
    "wof:name":"Khouttart Azag N-ouchchane",
    "wof:placetype":"locality"
},
  "geometry": {"coordinates":[-5.21758,31.52034],"type":"Point"}
}