{
  "type": "Feature",
  "properties": {
    "gn:admin1_code":"1.0",
    "gn:asciiname":"Douar El Qantra",
    "gn:country_code":"MA",
    "gn:dem":941,
    "gn:feature_class":"P",
    "gn:feature_code":"PPL",
    "gn:name":"Douar El Qantra",
    "gn:population":0,
    "gn:timezone":"Africa/Casablanca",
    "iso:country":"MA",
    "wof:name":"Douar El Qantra",
    "wof:placetype":"locality"
},
  "geometry": {"coordinates":[-5.04813,35.08884],"type":"Point"}
}