{
  "type": "Feature",
  "properties": {
    "gn:admin1_code":"9.0",
    "gn:asciiname":"Lemteriya",
    "gn:country_code":"MA",
    "gn:dem":41,
    "gn:feature_class":"P",
    "gn:feature_code":"PPL",
    "gn:name":"Lemteriya",
    "gn:population":0,
    "gn:timezone":"Africa/Casablanca",
    "iso:country":"MA",
    "wof:name":"Lemteriya",
    "wof:placetype":"locality"
},
  "geometry": {"coordinates":[-9.58373,30.25345],"type":"Point"}
}