{
  "type": "Feature",
  "properties": {
    "gn:admin1_code":"04",
    "gn:asciiname":"Qaryet Zaaytrat",
    "gn:country_code":"MA",
    "gn:dem":9,
    "gn:feature_class":"P",
    "gn:feature_code":"PPL",
    "gn:name":"Qaryet Zaaytrat",
    "gn:population":0,
    "gn:timezone":"Africa/Casablanca",
    "iso:country":"MA",
    "name:und_x_variant":[
        "Zhitrat",
        "Za\u00eftrate",
        "Douar Za\u00eftrat",
        "Qaryet Zaaytrat"
    ],
    "wof:name":"Qaryet Zaaytrat",
    "wof:placetype":"locality"
},
  "geometry": {"coordinates":[-6.33442,34.38027],"type":"Point"}
}