{
  "type": "Feature",
  "properties": {
    "gn:admin1_code":"5.0",
    "gn:asciiname":"Agandouwy-n-Ait Bou Warfad",
    "gn:country_code":"MA",
    "gn:dem":1694,
    "gn:feature_class":"P",
    "gn:feature_code":"PPL",
    "gn:name":"Agandouwy-n-A\u00eft Bou Warfad",
    "gn:population":0,
    "gn:timezone":"Africa/Casablanca",
    "iso:country":"MA",
    "wof:name":"Agandouwy-n-Ait Bou Warfad",
    "wof:placetype":"locality"
},
  "geometry": {"coordinates":[-6.59321,31.84146],"type":"Point"}
}