{
  "type": "Feature",
  "properties": {
    "gn:admin1_code":"3.0",
    "gn:asciiname":"Douar Bou Acfour",
    "gn:country_code":"MA",
    "gn:dem":1722,
    "gn:feature_class":"P",
    "gn:feature_code":"PPL",
    "gn:name":"Douar Bou A\u00e7four",
    "gn:population":0,
    "gn:timezone":"Africa/Casablanca",
    "iso:country":"MA",
    "wof:name":"Douar Bou Acfour",
    "wof:placetype":"locality"
},
  "geometry": {"coordinates":[-4.09178,33.82230999999999],"type":"Point"}
}