{
  "type": "Feature",
  "properties": {
    "gn:admin1_code":"7.0",
    "gn:asciiname":"Oulad Bel Oualda",
    "gn:country_code":"MA",
    "gn:dem":145,
    "gn:feature_class":"P",
    "gn:feature_code":"PPL",
    "gn:name":"Oulad Bel Oualda",
    "gn:population":0,
    "gn:timezone":"Africa/Casablanca",
    "iso:country":"MA",
    "wof:name":"Oulad Bel Oualda",
    "wof:placetype":"locality"
},
  "geometry": {"coordinates":[-9.1418,32.48818],"type":"Point"}
}