{
  "type": "Feature",
  "properties": {
    "gn:admin1_code":"03",
    "gn:asciiname":"Douar Gueddara",
    "gn:country_code":"MA",
    "gn:dem":98,
    "gn:feature_class":"P",
    "gn:feature_code":"PPL",
    "gn:name":"Douar Gueddara",
    "gn:population":0,
    "gn:timezone":"Africa/Casablanca",
    "iso:country":"MA",
    "name:und_x_variant":[
        "Douar el Gueddara"
    ],
    "wof:name":"Douar Gueddara",
    "wof:placetype":"locality"
},
  "geometry": {"coordinates":[-5.19022,34.31883],"type":"Point"}
}