{
  "type": "Feature",
  "properties": {
    "gn:admin1_code":"3.0",
    "gn:asciiname":"Ait Blal",
    "gn:country_code":"MA",
    "gn:dem":1260,
    "gn:feature_class":"P",
    "gn:feature_code":"PPL",
    "gn:name":"Ait Blal",
    "gn:population":0,
    "gn:timezone":"Africa/Casablanca",
    "iso:country":"MA",
    "wof:name":"Ait Blal",
    "wof:placetype":"locality"
},
  "geometry": {"coordinates":[-5.37232,33.63167],"type":"Point"}
}