{
  "type": "Feature",
  "properties": {
    "gn:admin1_code":"3.0",
    "gn:asciiname":"Ait Blal",
    "gn:country_code":"MA",
    "gn:dem":1260,
    "gn:feature_class":"P",
    "gn:feature_code":"PPL",
    "gn:name":"Ait Blal",
    "gn:population":0,
    "gn:timezone":"Africa/Casablanca",
    "iso:country":"MA",
    "name:ara_x_preferred":[
        "\u0622\u064a\u062a \u0628\u0644\u0627\u0644"
    ],
    "name:azb_x_preferred":[
        "\u0627\u06cc\u062a \u0628\u0644\u0627\u0644"
    ],
    "name:cat_x_preferred":[
        "Ait Blal"
    ],
    "name:ceb_x_preferred":[
        "Ait Blal"
    ],
    "name:fas_x_preferred":[
        "\u0627\u06cc\u062a \u0628\u0644\u0627\u0644"
    ],
    "name:ita_x_preferred":[
        "Ait Blal"
    ],
    "name:swe_x_preferred":[
        "Ait Blal"
    ],
    "wof:name":"Ait Blal",
    "wof:placetype":"locality"
},
  "geometry": {"coordinates":[-5.37232,33.63167],"type":"Point"}
}