{
  "type": "Feature",
  "properties": {
    "gn:admin1_code":"09",
    "gn:asciiname":"Tarhzout",
    "gn:country_code":"MA",
    "gn:dem":99,
    "gn:feature_class":"P",
    "gn:feature_code":"PPL",
    "gn:name":"Tarhzout",
    "gn:population":0,
    "gn:timezone":"Africa/Casablanca",
    "iso:country":"MA",
    "name:und_x_variant":[
        "Targhzout",
        "Tarhzout"
    ],
    "wof:name":"Tarhzout",
    "wof:placetype":"locality"
},
  "geometry": {"coordinates":[-9.44074,29.78845],"type":"Point"}
}