{
  "type": "Feature",
  "properties": {
    "gn:admin1_code":"09",
    "gn:asciiname":"Dar Douiou",
    "gn:country_code":"MA",
    "gn:dem":233,
    "gn:feature_class":"P",
    "gn:feature_code":"PPL",
    "gn:name":"Dar Douiou",
    "gn:population":0,
    "gn:timezone":"Africa/Casablanca",
    "iso:country":"MA",
    "name:und_x_variant":[
        "Dar Doulou",
        "Dar Douiou"
    ],
    "wof:name":"Dar Douiou",
    "wof:placetype":"locality"
},
  "geometry": {"coordinates":[-9.00225,30.29973],"type":"Point"}
}