{
  "type": "Feature",
  "properties": {
    "gn:admin1_code":"6.0",
    "gn:asciiname":"Douar Dhar Lhimer",
    "gn:country_code":"MA",
    "gn:dem":304,
    "gn:feature_class":"P",
    "gn:feature_code":"PPL",
    "gn:name":"Douar Dhar Lhimer",
    "gn:population":0,
    "gn:timezone":"Africa/Casablanca",
    "iso:country":"MA",
    "wof:name":"Douar Dhar Lhimer",
    "wof:placetype":"locality"
},
  "geometry": {"coordinates":[-7.16833,33.40463],"type":"Point"}
}