{
  "type": "Feature",
  "properties": {
    "gn:admin1_code":"5.0",
    "gn:asciiname":"Iqabliyn",
    "gn:country_code":"MA",
    "gn:dem":1161,
    "gn:feature_class":"P",
    "gn:feature_code":"PPL",
    "gn:name":"Iqabliyn",
    "gn:population":0,
    "gn:timezone":"Africa/Casablanca",
    "iso:country":"MA",
    "wof:name":"Iqabliyn",
    "wof:placetype":"locality"
},
  "geometry": {"coordinates":[-6.7013,31.7099],"type":"Point"}
}