{
  "type": "Feature",
  "properties": {
    "gn:admin1_code":"09",
    "gn:asciiname":"Dar Ourtane",
    "gn:country_code":"MA",
    "gn:dem":794,
    "gn:feature_class":"P",
    "gn:feature_code":"PPL",
    "gn:name":"Dar Ourtane",
    "gn:population":0,
    "gn:timezone":"Africa/Casablanca",
    "iso:country":"MA",
    "name:und_x_variant":[
        "Dourtane"
    ],
    "wof:name":"Dar Ourtane",
    "wof:placetype":"locality"
},
  "geometry": {"coordinates":[-9.15114,29.73403],"type":"Point"}
}