{
  "type": "Feature",
  "properties": {
    "gn:admin1_code":"09",
    "gn:asciiname":"Tirguitine",
    "gn:country_code":"MA",
    "gn:dem":1405,
    "gn:feature_class":"P",
    "gn:feature_code":"PPL",
    "gn:name":"Tirguitine",
    "gn:population":0,
    "gn:timezone":"Africa/Casablanca",
    "iso:country":"MA",
    "name:und_x_variant":[
        "Tirguittine",
        "Tirguitine"
    ],
    "wof:name":"Tirguitine",
    "wof:placetype":"locality"
},
  "geometry": {"coordinates":[-8.25622,30.23968],"type":"Point"}
}