{
  "type": "Feature",
  "properties": {
    "gn:admin1_code":"6.0",
    "gn:asciiname":"Douar Essahrayei Bou Cherif",
    "gn:country_code":"MA",
    "gn:dem":253,
    "gn:feature_class":"P",
    "gn:feature_code":"PPL",
    "gn:name":"Douar Essahrayei Bou Cherif",
    "gn:population":0,
    "gn:timezone":"Africa/Casablanca",
    "iso:country":"MA",
    "wof:name":"Douar Essahrayei Bou Cherif",
    "wof:placetype":"locality"
},
  "geometry": {"coordinates":[-8.24183,32.57366],"type":"Point"}
}