{
  "type": "Feature",
  "properties": {
    "gn:admin1_code":"5.0",
    "gn:asciiname":"Oulad Zina",
    "gn:country_code":"MA",
    "gn:dem":745,
    "gn:feature_class":"P",
    "gn:feature_code":"PPLL",
    "gn:name":"Oulad Zina",
    "gn:population":0,
    "gn:timezone":"Africa/Casablanca",
    "iso:country":"MA",
    "wof:name":"Oulad Zina",
    "wof:placetype":"locality"
},
  "geometry": {"coordinates":[-6.42614,32.82988],"type":"Point"}
}