{
  "type": "Feature",
  "properties": {
    "gn:admin1_code":"9.0",
    "gn:asciiname":"Taziymant",
    "gn:country_code":"MA",
    "gn:dem":1121,
    "gn:feature_class":"P",
    "gn:feature_code":"PPL",
    "gn:name":"Taziymant",
    "gn:population":0,
    "gn:timezone":"Africa/Casablanca",
    "iso:country":"MA",
    "name:und_x_variant":[
        "Tiyzniyt"
    ],
    "wof:name":"Taziymant",
    "wof:placetype":"locality"
},
  "geometry": {"coordinates":[-9.24865,29.62134],"type":"Point"}
}