{
  "type": "Feature",
  "properties": {
    "gn:admin1_code":"7.0",
    "gn:asciiname":"Douar n-Touzzoumt",
    "gn:country_code":"MA",
    "gn:dem":592,
    "gn:feature_class":"P",
    "gn:feature_code":"PPL",
    "gn:name":"Douar n-Touzzoumt",
    "gn:population":0,
    "gn:timezone":"Africa/Casablanca",
    "iso:country":"MA",
    "wof:name":"Douar n-Touzzoumt",
    "wof:placetype":"locality"
},
  "geometry": {"coordinates":[-9.52563,31.2901],"type":"Point"}
}