{
  "type": "Feature",
  "properties": {
    "gn:admin1_code":"01",
    "gn:asciiname":"Adraouiyine",
    "gn:country_code":"MA",
    "gn:dem":531,
    "gn:feature_class":"P",
    "gn:feature_code":"PPL",
    "gn:name":"Adraouiyine",
    "gn:population":0,
    "gn:timezone":"Africa/Casablanca",
    "iso:country":"MA",
    "wof:name":"Adraouiyine",
    "wof:placetype":"locality"
},
  "geometry": {"coordinates":[-5.10479,34.85401],"type":"Point"}
}