{
  "type": "Feature",
  "properties": {
    "gn:admin1_code":"6.0",
    "gn:asciiname":"Oulad Saleh Oulad El Maati",
    "gn:country_code":"MA",
    "gn:dem":442,
    "gn:feature_class":"P",
    "gn:feature_code":"PPL",
    "gn:name":"Oulad Saleh Oulad El Maati",
    "gn:population":0,
    "gn:timezone":"Africa/Casablanca",
    "iso:country":"MA",
    "wof:name":"Oulad Saleh Oulad El Maati",
    "wof:placetype":"locality"
},
  "geometry": {"coordinates":[-7.30653,33.14895],"type":"Point"}
}