{
  "type": "Feature",
  "properties": {
    "gn:country":"MA",
    "gn:fcode":"ADM3",
    "gn:population":6669,
    "iso:country":"MA",
    "name:ara_x_preferred":[
        "\u062d\u062f \u0627\u0644\u062f\u0631\u0627"
    ],
    "name:ara_x_variant":[
        "\u0643\u0634\u0648\u0644\u0629"
    ],
    "name:bul_x_preferred":[
        "\u041a\u0435\u0447\u043e\u0443\u043b\u0430"
    ],
    "name:cat_x_preferred":[
        "Kechoula"
    ],
    "name:ceb_x_preferred":[
        "Kechoula"
    ],
    "name:eng_x_preferred":[
        "Kechoula"
    ],
    "name:fra_x_preferred":[
        "Kechoula"
    ],
    "name:fra_x_variant":[
        "Kechoula (CR)",
        "Kechoula (Commune Rurale)"
    ],
    "name:ita_x_preferred":[
        "Kechoula"
    ],
    "name:swe_x_preferred":[
        "Kechoula"
    ],
    "qs:name":"Kechoula",
    "qs:photos_9r":0,
    "qs:photos_sr":0,
    "qs:pop_sr":"5",
    "wd:wordcount":61,
    "wof:name":"Kechoula",
    "wof:placetype":"localadmin",
    "wof:population":6669
},
  "geometry": {"coordinates":[-9.25513,31.53672],"type":"Point"}
}