{
  "type": "Feature",
  "properties": {
    "gn:admin1_code":"7.0",
    "gn:asciiname":"Khyam Amer Ould Sellami",
    "gn:country_code":"MA",
    "gn:dem":314,
    "gn:feature_class":"P",
    "gn:feature_code":"PPL",
    "gn:name":"Khyam Amer Ould Sellami",
    "gn:population":0,
    "gn:timezone":"Africa/Casablanca",
    "iso:country":"MA",
    "wof:name":"Khyam Amer Ould Sellami",
    "wof:placetype":"locality"
},
  "geometry": {"coordinates":[-8.33215,32.26963],"type":"Point"}
}