{
  "type": "Feature",
  "properties": {
    "gn:admin1_code":"7.0",
    "gn:asciiname":"Leib Maussa",
    "gn:country_code":"MA",
    "gn:dem":481,
    "gn:feature_class":"P",
    "gn:feature_code":"PPL",
    "gn:name":"Leib Maussa",
    "gn:population":0,
    "gn:timezone":"Africa/Casablanca",
    "iso:country":"MA",
    "wof:name":"Leib Maussa",
    "wof:placetype":"locality"
},
  "geometry": {"coordinates":[-7.81779,32.22497],"type":"Point"}
}