{
  "type": "Feature",
  "properties": {
    "gn:admin1_code":"03",
    "gn:asciiname":"Beni Ammar",
    "gn:country_code":"MA",
    "gn:dem":642,
    "gn:feature_class":"P",
    "gn:feature_code":"PPL",
    "gn:name":"Beni Ammar",
    "gn:population":0,
    "gn:timezone":"Africa/Casablanca",
    "iso:country":"MA",
    "name:und_x_variant":[
        "Dchar Beni Amar",
        "Beni Amar",
        "Beni Ammar"
    ],
    "wof:name":"Beni Ammar",
    "wof:placetype":"locality"
},
  "geometry": {"coordinates":[-5.43311,34.09455999999999],"type":"Point"}
}