{
  "type": "Feature",
  "properties": {
    "gn:admin1_code":"08",
    "gn:asciiname":"Ait Bou Mhand",
    "gn:country_code":"MA",
    "gn:dem":1215,
    "gn:feature_class":"P",
    "gn:feature_code":"PPL",
    "gn:name":"A\u00eft Bou Mhand",
    "gn:population":0,
    "gn:timezone":"Africa/Casablanca",
    "iso:country":"MA",
    "name:und_x_variant":[
        "A\u00eft Ben M\u2019hand",
        "A\u00eft Bou Mhand"
    ],
    "wof:name":"Ait Bou Mhand",
    "wof:placetype":"locality"
},
  "geometry": {"coordinates":[-7.12017,30.96101],"type":"Point"}
}