{
  "type": "Feature",
  "properties": {
    "gn:admin1_code":"7.0",
    "gn:asciiname":"Douar Lyazid",
    "gn:country_code":"MA",
    "gn:dem":422,
    "gn:feature_class":"P",
    "gn:feature_code":"PPL",
    "gn:name":"Douar Lyazid",
    "gn:population":0,
    "gn:timezone":"Africa/Casablanca",
    "iso:country":"MA",
    "wof:name":"Douar Lyazid",
    "wof:placetype":"locality"
},
  "geometry": {"coordinates":[-9.01185,31.61816],"type":"Point"}
}