{
  "type": "Feature",
  "properties": {
    "gn:admin1_code":"6.0",
    "gn:asciiname":"Douar Feddane Llada",
    "gn:country_code":"MA",
    "gn:dem":608,
    "gn:feature_class":"P",
    "gn:feature_code":"PPL",
    "gn:name":"Douar Feddane Llada",
    "gn:population":0,
    "gn:timezone":"Africa/Casablanca",
    "iso:country":"MA",
    "wof:name":"Douar Feddane Llada",
    "wof:placetype":"locality"
},
  "geometry": {"coordinates":[-7.40286,33.02109],"type":"Point"}
}