{
  "type": "Feature",
  "properties": {
    "gn:admin1_code":"5.0",
    "gn:asciiname":"Koudiat 'Ameur",
    "gn:country_code":"MA",
    "gn:dem":480,
    "gn:feature_class":"P",
    "gn:feature_code":"PPL",
    "gn:name":"Koudiat \u2019Ameur",
    "gn:population":0,
    "gn:timezone":"Africa/Casablanca",
    "iso:country":"MA",
    "wof:name":"Koudiat 'Ameur",
    "wof:placetype":"locality"
},
  "geometry": {"coordinates":[-6.87118,32.57011],"type":"Point"}
}