{
  "type": "Feature",
  "properties": {
    "gn:admin1_code":"03",
    "gn:asciiname":"El Madayne",
    "gn:country_code":"MA",
    "gn:dem":1046,
    "gn:feature_class":"P",
    "gn:feature_code":"PPL",
    "gn:name":"El Madayne",
    "gn:population":0,
    "gn:timezone":"Africa/Casablanca",
    "iso:country":"MA",
    "name:und_x_variant":[
        "Madiine"
    ],
    "wof:name":"El Madayne",
    "wof:placetype":"locality"
},
  "geometry": {"coordinates":[-4.30885,34.72616],"type":"Point"}
}