{
  "type": "Feature",
  "properties": {
    "gn:admin1_code":"7.0",
    "gn:asciiname":"Oulad Al Bwiyyat",
    "gn:country_code":"MA",
    "gn:dem":457,
    "gn:feature_class":"P",
    "gn:feature_code":"PPL",
    "gn:name":"Oulad Al Bwiyyat",
    "gn:population":0,
    "gn:timezone":"Africa/Casablanca",
    "iso:country":"MA",
    "wof:name":"Oulad Al Bwiyyat",
    "wof:placetype":"locality"
},
  "geometry": {"coordinates":[-8.01798,32.04181],"type":"Point"}
}