{
  "type": "Feature",
  "properties": {
    "gn:admin1_code":"1.0",
    "gn:asciiname":"Dar Rachid Libbad",
    "gn:country_code":"MA",
    "gn:dem":20,
    "gn:feature_class":"P",
    "gn:feature_code":"PPL",
    "gn:name":"Dar Rachid Libbad",
    "gn:population":0,
    "gn:timezone":"Africa/Casablanca",
    "iso:country":"MA",
    "wof:name":"Dar Rachid Libbad",
    "wof:placetype":"locality"
},
  "geometry": {"coordinates":[-5.34308,35.72790999999999],"type":"Point"}
}