{
  "type": "Feature",
  "properties": {
    "gn:admin1_code":"7.0",
    "gn:asciiname":"Bihouane",
    "gn:country_code":"MA",
    "gn:dem":508,
    "gn:feature_class":"P",
    "gn:feature_code":"PPL",
    "gn:name":"Bihouane",
    "gn:population":0,
    "gn:timezone":"Africa/Casablanca",
    "iso:country":"MA",
    "wof:name":"Bihouane",
    "wof:placetype":"locality"
},
  "geometry": {"coordinates":[-9.5392,31.17104],"type":"Point"}
}