{
  "type": "Feature",
  "properties": {
    "gn:admin1_code":"5.0",
    "gn:asciiname":"Ait Talabou 'Ali",
    "gn:country_code":"MA",
    "gn:dem":966,
    "gn:feature_class":"P",
    "gn:feature_code":"PPL",
    "gn:name":"A\u00eft Talabou \u2019Ali",
    "gn:population":0,
    "gn:timezone":"Africa/Casablanca",
    "iso:country":"MA",
    "wof:name":"Ait Talabou 'Ali",
    "wof:placetype":"locality"
},
  "geometry": {"coordinates":[-6.48879,32.11454000000001],"type":"Point"}
}