{
  "type": "Feature",
  "properties": {
    "gn:admin1_code":"04",
    "gn:asciiname":"Menia",
    "gn:country_code":"MA",
    "gn:dem":147,
    "gn:feature_class":"P",
    "gn:feature_code":"PPL",
    "gn:name":"Menia",
    "gn:population":0,
    "gn:timezone":"Africa/Casablanca",
    "iso:country":"MA",
    "name:bul_x_preferred":[
        "\u041c\u0435\u043d\u0438\u044f"
    ],
    "name:deu_x_preferred":[
        "Menia"
    ],
    "name:rus_x_preferred":[
        "\u041c\u0435\u043d\u0438\u044f"
    ],
    "name:und_x_variant":[
        "Mania"
    ],
    "wof:name":"Menia",
    "wof:placetype":"locality"
},
  "geometry": {"coordinates":[-5.44041,34.43622],"type":"Point"}
}