{
  "type": "Feature",
  "properties": {
    "gn:admin1_code":"10",
    "gn:asciiname":"Id Grou Ou Sourou",
    "gn:country_code":"MA",
    "gn:dem":268,
    "gn:feature_class":"P",
    "gn:feature_code":"PPL",
    "gn:name":"Id Grou Ou Sourou",
    "gn:population":0,
    "gn:timezone":"Africa/Casablanca",
    "iso:country":"MA",
    "name:und_x_variant":[
        "Id Gru U Suru",
        "Id Grou Ou Sourou"
    ],
    "wof:name":"Id Grou Ou Sourou",
    "wof:placetype":"locality"
},
  "geometry": {"coordinates":[-10.08,29.48],"type":"Point"}
}