{
  "type": "Feature",
  "properties": {
    "gn:admin1_code":"05",
    "gn:asciiname":"Moughyay",
    "gn:country_code":"MA",
    "gn:dem":507,
    "gn:feature_class":"P",
    "gn:feature_code":"PPL",
    "gn:name":"Moughyay",
    "gn:population":0,
    "gn:timezone":"Africa/Casablanca",
    "iso:country":"MA",
    "name:und_x_variant":[
        "Mouria\u00ef",
        "Moura\u00ef",
        "Moughyay"
    ],
    "wof:name":"Moughyay",
    "wof:placetype":"locality"
},
  "geometry": {"coordinates":[-6.98861,32.14282],"type":"Point"}
}