{
  "type": "Feature",
  "properties": {
    "gn:country":"MA",
    "gn:fcode":"ADM3",
    "gn:pop":8212,
    "iso:country":"MA",
    "name:ara_x_preferred":[
        "\u0627\u0646\u0632\u0643\u0627\u0646 (\u0627\u0644\u0628\u0644\u062f\u064a\u0629)"
    ],
    "name:fra_x_preferred":[
        "Lqliaa"
    ],
    "name:fra_x_variant":[
        "Lqliaa (CR)",
        "Lqliaa (Commune Rurale)"
    ],
    "qs:name":"Lqliaa",
    "qs:photos_9r":0,
    "qs:photos_sr":0,
    "qs:pop_sr":"5",
    "wd:wordcount":29,
    "wof:name":"Lqliaa",
    "wof:placetype":"localadmin",
    "wof:population":8212
},
  "geometry": {"coordinates":[-9.52151,30.31375],"type":"Point"}
}