{
  "type": "Feature",
  "properties": {
    "gn:admin1_code":"08",
    "gn:asciiname":"Irhrem n' Ourhbalou",
    "gn:country_code":"MA",
    "gn:dem":2700,
    "gn:feature_class":"P",
    "gn:feature_code":"PPL",
    "gn:name":"Irhrem n\u2019 Ourhbalou",
    "gn:population":0,
    "gn:timezone":"Africa/Casablanca",
    "iso:country":"MA",
    "wof:name":"Irhrem n' Ourhbalou",
    "wof:placetype":"locality"
},
  "geometry": {"coordinates":[-5.87319,32.01095],"type":"Point"}
}