{
  "type": "Feature",
  "properties": {
    "gn:admin1_code":"2.0",
    "gn:asciiname":"Dounet",
    "gn:country_code":"MA",
    "gn:dem":411,
    "gn:feature_class":"P",
    "gn:feature_code":"PPL",
    "gn:name":"Dounet",
    "gn:population":0,
    "gn:timezone":"Africa/Casablanca",
    "iso:country":"MA",
    "name:ita_x_preferred":[
        "Dounet"
    ],
    "name:msa_x_preferred":[
        "Dounet"
    ],
    "name:spa_x_preferred":[
        "Dounet"
    ],
    "name:zho_x_preferred":[
        "\u675c\u7d0d\u7279"
    ],
    "wof:name":"Dounet",
    "wof:placetype":"locality"
},
  "geometry": {"coordinates":[-3.4427,35.04398],"type":"Point"}
}