{
  "type": "Feature",
  "properties": {
    "gn:admin1_code":"08",
    "gn:asciiname":"Taourirt n'Irbial",
    "gn:country_code":"MA",
    "gn:dem":1634,
    "gn:feature_class":"P",
    "gn:feature_code":"PPL",
    "gn:name":"Taourirt n\u2019Irbial",
    "gn:population":0,
    "gn:timezone":"Africa/Casablanca",
    "iso:country":"MA",
    "wof:name":"Taourirt n'Irbial",
    "wof:placetype":"locality"
},
  "geometry": {"coordinates":[-5.62675,31.30869],"type":"Point"}
}