{
  "type": "Feature",
  "properties": {
    "gn:admin1_code":"01",
    "gn:asciiname":"El Hanata",
    "gn:country_code":"MA",
    "gn:dem":395,
    "gn:feature_class":"P",
    "gn:feature_code":"PPL",
    "gn:name":"El Hanata",
    "gn:population":0,
    "gn:timezone":"Africa/Casablanca",
    "iso:country":"MA",
    "name:und_x_variant":[
        "Hanatta",
        "El Hanata"
    ],
    "wof:name":"El Hanata",
    "wof:placetype":"locality"
},
  "geometry": {"coordinates":[-5.24345,34.63567],"type":"Point"}
}