{
  "type": "Feature",
  "properties": {
    "gn:admin1_code":"6.0",
    "gn:asciiname":"El Aloua",
    "gn:country_code":"MA",
    "gn:dem":426,
    "gn:feature_class":"P",
    "gn:feature_code":"PPL",
    "gn:name":"El Aloua",
    "gn:population":0,
    "gn:timezone":"Africa/Casablanca",
    "iso:country":"MA",
    "wof:name":"El Aloua",
    "wof:placetype":"locality"
},
  "geometry": {"coordinates":[-7.67561,32.94711],"type":"Point"}
}