{
  "type": "Feature",
  "properties": {
    "gn:admin1_code":"02",
    "gn:asciiname":"Tijdit",
    "gn:country_code":"MA",
    "gn:dem":321,
    "gn:feature_class":"P",
    "gn:feature_code":"PPL",
    "gn:name":"Tijdit",
    "gn:population":0,
    "gn:timezone":"Africa/Casablanca",
    "iso:country":"MA",
    "wof:name":"Tijdit",
    "wof:placetype":"locality"
},
  "geometry": {"coordinates":[-3.33738,35.14380999999999],"type":"Point"}
}