{
  "type": "Feature",
  "properties": {
    "gn:admin1_code":"9.0",
    "gn:asciiname":"Tagadirt-n-Sidi Ahmed",
    "gn:country_code":"MA",
    "gn:dem":619,
    "gn:feature_class":"P",
    "gn:feature_code":"PPL",
    "gn:name":"Tagadirt-n-Sidi Ahmed",
    "gn:population":0,
    "gn:timezone":"Africa/Casablanca",
    "iso:country":"MA",
    "wof:name":"Tagadirt-n-Sidi Ahmed",
    "wof:placetype":"locality"
},
  "geometry": {"coordinates":[-8.24422,30.6888],"type":"Point"}
}