{
  "type": "Feature",
  "properties": {
    "iso:country":"MA",
    "name:unk_x_variant":[
        "Ayt Tab"
    ],
    "qs:gn_country":"MA",
    "qs:gn_fcode":"PPL",
    "qs:gn_pop":0,
    "qs:name":"Ait Attab",
    "qs:name_adm0":"\u0627\u0644\u0645\u063a\u0631\u0628",
    "qs:name_adm1":"\u062a\u0627\u062f\u0644\u0629 \u0640 \u0623\u0632\u064a\u0644\u0627\u0644",
    "qs:photos":47,
    "qs:photos_1k":10,
    "qs:photos_9k":1,
    "qs:photos_9r":2,
    "qs:photos_all":47,
    "qs:photos_sr":2,
    "qs:placetype":"Town",
    "qs:pop_sr":"0",
    "qs:woe_adm0":23424893,
    "wd:wordcount":224,
    "wof:name":"Ait Attab",
    "wof:placetype":"locality"
},
  "geometry": {"coordinates":[-6.67575,32.10488],"type":"Point"}
}