{
  "type": "Feature",
  "properties": {
    "gn:admin1_code":"7.0",
    "gn:asciiname":"Lefrijat",
    "gn:country_code":"MA",
    "gn:dem":178,
    "gn:feature_class":"P",
    "gn:feature_code":"PPL",
    "gn:name":"Lefrijat",
    "gn:population":0,
    "gn:timezone":"Africa/Casablanca",
    "iso:country":"MA",
    "wof:name":"Lefrijat",
    "wof:placetype":"locality"
},
  "geometry": {"coordinates":[-9.19242,32.10462],"type":"Point"}
}