{
  "type": "Feature",
  "properties": {
    "gn:gn_country":"MA",
    "gn:gn_fcode":"ADM3",
    "gn:gn_pop":6023,
    "gn:population":6023,
    "iso:country":"MA",
    "name:ara_x_preferred":[
        "\u0627\u0641\u0631\u064a\u062c\u0629"
    ],
    "name:fra_x_preferred":[
        "Ida Ou Moumen"
    ],
    "name:fra_x_variant":[
        "Ida Ou Moumen (CR)",
        "Ida Ou Moumen (Commune Rurale)"
    ],
    "qs_pg:aaroncc":"MA",
    "qs_pg:gn_country":"MA",
    "qs_pg:gn_fcode":"ADM3",
    "qs_pg:gn_pop":6023,
    "qs_pg:name":"Ida Ou Moumen",
    "qs_pg:photos_9r":0,
    "qs_pg:photos_sr":0,
    "qs_pg:pop_sr":5,
    "qs_pg:qs_pg_placetype":"localadmin",
    "wof:name":"Ida Ou Moumen",
    "wof:placetype":"localadmin",
    "wof:population":6023
},
  "geometry": {"coordinates":[-9.00374,30.58335],"type":"Point"}
}