{
  "type": "Feature",
  "properties": {
    "gn:admin1_code":"3.0",
    "gn:asciiname":"Douar Ait Mimoune Ou Moussa",
    "gn:country_code":"MA",
    "gn:dem":1025,
    "gn:feature_class":"P",
    "gn:feature_code":"PPL",
    "gn:name":"Douar Ait Mimoune Ou Moussa",
    "gn:population":0,
    "gn:timezone":"Africa/Casablanca",
    "iso:country":"MA",
    "wof:name":"Douar Ait Mimoune Ou Moussa",
    "wof:placetype":"locality"
},
  "geometry": {"coordinates":[-5.57888,33.61124],"type":"Point"}
}