{
  "type": "Feature",
  "properties": {
    "gn:admin1_code":"03",
    "gn:asciiname":"Douar Beni Sraj",
    "gn:country_code":"MA",
    "gn:dem":951,
    "gn:feature_class":"P",
    "gn:feature_code":"PPL",
    "gn:name":"Douar Beni Sraj",
    "gn:population":0,
    "gn:timezone":"Africa/Casablanca",
    "iso:country":"MA",
    "name:und_x_variant":[
        "Beni Saraje",
        "Beni Sraj",
        "Douar Bou Srija",
        "Douar Beni Sraj"
    ],
    "wof:name":"Douar Beni Sraj",
    "wof:placetype":"locality"
},
  "geometry": {"coordinates":[-4.25871,33.98499],"type":"Point"}
}