{
  "type": "Feature",
  "properties": {
    "gn:admin1_code":"6.0",
    "gn:asciiname":"Dar Oulad al Haj Mohammed",
    "gn:country_code":"MA",
    "gn:dem":243,
    "gn:feature_class":"P",
    "gn:feature_code":"PPL",
    "gn:name":"Dar Oulad al Haj Mohammed",
    "gn:population":0,
    "gn:timezone":"Africa/Casablanca",
    "iso:country":"MA",
    "wof:name":"Dar Oulad al Haj Mohammed",
    "wof:placetype":"locality"
},
  "geometry": {"coordinates":[-7.89368,33.11419],"type":"Point"}
}