{
  "type": "Feature",
  "properties": {
    "gn:admin1_code":"03",
    "gn:asciiname":"Oulad Messaoud",
    "gn:country_code":"MA",
    "gn:dem":647,
    "gn:feature_class":"P",
    "gn:feature_code":"PPL",
    "gn:name":"Oulad Messaoud",
    "gn:population":0,
    "gn:timezone":"Africa/Casablanca",
    "iso:country":"MA",
    "name:und_x_variant":[
        "Douar Oulad Messaoud",
        "Oulad Messaoud"
    ],
    "wof:name":"Oulad Messaoud",
    "wof:placetype":"locality"
},
  "geometry": {"coordinates":[-4.33965,34.22834],"type":"Point"}
}