{
  "type": "Feature",
  "properties": {
    "gn:admin1_code":"10",
    "gn:asciiname":"Amot",
    "gn:country_code":"MA",
    "gn:dem":380,
    "gn:elevation":"0.0",
    "gn:feature_class":"P",
    "gn:feature_code":"PPL",
    "gn:name":"Amot",
    "gn:population":0,
    "gn:timezone":"Africa/Casablanca",
    "iso:country":"MA",
    "name:und_x_variant":[
        "Amot Poste",
        "Amotte",
        "Amot"
    ],
    "wof:name":"Amot",
    "wof:placetype":"locality"
},
  "geometry": {"coordinates":[-10.17988,28.19926],"type":"Point"}
}