{
  "type": "Feature",
  "properties": {
    "gn:admin1_code":"6.0",
    "gn:asciiname":"Rwawna",
    "gn:country_code":"MA",
    "gn:dem":452,
    "gn:feature_class":"P",
    "gn:feature_code":"PPL",
    "gn:name":"Rwawna",
    "gn:population":0,
    "gn:timezone":"Africa/Casablanca",
    "iso:country":"MA",
    "wof:name":"Rwawna",
    "wof:placetype":"locality"
},
  "geometry": {"coordinates":[-7.1166,32.54761],"type":"Point"}
}