{
  "type": "Feature",
  "properties": {
    "gn:admin1_code":"5.0",
    "gn:asciiname":"Amarciyd",
    "gn:country_code":"MA",
    "gn:dem":1259,
    "gn:feature_class":"P",
    "gn:feature_code":"PPL",
    "gn:name":"Amar\u00e7\u00efyd",
    "gn:population":0,
    "gn:timezone":"Africa/Casablanca",
    "iso:country":"MA",
    "wof:name":"Amarciyd",
    "wof:placetype":"locality"
},
  "geometry": {"coordinates":[-6.63309,31.91659000000001],"type":"Point"}
}