{
  "type": "Feature",
  "properties": {
    "gn:admin1_code":"3.0",
    "gn:asciiname":"Dar Driss Aarab",
    "gn:country_code":"MA",
    "gn:dem":497,
    "gn:feature_class":"P",
    "gn:feature_code":"PPL",
    "gn:name":"Dar Driss Aarab",
    "gn:population":0,
    "gn:timezone":"Africa/Casablanca",
    "iso:country":"MA",
    "wof:name":"Dar Driss Aarab",
    "wof:placetype":"locality"
},
  "geometry": {"coordinates":[-4.80592,33.94394],"type":"Point"}
}