{
  "type": "Feature",
  "properties": {
    "gn:admin1_code":"8.0",
    "gn:asciiname":"Oulad Tguir",
    "gn:country_code":"MA",
    "gn:dem":1046,
    "gn:feature_class":"P",
    "gn:feature_code":"PPL",
    "gn:name":"Oulad Tguir",
    "gn:population":0,
    "gn:timezone":"Africa/Casablanca",
    "iso:country":"MA",
    "wof:name":"Oulad Tguir",
    "wof:placetype":"locality"
},
  "geometry": {"coordinates":[-4.46753,31.91551],"type":"Point"}
}