{
  "type": "Feature",
  "properties": {
    "gn:admin1_code":"3.0",
    "gn:asciiname":"Sidi Nehhal",
    "gn:country_code":"MA",
    "gn:dem":152,
    "gn:feature_class":"P",
    "gn:feature_code":"PPL",
    "gn:name":"Sidi Nehhal",
    "gn:population":0,
    "gn:timezone":"Africa/Casablanca",
    "iso:country":"MA",
    "wof:name":"Sidi Nehhal",
    "wof:placetype":"locality"
},
  "geometry": {"coordinates":[-4.82003,34.20888],"type":"Point"}
}