{
  "type": "Feature",
  "properties": {
    "gn:admin1_code":"07",
    "gn:asciiname":"Oulad Hammou",
    "gn:country_code":"MA",
    "gn:dem":621,
    "gn:feature_class":"P",
    "gn:feature_code":"PPL",
    "gn:name":"Oulad Hammou",
    "gn:population":0,
    "gn:timezone":"Africa/Casablanca",
    "iso:country":"MA",
    "name:und_x_variant":[
        "Douar Sidi el Hameur",
        "Ouled Hamou",
        "Douar Oulad Hammou",
        "Oulad Hammou"
    ],
    "wof:name":"Oulad Hammou",
    "wof:placetype":"locality"
},
  "geometry": {"coordinates":[-7.89724,31.82528],"type":"Point"}
}