{
  "type": "Feature",
  "properties": {
    "gn:admin1_code":"07",
    "gn:asciiname":"Aouzer",
    "gn:country_code":"MA",
    "gn:dem":766,
    "gn:feature_class":"P",
    "gn:feature_code":"PPL",
    "gn:name":"Aouzer",
    "gn:population":0,
    "gn:timezone":"Africa/Casablanca",
    "iso:country":"MA",
    "name:und_x_variant":[
        "Aouzert",
        "Aouzar",
        "Aouzer"
    ],
    "wof:name":"Aouzer",
    "wof:placetype":"locality"
},
  "geometry": {"coordinates":[-8.11152,31.22398],"type":"Point"}
}