{
  "type": "Feature",
  "properties": {
    "gn:admin1_code":"01",
    "gn:asciiname":"Tagzout Entasa",
    "gn:country_code":"MA",
    "gn:dem":496,
    "gn:feature_class":"P",
    "gn:feature_code":"PPL",
    "gn:name":"Tagzout Entasa",
    "gn:population":0,
    "gn:timezone":"Africa/Casablanca",
    "iso:country":"MA",
    "wof:name":"Tagzout Entasa",
    "wof:placetype":"locality"
},
  "geometry": {"coordinates":[-3.83,34.95],"type":"Point"}
}