{
  "type": "Feature",
  "properties": {
    "gn:admin1_code":"01",
    "gn:asciiname":"Chelihat ed Dahs",
    "gn:country_code":"MA",
    "gn:dem":5,
    "gn:feature_class":"P",
    "gn:feature_code":"PPL",
    "gn:name":"Chelihat ed Dahs",
    "gn:population":0,
    "gn:timezone":"Africa/Casablanca",
    "iso:country":"MA",
    "name:und_x_variant":[
        "Sele hat de Dats",
        "Chelihat ed Dahs"
    ],
    "wof:name":"Chelihat ed Dahs",
    "wof:placetype":"locality"
},
  "geometry": {"coordinates":[-5.96645,35.12895],"type":"Point"}
}