{
  "type": "Feature",
  "properties": {
    "gn:admin1_code":"1.0",
    "gn:asciiname":"Bab Tamesstast",
    "gn:country_code":"MA",
    "gn:dem":1308,
    "gn:feature_class":"P",
    "gn:feature_code":"PPL",
    "gn:name":"Bab Tam\u00e9sstast",
    "gn:population":0,
    "gn:timezone":"Africa/Casablanca",
    "iso:country":"MA",
    "wof:name":"Bab Tamesstast",
    "wof:placetype":"locality"
},
  "geometry": {"coordinates":[-4.51736,35.00365],"type":"Point"}
}