{
  "type": "Feature",
  "properties": {
    "gn:admin1_code":"05",
    "gn:asciiname":"Souq Tlat Chougrane",
    "gn:country_code":"MA",
    "gn:dem":643,
    "gn:feature_class":"P",
    "gn:feature_code":"PPL",
    "gn:name":"Souq Tlat Chougrane",
    "gn:population":0,
    "gn:timezone":"Africa/Casablanca",
    "iso:country":"MA",
    "name:und_x_variant":[
        "Et Tleta",
        "Souk et Tleta",
        "Souk-et-Tleta-des-Ech-Chougrane",
        "Souk et Tleta des Chougrane",
        "Souq Tlat Chougrane"
    ],
    "wof:name":"Souq Tlat Chougrane",
    "wof:placetype":"locality"
},
  "geometry": {"coordinates":[-6.2806,33.01272],"type":"Point"}
}