{
  "type": "Feature",
  "properties": {
    "gn:admin1_code":"9.0",
    "gn:asciiname":"Douar Amentag",
    "gn:country_code":"MA",
    "gn:dem":73,
    "gn:feature_class":"P",
    "gn:feature_code":"PPL",
    "gn:name":"Douar Amentag",
    "gn:population":0,
    "gn:timezone":"Africa/Casablanca",
    "iso:country":"MA",
    "wof:name":"Douar Amentag",
    "wof:placetype":"locality"
},
  "geometry": {"coordinates":[-9.45328,30.29023],"type":"Point"}
}