{
  "type": "Feature",
  "properties": {
    "gn:admin1_code":"7.0",
    "gn:asciiname":"Tigzirt",
    "gn:country_code":"MA",
    "gn:dem":698,
    "gn:feature_class":"P",
    "gn:feature_code":"PPL",
    "gn:name":"Tigzirt",
    "gn:population":0,
    "gn:timezone":"Africa/Casablanca",
    "iso:country":"MA",
    "name:ara_x_preferred":[
        "\u062a\u064a\u0642\u0632\u064a\u0631\u062a"
    ],
    "name:azb_x_preferred":[
        "\u062a\u06cc\u0642\u0632\u06cc\u0631\u062a"
    ],
    "name:bre_x_preferred":[
        "Tigzirt"
    ],
    "name:fas_x_preferred":[
        "\u062a\u06cc\u0642\u0632\u06cc\u0631\u062a"
    ],
    "name:fra_x_preferred":[
        "Tigzirt"
    ],
    "name:ita_x_preferred":[
        "Tigzirt"
    ],
    "name:kab_x_preferred":[
        "Tigzirt"
    ],
    "name:msa_x_preferred":[
        "Tigzirt"
    ],
    "name:por_x_preferred":[
        "Tigzirt"
    ],
    "name:ron_x_preferred":[
        "Tigzirt"
    ],
    "name:spa_x_preferred":[
        "Tigzirt"
    ],
    "name:vie_x_preferred":[
        "Tigzirt"
    ],
    "name:zho_x_preferred":[
        "\u63d0\u683c\u6fdf\u723e\u7279"
    ],
    "wof:name":"Tigzirt",
    "wof:placetype":"locality"
},
  "geometry": {"coordinates":[-7.78385,31.45487],"type":"Point"}
}