{
  "type": "Feature",
  "properties": {
    "gn:admin1_code":"7.0",
    "gn:asciiname":"Tigzirt",
    "gn:country_code":"MA",
    "gn:dem":698,
    "gn:feature_class":"P",
    "gn:feature_code":"PPL",
    "gn:name":"Tigzirt",
    "gn:population":0,
    "gn:timezone":"Africa/Casablanca",
    "iso:country":"MA",
    "wof:name":"Tigzirt",
    "wof:placetype":"locality"
},
  "geometry": {"coordinates":[-7.78385,31.45487],"type":"Point"}
}