{
  "type": "Feature",
  "properties": {
    "gn:admin1_code":"01",
    "gn:admin2_code":"571.0",
    "gn:admin3_code":"1657103172.0",
    "gn:asciiname":"Saddina",
    "gn:country_code":"MA",
    "gn:dem":313,
    "gn:feature_class":"P",
    "gn:feature_code":"PPLA3",
    "gn:name":"Saddina",
    "gn:population":0,
    "gn:timezone":"Africa/Casablanca",
    "iso:country":"MA",
    "name:und_x_variant":[
        "Zatdina",
        "Saddina"
    ],
    "wof:name":"Saddina",
    "wof:placetype":"locality"
},
  "geometry": {"coordinates":[-5.45191,35.6141],"type":"Point"}
}