{
  "type": "Feature",
  "properties": {
    "gn:admin1_code":"6.0",
    "gn:asciiname":"Mwachma",
    "gn:country_code":"MA",
    "gn:dem":202,
    "gn:feature_class":"P",
    "gn:feature_code":"PPL",
    "gn:name":"Mwachma",
    "gn:population":0,
    "gn:timezone":"Africa/Casablanca",
    "iso:country":"MA",
    "wof:name":"Mwachma",
    "wof:placetype":"locality"
},
  "geometry": {"coordinates":[-7.99692,33.17336],"type":"Point"}
}