{
  "type": "Feature",
  "properties": {
    "gn:admin1_code":"07",
    "gn:asciiname":"Douar Nkhilat",
    "gn:country_code":"MA",
    "gn:dem":137,
    "gn:feature_class":"P",
    "gn:feature_code":"PPL",
    "gn:name":"Douar Nkhilat",
    "gn:population":0,
    "gn:timezone":"Africa/Casablanca",
    "iso:country":"MA",
    "name:und_x_variant":[
        "Nekhilat",
        "N\u2019khilat",
        "Douar en Nekhilat",
        "Douar Nkhilat"
    ],
    "wof:name":"Douar Nkhilat",
    "wof:placetype":"locality"
},
  "geometry": {"coordinates":[-9.0029,32.38346],"type":"Point"}
}