{
  "type": "Feature",
  "properties": {
    "gn:admin1_code":"2.0",
    "gn:asciiname":"Dar Mesbah",
    "gn:country_code":"MA",
    "gn:dem":431,
    "gn:feature_class":"P",
    "gn:feature_code":"PPL",
    "gn:name":"Dar Mesbah",
    "gn:population":0,
    "gn:timezone":"Africa/Casablanca",
    "iso:country":"MA",
    "wof:name":"Dar Mesbah",
    "wof:placetype":"locality"
},
  "geometry": {"coordinates":[-1.94784,34.86445],"type":"Point"}
}