{
  "type": "Feature",
  "properties": {
    "gn:admin1_code":"03",
    "gn:asciiname":"Douar Oumal",
    "gn:country_code":"MA",
    "gn:dem":694,
    "gn:feature_class":"P",
    "gn:feature_code":"PPL",
    "gn:name":"Douar Oumal",
    "gn:population":0,
    "gn:timezone":"Africa/Casablanca",
    "iso:country":"MA",
    "name:und_x_variant":[
        "Oumal"
    ],
    "wof:name":"Douar Oumal",
    "wof:placetype":"locality"
},
  "geometry": {"coordinates":[-4.16962,34.26642],"type":"Point"}
}