{
  "type": "Feature",
  "properties": {
    "gn:admin1_code":"9.0",
    "gn:asciiname":"Imi-n-Flous",
    "gn:country_code":"MA",
    "gn:dem":596,
    "gn:feature_class":"P",
    "gn:feature_code":"PPL",
    "gn:name":"Imi-n-Flous",
    "gn:population":0,
    "gn:timezone":"Africa/Casablanca",
    "iso:country":"MA",
    "wof:name":"Imi-n-Flous",
    "wof:placetype":"locality"
},
  "geometry": {"coordinates":[-8.86542,30.18605],"type":"Point"}
}