{
  "type": "Feature",
  "properties": {
    "gn:admin1_code":"04",
    "gn:asciiname":"Douar ech Chrif",
    "gn:country_code":"MA",
    "gn:dem":64,
    "gn:feature_class":"P",
    "gn:feature_code":"PPL",
    "gn:name":"Douar ech Chrif",
    "gn:population":0,
    "gn:timezone":"Africa/Casablanca",
    "iso:country":"MA",
    "name:und_x_variant":[
        "Dar ech Chrif",
        "Douar ech Chrif",
        "Ech Chrif"
    ],
    "wof:name":"Douar ech Chrif",
    "wof:placetype":"locality"
},
  "geometry": {"coordinates":[-5.50661,34.44162],"type":"Point"}
}