{
  "type": "Feature",
  "properties": {
    "gn:admin1_code":"5.0",
    "gn:asciiname":"Oulad Brahim",
    "gn:country_code":"MA",
    "gn:dem":759,
    "gn:feature_class":"P",
    "gn:feature_code":"PPL",
    "gn:name":"Oulad Brahim",
    "gn:population":0,
    "gn:timezone":"Africa/Casablanca",
    "iso:country":"MA",
    "wof:name":"Oulad Brahim",
    "wof:placetype":"locality"
},
  "geometry": {"coordinates":[-6.30373,32.80674],"type":"Point"}
}