{
  "type": "Feature",
  "properties": {
    "gn:admin1_code":"09",
    "gn:asciiname":"Wiyntsray",
    "gn:country_code":"MA",
    "gn:dem":1234,
    "gn:feature_class":"P",
    "gn:feature_code":"PPL",
    "gn:name":"Wiyntsray",
    "gn:population":0,
    "gn:timezone":"Africa/Casablanca",
    "iso:country":"MA",
    "name:und_x_variant":[
        "Ountesra\u00ef",
        "Ouin l\u2019Spraye",
        "Ouin l\u2019Sraya",
        "Wiyntsray"
    ],
    "wof:name":"Wiyntsray",
    "wof:placetype":"locality"
},
  "geometry": {"coordinates":[-9.19804,29.54205],"type":"Point"}
}