{
  "type": "Feature",
  "properties": {
    "gn:admin1_code":"9.0",
    "gn:asciiname":"Tine Chelkh Brahim",
    "gn:country_code":"MA",
    "gn:dem":84,
    "gn:feature_class":"P",
    "gn:feature_code":"PPL",
    "gn:name":"Tine Chelkh Brahim",
    "gn:population":0,
    "gn:timezone":"Africa/Casablanca",
    "iso:country":"MA",
    "wof:name":"Tine Chelkh Brahim",
    "wof:placetype":"locality"
},
  "geometry": {"coordinates":[-9.52089,30.09175],"type":"Point"}
}