{
  "type": "Feature",
  "properties": {
    "gn:admin1_code":"3.0",
    "gn:asciiname":"Douar Jnane Ettofil",
    "gn:country_code":"MA",
    "gn:dem":308,
    "gn:feature_class":"P",
    "gn:feature_code":"PPL",
    "gn:name":"Douar Jnane Ettofil",
    "gn:population":0,
    "gn:timezone":"Africa/Casablanca",
    "iso:country":"MA",
    "wof:name":"Douar Jnane Ettofil",
    "wof:placetype":"locality"
},
  "geometry": {"coordinates":[-4.96225,34.44766],"type":"Point"}
}