{
  "type": "Feature",
  "properties": {
    "gn:admin1_code":"1.0",
    "gn:asciiname":"Mriyyes Zayd",
    "gn:country_code":"MA",
    "gn:dem":23,
    "gn:feature_class":"P",
    "gn:feature_code":"PPL",
    "gn:name":"Mriyyes Zayd",
    "gn:population":0,
    "gn:timezone":"Africa/Casablanca",
    "iso:country":"MA",
    "wof:name":"Mriyyes Zayd",
    "wof:placetype":"locality"
},
  "geometry": {"coordinates":[-5.77009,35.75343],"type":"Point"}
}