{
  "type": "Feature",
  "properties": {
    "gn:admin1_code":"10.0",
    "gn:asciiname":"Talat N-Barka",
    "gn:country_code":"MA",
    "gn:dem":680,
    "gn:feature_class":"P",
    "gn:feature_code":"PPL",
    "gn:name":"Talat N-Barka",
    "gn:population":0,
    "gn:timezone":"Africa/Casablanca",
    "iso:country":"MA",
    "wof:name":"Talat N-Barka",
    "wof:placetype":"locality"
},
  "geometry": {"coordinates":[-9.95481,29.2074],"type":"Point"}
}