{
  "type": "Feature",
  "properties": {
    "gn:admin1_code":"3.0",
    "gn:asciiname":"Douar Iherayene",
    "gn:country_code":"MA",
    "gn:dem":568,
    "gn:feature_class":"P",
    "gn:feature_code":"PPL",
    "gn:name":"Douar Iherayene",
    "gn:population":0,
    "gn:timezone":"Africa/Casablanca",
    "iso:country":"MA",
    "wof:name":"Douar Iherayene",
    "wof:placetype":"locality"
},
  "geometry": {"coordinates":[-5.62898,33.83603],"type":"Point"}
}