{
  "type": "Feature",
  "properties": {
    "gn:admin1_code":"04",
    "gn:asciiname":"Douar Hrirdat",
    "gn:country_code":"MA",
    "gn:dem":80,
    "gn:feature_class":"P",
    "gn:feature_code":"PPL",
    "gn:name":"Douar Hrirdat",
    "gn:population":0,
    "gn:timezone":"Africa/Casablanca",
    "iso:country":"MA",
    "name:und_x_variant":[
        "Hrirdat"
    ],
    "wof:name":"Douar Hrirdat",
    "wof:placetype":"locality"
},
  "geometry": {"coordinates":[-5.93901,34.93652],"type":"Point"}
}