{
  "type": "Feature",
  "properties": {
    "gn:admin1_code":"07",
    "gn:asciiname":"Oulad Imloul",
    "gn:country_code":"MA",
    "gn:dem":444,
    "gn:feature_class":"P",
    "gn:feature_code":"PPL",
    "gn:name":"Oulad Imloul",
    "gn:population":0,
    "gn:timezone":"Africa/Casablanca",
    "iso:country":"MA",
    "name:ara_x_preferred":[
        "\u0623\u0648\u0644\u0627\u062f \u0627\u0645\u0644\u0648\u0644"
    ],
    "name:cat_x_preferred":[
        "Oulad Imloul"
    ],
    "name:ceb_x_preferred":[
        "Oulad Imloul"
    ],
    "name:ita_x_preferred":[
        "Oulad Imloul"
    ],
    "name:swe_x_preferred":[
        "Oulad Imloul"
    ],
    "name:und_x_variant":[
        "Douar Imloul",
        "Douar Oulad Imloul",
        "Oulad Imloul"
    ],
    "wof:name":"Oulad Imloul",
    "wof:placetype":"locality"
},
  "geometry": {"coordinates":[-7.71604,32.02519],"type":"Point"}
}