{
  "type": "Feature",
  "properties": {
    "gn:admin1_code":"08",
    "gn:asciiname":"Imilmane",
    "gn:country_code":"MA",
    "gn:dem":1810,
    "gn:feature_class":"P",
    "gn:feature_code":"PPL",
    "gn:name":"Imilmane",
    "gn:population":0,
    "gn:timezone":"Africa/Casablanca",
    "iso:country":"MA",
    "name:und_x_variant":[
        "Mellemane",
        "Imilmane"
    ],
    "wof:name":"Imilmane",
    "wof:placetype":"locality"
},
  "geometry": {"coordinates":[-6.715,31.30178],"type":"Point"}
}