{
  "type": "Feature",
  "properties": {
    "gn:admin1_code":"9.0",
    "gn:asciiname":"Tasqaymout",
    "gn:country_code":"MA",
    "gn:dem":1500,
    "gn:feature_class":"P",
    "gn:feature_code":"PPL",
    "gn:name":"Tasqaymout",
    "gn:population":0,
    "gn:timezone":"Africa/Casablanca",
    "iso:country":"MA",
    "wof:name":"Tasqaymout",
    "wof:placetype":"locality"
},
  "geometry": {"coordinates":[-8.69023,30.82928],"type":"Point"}
}