{
  "type": "Feature",
  "properties": {
    "gn:admin1_code":"9.0",
    "gn:asciiname":"Tibrida",
    "gn:country_code":"MA",
    "gn:dem":353,
    "gn:feature_class":"P",
    "gn:feature_code":"PPL",
    "gn:name":"Tibrida",
    "gn:population":0,
    "gn:timezone":"Africa/Casablanca",
    "iso:country":"MA",
    "wof:name":"Tibrida",
    "wof:placetype":"locality"
},
  "geometry": {"coordinates":[-9.33812,30.54564],"type":"Point"}
}