{
  "type": "Feature",
  "properties": {
    "gn:admin1_code":"03",
    "gn:asciiname":"Ait ben Maati",
    "gn:country_code":"MA",
    "gn:dem":327,
    "gn:feature_class":"P",
    "gn:feature_code":"PPL",
    "gn:name":"A\u00eft ben Maati",
    "gn:population":0,
    "gn:timezone":"Africa/Casablanca",
    "iso:country":"MA",
    "wof:name":"Ait ben Maati",
    "wof:placetype":"locality"
},
  "geometry": {"coordinates":[-5.80709,34.1363],"type":"Point"}
}