{
  "type": "Feature",
  "properties": {
    "gn:admin1_code":"7.0",
    "gn:asciiname":"Lagmoura",
    "gn:country_code":"MA",
    "gn:dem":153,
    "gn:feature_class":"P",
    "gn:feature_code":"PPL",
    "gn:name":"Lagmoura",
    "gn:population":0,
    "gn:timezone":"Africa/Casablanca",
    "iso:country":"MA",
    "wof:name":"Lagmoura",
    "wof:placetype":"locality"
},
  "geometry": {"coordinates":[-9.00519,32.27311],"type":"Point"}
}