{
  "type": "Feature",
  "properties": {
    "gn:admin1_code":"03",
    "gn:asciiname":"Khallad-n-Ait Ya'qoub",
    "gn:country_code":"MA",
    "gn:dem":1560,
    "gn:feature_class":"P",
    "gn:feature_code":"PPL",
    "gn:name":"Khallad-n-A\u00eft Ya\u2019qoub",
    "gn:population":0,
    "gn:timezone":"Africa/Casablanca",
    "iso:country":"MA",
    "name:und_x_variant":[
        "A\u00eft Yacoub",
        "Kholad n\u2019 A\u00eft Yacoub",
        "Kholad n\u2019A\u00eft Yakoub",
        "Khallad-n-A\u00eft Ya\u2019qoub"
    ],
    "wof:name":"Khallad-n-Ait Ya'qoub",
    "wof:placetype":"locality"
},
  "geometry": {"coordinates":[-4.7346,33.04888],"type":"Point"}
}