{
  "type": "Feature",
  "properties": {
    "gn:admin1_code":"6.0",
    "gn:asciiname":"Oulad El Haj Mohammed",
    "gn:country_code":"MA",
    "gn:dem":400,
    "gn:feature_class":"P",
    "gn:feature_code":"PPL",
    "gn:name":"Oulad El Haj Mohammed",
    "gn:population":0,
    "gn:timezone":"Africa/Casablanca",
    "iso:country":"MA",
    "wof:name":"Oulad El Haj Mohammed",
    "wof:placetype":"locality"
},
  "geometry": {"coordinates":[-7.69926,32.87486],"type":"Point"}
}