{
  "type": "Feature",
  "properties": {
    "gn:admin1_code":"7.0",
    "gn:asciiname":"'Zib Lamcoubar",
    "gn:country_code":"MA",
    "gn:dem":635,
    "gn:feature_class":"P",
    "gn:feature_code":"PPL",
    "gn:name":"\u2019Zib Lam\u00e7oubar",
    "gn:population":0,
    "gn:timezone":"Africa/Casablanca",
    "iso:country":"MA",
    "wof:name":"'Zib Lamcoubar",
    "wof:placetype":"locality"
},
  "geometry": {"coordinates":[-7.42652,31.78754],"type":"Point"}
}