{
  "type": "Feature",
  "properties": {
    "gn:admin1_code":"6.0",
    "gn:asciiname":"Oulad Jilali Ben Hafyane",
    "gn:country_code":"MA",
    "gn:dem":171,
    "gn:feature_class":"P",
    "gn:feature_code":"PPL",
    "gn:name":"Oulad Jilali Ben Hafyane",
    "gn:population":0,
    "gn:timezone":"Africa/Casablanca",
    "iso:country":"MA",
    "wof:name":"Oulad Jilali Ben Hafyane",
    "wof:placetype":"locality"
},
  "geometry": {"coordinates":[-7.1079,33.71227],"type":"Point"}
}