{
  "type": "Feature",
  "properties": {
    "gn:gn_country":"MA",
    "gn:gn_fcode":"ADM3",
    "gn:gn_pop":10836,
    "gn:population":10704,
    "iso:country":"MA",
    "name:ara_x_preferred":[
        "\u0633\u064a\u062f\u064a \u0634\u064a\u0643\u0631"
    ],
    "name:fra_x_preferred":[
        "Atouabet"
    ],
    "name:fra_x_variant":[
        "Atouabet (CR)",
        "Atouabet (Commune Rurale)"
    ],
    "qs_pg:aaroncc":"MA",
    "qs_pg:gn_country":"MA",
    "qs_pg:gn_fcode":"ADM3",
    "qs_pg:gn_pop":10836,
    "qs_pg:name":"Atouabet",
    "qs_pg:photos_9r":0,
    "qs_pg:photos_sr":0,
    "qs_pg:pop_sr":6,
    "qs_pg:qs_pg_placetype":"localadmin",
    "wof:name":"Atouabet",
    "wof:placetype":"localadmin",
    "wof:population":10704
},
  "geometry": {"coordinates":[-9.298,31.94939],"type":"Point"}
}