{
  "type": "Feature",
  "properties": {
    "gn:admin1_code":"07",
    "gn:asciiname":"Douar Lemdafra",
    "gn:country_code":"MA",
    "gn:dem":433,
    "gn:feature_class":"P",
    "gn:feature_code":"PPL",
    "gn:name":"Douar Lemdafra",
    "gn:population":0,
    "gn:timezone":"Africa/Casablanca",
    "iso:country":"MA",
    "name:und_x_variant":[
        "Douar Mdafra",
        "El M\u2019daffra",
        "Mdafra",
        "Douar Lemdafra"
    ],
    "wof:name":"Douar Lemdafra",
    "wof:placetype":"locality"
},
  "geometry": {"coordinates":[-8.66448,32.17246],"type":"Point"}
}