{
  "type": "Feature",
  "properties": {
    "gn:admin1_code":"6.0",
    "gn:asciiname":"Douar Bhanes",
    "gn:country_code":"MA",
    "gn:dem":566,
    "gn:feature_class":"P",
    "gn:feature_code":"PPL",
    "gn:name":"Douar Bhanes",
    "gn:population":0,
    "gn:timezone":"Africa/Casablanca",
    "iso:country":"MA",
    "wof:name":"Douar Bhanes",
    "wof:placetype":"locality"
},
  "geometry": {"coordinates":[-7.24212,33.0977],"type":"Point"}
}