{
  "type": "Feature",
  "properties": {
    "gn:admin1_code":"7.0",
    "gn:asciiname":"Agdai-n'Tiki",
    "gn:country_code":"MA",
    "gn:dem":1264,
    "gn:feature_class":"P",
    "gn:feature_code":"PPL",
    "gn:name":"Agda\u00ef-n\u2019Tiki",
    "gn:population":0,
    "gn:timezone":"Africa/Casablanca",
    "iso:country":"MA",
    "wof:name":"Agdai-n'Tiki",
    "wof:placetype":"locality"
},
  "geometry": {"coordinates":[-9.02052,31.0174],"type":"Point"}
}