{
  "type": "Feature",
  "properties": {
    "gn:admin1_code":"07",
    "gn:asciiname":"Douar Oulad Ahmed Ben El Haj",
    "gn:country_code":"MA",
    "gn:dem":414,
    "gn:feature_class":"P",
    "gn:feature_code":"PPL",
    "gn:name":"Douar Oulad Ahmed Ben El Haj",
    "gn:population":0,
    "gn:timezone":"Africa/Casablanca",
    "iso:country":"MA",
    "name:und_x_variant":[
        "Ben el Maati"
    ],
    "wof:name":"Douar Oulad Ahmed Ben El Haj",
    "wof:placetype":"locality"
},
  "geometry": {"coordinates":[-7.62243,32.17159],"type":"Point"}
}