{
  "type": "Feature",
  "properties": {
    "gn:admin1_code":"6.0",
    "gn:asciiname":"Douar El Bochtiyine",
    "gn:country_code":"MA",
    "gn:dem":173,
    "gn:feature_class":"P",
    "gn:feature_code":"PPL",
    "gn:name":"Douar El Bochtiyine",
    "gn:population":0,
    "gn:timezone":"Africa/Casablanca",
    "iso:country":"MA",
    "wof:name":"Douar El Bochtiyine",
    "wof:placetype":"locality"
},
  "geometry": {"coordinates":[-7.12091,33.49506],"type":"Point"}
}