{
  "type": "Feature",
  "properties": {
    "gn:admin1_code":"01",
    "gn:asciiname":"Aailiyine",
    "gn:country_code":"MA",
    "gn:dem":83,
    "gn:feature_class":"P",
    "gn:feature_code":"PPL",
    "gn:name":"Aa\u00efliyine",
    "gn:population":0,
    "gn:timezone":"Africa/Casablanca",
    "iso:country":"MA",
    "name:und_x_variant":[
        "Douar Ailiene",
        "Aailiyine",
        "Aa\u00efliyine"
    ],
    "wof:name":"Aailiyine",
    "wof:placetype":"locality"
},
  "geometry": {"coordinates":[-5.41738,35.77789],"type":"Point"}
}