{
  "type": "Feature",
  "properties": {
    "gn:admin1_code":"07",
    "gn:asciiname":"Tamgounsi",
    "gn:country_code":"MA",
    "gn:dem":1853,
    "gn:feature_class":"P",
    "gn:feature_code":"PPL",
    "gn:name":"Tamgounsi",
    "gn:population":0,
    "gn:timezone":"Africa/Casablanca",
    "iso:country":"MA",
    "name:und_x_variant":[
        "Tamganssi",
        "Tamgoursi",
        "Tamgounsi"
    ],
    "wof:name":"Tamgounsi",
    "wof:placetype":"locality"
},
  "geometry": {"coordinates":[-8.47157,31.05039],"type":"Point"}
}