{
  "type": "Feature",
  "properties": {
    "gn:admin1_code":"07",
    "gn:asciiname":"Ardamene",
    "gn:country_code":"MA",
    "gn:dem":783,
    "gn:feature_class":"P",
    "gn:feature_code":"PPL",
    "gn:name":"Ardamene",
    "gn:population":0,
    "gn:timezone":"Africa/Casablanca",
    "iso:country":"MA",
    "wof:name":"Ardamene",
    "wof:placetype":"locality"
},
  "geometry": {"coordinates":[-8.09928,31.21304],"type":"Point"}
}