{
  "type": "Feature",
  "properties": {
    "gn:admin1_code":"09",
    "gn:asciiname":"Tissint",
    "gn:country_code":"MA",
    "gn:dem":560,
    "gn:feature_class":"P",
    "gn:feature_code":"PPL",
    "gn:name":"Tissint",
    "gn:population":0,
    "gn:timezone":"Africa/Casablanca",
    "iso:country":"MA",
    "name:ara_x_preferred":[
        "\u062a\u064a\u0633\u064a\u0646\u062a"
    ],
    "name:cat_x_preferred":[
        "Tissint"
    ],
    "name:ita_x_preferred":[
        "Tissint"
    ],
    "name:und_x_variant":[
        "Agadir Tissinnt",
        "Tissinnt",
        "Agadir Tissint"
    ],
    "wof:name":"Tissint",
    "wof:placetype":"locality"
},
  "geometry": {"coordinates":[-7.31619,29.89826],"type":"Point"}
}