{
  "type": "Feature",
  "properties": {
    "gn:admin1_code":"01",
    "gn:asciiname":"Ikharroudene",
    "gn:country_code":"MA",
    "gn:dem":1362,
    "gn:feature_class":"P",
    "gn:feature_code":"PPL",
    "gn:name":"Ikharro\u00fbdene",
    "gn:population":0,
    "gn:timezone":"Africa/Casablanca",
    "iso:country":"MA",
    "wof:name":"Ikharroudene",
    "wof:placetype":"locality"
},
  "geometry": {"coordinates":[-4.36529,34.90705],"type":"Point"}
}