{
  "type": "Feature",
  "properties": {
    "gn:admin1_code":"05",
    "gn:asciiname":"Taghbalout",
    "gn:country_code":"MA",
    "gn:dem":1038,
    "gn:elevation":"0.0",
    "gn:feature_class":"P",
    "gn:feature_code":"PPL",
    "gn:name":"Taghbalout",
    "gn:population":0,
    "gn:timezone":"Africa/Casablanca",
    "iso:country":"MA",
    "wof:name":"Taghbalout",
    "wof:placetype":"locality"
},
  "geometry": {"coordinates":[-6.90337,31.72867],"type":"Point"}
}