{
  "type": "Feature",
  "properties": {
    "gn:admin1_code":"08",
    "gn:asciiname":"Ait Hani",
    "gn:country_code":"MA",
    "gn:dem":2007,
    "gn:feature_class":"P",
    "gn:feature_code":"PPL",
    "gn:name":"A\u00eft Hani",
    "gn:population":0,
    "gn:timezone":"Africa/Casablanca",
    "iso:country":"MA",
    "name:und_x_variant":[
        "A\u00eft Ani",
        "A\u00eft Hani"
    ],
    "wof:name":"Ait Hani",
    "wof:placetype":"locality"
},
  "geometry": {"coordinates":[-5.44803,31.79266],"type":"Point"}
}