{
  "type": "Feature",
  "properties": {
    "gn:admin1_code":"09",
    "gn:asciiname":"Tawrirt-n-Bounihi",
    "gn:country_code":"MA",
    "gn:dem":1084,
    "gn:feature_class":"P",
    "gn:feature_code":"PPL",
    "gn:name":"Tawrirt-n-Bounihi",
    "gn:population":0,
    "gn:timezone":"Africa/Casablanca",
    "iso:country":"MA",
    "name:und_x_variant":[
        "Taourirt n\u2019Bouni"
    ],
    "wof:name":"Tawrirt-n-Bounihi",
    "wof:placetype":"locality"
},
  "geometry": {"coordinates":[-8.88532,30.01099],"type":"Point"}
}