{
  "type": "Feature",
  "properties": {
    "gn:admin1_code":"1.0",
    "gn:asciiname":"Douar Manchaq",
    "gn:country_code":"MA",
    "gn:dem":299,
    "gn:feature_class":"P",
    "gn:feature_code":"PPL",
    "gn:name":"Douar Manchaq",
    "gn:population":0,
    "gn:timezone":"Africa/Casablanca",
    "iso:country":"MA",
    "wof:name":"Douar Manchaq",
    "wof:placetype":"locality"
},
  "geometry": {"coordinates":[-5.65046,35.10638],"type":"Point"}
}