{
  "type": "Feature",
  "properties": {
    "gn:admin1_code":"8.0",
    "gn:asciiname":"Toulntat",
    "gn:country_code":"MA",
    "gn:dem":2196,
    "gn:feature_class":"P",
    "gn:feature_code":"PPL",
    "gn:name":"Toulntat",
    "gn:population":0,
    "gn:timezone":"Africa/Casablanca",
    "iso:country":"MA",
    "wof:name":"Toulntat",
    "wof:placetype":"locality"
},
  "geometry": {"coordinates":[-7.15594,31.33358],"type":"Point"}
}