{
  "type": "Feature",
  "properties": {
    "gn:country":"MA",
    "gn:fcode":"ADM3",
    "gn:population":6637,
    "iso:country":"MA",
    "name:ara_x_preferred":[
        "\u062c\u0627\u0628\u0631\u064a\u0629"
    ],
    "name:ara_x_variant":[
        "\u062e\u0645\u064a\u0633 \u0642\u0635\u064a\u0628\u0629"
    ],
    "name:ary_x_preferred":[
        "\u062e\u0645\u064a\u0633 \u0644\u0642\u0635\u064a\u0628\u0629"
    ],
    "name:azb_x_preferred":[
        "\u062e\u0645\u06cc\u0633 \u0642\u0635\u06cc\u0628\u0647"
    ],
    "name:cat_x_preferred":[
        "Khmis Ksiba"
    ],
    "name:ceb_x_preferred":[
        "Khmis Ksiba"
    ],
    "name:eng_x_preferred":[
        "Khmis Ksiba"
    ],
    "name:fas_x_preferred":[
        "\u062e\u0645\u06cc\u0633 \u0642\u0635\u06cc\u0628\u0647"
    ],
    "name:fra_x_preferred":[
        "Khmis Ksiba"
    ],
    "name:fra_x_variant":[
        "Khmis Ksiba (CR)",
        "Khmis Ksiba (Commune Rurale)"
    ],
    "name:ita_x_preferred":[
        "Khmis Ksiba"
    ],
    "name:swe_x_preferred":[
        "Khmis Ksiba"
    ],
    "qs:name":"Khmis Ksiba",
    "qs:photos_9r":0,
    "qs:photos_sr":0,
    "qs:pop_sr":"5",
    "wd:wordcount":61,
    "wof:name":"Khmis Ksiba",
    "wof:placetype":"localadmin",
    "wof:population":6637
},
  "geometry": {"coordinates":[-8.20936,32.52489],"type":"Point"}
}