{
  "type": "Feature",
  "properties": {
    "gn:admin1_code":"05",
    "gn:asciiname":"Douar Hammadi Omar",
    "gn:country_code":"MA",
    "gn:dem":520,
    "gn:feature_class":"P",
    "gn:feature_code":"PPL",
    "gn:name":"Douar Hammadi Omar",
    "gn:population":0,
    "gn:timezone":"Africa/Casablanca",
    "iso:country":"MA",
    "wof:name":"Douar Hammadi Omar",
    "wof:placetype":"locality"
},
  "geometry": {"coordinates":[-6.87377,32.61593],"type":"Point"}
}