{
  "type": "Feature",
  "properties": {
    "gn:admin1_code":"4.0",
    "gn:asciiname":"Dar Sidi Lahsen",
    "gn:country_code":"MA",
    "gn:dem":560,
    "gn:feature_class":"P",
    "gn:feature_code":"PPL",
    "gn:name":"Dar Sidi Lahsen",
    "gn:population":0,
    "gn:timezone":"Africa/Casablanca",
    "iso:country":"MA",
    "wof:name":"Dar Sidi Lahsen",
    "wof:placetype":"locality"
},
  "geometry": {"coordinates":[-5.53526,34.14476],"type":"Point"}
}