{
  "type": "Feature",
  "properties": {
    "gn:admin1_code":"03",
    "gn:asciiname":"Douar el Bkhata",
    "gn:country_code":"MA",
    "gn:dem":356,
    "gn:feature_class":"P",
    "gn:feature_code":"PPL",
    "gn:name":"Douar el Bkhata",
    "gn:population":0,
    "gn:timezone":"Africa/Casablanca",
    "iso:country":"MA",
    "name:und_x_variant":[
        "Douar el Bekiala",
        "Douar el Bkhata"
    ],
    "wof:name":"Douar el Bkhata",
    "wof:placetype":"locality"
},
  "geometry": {"coordinates":[-4.88,34.32201],"type":"Point"}
}