{
  "type": "Feature",
  "properties": {
    "gn:admin1_code":"7.0",
    "gn:asciiname":"Ait bou Jellali",
    "gn:country_code":"MA",
    "gn:dem":764,
    "gn:feature_class":"P",
    "gn:feature_code":"PPL",
    "gn:name":"A\u00eft bou Jellali",
    "gn:population":0,
    "gn:timezone":"Africa/Casablanca",
    "iso:country":"MA",
    "wof:name":"Ait bou Jellali",
    "wof:placetype":"locality"
},
  "geometry": {"coordinates":[-9.25157,31.38694000000001],"type":"Point"}
}