{
  "type": "Feature",
  "properties": {
    "gn:admin1_code":"3.0",
    "gn:asciiname":"Ghoudane",
    "gn:country_code":"MA",
    "gn:dem":880,
    "gn:feature_class":"P",
    "gn:feature_code":"PPL",
    "gn:name":"Ghoudane",
    "gn:population":0,
    "gn:timezone":"Africa/Casablanca",
    "iso:country":"MA",
    "wof:name":"Ghoudane",
    "wof:placetype":"locality"
},
  "geometry": {"coordinates":[-5.31612,33.7336],"type":"Point"}
}