{
  "type": "Feature",
  "properties": {
    "gn:admin1_code":"7.0",
    "gn:asciiname":"Ait Hammadi Ou Ali",
    "gn:country_code":"MA",
    "gn:dem":575,
    "gn:feature_class":"P",
    "gn:feature_code":"PPL",
    "gn:name":"Ait Hammadi Ou Ali",
    "gn:population":0,
    "gn:timezone":"Africa/Casablanca",
    "iso:country":"MA",
    "wof:name":"Ait Hammadi Ou Ali",
    "wof:placetype":"locality"
},
  "geometry": {"coordinates":[-7.74696,31.57099],"type":"Point"}
}