{
  "type": "Feature",
  "properties": {
    "gn:admin1_code":"01",
    "gn:asciiname":"Douar Aouraghene",
    "gn:country_code":"MA",
    "gn:dem":496,
    "gn:feature_class":"P",
    "gn:feature_code":"PPL",
    "gn:name":"Douar Aouraghene",
    "gn:population":0,
    "gn:timezone":"Africa/Casablanca",
    "iso:country":"MA",
    "name:und_x_variant":[
        "Aouragouene",
        "Aourarhene",
        "Douar Aouraghene"
    ],
    "wof:name":"Douar Aouraghene",
    "wof:placetype":"locality"
},
  "geometry": {"coordinates":[-5.4341,35.31442],"type":"Point"}
}