{
  "type": "Feature",
  "properties": {
    "gn:admin1_code":"1.0",
    "gn:asciiname":"Douar Taghilt",
    "gn:country_code":"MA",
    "gn:dem":931,
    "gn:feature_class":"P",
    "gn:feature_code":"PPL",
    "gn:name":"Douar Taghilt",
    "gn:population":0,
    "gn:timezone":"Africa/Casablanca",
    "iso:country":"MA",
    "wof:name":"Douar Taghilt",
    "wof:placetype":"locality"
},
  "geometry": {"coordinates":[-4.75314,35.01411],"type":"Point"}
}