{
  "type": "Feature",
  "properties": {
    "gn:admin1_code":"10.0",
    "gn:asciiname":"Id Rays",
    "gn:country_code":"MA",
    "gn:dem":828,
    "gn:feature_class":"P",
    "gn:feature_code":"PPL",
    "gn:name":"Id Rays",
    "gn:population":0,
    "gn:timezone":"Africa/Casablanca",
    "iso:country":"MA",
    "wof:name":"Id Rays",
    "wof:placetype":"locality"
},
  "geometry": {"coordinates":[-9.80323,29.35978],"type":"Point"}
}