{
  "type": "Feature",
  "properties": {
    "gn:admin1_code":"4.0",
    "gn:asciiname":"Moulay Driss Aghbal",
    "gn:country_code":"MA",
    "gn:dem":355,
    "gn:feature_class":"P",
    "gn:feature_code":"PPL",
    "gn:name":"Moulay Driss Aghbal",
    "gn:population":0,
    "gn:timezone":"Africa/Casablanca",
    "iso:country":"MA",
    "name:ara_x_preferred":[
        "\u0645\u0648\u0644\u0627\u064a \u0625\u062f\u0631\u064a\u0633 \u0623\u063a\u0628\u0627\u0644"
    ],
    "name:cat_x_preferred":[
        "Moulay Driss Aghbal"
    ],
    "name:ceb_x_preferred":[
        "Moulay Driss Aghbal"
    ],
    "name:ita_x_preferred":[
        "Moulay Driss Aghbal"
    ],
    "name:swe_x_preferred":[
        "Moulay Driss Aghbal"
    ],
    "wof:name":"Moulay Driss Aghbal",
    "wof:placetype":"locality"
},
  "geometry": {"coordinates":[-6.49823,33.79019],"type":"Point"}
}