{
  "type": "Feature",
  "properties": {
    "gn:admin1_code":"10",
    "gn:asciiname":"Iguzaren",
    "gn:country_code":"MA",
    "gn:dem":380,
    "gn:feature_class":"P",
    "gn:feature_code":"PPL",
    "gn:name":"Iguzaren",
    "gn:population":0,
    "gn:timezone":"Africa/Casablanca",
    "iso:country":"MA",
    "name:und_x_variant":[
        "Guzaren",
        "Iguzaren"
    ],
    "wof:name":"Iguzaren",
    "wof:placetype":"locality"
},
  "geometry": {"coordinates":[-9.93,29.43],"type":"Point"}
}