{
  "type": "Feature",
  "properties": {
    "gn:admin1_code":"09",
    "gn:asciiname":"Tatelt",
    "gn:country_code":"MA",
    "gn:dem":1342,
    "gn:feature_class":"P",
    "gn:feature_code":"PPL",
    "gn:name":"Tatelt",
    "gn:population":0,
    "gn:timezone":"Africa/Casablanca",
    "iso:country":"MA",
    "name:und_x_variant":[
        "Tafelt",
        "Tatelte",
        "Tatelt"
    ],
    "wof:name":"Tatelt",
    "wof:placetype":"locality"
},
  "geometry": {"coordinates":[-9.32581,30.79733],"type":"Point"}
}