{
  "type": "Feature",
  "properties": {
    "gn:admin1_code":"5.0",
    "gn:asciiname":"Takflit",
    "gn:country_code":"MA",
    "gn:dem":776,
    "gn:feature_class":"P",
    "gn:feature_code":"PPL",
    "gn:name":"Takflit",
    "gn:population":0,
    "gn:timezone":"Africa/Casablanca",
    "iso:country":"MA",
    "wof:name":"Takflit",
    "wof:placetype":"locality"
},
  "geometry": {"coordinates":[-5.78881,32.85606],"type":"Point"}
}