{
  "type": "Feature",
  "properties": {
    "gn:admin1_code":"5.0",
    "gn:asciiname":"Qcar Barwag",
    "gn:country_code":"MA",
    "gn:dem":449,
    "gn:feature_class":"P",
    "gn:feature_code":"PPL",
    "gn:name":"Q\u00e7ar Barwag",
    "gn:population":0,
    "gn:timezone":"Africa/Casablanca",
    "iso:country":"MA",
    "wof:name":"Qcar Barwag",
    "wof:placetype":"locality"
},
  "geometry": {"coordinates":[-6.5308,32.27517],"type":"Point"}
}