{
  "type": "Feature",
  "properties": {
    "gn:admin1_code":"9.0",
    "gn:asciiname":"Agdal-n-Ait Ali",
    "gn:country_code":"MA",
    "gn:dem":214,
    "gn:feature_class":"P",
    "gn:feature_code":"PPL",
    "gn:name":"Agdal-n-Ait Ali",
    "gn:population":0,
    "gn:timezone":"Africa/Casablanca",
    "iso:country":"MA",
    "wof:name":"Agdal-n-Ait Ali",
    "wof:placetype":"locality"
},
  "geometry": {"coordinates":[-9.32638,30.024],"type":"Point"}
}