{
  "type": "Feature",
  "properties": {
    "gn:admin1_code":"6.0",
    "gn:asciiname":"Azibou Lqaid May Tahar",
    "gn:country_code":"MA",
    "gn:dem":134,
    "gn:feature_class":"P",
    "gn:feature_code":"PPL",
    "gn:name":"Azibou Lqa\u00efd May Tahar",
    "gn:population":0,
    "gn:timezone":"Africa/Casablanca",
    "iso:country":"MA",
    "wof:name":"Azibou Lqaid May Tahar",
    "wof:placetype":"locality"
},
  "geometry": {"coordinates":[-8.66585,32.8229],"type":"Point"}
}