{
  "type": "Feature",
  "properties": {
    "gn:admin1_code":"7.0",
    "gn:asciiname":"Tabrakht",
    "gn:country_code":"MA",
    "gn:dem":595,
    "gn:feature_class":"P",
    "gn:feature_code":"PPL",
    "gn:name":"Tabrakht",
    "gn:population":0,
    "gn:timezone":"Africa/Casablanca",
    "iso:country":"MA",
    "wof:name":"Tabrakht",
    "wof:placetype":"locality"
},
  "geometry": {"coordinates":[-9.38228,31.29718],"type":"Point"}
}