{
  "type": "Feature",
  "properties": {
    "gn:admin1_code":"2.0",
    "gn:asciiname":"Douar Ifettatene",
    "gn:country_code":"MA",
    "gn:dem":599,
    "gn:feature_class":"P",
    "gn:feature_code":"PPL",
    "gn:name":"Douar Ifettatene",
    "gn:population":0,
    "gn:timezone":"Africa/Casablanca",
    "iso:country":"MA",
    "wof:name":"Douar Ifettatene",
    "wof:placetype":"locality"
},
  "geometry": {"coordinates":[-3.53314,35.10335],"type":"Point"}
}