{
  "type": "Feature",
  "properties": {
    "gn:admin1_code":"7.0",
    "gn:asciiname":"Douar Id Jaa",
    "gn:country_code":"MA",
    "gn:dem":207,
    "gn:feature_class":"P",
    "gn:feature_code":"PPL",
    "gn:name":"Douar Id Jaa",
    "gn:population":0,
    "gn:timezone":"Africa/Casablanca",
    "iso:country":"MA",
    "wof:name":"Douar Id Jaa",
    "wof:placetype":"locality"
},
  "geometry": {"coordinates":[-9.59983,31.45209],"type":"Point"}
}