{
  "type": "Feature",
  "properties": {
    "gn:country":"MA",
    "gn:fcode":"ADM3",
    "gn:population":6178,
    "iso:country":"MA",
    "name:ara_x_preferred":[
        "\u0633\u064a\u062f\u064a \u063a\u0627\u0646\u0645"
    ],
    "name:fra_x_preferred":[
        "Sidi H Mad Ou M Bar"
    ],
    "name:fra_x_variant":[
        "Sidi H Mad Ou M Bar (CR)",
        "Sidi H Mad Ou M Bar (Commune Rurale)"
    ],
    "qs:name":"Sidi H Mad  Ou M Bar",
    "qs:photos_9r":0,
    "qs:photos_sr":0,
    "qs:pop_sr":"5",
    "wof:name":"Sidi H Mad Ou M Bar",
    "wof:placetype":"localadmin",
    "wof:population":6178
},
  "geometry": {"coordinates":[-9.69535,30.84253],"type":"Point"}
}