{
  "type": "Feature",
  "properties": {
    "gn:admin1_code":"09",
    "gn:asciiname":"Douar Larjame",
    "gn:country_code":"MA",
    "gn:dem":336,
    "gn:feature_class":"P",
    "gn:feature_code":"PPL",
    "gn:name":"Douar Larjame",
    "gn:population":0,
    "gn:timezone":"Africa/Casablanca",
    "iso:country":"MA",
    "name:und_x_variant":[
        "Larjam"
    ],
    "wof:name":"Douar Larjame",
    "wof:placetype":"locality"
},
  "geometry": {"coordinates":[-9.80316,29.57084],"type":"Point"}
}