{
  "type": "Feature",
  "properties": {
    "gn:admin1_code":"04",
    "gn:asciiname":"Douar Biyab Errih",
    "gn:country_code":"MA",
    "gn:dem":204,
    "gn:feature_class":"P",
    "gn:feature_code":"PPL",
    "gn:name":"Douar Biyab Errih",
    "gn:population":0,
    "gn:timezone":"Africa/Casablanca",
    "iso:country":"MA",
    "name:und_x_variant":[
        "Douar Bib el Rih",
        "Bo\u00efb rih",
        "Bib el Rih",
        "Douar Biyab Errih"
    ],
    "wof:name":"Douar Biyab Errih",
    "wof:placetype":"locality"
},
  "geometry": {"coordinates":[-5.80277,34.76309000000001],"type":"Point"}
}