{
  "type": "Feature",
  "properties": {
    "gn:admin1_code":"02",
    "gn:asciiname":"Tagdimt",
    "gn:country_code":"MA",
    "gn:dem":1174,
    "gn:feature_class":"P",
    "gn:feature_code":"PPL",
    "gn:name":"Tagdimt",
    "gn:population":0,
    "gn:timezone":"Africa/Casablanca",
    "iso:country":"MA",
    "name:und_x_variant":[
        "Tajdimt",
        "Tagdimt"
    ],
    "wof:name":"Tagdimt",
    "wof:placetype":"locality"
},
  "geometry": {"coordinates":[-3.83567,33.70701],"type":"Point"}
}