{
  "type": "Feature",
  "properties": {
    "gn:admin1_code":"03",
    "gn:asciiname":"Idissene",
    "gn:country_code":"MA",
    "gn:dem":1026,
    "gn:feature_class":"P",
    "gn:feature_code":"PPL",
    "gn:name":"Idissene",
    "gn:population":0,
    "gn:timezone":"Africa/Casablanca",
    "iso:country":"MA",
    "name:und_x_variant":[
        "Douar Idissene",
        "Idissene"
    ],
    "wof:name":"Idissene",
    "wof:placetype":"locality"
},
  "geometry": {"coordinates":[-4.15869,34.09179],"type":"Point"}
}