{
  "type": "Feature",
  "properties": {
    "gn:admin1_code":"7.0",
    "gn:asciiname":"Biirgn",
    "gn:country_code":"MA",
    "gn:dem":1234,
    "gn:feature_class":"P",
    "gn:feature_code":"PPL",
    "gn:name":"Biirgn",
    "gn:population":0,
    "gn:timezone":"Africa/Casablanca",
    "iso:country":"MA",
    "wof:name":"Biirgn",
    "wof:placetype":"locality"
},
  "geometry": {"coordinates":[-9.0368,31.08746],"type":"Point"}
}