{
  "type": "Feature",
  "properties": {
    "gn:admin1_code":"01",
    "gn:asciiname":"Ait Amar ou Said",
    "gn:country_code":"MA",
    "gn:dem":1171,
    "gn:feature_class":"P",
    "gn:feature_code":"PPL",
    "gn:name":"A\u00eft Amar ou Sa\u00efd",
    "gn:population":0,
    "gn:timezone":"Africa/Casablanca",
    "iso:country":"MA",
    "wof:name":"Ait Amar ou Said",
    "wof:placetype":"locality"
},
  "geometry": {"coordinates":[-4.10999,34.89723],"type":"Point"}
}