{
  "type": "Feature",
  "properties": {
    "gn:admin1_code":"06",
    "gn:asciiname":"Dar al Mnacera",
    "gn:country_code":"MA",
    "gn:dem":504,
    "gn:feature_class":"P",
    "gn:feature_code":"PPL",
    "gn:name":"Dar al Mnacera",
    "gn:population":0,
    "gn:timezone":"Africa/Casablanca",
    "iso:country":"MA",
    "name:und_x_variant":[
        "Dar el Mnacera",
        "Dar el Mnassera",
        "Dar al Mnacera"
    ],
    "wof:name":"Dar al Mnacera",
    "wof:placetype":"locality"
},
  "geometry": {"coordinates":[-7.45367,32.76289000000001],"type":"Point"}
}