{
  "type": "Feature",
  "properties": {
    "gn:admin1_code":"07",
    "gn:asciiname":"Ayt 'Attou ou L'Arbi",
    "gn:country_code":"MA",
    "gn:dem":472,
    "gn:feature_class":"P",
    "gn:feature_code":"PPL",
    "gn:name":"Ayt \u2019Attou ou L\u2019Arbi",
    "gn:population":0,
    "gn:timezone":"Africa/Casablanca",
    "iso:country":"MA",
    "name:und_x_variant":[
        "Bled A\u00eft Immour",
        "Ait Imour",
        "A\u00eft Immour",
        "Ayt \u2019Attou ou L\u2019Arbi"
    ],
    "wof:name":"Ayt 'Attou ou L'Arbi",
    "wof:placetype":"locality"
},
  "geometry": {"coordinates":[-8.24795,31.50279],"type":"Point"}
}