{
  "type": "Feature",
  "properties": {
    "gn:admin1_code":"01",
    "gn:asciiname":"Roussiyech",
    "gn:country_code":"MA",
    "gn:dem":309,
    "gn:feature_class":"P",
    "gn:feature_code":"PPL",
    "gn:name":"Roussiyech",
    "gn:population":0,
    "gn:timezone":"Africa/Casablanca",
    "iso:country":"MA",
    "name:und_x_variant":[
        "Rochies",
        "Jbila",
        "Er Roussiech",
        "Roussiyech"
    ],
    "wof:name":"Roussiyech",
    "wof:placetype":"locality"
},
  "geometry": {"coordinates":[-5.77744,35.48127],"type":"Point"}
}