{
  "type": "Feature",
  "properties": {
    "gn:admin1_code":"7.0",
    "gn:asciiname":"Ait Lahssene Ou Ali",
    "gn:country_code":"MA",
    "gn:dem":994,
    "gn:feature_class":"P",
    "gn:feature_code":"PPL",
    "gn:name":"Ait Lahssene Ou Ali",
    "gn:population":0,
    "gn:timezone":"Africa/Casablanca",
    "iso:country":"MA",
    "wof:name":"Ait Lahssene Ou Ali",
    "wof:placetype":"locality"
},
  "geometry": {"coordinates":[-7.64573,31.51855],"type":"Point"}
}