{
  "type": "Feature",
  "properties": {
    "gn:admin1_code":"01",
    "gn:asciiname":"Tarhnit",
    "gn:country_code":"MA",
    "gn:dem":436,
    "gn:feature_class":"P",
    "gn:feature_code":"PPL",
    "gn:name":"Tarhnit",
    "gn:population":0,
    "gn:timezone":"Africa/Casablanca",
    "iso:country":"MA",
    "name:und_x_variant":[
        "Taghnit",
        "Tarhnite",
        "Tarhnit"
    ],
    "wof:name":"Tarhnit",
    "wof:placetype":"locality"
},
  "geometry": {"coordinates":[-5.30602,34.78241],"type":"Point"}
}