{
  "type": "Feature",
  "properties": {
    "gn:admin1_code":"06",
    "gn:asciiname":"Douar Oulad Zouara",
    "gn:country_code":"MA",
    "gn:dem":58,
    "gn:feature_class":"P",
    "gn:feature_code":"PPL",
    "gn:name":"Douar Oulad Zouara",
    "gn:population":0,
    "gn:timezone":"Africa/Casablanca",
    "iso:country":"MA",
    "wof:name":"Douar Oulad Zouara",
    "wof:placetype":"locality"
},
  "geometry": {"coordinates":[-8.48212,33.10065],"type":"Point"}
}