{
  "type": "Feature",
  "properties": {
    "gn:admin1_code":"7.0",
    "gn:asciiname":"Tissila Fouqania",
    "gn:country_code":"MA",
    "gn:dem":680,
    "gn:feature_class":"P",
    "gn:feature_code":"PPL",
    "gn:name":"Tissila Fouqania",
    "gn:population":0,
    "gn:timezone":"Africa/Casablanca",
    "iso:country":"MA",
    "wof:name":"Tissila Fouqania",
    "wof:placetype":"locality"
},
  "geometry": {"coordinates":[-7.78842,31.46582],"type":"Point"}
}