{
  "type": "Feature",
  "properties": {
    "gn:admin1_code":"05",
    "gn:asciiname":"Ac Amane",
    "gn:country_code":"MA",
    "gn:dem":1305,
    "gn:feature_class":"P",
    "gn:feature_code":"PPL",
    "gn:name":"A\u00e7 Amane",
    "gn:population":0,
    "gn:timezone":"Africa/Casablanca",
    "iso:country":"MA",
    "name:und_x_variant":[
        "A\u00e7 Amane",
        "Assamane"
    ],
    "wof:name":"Ac Amane",
    "wof:placetype":"locality"
},
  "geometry": {"coordinates":[-6.36564,31.91711],"type":"Point"}
}