{
  "type": "Feature",
  "properties": {
    "gn:admin1_code":"3.0",
    "gn:asciiname":"Qarbouce",
    "gn:country_code":"MA",
    "gn:dem":843,
    "gn:feature_class":"P",
    "gn:feature_code":"PPL",
    "gn:name":"Qarbou\u00e7e",
    "gn:population":0,
    "gn:timezone":"Africa/Casablanca",
    "iso:country":"MA",
    "wof:name":"Qarbouce",
    "wof:placetype":"locality"
},
  "geometry": {"coordinates":[-4.36151,33.8062],"type":"Point"}
}