{
  "type": "Feature",
  "properties": {
    "gn:admin1_code":"9.0",
    "gn:asciiname":"Ikakern",
    "gn:country_code":"MA",
    "gn:dem":1038,
    "gn:feature_class":"P",
    "gn:feature_code":"PPL",
    "gn:name":"Ikakern",
    "gn:population":0,
    "gn:timezone":"Africa/Casablanca",
    "iso:country":"MA",
    "wof:name":"Ikakern",
    "wof:placetype":"locality"
},
  "geometry": {"coordinates":[-8.975,30.83209],"type":"Point"}
}