{
  "type": "Feature",
  "properties": {
    "gn:admin1_code":"9.0",
    "gn:asciiname":"Tirouf",
    "gn:country_code":"MA",
    "gn:dem":1041,
    "gn:feature_class":"P",
    "gn:feature_code":"PPL",
    "gn:name":"Tirouf",
    "gn:population":0,
    "gn:timezone":"Africa/Casablanca",
    "iso:country":"MA",
    "wof:name":"Tirouf",
    "wof:placetype":"locality"
},
  "geometry": {"coordinates":[-9.1283,29.82493],"type":"Point"}
}