{
  "type": "Feature",
  "properties": {
    "gn:admin1_code":"7.0",
    "gn:asciiname":"Douar Oulad Sehb Selamna",
    "gn:country_code":"MA",
    "gn:dem":281,
    "gn:feature_class":"P",
    "gn:feature_code":"PPL",
    "gn:name":"Douar Oulad Sehb Selamna",
    "gn:population":0,
    "gn:timezone":"Africa/Casablanca",
    "iso:country":"MA",
    "wof:name":"Douar Oulad Sehb Selamna",
    "wof:placetype":"locality"
},
  "geometry": {"coordinates":[-9.1105,32.00573],"type":"Point"}
}