{
  "type": "Feature",
  "properties": {
    "gn:admin1_code":"09",
    "gn:asciiname":"Taghroutane",
    "gn:country_code":"MA",
    "gn:dem":732,
    "gn:feature_class":"P",
    "gn:feature_code":"PPL",
    "gn:name":"Taghroutane",
    "gn:population":0,
    "gn:timezone":"Africa/Casablanca",
    "iso:country":"MA",
    "name:und_x_variant":[
        "Tarhroutane",
        "Taghroutane"
    ],
    "wof:name":"Taghroutane",
    "wof:placetype":"locality"
},
  "geometry": {"coordinates":[-9.50999,30.56679],"type":"Point"}
}