{
  "type": "Feature",
  "properties": {
    "gn:admin1_code":"01",
    "gn:asciiname":"Zhara",
    "gn:country_code":"MA",
    "gn:dem":124,
    "gn:feature_class":"P",
    "gn:feature_code":"PPL",
    "gn:name":"Zhara",
    "gn:population":0,
    "gn:timezone":"Africa/Casablanca",
    "iso:country":"MA",
    "name:und_x_variant":[
        "Sidi Zahara",
        "Zahara",
        "Zhara"
    ],
    "wof:name":"Zhara",
    "wof:placetype":"locality"
},
  "geometry": {"coordinates":[-5.57569,35.83067],"type":"Point"}
}