{
  "type": "Feature",
  "properties": {
    "gn:admin1_code":"5.0",
    "gn:asciiname":"Tazerwalt",
    "gn:country_code":"MA",
    "gn:dem":632,
    "gn:feature_class":"P",
    "gn:feature_code":"PPL",
    "gn:name":"Tazerwalt",
    "gn:population":0,
    "gn:timezone":"Africa/Casablanca",
    "iso:country":"MA",
    "name:cat_x_preferred":[
        "Tazerwalt"
    ],
    "name:fra_x_preferred":[
        "Tazeroualt"
    ],
    "name:por_x_preferred":[
        "Tazerwalt"
    ],
    "wof:name":"Tazerwalt",
    "wof:placetype":"locality"
},
  "geometry": {"coordinates":[-6.81184,32.10429],"type":"Point"}
}