{
  "type": "Feature",
  "properties": {
    "gn:admin1_code":"6.0",
    "gn:asciiname":"El Khmis",
    "gn:country_code":"MA",
    "gn:dem":450,
    "gn:feature_class":"P",
    "gn:feature_code":"PPL",
    "gn:name":"El Khmis",
    "gn:population":0,
    "gn:timezone":"Africa/Casablanca",
    "iso:country":"MA",
    "wof:name":"El Khmis",
    "wof:placetype":"locality"
},
  "geometry": {"coordinates":[-7.58491,32.97858],"type":"Point"}
}