{
  "type": "Feature",
  "properties": {
    "gn:admin1_code":"8.0",
    "gn:asciiname":"Qcar Jir",
    "gn:country_code":"MA",
    "gn:dem":778,
    "gn:feature_class":"P",
    "gn:feature_code":"PPL",
    "gn:name":"Q\u00e7ar Jir",
    "gn:population":0,
    "gn:timezone":"Africa/Casablanca",
    "iso:country":"MA",
    "wof:name":"Qcar Jir",
    "wof:placetype":"locality"
},
  "geometry": {"coordinates":[-4.28009,31.34045],"type":"Point"}
}