{
  "type": "Feature",
  "properties": {
    "gn:admin1_code":"5.0",
    "gn:asciiname":"Adras",
    "gn:country_code":"MA",
    "gn:dem":1775,
    "gn:feature_class":"P",
    "gn:feature_code":"PPL",
    "gn:name":"Adras",
    "gn:population":0,
    "gn:timezone":"Africa/Casablanca",
    "iso:country":"MA",
    "wof:name":"Adras",
    "wof:placetype":"locality"
},
  "geometry": {"coordinates":[-6.98882,31.636],"type":"Point"}
}