{
  "type": "Feature",
  "properties": {
    "gn:admin1_code":"9.0",
    "gn:asciiname":"Tararhine",
    "gn:country_code":"MA",
    "gn:dem":403,
    "gn:feature_class":"P",
    "gn:feature_code":"PPL",
    "gn:name":"Tararhine",
    "gn:population":0,
    "gn:timezone":"Africa/Casablanca",
    "iso:country":"MA",
    "wof:name":"Tararhine",
    "wof:placetype":"locality"
},
  "geometry": {"coordinates":[-8.51554,30.53659],"type":"Point"}
}