{
  "type": "Feature",
  "properties": {
    "gn:admin1_code":"9.0",
    "gn:asciiname":"Bou Ferdou",
    "gn:country_code":"MA",
    "gn:dem":144,
    "gn:feature_class":"P",
    "gn:feature_code":"PPL",
    "gn:name":"Bou Ferdou",
    "gn:population":0,
    "gn:timezone":"Africa/Casablanca",
    "iso:country":"MA",
    "wof:name":"Bou Ferdou",
    "wof:placetype":"locality"
},
  "geometry": {"coordinates":[-9.78755,30.69173],"type":"Point"}
}