{
  "type": "Feature",
  "properties": {
    "gn:admin1_code":"5.0",
    "gn:asciiname":"Ait Hamou-Youssef",
    "gn:country_code":"MA",
    "gn:dem":937,
    "gn:feature_class":"P",
    "gn:feature_code":"PPL",
    "gn:name":"A\u00eft Hamou-Youssef",
    "gn:population":0,
    "gn:timezone":"Africa/Casablanca",
    "iso:country":"MA",
    "wof:name":"Ait Hamou-Youssef",
    "wof:placetype":"locality"
},
  "geometry": {"coordinates":[-6.32109,32.89214],"type":"Point"}
}