{
  "type": "Feature",
  "properties": {
    "gn:admin1_code":"03",
    "gn:asciiname":"Zaouia Ben Smine",
    "gn:country_code":"MA",
    "gn:dem":1372,
    "gn:feature_class":"P",
    "gn:feature_code":"PPL",
    "gn:name":"Zaouia Ben Smine",
    "gn:population":0,
    "gn:timezone":"Africa/Casablanca",
    "iso:country":"MA",
    "wof:name":"Zaouia Ben Smine",
    "wof:placetype":"locality"
},
  "geometry": {"coordinates":[-5.1889,33.5029],"type":"Point"}
}