{
  "type": "Feature",
  "properties": {
    "gn:admin1_code":"2.0",
    "gn:asciiname":"Douar Rhamna",
    "gn:country_code":"MA",
    "gn:dem":874,
    "gn:feature_class":"P",
    "gn:feature_code":"PPL",
    "gn:name":"Douar Rhamna",
    "gn:population":0,
    "gn:timezone":"Africa/Casablanca",
    "iso:country":"MA",
    "wof:name":"Douar Rhamna",
    "wof:placetype":"locality"
},
  "geometry": {"coordinates":[-2.49676,34.72139],"type":"Point"}
}