{
  "type": "Feature",
  "properties": {
    "gn:admin1_code":"03",
    "gn:asciiname":"Douar Chiahna",
    "gn:country_code":"MA",
    "gn:dem":735,
    "gn:feature_class":"P",
    "gn:feature_code":"PPL",
    "gn:name":"Douar Chiahna",
    "gn:population":0,
    "gn:timezone":"Africa/Casablanca",
    "iso:country":"MA",
    "name:und_x_variant":[
        "Chiahna"
    ],
    "wof:name":"Douar Chiahna",
    "wof:placetype":"locality"
},
  "geometry": {"coordinates":[-3.86978,34.32211],"type":"Point"}
}