{
  "type": "Feature",
  "properties": {
    "gn:admin1_code":"4.0",
    "gn:asciiname":"Chihiyine",
    "gn:country_code":"MA",
    "gn:dem":344,
    "gn:feature_class":"P",
    "gn:feature_code":"PPL",
    "gn:name":"Chihiyine",
    "gn:population":0,
    "gn:timezone":"Africa/Casablanca",
    "iso:country":"MA",
    "wof:name":"Chihiyine",
    "wof:placetype":"locality"
},
  "geometry": {"coordinates":[-6.94454,33.62546],"type":"Point"}
}