{
  "type": "Feature",
  "properties": {
    "gn:admin1_code":"7.0",
    "gn:asciiname":"Douar Oulad Al Hachmi",
    "gn:country_code":"MA",
    "gn:dem":108,
    "gn:feature_class":"P",
    "gn:feature_code":"PPL",
    "gn:name":"Douar Oulad Al Hachmi",
    "gn:population":0,
    "gn:timezone":"Africa/Casablanca",
    "iso:country":"MA",
    "wof:name":"Douar Oulad Al Hachmi",
    "wof:placetype":"locality"
},
  "geometry": {"coordinates":[-9.30848,32.04884000000001],"type":"Point"}
}