{
  "type": "Feature",
  "properties": {
    "gn:admin1_code":"9.0",
    "gn:asciiname":"Timskit",
    "gn:country_code":"MA",
    "gn:dem":931,
    "gn:feature_class":"P",
    "gn:feature_code":"PPL",
    "gn:name":"Timskit",
    "gn:population":0,
    "gn:timezone":"Africa/Casablanca",
    "iso:country":"MA",
    "wof:name":"Timskit",
    "wof:placetype":"locality"
},
  "geometry": {"coordinates":[-7.95284,30.70865],"type":"Point"}
}