{
  "type": "Feature",
  "properties": {
    "gn:admin1_code":"03",
    "gn:asciiname":"Anosseur",
    "gn:country_code":"MA",
    "gn:dem":1375,
    "gn:feature_class":"P",
    "gn:feature_code":"PPL",
    "gn:name":"Anosseur",
    "gn:population":0,
    "gn:timezone":"Africa/Casablanca",
    "iso:country":"MA",
    "name:und_x_variant":[
        "Al Ano\u00e7er",
        "Ansoseur",
        "Annoceur",
        "Annosseur",
        "Anosseur"
    ],
    "wof:name":"Anosseur",
    "wof:placetype":"locality"
},
  "geometry": {"coordinates":[-4.8474,33.67145],"type":"Point"}
}