{
  "type": "Feature",
  "properties": {
    "gn:admin1_code":"08",
    "gn:asciiname":"Mimarighene",
    "gn:country_code":"MA",
    "gn:dem":762,
    "gn:feature_class":"P",
    "gn:feature_code":"PPL",
    "gn:name":"Mimarighene",
    "gn:population":0,
    "gn:timezone":"Africa/Casablanca",
    "iso:country":"MA",
    "name:und_x_variant":[
        "Mimarirhene",
        "Mimarigh\u00e9ne",
        "Mimarighene"
    ],
    "wof:name":"Mimarighene",
    "wof:placetype":"locality"
},
  "geometry": {"coordinates":[-4.92997,31.10328],"type":"Point"}
}