{
  "type": "Feature",
  "properties": {
    "gn:admin1_code":"7.0",
    "gn:asciiname":"Bou Ou Azar",
    "gn:country_code":"MA",
    "gn:dem":1330,
    "gn:feature_class":"P",
    "gn:feature_code":"PPL",
    "gn:name":"Bou Ou Azar",
    "gn:population":0,
    "gn:timezone":"Africa/Casablanca",
    "iso:country":"MA",
    "wof:name":"Bou Ou Azar",
    "wof:placetype":"locality"
},
  "geometry": {"coordinates":[-9.21823,30.98435],"type":"Point"}
}