{
  "type": "Feature",
  "properties": {
    "gn:admin1_code":"01",
    "gn:asciiname":"Douar Amlouk",
    "gn:country_code":"MA",
    "gn:dem":715,
    "gn:feature_class":"P",
    "gn:feature_code":"PPL",
    "gn:name":"Douar Amlouk",
    "gn:population":0,
    "gn:timezone":"Africa/Casablanca",
    "iso:country":"MA",
    "name:und_x_variant":[
        "Amelous",
        "Amelaous",
        "Douar Amlouk"
    ],
    "wof:name":"Douar Amlouk",
    "wof:placetype":"locality"
},
  "geometry": {"coordinates":[-4.82059,35.10625],"type":"Point"}
}