{
  "type": "Feature",
  "properties": {
    "gn:admin1_code":"7.0",
    "gn:asciiname":"Ait Lechguer",
    "gn:country_code":"MA",
    "gn:dem":539,
    "gn:feature_class":"P",
    "gn:feature_code":"PPL",
    "gn:name":"A\u00eft Lechguer",
    "gn:population":0,
    "gn:timezone":"Africa/Casablanca",
    "iso:country":"MA",
    "wof:name":"Ait Lechguer",
    "wof:placetype":"locality"
},
  "geometry": {"coordinates":[-9.42873,31.32396],"type":"Point"}
}