{
  "type": "Feature",
  "properties": {
    "gn:admin1_code":"9.0",
    "gn:asciiname":"Timsal",
    "gn:country_code":"MA",
    "gn:dem":1163,
    "gn:feature_class":"P",
    "gn:feature_code":"PPL",
    "gn:name":"Timsal",
    "gn:population":0,
    "gn:timezone":"Africa/Casablanca",
    "iso:country":"MA",
    "wof:name":"Timsal",
    "wof:placetype":"locality"
},
  "geometry": {"coordinates":[-8.53144,29.86508],"type":"Point"}
}