{
  "type": "Feature",
  "properties": {
    "gn:admin1_code":"9.0",
    "gn:asciiname":"Tamsoult-n-Ait Haroun",
    "gn:country_code":"MA",
    "gn:dem":1115,
    "gn:feature_class":"P",
    "gn:feature_code":"PPL",
    "gn:name":"Tamsoult-n-A\u00eft Haroun",
    "gn:population":0,
    "gn:timezone":"Africa/Casablanca",
    "iso:country":"MA",
    "wof:name":"Tamsoult-n-Ait Haroun",
    "wof:placetype":"locality"
},
  "geometry": {"coordinates":[-8.5335,29.83547],"type":"Point"}
}