{
  "type": "Feature",
  "properties": {
    "gn:admin1_code":"9.0",
    "gn:asciiname":"Lamghartine",
    "gn:country_code":"MA",
    "gn:dem":595,
    "gn:feature_class":"P",
    "gn:feature_code":"PPL",
    "gn:name":"Lamghartine",
    "gn:population":0,
    "gn:timezone":"Africa/Casablanca",
    "iso:country":"MA",
    "wof:name":"Lamghartine",
    "wof:placetype":"locality"
},
  "geometry": {"coordinates":[-8.27301,30.67204000000001],"type":"Point"}
}