{
  "type": "Feature",
  "properties": {
    "gn:admin1_code":"3.0",
    "gn:asciiname":"Douar Lkharba",
    "gn:country_code":"MA",
    "gn:dem":338,
    "gn:feature_class":"P",
    "gn:feature_code":"PPL",
    "gn:name":"Douar Lkharba",
    "gn:population":0,
    "gn:timezone":"Africa/Casablanca",
    "iso:country":"MA",
    "wof:name":"Douar Lkharba",
    "wof:placetype":"locality"
},
  "geometry": {"coordinates":[-4.67435,34.25204],"type":"Point"}
}