{
  "type": "Feature",
  "properties": {
    "gn:country":"MA",
    "gn:fcode":"ADM3",
    "gn:pop":21728,
    "iso:country":"MA",
    "name:ara_x_preferred":[
        "\u0623\u0648\u0644\u0627\u062f \u062f\u0627\u0648\u0648\u062f \u0627\u0632\u062e\u0627\u0646\u064a\u0646"
    ],
    "name:fra_x_preferred":[
        "Oulad Settout"
    ],
    "name:fra_x_variant":[
        "Oulad Settout (CR)",
        "Oulad Settout (Commune Rurale)"
    ],
    "qs:name":"Oulad Settout",
    "qs:photos_9r":0,
    "qs:photos_sr":0,
    "qs:pop_sr":"7",
    "wd:wordcount":57,
    "wof:name":"Oulad Settout",
    "wof:placetype":"localadmin",
    "wof:population":21728
},
  "geometry": {"coordinates":[-2.74256,34.92151],"type":"Point"}
}