{
  "type": "Feature",
  "properties": {
    "gn:country":"MA",
    "gn:fcode":"ADM3",
    "gn:population":21728,
    "iso:country":"MA",
    "name:ara_x_preferred":[
        "\u0623\u0648\u0644\u0627\u062f \u062f\u0627\u0648\u0648\u062f \u0627\u0632\u062e\u0627\u0646\u064a\u0646"
    ],
    "name:ara_x_variant":[
        "\u0623\u0648\u0644\u0627\u062f \u0633\u062a\u0648\u062a"
    ],
    "name:ary_x_preferred":[
        "\u0648\u0644\u0627\u062f \u0633\u062a\u0648\u062a"
    ],
    "name:cat_x_preferred":[
        "Oulad Settout"
    ],
    "name:ceb_x_preferred":[
        "Oulad Settout"
    ],
    "name:eng_x_preferred":[
        "Oulad Settout"
    ],
    "name:fra_x_preferred":[
        "Oulad Settout"
    ],
    "name:fra_x_variant":[
        "Oulad Settout (CR)",
        "Oulad Settout (Commune Rurale)"
    ],
    "name:ita_x_preferred":[
        "Oulad Settout"
    ],
    "name:spa_x_preferred":[
        "Ulad Settut"
    ],
    "name:swe_x_preferred":[
        "Oulad Settout"
    ],
    "name:zho_x_preferred":[
        "\u6b27\u62c9\u5fb7-\u585e\u900f\u7279"
    ],
    "qs:name":"Oulad Settout",
    "qs:photos_9r":0,
    "qs:photos_sr":0,
    "qs:pop_sr":"7",
    "wd:wordcount":57,
    "wof:name":"Oulad Settout",
    "wof:placetype":"localadmin",
    "wof:population":21728
},
  "geometry": {"coordinates":[-2.74256,34.92151],"type":"Point"}
}