{
  "type": "Feature",
  "properties": {
    "gn:admin1_code":"03",
    "gn:asciiname":"Ouizert",
    "gn:country_code":"MA",
    "gn:dem":1020,
    "gn:feature_class":"P",
    "gn:feature_code":"PPL",
    "gn:name":"Ouizert",
    "gn:population":0,
    "gn:timezone":"Africa/Casablanca",
    "iso:country":"MA",
    "name:und_x_variant":[
        "Ouizret",
        "Ouizert"
    ],
    "wof:name":"Ouizert",
    "wof:placetype":"locality"
},
  "geometry": {"coordinates":[-4.08869,32.86479],"type":"Point"}
}