{
  "type": "Feature",
  "properties": {
    "gn:admin1_code":"6.0",
    "gn:asciiname":"Eli Rehahla",
    "gn:country_code":"MA",
    "gn:dem":509,
    "gn:feature_class":"P",
    "gn:feature_code":"PPL",
    "gn:name":"Eli Rehahla",
    "gn:population":0,
    "gn:timezone":"Africa/Casablanca",
    "iso:country":"MA",
    "wof:name":"Eli Rehahla",
    "wof:placetype":"locality"
},
  "geometry": {"coordinates":[-7.44968,32.71047],"type":"Point"}
}