{
  "type": "Feature",
  "properties": {
    "gn:admin1_code":"4.0",
    "gn:asciiname":"Cooperative Chriblat",
    "gn:country_code":"MA",
    "gn:dem":10,
    "gn:feature_class":"P",
    "gn:feature_code":"PPLF",
    "gn:name":"Coop\u00e9rative Chriblat",
    "gn:population":0,
    "gn:timezone":"Africa/Casablanca",
    "iso:country":"MA",
    "wof:name":"Cooperative Chriblat",
    "wof:placetype":"locality"
},
  "geometry": {"coordinates":[-6.32643,34.53274],"type":"Point"}
}