{
  "type": "Feature",
  "properties": {
    "gn:admin1_code":"09",
    "gn:asciiname":"Tiyghmrt",
    "gn:country_code":"MA",
    "gn:dem":864,
    "gn:feature_class":"P",
    "gn:feature_code":"PPL",
    "gn:name":"Tiyghmrt",
    "gn:population":0,
    "gn:timezone":"Africa/Casablanca",
    "iso:country":"MA",
    "name:und_x_variant":[
        "Tighmert",
        "Tirhmert",
        "Tiyghmrt"
    ],
    "wof:name":"Tiyghmrt",
    "wof:placetype":"locality"
},
  "geometry": {"coordinates":[-9.10012,29.65969],"type":"Point"}
}