{
  "type": "Feature",
  "properties": {
    "gn:admin1_code":"07",
    "gn:asciiname":"Agadir n-Ait Ifrane",
    "gn:country_code":"MA",
    "gn:dem":477,
    "gn:feature_class":"P",
    "gn:feature_code":"PPL",
    "gn:name":"Agadir n-Ait Ifrane",
    "gn:population":0,
    "gn:timezone":"Africa/Casablanca",
    "iso:country":"MA",
    "name:und_x_variant":[
        "Ifrane"
    ],
    "wof:name":"Agadir n-Ait Ifrane",
    "wof:placetype":"locality"
},
  "geometry": {"coordinates":[-9.59083,31.21089000000001],"type":"Point"}
}