{
  "type": "Feature",
  "properties": {
    "gn:admin1_code":"2.0",
    "gn:asciiname":"Imechrobene",
    "gn:country_code":"MA",
    "gn:dem":137,
    "gn:feature_class":"P",
    "gn:feature_code":"PPL",
    "gn:name":"Imechrobene",
    "gn:population":0,
    "gn:timezone":"Africa/Casablanca",
    "iso:country":"MA",
    "wof:name":"Imechrobene",
    "wof:placetype":"locality"
},
  "geometry": {"coordinates":[-3.00281,35.14422],"type":"Point"}
}