{
  "type": "Feature",
  "properties": {
    "gn:admin1_code":"08",
    "gn:asciiname":"Assamer n'Ait Mohamed",
    "gn:country_code":"MA",
    "gn:dem":2284,
    "gn:feature_class":"P",
    "gn:feature_code":"PPL",
    "gn:name":"Assamer n\u2019A\u00eft Mohamed",
    "gn:population":0,
    "gn:timezone":"Africa/Casablanca",
    "iso:country":"MA",
    "name:und_x_variant":[
        "Assameur n\u2019A\u00eft Mohamed",
        "Assamer n\u2019A\u00eft Mohamed"
    ],
    "wof:name":"Assamer n'Ait Mohamed",
    "wof:placetype":"locality"
},
  "geometry": {"coordinates":[-4.81,32.38],"type":"Point"}
}