{
  "type": "Feature",
  "properties": {
    "gn:admin1_code":"7.0",
    "gn:asciiname":"'Azib Ayt Ou Nadam",
    "gn:country_code":"MA",
    "gn:dem":544,
    "gn:feature_class":"P",
    "gn:feature_code":"PPL",
    "gn:name":"\u2019Azib Ayt Ou Nadam",
    "gn:population":0,
    "gn:timezone":"Africa/Casablanca",
    "iso:country":"MA",
    "wof:name":"'Azib Ayt Ou Nadam",
    "wof:placetype":"locality"
},
  "geometry": {"coordinates":[-8.46986,31.40839],"type":"Point"}
}