{
  "type": "Feature",
  "properties": {
    "gn:admin1_code":"07",
    "gn:asciiname":"Douar Leghaouzi",
    "gn:country_code":"MA",
    "gn:dem":195,
    "gn:feature_class":"P",
    "gn:feature_code":"PPL",
    "gn:name":"Douar Leghaouzi",
    "gn:population":0,
    "gn:timezone":"Africa/Casablanca",
    "iso:country":"MA",
    "name:und_x_variant":[
        "Laghouazi",
        "Douar el Rhouazi",
        "El Rhouazi",
        "Douar Leghaouzi"
    ],
    "wof:name":"Douar Leghaouzi",
    "wof:placetype":"locality"
},
  "geometry": {"coordinates":[-8.70267,32.36594],"type":"Point"}
}