{
  "type": "Feature",
  "properties": {
    "gn:admin1_code":"07",
    "gn:asciiname":"Lekmichat",
    "gn:country_code":"MA",
    "gn:dem":312,
    "gn:feature_class":"P",
    "gn:feature_code":"PPL",
    "gn:name":"Lekmichat",
    "gn:population":0,
    "gn:timezone":"Africa/Casablanca",
    "iso:country":"MA",
    "name:und_x_variant":[
        "El Koumichat"
    ],
    "wof:name":"Lekmichat",
    "wof:placetype":"locality"
},
  "geometry": {"coordinates":[-8.40023,32.27931],"type":"Point"}
}