{
  "type": "Feature",
  "properties": {
    "gn:admin1_code":"03",
    "gn:asciiname":"Douar Ait Bouzemmour",
    "gn:country_code":"MA",
    "gn:dem":515,
    "gn:feature_class":"P",
    "gn:feature_code":"PPL",
    "gn:name":"Douar Ait Bouzemmour",
    "gn:population":0,
    "gn:timezone":"Africa/Casablanca",
    "iso:country":"MA",
    "name:und_x_variant":[
        "Douar A\u00eft Ben Zemour",
        "A\u00eft Ben Zemour",
        "Douar Ait Bouzemmour"
    ],
    "wof:name":"Douar Ait Bouzemmour",
    "wof:placetype":"locality"
},
  "geometry": {"coordinates":[-4.67338,34.00438],"type":"Point"}
}