{
  "type": "Feature",
  "properties": {
    "gn:admin1_code":"7.0",
    "gn:asciiname":"Imi-n-Ighzer",
    "gn:country_code":"MA",
    "gn:dem":914,
    "gn:feature_class":"P",
    "gn:feature_code":"PPL",
    "gn:name":"Imi-n-Ighzer",
    "gn:population":0,
    "gn:timezone":"Africa/Casablanca",
    "iso:country":"MA",
    "wof:name":"Imi-n-Ighzer",
    "wof:placetype":"locality"
},
  "geometry": {"coordinates":[-8.46858,31.19873],"type":"Point"}
}