{
  "type": "Feature",
  "properties": {
    "gn:admin1_code":"5.0",
    "gn:asciiname":"Tanout el Moua ou Ksou",
    "gn:country_code":"MA",
    "gn:dem":851,
    "gn:feature_class":"P",
    "gn:feature_code":"PPL",
    "gn:name":"Tanout el Moua ou Ksou",
    "gn:population":0,
    "gn:timezone":"Africa/Casablanca",
    "iso:country":"MA",
    "wof:name":"Tanout el Moua ou Ksou",
    "wof:placetype":"locality"
},
  "geometry": {"coordinates":[-5.76215,32.94105],"type":"Point"}
}