{
  "type": "Feature",
  "properties": {
    "gn:admin1_code":"9.0",
    "gn:asciiname":"Ajacuan",
    "gn:country_code":"MA",
    "gn:dem":48,
    "gn:feature_class":"P",
    "gn:feature_code":"PPL",
    "gn:name":"Ajacuan",
    "gn:population":0,
    "gn:timezone":"Africa/Casablanca",
    "iso:country":"MA",
    "wof:name":"Ajacuan",
    "wof:placetype":"locality"
},
  "geometry": {"coordinates":[-9.46504,30.30128],"type":"Point"}
}