{
  "type": "Feature",
  "properties": {
    "gn:admin1_code":"08",
    "gn:asciiname":"Zouiyya",
    "gn:country_code":"MA",
    "gn:dem":1233,
    "gn:feature_class":"P",
    "gn:feature_code":"PPL",
    "gn:name":"Zouiyya",
    "gn:population":0,
    "gn:timezone":"Africa/Casablanca",
    "iso:country":"MA",
    "wof:name":"Zouiyya",
    "wof:placetype":"locality"
},
  "geometry": {"coordinates":[-6.57654,31.08119000000001],"type":"Point"}
}