{
  "type": "Feature",
  "properties": {
    "gn:admin1_code":"01",
    "gn:asciiname":"Hatat El Madina",
    "gn:country_code":"MA",
    "gn:dem":239,
    "gn:feature_class":"P",
    "gn:feature_code":"PPLL",
    "gn:name":"Hatat El Madina",
    "gn:population":0,
    "gn:timezone":"Africa/Casablanca",
    "iso:country":"MA",
    "name:und_x_variant":[
        "Mermat"
    ],
    "wof:name":"Hatat El Madina",
    "wof:placetype":"locality"
},
  "geometry": {"coordinates":[-5.81768,35.26341],"type":"Point"}
}