{
  "type": "Feature",
  "properties": {
    "gn:admin1_code":"7.0",
    "gn:asciiname":"Dar Ait Ahmed ou Lahsene",
    "gn:country_code":"MA",
    "gn:dem":888,
    "gn:feature_class":"P",
    "gn:feature_code":"PPL",
    "gn:name":"Dar A\u00eft Ahmed ou Lahsene",
    "gn:population":0,
    "gn:timezone":"Africa/Casablanca",
    "iso:country":"MA",
    "wof:name":"Dar Ait Ahmed ou Lahsene",
    "wof:placetype":"locality"
},
  "geometry": {"coordinates":[-8.24568,31.2642],"type":"Point"}
}