{
  "type": "Feature",
  "properties": {
    "gn:admin1_code":"7.0",
    "gn:asciiname":"Louafi Lakhrab",
    "gn:country_code":"MA",
    "gn:dem":160,
    "gn:feature_class":"P",
    "gn:feature_code":"PPL",
    "gn:name":"Louafi Lakhrab",
    "gn:population":0,
    "gn:timezone":"Africa/Casablanca",
    "iso:country":"MA",
    "name:und_x_variant":[
        "El-Haj-el-Ouafi"
    ],
    "wof:name":"Louafi Lakhrab",
    "wof:placetype":"locality"
},
  "geometry": {"coordinates":[-8.93561,32.3884],"type":"Point"}
}