{
  "type": "Feature",
  "properties": {
    "gn:admin1_code":"7.0",
    "gn:asciiname":"Dar Abdelkader Ben Mohamed",
    "gn:country_code":"MA",
    "gn:dem":495,
    "gn:feature_class":"P",
    "gn:feature_code":"PPL",
    "gn:name":"Dar Abdelkader Ben Mohamed",
    "gn:population":0,
    "gn:timezone":"Africa/Casablanca",
    "iso:country":"MA",
    "wof:name":"Dar Abdelkader Ben Mohamed",
    "wof:placetype":"locality"
},
  "geometry": {"coordinates":[-7.73975,32.24359],"type":"Point"}
}