{
  "type": "Feature",
  "properties": {
    "gn:admin1_code":"01",
    "gn:asciiname":"El Maadene",
    "gn:country_code":"MA",
    "gn:dem":461,
    "gn:feature_class":"P",
    "gn:feature_code":"PPL",
    "gn:name":"El Maadene",
    "gn:population":0,
    "gn:timezone":"Africa/Casablanca",
    "iso:country":"MA",
    "name:und_x_variant":[
        "El Maaden",
        "El Maadene"
    ],
    "wof:name":"El Maadene",
    "wof:placetype":"locality"
},
  "geometry": {"coordinates":[-3.95403,35.01557],"type":"Point"}
}