{
  "type": "Feature",
  "properties": {
    "gn:admin1_code":"7.0",
    "gn:asciiname":"Ait Elloubane",
    "gn:country_code":"MA",
    "gn:dem":112,
    "gn:feature_class":"P",
    "gn:feature_code":"PPL",
    "gn:name":"Ait Elloubane",
    "gn:population":0,
    "gn:timezone":"Africa/Casablanca",
    "iso:country":"MA",
    "wof:name":"Ait Elloubane",
    "wof:placetype":"locality"
},
  "geometry": {"coordinates":[-9.69934,31.52008],"type":"Point"}
}