{
  "type": "Feature",
  "properties": {
    "gn:admin1_code":"07",
    "gn:asciiname":"Oulad Bouanane",
    "gn:country_code":"MA",
    "gn:dem":135,
    "gn:feature_class":"P",
    "gn:feature_code":"PPL",
    "gn:name":"Oulad Bouanane",
    "gn:population":0,
    "gn:timezone":"Africa/Casablanca",
    "iso:country":"MA",
    "name:und_x_variant":[
        "Oulad bou Hanane",
        "Ouled Bouanane",
        "Douar Oulad Bouanane",
        "Oulad Bouanane"
    ],
    "wof:name":"Oulad Bouanane",
    "wof:placetype":"locality"
},
  "geometry": {"coordinates":[-9.03181,32.36431],"type":"Point"}
}