{
  "type": "Feature",
  "properties": {
    "gn:admin1_code":"9.0",
    "gn:asciiname":"Tounef",
    "gn:country_code":"MA",
    "gn:dem":77,
    "gn:feature_class":"P",
    "gn:feature_code":"PPL",
    "gn:name":"Tounef",
    "gn:population":0,
    "gn:timezone":"Africa/Casablanca",
    "iso:country":"MA",
    "wof:name":"Tounef",
    "wof:placetype":"locality"
},
  "geometry": {"coordinates":[-9.52881,30.10031],"type":"Point"}
}