{
  "type": "Feature",
  "properties": {
    "gn:admin1_code":"9.0",
    "gn:asciiname":"Tine Mbarek ou Lhous",
    "gn:country_code":"MA",
    "gn:dem":123,
    "gn:feature_class":"P",
    "gn:feature_code":"PPL",
    "gn:name":"Tine Mbarek ou Lhous",
    "gn:population":0,
    "gn:timezone":"Africa/Casablanca",
    "iso:country":"MA",
    "wof:name":"Tine Mbarek ou Lhous",
    "wof:placetype":"locality"
},
  "geometry": {"coordinates":[-9.4598,30.06037],"type":"Point"}
}