{
  "type": "Feature",
  "properties": {
    "gn:admin1_code":"6.0",
    "gn:asciiname":"Douar Oulad Jbel Lefqih",
    "gn:country_code":"MA",
    "gn:dem":278,
    "gn:feature_class":"P",
    "gn:feature_code":"PPL",
    "gn:name":"Douar Oulad Jbel Lefqih",
    "gn:population":0,
    "gn:timezone":"Africa/Casablanca",
    "iso:country":"MA",
    "wof:name":"Douar Oulad Jbel Lefqih",
    "wof:placetype":"locality"
},
  "geometry": {"coordinates":[-7.08591,33.53244],"type":"Point"}
}