{
  "type": "Feature",
  "properties": {
    "gn:admin1_code":"08",
    "gn:asciiname":"Amerdout",
    "gn:country_code":"MA",
    "gn:dem":806,
    "gn:feature_class":"P",
    "gn:feature_code":"PPL",
    "gn:name":"Amerdout",
    "gn:population":0,
    "gn:timezone":"Africa/Casablanca",
    "iso:country":"MA",
    "wof:name":"Amerdout",
    "wof:placetype":"locality"
},
  "geometry": {"coordinates":[-6.09913,30.4982],"type":"Point"}
}