{
  "type": "Feature",
  "properties": {
    "gn:admin1_code":"7.0",
    "gn:asciiname":"Drissiya",
    "gn:country_code":"MA",
    "gn:dem":683,
    "gn:feature_class":"P",
    "gn:feature_code":"PPL",
    "gn:name":"Drissiya",
    "gn:population":0,
    "gn:timezone":"Africa/Casablanca",
    "iso:country":"MA",
    "wof:name":"Drissiya",
    "wof:placetype":"locality"
},
  "geometry": {"coordinates":[-7.32455,31.76835],"type":"Point"}
}