{
  "type": "Feature",
  "properties": {
    "gn:admin1_code":"3.0",
    "gn:asciiname":"Douar Lemsamda",
    "gn:country_code":"MA",
    "gn:dem":274,
    "gn:feature_class":"P",
    "gn:feature_code":"PPL",
    "gn:name":"Douar Lemsamda",
    "gn:population":0,
    "gn:timezone":"Africa/Casablanca",
    "iso:country":"MA",
    "wof:name":"Douar Lemsamda",
    "wof:placetype":"locality"
},
  "geometry": {"coordinates":[-5.28887,34.34687],"type":"Point"}
}