{
  "type": "Feature",
  "properties": {
    "gn:country":"MA",
    "gn:fcode":"ADM3",
    "gn:population":3456,
    "iso:country":"MA",
    "name:ara_x_preferred":[
        "\u0627\u062c\u0628\u0627\u0631\u0646\u0629"
    ],
    "name:cat_x_preferred":[
        "Jbarna"
    ],
    "name:ceb_x_preferred":[
        "Jbarna"
    ],
    "name:fra_x_preferred":[
        "Jbarna"
    ],
    "name:fra_x_variant":[
        "Jbarna (CR)",
        "Jbarna (Commune Rurale)"
    ],
    "name:ita_x_preferred":[
        "Jbarna"
    ],
    "name:swe_x_preferred":[
        "Jbarna"
    ],
    "qs_pg:aaroncc":"MA",
    "qs_pg:gn_country":"MA",
    "qs_pg:gn_fcode":"ADM3",
    "qs_pg:gn_pop":3456,
    "qs_pg:name":"Jbarna",
    "qs_pg:photos_9r":0,
    "qs_pg:photos_sr":0,
    "qs_pg:pop_sr":4,
    "qs_pg:qs_pg_placetype":"localadmin",
    "wof:name":"Jbarna",
    "wof:placetype":"localadmin",
    "wof:population":2730
},
  "geometry": {"coordinates":[-3.84965,34.51588],"type":"Point"}
}