{
  "type": "Feature",
  "properties": {
    "gn:admin1_code":"5.0",
    "gn:asciiname":"Talansought",
    "gn:country_code":"MA",
    "gn:dem":1539,
    "gn:feature_class":"P",
    "gn:feature_code":"PPL",
    "gn:name":"Talansought",
    "gn:population":0,
    "gn:timezone":"Africa/Casablanca",
    "iso:country":"MA",
    "wof:name":"Talansought",
    "wof:placetype":"locality"
},
  "geometry": {"coordinates":[-6.29404,31.97369],"type":"Point"}
}