{
  "type": "Feature",
  "properties": {
    "gn:admin1_code":"5.0",
    "gn:asciiname":"Ait Ali ou Kessou",
    "gn:country_code":"MA",
    "gn:dem":850,
    "gn:feature_class":"P",
    "gn:feature_code":"PPL",
    "gn:name":"A\u00eft Ali ou Kessou",
    "gn:population":0,
    "gn:timezone":"Africa/Casablanca",
    "iso:country":"MA",
    "wof:name":"Ait Ali ou Kessou",
    "wof:placetype":"locality"
},
  "geometry": {"coordinates":[-5.60619,32.83932],"type":"Point"}
}