{
  "type": "Feature",
  "properties": {
    "gn:admin1_code":"5.0",
    "gn:asciiname":"Beni Akouti",
    "gn:country_code":"MA",
    "gn:dem":792,
    "gn:feature_class":"P",
    "gn:feature_code":"PPL",
    "gn:name":"Beni Akouti",
    "gn:population":0,
    "gn:timezone":"Africa/Casablanca",
    "iso:country":"MA",
    "wof:name":"Beni Akouti",
    "wof:placetype":"locality"
},
  "geometry": {"coordinates":[-5.75869,32.79519000000001],"type":"Point"}
}