{
  "type": "Feature",
  "properties": {
    "gn:admin1_code":"7.0",
    "gn:asciiname":"Douar Lehsasna",
    "gn:country_code":"MA",
    "gn:dem":227,
    "gn:feature_class":"P",
    "gn:feature_code":"PPL",
    "gn:name":"Douar Lehsasna",
    "gn:population":0,
    "gn:timezone":"Africa/Casablanca",
    "iso:country":"MA",
    "wof:name":"Douar Lehsasna",
    "wof:placetype":"locality"
},
  "geometry": {"coordinates":[-8.97319,32.1386],"type":"Point"}
}