{
  "type": "Feature",
  "properties": {
    "gn:admin1_code":"3.0",
    "gn:asciiname":"Douar Ait Moha Ou Aqqa",
    "gn:country_code":"MA",
    "gn:dem":1535,
    "gn:feature_class":"P",
    "gn:feature_code":"PPL",
    "gn:name":"Douar Ait Moha Ou Aqqa",
    "gn:population":0,
    "gn:timezone":"Africa/Casablanca",
    "iso:country":"MA",
    "wof:name":"Douar Ait Moha Ou Aqqa",
    "wof:placetype":"locality"
},
  "geometry": {"coordinates":[-4.82376,33.59458],"type":"Point"}
}