{
  "type": "Feature",
  "properties": {
    "gn:admin1_code":"05",
    "gn:asciiname":"Al 'Assara",
    "gn:country_code":"MA",
    "gn:dem":400,
    "gn:feature_class":"P",
    "gn:feature_code":"PPL",
    "gn:name":"Al \u2019Assara",
    "gn:population":0,
    "gn:timezone":"Africa/Casablanca",
    "iso:country":"MA",
    "name:und_x_variant":[
        "Lassara",
        "El Assara",
        "Al \u2019Assara"
    ],
    "wof:name":"Al 'Assara",
    "wof:placetype":"locality"
},
  "geometry": {"coordinates":[-6.71303,32.35661],"type":"Point"}
}