{
  "type": "Feature",
  "properties": {
    "gn:admin1_code":"10.0",
    "gn:asciiname":"Id 'Bayd",
    "gn:country_code":"MA",
    "gn:dem":805,
    "gn:feature_class":"P",
    "gn:feature_code":"PPL",
    "gn:name":"Id \u2019Bayd",
    "gn:population":0,
    "gn:timezone":"Africa/Casablanca",
    "iso:country":"MA",
    "wof:name":"Id 'Bayd",
    "wof:placetype":"locality"
},
  "geometry": {"coordinates":[-9.89046,29.29181],"type":"Point"}
}