{
  "type": "Feature",
  "properties": {
    "gn:admin1_code":"09",
    "gn:asciiname":"Tagadirt-n-Ouchbarou",
    "gn:country_code":"MA",
    "gn:dem":781,
    "gn:feature_class":"P",
    "gn:feature_code":"PPL",
    "gn:name":"Tagadirt-n-Ouchbarou",
    "gn:population":0,
    "gn:timezone":"Africa/Casablanca",
    "iso:country":"MA",
    "name:und_x_variant":[
        "Jerir Tagadirt Achbaro",
        "Taourirt n\u2019Ouchbaro",
        "Tagadirt-n-Ouchbarou"
    ],
    "wof:name":"Tagadirt-n-Ouchbarou",
    "wof:placetype":"locality"
},
  "geometry": {"coordinates":[-8.47083,30.75393],"type":"Point"}
}