{
  "type": "Feature",
  "properties": {
    "gn:admin1_code":"7.0",
    "gn:asciiname":"Agadir-n-Tkikhfist",
    "gn:country_code":"MA",
    "gn:dem":928,
    "gn:feature_class":"P",
    "gn:feature_code":"PPL",
    "gn:name":"Agadir-n-Tkikhfist",
    "gn:population":0,
    "gn:timezone":"Africa/Casablanca",
    "iso:country":"MA",
    "wof:name":"Agadir-n-Tkikhfist",
    "wof:placetype":"locality"
},
  "geometry": {"coordinates":[-7.76256,31.35643],"type":"Point"}
}