{
  "type": "Feature",
  "properties": {
    "gn:admin1_code":"09",
    "gn:asciiname":"Afaiane",
    "gn:country_code":"MA",
    "gn:dem":736,
    "gn:feature_class":"P",
    "gn:feature_code":"PPL",
    "gn:name":"Afa\u00efane",
    "gn:population":0,
    "gn:timezone":"Africa/Casablanca",
    "iso:country":"MA",
    "name:und_x_variant":[
        "Afayade",
        "Afa\u00efane",
        "Afayane"
    ],
    "wof:name":"Afaiane",
    "wof:placetype":"locality"
},
  "geometry": {"coordinates":[-9.20251,30.01091],"type":"Point"}
}