{
  "type": "Feature",
  "properties": {
    "gn:admin1_code":"10",
    "gn:asciiname":"Bou Izakarn",
    "gn:country_code":"MA",
    "gn:dem":635,
    "gn:feature_class":"P",
    "gn:feature_code":"PPL",
    "gn:name":"Bou Izakarn",
    "gn:population":0,
    "gn:timezone":"Africa/Casablanca",
    "iso:country":"MA",
    "name:und_x_variant":[
        "Bou Izakarene",
        "Bou Izakaren",
        "Bu Isacarn",
        "Bou Izakarn"
    ],
    "wof:name":"Bou Izakarn",
    "wof:placetype":"locality"
},
  "geometry": {"coordinates":[-9.71181,29.17705],"type":"Point"}
}