{
  "type": "Feature",
  "properties": {
    "gn:admin1_code":"7.0",
    "gn:asciiname":"Oulad Jarrar",
    "gn:country_code":"MA",
    "gn:dem":106,
    "gn:feature_class":"P",
    "gn:feature_code":"PPL",
    "gn:name":"Oulad Jarrar",
    "gn:population":0,
    "gn:timezone":"Africa/Casablanca",
    "iso:country":"MA",
    "wof:name":"Oulad Jarrar",
    "wof:placetype":"locality"
},
  "geometry": {"coordinates":[-9.44597,31.87481],"type":"Point"}
}