{
  "type": "Feature",
  "properties": {
    "gn:admin1_code":"9.0",
    "gn:asciiname":"Ait Boutiliy",
    "gn:country_code":"MA",
    "gn:dem":1507,
    "gn:feature_class":"P",
    "gn:feature_code":"PPL",
    "gn:name":"A\u00eft Boutiliy",
    "gn:population":0,
    "gn:timezone":"Africa/Casablanca",
    "iso:country":"MA",
    "wof:name":"Ait Boutiliy",
    "wof:placetype":"locality"
},
  "geometry": {"coordinates":[-8.65971,30.07797],"type":"Point"}
}