{
  "type": "Feature",
  "properties": {
    "gn:admin1_code":"10",
    "gn:asciiname":"Talilit",
    "gn:country_code":"MA",
    "gn:dem":844,
    "gn:feature_class":"P",
    "gn:feature_code":"PPL",
    "gn:name":"Talilit",
    "gn:population":0,
    "gn:timezone":"Africa/Casablanca",
    "iso:country":"MA",
    "name:ara_x_preferred":[
        "\u062a\u0644\u064a\u0644\u064a\u062a"
    ],
    "name:cat_x_preferred":[
        "Talilit"
    ],
    "name:ceb_x_preferred":[
        "Talilit"
    ],
    "name:swe_x_preferred":[
        "Talilit"
    ],
    "wof:name":"Talilit",
    "wof:placetype":"locality"
},
  "geometry": {"coordinates":[-9.10459,29.17782],"type":"Point"}
}