{
  "type": "Feature",
  "properties": {
    "gn:admin1_code":"09",
    "gn:asciiname":"Tafraout n'Ait Zerkri",
    "gn:country_code":"MA",
    "gn:dem":1069,
    "gn:feature_class":"P",
    "gn:feature_code":"PPL",
    "gn:name":"Tafraout n\u2019A\u00eft Zerkri",
    "gn:population":0,
    "gn:timezone":"Africa/Casablanca",
    "iso:country":"MA",
    "name:und_x_variant":[
        "Tafraout n\u2019A\u00eft Zerkri",
        "Tafraout n\u2019A\u00eft Zekri"
    ],
    "wof:name":"Tafraout n'Ait Zerkri",
    "wof:placetype":"locality"
},
  "geometry": {"coordinates":[-8.73581,30.66566],"type":"Point"}
}