{
  "type": "Feature",
  "properties": {
    "gn:admin1_code":"7.0",
    "gn:asciiname":"Id Ouarray",
    "gn:country_code":"MA",
    "gn:dem":337,
    "gn:feature_class":"P",
    "gn:feature_code":"PPL",
    "gn:name":"Id Ouarray",
    "gn:population":0,
    "gn:timezone":"Africa/Casablanca",
    "iso:country":"MA",
    "wof:name":"Id Ouarray",
    "wof:placetype":"locality"
},
  "geometry": {"coordinates":[-9.66026,31.1128],"type":"Point"}
}