{
  "type": "Feature",
  "properties": {
    "gn:admin1_code":"08",
    "gn:asciiname":"Ayt Ouchrif",
    "gn:country_code":"MA",
    "gn:dem":1621,
    "gn:feature_class":"P",
    "gn:feature_code":"PPL",
    "gn:name":"Ayt Ouchrif",
    "gn:population":0,
    "gn:timezone":"Africa/Casablanca",
    "iso:country":"MA",
    "name:und_x_variant":[
        "A\u00eft Ou Ch\u00e9rif",
        "A\u00eft Ou Chrif",
        "Ayt Ouchrif"
    ],
    "wof:name":"Ayt Ouchrif",
    "wof:placetype":"locality"
},
  "geometry": {"coordinates":[-5.24457,32.65175],"type":"Point"}
}