{
  "type": "Feature",
  "properties": {
    "gn:admin1_code":"03",
    "gn:asciiname":"Taggour",
    "gn:country_code":"MA",
    "gn:dem":818,
    "gn:feature_class":"P",
    "gn:feature_code":"PPL",
    "gn:name":"Taggour",
    "gn:population":0,
    "gn:timezone":"Africa/Casablanca",
    "iso:country":"MA",
    "name:und_x_variant":[
        "Touggour",
        "Touggourt",
        "Teggour",
        "Taggour"
    ],
    "wof:name":"Taggour",
    "wof:placetype":"locality"
},
  "geometry": {"coordinates":[-3.84942,33.18975],"type":"Point"}
}