{
  "type": "Feature",
  "properties": {
    "gn:admin1_code":"7.0",
    "gn:asciiname":"Ait Bouskour",
    "gn:country_code":"MA",
    "gn:dem":1092,
    "gn:feature_class":"P",
    "gn:feature_code":"PPL",
    "gn:name":"A\u00eft Bouskour",
    "gn:population":0,
    "gn:timezone":"Africa/Casablanca",
    "iso:country":"MA",
    "wof:name":"Ait Bouskour",
    "wof:placetype":"locality"
},
  "geometry": {"coordinates":[-7.48723,31.49565],"type":"Point"}
}