{
  "type": "Feature",
  "properties": {
    "gn:admin1_code":"04",
    "gn:asciiname":"Oulad Masbah",
    "gn:country_code":"MA",
    "gn:dem":23,
    "gn:feature_class":"P",
    "gn:feature_code":"PPL",
    "gn:name":"Oulad Masbah",
    "gn:population":0,
    "gn:timezone":"Africa/Casablanca",
    "iso:country":"MA",
    "name:und_x_variant":[
        "Douar Oulad Masbah",
        "Oulad Mesbah",
        "Oulad Masbah"
    ],
    "wof:name":"Oulad Masbah",
    "wof:placetype":"locality"
},
  "geometry": {"coordinates":[-6.31606,34.79325],"type":"Point"}
}