{
  "type": "Feature",
  "properties": {
    "gn:admin1_code":"05",
    "gn:asciiname":"Ait Bou Rhiout",
    "gn:country_code":"MA",
    "gn:dem":1050,
    "gn:elevation":"0.0",
    "gn:feature_class":"P",
    "gn:feature_code":"PPL",
    "gn:name":"A\u00eft Bou Rhiout",
    "gn:population":0,
    "gn:timezone":"Africa/Casablanca",
    "iso:country":"MA",
    "wof:name":"Ait Bou Rhiout",
    "wof:placetype":"locality"
},
  "geometry": {"coordinates":[-6.87907,31.84451],"type":"Point"}
}