{
  "type": "Feature",
  "properties": {
    "gn:admin1_code":"07",
    "gn:asciiname":"Oulad Bouchayb",
    "gn:country_code":"MA",
    "gn:dem":488,
    "gn:feature_class":"P",
    "gn:feature_code":"PPL",
    "gn:name":"Oulad Bouchayb",
    "gn:population":0,
    "gn:timezone":"Africa/Casablanca",
    "iso:country":"MA",
    "name:und_x_variant":[
        "Oulad Ben Cha\u00efb",
        "Ouled Bou Cha\u00efb",
        "Oulad Bou Cha\u00efb",
        "Oulad Bouchayb"
    ],
    "wof:name":"Oulad Bouchayb",
    "wof:placetype":"locality"
},
  "geometry": {"coordinates":[-8.91133,31.91098],"type":"Point"}
}