{
  "type": "Feature",
  "properties": {
    "gn:admin1_code":"08",
    "gn:asciiname":"Ait Zaokri",
    "gn:country_code":"MA",
    "gn:dem":1351,
    "gn:feature_class":"P",
    "gn:feature_code":"PPL",
    "gn:name":"A\u00eft Zaokri",
    "gn:population":0,
    "gn:timezone":"Africa/Casablanca",
    "iso:country":"MA",
    "name:und_x_variant":[
        "A\u00eft Zaakri",
        "A\u00eft Zaokri"
    ],
    "wof:name":"Ait Zaokri",
    "wof:placetype":"locality"
},
  "geometry": {"coordinates":[-5.58,31.55],"type":"Point"}
}