{
  "type": "Feature",
  "properties": {
    "gn:admin1_code":"02",
    "gn:asciiname":"Douar Boujibar",
    "gn:country_code":"MA",
    "gn:dem":68,
    "gn:feature_class":"P",
    "gn:feature_code":"PPL",
    "gn:name":"Douar Boujibar",
    "gn:population":0,
    "gn:timezone":"Africa/Casablanca",
    "iso:country":"MA",
    "name:und_x_variant":[
        "Buyibar",
        "Bo\u00fbj\u00eeb\u00e2r",
        "Douar Boujibar"
    ],
    "wof:name":"Douar Boujibar",
    "wof:placetype":"locality"
},
  "geometry": {"coordinates":[-3.72133,35.28021],"type":"Point"}
}