{
  "type": "Feature",
  "properties": {
    "gn:admin1_code":"7.0",
    "gn:asciiname":"Rge. de Timichchi",
    "gn:country_code":"MA",
    "gn:dem":1938,
    "gn:feature_class":"P",
    "gn:feature_code":"PPL",
    "gn:name":"Rge. de Timichchi",
    "gn:population":0,
    "gn:timezone":"Africa/Casablanca",
    "iso:country":"MA",
    "wof:name":"Rge. de Timichchi",
    "wof:placetype":"locality"
},
  "geometry": {"coordinates":[-7.76785,31.19305],"type":"Point"}
}