{
  "type": "Feature",
  "properties": {
    "gn:admin1_code":"05",
    "gn:asciiname":"Ait Boulmane",
    "gn:country_code":"MA",
    "gn:dem":1152,
    "gn:elevation":"0.0",
    "gn:feature_class":"P",
    "gn:feature_code":"PPL",
    "gn:name":"A\u00eft Boulmane",
    "gn:population":0,
    "gn:timezone":"Africa/Casablanca",
    "iso:country":"MA",
    "wof:name":"Ait Boulmane",
    "wof:placetype":"locality"
},
  "geometry": {"coordinates":[-6.93321,31.75976],"type":"Point"}
}