{
  "type": "Feature",
  "properties": {
    "gn:admin1_code":"03",
    "gn:asciiname":"Douar Oulad Bouzekri",
    "gn:country_code":"MA",
    "gn:dem":356,
    "gn:feature_class":"P",
    "gn:feature_code":"PPL",
    "gn:name":"Douar Oulad Bouzekri",
    "gn:population":0,
    "gn:timezone":"Africa/Casablanca",
    "iso:country":"MA",
    "name:und_x_variant":[
        "Douar Ben Scri",
        "Ouled Bouzekri",
        "Douar Oulad Bouzekri",
        "Ain Lmehraz"
    ],
    "wof:name":"Douar Oulad Bouzekri",
    "wof:placetype":"locality"
},
  "geometry": {"coordinates":[-5.29262,34.2061],"type":"Point"}
}