{
  "type": "Feature",
  "properties": {
    "gn:admin1_code":"6.0",
    "gn:asciiname":"Ghalla",
    "gn:country_code":"MA",
    "gn:dem":564,
    "gn:feature_class":"P",
    "gn:feature_code":"PPL",
    "gn:name":"Ghalla",
    "gn:population":0,
    "gn:timezone":"Africa/Casablanca",
    "iso:country":"MA",
    "wof:name":"Ghalla",
    "wof:placetype":"locality"
},
  "geometry": {"coordinates":[-7.09458,32.63786],"type":"Point"}
}