{
  "type": "Feature",
  "properties": {
    "gn:admin1_code":"4.0",
    "gn:asciiname":"Oued Lbaqqal",
    "gn:country_code":"MA",
    "gn:dem":128,
    "gn:feature_class":"P",
    "gn:feature_code":"PPL",
    "gn:name":"Oued Lbaqqal",
    "gn:population":0,
    "gn:timezone":"Africa/Casablanca",
    "iso:country":"MA",
    "wof:name":"Oued Lbaqqal",
    "wof:placetype":"locality"
},
  "geometry": {"coordinates":[-5.88053,34.82947],"type":"Point"}
}