{
  "type": "Feature",
  "properties": {
    "gn:admin1_code":"1.0",
    "gn:asciiname":"Douar Azaghar",
    "gn:country_code":"MA",
    "gn:dem":469,
    "gn:feature_class":"P",
    "gn:feature_code":"PPL",
    "gn:name":"Douar Azaghar",
    "gn:population":0,
    "gn:timezone":"Africa/Casablanca",
    "iso:country":"MA",
    "wof:name":"Douar Azaghar",
    "wof:placetype":"locality"
},
  "geometry": {"coordinates":[-4.98083,35.17477],"type":"Point"}
}