{
  "type": "Feature",
  "properties": {
    "gn:admin1_code":"6.0",
    "gn:asciiname":"Douar Bou Amri",
    "gn:country_code":"MA",
    "gn:dem":299,
    "gn:feature_class":"P",
    "gn:feature_code":"PPL",
    "gn:name":"Douar Bou Amri",
    "gn:population":0,
    "gn:timezone":"Africa/Casablanca",
    "iso:country":"MA",
    "wof:name":"Douar Bou Amri",
    "wof:placetype":"locality"
},
  "geometry": {"coordinates":[-7.09724,33.53391],"type":"Point"}
}