{
  "type": "Feature",
  "properties": {
    "gn:admin1_code":"08",
    "gn:asciiname":"Taghreft",
    "gn:country_code":"MA",
    "gn:dem":2194,
    "gn:feature_class":"P",
    "gn:feature_code":"PPL",
    "gn:name":"Taghreft",
    "gn:population":0,
    "gn:timezone":"Africa/Casablanca",
    "iso:country":"MA",
    "wof:name":"Taghreft",
    "wof:placetype":"locality"
},
  "geometry": {"coordinates":[-6.25712,31.61652],"type":"Point"}
}