{
  "type": "Feature",
  "properties": {
    "gn:admin1_code":"2.0",
    "gn:asciiname":"Oulad Allal",
    "gn:country_code":"MA",
    "gn:dem":182,
    "gn:feature_class":"P",
    "gn:feature_code":"PPL",
    "gn:name":"Oulad Allal",
    "gn:population":0,
    "gn:timezone":"Africa/Casablanca",
    "iso:country":"MA",
    "wof:name":"Oulad Allal",
    "wof:placetype":"locality"
},
  "geometry": {"coordinates":[-3.06215,34.9994],"type":"Point"}
}