{
  "type": "Feature",
  "properties": {
    "gn:admin1_code":"2.0",
    "gn:asciiname":"Zarroura",
    "gn:country_code":"MA",
    "gn:dem":33,
    "gn:feature_class":"P",
    "gn:feature_code":"PPL",
    "gn:name":"Zarroura",
    "gn:population":0,
    "gn:timezone":"Africa/Casablanca",
    "iso:country":"MA",
    "wof:name":"Zarroura",
    "wof:placetype":"locality"
},
  "geometry": {"coordinates":[-3.15928,35.20933],"type":"Point"}
}