{
  "type": "Feature",
  "properties": {
    "gn:admin1_code":"7.0",
    "gn:asciiname":"Ait Ouakhoun",
    "gn:country_code":"MA",
    "gn:dem":1351,
    "gn:feature_class":"P",
    "gn:feature_code":"PPL",
    "gn:name":"A\u00eft Ouakhoun",
    "gn:population":0,
    "gn:timezone":"Africa/Casablanca",
    "iso:country":"MA",
    "wof:name":"Ait Ouakhoun",
    "wof:placetype":"locality"
},
  "geometry": {"coordinates":[-9.13129,31.03608],"type":"Point"}
}