{
  "type": "Feature",
  "properties": {
    "gn:admin1_code":"10",
    "gn:asciiname":"Id Bou Oudfel",
    "gn:country_code":"MA",
    "gn:dem":1424,
    "gn:feature_class":"P",
    "gn:feature_code":"PPL",
    "gn:name":"Id Bou Oudfel",
    "gn:population":0,
    "gn:timezone":"Africa/Casablanca",
    "iso:country":"MA",
    "name:und_x_variant":[
        "Id Boudfel",
        "Id Bou Oudfel"
    ],
    "wof:name":"Id Bou Oudfel",
    "wof:placetype":"locality"
},
  "geometry": {"coordinates":[-9.25925,29.40015],"type":"Point"}
}