{
  "type": "Feature",
  "properties": {
    "gn:admin1_code":"05",
    "gn:asciiname":"Akhachane",
    "gn:country_code":"MA",
    "gn:dem":1537,
    "gn:feature_class":"P",
    "gn:feature_code":"PPL",
    "gn:name":"Akhachane",
    "gn:population":0,
    "gn:timezone":"Africa/Casablanca",
    "iso:country":"MA",
    "wof:name":"Akhachane",
    "wof:placetype":"locality"
},
  "geometry": {"coordinates":[-6.13431,32.05306],"type":"Point"}
}