{
  "type": "Feature",
  "properties": {
    "gn:admin1_code":"02",
    "gn:asciiname":"Douar Souani",
    "gn:country_code":"MA",
    "gn:dem":7,
    "gn:feature_class":"P",
    "gn:feature_code":"PPL",
    "gn:name":"Douar Souani",
    "gn:population":0,
    "gn:timezone":"Africa/Casablanca",
    "iso:country":"MA",
    "wof:name":"Douar Souani",
    "wof:placetype":"locality"
},
  "geometry": {"coordinates":[-3.77727,35.20862],"type":"Point"}
}