{
  "type": "Feature",
  "properties": {
    "gn:admin1_code":"03",
    "gn:asciiname":"Sidi Daououd",
    "gn:country_code":"MA",
    "gn:dem":928,
    "gn:feature_class":"P",
    "gn:feature_code":"PPL",
    "gn:name":"Sidi Daououd",
    "gn:population":0,
    "gn:timezone":"Africa/Casablanca",
    "iso:country":"MA",
    "name:und_x_variant":[
        "Sidi Daoud"
    ],
    "wof:name":"Sidi Daououd",
    "wof:placetype":"locality"
},
  "geometry": {"coordinates":[-4.25803,34.55245],"type":"Point"}
}