{
  "type": "Feature",
  "properties": {
    "gn:admin1_code":"1.0",
    "gn:asciiname":"Douar Izzoudene",
    "gn:country_code":"MA",
    "gn:dem":315,
    "gn:feature_class":"P",
    "gn:feature_code":"PPL",
    "gn:name":"Douar Izzoudene",
    "gn:population":0,
    "gn:timezone":"Africa/Casablanca",
    "iso:country":"MA",
    "wof:name":"Douar Izzoudene",
    "wof:placetype":"locality"
},
  "geometry": {"coordinates":[-3.99459,35.1051],"type":"Point"}
}