{
  "type": "Feature",
  "properties": {
    "gn:admin1_code":"6.0",
    "gn:asciiname":"Douar Bir Tayek",
    "gn:country_code":"MA",
    "gn:dem":311,
    "gn:feature_class":"P",
    "gn:feature_code":"PPL",
    "gn:name":"Douar Bir Tayek",
    "gn:population":0,
    "gn:timezone":"Africa/Casablanca",
    "iso:country":"MA",
    "wof:name":"Douar Bir Tayek",
    "wof:placetype":"locality"
},
  "geometry": {"coordinates":[-7.01882,33.6015],"type":"Point"}
}