{
  "type": "Feature",
  "properties": {
    "gn:admin1_code":"7.0",
    "gn:asciiname":"Mon. Fre d'Azrif",
    "gn:country_code":"MA",
    "gn:dem":1566,
    "gn:feature_class":"P",
    "gn:feature_code":"PPL",
    "gn:name":"Mon. Fre d\u2019Azrif",
    "gn:population":0,
    "gn:timezone":"Africa/Casablanca",
    "iso:country":"MA",
    "wof:name":"Mon. Fre d'Azrif",
    "wof:placetype":"locality"
},
  "geometry": {"coordinates":[-7.26245,31.53962000000001],"type":"Point"}
}