{
  "type": "Feature",
  "properties": {
    "gn:admin1_code":"2.0",
    "gn:asciiname":"Douar Ain Kasba",
    "gn:country_code":"MA",
    "gn:dem":486,
    "gn:feature_class":"P",
    "gn:feature_code":"PPL",
    "gn:name":"Douar Ain Kasba",
    "gn:population":0,
    "gn:timezone":"Africa/Casablanca",
    "iso:country":"MA",
    "wof:name":"Douar Ain Kasba",
    "wof:placetype":"locality"
},
  "geometry": {"coordinates":[-3.64962,35.06827],"type":"Point"}
}