{
  "type": "Feature",
  "properties": {
    "gn:admin1_code":"06",
    "gn:asciiname":"Douar Lahmadat",
    "gn:country_code":"MA",
    "gn:dem":386,
    "gn:feature_class":"P",
    "gn:feature_code":"PPL",
    "gn:name":"Douar Lahmadat",
    "gn:population":0,
    "gn:timezone":"Africa/Casablanca",
    "iso:country":"MA",
    "name:und_x_variant":[
        "Lahmadate",
        "Lalmadak",
        "Lahmadat"
    ],
    "wof:name":"Douar Lahmadat",
    "wof:placetype":"locality"
},
  "geometry": {"coordinates":[-7.10028,32.4308],"type":"Point"}
}