{
  "type": "Feature",
  "properties": {
    "gn:admin1_code":"7.0",
    "gn:asciiname":"Dar Bel Lakroun",
    "gn:country_code":"MA",
    "gn:dem":519,
    "gn:feature_class":"P",
    "gn:feature_code":"PPL",
    "gn:name":"Dar Bel Lakroun",
    "gn:population":0,
    "gn:timezone":"Africa/Casablanca",
    "iso:country":"MA",
    "wof:name":"Dar Bel Lakroun",
    "wof:placetype":"locality"
},
  "geometry": {"coordinates":[-7.23136,31.99373],"type":"Point"}
}