{
  "type": "Feature",
  "properties": {
    "gn:admin1_code":"1.0",
    "gn:asciiname":"Douar Dar Amalou",
    "gn:country_code":"MA",
    "gn:dem":360,
    "gn:feature_class":"P",
    "gn:feature_code":"PPL",
    "gn:name":"Douar Dar Amalou",
    "gn:population":0,
    "gn:timezone":"Africa/Casablanca",
    "iso:country":"MA",
    "wof:name":"Douar Dar Amalou",
    "wof:placetype":"locality"
},
  "geometry": {"coordinates":[-5.04538,35.32914],"type":"Point"}
}