{
  "type": "Feature",
  "properties": {
    "gn:admin1_code":"01",
    "gn:asciiname":"Oulad Chaehbi",
    "gn:country_code":"MA",
    "gn:dem":70,
    "gn:feature_class":"P",
    "gn:feature_code":"PPL",
    "gn:name":"Oulad Chaehbi",
    "gn:population":0,
    "gn:timezone":"Africa/Casablanca",
    "iso:country":"MA",
    "wof:name":"Oulad Chaehbi",
    "wof:placetype":"locality"
},
  "geometry": {"coordinates":[-5.94555,35.13854],"type":"Point"}
}