{
  "type": "Feature",
  "properties": {
    "gn:admin1_code":"9.0",
    "gn:asciiname":"Douar Ain Oulad Jerrar",
    "gn:country_code":"MA",
    "gn:dem":361,
    "gn:feature_class":"P",
    "gn:feature_code":"PPL",
    "gn:name":"Douar Ain Oulad Jerrar",
    "gn:population":0,
    "gn:timezone":"Africa/Casablanca",
    "iso:country":"MA",
    "wof:name":"Douar Ain Oulad Jerrar",
    "wof:placetype":"locality"
},
  "geometry": {"coordinates":[-9.75136,29.57353],"type":"Point"}
}