{
  "type": "Feature",
  "properties": {
    "gn:admin1_code":"05",
    "gn:asciiname":"Tiswitiyne",
    "gn:country_code":"MA",
    "gn:dem":2167,
    "gn:feature_class":"P",
    "gn:feature_code":"PPL",
    "gn:name":"Tiswitiyne",
    "gn:population":0,
    "gn:timezone":"Africa/Casablanca",
    "iso:country":"MA",
    "name:und_x_variant":[
        "Tislouitine",
        "Tizloutine",
        "Tiswitiyne"
    ],
    "wof:name":"Tiswitiyne",
    "wof:placetype":"locality"
},
  "geometry": {"coordinates":[-7.09915,31.42673],"type":"Point"}
}