{
  "type": "Feature",
  "properties": {
    "gn:admin1_code":"02",
    "gn:asciiname":"Madrar",
    "gn:country_code":"MA",
    "gn:dem":1411,
    "gn:feature_class":"P",
    "gn:feature_code":"PPL",
    "gn:name":"Madrar",
    "gn:population":0,
    "gn:timezone":"Africa/Casablanca",
    "iso:country":"MA",
    "name:und_x_variant":[
        "Medrar"
    ],
    "wof:name":"Madrar",
    "wof:placetype":"locality"
},
  "geometry": {"coordinates":[-3.78247,32.47704],"type":"Point"}
}