{
  "type": "Feature",
  "properties": {
    "gn:admin1_code":"5.0",
    "gn:asciiname":"Ait A'ninas",
    "gn:country_code":"MA",
    "gn:dem":1856,
    "gn:feature_class":"P",
    "gn:feature_code":"PPL",
    "gn:name":"A\u00eft A\u2019ninas",
    "gn:population":0,
    "gn:timezone":"Africa/Casablanca",
    "iso:country":"MA",
    "wof:name":"Ait A'ninas",
    "wof:placetype":"locality"
},
  "geometry": {"coordinates":[-6.79438,31.60082],"type":"Point"}
}