{
  "type": "Feature",
  "properties": {
    "gn:admin1_code":"08",
    "gn:asciiname":"Tousefseddi",
    "gn:country_code":"MA",
    "gn:dem":2679,
    "gn:feature_class":"P",
    "gn:feature_code":"PPL",
    "gn:name":"Tousefseddi",
    "gn:population":0,
    "gn:timezone":"Africa/Casablanca",
    "iso:country":"MA",
    "wof:name":"Tousefseddi",
    "wof:placetype":"locality"
},
  "geometry": {"coordinates":[-5.81144,32.0906],"type":"Point"}
}