{
  "type": "Feature",
  "properties": {
    "gn:admin1_code":"9.0",
    "gn:asciiname":"Ait Issa",
    "gn:country_code":"MA",
    "gn:dem":779,
    "gn:feature_class":"P",
    "gn:feature_code":"PPL",
    "gn:name":"A\u00eft Issa",
    "gn:population":0,
    "gn:timezone":"Africa/Casablanca",
    "iso:country":"MA",
    "wof:name":"Ait Issa",
    "wof:placetype":"locality"
},
  "geometry": {"coordinates":[-9.79098,29.42901],"type":"Point"}
}