{
  "type": "Feature",
  "properties": {
    "gn:admin1_code":"09",
    "gn:admin2_code":"163.0",
    "gn:admin3_code":"416303332.0",
    "gn:asciiname":"Tanalt",
    "gn:country_code":"MA",
    "gn:dem":932,
    "gn:feature_class":"P",
    "gn:feature_code":"PPLA3",
    "gn:name":"Tanalt",
    "gn:population":0,
    "gn:timezone":"Africa/Casablanca",
    "iso:country":"MA",
    "name:ara_x_preferred":[
        "\u062a\u0646\u0627\u0644\u062a"
    ],
    "name:cat_x_preferred":[
        "Tanalt"
    ],
    "name:ceb_x_preferred":[
        "Tanalt"
    ],
    "name:fra_x_preferred":[
        "Tanalt"
    ],
    "name:ita_x_preferred":[
        "Tanalt"
    ],
    "name:swe_x_preferred":[
        "Tanalt"
    ],
    "wof:name":"Tanalt",
    "wof:placetype":"locality"
},
  "geometry": {"coordinates":[-9.16796,29.77548],"type":"Point"}
}