{
  "type": "Feature",
  "properties": {
    "gn:admin1_code":"1.0",
    "gn:asciiname":"Douar Amarich",
    "gn:country_code":"MA",
    "gn:dem":263,
    "gn:feature_class":"P",
    "gn:feature_code":"PPL",
    "gn:name":"Douar Amarich",
    "gn:population":0,
    "gn:timezone":"Africa/Casablanca",
    "iso:country":"MA",
    "wof:name":"Douar Amarich",
    "wof:placetype":"locality"
},
  "geometry": {"coordinates":[-5.54428,35.58787],"type":"Point"}
}