{
  "type": "Feature",
  "properties": {
    "gn:admin1_code":"07",
    "gn:asciiname":"Agadir Ouazeg",
    "gn:country_code":"MA",
    "gn:dem":1453,
    "gn:feature_class":"P",
    "gn:feature_code":"PPL",
    "gn:name":"Agadir Ouazeg",
    "gn:population":0,
    "gn:timezone":"Africa/Casablanca",
    "iso:country":"MA",
    "wof:name":"Agadir Ouazeg",
    "wof:placetype":"locality"
},
  "geometry": {"coordinates":[-8.64164,31.14323],"type":"Point"}
}