{
  "type": "Feature",
  "properties": {
    "gn:admin1_code":"07",
    "gn:admin2_code":"41.0",
    "gn:admin3_code":"704103012.0",
    "gn:asciiname":"Abadou",
    "gn:country_code":"MA",
    "gn:dem":1111,
    "gn:feature_class":"P",
    "gn:feature_code":"PPLA3",
    "gn:name":"Abadou",
    "gn:population":0,
    "gn:timezone":"Africa/Casablanca",
    "iso:country":"MA",
    "name:ara_x_preferred":[
        "\u0623\u0628\u0627\u062f\u0648"
    ],
    "name:azb_x_preferred":[
        "\u0622\u0628\u0627\u062f\u0648"
    ],
    "name:cat_x_preferred":[
        "Abadou"
    ],
    "name:ceb_x_preferred":[
        "Abadou"
    ],
    "name:fas_x_preferred":[
        "\u0622\u0628\u0627\u062f\u0648"
    ],
    "name:fra_x_preferred":[
        "Abadou"
    ],
    "name:ita_x_preferred":[
        "Abadou"
    ],
    "name:swe_x_preferred":[
        "Abadou"
    ],
    "name:urd_x_preferred":[
        "\u0627\u0628\u0627\u062f\u0648"
    ],
    "wof:name":"Abadou",
    "wof:placetype":"locality"
},
  "geometry": {"coordinates":[-7.31308,31.57917],"type":"Point"}
}