{
  "type": "Feature",
  "properties": {
    "gn:admin1_code":"09",
    "gn:asciiname":"Ait M'bark",
    "gn:country_code":"MA",
    "gn:dem":203,
    "gn:feature_class":"P",
    "gn:feature_code":"PPL",
    "gn:name":"A\u00eft M\u2019bark",
    "gn:population":0,
    "gn:timezone":"Africa/Casablanca",
    "iso:country":"MA",
    "name:und_x_variant":[
        "A\u00eft M\u2019bark",
        "A\u00eft Mbarek"
    ],
    "wof:name":"Ait M'bark",
    "wof:placetype":"locality"
},
  "geometry": {"coordinates":[-9.04885,30.51688],"type":"Point"}
}