{
  "type": "Feature",
  "properties": {
    "gn:admin1_code":"7.0",
    "gn:asciiname":"Idmmine",
    "gn:country_code":"MA",
    "gn:dem":227,
    "gn:feature_class":"P",
    "gn:feature_code":"PPL",
    "gn:name":"Idmmine",
    "gn:population":0,
    "gn:timezone":"Africa/Casablanca",
    "iso:country":"MA",
    "wof:name":"Idmmine",
    "wof:placetype":"locality"
},
  "geometry": {"coordinates":[-9.79069,31.19024000000001],"type":"Point"}
}