{
  "type": "Feature",
  "properties": {
    "gn:admin1_code":"06",
    "gn:asciiname":"Douar Lehialfa Laamamra",
    "gn:country_code":"MA",
    "gn:dem":180,
    "gn:feature_class":"P",
    "gn:feature_code":"PPL",
    "gn:name":"Douar Lehialfa Laamamra",
    "gn:population":0,
    "gn:timezone":"Africa/Casablanca",
    "iso:country":"MA",
    "name:und_x_variant":[
        "Douar el Helalfa"
    ],
    "wof:name":"Douar Lehialfa Laamamra",
    "wof:placetype":"locality"
},
  "geometry": {"coordinates":[-8.52932,32.59648],"type":"Point"}
}