{
  "type": "Feature",
  "properties": {
    "gn:admin1_code":"02",
    "gn:asciiname":"I-n- Haj",
    "gn:country_code":"MA",
    "gn:dem":167,
    "gn:feature_class":"P",
    "gn:feature_code":"PPL",
    "gn:name":"I-n- H\u00e2j",
    "gn:population":0,
    "gn:timezone":"Africa/Casablanca",
    "iso:country":"MA",
    "wof:name":"I-n- Haj",
    "wof:placetype":"locality"
},
  "geometry": {"coordinates":[-3.088,35.17618],"type":"Point"}
}