{
  "type": "Feature",
  "properties": {
    "gn:admin1_code":"09",
    "gn:asciiname":"Tifarwine",
    "gn:country_code":"MA",
    "gn:dem":1056,
    "gn:feature_class":"P",
    "gn:feature_code":"PPL",
    "gn:name":"Tifarwine",
    "gn:population":0,
    "gn:timezone":"Africa/Casablanca",
    "iso:country":"MA",
    "name:und_x_variant":[
        "Tiferouine"
    ],
    "wof:name":"Tifarwine",
    "wof:placetype":"locality"
},
  "geometry": {"coordinates":[-8.15423,30.5633],"type":"Point"}
}