{
  "type": "Feature",
  "properties": {
    "gn:admin1_code":"5.0",
    "gn:asciiname":"Talmouwda'at",
    "gn:country_code":"MA",
    "gn:dem":1485,
    "gn:feature_class":"P",
    "gn:feature_code":"PPL",
    "gn:name":"Talmouwda\u2019at",
    "gn:population":0,
    "gn:timezone":"Africa/Casablanca",
    "iso:country":"MA",
    "wof:name":"Talmouwda'at",
    "wof:placetype":"locality"
},
  "geometry": {"coordinates":[-6.53655,31.99322],"type":"Point"}
}