{
  "type": "Feature",
  "properties": {
    "gn:admin1_code":"4.0",
    "gn:asciiname":"Jhahfa",
    "gn:country_code":"MA",
    "gn:dem":9,
    "gn:feature_class":"P",
    "gn:feature_code":"PPL",
    "gn:name":"Jhahfa",
    "gn:population":0,
    "gn:timezone":"Africa/Casablanca",
    "iso:country":"MA",
    "wof:name":"Jhahfa",
    "wof:placetype":"locality"
},
  "geometry": {"coordinates":[-6.5263,34.35143],"type":"Point"}
}