{
  "type": "Feature",
  "properties": {
    "gn:admin1_code":"7.0",
    "gn:asciiname":"Douar Ait Said Ou Hammou",
    "gn:country_code":"MA",
    "gn:dem":167,
    "gn:feature_class":"P",
    "gn:feature_code":"PPL",
    "gn:name":"Douar Ait Said Ou Hammou",
    "gn:population":0,
    "gn:timezone":"Africa/Casablanca",
    "iso:country":"MA",
    "wof:name":"Douar Ait Said Ou Hammou",
    "wof:placetype":"locality"
},
  "geometry": {"coordinates":[-9.57573,31.44016],"type":"Point"}
}