{
  "type": "Feature",
  "properties": {
    "gn:admin1_code":"7.0",
    "gn:asciiname":"Douar Haddada",
    "gn:country_code":"MA",
    "gn:dem":424,
    "gn:feature_class":"P",
    "gn:feature_code":"PPL",
    "gn:name":"Douar Haddada",
    "gn:population":0,
    "gn:timezone":"Africa/Casablanca",
    "iso:country":"MA",
    "wof:name":"Douar Haddada",
    "wof:placetype":"locality"
},
  "geometry": {"coordinates":[-8.81126,32.10277],"type":"Point"}
}