{
  "type": "Feature",
  "properties": {
    "gn:admin1_code":"01",
    "gn:asciiname":"Douar Shene",
    "gn:country_code":"MA",
    "gn:dem":123,
    "gn:feature_class":"P",
    "gn:feature_code":"PPL",
    "gn:name":"Douar Shene",
    "gn:population":0,
    "gn:timezone":"Africa/Casablanca",
    "iso:country":"MA",
    "name:und_x_variant":[
        "Douar Sane"
    ],
    "wof:name":"Douar Shene",
    "wof:placetype":"locality"
},
  "geometry": {"coordinates":[-5.3596,35.74282],"type":"Point"}
}