{
  "type": "Feature",
  "properties": {
    "gn:admin1_code":"7.0",
    "gn:asciiname":"Ayt Sidi Ben Yich",
    "gn:country_code":"MA",
    "gn:dem":760,
    "gn:feature_class":"P",
    "gn:feature_code":"PPL",
    "gn:name":"Ayt Sidi Ben Yich",
    "gn:population":0,
    "gn:timezone":"Africa/Casablanca",
    "iso:country":"MA",
    "wof:name":"Ayt Sidi Ben Yich",
    "wof:placetype":"locality"
},
  "geometry": {"coordinates":[-7.06003,31.77962],"type":"Point"}
}