{
  "type": "Feature",
  "properties": {
    "gn:admin1_code":"9.0",
    "gn:asciiname":"Ourella",
    "gn:country_code":"MA",
    "gn:dem":502,
    "gn:feature_class":"P",
    "gn:feature_code":"PPL",
    "gn:name":"Ourella",
    "gn:population":0,
    "gn:timezone":"Africa/Casablanca",
    "iso:country":"MA",
    "wof:name":"Ourella",
    "wof:placetype":"locality"
},
  "geometry": {"coordinates":[-9.09335,30.15426],"type":"Point"}
}