{
  "type": "Feature",
  "properties": {
    "gn:admin1_code":"08",
    "gn:admin2_code":"201.0",
    "gn:admin3_code":"1320105052.0",
    "gn:asciiname":"Assoul",
    "gn:country_code":"MA",
    "gn:dem":1641,
    "gn:feature_class":"P",
    "gn:feature_code":"PPLA3",
    "gn:name":"Assoul",
    "gn:population":0,
    "gn:timezone":"Africa/Casablanca",
    "iso:country":"MA",
    "name:ara_x_preferred":[
        "\u0623\u0633\u0648\u0644"
    ],
    "name:azb_x_preferred":[
        "\u0627\u0633\u0648\u0644"
    ],
    "name:cat_x_preferred":[
        "Assoul"
    ],
    "name:ceb_x_preferred":[
        "Assoul"
    ],
    "name:fas_x_preferred":[
        "\u0627\u0633\u0648\u0644"
    ],
    "name:fra_x_preferred":[
        "Assoul"
    ],
    "name:ita_x_preferred":[
        "Assoul"
    ],
    "name:swe_x_preferred":[
        "Assoul"
    ],
    "name:und_x_variant":[
        "Assoul Ksar",
        "Assoul"
    ],
    "wof:name":"Assoul",
    "wof:placetype":"locality"
},
  "geometry": {"coordinates":[-5.20812,31.95286],"type":"Point"}
}