{
  "type": "Feature",
  "properties": {
    "gn:admin1_code":"46",
    "gn:asciiname":"Tazrout",
    "gn:country_code":"MA",
    "gn:dem":959,
    "gn:feature_class":"P",
    "gn:feature_code":"PPL",
    "gn:name":"Tazrout",
    "gn:population":0,
    "gn:timezone":"Africa/Casablanca",
    "iso:country":"MA",
    "wof:name":"Tazrout",
    "wof:placetype":"locality"
},
  "geometry": {"coordinates":[-4.48,33.88],"type":"Point"}
}