{
  "type": "Feature",
  "properties": {
    "gn:admin1_code":"08",
    "gn:asciiname":"Ait Oumghar",
    "gn:country_code":"MA",
    "gn:dem":1535,
    "gn:feature_class":"P",
    "gn:feature_code":"PPL",
    "gn:name":"A\u00eft Oumghar",
    "gn:population":0,
    "gn:timezone":"Africa/Casablanca",
    "iso:country":"MA",
    "wof:name":"Ait Oumghar",
    "wof:placetype":"locality"
},
  "geometry": {"coordinates":[-4.95431,32.67009],"type":"Point"}
}