{
  "type": "Feature",
  "properties": {
    "gn:admin1_code":"5.0",
    "gn:asciiname":"Laflalha",
    "gn:country_code":"MA",
    "gn:dem":763,
    "gn:feature_class":"P",
    "gn:feature_code":"PPL",
    "gn:name":"Laflalha",
    "gn:population":0,
    "gn:timezone":"Africa/Casablanca",
    "iso:country":"MA",
    "wof:name":"Laflalha",
    "wof:placetype":"locality"
},
  "geometry": {"coordinates":[-6.35962,32.81888],"type":"Point"}
}