{
  "type": "Feature",
  "properties": {
    "gn:admin1_code":"09",
    "gn:asciiname":"Agadir Tazghout",
    "gn:country_code":"MA",
    "gn:dem":1015,
    "gn:feature_class":"P",
    "gn:feature_code":"PPL",
    "gn:name":"Agadir Tazghout",
    "gn:population":0,
    "gn:timezone":"Africa/Casablanca",
    "iso:country":"MA",
    "name:und_x_variant":[
        "Tazrout"
    ],
    "wof:name":"Agadir Tazghout",
    "wof:placetype":"locality"
},
  "geometry": {"coordinates":[-8.8834,30.12079],"type":"Point"}
}