{
  "type": "Feature",
  "properties": {
    "gn:admin1_code":"5.0",
    "gn:asciiname":"Mlikat",
    "gn:country_code":"MA",
    "gn:dem":597,
    "gn:feature_class":"P",
    "gn:feature_code":"PPL",
    "gn:name":"Mlikat",
    "gn:population":0,
    "gn:timezone":"Africa/Casablanca",
    "iso:country":"MA",
    "wof:name":"Mlikat",
    "wof:placetype":"locality"
},
  "geometry": {"coordinates":[-6.82637,32.68037],"type":"Point"}
}