{
  "type": "Feature",
  "properties": {
    "gn:admin1_code":"7.0",
    "gn:asciiname":"Douar Abiydat",
    "gn:country_code":"MA",
    "gn:dem":182,
    "gn:feature_class":"P",
    "gn:feature_code":"PPL",
    "gn:name":"Douar Abiydat",
    "gn:population":0,
    "gn:timezone":"Africa/Casablanca",
    "iso:country":"MA",
    "wof:name":"Douar Abiydat",
    "wof:placetype":"locality"
},
  "geometry": {"coordinates":[-8.96203,32.20773],"type":"Point"}
}