{
  "type": "Feature",
  "properties": {
    "gn:admin1_code":"07",
    "gn:asciiname":"Tagantane",
    "gn:country_code":"MA",
    "gn:dem":735,
    "gn:feature_class":"P",
    "gn:feature_code":"PPL",
    "gn:name":"Tagantane",
    "gn:population":0,
    "gn:timezone":"Africa/Casablanca",
    "iso:country":"MA",
    "name:und_x_variant":[
        "Taguentane"
    ],
    "wof:name":"Tagantane",
    "wof:placetype":"locality"
},
  "geometry": {"coordinates":[-8.76817,31.22162],"type":"Point"}
}