{
  "type": "Feature",
  "properties": {
    "gn:admin1_code":"1.0",
    "gn:asciiname":"Katsou",
    "gn:country_code":"MA",
    "gn:dem":42,
    "gn:feature_class":"P",
    "gn:feature_code":"PPL",
    "gn:name":"Katsou",
    "gn:population":0,
    "gn:timezone":"Africa/Casablanca",
    "iso:country":"MA",
    "wof:name":"Katsou",
    "wof:placetype":"locality"
},
  "geometry": {"coordinates":[-5.4528,35.54677],"type":"Point"}
}