{
  "type": "Feature",
  "properties": {
    "gn:admin1_code":"7.0",
    "gn:asciiname":"Zouitat",
    "gn:country_code":"MA",
    "gn:dem":290,
    "gn:feature_class":"P",
    "gn:feature_code":"PPL",
    "gn:name":"Zouitat",
    "gn:population":0,
    "gn:timezone":"Africa/Casablanca",
    "iso:country":"MA",
    "wof:name":"Zouitat",
    "wof:placetype":"locality"
},
  "geometry": {"coordinates":[-7.42207,32.43744],"type":"Point"}
}