{
  "type": "Feature",
  "properties": {
    "gn:admin1_code":"01",
    "gn:asciiname":"Ahadoune",
    "gn:country_code":"MA",
    "gn:dem":501,
    "gn:feature_class":"P",
    "gn:feature_code":"PPL",
    "gn:name":"Ahadoune",
    "gn:population":0,
    "gn:timezone":"Africa/Casablanca",
    "iso:country":"MA",
    "name:und_x_variant":[
        "Afechtal"
    ],
    "wof:name":"Ahadoune",
    "wof:placetype":"locality"
},
  "geometry": {"coordinates":[-5.2342,35.38187],"type":"Point"}
}