{
  "type": "Feature",
  "properties": {
    "gn:admin1_code":"10",
    "gn:asciiname":"Id Bakrim",
    "gn:country_code":"MA",
    "gn:dem":1162,
    "gn:feature_class":"P",
    "gn:feature_code":"PPL",
    "gn:name":"Id Bakrim",
    "gn:population":0,
    "gn:timezone":"Africa/Casablanca",
    "iso:country":"MA",
    "wof:name":"Id Bakrim",
    "wof:placetype":"locality"
},
  "geometry": {"coordinates":[-9.45128,29.38296],"type":"Point"}
}