{
  "type": "Feature",
  "properties": {
    "gn:admin1_code":"04",
    "gn:asciiname":"Douar Maarif",
    "gn:country_code":"MA",
    "gn:dem":103,
    "gn:feature_class":"P",
    "gn:feature_code":"PPL",
    "gn:name":"Douar Maarif",
    "gn:population":0,
    "gn:timezone":"Africa/Casablanca",
    "iso:country":"MA",
    "name:und_x_variant":[
        "El Ma\u00e2rif A\u00efn Karouache",
        "Maarif Ben Karrouch",
        "Douar Maarif"
    ],
    "wof:name":"Douar Maarif",
    "wof:placetype":"locality"
},
  "geometry": {"coordinates":[-5.44857,34.50963],"type":"Point"}
}