{
  "type": "Feature",
  "properties": {
    "gn:admin1_code":"7.0",
    "gn:asciiname":"Ait Ali el Malik",
    "gn:country_code":"MA",
    "gn:dem":1327,
    "gn:feature_class":"P",
    "gn:feature_code":"PPL",
    "gn:name":"A\u00eft Ali el Malik",
    "gn:population":0,
    "gn:timezone":"Africa/Casablanca",
    "iso:country":"MA",
    "wof:name":"Ait Ali el Malik",
    "wof:placetype":"locality"
},
  "geometry": {"coordinates":[-9.21649,30.8842],"type":"Point"}
}