{
  "type": "Feature",
  "properties": {
    "gn:admin1_code":"03",
    "gn:asciiname":"Douar Ouled Abdh. Moussa",
    "gn:country_code":"MA",
    "gn:dem":586,
    "gn:feature_class":"P",
    "gn:feature_code":"PPL",
    "gn:name":"Douar Ouled Abdh. Moussa",
    "gn:population":0,
    "gn:timezone":"Africa/Casablanca",
    "iso:country":"MA",
    "name:und_x_variant":[
        "Douar Ouled Abdallah Moussa",
        "Oulad Abdallah Moussa",
        "Douar Ouled Abdh. Moussa"
    ],
    "wof:name":"Douar Ouled Abdh. Moussa",
    "wof:placetype":"locality"
},
  "geometry": {"coordinates":[-4.18483,34.33711],"type":"Point"}
}