{
  "type": "Feature",
  "properties": {
    "gn:admin1_code":"07",
    "gn:asciiname":"Al Mhamid",
    "gn:country_code":"MA",
    "gn:dem":480,
    "gn:feature_class":"P",
    "gn:feature_code":"PPL",
    "gn:name":"Al Mhamid",
    "gn:population":0,
    "gn:timezone":"Africa/Casablanca",
    "iso:country":"MA",
    "name:und_x_variant":[
        "Douar el Mahmid",
        "Hbl Hmid",
        "El Mahmid",
        "Al Mhamid"
    ],
    "wof:name":"Al Mhamid",
    "wof:placetype":"locality"
},
  "geometry": {"coordinates":[-8.03922,31.59163],"type":"Point"}
}