{
  "type": "Feature",
  "properties": {
    "gn:admin1_code":"01",
    "gn:asciiname":"Mazoura",
    "gn:country_code":"MA",
    "gn:dem":528,
    "gn:feature_class":"P",
    "gn:feature_code":"PPL",
    "gn:name":"Mazoura",
    "gn:population":0,
    "gn:timezone":"Africa/Casablanca",
    "iso:country":"MA",
    "name:und_x_variant":[
        "Majoura",
        "Mazoura"
    ],
    "wof:name":"Mazoura",
    "wof:placetype":"locality"
},
  "geometry": {"coordinates":[-5.42284,34.79017],"type":"Point"}
}