{
  "type": "Feature",
  "properties": {
    "gn:admin1_code":"7.0",
    "gn:asciiname":"Douar Lhkarba",
    "gn:country_code":"MA",
    "gn:dem":506,
    "gn:feature_class":"P",
    "gn:feature_code":"PPL",
    "gn:name":"Douar Lhkarba",
    "gn:population":0,
    "gn:timezone":"Africa/Casablanca",
    "iso:country":"MA",
    "wof:name":"Douar Lhkarba",
    "wof:placetype":"locality"
},
  "geometry": {"coordinates":[-8.29707,32.11384],"type":"Point"}
}