{
  "type": "Feature",
  "properties": {
    "gn:admin1_code":"7.0",
    "gn:asciiname":"Douar Oulad Abdellah",
    "gn:country_code":"MA",
    "gn:dem":471,
    "gn:feature_class":"P",
    "gn:feature_code":"PPL",
    "gn:name":"Douar Oulad Abdellah",
    "gn:population":0,
    "gn:timezone":"Africa/Casablanca",
    "iso:country":"MA",
    "wof:name":"Douar Oulad Abdellah",
    "wof:placetype":"locality"
},
  "geometry": {"coordinates":[-7.89016,32.43532],"type":"Point"}
}