{
  "type": "Feature",
  "properties": {
    "gn:admin1_code":"09",
    "gn:asciiname":"Ait Talab Boubkar",
    "gn:country_code":"MA",
    "gn:dem":1731,
    "gn:feature_class":"P",
    "gn:feature_code":"PPL",
    "gn:name":"A\u00eft Talab Boubkar",
    "gn:population":0,
    "gn:timezone":"Africa/Casablanca",
    "iso:country":"MA",
    "name:und_x_variant":[
        "A\u00eft Talab Boubkar",
        "A\u00eft Taleb"
    ],
    "wof:name":"Ait Talab Boubkar",
    "wof:placetype":"locality"
},
  "geometry": {"coordinates":[-8.55028,30.03759],"type":"Point"}
}