{
  "type": "Feature",
  "properties": {
    "gn:admin1_code":"2.0",
    "gn:asciiname":"Belhoua",
    "gn:country_code":"MA",
    "gn:dem":1066,
    "gn:feature_class":"P",
    "gn:feature_code":"PPLL",
    "gn:name":"Belhoua",
    "gn:population":0,
    "gn:timezone":"Africa/Casablanca",
    "iso:country":"MA",
    "wof:name":"Belhoua",
    "wof:placetype":"locality"
},
  "geometry": {"coordinates":[-1.85,34.50510999999999],"type":"Point"}
}