{
  "type": "Feature",
  "properties": {
    "gn:admin1_code":"01",
    "gn:asciiname":"Douar Sidi Bouafif",
    "gn:country_code":"MA",
    "gn:dem":26,
    "gn:feature_class":"P",
    "gn:feature_code":"PPL",
    "gn:name":"Douar Sidi Bouafif",
    "gn:population":0,
    "gn:timezone":"Africa/Casablanca",
    "iso:country":"MA",
    "wof:name":"Douar Sidi Bouafif",
    "wof:placetype":"locality"
},
  "geometry": {"coordinates":[-3.86732,35.17244],"type":"Point"}
}