{
  "type": "Feature",
  "properties": {
    "gn:admin1_code":"7.0",
    "gn:asciiname":"Sidi Boudahliya",
    "gn:country_code":"MA",
    "gn:dem":488,
    "gn:feature_class":"P",
    "gn:feature_code":"PPL",
    "gn:name":"Sidi Boudahliya",
    "gn:population":0,
    "gn:timezone":"Africa/Casablanca",
    "iso:country":"MA",
    "wof:name":"Sidi Boudahliya",
    "wof:placetype":"locality"
},
  "geometry": {"coordinates":[-7.81796,31.632],"type":"Point"}
}