{
  "type": "Feature",
  "properties": {
    "gn:country":"MA",
    "gn:fcode":"ADM3",
    "gn:pop":6740,
    "iso:country":"MA",
    "name:ara_x_preferred":[
        "\u062a\u0628\u0627\u0646\u062a"
    ],
    "name:fra_x_preferred":[
        "Ait Blal"
    ],
    "name:fra_x_variant":[
        "Ait Blal (CR)",
        "Ait Blal (Commune Rurale)"
    ],
    "qs:name":"Ait Blal",
    "qs:photos_9r":0,
    "qs:photos_sr":0,
    "qs:pop_sr":"5",
    "wd:wordcount":60,
    "wof:name":"Ait Blal",
    "wof:placetype":"localadmin",
    "wof:population":6740
},
  "geometry": {"coordinates":[-6.70048,31.68533],"type":"Point"}
}