{
  "type": "Feature",
  "properties": {
    "gn:admin1_code":"6.0",
    "gn:asciiname":"Douar Qouabaa",
    "gn:country_code":"MA",
    "gn:dem":516,
    "gn:feature_class":"P",
    "gn:feature_code":"PPL",
    "gn:name":"Douar Qouabaa",
    "gn:population":0,
    "gn:timezone":"Africa/Casablanca",
    "iso:country":"MA",
    "wof:name":"Douar Qouabaa",
    "wof:placetype":"locality"
},
  "geometry": {"coordinates":[-7.40494,32.70115],"type":"Point"}
}