{
  "type": "Feature",
  "properties": {
    "gn:admin1_code":"7.0",
    "gn:asciiname":"Douar Machmach",
    "gn:country_code":"MA",
    "gn:dem":518,
    "gn:feature_class":"P",
    "gn:feature_code":"PPL",
    "gn:name":"Douar Machmach",
    "gn:population":0,
    "gn:timezone":"Africa/Casablanca",
    "iso:country":"MA",
    "wof:name":"Douar Machmach",
    "wof:placetype":"locality"
},
  "geometry": {"coordinates":[-7.75183,31.64904000000001],"type":"Point"}
}