{
  "type": "Feature",
  "properties": {
    "gn:admin1_code":"1.0",
    "gn:asciiname":"Lammamna",
    "gn:country_code":"MA",
    "gn:dem":60,
    "gn:feature_class":"P",
    "gn:feature_code":"PPL",
    "gn:name":"Lammamna",
    "gn:population":0,
    "gn:timezone":"Africa/Casablanca",
    "iso:country":"MA",
    "wof:name":"Lammamna",
    "wof:placetype":"locality"
},
  "geometry": {"coordinates":[-6.07404,35.0143],"type":"Point"}
}