{
  "type": "Feature",
  "properties": {
    "gn:admin1_code":"06",
    "gn:asciiname":"Dar Sidi Bou Ch'ayb Ben 'Abdallah",
    "gn:country_code":"MA",
    "gn:dem":580,
    "gn:feature_class":"P",
    "gn:feature_code":"PPL",
    "gn:name":"Dar Sidi Bou Ch\u2019ayb Ben \u2019Abdallah",
    "gn:population":0,
    "gn:timezone":"Africa/Casablanca",
    "iso:country":"MA",
    "name:und_x_variant":[
        "Douar Sidi bou Cha\u00efb ben Abdallah",
        "Dar Sidi Ben Cha\u00efb Ben Abdallah",
        "Dar Sidi Bou Ch\u2019ayb Ben \u2019Abdallah"
    ],
    "wof:name":"Dar Sidi Bou Ch'ayb Ben 'Abdallah",
    "wof:placetype":"locality"
},
  "geometry": {"coordinates":[-7.41278,32.96131],"type":"Point"}
}