{
  "type": "Feature",
  "properties": {
    "gn:admin1_code":"7.0",
    "gn:asciiname":"Id Oumejjoud",
    "gn:country_code":"MA",
    "gn:dem":465,
    "gn:feature_class":"P",
    "gn:feature_code":"PPL",
    "gn:name":"Id Oumejjoud",
    "gn:population":0,
    "gn:timezone":"Africa/Casablanca",
    "iso:country":"MA",
    "wof:name":"Id Oumejjoud",
    "wof:placetype":"locality"
},
  "geometry": {"coordinates":[-9.70107,31.15207],"type":"Point"}
}