{
  "type": "Feature",
  "properties": {
    "gn:admin1_code":"1.0",
    "gn:asciiname":"Hay Chaayb",
    "gn:country_code":"MA",
    "gn:dem":310,
    "gn:feature_class":"P",
    "gn:feature_code":"PPL",
    "gn:name":"Hay Chaayb",
    "gn:population":0,
    "gn:timezone":"Africa/Casablanca",
    "iso:country":"MA",
    "wof:name":"Hay Chaayb",
    "wof:placetype":"locality"
},
  "geometry": {"coordinates":[-5.60994,34.87863],"type":"Point"}
}