{
  "type": "Feature",
  "properties": {
    "gn:admin1_code":"8.0",
    "gn:asciiname":"Timgualt",
    "gn:country_code":"MA",
    "gn:dem":1881,
    "gn:feature_class":"P",
    "gn:feature_code":"PPL",
    "gn:name":"Timgualt",
    "gn:population":0,
    "gn:timezone":"Africa/Casablanca",
    "iso:country":"MA",
    "wof:name":"Timgualt",
    "wof:placetype":"locality"
},
  "geometry": {"coordinates":[-7.60536,30.40711],"type":"Point"}
}