{
  "type": "Feature",
  "properties": {
    "gn:admin1_code":"1.0",
    "gn:asciiname":"Douar Louadiyine",
    "gn:country_code":"MA",
    "gn:dem":466,
    "gn:feature_class":"P",
    "gn:feature_code":"PPL",
    "gn:name":"Douar Louadiyine",
    "gn:population":0,
    "gn:timezone":"Africa/Casablanca",
    "iso:country":"MA",
    "wof:name":"Douar Louadiyine",
    "wof:placetype":"locality"
},
  "geometry": {"coordinates":[-5.51039,34.91091],"type":"Point"}
}