{
  "type": "Feature",
  "properties": {
    "gn:admin1_code":"08",
    "gn:asciiname":"Talialit",
    "gn:country_code":"MA",
    "gn:dem":1633,
    "gn:feature_class":"P",
    "gn:feature_code":"PPL",
    "gn:name":"Talialit",
    "gn:population":0,
    "gn:timezone":"Africa/Casablanca",
    "iso:country":"MA",
    "name:und_x_variant":[
        "Tallalit",
        "Kasba Tilialit"
    ],
    "wof:name":"Talialit",
    "wof:placetype":"locality"
},
  "geometry": {"coordinates":[-4.87285,33.02478],"type":"Point"}
}