{
  "type": "Feature",
  "properties": {
    "gn:admin1_code":"7.0",
    "gn:asciiname":"Dar Bel Haj",
    "gn:country_code":"MA",
    "gn:dem":203,
    "gn:feature_class":"P",
    "gn:feature_code":"PPL",
    "gn:name":"Dar Bel Haj",
    "gn:population":0,
    "gn:timezone":"Africa/Casablanca",
    "iso:country":"MA",
    "wof:name":"Dar Bel Haj",
    "wof:placetype":"locality"
},
  "geometry": {"coordinates":[-8.84964,32.22317],"type":"Point"}
}