{
  "type": "Feature",
  "properties": {
    "gn:admin1_code":"1.0",
    "gn:asciiname":"Dar Massaoud",
    "gn:country_code":"MA",
    "gn:dem":490,
    "gn:feature_class":"P",
    "gn:feature_code":"PPL",
    "gn:name":"Dar Massaoud",
    "gn:population":0,
    "gn:timezone":"Africa/Casablanca",
    "iso:country":"MA",
    "wof:name":"Dar Massaoud",
    "wof:placetype":"locality"
},
  "geometry": {"coordinates":[-4.06644,35.07334],"type":"Point"}
}