{
  "type": "Feature",
  "properties": {
    "gn:admin1_code":"7.0",
    "gn:asciiname":"Douar Oulad El Haj Omar",
    "gn:country_code":"MA",
    "gn:dem":253,
    "gn:feature_class":"P",
    "gn:feature_code":"PPL",
    "gn:name":"Douar Oulad El Haj Omar",
    "gn:population":0,
    "gn:timezone":"Africa/Casablanca",
    "iso:country":"MA",
    "wof:name":"Douar Oulad El Haj Omar",
    "wof:placetype":"locality"
},
  "geometry": {"coordinates":[-9.11715,32.03307],"type":"Point"}
}