{
  "type": "Feature",
  "properties": {
    "gn:admin1_code":"4.0",
    "gn:asciiname":"Laayayda Oulad Mimoun I",
    "gn:country_code":"MA",
    "gn:dem":397,
    "gn:feature_class":"P",
    "gn:feature_code":"PPL",
    "gn:name":"Laayayda Oulad Mimoun I",
    "gn:population":0,
    "gn:timezone":"Africa/Casablanca",
    "iso:country":"MA",
    "wof:name":"Laayayda Oulad Mimoun I",
    "wof:placetype":"locality"
},
  "geometry": {"coordinates":[-6.59983,33.70350999999999],"type":"Point"}
}