{
  "type": "Feature",
  "properties": {
    "gn:admin1_code":"03",
    "gn:asciiname":"Douar Oulad El Haouari",
    "gn:country_code":"MA",
    "gn:dem":494,
    "gn:feature_class":"P",
    "gn:feature_code":"PPL",
    "gn:name":"Douar Oulad El Haouari",
    "gn:population":0,
    "gn:timezone":"Africa/Casablanca",
    "iso:country":"MA",
    "wof:name":"Douar Oulad El Haouari",
    "wof:placetype":"locality"
},
  "geometry": {"coordinates":[-4.98873,33.96921],"type":"Point"}
}