{
  "type": "Feature",
  "properties": {
    "gn:admin1_code":"9.0",
    "gn:asciiname":"Ahgral",
    "gn:country_code":"MA",
    "gn:dem":1228,
    "gn:feature_class":"P",
    "gn:feature_code":"PPL",
    "gn:name":"Ahgral",
    "gn:population":0,
    "gn:timezone":"Africa/Casablanca",
    "iso:country":"MA",
    "wof:name":"Ahgral",
    "wof:placetype":"locality"
},
  "geometry": {"coordinates":[-9.18086,29.64364],"type":"Point"}
}