{
  "type": "Feature",
  "properties": {
    "gn:admin1_code":"01",
    "gn:asciiname":"Douar Ifdissene",
    "gn:country_code":"MA",
    "gn:dem":45,
    "gn:feature_class":"P",
    "gn:feature_code":"PPL",
    "gn:name":"Douar Ifdissene",
    "gn:population":0,
    "gn:timezone":"Africa/Casablanca",
    "iso:country":"MA",
    "wof:name":"Douar Ifdissene",
    "wof:placetype":"locality"
},
  "geometry": {"coordinates":[-3.82581,35.1514],"type":"Point"}
}