{
  "type": "Feature",
  "properties": {
    "gn:admin1_code":"07",
    "gn:asciiname":"Tagoudacht",
    "gn:country_code":"MA",
    "gn:dem":1126,
    "gn:feature_class":"P",
    "gn:feature_code":"PPL",
    "gn:name":"Tagoudacht",
    "gn:population":0,
    "gn:timezone":"Africa/Casablanca",
    "iso:country":"MA",
    "name:und_x_variant":[
        "Tagdachte",
        "Tagacht",
        "Tagoudacht"
    ],
    "wof:name":"Tagoudacht",
    "wof:placetype":"locality"
},
  "geometry": {"coordinates":[-9.1998,31.07924],"type":"Point"}
}