{
  "type": "Feature",
  "properties": {
    "gn:admin1_code":"9.0",
    "gn:asciiname":"Ait Jloun",
    "gn:country_code":"MA",
    "gn:dem":686,
    "gn:feature_class":"P",
    "gn:feature_code":"PPL",
    "gn:name":"A\u00eft Jloun",
    "gn:population":0,
    "gn:timezone":"Africa/Casablanca",
    "iso:country":"MA",
    "wof:name":"Ait Jloun",
    "wof:placetype":"locality"
},
  "geometry": {"coordinates":[-9.04809,30.14229000000001],"type":"Point"}
}