{
  "type": "Feature",
  "properties": {
    "gn:admin1_code":"04",
    "gn:asciiname":"Oulad Abdallah",
    "gn:country_code":"MA",
    "gn:dem":16,
    "gn:feature_class":"P",
    "gn:feature_code":"PPL",
    "gn:name":"Oulad Abdallah",
    "gn:population":0,
    "gn:timezone":"Africa/Casablanca",
    "iso:country":"MA",
    "name:und_x_variant":[
        "Douar Oulad Abdallah",
        "Ouled Abdellah",
        "Oulad Abdallah"
    ],
    "wof:name":"Oulad Abdallah",
    "wof:placetype":"locality"
},
  "geometry": {"coordinates":[-6.06678,34.68367],"type":"Point"}
}