{
  "type": "Feature",
  "properties": {
    "gn:admin1_code":"9.0",
    "gn:asciiname":"Id ou Hadar",
    "gn:country_code":"MA",
    "gn:dem":607,
    "gn:feature_class":"P",
    "gn:feature_code":"PPL",
    "gn:name":"Id ou Hadar",
    "gn:population":0,
    "gn:timezone":"Africa/Casablanca",
    "iso:country":"MA",
    "wof:name":"Id ou Hadar",
    "wof:placetype":"locality"
},
  "geometry": {"coordinates":[-9.8667,29.48297],"type":"Point"}
}