{
  "type": "Feature",
  "properties": {
    "gn:admin1_code":"07",
    "gn:asciiname":"Taballet",
    "gn:country_code":"MA",
    "gn:dem":1388,
    "gn:feature_class":"P",
    "gn:feature_code":"PPL",
    "gn:name":"Taballet",
    "gn:population":0,
    "gn:timezone":"Africa/Casablanca",
    "iso:country":"MA",
    "wof:name":"Taballet",
    "wof:placetype":"locality"
},
  "geometry": {"coordinates":[-9.18605,30.8299],"type":"Point"}
}