{
  "type": "Feature",
  "properties": {
    "gn:admin1_code":"7.0",
    "gn:asciiname":"Dar El Haqini Miloud",
    "gn:country_code":"MA",
    "gn:dem":373,
    "gn:feature_class":"P",
    "gn:feature_code":"PPL",
    "gn:name":"Dar El Haqini Miloud",
    "gn:population":0,
    "gn:timezone":"Africa/Casablanca",
    "iso:country":"MA",
    "wof:name":"Dar El Haqini Miloud",
    "wof:placetype":"locality"
},
  "geometry": {"coordinates":[-8.43894,31.61274],"type":"Point"}
}