{
  "type": "Feature",
  "properties": {
    "gn:admin1_code":"7.0",
    "gn:asciiname":"Laarab",
    "gn:country_code":"MA",
    "gn:dem":313,
    "gn:feature_class":"P",
    "gn:feature_code":"PPL",
    "gn:name":"Laarab",
    "gn:population":0,
    "gn:timezone":"Africa/Casablanca",
    "iso:country":"MA",
    "wof:name":"Laarab",
    "wof:placetype":"locality"
},
  "geometry": {"coordinates":[-9.00306,31.89333],"type":"Point"}
}