{
  "type": "Feature",
  "properties": {
    "gn:admin1_code":"01",
    "gn:asciiname":"Douar Iberranene",
    "gn:country_code":"MA",
    "gn:dem":596,
    "gn:feature_class":"P",
    "gn:feature_code":"PPL",
    "gn:name":"Douar Iberranene",
    "gn:population":0,
    "gn:timezone":"Africa/Casablanca",
    "iso:country":"MA",
    "name:und_x_variant":[
        "Ibarhouna",
        "Ibranene",
        "Ibarhonen",
        "Ibarhonene",
        "Ibr\u00e2nene",
        "Abranane",
        "Douar Iberranene"
    ],
    "wof:name":"Douar Iberranene",
    "wof:placetype":"locality"
},
  "geometry": {"coordinates":[-4.3837,35.03272],"type":"Point"}
}