{
  "type": "Feature",
  "properties": {
    "gn:admin1_code":"05",
    "gn:asciiname":"Tizart",
    "gn:country_code":"MA",
    "gn:dem":1309,
    "gn:feature_class":"P",
    "gn:feature_code":"PPL",
    "gn:name":"Tizart",
    "gn:population":0,
    "gn:timezone":"Africa/Casablanca",
    "iso:country":"MA",
    "name:und_x_variant":[
        "Tazirte",
        "Tizzert",
        "Tizart"
    ],
    "wof:name":"Tizart",
    "wof:placetype":"locality"
},
  "geometry": {"coordinates":[-7.04535,31.48814],"type":"Point"}
}