{
  "type": "Feature",
  "properties": {
    "gn:admin1_code":"1.0",
    "gn:asciiname":"Raoudet Nsara",
    "gn:country_code":"MA",
    "gn:dem":217,
    "gn:feature_class":"P",
    "gn:feature_code":"PPL",
    "gn:name":"Raoudet Nsara",
    "gn:population":0,
    "gn:timezone":"Africa/Casablanca",
    "iso:country":"MA",
    "wof:name":"Raoudet Nsara",
    "wof:placetype":"locality"
},
  "geometry": {"coordinates":[-5.67411,35.81507],"type":"Point"}
}