{
  "type": "Feature",
  "properties": {
    "gn:admin1_code":"10.0",
    "gn:asciiname":"Id Al 'Asri",
    "gn:country_code":"MA",
    "gn:dem":440,
    "gn:feature_class":"P",
    "gn:feature_code":"PPL",
    "gn:name":"Id Al \u2019Asri",
    "gn:population":0,
    "gn:timezone":"Africa/Casablanca",
    "iso:country":"MA",
    "wof:name":"Id Al 'Asri",
    "wof:placetype":"locality"
},
  "geometry": {"coordinates":[-9.9037,29.45737],"type":"Point"}
}