{
  "type": "Feature",
  "properties": {
    "gn:admin1_code":"6.0",
    "gn:asciiname":"Oulad El Ghezouani",
    "gn:country_code":"MA",
    "gn:dem":220,
    "gn:feature_class":"P",
    "gn:feature_code":"PPL",
    "gn:name":"Oulad El Ghezouani",
    "gn:population":0,
    "gn:timezone":"Africa/Casablanca",
    "iso:country":"MA",
    "wof:name":"Oulad El Ghezouani",
    "wof:placetype":"locality"
},
  "geometry": {"coordinates":[-8.45711,32.49001],"type":"Point"}
}