{
  "type": "Feature",
  "properties": {
    "gn:admin1_code":"1.0",
    "gn:asciiname":"Hounat Essedra Lmahrouqa",
    "gn:country_code":"MA",
    "gn:dem":289,
    "gn:feature_class":"P",
    "gn:feature_code":"PPL",
    "gn:name":"Hounat Essedra Lmahrouqa",
    "gn:population":0,
    "gn:timezone":"Africa/Casablanca",
    "iso:country":"MA",
    "wof:name":"Hounat Essedra Lmahrouqa",
    "wof:placetype":"locality"
},
  "geometry": {"coordinates":[-5.39994,34.65068],"type":"Point"}
}