{
  "type": "Feature",
  "properties": {
    "gn:admin1_code":"07",
    "gn:asciiname":"Alaouzadn",
    "gn:country_code":"MA",
    "gn:dem":527,
    "gn:feature_class":"P",
    "gn:feature_code":"PPL",
    "gn:name":"Alaouzadn",
    "gn:population":0,
    "gn:timezone":"Africa/Casablanca",
    "iso:country":"MA",
    "name:und_x_variant":[
        "Ahl Zoun"
    ],
    "wof:name":"Alaouzadn",
    "wof:placetype":"locality"
},
  "geometry": {"coordinates":[-9.51921,30.90972],"type":"Point"}
}