{
  "type": "Feature",
  "properties": {
    "gn:admin1_code":"9.0",
    "gn:asciiname":"Zragfa",
    "gn:country_code":"MA",
    "gn:dem":158,
    "gn:feature_class":"P",
    "gn:feature_code":"PPL",
    "gn:name":"Zragfa",
    "gn:population":0,
    "gn:timezone":"Africa/Casablanca",
    "iso:country":"MA",
    "wof:name":"Zragfa",
    "wof:placetype":"locality"
},
  "geometry": {"coordinates":[-9.24487,30.29501],"type":"Point"}
}