{
  "type": "Feature",
  "properties": {
    "gn:admin1_code":"3.0",
    "gn:asciiname":"Douar Ait Laari Azegraf",
    "gn:country_code":"MA",
    "gn:dem":1035,
    "gn:feature_class":"P",
    "gn:feature_code":"PPL",
    "gn:name":"Douar Ait Laari Azegraf",
    "gn:population":0,
    "gn:timezone":"Africa/Casablanca",
    "iso:country":"MA",
    "wof:name":"Douar Ait Laari Azegraf",
    "wof:placetype":"locality"
},
  "geometry": {"coordinates":[-4.01117,34.02762],"type":"Point"}
}