{
  "type": "Feature",
  "properties": {
    "gn:admin1_code":"1.0",
    "gn:asciiname":"Douar Ain Sittenne",
    "gn:country_code":"MA",
    "gn:dem":870,
    "gn:feature_class":"P",
    "gn:feature_code":"PPL",
    "gn:name":"Douar Ain Sittenne",
    "gn:population":0,
    "gn:timezone":"Africa/Casablanca",
    "iso:country":"MA",
    "wof:name":"Douar Ain Sittenne",
    "wof:placetype":"locality"
},
  "geometry": {"coordinates":[-5.41411,35.16774],"type":"Point"}
}