{
  "type": "Feature",
  "properties": {
    "gn:admin1_code":"01",
    "gn:asciiname":"Souani",
    "gn:country_code":"MA",
    "gn:dem":6,
    "gn:feature_class":"P",
    "gn:feature_code":"PPL",
    "gn:name":"Souani",
    "gn:population":0,
    "gn:timezone":"Africa/Casablanca",
    "iso:country":"MA",
    "name:ara_x_preferred":[
        "\u0627\u0644\u0633\u0648\u0627\u0646\u064a"
    ],
    "name:azb_x_preferred":[
        "\u0633\u0648\u0627\u0646\u06cc"
    ],
    "name:fas_x_preferred":[
        "\u0633\u0648\u0627\u0646\u06cc"
    ],
    "name:fra_x_preferred":[
        "Souani"
    ],
    "name:ita_x_preferred":[
        "Souani"
    ],
    "name:msa_x_preferred":[
        "Souani"
    ],
    "name:pol_x_preferred":[
        "As-Sawani"
    ],
    "name:por_x_preferred":[
        "Souani"
    ],
    "name:ron_x_preferred":[
        "Souani"
    ],
    "name:spa_x_preferred":[
        "Souani"
    ],
    "name:vie_x_preferred":[
        "Souani"
    ],
    "wof:name":"Souani",
    "wof:placetype":"locality"
},
  "geometry": {"coordinates":[-3.85086,35.19095],"type":"Point"}
}