{
  "type": "Feature",
  "properties": {
    "gn:admin1_code":"07",
    "gn:asciiname":"Ougdalene",
    "gn:country_code":"MA",
    "gn:dem":2433,
    "gn:feature_class":"P",
    "gn:feature_code":"PPL",
    "gn:name":"Ougdalene",
    "gn:population":0,
    "gn:timezone":"Africa/Casablanca",
    "iso:country":"MA",
    "name:und_x_variant":[
        "Ougdal\u00e8n",
        "Ougdalene"
    ],
    "wof:name":"Ougdalene",
    "wof:placetype":"locality"
},
  "geometry": {"coordinates":[-8.76,30.88],"type":"Point"}
}