{
  "type": "Feature",
  "properties": {
    "gn:admin1_code":"6.0",
    "gn:asciiname":"Douar Bdaouat",
    "gn:country_code":"MA",
    "gn:dem":637,
    "gn:feature_class":"P",
    "gn:feature_code":"PPL",
    "gn:name":"Douar Bdaouat",
    "gn:population":0,
    "gn:timezone":"Africa/Casablanca",
    "iso:country":"MA",
    "wof:name":"Douar Bdaouat",
    "wof:placetype":"locality"
},
  "geometry": {"coordinates":[-7.23117,33.07659],"type":"Point"}
}