{
  "type": "Feature",
  "properties": {
    "gn:admin1_code":"7.0",
    "gn:asciiname":"Dar Loussou",
    "gn:country_code":"MA",
    "gn:dem":339,
    "gn:feature_class":"P",
    "gn:feature_code":"PPL",
    "gn:name":"Dar Loussou",
    "gn:population":0,
    "gn:timezone":"Africa/Casablanca",
    "iso:country":"MA",
    "wof:name":"Dar Loussou",
    "wof:placetype":"locality"
},
  "geometry": {"coordinates":[-8.74618,31.56544],"type":"Point"}
}