{
  "type": "Feature",
  "properties": {
    "gn:admin1_code":"6.0",
    "gn:asciiname":"Khyam Oulad Chtoula",
    "gn:country_code":"MA",
    "gn:dem":322,
    "gn:feature_class":"P",
    "gn:feature_code":"PPL",
    "gn:name":"Khyam Oulad Chtoula",
    "gn:population":0,
    "gn:timezone":"Africa/Casablanca",
    "iso:country":"MA",
    "wof:name":"Khyam Oulad Chtoula",
    "wof:placetype":"locality"
},
  "geometry": {"coordinates":[-8.21082,32.55035],"type":"Point"}
}