{
  "type": "Feature",
  "properties": {
    "gn:admin1_code":"09",
    "gn:asciiname":"Bou Khechba",
    "gn:country_code":"MA",
    "gn:dem":178,
    "gn:feature_class":"P",
    "gn:feature_code":"PPL",
    "gn:name":"Bou Khechba",
    "gn:population":0,
    "gn:timezone":"Africa/Casablanca",
    "iso:country":"MA",
    "name:und_x_variant":[
        "Boukhchela",
        "Bou Khechba"
    ],
    "wof:name":"Bou Khechba",
    "wof:placetype":"locality"
},
  "geometry": {"coordinates":[-9.08687,30.31592],"type":"Point"}
}