{
  "type": "Feature",
  "properties": {
    "gn:admin1_code":"08",
    "gn:asciiname":"Moumarigh",
    "gn:country_code":"MA",
    "gn:dem":1695,
    "gn:feature_class":"P",
    "gn:feature_code":"PPL",
    "gn:name":"Moumarigh",
    "gn:population":0,
    "gn:timezone":"Africa/Casablanca",
    "iso:country":"MA",
    "name:und_x_variant":[
        "Moumarirh",
        "Moumarigh"
    ],
    "wof:name":"Moumarigh",
    "wof:placetype":"locality"
},
  "geometry": {"coordinates":[-5.78111,31.25264],"type":"Point"}
}