{
  "type": "Feature",
  "properties": {
    "gn:admin1_code":"07",
    "gn:asciiname":"Ait Ali",
    "gn:country_code":"MA",
    "gn:dem":167,
    "gn:feature_class":"P",
    "gn:feature_code":"PPL",
    "gn:name":"Ait Ali",
    "gn:population":0,
    "gn:timezone":"Africa/Casablanca",
    "iso:country":"MA",
    "name:und_x_variant":[
        "A\u00eft Choukaia",
        "A\u00eft Ali",
        "Ait Ali"
    ],
    "wof:name":"Ait Ali",
    "wof:placetype":"locality"
},
  "geometry": {"coordinates":[-9.71042,31.30325],"type":"Point"}
}