{
  "type": "Feature",
  "properties": {
    "gn:admin1_code":"4.0",
    "gn:asciiname":"Dar Agnaou Lahsen",
    "gn:country_code":"MA",
    "gn:dem":318,
    "gn:feature_class":"P",
    "gn:feature_code":"PPL",
    "gn:name":"Dar Agnaou Lahsen",
    "gn:population":0,
    "gn:timezone":"Africa/Casablanca",
    "iso:country":"MA",
    "wof:name":"Dar Agnaou Lahsen",
    "wof:placetype":"locality"
},
  "geometry": {"coordinates":[-6.96309,33.6598],"type":"Point"}
}