{
  "type": "Feature",
  "properties": {
    "gn:admin1_code":"09",
    "gn:asciiname":"Timsiyane",
    "gn:country_code":"MA",
    "gn:dem":1386,
    "gn:feature_class":"P",
    "gn:feature_code":"PPL",
    "gn:name":"Timsiyane",
    "gn:population":0,
    "gn:timezone":"Africa/Casablanca",
    "iso:country":"MA",
    "name:und_x_variant":[
        "Tinsiane"
    ],
    "wof:name":"Timsiyane",
    "wof:placetype":"locality"
},
  "geometry": {"coordinates":[-8.62318,30.092],"type":"Point"}
}