{
  "type": "Feature",
  "properties": {
    "gn:admin1_code":"7.0",
    "gn:asciiname":"Douar Id Hachtouf",
    "gn:country_code":"MA",
    "gn:dem":548,
    "gn:feature_class":"P",
    "gn:feature_code":"PPL",
    "gn:name":"Douar Id Hachtouf",
    "gn:population":0,
    "gn:timezone":"Africa/Casablanca",
    "iso:country":"MA",
    "wof:name":"Douar Id Hachtouf",
    "wof:placetype":"locality"
},
  "geometry": {"coordinates":[-9.59367,31.28567],"type":"Point"}
}