{
  "type": "Feature",
  "properties": {
    "gn:admin1_code":"3.0",
    "gn:asciiname":"Douar Lkoudya",
    "gn:country_code":"MA",
    "gn:dem":469,
    "gn:feature_class":"P",
    "gn:feature_code":"PPL",
    "gn:name":"Douar Lkoudya",
    "gn:population":0,
    "gn:timezone":"Africa/Casablanca",
    "iso:country":"MA",
    "wof:name":"Douar Lkoudya",
    "wof:placetype":"locality"
},
  "geometry": {"coordinates":[-4.7002,34.17875],"type":"Point"}
}