{
  "type": "Feature",
  "properties": {
    "gn:admin1_code":"5.0",
    "gn:asciiname":"Ayt Ben Mansour",
    "gn:country_code":"MA",
    "gn:dem":743,
    "gn:feature_class":"P",
    "gn:feature_code":"PPL",
    "gn:name":"Ayt Ben Mansour",
    "gn:population":0,
    "gn:timezone":"Africa/Casablanca",
    "iso:country":"MA",
    "wof:name":"Ayt Ben Mansour",
    "wof:placetype":"locality"
},
  "geometry": {"coordinates":[-6.70664,32.08856],"type":"Point"}
}