{
  "type": "Feature",
  "properties": {
    "gn:admin1_code":"5.0",
    "gn:asciiname":"Tighfist-n-Ait Tmaghrit",
    "gn:country_code":"MA",
    "gn:dem":2254,
    "gn:feature_class":"P",
    "gn:feature_code":"PPL",
    "gn:name":"Tighfist-n-A\u00eft Tmaghrit",
    "gn:population":0,
    "gn:timezone":"Africa/Casablanca",
    "iso:country":"MA",
    "wof:name":"Tighfist-n-Ait Tmaghrit",
    "wof:placetype":"locality"
},
  "geometry": {"coordinates":[-6.95494,31.36159],"type":"Point"}
}