{
  "type": "Feature",
  "properties": {
    "gn:admin1_code":"7.0",
    "gn:asciiname":"Lahboulat",
    "gn:country_code":"MA",
    "gn:dem":79,
    "gn:feature_class":"P",
    "gn:feature_code":"PPL",
    "gn:name":"Lahboulat",
    "gn:population":0,
    "gn:timezone":"Africa/Casablanca",
    "iso:country":"MA",
    "wof:name":"Lahboulat",
    "wof:placetype":"locality"
},
  "geometry": {"coordinates":[-9.2206,32.42525999999999],"type":"Point"}
}