{
  "type": "Feature",
  "properties": {
    "gn:admin1_code":"09",
    "gn:asciiname":"Iggur Ilerd",
    "gn:country_code":"MA",
    "gn:dem":684,
    "gn:feature_class":"P",
    "gn:feature_code":"PPL",
    "gn:name":"Iggur Ilerd",
    "gn:population":0,
    "gn:timezone":"Africa/Casablanca",
    "iso:country":"MA",
    "name:und_x_variant":[
        "Iggui Aferd"
    ],
    "wof:name":"Iggur Ilerd",
    "wof:placetype":"locality"
},
  "geometry": {"coordinates":[-9.10428,30.07437],"type":"Point"}
}