{
  "type": "Feature",
  "properties": {
    "gn:admin1_code":"1.0",
    "gn:asciiname":"Douar Lahricha",
    "gn:country_code":"MA",
    "gn:dem":122,
    "gn:feature_class":"P",
    "gn:feature_code":"PPL",
    "gn:name":"Douar Lahricha",
    "gn:population":0,
    "gn:timezone":"Africa/Casablanca",
    "iso:country":"MA",
    "wof:name":"Douar Lahricha",
    "wof:placetype":"locality"
},
  "geometry": {"coordinates":[-5.50344,34.98588],"type":"Point"}
}