{
  "type": "Feature",
  "properties": {
    "gn:admin1_code":"03",
    "gn:asciiname":"Douar Tamra",
    "gn:country_code":"MA",
    "gn:dem":394,
    "gn:feature_class":"P",
    "gn:feature_code":"PPL",
    "gn:name":"Douar Tamra",
    "gn:population":0,
    "gn:timezone":"Africa/Casablanca",
    "iso:country":"MA",
    "name:und_x_variant":[
        "Temsa",
        "Douar Simra",
        "Douar Temra",
        "Douar Tamra"
    ],
    "wof:name":"Douar Tamra",
    "wof:placetype":"locality"
},
  "geometry": {"coordinates":[-5.30462,34.22569],"type":"Point"}
}