{
  "type": "Feature",
  "properties": {
    "gn:admin1_code":"09",
    "gn:asciiname":"Bahmou",
    "gn:country_code":"MA",
    "gn:dem":365,
    "gn:feature_class":"P",
    "gn:feature_code":"PPL",
    "gn:name":"Bahmou",
    "gn:population":0,
    "gn:timezone":"Africa/Casablanca",
    "iso:country":"MA",
    "wof:name":"Bahmou",
    "wof:placetype":"locality"
},
  "geometry": {"coordinates":[-9.86,29.67],"type":"Point"}
}