{
  "type": "Feature",
  "properties": {
    "gn:admin1_code":"07",
    "gn:asciiname":"Lebhalla",
    "gn:country_code":"MA",
    "gn:dem":321,
    "gn:feature_class":"P",
    "gn:feature_code":"PPL",
    "gn:name":"Lebhalla",
    "gn:population":0,
    "gn:timezone":"Africa/Casablanca",
    "iso:country":"MA",
    "name:und_x_variant":[
        "Ben Allah"
    ],
    "wof:name":"Lebhalla",
    "wof:placetype":"locality"
},
  "geometry": {"coordinates":[-8.38069,32.27350999999999],"type":"Point"}
}