{
  "type": "Feature",
  "properties": {
    "gn:admin1_code":"7.0",
    "gn:asciiname":"Douar Ait Bou Amara",
    "gn:country_code":"MA",
    "gn:dem":435,
    "gn:feature_class":"P",
    "gn:feature_code":"PPL",
    "gn:name":"Douar Ait Bou Amara",
    "gn:population":0,
    "gn:timezone":"Africa/Casablanca",
    "iso:country":"MA",
    "wof:name":"Douar Ait Bou Amara",
    "wof:placetype":"locality"
},
  "geometry": {"coordinates":[-9.32666,31.5562],"type":"Point"}
}