{
  "type": "Feature",
  "properties": {
    "gn:admin1_code":"05",
    "gn:asciiname":"Timqit",
    "gn:country_code":"MA",
    "gn:dem":2095,
    "gn:feature_class":"P",
    "gn:feature_code":"PPL",
    "gn:name":"Timqit",
    "gn:population":0,
    "gn:timezone":"Africa/Casablanca",
    "iso:country":"MA",
    "name:und_x_variant":[
        "Timkit"
    ],
    "wof:name":"Timqit",
    "wof:placetype":"locality"
},
  "geometry": {"coordinates":[-6.04321,32.09809],"type":"Point"}
}