{
  "type": "Feature",
  "properties": {
    "gn:admin1_code":"06",
    "gn:asciiname":"Kechacha",
    "gn:country_code":"MA",
    "gn:dem":274,
    "gn:feature_class":"P",
    "gn:feature_code":"PPL",
    "gn:name":"Kechacha",
    "gn:population":0,
    "gn:timezone":"Africa/Casablanca",
    "iso:country":"MA",
    "wof:name":"Kechacha",
    "wof:placetype":"locality"
},
  "geometry": {"coordinates":[-7.88419,32.71899000000001],"type":"Point"}
}