{
  "type": "Feature",
  "properties": {
    "gn:admin1_code":"7.0",
    "gn:asciiname":"Sidi Ali ou Salah",
    "gn:country_code":"MA",
    "gn:dem":499,
    "gn:feature_class":"P",
    "gn:feature_code":"PPL",
    "gn:name":"Sidi Ali ou Salah",
    "gn:population":0,
    "gn:timezone":"Africa/Casablanca",
    "iso:country":"MA",
    "wof:name":"Sidi Ali ou Salah",
    "wof:placetype":"locality"
},
  "geometry": {"coordinates":[-9.6146,30.92108],"type":"Point"}
}