{
  "type": "Feature",
  "properties": {
    "gn:admin1_code":"7.0",
    "gn:asciiname":"Erremilat",
    "gn:country_code":"MA",
    "gn:dem":193,
    "gn:feature_class":"P",
    "gn:feature_code":"PPLL",
    "gn:name":"Erremilat",
    "gn:population":0,
    "gn:timezone":"Africa/Casablanca",
    "iso:country":"MA",
    "wof:name":"Erremilat",
    "wof:placetype":"locality"
},
  "geometry": {"coordinates":[-9.58707,31.59532],"type":"Point"}
}