{
  "type": "Feature",
  "properties": {
    "gn:admin1_code":"09",
    "gn:asciiname":"Tagadirt-n-Ait Lahsene",
    "gn:country_code":"MA",
    "gn:dem":870,
    "gn:feature_class":"P",
    "gn:feature_code":"PPL",
    "gn:name":"Tagadirt-n-A\u00eft Lahsene",
    "gn:population":0,
    "gn:timezone":"Africa/Casablanca",
    "iso:country":"MA",
    "name:und_x_variant":[
        "Tagadirt-n-A\u00eft Lahsene",
        "Tagadirt"
    ],
    "wof:name":"Tagadirt-n-Ait Lahsene",
    "wof:placetype":"locality"
},
  "geometry": {"coordinates":[-8.20017,30.54184],"type":"Point"}
}