{
  "type": "Feature",
  "properties": {
    "gn:admin1_code":"7.0",
    "gn:asciiname":"Douar Laassara Rouahla",
    "gn:country_code":"MA",
    "gn:dem":354,
    "gn:feature_class":"P",
    "gn:feature_code":"PPL",
    "gn:name":"Douar Laassara Rouahla",
    "gn:population":0,
    "gn:timezone":"Africa/Casablanca",
    "iso:country":"MA",
    "wof:name":"Douar Laassara Rouahla",
    "wof:placetype":"locality"
},
  "geometry": {"coordinates":[-8.91187,31.58402],"type":"Point"}
}