{
  "type": "Feature",
  "properties": {
    "gn:admin1_code":"09",
    "gn:asciiname":"Dou Tgadirt",
    "gn:country_code":"MA",
    "gn:dem":1555,
    "gn:feature_class":"P",
    "gn:feature_code":"PPL",
    "gn:name":"Dou Tgadirt",
    "gn:population":0,
    "gn:timezone":"Africa/Casablanca",
    "iso:country":"MA",
    "wof:name":"Dou Tgadirt",
    "wof:placetype":"locality"
},
  "geometry": {"coordinates":[-8.71916,29.94055],"type":"Point"}
}