{
  "type": "Feature",
  "properties": {
    "gn:country":"MA",
    "gn:fcode":"ADM3",
    "gn:pop":187708,
    "iso:country":"MA",
    "name:ara_x_preferred":[
        "\u0627\u0644\u0647\u0631\u0627\u0648\u064a\u064a\u0646"
    ],
    "name:fra_x_preferred":[
        "Mohammedia"
    ],
    "name:fra_x_variant":[
        "Mohammedia (MU)",
        "Mohammedia (Commune Urbaine)"
    ],
    "qs:name":"Mohammedia",
    "qs:photos_9r":0,
    "qs:photos_sr":0,
    "qs:pop_sr":"9",
    "wd:wordcount":1655,
    "wof:name":"Mohammedia",
    "wof:placetype":"localadmin",
    "wof:population":187708
},
  "geometry": {"coordinates":[-7.38502,33.69474],"type":"Point"}
}