{
  "type": "Feature",
  "properties": {
    "gn:admin1_code":"1.0",
    "gn:asciiname":"Douar Iberkanene",
    "gn:country_code":"MA",
    "gn:dem":588,
    "gn:feature_class":"P",
    "gn:feature_code":"PPL",
    "gn:name":"Douar Iberkanene",
    "gn:population":0,
    "gn:timezone":"Africa/Casablanca",
    "iso:country":"MA",
    "wof:name":"Douar Iberkanene",
    "wof:placetype":"locality"
},
  "geometry": {"coordinates":[-3.85728,35.06411],"type":"Point"}
}