{
  "type": "Feature",
  "properties": {
    "gn:country":"MA",
    "gn:fcode":"ADM3",
    "gn:population":11504,
    "iso:country":"MA",
    "name:ara_x_preferred":[
        "\u0627\u064a\u0631\u064a\u063a \u0646\u062a\u0627\u0647\u0644\u0629"
    ],
    "name:ara_x_variant":[
        "\u0639\u064a\u0646 \u0646\u0632\u0627\u063a"
    ],
    "name:azb_x_preferred":[
        "\u0622\u0626\u06cc\u0646 \u0627\u0646\u0632\u0627\u0642"
    ],
    "name:ceb_x_preferred":[
        "Ain Nzagh"
    ],
    "name:fas_x_preferred":[
        "\u0622\u0626\u06cc\u0646 \u0627\u0646\u0632\u0627\u0642"
    ],
    "name:fra_x_preferred":[
        "Ain Nzagh"
    ],
    "name:fra_x_variant":[
        "Ain Nzagh (CR)",
        "Ain Nzagh (Commune Rurale)"
    ],
    "name:swe_x_preferred":[
        "Ain Nzagh"
    ],
    "qs_pg:aaroncc":"MA",
    "qs_pg:gn_country":"MA",
    "qs_pg:gn_fcode":"ADM3",
    "qs_pg:gn_pop":11504,
    "qs_pg:name":"Ain Nzagh",
    "qs_pg:photos_9r":0,
    "qs_pg:photos_sr":0,
    "qs_pg:pop_sr":6,
    "qs_pg:qs_pg_placetype":"localadmin",
    "wof:name":"Ain Nzagh",
    "wof:placetype":"localadmin",
    "wof:population":11504
},
  "geometry": {"coordinates":[-7.58408,32.94826],"type":"Point"}
}