{
  "type": "Feature",
  "properties": {
    "gn:admin1_code":"8.0",
    "gn:asciiname":"Anghassa",
    "gn:country_code":"MA",
    "gn:dem":1431,
    "gn:feature_class":"P",
    "gn:feature_code":"PPL",
    "gn:name":"Anghassa",
    "gn:population":0,
    "gn:timezone":"Africa/Casablanca",
    "iso:country":"MA",
    "wof:name":"Anghassa",
    "wof:placetype":"locality"
},
  "geometry": {"coordinates":[-7.19901,31.13738],"type":"Point"}
}