{
  "type": "Feature",
  "properties": {
    "gn:admin1_code":"01",
    "gn:asciiname":"Ichtal",
    "gn:country_code":"MA",
    "gn:dem":393,
    "gn:feature_class":"P",
    "gn:feature_code":"PPL",
    "gn:name":"Ichtal",
    "gn:population":0,
    "gn:timezone":"Africa/Casablanca",
    "iso:country":"MA",
    "wof:name":"Ichtal",
    "wof:placetype":"locality"
},
  "geometry": {"coordinates":[-5.26962,35.2404],"type":"Point"}
}