{
  "type": "Feature",
  "properties": {
    "gn:admin1_code":"06",
    "gn:asciiname":"Douar Bel Kouch",
    "gn:country_code":"MA",
    "gn:dem":83,
    "gn:feature_class":"P",
    "gn:feature_code":"PPL",
    "gn:name":"Douar Bel Kouch",
    "gn:population":0,
    "gn:timezone":"Africa/Casablanca",
    "iso:country":"MA",
    "wof:name":"Douar Bel Kouch",
    "wof:placetype":"locality"
},
  "geometry": {"coordinates":[-8.86892,32.84338],"type":"Point"}
}