{
  "type": "Feature",
  "properties": {
    "gn:admin1_code":"09",
    "gn:asciiname":"Tanmagalt",
    "gn:country_code":"MA",
    "gn:dem":1686,
    "gn:feature_class":"P",
    "gn:feature_code":"PPL",
    "gn:name":"Tanmagalt",
    "gn:population":0,
    "gn:timezone":"Africa/Casablanca",
    "iso:country":"MA",
    "name:und_x_variant":[
        "Tanmagalte",
        "Tanmag",
        "Tanmaguelt",
        "Tanmagalt"
    ],
    "wof:name":"Tanmagalt",
    "wof:placetype":"locality"
},
  "geometry": {"coordinates":[-7.9776,30.86363],"type":"Point"}
}