{
  "type": "Feature",
  "properties": {
    "gn:admin1_code":"08",
    "gn:asciiname":"Tafraout n'Ait Bou n'Grouf",
    "gn:country_code":"MA",
    "gn:dem":1717,
    "gn:feature_class":"P",
    "gn:feature_code":"PPL",
    "gn:name":"Tafraout n\u2019A\u00eft Bou n\u2019Grouf",
    "gn:population":0,
    "gn:timezone":"Africa/Casablanca",
    "iso:country":"MA",
    "wof:name":"Tafraout n'Ait Bou n'Grouf",
    "wof:placetype":"locality"
},
  "geometry": {"coordinates":[-6.73797,31.23677],"type":"Point"}
}