{
  "type": "Feature",
  "properties": {
    "gn:admin1_code":"07",
    "gn:asciiname":"Nzala Ghedira Al Khecheb",
    "gn:country_code":"MA",
    "gn:dem":467,
    "gn:feature_class":"P",
    "gn:feature_code":"PPL",
    "gn:name":"Nzala Ghedira Al Khecheb",
    "gn:population":0,
    "gn:timezone":"Africa/Casablanca",
    "iso:country":"MA",
    "name:und_x_variant":[
        "Nzala Rhedira el Khecheb",
        "Nzalet Chme\u00efda",
        "Nzala Ghedira Al Khecheb"
    ],
    "wof:name":"Nzala Ghedira Al Khecheb",
    "wof:placetype":"locality"
},
  "geometry": {"coordinates":[-8.18091,32.0728],"type":"Point"}
}