{
  "type": "Feature",
  "properties": {
    "gn:admin1_code":"7.0",
    "gn:asciiname":"Moulia",
    "gn:country_code":"MA",
    "gn:dem":655,
    "gn:feature_class":"P",
    "gn:feature_code":"PPL",
    "gn:name":"Moulia",
    "gn:population":0,
    "gn:timezone":"Africa/Casablanca",
    "iso:country":"MA",
    "wof:name":"Moulia",
    "wof:placetype":"locality"
},
  "geometry": {"coordinates":[-9.58503,31.03286],"type":"Point"}
}