{
  "type": "Feature",
  "properties": {
    "gn:admin1_code":"04",
    "gn:asciiname":"Douar Lemlaguit Rmiqiyyine",
    "gn:country_code":"MA",
    "gn:dem":7,
    "gn:feature_class":"P",
    "gn:feature_code":"PPL",
    "gn:name":"Douar Lemlaguit Rmiqiyyine",
    "gn:population":0,
    "gn:timezone":"Africa/Casablanca",
    "iso:country":"MA",
    "name:und_x_variant":[
        "Dar Remiki"
    ],
    "wof:name":"Douar Lemlaguit Rmiqiyyine",
    "wof:placetype":"locality"
},
  "geometry": {"coordinates":[-6.38842,34.62971],"type":"Point"}
}