{
  "type": "Feature",
  "properties": {
    "gn:admin1_code":"10",
    "gn:asciiname":"Id Salem",
    "gn:country_code":"MA",
    "gn:dem":706,
    "gn:feature_class":"P",
    "gn:feature_code":"PPL",
    "gn:name":"Id Salem",
    "gn:population":0,
    "gn:timezone":"Africa/Casablanca",
    "iso:country":"MA",
    "wof:name":"Id Salem",
    "wof:placetype":"locality"
},
  "geometry": {"coordinates":[-9.5166,29.18847],"type":"Point"}
}