{
  "type": "Feature",
  "properties": {
    "gn:gn_country":"MA",
    "gn:gn_fcode":"ADM3",
    "gn:gn_pop":7434,
    "gn:population":7823,
    "iso:country":"MA",
    "name:ara_x_preferred":[
        "\u0645\u0631\u0643\u0632 \u0628\u0631\u064a\u0643\u0634\u0629"
    ],
    "name:fra_x_preferred":[
        "Souk Kdim"
    ],
    "name:fra_x_variant":[
        "Souk Kdim (CR)",
        "Souk Kdim (Commune Rurale)"
    ],
    "qs_pg:aaroncc":"MA",
    "qs_pg:gn_country":"MA",
    "qs_pg:gn_fcode":"ADM3",
    "qs_pg:gn_pop":7434,
    "qs_pg:name":"Souk Kdim",
    "qs_pg:photos_9r":0,
    "qs_pg:photos_sr":0,
    "qs_pg:pop_sr":5,
    "qs_pg:qs_pg_placetype":"localadmin",
    "wof:name":"Souk Kdim",
    "wof:placetype":"localadmin",
    "wof:population":7823
},
  "geometry": {"coordinates":[-5.5246,35.60685],"type":"Point"}
}