{
  "type": "Feature",
  "properties": {
    "gn:admin1_code":"9.0",
    "gn:asciiname":"Ait Ouarab",
    "gn:country_code":"MA",
    "gn:dem":468,
    "gn:feature_class":"P",
    "gn:feature_code":"PPL",
    "gn:name":"A\u00eft Ouarab",
    "gn:population":0,
    "gn:timezone":"Africa/Casablanca",
    "iso:country":"MA",
    "wof:name":"Ait Ouarab",
    "wof:placetype":"locality"
},
  "geometry": {"coordinates":[-9.22276,30.00724],"type":"Point"}
}