{
  "type": "Feature",
  "properties": {
    "gn:admin1_code":"3.0",
    "gn:asciiname":"Douar Bni Alouhouna",
    "gn:country_code":"MA",
    "gn:dem":782,
    "gn:feature_class":"P",
    "gn:feature_code":"PPL",
    "gn:name":"Douar Bni Alouhouna",
    "gn:population":0,
    "gn:timezone":"Africa/Casablanca",
    "iso:country":"MA",
    "wof:name":"Douar Bni Alouhouna",
    "wof:placetype":"locality"
},
  "geometry": {"coordinates":[-4.33401,34.37459],"type":"Point"}
}