{
  "type": "Feature",
  "properties": {
    "gn:admin1_code":"7.0",
    "gn:asciiname":"Douar Ait Ben Taleb",
    "gn:country_code":"MA",
    "gn:dem":234,
    "gn:feature_class":"P",
    "gn:feature_code":"PPL",
    "gn:name":"Douar Ait Ben Taleb",
    "gn:population":0,
    "gn:timezone":"Africa/Casablanca",
    "iso:country":"MA",
    "wof:name":"Douar Ait Ben Taleb",
    "wof:placetype":"locality"
},
  "geometry": {"coordinates":[-9.35503,31.81092],"type":"Point"}
}