{
  "type": "Feature",
  "properties": {
    "gn:admin1_code":"3.0",
    "gn:asciiname":"Ait Abbou",
    "gn:country_code":"MA",
    "gn:dem":971,
    "gn:feature_class":"P",
    "gn:feature_code":"PPL",
    "gn:name":"Ait Abbou",
    "gn:population":0,
    "gn:timezone":"Africa/Casablanca",
    "iso:country":"MA",
    "wof:name":"Ait Abbou",
    "wof:placetype":"locality"
},
  "geometry": {"coordinates":[-5.25605,33.73136],"type":"Point"}
}