{
  "type": "Feature",
  "properties": {
    "gn:admin1_code":"07",
    "gn:asciiname":"Ighir",
    "gn:country_code":"MA",
    "gn:dem":1443,
    "gn:feature_class":"P",
    "gn:feature_code":"PPL",
    "gn:name":"Ighir",
    "gn:population":0,
    "gn:timezone":"Africa/Casablanca",
    "iso:country":"MA",
    "name:und_x_variant":[
        "Irhir",
        "Aguerzra"
    ],
    "wof:name":"Ighir",
    "wof:placetype":"locality"
},
  "geometry": {"coordinates":[-8.07861,30.97871],"type":"Point"}
}