{
  "type": "Feature",
  "properties": {
    "gn:admin1_code":"9.0",
    "gn:asciiname":"Tamsoult",
    "gn:country_code":"MA",
    "gn:dem":1539,
    "gn:feature_class":"P",
    "gn:feature_code":"PPL",
    "gn:name":"Tamsoult",
    "gn:population":0,
    "gn:timezone":"Africa/Casablanca",
    "iso:country":"MA",
    "wof:name":"Tamsoult",
    "wof:placetype":"locality"
},
  "geometry": {"coordinates":[-8.92512,30.70882000000001],"type":"Point"}
}