{
  "type": "Feature",
  "properties": {
    "gn:admin1_code":"9.0",
    "gn:asciiname":"Tighoula",
    "gn:country_code":"MA",
    "gn:dem":560,
    "gn:feature_class":"P",
    "gn:feature_code":"PPL",
    "gn:name":"Tighoula",
    "gn:population":0,
    "gn:timezone":"Africa/Casablanca",
    "iso:country":"MA",
    "wof:name":"Tighoula",
    "wof:placetype":"locality"
},
  "geometry": {"coordinates":[-9.29344,29.89597],"type":"Point"}
}