{
  "type": "Feature",
  "properties": {
    "gn:admin1_code":"05",
    "gn:asciiname":"Tamarnout",
    "gn:country_code":"MA",
    "gn:dem":1359,
    "gn:elevation":"0.0",
    "gn:feature_class":"P",
    "gn:feature_code":"PPL",
    "gn:name":"Tamarnout",
    "gn:population":0,
    "gn:timezone":"Africa/Casablanca",
    "iso:country":"MA",
    "name:und_x_variant":[
        "Tomarnoute",
        "Tamernoute",
        "Tamarnout"
    ],
    "wof:name":"Tamarnout",
    "wof:placetype":"locality"
},
  "geometry": {"coordinates":[-6.55354,31.69826],"type":"Point"}
}