{
  "type": "Feature",
  "properties": {
    "gn:admin1_code":"03",
    "gn:asciiname":"El Khanadek",
    "gn:country_code":"MA",
    "gn:dem":605,
    "gn:feature_class":"P",
    "gn:feature_code":"PPL",
    "gn:name":"El Khanadek",
    "gn:population":0,
    "gn:timezone":"Africa/Casablanca",
    "iso:country":"MA",
    "name:und_x_variant":[
        "El Khenadek",
        "El Khanadek"
    ],
    "wof:name":"El Khanadek",
    "wof:placetype":"locality"
},
  "geometry": {"coordinates":[-5.44968,34.08959],"type":"Point"}
}