{
  "type": "Feature",
  "properties": {
    "gn:admin1_code":"1.0",
    "gn:asciiname":"Bnoniyene",
    "gn:country_code":"MA",
    "gn:dem":107,
    "gn:feature_class":"P",
    "gn:feature_code":"PPL",
    "gn:name":"Bnoniyene",
    "gn:population":0,
    "gn:timezone":"Africa/Casablanca",
    "iso:country":"MA",
    "wof:name":"Bnoniyene",
    "wof:placetype":"locality"
},
  "geometry": {"coordinates":[-6.06463,35.34338],"type":"Point"}
}