{
  "type": "Feature",
  "properties": {
    "gn:admin1_code":"2.0",
    "gn:asciiname":"Tzayast",
    "gn:country_code":"MA",
    "gn:dem":86,
    "gn:feature_class":"P",
    "gn:feature_code":"PPL",
    "gn:name":"Tzayast",
    "gn:population":0,
    "gn:timezone":"Africa/Casablanca",
    "iso:country":"MA",
    "wof:name":"Tzayast",
    "wof:placetype":"locality"
},
  "geometry": {"coordinates":[-2.43119,34.93547],"type":"Point"}
}