{
  "type": "Feature",
  "properties": {
    "gn:admin1_code":"3.0",
    "gn:asciiname":"Douar Sahel Laqseb",
    "gn:country_code":"MA",
    "gn:dem":266,
    "gn:feature_class":"P",
    "gn:feature_code":"PPL",
    "gn:name":"Douar Sahel Laqseb",
    "gn:population":0,
    "gn:timezone":"Africa/Casablanca",
    "iso:country":"MA",
    "wof:name":"Douar Sahel Laqseb",
    "wof:placetype":"locality"
},
  "geometry": {"coordinates":[-4.33635,34.16463],"type":"Point"}
}