{
  "type": "Feature",
  "properties": {
    "gn:admin1_code":"09",
    "gn:asciiname":"Touzdiyine",
    "gn:country_code":"MA",
    "gn:dem":1634,
    "gn:feature_class":"P",
    "gn:feature_code":"PPL",
    "gn:name":"Touzdiyine",
    "gn:population":0,
    "gn:timezone":"Africa/Casablanca",
    "iso:country":"MA",
    "name:und_x_variant":[
        "Tousdiine",
        "Touzdine",
        "Tousdine",
        "Touzdiine",
        "Touzdiyine"
    ],
    "wof:name":"Touzdiyine",
    "wof:placetype":"locality"
},
  "geometry": {"coordinates":[-7.87194,30.61099],"type":"Point"}
}