{
  "type": "Feature",
  "properties": {
    "gn:admin1_code":"2.0",
    "gn:asciiname":"Poste",
    "gn:country_code":"MA",
    "gn:dem":251,
    "gn:feature_class":"P",
    "gn:feature_code":"PPL",
    "gn:name":"Poste",
    "gn:population":0,
    "gn:timezone":"Africa/Casablanca",
    "iso:country":"MA",
    "name:fra_x_preferred":[
        "Poste"
    ],
    "wof:name":"Poste",
    "wof:placetype":"locality"
},
  "geometry": {"coordinates":[-3.07032,35.11246],"type":"Point"}
}