{
  "type": "Feature",
  "properties": {
    "gn:admin1_code":"10.0",
    "gn:asciiname":"Amdine",
    "gn:country_code":"MA",
    "gn:dem":362,
    "gn:feature_class":"P",
    "gn:feature_code":"PPL",
    "gn:name":"Amdine",
    "gn:population":0,
    "gn:timezone":"Africa/Casablanca",
    "iso:country":"MA",
    "wof:name":"Amdine",
    "wof:placetype":"locality"
},
  "geometry": {"coordinates":[-9.95029,29.34097],"type":"Point"}
}