{
  "type": "Feature",
  "properties": {
    "gn:country":"MA",
    "gn:fcode":"ADM3",
    "gn:population":11667,
    "iso:country":"MA",
    "name:ara_x_preferred":[
        "\u0637\u0627\u062d"
    ],
    "name:deu_x_preferred":[
        "Assa"
    ],
    "name:fra_x_preferred":[
        "Assa"
    ],
    "name:fra_x_variant":[
        "Assa (MU)",
        "Assa (Commune Urbaine)"
    ],
    "name:isl_x_preferred":[
        "Assa"
    ],
    "name:nld_x_preferred":[
        "Assa"
    ],
    "name:pol_x_preferred":[
        "Assa"
    ],
    "name:rus_x_preferred":[
        "\u0410\u0441\u0441\u0430"
    ],
    "name:swe_x_preferred":[
        "Assa"
    ],
    "name:ukr_x_preferred":[
        "\u0410\u0441\u0441\u0430"
    ],
    "qs_pg:aaroncc":"MA",
    "qs_pg:gn_country":"MA",
    "qs_pg:gn_fcode":"ADM3",
    "qs_pg:gn_pop":11667,
    "qs_pg:name":"Assa",
    "qs_pg:photos_9r":0,
    "qs_pg:photos_sr":0,
    "qs_pg:pop_sr":6,
    "qs_pg:qs_pg_placetype":"localadmin",
    "wof:name":"Assa",
    "wof:placetype":"localadmin",
    "wof:population":11667
},
  "geometry": {"coordinates":[-9.34822,28.67999],"type":"Point"}
}