{
  "type": "Feature",
  "properties": {
    "gn:admin1_code":"7.0",
    "gn:asciiname":"Ahl Tayebou Mrabtine",
    "gn:country_code":"MA",
    "gn:dem":382,
    "gn:feature_class":"P",
    "gn:feature_code":"PPL",
    "gn:name":"Ahl Tayebou Mrabtine",
    "gn:population":0,
    "gn:timezone":"Africa/Casablanca",
    "iso:country":"MA",
    "wof:name":"Ahl Tayebou Mrabtine",
    "wof:placetype":"locality"
},
  "geometry": {"coordinates":[-8.17652,31.67899],"type":"Point"}
}