{
  "type": "Feature",
  "properties": {
    "gn:country":"MA",
    "gn:fcode":"ADM3",
    "gn:pop":8265,
    "iso:country":"MA",
    "name:ara_x_preferred":[
        "\u0623\u0648\u0644\u0627\u062f \u0628\u0648\u063a\u0627\u062f\u064a"
    ],
    "name:fra_x_preferred":[
        "Cherrat"
    ],
    "name:fra_x_variant":[
        "Cherrat (CR)",
        "Cherrat (Commune Rurale)"
    ],
    "qs:name":"Cherrat",
    "qs:photos_9r":0,
    "qs:photos_sr":0,
    "qs:pop_sr":"5",
    "wof:name":"Cherrat",
    "wof:placetype":"localadmin",
    "wof:population":8265
},
  "geometry": {"coordinates":[-7.10129,33.77653],"type":"Point"}
}