{
  "type": "Feature",
  "properties": {
    "gn:admin1_code":"3.0",
    "gn:asciiname":"Ait Sidi Chibani",
    "gn:country_code":"MA",
    "gn:dem":752,
    "gn:feature_class":"P",
    "gn:feature_code":"PPL",
    "gn:name":"Ait Sidi Chibani",
    "gn:population":0,
    "gn:timezone":"Africa/Casablanca",
    "iso:country":"MA",
    "wof:name":"Ait Sidi Chibani",
    "wof:placetype":"locality"
},
  "geometry": {"coordinates":[-5.62499,33.7109],"type":"Point"}
}