{
  "type": "Feature",
  "properties": {
    "gn:admin1_code":"05",
    "gn:asciiname":"Igouzouln",
    "gn:country_code":"MA",
    "gn:dem":1020,
    "gn:elevation":"0.0",
    "gn:feature_class":"P",
    "gn:feature_code":"PPL",
    "gn:name":"Igouzouln",
    "gn:population":0,
    "gn:timezone":"Africa/Casablanca",
    "iso:country":"MA",
    "name:und_x_variant":[
        "Igousouln"
    ],
    "wof:name":"Igouzouln",
    "wof:placetype":"locality"
},
  "geometry": {"coordinates":[-6.88652,31.70536],"type":"Point"}
}