{
  "type": "Feature",
  "properties": {
    "gn:admin1_code":"2.0",
    "gn:asciiname":"Oued El Amri",
    "gn:country_code":"MA",
    "gn:dem":109,
    "gn:feature_class":"P",
    "gn:feature_code":"PPL",
    "gn:name":"Oued El Amri",
    "gn:population":0,
    "gn:timezone":"Africa/Casablanca",
    "iso:country":"MA",
    "wof:name":"Oued El Amri",
    "wof:placetype":"locality"
},
  "geometry": {"coordinates":[-2.22687,35.00845],"type":"Point"}
}