{
  "type": "Feature",
  "properties": {
    "gn:country":"MA",
    "gn:fcode":"ADM3",
    "gn:population":10175,
    "iso:country":"MA",
    "name:ara_x_preferred":[
        "\u0623\u0648\u0644\u0627\u062f \u062d\u0633\u0648\u0646 \u062d\u0645\u0631\u064a"
    ],
    "name:ara_x_variant":[
        "\u0633\u064a\u062f\u064a \u0639\u0628\u062f \u0627\u0644\u0644\u0647"
    ],
    "name:ary_x_preferred":[
        "\u0633\u064a\u062f\u064a \u0639\u0628\u062f \u0627\u0644\u0644\u0647"
    ],
    "name:cat_x_preferred":[
        "Sidi Abdallah"
    ],
    "name:ceb_x_preferred":[
        "Sidi Abdallah"
    ],
    "name:eng_x_preferred":[
        "Sidi Abdallah"
    ],
    "name:fas_x_preferred":[
        "\u0633\u06cc\u062f\u06cc \u0639\u0628\u062f\u0627\u0644\u0644\u0647"
    ],
    "name:fra_x_preferred":[
        "Sidi Abdallah"
    ],
    "name:fra_x_variant":[
        "Sidi Abdallah (CR)",
        "Sidi Abdallah (Commune Rurale)"
    ],
    "name:ita_x_preferred":[
        "Sidi Abdallah"
    ],
    "name:swe_x_preferred":[
        "Sidi Abdallah"
    ],
    "qs:name":"Sidi Abdallah",
    "qs:photos_9r":0,
    "qs:photos_sr":0,
    "qs:pop_sr":"6",
    "wd:wordcount":65,
    "wof:name":"Sidi Abdallah",
    "wof:placetype":"localadmin",
    "wof:population":10175
},
  "geometry": {"coordinates":[-7.8243,32.60334],"type":"Point"}
}