{
  "type": "Feature",
  "properties": {
    "gn:admin1_code":"3.0",
    "gn:asciiname":"Douar Zmamra",
    "gn:country_code":"MA",
    "gn:dem":289,
    "gn:feature_class":"P",
    "gn:feature_code":"PPL",
    "gn:name":"Douar Zmamra",
    "gn:population":0,
    "gn:timezone":"Africa/Casablanca",
    "iso:country":"MA",
    "wof:name":"Douar Zmamra",
    "wof:placetype":"locality"
},
  "geometry": {"coordinates":[-4.58614,34.09892],"type":"Point"}
}