{
  "type": "Feature",
  "properties": {
    "gn:admin1_code":"5.0",
    "gn:asciiname":"Ta'init",
    "gn:country_code":"MA",
    "gn:dem":980,
    "gn:feature_class":"P",
    "gn:feature_code":"PPL",
    "gn:name":"Ta\u2019init",
    "gn:population":0,
    "gn:timezone":"Africa/Casablanca",
    "iso:country":"MA",
    "wof:name":"Ta'init",
    "wof:placetype":"locality"
},
  "geometry": {"coordinates":[-6.82708,31.8891],"type":"Point"}
}