{
  "type": "Feature",
  "properties": {
    "gn:admin1_code":"7.0",
    "gn:asciiname":"Douar Id Abdenbi",
    "gn:country_code":"MA",
    "gn:dem":541,
    "gn:feature_class":"P",
    "gn:feature_code":"PPL",
    "gn:name":"Douar Id Abdenbi",
    "gn:population":0,
    "gn:timezone":"Africa/Casablanca",
    "iso:country":"MA",
    "wof:name":"Douar Id Abdenbi",
    "wof:placetype":"locality"
},
  "geometry": {"coordinates":[-9.52031,31.29749],"type":"Point"}
}