{
  "type": "Feature",
  "properties": {
    "gn:admin1_code":"2.0",
    "gn:asciiname":"Douar Lmaghsal Lakehal",
    "gn:country_code":"MA",
    "gn:dem":527,
    "gn:feature_class":"P",
    "gn:feature_code":"PPL",
    "gn:name":"Douar Lmaghsal Lakehal",
    "gn:population":0,
    "gn:timezone":"Africa/Casablanca",
    "iso:country":"MA",
    "wof:name":"Douar Lmaghsal Lakehal",
    "wof:placetype":"locality"
},
  "geometry": {"coordinates":[-1.91325,34.73517],"type":"Point"}
}