{
  "type": "Feature",
  "properties": {
    "gn:admin1_code":"4.0",
    "gn:asciiname":"Douar Oulad Ali Ben Farhoune",
    "gn:country_code":"MA",
    "gn:dem":377,
    "gn:feature_class":"P",
    "gn:feature_code":"PPL",
    "gn:name":"Douar Oulad Ali Ben Farhoune",
    "gn:population":0,
    "gn:timezone":"Africa/Casablanca",
    "iso:country":"MA",
    "wof:name":"Douar Oulad Ali Ben Farhoune",
    "wof:placetype":"locality"
},
  "geometry": {"coordinates":[-6.52288,33.667],"type":"Point"}
}