{
  "type": "Feature",
  "properties": {
    "gn:admin1_code":"7.0",
    "gn:asciiname":"Sidi Hsayn ou-Ali",
    "gn:country_code":"MA",
    "gn:dem":973,
    "gn:feature_class":"P",
    "gn:feature_code":"PPL",
    "gn:name":"Sidi Hsayn ou-Ali",
    "gn:population":0,
    "gn:timezone":"Africa/Casablanca",
    "iso:country":"MA",
    "wof:name":"Sidi Hsayn ou-Ali",
    "wof:placetype":"locality"
},
  "geometry": {"coordinates":[-7.23682,31.60822000000001],"type":"Point"}
}