{
  "type": "Feature",
  "properties": {
    "gn:admin1_code":"7.0",
    "gn:asciiname":"Ait Tameldou",
    "gn:country_code":"MA",
    "gn:dem":613,
    "gn:feature_class":"P",
    "gn:feature_code":"PPL",
    "gn:name":"Ait Tameldou",
    "gn:population":0,
    "gn:timezone":"Africa/Casablanca",
    "iso:country":"MA",
    "wof:name":"Ait Tameldou",
    "wof:placetype":"locality"
},
  "geometry": {"coordinates":[-7.65976,31.60538],"type":"Point"}
}