{
  "type": "Feature",
  "properties": {
    "gn:admin1_code":"08",
    "gn:asciiname":"Tazlaft",
    "gn:country_code":"MA",
    "gn:dem":1125,
    "gn:feature_class":"P",
    "gn:feature_code":"PPL",
    "gn:name":"Tazlaft",
    "gn:population":0,
    "gn:timezone":"Africa/Casablanca",
    "iso:country":"MA",
    "wof:name":"Tazlaft",
    "wof:placetype":"locality"
},
  "geometry": {"coordinates":[-5.36642,31.09886],"type":"Point"}
}