{
  "type": "Feature",
  "properties": {
    "gn:admin1_code":"47.0",
    "gn:asciiname":"Imska",
    "gn:country_code":"MA",
    "gn:dem":1442,
    "gn:feature_class":"P",
    "gn:feature_code":"PPL",
    "gn:name":"Imska",
    "gn:population":0,
    "gn:timezone":"Africa/Casablanca",
    "iso:country":"MA",
    "wof:name":"Imska",
    "wof:placetype":"locality"
},
  "geometry": {"coordinates":[-7.93682,31.20876],"type":"Point"}
}