{
  "type": "Feature",
  "properties": {
    "gn:admin1_code":"9.0",
    "gn:asciiname":"Agni Issagn",
    "gn:country_code":"MA",
    "gn:dem":1458,
    "gn:feature_class":"P",
    "gn:feature_code":"PPL",
    "gn:name":"Agni Issagn",
    "gn:population":0,
    "gn:timezone":"Africa/Casablanca",
    "iso:country":"MA",
    "wof:name":"Agni Issagn",
    "wof:placetype":"locality"
},
  "geometry": {"coordinates":[-9.09901,29.82536],"type":"Point"}
}