{
  "type": "Feature",
  "properties": {
    "gn:admin1_code":"01",
    "gn:asciiname":"Douar Lebsabes",
    "gn:country_code":"MA",
    "gn:dem":237,
    "gn:feature_class":"P",
    "gn:feature_code":"PPL",
    "gn:name":"Douar Lebsabes",
    "gn:population":0,
    "gn:timezone":"Africa/Casablanca",
    "iso:country":"MA",
    "name:und_x_variant":[
        "Bsabesse",
        "Bsabiss",
        "Bsabis",
        "Douar Lebsabes"
    ],
    "wof:name":"Douar Lebsabes",
    "wof:placetype":"locality"
},
  "geometry": {"coordinates":[-5.44916,34.67336],"type":"Point"}
}