{
  "type": "Feature",
  "properties": {
    "gn:admin1_code":"1.0",
    "gn:asciiname":"Bou Hnani",
    "gn:country_code":"MA",
    "gn:dem":6,
    "gn:feature_class":"P",
    "gn:feature_code":"PPL",
    "gn:name":"Bou Hnani",
    "gn:population":0,
    "gn:timezone":"Africa/Casablanca",
    "iso:country":"MA",
    "wof:name":"Bou Hnani",
    "wof:placetype":"locality"
},
  "geometry": {"coordinates":[-6.1217,35.17737],"type":"Point"}
}