{
  "type": "Feature",
  "properties": {
    "gn:admin1_code":"07",
    "gn:asciiname":"Aderar",
    "gn:country_code":"MA",
    "gn:dem":921,
    "gn:feature_class":"P",
    "gn:feature_code":"PPL",
    "gn:name":"Aderar",
    "gn:population":0,
    "gn:timezone":"Africa/Casablanca",
    "iso:country":"MA",
    "name:und_x_variant":[
        "Adrar",
        "Aderar"
    ],
    "wof:name":"Aderar",
    "wof:placetype":"locality"
},
  "geometry": {"coordinates":[-9.3566,30.8967],"type":"Point"}
}