{
  "type": "Feature",
  "properties": {
    "gn:admin1_code":"9.0",
    "gn:asciiname":"Ait Ouzaghar",
    "gn:country_code":"MA",
    "gn:dem":2017,
    "gn:feature_class":"P",
    "gn:feature_code":"PPL",
    "gn:name":"A\u00eft Ouzaghar",
    "gn:population":0,
    "gn:timezone":"Africa/Casablanca",
    "iso:country":"MA",
    "wof:name":"Ait Ouzaghar",
    "wof:placetype":"locality"
},
  "geometry": {"coordinates":[-7.77932,30.82131],"type":"Point"}
}