{
  "type": "Feature",
  "properties": {
    "gn:admin1_code":"03",
    "gn:asciiname":"Aouchtam",
    "gn:country_code":"MA",
    "gn:dem":1083,
    "gn:feature_class":"P",
    "gn:feature_code":"PPL",
    "gn:name":"Aouchtam",
    "gn:population":0,
    "gn:timezone":"Africa/Casablanca",
    "iso:country":"MA",
    "wof:name":"Aouchtam",
    "wof:placetype":"locality"
},
  "geometry": {"coordinates":[-4.28155,34.54099],"type":"Point"}
}