{
  "type": "Feature",
  "properties": {
    "gn:admin1_code":"2.0",
    "gn:asciiname":"Iboudoutene",
    "gn:country_code":"MA",
    "gn:dem":99,
    "gn:feature_class":"P",
    "gn:feature_code":"PPL",
    "gn:name":"Iboudoutene",
    "gn:population":0,
    "gn:timezone":"Africa/Casablanca",
    "iso:country":"MA",
    "wof:name":"Iboudoutene",
    "wof:placetype":"locality"
},
  "geometry": {"coordinates":[-2.55516,35.07604],"type":"Point"}
}