{
  "type": "Feature",
  "properties": {
    "gn:admin1_code":"09",
    "gn:asciiname":"Ghartoum",
    "gn:country_code":"MA",
    "gn:dem":1672,
    "gn:feature_class":"P",
    "gn:feature_code":"PPL",
    "gn:name":"Ghartoum",
    "gn:population":0,
    "gn:timezone":"Africa/Casablanca",
    "iso:country":"MA",
    "name:und_x_variant":[
        "Ghratoun",
        "Grattoun",
        "Ghartoum"
    ],
    "wof:name":"Ghartoum",
    "wof:placetype":"locality"
},
  "geometry": {"coordinates":[-7.85511,30.27576],"type":"Point"}
}