{
  "type": "Feature",
  "properties": {
    "gn:admin1_code":"10",
    "gn:asciiname":"Sidi Hibba",
    "gn:country_code":"MA",
    "gn:dem":346,
    "gn:feature_class":"P",
    "gn:feature_code":"PPL",
    "gn:name":"Sidi Hibba",
    "gn:population":0,
    "gn:timezone":"Africa/Casablanca",
    "iso:country":"MA",
    "name:und_x_variant":[
        "Sidi Heiba",
        "Sidi Hibba"
    ],
    "wof:name":"Sidi Hibba",
    "wof:placetype":"locality"
},
  "geometry": {"coordinates":[-10.29499,29.15034],"type":"Point"}
}