{
  "type": "Feature",
  "properties": {
    "gn:admin1_code":"07",
    "gn:asciiname":"Douar Oulad Alyat Ejjabbala",
    "gn:country_code":"MA",
    "gn:dem":577,
    "gn:feature_class":"P",
    "gn:feature_code":"PPL",
    "gn:name":"Douar Oulad Alyat Ejjabbala",
    "gn:population":0,
    "gn:timezone":"Africa/Casablanca",
    "iso:country":"MA",
    "name:und_x_variant":[
        "Oulad-Alyet"
    ],
    "wof:name":"Douar Oulad Alyat Ejjabbala",
    "wof:placetype":"locality"
},
  "geometry": {"coordinates":[-8.0752,31.88463],"type":"Point"}
}