{
  "type": "Feature",
  "properties": {
    "gn:admin1_code":"7.0",
    "gn:asciiname":"Laanatra",
    "gn:country_code":"MA",
    "gn:dem":282,
    "gn:feature_class":"P",
    "gn:feature_code":"PPL",
    "gn:name":"Laanatra",
    "gn:population":0,
    "gn:timezone":"Africa/Casablanca",
    "iso:country":"MA",
    "wof:name":"Laanatra",
    "wof:placetype":"locality"
},
  "geometry": {"coordinates":[-8.42115,32.29886],"type":"Point"}
}