{
  "type": "Feature",
  "properties": {
    "gn:admin1_code":"8.0",
    "gn:asciiname":"La'zib-n-Tadayt",
    "gn:country_code":"MA",
    "gn:dem":1612,
    "gn:feature_class":"P",
    "gn:feature_code":"PPL",
    "gn:name":"La\u2019zib-n-Tadayt",
    "gn:population":0,
    "gn:timezone":"Africa/Casablanca",
    "iso:country":"MA",
    "wof:name":"La'zib-n-Tadayt",
    "wof:placetype":"locality"
},
  "geometry": {"coordinates":[-6.90068,31.2514],"type":"Point"}
}