{
  "type": "Feature",
  "properties": {
    "gn:admin1_code":"07",
    "gn:asciiname":"Regraga",
    "gn:country_code":"MA",
    "gn:dem":151,
    "gn:feature_class":"P",
    "gn:feature_code":"PPL",
    "gn:name":"Regraga",
    "gn:population":0,
    "gn:timezone":"Africa/Casablanca",
    "iso:country":"MA",
    "name:und_x_variant":[
        "Douar Rgarga",
        "Regraga",
        "Rgarga",
        "Rharga"
    ],
    "wof:name":"Regraga",
    "wof:placetype":"locality"
},
  "geometry": {"coordinates":[-9.03051,32.2611],"type":"Point"}
}