{
  "type": "Feature",
  "properties": {
    "gn:admin1_code":"6.0",
    "gn:asciiname":"Dar al Haj 'Abdallah",
    "gn:country_code":"MA",
    "gn:dem":234,
    "gn:feature_class":"P",
    "gn:feature_code":"PPL",
    "gn:name":"Dar al Haj \u2019Abdallah",
    "gn:population":0,
    "gn:timezone":"Africa/Casablanca",
    "iso:country":"MA",
    "wof:name":"Dar al Haj 'Abdallah",
    "wof:placetype":"locality"
},
  "geometry": {"coordinates":[-7.86451,33.15802],"type":"Point"}
}