{
  "type": "Feature",
  "properties": {
    "gn:admin1_code":"7.0",
    "gn:asciiname":"Arghal",
    "gn:country_code":"MA",
    "gn:dem":1472,
    "gn:feature_class":"P",
    "gn:feature_code":"PPL",
    "gn:name":"Arghal",
    "gn:population":0,
    "gn:timezone":"Africa/Casablanca",
    "iso:country":"MA",
    "wof:name":"Arghal",
    "wof:placetype":"locality"
},
  "geometry": {"coordinates":[-7.40526,31.38146],"type":"Point"}
}