{
  "type": "Feature",
  "properties": {
    "gn:admin1_code":"07",
    "gn:asciiname":"Chqinat",
    "gn:country_code":"MA",
    "gn:dem":97,
    "gn:feature_class":"P",
    "gn:feature_code":"PPL",
    "gn:name":"Chqinat",
    "gn:population":0,
    "gn:timezone":"Africa/Casablanca",
    "iso:country":"MA",
    "name:und_x_variant":[
        "Chninat",
        "Douar Cheninat",
        "Cheninat",
        "Chqinat"
    ],
    "wof:name":"Chqinat",
    "wof:placetype":"locality"
},
  "geometry": {"coordinates":[-9.21494,32.41958],"type":"Point"}
}