{
  "type": "Feature",
  "properties": {
    "gn:admin1_code":"9.0",
    "gn:asciiname":"Tazarine ou Chemal",
    "gn:country_code":"MA",
    "gn:dem":960,
    "gn:feature_class":"P",
    "gn:feature_code":"PPL",
    "gn:name":"Tazarine ou Chemal",
    "gn:population":0,
    "gn:timezone":"Africa/Casablanca",
    "iso:country":"MA",
    "wof:name":"Tazarine ou Chemal",
    "wof:placetype":"locality"
},
  "geometry": {"coordinates":[-9.35174,30.6619],"type":"Point"}
}