{
  "type": "Feature",
  "properties": {
    "gn:admin1_code":"5.0",
    "gn:asciiname":"Agni Nafassi",
    "gn:country_code":"MA",
    "gn:dem":1978,
    "gn:feature_class":"P",
    "gn:feature_code":"PPL",
    "gn:name":"Agni Nafassi",
    "gn:population":0,
    "gn:timezone":"Africa/Casablanca",
    "iso:country":"MA",
    "wof:name":"Agni Nafassi",
    "wof:placetype":"locality"
},
  "geometry": {"coordinates":[-6.90993,31.38268],"type":"Point"}
}