{
  "type": "Feature",
  "properties": {
    "gn:admin1_code":"03",
    "gn:asciiname":"Douar Zbayr",
    "gn:country_code":"MA",
    "gn:dem":468,
    "gn:feature_class":"P",
    "gn:feature_code":"PPL",
    "gn:name":"Douar Zbayr",
    "gn:population":0,
    "gn:timezone":"Africa/Casablanca",
    "iso:country":"MA",
    "name:und_x_variant":[
        "Zbair"
    ],
    "wof:name":"Douar Zbayr",
    "wof:placetype":"locality"
},
  "geometry": {"coordinates":[-4.35104,34.48097],"type":"Point"}
}