{
  "type": "Feature",
  "properties": {
    "gn:country":"MA",
    "gn:fcode":"ADM3",
    "gn:pop":7398,
    "iso:country":"MA",
    "name:ara_x_preferred":[
        "\u0627\u0644\u0643\u062f\u064a\u0629 \u0627\u0644\u0628\u064a\u0636\u0627\u0621"
    ],
    "name:fra_x_preferred":[
        "Imilmaiss"
    ],
    "name:fra_x_variant":[
        "Imilmaiss (CR)",
        "Imilmaiss (Commune Rurale)"
    ],
    "qs:name":"Imilmaiss",
    "qs:photos_9r":0,
    "qs:photos_sr":0,
    "qs:pop_sr":"5",
    "wd:wordcount":60,
    "wof:name":"Imilmaiss",
    "wof:placetype":"localadmin",
    "wof:population":7398
},
  "geometry": {"coordinates":[-8.8202,30.88455],"type":"Point"}
}