{
  "type": "Feature",
  "properties": {
    "gn:admin1_code":"9.0",
    "gn:asciiname":"Teguemmi Ou Amghar",
    "gn:country_code":"MA",
    "gn:dem":148,
    "gn:feature_class":"P",
    "gn:feature_code":"PPL",
    "gn:name":"Teguemmi Ou Amghar",
    "gn:population":0,
    "gn:timezone":"Africa/Casablanca",
    "iso:country":"MA",
    "wof:name":"Teguemmi Ou Amghar",
    "wof:placetype":"locality"
},
  "geometry": {"coordinates":[-9.40386,30.06324],"type":"Point"}
}