{
  "type": "Feature",
  "properties": {
    "gn:admin1_code":"6.0",
    "gn:asciiname":"Htatba",
    "gn:country_code":"MA",
    "gn:dem":157,
    "gn:feature_class":"P",
    "gn:feature_code":"PPL",
    "gn:name":"Htatba",
    "gn:population":0,
    "gn:timezone":"Africa/Casablanca",
    "iso:country":"MA",
    "wof:name":"Htatba",
    "wof:placetype":"locality"
},
  "geometry": {"coordinates":[-8.14518,32.98722],"type":"Point"}
}