{
  "type": "Feature",
  "properties": {
    "gn:country":"MA",
    "gn:fcode":"ADM3",
    "gn:population":42338,
    "iso:country":"MA",
    "name:ara_x_preferred":[
        "\u0633\u064a\u062f\u064a \u064a\u062d\u064a\u0649 \u0627\u0644\u063a\u0631\u0628 (\u0627\u0644\u0628\u0644\u062f\u064a\u0629)"
    ],
    "name:ara_x_variant":[
        "\u0633\u0648\u0642 \u0627\u0644\u0623\u0631\u0628\u0639\u0627\u0621"
    ],
    "name:ary_x_preferred":[
        "\u0633\u0648\u0642 \u0644\u0627\u0631\u0628\u0639"
    ],
    "name:cat_x_preferred":[
        "Souk El Arbaa"
    ],
    "name:ceb_x_preferred":[
        "Souk El Arbaa"
    ],
    "name:deu_x_preferred":[
        "Souk El Arbaa"
    ],
    "name:eng_x_preferred":[
        "Souk El Arbaa"
    ],
    "name:fas_x_preferred":[
        "\u0633\u0648\u0642 \u0627\u0644\u0627\u0631\u0628\u0639\u0627\u0621"
    ],
    "name:fra_x_preferred":[
        "Souk El Arbaa"
    ],
    "name:fra_x_variant":[
        "Souk El Arbaa (MU)",
        "Souk El Arbaa (Commune Urbaine)"
    ],
    "name:ita_x_preferred":[
        "Souk el Arbaa"
    ],
    "name:jpn_x_preferred":[
        "\u30b9\u30fc\u30af\u30fb\u30a8\u30eb\u30fb\u30a2\u30eb\u30d0"
    ],
    "name:nld_x_preferred":[
        "Souk El Arbaa"
    ],
    "name:rus_x_preferred":[
        "\u0421\u0443\u043a-\u044d\u043b\u044c-\u0410\u0440\u0431\u0430"
    ],
    "name:swe_x_preferred":[
        "Souk El Arbaa"
    ],
    "qs:name":"Souk El Arbaa",
    "qs:photos_9r":0,
    "qs:photos_sr":0,
    "qs:pop_sr":"7",
    "wd:wordcount":37,
    "wof:name":"Souk El Arbaa",
    "wof:placetype":"localadmin",
    "wof:population":42338
},
  "geometry": {"coordinates":[-5.99819,34.68252],"type":"Point"}
}