{
  "type": "Feature",
  "properties": {
    "gn:country":"MA",
    "gn:fcode":"ADM3",
    "gn:pop":42338,
    "iso:country":"MA",
    "name:ara_x_preferred":[
        "\u0633\u064a\u062f\u064a \u064a\u062d\u064a\u0649 \u0627\u0644\u063a\u0631\u0628 (\u0627\u0644\u0628\u0644\u062f\u064a\u0629)"
    ],
    "name:fra_x_preferred":[
        "Souk El Arbaa"
    ],
    "name:fra_x_variant":[
        "Souk El Arbaa (MU)",
        "Souk El Arbaa (Commune Urbaine)"
    ],
    "qs:name":"Souk El Arbaa",
    "qs:photos_9r":0,
    "qs:photos_sr":0,
    "qs:pop_sr":"7",
    "wd:wordcount":37,
    "wof:name":"Souk El Arbaa",
    "wof:placetype":"localadmin",
    "wof:population":42338
},
  "geometry": {"coordinates":[-5.99819,34.68252],"type":"Point"}
}