{
  "type": "Feature",
  "properties": {
    "gn:admin1_code":"6.0",
    "gn:asciiname":"Oulad Abd Es-Selam Bel Haj",
    "gn:country_code":"MA",
    "gn:dem":452,
    "gn:feature_class":"P",
    "gn:feature_code":"PPL",
    "gn:name":"Oulad Abd Es-Selam Bel Haj",
    "gn:population":0,
    "gn:timezone":"Africa/Casablanca",
    "iso:country":"MA",
    "wof:name":"Oulad Abd Es-Selam Bel Haj",
    "wof:placetype":"locality"
},
  "geometry": {"coordinates":[-7.56647,32.74844],"type":"Point"}
}