{
  "type": "Feature",
  "properties": {
    "gn:admin1_code":"05",
    "gn:asciiname":"Tarouia",
    "gn:country_code":"MA",
    "gn:dem":909,
    "gn:feature_class":"P",
    "gn:feature_code":"PPL",
    "gn:name":"Tarou\u00efa",
    "gn:population":0,
    "gn:timezone":"Africa/Casablanca",
    "iso:country":"MA",
    "name:und_x_variant":[
        "Tarou\u00efa",
        "Tarhia"
    ],
    "wof:name":"Tarouia",
    "wof:placetype":"locality"
},
  "geometry": {"coordinates":[-7.25488,31.7009],"type":"Point"}
}