{
  "type": "Feature",
  "properties": {
    "gn:admin1_code":"06",
    "gn:asciiname":"Douar Lahmamna",
    "gn:country_code":"MA",
    "gn:dem":112,
    "gn:feature_class":"P",
    "gn:feature_code":"PPL",
    "gn:name":"Douar Lahmamna",
    "gn:population":0,
    "gn:timezone":"Africa/Casablanca",
    "iso:country":"MA",
    "name:und_x_variant":[
        "Douar el Rhoualma"
    ],
    "wof:name":"Douar Lahmamna",
    "wof:placetype":"locality"
},
  "geometry": {"coordinates":[-8.731,32.76758],"type":"Point"}
}