{
  "type": "Feature",
  "properties": {
    "gn:admin1_code":"5.0",
    "gn:asciiname":"Taghrout-n-Ait Halwane",
    "gn:country_code":"MA",
    "gn:dem":978,
    "gn:feature_class":"P",
    "gn:feature_code":"PPL",
    "gn:name":"Taghrout-n-A\u00eft Halwane",
    "gn:population":0,
    "gn:timezone":"Africa/Casablanca",
    "iso:country":"MA",
    "wof:name":"Taghrout-n-Ait Halwane",
    "wof:placetype":"locality"
},
  "geometry": {"coordinates":[-6.40817,32.13169],"type":"Point"}
}