{
  "type": "Feature",
  "properties": {
    "gn:admin1_code":"02",
    "gn:asciiname":"Al Mame",
    "gn:country_code":"MA",
    "gn:dem":1915,
    "gn:feature_class":"P",
    "gn:feature_code":"PPL",
    "gn:name":"Al Mame",
    "gn:population":0,
    "gn:timezone":"Africa/Casablanca",
    "iso:country":"MA",
    "name:und_x_variant":[
        "Almane"
    ],
    "wof:name":"Al Mame",
    "wof:placetype":"locality"
},
  "geometry": {"coordinates":[-3.9423,32.55316],"type":"Point"}
}