{
  "type": "Feature",
  "properties": {
    "gn:admin1_code":"08",
    "gn:asciiname":"Tioughassine",
    "gn:country_code":"MA",
    "gn:dem":1718,
    "gn:feature_class":"P",
    "gn:feature_code":"PPL",
    "gn:name":"Tioughassine",
    "gn:population":0,
    "gn:timezone":"Africa/Casablanca",
    "iso:country":"MA",
    "wof:name":"Tioughassine",
    "wof:placetype":"locality"
},
  "geometry": {"coordinates":[-7.15832,31.24366],"type":"Point"}
}