{
  "type": "Feature",
  "properties": {
    "gn:admin1_code":"3.0",
    "gn:asciiname":"Ait Ben Hsine",
    "gn:country_code":"MA",
    "gn:dem":1146,
    "gn:feature_class":"P",
    "gn:feature_code":"PPL",
    "gn:name":"Ait Ben Hsine",
    "gn:population":0,
    "gn:timezone":"Africa/Casablanca",
    "iso:country":"MA",
    "wof:name":"Ait Ben Hsine",
    "wof:placetype":"locality"
},
  "geometry": {"coordinates":[-5.34384,33.66262],"type":"Point"}
}