{
  "type": "Feature",
  "properties": {
    "gn:admin1_code":"01",
    "gn:asciiname":"Laaouama",
    "gn:country_code":"MA",
    "gn:dem":90,
    "gn:feature_class":"P",
    "gn:feature_code":"PPL",
    "gn:name":"Laaouama",
    "gn:population":0,
    "gn:timezone":"Africa/Casablanca",
    "iso:country":"MA",
    "name:ara_x_preferred":[
        "\u0627\u0644\u0639\u0648\u0627\u0645\u0629"
    ],
    "name:cat_x_preferred":[
        "Laaouama"
    ],
    "name:ceb_x_preferred":[
        "Laaouama"
    ],
    "name:ita_x_preferred":[
        "Laaouama"
    ],
    "name:spa_x_preferred":[
        "Laaouama"
    ],
    "name:swe_x_preferred":[
        "Laaouama"
    ],
    "name:und_x_variant":[
        "El Aouama",
        "Aouama"
    ],
    "name:urd_x_preferred":[
        "\u0627\u0644\u0639\u0648\u0627\u0645\u06c1"
    ],
    "wof:name":"Laaouama",
    "wof:placetype":"locality"
},
  "geometry": {"coordinates":[-5.7934,35.7228],"type":"Point"}
}