{
  "type": "Feature",
  "properties": {
    "gn:admin1_code":"01",
    "gn:asciiname":"Laaouama",
    "gn:country_code":"MA",
    "gn:dem":90,
    "gn:feature_class":"P",
    "gn:feature_code":"PPL",
    "gn:name":"Laaouama",
    "gn:population":0,
    "gn:timezone":"Africa/Casablanca",
    "iso:country":"MA",
    "name:und_x_variant":[
        "El Aouama",
        "Aouama",
        "Laaouama"
    ],
    "wof:name":"Laaouama",
    "wof:placetype":"locality"
},
  "geometry": {"coordinates":[-5.7934,35.7228],"type":"Point"}
}