{
  "type": "Feature",
  "properties": {
    "gn:admin1_code":"07",
    "gn:asciiname":"Ayt Bou Zguia",
    "gn:country_code":"MA",
    "gn:dem":624,
    "gn:feature_class":"P",
    "gn:feature_code":"PPL",
    "gn:name":"Ayt Bou Zguia",
    "gn:population":0,
    "gn:timezone":"Africa/Casablanca",
    "iso:country":"MA",
    "name:und_x_variant":[
        "Sidi Bouzskia",
        "A\u00eft Bou Zguia",
        "Ayt Bou Zguia"
    ],
    "wof:name":"Ayt Bou Zguia",
    "wof:placetype":"locality"
},
  "geometry": {"coordinates":[-7.87603,31.48203],"type":"Point"}
}