{
  "type": "Feature",
  "properties": {
    "gn:admin1_code":"09",
    "gn:asciiname":"Iml Ougadir",
    "gn:country_code":"MA",
    "gn:dem":312,
    "gn:feature_class":"P",
    "gn:feature_code":"PPL",
    "gn:name":"Iml Ougadir",
    "gn:population":0,
    "gn:timezone":"Africa/Casablanca",
    "iso:country":"MA",
    "name:und_x_variant":[
        "Augader",
        "Imi Ougadir",
        "Iml Ougadir"
    ],
    "wof:name":"Iml Ougadir",
    "wof:placetype":"locality"
},
  "geometry": {"coordinates":[-9.04323,30.21357],"type":"Point"}
}