{
  "type": "Feature",
  "properties": {
    "gn:admin1_code":"7.0",
    "gn:asciiname":"Imi-n-Taddart",
    "gn:country_code":"MA",
    "gn:dem":1450,
    "gn:feature_class":"P",
    "gn:feature_code":"PPL",
    "gn:name":"Imi-n-Taddart",
    "gn:population":0,
    "gn:timezone":"Africa/Casablanca",
    "iso:country":"MA",
    "wof:name":"Imi-n-Taddart",
    "wof:placetype":"locality"
},
  "geometry": {"coordinates":[-7.6677,31.25077000000001],"type":"Point"}
}