{
  "type": "Feature",
  "properties": {
    "gn:admin1_code":"07",
    "gn:asciiname":"Douar Lebelaaid",
    "gn:country_code":"MA",
    "gn:dem":370,
    "gn:feature_class":"P",
    "gn:feature_code":"PPL",
    "gn:name":"Douar Lebelaaid",
    "gn:population":0,
    "gn:timezone":"Africa/Casablanca",
    "iso:country":"MA",
    "name:und_x_variant":[
        "Douar Bela\u00efd",
        "Bha\u00efd",
        "Bela\u00efd",
        "Douar Lebelaaid"
    ],
    "wof:name":"Douar Lebelaaid",
    "wof:placetype":"locality"
},
  "geometry": {"coordinates":[-8.28227,32.21528],"type":"Point"}
}