{
  "type": "Feature",
  "properties": {
    "gn:admin1_code":"6.0",
    "gn:asciiname":"La'bab",
    "gn:country_code":"MA",
    "gn:dem":437,
    "gn:feature_class":"P",
    "gn:feature_code":"PPL",
    "gn:name":"La\u2019bab",
    "gn:population":0,
    "gn:timezone":"Africa/Casablanca",
    "iso:country":"MA",
    "wof:name":"La'bab",
    "wof:placetype":"locality"
},
  "geometry": {"coordinates":[-7.10368,32.51541],"type":"Point"}
}