{
  "type": "Feature",
  "properties": {
    "gn:admin1_code":"3.0",
    "gn:asciiname":"Dar Bel Aid",
    "gn:country_code":"MA",
    "gn:dem":1035,
    "gn:feature_class":"P",
    "gn:feature_code":"PPL",
    "gn:name":"Dar Bel Aid",
    "gn:population":0,
    "gn:timezone":"Africa/Casablanca",
    "iso:country":"MA",
    "wof:name":"Dar Bel Aid",
    "wof:placetype":"locality"
},
  "geometry": {"coordinates":[-5.58353,33.60197],"type":"Point"}
}