{
  "type": "Feature",
  "properties": {
    "gn:admin1_code":"6.0",
    "gn:asciiname":"Bhara",
    "gn:country_code":"MA",
    "gn:dem":564,
    "gn:feature_class":"P",
    "gn:feature_code":"PPL",
    "gn:name":"Bhara",
    "gn:population":0,
    "gn:timezone":"Africa/Casablanca",
    "iso:country":"MA",
    "wof:name":"Bhara",
    "wof:placetype":"locality"
},
  "geometry": {"coordinates":[-7.5034,32.91801],"type":"Point"}
}