{
  "type": "Feature",
  "properties": {
    "gn:admin1_code":"03",
    "gn:asciiname":"Rechachma",
    "gn:country_code":"MA",
    "gn:dem":78,
    "gn:feature_class":"P",
    "gn:feature_code":"PPL",
    "gn:name":"Rechachma",
    "gn:population":0,
    "gn:timezone":"Africa/Casablanca",
    "iso:country":"MA",
    "name:und_x_variant":[
        "Ghechachma",
        "Rechachma"
    ],
    "wof:name":"Rechachma",
    "wof:placetype":"locality"
},
  "geometry": {"coordinates":[-5.38261,34.27735999999999],"type":"Point"}
}