{
  "type": "Feature",
  "properties": {
    "gn:country":"MA",
    "gn:fcode":"ADM3",
    "gn:population":20236,
    "iso:country":"MA",
    "name:ara_x_preferred":[
        "\u0644\u0645\u0647\u0627\u0631\u0632\u0629 \u0627\u0644\u0633\u0627\u062d\u0644"
    ],
    "name:ara_x_variant":[
        "\u0648\u0644\u0627\u062f \u0631\u062d\u0645\u0648\u0646"
    ],
    "name:ary_x_preferred":[
        "\u0648\u0644\u0627\u062f \u0631\u062d\u0645\u0648\u0646"
    ],
    "name:cat_x_preferred":[
        "Oulad Rahmoune"
    ],
    "name:ceb_x_preferred":[
        "Oulad Rahmoune"
    ],
    "name:eng_x_preferred":[
        "Oulad Rahmoune"
    ],
    "name:fra_x_preferred":[
        "Oulad Rahmoune"
    ],
    "name:fra_x_variant":[
        "Oulad Rahmoune (CR)",
        "Oulad Rahmoune (Commune Rurale)"
    ],
    "name:ita_x_preferred":[
        "Oulad Rahmoune"
    ],
    "name:swe_x_preferred":[
        "Oulad Rahmoune"
    ],
    "qs:name":"Oulad Rahmoune",
    "qs:photos_9r":0,
    "qs:photos_sr":0,
    "qs:pop_sr":"7",
    "wd:wordcount":61,
    "wof:name":"Oulad Rahmoune",
    "wof:placetype":"localadmin",
    "wof:population":20236
},
  "geometry": {"coordinates":[-8.33704,33.18968],"type":"Point"}
}