{
  "type": "Feature",
  "properties": {
    "gn:country":"MA",
    "gn:fcode":"ADM3",
    "gn:pop":20236,
    "iso:country":"MA",
    "name:ara_x_preferred":[
        "\u0644\u0645\u0647\u0627\u0631\u0632\u0629 \u0627\u0644\u0633\u0627\u062d\u0644"
    ],
    "name:fra_x_preferred":[
        "Oulad Rahmoune"
    ],
    "name:fra_x_variant":[
        "Oulad Rahmoune (CR)",
        "Oulad Rahmoune (Commune Rurale)"
    ],
    "qs:name":"Oulad Rahmoune",
    "qs:photos_9r":0,
    "qs:photos_sr":0,
    "qs:pop_sr":"7",
    "wd:wordcount":61,
    "wof:name":"Oulad Rahmoune",
    "wof:placetype":"localadmin",
    "wof:population":20236
},
  "geometry": {"coordinates":[-8.33704,33.18968],"type":"Point"}
}