{
  "type": "Feature",
  "properties": {
    "gn:admin1_code":"9.0",
    "gn:asciiname":"Ait Takarch",
    "gn:country_code":"MA",
    "gn:dem":446,
    "gn:feature_class":"P",
    "gn:feature_code":"PPL",
    "gn:name":"A\u00eft Takarch",
    "gn:population":0,
    "gn:timezone":"Africa/Casablanca",
    "iso:country":"MA",
    "wof:name":"Ait Takarch",
    "wof:placetype":"locality"
},
  "geometry": {"coordinates":[-9.35619,29.84497],"type":"Point"}
}