{
  "type": "Feature",
  "properties": {
    "gn:admin1_code":"01",
    "gn:asciiname":"Douar Ezzouaoiuyine",
    "gn:country_code":"MA",
    "gn:dem":254,
    "gn:feature_class":"P",
    "gn:feature_code":"PPL",
    "gn:name":"Douar Ezzouaoiuyine",
    "gn:population":0,
    "gn:timezone":"Africa/Casablanca",
    "iso:country":"MA",
    "name:und_x_variant":[
        "Zouaouj\u00e8ne",
        "Ez Zouaouiyne",
        "Es Zouaouiine",
        "Ez Zouaouiine",
        "Douar Ezzouaoiuyine"
    ],
    "wof:name":"Douar Ezzouaoiuyine",
    "wof:placetype":"locality"
},
  "geometry": {"coordinates":[-5.44731,34.65834],"type":"Point"}
}