{
  "type": "Feature",
  "properties": {
    "gn:admin1_code":"5.0",
    "gn:asciiname":"Zagda",
    "gn:country_code":"MA",
    "gn:dem":2057,
    "gn:feature_class":"P",
    "gn:feature_code":"PPL",
    "gn:name":"Zagda",
    "gn:population":0,
    "gn:timezone":"Africa/Casablanca",
    "iso:country":"MA",
    "wof:name":"Zagda",
    "wof:placetype":"locality"
},
  "geometry": {"coordinates":[-7.12104,31.45547],"type":"Point"}
}