{
  "type": "Feature",
  "properties": {
    "gn:admin1_code":"4.0",
    "gn:asciiname":"Ait Ben Qassou",
    "gn:country_code":"MA",
    "gn:dem":273,
    "gn:feature_class":"P",
    "gn:feature_code":"PPL",
    "gn:name":"A\u00eft Ben Qassou",
    "gn:population":0,
    "gn:timezone":"Africa/Casablanca",
    "iso:country":"MA",
    "wof:name":"Ait Ben Qassou",
    "wof:placetype":"locality"
},
  "geometry": {"coordinates":[-6.36456,33.96116],"type":"Point"}
}