{
  "type": "Feature",
  "properties": {
    "gn:admin1_code":"05",
    "gn:asciiname":"Tafrant",
    "gn:country_code":"MA",
    "gn:dem":1196,
    "gn:elevation":"0.0",
    "gn:feature_class":"P",
    "gn:feature_code":"PPL",
    "gn:name":"Tafrant",
    "gn:population":0,
    "gn:timezone":"Africa/Casablanca",
    "iso:country":"MA",
    "name:ara_x_preferred":[
        "\u062a\u0627\u0641\u0631\u0627\u0646\u062a"
    ],
    "name:cat_x_preferred":[
        "Tafrant"
    ],
    "name:ita_x_preferred":[
        "Tafrant"
    ],
    "name:und_x_variant":[
        "Tafrent"
    ],
    "wof:name":"Tafrant",
    "wof:placetype":"locality"
},
  "geometry": {"coordinates":[-6.96061,31.69201],"type":"Point"}
}