{
  "type": "Feature",
  "properties": {
    "gn:admin1_code":"4.0",
    "gn:asciiname":"Douar Lekhmamra",
    "gn:country_code":"MA",
    "gn:dem":105,
    "gn:feature_class":"P",
    "gn:feature_code":"PPL",
    "gn:name":"Douar Lekhmamra",
    "gn:population":0,
    "gn:timezone":"Africa/Casablanca",
    "iso:country":"MA",
    "wof:name":"Douar Lekhmamra",
    "wof:placetype":"locality"
},
  "geometry": {"coordinates":[-5.44593,34.51744],"type":"Point"}
}