{
  "type": "Feature",
  "properties": {
    "gn:admin1_code":"7.0",
    "gn:asciiname":"Zwalil",
    "gn:country_code":"MA",
    "gn:dem":1745,
    "gn:feature_class":"P",
    "gn:feature_code":"PPL",
    "gn:name":"Zwalil",
    "gn:population":0,
    "gn:timezone":"Africa/Casablanca",
    "iso:country":"MA",
    "wof:name":"Zwalil",
    "wof:placetype":"locality"
},
  "geometry": {"coordinates":[-8.41826,31.12361],"type":"Point"}
}