{
  "type": "Feature",
  "properties": {
    "gn:admin1_code":"3.0",
    "gn:asciiname":"Ait Hsine",
    "gn:country_code":"MA",
    "gn:dem":736,
    "gn:feature_class":"P",
    "gn:feature_code":"PPL",
    "gn:name":"Ait Hsine",
    "gn:population":0,
    "gn:timezone":"Africa/Casablanca",
    "iso:country":"MA",
    "wof:name":"Ait Hsine",
    "wof:placetype":"locality"
},
  "geometry": {"coordinates":[-5.28257,33.82387],"type":"Point"}
}