{
  "type": "Feature",
  "properties": {
    "gn:admin1_code":"09",
    "gn:admin2_code":"541.0",
    "gn:admin3_code":"454104092.0",
    "gn:asciiname":"Arazane",
    "gn:country_code":"MA",
    "gn:dem":357,
    "gn:feature_class":"P",
    "gn:feature_code":"PPLA3",
    "gn:name":"Arazane",
    "gn:population":0,
    "gn:timezone":"Africa/Casablanca",
    "iso:country":"MA",
    "name:und_x_variant":[
        "Arazene",
        "Arazane"
    ],
    "wof:name":"Arazane",
    "wof:placetype":"locality"
},
  "geometry": {"coordinates":[-8.60637,30.50346],"type":"Point"}
}