{
  "type": "Feature",
  "properties": {
    "gn:admin1_code":"09",
    "gn:asciiname":"Anamrane",
    "gn:country_code":"MA",
    "gn:dem":393,
    "gn:feature_class":"P",
    "gn:feature_code":"PPL",
    "gn:name":"Anamrane",
    "gn:population":0,
    "gn:timezone":"Africa/Casablanca",
    "iso:country":"MA",
    "name:und_x_variant":[
        "A\u00eft Amrane",
        "Anamrane"
    ],
    "wof:name":"Anamrane",
    "wof:placetype":"locality"
},
  "geometry": {"coordinates":[-9.37627,29.75604],"type":"Point"}
}