{
  "type": "Feature",
  "properties": {
    "gn:admin1_code":"01",
    "gn:asciiname":"Douar Bni Malek",
    "gn:country_code":"MA",
    "gn:dem":200,
    "gn:feature_class":"P",
    "gn:feature_code":"PPL",
    "gn:name":"Douar Bni Malek",
    "gn:population":0,
    "gn:timezone":"Africa/Casablanca",
    "iso:country":"MA",
    "name:und_x_variant":[
        "Douar Beni Malek",
        "Beni Mallek",
        "Beni Malek",
        "Douar Bni Malek"
    ],
    "wof:name":"Douar Bni Malek",
    "wof:placetype":"locality"
},
  "geometry": {"coordinates":[-5.64219,34.78059],"type":"Point"}
}