{
  "type": "Feature",
  "properties": {
    "gn:admin1_code":"6.0",
    "gn:asciiname":"Oulad Ben Tahar",
    "gn:country_code":"MA",
    "gn:dem":118,
    "gn:feature_class":"P",
    "gn:feature_code":"PPL",
    "gn:name":"Oulad Ben Tahar",
    "gn:population":0,
    "gn:timezone":"Africa/Casablanca",
    "iso:country":"MA",
    "wof:name":"Oulad Ben Tahar",
    "wof:placetype":"locality"
},
  "geometry": {"coordinates":[-8.91016,32.58677],"type":"Point"}
}