{
  "type": "Feature",
  "properties": {
    "gn:admin1_code":"2.0",
    "gn:asciiname":"Douar Lehramna",
    "gn:country_code":"MA",
    "gn:dem":642,
    "gn:feature_class":"P",
    "gn:feature_code":"PPL",
    "gn:name":"Douar Lehramna",
    "gn:population":0,
    "gn:timezone":"Africa/Casablanca",
    "iso:country":"MA",
    "wof:name":"Douar Lehramna",
    "wof:placetype":"locality"
},
  "geometry": {"coordinates":[-2.13912,34.71483],"type":"Point"}
}