{
  "type": "Feature",
  "properties": {
    "gn:country":"MA",
    "gn:fcode":"ADM3",
    "gn:population":2995,
    "iso:country":"MA",
    "name:ara_x_preferred":[
        "\u062f\u0628\u062f\u0648 (\u0627\u0644\u0628\u0644\u062f\u064a\u0629)"
    ],
    "name:fra_x_preferred":[
        "Oulad Sidi Abdelhak"
    ],
    "name:fra_x_variant":[
        "Oulad Sidi Abdelhak (CR)",
        "Oulad Sidi Abdelhak (Commune Rurale)"
    ],
    "qs:name":"Oulad Sidi  Abdelhak",
    "qs:photos_9r":0,
    "qs:photos_sr":0,
    "qs:pop_sr":"4",
    "wof:name":"Oulad Sidi Abdelhak",
    "wof:placetype":"localadmin",
    "wof:population":2995
},
  "geometry": {"coordinates":[-1.78552,33.91565],"type":"Point"}
}