{
  "type": "Feature",
  "properties": {
    "gn:admin1_code":"3.0",
    "gn:asciiname":"Douar Tamist Mechkabba",
    "gn:country_code":"MA",
    "gn:dem":1284,
    "gn:feature_class":"P",
    "gn:feature_code":"PPL",
    "gn:name":"Douar Tamist Mechkabba",
    "gn:population":0,
    "gn:timezone":"Africa/Casablanca",
    "iso:country":"MA",
    "wof:name":"Douar Tamist Mechkabba",
    "wof:placetype":"locality"
},
  "geometry": {"coordinates":[-4.02602,34.01768],"type":"Point"}
}