{
  "type": "Feature",
  "properties": {
    "gn:admin1_code":"09",
    "gn:asciiname":"Tadouart",
    "gn:country_code":"MA",
    "gn:dem":194,
    "gn:feature_class":"P",
    "gn:feature_code":"PPL",
    "gn:name":"Tadouart",
    "gn:population":0,
    "gn:timezone":"Africa/Casablanca",
    "iso:country":"MA",
    "name:und_x_variant":[
        "Tadouarte",
        "Tadouart"
    ],
    "wof:name":"Tadouart",
    "wof:placetype":"locality"
},
  "geometry": {"coordinates":[-9.76937,29.72586],"type":"Point"}
}