{
  "type": "Feature",
  "properties": {
    "gn:admin1_code":"07",
    "gn:asciiname":"Zaouit Ait Mimoun",
    "gn:country_code":"MA",
    "gn:dem":1321,
    "gn:feature_class":"P",
    "gn:feature_code":"PPL",
    "gn:name":"Zaou\u00eft A\u00eft Mimoun",
    "gn:population":0,
    "gn:timezone":"Africa/Casablanca",
    "iso:country":"MA",
    "name:und_x_variant":[
        "A\u00eft mimoune",
        "A\u00eft Mimoun",
        "Zaou\u00eft A\u00eft Mimoun"
    ],
    "wof:name":"Zaouit Ait Mimoun",
    "wof:placetype":"locality"
},
  "geometry": {"coordinates":[-7.27169,31.5607],"type":"Point"}
}