{
  "type": "Feature",
  "properties": {
    "gn:admin1_code":"03",
    "gn:asciiname":"Chorfa Moulay Hajja",
    "gn:country_code":"MA",
    "gn:dem":555,
    "gn:feature_class":"P",
    "gn:feature_code":"PPL",
    "gn:name":"Chorfa Moulay Hajja",
    "gn:population":0,
    "gn:timezone":"Africa/Casablanca",
    "iso:country":"MA",
    "wof:name":"Chorfa Moulay Hajja",
    "wof:placetype":"locality"
},
  "geometry": {"coordinates":[-4.43,34.48],"type":"Point"}
}