{
  "type": "Feature",
  "properties": {
    "gn:admin1_code":"09",
    "gn:asciiname":"Tine Chaoui",
    "gn:country_code":"MA",
    "gn:dem":130,
    "gn:feature_class":"P",
    "gn:feature_code":"PPL",
    "gn:name":"Tine Chaoui",
    "gn:population":0,
    "gn:timezone":"Africa/Casablanca",
    "iso:country":"MA",
    "name:und_x_variant":[
        "Ti n\u2019 Chaoui"
    ],
    "wof:name":"Tine Chaoui",
    "wof:placetype":"locality"
},
  "geometry": {"coordinates":[-9.46655,30.04087],"type":"Point"}
}