{
  "type": "Feature",
  "properties": {
    "gn:admin1_code":"1.0",
    "gn:asciiname":"Douar Angzane",
    "gn:country_code":"MA",
    "gn:dem":980,
    "gn:feature_class":"P",
    "gn:feature_code":"PPL",
    "gn:name":"Douar Angzane",
    "gn:population":0,
    "gn:timezone":"Africa/Casablanca",
    "iso:country":"MA",
    "wof:name":"Douar Angzane",
    "wof:placetype":"locality"
},
  "geometry": {"coordinates":[-4.89225,35.12931],"type":"Point"}
}