{
  "type": "Feature",
  "properties": {
    "gn:admin1_code":"01",
    "gn:asciiname":"Tegrega",
    "gn:country_code":"MA",
    "gn:dem":370,
    "gn:feature_class":"P",
    "gn:feature_code":"PPL",
    "gn:name":"Tegrega",
    "gn:population":0,
    "gn:timezone":"Africa/Casablanca",
    "iso:country":"MA",
    "name:und_x_variant":[
        "T\u00e2gagra",
        "Taguerguerat",
        "Tzegregra",
        "Tegrega"
    ],
    "wof:name":"Tegrega",
    "wof:placetype":"locality"
},
  "geometry": {"coordinates":[-4.18633,35.1475],"type":"Point"}
}