{
  "type": "Feature",
  "properties": {
    "gn:country":"MA",
    "gn:fcode":"ADM3",
    "gn:pop":12539,
    "iso:country":"MA",
    "name:ara_x_preferred":[
        "\u0628\u0648\u063a\u0631\u064a\u0628\u0629"
    ],
    "name:fra_x_preferred":[
        "Chouihia"
    ],
    "name:fra_x_variant":[
        "Chouihia (CR)",
        "Chouihia (Commune Rurale)"
    ],
    "qs:name":"Chouihia",
    "qs:photos_9r":0,
    "qs:photos_sr":0,
    "qs:pop_sr":"6",
    "wof:name":"Chouihia",
    "wof:placetype":"localadmin",
    "wof:population":12539
},
  "geometry": {"coordinates":[-2.66371,34.81317],"type":"Point"}
}