{
  "type": "Feature",
  "properties": {
    "gn:admin1_code":"02",
    "gn:asciiname":"Techra",
    "gn:country_code":"MA",
    "gn:dem":556,
    "gn:feature_class":"P",
    "gn:feature_code":"PPL",
    "gn:name":"Techra",
    "gn:population":0,
    "gn:timezone":"Africa/Casablanca",
    "iso:country":"MA",
    "wof:name":"Techra",
    "wof:placetype":"locality"
},
  "geometry": {"coordinates":[-3.55,34.81],"type":"Point"}
}