{
  "type": "Feature",
  "properties": {
    "gn:admin1_code":"7.0",
    "gn:asciiname":"Mezbit",
    "gn:country_code":"MA",
    "gn:dem":1038,
    "gn:feature_class":"P",
    "gn:feature_code":"PPL",
    "gn:name":"Mezbit",
    "gn:population":0,
    "gn:timezone":"Africa/Casablanca",
    "iso:country":"MA",
    "wof:name":"Mezbit",
    "wof:placetype":"locality"
},
  "geometry": {"coordinates":[-9.00999,31.14703],"type":"Point"}
}