{
  "type": "Feature",
  "properties": {
    "gn:admin1_code":"7.0",
    "gn:asciiname":"Oulad Ben Hammou",
    "gn:country_code":"MA",
    "gn:dem":445,
    "gn:feature_class":"P",
    "gn:feature_code":"PPL",
    "gn:name":"Oulad Ben Hammou",
    "gn:population":0,
    "gn:timezone":"Africa/Casablanca",
    "iso:country":"MA",
    "wof:name":"Oulad Ben Hammou",
    "wof:placetype":"locality"
},
  "geometry": {"coordinates":[-9.01635,31.93164],"type":"Point"}
}