{
  "type": "Feature",
  "properties": {
    "gn:admin1_code":"8.0",
    "gn:asciiname":"Tannat",
    "gn:country_code":"MA",
    "gn:dem":1702,
    "gn:feature_class":"P",
    "gn:feature_code":"PPL",
    "gn:name":"Tannat",
    "gn:population":0,
    "gn:timezone":"Africa/Casablanca",
    "iso:country":"MA",
    "wof:name":"Tannat",
    "wof:placetype":"locality"
},
  "geometry": {"coordinates":[-7.23433,31.13453],"type":"Point"}
}