{
  "type": "Feature",
  "properties": {
    "gn:admin1_code":"8.0",
    "gn:asciiname":"Tannat",
    "gn:country_code":"MA",
    "gn:dem":1702,
    "gn:feature_class":"P",
    "gn:feature_code":"PPL",
    "gn:name":"Tannat",
    "gn:population":0,
    "gn:timezone":"Africa/Casablanca",
    "iso:country":"MA",
    "name:bul_x_preferred":[
        "\u0422\u0430\u043d\u0430\u0442"
    ],
    "name:chv_x_preferred":[
        "\u0422\u0430\u043d\u043d\u0430\u0442"
    ],
    "name:deu_x_preferred":[
        "Tannat"
    ],
    "name:fra_x_preferred":[
        "Tannat"
    ],
    "name:nld_x_preferred":[
        "Tannat"
    ],
    "name:pol_x_preferred":[
        "Tannat"
    ],
    "name:por_x_preferred":[
        "Tannat"
    ],
    "name:rus_x_preferred":[
        "\u0422\u0430\u043d\u043d\u0430\u0442"
    ],
    "name:spa_x_preferred":[
        "Tannat"
    ],
    "name:swe_x_preferred":[
        "Tannat"
    ],
    "name:ukr_x_preferred":[
        "\u0422\u0430\u043d\u043d\u0430"
    ],
    "wof:name":"Tannat",
    "wof:placetype":"locality"
},
  "geometry": {"coordinates":[-7.23433,31.13453],"type":"Point"}
}