{
  "type": "Feature",
  "properties": {
    "gn:admin1_code":"7.0",
    "gn:asciiname":"Douar Naji Allal",
    "gn:country_code":"MA",
    "gn:dem":278,
    "gn:feature_class":"P",
    "gn:feature_code":"PPL",
    "gn:name":"Douar Naji Allal",
    "gn:population":0,
    "gn:timezone":"Africa/Casablanca",
    "iso:country":"MA",
    "wof:name":"Douar Naji Allal",
    "wof:placetype":"locality"
},
  "geometry": {"coordinates":[-9.31683,31.79608],"type":"Point"}
}