{
  "type": "Feature",
  "properties": {
    "gn:admin1_code":"06",
    "gn:asciiname":"Dhaba",
    "gn:country_code":"MA",
    "gn:dem":543,
    "gn:feature_class":"P",
    "gn:feature_code":"PPL",
    "gn:name":"Dhaba",
    "gn:population":0,
    "gn:timezone":"Africa/Casablanca",
    "iso:country":"MA",
    "name:und_x_variant":[
        "Douar Djilali Ben Regha\u00ef",
        "Douar Jilali Ben Rerha\u00ef",
        "Dhaba"
    ],
    "wof:name":"Dhaba",
    "wof:placetype":"locality"
},
  "geometry": {"coordinates":[-7.42578,32.8019],"type":"Point"}
}