{
  "type": "Feature",
  "properties": {
    "gn:admin1_code":"06",
    "gn:asciiname":"Dhaba",
    "gn:country_code":"MA",
    "gn:dem":543,
    "gn:feature_class":"P",
    "gn:feature_code":"PPL",
    "gn:name":"Dhaba",
    "gn:population":0,
    "gn:timezone":"Africa/Casablanca",
    "iso:country":"MA",
    "name:afr_x_preferred":[
        "Dhaba"
    ],
    "name:fas_x_preferred":[
        "\u062f\u0628\u0647"
    ],
    "name:guj_x_preferred":[
        "\u0aa2\u0abe\u0aac\u0abe"
    ],
    "name:hin_x_preferred":[
        "\u0922\u093e\u092c\u093e"
    ],
    "name:spa_x_preferred":[
        "Dhaba"
    ],
    "name:und_x_variant":[
        "Douar Djilali Ben Regha\u00ef",
        "Douar Jilali Ben Rerha\u00ef"
    ],
    "wof:name":"Dhaba",
    "wof:placetype":"locality"
},
  "geometry": {"coordinates":[-7.42578,32.8019],"type":"Point"}
}