{
  "type": "Feature",
  "properties": {
    "gn:admin1_code":"2.0",
    "gn:asciiname":"Douar Taghasrout",
    "gn:country_code":"MA",
    "gn:dem":606,
    "gn:feature_class":"P",
    "gn:feature_code":"PPL",
    "gn:name":"Douar Taghasrout",
    "gn:population":0,
    "gn:timezone":"Africa/Casablanca",
    "iso:country":"MA",
    "wof:name":"Douar Taghasrout",
    "wof:placetype":"locality"
},
  "geometry": {"coordinates":[-2.37526,34.82657],"type":"Point"}
}