{
  "type": "Feature",
  "properties": {
    "gn:admin1_code":"07",
    "gn:asciiname":"Mohammed Gouzzouli",
    "gn:country_code":"MA",
    "gn:dem":110,
    "gn:feature_class":"P",
    "gn:feature_code":"PPL",
    "gn:name":"Mohammed Gouzzouli",
    "gn:population":0,
    "gn:timezone":"Africa/Casablanca",
    "iso:country":"MA",
    "name:und_x_variant":[
        "Douar Mohammed Guezzouli",
        "Mohammed Gouzzouli"
    ],
    "wof:name":"Mohammed Gouzzouli",
    "wof:placetype":"locality"
},
  "geometry": {"coordinates":[-9.26,31.96],"type":"Point"}
}