{
  "type": "Feature",
  "properties": {
    "gn:admin1_code":"7.0",
    "gn:asciiname":"Douar Mbarek Ben Said",
    "gn:country_code":"MA",
    "gn:dem":420,
    "gn:feature_class":"P",
    "gn:feature_code":"PPL",
    "gn:name":"Douar Mbarek Ben Said",
    "gn:population":0,
    "gn:timezone":"Africa/Casablanca",
    "iso:country":"MA",
    "wof:name":"Douar Mbarek Ben Said",
    "wof:placetype":"locality"
},
  "geometry": {"coordinates":[-8.43206,31.90466],"type":"Point"}
}