{
  "type": "Feature",
  "properties": {
    "gn:admin1_code":"9.0",
    "gn:asciiname":"Laqsabt",
    "gn:country_code":"MA",
    "gn:dem":1114,
    "gn:feature_class":"P",
    "gn:feature_code":"PPL",
    "gn:name":"Laqsabt",
    "gn:population":0,
    "gn:timezone":"Africa/Casablanca",
    "iso:country":"MA",
    "wof:name":"Laqsabt",
    "wof:placetype":"locality"
},
  "geometry": {"coordinates":[-8.66159,30.21867],"type":"Point"}
}