{
  "type": "Feature",
  "properties": {
    "gn:admin1_code":"09",
    "gn:asciiname":"Awgounz",
    "gn:country_code":"MA",
    "gn:dem":986,
    "gn:feature_class":"P",
    "gn:feature_code":"PPL",
    "gn:name":"Awgounz",
    "gn:population":0,
    "gn:timezone":"Africa/Casablanca",
    "iso:country":"MA",
    "name:und_x_variant":[
        "Aougounz"
    ],
    "wof:name":"Awgounz",
    "wof:placetype":"locality"
},
  "geometry": {"coordinates":[-9.18716,29.82155],"type":"Point"}
}