{
  "type": "Feature",
  "properties": {
    "gn:admin1_code":"09",
    "gn:asciiname":"Assoul",
    "gn:country_code":"MA",
    "gn:dem":1037,
    "gn:feature_class":"P",
    "gn:feature_code":"PPL",
    "gn:name":"Assoul",
    "gn:population":0,
    "gn:timezone":"Africa/Casablanca",
    "iso:country":"MA",
    "wof:name":"Assoul",
    "wof:placetype":"locality"
},
  "geometry": {"coordinates":[-7.89976,30.52002],"type":"Point"}
}