{
  "type": "Feature",
  "properties": {
    "gn:admin1_code":"5.0",
    "gn:asciiname":"Ait Hammou 'ali",
    "gn:country_code":"MA",
    "gn:dem":815,
    "gn:feature_class":"P",
    "gn:feature_code":"PPL",
    "gn:name":"A\u00eft Hammou \u2019ali",
    "gn:population":0,
    "gn:timezone":"Africa/Casablanca",
    "iso:country":"MA",
    "wof:name":"Ait Hammou 'ali",
    "wof:placetype":"locality"
},
  "geometry": {"coordinates":[-6.95268,31.83594],"type":"Point"}
}