{
  "type": "Feature",
  "properties": {
    "gn:admin1_code":"07",
    "gn:asciiname":"Agadir Ait Ameur",
    "gn:country_code":"MA",
    "gn:dem":892,
    "gn:feature_class":"P",
    "gn:feature_code":"PPL",
    "gn:name":"Agadir A\u00eft Ameur",
    "gn:population":0,
    "gn:timezone":"Africa/Casablanca",
    "iso:country":"MA",
    "wof:name":"Agadir Ait Ameur",
    "wof:placetype":"locality"
},
  "geometry": {"coordinates":[-9.21257,31.25248],"type":"Point"}
}