{
  "type": "Feature",
  "properties": {
    "gn:admin1_code":"08",
    "gn:asciiname":"Zawyat Ouzdine",
    "gn:country_code":"MA",
    "gn:dem":1227,
    "gn:feature_class":"P",
    "gn:feature_code":"PPL",
    "gn:name":"Zawyat Ouzdine",
    "gn:population":0,
    "gn:timezone":"Africa/Casablanca",
    "iso:country":"MA",
    "name:und_x_variant":[
        "Zaou\u00efa ouazdine",
        "Zawyat Ouzdine",
        "Zaouia Ouzdine",
        "Zaouiat Ouzdine"
    ],
    "wof:name":"Zawyat Ouzdine",
    "wof:placetype":"locality"
},
  "geometry": {"coordinates":[-6.64359,30.56119],"type":"Point"}
}