{
  "type": "Feature",
  "properties": {
    "gn:admin1_code":"7.0",
    "gn:asciiname":"Douar Legmara",
    "gn:country_code":"MA",
    "gn:dem":167,
    "gn:feature_class":"P",
    "gn:feature_code":"PPL",
    "gn:name":"Douar Legmara",
    "gn:population":0,
    "gn:timezone":"Africa/Casablanca",
    "iso:country":"MA",
    "wof:name":"Douar Legmara",
    "wof:placetype":"locality"
},
  "geometry": {"coordinates":[-9.15287,32.13927],"type":"Point"}
}