{
  "type": "Feature",
  "properties": {
    "gn:country":"MA",
    "gn:fcode":"ADM3",
    "gn:population":12088,
    "iso:country":"MA",
    "name:ara_x_preferred":[
        "\u062a\u0627\u0646\u0642\u0648\u0628"
    ],
    "name:ara_x_variant":[
        "\u0648\u0627\u062f \u0645\u0644\u062d\u0629"
    ],
    "name:ary_x_preferred":[
        "\u0648\u0627\u062f \u0645\u0627\u0644\u062d\u0629"
    ],
    "name:cat_x_preferred":[
        "Oued Malha"
    ],
    "name:ceb_x_preferred":[
        "Oued Malha"
    ],
    "name:eng_x_preferred":[
        "Oued Malha"
    ],
    "name:fra_x_preferred":[
        "Oued Malha"
    ],
    "name:fra_x_variant":[
        "Oued Malha (CR)",
        "Oued Malha (Commune Rurale)"
    ],
    "name:ita_x_preferred":[
        "Oued Malha"
    ],
    "name:spa_x_preferred":[
        "Puente Melha"
    ],
    "name:swe_x_preferred":[
        "Oued Malha"
    ],
    "name:urd_x_preferred":[
        "\u0648\u0627\u062f \u0645\u0644\u062d\u06c1"
    ],
    "qs:name":"Oued Malha",
    "qs:photos_9r":0,
    "qs:photos_sr":0,
    "qs:pop_sr":"6",
    "wd:wordcount":81,
    "wof:name":"Oued Malha",
    "wof:placetype":"localadmin",
    "wof:population":12088
},
  "geometry": {"coordinates":[-5.02018,34.9151],"type":"Point"}
}