{
  "type": "Feature",
  "properties": {
    "gn:country":"MA",
    "gn:fcode":"ADM3",
    "gn:pop":12088,
    "iso:country":"MA",
    "name:ara_x_preferred":[
        "\u062a\u0627\u0646\u0642\u0648\u0628"
    ],
    "name:fra_x_preferred":[
        "Oued Malha"
    ],
    "name:fra_x_variant":[
        "Oued Malha (CR)",
        "Oued Malha (Commune Rurale)"
    ],
    "qs:name":"Oued Malha",
    "qs:photos_9r":0,
    "qs:photos_sr":0,
    "qs:pop_sr":"6",
    "wd:wordcount":81,
    "wof:name":"Oued Malha",
    "wof:placetype":"localadmin",
    "wof:population":12088
},
  "geometry": {"coordinates":[-5.02018,34.9151],"type":"Point"}
}