{
  "type": "Feature",
  "properties": {
    "gn:admin1_code":"08",
    "gn:asciiname":"Tighremt n'Ait Ahmed",
    "gn:country_code":"MA",
    "gn:dem":2254,
    "gn:feature_class":"P",
    "gn:feature_code":"PPL",
    "gn:name":"Tighremt n\u2019Ait Ahmed",
    "gn:population":0,
    "gn:timezone":"Africa/Casablanca",
    "iso:country":"MA",
    "name:und_x_variant":[
        "Tirhemt n\u2019A\u00eft Ahmed",
        "Tirhremt n\u2019Ait Ahmed",
        "Tighremt n\u2019Ait Ahmed",
        "Talat n\u2019A\u00eft Ahmed"
    ],
    "wof:name":"Tighremt n'Ait Ahmed",
    "wof:placetype":"locality"
},
  "geometry": {"coordinates":[-6.31968,31.59228],"type":"Point"}
}