{
  "type": "Feature",
  "properties": {
    "gn:admin1_code":"07",
    "gn:asciiname":"Oulad el Maichat",
    "gn:country_code":"MA",
    "gn:dem":156,
    "gn:feature_class":"P",
    "gn:feature_code":"PPL",
    "gn:name":"Oulad el Ma\u00efchat",
    "gn:population":0,
    "gn:timezone":"Africa/Casablanca",
    "iso:country":"MA",
    "name:und_x_variant":[
        "Ouled Machihia",
        "Oulad el Ma\u00efchat"
    ],
    "wof:name":"Oulad el Maichat",
    "wof:placetype":"locality"
},
  "geometry": {"coordinates":[-9.03679,32.17855],"type":"Point"}
}