{
  "type": "Feature",
  "properties": {
    "gn:admin1_code":"05",
    "gn:asciiname":"Ait 'Ali 'Abdallah",
    "gn:country_code":"MA",
    "gn:dem":1589,
    "gn:feature_class":"P",
    "gn:feature_code":"PPL",
    "gn:name":"A\u00eft \u2019Ali \u2019Abdallah",
    "gn:population":0,
    "gn:timezone":"Africa/Casablanca",
    "iso:country":"MA",
    "name:und_x_variant":[
        "Ait Ali Ou Abdellah",
        "A\u00eft Ali Ou Abdallah",
        "A\u00eft \u2019Ali \u2019Abdallah"
    ],
    "wof:name":"Ait 'Ali 'Abdallah",
    "wof:placetype":"locality"
},
  "geometry": {"coordinates":[-6.30272,32.02055],"type":"Point"}
}