{
  "type": "Feature",
  "properties": {
    "gn:admin1_code":"7.0",
    "gn:asciiname":"Douar Oulad Bouchaib",
    "gn:country_code":"MA",
    "gn:dem":472,
    "gn:feature_class":"P",
    "gn:feature_code":"PPL",
    "gn:name":"Douar Oulad Bouchaib",
    "gn:population":0,
    "gn:timezone":"Africa/Casablanca",
    "iso:country":"MA",
    "wof:name":"Douar Oulad Bouchaib",
    "wof:placetype":"locality"
},
  "geometry": {"coordinates":[-8.28327,32.03838],"type":"Point"}
}