{
  "type": "Feature",
  "properties": {
    "gn:admin1_code":"7.0",
    "gn:asciiname":"Dar Jilall Ben Dima",
    "gn:country_code":"MA",
    "gn:dem":366,
    "gn:feature_class":"P",
    "gn:feature_code":"PPL",
    "gn:name":"Dar Jilall Ben Dima",
    "gn:population":0,
    "gn:timezone":"Africa/Casablanca",
    "iso:country":"MA",
    "wof:name":"Dar Jilall Ben Dima",
    "wof:placetype":"locality"
},
  "geometry": {"coordinates":[-8.38361,31.63839],"type":"Point"}
}