{
  "type": "Feature",
  "properties": {
    "gn:admin1_code":"7.0",
    "gn:asciiname":"Tassila Ourhyout",
    "gn:country_code":"MA",
    "gn:dem":49,
    "gn:feature_class":"P",
    "gn:feature_code":"PPL",
    "gn:name":"Tassila Ourhyout",
    "gn:population":0,
    "gn:timezone":"Africa/Casablanca",
    "iso:country":"MA",
    "wof:name":"Tassila Ourhyout",
    "wof:placetype":"locality"
},
  "geometry": {"coordinates":[-9.81581,31.18663],"type":"Point"}
}