{
  "type": "Feature",
  "properties": {
    "gn:admin1_code":"07",
    "gn:asciiname":"Jaaydat El Bakkouchiya",
    "gn:country_code":"MA",
    "gn:dem":615,
    "gn:feature_class":"P",
    "gn:feature_code":"PPL",
    "gn:name":"Jaaydat El Bakkouchiya",
    "gn:population":0,
    "gn:timezone":"Africa/Casablanca",
    "iso:country":"MA",
    "name:und_x_variant":[
        "Chorfa Ja\u00efdat",
        "Ja\u00efdat",
        "Jaaydat El Bakkouchiya"
    ],
    "wof:name":"Jaaydat El Bakkouchiya",
    "wof:placetype":"locality"
},
  "geometry": {"coordinates":[-7.79402,31.87324000000001],"type":"Point"}
}