{
  "type": "Feature",
  "properties": {
    "gn:admin1_code":"06",
    "gn:asciiname":"Oulad Ben Sassi",
    "gn:country_code":"MA",
    "gn:dem":108,
    "gn:feature_class":"P",
    "gn:feature_code":"PPL",
    "gn:name":"Oulad Ben Sassi",
    "gn:population":0,
    "gn:timezone":"Africa/Casablanca",
    "iso:country":"MA",
    "name:und_x_variant":[
        "Douar Oulad bou Ras"
    ],
    "wof:name":"Oulad Ben Sassi",
    "wof:placetype":"locality"
},
  "geometry": {"coordinates":[-8.5224,33.02289],"type":"Point"}
}