{
  "type": "Feature",
  "properties": {
    "gn:admin1_code":"09",
    "gn:asciiname":"Dahrat",
    "gn:country_code":"MA",
    "gn:dem":592,
    "gn:feature_class":"P",
    "gn:feature_code":"PPL",
    "gn:name":"Dahrat",
    "gn:population":0,
    "gn:timezone":"Africa/Casablanca",
    "iso:country":"MA",
    "name:und_x_variant":[
        "Darat"
    ],
    "wof:name":"Dahrat",
    "wof:placetype":"locality"
},
  "geometry": {"coordinates":[-8.27028,30.66224],"type":"Point"}
}