{
  "type": "Feature",
  "properties": {
    "gn:country":"MA",
    "gn:fcode":"ADM3",
    "gn:population":20126,
    "iso:country":"MA",
    "name:ara_x_preferred":[
        "\u0627\u0644\u062c\u0631\u0641 (\u0627\u0644\u0628\u0644\u062f\u064a\u0629)"
    ],
    "name:fra_x_preferred":[
        "Moulay Ali Cherif"
    ],
    "name:fra_x_variant":[
        "Moulay Ali Cherif (MU)",
        "Moulay Ali Cherif (Commune Urbaine)"
    ],
    "qs:name":"Moulay Ali Cherif",
    "qs:photos_9r":0,
    "qs:photos_sr":0,
    "qs:pop_sr":"7",
    "wof:name":"Moulay Ali Cherif",
    "wof:placetype":"localadmin",
    "wof:population":20126
},
  "geometry": {"coordinates":[-4.2699,31.27285],"type":"Point"}
}