{
  "type": "Feature",
  "properties": {
    "gn:admin1_code":"01",
    "gn:asciiname":"Zaouyet Bni Bakht",
    "gn:country_code":"MA",
    "gn:dem":425,
    "gn:feature_class":"P",
    "gn:feature_code":"PPL",
    "gn:name":"Zaouyet Bni Bakht",
    "gn:population":0,
    "gn:timezone":"Africa/Casablanca",
    "iso:country":"MA",
    "name:und_x_variant":[
        "Zaouia"
    ],
    "wof:name":"Zaouyet Bni Bakht",
    "wof:placetype":"locality"
},
  "geometry": {"coordinates":[-5.01791,35.28986],"type":"Point"}
}