{
  "type": "Feature",
  "properties": {
    "gn:admin1_code":"4.0",
    "gn:asciiname":"Dar El Haj Mohamed Moussa",
    "gn:country_code":"MA",
    "gn:dem":446,
    "gn:feature_class":"P",
    "gn:feature_code":"PPL",
    "gn:name":"Dar El Haj Mohamed Moussa",
    "gn:population":0,
    "gn:timezone":"Africa/Casablanca",
    "iso:country":"MA",
    "wof:name":"Dar El Haj Mohamed Moussa",
    "wof:placetype":"locality"
},
  "geometry": {"coordinates":[-6.49864,33.65037],"type":"Point"}
}