{
  "type": "Feature",
  "properties": {
    "gn:admin1_code":"07",
    "gn:asciiname":"Bouih Ben Aissa",
    "gn:country_code":"MA",
    "gn:dem":158,
    "gn:feature_class":"P",
    "gn:feature_code":"PPL",
    "gn:name":"Bouih Ben A\u00efssa",
    "gn:population":0,
    "gn:timezone":"Africa/Casablanca",
    "iso:country":"MA",
    "name:und_x_variant":[
        "Oulad Bou\u00ef Ben A\u00efssa",
        "Bouih Ben A\u00efssa"
    ],
    "wof:name":"Bouih Ben Aissa",
    "wof:placetype":"locality"
},
  "geometry": {"coordinates":[-9.53,31.68],"type":"Point"}
}