{
  "type": "Feature",
  "properties": {
    "gn:admin1_code":"2.0",
    "gn:asciiname":"Douar Ben Boukhallouf",
    "gn:country_code":"MA",
    "gn:dem":804,
    "gn:feature_class":"P",
    "gn:feature_code":"PPL",
    "gn:name":"Douar Ben Boukhallouf",
    "gn:population":0,
    "gn:timezone":"Africa/Casablanca",
    "iso:country":"MA",
    "wof:name":"Douar Ben Boukhallouf",
    "wof:placetype":"locality"
},
  "geometry": {"coordinates":[-2.18681,34.75839000000001],"type":"Point"}
}