{
  "type": "Feature",
  "properties": {
    "gn:admin1_code":"08",
    "gn:asciiname":"Boudenib",
    "gn:country_code":"MA",
    "gn:dem":957,
    "gn:feature_class":"P",
    "gn:feature_code":"PPL",
    "gn:name":"Boudenib",
    "gn:population":0,
    "gn:timezone":"Africa/Casablanca",
    "iso:country":"MA",
    "name:ara_x_preferred":[
        "\u0628\u0648\u0630\u0646\u064a\u0628"
    ],
    "name:azb_x_preferred":[
        "\u0628\u0648\u0630\u0646\u06cc\u0628"
    ],
    "name:cat_x_preferred":[
        "Boudnib"
    ],
    "name:ceb_x_preferred":[
        "Boudenib"
    ],
    "name:deu_x_preferred":[
        "Boudnib"
    ],
    "name:fas_x_preferred":[
        "\u0628\u0648\u0630\u0646\u06cc\u0628"
    ],
    "name:fra_x_preferred":[
        "Boudnib"
    ],
    "name:ita_x_preferred":[
        "Boudnib"
    ],
    "name:por_x_preferred":[
        "Boudenib"
    ],
    "name:swe_x_preferred":[
        "Boudenib"
    ],
    "name:und_x_variant":[
        "Boudenib Centre"
    ],
    "wof:name":"Boudenib",
    "wof:placetype":"locality"
},
  "geometry": {"coordinates":[-3.60604,31.95229],"type":"Point"}
}