{
  "type": "Feature",
  "properties": {
    "gn:admin1_code":"08",
    "gn:asciiname":"Boudenib",
    "gn:country_code":"MA",
    "gn:dem":957,
    "gn:feature_class":"P",
    "gn:feature_code":"PPL",
    "gn:name":"Boudenib",
    "gn:population":0,
    "gn:timezone":"Africa/Casablanca",
    "iso:country":"MA",
    "name:und_x_variant":[
        "Boudenib Centre",
        "Boudenib"
    ],
    "wof:name":"Boudenib",
    "wof:placetype":"locality"
},
  "geometry": {"coordinates":[-3.60604,31.95229],"type":"Point"}
}