{
  "type": "Feature",
  "properties": {
    "gn:admin1_code":"9.0",
    "gn:asciiname":"Tazoult La'moud",
    "gn:country_code":"MA",
    "gn:dem":551,
    "gn:feature_class":"P",
    "gn:feature_code":"PPL",
    "gn:name":"Tazoult La\u2019moud",
    "gn:population":0,
    "gn:timezone":"Africa/Casablanca",
    "iso:country":"MA",
    "wof:name":"Tazoult La'moud",
    "wof:placetype":"locality"
},
  "geometry": {"coordinates":[-9.25306,29.96933],"type":"Point"}
}