{
  "type": "Feature",
  "properties": {
    "gn:admin1_code":"9.0",
    "gn:asciiname":"Targa",
    "gn:country_code":"MA",
    "gn:dem":1053,
    "gn:feature_class":"P",
    "gn:feature_code":"PPL",
    "gn:name":"Targa",
    "gn:population":0,
    "gn:timezone":"Africa/Casablanca",
    "iso:country":"MA",
    "name:cat_x_preferred":[
        "Targa"
    ],
    "name:ceb_x_preferred":[
        "Targa"
    ],
    "name:ces_x_preferred":[
        "Targa"
    ],
    "name:deu_x_preferred":[
        "Targa"
    ],
    "name:fra_x_preferred":[
        "Targa"
    ],
    "name:ita_x_preferred":[
        "Targa"
    ],
    "name:nld_x_preferred":[
        "Targa"
    ],
    "name:swe_x_preferred":[
        "Targa"
    ],
    "wof:name":"Targa",
    "wof:placetype":"locality"
},
  "geometry": {"coordinates":[-9.11985,29.97221],"type":"Point"}
}