{
  "type": "Feature",
  "properties": {
    "gn:gn_country":"MA",
    "gn:gn_fcode":"ADM3",
    "gn:gn_pop":5119,
    "gn:population":5119,
    "iso:country":"MA",
    "name:ara_x_preferred":[
        "\u062a\u0627\u062f\u064a\u063a\u0648\u0633\u062a"
    ],
    "name:fra_x_preferred":[
        "Amouguer"
    ],
    "name:fra_x_variant":[
        "Amouguer (CR)",
        "Amouguer (Commune Rurale)"
    ],
    "qs_pg:aaroncc":"MA",
    "qs_pg:gn_country":"MA",
    "qs_pg:gn_fcode":"ADM3",
    "qs_pg:gn_pop":5119,
    "qs_pg:name":"Amouguer",
    "qs_pg:photos_9r":0,
    "qs_pg:photos_sr":0,
    "qs_pg:pop_sr":5,
    "qs_pg:qs_pg_placetype":"localadmin",
    "wof:name":"Amouguer",
    "wof:placetype":"localadmin",
    "wof:population":5119
},
  "geometry": {"coordinates":[-4.90879,32.27211],"type":"Point"}
}