{
  "type": "Feature",
  "properties": {
    "gn:admin1_code":"01",
    "gn:asciiname":"Douar Dhar Tazemmourt",
    "gn:country_code":"MA",
    "gn:dem":581,
    "gn:feature_class":"P",
    "gn:feature_code":"PPL",
    "gn:name":"Douar Dhar Tazemmourt",
    "gn:population":0,
    "gn:timezone":"Africa/Casablanca",
    "iso:country":"MA",
    "name:und_x_variant":[
        "Dar Tazammo\u00fbrt"
    ],
    "wof:name":"Douar Dhar Tazemmourt",
    "wof:placetype":"locality"
},
  "geometry": {"coordinates":[-4.08191,35.09188],"type":"Point"}
}