{
  "type": "Feature",
  "properties": {
    "gn:admin1_code":"02",
    "gn:asciiname":"Tifziouine",
    "gn:country_code":"MA",
    "gn:dem":425,
    "gn:feature_class":"P",
    "gn:feature_code":"PPL",
    "gn:name":"Tifziouine",
    "gn:population":0,
    "gn:timezone":"Africa/Casablanca",
    "iso:country":"MA",
    "wof:name":"Tifziouine",
    "wof:placetype":"locality"
},
  "geometry": {"coordinates":[-3.45,34.18],"type":"Point"}
}