{
  "type": "Feature",
  "properties": {
    "gn:country":"MA",
    "gn:fcode":"ADM3",
    "gn:population":11039,
    "iso:country":"MA",
    "name:ara_x_preferred":[
        "\u063a\u0641\u0633\u0627\u064a (\u0627\u0644\u0628\u0644\u062f\u064a\u0629)"
    ],
    "name:ara_x_variant":[
        "\u0639\u064a\u0646 \u0627\u0644\u0634\u0643\u0627\u0643"
    ],
    "name:azb_x_preferred":[
        "\u0639\u06cc\u0646 \u0634\u06a9\u0627\u06a9"
    ],
    "name:cat_x_preferred":[
        "Ain Cheggag"
    ],
    "name:ceb_x_preferred":[
        "A\u00efn Cheggag"
    ],
    "name:fas_x_preferred":[
        "\u0639\u06cc\u0646 \u0634\u06a9\u0627\u06a9"
    ],
    "name:fra_x_preferred":[
        "Ain Cheggag"
    ],
    "name:fra_x_variant":[
        "Ain Cheggag (CR)",
        "Ain Cheggag (Commune Rurale)",
        "A\u00efn Cheggag"
    ],
    "name:ita_x_preferred":[
        "Ain Cheggag"
    ],
    "name:swe_x_preferred":[
        "A\u00efn Cheggag"
    ],
    "qs_pg:aaroncc":"MA",
    "qs_pg:gn_country":"MA",
    "qs_pg:gn_fcode":"ADM3",
    "qs_pg:gn_pop":11039,
    "qs_pg:name":"Ain Cheggag",
    "qs_pg:photos_9r":0,
    "qs_pg:photos_sr":0,
    "qs_pg:pop_sr":6,
    "qs_pg:qs_pg_placetype":"localadmin",
    "wof:name":"Ain Cheggag",
    "wof:placetype":"localadmin",
    "wof:population":11039
},
  "geometry": {"coordinates":[-5.05987,33.86352],"type":"Point"}
}