{
  "type": "Feature",
  "properties": {
    "gn:admin1_code":"7.0",
    "gn:asciiname":"Douar Dat Azizi",
    "gn:country_code":"MA",
    "gn:dem":186,
    "gn:feature_class":"P",
    "gn:feature_code":"PPL",
    "gn:name":"Douar Dat Azizi",
    "gn:population":0,
    "gn:timezone":"Africa/Casablanca",
    "iso:country":"MA",
    "wof:name":"Douar Dat Azizi",
    "wof:placetype":"locality"
},
  "geometry": {"coordinates":[-8.74431,32.35365],"type":"Point"}
}