{
  "type": "Feature",
  "properties": {
    "gn:admin1_code":"7.0",
    "gn:asciiname":"Douar Ouayanna",
    "gn:country_code":"MA",
    "gn:dem":516,
    "gn:feature_class":"P",
    "gn:feature_code":"PPL",
    "gn:name":"Douar Ouayanna",
    "gn:population":0,
    "gn:timezone":"Africa/Casablanca",
    "iso:country":"MA",
    "wof:name":"Douar Ouayanna",
    "wof:placetype":"locality"
},
  "geometry": {"coordinates":[-8.94526,31.94634000000001],"type":"Point"}
}