{
  "type": "Feature",
  "properties": {
    "gn:country":"MA",
    "gn:fcode":"ADM3",
    "gn:pop":19477,
    "iso:country":"MA",
    "name:ara_x_preferred":[
        "\u0645\u0648\u0627\u0644\u064a\u0646 \u0627\u0644\u063a\u0627\u0628\u0629"
    ],
    "name:fra_x_preferred":[
        "Ahfir"
    ],
    "name:fra_x_variant":[
        "Ahfir (MU)",
        "Ahfir (Commune Urbaine)"
    ],
    "qs:name":"Ahfir",
    "qs:photos_9r":0,
    "qs:photos_sr":0,
    "qs:pop_sr":"6",
    "wd:wordcount":46,
    "wof:name":"Ahfir",
    "wof:placetype":"localadmin",
    "wof:population":19477
},
  "geometry": {"coordinates":[-2.10665,34.95274],"type":"Point"}
}