{
  "type": "Feature",
  "properties": {
    "gn:admin1_code":"7.0",
    "gn:asciiname":"Derb Qaouas",
    "gn:country_code":"MA",
    "gn:dem":100,
    "gn:feature_class":"P",
    "gn:feature_code":"PPL",
    "gn:name":"Derb Qaouas",
    "gn:population":0,
    "gn:timezone":"Africa/Casablanca",
    "iso:country":"MA",
    "wof:name":"Derb Qaouas",
    "wof:placetype":"locality"
},
  "geometry": {"coordinates":[-9.24414,32.32062],"type":"Point"}
}