{
  "type": "Feature",
  "properties": {
    "gn:admin1_code":"09",
    "gn:asciiname":"Tagadirt Ou Fella",
    "gn:country_code":"MA",
    "gn:dem":402,
    "gn:feature_class":"P",
    "gn:feature_code":"PPL",
    "gn:name":"Tagadirt Ou Fella",
    "gn:population":0,
    "gn:timezone":"Africa/Casablanca",
    "iso:country":"MA",
    "wof:name":"Tagadirt Ou Fella",
    "wof:placetype":"locality"
},
  "geometry": {"coordinates":[-9.58647,30.49807],"type":"Point"}
}