{
  "type": "Feature",
  "properties": {
    "gn:admin1_code":"9.0",
    "gn:asciiname":"Id Boumhdi",
    "gn:country_code":"MA",
    "gn:dem":482,
    "gn:feature_class":"P",
    "gn:feature_code":"PPL",
    "gn:name":"Id Boumhdi",
    "gn:population":0,
    "gn:timezone":"Africa/Casablanca",
    "iso:country":"MA",
    "wof:name":"Id Boumhdi",
    "wof:placetype":"locality"
},
  "geometry": {"coordinates":[-9.42539,29.6395],"type":"Point"}
}