{
  "type": "Feature",
  "properties": {
    "gn:admin1_code":"10",
    "gn:asciiname":"Id Aachour",
    "gn:country_code":"MA",
    "gn:dem":631,
    "gn:feature_class":"P",
    "gn:feature_code":"PPL",
    "gn:name":"Id Aachour",
    "gn:population":0,
    "gn:timezone":"Africa/Casablanca",
    "iso:country":"MA",
    "name:und_x_variant":[
        "Id Aaxor",
        "Id Aachour"
    ],
    "wof:name":"Id Aachour",
    "wof:placetype":"locality"
},
  "geometry": {"coordinates":[-10.02135,29.22921],"type":"Point"}
}