{
  "type": "Feature",
  "properties": {
    "gn:admin1_code":"10",
    "gn:asciiname":"Ait Ben Cherif",
    "gn:country_code":"MA",
    "gn:dem":330,
    "gn:feature_class":"P",
    "gn:feature_code":"PPL",
    "gn:name":"A\u00eft Ben Cherif",
    "gn:population":0,
    "gn:timezone":"Africa/Casablanca",
    "iso:country":"MA",
    "name:und_x_variant":[
        "Ait Benxerif",
        "A\u00eft Ben Cherif"
    ],
    "wof:name":"Ait Ben Cherif",
    "wof:placetype":"locality"
},
  "geometry": {"coordinates":[-10.04513,29.3787],"type":"Point"}
}