{
  "type": "Feature",
  "properties": {
    "gn:admin1_code":"7.0",
    "gn:asciiname":"Douar Sidi Bou Asmene",
    "gn:country_code":"MA",
    "gn:dem":480,
    "gn:feature_class":"P",
    "gn:feature_code":"PPL",
    "gn:name":"Douar Sidi Bou Asmene",
    "gn:population":0,
    "gn:timezone":"Africa/Casablanca",
    "iso:country":"MA",
    "wof:name":"Douar Sidi Bou Asmene",
    "wof:placetype":"locality"
},
  "geometry": {"coordinates":[-9.46761,31.7329],"type":"Point"}
}