{
  "type": "Feature",
  "properties": {
    "gn:admin1_code":"1.0",
    "gn:asciiname":"Ouaouzgane",
    "gn:country_code":"MA",
    "gn:dem":1352,
    "gn:feature_class":"P",
    "gn:feature_code":"PPL",
    "gn:name":"Ouaouzgane",
    "gn:population":0,
    "gn:timezone":"Africa/Casablanca",
    "iso:country":"MA",
    "name:ara_x_preferred":[
        "\u0648\u0648\u0632\u06ad\u0627\u0646"
    ],
    "name:cat_x_preferred":[
        "Ouaouzgane"
    ],
    "name:ceb_x_preferred":[
        "Ouaouzgane"
    ],
    "name:ita_x_preferred":[
        "Ouaouzgane"
    ],
    "name:swe_x_preferred":[
        "Ouaouzgane"
    ],
    "name:urd_x_preferred":[
        "\u0648\u0648\u0632\u06af\u0627\u0646"
    ],
    "wof:name":"Ouaouzgane",
    "wof:placetype":"locality"
},
  "geometry": {"coordinates":[-4.51813,35.01989],"type":"Point"}
}