{
  "type": "Feature",
  "properties": {
    "gn:admin1_code":"05",
    "gn:asciiname":"Ouanitkh",
    "gn:country_code":"MA",
    "gn:dem":946,
    "gn:elevation":"0.0",
    "gn:feature_class":"P",
    "gn:feature_code":"PPL",
    "gn:name":"Ouanitkh",
    "gn:population":0,
    "gn:timezone":"Africa/Casablanca",
    "iso:country":"MA",
    "wof:name":"Ouanitkh",
    "wof:placetype":"locality"
},
  "geometry": {"coordinates":[-6.79078,31.81819],"type":"Point"}
}