{
  "type": "Feature",
  "properties": {
    "gn:admin1_code":"7.0",
    "gn:asciiname":"Douar Ben El Arbi",
    "gn:country_code":"MA",
    "gn:dem":524,
    "gn:feature_class":"P",
    "gn:feature_code":"PPL",
    "gn:name":"Douar Ben El Arbi",
    "gn:population":0,
    "gn:timezone":"Africa/Casablanca",
    "iso:country":"MA",
    "wof:name":"Douar Ben El Arbi",
    "wof:placetype":"locality"
},
  "geometry": {"coordinates":[-8.92971,32.02643],"type":"Point"}
}