{
  "type": "Feature",
  "properties": {
    "gn:admin1_code":"8.0",
    "gn:asciiname":"Torst",
    "gn:country_code":"MA",
    "gn:dem":1462,
    "gn:feature_class":"P",
    "gn:feature_code":"PPL",
    "gn:name":"Torst",
    "gn:population":0,
    "gn:timezone":"Africa/Casablanca",
    "iso:country":"MA",
    "wof:name":"Torst",
    "wof:placetype":"locality"
},
  "geometry": {"coordinates":[-7.13092,31.1605],"type":"Point"}
}