{
  "type": "Feature",
  "properties": {
    "gn:admin1_code":"03",
    "gn:asciiname":"Ezzaouia Amjour",
    "gn:country_code":"MA",
    "gn:dem":410,
    "gn:feature_class":"P",
    "gn:feature_code":"PPL",
    "gn:name":"Ezzaouia Amjour",
    "gn:population":0,
    "gn:timezone":"Africa/Casablanca",
    "iso:country":"MA",
    "name:und_x_variant":[
        "Dmejot",
        "Zaouia Amjot",
        "Ezzaouia Amjour"
    ],
    "wof:name":"Ezzaouia Amjour",
    "wof:placetype":"locality"
},
  "geometry": {"coordinates":[-5.1357,34.6981],"type":"Point"}
}