{
  "type": "Feature",
  "properties": {
    "gn:admin1_code":"7.0",
    "gn:asciiname":"Acaka",
    "gn:country_code":"MA",
    "gn:dem":1011,
    "gn:feature_class":"P",
    "gn:feature_code":"PPL",
    "gn:name":"A\u00e7aka",
    "gn:population":0,
    "gn:timezone":"Africa/Casablanca",
    "iso:country":"MA",
    "wof:name":"Acaka",
    "wof:placetype":"locality"
},
  "geometry": {"coordinates":[-7.53496,31.45333],"type":"Point"}
}