{
  "type": "Feature",
  "properties": {
    "gn:admin1_code":"2.0",
    "gn:asciiname":"Douar Debabra",
    "gn:country_code":"MA",
    "gn:dem":792,
    "gn:feature_class":"P",
    "gn:feature_code":"PPL",
    "gn:name":"Douar Debabra",
    "gn:population":0,
    "gn:timezone":"Africa/Casablanca",
    "iso:country":"MA",
    "wof:name":"Douar Debabra",
    "wof:placetype":"locality"
},
  "geometry": {"coordinates":[-2.03483,34.4988],"type":"Point"}
}