{
  "type": "Feature",
  "properties": {
    "gn:admin1_code":"6.0",
    "gn:asciiname":"Douar Moualine El Oued",
    "gn:country_code":"MA",
    "gn:dem":240,
    "gn:feature_class":"P",
    "gn:feature_code":"PPL",
    "gn:name":"Douar Moualine El Oued",
    "gn:population":0,
    "gn:timezone":"Africa/Casablanca",
    "iso:country":"MA",
    "wof:name":"Douar Moualine El Oued",
    "wof:placetype":"locality"
},
  "geometry": {"coordinates":[-7.11878,33.51536],"type":"Point"}
}