{
  "type": "Feature",
  "properties": {
    "gn:admin1_code":"7.0",
    "gn:asciiname":"Iguemine",
    "gn:country_code":"MA",
    "gn:dem":653,
    "gn:feature_class":"P",
    "gn:feature_code":"PPL",
    "gn:name":"Iguemine",
    "gn:population":0,
    "gn:timezone":"Africa/Casablanca",
    "iso:country":"MA",
    "wof:name":"Iguemine",
    "wof:placetype":"locality"
},
  "geometry": {"coordinates":[-9.57342,31.23364],"type":"Point"}
}