{
  "type": "Feature",
  "properties": {
    "gn:admin1_code":"03",
    "gn:asciiname":"Zaouia",
    "gn:country_code":"MA",
    "gn:dem":672,
    "gn:feature_class":"P",
    "gn:feature_code":"PPL",
    "gn:name":"Zaouia",
    "gn:population":0,
    "gn:timezone":"Africa/Casablanca",
    "iso:country":"MA",
    "wof:name":"Zaouia",
    "wof:placetype":"locality"
},
  "geometry": {"coordinates":[-4.54768,34.60794],"type":"Point"}
}