{
  "type": "Feature",
  "properties": {
    "gn:admin1_code":"9.0",
    "gn:asciiname":"Ait Hmid",
    "gn:country_code":"MA",
    "gn:dem":625,
    "gn:feature_class":"P",
    "gn:feature_code":"PPL",
    "gn:name":"A\u00eft Hmid",
    "gn:population":0,
    "gn:timezone":"Africa/Casablanca",
    "iso:country":"MA",
    "wof:name":"Ait Hmid",
    "wof:placetype":"locality"
},
  "geometry": {"coordinates":[-8.32411,30.72401],"type":"Point"}
}