{
  "type": "Feature",
  "properties": {
    "gn:admin1_code":"10",
    "gn:asciiname":"Timgrat",
    "gn:country_code":"MA",
    "gn:dem":260,
    "gn:feature_class":"P",
    "gn:feature_code":"PPL",
    "gn:name":"Timgrat",
    "gn:population":0,
    "gn:timezone":"Africa/Casablanca",
    "iso:country":"MA",
    "name:und_x_variant":[
        "Timgrate",
        "Timgrat"
    ],
    "wof:name":"Timgrat",
    "wof:placetype":"locality"
},
  "geometry": {"coordinates":[-10.03,29.45],"type":"Point"}
}