{
  "type": "Feature",
  "properties": {
    "gn:admin1_code":"6.0",
    "gn:asciiname":"Oulad Lhachmi",
    "gn:country_code":"MA",
    "gn:dem":213,
    "gn:feature_class":"P",
    "gn:feature_code":"PPL",
    "gn:name":"Oulad Lhachmi",
    "gn:population":0,
    "gn:timezone":"Africa/Casablanca",
    "iso:country":"MA",
    "wof:name":"Oulad Lhachmi",
    "wof:placetype":"locality"
},
  "geometry": {"coordinates":[-7.254,33.57481],"type":"Point"}
}