{
  "type": "Feature",
  "properties": {
    "gn:admin1_code":"8.0",
    "gn:asciiname":"Amane Zarkuiwane",
    "gn:country_code":"MA",
    "gn:dem":1736,
    "gn:feature_class":"P",
    "gn:feature_code":"PPL",
    "gn:name":"Amane Zarkuiwane",
    "gn:population":0,
    "gn:timezone":"Africa/Casablanca",
    "iso:country":"MA",
    "wof:name":"Amane Zarkuiwane",
    "wof:placetype":"locality"
},
  "geometry": {"coordinates":[-6.85672,31.28556],"type":"Point"}
}