{
  "type": "Feature",
  "properties": {
    "gn:admin1_code":"2.0",
    "gn:asciiname":"Douar Hassi Lahmar",
    "gn:country_code":"MA",
    "gn:dem":923,
    "gn:feature_class":"P",
    "gn:feature_code":"PPL",
    "gn:name":"Douar Hassi Lahmar",
    "gn:population":0,
    "gn:timezone":"Africa/Casablanca",
    "iso:country":"MA",
    "wof:name":"Douar Hassi Lahmar",
    "wof:placetype":"locality"
},
  "geometry": {"coordinates":[-2.21621,34.51618],"type":"Point"}
}