{
  "type": "Feature",
  "properties": {
    "gn:admin1_code":"9.0",
    "gn:asciiname":"Agadir La'rab",
    "gn:country_code":"MA",
    "gn:dem":549,
    "gn:feature_class":"P",
    "gn:feature_code":"PPL",
    "gn:name":"Agadir La\u2019rab",
    "gn:population":0,
    "gn:timezone":"Africa/Casablanca",
    "iso:country":"MA",
    "wof:name":"Agadir La'rab",
    "wof:placetype":"locality"
},
  "geometry": {"coordinates":[-8.4712,30.67898],"type":"Point"}
}