{
  "type": "Feature",
  "properties": {
    "gn:admin1_code":"9.0",
    "gn:asciiname":"Dar Dufilla",
    "gn:country_code":"MA",
    "gn:dem":311,
    "gn:feature_class":"P",
    "gn:feature_code":"PPL",
    "gn:name":"Dar Dufilla",
    "gn:population":0,
    "gn:timezone":"Africa/Casablanca",
    "iso:country":"MA",
    "wof:name":"Dar Dufilla",
    "wof:placetype":"locality"
},
  "geometry": {"coordinates":[-9.7837,30.84956],"type":"Point"}
}