{
  "type": "Feature",
  "properties": {
    "gn:admin1_code":"5.0",
    "gn:asciiname":"Ait Sma'il",
    "gn:country_code":"MA",
    "gn:dem":990,
    "gn:feature_class":"P",
    "gn:feature_code":"PPL",
    "gn:name":"A\u00eft Sma\u2019il",
    "gn:population":0,
    "gn:timezone":"Africa/Casablanca",
    "iso:country":"MA",
    "wof:name":"Ait Sma'il",
    "wof:placetype":"locality"
},
  "geometry": {"coordinates":[-6.97232,31.78874],"type":"Point"}
}