{
  "type": "Feature",
  "properties": {
    "gn:admin1_code":"9.0",
    "gn:asciiname":"Souq Al Kniis Ida Ougnidiyf",
    "gn:country_code":"MA",
    "gn:dem":1203,
    "gn:feature_class":"P",
    "gn:feature_code":"PPL",
    "gn:name":"Souq Al Kniis Ida Ougnidiyf",
    "gn:population":0,
    "gn:timezone":"Africa/Casablanca",
    "iso:country":"MA",
    "wof:name":"Souq Al Kniis Ida Ougnidiyf",
    "wof:placetype":"locality"
},
  "geometry": {"coordinates":[-9.00737,29.86026],"type":"Point"}
}