{
  "type": "Feature",
  "properties": {
    "gn:admin1_code":"01",
    "gn:asciiname":"Bakal",
    "gn:country_code":"MA",
    "gn:dem":315,
    "gn:feature_class":"P",
    "gn:feature_code":"PPL",
    "gn:name":"Bakal",
    "gn:population":0,
    "gn:timezone":"Africa/Casablanca",
    "iso:country":"MA",
    "name:ben_x_preferred":[
        "\u09ac\u09be\u0995\u09be\u09b2"
    ],
    "name:ceb_x_preferred":[
        "Bakal"
    ],
    "name:ell_x_preferred":[
        "\u039c\u03c0\u03b1\u03ba\u03ac\u03bb"
    ],
    "name:heb_x_preferred":[
        "\u05d1\u05d0\u05e7\u05dc"
    ],
    "name:hin_x_preferred":[
        "\u092c\u0915\u093e\u0932"
    ],
    "name:hun_x_preferred":[
        "Bakal"
    ],
    "name:ind_x_preferred":[
        "Bakal"
    ],
    "name:jpn_x_preferred":[
        "\u30d0\u30ab\u30eb"
    ],
    "name:por_x_preferred":[
        "Bakal"
    ],
    "name:spa_x_preferred":[
        "Bakal"
    ],
    "name:swe_x_preferred":[
        "Bakal"
    ],
    "name:tgl_x_preferred":[
        "Bakal"
    ],
    "name:urd_x_preferred":[
        "\u0628\u0627\u06a9\u0627\u0644"
    ],
    "name:vie_x_preferred":[
        "Bakal"
    ],
    "wof:name":"Bakal",
    "wof:placetype":"locality"
},
  "geometry": {"coordinates":[-5.55336,35.03631],"type":"Point"}
}