{
  "type": "Feature",
  "properties": {
    "gn:admin1_code":"01",
    "gn:asciiname":"Bakal",
    "gn:country_code":"MA",
    "gn:dem":315,
    "gn:feature_class":"P",
    "gn:feature_code":"PPL",
    "gn:name":"Bakal",
    "gn:population":0,
    "gn:timezone":"Africa/Casablanca",
    "iso:country":"MA",
    "name:ceb_x_preferred":[
        "Bakal"
    ],
    "name:spa_x_preferred":[
        "Bakal"
    ],
    "name:swe_x_preferred":[
        "Bakal"
    ],
    "name:tgl_x_preferred":[
        "Bakal"
    ],
    "wof:name":"Bakal",
    "wof:placetype":"locality"
},
  "geometry": {"coordinates":[-5.55336,35.03631],"type":"Point"}
}