{
  "type": "Feature",
  "properties": {
    "gn:admin1_code":"9.0",
    "gn:asciiname":"Agard-n-Oudad",
    "gn:country_code":"MA",
    "gn:dem":1462,
    "gn:feature_class":"P",
    "gn:feature_code":"PPL",
    "gn:name":"Agard-n-Oudad",
    "gn:population":0,
    "gn:timezone":"Africa/Casablanca",
    "iso:country":"MA",
    "wof:name":"Agard-n-Oudad",
    "wof:placetype":"locality"
},
  "geometry": {"coordinates":[-8.61881,30.0845],"type":"Point"}
}