{
  "type": "Feature",
  "properties": {
    "gn:admin1_code":"2.0",
    "gn:asciiname":"Douar Zeghoul",
    "gn:country_code":"MA",
    "gn:dem":528,
    "gn:feature_class":"P",
    "gn:feature_code":"PPL",
    "gn:name":"Douar Zeghoul",
    "gn:population":0,
    "gn:timezone":"Africa/Casablanca",
    "iso:country":"MA",
    "wof:name":"Douar Zeghoul",
    "wof:placetype":"locality"
},
  "geometry": {"coordinates":[-3.59377,35.06634],"type":"Point"}
}