{
  "type": "Feature",
  "properties": {
    "gn:admin1_code":"1.0",
    "gn:asciiname":"Dar Ettalih",
    "gn:country_code":"MA",
    "gn:dem":397,
    "gn:feature_class":"P",
    "gn:feature_code":"PPL",
    "gn:name":"Dar Ettalih",
    "gn:population":0,
    "gn:timezone":"Africa/Casablanca",
    "iso:country":"MA",
    "wof:name":"Dar Ettalih",
    "wof:placetype":"locality"
},
  "geometry": {"coordinates":[-5.19599,34.74431],"type":"Point"}
}