{
  "type": "Feature",
  "properties": {
    "gn:admin1_code":"02",
    "gn:asciiname":"Al Ghasli",
    "gn:country_code":"MA",
    "gn:dem":1084,
    "gn:feature_class":"P",
    "gn:feature_code":"PPL",
    "gn:name":"Al Ghasli",
    "gn:population":0,
    "gn:timezone":"Africa/Casablanca",
    "iso:country":"MA",
    "name:und_x_variant":[
        "A\u00eft Abdelli"
    ],
    "wof:name":"Al Ghasli",
    "wof:placetype":"locality"
},
  "geometry": {"coordinates":[-3.18087,32.47903],"type":"Point"}
}