{
  "type": "Feature",
  "properties": {
    "gn:admin1_code":"7.0",
    "gn:asciiname":"Dar Chahid Jillali",
    "gn:country_code":"MA",
    "gn:dem":450,
    "gn:feature_class":"P",
    "gn:feature_code":"PPL",
    "gn:name":"Dar Chahid Jillali",
    "gn:population":0,
    "gn:timezone":"Africa/Casablanca",
    "iso:country":"MA",
    "wof:name":"Dar Chahid Jillali",
    "wof:placetype":"locality"
},
  "geometry": {"coordinates":[-7.66388,32.21975],"type":"Point"}
}