{
  "type": "Feature",
  "properties": {
    "gn:admin1_code":"2.0",
    "gn:asciiname":"Adoui",
    "gn:country_code":"MA",
    "gn:dem":540,
    "gn:feature_class":"P",
    "gn:feature_code":"PPL",
    "gn:name":"Adoui",
    "gn:population":0,
    "gn:timezone":"Africa/Casablanca",
    "iso:country":"MA",
    "wof:name":"Adoui",
    "wof:placetype":"locality"
},
  "geometry": {"coordinates":[-3.44184,35.10281],"type":"Point"}
}