{
  "type": "Feature",
  "properties": {
    "gn:country":"MA",
    "gn:fcode":"ADM3",
    "gn:pop":34851,
    "iso:country":"MA",
    "name:ara_x_preferred":[
        "\u0627\u0643\u062f\u0632 (\u0627\u0644\u0628\u0644\u062f\u064a\u0629)"
    ],
    "name:bos_x_preferred":[
        "Zagora"
    ],
    "name:bul_x_preferred":[
        "\u0417\u0430\u0433\u043e\u0440\u0430"
    ],
    "name:ceb_x_preferred":[
        "Zagora"
    ],
    "name:cym_x_preferred":[
        "Zagora"
    ],
    "name:deu_x_preferred":[
        "Zagora"
    ],
    "name:fra_x_preferred":[
        "Zagora"
    ],
    "name:fra_x_variant":[
        "Zagora (MU)",
        "Zagora (Commune Urbaine)"
    ],
    "name:hrv_x_preferred":[
        "Zagora"
    ],
    "name:hun_x_preferred":[
        "Zagora"
    ],
    "name:ita_x_preferred":[
        "Zagora"
    ],
    "name:kab_x_preferred":[
        "Tazaggurt"
    ],
    "name:lit_x_preferred":[
        "Zagora"
    ],
    "name:nld_x_preferred":[
        "Zagora"
    ],
    "name:pol_x_preferred":[
        "Zagora"
    ],
    "name:rus_x_preferred":[
        "\u0417\u0430\u0433\u043e\u0440\u0430"
    ],
    "name:sco_x_preferred":[
        "Zagora"
    ],
    "name:slv_x_preferred":[
        "Zagora"
    ],
    "name:spa_x_preferred":[
        "Zagora"
    ],
    "name:srp_x_preferred":[
        "\u0417\u0430\u0433\u043e\u0440\u0430"
    ],
    "name:swe_x_preferred":[
        "Zagora"
    ],
    "name:ukr_x_preferred":[
        "\u0417\u0430\u0433\u043e\u0440\u0430"
    ],
    "qs:name":"Zagora",
    "qs:photos_9r":0,
    "qs:photos_sr":0,
    "qs:pop_sr":"7",
    "wd:wordcount":112,
    "wof:name":"Zagora",
    "wof:placetype":"localadmin",
    "wof:population":34851
},
  "geometry": {"coordinates":[-5.83517,30.30452],"type":"Point"}
}