{
  "type": "Feature",
  "properties": {
    "gn:country":"MA",
    "gn:fcode":"ADM3",
    "gn:pop":34851,
    "iso:country":"MA",
    "name:ara_x_preferred":[
        "\u0627\u0643\u062f\u0632 (\u0627\u0644\u0628\u0644\u062f\u064a\u0629)"
    ],
    "name:fra_x_preferred":[
        "Zagora"
    ],
    "name:fra_x_variant":[
        "Zagora (MU)",
        "Zagora (Commune Urbaine)"
    ],
    "qs:name":"Zagora",
    "qs:photos_9r":0,
    "qs:photos_sr":0,
    "qs:pop_sr":"7",
    "wd:wordcount":112,
    "wof:name":"Zagora",
    "wof:placetype":"localadmin",
    "wof:population":34851
},
  "geometry": {"coordinates":[-5.83517,30.30452],"type":"Point"}
}