{
  "type": "Feature",
  "properties": {
    "gn:admin1_code":"07",
    "gn:asciiname":"El Ain",
    "gn:country_code":"MA",
    "gn:dem":681,
    "gn:feature_class":"P",
    "gn:feature_code":"PPL",
    "gn:name":"El A\u00efn",
    "gn:population":0,
    "gn:timezone":"Africa/Casablanca",
    "iso:country":"MA",
    "name:und_x_variant":[
        "El A\u00efn",
        "Al A\u00efn"
    ],
    "wof:name":"El Ain",
    "wof:placetype":"locality"
},
  "geometry": {"coordinates":[-9.18813,31.37351],"type":"Point"}
}