{
  "type": "Feature",
  "properties": {
    "gn:admin1_code":"08",
    "gn:asciiname":"Ihaouna Ikedat",
    "gn:country_code":"MA",
    "gn:dem":2283,
    "gn:feature_class":"P",
    "gn:feature_code":"PPL",
    "gn:name":"Ihaouna Ikedat",
    "gn:population":0,
    "gn:timezone":"Africa/Casablanca",
    "iso:country":"MA",
    "wof:name":"Ihaouna Ikedat",
    "wof:placetype":"locality"
},
  "geometry": {"coordinates":[-5.52786,32.16345],"type":"Point"}
}