{
  "type": "Feature",
  "properties": {
    "gn:admin1_code":"4.0",
    "gn:asciiname":"Larnsatfa",
    "gn:country_code":"MA",
    "gn:dem":12,
    "gn:feature_class":"P",
    "gn:feature_code":"PPL",
    "gn:name":"Larnsatfa",
    "gn:population":0,
    "gn:timezone":"Africa/Casablanca",
    "iso:country":"MA",
    "wof:name":"Larnsatfa",
    "wof:placetype":"locality"
},
  "geometry": {"coordinates":[-6.71101,34.15545],"type":"Point"}
}