{
  "type": "Feature",
  "properties": {
    "gn:admin1_code":"09",
    "gn:asciiname":"Andour",
    "gn:country_code":"MA",
    "gn:dem":1099,
    "gn:feature_class":"P",
    "gn:feature_code":"PPL",
    "gn:name":"Andour",
    "gn:population":0,
    "gn:timezone":"Africa/Casablanca",
    "iso:country":"MA",
    "wof:name":"Andour",
    "wof:placetype":"locality"
},
  "geometry": {"coordinates":[-8.00669,30.64518],"type":"Point"}
}