{
  "type": "Feature",
  "properties": {
    "gn:admin1_code":"6.0",
    "gn:asciiname":"Lakhzazra",
    "gn:country_code":"MA",
    "gn:dem":670,
    "gn:feature_class":"P",
    "gn:feature_code":"PPL",
    "gn:name":"Lakhzazra",
    "gn:population":0,
    "gn:timezone":"Africa/Casablanca",
    "iso:country":"MA",
    "name:ara_x_preferred":[
        "\u0627\u0644\u062e\u0632\u0627\u0632\u0631\u0629"
    ],
    "name:cat_x_preferred":[
        "Lakhzazra"
    ],
    "name:ceb_x_preferred":[
        "Lakhzazra"
    ],
    "name:ita_x_preferred":[
        "Lakhzazra"
    ],
    "name:swe_x_preferred":[
        "Lakhzazra"
    ],
    "name:urd_x_preferred":[
        "\u0644\u06a9\u06be\u0632\u0627\u0632\u0631\u0627"
    ],
    "wof:name":"Lakhzazra",
    "wof:placetype":"locality"
},
  "geometry": {"coordinates":[-7.04581,33.02933],"type":"Point"}
}