{
  "type": "Feature",
  "properties": {
    "gn:admin1_code":"6.0",
    "gn:asciiname":"Bayzat",
    "gn:country_code":"MA",
    "gn:dem":136,
    "gn:feature_class":"P",
    "gn:feature_code":"PPL",
    "gn:name":"Bayzat",
    "gn:population":0,
    "gn:timezone":"Africa/Casablanca",
    "iso:country":"MA",
    "wof:name":"Bayzat",
    "wof:placetype":"locality"
},
  "geometry": {"coordinates":[-8.17614,32.93613],"type":"Point"}
}