{
  "type": "Feature",
  "properties": {
    "gn:admin1_code":"08",
    "gn:asciiname":"Lboui",
    "gn:country_code":"MA",
    "gn:dem":1964,
    "gn:feature_class":"P",
    "gn:feature_code":"PPL",
    "gn:name":"Lboui",
    "gn:population":0,
    "gn:timezone":"Africa/Casablanca",
    "iso:country":"MA",
    "name:und_x_variant":[
        "Ibour"
    ],
    "wof:name":"Lboui",
    "wof:placetype":"locality"
},
  "geometry": {"coordinates":[-7.27894,31.30366],"type":"Point"}
}