{
  "type": "Feature",
  "properties": {
    "gn:admin1_code":"01",
    "gn:asciiname":"Issalloufene",
    "gn:country_code":"MA",
    "gn:dem":427,
    "gn:feature_class":"P",
    "gn:feature_code":"PPL",
    "gn:name":"Issalloufene",
    "gn:population":0,
    "gn:timezone":"Africa/Casablanca",
    "iso:country":"MA",
    "name:und_x_variant":[
        "A\u00efnsoune"
    ],
    "wof:name":"Issalloufene",
    "wof:placetype":"locality"
},
  "geometry": {"coordinates":[-5.2326,35.44595],"type":"Point"}
}