{
  "type": "Feature",
  "properties": {
    "gn:admin1_code":"1.0",
    "gn:asciiname":"Douar Bab Lkoucha",
    "gn:country_code":"MA",
    "gn:dem":280,
    "gn:feature_class":"P",
    "gn:feature_code":"PPL",
    "gn:name":"Douar Bab Lkoucha",
    "gn:population":0,
    "gn:timezone":"Africa/Casablanca",
    "iso:country":"MA",
    "wof:name":"Douar Bab Lkoucha",
    "wof:placetype":"locality"
},
  "geometry": {"coordinates":[-4.21894,35.10847],"type":"Point"}
}