{
  "type": "Feature",
  "properties": {
    "gn:asciiname":"Medina De Rabat",
    "gn:country_code":"MA",
    "gn:dem":23,
    "gn:feature_class":"P",
    "gn:feature_code":"PPL",
    "gn:name":"Medina De Rabat",
    "gn:population":0,
    "gn:timezone":"Africa/Casablanca",
    "iso:country":"MA",
    "wof:name":"Medina De Rabat",
    "wof:placetype":"locality"
},
  "geometry": {"coordinates":[-6.8359,34.02542],"type":"Point"}
}