{
  "type": "Feature",
  "properties": {
    "gn:admin1_code":"08",
    "gn:asciiname":"Ait Ali Ou Khai",
    "gn:country_code":"MA",
    "gn:dem":793,
    "gn:feature_class":"P",
    "gn:feature_code":"PPL",
    "gn:name":"A\u00eft Ali Ou Kha\u00ef",
    "gn:population":0,
    "gn:timezone":"Africa/Casablanca",
    "iso:country":"MA",
    "wof:name":"Ait Ali Ou Khai",
    "wof:placetype":"locality"
},
  "geometry": {"coordinates":[-5.24269,30.84594],"type":"Point"}
}