{
  "type": "Feature",
  "properties": {
    "gn:admin1_code":"9.0",
    "gn:asciiname":"Takout Nabla Ou Arab",
    "gn:country_code":"MA",
    "gn:dem":699,
    "gn:feature_class":"P",
    "gn:feature_code":"PPL",
    "gn:name":"Takout Nabla Ou Arab",
    "gn:population":0,
    "gn:timezone":"Africa/Casablanca",
    "iso:country":"MA",
    "wof:name":"Takout Nabla Ou Arab",
    "wof:placetype":"locality"
},
  "geometry": {"coordinates":[-9.51388,30.75617],"type":"Point"}
}