{
  "type": "Feature",
  "properties": {
    "gn:admin1_code":"05",
    "gn:asciiname":"Douar Oulad Rgui'a",
    "gn:country_code":"MA",
    "gn:dem":434,
    "gn:feature_class":"P",
    "gn:feature_code":"PPL",
    "gn:name":"Douar Oulad Rgui\u2019a",
    "gn:population":0,
    "gn:timezone":"Africa/Casablanca",
    "iso:country":"MA",
    "name:und_x_variant":[
        "Oulad Rouki\u2019a",
        "Oulad Regui\u00e2a",
        "Douar Oulad Rgui\u2019a"
    ],
    "wof:name":"Douar Oulad Rgui'a",
    "wof:placetype":"locality"
},
  "geometry": {"coordinates":[-6.59675,32.45417],"type":"Point"}
}