{
  "type": "Feature",
  "properties": {
    "gn:admin1_code":"07",
    "gn:asciiname":"Gtaybat",
    "gn:country_code":"MA",
    "gn:dem":80,
    "gn:feature_class":"P",
    "gn:feature_code":"PPL",
    "gn:name":"Gtaybat",
    "gn:population":0,
    "gn:timezone":"Africa/Casablanca",
    "iso:country":"MA",
    "name:und_x_variant":[
        "Lagta\u00efbat",
        "Douar Gouta\u00efbat",
        "Gouta\u00efbat",
        "Gtaybat"
    ],
    "wof:name":"Gtaybat",
    "wof:placetype":"locality"
},
  "geometry": {"coordinates":[-9.16911,32.60717],"type":"Point"}
}