{
  "type": "Feature",
  "properties": {
    "gn:admin1_code":"09",
    "gn:asciiname":"Talatane",
    "gn:country_code":"MA",
    "gn:dem":1343,
    "gn:feature_class":"P",
    "gn:feature_code":"PPL",
    "gn:name":"Talatane",
    "gn:population":0,
    "gn:timezone":"Africa/Casablanca",
    "iso:country":"MA",
    "wof:name":"Talatane",
    "wof:placetype":"locality"
},
  "geometry": {"coordinates":[-8.89832,30.89741],"type":"Point"}
}