{
  "type": "Feature",
  "properties": {
    "gn:admin1_code":"2.0",
    "gn:asciiname":"Douar Oulad Sidi Mohamed Harchaoua",
    "gn:country_code":"MA",
    "gn:dem":636,
    "gn:feature_class":"P",
    "gn:feature_code":"PPL",
    "gn:name":"Douar Oulad Sidi Mohamed Harchaoua",
    "gn:population":0,
    "gn:timezone":"Africa/Casablanca",
    "iso:country":"MA",
    "wof:name":"Douar Oulad Sidi Mohamed Harchaoua",
    "wof:placetype":"locality"
},
  "geometry": {"coordinates":[-2.42601,34.53948],"type":"Point"}
}