{
  "type": "Feature",
  "properties": {
    "gn:admin1_code":"09",
    "gn:asciiname":"Aglagal",
    "gn:country_code":"MA",
    "gn:dem":1295,
    "gn:feature_class":"P",
    "gn:feature_code":"PPL",
    "gn:name":"Aglagal",
    "gn:population":0,
    "gn:timezone":"Africa/Casablanca",
    "iso:country":"MA",
    "wof:name":"Aglagal",
    "wof:placetype":"locality"
},
  "geometry": {"coordinates":[-8.19458,30.25257],"type":"Point"}
}