{
  "type": "Feature",
  "properties": {
    "gn:admin1_code":"04",
    "gn:asciiname":"Laanabra",
    "gn:country_code":"MA",
    "gn:dem":79,
    "gn:feature_class":"P",
    "gn:feature_code":"PPL",
    "gn:name":"Laanabra",
    "gn:population":0,
    "gn:timezone":"Africa/Casablanca",
    "iso:country":"MA",
    "name:und_x_variant":[
        "Douar el Anaber",
        "El Anaber",
        "Laanabra"
    ],
    "wof:name":"Laanabra",
    "wof:placetype":"locality"
},
  "geometry": {"coordinates":[-5.87816,34.72825],"type":"Point"}
}