{
  "type": "Feature",
  "properties": {
    "gn:admin1_code":"08",
    "gn:asciiname":"Douar Tam'azzert",
    "gn:country_code":"MA",
    "gn:dem":1667,
    "gn:feature_class":"P",
    "gn:feature_code":"PPL",
    "gn:name":"Douar Tam\u2019azzert",
    "gn:population":0,
    "gn:timezone":"Africa/Casablanca",
    "iso:country":"MA",
    "name:und_x_variant":[
        "Douar Tam\u2019azzert",
        "Tamazert"
    ],
    "wof:name":"Douar Tam'azzert",
    "wof:placetype":"locality"
},
  "geometry": {"coordinates":[-5.2058,32.63656],"type":"Point"}
}