{
  "type": "Feature",
  "properties": {
    "gn:admin1_code":"07",
    "gn:asciiname":"Chioukh",
    "gn:country_code":"MA",
    "gn:dem":174,
    "gn:feature_class":"P",
    "gn:feature_code":"PPL",
    "gn:name":"Chioukh",
    "gn:population":0,
    "gn:timezone":"Africa/Casablanca",
    "iso:country":"MA",
    "name:und_x_variant":[
        "Chiouk",
        "Chioukh"
    ],
    "wof:name":"Chioukh",
    "wof:placetype":"locality"
},
  "geometry": {"coordinates":[-9.07277,32.19109],"type":"Point"}
}