{
  "type": "Feature",
  "properties": {
    "gn:admin1_code":"7.0",
    "gn:asciiname":"Oum Essabyane",
    "gn:country_code":"MA",
    "gn:dem":187,
    "gn:feature_class":"P",
    "gn:feature_code":"PPL",
    "gn:name":"Oum Essabyane",
    "gn:population":0,
    "gn:timezone":"Africa/Casablanca",
    "iso:country":"MA",
    "wof:name":"Oum Essabyane",
    "wof:placetype":"locality"
},
  "geometry": {"coordinates":[-8.78838,32.27406],"type":"Point"}
}