{
  "type": "Feature",
  "properties": {
    "gn:admin1_code":"02",
    "gn:asciiname":"Qcar Oulad El 'Abbas",
    "gn:country_code":"MA",
    "gn:dem":881,
    "gn:feature_class":"P",
    "gn:feature_code":"PPL",
    "gn:name":"Q\u00e7ar Oulad El \u2019Abbas",
    "gn:population":0,
    "gn:timezone":"Africa/Casablanca",
    "iso:country":"MA",
    "name:und_x_variant":[
        "Q\u00e7ar Oulad El \u2019Abbas",
        "Oulad Abbes"
    ],
    "wof:name":"Qcar Oulad El 'Abbas",
    "wof:placetype":"locality"
},
  "geometry": {"coordinates":[-3.03181,32.08138],"type":"Point"}
}