{
  "type": "Feature",
  "properties": {
    "gn:admin1_code":"06",
    "gn:asciiname":"Oulad Raho",
    "gn:country_code":"MA",
    "gn:dem":425,
    "gn:feature_class":"P",
    "gn:feature_code":"PPL",
    "gn:name":"Oulad Raho",
    "gn:population":0,
    "gn:timezone":"Africa/Casablanca",
    "iso:country":"MA",
    "name:und_x_variant":[
        "Dar Oulad Rehou",
        "Oulad Rahou",
        "Oulad Raho"
    ],
    "wof:name":"Oulad Raho",
    "wof:placetype":"locality"
},
  "geometry": {"coordinates":[-7.67965,32.85582],"type":"Point"}
}