{
  "type": "Feature",
  "properties": {
    "gn:country":"MA",
    "gn:fcode":"ADM3",
    "gn:pop":137778,
    "iso:country":"MA",
    "name:ara_x_preferred":[
        "\u062a\u0627\u0632\u0629 (\u0627\u0644\u0628\u0644\u062f\u064a\u0629)"
    ],
    "name:fra_x_preferred":[
        "Taza"
    ],
    "name:fra_x_variant":[
        "Taza (MU)",
        "Taza (Commune Urbaine)"
    ],
    "qs:name":"Taza",
    "qs:photos_9r":0,
    "qs:photos_sr":0,
    "qs:pop_sr":"9",
    "wd:wordcount":977,
    "wof:name":"Taza",
    "wof:placetype":"localadmin",
    "wof:population":137778
},
  "geometry": {"coordinates":[-4.0088,34.215],"type":"Point"}
}