{
  "type": "Feature",
  "properties": {
    "gn:admin1_code":"09",
    "gn:asciiname":"Tannoumst",
    "gn:country_code":"MA",
    "gn:dem":1315,
    "gn:feature_class":"P",
    "gn:feature_code":"PPL",
    "gn:name":"Tannoumst",
    "gn:population":0,
    "gn:timezone":"Africa/Casablanca",
    "iso:country":"MA",
    "name:und_x_variant":[
        "Tanoumest",
        "Der Tijmi",
        "Dar Tiguemmi"
    ],
    "wof:name":"Tannoumst",
    "wof:placetype":"locality"
},
  "geometry": {"coordinates":[-9.10139,29.95165],"type":"Point"}
}