{
  "type": "Feature",
  "properties": {
    "gn:admin1_code":"03",
    "gn:asciiname":"El Khenachfa",
    "gn:country_code":"MA",
    "gn:dem":645,
    "gn:feature_class":"P",
    "gn:feature_code":"PPL",
    "gn:name":"El Khenachfa",
    "gn:population":0,
    "gn:timezone":"Africa/Casablanca",
    "iso:country":"MA",
    "name:und_x_variant":[
        "Khamachfa",
        "El Khenachfa"
    ],
    "wof:name":"El Khenachfa",
    "wof:placetype":"locality"
},
  "geometry": {"coordinates":[-4.88,34.58],"type":"Point"}
}