{
  "type": "Feature",
  "properties": {
    "gn:admin1_code":"6.0",
    "gn:asciiname":"Douar Ettalae",
    "gn:country_code":"MA",
    "gn:dem":529,
    "gn:feature_class":"P",
    "gn:feature_code":"PPL",
    "gn:name":"Douar Ettalae",
    "gn:population":0,
    "gn:timezone":"Africa/Casablanca",
    "iso:country":"MA",
    "wof:name":"Douar Ettalae",
    "wof:placetype":"locality"
},
  "geometry": {"coordinates":[-7.48824,32.66317],"type":"Point"}
}