{
  "type": "Feature",
  "properties": {
    "gn:admin1_code":"6.0",
    "gn:asciiname":"Lahjar Lebyad",
    "gn:country_code":"MA",
    "gn:dem":425,
    "gn:feature_class":"P",
    "gn:feature_code":"PPL",
    "gn:name":"Lahjar Lebyad",
    "gn:population":0,
    "gn:timezone":"Africa/Casablanca",
    "iso:country":"MA",
    "wof:name":"Lahjar Lebyad",
    "wof:placetype":"locality"
},
  "geometry": {"coordinates":[-7.07567,33.31414],"type":"Point"}
}