{
  "type": "Feature",
  "properties": {
    "gn:admin1_code":"9.0",
    "gn:asciiname":"Tilliyn",
    "gn:country_code":"MA",
    "gn:dem":444,
    "gn:feature_class":"P",
    "gn:feature_code":"PPL",
    "gn:name":"Tilliyn",
    "gn:population":0,
    "gn:timezone":"Africa/Casablanca",
    "iso:country":"MA",
    "wof:name":"Tilliyn",
    "wof:placetype":"locality"
},
  "geometry": {"coordinates":[-9.32629,29.65424],"type":"Point"}
}