{
  "type": "Feature",
  "properties": {
    "gn:admin1_code":"09",
    "gn:asciiname":"Arouays",
    "gn:country_code":"MA",
    "gn:dem":64,
    "gn:feature_class":"P",
    "gn:feature_code":"PPL",
    "gn:name":"Arouays",
    "gn:population":0,
    "gn:timezone":"Africa/Casablanca",
    "iso:country":"MA",
    "name:und_x_variant":[
        "Roua\u00efsse",
        "Arrou\u00efs",
        "Arroua\u00efs",
        "Arouays"
    ],
    "wof:name":"Arouays",
    "wof:placetype":"locality"
},
  "geometry": {"coordinates":[-9.59073,30.21321],"type":"Point"}
}