{
  "type": "Feature",
  "properties": {
    "gn:admin1_code":"6.0",
    "gn:asciiname":"Oulad Drhourhi",
    "gn:country_code":"MA",
    "gn:dem":375,
    "gn:feature_class":"P",
    "gn:feature_code":"PPL",
    "gn:name":"Oulad Drhourhi",
    "gn:population":0,
    "gn:timezone":"Africa/Casablanca",
    "iso:country":"MA",
    "wof:name":"Oulad Drhourhi",
    "wof:placetype":"locality"
},
  "geometry": {"coordinates":[-7.75681,32.89791],"type":"Point"}
}