{
  "type": "Feature",
  "properties": {
    "gn:admin1_code":"01",
    "gn:asciiname":"Jebel Zemzem",
    "gn:country_code":"MA",
    "gn:dem":167,
    "gn:feature_class":"P",
    "gn:feature_code":"PPL",
    "gn:name":"Jebel Zemzem",
    "gn:population":0,
    "gn:timezone":"Africa/Casablanca",
    "iso:country":"MA",
    "name:und_x_variant":[
        "Jbel Zemzem",
        "Jebel Zemzem"
    ],
    "wof:name":"Jebel Zemzem",
    "wof:placetype":"locality"
},
  "geometry": {"coordinates":[-5.36501,35.74025],"type":"Point"}
}