{
  "type": "Feature",
  "properties": {
    "gn:admin1_code":"05",
    "gn:asciiname":"Zawyat Ahancal",
    "gn:country_code":"MA",
    "gn:dem":1651,
    "gn:feature_class":"P",
    "gn:feature_code":"PPL",
    "gn:name":"Zawyat Ahan\u00e7al",
    "gn:population":0,
    "gn:timezone":"Africa/Casablanca",
    "iso:country":"MA",
    "name:und_x_variant":[
        "Zaouia Ahanesal",
        "Zaouia Ahansal",
        "Zawyat Ahan\u00e7al"
    ],
    "wof:name":"Zawyat Ahancal",
    "wof:placetype":"locality"
},
  "geometry": {"coordinates":[-6.10118,31.83179],"type":"Point"}
}