{
  "type": "Feature",
  "properties": {
    "gn:admin1_code":"09",
    "gn:asciiname":"Ait Rahmoun",
    "gn:country_code":"MA",
    "gn:dem":186,
    "gn:feature_class":"P",
    "gn:feature_code":"PPL",
    "gn:name":"A\u00eft Rahmoun",
    "gn:population":0,
    "gn:timezone":"Africa/Casablanca",
    "iso:country":"MA",
    "wof:name":"Ait Rahmoun",
    "wof:placetype":"locality"
},
  "geometry": {"coordinates":[-8.99029,30.40802],"type":"Point"}
}