{
  "type": "Feature",
  "properties": {
    "gn:admin1_code":"7.0",
    "gn:asciiname":"Id Jaa",
    "gn:country_code":"MA",
    "gn:dem":169,
    "gn:feature_class":"P",
    "gn:feature_code":"PPL",
    "gn:name":"Id Jaa",
    "gn:population":0,
    "gn:timezone":"Africa/Casablanca",
    "iso:country":"MA",
    "wof:name":"Id Jaa",
    "wof:placetype":"locality"
},
  "geometry": {"coordinates":[-9.7817,31.11147],"type":"Point"}
}