{
  "type": "Feature",
  "properties": {
    "gn:admin1_code":"10",
    "gn:asciiname":"Dahet",
    "gn:country_code":"MA",
    "gn:dem":358,
    "gn:feature_class":"P",
    "gn:feature_code":"PPL",
    "gn:name":"Dahet",
    "gn:population":0,
    "gn:timezone":"Africa/Casablanca",
    "iso:country":"MA",
    "wof:name":"Dahet",
    "wof:placetype":"locality"
},
  "geometry": {"coordinates":[-10.00822,29.35346],"type":"Point"}
}