{
  "type": "Feature",
  "properties": {
    "gn:admin1_code":"08",
    "gn:asciiname":"Ouled Habboub",
    "gn:country_code":"MA",
    "gn:dem":1650,
    "gn:feature_class":"P",
    "gn:feature_code":"PPL",
    "gn:name":"Ouled Habboub",
    "gn:population":0,
    "gn:timezone":"Africa/Casablanca",
    "iso:country":"MA",
    "wof:name":"Ouled Habboub",
    "wof:placetype":"locality"
},
  "geometry": {"coordinates":[-5.2816,32.66599],"type":"Point"}
}