{
  "type": "Feature",
  "properties": {
    "gn:admin1_code":"01",
    "gn:asciiname":"Douar Taglit",
    "gn:country_code":"MA",
    "gn:dem":192,
    "gn:feature_class":"P",
    "gn:feature_code":"PPL",
    "gn:name":"Douar Taglit",
    "gn:population":0,
    "gn:timezone":"Africa/Casablanca",
    "iso:country":"MA",
    "name:und_x_variant":[
        "Taguelt",
        "Taguelit",
        "Douar Taglit"
    ],
    "wof:name":"Douar Taglit",
    "wof:placetype":"locality"
},
  "geometry": {"coordinates":[-4.5346,35.13817],"type":"Point"}
}