{
  "type": "Feature",
  "properties": {
    "gn:admin1_code":"7.0",
    "gn:asciiname":"Ait Sidi Hamou",
    "gn:country_code":"MA",
    "gn:dem":408,
    "gn:feature_class":"P",
    "gn:feature_code":"PPL",
    "gn:name":"A\u00eft Sidi Hamou",
    "gn:population":0,
    "gn:timezone":"Africa/Casablanca",
    "iso:country":"MA",
    "wof:name":"Ait Sidi Hamou",
    "wof:placetype":"locality"
},
  "geometry": {"coordinates":[-9.38822,31.46402],"type":"Point"}
}