{
  "type": "Feature",
  "properties": {
    "gn:admin1_code":"07",
    "gn:asciiname":"Douar Aliouat",
    "gn:country_code":"MA",
    "gn:dem":397,
    "gn:feature_class":"P",
    "gn:feature_code":"PPL",
    "gn:name":"Douar Aliouat",
    "gn:population":0,
    "gn:timezone":"Africa/Casablanca",
    "iso:country":"MA",
    "name:und_x_variant":[
        "Aliouat"
    ],
    "wof:name":"Douar Aliouat",
    "wof:placetype":"locality"
},
  "geometry": {"coordinates":[-8.41319,31.58156],"type":"Point"}
}