{
  "type": "Feature",
  "properties": {
    "gn:admin1_code":"6.0",
    "gn:asciiname":"Oulad Moussa Ben Moslina",
    "gn:country_code":"MA",
    "gn:dem":544,
    "gn:feature_class":"P",
    "gn:feature_code":"PPL",
    "gn:name":"Oulad Moussa Ben Moslina",
    "gn:population":0,
    "gn:timezone":"Africa/Casablanca",
    "iso:country":"MA",
    "wof:name":"Oulad Moussa Ben Moslina",
    "wof:placetype":"locality"
},
  "geometry": {"coordinates":[-7.44824,33.00803],"type":"Point"}
}