{
  "type": "Feature",
  "properties": {
    "gn:admin1_code":"07",
    "gn:asciiname":"El Hameinat",
    "gn:country_code":"MA",
    "gn:dem":732,
    "gn:feature_class":"P",
    "gn:feature_code":"PPL",
    "gn:name":"El Hameinat",
    "gn:population":0,
    "gn:timezone":"Africa/Casablanca",
    "iso:country":"MA",
    "wof:name":"El Hameinat",
    "wof:placetype":"locality"
},
  "geometry": {"coordinates":[-9.30359,31.29015],"type":"Point"}
}