{
  "type": "Feature",
  "properties": {
    "gn:gn_country":"MA",
    "gn:gn_fcode":"ADM3",
    "gn:gn_pop":5008,
    "gn:population":4609,
    "iso:country":"MA",
    "name:ara_x_preferred":[
        "\u0648\u0627\u062f\u064a \u0632\u0645 (\u0627\u0644\u0628\u0644\u062f\u064a\u0629)"
    ],
    "name:fra_x_preferred":[
        "Ain Kaicher"
    ],
    "name:fra_x_variant":[
        "Ain Kaicher (CR)",
        "Ain Kaicher (Commune Rurale)"
    ],
    "qs_pg:aaroncc":"MA",
    "qs_pg:gn_country":"MA",
    "qs_pg:gn_fcode":"ADM3",
    "qs_pg:gn_pop":5008,
    "qs_pg:name":"Ain Kaicher",
    "qs_pg:photos_9r":0,
    "qs_pg:photos_sr":0,
    "qs_pg:pop_sr":5,
    "qs_pg:qs_pg_placetype":"localadmin",
    "wof:name":"Ain Kaicher",
    "wof:placetype":"localadmin",
    "wof:population":4609
},
  "geometry": {"coordinates":[-6.53609,32.77898],"type":"Point"}
}