{
  "type": "Feature",
  "properties": {
    "gn:admin1_code":"07",
    "gn:asciiname":"El Hajeb-n-Ayt Wadouz",
    "gn:country_code":"MA",
    "gn:dem":757,
    "gn:feature_class":"P",
    "gn:feature_code":"PPL",
    "gn:name":"El Hajeb-n-Ayt Wadouz",
    "gn:population":0,
    "gn:timezone":"Africa/Casablanca",
    "iso:country":"MA",
    "name:und_x_variant":[
        "A\u00eft Ouadouz",
        "El Hajeb n\u2019A\u00eft Ouadouz",
        "El Hajeb-n-Ayt Wadouz"
    ],
    "wof:name":"El Hajeb-n-Ayt Wadouz",
    "wof:placetype":"locality"
},
  "geometry": {"coordinates":[-7.77722,31.42459],"type":"Point"}
}