{
  "type": "Feature",
  "properties": {
    "gn:admin1_code":"04",
    "gn:asciiname":"Oulad Aissa Tirs",
    "gn:country_code":"MA",
    "gn:dem":145,
    "gn:feature_class":"P",
    "gn:feature_code":"PPL",
    "gn:name":"Oulad Aissa Tirs",
    "gn:population":0,
    "gn:timezone":"Africa/Casablanca",
    "iso:country":"MA",
    "name:und_x_variant":[
        "Oulad \u2019Issa",
        "Ouled N\u00efssa",
        "Oulad A\u00efssa",
        "Douar Oulad A\u00efssa",
        "Oulad Aissa Tirs"
    ],
    "wof:name":"Oulad Aissa Tirs",
    "wof:placetype":"locality"
},
  "geometry": {"coordinates":[-5.9111,34.67041],"type":"Point"}
}