{
  "type": "Feature",
  "properties": {
    "gn:admin1_code":"9.0",
    "gn:asciiname":"Tizgui",
    "gn:country_code":"MA",
    "gn:dem":1272,
    "gn:feature_class":"P",
    "gn:feature_code":"PPL",
    "gn:name":"Tizgui",
    "gn:population":0,
    "gn:timezone":"Africa/Casablanca",
    "iso:country":"MA",
    "wof:name":"Tizgui",
    "wof:placetype":"locality"
},
  "geometry": {"coordinates":[-8.13848,30.88042],"type":"Point"}
}