{
  "type": "Feature",
  "properties": {
    "gn:admin1_code":"09",
    "gn:asciiname":"Tanarcht",
    "gn:country_code":"MA",
    "gn:dem":1649,
    "gn:feature_class":"P",
    "gn:feature_code":"PPL",
    "gn:name":"Tanarcht",
    "gn:population":0,
    "gn:timezone":"Africa/Casablanca",
    "iso:country":"MA",
    "name:und_x_variant":[
        "Tanarchte",
        "Tenerhch",
        "Tanarcht"
    ],
    "wof:name":"Tanarcht",
    "wof:placetype":"locality"
},
  "geometry": {"coordinates":[-7.94447,30.28049],"type":"Point"}
}