{
  "type": "Feature",
  "properties": {
    "gn:admin1_code":"6.0",
    "gn:asciiname":"Cooperative Ettaqaddom",
    "gn:country_code":"MA",
    "gn:dem":473,
    "gn:feature_class":"P",
    "gn:feature_code":"PPLF",
    "gn:name":"Coop\u00e9rative Ettaqaddom",
    "gn:population":0,
    "gn:timezone":"Africa/Casablanca",
    "iso:country":"MA",
    "wof:name":"Cooperative Ettaqaddom",
    "wof:placetype":"locality"
},
  "geometry": {"coordinates":[-7.25343,32.59028],"type":"Point"}
}