{
  "type": "Feature",
  "properties": {
    "gn:admin1_code":"9.0",
    "gn:asciiname":"Ait bel Haman",
    "gn:country_code":"MA",
    "gn:dem":154,
    "gn:feature_class":"P",
    "gn:feature_code":"PPL",
    "gn:name":"A\u00eft bel Haman",
    "gn:population":0,
    "gn:timezone":"Africa/Casablanca",
    "iso:country":"MA",
    "wof:name":"Ait bel Haman",
    "wof:placetype":"locality"
},
  "geometry": {"coordinates":[-9.1647,30.50004],"type":"Point"}
}