{
  "type": "Feature",
  "properties": {
    "gn:country":"MA",
    "gn:fcode":"ADM3",
    "gn:pop":12153,
    "iso:country":"MA",
    "name:ara_x_preferred":[
        "\u0628\u0646\u064a \u064a\u062e\u0644\u0641"
    ],
    "name:ara_x_variant":[
        "\u0627\u0644\u0646\u0648\u0627\u0635\u0631"
    ],
    "name:bul_x_preferred":[
        "\u041d\u043e\u0443\u0430\u0441\u0435\u0443\u0440"
    ],
    "name:cat_x_preferred":[
        "Nouaceur"
    ],
    "name:ceb_x_preferred":[
        "Nouaseur"
    ],
    "name:deu_x_preferred":[
        "Nouaceur"
    ],
    "name:eng_x_preferred":[
        "Nouaceur"
    ],
    "name:fra_x_preferred":[
        "Nouaceur"
    ],
    "name:fra_x_variant":[
        "Nouaceur (MU)",
        "Nouaceur (Commune Urbaine)"
    ],
    "name:ita_x_preferred":[
        "Nouaceur"
    ],
    "name:jpn_x_preferred":[
        "\u30ce\u30a6\u30a2\u30bb\u30a6\u30eb"
    ],
    "name:nld_x_preferred":[
        "Nouaceur"
    ],
    "name:por_x_preferred":[
        "Nouaceur"
    ],
    "name:swe_x_preferred":[
        "Nouaceur"
    ],
    "qs:name":"Nouaceur",
    "qs:photos_9r":0,
    "qs:photos_sr":0,
    "qs:pop_sr":"6",
    "wd:wordcount":71,
    "wof:name":"Nouaceur",
    "wof:placetype":"localadmin",
    "wof:population":12153
},
  "geometry": {"coordinates":[-7.57927,33.3852],"type":"Point"}
}