{
  "type": "Feature",
  "properties": {
    "gn:admin1_code":"08",
    "gn:asciiname":"Bou Tiguit-n-Waltkit",
    "gn:country_code":"MA",
    "gn:dem":1229,
    "gn:feature_class":"P",
    "gn:feature_code":"PPL",
    "gn:name":"Bou Tiguit-n-Waltkit",
    "gn:population":0,
    "gn:timezone":"Africa/Casablanca",
    "iso:country":"MA",
    "name:und_x_variant":[
        "Bou Tigguit n\u2019Oualrkit"
    ],
    "wof:name":"Bou Tiguit-n-Waltkit",
    "wof:placetype":"locality"
},
  "geometry": {"coordinates":[-5.92113,30.99866],"type":"Point"}
}