{
  "type": "Feature",
  "properties": {
    "gn:admin1_code":"10",
    "gn:asciiname":"Assouakine",
    "gn:country_code":"MA",
    "gn:dem":356,
    "gn:feature_class":"P",
    "gn:feature_code":"PPL",
    "gn:name":"Assouakine",
    "gn:population":0,
    "gn:timezone":"Africa/Casablanca",
    "iso:country":"MA",
    "name:und_x_variant":[
        "Azuakin",
        "Assouakine"
    ],
    "wof:name":"Assouakine",
    "wof:placetype":"locality"
},
  "geometry": {"coordinates":[-10.28,29.11],"type":"Point"}
}