{
  "type": "Feature",
  "properties": {
    "gn:country":"MA",
    "gn:fcode":"ADM3",
    "gn:population":15062,
    "iso:country":"MA",
    "name:ara_x_preferred":[
        "\u062a\u062d\u0646\u0627\u0648\u062a"
    ],
    "name:fra_x_preferred":[
        "Tameslohte"
    ],
    "name:fra_x_variant":[
        "Tameslohte (CR)",
        "Tameslohte (Commune Rurale)"
    ],
    "qs_pg:aaroncc":"MA",
    "qs_pg:gn_country":"MA",
    "qs_pg:gn_fcode":"ADM3",
    "qs_pg:gn_pop":15062,
    "qs_pg:name":"Tameslohte",
    "qs_pg:photos_9r":0,
    "qs_pg:photos_sr":0,
    "qs_pg:pop_sr":6,
    "qs_pg:qs_pg_placetype":"localadmin",
    "wof:name":"Tameslohte",
    "wof:placetype":"localadmin",
    "wof:population":15062
},
  "geometry": {"coordinates":[-8.05316,31.4562],"type":"Point"}
}