{
  "type": "Feature",
  "properties": {
    "gn:admin1_code":"5.0",
    "gn:asciiname":"Sarif",
    "gn:country_code":"MA",
    "gn:dem":1059,
    "gn:feature_class":"P",
    "gn:feature_code":"PPL",
    "gn:name":"Sarif",
    "gn:population":0,
    "gn:timezone":"Africa/Casablanca",
    "iso:country":"MA",
    "name:deu_x_preferred":[
        "Sarif"
    ],
    "wof:name":"Sarif",
    "wof:placetype":"locality"
},
  "geometry": {"coordinates":[-6.01711,32.56824],"type":"Point"}
}