{
  "type": "Feature",
  "properties": {
    "gn:admin1_code":"05",
    "gn:asciiname":"El Mers",
    "gn:country_code":"MA",
    "gn:dem":1716,
    "gn:feature_class":"P",
    "gn:feature_code":"PPL",
    "gn:name":"El Mers",
    "gn:population":0,
    "gn:timezone":"Africa/Casablanca",
    "iso:country":"MA",
    "name:ara_x_preferred":[
        "\u0627\u0644\u0645\u0631\u0633"
    ],
    "name:cat_x_preferred":[
        "El Mers"
    ],
    "name:ita_x_preferred":[
        "El Mers"
    ],
    "wof:name":"El Mers",
    "wof:placetype":"locality"
},
  "geometry": {"coordinates":[-5.58907,32.65408],"type":"Point"}
}