{
  "type": "Feature",
  "properties": {
    "gn:admin1_code":"01",
    "gn:asciiname":"Douar Ait Aissa",
    "gn:country_code":"MA",
    "gn:dem":720,
    "gn:feature_class":"P",
    "gn:feature_code":"PPL",
    "gn:name":"Douar Ait Aissa",
    "gn:population":0,
    "gn:timezone":"Africa/Casablanca",
    "iso:country":"MA",
    "name:und_x_variant":[
        "Ait Aisa",
        "A\u00eft A\u00efssa",
        "Douar Ait Aissa"
    ],
    "wof:name":"Douar Ait Aissa",
    "wof:placetype":"locality"
},
  "geometry": {"coordinates":[-3.85537,35.01121],"type":"Point"}
}