{
  "type": "Feature",
  "properties": {
    "gn:admin1_code":"10.0",
    "gn:asciiname":"Ti-n-Hmed 'Abdallah",
    "gn:country_code":"MA",
    "gn:dem":890,
    "gn:feature_class":"P",
    "gn:feature_code":"PPL",
    "gn:name":"Ti-n-Hmed \u2019Abdallah",
    "gn:population":0,
    "gn:timezone":"Africa/Casablanca",
    "iso:country":"MA",
    "wof:name":"Ti-n-Hmed 'Abdallah",
    "wof:placetype":"locality"
},
  "geometry": {"coordinates":[-9.75085,29.39536],"type":"Point"}
}