{
  "type": "Feature",
  "properties": {
    "gn:admin1_code":"7.0",
    "gn:asciiname":"Lkreim",
    "gn:country_code":"MA",
    "gn:dem":510,
    "gn:feature_class":"P",
    "gn:feature_code":"PPL",
    "gn:name":"Lkre\u00efm",
    "gn:population":0,
    "gn:timezone":"Africa/Casablanca",
    "iso:country":"MA",
    "wof:name":"Lkreim",
    "wof:placetype":"locality"
},
  "geometry": {"coordinates":[-8.74167,31.38859],"type":"Point"}
}