{
  "type": "Feature",
  "properties": {
    "gn:admin1_code":"5.0",
    "gn:asciiname":"Aghbalou",
    "gn:country_code":"MA",
    "gn:dem":791,
    "gn:feature_class":"P",
    "gn:feature_code":"PPL",
    "gn:name":"Aghbalou",
    "gn:population":0,
    "gn:timezone":"Africa/Casablanca",
    "iso:country":"MA",
    "name:fra_x_preferred":[
        "Aghbalou"
    ],
    "name:ron_x_preferred":[
        "Aghbalou"
    ],
    "wof:name":"Aghbalou",
    "wof:placetype":"locality"
},
  "geometry": {"coordinates":[-6.63579,32.07404],"type":"Point"}
}