{
  "type": "Feature",
  "properties": {
    "gn:admin1_code":"09",
    "gn:asciiname":"Imi Ou Guemmi n'Ait Ilougane",
    "gn:country_code":"MA",
    "gn:dem":246,
    "gn:feature_class":"P",
    "gn:feature_code":"PPL",
    "gn:name":"Imi Ou Guemmi n\u2019A\u00eft Ilougane",
    "gn:population":0,
    "gn:timezone":"Africa/Casablanca",
    "iso:country":"MA",
    "name:und_x_variant":[
        "Mourgourni",
        "Mourgoumi",
        "Imi Ou Guemmi n\u2019A\u00eft Ilougane"
    ],
    "wof:name":"Imi Ou Guemmi n'Ait Ilougane",
    "wof:placetype":"locality"
},
  "geometry": {"coordinates":[-9.37697,29.87876],"type":"Point"}
}