{
  "type": "Feature",
  "properties": {
    "gn:admin1_code":"9.0",
    "gn:asciiname":"Targa",
    "gn:country_code":"MA",
    "gn:dem":1849,
    "gn:feature_class":"P",
    "gn:feature_code":"PPL",
    "gn:name":"Targa",
    "gn:population":0,
    "gn:timezone":"Africa/Casablanca",
    "iso:country":"MA",
    "wof:name":"Targa",
    "wof:placetype":"locality"
},
  "geometry": {"coordinates":[-7.93302,30.97332],"type":"Point"}
}