{
  "type": "Feature",
  "properties": {
    "gn:admin1_code":"01",
    "gn:asciiname":"Tagzirt",
    "gn:country_code":"MA",
    "gn:dem":1253,
    "gn:feature_class":"P",
    "gn:feature_code":"PPL",
    "gn:name":"Tagzirt",
    "gn:population":0,
    "gn:timezone":"Africa/Casablanca",
    "iso:country":"MA",
    "wof:name":"Tagzirt",
    "wof:placetype":"locality"
},
  "geometry": {"coordinates":[-4.43,34.76],"type":"Point"}
}