{
  "type": "Feature",
  "properties": {
    "gn:admin1_code":"5.0",
    "gn:asciiname":"Tassaqiymouwt",
    "gn:country_code":"MA",
    "gn:dem":1815,
    "gn:feature_class":"P",
    "gn:feature_code":"PPL",
    "gn:name":"Tassaqiymouwt",
    "gn:population":0,
    "gn:timezone":"Africa/Casablanca",
    "iso:country":"MA",
    "wof:name":"Tassaqiymouwt",
    "wof:placetype":"locality"
},
  "geometry": {"coordinates":[-6.50997,31.95206],"type":"Point"}
}