{
  "type": "Feature",
  "properties": {
    "gn:admin1_code":"9.0",
    "gn:asciiname":"Tighza",
    "gn:country_code":"MA",
    "gn:dem":43,
    "gn:feature_class":"P",
    "gn:feature_code":"PPL",
    "gn:name":"Tighza",
    "gn:population":0,
    "gn:timezone":"Africa/Casablanca",
    "iso:country":"MA",
    "wof:name":"Tighza",
    "wof:placetype":"locality"
},
  "geometry": {"coordinates":[-9.65316,30.49532],"type":"Point"}
}