{
  "type": "Feature",
  "properties": {
    "gn:admin1_code":"9.0",
    "gn:asciiname":"Imi-n-Missant",
    "gn:country_code":"MA",
    "gn:dem":1388,
    "gn:feature_class":"P",
    "gn:feature_code":"PPL",
    "gn:name":"Imi-n-Missant",
    "gn:population":0,
    "gn:timezone":"Africa/Casablanca",
    "iso:country":"MA",
    "wof:name":"Imi-n-Missant",
    "wof:placetype":"locality"
},
  "geometry": {"coordinates":[-7.87769,30.83544],"type":"Point"}
}