{
  "type": "Feature",
  "properties": {
    "gn:admin1_code":"7.0",
    "gn:asciiname":"Douar Afarane",
    "gn:country_code":"MA",
    "gn:dem":571,
    "gn:feature_class":"P",
    "gn:feature_code":"PPL",
    "gn:name":"Douar Afarane",
    "gn:population":0,
    "gn:timezone":"Africa/Casablanca",
    "iso:country":"MA",
    "wof:name":"Douar Afarane",
    "wof:placetype":"locality"
},
  "geometry": {"coordinates":[-7.84139,31.52965],"type":"Point"}
}