{
  "type": "Feature",
  "properties": {
    "gn:admin1_code":"9.0",
    "gn:asciiname":"Tirakht",
    "gn:country_code":"MA",
    "gn:dem":1018,
    "gn:feature_class":"P",
    "gn:feature_code":"PPL",
    "gn:name":"Tirakht",
    "gn:population":0,
    "gn:timezone":"Africa/Casablanca",
    "iso:country":"MA",
    "wof:name":"Tirakht",
    "wof:placetype":"locality"
},
  "geometry": {"coordinates":[-8.76013,30.73986],"type":"Point"}
}