{
  "type": "Feature",
  "properties": {
    "gn:admin1_code":"3.0",
    "gn:asciiname":"Douar Bou Issa",
    "gn:country_code":"MA",
    "gn:dem":756,
    "gn:feature_class":"P",
    "gn:feature_code":"PPL",
    "gn:name":"Douar Bou Issa",
    "gn:population":0,
    "gn:timezone":"Africa/Casablanca",
    "iso:country":"MA",
    "wof:name":"Douar Bou Issa",
    "wof:placetype":"locality"
},
  "geometry": {"coordinates":[-4.3836,34.01057],"type":"Point"}
}