{
  "type": "Feature",
  "properties": {
    "gn:admin1_code":"5.0",
    "gn:asciiname":"Ait Touganit",
    "gn:country_code":"MA",
    "gn:dem":1151,
    "gn:feature_class":"P",
    "gn:feature_code":"PPL",
    "gn:name":"A\u00eft Touganit",
    "gn:population":0,
    "gn:timezone":"Africa/Casablanca",
    "iso:country":"MA",
    "wof:name":"Ait Touganit",
    "wof:placetype":"locality"
},
  "geometry": {"coordinates":[-6.36757,32.05829],"type":"Point"}
}