{
  "type": "Feature",
  "properties": {
    "gn:admin1_code":"2.0",
    "gn:asciiname":"Douar Cruemaz",
    "gn:country_code":"MA",
    "gn:dem":822,
    "gn:feature_class":"P",
    "gn:feature_code":"PPL",
    "gn:name":"Douar Cruemaz",
    "gn:population":0,
    "gn:timezone":"Africa/Casablanca",
    "iso:country":"MA",
    "wof:name":"Douar Cruemaz",
    "wof:placetype":"locality"
},
  "geometry": {"coordinates":[-2.07083,34.50406],"type":"Point"}
}