{
  "type": "Feature",
  "properties": {
    "gn:admin1_code":"04",
    "gn:asciiname":"Douar Chbanet",
    "gn:country_code":"MA",
    "gn:dem":163,
    "gn:feature_class":"P",
    "gn:feature_code":"PPL",
    "gn:name":"Douar Chbanet",
    "gn:population":0,
    "gn:timezone":"Africa/Casablanca",
    "iso:country":"MA",
    "wof:name":"Douar Chbanet",
    "wof:placetype":"locality"
},
  "geometry": {"coordinates":[-5.62505,34.24213],"type":"Point"}
}