{
  "type": "Feature",
  "properties": {
    "gn:admin1_code":"7.0",
    "gn:asciiname":"Ifarkhas",
    "gn:country_code":"MA",
    "gn:dem":1022,
    "gn:feature_class":"P",
    "gn:feature_code":"PPL",
    "gn:name":"Ifarkhas",
    "gn:population":0,
    "gn:timezone":"Africa/Casablanca",
    "iso:country":"MA",
    "wof:name":"Ifarkhas",
    "wof:placetype":"locality"
},
  "geometry": {"coordinates":[-9.06769,31.22066],"type":"Point"}
}