{
  "type": "Feature",
  "properties": {
    "gn:admin1_code":"09",
    "gn:asciiname":"Amkraz",
    "gn:country_code":"MA",
    "gn:dem":1057,
    "gn:feature_class":"P",
    "gn:feature_code":"PPL",
    "gn:name":"Amkraz",
    "gn:population":0,
    "gn:timezone":"Africa/Casablanca",
    "iso:country":"MA",
    "name:und_x_variant":[
        "Amekraz",
        "Amkraz"
    ],
    "wof:name":"Amkraz",
    "wof:placetype":"locality"
},
  "geometry": {"coordinates":[-9.27766,29.60288],"type":"Point"}
}