{
  "type": "Feature",
  "properties": {
    "gn:admin1_code":"7.0",
    "gn:asciiname":"Oulad Sliman",
    "gn:country_code":"MA",
    "gn:dem":76,
    "gn:feature_class":"P",
    "gn:feature_code":"PPL",
    "gn:name":"Oulad Sliman",
    "gn:population":0,
    "gn:timezone":"Africa/Casablanca",
    "iso:country":"MA",
    "wof:name":"Oulad Sliman",
    "wof:placetype":"locality"
},
  "geometry": {"coordinates":[-9.30455,32.0807],"type":"Point"}
}