{
  "type": "Feature",
  "properties": {
    "gn:admin1_code":"01",
    "gn:asciiname":"Addar",
    "gn:country_code":"MA",
    "gn:dem":655,
    "gn:feature_class":"P",
    "gn:feature_code":"PPL",
    "gn:name":"Addar",
    "gn:population":0,
    "gn:timezone":"Africa/Casablanca",
    "iso:country":"MA",
    "wof:name":"Addar",
    "wof:placetype":"locality"
},
  "geometry": {"coordinates":[-5.34483,35.43844],"type":"Point"}
}