{
  "type": "Feature",
  "properties": {
    "gn:admin1_code":"7.0",
    "gn:asciiname":"Douar Abdellah Ben Lkarkour",
    "gn:country_code":"MA",
    "gn:dem":462,
    "gn:feature_class":"P",
    "gn:feature_code":"PPL",
    "gn:name":"Douar Abdellah Ben Lkarkour",
    "gn:population":0,
    "gn:timezone":"Africa/Casablanca",
    "iso:country":"MA",
    "wof:name":"Douar Abdellah Ben Lkarkour",
    "wof:placetype":"locality"
},
  "geometry": {"coordinates":[-9.0133,31.64286],"type":"Point"}
}