{
  "type": "Feature",
  "properties": {
    "gn:admin1_code":"03",
    "gn:asciiname":"Mrabtine Feddane el Kbir",
    "gn:country_code":"MA",
    "gn:dem":1146,
    "gn:feature_class":"P",
    "gn:feature_code":"PPL",
    "gn:name":"Mrabtine Feddane el Kbir",
    "gn:population":0,
    "gn:timezone":"Africa/Casablanca",
    "iso:country":"MA",
    "name:und_x_variant":[
        "Mrabtines de Feddanes",
        "Mrabtine Feddane el Kbir"
    ],
    "wof:name":"Mrabtine Feddane el Kbir",
    "wof:placetype":"locality"
},
  "geometry": {"coordinates":[-4.06535,34.63561],"type":"Point"}
}