{
  "type": "Feature",
  "properties": {
    "gn:admin1_code":"7.0",
    "gn:asciiname":"Dar Oulad Thami",
    "gn:country_code":"MA",
    "gn:dem":344,
    "gn:feature_class":"P",
    "gn:feature_code":"PPL",
    "gn:name":"Dar Oulad Thami",
    "gn:population":0,
    "gn:timezone":"Africa/Casablanca",
    "iso:country":"MA",
    "wof:name":"Dar Oulad Thami",
    "wof:placetype":"locality"
},
  "geometry": {"coordinates":[-7.51321,32.3592],"type":"Point"}
}