{
  "type": "Feature",
  "properties": {
    "gn:admin1_code":"08",
    "gn:asciiname":"Louggagh",
    "gn:country_code":"MA",
    "gn:dem":1925,
    "gn:feature_class":"P",
    "gn:feature_code":"PPL",
    "gn:name":"Louggagh",
    "gn:population":0,
    "gn:timezone":"Africa/Casablanca",
    "iso:country":"MA",
    "name:und_x_variant":[
        "Lougaghe",
        "Louggouarh",
        "Louggagh"
    ],
    "wof:name":"Louggagh",
    "wof:placetype":"locality"
},
  "geometry": {"coordinates":[-5.0646,32.40168],"type":"Point"}
}