{
  "type": "Feature",
  "properties": {
    "gn:admin1_code":"9.0",
    "gn:asciiname":"Menzanit",
    "gn:country_code":"MA",
    "gn:dem":1812,
    "gn:feature_class":"P",
    "gn:feature_code":"PPL",
    "gn:name":"Menzanit",
    "gn:population":0,
    "gn:timezone":"Africa/Casablanca",
    "iso:country":"MA",
    "wof:name":"Menzanit",
    "wof:placetype":"locality"
},
  "geometry": {"coordinates":[-8.61858,30.84925],"type":"Point"}
}