{
  "type": "Feature",
  "properties": {
    "gn:admin1_code":"2.0",
    "gn:asciiname":"Douar Iqedjouchene",
    "gn:country_code":"MA",
    "gn:dem":382,
    "gn:feature_class":"P",
    "gn:feature_code":"PPL",
    "gn:name":"Douar Iqedjouchene",
    "gn:population":0,
    "gn:timezone":"Africa/Casablanca",
    "iso:country":"MA",
    "wof:name":"Douar Iqedjouchene",
    "wof:placetype":"locality"
},
  "geometry": {"coordinates":[-3.66553,35.10412],"type":"Point"}
}