{
  "type": "Feature",
  "properties": {
    "gn:admin1_code":"7.0",
    "gn:asciiname":"Id Ou Ben Ahmed",
    "gn:country_code":"MA",
    "gn:dem":309,
    "gn:feature_class":"P",
    "gn:feature_code":"PPL",
    "gn:name":"Id Ou Ben Ahmed",
    "gn:population":0,
    "gn:timezone":"Africa/Casablanca",
    "iso:country":"MA",
    "wof:name":"Id Ou Ben Ahmed",
    "wof:placetype":"locality"
},
  "geometry": {"coordinates":[-9.69048,31.25535],"type":"Point"}
}