{
  "type": "Feature",
  "properties": {
    "gn:admin1_code":"03",
    "gn:asciiname":"Jiber",
    "gn:country_code":"MA",
    "gn:dem":1442,
    "gn:feature_class":"P",
    "gn:feature_code":"PPL",
    "gn:name":"Jiber",
    "gn:population":0,
    "gn:timezone":"Africa/Casablanca",
    "iso:country":"MA",
    "wof:name":"Jiber",
    "wof:placetype":"locality"
},
  "geometry": {"coordinates":[-4.86972,33.68525],"type":"Point"}
}