{
  "type": "Feature",
  "properties": {
    "gn:admin1_code":"05",
    "gn:asciiname":"Douar Ayt Hammou",
    "gn:country_code":"MA",
    "gn:dem":531,
    "gn:feature_class":"P",
    "gn:feature_code":"PPL",
    "gn:name":"Douar Ayt Hammou",
    "gn:population":0,
    "gn:timezone":"Africa/Casablanca",
    "iso:country":"MA",
    "name:und_x_variant":[
        "A\u00eft Hammou"
    ],
    "wof:name":"Douar Ayt Hammou",
    "wof:placetype":"locality"
},
  "geometry": {"coordinates":[-6.2564,32.5225],"type":"Point"}
}