{
  "type": "Feature",
  "properties": {
    "gn:country":"MA",
    "gn:fcode":"ADM3",
    "gn:pop":11122,
    "iso:country":"MA",
    "name:ara_x_preferred":[
        "\u0623\u0648\u0644\u0627\u062f \u0633\u0639\u064a\u062f \u0627\u0644\u0648\u0627\u062f"
    ],
    "name:fra_x_preferred":[
        "Semguet"
    ],
    "name:fra_x_variant":[
        "Semguet (CR)",
        "Semguet (Commune Rurale)"
    ],
    "qs:name":"Semguet",
    "qs:photos_9r":0,
    "qs:photos_sr":0,
    "qs:pop_sr":"6",
    "wd:wordcount":59,
    "wof:name":"Semguet",
    "wof:placetype":"localadmin",
    "wof:population":11122
},
  "geometry": {"coordinates":[-6.18188,32.64782],"type":"Point"}
}