{
  "type": "Feature",
  "properties": {
    "gn:admin1_code":"9.0",
    "gn:asciiname":"Ighiyr Iyfran",
    "gn:country_code":"MA",
    "gn:dem":1328,
    "gn:feature_class":"P",
    "gn:feature_code":"PPL",
    "gn:name":"Ighiyr Iyfran",
    "gn:population":0,
    "gn:timezone":"Africa/Casablanca",
    "iso:country":"MA",
    "wof:name":"Ighiyr Iyfran",
    "wof:placetype":"locality"
},
  "geometry": {"coordinates":[-9.00999,29.95187],"type":"Point"}
}