{
  "type": "Feature",
  "properties": {
    "gn:country":"MA",
    "gn:fcode":"ADM3",
    "gn:population":20797,
    "iso:country":"MA",
    "name:ara_x_preferred":[
        "\u0644\u0639\u0645\u0627\u0645\u0631\u0629"
    ],
    "name:fra_x_preferred":[
        "Nagga"
    ],
    "name:fra_x_variant":[
        "Nagga (CR)",
        "Nagga (Commune Rurale)"
    ],
    "qs:name":"Nagga",
    "qs:photos_9r":0,
    "qs:photos_sr":0,
    "qs:pop_sr":"7",
    "wof:name":"Nagga",
    "wof:placetype":"localadmin",
    "wof:population":20797
},
  "geometry": {"coordinates":[-9.04334,32.05714],"type":"Point"}
}