{
  "type": "Feature",
  "properties": {
    "gn:admin1_code":"9.0",
    "gn:asciiname":"Ait At Talb Mas'oud",
    "gn:country_code":"MA",
    "gn:dem":826,
    "gn:feature_class":"P",
    "gn:feature_code":"PPL",
    "gn:name":"A\u00eft At Talb Mas\u2019oud",
    "gn:population":0,
    "gn:timezone":"Africa/Casablanca",
    "iso:country":"MA",
    "wof:name":"Ait At Talb Mas'oud",
    "wof:placetype":"locality"
},
  "geometry": {"coordinates":[-9.20027,29.96769],"type":"Point"}
}