{
  "type": "Feature",
  "properties": {
    "gn:admin1_code":"1.0",
    "gn:asciiname":"Douar Rmel",
    "gn:country_code":"MA",
    "gn:dem":22,
    "gn:feature_class":"P",
    "gn:feature_code":"PPL",
    "gn:name":"Douar Rmel",
    "gn:population":0,
    "gn:timezone":"Africa/Casablanca",
    "iso:country":"MA",
    "wof:name":"Douar Rmel",
    "wof:placetype":"locality"
},
  "geometry": {"coordinates":[-5.83343,35.47651],"type":"Point"}
}