{
  "type": "Feature",
  "properties": {
    "gn:admin1_code":"7.0",
    "gn:asciiname":"Ighir-n-Wadou",
    "gn:country_code":"MA",
    "gn:dem":1153,
    "gn:feature_class":"P",
    "gn:feature_code":"PPL",
    "gn:name":"Ighir-n-Wadou",
    "gn:population":0,
    "gn:timezone":"Africa/Casablanca",
    "iso:country":"MA",
    "wof:name":"Ighir-n-Wadou",
    "wof:placetype":"locality"
},
  "geometry": {"coordinates":[-7.96469,31.26008],"type":"Point"}
}