{
  "type": "Feature",
  "properties": {
    "gn:admin1_code":"07",
    "gn:asciiname":"Naama",
    "gn:country_code":"MA",
    "gn:dem":113,
    "gn:feature_class":"P",
    "gn:feature_code":"PPL",
    "gn:name":"Naama",
    "gn:population":0,
    "gn:timezone":"Africa/Casablanca",
    "iso:country":"MA",
    "name:ara_x_preferred":[
        "\u0646\u0639\u0645\u0629"
    ],
    "name:ceb_x_preferred":[
        "Naama"
    ],
    "name:deu_x_preferred":[
        "Naama"
    ],
    "name:fin_x_preferred":[
        "Naama"
    ],
    "name:fra_x_preferred":[
        "Naama"
    ],
    "name:pnb_x_preferred":[
        "\u0646\u0639\u0627\u0645\u06c1"
    ],
    "name:pol_x_preferred":[
        "Naama"
    ],
    "name:swe_x_preferred":[
        "Naama"
    ],
    "name:und_x_variant":[
        "Naamate",
        "Douar Naamat"
    ],
    "wof:name":"Naama",
    "wof:placetype":"locality"
},
  "geometry": {"coordinates":[-9.13339,32.52976],"type":"Point"}
}