{
  "type": "Feature",
  "properties": {
    "gn:admin1_code":"07",
    "gn:asciiname":"Naama",
    "gn:country_code":"MA",
    "gn:dem":113,
    "gn:feature_class":"P",
    "gn:feature_code":"PPL",
    "gn:name":"Naama",
    "gn:population":0,
    "gn:timezone":"Africa/Casablanca",
    "iso:country":"MA",
    "name:und_x_variant":[
        "Naamate",
        "Douar Naamat",
        "Naama"
    ],
    "wof:name":"Naama",
    "wof:placetype":"locality"
},
  "geometry": {"coordinates":[-9.13339,32.52976],"type":"Point"}
}