{
  "type": "Feature",
  "properties": {
    "gn:admin1_code":"01",
    "gn:asciiname":"Aouaja",
    "gn:country_code":"MA",
    "gn:dem":454,
    "gn:feature_class":"P",
    "gn:feature_code":"PPL",
    "gn:name":"Aouaja",
    "gn:population":0,
    "gn:timezone":"Africa/Casablanca",
    "iso:country":"MA",
    "name:und_x_variant":[
        "Aouacha"
    ],
    "wof:name":"Aouaja",
    "wof:placetype":"locality"
},
  "geometry": {"coordinates":[-5.70614,35.07057],"type":"Point"}
}