{
  "type": "Feature",
  "properties": {
    "gn:admin1_code":"9.0",
    "gn:asciiname":"Ait Mhmd",
    "gn:country_code":"MA",
    "gn:dem":596,
    "gn:feature_class":"P",
    "gn:feature_code":"PPL",
    "gn:name":"A\u00eft Mhmd",
    "gn:population":0,
    "gn:timezone":"Africa/Casablanca",
    "iso:country":"MA",
    "wof:name":"Ait Mhmd",
    "wof:placetype":"locality"
},
  "geometry": {"coordinates":[-9.38656,29.50452],"type":"Point"}
}