{
  "type": "Feature",
  "properties": {
    "gn:admin1_code":"9.0",
    "gn:asciiname":"Tidli",
    "gn:country_code":"MA",
    "gn:dem":415,
    "gn:feature_class":"P",
    "gn:feature_code":"PPL",
    "gn:name":"Tidli",
    "gn:population":0,
    "gn:timezone":"Africa/Casablanca",
    "iso:country":"MA",
    "wof:name":"Tidli",
    "wof:placetype":"locality"
},
  "geometry": {"coordinates":[-9.37131,29.78023],"type":"Point"}
}