{
  "type": "Feature",
  "properties": {
    "gn:admin1_code":"9.0",
    "gn:asciiname":"Tidli",
    "gn:country_code":"MA",
    "gn:dem":415,
    "gn:feature_class":"P",
    "gn:feature_code":"PPL",
    "gn:name":"Tidli",
    "gn:population":0,
    "gn:timezone":"Africa/Casablanca",
    "iso:country":"MA",
    "name:ara_x_preferred":[
        "\u062a\u064a\u062f\u0644\u064a"
    ],
    "name:azb_x_preferred":[
        "\u062a\u06cc\u062f\u0644\u06cc"
    ],
    "name:cat_x_preferred":[
        "Tidli"
    ],
    "name:ceb_x_preferred":[
        "Tidli"
    ],
    "name:fas_x_preferred":[
        "\u062a\u06cc\u062f\u0644\u06cc"
    ],
    "name:ita_x_preferred":[
        "Tidli"
    ],
    "name:swe_x_preferred":[
        "Tidli"
    ],
    "wof:name":"Tidli",
    "wof:placetype":"locality"
},
  "geometry": {"coordinates":[-9.37131,29.78023],"type":"Point"}
}