{
  "type": "Feature",
  "properties": {
    "gn:admin1_code":"01",
    "gn:asciiname":"Douar Bni Ftouh",
    "gn:country_code":"MA",
    "gn:dem":985,
    "gn:feature_class":"P",
    "gn:feature_code":"PPL",
    "gn:name":"Douar Bni Ftouh",
    "gn:population":0,
    "gn:timezone":"Africa/Casablanca",
    "iso:country":"MA",
    "name:und_x_variant":[
        "Bounni"
    ],
    "wof:name":"Douar Bni Ftouh",
    "wof:placetype":"locality"
},
  "geometry": {"coordinates":[-5.04406,35.09694],"type":"Point"}
}