{
  "type": "Feature",
  "properties": {
    "gn:admin1_code":"08",
    "gn:asciiname":"Ali Ou Grou",
    "gn:country_code":"MA",
    "gn:dem":1612,
    "gn:feature_class":"P",
    "gn:feature_code":"PPL",
    "gn:name":"Ali Ou Grou",
    "gn:population":0,
    "gn:timezone":"Africa/Casablanca",
    "iso:country":"MA",
    "name:und_x_variant":[
        "A\u00eft el gous",
        "Ali Ou Grou"
    ],
    "wof:name":"Ali Ou Grou",
    "wof:placetype":"locality"
},
  "geometry": {"coordinates":[-4.3808,32.47022],"type":"Point"}
}