{
  "type": "Feature",
  "properties": {
    "gn:admin1_code":"07",
    "gn:asciiname":"Tleta des Oulad Dlim",
    "gn:country_code":"MA",
    "gn:dem":544,
    "gn:feature_class":"P",
    "gn:feature_code":"PPL",
    "gn:name":"Tleta des Oulad Dlim",
    "gn:population":0,
    "gn:timezone":"Africa/Casablanca",
    "iso:country":"MA",
    "name:und_x_variant":[
        "Et Tleta des Oulad Dlim",
        "Tleta Oulad Dlim",
        "Et Tleta",
        "Tleta des Oulad Dlim"
    ],
    "wof:name":"Tleta des Oulad Dlim",
    "wof:placetype":"locality"
},
  "geometry": {"coordinates":[-8.25909,31.95183],"type":"Point"}
}