{
  "type": "Feature",
  "properties": {
    "gn:admin1_code":"04",
    "gn:asciiname":"Ain Bou Aiba",
    "gn:country_code":"MA",
    "gn:dem":89,
    "gn:feature_class":"P",
    "gn:feature_code":"PPL",
    "gn:name":"A\u00efn Bou A\u00efba",
    "gn:population":0,
    "gn:timezone":"Africa/Casablanca",
    "iso:country":"MA",
    "wof:name":"Ain Bou Aiba",
    "wof:placetype":"locality"
},
  "geometry": {"coordinates":[-7.02,33.84],"type":"Point"}
}