{
  "type": "Feature",
  "properties": {
    "gn:admin1_code":"02",
    "gn:asciiname":"Taourirt Ayyad",
    "gn:country_code":"MA",
    "gn:dem":70,
    "gn:feature_class":"P",
    "gn:feature_code":"PPL",
    "gn:name":"Taourirt Ayyad",
    "gn:population":0,
    "gn:timezone":"Africa/Casablanca",
    "iso:country":"MA",
    "wof:name":"Taourirt Ayyad",
    "wof:placetype":"locality"
},
  "geometry": {"coordinates":[-3.76899,35.18788],"type":"Point"}
}