{
  "type": "Feature",
  "properties": {
    "gn:admin1_code":"7.0",
    "gn:asciiname":"Dar Ben Hammou",
    "gn:country_code":"MA",
    "gn:dem":435,
    "gn:feature_class":"P",
    "gn:feature_code":"PPL",
    "gn:name":"Dar Ben Hammou",
    "gn:population":0,
    "gn:timezone":"Africa/Casablanca",
    "iso:country":"MA",
    "wof:name":"Dar Ben Hammou",
    "wof:placetype":"locality"
},
  "geometry": {"coordinates":[-7.82367,32.1554],"type":"Point"}
}