{
  "type": "Feature",
  "properties": {
    "gn:admin1_code":"7.0",
    "gn:asciiname":"Ait Ouaarab",
    "gn:country_code":"MA",
    "gn:dem":350,
    "gn:feature_class":"P",
    "gn:feature_code":"PPL",
    "gn:name":"A\u00eft Ouaarab",
    "gn:population":0,
    "gn:timezone":"Africa/Casablanca",
    "iso:country":"MA",
    "wof:name":"Ait Ouaarab",
    "wof:placetype":"locality"
},
  "geometry": {"coordinates":[-9.4964,31.3465],"type":"Point"}
}