{
  "type": "Feature",
  "properties": {
    "gn:admin1_code":"6.0",
    "gn:asciiname":"Oulad Ahmed Ben Hammou",
    "gn:country_code":"MA",
    "gn:dem":471,
    "gn:feature_class":"P",
    "gn:feature_code":"PPL",
    "gn:name":"Oulad Ahmed Ben Hammou",
    "gn:population":0,
    "gn:timezone":"Africa/Casablanca",
    "iso:country":"MA",
    "wof:name":"Oulad Ahmed Ben Hammou",
    "wof:placetype":"locality"
},
  "geometry": {"coordinates":[-7.6563,32.76291],"type":"Point"}
}