{
  "type": "Feature",
  "properties": {
    "gn:admin1_code":"7.0",
    "gn:asciiname":"Douar Hmara Essouani",
    "gn:country_code":"MA",
    "gn:dem":391,
    "gn:feature_class":"P",
    "gn:feature_code":"PPL",
    "gn:name":"Douar Hmara Essouani",
    "gn:population":0,
    "gn:timezone":"Africa/Casablanca",
    "iso:country":"MA",
    "wof:name":"Douar Hmara Essouani",
    "wof:placetype":"locality"
},
  "geometry": {"coordinates":[-8.5897,32.08931],"type":"Point"}
}