{
  "type": "Feature",
  "properties": {
    "gn:admin1_code":"07",
    "gn:asciiname":"Wayfirt",
    "gn:country_code":"MA",
    "gn:dem":1126,
    "gn:feature_class":"P",
    "gn:feature_code":"PPL",
    "gn:name":"Wayfirt",
    "gn:population":0,
    "gn:timezone":"Africa/Casablanca",
    "iso:country":"MA",
    "name:und_x_variant":[
        "Ouayfirte",
        "Ouaifirte",
        "Ouaifir",
        "Wayfirt"
    ],
    "wof:name":"Wayfirt",
    "wof:placetype":"locality"
},
  "geometry": {"coordinates":[-7.53813,31.44223],"type":"Point"}
}