{
  "type": "Feature",
  "properties": {
    "gn:admin1_code":"1.0",
    "gn:asciiname":"Sidi Mohamed Laatir",
    "gn:country_code":"MA",
    "gn:dem":785,
    "gn:feature_class":"P",
    "gn:feature_code":"PPL",
    "gn:name":"Sidi Mohamed Laatir",
    "gn:population":0,
    "gn:timezone":"Africa/Casablanca",
    "iso:country":"MA",
    "wof:name":"Sidi Mohamed Laatir",
    "wof:placetype":"locality"
},
  "geometry": {"coordinates":[-4.97047,35.1428],"type":"Point"}
}