{
  "type": "Feature",
  "properties": {
    "gn:admin1_code":"7.0",
    "gn:asciiname":"Et Tout",
    "gn:country_code":"MA",
    "gn:dem":1429,
    "gn:feature_class":"P",
    "gn:feature_code":"PPL",
    "gn:name":"Et Tout",
    "gn:population":0,
    "gn:timezone":"Africa/Casablanca",
    "iso:country":"MA",
    "wof:name":"Et Tout",
    "wof:placetype":"locality"
},
  "geometry": {"coordinates":[-9.09525,30.99835],"type":"Point"}
}