{
  "type": "Feature",
  "properties": {
    "gn:admin1_code":"01",
    "gn:asciiname":"Ain es Souk",
    "gn:country_code":"MA",
    "gn:dem":337,
    "gn:feature_class":"P",
    "gn:feature_code":"PPL",
    "gn:name":"A\u00efn es Souk",
    "gn:population":0,
    "gn:timezone":"Africa/Casablanca",
    "iso:country":"MA",
    "name:und_x_variant":[
        "A\u00efn Souk",
        "A\u00efn es Souk"
    ],
    "wof:name":"Ain es Souk",
    "wof:placetype":"locality"
},
  "geometry": {"coordinates":[-5.33552,34.69237],"type":"Point"}
}