{
  "type": "Feature",
  "properties": {
    "gn:admin1_code":"01",
    "gn:asciiname":"Douar Tazekhenatet",
    "gn:country_code":"MA",
    "gn:dem":673,
    "gn:feature_class":"P",
    "gn:feature_code":"PPL",
    "gn:name":"Douar Tazekhenatet",
    "gn:population":0,
    "gn:timezone":"Africa/Casablanca",
    "iso:country":"MA",
    "name:und_x_variant":[
        "Tizeknatate",
        "Tisgouenatane",
        "Douar Tazekhenatet"
    ],
    "wof:name":"Douar Tazekhenatet",
    "wof:placetype":"locality"
},
  "geometry": {"coordinates":[-4.86715,35.15541],"type":"Point"}
}