{
  "type": "Feature",
  "properties": {
    "gn:admin1_code":"08",
    "gn:asciiname":"Zaouit Moulay Abdallah",
    "gn:country_code":"MA",
    "gn:dem":1015,
    "gn:feature_class":"P",
    "gn:feature_code":"PPL",
    "gn:name":"Zaouit Moulay Abdallah",
    "gn:population":0,
    "gn:timezone":"Africa/Casablanca",
    "iso:country":"MA",
    "wof:name":"Zaouit Moulay Abdallah",
    "wof:placetype":"locality"
},
  "geometry": {"coordinates":[-4.395,31.9279],"type":"Point"}
}