{
  "type": "Feature",
  "properties": {
    "gn:admin1_code":"07",
    "gn:asciiname":"Douar Goulla",
    "gn:country_code":"MA",
    "gn:dem":409,
    "gn:feature_class":"P",
    "gn:feature_code":"PPL",
    "gn:name":"Douar Goulla",
    "gn:population":0,
    "gn:timezone":"Africa/Casablanca",
    "iso:country":"MA",
    "name:und_x_variant":[
        "Boulla",
        "Douar Saleh"
    ],
    "wof:name":"Douar Goulla",
    "wof:placetype":"locality"
},
  "geometry": {"coordinates":[-9.02015,31.61224],"type":"Point"}
}