{
  "type": "Feature",
  "properties": {
    "gn:admin1_code":"07",
    "gn:asciiname":"Tassila Matil",
    "gn:country_code":"MA",
    "gn:dem":767,
    "gn:feature_class":"P",
    "gn:feature_code":"PPL",
    "gn:name":"Tassila Matil",
    "gn:population":0,
    "gn:timezone":"Africa/Casablanca",
    "iso:country":"MA",
    "name:und_x_variant":[
        "Tassila"
    ],
    "wof:name":"Tassila Matil",
    "wof:placetype":"locality"
},
  "geometry": {"coordinates":[-9.2567,31.30872],"type":"Point"}
}