{
  "type": "Feature",
  "properties": {
    "gn:admin1_code":"5.0",
    "gn:asciiname":"Ighir-n-Tnoughrine",
    "gn:country_code":"MA",
    "gn:dem":2028,
    "gn:feature_class":"P",
    "gn:feature_code":"PPL",
    "gn:name":"Ighir-n-Tnoughrine",
    "gn:population":0,
    "gn:timezone":"Africa/Casablanca",
    "iso:country":"MA",
    "wof:name":"Ighir-n-Tnoughrine",
    "wof:placetype":"locality"
},
  "geometry": {"coordinates":[-6.91317,31.37103],"type":"Point"}
}