{
  "type": "Feature",
  "properties": {
    "gn:admin1_code":"01",
    "gn:asciiname":"Tanja Lbalya",
    "gn:country_code":"MA",
    "gn:dem":44,
    "gn:feature_class":"P",
    "gn:feature_code":"PPL",
    "gn:name":"Tanja Lbalya",
    "gn:population":0,
    "gn:timezone":"Africa/Casablanca",
    "iso:country":"MA",
    "name:und_x_variant":[
        "Tandja al Balia",
        "Tanja Balia",
        "El Balia",
        "Tanja Lbalya"
    ],
    "wof:name":"Tanja Lbalya",
    "wof:placetype":"locality"
},
  "geometry": {"coordinates":[-5.77064,35.76935],"type":"Point"}
}