{
  "type": "Feature",
  "properties": {
    "gn:admin1_code":"06",
    "gn:asciiname":"Beni Yakhlef",
    "gn:country_code":"MA",
    "gn:dem":71,
    "gn:feature_class":"P",
    "gn:feature_code":"PPL",
    "gn:name":"Beni Yakhlef",
    "gn:population":0,
    "gn:timezone":"Africa/Casablanca",
    "iso:country":"MA",
    "name:und_x_variant":[
        "Saint-Jean de Fedala",
        "Louizia",
        "Ellouizia",
        "Al Lwiziya",
        "Elluoizia",
        "Al Luwayz\u012byah",
        "Beni Yakhlef"
    ],
    "wof:name":"Beni Yakhlef",
    "wof:placetype":"locality"
},
  "geometry": {"coordinates":[-7.33924,33.68407],"type":"Point"}
}