{
  "type": "Feature",
  "properties": {
    "gn:admin1_code":"3.0",
    "gn:asciiname":"Cooperative El Omariya",
    "gn:country_code":"MA",
    "gn:dem":801,
    "gn:feature_class":"P",
    "gn:feature_code":"PPLF",
    "gn:name":"Coop\u00e9rative El Omariya",
    "gn:population":0,
    "gn:timezone":"Africa/Casablanca",
    "iso:country":"MA",
    "name:und_x_variant":[
        "Coop\u00e9rative El Omariya",
        "Sous Centre"
    ],
    "wof:name":"Cooperative El Omariya",
    "wof:placetype":"locality"
},
  "geometry": {"coordinates":[-5.65635,33.66989],"type":"Point"}
}