{
  "type": "Feature",
  "properties": {
    "gn:admin1_code":"1.0",
    "gn:asciiname":"Douar Dhar Lekbir",
    "gn:country_code":"MA",
    "gn:dem":161,
    "gn:feature_class":"P",
    "gn:feature_code":"PPL",
    "gn:name":"Douar Dhar Lekbir",
    "gn:population":0,
    "gn:timezone":"Africa/Casablanca",
    "iso:country":"MA",
    "wof:name":"Douar Dhar Lekbir",
    "wof:placetype":"locality"
},
  "geometry": {"coordinates":[-5.60983,35.57295],"type":"Point"}
}