{
  "type": "Feature",
  "properties": {
    "gn:admin1_code":"07",
    "gn:asciiname":"Douar Laouamra",
    "gn:country_code":"MA",
    "gn:dem":225,
    "gn:feature_class":"P",
    "gn:feature_code":"PPL",
    "gn:name":"Douar Laouamra",
    "gn:population":0,
    "gn:timezone":"Africa/Casablanca",
    "iso:country":"MA",
    "name:und_x_variant":[
        "Laouamra",
        "El Aouamra",
        "Douar Laouamra"
    ],
    "wof:name":"Douar Laouamra",
    "wof:placetype":"locality"
},
  "geometry": {"coordinates":[-8.70794,31.79736],"type":"Point"}
}