{
  "type": "Feature",
  "properties": {
    "gn:admin1_code":"7.0",
    "gn:asciiname":"Douar Lemachat",
    "gn:country_code":"MA",
    "gn:dem":575,
    "gn:feature_class":"P",
    "gn:feature_code":"PPL",
    "gn:name":"Douar Lemachat",
    "gn:population":0,
    "gn:timezone":"Africa/Casablanca",
    "iso:country":"MA",
    "name:und_x_variant":[
        "Maachat"
    ],
    "wof:name":"Douar Lemachat",
    "wof:placetype":"locality"
},
  "geometry": {"coordinates":[-7.56043,31.7621],"type":"Point"}
}