{
  "type": "Feature",
  "properties": {
    "gn:admin1_code":"08",
    "gn:asciiname":"Tahoudat",
    "gn:country_code":"MA",
    "gn:dem":1614,
    "gn:feature_class":"P",
    "gn:feature_code":"PPL",
    "gn:name":"Tahoudat",
    "gn:population":0,
    "gn:timezone":"Africa/Casablanca",
    "iso:country":"MA",
    "name:und_x_variant":[
        "Ksar taouda\u00e2t",
        "Taoudat",
        "Tahoudat"
    ],
    "wof:name":"Tahoudat",
    "wof:placetype":"locality"
},
  "geometry": {"coordinates":[-5.30699,31.7551],"type":"Point"}
}