{
  "type": "Feature",
  "properties": {
    "gn:admin1_code":"7.0",
    "gn:asciiname":"Douar Salas",
    "gn:country_code":"MA",
    "gn:dem":471,
    "gn:feature_class":"P",
    "gn:feature_code":"PPL",
    "gn:name":"Douar Salas",
    "gn:population":0,
    "gn:timezone":"Africa/Casablanca",
    "iso:country":"MA",
    "wof:name":"Douar Salas",
    "wof:placetype":"locality"
},
  "geometry": {"coordinates":[-8.17442,31.52844],"type":"Point"}
}