{
  "type": "Feature",
  "properties": {
    "gn:admin1_code":"3.0",
    "gn:asciiname":"Leghrasla",
    "gn:country_code":"MA",
    "gn:dem":133,
    "gn:feature_class":"P",
    "gn:feature_code":"PPL",
    "gn:name":"Leghrasla",
    "gn:population":0,
    "gn:timezone":"Africa/Casablanca",
    "iso:country":"MA",
    "wof:name":"Leghrasla",
    "wof:placetype":"locality"
},
  "geometry": {"coordinates":[-5.02676,34.30124],"type":"Point"}
}