{
  "type": "Feature",
  "properties": {
    "gn:admin1_code":"09",
    "gn:asciiname":"Fougsar",
    "gn:country_code":"MA",
    "gn:dem":1736,
    "gn:feature_class":"P",
    "gn:feature_code":"PPL",
    "gn:name":"Fougsar",
    "gn:population":0,
    "gn:timezone":"Africa/Casablanca",
    "iso:country":"MA",
    "name:und_x_variant":[
        "Fouggsert",
        "Fougsar"
    ],
    "wof:name":"Fougsar",
    "wof:placetype":"locality"
},
  "geometry": {"coordinates":[-8.61594,29.92065],"type":"Point"}
}