{
  "type": "Feature",
  "properties": {
    "gn:admin1_code":"6.0",
    "gn:asciiname":"Ahl Lkifane",
    "gn:country_code":"MA",
    "gn:dem":122,
    "gn:feature_class":"P",
    "gn:feature_code":"PPLL",
    "gn:name":"Ahl Lkifane",
    "gn:population":0,
    "gn:timezone":"Africa/Casablanca",
    "iso:country":"MA",
    "wof:name":"Ahl Lkifane",
    "wof:placetype":"locality"
},
  "geometry": {"coordinates":[-8.88019,32.64395],"type":"Point"}
}