{
  "type": "Feature",
  "properties": {
    "gn:admin1_code":"4.0",
    "gn:asciiname":"Oulad Khlifa",
    "gn:country_code":"MA",
    "gn:dem":24,
    "gn:feature_class":"P",
    "gn:feature_code":"PPL",
    "gn:name":"Oulad Khlifa",
    "gn:population":0,
    "gn:timezone":"Africa/Casablanca",
    "iso:country":"MA",
    "wof:name":"Oulad Khlifa",
    "wof:placetype":"locality"
},
  "geometry": {"coordinates":[-6.58279,34.31303],"type":"Point"}
}