{
  "type": "Feature",
  "properties": {
    "gn:admin1_code":"09",
    "gn:asciiname":"Azrou",
    "gn:country_code":"MA",
    "gn:dem":1984,
    "gn:feature_class":"P",
    "gn:feature_code":"PPL",
    "gn:name":"Azrou",
    "gn:population":0,
    "gn:timezone":"Africa/Casablanca",
    "iso:country":"MA",
    "wof:name":"Azrou",
    "wof:placetype":"locality"
},
  "geometry": {"coordinates":[-7.76401,31.01643],"type":"Point"}
}