{
  "type": "Feature",
  "properties": {
    "gn:admin1_code":"6.0",
    "gn:asciiname":"Douar Leghzaouna Chouaouta",
    "gn:country_code":"MA",
    "gn:dem":415,
    "gn:feature_class":"P",
    "gn:feature_code":"PPL",
    "gn:name":"Douar Leghzaouna Chouaouta",
    "gn:population":0,
    "gn:timezone":"Africa/Casablanca",
    "iso:country":"MA",
    "wof:name":"Douar Leghzaouna Chouaouta",
    "wof:placetype":"locality"
},
  "geometry": {"coordinates":[-6.99402,33.46149],"type":"Point"}
}