{
  "type": "Feature",
  "properties": {
    "gn:admin1_code":"04",
    "gn:asciiname":"Douar Oulad El Arbi Ettouil",
    "gn:country_code":"MA",
    "gn:dem":148,
    "gn:feature_class":"P",
    "gn:feature_code":"PPL",
    "gn:name":"Douar Oulad El Arbi Ettouil",
    "gn:population":0,
    "gn:timezone":"Africa/Casablanca",
    "iso:country":"MA",
    "name:und_x_variant":[
        "Douar Larbi Touil",
        "Ouled Larbi Touil",
        "Larbi Touil",
        "Douar Oulad El Arbi Ettouil"
    ],
    "wof:name":"Douar Oulad El Arbi Ettouil",
    "wof:placetype":"locality"
},
  "geometry": {"coordinates":[-5.85558,34.82201],"type":"Point"}
}