{
  "type": "Feature",
  "properties": {
    "gn:admin1_code":"1.0",
    "gn:asciiname":"Douar Ourket",
    "gn:country_code":"MA",
    "gn:dem":892,
    "gn:feature_class":"P",
    "gn:feature_code":"PPL",
    "gn:name":"Douar Ourket",
    "gn:population":0,
    "gn:timezone":"Africa/Casablanca",
    "iso:country":"MA",
    "wof:name":"Douar Ourket",
    "wof:placetype":"locality"
},
  "geometry": {"coordinates":[-4.90431,35.23435999999999],"type":"Point"}
}