{
  "type": "Feature",
  "properties": {
    "gn:admin1_code":"10",
    "gn:asciiname":"Tadrar Ihoudrar",
    "gn:country_code":"MA",
    "gn:dem":312,
    "gn:feature_class":"P",
    "gn:feature_code":"PPL",
    "gn:name":"Tadrar Ihoudrar",
    "gn:population":0,
    "gn:timezone":"Africa/Casablanca",
    "iso:country":"MA",
    "name:und_x_variant":[
        "Tadrat Ibudraren",
        "Tadrart Ibudraren",
        "Tadrar Ihoudrar"
    ],
    "wof:name":"Tadrar Ihoudrar",
    "wof:placetype":"locality"
},
  "geometry": {"coordinates":[-9.98,29.45],"type":"Point"}
}