{
  "type": "Feature",
  "properties": {
    "gn:admin1_code":"7.0",
    "gn:asciiname":"Talatnine",
    "gn:country_code":"MA",
    "gn:dem":581,
    "gn:feature_class":"P",
    "gn:feature_code":"PPL",
    "gn:name":"Talatnine",
    "gn:population":0,
    "gn:timezone":"Africa/Casablanca",
    "iso:country":"MA",
    "wof:name":"Talatnine",
    "wof:placetype":"locality"
},
  "geometry": {"coordinates":[-9.67142,31.24794],"type":"Point"}
}