{
  "type": "Feature",
  "properties": {
    "gn:admin1_code":"07",
    "gn:asciiname":"Aghannaj",
    "gn:country_code":"MA",
    "gn:dem":95,
    "gn:feature_class":"P",
    "gn:feature_code":"PPL",
    "gn:name":"Aghannaj",
    "gn:population":0,
    "gn:timezone":"Africa/Casablanca",
    "iso:country":"MA",
    "name:und_x_variant":[
        "Aghnajane"
    ],
    "wof:name":"Aghannaj",
    "wof:placetype":"locality"
},
  "geometry": {"coordinates":[-9.78828,31.26606],"type":"Point"}
}