{
  "type": "Feature",
  "properties": {
    "gn:admin1_code":"06",
    "gn:asciiname":"Mohamed ben Mohammed",
    "gn:country_code":"MA",
    "gn:dem":154,
    "gn:feature_class":"P",
    "gn:feature_code":"PPL",
    "gn:name":"Mohamed ben Mohammed",
    "gn:population":0,
    "gn:timezone":"Africa/Casablanca",
    "iso:country":"MA",
    "name:und_x_variant":[
        "Douar Mohammed ben Mohammed"
    ],
    "wof:name":"Mohamed ben Mohammed",
    "wof:placetype":"locality"
},
  "geometry": {"coordinates":[-8.09604,32.99594],"type":"Point"}
}