{
  "type": "Feature",
  "properties": {
    "gn:admin1_code":"09",
    "gn:asciiname":"Zarhenrhine",
    "gn:country_code":"MA",
    "gn:dem":909,
    "gn:feature_class":"P",
    "gn:feature_code":"PPL",
    "gn:name":"Zarhenrhine",
    "gn:population":0,
    "gn:timezone":"Africa/Casablanca",
    "iso:country":"MA",
    "name:und_x_variant":[
        "Tagenghine",
        "Zarhenrhin",
        "Zarhenrhine"
    ],
    "wof:name":"Zarhenrhine",
    "wof:placetype":"locality"
},
  "geometry": {"coordinates":[-9.06418,30.68243],"type":"Point"}
}