{
  "type": "Feature",
  "properties": {
    "iso:country":"MA",
    "qs:gn_pop":0,
    "qs:name":"Douar Ouriki",
    "qs:name_adm0":"\u0627\u0644\u0645\u063a\u0631\u0628",
    "qs:name_adm1":"\u0645\u0631\u0627\u0643\u0634 \u0640 \u062a\u0627\u0646\u0633\u064a\u0641\u062a \u0640 \u0627\u0644\u062d\u0648\u0632",
    "qs:photos":203,
    "qs:photos_1k":41,
    "qs:photos_9k":1,
    "qs:photos_9r":4,
    "qs:photos_all":203,
    "qs:photos_sr":4,
    "qs:placetype":"Town",
    "qs:pop_sr":"0",
    "qs:woe_adm0":23424893,
    "wof:name":"Douar Ouriki",
    "wof:placetype":"locality"
},
  "geometry": {"coordinates":[-7.804498,31.375916],"type":"Point"}
}