{
  "type": "Feature",
  "properties": {
    "gn:admin1_code":"09",
    "gn:asciiname":"Dchira",
    "gn:country_code":"MA",
    "gn:dem":166,
    "gn:feature_class":"P",
    "gn:feature_code":"PPL",
    "gn:name":"Dchira",
    "gn:population":0,
    "gn:timezone":"Africa/Casablanca",
    "iso:country":"MA",
    "name:und_x_variant":[
        "Dche\u00efra",
        "Dcha\u00efra",
        "Dchira"
    ],
    "wof:name":"Dchira",
    "wof:placetype":"locality"
},
  "geometry": {"coordinates":[-9.70862,29.76108],"type":"Point"}
}