{
  "type": "Feature",
  "properties": {
    "gn:admin1_code":"03",
    "gn:asciiname":"Douar Taaouniyat El Qods",
    "gn:country_code":"MA",
    "gn:dem":403,
    "gn:feature_class":"P",
    "gn:feature_code":"PPL",
    "gn:name":"Douar Taaouniyat El Qods",
    "gn:population":0,
    "gn:timezone":"Africa/Casablanca",
    "iso:country":"MA",
    "wof:name":"Douar Taaouniyat El Qods",
    "wof:placetype":"locality"
},
  "geometry": {"coordinates":[-4.6982,34.40221],"type":"Point"}
}