{
  "type": "Feature",
  "properties": {
    "gn:admin1_code":"01",
    "gn:asciiname":"Oulad Ben Abdallah",
    "gn:country_code":"MA",
    "gn:dem":135,
    "gn:feature_class":"P",
    "gn:feature_code":"PPL",
    "gn:name":"Oulad Ben Abdallah",
    "gn:population":0,
    "gn:timezone":"Africa/Casablanca",
    "iso:country":"MA",
    "name:und_x_variant":[
        "Oulad Abdallah",
        "Oulad Ben Abdallah"
    ],
    "wof:name":"Oulad Ben Abdallah",
    "wof:placetype":"locality"
},
  "geometry": {"coordinates":[-5.96439,35.37209],"type":"Point"}
}