{
  "type": "Feature",
  "properties": {
    "gn:admin1_code":"9.0",
    "gn:asciiname":"Ait Tamzayt",
    "gn:country_code":"MA",
    "gn:dem":67,
    "gn:feature_class":"P",
    "gn:feature_code":"PPL",
    "gn:name":"Ait Tamzayt",
    "gn:population":0,
    "gn:timezone":"Africa/Casablanca",
    "iso:country":"MA",
    "wof:name":"Ait Tamzayt",
    "wof:placetype":"locality"
},
  "geometry": {"coordinates":[-9.66448,30.48071],"type":"Point"}
}