{
  "type": "Feature",
  "properties": {
    "gn:admin1_code":"5.0",
    "gn:asciiname":"Jemaa",
    "gn:country_code":"MA",
    "gn:dem":524,
    "gn:feature_class":"P",
    "gn:feature_code":"PPL",
    "gn:name":"Jemaa",
    "gn:population":0,
    "gn:timezone":"Africa/Casablanca",
    "iso:country":"MA",
    "wof:name":"Jemaa",
    "wof:placetype":"locality"
},
  "geometry": {"coordinates":[-6.2356,32.55907],"type":"Point"}
}