{
  "type": "Feature",
  "properties": {
    "gn:admin1_code":"7.0",
    "gn:asciiname":"Imich",
    "gn:country_code":"MA",
    "gn:dem":656,
    "gn:feature_class":"P",
    "gn:feature_code":"PPL",
    "gn:name":"Imich",
    "gn:population":0,
    "gn:timezone":"Africa/Casablanca",
    "iso:country":"MA",
    "wof:name":"Imich",
    "wof:placetype":"locality"
},
  "geometry": {"coordinates":[-9.42284,31.29651],"type":"Point"}
}