{
  "type": "Feature",
  "properties": {
    "gn:admin1_code":"03",
    "gn:asciiname":"Douar El Mers",
    "gn:country_code":"MA",
    "gn:dem":720,
    "gn:feature_class":"P",
    "gn:feature_code":"PPL",
    "gn:name":"Douar El Mers",
    "gn:population":0,
    "gn:timezone":"Africa/Casablanca",
    "iso:country":"MA",
    "name:und_x_variant":[
        "El Mers"
    ],
    "wof:name":"Douar El Mers",
    "wof:placetype":"locality"
},
  "geometry": {"coordinates":[-4.38607,34.28939],"type":"Point"}
}