{
  "type": "Feature",
  "properties": {
    "gn:admin1_code":"07",
    "gn:asciiname":"Goumarat",
    "gn:country_code":"MA",
    "gn:dem":479,
    "gn:feature_class":"P",
    "gn:feature_code":"PPL",
    "gn:name":"Goumarat",
    "gn:population":0,
    "gn:timezone":"Africa/Casablanca",
    "iso:country":"MA",
    "name:und_x_variant":[
        "Che\u00efkh Lahsene",
        "Guemarat",
        "Douar Cheikh Lahsene",
        "Goumarate",
        "Goumarat"
    ],
    "wof:name":"Goumarat",
    "wof:placetype":"locality"
},
  "geometry": {"coordinates":[-8.19975,32.06255],"type":"Point"}
}