{
  "type": "Feature",
  "properties": {
    "gn:admin1_code":"7.0",
    "gn:asciiname":"Oulad Taleb",
    "gn:country_code":"MA",
    "gn:dem":510,
    "gn:feature_class":"P",
    "gn:feature_code":"PPL",
    "gn:name":"Oulad Taleb",
    "gn:population":0,
    "gn:timezone":"Africa/Casablanca",
    "iso:country":"MA",
    "wof:name":"Oulad Taleb",
    "wof:placetype":"locality"
},
  "geometry": {"coordinates":[-7.92179,32.40072],"type":"Point"}
}