{
  "type": "Feature",
  "properties": {
    "gn:admin1_code":"6.0",
    "gn:asciiname":"Ramliya",
    "gn:country_code":"MA",
    "gn:dem":116,
    "gn:feature_class":"P",
    "gn:feature_code":"PPL",
    "gn:name":"Ramliya",
    "gn:population":0,
    "gn:timezone":"Africa/Casablanca",
    "iso:country":"MA",
    "wof:name":"Ramliya",
    "wof:placetype":"locality"
},
  "geometry": {"coordinates":[-7.08766,33.77165],"type":"Point"}
}