{
  "type": "Feature",
  "properties": {
    "gn:admin1_code":"04",
    "gn:asciiname":"Boumehidi",
    "gn:country_code":"MA",
    "gn:dem":15,
    "gn:feature_class":"P",
    "gn:feature_code":"PPL",
    "gn:name":"Boumehidi",
    "gn:population":0,
    "gn:timezone":"Africa/Casablanca",
    "iso:country":"MA",
    "name:und_x_variant":[
        "Douar Boumehidi",
        "Boumehidi"
    ],
    "wof:name":"Boumehidi",
    "wof:placetype":"locality"
},
  "geometry": {"coordinates":[-6.10429,34.719],"type":"Point"}
}