{
  "type": "Feature",
  "properties": {
    "gn:admin1_code":"04",
    "gn:asciiname":"Douar Oulad Essaada",
    "gn:country_code":"MA",
    "gn:dem":139,
    "gn:feature_class":"P",
    "gn:feature_code":"PPL",
    "gn:name":"Douar Oulad Essaada",
    "gn:population":0,
    "gn:timezone":"Africa/Casablanca",
    "iso:country":"MA",
    "name:und_x_variant":[
        "Ouled Sa\u00e2da",
        "Oulad Saada",
        "Douar Oulad Saada",
        "Douar Oulad Essaada"
    ],
    "wof:name":"Douar Oulad Essaada",
    "wof:placetype":"locality"
},
  "geometry": {"coordinates":[-5.66737,34.68843],"type":"Point"}
}