{
  "type": "Feature",
  "properties": {
    "gn:admin1_code":"7.0",
    "gn:asciiname":"Douar Bir Essedra",
    "gn:country_code":"MA",
    "gn:dem":603,
    "gn:feature_class":"P",
    "gn:feature_code":"PPL",
    "gn:name":"Douar Bir Essedra",
    "gn:population":0,
    "gn:timezone":"Africa/Casablanca",
    "iso:country":"MA",
    "wof:name":"Douar Bir Essedra",
    "wof:placetype":"locality"
},
  "geometry": {"coordinates":[-7.58678,31.98275],"type":"Point"}
}