{
  "type": "Feature",
  "properties": {
    "gn:admin1_code":"01",
    "gn:asciiname":"Chaib",
    "gn:country_code":"MA",
    "gn:dem":1034,
    "gn:feature_class":"P",
    "gn:feature_code":"PPL",
    "gn:name":"Cha\u00efb",
    "gn:population":0,
    "gn:timezone":"Africa/Casablanca",
    "iso:country":"MA",
    "wof:name":"Chaib",
    "wof:placetype":"locality"
},
  "geometry": {"coordinates":[-4.28,34.95],"type":"Point"}
}