{
  "type": "Feature",
  "properties": {
    "gn:admin1_code":"9.0",
    "gn:asciiname":"Imi-n-Ifriy",
    "gn:country_code":"MA",
    "gn:dem":2050,
    "gn:feature_class":"P",
    "gn:feature_code":"PPL",
    "gn:name":"Imi-n-Ifriy",
    "gn:population":0,
    "gn:timezone":"Africa/Casablanca",
    "iso:country":"MA",
    "wof:name":"Imi-n-Ifriy",
    "wof:placetype":"locality"
},
  "geometry": {"coordinates":[-7.74303,30.20404000000001],"type":"Point"}
}