{
  "type": "Feature",
  "properties": {
    "gn:admin1_code":"9.0",
    "gn:asciiname":"Amasmsa",
    "gn:country_code":"MA",
    "gn:dem":1723,
    "gn:feature_class":"P",
    "gn:feature_code":"PPL",
    "gn:name":"Amasmsa",
    "gn:population":0,
    "gn:timezone":"Africa/Casablanca",
    "iso:country":"MA",
    "wof:name":"Amasmsa",
    "wof:placetype":"locality"
},
  "geometry": {"coordinates":[-8.35379,30.09466],"type":"Point"}
}