{
  "type": "Feature",
  "properties": {
    "gn:admin1_code":"09",
    "gn:asciiname":"Ait Bakka",
    "gn:country_code":"MA",
    "gn:dem":947,
    "gn:feature_class":"P",
    "gn:feature_code":"PPL",
    "gn:name":"A\u00eft Bakka",
    "gn:population":0,
    "gn:timezone":"Africa/Casablanca",
    "iso:country":"MA",
    "wof:name":"Ait Bakka",
    "wof:placetype":"locality"
},
  "geometry": {"coordinates":[-8.75725,30.25182],"type":"Point"}
}