{
  "type": "Feature",
  "properties": {
    "gn:admin1_code":"10",
    "gn:asciiname":"Adai",
    "gn:country_code":"MA",
    "gn:dem":698,
    "gn:feature_class":"P",
    "gn:feature_code":"PPL",
    "gn:name":"Ada\u00ef",
    "gn:population":0,
    "gn:timezone":"Africa/Casablanca",
    "iso:country":"MA",
    "name:ceb_x_preferred":[
        "Adai"
    ],
    "name:fra_x_preferred":[
        "Adai"
    ],
    "name:glg_x_preferred":[
        "Adai"
    ],
    "name:swe_x_preferred":[
        "Adai"
    ],
    "name:tel_x_preferred":[
        "\u0c05\u0c21\u0c48"
    ],
    "name:und_x_variant":[
        "Souk Tnine d\u2019Adai",
        "Aday",
        "Ida\u00efssa Ametedi",
        "Addaye n\u2019Ait Herbil",
        "Ada\u00ef"
    ],
    "wof:name":"Adai",
    "wof:placetype":"locality"
},
  "geometry": {"coordinates":[-9.29972,29.14452],"type":"Point"}
}