{
  "type": "Feature",
  "properties": {
    "gn:admin1_code":"09",
    "gn:asciiname":"Id Ouchchene",
    "gn:country_code":"MA",
    "gn:dem":71,
    "gn:feature_class":"P",
    "gn:feature_code":"PPL",
    "gn:name":"Id Ouchchene",
    "gn:population":0,
    "gn:timezone":"Africa/Casablanca",
    "iso:country":"MA",
    "name:und_x_variant":[
        "Id Ouchchane",
        "Id Ouchchene"
    ],
    "wof:name":"Id Ouchchene",
    "wof:placetype":"locality"
},
  "geometry": {"coordinates":[-9.83758,30.6946],"type":"Point"}
}