{
  "type": "Feature",
  "properties": {
    "gn:admin1_code":"3.0",
    "gn:asciiname":"Qantrat Rghioua",
    "gn:country_code":"MA",
    "gn:dem":267,
    "gn:feature_class":"P",
    "gn:feature_code":"PPLL",
    "gn:name":"Qantrat Rghioua",
    "gn:population":0,
    "gn:timezone":"Africa/Casablanca",
    "iso:country":"MA",
    "wof:name":"Qantrat Rghioua",
    "wof:placetype":"locality"
},
  "geometry": {"coordinates":[-4.61052,34.49098],"type":"Point"}
}