{
  "type": "Feature",
  "properties": {
    "gn:admin1_code":"7.0",
    "gn:asciiname":"Edcher Lahmer",
    "gn:country_code":"MA",
    "gn:dem":422,
    "gn:feature_class":"P",
    "gn:feature_code":"PPL",
    "gn:name":"Edcher Lahmer",
    "gn:population":0,
    "gn:timezone":"Africa/Casablanca",
    "iso:country":"MA",
    "wof:name":"Edcher Lahmer",
    "wof:placetype":"locality"
},
  "geometry": {"coordinates":[-8.70427,32.20858],"type":"Point"}
}