{
  "type": "Feature",
  "properties": {
    "gn:admin1_code":"10",
    "gn:asciiname":"Tal'aynt Ikharbine",
    "gn:country_code":"MA",
    "gn:dem":461,
    "gn:feature_class":"P",
    "gn:feature_code":"PPL",
    "gn:name":"Tal\u2019aynt Ikharbine",
    "gn:population":0,
    "gn:timezone":"Africa/Casablanca",
    "iso:country":"MA",
    "name:und_x_variant":[
        "Toutline A\u00efn Irerbine",
        "Talaint-Irherbiin",
        "Tala\u00efnt Irherbiine",
        "Tal\u2019aynt Ikharbine"
    ],
    "wof:name":"Tal'aynt Ikharbine",
    "wof:placetype":"locality"
},
  "geometry": {"coordinates":[-9.81596,29.03122],"type":"Point"}
}