{
  "type": "Feature",
  "properties": {
    "gn:admin1_code":"3.0",
    "gn:asciiname":"Iharoujen",
    "gn:country_code":"MA",
    "gn:dem":1235,
    "gn:feature_class":"P",
    "gn:feature_code":"PPL",
    "gn:name":"Iharoujen",
    "gn:population":0,
    "gn:timezone":"Africa/Casablanca",
    "iso:country":"MA",
    "wof:name":"Iharoujen",
    "wof:placetype":"locality"
},
  "geometry": {"coordinates":[-5.31954,33.51711],"type":"Point"}
}