{
  "type": "Feature",
  "properties": {
    "gn:admin1_code":"10",
    "gn:asciiname":"Bouchma",
    "gn:country_code":"MA",
    "gn:dem":291,
    "gn:feature_class":"P",
    "gn:feature_code":"PPL",
    "gn:name":"Bouchma",
    "gn:population":0,
    "gn:timezone":"Africa/Casablanca",
    "iso:country":"MA",
    "name:und_x_variant":[
        "Buxma",
        "Bouchma"
    ],
    "wof:name":"Bouchma",
    "wof:placetype":"locality"
},
  "geometry": {"coordinates":[-10.22267,29.1567],"type":"Point"}
}