{
  "type": "Feature",
  "properties": {
    "gn:admin1_code":"5.0",
    "gn:asciiname":"Es Sebt el Maadna",
    "gn:country_code":"MA",
    "gn:dem":921,
    "gn:feature_class":"P",
    "gn:feature_code":"PPL",
    "gn:name":"Es Sebt el Ma\u00e2dna",
    "gn:population":0,
    "gn:timezone":"Africa/Casablanca",
    "iso:country":"MA",
    "wof:name":"Es Sebt el Maadna",
    "wof:placetype":"locality"
},
  "geometry": {"coordinates":[-6.4816,32.92106],"type":"Point"}
}