{
  "type": "Feature",
  "properties": {
    "gn:admin1_code":"05",
    "gn:asciiname":"Ait Ouichouane",
    "gn:country_code":"MA",
    "gn:dem":832,
    "gn:elevation":"0.0",
    "gn:feature_class":"P",
    "gn:feature_code":"PPL",
    "gn:name":"A\u00eft Ouichouane",
    "gn:population":0,
    "gn:timezone":"Africa/Casablanca",
    "iso:country":"MA",
    "wof:name":"Ait Ouichouane",
    "wof:placetype":"locality"
},
  "geometry": {"coordinates":[-6.89192,31.97034],"type":"Point"}
}