{
  "type": "Feature",
  "properties": {
    "gn:admin1_code":"01",
    "gn:asciiname":"Souani Nekkour",
    "gn:country_code":"MA",
    "gn:dem":9,
    "gn:feature_class":"P",
    "gn:feature_code":"PPL",
    "gn:name":"Souani Nekkour",
    "gn:population":0,
    "gn:timezone":"Africa/Casablanca",
    "iso:country":"MA",
    "wof:name":"Souani Nekkour",
    "wof:placetype":"locality"
},
  "geometry": {"coordinates":[-3.83018,35.19465],"type":"Point"}
}