{
  "type": "Feature",
  "properties": {
    "gn:admin1_code":"7.0",
    "gn:asciiname":"Al Mtafia",
    "gn:country_code":"MA",
    "gn:dem":517,
    "gn:feature_class":"P",
    "gn:feature_code":"PPL",
    "gn:name":"Al Mtafia",
    "gn:population":0,
    "gn:timezone":"Africa/Casablanca",
    "iso:country":"MA",
    "wof:name":"Al Mtafia",
    "wof:placetype":"locality"
},
  "geometry": {"coordinates":[-8.25839,31.47268],"type":"Point"}
}