{
  "type": "Feature",
  "properties": {
    "gn:admin1_code":"09",
    "gn:asciiname":"Iggui n'Tama",
    "gn:country_code":"MA",
    "gn:dem":975,
    "gn:feature_class":"P",
    "gn:feature_code":"PPL",
    "gn:name":"Iggui n\u2019Tama",
    "gn:population":0,
    "gn:timezone":"Africa/Casablanca",
    "iso:country":"MA",
    "name:und_x_variant":[
        "Iggi n\u2019Tama",
        "Igni n\u2019Tama",
        "Iggui n\u2019Tama"
    ],
    "wof:name":"Iggui n'Tama",
    "wof:placetype":"locality"
},
  "geometry": {"coordinates":[-9.39503,30.81446],"type":"Point"}
}