{
  "type": "Feature",
  "properties": {
    "gn:admin1_code":"01",
    "gn:asciiname":"Souariene",
    "gn:country_code":"MA",
    "gn:dem":108,
    "gn:feature_class":"P",
    "gn:feature_code":"PPL",
    "gn:name":"Souariene",
    "gn:population":0,
    "gn:timezone":"Africa/Casablanca",
    "iso:country":"MA",
    "name:und_x_variant":[
        "Chouari\u00e8n",
        "Souariene"
    ],
    "wof:name":"Souariene",
    "wof:placetype":"locality"
},
  "geometry": {"coordinates":[-5.82067,35.06082],"type":"Point"}
}