{
  "type": "Feature",
  "properties": {
    "gn:country":"MA",
    "gn:fcode":"ADM3",
    "gn:pop":13291,
    "iso:country":"MA",
    "name:ara_x_preferred":[
        "\u0623\u064a\u062a \u062d\u0631\u0632 \u0627\u0644\u0644\u0647"
    ],
    "name:fra_x_preferred":[
        "Agourai"
    ],
    "name:fra_x_variant":[
        "Agourai (MU)",
        "Agourai (Commune Urbaine)"
    ],
    "qs:name":"Agourai",
    "qs:photos_9r":0,
    "qs:photos_sr":0,
    "qs:pop_sr":"6",
    "wd:wordcount":24,
    "wof:name":"Agourai",
    "wof:placetype":"localadmin",
    "wof:population":13291
},
  "geometry": {"coordinates":[-5.59183,33.63883],"type":"Point"}
}