{
  "type": "Feature",
  "properties": {
    "gn:admin1_code":"3.0",
    "gn:asciiname":"Ait Brahim",
    "gn:country_code":"MA",
    "gn:dem":825,
    "gn:feature_class":"P",
    "gn:feature_code":"PPL",
    "gn:name":"Ait Brahim",
    "gn:population":0,
    "gn:timezone":"Africa/Casablanca",
    "iso:country":"MA",
    "wof:name":"Ait Brahim",
    "wof:placetype":"locality"
},
  "geometry": {"coordinates":[-5.70362,33.65228],"type":"Point"}
}