{
  "type": "Feature",
  "properties": {
    "gn:gn_country":"MA",
    "gn:gn_fcode":"ADM3",
    "gn:gn_pop":3534,
    "gn:population":2410,
    "iso:country":"MA",
    "name:ara_x_preferred":[
        "\u0628\u0646\u064a \u0623\u062d\u0645\u062f  \u0627\u0644\u063a\u0631\u0628\u064a\u0629"
    ],
    "name:fra_x_preferred":[
        "Bouyablane"
    ],
    "name:fra_x_variant":[
        "Bouyablane (CR)",
        "Bouyablane (Commune Rurale)"
    ],
    "qs_pg:aaroncc":"MA",
    "qs_pg:gn_country":"MA",
    "qs_pg:gn_fcode":"ADM3",
    "qs_pg:gn_pop":3534,
    "qs_pg:name":"Bouyablane",
    "qs_pg:photos_9r":0,
    "qs_pg:photos_sr":0,
    "qs_pg:pop_sr":4,
    "qs_pg:qs_pg_placetype":"localadmin",
    "wof:name":"Bouyablane",
    "wof:placetype":"localadmin",
    "wof:population":2410
},
  "geometry": {"coordinates":[-4.0401,33.76755],"type":"Point"}
}