{
  "type": "Feature",
  "properties": {
    "gn:admin1_code":"7.0",
    "gn:asciiname":"Douar Laazib",
    "gn:country_code":"MA",
    "gn:dem":504,
    "gn:feature_class":"P",
    "gn:feature_code":"PPL",
    "gn:name":"Douar Laazib",
    "gn:population":0,
    "gn:timezone":"Africa/Casablanca",
    "iso:country":"MA",
    "wof:name":"Douar Laazib",
    "wof:placetype":"locality"
},
  "geometry": {"coordinates":[-8.94237,31.94303],"type":"Point"}
}