{
  "type": "Feature",
  "properties": {
    "gn:admin1_code":"1.0",
    "gn:asciiname":"Errabda",
    "gn:country_code":"MA",
    "gn:dem":741,
    "gn:feature_class":"P",
    "gn:feature_code":"PPL",
    "gn:name":"Errabda",
    "gn:population":0,
    "gn:timezone":"Africa/Casablanca",
    "iso:country":"MA",
    "wof:name":"Errabda",
    "wof:placetype":"locality"
},
  "geometry": {"coordinates":[-3.86631,35.04565],"type":"Point"}
}