{
  "type": "Feature",
  "properties": {
    "gn:admin1_code":"08",
    "gn:asciiname":"Tizegzaouine",
    "gn:country_code":"MA",
    "gn:dem":1236,
    "gn:feature_class":"P",
    "gn:feature_code":"PPL",
    "gn:name":"Tizegzaouine",
    "gn:population":0,
    "gn:timezone":"Africa/Casablanca",
    "iso:country":"MA",
    "name:und_x_variant":[
        "Tizgzawine",
        "Tizegzaouine"
    ],
    "wof:name":"Tizegzaouine",
    "wof:placetype":"locality"
},
  "geometry": {"coordinates":[-6.85904,30.49139000000001],"type":"Point"}
}