{
  "type": "Feature",
  "properties": {
    "gn:admin1_code":"08",
    "gn:asciiname":"Tayfst",
    "gn:country_code":"MA",
    "gn:dem":1367,
    "gn:feature_class":"P",
    "gn:feature_code":"PPL",
    "gn:name":"Tayfst",
    "gn:population":0,
    "gn:timezone":"Africa/Casablanca",
    "iso:country":"MA",
    "name:und_x_variant":[
        "Ta\u00effst",
        "Ta\u00effaste",
        "Ta\u00effest",
        "Tayfst"
    ],
    "wof:name":"Tayfst",
    "wof:placetype":"locality"
},
  "geometry": {"coordinates":[-7.1325,31.12035],"type":"Point"}
}