{
  "type": "Feature",
  "properties": {
    "gn:admin1_code":"7.0",
    "gn:asciiname":"Ait El Khabich",
    "gn:country_code":"MA",
    "gn:dem":483,
    "gn:feature_class":"P",
    "gn:feature_code":"PPL",
    "gn:name":"Ait El Khabich",
    "gn:population":0,
    "gn:timezone":"Africa/Casablanca",
    "iso:country":"MA",
    "wof:name":"Ait El Khabich",
    "wof:placetype":"locality"
},
  "geometry": {"coordinates":[-9.50739,31.24574],"type":"Point"}
}