{
  "type": "Feature",
  "properties": {
    "gn:country":"MA",
    "gn:fcode":"ADM3",
    "gn:pop":512,
    "iso:country":"MA",
    "name:ara_x_preferred":[
        "\u0628\u0648\u062c\u062f\u0648\u0631 (\u0627\u0644\u0628\u0644\u062f\u064a\u0629)"
    ],
    "name:fra_x_preferred":[
        "Gueltat Zemmour"
    ],
    "name:fra_x_variant":[
        "Gueltat Zemmour (CR)",
        "Gueltat Zemmour (Commune Rurale)"
    ],
    "qs:name":"Gueltat Zemmour",
    "qs:photos_9r":0,
    "qs:photos_sr":0,
    "qs:pop_sr":"2",
    "wd:wordcount":309,
    "wof:name":"Gueltat Zemmour",
    "wof:placetype":"localadmin",
    "wof:population":512
},
  "geometry": {"coordinates":[-12.89066,25.25419],"type":"Point"}
}