{
  "type": "Feature",
  "properties": {
    "gn:country":"MA",
    "gn:fcode":"ADM3",
    "gn:population":512,
    "iso:country":"MA",
    "name:ara_x_preferred":[
        "\u0628\u0648\u062c\u062f\u0648\u0631 (\u0627\u0644\u0628\u0644\u062f\u064a\u0629)"
    ],
    "name:ara_x_variant":[
        "\u0643\u0648\u0644\u062a\u0629 \u0632\u0645\u0648\u0631",
        "\u0643\u0644\u062a\u0629 \u0632\u0645\u0648\u0631"
    ],
    "name:ary_x_preferred":[
        "\u06ad\u0644\u062a\u0629 \u0632\u0645\u0648\u0631"
    ],
    "name:arz_x_preferred":[
        "\u0643\u0644\u062a\u0647 \u0632\u0645\u0648\u0631"
    ],
    "name:cat_x_preferred":[
        "Guelta Zemur"
    ],
    "name:ceb_x_preferred":[
        "Gueltat Zemmour"
    ],
    "name:deu_x_preferred":[
        "Guelta Zemmur"
    ],
    "name:eng_x_preferred":[
        "Guelta Zemmur"
    ],
    "name:epo_x_preferred":[
        "Guelta Zemmur"
    ],
    "name:fas_x_preferred":[
        "\u06a9\u0644\u062a\u0647 \u0632\u0645\u0648\u0631"
    ],
    "name:fra_x_preferred":[
        "Gueltat Zemmour"
    ],
    "name:fra_x_variant":[
        "Gueltat Zemmour (CR)",
        "Gueltat Zemmour (Commune Rurale)"
    ],
    "name:ita_x_preferred":[
        "Guelta Zemmur"
    ],
    "name:jpn_x_preferred":[
        "\u30b2\u30eb\u30bf\u30fb\u30bb\u30e0\u30fc\u30eb"
    ],
    "name:kaz_x_preferred":[
        "\u0413\u0435\u043b\u044c\u0442\u0430-\u0417\u0435\u043c\u043c\u0443\u0440"
    ],
    "name:nld_x_preferred":[
        "Guelta Zemmur"
    ],
    "name:pol_x_preferred":[
        "Kaltat Zammur"
    ],
    "name:rus_x_preferred":[
        "\u0413\u0435\u043b\u044c\u0442\u0430-\u0417\u0435\u043c\u043c\u0443\u0440"
    ],
    "name:spa_x_preferred":[
        "Guelta Zemmur"
    ],
    "name:swe_x_preferred":[
        "Gueltat Zemmour"
    ],
    "name:zho_x_preferred":[
        "\u683c\u5c14\u5854\u6cfd\u7a46\u5c14"
    ],
    "qs:name":"Gueltat Zemmour",
    "qs:photos_9r":0,
    "qs:photos_sr":0,
    "qs:pop_sr":"2",
    "wd:wordcount":309,
    "wof:name":"Gueltat Zemmour",
    "wof:placetype":"localadmin",
    "wof:population":512
},
  "geometry": {"coordinates":[-12.89066,25.25419],"type":"Point"}
}