{
  "type": "Feature",
  "properties": {
    "gn:admin1_code":"01",
    "gn:asciiname":"Douar Tioukal",
    "gn:country_code":"MA",
    "gn:dem":726,
    "gn:feature_class":"P",
    "gn:feature_code":"PPL",
    "gn:name":"Douar Tioukal",
    "gn:population":0,
    "gn:timezone":"Africa/Casablanca",
    "iso:country":"MA",
    "name:und_x_variant":[
        "Tioukal"
    ],
    "wof:name":"Douar Tioukal",
    "wof:placetype":"locality"
},
  "geometry": {"coordinates":[-5.42685,35.13959000000001],"type":"Point"}
}