{
  "type": "Feature",
  "properties": {
    "gn:admin1_code":"7.0",
    "gn:asciiname":"Sidi Mahdoud",
    "gn:country_code":"MA",
    "gn:dem":327,
    "gn:feature_class":"P",
    "gn:feature_code":"PPL",
    "gn:name":"Sidi Mahdoud",
    "gn:population":0,
    "gn:timezone":"Africa/Casablanca",
    "iso:country":"MA",
    "wof:name":"Sidi Mahdoud",
    "wof:placetype":"locality"
},
  "geometry": {"coordinates":[-9.64974,31.11489000000001],"type":"Point"}
}