{
  "type": "Feature",
  "properties": {
    "gn:admin1_code":"7.0",
    "gn:asciiname":"Ait Abd es Slam",
    "gn:country_code":"MA",
    "gn:dem":868,
    "gn:feature_class":"P",
    "gn:feature_code":"PPL",
    "gn:name":"A\u00eft Abd es Slam",
    "gn:population":0,
    "gn:timezone":"Africa/Casablanca",
    "iso:country":"MA",
    "wof:name":"Ait Abd es Slam",
    "wof:placetype":"locality"
},
  "geometry": {"coordinates":[-8.23278,31.26802],"type":"Point"}
}