{
  "type": "Feature",
  "properties": {
    "gn:admin1_code":"9.0",
    "gn:asciiname":"Bordj",
    "gn:country_code":"MA",
    "gn:dem":758,
    "gn:feature_class":"P",
    "gn:feature_code":"PPL",
    "gn:name":"Bordj",
    "gn:population":0,
    "gn:timezone":"Africa/Casablanca",
    "iso:country":"MA",
    "wof:name":"Bordj",
    "wof:placetype":"locality"
},
  "geometry": {"coordinates":[-9.12768,30.77662],"type":"Point"}
}