{
  "type": "Feature",
  "properties": {
    "gn:admin1_code":"7.0",
    "gn:asciiname":"Cooperative Argane El Khir",
    "gn:country_code":"MA",
    "gn:dem":208,
    "gn:feature_class":"P",
    "gn:feature_code":"PPLF",
    "gn:name":"Coop\u00e9rative Argane El Khir",
    "gn:population":0,
    "gn:timezone":"Africa/Casablanca",
    "iso:country":"MA",
    "wof:name":"Cooperative Argane El Khir",
    "wof:placetype":"locality"
},
  "geometry": {"coordinates":[-9.62023,31.52467],"type":"Point"}
}