{
  "type": "Feature",
  "properties": {
    "gn:admin1_code":"09",
    "gn:asciiname":"Tifirras",
    "gn:country_code":"MA",
    "gn:dem":1211,
    "gn:feature_class":"P",
    "gn:feature_code":"PPL",
    "gn:name":"Tifirras",
    "gn:population":0,
    "gn:timezone":"Africa/Casablanca",
    "iso:country":"MA",
    "name:und_x_variant":[
        "Tifirest"
    ],
    "wof:name":"Tifirras",
    "wof:placetype":"locality"
},
  "geometry": {"coordinates":[-8.11855,30.47217],"type":"Point"}
}