{
  "type": "Feature",
  "properties": {
    "gn:admin1_code":"9.0",
    "gn:asciiname":"Tawdant",
    "gn:country_code":"MA",
    "gn:dem":959,
    "gn:feature_class":"P",
    "gn:feature_code":"PPL",
    "gn:name":"Tawdant",
    "gn:population":0,
    "gn:timezone":"Africa/Casablanca",
    "iso:country":"MA",
    "wof:name":"Tawdant",
    "wof:placetype":"locality"
},
  "geometry": {"coordinates":[-9.14201,29.82218],"type":"Point"}
}