{
  "type": "Feature",
  "properties": {
    "gn:admin1_code":"01",
    "gn:asciiname":"Douar Laansar",
    "gn:country_code":"MA",
    "gn:dem":385,
    "gn:feature_class":"P",
    "gn:feature_code":"PPL",
    "gn:name":"Douar Laansar",
    "gn:population":0,
    "gn:timezone":"Africa/Casablanca",
    "iso:country":"MA",
    "name:und_x_variant":[
        "Aonzar"
    ],
    "wof:name":"Douar Laansar",
    "wof:placetype":"locality"
},
  "geometry": {"coordinates":[-5.57691,35.60567],"type":"Point"}
}