{
  "type": "Feature",
  "properties": {
    "gn:admin1_code":"6.0",
    "gn:asciiname":"El Mouaaenine",
    "gn:country_code":"MA",
    "gn:dem":198,
    "gn:feature_class":"P",
    "gn:feature_code":"PPL",
    "gn:name":"El Mouaaenine",
    "gn:population":0,
    "gn:timezone":"Africa/Casablanca",
    "iso:country":"MA",
    "wof:name":"El Mouaaenine",
    "wof:placetype":"locality"
},
  "geometry": {"coordinates":[-8.11668,32.89524],"type":"Point"}
}