{
  "type": "Feature",
  "properties": {
    "gn:admin1_code":"3.0",
    "gn:asciiname":"Coop. Douar El Moussakene",
    "gn:country_code":"MA",
    "gn:dem":154,
    "gn:feature_class":"P",
    "gn:feature_code":"PPL",
    "gn:name":"Coop. Douar El Moussakene",
    "gn:population":0,
    "gn:timezone":"Africa/Casablanca",
    "iso:country":"MA",
    "wof:name":"Coop. Douar El Moussakene",
    "wof:placetype":"locality"
},
  "geometry": {"coordinates":[-4.81011,34.20999],"type":"Point"}
}