{
  "type": "Feature",
  "properties": {
    "gn:admin1_code":"01",
    "gn:asciiname":"Abiyat",
    "gn:country_code":"MA",
    "gn:dem":100,
    "gn:feature_class":"P",
    "gn:feature_code":"PPL",
    "gn:name":"Abiyat",
    "gn:population":0,
    "gn:timezone":"Africa/Casablanca",
    "iso:country":"MA",
    "name:und_x_variant":[
        "Abial",
        "Abiat",
        "Abiyat"
    ],
    "wof:name":"Abiyat",
    "wof:placetype":"locality"
},
  "geometry": {"coordinates":[-5.86098,35.40869],"type":"Point"}
}