{
  "type": "Feature",
  "properties": {
    "gn:admin1_code":"4.0",
    "gn:asciiname":"Dar Lkhamis Hssina",
    "gn:country_code":"MA",
    "gn:dem":12,
    "gn:feature_class":"P",
    "gn:feature_code":"PPL",
    "gn:name":"Dar Lkhamis Hssina",
    "gn:population":0,
    "gn:timezone":"Africa/Casablanca",
    "iso:country":"MA",
    "wof:name":"Dar Lkhamis Hssina",
    "wof:placetype":"locality"
},
  "geometry": {"coordinates":[-6.17183,34.74517],"type":"Point"}
}