{
  "type": "Feature",
  "properties": {
    "gn:admin1_code":"7.0",
    "gn:asciiname":"Douar Jilali Bou Aissa",
    "gn:country_code":"MA",
    "gn:dem":441,
    "gn:feature_class":"P",
    "gn:feature_code":"PPL",
    "gn:name":"Douar Jilali Bou A\u00efssa",
    "gn:population":0,
    "gn:timezone":"Africa/Casablanca",
    "iso:country":"MA",
    "wof:name":"Douar Jilali Bou Aissa",
    "wof:placetype":"locality"
},
  "geometry": {"coordinates":[-7.24378,32.11679],"type":"Point"}
}