{
  "type": "Feature",
  "properties": {
    "gn:admin1_code":"02",
    "gn:asciiname":"Bou Hlal",
    "gn:country_code":"MA",
    "gn:dem":491,
    "gn:feature_class":"P",
    "gn:feature_code":"PPL",
    "gn:name":"Bou Hlal",
    "gn:population":0,
    "gn:timezone":"Africa/Casablanca",
    "iso:country":"MA",
    "wof:name":"Bou Hlal",
    "wof:placetype":"locality"
},
  "geometry": {"coordinates":[-3.48777,33.91942],"type":"Point"}
}