{
  "type": "Feature",
  "properties": {
    "gn:admin1_code":"7.0",
    "gn:asciiname":"Afoud",
    "gn:country_code":"MA",
    "gn:dem":1651,
    "gn:feature_class":"P",
    "gn:feature_code":"PPL",
    "gn:name":"Afoud",
    "gn:population":0,
    "gn:timezone":"Africa/Casablanca",
    "iso:country":"MA",
    "wof:name":"Afoud",
    "wof:placetype":"locality"
},
  "geometry": {"coordinates":[-7.52039,31.31701],"type":"Point"}
}