{
  "type": "Feature",
  "properties": {
    "gn:admin1_code":"2.0",
    "gn:asciiname":"Douar Timergam",
    "gn:country_code":"MA",
    "gn:dem":624,
    "gn:feature_class":"P",
    "gn:feature_code":"PPL",
    "gn:name":"Douar Timergam",
    "gn:population":0,
    "gn:timezone":"Africa/Casablanca",
    "iso:country":"MA",
    "wof:name":"Douar Timergam",
    "wof:placetype":"locality"
},
  "geometry": {"coordinates":[-2.31421,34.68772],"type":"Point"}
}