{
  "type": "Feature",
  "properties": {
    "gn:admin1_code":"01",
    "gn:asciiname":"Douar Orrane",
    "gn:country_code":"MA",
    "gn:dem":990,
    "gn:feature_class":"P",
    "gn:feature_code":"PPL",
    "gn:name":"Douar Orrane",
    "gn:population":0,
    "gn:timezone":"Africa/Casablanca",
    "iso:country":"MA",
    "name:und_x_variant":[
        "Iordane"
    ],
    "wof:name":"Douar Orrane",
    "wof:placetype":"locality"
},
  "geometry": {"coordinates":[-5.09422,35.08869],"type":"Point"}
}