{
  "type": "Feature",
  "properties": {
    "gn:admin1_code":"10",
    "gn:asciiname":"Id Barka",
    "gn:country_code":"MA",
    "gn:dem":892,
    "gn:feature_class":"P",
    "gn:feature_code":"PPL",
    "gn:name":"Id Barka",
    "gn:population":0,
    "gn:timezone":"Africa/Casablanca",
    "iso:country":"MA",
    "name:und_x_variant":[
        "Id Berka"
    ],
    "wof:name":"Id Barka",
    "wof:placetype":"locality"
},
  "geometry": {"coordinates":[-9.77671,29.38747],"type":"Point"}
}