{
  "type": "Feature",
  "properties": {
    "gn:admin1_code":"03",
    "gn:asciiname":"Beni Oulid",
    "gn:country_code":"MA",
    "gn:dem":388,
    "gn:feature_class":"P",
    "gn:feature_code":"PPL",
    "gn:name":"Beni Oulid",
    "gn:population":0,
    "gn:timezone":"Africa/Casablanca",
    "iso:country":"MA",
    "wof:name":"Beni Oulid",
    "wof:placetype":"locality"
},
  "geometry": {"coordinates":[-4.446,34.58894],"type":"Point"}
}