{
  "type": "Feature",
  "properties": {
    "gn:admin1_code":"10",
    "gn:asciiname":"Tabainout",
    "gn:country_code":"MA",
    "gn:dem":324,
    "gn:feature_class":"P",
    "gn:feature_code":"PPL",
    "gn:name":"Taba\u00efnout",
    "gn:population":0,
    "gn:timezone":"Africa/Casablanca",
    "iso:country":"MA",
    "name:und_x_variant":[
        "Tabainut",
        "Taba\u00efnout"
    ],
    "wof:name":"Tabainout",
    "wof:placetype":"locality"
},
  "geometry": {"coordinates":[-10.18766,29.23937],"type":"Point"}
}