{
  "type": "Feature",
  "properties": {
    "gn:admin1_code":"9.0",
    "gn:asciiname":"Tiguemi Azrou",
    "gn:country_code":"MA",
    "gn:dem":1116,
    "gn:feature_class":"P",
    "gn:feature_code":"PPL",
    "gn:name":"Tiguemi Azrou",
    "gn:population":0,
    "gn:timezone":"Africa/Casablanca",
    "iso:country":"MA",
    "wof:name":"Tiguemi Azrou",
    "wof:placetype":"locality"
},
  "geometry": {"coordinates":[-9.13872,30.71206],"type":"Point"}
}