{
  "type": "Feature",
  "properties": {
    "gn:admin1_code":"07",
    "gn:asciiname":"Oulad Ben Omar",
    "gn:country_code":"MA",
    "gn:dem":518,
    "gn:feature_class":"P",
    "gn:feature_code":"PPL",
    "gn:name":"Oulad Ben Omar",
    "gn:population":0,
    "gn:timezone":"Africa/Casablanca",
    "iso:country":"MA",
    "name:und_x_variant":[
        "Douar Oulad ben Omar",
        "Ouled Amar",
        "Oulad Ben Omar"
    ],
    "wof:name":"Oulad Ben Omar",
    "wof:placetype":"locality"
},
  "geometry": {"coordinates":[-7.58216,32.00183],"type":"Point"}
}