{
  "type": "Feature",
  "properties": {
    "gn:admin1_code":"09",
    "gn:asciiname":"Ait ou Arad",
    "gn:country_code":"MA",
    "gn:dem":290,
    "gn:feature_class":"P",
    "gn:feature_code":"PPL",
    "gn:name":"A\u00eft ou Arad",
    "gn:population":0,
    "gn:timezone":"Africa/Casablanca",
    "iso:country":"MA",
    "name:und_x_variant":[
        "A\u00eft ou Arad",
        "A\u00eft Ou Azad"
    ],
    "wof:name":"Ait ou Arad",
    "wof:placetype":"locality"
},
  "geometry": {"coordinates":[-9.34837,30.52082],"type":"Point"}
}