{
  "type": "Feature",
  "properties": {
    "gn:admin1_code":"6.0",
    "gn:asciiname":"Douar Azib Lghaouti",
    "gn:country_code":"MA",
    "gn:dem":251,
    "gn:feature_class":"P",
    "gn:feature_code":"PPL",
    "gn:name":"Douar Azib Lghaouti",
    "gn:population":0,
    "gn:timezone":"Africa/Casablanca",
    "iso:country":"MA",
    "wof:name":"Douar Azib Lghaouti",
    "wof:placetype":"locality"
},
  "geometry": {"coordinates":[-8.40875,32.48373],"type":"Point"}
}