{
  "type": "Feature",
  "properties": {
    "gn:admin1_code":"5.0",
    "gn:asciiname":"Azib Al Houssein Ou Abdallah",
    "gn:country_code":"MA",
    "gn:dem":1240,
    "gn:feature_class":"P",
    "gn:feature_code":"PPL",
    "gn:name":"Azib Al Houssein Ou Abdallah",
    "gn:population":0,
    "gn:timezone":"Africa/Casablanca",
    "iso:country":"MA",
    "wof:name":"Azib Al Houssein Ou Abdallah",
    "wof:placetype":"locality"
},
  "geometry": {"coordinates":[-7.01832,31.69875],"type":"Point"}
}