{
  "type": "Feature",
  "properties": {
    "gn:admin1_code":"01",
    "gn:asciiname":"Rhamna",
    "gn:country_code":"MA",
    "gn:dem":53,
    "gn:feature_class":"P",
    "gn:feature_code":"PPL",
    "gn:name":"Rhamna",
    "gn:population":0,
    "gn:timezone":"Africa/Casablanca",
    "iso:country":"MA",
    "name:und_x_variant":[
        "Er Rehamna",
        "Ghamna"
    ],
    "wof:name":"Rhamna",
    "wof:placetype":"locality"
},
  "geometry": {"coordinates":[-6.15282,35.08213],"type":"Point"}
}