{
  "type": "Feature",
  "properties": {
    "gn:admin1_code":"01",
    "gn:asciiname":"Assaki",
    "gn:country_code":"MA",
    "gn:dem":956,
    "gn:feature_class":"P",
    "gn:feature_code":"PPL",
    "gn:name":"Ass\u00e2ki",
    "gn:population":0,
    "gn:timezone":"Africa/Casablanca",
    "iso:country":"MA",
    "name:ara_x_preferred":[
        "\u0623\u0633\u0627\u0643\u064a"
    ],
    "name:cat_x_preferred":[
        "Assaki"
    ],
    "name:ita_x_preferred":[
        "Assaki"
    ],
    "name:und_x_variant":[
        "Ass\u00e2ki"
    ],
    "wof:name":"Assaki",
    "wof:placetype":"locality"
},
  "geometry": {"coordinates":[-4.68467,35.04221],"type":"Point"}
}