{
  "type": "Feature",
  "properties": {
    "gn:admin1_code":"4.0",
    "gn:asciiname":"Laabboubiyine",
    "gn:country_code":"MA",
    "gn:dem":47,
    "gn:feature_class":"P",
    "gn:feature_code":"PPL",
    "gn:name":"Laabboubiyine",
    "gn:population":0,
    "gn:timezone":"Africa/Casablanca",
    "iso:country":"MA",
    "wof:name":"Laabboubiyine",
    "wof:placetype":"locality"
},
  "geometry": {"coordinates":[-6.50868,34.17499],"type":"Point"}
}