{
  "type": "Feature",
  "properties": {
    "gn:country":"MA",
    "gn:fcode":"ADM3",
    "gn:population":5056,
    "iso:country":"MA",
    "name:ara_x_preferred":[
        "\u0645\u0644\u064a\u0644\u0629"
    ],
    "name:fra_x_preferred":[
        "Oulad Ali Toualaa"
    ],
    "name:fra_x_variant":[
        "Oulad Ali Toualaa (CR)",
        "Oulad Ali Toualaa (Commune Rurale)"
    ],
    "qs_pg:aaroncc":"MA",
    "qs_pg:gn_country":"MA",
    "qs_pg:gn_fcode":"ADM3",
    "qs_pg:gn_pop":5056,
    "qs_pg:name":"Oulad Ali Toualaa",
    "qs_pg:photos_9r":0,
    "qs_pg:photos_sr":0,
    "qs_pg:pop_sr":5,
    "qs_pg:qs_pg_placetype":"localadmin",
    "wof:name":"Oulad Ali Toualaa",
    "wof:placetype":"localadmin",
    "wof:population":5504
},
  "geometry": {"coordinates":[-7.17718,33.43868],"type":"Point"}
}