{
  "type": "Feature",
  "properties": {
    "gn:admin1_code":"9.0",
    "gn:asciiname":"Takoujit",
    "gn:country_code":"MA",
    "gn:dem":749,
    "gn:feature_class":"P",
    "gn:feature_code":"PPL",
    "gn:name":"Takoujit",
    "gn:population":0,
    "gn:timezone":"Africa/Casablanca",
    "iso:country":"MA",
    "wof:name":"Takoujit",
    "wof:placetype":"locality"
},
  "geometry": {"coordinates":[-9.78452,29.44596],"type":"Point"}
}