{
  "type": "Feature",
  "properties": {
    "gn:admin1_code":"09",
    "gn:asciiname":"Imiriy",
    "gn:country_code":"MA",
    "gn:dem":1443,
    "gn:feature_class":"P",
    "gn:feature_code":"PPL",
    "gn:name":"Imiriy",
    "gn:population":0,
    "gn:timezone":"Africa/Casablanca",
    "iso:country":"MA",
    "name:und_x_variant":[
        "Imiri"
    ],
    "wof:name":"Imiriy",
    "wof:placetype":"locality"
},
  "geometry": {"coordinates":[-8.34328,30.2109],"type":"Point"}
}