{
  "type": "Feature",
  "properties": {
    "gn:admin1_code":"08",
    "gn:asciiname":"Idalioun",
    "gn:country_code":"MA",
    "gn:dem":1896,
    "gn:feature_class":"P",
    "gn:feature_code":"PPL",
    "gn:name":"Idalioun",
    "gn:population":0,
    "gn:timezone":"Africa/Casablanca",
    "iso:country":"MA",
    "name:und_x_variant":[
        "Ksar Idalouin",
        "Idalioum",
        "Idalioun"
    ],
    "wof:name":"Idalioun",
    "wof:placetype":"locality"
},
  "geometry": {"coordinates":[-4.87666,32.36064],"type":"Point"}
}