{
  "type": "Feature",
  "properties": {
    "gn:admin1_code":"7.0",
    "gn:asciiname":"Sidi Moubark",
    "gn:country_code":"MA",
    "gn:dem":1316,
    "gn:feature_class":"P",
    "gn:feature_code":"PPL",
    "gn:name":"Sidi Moubark",
    "gn:population":0,
    "gn:timezone":"Africa/Casablanca",
    "iso:country":"MA",
    "wof:name":"Sidi Moubark",
    "wof:placetype":"locality"
},
  "geometry": {"coordinates":[-9.05246,31.02031],"type":"Point"}
}