{
  "type": "Feature",
  "properties": {
    "gn:admin1_code":"2.0",
    "gn:asciiname":"Douar Yat Hammou Haddou",
    "gn:country_code":"MA",
    "gn:dem":201,
    "gn:feature_class":"P",
    "gn:feature_code":"PPL",
    "gn:name":"Douar Yat Hammou Haddou",
    "gn:population":0,
    "gn:timezone":"Africa/Casablanca",
    "iso:country":"MA",
    "wof:name":"Douar Yat Hammou Haddou",
    "wof:placetype":"locality"
},
  "geometry": {"coordinates":[-2.67476,35.04584000000001],"type":"Point"}
}