{
  "type": "Feature",
  "properties": {
    "gn:asciiname":"Lakhzana",
    "gn:country_code":"MA",
    "gn:dem":551,
    "gn:feature_class":"P",
    "gn:feature_code":"PPLS",
    "gn:name":"Lakhzana",
    "gn:population":0,
    "gn:timezone":"Africa/Casablanca",
    "iso:country":"MA",
    "wof:name":"Lakhzana",
    "wof:placetype":"locality"
},
  "geometry": {"coordinates":[-4.43219,34.01578],"type":"Point"}
}