{
  "type": "Feature",
  "properties": {
    "gn:admin1_code":"08",
    "gn:asciiname":"Ait Baha",
    "gn:country_code":"MA",
    "gn:dem":1416,
    "gn:feature_class":"P",
    "gn:feature_code":"PPL",
    "gn:name":"A\u00eft Baha",
    "gn:population":0,
    "gn:timezone":"Africa/Casablanca",
    "iso:country":"MA",
    "name:ara_x_preferred":[
        "\u0622\u064a\u062a \u0628\u0627\u0647\u0627"
    ],
    "name:azb_x_preferred":[
        "\u0622\u06cc\u062a \u0628\u0627\u0647\u0627"
    ],
    "name:cat_x_preferred":[
        "A\u00eft Baha"
    ],
    "name:ceb_x_preferred":[
        "Ait Baha"
    ],
    "name:deu_x_preferred":[
        "A\u00eft Baha"
    ],
    "name:eus_x_preferred":[
        "Ait Baha"
    ],
    "name:fas_x_preferred":[
        "\u0622\u06cc\u062a \u0628\u0627\u0647\u0627"
    ],
    "name:fra_x_preferred":[
        "A\u00eft Baha"
    ],
    "name:por_x_preferred":[
        "Ait Baha"
    ],
    "name:zho_x_preferred":[
        "\u963f\u4f0a\u7279\u5df4\u54c8"
    ],
    "wof:name":"Ait Baha",
    "wof:placetype":"locality"
},
  "geometry": {"coordinates":[-5.58821,31.57822],"type":"Point"}
}