{
  "type": "Feature",
  "properties": {
    "gn:admin1_code":"08",
    "gn:asciiname":"Ait Baha",
    "gn:country_code":"MA",
    "gn:dem":1416,
    "gn:feature_class":"P",
    "gn:feature_code":"PPL",
    "gn:name":"A\u00eft Baha",
    "gn:population":0,
    "gn:timezone":"Africa/Casablanca",
    "iso:country":"MA",
    "name:und_x_variant":[
        "A\u00eft Baha"
    ],
    "wof:name":"Ait Baha",
    "wof:placetype":"locality"
},
  "geometry": {"coordinates":[-5.58821,31.57822],"type":"Point"}
}