{
  "type": "Feature",
  "properties": {
    "gn:admin1_code":"05",
    "gn:asciiname":"Sidi Isbel",
    "gn:country_code":"MA",
    "gn:dem":1972,
    "gn:feature_class":"P",
    "gn:feature_code":"PPL",
    "gn:name":"Sidi Isbel",
    "gn:population":0,
    "gn:timezone":"Africa/Casablanca",
    "iso:country":"MA",
    "wof:name":"Sidi Isbel",
    "wof:placetype":"locality"
},
  "geometry": {"coordinates":[-6.87558,31.43642],"type":"Point"}
}