{
  "type": "Feature",
  "properties": {
    "gn:admin1_code":"07",
    "gn:asciiname":"Douar Oulad Brahim Bel Kiyyal",
    "gn:country_code":"MA",
    "gn:dem":565,
    "gn:feature_class":"P",
    "gn:feature_code":"PPL",
    "gn:name":"Douar Oulad Brahim Bel Kiyyal",
    "gn:population":0,
    "gn:timezone":"Africa/Casablanca",
    "iso:country":"MA",
    "name:und_x_variant":[
        "Oulad Brahim"
    ],
    "wof:name":"Douar Oulad Brahim Bel Kiyyal",
    "wof:placetype":"locality"
},
  "geometry": {"coordinates":[-7.73712,31.83195],"type":"Point"}
}