{
  "type": "Feature",
  "properties": {
    "gn:admin1_code":"02",
    "gn:asciiname":"Beni Yabel",
    "gn:country_code":"MA",
    "gn:dem":967,
    "gn:feature_class":"P",
    "gn:feature_code":"PPL",
    "gn:name":"Beni Yabel",
    "gn:population":0,
    "gn:timezone":"Africa/Casablanca",
    "iso:country":"MA",
    "name:und_x_variant":[
        "Beni Yabal",
        "Beni Yabel"
    ],
    "wof:name":"Beni Yabel",
    "wof:placetype":"locality"
},
  "geometry": {"coordinates":[-3.04943,32.18147],"type":"Point"}
}