{
  "type": "Feature",
  "properties": {
    "gn:admin1_code":"6.0",
    "gn:asciiname":"Dar Mohammed Bel Haj",
    "gn:country_code":"MA",
    "gn:dem":330,
    "gn:feature_class":"P",
    "gn:feature_code":"PPL",
    "gn:name":"Dar Mohammed Bel Haj",
    "gn:population":0,
    "gn:timezone":"Africa/Casablanca",
    "iso:country":"MA",
    "wof:name":"Dar Mohammed Bel Haj",
    "wof:placetype":"locality"
},
  "geometry": {"coordinates":[-7.81889,33.00484],"type":"Point"}
}