{
  "type": "Feature",
  "properties": {
    "gn:admin1_code":"07",
    "gn:asciiname":"Algou",
    "gn:country_code":"MA",
    "gn:dem":871,
    "gn:feature_class":"P",
    "gn:feature_code":"PPL",
    "gn:name":"Algou",
    "gn:population":0,
    "gn:timezone":"Africa/Casablanca",
    "iso:country":"MA",
    "name:und_x_variant":[
        "Algo"
    ],
    "wof:name":"Algou",
    "wof:placetype":"locality"
},
  "geometry": {"coordinates":[-8.65251,31.22554],"type":"Point"}
}