{
  "type": "Feature",
  "properties": {
    "gn:admin1_code":"6.0",
    "gn:asciiname":"Flissat",
    "gn:country_code":"MA",
    "gn:dem":289,
    "gn:feature_class":"P",
    "gn:feature_code":"PPL",
    "gn:name":"Flissat",
    "gn:population":0,
    "gn:timezone":"Africa/Casablanca",
    "iso:country":"MA",
    "wof:name":"Flissat",
    "wof:placetype":"locality"
},
  "geometry": {"coordinates":[-7.94055,32.94801],"type":"Point"}
}