{
  "type": "Feature",
  "properties": {
    "gn:admin1_code":"7.0",
    "gn:asciiname":"Tiguemmi Said Atanane",
    "gn:country_code":"MA",
    "gn:dem":320,
    "gn:feature_class":"P",
    "gn:feature_code":"PPL",
    "gn:name":"Tiguemmi Sa\u00efd Atanane",
    "gn:population":0,
    "gn:timezone":"Africa/Casablanca",
    "iso:country":"MA",
    "wof:name":"Tiguemmi Said Atanane",
    "wof:placetype":"locality"
},
  "geometry": {"coordinates":[-9.69512,30.98356],"type":"Point"}
}