{
  "type": "Feature",
  "properties": {
    "gn:admin1_code":"08",
    "gn:asciiname":"lmi n'Tazaght",
    "gn:country_code":"MA",
    "gn:dem":1718,
    "gn:feature_class":"P",
    "gn:feature_code":"PPL",
    "gn:name":"lmi n\u2019Tazaght",
    "gn:population":0,
    "gn:timezone":"Africa/Casablanca",
    "iso:country":"MA",
    "name:und_x_variant":[
        "Imi n\u2019Tazarht",
        "Imi n\u2019Tazaglite",
        "lmi n\u2019Tazaght"
    ],
    "wof:name":"lmi n'Tazaght",
    "wof:placetype":"locality"
},
  "geometry": {"coordinates":[-6.68119,31.28714],"type":"Point"}
}