{
  "type": "Feature",
  "properties": {
    "gn:admin1_code":"08",
    "gn:asciiname":"Tiguirna",
    "gn:country_code":"MA",
    "gn:dem":948,
    "gn:feature_class":"P",
    "gn:feature_code":"PPL",
    "gn:name":"Tiguirna",
    "gn:population":0,
    "gn:timezone":"Africa/Casablanca",
    "iso:country":"MA",
    "name:und_x_variant":[
        "Ksar Tiguerna",
        "Tiguelna",
        "Tiguerna",
        "Tiguirna"
    ],
    "wof:name":"Tiguirna",
    "wof:placetype":"locality"
},
  "geometry": {"coordinates":[-5.26035,31.04206],"type":"Point"}
}