{
  "type": "Feature",
  "properties": {
    "gn:admin1_code":"09",
    "gn:asciiname":"Taourir Ait Ou Sa",
    "gn:country_code":"MA",
    "gn:dem":753,
    "gn:feature_class":"P",
    "gn:feature_code":"PPL",
    "gn:name":"Taourir A\u00eft Ou Sa",
    "gn:population":0,
    "gn:timezone":"Africa/Casablanca",
    "iso:country":"MA",
    "name:und_x_variant":[
        "Au Oussa",
        "Taourir A\u00eft Ou Sa"
    ],
    "wof:name":"Taourir Ait Ou Sa",
    "wof:placetype":"locality"
},
  "geometry": {"coordinates":[-9.59738,30.66381],"type":"Point"}
}