{
  "type": "Feature",
  "properties": {
    "gn:admin1_code":"7.0",
    "gn:asciiname":"Douar Idouamar",
    "gn:country_code":"MA",
    "gn:dem":175,
    "gn:feature_class":"P",
    "gn:feature_code":"PPL",
    "gn:name":"Douar Idouamar",
    "gn:population":0,
    "gn:timezone":"Africa/Casablanca",
    "iso:country":"MA",
    "wof:name":"Douar Idouamar",
    "wof:placetype":"locality"
},
  "geometry": {"coordinates":[-9.60614,31.41595],"type":"Point"}
}