{
  "type": "Feature",
  "properties": {
    "gn:admin1_code":"7.0",
    "gn:asciiname":"Legdadra",
    "gn:country_code":"MA",
    "gn:dem":206,
    "gn:feature_class":"P",
    "gn:feature_code":"PPL",
    "gn:name":"Legdadra",
    "gn:population":0,
    "gn:timezone":"Africa/Casablanca",
    "iso:country":"MA",
    "wof:name":"Legdadra",
    "wof:placetype":"locality"
},
  "geometry": {"coordinates":[-8.65903,32.41948],"type":"Point"}
}