{
  "type": "Feature",
  "properties": {
    "iso:country":"MA",
    "name:ara_x_preferred":[
        "\u0628\u0646\u064a \u0627\u0646\u0635\u0627\u0631"
    ],
    "name:baq_x_preferred":[
        "Beni Ansar"
    ],
    "name:cat_x_preferred":[
        "Beni Ensar"
    ],
    "name:deu_x_preferred":[
        "Beni Ansar"
    ],
    "name:dut_x_preferred":[
        "Beni Ansar"
    ],
    "name:eng_x_preferred":[
        "Beni Ansar / A\u00eft Nsar"
    ],
    "name:fra_x_preferred":[
        "Beni Ensar"
    ],
    "name:fre_x_preferred":[
        "Bni Ansar"
    ],
    "name:ger_x_preferred":[
        "Beni Ansar"
    ],
    "name:ita_x_preferred":[
        "Beni Ensar"
    ],
    "name:kab_x_preferred":[
        "At N\u1e63ar"
    ],
    "name:nld_x_preferred":[
        "Beni Ensar"
    ],
    "name:spa_x_preferred":[
        "Beni Ensar"
    ],
    "name:srd_x_preferred":[
        "Beni Ansar"
    ],
    "name:swe_x_preferred":[
        "Beni Enzar"
    ],
    "name:unk_x_variant":[
        "Beni Anzar"
    ],
    "qs:gn_country":"MA",
    "qs:gn_fcode":"PPL",
    "qs:gn_pop":0,
    "qs:name":"Beni Enzar",
    "qs:name_adm0":"\u0627\u0644\u0645\u063a\u0631\u0628",
    "qs:name_adm1":"\u0627\u0644\u062c\u0647\u0629 \u0627\u0644\u0634\u0631\u0642\u064a\u0629",
    "qs:photos":27,
    "qs:photos_1k":5,
    "qs:photos_9k":1,
    "qs:photos_9r":2,
    "qs:photos_all":27,
    "qs:photos_sr":2,
    "qs:placetype":"Town",
    "qs:pop_sr":"0",
    "qs:woe_adm0":23424893,
    "wd:population":56562,
    "wd:wordcount":155,
    "wof:name":"Beni Enzar",
    "wof:placetype":"locality",
    "wof:population":56562
},
  "geometry": {"coordinates":[-2.93,35.26],"type":"Point"}
}