{
  "type": "Feature",
  "properties": {
    "gn:admin1_code":"08",
    "gn:asciiname":"Ait Yahya Ou Moussa",
    "gn:country_code":"MA",
    "gn:dem":841,
    "gn:feature_class":"P",
    "gn:feature_code":"PPL",
    "gn:name":"A\u00eft Yahya Ou Moussa",
    "gn:population":0,
    "gn:timezone":"Africa/Casablanca",
    "iso:country":"MA",
    "wof:name":"Ait Yahya Ou Moussa",
    "wof:placetype":"locality"
},
  "geometry": {"coordinates":[-5.68,30.51],"type":"Point"}
}