{
  "type": "Feature",
  "properties": {
    "gn:admin1_code":"7.0",
    "gn:asciiname":"Douar Ait Lebchir",
    "gn:country_code":"MA",
    "gn:dem":478,
    "gn:feature_class":"P",
    "gn:feature_code":"PPL",
    "gn:name":"Douar Ait Lebchir",
    "gn:population":0,
    "gn:timezone":"Africa/Casablanca",
    "iso:country":"MA",
    "wof:name":"Douar Ait Lebchir",
    "wof:placetype":"locality"
},
  "geometry": {"coordinates":[-9.33219,31.52173],"type":"Point"}
}