{
  "type": "Feature",
  "properties": {
    "gn:country":"MA",
    "gn:fcode":"PPLA3",
    "gn:pop":43696,
    "iso:country":"MA",
    "name:ara_x_preferred":[
        "\u062c\u0631\u0627\u062f\u0629"
    ],
    "name:cat_x_preferred":[
        "Jerada"
    ],
    "name:eng_x_preferred":[
        "Jerada"
    ],
    "name:fra_x_preferred":[
        "Jerada"
    ],
    "name:heb_x_preferred":[
        "\u05d2'\u05e8\u05d0\u05d3\u05d4"
    ],
    "name:ita_x_preferred":[
        "Jerada"
    ],
    "name:jpn_x_preferred":[
        "\u30b8\u30a7\u30e9\u30c0"
    ],
    "name:kab_x_preferred":[
        "Jrada"
    ],
    "name:nld_x_preferred":[
        "Jerada"
    ],
    "name:pol_x_preferred":[
        "D\u017carada"
    ],
    "name:por_x_preferred":[
        "Jerada"
    ],
    "name:rus_x_preferred":[
        "\u0414\u0436\u0435\u0440\u0430\u0434\u0430"
    ],
    "name:spa_x_preferred":[
        "Yerada"
    ],
    "name:swe_x_preferred":[
        "Jerada"
    ],
    "name:unk_x_variant":[
        "Djerada"
    ],
    "name:urd_x_preferred":[
        "\u062c\u0631\u0627\u062f\u06c1"
    ],
    "qs:gn_pop":0,
    "qs:name":"Jerada",
    "qs:name_adm0":"\u0627\u0644\u0645\u063a\u0631\u0628",
    "qs:name_adm1":"\u0627\u0644\u062c\u0647\u0629 \u0627\u0644\u0634\u0631\u0642\u064a\u0629",
    "qs:photos":14,
    "qs:photos_1k":3,
    "qs:photos_9k":1,
    "qs:photos_9r":1,
    "qs:photos_all":14,
    "qs:photos_sr":1,
    "qs:placetype":"Town",
    "qs:pop_sr":"0",
    "qs:woe_adm0":23424893,
    "wd:wordcount":279,
    "wof:name":"Jerada",
    "wof:placetype":"locality",
    "wof:population":43696
},
  "geometry": {"coordinates":[-2.167309,34.3185],"type":"Point"}
}