{
  "type": "Feature",
  "properties": {
    "gn:admin1_code":"3.0",
    "gn:asciiname":"El Karyane",
    "gn:country_code":"MA",
    "gn:dem":705,
    "gn:feature_class":"P",
    "gn:feature_code":"PPL",
    "gn:name":"El Karyane",
    "gn:population":0,
    "gn:timezone":"Africa/Casablanca",
    "iso:country":"MA",
    "wof:name":"El Karyane",
    "wof:placetype":"locality"
},
  "geometry": {"coordinates":[-5.67715,33.72184],"type":"Point"}
}