{
  "type": "Feature",
  "properties": {
    "gn:admin1_code":"9.0",
    "gn:asciiname":"Tiyyitsk",
    "gn:country_code":"MA",
    "gn:dem":860,
    "gn:feature_class":"P",
    "gn:feature_code":"PPL",
    "gn:name":"Tiyyitsk",
    "gn:population":0,
    "gn:timezone":"Africa/Casablanca",
    "iso:country":"MA",
    "wof:name":"Tiyyitsk",
    "wof:placetype":"locality"
},
  "geometry": {"coordinates":[-9.02889,29.73315],"type":"Point"}
}