{
  "type": "Feature",
  "properties": {
    "gn:admin1_code":"4.0",
    "gn:asciiname":"Oulad Chane Miloud Aghzaf",
    "gn:country_code":"MA",
    "gn:dem":314,
    "gn:feature_class":"P",
    "gn:feature_code":"PPL",
    "gn:name":"Oulad Chane Miloud Aghzaf",
    "gn:population":0,
    "gn:timezone":"Africa/Casablanca",
    "iso:country":"MA",
    "wof:name":"Oulad Chane Miloud Aghzaf",
    "wof:placetype":"locality"
},
  "geometry": {"coordinates":[-6.20613,33.6737],"type":"Point"}
}