{
  "type": "Feature",
  "properties": {
    "gn:admin1_code":"1.0",
    "gn:asciiname":"Douar Tinnes",
    "gn:country_code":"MA",
    "gn:dem":368,
    "gn:feature_class":"P",
    "gn:feature_code":"PPL",
    "gn:name":"Douar Tinnes",
    "gn:population":0,
    "gn:timezone":"Africa/Casablanca",
    "iso:country":"MA",
    "wof:name":"Douar Tinnes",
    "wof:placetype":"locality"
},
  "geometry": {"coordinates":[-5.19127,35.29262],"type":"Point"}
}