{
  "type": "Feature",
  "properties": {
    "gn:admin1_code":"8.0",
    "gn:asciiname":"Tawrirt-n-Iguidou",
    "gn:country_code":"MA",
    "gn:dem":2532,
    "gn:feature_class":"P",
    "gn:feature_code":"PPL",
    "gn:name":"Tawrirt-n-Iguidou",
    "gn:population":0,
    "gn:timezone":"Africa/Casablanca",
    "iso:country":"MA",
    "wof:name":"Tawrirt-n-Iguidou",
    "wof:placetype":"locality"
},
  "geometry": {"coordinates":[-6.78946,31.31964],"type":"Point"}
}