{
  "type": "Feature",
  "properties": {
    "gn:admin1_code":"9.0",
    "gn:asciiname":"Lalla Aicha Oult Mhand",
    "gn:country_code":"MA",
    "gn:dem":49,
    "gn:feature_class":"P",
    "gn:feature_code":"PPL",
    "gn:name":"Lalla Aicha Oult Mhand",
    "gn:population":0,
    "gn:timezone":"Africa/Casablanca",
    "iso:country":"MA",
    "wof:name":"Lalla Aicha Oult Mhand",
    "wof:placetype":"locality"
},
  "geometry": {"coordinates":[-9.82822,30.69122],"type":"Point"}
}