{
  "type": "Feature",
  "properties": {
    "gn:admin1_code":"08",
    "gn:asciiname":"Tighajdat",
    "gn:country_code":"MA",
    "gn:dem":1390,
    "gn:feature_class":"P",
    "gn:feature_code":"PPL",
    "gn:name":"Tighajdat",
    "gn:population":0,
    "gn:timezone":"Africa/Casablanca",
    "iso:country":"MA",
    "name:und_x_variant":[
        "Tachihat",
        "Tachichat",
        "Tighajdat"
    ],
    "wof:name":"Tighajdat",
    "wof:placetype":"locality"
},
  "geometry": {"coordinates":[-4.62671,32.23924],"type":"Point"}
}