{
  "type": "Feature",
  "properties": {
    "gn:admin1_code":"9.0",
    "gn:asciiname":"Ait Moussa",
    "gn:country_code":"MA",
    "gn:dem":855,
    "gn:feature_class":"P",
    "gn:feature_code":"PPL",
    "gn:name":"A\u00eft Moussa",
    "gn:population":0,
    "gn:timezone":"Africa/Casablanca",
    "iso:country":"MA",
    "wof:name":"Ait Moussa",
    "wof:placetype":"locality"
},
  "geometry": {"coordinates":[-9.18577,29.83718],"type":"Point"}
}