{
  "type": "Feature",
  "properties": {
    "gn:admin1_code":"08",
    "gn:asciiname":"Tabiyat",
    "gn:country_code":"MA",
    "gn:dem":1428,
    "gn:feature_class":"P",
    "gn:feature_code":"PPL",
    "gn:name":"Tabiyat",
    "gn:population":0,
    "gn:timezone":"Africa/Casablanca",
    "iso:country":"MA",
    "name:und_x_variant":[
        "Tabia"
    ],
    "wof:name":"Tabiyat",
    "wof:placetype":"locality"
},
  "geometry": {"coordinates":[-4.68438,32.23431],"type":"Point"}
}