{
  "type": "Feature",
  "properties": {
    "gn:admin1_code":"07",
    "gn:asciiname":"Douar Laadilat Oulad Hmida Ben Mbarek",
    "gn:country_code":"MA",
    "gn:dem":285,
    "gn:feature_class":"P",
    "gn:feature_code":"PPL",
    "gn:name":"Douar Laadilat Oulad Hmida Ben Mbarek",
    "gn:population":0,
    "gn:timezone":"Africa/Casablanca",
    "iso:country":"MA",
    "name:und_x_variant":[
        "Lalla\u00eflat",
        "El Adilate",
        "El Adilat",
        "Douar Laadilat Oulad Hmida Ben Mbarek"
    ],
    "wof:name":"Douar Laadilat Oulad Hmida Ben Mbarek",
    "wof:placetype":"locality"
},
  "geometry": {"coordinates":[-8.90525,31.78129],"type":"Point"}
}