{
  "type": "Feature",
  "properties": {
    "gn:admin1_code":"7.0",
    "gn:asciiname":"Douar Oulad Somlem Cheikh",
    "gn:country_code":"MA",
    "gn:dem":88,
    "gn:feature_class":"P",
    "gn:feature_code":"PPL",
    "gn:name":"Douar Oulad Somlem Cheikh",
    "gn:population":0,
    "gn:timezone":"Africa/Casablanca",
    "iso:country":"MA",
    "wof:name":"Douar Oulad Somlem Cheikh",
    "wof:placetype":"locality"
},
  "geometry": {"coordinates":[-9.0515,32.47212],"type":"Point"}
}