{
  "type": "Feature",
  "properties": {
    "gn:country":"MA",
    "gn:fcode":"ADM3",
    "gn:pop":12040,
    "iso:country":"MA",
    "name:ara_x_preferred":[
        "\u0627\u0644\u0639\u0631\u0643\u0648\u0628"
    ],
    "name:fra_x_preferred":[
        "Aznaguen"
    ],
    "name:fra_x_variant":[
        "Aznaguen (CR)",
        "Aznaguen (Commune Rurale)"
    ],
    "qs:name":"Aznaguen",
    "qs:photos_9r":0,
    "qs:photos_sr":0,
    "qs:pop_sr":"6",
    "wd:wordcount":57,
    "wof:name":"Aznaguen",
    "wof:placetype":"localadmin",
    "wof:population":12040
},
  "geometry": {"coordinates":[-7.44506,30.3335],"type":"Point"}
}