{
  "type": "Feature",
  "properties": {
    "gn:country":"MA",
    "gn:fcode":"ADM3",
    "gn:population":12040,
    "iso:country":"MA",
    "name:ara_x_preferred":[
        "\u0627\u0644\u0639\u0631\u0643\u0648\u0628"
    ],
    "name:ara_x_variant":[
        "\u0623\u0632\u0646\u0627\u06ad\u0646"
    ],
    "name:ary_x_preferred":[
        "\u0623\u0632\u0646\u0627\u06af\u0646"
    ],
    "name:azb_x_preferred":[
        "\u0627\u0632\u0646\u0627\u06a9\u0646"
    ],
    "name:bul_x_preferred":[
        "\u0410\u0437\u043d\u0430\u0433\u0443\u0435\u043d"
    ],
    "name:cat_x_preferred":[
        "Aznaguen"
    ],
    "name:ceb_x_preferred":[
        "Aznaguen"
    ],
    "name:eng_x_preferred":[
        "Aznaguen"
    ],
    "name:fas_x_preferred":[
        "\u0627\u0632\u0646\u0627\u06a9\u0646"
    ],
    "name:fra_x_preferred":[
        "Aznaguen"
    ],
    "name:fra_x_variant":[
        "Aznaguen (CR)",
        "Aznaguen (Commune Rurale)"
    ],
    "name:ita_x_preferred":[
        "Aznaguen"
    ],
    "name:swe_x_preferred":[
        "Aznaguen"
    ],
    "qs:name":"Aznaguen",
    "qs:photos_9r":0,
    "qs:photos_sr":0,
    "qs:pop_sr":"6",
    "wd:wordcount":57,
    "wof:name":"Aznaguen",
    "wof:placetype":"localadmin",
    "wof:population":12040
},
  "geometry": {"coordinates":[-7.44506,30.3335],"type":"Point"}
}