{
  "type": "Feature",
  "properties": {
    "gn:admin1_code":"3.0",
    "gn:asciiname":"Douar Azib El Caid",
    "gn:country_code":"MA",
    "gn:dem":240,
    "gn:feature_class":"P",
    "gn:feature_code":"PPL",
    "gn:name":"Douar Azib El Caid",
    "gn:population":0,
    "gn:timezone":"Africa/Casablanca",
    "iso:country":"MA",
    "wof:name":"Douar Azib El Caid",
    "wof:placetype":"locality"
},
  "geometry": {"coordinates":[-5.73303,34.07793],"type":"Point"}
}