{
  "type": "Feature",
  "properties": {
    "gn:admin1_code":"6.0",
    "gn:asciiname":"'Acacda",
    "gn:country_code":"MA",
    "gn:dem":229,
    "gn:feature_class":"P",
    "gn:feature_code":"PPL",
    "gn:name":"\u2019A\u00e7a\u00e7da",
    "gn:population":0,
    "gn:timezone":"Africa/Casablanca",
    "iso:country":"MA",
    "wof:name":"'Acacda",
    "wof:placetype":"locality"
},
  "geometry": {"coordinates":[-7.79091,33.20209000000001],"type":"Point"}
}