{
  "type": "Feature",
  "properties": {
    "gn:admin1_code":"2.0",
    "gn:asciiname":"Douar Boughaleb",
    "gn:country_code":"MA",
    "gn:dem":637,
    "gn:feature_class":"P",
    "gn:feature_code":"PPL",
    "gn:name":"Douar Boughaleb",
    "gn:population":0,
    "gn:timezone":"Africa/Casablanca",
    "iso:country":"MA",
    "wof:name":"Douar Boughaleb",
    "wof:placetype":"locality"
},
  "geometry": {"coordinates":[-2.32968,34.70785],"type":"Point"}
}