{
  "type": "Feature",
  "properties": {
    "gn:admin1_code":"07",
    "gn:asciiname":"Tiskourine",
    "gn:country_code":"MA",
    "gn:dem":376,
    "gn:feature_class":"P",
    "gn:feature_code":"PPL",
    "gn:name":"Tiskour\u00edne",
    "gn:population":0,
    "gn:timezone":"Africa/Casablanca",
    "iso:country":"MA",
    "wof:name":"Tiskourine",
    "wof:placetype":"locality"
},
  "geometry": {"coordinates":[-9.33,31.76],"type":"Point"}
}