{
  "type": "Feature",
  "properties": {
    "gn:gn_country":"MA",
    "gn:gn_fcode":"ADM3",
    "gn:gn_pop":11225,
    "gn:population":12233,
    "iso:country":"MA",
    "name:ara_x_preferred":[
        "\u0623\u0648\u0644\u0627\u062f \u064a\u0639\u0642\u0648\u0628"
    ],
    "name:fra_x_preferred":[
        "Oulad Zarrad"
    ],
    "name:fra_x_variant":[
        "Oulad Zarrad (CR)",
        "Oulad Zarrad (Commune Rurale)"
    ],
    "qs_pg:aaroncc":"MA",
    "qs_pg:gn_country":"MA",
    "qs_pg:gn_fcode":"ADM3",
    "qs_pg:gn_pop":11225,
    "qs_pg:name":"Oulad Zarrad",
    "qs_pg:photos_9r":0,
    "qs_pg:photos_sr":0,
    "qs_pg:pop_sr":6,
    "qs_pg:qs_pg_placetype":"localadmin",
    "wof:name":"Oulad Zarrad",
    "wof:placetype":"localadmin",
    "wof:population":12233
},
  "geometry": {"coordinates":[-7.64853,32.11],"type":"Point"}
}