{
  "type": "Feature",
  "properties": {
    "gn:admin1_code":"9.0",
    "gn:asciiname":"Ait Ouachtouk",
    "gn:country_code":"MA",
    "gn:dem":630,
    "gn:feature_class":"P",
    "gn:feature_code":"PPL",
    "gn:name":"A\u00eft Ouachtouk",
    "gn:population":0,
    "gn:timezone":"Africa/Casablanca",
    "iso:country":"MA",
    "wof:name":"Ait Ouachtouk",
    "wof:placetype":"locality"
},
  "geometry": {"coordinates":[-9.17047,30.6652],"type":"Point"}
}