{
  "type": "Feature",
  "properties": {
    "gn:admin1_code":"10",
    "gn:asciiname":"Ait Hsayn",
    "gn:country_code":"MA",
    "gn:dem":368,
    "gn:feature_class":"P",
    "gn:feature_code":"PPL",
    "gn:name":"A\u00eft Hsayn",
    "gn:population":0,
    "gn:timezone":"Africa/Casablanca",
    "iso:country":"MA",
    "name:und_x_variant":[
        "Sidi Hosain",
        "Sidi Hossa\u00efn",
        "A\u00eft Hsayn"
    ],
    "wof:name":"Ait Hsayn",
    "wof:placetype":"locality"
},
  "geometry": {"coordinates":[-9.92796,29.39965],"type":"Point"}
}