{
  "type": "Feature",
  "properties": {
    "gn:admin1_code":"6.0",
    "gn:asciiname":"Oulad Attoum",
    "gn:country_code":"MA",
    "gn:dem":504,
    "gn:feature_class":"P",
    "gn:feature_code":"PPL",
    "gn:name":"Oulad Attoum",
    "gn:population":0,
    "gn:timezone":"Africa/Casablanca",
    "iso:country":"MA",
    "wof:name":"Oulad Attoum",
    "wof:placetype":"locality"
},
  "geometry": {"coordinates":[-7.59944,32.80083],"type":"Point"}
}