{
  "type": "Feature",
  "properties": {
    "gn:admin1_code":"7.0",
    "gn:asciiname":"Douar Darqaoua",
    "gn:country_code":"MA",
    "gn:dem":497,
    "gn:feature_class":"P",
    "gn:feature_code":"PPL",
    "gn:name":"Douar Darqaoua",
    "gn:population":0,
    "gn:timezone":"Africa/Casablanca",
    "iso:country":"MA",
    "wof:name":"Douar Darqaoua",
    "wof:placetype":"locality"
},
  "geometry": {"coordinates":[-7.7815,31.64973],"type":"Point"}
}