{
  "type": "Feature",
  "properties": {
    "gn:admin1_code":"10",
    "gn:asciiname":"Tisaguine",
    "gn:country_code":"MA",
    "gn:dem":351,
    "gn:feature_class":"P",
    "gn:feature_code":"PPL",
    "gn:name":"Tisaguine",
    "gn:population":0,
    "gn:timezone":"Africa/Casablanca",
    "iso:country":"MA",
    "name:und_x_variant":[
        "Tisag\u00fcin",
        "Tisaguine"
    ],
    "wof:name":"Tisaguine",
    "wof:placetype":"locality"
},
  "geometry": {"coordinates":[-10.16689,29.21132],"type":"Point"}
}