{
  "type": "Feature",
  "properties": {
    "gn:admin1_code":"3.0",
    "gn:asciiname":"Douar Ait Oued Fel",
    "gn:country_code":"MA",
    "gn:dem":879,
    "gn:feature_class":"P",
    "gn:feature_code":"PPL",
    "gn:name":"Douar Ait Oued Fel",
    "gn:population":0,
    "gn:timezone":"Africa/Casablanca",
    "iso:country":"MA",
    "wof:name":"Douar Ait Oued Fel",
    "wof:placetype":"locality"
},
  "geometry": {"coordinates":[-5.00824,33.7969],"type":"Point"}
}