{
  "type": "Feature",
  "properties": {
    "gn:country":"MA",
    "gn:fcode":"ADM3",
    "gn:pop":6100,
    "iso:country":"MA",
    "name:ara_x_preferred":[
        "\u0627\u062a\u0631\u0627\u064a\u0628\u0629"
    ],
    "name:fra_x_preferred":[
        "Bab Boudir"
    ],
    "name:fra_x_variant":[
        "Bab Boudir (CR)",
        "Bab Boudir (Commune Rurale)"
    ],
    "qs:name":"Bab Boudir",
    "qs:photos_9r":0,
    "qs:photos_sr":0,
    "qs:pop_sr":"5",
    "wd:wordcount":77,
    "wof:name":"Bab Boudir",
    "wof:placetype":"localadmin",
    "wof:population":6100
},
  "geometry": {"coordinates":[-4.09088,34.0854],"type":"Point"}
}