{
  "type": "Feature",
  "properties": {
    "gn:admin1_code":"4.0",
    "gn:asciiname":"Souq Tnine Sidi 'Abdarrazzaq",
    "gn:country_code":"MA",
    "gn:dem":339,
    "gn:feature_class":"P",
    "gn:feature_code":"PPL",
    "gn:name":"Souq Tnine Sidi \u2019Abdarrazzaq",
    "gn:population":0,
    "gn:timezone":"Africa/Casablanca",
    "iso:country":"MA",
    "wof:name":"Souq Tnine Sidi 'Abdarrazzaq",
    "wof:placetype":"locality"
},
  "geometry": {"coordinates":[-6.162,33.96279000000001],"type":"Point"}
}