{
  "type": "Feature",
  "properties": {
    "gn:admin1_code":"01",
    "gn:asciiname":"Asgar",
    "gn:country_code":"MA",
    "gn:dem":133,
    "gn:feature_class":"P",
    "gn:feature_code":"PPL",
    "gn:name":"Asgar",
    "gn:population":0,
    "gn:timezone":"Africa/Casablanca",
    "iso:country":"MA",
    "name:deu_x_preferred":[
        "Asgar"
    ],
    "name:und_x_variant":[
        "Azghar"
    ],
    "wof:name":"Asgar",
    "wof:placetype":"locality"
},
  "geometry": {"coordinates":[-3.90402,35.17722],"type":"Point"}
}