{
  "type": "Feature",
  "properties": {
    "gn:admin1_code":"01",
    "gn:asciiname":"Younane",
    "gn:country_code":"MA",
    "gn:dem":405,
    "gn:feature_class":"P",
    "gn:feature_code":"PPL",
    "gn:name":"Younane",
    "gn:population":0,
    "gn:timezone":"Africa/Casablanca",
    "iso:country":"MA",
    "name:und_x_variant":[
        "Iounane",
        "Younane"
    ],
    "wof:name":"Younane",
    "wof:placetype":"locality"
},
  "geometry": {"coordinates":[-5.28071,34.78143],"type":"Point"}
}