{
  "type": "Feature",
  "properties": {
    "gn:country":"MA",
    "gn:fcode":"ADM3",
    "gn:population":35161,
    "iso:country":"MA",
    "name:ara_x_preferred":[
        "\u0627\u0644\u0639\u0631\u0627\u0626\u0634 (\u0627\u0644\u0628\u0644\u062f\u064a\u0629)"
    ],
    "name:ara_x_variant":[
        "\u0627\u0644\u0639\u0648\u0627\u0645\u0631\u0629"
    ],
    "name:cat_x_preferred":[
        "Laouamra"
    ],
    "name:ceb_x_preferred":[
        "Laouamra"
    ],
    "name:fra_x_preferred":[
        "Laouamra"
    ],
    "name:fra_x_variant":[
        "Laouamra (CR)",
        "Laouamra (Commune Rurale)"
    ],
    "name:ita_x_preferred":[
        "Laouamra"
    ],
    "name:swe_x_preferred":[
        "Laouamra"
    ],
    "name:urd_x_preferred":[
        "\u0627\u0644\u0639\u0648\u0627\u0645\u0631\u06c1"
    ],
    "qs:name":"Laouamra",
    "qs:photos_9r":0,
    "qs:photos_sr":0,
    "qs:pop_sr":"7",
    "wd:wordcount":78,
    "wof:name":"Laouamra",
    "wof:placetype":"localadmin",
    "wof:population":35161
},
  "geometry": {"coordinates":[-6.1413,35.08053],"type":"Point"}
}