{
  "type": "Feature",
  "properties": {
    "gn:admin1_code":"09",
    "gn:asciiname":"Zaouia Sidi Aiad",
    "gn:country_code":"MA",
    "gn:dem":150,
    "gn:feature_class":"P",
    "gn:feature_code":"PPL",
    "gn:name":"Zaouia Sidi A\u00efad",
    "gn:population":0,
    "gn:timezone":"Africa/Casablanca",
    "iso:country":"MA",
    "name:und_x_variant":[
        "Zaouia Sidi Aayad",
        "Zaouia Sidi Aa\u00efad",
        "Zaouia",
        "Zaouia Sidi A\u00efad"
    ],
    "wof:name":"Zaouia Sidi Aiad",
    "wof:placetype":"locality"
},
  "geometry": {"coordinates":[-9.21773,30.33028],"type":"Point"}
}