{
  "type": "Feature",
  "properties": {
    "gn:admin1_code":"03",
    "gn:asciiname":"Douar Ras Bou Rkaiz",
    "gn:country_code":"MA",
    "gn:dem":575,
    "gn:feature_class":"P",
    "gn:feature_code":"PPL",
    "gn:name":"Douar Ras Bou Rka\u00efz",
    "gn:population":0,
    "gn:timezone":"Africa/Casablanca",
    "iso:country":"MA",
    "name:und_x_variant":[
        "Bou Rkeiz",
        "Dar Ras Bou Rka\u00efz",
        "Douar Ras Bou Rka\u00efz"
    ],
    "wof:name":"Douar Ras Bou Rkaiz",
    "wof:placetype":"locality"
},
  "geometry": {"coordinates":[-5.08598,33.90393],"type":"Point"}
}