{
  "type": "Feature",
  "properties": {
    "gn:admin1_code":"7.0",
    "gn:asciiname":"Ait Hammane",
    "gn:country_code":"MA",
    "gn:dem":445,
    "gn:feature_class":"P",
    "gn:feature_code":"PPL",
    "gn:name":"A\u00eft Hammane",
    "gn:population":0,
    "gn:timezone":"Africa/Casablanca",
    "iso:country":"MA",
    "wof:name":"Ait Hammane",
    "wof:placetype":"locality"
},
  "geometry": {"coordinates":[-8.00913,32.09215],"type":"Point"}
}