{
  "type": "Feature",
  "properties": {
    "gn:admin1_code":"7.0",
    "gn:asciiname":"Taswakt",
    "gn:country_code":"MA",
    "gn:dem":1276,
    "gn:feature_class":"P",
    "gn:feature_code":"PPL",
    "gn:name":"Taswakt",
    "gn:population":0,
    "gn:timezone":"Africa/Casablanca",
    "iso:country":"MA",
    "wof:name":"Taswakt",
    "wof:placetype":"locality"
},
  "geometry": {"coordinates":[-8.24709,30.9593],"type":"Point"}
}