{
  "type": "Feature",
  "properties": {
    "gn:admin1_code":"7.0",
    "gn:asciiname":"Taloutimt",
    "gn:country_code":"MA",
    "gn:dem":829,
    "gn:feature_class":"P",
    "gn:feature_code":"PPL",
    "gn:name":"Taloutimt",
    "gn:population":0,
    "gn:timezone":"Africa/Casablanca",
    "iso:country":"MA",
    "wof:name":"Taloutimt",
    "wof:placetype":"locality"
},
  "geometry": {"coordinates":[-8.43278,31.24973],"type":"Point"}
}