{
  "type": "Feature",
  "properties": {
    "gn:admin1_code":"04",
    "gn:asciiname":"Douar Lehmamda",
    "gn:country_code":"MA",
    "gn:dem":198,
    "gn:feature_class":"P",
    "gn:feature_code":"PPL",
    "gn:name":"Douar Lehmamda",
    "gn:population":0,
    "gn:timezone":"Africa/Casablanca",
    "iso:country":"MA",
    "name:und_x_variant":[
        "Al Amenda",
        "Douar el Amenda",
        "Douar Lehmamda"
    ],
    "wof:name":"Douar Lehmamda",
    "wof:placetype":"locality"
},
  "geometry": {"coordinates":[-5.61219,34.177],"type":"Point"}
}