{
  "type": "Feature",
  "properties": {
    "gn:admin1_code":"9.0",
    "gn:asciiname":"Douar Tagadri",
    "gn:country_code":"MA",
    "gn:dem":503,
    "gn:feature_class":"P",
    "gn:feature_code":"PPL",
    "gn:name":"Douar Tagadri",
    "gn:population":0,
    "gn:timezone":"Africa/Casablanca",
    "iso:country":"MA",
    "wof:name":"Douar Tagadri",
    "wof:placetype":"locality"
},
  "geometry": {"coordinates":[-9.88292,29.52013],"type":"Point"}
}