{
  "type": "Feature",
  "properties": {
    "gn:admin1_code":"01",
    "gn:asciiname":"Douar Belouazene",
    "gn:country_code":"MA",
    "gn:dem":158,
    "gn:feature_class":"P",
    "gn:feature_code":"PPL",
    "gn:name":"Douar Belouazene",
    "gn:population":0,
    "gn:timezone":"Africa/Casablanca",
    "iso:country":"MA",
    "name:und_x_variant":[
        "Dar Belouasene",
        "Boulouz\u00e8ne",
        "Belouazene",
        "Douar Belouazene"
    ],
    "wof:name":"Douar Belouazene",
    "wof:placetype":"locality"
},
  "geometry": {"coordinates":[-5.41743,35.67224],"type":"Point"}
}