{
  "type": "Feature",
  "properties": {
    "gn:admin1_code":"5.0",
    "gn:asciiname":"Ait Benaouch",
    "gn:country_code":"MA",
    "gn:dem":874,
    "gn:feature_class":"P",
    "gn:feature_code":"PPL",
    "gn:name":"Ait Benaouch",
    "gn:population":0,
    "gn:timezone":"Africa/Casablanca",
    "iso:country":"MA",
    "wof:name":"Ait Benaouch",
    "wof:placetype":"locality"
},
  "geometry": {"coordinates":[-7.18736,31.70287],"type":"Point"}
}