{
  "type": "Feature",
  "properties": {
    "gn:admin1_code":"07",
    "gn:asciiname":"Douar Leqlia",
    "gn:country_code":"MA",
    "gn:dem":405,
    "gn:feature_class":"P",
    "gn:feature_code":"PPL",
    "gn:name":"Douar Leqlia",
    "gn:population":0,
    "gn:timezone":"Africa/Casablanca",
    "iso:country":"MA",
    "name:und_x_variant":[
        "Enfalis",
        "El Koulea",
        "Douar Leqlia"
    ],
    "wof:name":"Douar Leqlia",
    "wof:placetype":"locality"
},
  "geometry": {"coordinates":[-9.09673,31.56091],"type":"Point"}
}