{
  "type": "Feature",
  "properties": {
    "gn:admin1_code":"3.0",
    "gn:asciiname":"Ait Alla",
    "gn:country_code":"MA",
    "gn:dem":619,
    "gn:feature_class":"P",
    "gn:feature_code":"PPL",
    "gn:name":"Ait Alla",
    "gn:population":0,
    "gn:timezone":"Africa/Casablanca",
    "iso:country":"MA",
    "wof:name":"Ait Alla",
    "wof:placetype":"locality"
},
  "geometry": {"coordinates":[-4.52597,33.95115],"type":"Point"}
}