{
  "type": "Feature",
  "properties": {
    "gn:admin1_code":"7.0",
    "gn:asciiname":"Douar Foum Briouiga",
    "gn:country_code":"MA",
    "gn:dem":418,
    "gn:feature_class":"P",
    "gn:feature_code":"PPL",
    "gn:name":"Douar Foum Briouiga",
    "gn:population":0,
    "gn:timezone":"Africa/Casablanca",
    "iso:country":"MA",
    "wof:name":"Douar Foum Briouiga",
    "wof:placetype":"locality"
},
  "geometry": {"coordinates":[-7.49737,32.2339],"type":"Point"}
}