{
  "type": "Feature",
  "properties": {
    "gn:admin1_code":"07",
    "gn:asciiname":"Lamhadi",
    "gn:country_code":"MA",
    "gn:dem":161,
    "gn:feature_class":"P",
    "gn:feature_code":"PPL",
    "gn:name":"Lamhadi",
    "gn:population":0,
    "gn:timezone":"Africa/Casablanca",
    "iso:country":"MA",
    "name:ara_x_preferred":[
        "\u0644\u0645\u0647\u0627\u062f\u064a"
    ],
    "name:cat_x_preferred":[
        "Lamhadi"
    ],
    "name:ceb_x_preferred":[
        "Lamhadi"
    ],
    "name:ita_x_preferred":[
        "Lamhadi"
    ],
    "name:swe_x_preferred":[
        "Lamhadi"
    ],
    "name:und_x_variant":[
        "Douar el Mohadi",
        "Lemhadi",
        "Mohadi",
        "El Mohadi",
        "Lamhadi"
    ],
    "name:urd_x_preferred":[
        "\u0644\u0627\u0645\u06c1\u0627\u0688\u06cc"
    ],
    "wof:name":"Lamhadi",
    "wof:placetype":"locality"
},
  "geometry": {"coordinates":[-9.01344,32.29725],"type":"Point"}
}