{
  "type": "Feature",
  "properties": {
    "gn:admin1_code":"5.0",
    "gn:asciiname":"Dar Ait Hammou",
    "gn:country_code":"MA",
    "gn:dem":1261,
    "gn:feature_class":"P",
    "gn:feature_code":"PPL",
    "gn:name":"Dar Ait Hammou",
    "gn:population":0,
    "gn:timezone":"Africa/Casablanca",
    "iso:country":"MA",
    "wof:name":"Dar Ait Hammou",
    "wof:placetype":"locality"
},
  "geometry": {"coordinates":[-7.01523,31.66486],"type":"Point"}
}