{
  "type": "Feature",
  "properties": {
    "gn:admin1_code":"2.0",
    "gn:asciiname":"Oulad Allai",
    "gn:country_code":"MA",
    "gn:dem":234,
    "gn:feature_class":"P",
    "gn:feature_code":"PPL",
    "gn:name":"Oulad Allai",
    "gn:population":0,
    "gn:timezone":"Africa/Casablanca",
    "iso:country":"MA",
    "wof:name":"Oulad Allai",
    "wof:placetype":"locality"
},
  "geometry": {"coordinates":[-3.06628,35.03393],"type":"Point"}
}