{
  "type": "Feature",
  "properties": {
    "gn:admin1_code":"03",
    "gn:asciiname":"Tacharbant",
    "gn:country_code":"MA",
    "gn:dem":1286,
    "gn:feature_class":"P",
    "gn:feature_code":"PPL",
    "gn:name":"Tacharbant",
    "gn:population":0,
    "gn:timezone":"Africa/Casablanca",
    "iso:country":"MA",
    "name:und_x_variant":[
        "Tacherbant"
    ],
    "wof:name":"Tacharbant",
    "wof:placetype":"locality"
},
  "geometry": {"coordinates":[-3.95003,34.68271],"type":"Point"}
}