{
  "type": "Feature",
  "properties": {
    "gn:admin1_code":"6.0",
    "gn:asciiname":"Oulad Sidi Ahmed Ben Amar",
    "gn:country_code":"MA",
    "gn:dem":441,
    "gn:feature_class":"P",
    "gn:feature_code":"PPL",
    "gn:name":"Oulad Sidi Ahmed Ben Amar",
    "gn:population":0,
    "gn:timezone":"Africa/Casablanca",
    "iso:country":"MA",
    "wof:name":"Oulad Sidi Ahmed Ben Amar",
    "wof:placetype":"locality"
},
  "geometry": {"coordinates":[-7.64581,32.93948],"type":"Point"}
}