{
  "type": "Feature",
  "properties": {
    "gn:admin1_code":"08",
    "gn:asciiname":"Ouaouguinekht",
    "gn:country_code":"MA",
    "gn:dem":1188,
    "gn:feature_class":"P",
    "gn:feature_code":"PPL",
    "gn:name":"Ouaouguinekht",
    "gn:population":0,
    "gn:timezone":"Africa/Casablanca",
    "iso:country":"MA",
    "name:und_x_variant":[
        "Wawguineght",
        "Ouaouguinekhte",
        "Ouaouguinekht"
    ],
    "wof:name":"Ouaouguinekht",
    "wof:placetype":"locality"
},
  "geometry": {"coordinates":[-7.07873,30.43476],"type":"Point"}
}