{
  "type": "Feature",
  "properties": {
    "gn:admin1_code":"07",
    "gn:asciiname":"Id El Arbi",
    "gn:country_code":"MA",
    "gn:dem":372,
    "gn:feature_class":"P",
    "gn:feature_code":"PPL",
    "gn:name":"Id El Arbi",
    "gn:population":0,
    "gn:timezone":"Africa/Casablanca",
    "iso:country":"MA",
    "name:und_x_variant":[
        "Id Larbi"
    ],
    "wof:name":"Id El Arbi",
    "wof:placetype":"locality"
},
  "geometry": {"coordinates":[-9.66471,31.00873],"type":"Point"}
}