{
  "type": "Feature",
  "properties": {
    "gn:admin1_code":"07",
    "gn:asciiname":"Sidi Bou Oukfa",
    "gn:country_code":"MA",
    "gn:dem":272,
    "gn:feature_class":"P",
    "gn:feature_code":"PPL",
    "gn:name":"Sidi Bou Oukfa",
    "gn:population":0,
    "gn:timezone":"Africa/Casablanca",
    "iso:country":"MA",
    "wof:name":"Sidi Bou Oukfa",
    "wof:placetype":"locality"
},
  "geometry": {"coordinates":[-7.69922,32.50244],"type":"Point"}
}