{
  "type": "Feature",
  "properties": {
    "gn:admin1_code":"5.0",
    "gn:asciiname":"Ayioun",
    "gn:country_code":"MA",
    "gn:dem":1156,
    "gn:feature_class":"P",
    "gn:feature_code":"PPL",
    "gn:name":"Ayioun",
    "gn:population":0,
    "gn:timezone":"Africa/Casablanca",
    "iso:country":"MA",
    "wof:name":"Ayioun",
    "wof:placetype":"locality"
},
  "geometry": {"coordinates":[-7.17245,31.64354],"type":"Point"}
}