{
  "type": "Feature",
  "properties": {
    "gn:admin1_code":"6.0",
    "gn:asciiname":"Oulad Cheikh El Mati",
    "gn:country_code":"MA",
    "gn:dem":433,
    "gn:feature_class":"P",
    "gn:feature_code":"PPL",
    "gn:name":"Oulad Che\u00efkh El Mati",
    "gn:population":0,
    "gn:timezone":"Africa/Casablanca",
    "iso:country":"MA",
    "wof:name":"Oulad Cheikh El Mati",
    "wof:placetype":"locality"
},
  "geometry": {"coordinates":[-7.58611,32.63056],"type":"Point"}
}