{
  "type": "Feature",
  "properties": {
    "gn:admin1_code":"1.0",
    "gn:asciiname":"Douar Azib Ben Salah",
    "gn:country_code":"MA",
    "gn:dem":1180,
    "gn:feature_class":"P",
    "gn:feature_code":"PPL",
    "gn:name":"Douar Azib Ben Salah",
    "gn:population":0,
    "gn:timezone":"Africa/Casablanca",
    "iso:country":"MA",
    "wof:name":"Douar Azib Ben Salah",
    "wof:placetype":"locality"
},
  "geometry": {"coordinates":[-5.02618,35.03253],"type":"Point"}
}