{
  "type": "Feature",
  "properties": {
    "gn:admin1_code":"5.0",
    "gn:asciiname":"Achchab",
    "gn:country_code":"MA",
    "gn:dem":1047,
    "gn:feature_class":"P",
    "gn:feature_code":"PPL",
    "gn:name":"\u00c2chchab",
    "gn:population":0,
    "gn:timezone":"Africa/Casablanca",
    "iso:country":"MA",
    "wof:name":"Achchab",
    "wof:placetype":"locality"
},
  "geometry": {"coordinates":[-5.54447,32.75045],"type":"Point"}
}