{
  "type": "Feature",
  "properties": {
    "gn:admin1_code":"08",
    "gn:asciiname":"Agouddim",
    "gn:country_code":"MA",
    "gn:dem":1852,
    "gn:feature_class":"P",
    "gn:feature_code":"PPL",
    "gn:name":"Agouddim",
    "gn:population":0,
    "gn:timezone":"Africa/Casablanca",
    "iso:country":"MA",
    "name:und_x_variant":[
        "Agoudim",
        "Aguoddim",
        "Agouddim"
    ],
    "wof:name":"Agouddim",
    "wof:placetype":"locality"
},
  "geometry": {"coordinates":[-6.85335,31.30625],"type":"Point"}
}