{
  "type": "Feature",
  "properties": {
    "gn:admin1_code":"7.0",
    "gn:asciiname":"Al Hourriya",
    "gn:country_code":"MA",
    "gn:dem":603,
    "gn:feature_class":"P",
    "gn:feature_code":"PPL",
    "gn:name":"Al Hourriya",
    "gn:population":0,
    "gn:timezone":"Africa/Casablanca",
    "iso:country":"MA",
    "wof:name":"Al Hourriya",
    "wof:placetype":"locality"
},
  "geometry": {"coordinates":[-7.48237,31.80023],"type":"Point"}
}