{
  "type": "Feature",
  "properties": {
    "gn:admin1_code":"10.0",
    "gn:asciiname":"Tacharit",
    "gn:country_code":"MA",
    "gn:dem":429,
    "gn:feature_class":"P",
    "gn:feature_code":"PPL",
    "gn:name":"Tacharit",
    "gn:population":0,
    "gn:timezone":"Africa/Casablanca",
    "iso:country":"MA",
    "wof:name":"Tacharit",
    "wof:placetype":"locality"
},
  "geometry": {"coordinates":[-9.82239,29.02407],"type":"Point"}
}