{
  "type": "Feature",
  "properties": {
    "gn:admin1_code":"07",
    "gn:asciiname":"Douar Bouchrit",
    "gn:country_code":"MA",
    "gn:dem":316,
    "gn:feature_class":"P",
    "gn:feature_code":"PPL",
    "gn:name":"Douar Bouchrit",
    "gn:population":0,
    "gn:timezone":"Africa/Casablanca",
    "iso:country":"MA",
    "name:und_x_variant":[
        "Douar Cheikh el Ouali",
        "Bouchrite",
        "Bouchrit",
        "Douar Bouchrit"
    ],
    "wof:name":"Douar Bouchrit",
    "wof:placetype":"locality"
},
  "geometry": {"coordinates":[-8.3376,32.28444],"type":"Point"}
}