{
  "type": "Feature",
  "properties": {
    "gn:admin1_code":"4.0",
    "gn:asciiname":"Douar Ait Boumehdi",
    "gn:country_code":"MA",
    "gn:dem":344,
    "gn:feature_class":"P",
    "gn:feature_code":"PPL",
    "gn:name":"Douar Ait Boumehdi",
    "gn:population":0,
    "gn:timezone":"Africa/Casablanca",
    "iso:country":"MA",
    "wof:name":"Douar Ait Boumehdi",
    "wof:placetype":"locality"
},
  "geometry": {"coordinates":[-6.10804,33.73712],"type":"Point"}
}