{
  "type": "Feature",
  "properties": {
    "gn:admin1_code":"08",
    "gn:asciiname":"Safsaf",
    "gn:country_code":"MA",
    "gn:dem":1049,
    "gn:feature_class":"P",
    "gn:feature_code":"PPL",
    "gn:name":"Safsaf",
    "gn:population":0,
    "gn:timezone":"Africa/Casablanca",
    "iso:country":"MA",
    "name:ara_x_preferred":[
        "\u0635\u0641\u0635\u0627\u0641"
    ],
    "name:heb_x_preferred":[
        "\u05e6\u05e4\u05e6\u05d0\u05e3"
    ],
    "name:pol_x_preferred":[
        "Safsaf"
    ],
    "wof:name":"Safsaf",
    "wof:placetype":"locality"
},
  "geometry": {"coordinates":[-4.58,31.85],"type":"Point"}
}