{
  "type": "Feature",
  "properties": {
    "gn:admin1_code":"1.0",
    "gn:asciiname":"Gare De Peage",
    "gn:country_code":"MA",
    "gn:dem":101,
    "gn:feature_class":"P",
    "gn:feature_code":"PPL",
    "gn:name":"Gare De Peage",
    "gn:population":0,
    "gn:timezone":"Africa/Casablanca",
    "iso:country":"MA",
    "wof:name":"Gare De Peage",
    "wof:placetype":"locality"
},
  "geometry": {"coordinates":[-6.00673,35.33212],"type":"Point"}
}