{
  "type": "Feature",
  "properties": {
    "gn:admin1_code":"1.0",
    "gn:asciiname":"Douar Taghat Darouah",
    "gn:country_code":"MA",
    "gn:dem":196,
    "gn:feature_class":"P",
    "gn:feature_code":"PPL",
    "gn:name":"Douar Taghat Darouah",
    "gn:population":0,
    "gn:timezone":"Africa/Casablanca",
    "iso:country":"MA",
    "wof:name":"Douar Taghat Darouah",
    "wof:placetype":"locality"
},
  "geometry": {"coordinates":[-4.70568,35.16347],"type":"Point"}
}