{
  "type": "Feature",
  "properties": {
    "gn:admin1_code":"03",
    "gn:asciiname":"Douar Jbel Aghlal",
    "gn:country_code":"MA",
    "gn:dem":537,
    "gn:feature_class":"P",
    "gn:feature_code":"PPL",
    "gn:name":"Douar Jbel Aghlal",
    "gn:population":0,
    "gn:timezone":"Africa/Casablanca",
    "iso:country":"MA",
    "name:und_x_variant":[
        "Douar Jebat Arhoulel",
        "Jebat Arhoulel",
        "Douar Jbel Aghlal"
    ],
    "wof:name":"Douar Jbel Aghlal",
    "wof:placetype":"locality"
},
  "geometry": {"coordinates":[-4.43863,34.279],"type":"Point"}
}