{
  "type": "Feature",
  "properties": {
    "gn:admin1_code":"10",
    "gn:asciiname":"Dar Id Boused",
    "gn:country_code":"MA",
    "gn:dem":349,
    "gn:feature_class":"P",
    "gn:feature_code":"PPL",
    "gn:name":"Dar Id Boused",
    "gn:population":0,
    "gn:timezone":"Africa/Casablanca",
    "iso:country":"MA",
    "name:und_x_variant":[
        "Dar Iddu-xait",
        "Dar Idbu-xait",
        "Dar Id Boused"
    ],
    "wof:name":"Dar Id Boused",
    "wof:placetype":"locality"
},
  "geometry": {"coordinates":[-10.29339,29.18731],"type":"Point"}
}