{
  "type": "Feature",
  "properties": {
    "gn:admin1_code":"9.0",
    "gn:asciiname":"Oulad Salem",
    "gn:country_code":"MA",
    "gn:dem":423,
    "gn:feature_class":"P",
    "gn:feature_code":"PPL",
    "gn:name":"Oulad Salem",
    "gn:population":0,
    "gn:timezone":"Africa/Casablanca",
    "iso:country":"MA",
    "wof:name":"Oulad Salem",
    "wof:placetype":"locality"
},
  "geometry": {"coordinates":[-8.57882,30.62474000000001],"type":"Point"}
}