{
  "type": "Feature",
  "properties": {
    "gn:admin1_code":"08",
    "gn:asciiname":"Anfar",
    "gn:country_code":"MA",
    "gn:dem":948,
    "gn:feature_class":"P",
    "gn:feature_code":"PPL",
    "gn:name":"Anfar",
    "gn:population":0,
    "gn:timezone":"Africa/Casablanca",
    "iso:country":"MA",
    "wof:name":"Anfar",
    "wof:placetype":"locality"
},
  "geometry": {"coordinates":[-4.80086,31.63899],"type":"Point"}
}