{
  "type": "Feature",
  "properties": {
    "gn:admin1_code":"6.0",
    "gn:asciiname":"Douar Ali Bin El Maah",
    "gn:country_code":"MA",
    "gn:dem":518,
    "gn:feature_class":"P",
    "gn:feature_code":"PPL",
    "gn:name":"Douar Ali Bin El Maah",
    "gn:population":0,
    "gn:timezone":"Africa/Casablanca",
    "iso:country":"MA",
    "wof:name":"Douar Ali Bin El Maah",
    "wof:placetype":"locality"
},
  "geometry": {"coordinates":[-7.45661,32.66872],"type":"Point"}
}