{
  "type": "Feature",
  "properties": {
    "gn:admin1_code":"09",
    "gn:asciiname":"Masmout",
    "gn:country_code":"MA",
    "gn:dem":1245,
    "gn:feature_class":"P",
    "gn:feature_code":"PPL",
    "gn:name":"Masmout",
    "gn:population":0,
    "gn:timezone":"Africa/Casablanca",
    "iso:country":"MA",
    "name:und_x_variant":[
        "Mesmout"
    ],
    "wof:name":"Masmout",
    "wof:placetype":"locality"
},
  "geometry": {"coordinates":[-8.65431,30.16906],"type":"Point"}
}