{
  "type": "Feature",
  "properties": {
    "gn:admin1_code":"09",
    "gn:asciiname":"Dghaimis",
    "gn:country_code":"MA",
    "gn:dem":93,
    "gn:feature_class":"P",
    "gn:feature_code":"PPL",
    "gn:name":"Dgha\u00efmis",
    "gn:population":0,
    "gn:timezone":"Africa/Casablanca",
    "iso:country":"MA",
    "name:und_x_variant":[
        "Drha\u00efmis",
        "Dra\u00efnis",
        "Dra\u00efmiz",
        "Dgha\u00efmis"
    ],
    "wof:name":"Dghaimis",
    "wof:placetype":"locality"
},
  "geometry": {"coordinates":[-9.75346,29.83749000000001],"type":"Point"}
}