{
  "type": "Feature",
  "properties": {
    "gn:admin1_code":"01",
    "gn:asciiname":"Tiliouane",
    "gn:country_code":"MA",
    "gn:dem":527,
    "gn:feature_class":"P",
    "gn:feature_code":"PPL",
    "gn:name":"Tiliouane",
    "gn:population":0,
    "gn:timezone":"Africa/Casablanca",
    "iso:country":"MA",
    "name:und_x_variant":[
        "Tiliouene",
        "Tilouane",
        "Tiliouine",
        "Tiliouane"
    ],
    "wof:name":"Tiliouane",
    "wof:placetype":"locality"
},
  "geometry": {"coordinates":[-5.26723,34.92873],"type":"Point"}
}