{
  "type": "Feature",
  "properties": {
    "gn:admin1_code":"7.0",
    "gn:asciiname":"Douar Oulad Ben Khayi",
    "gn:country_code":"MA",
    "gn:dem":156,
    "gn:feature_class":"P",
    "gn:feature_code":"PPL",
    "gn:name":"Douar Oulad Ben Khayi",
    "gn:population":0,
    "gn:timezone":"Africa/Casablanca",
    "iso:country":"MA",
    "wof:name":"Douar Oulad Ben Khayi",
    "wof:placetype":"locality"
},
  "geometry": {"coordinates":[-8.87582,32.46588],"type":"Point"}
}