{
  "type": "Feature",
  "properties": {
    "gn:admin1_code":"03",
    "gn:asciiname":"Douar Sehb Lkhorchef",
    "gn:country_code":"MA",
    "gn:dem":673,
    "gn:feature_class":"P",
    "gn:feature_code":"PPL",
    "gn:name":"Douar Sehb Lkhorchef",
    "gn:population":0,
    "gn:timezone":"Africa/Casablanca",
    "iso:country":"MA",
    "name:und_x_variant":[
        "Douar Seheb el Khorchef",
        "Seheb el Khorchef",
        "Douar Sehb Lkhorchef"
    ],
    "wof:name":"Douar Sehb Lkhorchef",
    "wof:placetype":"locality"
},
  "geometry": {"coordinates":[-4.42416,34.01682],"type":"Point"}
}