{
  "type": "Feature",
  "properties": {
    "gn:admin1_code":"01",
    "gn:asciiname":"Ihaddounene",
    "gn:country_code":"MA",
    "gn:dem":294,
    "gn:feature_class":"P",
    "gn:feature_code":"PPL",
    "gn:name":"Ihaddounene",
    "gn:population":0,
    "gn:timezone":"Africa/Casablanca",
    "iso:country":"MA",
    "wof:name":"Ihaddounene",
    "wof:placetype":"locality"
},
  "geometry": {"coordinates":[-5.16527,35.45337],"type":"Point"}
}