{
  "type": "Feature",
  "properties": {
    "gn:admin1_code":"07",
    "gn:asciiname":"Agadir n'Ait Bou Fenzi",
    "gn:country_code":"MA",
    "gn:dem":1173,
    "gn:feature_class":"P",
    "gn:feature_code":"PPL",
    "gn:name":"Agadir n\u2019A\u00eft Bou Fenzi",
    "gn:population":0,
    "gn:timezone":"Africa/Casablanca",
    "iso:country":"MA",
    "name:und_x_variant":[
        "Dar Ca\u00efd bou Fenzi",
        "Dar Ca\u00efd Allal bou Fenzi",
        "Dar el Ca\u00efd Allal Bou Fenzi",
        "Agadir n\u2019A\u00eft Bou Fenzi"
    ],
    "wof:name":"Agadir n'Ait Bou Fenzi",
    "wof:placetype":"locality"
},
  "geometry": {"coordinates":[-9.37386,31.05995],"type":"Point"}
}