{
  "type": "Feature",
  "properties": {
    "gn:admin1_code":"04",
    "gn:asciiname":"Douar Oulad El Arbi Laourch",
    "gn:country_code":"MA",
    "gn:dem":205,
    "gn:feature_class":"P",
    "gn:feature_code":"PPL",
    "gn:name":"Douar Oulad El Arbi Laourch",
    "gn:population":0,
    "gn:timezone":"Africa/Casablanca",
    "iso:country":"MA",
    "name:und_x_variant":[
        "Oulad al \u2019Arabi",
        "Oulad al \u2019Arbi",
        "Douar Oulad El Arbi Laourch"
    ],
    "wof:name":"Douar Oulad El Arbi Laourch",
    "wof:placetype":"locality"
},
  "geometry": {"coordinates":[-5.44789,34.55088],"type":"Point"}
}