{
  "type": "Feature",
  "properties": {
    "gn:admin1_code":"01",
    "gn:asciiname":"Azarif",
    "gn:country_code":"MA",
    "gn:dem":350,
    "gn:feature_class":"P",
    "gn:feature_code":"PPL",
    "gn:name":"Azarif",
    "gn:population":0,
    "gn:timezone":"Africa/Casablanca",
    "iso:country":"MA",
    "wof:name":"Azarif",
    "wof:placetype":"locality"
},
  "geometry": {"coordinates":[-5.27947,34.76767],"type":"Point"}
}