{
  "type": "Feature",
  "properties": {
    "gn:admin1_code":"10",
    "gn:asciiname":"Gaour",
    "gn:country_code":"MA",
    "gn:dem":1411,
    "gn:feature_class":"P",
    "gn:feature_code":"PPL",
    "gn:name":"Gaour",
    "gn:population":0,
    "gn:timezone":"Africa/Casablanca",
    "iso:country":"MA",
    "name:und_x_variant":[
        "Gaeur",
        "Gaour"
    ],
    "wof:name":"Gaour",
    "wof:placetype":"locality"
},
  "geometry": {"coordinates":[-9.27792,29.42081],"type":"Point"}
}