{
  "type": "Feature",
  "properties": {
    "gn:admin1_code":"7.0",
    "gn:asciiname":"Irhir Obdir",
    "gn:country_code":"MA",
    "gn:dem":1173,
    "gn:feature_class":"P",
    "gn:feature_code":"PPL",
    "gn:name":"Irhir Obdir",
    "gn:population":0,
    "gn:timezone":"Africa/Casablanca",
    "iso:country":"MA",
    "wof:name":"Irhir Obdir",
    "wof:placetype":"locality"
},
  "geometry": {"coordinates":[-7.3262,31.55704],"type":"Point"}
}