{
  "type": "Feature",
  "properties": {
    "gn:admin1_code":"9.0",
    "gn:asciiname":"Taghaliymt",
    "gn:country_code":"MA",
    "gn:dem":1231,
    "gn:feature_class":"P",
    "gn:feature_code":"PPL",
    "gn:name":"Taghaliymt",
    "gn:population":0,
    "gn:timezone":"Africa/Casablanca",
    "iso:country":"MA",
    "wof:name":"Taghaliymt",
    "wof:placetype":"locality"
},
  "geometry": {"coordinates":[-9.15851,29.6137],"type":"Point"}
}