{
  "type": "Feature",
  "properties": {
    "gn:admin1_code":"1.0",
    "gn:asciiname":"Houmat Tala Aakmene",
    "gn:country_code":"MA",
    "gn:dem":858,
    "gn:feature_class":"P",
    "gn:feature_code":"PPL",
    "gn:name":"Houmat Tala Aakmene",
    "gn:population":0,
    "gn:timezone":"Africa/Casablanca",
    "iso:country":"MA",
    "wof:name":"Houmat Tala Aakmene",
    "wof:placetype":"locality"
},
  "geometry": {"coordinates":[-4.77866,35.03419],"type":"Point"}
}