{
  "type": "Feature",
  "properties": {
    "gn:admin1_code":"02",
    "gn:asciiname":"Boudileb",
    "gn:country_code":"MA",
    "gn:dem":519,
    "gn:feature_class":"P",
    "gn:feature_code":"PPL",
    "gn:name":"Bo\u00fbd\u00eeleb",
    "gn:population":0,
    "gn:timezone":"Africa/Casablanca",
    "iso:country":"MA",
    "wof:name":"Boudileb",
    "wof:placetype":"locality"
},
  "geometry": {"coordinates":[-3.70678,35.04405],"type":"Point"}
}