{
  "type": "Feature",
  "properties": {
    "gn:admin1_code":"09",
    "gn:asciiname":"Ighil Ismalane",
    "gn:country_code":"MA",
    "gn:dem":1170,
    "gn:feature_class":"P",
    "gn:feature_code":"PPL",
    "gn:name":"Ighil Ismalane",
    "gn:population":0,
    "gn:timezone":"Africa/Casablanca",
    "iso:country":"MA",
    "name:und_x_variant":[
        "Irhil Ismellal\u00e8n",
        "Irhil Ismellalene",
        "Ighil Ismalane"
    ],
    "wof:name":"Ighil Ismalane",
    "wof:placetype":"locality"
},
  "geometry": {"coordinates":[-8.81849,30.14429],"type":"Point"}
}