{
  "type": "Feature",
  "properties": {
    "gn:admin1_code":"04",
    "gn:asciiname":"Douar Sidi Mohammed",
    "gn:country_code":"MA",
    "gn:dem":298,
    "gn:feature_class":"P",
    "gn:feature_code":"PPL",
    "gn:name":"Douar Sidi Mohammed",
    "gn:population":0,
    "gn:timezone":"Africa/Casablanca",
    "iso:country":"MA",
    "wof:name":"Douar Sidi Mohammed",
    "wof:placetype":"locality"
},
  "geometry": {"coordinates":[-6.35406,33.94724],"type":"Point"}
}