{
  "type": "Feature",
  "properties": {
    "gn:admin1_code":"7.0",
    "gn:asciiname":"Dar Abdelkader Labhar",
    "gn:country_code":"MA",
    "gn:dem":437,
    "gn:feature_class":"P",
    "gn:feature_code":"PPL",
    "gn:name":"Dar Abdelkader Labhar",
    "gn:population":0,
    "gn:timezone":"Africa/Casablanca",
    "iso:country":"MA",
    "wof:name":"Dar Abdelkader Labhar",
    "wof:placetype":"locality"
},
  "geometry": {"coordinates":[-7.74426,32.18474000000001],"type":"Point"}
}