{
  "type": "Feature",
  "properties": {
    "gn:admin1_code":"2.0",
    "gn:asciiname":"Douar Tmadet",
    "gn:country_code":"MA",
    "gn:dem":99,
    "gn:feature_class":"P",
    "gn:feature_code":"PPL",
    "gn:name":"Douar Tmadet",
    "gn:population":0,
    "gn:timezone":"Africa/Casablanca",
    "iso:country":"MA",
    "wof:name":"Douar Tmadet",
    "wof:placetype":"locality"
},
  "geometry": {"coordinates":[-2.53289,35.07765999999999],"type":"Point"}
}