{
  "type": "Feature",
  "properties": {
    "gn:admin1_code":"09",
    "gn:asciiname":"Ait Taleb Mohamed",
    "gn:country_code":"MA",
    "gn:dem":211,
    "gn:feature_class":"P",
    "gn:feature_code":"PPL",
    "gn:name":"A\u00eft Taleb Mohamed",
    "gn:population":0,
    "gn:timezone":"Africa/Casablanca",
    "iso:country":"MA",
    "name:und_x_variant":[
        "Oulad Moumen",
        "A\u00eft Taleb Mohammed",
        "A\u00eft Taleb Mohamed"
    ],
    "wof:name":"Ait Taleb Mohamed",
    "wof:placetype":"locality"
},
  "geometry": {"coordinates":[-9.03797,30.52139],"type":"Point"}
}