{
  "type": "Feature",
  "properties": {
    "gn:admin1_code":"09",
    "gn:asciiname":"Chakoukane",
    "gn:country_code":"MA",
    "gn:dem":887,
    "gn:feature_class":"P",
    "gn:feature_code":"PPL",
    "gn:name":"Chakoukane",
    "gn:population":0,
    "gn:timezone":"Africa/Casablanca",
    "iso:country":"MA",
    "name:und_x_variant":[
        "Ichakouk\u00e8n",
        "Ichakoukene",
        "Chakoukane"
    ],
    "wof:name":"Chakoukane",
    "wof:placetype":"locality"
},
  "geometry": {"coordinates":[-7.98161,30.73688],"type":"Point"}
}