{
  "type": "Feature",
  "properties": {
    "gn:admin1_code":"06",
    "gn:asciiname":"El Haouari",
    "gn:country_code":"MA",
    "gn:dem":127,
    "gn:feature_class":"P",
    "gn:feature_code":"PPL",
    "gn:name":"El Haouari",
    "gn:population":0,
    "gn:timezone":"Africa/Casablanca",
    "iso:country":"MA",
    "name:und_x_variant":[
        "Douar el Haouari",
        "El Haouari"
    ],
    "wof:name":"El Haouari",
    "wof:placetype":"locality"
},
  "geometry": {"coordinates":[-8.74479,32.67777],"type":"Point"}
}