{
  "type": "Feature",
  "properties": {
    "gn:admin1_code":"9.0",
    "gn:asciiname":"Takatart",
    "gn:country_code":"MA",
    "gn:dem":579,
    "gn:feature_class":"P",
    "gn:feature_code":"PPL",
    "gn:name":"Takatart",
    "gn:population":0,
    "gn:timezone":"Africa/Casablanca",
    "iso:country":"MA",
    "wof:name":"Takatart",
    "wof:placetype":"locality"
},
  "geometry": {"coordinates":[-9.21179,29.94529],"type":"Point"}
}