{
  "type": "Feature",
  "properties": {
    "gn:admin1_code":"2.0",
    "gn:asciiname":"Izime",
    "gn:country_code":"MA",
    "gn:dem":432,
    "gn:feature_class":"P",
    "gn:feature_code":"PPL",
    "gn:name":"Izime",
    "gn:population":0,
    "gn:timezone":"Africa/Casablanca",
    "iso:country":"MA",
    "wof:name":"Izime",
    "wof:placetype":"locality"
},
  "geometry": {"coordinates":[-3.4218,35.07253],"type":"Point"}
}