{
  "type": "Feature",
  "properties": {
    "gn:admin1_code":"03",
    "gn:asciiname":"Ait Lhaj All",
    "gn:country_code":"MA",
    "gn:dem":689,
    "gn:feature_class":"P",
    "gn:feature_code":"PPL",
    "gn:name":"Ait Lhaj All",
    "gn:population":0,
    "gn:timezone":"Africa/Casablanca",
    "iso:country":"MA",
    "name:und_x_variant":[
        "El Haj Ali"
    ],
    "wof:name":"Ait Lhaj All",
    "wof:placetype":"locality"
},
  "geometry": {"coordinates":[-5.29394,33.84015],"type":"Point"}
}