{
  "type": "Feature",
  "properties": {
    "gn:admin1_code":"7.0",
    "gn:asciiname":"Rbaat El Amari",
    "gn:country_code":"MA",
    "gn:dem":398,
    "gn:feature_class":"P",
    "gn:feature_code":"PPL",
    "gn:name":"Rbaat El Amari",
    "gn:population":0,
    "gn:timezone":"Africa/Casablanca",
    "iso:country":"MA",
    "wof:name":"Rbaat El Amari",
    "wof:placetype":"locality"
},
  "geometry": {"coordinates":[-8.9305,32.07801],"type":"Point"}
}