{
  "type": "Feature",
  "properties": {
    "gn:admin1_code":"03",
    "gn:asciiname":"El Kelaa",
    "gn:country_code":"MA",
    "gn:dem":659,
    "gn:feature_class":"P",
    "gn:feature_code":"PPL",
    "gn:name":"El Kelaa",
    "gn:population":0,
    "gn:timezone":"Africa/Casablanca",
    "iso:country":"MA",
    "name:und_x_variant":[
        "Kela\u00e2",
        "El Kelaa"
    ],
    "wof:name":"El Kelaa",
    "wof:placetype":"locality"
},
  "geometry": {"coordinates":[-5.36569,34.03214000000001],"type":"Point"}
}