{
  "type": "Feature",
  "properties": {
    "gn:admin1_code":"04",
    "gn:asciiname":"El Maarif",
    "gn:country_code":"MA",
    "gn:dem":17,
    "gn:feature_class":"P",
    "gn:feature_code":"PPL",
    "gn:name":"El Maarif",
    "gn:population":0,
    "gn:timezone":"Africa/Casablanca",
    "iso:country":"MA",
    "name:und_x_variant":[
        "El Ma\u00e2rif Dahr el Hdaj",
        "El Maarif"
    ],
    "wof:name":"El Maarif",
    "wof:placetype":"locality"
},
  "geometry": {"coordinates":[-6.10648,34.85731],"type":"Point"}
}