{
  "type": "Feature",
  "properties": {
    "gn:admin1_code":"7.0",
    "gn:asciiname":"Tifirhas",
    "gn:country_code":"MA",
    "gn:dem":1207,
    "gn:feature_class":"P",
    "gn:feature_code":"PPL",
    "gn:name":"Tifirhas",
    "gn:population":0,
    "gn:timezone":"Africa/Casablanca",
    "iso:country":"MA",
    "wof:name":"Tifirhas",
    "wof:placetype":"locality"
},
  "geometry": {"coordinates":[-9.0761,31.19958],"type":"Point"}
}