{
  "type": "Feature",
  "properties": {
    "gn:admin1_code":"5.0",
    "gn:asciiname":"Tizi-n-Tanikt",
    "gn:country_code":"MA",
    "gn:dem":766,
    "gn:feature_class":"P",
    "gn:feature_code":"PPL",
    "gn:name":"Tizi-n-Tanikt",
    "gn:population":0,
    "gn:timezone":"Africa/Casablanca",
    "iso:country":"MA",
    "wof:name":"Tizi-n-Tanikt",
    "wof:placetype":"locality"
},
  "geometry": {"coordinates":[-6.95939,31.84081],"type":"Point"}
}