{
  "type": "Feature",
  "properties": {
    "gn:admin1_code":"3.0",
    "gn:asciiname":"Dar Fadili Mimoune",
    "gn:country_code":"MA",
    "gn:dem":1255,
    "gn:feature_class":"P",
    "gn:feature_code":"PPL",
    "gn:name":"Dar Fadili Mimoune",
    "gn:population":0,
    "gn:timezone":"Africa/Casablanca",
    "iso:country":"MA",
    "wof:name":"Dar Fadili Mimoune",
    "wof:placetype":"locality"
},
  "geometry": {"coordinates":[-5.31012,33.50769],"type":"Point"}
}