{
  "type": "Feature",
  "properties": {
    "gn:admin1_code":"04",
    "gn:asciiname":"Douar Oulad Mimoune",
    "gn:country_code":"MA",
    "gn:dem":133,
    "gn:feature_class":"P",
    "gn:feature_code":"PPL",
    "gn:name":"Douar Oulad Mimoune",
    "gn:population":0,
    "gn:timezone":"Africa/Casablanca",
    "iso:country":"MA",
    "name:und_x_variant":[
        "Oulad Mimoun",
        "Douar Oulad Mimoun",
        "Douar Oulad Mimoune"
    ],
    "wof:name":"Douar Oulad Mimoune",
    "wof:placetype":"locality"
},
  "geometry": {"coordinates":[-5.83525,34.7129],"type":"Point"}
}