{
  "type": "Feature",
  "properties": {
    "gn:admin1_code":"01",
    "gn:asciiname":"Menkal",
    "gn:country_code":"MA",
    "gn:dem":65,
    "gn:feature_class":"P",
    "gn:feature_code":"PPL",
    "gn:name":"Menkal",
    "gn:population":0,
    "gn:timezone":"Africa/Casablanca",
    "iso:country":"MA",
    "wof:name":"Menkal",
    "wof:placetype":"locality"
},
  "geometry": {"coordinates":[-5.46358,35.54555],"type":"Point"}
}