{
  "type": "Feature",
  "properties": {
    "gn:admin1_code":"5.0",
    "gn:asciiname":"Talazggaghn",
    "gn:country_code":"MA",
    "gn:dem":1369,
    "gn:feature_class":"P",
    "gn:feature_code":"PPL",
    "gn:name":"Talazggaghn",
    "gn:population":0,
    "gn:timezone":"Africa/Casablanca",
    "iso:country":"MA",
    "wof:name":"Talazggaghn",
    "wof:placetype":"locality"
},
  "geometry": {"coordinates":[-6.47151,32.13422],"type":"Point"}
}