{
  "type": "Feature",
  "properties": {
    "gn:admin1_code":"5.0",
    "gn:asciiname":"Maygou",
    "gn:country_code":"MA",
    "gn:dem":1184,
    "gn:feature_class":"P",
    "gn:feature_code":"PPL",
    "gn:name":"Maygou",
    "gn:population":0,
    "gn:timezone":"Africa/Casablanca",
    "iso:country":"MA",
    "wof:name":"Maygou",
    "wof:placetype":"locality"
},
  "geometry": {"coordinates":[-6.89545,31.77699],"type":"Point"}
}