{
  "type": "Feature",
  "properties": {
    "gn:admin1_code":"09",
    "gn:asciiname":"Tirhanimine",
    "gn:country_code":"MA",
    "gn:dem":753,
    "gn:feature_class":"P",
    "gn:feature_code":"PPL",
    "gn:name":"Tirhanimine",
    "gn:population":0,
    "gn:timezone":"Africa/Casablanca",
    "iso:country":"MA",
    "name:und_x_variant":[
        "Tighanimine",
        "Tirhanimine"
    ],
    "wof:name":"Tirhanimine",
    "wof:placetype":"locality"
},
  "geometry": {"coordinates":[-9.42306,30.59385],"type":"Point"}
}