{
  "type": "Feature",
  "properties": {
    "gn:admin1_code":"08",
    "gn:asciiname":"Aguim",
    "gn:country_code":"MA",
    "gn:dem":1710,
    "gn:feature_class":"P",
    "gn:feature_code":"PPL",
    "gn:name":"Aguim",
    "gn:population":0,
    "gn:timezone":"Africa/Casablanca",
    "iso:country":"MA",
    "name:und_x_variant":[
        "Agouim",
        "Aguim"
    ],
    "wof:name":"Aguim",
    "wof:placetype":"locality"
},
  "geometry": {"coordinates":[-7.4616,31.15568],"type":"Point"}
}