{
  "type": "Feature",
  "properties": {
    "gn:admin1_code":"2.0",
    "gn:asciiname":"Oulad Ziane",
    "gn:country_code":"MA",
    "gn:dem":439,
    "gn:feature_class":"P",
    "gn:feature_code":"PPL",
    "gn:name":"Oulad Ziane",
    "gn:population":0,
    "gn:timezone":"Africa/Casablanca",
    "iso:country":"MA",
    "wof:name":"Oulad Ziane",
    "wof:placetype":"locality"
},
  "geometry": {"coordinates":[-1.89501,34.82194],"type":"Point"}
}