{
  "type": "Feature",
  "properties": {
    "gn:admin1_code":"01",
    "gn:asciiname":"Boukhaled",
    "gn:country_code":"MA",
    "gn:dem":280,
    "gn:feature_class":"P",
    "gn:feature_code":"PPL",
    "gn:name":"Boukhaled",
    "gn:population":0,
    "gn:timezone":"Africa/Casablanca",
    "iso:country":"MA",
    "name:und_x_variant":[
        "Bou Khalled"
    ],
    "wof:name":"Boukhaled",
    "wof:placetype":"locality"
},
  "geometry": {"coordinates":[-5.412,35.49502000000001],"type":"Point"}
}