{
  "type": "Feature",
  "properties": {
    "gn:admin1_code":"7.0",
    "gn:asciiname":"Taynit",
    "gn:country_code":"MA",
    "gn:dem":1291,
    "gn:feature_class":"P",
    "gn:feature_code":"PPL",
    "gn:name":"Taynit",
    "gn:population":0,
    "gn:timezone":"Africa/Casablanca",
    "iso:country":"MA",
    "wof:name":"Taynit",
    "wof:placetype":"locality"
},
  "geometry": {"coordinates":[-7.67055,31.3754],"type":"Point"}
}