{
  "type": "Feature",
  "properties": {
    "gn:admin1_code":"11",
    "gn:admin2_code":"121.0",
    "gn:admin3_code":"212103012.0",
    "gn:asciiname":"Gueltat Zemmour",
    "gn:country_code":"MA",
    "gn:dem":419,
    "gn:feature_class":"P",
    "gn:feature_code":"PPL",
    "gn:name":"Gueltat Zemmour",
    "gn:population":6740,
    "gn:timezone":"Africa/Casablanca",
    "iso:country":"MA",
    "wof:name":"Gueltat Zemmour",
    "wof:placetype":"locality",
    "wof:population":6740
},
  "geometry": {"coordinates":[-12.37168,25.14276],"type":"Point"}
}