{
  "type": "Feature",
  "properties": {
    "gn:admin1_code":"11",
    "gn:admin2_code":"121.0",
    "gn:admin3_code":"212103012.0",
    "gn:asciiname":"Gueltat Zemmour",
    "gn:country_code":"MA",
    "gn:dem":419,
    "gn:feature_class":"P",
    "gn:feature_code":"PPL",
    "gn:name":"Gueltat Zemmour",
    "gn:population":6740,
    "gn:timezone":"Africa/Casablanca",
    "iso:country":"MA",
    "name:ara_x_preferred":[
        "\u0643\u0648\u0644\u062a\u0629 \u0632\u0645\u0648\u0631"
    ],
    "name:cat_x_preferred":[
        "Guelta Zemur"
    ],
    "name:deu_x_preferred":[
        "Guelta Zemmur"
    ],
    "name:epo_x_preferred":[
        "Guelta Zemmur"
    ],
    "name:fra_x_preferred":[
        "Gueltat Zemmour"
    ],
    "name:ita_x_preferred":[
        "Guelta Zemmur"
    ],
    "name:kaz_x_preferred":[
        "\u0413\u0435\u043b\u044c\u0442\u0430-\u0417\u0435\u043c\u043c\u0443\u0440"
    ],
    "name:pol_x_preferred":[
        "Kaltat Zammur"
    ],
    "name:rus_x_preferred":[
        "\u0413\u0430\u043b\u044c\u0442\u0430\u0442-\u0417\u0435\u043c\u043c\u0443\u0440"
    ],
    "name:spa_x_preferred":[
        "Guelta Zemmur"
    ],
    "wof:name":"Gueltat Zemmour",
    "wof:placetype":"locality",
    "wof:population":6740
},
  "geometry": {"coordinates":[-12.37168,25.14276],"type":"Point"}
}