{
  "type": "Feature",
  "properties": {
    "gn:admin1_code":"02",
    "gn:asciiname":"Douar Oulad Abdelkarim",
    "gn:country_code":"MA",
    "gn:dem":824,
    "gn:feature_class":"P",
    "gn:feature_code":"PPL",
    "gn:name":"Douar Oulad Abdelkarim",
    "gn:population":0,
    "gn:timezone":"Africa/Casablanca",
    "iso:country":"MA",
    "name:und_x_variant":[
        "Oulad Abd el Krim"
    ],
    "wof:name":"Douar Oulad Abdelkarim",
    "wof:placetype":"locality"
},
  "geometry": {"coordinates":[-2.29006,34.83029000000001],"type":"Point"}
}