{
  "type": "Feature",
  "properties": {
    "gn:admin1_code":"9.0",
    "gn:asciiname":"Tagadiyrt",
    "gn:country_code":"MA",
    "gn:dem":448,
    "gn:feature_class":"P",
    "gn:feature_code":"PPL",
    "gn:name":"Tagadiyrt",
    "gn:population":0,
    "gn:timezone":"Africa/Casablanca",
    "iso:country":"MA",
    "wof:name":"Tagadiyrt",
    "wof:placetype":"locality"
},
  "geometry": {"coordinates":[-9.41354,29.68671],"type":"Point"}
}