{
  "type": "Feature",
  "properties": {
    "gn:admin1_code":"07",
    "gn:asciiname":"Douar Oulad Ben Azzouz Er-Rich",
    "gn:country_code":"MA",
    "gn:dem":452,
    "gn:feature_class":"P",
    "gn:feature_code":"PPL",
    "gn:name":"Douar Oulad Ben Azzouz Er-Rich",
    "gn:population":0,
    "gn:timezone":"Africa/Casablanca",
    "iso:country":"MA",
    "name:und_x_variant":[
        "Oulad ben Azzouz",
        "Douar Oulad Ben Azzouz",
        "Douar Ouled Ben Azzouz",
        "Douar Oulad Ben Azzouz Er-Rich"
    ],
    "wof:name":"Douar Oulad Ben Azzouz Er-Rich",
    "wof:placetype":"locality"
},
  "geometry": {"coordinates":[-8.48107,32.0113],"type":"Point"}
}