{
  "type": "Feature",
  "properties": {
    "gn:admin1_code":"08",
    "gn:asciiname":"Guiwaz",
    "gn:country_code":"MA",
    "gn:dem":765,
    "gn:feature_class":"P",
    "gn:feature_code":"PPL",
    "gn:name":"Guiwaz",
    "gn:population":0,
    "gn:timezone":"Africa/Casablanca",
    "iso:country":"MA",
    "name:und_x_variant":[
        "Ksar Guiouz",
        "Guiouaz",
        "Guiwaz"
    ],
    "wof:name":"Guiwaz",
    "wof:placetype":"locality"
},
  "geometry": {"coordinates":[-4.31398,31.30346],"type":"Point"}
}