{
  "type": "Feature",
  "properties": {
    "gn:admin1_code":"4.0",
    "gn:asciiname":"Cooperative Farah",
    "gn:country_code":"MA",
    "gn:dem":13,
    "gn:feature_class":"P",
    "gn:feature_code":"PPLF",
    "gn:name":"Coop\u00e9rative Farah",
    "gn:population":0,
    "gn:timezone":"Africa/Casablanca",
    "iso:country":"MA",
    "wof:name":"Cooperative Farah",
    "wof:placetype":"locality"
},
  "geometry": {"coordinates":[-6.12763,34.73177],"type":"Point"}
}