{
  "type": "Feature",
  "properties": {
    "gn:admin1_code":"7.0",
    "gn:asciiname":"Tagadirt-n-Oumius",
    "gn:country_code":"MA",
    "gn:dem":1424,
    "gn:feature_class":"P",
    "gn:feature_code":"PPL",
    "gn:name":"Tagadirt-n-Oumius",
    "gn:population":0,
    "gn:timezone":"Africa/Casablanca",
    "iso:country":"MA",
    "wof:name":"Tagadirt-n-Oumius",
    "wof:placetype":"locality"
},
  "geometry": {"coordinates":[-8.20816,30.96726],"type":"Point"}
}