{
  "type": "Feature",
  "properties": {
    "gn:admin1_code":"03",
    "gn:asciiname":"Ait Ali Moussa",
    "gn:country_code":"MA",
    "gn:dem":584,
    "gn:feature_class":"P",
    "gn:feature_code":"PPL",
    "gn:name":"A\u00eft Ali Moussa",
    "gn:population":0,
    "gn:timezone":"Africa/Casablanca",
    "iso:country":"MA",
    "name:und_x_variant":[
        "A\u00eft Ali Ou Moussa",
        "A\u00eft Ali Moussa"
    ],
    "wof:name":"Ait Ali Moussa",
    "wof:placetype":"locality"
},
  "geometry": {"coordinates":[-5.45,33.88],"type":"Point"}
}