{
  "type": "Feature",
  "properties": {
    "gn:admin1_code":"07",
    "gn:asciiname":"Douar Oulad El Makki",
    "gn:country_code":"MA",
    "gn:dem":217,
    "gn:feature_class":"P",
    "gn:feature_code":"PPL",
    "gn:name":"Douar Oulad El Makki",
    "gn:population":0,
    "gn:timezone":"Africa/Casablanca",
    "iso:country":"MA",
    "name:und_x_variant":[
        "Douar Allal Ben Mekki",
        "Ouled Mekki",
        "Oulad Mekki",
        "Douar Oulad El Makki"
    ],
    "wof:name":"Douar Oulad El Makki",
    "wof:placetype":"locality"
},
  "geometry": {"coordinates":[-9.10749,31.79791],"type":"Point"}
}