{
  "type": "Feature",
  "properties": {
    "gn:admin1_code":"07",
    "gn:asciiname":"Douar Rguibat Hmiri",
    "gn:country_code":"MA",
    "gn:dem":365,
    "gn:feature_class":"P",
    "gn:feature_code":"PPL",
    "gn:name":"Douar Rguibat Hmiri",
    "gn:population":0,
    "gn:timezone":"Africa/Casablanca",
    "iso:country":"MA",
    "name:und_x_variant":[
        "Douar Reguibate",
        "Rguibate",
        "Rguibate Oued",
        "Rguibat",
        "Douar Rguibat Hmiri"
    ],
    "wof:name":"Douar Rguibat Hmiri",
    "wof:placetype":"locality"
},
  "geometry": {"coordinates":[-8.32755,32.35347],"type":"Point"}
}