{
  "type": "Feature",
  "properties": {
    "gn:admin1_code":"7.0",
    "gn:asciiname":"Ayt Laghawi",
    "gn:country_code":"MA",
    "gn:dem":687,
    "gn:feature_class":"P",
    "gn:feature_code":"PPL",
    "gn:name":"Ayt Laghawi",
    "gn:population":0,
    "gn:timezone":"Africa/Casablanca",
    "iso:country":"MA",
    "wof:name":"Ayt Laghawi",
    "wof:placetype":"locality"
},
  "geometry": {"coordinates":[-7.14278,31.792],"type":"Point"}
}