{
  "type": "Feature",
  "properties": {
    "gn:admin1_code":"07",
    "gn:asciiname":"Zaouia Sidi Ahmed Ou Brahim",
    "gn:country_code":"MA",
    "gn:dem":756,
    "gn:feature_class":"P",
    "gn:feature_code":"PPL",
    "gn:name":"Zaouia Sidi Ahmed Ou Brahim",
    "gn:population":0,
    "gn:timezone":"Africa/Casablanca",
    "iso:country":"MA",
    "name:und_x_variant":[
        "Zaou\u00eft Sidi Brahim",
        "Zaouia Sidi Ahmed Ou Brahim"
    ],
    "wof:name":"Zaouia Sidi Ahmed Ou Brahim",
    "wof:placetype":"locality"
},
  "geometry": {"coordinates":[-8.61129,31.23903],"type":"Point"}
}