{
  "type": "Feature",
  "properties": {
    "gn:admin1_code":"3.0",
    "gn:asciiname":"Bir Sidi Ahmed",
    "gn:country_code":"MA",
    "gn:dem":576,
    "gn:feature_class":"P",
    "gn:feature_code":"PPL",
    "gn:name":"Bir Sidi Ahmed",
    "gn:population":0,
    "gn:timezone":"Africa/Casablanca",
    "iso:country":"MA",
    "wof:name":"Bir Sidi Ahmed",
    "wof:placetype":"locality"
},
  "geometry": {"coordinates":[-4.50838,34.22443],"type":"Point"}
}