{
  "type": "Feature",
  "properties": {
    "gn:admin1_code":"7.0",
    "gn:asciiname":"Hajra El Bida",
    "gn:country_code":"MA",
    "gn:dem":289,
    "gn:feature_class":"P",
    "gn:feature_code":"PPL",
    "gn:name":"Hajra El Bida",
    "gn:population":0,
    "gn:timezone":"Africa/Casablanca",
    "iso:country":"MA",
    "wof:name":"Hajra El Bida",
    "wof:placetype":"locality"
},
  "geometry": {"coordinates":[-7.57775,32.4001],"type":"Point"}
}