{
  "type": "Feature",
  "properties": {
    "gn:admin1_code":"06",
    "gn:asciiname":"Sidi 'Abdel'aziz",
    "gn:country_code":"MA",
    "gn:dem":206,
    "gn:feature_class":"P",
    "gn:feature_code":"PPL",
    "gn:name":"Sidi \u2019Abdel\u2019aziz",
    "gn:population":0,
    "gn:timezone":"Africa/Casablanca",
    "iso:country":"MA",
    "name:und_x_variant":[
        "Sidi \u2019Abdel\u2019aziz",
        "Sidi Abd el Aziz"
    ],
    "wof:name":"Sidi 'Abdel'aziz",
    "wof:placetype":"locality"
},
  "geometry": {"coordinates":[-7.96166,33.15646],"type":"Point"}
}