{
  "type": "Feature",
  "properties": {
    "gn:admin1_code":"08",
    "gn:asciiname":"Ayt Seddour",
    "gn:country_code":"MA",
    "gn:dem":1356,
    "gn:feature_class":"P",
    "gn:feature_code":"PPL",
    "gn:name":"Ayt Seddour",
    "gn:population":0,
    "gn:timezone":"Africa/Casablanca",
    "iso:country":"MA",
    "name:und_x_variant":[
        "Borj de Seddour",
        "Bordj de Seddour",
        "A\u00eft Seddour",
        "Ayt Seddour"
    ],
    "wof:name":"Ayt Seddour",
    "wof:placetype":"locality"
},
  "geometry": {"coordinates":[-4.46415,32.18281],"type":"Point"}
}