{
  "type": "Feature",
  "properties": {
    "gn:admin1_code":"07",
    "gn:asciiname":"Taguennza",
    "gn:country_code":"MA",
    "gn:dem":590,
    "gn:feature_class":"P",
    "gn:feature_code":"PPL",
    "gn:name":"Taguennza",
    "gn:population":0,
    "gn:timezone":"Africa/Casablanca",
    "iso:country":"MA",
    "name:und_x_variant":[
        "Taguenza"
    ],
    "wof:name":"Taguennza",
    "wof:placetype":"locality"
},
  "geometry": {"coordinates":[-8.12367,31.39731],"type":"Point"}
}