{
  "type": "Feature",
  "properties": {
    "gn:admin1_code":"01",
    "gn:asciiname":"Douar Brareq",
    "gn:country_code":"MA",
    "gn:dem":407,
    "gn:feature_class":"P",
    "gn:feature_code":"PPL",
    "gn:name":"Douar Brareq",
    "gn:population":0,
    "gn:timezone":"Africa/Casablanca",
    "iso:country":"MA",
    "name:und_x_variant":[
        "Dar el Berarak"
    ],
    "wof:name":"Douar Brareq",
    "wof:placetype":"locality"
},
  "geometry": {"coordinates":[-5.56426,35.7169],"type":"Point"}
}