{
  "type": "Feature",
  "properties": {
    "gn:admin1_code":"7.0",
    "gn:asciiname":"Douar Moulay Calah",
    "gn:country_code":"MA",
    "gn:dem":580,
    "gn:feature_class":"P",
    "gn:feature_code":"PPL",
    "gn:name":"Douar Moulay \u00c7alah",
    "gn:population":0,
    "gn:timezone":"Africa/Casablanca",
    "iso:country":"MA",
    "wof:name":"Douar Moulay Calah",
    "wof:placetype":"locality"
},
  "geometry": {"coordinates":[-7.402,31.87282],"type":"Point"}
}