{
  "type": "Feature",
  "properties": {
    "gn:admin1_code":"6.0",
    "gn:asciiname":"El Hallouf",
    "gn:country_code":"MA",
    "gn:dem":233,
    "gn:feature_class":"P",
    "gn:feature_code":"PPL",
    "gn:name":"El Hallouf",
    "gn:population":0,
    "gn:timezone":"Africa/Casablanca",
    "iso:country":"MA",
    "wof:name":"El Hallouf",
    "wof:placetype":"locality"
},
  "geometry": {"coordinates":[-7.7315,32.63604],"type":"Point"}
}