{
  "type": "Feature",
  "properties": {
    "gn:admin1_code":"07",
    "gn:asciiname":"Oulad Bou Henda",
    "gn:country_code":"MA",
    "gn:dem":308,
    "gn:feature_class":"P",
    "gn:feature_code":"PPL",
    "gn:name":"Oulad Bou Henda",
    "gn:population":0,
    "gn:timezone":"Africa/Casablanca",
    "iso:country":"MA",
    "name:und_x_variant":[
        "Douar Oulad Bou Hennda",
        "Ouled Bouhouda",
        "Oulad Bou Hennda",
        "Oulad Bou Henda"
    ],
    "wof:name":"Oulad Bou Henda",
    "wof:placetype":"locality"
},
  "geometry": {"coordinates":[-8.08602,32.51949],"type":"Point"}
}