{
  "type": "Feature",
  "properties": {
    "gn:admin1_code":"7.0",
    "gn:asciiname":"Douar Hayyouk",
    "gn:country_code":"MA",
    "gn:dem":167,
    "gn:feature_class":"P",
    "gn:feature_code":"PPL",
    "gn:name":"Douar Hayyouk",
    "gn:population":0,
    "gn:timezone":"Africa/Casablanca",
    "iso:country":"MA",
    "wof:name":"Douar Hayyouk",
    "wof:placetype":"locality"
},
  "geometry": {"coordinates":[-8.99489,32.18859],"type":"Point"}
}