{
  "type": "Feature",
  "properties": {
    "gn:admin1_code":"10",
    "gn:asciiname":"Tazarine",
    "gn:country_code":"MA",
    "gn:dem":427,
    "gn:feature_class":"P",
    "gn:feature_code":"PPL",
    "gn:name":"Tazarine",
    "gn:population":0,
    "gn:timezone":"Africa/Casablanca",
    "iso:country":"MA",
    "name:ara_x_preferred":[
        "\u062a\u0627\u0632\u0627\u0631\u064a\u0646"
    ],
    "name:cat_x_preferred":[
        "Tazarine"
    ],
    "name:und_x_variant":[
        "Tasarin",
        "Tazarine"
    ],
    "wof:name":"Tazarine",
    "wof:placetype":"locality"
},
  "geometry": {"coordinates":[-10.08,29.45],"type":"Point"}
}