{
  "type": "Feature",
  "properties": {
    "gn:admin1_code":"01",
    "gn:asciiname":"Et Tnine des Beni Ammart",
    "gn:country_code":"MA",
    "gn:dem":1229,
    "gn:feature_class":"P",
    "gn:feature_code":"PPL",
    "gn:name":"Et Tnine des Beni Ammart",
    "gn:population":0,
    "gn:timezone":"Africa/Casablanca",
    "iso:country":"MA",
    "name:und_x_variant":[
        "Beni Ammart",
        "Et Tnine des Beni Amret",
        "Et Tnine des Beni Ammart"
    ],
    "wof:name":"Et Tnine des Beni Ammart",
    "wof:placetype":"locality"
},
  "geometry": {"coordinates":[-4.15842,34.80993],"type":"Point"}
}