{
  "type": "Feature",
  "properties": {
    "gn:admin1_code":"04",
    "gn:asciiname":"Oulad Ayyad",
    "gn:country_code":"MA",
    "gn:dem":29,
    "gn:feature_class":"P",
    "gn:feature_code":"PPL",
    "gn:name":"Oulad Ayyad",
    "gn:population":0,
    "gn:timezone":"Africa/Casablanca",
    "iso:country":"MA",
    "name:ara_x_preferred":[
        "\u0623\u0648\u0644\u0627\u062f \u0639\u064a\u0627\u062f"
    ],
    "name:cat_x_preferred":[
        "Oulad Ayyad"
    ],
    "name:ceb_x_preferred":[
        "Oulad Ayyad"
    ],
    "name:ita_x_preferred":[
        "Oulad Ayyad"
    ],
    "name:swe_x_preferred":[
        "Oulad Ayyad"
    ],
    "name:und_x_variant":[
        "Oulad Ayad"
    ],
    "wof:name":"Oulad Ayyad",
    "wof:placetype":"locality"
},
  "geometry": {"coordinates":[-6.14513,34.77075],"type":"Point"}
}