{
  "type": "Feature",
  "properties": {
    "gn:admin1_code":"9.0",
    "gn:asciiname":"Tadouart Oufella",
    "gn:country_code":"MA",
    "gn:dem":164,
    "gn:feature_class":"P",
    "gn:feature_code":"PPL",
    "gn:name":"Tadouart Oufella",
    "gn:population":0,
    "gn:timezone":"Africa/Casablanca",
    "iso:country":"MA",
    "wof:name":"Tadouart Oufella",
    "wof:placetype":"locality"
},
  "geometry": {"coordinates":[-9.28285,30.51075],"type":"Point"}
}