{
  "type": "Feature",
  "properties": {
    "gn:admin1_code":"1.0",
    "gn:asciiname":"Douar Ritouq",
    "gn:country_code":"MA",
    "gn:dem":811,
    "gn:feature_class":"P",
    "gn:feature_code":"PPL",
    "gn:name":"Douar Ritouq",
    "gn:population":0,
    "gn:timezone":"Africa/Casablanca",
    "iso:country":"MA",
    "wof:name":"Douar Ritouq",
    "wof:placetype":"locality"
},
  "geometry": {"coordinates":[-5.08645,35.02947],"type":"Point"}
}