{
  "type": "Feature",
  "properties": {
    "gn:admin1_code":"1.0",
    "gn:asciiname":"Douar Boucherif",
    "gn:country_code":"MA",
    "gn:dem":202,
    "gn:feature_class":"P",
    "gn:feature_code":"PPL",
    "gn:name":"Douar Boucherif",
    "gn:population":0,
    "gn:timezone":"Africa/Casablanca",
    "iso:country":"MA",
    "wof:name":"Douar Boucherif",
    "wof:placetype":"locality"
},
  "geometry": {"coordinates":[-5.37917,34.6347],"type":"Point"}
}