{
  "type": "Feature",
  "properties": {
    "gn:admin1_code":"02",
    "gn:asciiname":"Stah el Marhsel",
    "gn:country_code":"MA",
    "gn:dem":592,
    "gn:feature_class":"P",
    "gn:feature_code":"PPL",
    "gn:name":"Stah el Marhsel",
    "gn:population":0,
    "gn:timezone":"Africa/Casablanca",
    "iso:country":"MA",
    "name:und_x_variant":[
        "Douar Stah el Marhsel",
        "Stah el Marhsel"
    ],
    "wof:name":"Stah el Marhsel",
    "wof:placetype":"locality"
},
  "geometry": {"coordinates":[-3.76616,34.04634],"type":"Point"}
}