{
  "type": "Feature",
  "properties": {
    "gn:admin1_code":"1.0",
    "gn:asciiname":"Trabqech",
    "gn:country_code":"MA",
    "gn:dem":130,
    "gn:feature_class":"P",
    "gn:feature_code":"PPL",
    "gn:name":"Trabqech",
    "gn:population":0,
    "gn:timezone":"Africa/Casablanca",
    "iso:country":"MA",
    "wof:name":"Trabqech",
    "wof:placetype":"locality"
},
  "geometry": {"coordinates":[-5.53738,35.79765],"type":"Point"}
}