{
  "type": "Feature",
  "properties": {
    "gn:admin1_code":"09",
    "gn:asciiname":"Ighrem",
    "gn:country_code":"MA",
    "gn:dem":1464,
    "gn:feature_class":"P",
    "gn:feature_code":"PPL",
    "gn:name":"Ighrem",
    "gn:population":0,
    "gn:timezone":"Africa/Casablanca",
    "iso:country":"MA",
    "name:und_x_variant":[
        "Irherm"
    ],
    "wof:name":"Ighrem",
    "wof:placetype":"locality"
},
  "geometry": {"coordinates":[-8.10254,30.8825],"type":"Point"}
}