{
  "type": "Feature",
  "properties": {
    "gn:admin1_code":"03",
    "gn:asciiname":"Tahrzout",
    "gn:country_code":"MA",
    "gn:dem":1294,
    "gn:feature_class":"P",
    "gn:feature_code":"PPL",
    "gn:name":"Tahrzout",
    "gn:population":0,
    "gn:timezone":"Africa/Casablanca",
    "iso:country":"MA",
    "wof:name":"Tahrzout",
    "wof:placetype":"locality"
},
  "geometry": {"coordinates":[-4.39035,33.44154],"type":"Point"}
}