{
  "type": "Feature",
  "properties": {
    "gn:admin1_code":"05",
    "gn:asciiname":"Tissa",
    "gn:country_code":"MA",
    "gn:dem":1658,
    "gn:feature_class":"P",
    "gn:feature_code":"PPL",
    "gn:name":"Tissa",
    "gn:population":0,
    "gn:timezone":"Africa/Casablanca",
    "iso:country":"MA",
    "wof:name":"Tissa",
    "wof:placetype":"locality"
},
  "geometry": {"coordinates":[-6.54886,31.89494],"type":"Point"}
}