{
  "type": "Feature",
  "properties": {
    "gn:country":"MA",
    "gn:fcode":"ADM3",
    "gn:population":13721,
    "iso:country":"MA",
    "name:ara_x_preferred":[
        "\u062a\u0627\u0646\u0633\u064a\u0641\u062a"
    ],
    "name:ara_x_variant":[
        "\u0623\u064a\u0648\u0646\u0627\u0646",
        "\u062a\u0627\u0632\u0627\u0631\u064a\u0646"
    ],
    "name:cat_x_preferred":[
        "Tazarine"
    ],
    "name:eng_x_preferred":[
        "Tazarine"
    ],
    "name:fra_x_preferred":[
        "Tazarine"
    ],
    "name:fra_x_variant":[
        "Tazarine (CR)",
        "Tazarine (Commune Rurale)"
    ],
    "name:ita_x_preferred":[
        "Tazarine"
    ],
    "qs:name":"Tazarine",
    "qs:photos_9r":0,
    "qs:photos_sr":0,
    "qs:pop_sr":"6",
    "wd:wordcount":86,
    "wof:name":"Tazarine",
    "wof:placetype":"localadmin",
    "wof:population":13721
},
  "geometry": {"coordinates":[-5.54352,30.81469],"type":"Point"}
}