{
  "type": "Feature",
  "properties": {
    "gn:admin1_code":"3.0",
    "gn:asciiname":"Douar Oulad El Haj El Arbi",
    "gn:country_code":"MA",
    "gn:dem":336,
    "gn:feature_class":"P",
    "gn:feature_code":"PPL",
    "gn:name":"Douar Oulad El Haj El Arbi",
    "gn:population":0,
    "gn:timezone":"Africa/Casablanca",
    "iso:country":"MA",
    "wof:name":"Douar Oulad El Haj El Arbi",
    "wof:placetype":"locality"
},
  "geometry": {"coordinates":[-5.03574,34.42823],"type":"Point"}
}