{
  "type": "Feature",
  "properties": {
    "gn:admin1_code":"7.0",
    "gn:asciiname":"Douar Ben Achar",
    "gn:country_code":"MA",
    "gn:dem":562,
    "gn:feature_class":"P",
    "gn:feature_code":"PPL",
    "gn:name":"Douar Ben Achar",
    "gn:population":0,
    "gn:timezone":"Africa/Casablanca",
    "iso:country":"MA",
    "wof:name":"Douar Ben Achar",
    "wof:placetype":"locality"
},
  "geometry": {"coordinates":[-7.83079,31.53971],"type":"Point"}
}