{
  "type": "Feature",
  "properties": {
    "gn:admin1_code":"02",
    "gn:asciiname":"El Agued",
    "gn:country_code":"MA",
    "gn:dem":570,
    "gn:feature_class":"P",
    "gn:feature_code":"PPL",
    "gn:name":"El Agued",
    "gn:population":0,
    "gn:timezone":"Africa/Casablanca",
    "iso:country":"MA",
    "name:und_x_variant":[
        "Flagued",
        "El Agued"
    ],
    "wof:name":"El Agued",
    "wof:placetype":"locality"
},
  "geometry": {"coordinates":[-3.0713,34.73571],"type":"Point"}
}