{
  "type": "Feature",
  "properties": {
    "gn:admin1_code":"01",
    "gn:asciiname":"El Malha",
    "gn:country_code":"MA",
    "gn:dem":347,
    "gn:feature_class":"P",
    "gn:feature_code":"PPL",
    "gn:name":"El Malha",
    "gn:population":0,
    "gn:timezone":"Africa/Casablanca",
    "iso:country":"MA",
    "name:und_x_variant":[
        "Al Malha",
        "El Malha"
    ],
    "wof:name":"El Malha",
    "wof:placetype":"locality"
},
  "geometry": {"coordinates":[-5.04371,34.93684],"type":"Point"}
}