{
  "type": "Feature",
  "properties": {
    "gn:admin1_code":"07",
    "gn:asciiname":"Tahannawt",
    "gn:country_code":"MA",
    "gn:dem":942,
    "gn:feature_class":"P",
    "gn:feature_code":"PPL",
    "gn:name":"Tahannawt",
    "gn:population":0,
    "gn:timezone":"Africa/Casablanca",
    "iso:country":"MA",
    "name:eng_x_preferred":[
        "Tahannout"
    ],
    "name:eng_x_variant":[
        "Tahnaout"
    ],
    "name:und_x_variant":[
        "Tahanaout",
        "Tahanaoute",
        "Tahanaut",
        "Tahannawt"
    ],
    "wof:name":"Tahannawt",
    "wof:placetype":"locality"
},
  "geometry": {"coordinates":[-7.95012,31.35236],"type":"Point"}
}