{
  "type": "Feature",
  "properties": {
    "gn:admin1_code":"9.0",
    "gn:asciiname":"Asgawr",
    "gn:country_code":"MA",
    "gn:dem":986,
    "gn:feature_class":"P",
    "gn:feature_code":"PPL",
    "gn:name":"Asgawr",
    "gn:population":0,
    "gn:timezone":"Africa/Casablanca",
    "iso:country":"MA",
    "wof:name":"Asgawr",
    "wof:placetype":"locality"
},
  "geometry": {"coordinates":[-8.97027,29.76836],"type":"Point"}
}