{
  "type": "Feature",
  "properties": {
    "gn:admin1_code":"9.0",
    "gn:asciiname":"Ait Ourtata",
    "gn:country_code":"MA",
    "gn:dem":2117,
    "gn:feature_class":"P",
    "gn:feature_code":"PPL",
    "gn:name":"A\u00eft Ourtata",
    "gn:population":0,
    "gn:timezone":"Africa/Casablanca",
    "iso:country":"MA",
    "wof:name":"Ait Ourtata",
    "wof:placetype":"locality"
},
  "geometry": {"coordinates":[-7.73575,30.81608],"type":"Point"}
}