{
  "type": "Feature",
  "properties": {
    "gn:admin1_code":"01",
    "gn:asciiname":"Oulad Amrane el Mekki",
    "gn:country_code":"MA",
    "gn:dem":38,
    "gn:feature_class":"P",
    "gn:feature_code":"PPL",
    "gn:name":"Oulad Amrane el Mekki",
    "gn:population":0,
    "gn:timezone":"Africa/Casablanca",
    "iso:country":"MA",
    "name:ara_x_preferred":[
        "\u0623\u0648\u0644\u0627\u062f \u0639\u0645\u0631\u0627\u0646"
    ],
    "name:azb_x_preferred":[
        "\u0627\u0648\u0644\u0627\u062f \u0639\u0645\u0631\u0627\u0646"
    ],
    "name:cat_x_preferred":[
        "Oulad Amrane"
    ],
    "name:fas_x_preferred":[
        "\u0627\u0648\u0644\u0627\u062f \u0639\u0645\u0631\u0627\u0646"
    ],
    "name:fra_x_preferred":[
        "Oulad Amrane"
    ],
    "name:ita_x_preferred":[
        "Oulad Amrane"
    ],
    "name:und_x_variant":[
        "Ulad Aaman el Crota",
        "Oulad Amrane el Krota",
        "Oulad Amrane el Mekki"
    ],
    "wof:name":"Oulad Amrane el Mekki",
    "wof:placetype":"locality"
},
  "geometry": {"coordinates":[-5.95551,35.22226],"type":"Point"}
}