{
  "type": "Feature",
  "properties": {
    "gn:admin1_code":"3.0",
    "gn:asciiname":"Douar Echorfa",
    "gn:country_code":"MA",
    "gn:dem":733,
    "gn:feature_class":"P",
    "gn:feature_code":"PPL",
    "gn:name":"Douar Echorfa",
    "gn:population":0,
    "gn:timezone":"Africa/Casablanca",
    "iso:country":"MA",
    "wof:name":"Douar Echorfa",
    "wof:placetype":"locality"
},
  "geometry": {"coordinates":[-4.35355,34.36283],"type":"Point"}
}