{
  "type": "Feature",
  "properties": {
    "gn:admin1_code":"09",
    "gn:asciiname":"Asgoun",
    "gn:country_code":"MA",
    "gn:dem":1678,
    "gn:feature_class":"P",
    "gn:feature_code":"PPL",
    "gn:name":"Asgoun",
    "gn:population":0,
    "gn:timezone":"Africa/Casablanca",
    "iso:country":"MA",
    "wof:name":"Asgoun",
    "wof:placetype":"locality"
},
  "geometry": {"coordinates":[-8.53968,30.0288],"type":"Point"}
}