{
  "type": "Feature",
  "properties": {
    "gn:admin1_code":"3.0",
    "gn:asciiname":"Qiyada",
    "gn:country_code":"MA",
    "gn:dem":622,
    "gn:feature_class":"P",
    "gn:feature_code":"PPL",
    "gn:name":"Qiyada",
    "gn:population":0,
    "gn:timezone":"Africa/Casablanca",
    "iso:country":"MA",
    "wof:name":"Qiyada",
    "wof:placetype":"locality"
},
  "geometry": {"coordinates":[-5.54536,34.02192],"type":"Point"}
}