{
  "type": "Feature",
  "properties": {
    "gn:admin1_code":"10",
    "gn:asciiname":"Id Mansour",
    "gn:country_code":"MA",
    "gn:dem":757,
    "gn:feature_class":"P",
    "gn:feature_code":"PPL",
    "gn:name":"Id Mansour",
    "gn:population":0,
    "gn:timezone":"Africa/Casablanca",
    "iso:country":"MA",
    "name:und_x_variant":[
        "Id Mansous",
        "Id Mansour"
    ],
    "wof:name":"Id Mansour",
    "wof:placetype":"locality"
},
  "geometry": {"coordinates":[-9.54735,29.19713],"type":"Point"}
}