{
  "type": "Feature",
  "properties": {
    "gn:country":"MA",
    "gn:fcode":"ADM3",
    "gn:population":3023,
    "iso:country":"MA",
    "name:ara_x_preferred":[
        "\u062a\u0627\u0643\u0644\u0641\u062a"
    ],
    "name:ara_x_variant":[
        "\u062a\u064a\u0641\u0631\u062a \u0646\u0622\u064a\u062a \u062d\u0645\u0632\u0629"
    ],
    "name:ary_x_preferred":[
        "\u062a\u064a\u0641\u0651\u0631\u062a \u0646 \u0622\u064a\u062a \u062d\u0645\u0632\u0629"
    ],
    "name:cat_x_preferred":[
        "Tiffert N'Ait Hamza"
    ],
    "name:eng_x_preferred":[
        "Tiffert N'Ait Hamza"
    ],
    "name:fra_x_preferred":[
        "Tiffert N Ait Hamza"
    ],
    "name:fra_x_variant":[
        "Tiffert N Ait Hamza (CR)",
        "Tiffert N Ait Hamza (Commune Rurale)",
        "Tiffert N'Ait Hamza"
    ],
    "name:ita_x_preferred":[
        "Tiffert N'Ait Hamza"
    ],
    "qs:name":"Tiffert N Ait Hamza",
    "qs:photos_9r":0,
    "qs:photos_sr":0,
    "qs:pop_sr":"4",
    "wd:wordcount":78,
    "wof:name":"Tiffert N Ait Hamza",
    "wof:placetype":"localadmin",
    "wof:population":3023
},
  "geometry": {"coordinates":[-5.94942,32.30243],"type":"Point"}
}