{
  "type": "Feature",
  "properties": {
    "gn:country":"MA",
    "gn:fcode":"ADM3",
    "gn:pop":3023,
    "iso:country":"MA",
    "name:ara_x_preferred":[
        "\u062a\u0627\u0643\u0644\u0641\u062a"
    ],
    "name:fra_x_preferred":[
        "Tiffert N Ait Hamza"
    ],
    "name:fra_x_variant":[
        "Tiffert N Ait Hamza (CR)",
        "Tiffert N Ait Hamza (Commune Rurale)"
    ],
    "qs:name":"Tiffert N Ait Hamza",
    "qs:photos_9r":0,
    "qs:photos_sr":0,
    "qs:pop_sr":"4",
    "wd:wordcount":78,
    "wof:name":"Tiffert N Ait Hamza",
    "wof:placetype":"localadmin",
    "wof:population":3023
},
  "geometry": {"coordinates":[-5.94942,32.30243],"type":"Point"}
}