{
  "type": "Feature",
  "properties": {
    "gn:admin1_code":"6.0",
    "gn:asciiname":"Douar Oulad Ahmed Ben Tahar",
    "gn:country_code":"MA",
    "gn:dem":460,
    "gn:feature_class":"P",
    "gn:feature_code":"PPL",
    "gn:name":"Douar Oulad Ahmed Ben Tahar",
    "gn:population":0,
    "gn:timezone":"Africa/Casablanca",
    "iso:country":"MA",
    "wof:name":"Douar Oulad Ahmed Ben Tahar",
    "wof:placetype":"locality"
},
  "geometry": {"coordinates":[-7.40257,32.60602],"type":"Point"}
}