{
  "type": "Feature",
  "properties": {
    "gn:admin1_code":"2.0",
    "gn:asciiname":"Douar Oulad Abdellah Ben Kaddour",
    "gn:country_code":"MA",
    "gn:dem":635,
    "gn:feature_class":"P",
    "gn:feature_code":"PPL",
    "gn:name":"Douar Oulad Abdellah Ben Kaddour",
    "gn:population":0,
    "gn:timezone":"Africa/Casablanca",
    "iso:country":"MA",
    "wof:name":"Douar Oulad Abdellah Ben Kaddour",
    "wof:placetype":"locality"
},
  "geometry": {"coordinates":[-2.41516,34.59192],"type":"Point"}
}