{
  "type": "Feature",
  "properties": {
    "gn:admin1_code":"10.0",
    "gn:asciiname":"Id Hmed Lahsene",
    "gn:country_code":"MA",
    "gn:dem":912,
    "gn:feature_class":"P",
    "gn:feature_code":"PPL",
    "gn:name":"Id Hmed Lahsene",
    "gn:population":0,
    "gn:timezone":"Africa/Casablanca",
    "iso:country":"MA",
    "wof:name":"Id Hmed Lahsene",
    "wof:placetype":"locality"
},
  "geometry": {"coordinates":[-9.79639,29.31169],"type":"Point"}
}