{
  "type": "Feature",
  "properties": {
    "gn:admin1_code":"01",
    "gn:asciiname":"Laaraara",
    "gn:country_code":"MA",
    "gn:dem":666,
    "gn:feature_class":"P",
    "gn:feature_code":"PPL",
    "gn:name":"Laaraara",
    "gn:population":0,
    "gn:timezone":"Africa/Casablanca",
    "iso:country":"MA",
    "name:und_x_variant":[
        "Laraara"
    ],
    "wof:name":"Laaraara",
    "wof:placetype":"locality"
},
  "geometry": {"coordinates":[-4.64542,35.16118],"type":"Point"}
}