{
  "type": "Feature",
  "properties": {
    "gn:admin1_code":"7.0",
    "gn:asciiname":"Douar Leabacule",
    "gn:country_code":"MA",
    "gn:dem":483,
    "gn:feature_class":"P",
    "gn:feature_code":"PPL",
    "gn:name":"Douar Leabacule",
    "gn:population":0,
    "gn:timezone":"Africa/Casablanca",
    "iso:country":"MA",
    "wof:name":"Douar Leabacule",
    "wof:placetype":"locality"
},
  "geometry": {"coordinates":[-7.81855,31.64015],"type":"Point"}
}