{
  "type": "Feature",
  "properties": {
    "gn:admin1_code":"3.0",
    "gn:asciiname":"Douar Smaala",
    "gn:country_code":"MA",
    "gn:dem":99,
    "gn:feature_class":"P",
    "gn:feature_code":"PPL",
    "gn:name":"Douar Smaala",
    "gn:population":0,
    "gn:timezone":"Africa/Casablanca",
    "iso:country":"MA",
    "wof:name":"Douar Smaala",
    "wof:placetype":"locality"
},
  "geometry": {"coordinates":[-5.41144,34.23809],"type":"Point"}
}