{
  "type": "Feature",
  "properties": {
    "gn:admin1_code":"4.0",
    "gn:asciiname":"Lfardi",
    "gn:country_code":"MA",
    "gn:dem":86,
    "gn:feature_class":"P",
    "gn:feature_code":"PPL",
    "gn:name":"Lfardi",
    "gn:population":0,
    "gn:timezone":"Africa/Casablanca",
    "iso:country":"MA",
    "wof:name":"Lfardi",
    "wof:placetype":"locality"
},
  "geometry": {"coordinates":[-6.98218,33.84723],"type":"Point"}
}