{
  "type": "Feature",
  "properties": {
    "gn:admin1_code":"6.0",
    "gn:asciiname":"Oulad Sidi Tahar",
    "gn:country_code":"MA",
    "gn:dem":143,
    "gn:feature_class":"P",
    "gn:feature_code":"PPL",
    "gn:name":"Oulad Sidi Tahar",
    "gn:population":0,
    "gn:timezone":"Africa/Casablanca",
    "iso:country":"MA",
    "wof:name":"Oulad Sidi Tahar",
    "wof:placetype":"locality"
},
  "geometry": {"coordinates":[-8.19654,32.96735],"type":"Point"}
}