{
  "type": "Feature",
  "properties": {
    "gn:admin1_code":"7.0",
    "gn:asciiname":"Douar Zaouiat Sidi Ahmed Ben Mbarek",
    "gn:country_code":"MA",
    "gn:dem":438,
    "gn:feature_class":"P",
    "gn:feature_code":"PPL",
    "gn:name":"Douar Zaouiat Sidi Ahmed Ben Mbarek",
    "gn:population":0,
    "gn:timezone":"Africa/Casablanca",
    "iso:country":"MA",
    "wof:name":"Douar Zaouiat Sidi Ahmed Ben Mbarek",
    "wof:placetype":"locality"
},
  "geometry": {"coordinates":[-8.94984,32.09976],"type":"Point"}
}