{
  "type": "Feature",
  "properties": {
    "gn:admin1_code":"7.0",
    "gn:asciiname":"Achibane",
    "gn:country_code":"MA",
    "gn:dem":571,
    "gn:feature_class":"P",
    "gn:feature_code":"PPL",
    "gn:name":"Achibane",
    "gn:population":0,
    "gn:timezone":"Africa/Casablanca",
    "iso:country":"MA",
    "wof:name":"Achibane",
    "wof:placetype":"locality"
},
  "geometry": {"coordinates":[-9.60455,30.98785],"type":"Point"}
}