{
  "type": "Feature",
  "properties": {
    "gn:country":"MA",
    "gn:fcode":"ADM3",
    "gn:pop":10708,
    "iso:country":"MA",
    "name:ara_x_preferred":[
        "\u0628\u0646\u064a \u0641\u063a\u0644\u0648\u0645"
    ],
    "name:ara_x_variant":[
        "\u0631\u0627\u0633 \u0627\u0644\u0642\u0635\u0631"
    ],
    "name:cat_x_preferred":[
        "Ras Laksar"
    ],
    "name:ceb_x_preferred":[
        "Ras Laksar"
    ],
    "name:eng_x_preferred":[
        "Ras Laksar"
    ],
    "name:fra_x_preferred":[
        "Ras Laksar"
    ],
    "name:fra_x_variant":[
        "Ras Laksar (CR)",
        "Ras Laksar (Commune Rurale)"
    ],
    "name:ita_x_preferred":[
        "Ras Laksar"
    ],
    "name:swe_x_preferred":[
        "Ras Laksar"
    ],
    "qs:name":"Ras Laksar",
    "qs:photos_9r":0,
    "qs:photos_sr":0,
    "qs:pop_sr":"6",
    "wd:wordcount":99,
    "wof:name":"Ras Laksar",
    "wof:placetype":"localadmin",
    "wof:population":10708
},
  "geometry": {"coordinates":[-3.81689,33.94256],"type":"Point"}
}