{
  "type": "Feature",
  "properties": {
    "gn:admin1_code":"9.0",
    "gn:asciiname":"Adouwar",
    "gn:country_code":"MA",
    "gn:dem":491,
    "gn:feature_class":"P",
    "gn:feature_code":"PPL",
    "gn:name":"Adouwar",
    "gn:population":0,
    "gn:timezone":"Africa/Casablanca",
    "iso:country":"MA",
    "wof:name":"Adouwar",
    "wof:placetype":"locality"
},
  "geometry": {"coordinates":[-8.43613,30.62026],"type":"Point"}
}