{
  "type": "Feature",
  "properties": {
    "gn:admin1_code":"4.0",
    "gn:asciiname":"Zouayed",
    "gn:country_code":"MA",
    "gn:dem":12,
    "gn:feature_class":"P",
    "gn:feature_code":"PPL",
    "gn:name":"Zouayed",
    "gn:population":0,
    "gn:timezone":"Africa/Casablanca",
    "iso:country":"MA",
    "wof:name":"Zouayed",
    "wof:placetype":"locality"
},
  "geometry": {"coordinates":[-6.09844,34.61495],"type":"Point"}
}