{
  "type": "Feature",
  "properties": {
    "gn:admin1_code":"5.0",
    "gn:asciiname":"Oulad S'id",
    "gn:country_code":"MA",
    "gn:dem":440,
    "gn:feature_class":"P",
    "gn:feature_code":"PPL",
    "gn:name":"Oulad S\u2019id",
    "gn:population":0,
    "gn:timezone":"Africa/Casablanca",
    "iso:country":"MA",
    "wof:name":"Oulad S'id",
    "wof:placetype":"locality"
},
  "geometry": {"coordinates":[-6.58658,32.46355],"type":"Point"}
}