{
  "type": "Feature",
  "properties": {
    "gn:admin1_code":"04",
    "gn:asciiname":"Douar Laayayda",
    "gn:country_code":"MA",
    "gn:dem":177,
    "gn:feature_class":"P",
    "gn:feature_code":"PPL",
    "gn:name":"Douar Laayayda",
    "gn:population":0,
    "gn:timezone":"Africa/Casablanca",
    "iso:country":"MA",
    "name:und_x_variant":[
        "Laa\u2019ya\u00efda"
    ],
    "wof:name":"Douar Laayayda",
    "wof:placetype":"locality"
},
  "geometry": {"coordinates":[-5.95596,34.89111],"type":"Point"}
}