{
  "type": "Feature",
  "properties": {
    "gn:admin1_code":"9.0",
    "gn:asciiname":"Tihabuarinel",
    "gn:country_code":"MA",
    "gn:dem":32,
    "gn:feature_class":"P",
    "gn:feature_code":"PPL",
    "gn:name":"Tihabuarinel",
    "gn:population":0,
    "gn:timezone":"Africa/Casablanca",
    "iso:country":"MA",
    "wof:name":"Tihabuarinel",
    "wof:placetype":"locality"
},
  "geometry": {"coordinates":[-9.66668,30.49593],"type":"Point"}
}