{
  "type": "Feature",
  "properties": {
    "gn:admin1_code":"05",
    "gn:asciiname":"Azib Tissiliane",
    "gn:country_code":"MA",
    "gn:dem":1884,
    "gn:feature_class":"P",
    "gn:feature_code":"PPL",
    "gn:name":"Azib Tissiliane",
    "gn:population":0,
    "gn:timezone":"Africa/Casablanca",
    "iso:country":"MA",
    "wof:name":"Azib Tissiliane",
    "wof:placetype":"locality"
},
  "geometry": {"coordinates":[-7.04962,31.58552],"type":"Point"}
}