{
  "type": "Feature",
  "properties": {
    "gn:admin1_code":"5.0",
    "gn:asciiname":"Azlag",
    "gn:country_code":"MA",
    "gn:dem":858,
    "gn:feature_class":"P",
    "gn:feature_code":"PPL",
    "gn:name":"Azlag",
    "gn:population":0,
    "gn:timezone":"Africa/Casablanca",
    "iso:country":"MA",
    "wof:name":"Azlag",
    "wof:placetype":"locality"
},
  "geometry": {"coordinates":[-7.01021,31.77271],"type":"Point"}
}