{
  "type": "Feature",
  "properties": {
    "gn:admin1_code":"04",
    "gn:asciiname":"Dar Caid Ibrahim",
    "gn:country_code":"MA",
    "gn:dem":71,
    "gn:feature_class":"P",
    "gn:feature_code":"PPL",
    "gn:name":"Dar Ca\u00efd Ibrahim",
    "gn:population":0,
    "gn:timezone":"Africa/Casablanca",
    "iso:country":"MA",
    "wof:name":"Dar Caid Ibrahim",
    "wof:placetype":"locality"
},
  "geometry": {"coordinates":[-6.61,33.96],"type":"Point"}
}