{
  "type": "Feature",
  "properties": {
    "gn:admin1_code":"10.0",
    "gn:asciiname":"Tiguemmou",
    "gn:country_code":"MA",
    "gn:dem":275,
    "gn:feature_class":"P",
    "gn:feature_code":"PPL",
    "gn:name":"Tiguemmou",
    "gn:population":0,
    "gn:timezone":"Africa/Casablanca",
    "iso:country":"MA",
    "wof:name":"Tiguemmou",
    "wof:placetype":"locality"
},
  "geometry": {"coordinates":[-10.00215,29.52011],"type":"Point"}
}