{
  "type": "Feature",
  "properties": {
    "gn:admin1_code":"3.0",
    "gn:asciiname":"Dar Ait El Mahjoub",
    "gn:country_code":"MA",
    "gn:dem":634,
    "gn:feature_class":"P",
    "gn:feature_code":"PPL",
    "gn:name":"Dar Ait El Mahjoub",
    "gn:population":0,
    "gn:timezone":"Africa/Casablanca",
    "iso:country":"MA",
    "wof:name":"Dar Ait El Mahjoub",
    "wof:placetype":"locality"
},
  "geometry": {"coordinates":[-4.71539,33.9367],"type":"Point"}
}