{
  "type": "Feature",
  "properties": {
    "gn:admin1_code":"7.0",
    "gn:asciiname":"Ait Bouzid",
    "gn:country_code":"MA",
    "gn:dem":1275,
    "gn:feature_class":"P",
    "gn:feature_code":"PPL",
    "gn:name":"A\u00eft Bouzid",
    "gn:population":0,
    "gn:timezone":"Africa/Casablanca",
    "iso:country":"MA",
    "wof:name":"Ait Bouzid",
    "wof:placetype":"locality"
},
  "geometry": {"coordinates":[-7.29874,31.55787],"type":"Point"}
}