{
  "type": "Feature",
  "properties": {
    "gn:admin1_code":"07",
    "gn:asciiname":"Srairi",
    "gn:country_code":"MA",
    "gn:dem":572,
    "gn:feature_class":"P",
    "gn:feature_code":"PPL",
    "gn:name":"Sra\u00efri",
    "gn:population":0,
    "gn:timezone":"Africa/Casablanca",
    "iso:country":"MA",
    "name:und_x_variant":[
        "Douar Sra\u00efri",
        "Sra\u00efri"
    ],
    "wof:name":"Srairi",
    "wof:placetype":"locality"
},
  "geometry": {"coordinates":[-7.87803,31.52482],"type":"Point"}
}