{
  "type": "Feature",
  "properties": {
    "gn:admin1_code":"09",
    "gn:asciiname":"Ait Mrane",
    "gn:country_code":"MA",
    "gn:dem":1053,
    "gn:feature_class":"P",
    "gn:feature_code":"PPL",
    "gn:name":"A\u00eft Mrane",
    "gn:population":0,
    "gn:timezone":"Africa/Casablanca",
    "iso:country":"MA",
    "name:und_x_variant":[
        "Agouni",
        "Agounsi",
        "A\u00eft Mrane"
    ],
    "wof:name":"Ait Mrane",
    "wof:placetype":"locality"
},
  "geometry": {"coordinates":[-9.27777,29.65152],"type":"Point"}
}