{
  "type": "Feature",
  "properties": {
    "gn:admin1_code":"6.0",
    "gn:asciiname":"Douar Ben Raada Oulad Ghanem",
    "gn:country_code":"MA",
    "gn:dem":182,
    "gn:feature_class":"P",
    "gn:feature_code":"PPL",
    "gn:name":"Douar Ben Raada Oulad Ghanem",
    "gn:population":0,
    "gn:timezone":"Africa/Casablanca",
    "iso:country":"MA",
    "wof:name":"Douar Ben Raada Oulad Ghanem",
    "wof:placetype":"locality"
},
  "geometry": {"coordinates":[-8.60067,32.59785],"type":"Point"}
}