{
  "type": "Feature",
  "properties": {
    "gn:admin1_code":"09",
    "gn:asciiname":"Sidi Mohand Ou Mbrarek",
    "gn:country_code":"MA",
    "gn:dem":1605,
    "gn:feature_class":"P",
    "gn:feature_code":"PPL",
    "gn:name":"Sidi Mohand Ou Mbrarek",
    "gn:population":0,
    "gn:timezone":"Africa/Casablanca",
    "iso:country":"MA",
    "name:und_x_variant":[
        "Imi n\u2019Ougni",
        "Sidi Mohand Ou Embark",
        "Sidi Mohand Ou Mbrarek"
    ],
    "wof:name":"Sidi Mohand Ou Mbrarek",
    "wof:placetype":"locality"
},
  "geometry": {"coordinates":[-7.7345,30.47076],"type":"Point"}
}