{
  "type": "Feature",
  "properties": {
    "gn:admin1_code":"4.0",
    "gn:asciiname":"Ait Lahssen",
    "gn:country_code":"MA",
    "gn:dem":711,
    "gn:feature_class":"P",
    "gn:feature_code":"PPL",
    "gn:name":"Ait Lahssen",
    "gn:population":0,
    "gn:timezone":"Africa/Casablanca",
    "iso:country":"MA",
    "wof:name":"Ait Lahssen",
    "wof:placetype":"locality"
},
  "geometry": {"coordinates":[-5.86228,33.67089],"type":"Point"}
}