{
  "type": "Feature",
  "properties": {
    "gn:admin1_code":"03",
    "gn:asciiname":"Douar Bou Biyyad",
    "gn:country_code":"MA",
    "gn:dem":447,
    "gn:feature_class":"P",
    "gn:feature_code":"PPL",
    "gn:name":"Douar Bou Biyyad",
    "gn:population":0,
    "gn:timezone":"Africa/Casablanca",
    "iso:country":"MA",
    "name:und_x_variant":[
        "Douar Boubiad",
        "Boubiad",
        "Douar Bou Biyyad"
    ],
    "wof:name":"Douar Bou Biyyad",
    "wof:placetype":"locality"
},
  "geometry": {"coordinates":[-4.87648,34.46227],"type":"Point"}
}