{
  "type": "Feature",
  "properties": {
    "gn:admin1_code":"7.0",
    "gn:asciiname":"Ayt Ben Barsa",
    "gn:country_code":"MA",
    "gn:dem":638,
    "gn:feature_class":"P",
    "gn:feature_code":"PPL",
    "gn:name":"Ayt Ben Barsa",
    "gn:population":0,
    "gn:timezone":"Africa/Casablanca",
    "iso:country":"MA",
    "wof:name":"Ayt Ben Barsa",
    "wof:placetype":"locality"
},
  "geometry": {"coordinates":[-7.10393,31.87136],"type":"Point"}
}