{
  "type": "Feature",
  "properties": {
    "gn:admin1_code":"7.0",
    "gn:asciiname":"Izourzene",
    "gn:country_code":"MA",
    "gn:dem":752,
    "gn:feature_class":"P",
    "gn:feature_code":"PPL",
    "gn:name":"Izourzene",
    "gn:population":0,
    "gn:timezone":"Africa/Casablanca",
    "iso:country":"MA",
    "wof:name":"Izourzene",
    "wof:placetype":"locality"
},
  "geometry": {"coordinates":[-8.94966,31.23534],"type":"Point"}
}