{
  "type": "Feature",
  "properties": {
    "gn:admin1_code":"5.0",
    "gn:asciiname":"Oulad Hassine",
    "gn:country_code":"MA",
    "gn:dem":732,
    "gn:feature_class":"P",
    "gn:feature_code":"PPL",
    "gn:name":"Oulad Hassine",
    "gn:population":0,
    "gn:timezone":"Africa/Casablanca",
    "iso:country":"MA",
    "wof:name":"Oulad Hassine",
    "wof:placetype":"locality"
},
  "geometry": {"coordinates":[-6.34184,32.81188],"type":"Point"}
}