{
  "type": "Feature",
  "properties": {
    "gn:admin1_code":"04",
    "gn:asciiname":"Douar Oulad Tourjer",
    "gn:country_code":"MA",
    "gn:dem":30,
    "gn:feature_class":"P",
    "gn:feature_code":"PPL",
    "gn:name":"Douar Oulad Tourjer",
    "gn:population":0,
    "gn:timezone":"Africa/Casablanca",
    "iso:country":"MA",
    "name:und_x_variant":[
        "Oulad Touiet",
        "Ouled Tonaijar",
        "Oulad Touijer",
        "Douar Oulad Touijer",
        "Douar Oulad Tourjer"
    ],
    "wof:name":"Douar Oulad Tourjer",
    "wof:placetype":"locality"
},
  "geometry": {"coordinates":[-5.82078,34.50285],"type":"Point"}
}