{
  "type": "Feature",
  "properties": {
    "gn:admin1_code":"01",
    "gn:asciiname":"El Haoud",
    "gn:country_code":"MA",
    "gn:dem":1111,
    "gn:feature_class":"P",
    "gn:feature_code":"PPL",
    "gn:name":"El Haoud",
    "gn:population":0,
    "gn:timezone":"Africa/Casablanca",
    "iso:country":"MA",
    "wof:name":"El Haoud",
    "wof:placetype":"locality"
},
  "geometry": {"coordinates":[-4.68,34.78],"type":"Point"}
}