{
  "type": "Feature",
  "properties": {
    "iso:country":"MA",
    "qs:gn_pop":0,
    "qs:name":"Ait Sidi M'hamed Ou Lahcen",
    "qs:name_adm0":"\u0627\u0644\u0645\u063a\u0631\u0628",
    "qs:name_adm1":"\u0645\u0643\u0646\u0627\u0633 \u0640 \u062a\u0627\u0641\u064a\u0644\u0627\u0644\u062a",
    "qs:photos":29,
    "qs:photos_1k":6,
    "qs:photos_9k":1,
    "qs:photos_9r":2,
    "qs:photos_all":29,
    "qs:photos_sr":2,
    "qs:placetype":"Town",
    "qs:pop_sr":"0",
    "qs:woe_adm0":23424893,
    "wof:name":"Ait Sidi M'hamed Ou Lahcen",
    "wof:placetype":"locality"
},
  "geometry": {"coordinates":[-4.95278,31.692909],"type":"Point"}
}