{
  "type": "Feature",
  "properties": {
    "gn:admin1_code":"06",
    "gn:asciiname":"Tnine Lgharbia",
    "gn:country_code":"MA",
    "gn:dem":139,
    "gn:feature_class":"P",
    "gn:feature_code":"PPL",
    "gn:name":"Tnine Lgharbia",
    "gn:population":0,
    "gn:timezone":"Africa/Casablanca",
    "iso:country":"MA",
    "name:und_x_variant":[
        "Souk et Tnine Gharbia",
        "Et Tnine Rharbia",
        "Tnine Rharb\u00e2a",
        "Et Tnine Gharbia",
        "Et Tnine el Rharbia",
        "Tnine Lgharbia"
    ],
    "wof:name":"Tnine Lgharbia",
    "wof:placetype":"locality"
},
  "geometry": {"coordinates":[-8.85464,32.57049],"type":"Point"}
}