{
  "type": "Feature",
  "properties": {
    "gn:admin1_code":"9.0",
    "gn:asciiname":"Ifisk",
    "gn:country_code":"MA",
    "gn:dem":953,
    "gn:feature_class":"P",
    "gn:feature_code":"PPL",
    "gn:name":"Ifisk",
    "gn:population":0,
    "gn:timezone":"Africa/Casablanca",
    "iso:country":"MA",
    "wof:name":"Ifisk",
    "wof:placetype":"locality"
},
  "geometry": {"coordinates":[-8.66179,30.32298],"type":"Point"}
}