{
  "type": "Feature",
  "properties": {
    "gn:admin1_code":"7.0",
    "gn:asciiname":"Dar el Baida",
    "gn:country_code":"MA",
    "gn:dem":1011,
    "gn:feature_class":"P",
    "gn:feature_code":"PPL",
    "gn:name":"Dar el Ba\u00efda",
    "gn:population":0,
    "gn:timezone":"Africa/Casablanca",
    "iso:country":"MA",
    "wof:name":"Dar el Baida",
    "wof:placetype":"locality"
},
  "geometry": {"coordinates":[-7.32706,31.64603],"type":"Point"}
}