{
  "type": "Feature",
  "properties": {
    "gn:admin1_code":"6.0",
    "gn:asciiname":"Douar Ghanem El Fawala",
    "gn:country_code":"MA",
    "gn:dem":137,
    "gn:feature_class":"P",
    "gn:feature_code":"PPL",
    "gn:name":"Douar Ghanem El Fawala",
    "gn:population":0,
    "gn:timezone":"Africa/Casablanca",
    "iso:country":"MA",
    "wof:name":"Douar Ghanem El Fawala",
    "wof:placetype":"locality"
},
  "geometry": {"coordinates":[-8.66482,32.75821],"type":"Point"}
}