{
  "type": "Feature",
  "properties": {
    "gn:admin1_code":"5.0",
    "gn:asciiname":"Tighouwla",
    "gn:country_code":"MA",
    "gn:dem":1932,
    "gn:feature_class":"P",
    "gn:feature_code":"PPL",
    "gn:name":"Tighouwla",
    "gn:population":0,
    "gn:timezone":"Africa/Casablanca",
    "iso:country":"MA",
    "wof:name":"Tighouwla",
    "wof:placetype":"locality"
},
  "geometry": {"coordinates":[-6.5099,31.79798],"type":"Point"}
}