{
  "type": "Feature",
  "properties": {
    "gn:admin1_code":"7.0",
    "gn:asciiname":"Oulad Sidi Bel'id",
    "gn:country_code":"MA",
    "gn:dem":65,
    "gn:feature_class":"P",
    "gn:feature_code":"PPL",
    "gn:name":"Oulad Sidi Bel\u2019id",
    "gn:population":0,
    "gn:timezone":"Africa/Casablanca",
    "iso:country":"MA",
    "wof:name":"Oulad Sidi Bel'id",
    "wof:placetype":"locality"
},
  "geometry": {"coordinates":[-9.30295,32.09867],"type":"Point"}
}