{
  "type": "Feature",
  "properties": {
    "gn:admin1_code":"03",
    "gn:asciiname":"Kaouane",
    "gn:country_code":"MA",
    "gn:dem":1141,
    "gn:feature_class":"P",
    "gn:feature_code":"PPL",
    "gn:name":"Kaouane",
    "gn:population":0,
    "gn:timezone":"Africa/Casablanca",
    "iso:country":"MA",
    "wof:name":"Kaouane",
    "wof:placetype":"locality"
},
  "geometry": {"coordinates":[-4.24514,33.96351],"type":"Point"}
}