{
  "type": "Feature",
  "properties": {
    "gn:admin1_code":"5.0",
    "gn:asciiname":"Ait Ouzdoud",
    "gn:country_code":"MA",
    "gn:dem":1392,
    "gn:feature_class":"P",
    "gn:feature_code":"PPL",
    "gn:name":"A\u00eft Ouzdoud",
    "gn:population":0,
    "gn:timezone":"Africa/Casablanca",
    "iso:country":"MA",
    "wof:name":"Ait Ouzdoud",
    "wof:placetype":"locality"
},
  "geometry": {"coordinates":[-6.73014,31.70149],"type":"Point"}
}