{
  "type": "Feature",
  "properties": {
    "gn:admin1_code":"7.0",
    "gn:asciiname":"Ighi",
    "gn:country_code":"MA",
    "gn:dem":893,
    "gn:feature_class":"P",
    "gn:feature_code":"PPL",
    "gn:name":"Ighi",
    "gn:population":0,
    "gn:timezone":"Africa/Casablanca",
    "iso:country":"MA",
    "wof:name":"Ighi",
    "wof:placetype":"locality"
},
  "geometry": {"coordinates":[-7.68184,31.51385],"type":"Point"}
}