{
  "type": "Feature",
  "properties": {
    "gn:admin1_code":"05",
    "gn:admin2_code":"81.0",
    "gn:admin3_code":"1208105192.0",
    "gn:asciiname":"Taounza",
    "gn:country_code":"MA",
    "gn:dem":681,
    "gn:feature_class":"P",
    "gn:feature_code":"PPLA3",
    "gn:name":"Taounza",
    "gn:population":0,
    "gn:timezone":"Africa/Casablanca",
    "iso:country":"MA",
    "name:ara_x_preferred":[
        "\u062a\u0627\u0648\u0646\u0632\u0627"
    ],
    "name:cat_x_preferred":[
        "Taounza"
    ],
    "name:ceb_x_preferred":[
        "Taounza"
    ],
    "name:ita_x_preferred":[
        "Taounza"
    ],
    "name:swe_x_preferred":[
        "Taounza"
    ],
    "wof:name":"Taounza",
    "wof:placetype":"locality"
},
  "geometry": {"coordinates":[-6.60607,32.09368],"type":"Point"}
}