{
  "type": "Feature",
  "properties": {
    "gn:admin1_code":"06",
    "gn:asciiname":"Zaouiet El Kettani",
    "gn:country_code":"MA",
    "gn:dem":59,
    "gn:feature_class":"P",
    "gn:feature_code":"PPL",
    "gn:name":"Zaouiet El Kettani",
    "gn:population":0,
    "gn:timezone":"Africa/Casablanca",
    "iso:country":"MA",
    "name:und_x_variant":[
        "Zaouia el Kettani",
        "Zaouiat el Ketani",
        "Zaouiet El Kettani"
    ],
    "wof:name":"Zaouiet El Kettani",
    "wof:placetype":"locality"
},
  "geometry": {"coordinates":[-8.54868,33.12989],"type":"Point"}
}