{
  "type": "Feature",
  "properties": {
    "gn:admin1_code":"09",
    "gn:asciiname":"Imoula",
    "gn:country_code":"MA",
    "gn:dem":1077,
    "gn:feature_class":"P",
    "gn:feature_code":"PPL",
    "gn:name":"Imoula",
    "gn:population":0,
    "gn:timezone":"Africa/Casablanca",
    "iso:country":"MA",
    "wof:name":"Imoula",
    "wof:placetype":"locality"
},
  "geometry": {"coordinates":[-9.39437,30.64627],"type":"Point"}
}