{
  "type": "Feature",
  "properties": {
    "gn:admin1_code":"4.0",
    "gn:asciiname":"Douar Ait Ben Qassou",
    "gn:country_code":"MA",
    "gn:dem":150,
    "gn:feature_class":"P",
    "gn:feature_code":"PPL",
    "gn:name":"Douar Ait Ben Qassou",
    "gn:population":0,
    "gn:timezone":"Africa/Casablanca",
    "iso:country":"MA",
    "wof:name":"Douar Ait Ben Qassou",
    "wof:placetype":"locality"
},
  "geometry": {"coordinates":[-6.50428,34.05465],"type":"Point"}
}