{
  "type": "Feature",
  "properties": {
    "gn:admin1_code":"7.0",
    "gn:asciiname":"Douar Erremitiya",
    "gn:country_code":"MA",
    "gn:dem":493,
    "gn:feature_class":"P",
    "gn:feature_code":"PPL",
    "gn:name":"Douar Erremitiya",
    "gn:population":0,
    "gn:timezone":"Africa/Casablanca",
    "iso:country":"MA",
    "wof:name":"Douar Erremitiya",
    "wof:placetype":"locality"
},
  "geometry": {"coordinates":[-8.33626,31.97736],"type":"Point"}
}