{
  "type": "Feature",
  "properties": {
    "gn:country":"MA",
    "gn:fcode":"ADM3",
    "gn:pop":16065,
    "iso:country":"MA",
    "name:ara_x_preferred":[
        "\u0627\u0644\u0633\u0639\u064a\u062f\u064a\u0629 (\u0627\u0644\u0628\u0644\u062f\u064a\u0629)"
    ],
    "name:ara_x_variant":[
        "\u0632\u0643\u0632\u0644"
    ],
    "name:cat_x_preferred":[
        "Zegzel"
    ],
    "name:ceb_x_preferred":[
        "Zegzel"
    ],
    "name:fra_x_preferred":[
        "Zegzel"
    ],
    "name:fra_x_variant":[
        "Zegzel (CR)",
        "Zegzel (Commune Rurale)"
    ],
    "name:ita_x_preferred":[
        "Zegzel"
    ],
    "name:nld_x_preferred":[
        "Zegzel"
    ],
    "name:swe_x_preferred":[
        "Zegzel"
    ],
    "qs:name":"Zegzel",
    "qs:photos_9r":0,
    "qs:photos_sr":0,
    "qs:pop_sr":"6",
    "wof:name":"Zegzel",
    "wof:placetype":"localadmin",
    "wof:population":16065
},
  "geometry": {"coordinates":[-2.35921,34.91324],"type":"Point"}
}