{
  "type": "Feature",
  "properties": {
    "gn:admin1_code":"7.0",
    "gn:asciiname":"Tighza",
    "gn:country_code":"MA",
    "gn:dem":422,
    "gn:feature_class":"P",
    "gn:feature_code":"PPL",
    "gn:name":"Tighza",
    "gn:population":0,
    "gn:timezone":"Africa/Casablanca",
    "iso:country":"MA",
    "name:cat_x_preferred":[
        "Tighza"
    ],
    "name:ceb_x_preferred":[
        "Tighza"
    ],
    "name:fra_x_preferred":[
        "Tighza"
    ],
    "name:swe_x_preferred":[
        "Tighza"
    ],
    "wof:name":"Tighza",
    "wof:placetype":"locality"
},
  "geometry": {"coordinates":[-9.57216,31.15315],"type":"Point"}
}