{
  "type": "Feature",
  "properties": {
    "gn:admin1_code":"04",
    "gn:asciiname":"Douar Essettiyine",
    "gn:country_code":"MA",
    "gn:dem":58,
    "gn:feature_class":"P",
    "gn:feature_code":"PPL",
    "gn:name":"Douar Essettiyine",
    "gn:population":0,
    "gn:timezone":"Africa/Casablanca",
    "iso:country":"MA",
    "name:und_x_variant":[
        "Sate\u00efne",
        "Douar es Setine",
        "Es Setine",
        "Douar Essettiyine"
    ],
    "wof:name":"Douar Essettiyine",
    "wof:placetype":"locality"
},
  "geometry": {"coordinates":[-5.63599,34.57006],"type":"Point"}
}