{
  "type": "Feature",
  "properties": {
    "gn:admin1_code":"8.0",
    "gn:asciiname":"Imi-n-Tiguiza",
    "gn:country_code":"MA",
    "gn:dem":1666,
    "gn:feature_class":"P",
    "gn:feature_code":"PPL",
    "gn:name":"Imi-n-Tiguiza",
    "gn:population":0,
    "gn:timezone":"Africa/Casablanca",
    "iso:country":"MA",
    "wof:name":"Imi-n-Tiguiza",
    "wof:placetype":"locality"
},
  "geometry": {"coordinates":[-6.28999,30.87258],"type":"Point"}
}