{
  "type": "Feature",
  "properties": {
    "gn:admin1_code":"9.0",
    "gn:asciiname":"Douar Issil Oufella",
    "gn:country_code":"MA",
    "gn:dem":335,
    "gn:feature_class":"P",
    "gn:feature_code":"PPL",
    "gn:name":"Douar Issil Oufella",
    "gn:population":0,
    "gn:timezone":"Africa/Casablanca",
    "iso:country":"MA",
    "wof:name":"Douar Issil Oufella",
    "wof:placetype":"locality"
},
  "geometry": {"coordinates":[-9.82994,29.57382],"type":"Point"}
}