{
  "type": "Feature",
  "properties": {
    "gn:admin1_code":"09",
    "gn:asciiname":"Taghzout",
    "gn:country_code":"MA",
    "gn:dem":944,
    "gn:feature_class":"P",
    "gn:feature_code":"PPL",
    "gn:name":"Taghzout",
    "gn:population":0,
    "gn:timezone":"Africa/Casablanca",
    "iso:country":"MA",
    "name:ara_x_preferred":[
        "\u062a\u0627\u063a\u0632\u0648\u062a"
    ],
    "name:ceb_x_preferred":[
        "Taghzout"
    ],
    "name:fra_x_preferred":[
        "Taghzout"
    ],
    "name:ita_x_preferred":[
        "Taghzout"
    ],
    "name:msa_x_preferred":[
        "Taghzout"
    ],
    "name:ron_x_preferred":[
        "Taghzout"
    ],
    "name:swe_x_preferred":[
        "Taghzout"
    ],
    "name:und_x_variant":[
        "Tarhzoute",
        "Tarhzout"
    ],
    "wof:name":"Taghzout",
    "wof:placetype":"locality"
},
  "geometry": {"coordinates":[-8.00631,30.52683],"type":"Point"}
}