{
  "type": "Feature",
  "properties": {
    "gn:admin1_code":"08",
    "gn:asciiname":"Algouz",
    "gn:country_code":"MA",
    "gn:dem":1625,
    "gn:feature_class":"P",
    "gn:feature_code":"PPL",
    "gn:name":"Algouz",
    "gn:population":0,
    "gn:timezone":"Africa/Casablanca",
    "iso:country":"MA",
    "name:und_x_variant":[
        "Alougouz",
        "Algouz"
    ],
    "wof:name":"Algouz",
    "wof:placetype":"locality"
},
  "geometry": {"coordinates":[-7.45116,30.35696],"type":"Point"}
}