{
  "type": "Feature",
  "properties": {
    "gn:admin1_code":"6.0",
    "gn:asciiname":"Ez-zemamra",
    "gn:country_code":"MA",
    "gn:dem":405,
    "gn:feature_class":"P",
    "gn:feature_code":"PPL",
    "gn:name":"Ez-zemamra",
    "gn:population":0,
    "gn:timezone":"Africa/Casablanca",
    "iso:country":"MA",
    "wof:name":"Ez-zemamra",
    "wof:placetype":"locality"
},
  "geometry": {"coordinates":[-7.69232,32.87372],"type":"Point"}
}