{
  "type": "Feature",
  "properties": {
    "gn:admin1_code":"09",
    "gn:asciiname":"Ifrhel",
    "gn:country_code":"MA",
    "gn:dem":278,
    "gn:feature_class":"P",
    "gn:feature_code":"PPL",
    "gn:name":"Ifrhel",
    "gn:population":0,
    "gn:timezone":"Africa/Casablanca",
    "iso:country":"MA",
    "name:und_x_variant":[
        "Ifghale",
        "Ifrhel"
    ],
    "wof:name":"Ifrhel",
    "wof:placetype":"locality"
},
  "geometry": {"coordinates":[-9.2198,30.12768],"type":"Point"}
}