{
  "type": "Feature",
  "properties": {
    "gn:admin1_code":"03",
    "gn:asciiname":"Taferdoust",
    "gn:country_code":"MA",
    "gn:dem":1212,
    "gn:feature_class":"P",
    "gn:feature_code":"PPL",
    "gn:name":"Taferdoust",
    "gn:population":0,
    "gn:timezone":"Africa/Casablanca",
    "iso:country":"MA",
    "name:und_x_variant":[
        "Kasba Taferdoust",
        "Taferdoust"
    ],
    "wof:name":"Taferdoust",
    "wof:placetype":"locality"
},
  "geometry": {"coordinates":[-4.63945,33.47528],"type":"Point"}
}