{
  "type": "Feature",
  "properties": {
    "gn:admin1_code":"08",
    "gn:asciiname":"Tamellalt",
    "gn:country_code":"MA",
    "gn:dem":1607,
    "gn:feature_class":"P",
    "gn:feature_code":"PPL",
    "gn:name":"Tamellalt",
    "gn:population":0,
    "gn:timezone":"Africa/Casablanca",
    "iso:country":"MA",
    "name:und_x_variant":[
        "Tamlalt",
        "Tamellalt"
    ],
    "wof:name":"Tamellalt",
    "wof:placetype":"locality"
},
  "geometry": {"coordinates":[-5.9818,31.44454],"type":"Point"}
}