{
  "type": "Feature",
  "properties": {
    "gn:admin1_code":"7.0",
    "gn:asciiname":"Dar Kalami",
    "gn:country_code":"MA",
    "gn:dem":377,
    "gn:feature_class":"P",
    "gn:feature_code":"PPL",
    "gn:name":"Dar Kalami",
    "gn:population":0,
    "gn:timezone":"Africa/Casablanca",
    "iso:country":"MA",
    "wof:name":"Dar Kalami",
    "wof:placetype":"locality"
},
  "geometry": {"coordinates":[-8.28225,32.36317],"type":"Point"}
}