{
  "type": "Feature",
  "properties": {
    "gn:admin1_code":"8.0",
    "gn:asciiname":"Tinegbite",
    "gn:country_code":"MA",
    "gn:dem":1037,
    "gn:feature_class":"P",
    "gn:feature_code":"PPL",
    "gn:name":"Tinegbite",
    "gn:population":0,
    "gn:timezone":"Africa/Casablanca",
    "iso:country":"MA",
    "wof:name":"Tinegbite",
    "wof:placetype":"neighbourhood"
},
  "geometry": {"coordinates":[-4.43462,31.91104],"type":"Point"}
}