{
  "type": "Feature",
  "properties": {
    "gn:admin1_code":"02",
    "gn:asciiname":"Israssiyine",
    "gn:country_code":"MA",
    "gn:dem":193,
    "gn:feature_class":"P",
    "gn:feature_code":"PPL",
    "gn:name":"Israssiyine",
    "gn:population":0,
    "gn:timezone":"Africa/Casablanca",
    "iso:country":"MA",
    "wof:name":"Israssiyine",
    "wof:placetype":"locality"
},
  "geometry": {"coordinates":[-3.75993,35.20334000000001],"type":"Point"}
}