{
  "type": "Feature",
  "properties": {
    "gn:admin1_code":"1.0",
    "gn:asciiname":"Douar Lfouarat",
    "gn:country_code":"MA",
    "gn:dem":392,
    "gn:feature_class":"P",
    "gn:feature_code":"PPL",
    "gn:name":"Douar Lfouarat",
    "gn:population":0,
    "gn:timezone":"Africa/Casablanca",
    "iso:country":"MA",
    "wof:name":"Douar Lfouarat",
    "wof:placetype":"locality"
},
  "geometry": {"coordinates":[-5.21118,34.66083],"type":"Point"}
}