{
  "type": "Feature",
  "properties": {
    "gn:admin1_code":"7.0",
    "gn:asciiname":"Azazin Fardine",
    "gn:country_code":"MA",
    "gn:dem":1316,
    "gn:feature_class":"P",
    "gn:feature_code":"PPL",
    "gn:name":"Azazin Fardine",
    "gn:population":0,
    "gn:timezone":"Africa/Casablanca",
    "iso:country":"MA",
    "wof:name":"Azazin Fardine",
    "wof:placetype":"locality"
},
  "geometry": {"coordinates":[-9.17684,31.01085],"type":"Point"}
}