{
  "type": "Feature",
  "properties": {
    "gn:admin1_code":"01",
    "gn:asciiname":"Dahriyine",
    "gn:country_code":"MA",
    "gn:dem":513,
    "gn:feature_class":"P",
    "gn:feature_code":"PPL",
    "gn:name":"Dahriyine",
    "gn:population":0,
    "gn:timezone":"Africa/Casablanca",
    "iso:country":"MA",
    "name:und_x_variant":[
        "Dahar"
    ],
    "wof:name":"Dahriyine",
    "wof:placetype":"locality"
},
  "geometry": {"coordinates":[-5.47602,35.42769000000001],"type":"Point"}
}