{
  "type": "Feature",
  "properties": {
    "gn:admin1_code":"07",
    "gn:asciiname":"Douar Bouanane",
    "gn:country_code":"MA",
    "gn:dem":459,
    "gn:feature_class":"P",
    "gn:feature_code":"PPL",
    "gn:name":"Douar Bouanane",
    "gn:population":0,
    "gn:timezone":"Africa/Casablanca",
    "iso:country":"MA",
    "name:und_x_variant":[
        "Douar Oulad bou Anan",
        "Douar Oulad Bou Anane",
        "Douar Bouanane"
    ],
    "wof:name":"Douar Bouanane",
    "wof:placetype":"locality"
},
  "geometry": {"coordinates":[-8.46501,32.20513],"type":"Point"}
}