{
  "type": "Feature",
  "properties": {
    "gn:admin1_code":"07",
    "gn:asciiname":"Hay El Hassani",
    "gn:country_code":"MA",
    "gn:dem":343,
    "gn:feature_class":"P",
    "gn:feature_code":"PPL",
    "gn:name":"Hay El Hassani",
    "gn:population":0,
    "gn:timezone":"Africa/Casablanca",
    "iso:country":"MA",
    "name:fra_x_preferred":[
        "Hay El Hassani"
    ],
    "name:und_x_variant":[
        "Dar Cheikh Hassane",
        "Che\u00efkh Bel Hassane"
    ],
    "wof:name":"Hay El Hassani",
    "wof:placetype":"neighbourhood"
},
  "geometry": {"coordinates":[-8.7343,31.55537],"type":"Point"}
}