{
  "type": "Feature",
  "properties": {
    "gn:admin1_code":"4.0",
    "gn:asciiname":"Douar Ait Mouha Ben Daoud",
    "gn:country_code":"MA",
    "gn:dem":293,
    "gn:feature_class":"P",
    "gn:feature_code":"PPL",
    "gn:name":"Douar Ait Mouha Ben Daoud",
    "gn:population":0,
    "gn:timezone":"Africa/Casablanca",
    "iso:country":"MA",
    "wof:name":"Douar Ait Mouha Ben Daoud",
    "wof:placetype":"locality"
},
  "geometry": {"coordinates":[-6.19595,33.6565],"type":"Point"}
}