{
  "type": "Feature",
  "properties": {
    "gn:admin1_code":"3.0",
    "gn:asciiname":"Cooperative Griasandi",
    "gn:country_code":"MA",
    "gn:dem":352,
    "gn:feature_class":"P",
    "gn:feature_code":"PPLF",
    "gn:name":"Coop\u00e9rative Griasandi",
    "gn:population":0,
    "gn:timezone":"Africa/Casablanca",
    "iso:country":"MA",
    "wof:name":"Cooperative Griasandi",
    "wof:placetype":"locality"
},
  "geometry": {"coordinates":[-5.58658,34.07399],"type":"Point"}
}