{
  "type": "Feature",
  "properties": {
    "gn:admin1_code":"4.0",
    "gn:asciiname":"Mharza",
    "gn:country_code":"MA",
    "gn:dem":269,
    "gn:feature_class":"P",
    "gn:feature_code":"PPLL",
    "gn:name":"Mharza",
    "gn:population":0,
    "gn:timezone":"Africa/Casablanca",
    "iso:country":"MA",
    "wof:name":"Mharza",
    "wof:placetype":"locality"
},
  "geometry": {"coordinates":[-6.44799,33.59564],"type":"Point"}
}