{
  "type": "Feature",
  "properties": {
    "gn:admin1_code":"09",
    "gn:asciiname":"Tizguiy",
    "gn:country_code":"MA",
    "gn:dem":1250,
    "gn:feature_class":"P",
    "gn:feature_code":"PPL",
    "gn:name":"Tizguiy",
    "gn:population":0,
    "gn:timezone":"Africa/Casablanca",
    "iso:country":"MA",
    "name:und_x_variant":[
        "Tizgui",
        "Tizguiy",
        "Ighir n Tizgui"
    ],
    "wof:name":"Tizguiy",
    "wof:placetype":"locality"
},
  "geometry": {"coordinates":[-8.32034,30.03997],"type":"Point"}
}