{
  "type": "Feature",
  "properties": {
    "gn:admin1_code":"07",
    "gn:asciiname":"Oulad Mbarek",
    "gn:country_code":"MA",
    "gn:dem":238,
    "gn:feature_class":"P",
    "gn:feature_code":"PPL",
    "gn:name":"Oulad Mbarek",
    "gn:population":0,
    "gn:timezone":"Africa/Casablanca",
    "iso:country":"MA",
    "name:und_x_variant":[
        "Sidi Mbarek",
        "Ouled m\u2019Bark",
        "Oulad Mbarek"
    ],
    "wof:name":"Oulad Mbarek",
    "wof:placetype":"locality"
},
  "geometry": {"coordinates":[-8.78598,31.85742],"type":"Point"}
}