{
  "type": "Feature",
  "properties": {
    "gn:admin1_code":"6.0",
    "gn:asciiname":"Douar Oulad El Haj Habib",
    "gn:country_code":"MA",
    "gn:dem":685,
    "gn:feature_class":"P",
    "gn:feature_code":"PPL",
    "gn:name":"Douar Oulad El Haj Habib",
    "gn:population":0,
    "gn:timezone":"Africa/Casablanca",
    "iso:country":"MA",
    "wof:name":"Douar Oulad El Haj Habib",
    "wof:placetype":"locality"
},
  "geometry": {"coordinates":[-7.09079,33.01371],"type":"Point"}
}