{
  "type": "Feature",
  "properties": {
    "gn:admin1_code":"06",
    "gn:asciiname":"Douar Ouled Kouri",
    "gn:country_code":"MA",
    "gn:dem":217,
    "gn:feature_class":"P",
    "gn:feature_code":"PPL",
    "gn:name":"Douar Ouled Kouri",
    "gn:population":0,
    "gn:timezone":"Africa/Casablanca",
    "iso:country":"MA",
    "wof:name":"Douar Ouled Kouri",
    "wof:placetype":"locality"
},
  "geometry": {"coordinates":[-8.33399,32.58452],"type":"Point"}
}