{
  "type": "Feature",
  "properties": {
    "gn:admin1_code":"7.0",
    "gn:asciiname":"Dar Ettalyane",
    "gn:country_code":"MA",
    "gn:dem":348,
    "gn:feature_class":"P",
    "gn:feature_code":"PPL",
    "gn:name":"Dar Ettalyane",
    "gn:population":0,
    "gn:timezone":"Africa/Casablanca",
    "iso:country":"MA",
    "wof:name":"Dar Ettalyane",
    "wof:placetype":"locality"
},
  "geometry": {"coordinates":[-9.71169,31.17917000000001],"type":"Point"}
}