{
  "type": "Feature",
  "properties": {
    "gn:admin1_code":"6.0",
    "gn:asciiname":"Dar Cheikh El Maataoui",
    "gn:country_code":"MA",
    "gn:dem":425,
    "gn:feature_class":"P",
    "gn:feature_code":"PPL",
    "gn:name":"Dar Cheikh El Maataoui",
    "gn:population":0,
    "gn:timezone":"Africa/Casablanca",
    "iso:country":"MA",
    "wof:name":"Dar Cheikh El Maataoui",
    "wof:placetype":"locality"
},
  "geometry": {"coordinates":[-7.16958,33.22169],"type":"Point"}
}