{
  "type": "Feature",
  "properties": {
    "gn:admin1_code":"1.0",
    "gn:asciiname":"Lkhandqiyine",
    "gn:country_code":"MA",
    "gn:dem":241,
    "gn:feature_class":"P",
    "gn:feature_code":"PPL",
    "gn:name":"Lkhandqiyine",
    "gn:population":0,
    "gn:timezone":"Africa/Casablanca",
    "iso:country":"MA",
    "wof:name":"Lkhandqiyine",
    "wof:placetype":"locality"
},
  "geometry": {"coordinates":[-5.54388,35.45366],"type":"Point"}
}