{
  "type": "Feature",
  "properties": {
    "gn:admin1_code":"08",
    "gn:asciiname":"Ayt 'Amer",
    "gn:country_code":"MA",
    "gn:dem":1238,
    "gn:feature_class":"P",
    "gn:feature_code":"PPL",
    "gn:name":"Ayt \u2019Amer",
    "gn:population":0,
    "gn:timezone":"Africa/Casablanca",
    "iso:country":"MA",
    "name:und_x_variant":[
        "A\u00eft Ameur",
        "A\u00eft Amar",
        "Ayt \u2019Amer"
    ],
    "wof:name":"Ayt 'Amer",
    "wof:placetype":"locality"
},
  "geometry": {"coordinates":[-4.37886,32.21155],"type":"Point"}
}