{
  "type": "Feature",
  "properties": {
    "gn:admin1_code":"01",
    "gn:asciiname":"Douar Oulad Lahsen",
    "gn:country_code":"MA",
    "gn:dem":117,
    "gn:feature_class":"P",
    "gn:feature_code":"PPL",
    "gn:name":"Douar Oulad Lahsen",
    "gn:population":0,
    "gn:timezone":"Africa/Casablanca",
    "iso:country":"MA",
    "name:und_x_variant":[
        "Oulad Lahsen"
    ],
    "wof:name":"Douar Oulad Lahsen",
    "wof:placetype":"locality"
},
  "geometry": {"coordinates":[-5.99626,35.31384],"type":"Point"}
}