{
  "type": "Feature",
  "properties": {
    "gn:admin1_code":"9.0",
    "gn:asciiname":"Douar Ogo Hmadi Oufella",
    "gn:country_code":"MA",
    "gn:dem":742,
    "gn:feature_class":"P",
    "gn:feature_code":"PPL",
    "gn:name":"Douar Ogo Hmadi Oufella",
    "gn:population":0,
    "gn:timezone":"Africa/Casablanca",
    "iso:country":"MA",
    "wof:name":"Douar Ogo Hmadi Oufella",
    "wof:placetype":"locality"
},
  "geometry": {"coordinates":[-9.78861,29.5221],"type":"Point"}
}