{
  "type": "Feature",
  "properties": {
    "gn:admin1_code":"02",
    "gn:asciiname":"Oulad Haddou Fares",
    "gn:country_code":"MA",
    "gn:dem":405,
    "gn:feature_class":"P",
    "gn:feature_code":"PPL",
    "gn:name":"Oulad Haddou Fares",
    "gn:population":0,
    "gn:timezone":"Africa/Casablanca",
    "iso:country":"MA",
    "wof:name":"Oulad Haddou Fares",
    "wof:placetype":"locality"
},
  "geometry": {"coordinates":[-3.26014,35.18433],"type":"Point"}
}