{
  "type": "Feature",
  "properties": {
    "gn:admin1_code":"09",
    "gn:asciiname":"Innrarene",
    "gn:country_code":"MA",
    "gn:dem":184,
    "gn:feature_class":"P",
    "gn:feature_code":"PPL",
    "gn:name":"Innrarene",
    "gn:population":0,
    "gn:timezone":"Africa/Casablanca",
    "iso:country":"MA",
    "name:und_x_variant":[
        "Inrarane",
        "Innrarene"
    ],
    "wof:name":"Innrarene",
    "wof:placetype":"locality"
},
  "geometry": {"coordinates":[-9.56883,30.55482],"type":"Point"}
}