{
  "type": "Feature",
  "properties": {
    "gn:admin1_code":"07",
    "gn:asciiname":"Sidi Mbarek",
    "gn:country_code":"MA",
    "gn:dem":481,
    "gn:feature_class":"P",
    "gn:feature_code":"PPL",
    "gn:name":"Sidi Mbarek",
    "gn:population":0,
    "gn:timezone":"Africa/Casablanca",
    "iso:country":"MA",
    "name:und_x_variant":[
        "Sidi Embark",
        "Sidi Mbark",
        "Sidi Mbarek"
    ],
    "wof:name":"Sidi Mbarek",
    "wof:placetype":"locality"
},
  "geometry": {"coordinates":[-9.53139,31.12655],"type":"Point"}
}