{
  "type": "Feature",
  "properties": {
    "gn:admin1_code":"1.0",
    "gn:asciiname":"Houmat Ikaoutat Essoufla",
    "gn:country_code":"MA",
    "gn:dem":994,
    "gn:feature_class":"P",
    "gn:feature_code":"PPL",
    "gn:name":"Houmat Ikaoutat Essoufla",
    "gn:population":0,
    "gn:timezone":"Africa/Casablanca",
    "iso:country":"MA",
    "wof:name":"Houmat Ikaoutat Essoufla",
    "wof:placetype":"locality"
},
  "geometry": {"coordinates":[-5.18941,35.01715],"type":"Point"}
}