{
  "type": "Feature",
  "properties": {
    "gn:asciiname":"Ait Kamara",
    "gn:country_code":"MA",
    "gn:dem":292,
    "gn:feature_class":"P",
    "gn:feature_code":"PPL",
    "gn:name":"Ait Kamara",
    "gn:population":0,
    "gn:timezone":"Africa/Casablanca",
    "iso:country":"MA",
    "name:ara_x_preferred":[
        "\u0622\u064a\u062a \u0642\u0645\u0631\u0629"
    ],
    "name:cat_x_preferred":[
        "Ait Kamra"
    ],
    "name:ceb_x_preferred":[
        "Ait Kamra"
    ],
    "name:fra_x_preferred":[
        "A\u00eft Kamra"
    ],
    "name:ita_x_preferred":[
        "Ait Kamra"
    ],
    "name:nld_x_preferred":[
        "Ait Kamara"
    ],
    "name:swe_x_preferred":[
        "Ait Kamra"
    ],
    "name:urd_x_preferred":[
        "\u0622\u06cc\u062a \u0642\u0645\u0631\u06c1"
    ],
    "wof:name":"Ait Kamara",
    "wof:placetype":"locality"
},
  "geometry": {"coordinates":[-3.98274,35.14425],"type":"Point"}
}