{
  "type": "Feature",
  "properties": {
    "gn:asciiname":"Ait Kamara",
    "gn:country_code":"MA",
    "gn:dem":292,
    "gn:feature_class":"P",
    "gn:feature_code":"PPL",
    "gn:name":"Ait Kamara",
    "gn:population":0,
    "gn:timezone":"Africa/Casablanca",
    "iso:country":"MA",
    "wof:name":"Ait Kamara",
    "wof:placetype":"locality"
},
  "geometry": {"coordinates":[-3.98274,35.14425],"type":"Point"}
}