{
  "type": "Feature",
  "properties": {
    "gn:admin1_code":"04",
    "gn:asciiname":"Douar Lmarja",
    "gn:country_code":"MA",
    "gn:dem":154,
    "gn:feature_class":"P",
    "gn:feature_code":"PPL",
    "gn:name":"Douar Lmarja",
    "gn:population":0,
    "gn:timezone":"Africa/Casablanca",
    "iso:country":"MA",
    "name:und_x_variant":[
        "Douar el Marja",
        "El Maria",
        "Marjah",
        "El Marjah",
        "Douar Lmarja"
    ],
    "wof:name":"Douar Lmarja",
    "wof:placetype":"locality"
},
  "geometry": {"coordinates":[-5.91133,34.79105],"type":"Point"}
}