{
  "type": "Feature",
  "properties": {
    "gn:admin1_code":"7.0",
    "gn:asciiname":"Ould Ben Amouu Touiziza",
    "gn:country_code":"MA",
    "gn:dem":446,
    "gn:feature_class":"P",
    "gn:feature_code":"PPL",
    "gn:name":"Ould Ben Amouu Touiziza",
    "gn:population":0,
    "gn:timezone":"Africa/Casablanca",
    "iso:country":"MA",
    "wof:name":"Ould Ben Amouu Touiziza",
    "wof:placetype":"locality"
},
  "geometry": {"coordinates":[-7.84449,32.1675],"type":"Point"}
}