{
  "type": "Feature",
  "properties": {
    "gn:admin1_code":"07",
    "gn:asciiname":"Bouzid",
    "gn:country_code":"MA",
    "gn:dem":390,
    "gn:feature_class":"P",
    "gn:feature_code":"PPL",
    "gn:name":"Bouzid",
    "gn:population":0,
    "gn:timezone":"Africa/Casablanca",
    "iso:country":"MA",
    "wof:name":"Bouzid",
    "wof:placetype":"locality"
},
  "geometry": {"coordinates":[-8.78626,31.50703],"type":"Point"}
}