{
  "type": "Feature",
  "properties": {
    "gn:admin1_code":"4.0",
    "gn:asciiname":"Cooperative El Ahd",
    "gn:country_code":"MA",
    "gn:dem":28,
    "gn:feature_class":"P",
    "gn:feature_code":"PPLF",
    "gn:name":"Coop\u00e8rative El Ahd",
    "gn:population":0,
    "gn:timezone":"Africa/Casablanca",
    "iso:country":"MA",
    "wof:name":"Cooperative El Ahd",
    "wof:placetype":"locality"
},
  "geometry": {"coordinates":[-5.89111,34.532],"type":"Point"}
}