{
  "type": "Feature",
  "properties": {
    "gn:admin1_code":"09",
    "gn:asciiname":"Tisfriwine",
    "gn:country_code":"MA",
    "gn:dem":1267,
    "gn:feature_class":"P",
    "gn:feature_code":"PPL",
    "gn:name":"Tisfriwine",
    "gn:population":0,
    "gn:timezone":"Africa/Casablanca",
    "iso:country":"MA",
    "name:und_x_variant":[
        "Tisferouine",
        "Tisfriouine"
    ],
    "wof:name":"Tisfriwine",
    "wof:placetype":"locality"
},
  "geometry": {"coordinates":[-7.81988,30.05858],"type":"Point"}
}