{
  "type": "Feature",
  "properties": {
    "gn:admin1_code":"06",
    "gn:asciiname":"Douar Ahmed Bel Ghalya",
    "gn:country_code":"MA",
    "gn:dem":283,
    "gn:feature_class":"P",
    "gn:feature_code":"PPL",
    "gn:name":"Douar Ahmed Bel Ghalya",
    "gn:population":0,
    "gn:timezone":"Africa/Casablanca",
    "iso:country":"MA",
    "name:und_x_variant":[
        "Sidi Ahmed ben Mbarka"
    ],
    "wof:name":"Douar Ahmed Bel Ghalya",
    "wof:placetype":"locality"
},
  "geometry": {"coordinates":[-8.41345,32.39584],"type":"Point"}
}