{
  "type": "Feature",
  "properties": {
    "gn:admin1_code":"5.0",
    "gn:asciiname":"Imazi",
    "gn:country_code":"MA",
    "gn:dem":2273,
    "gn:feature_class":"P",
    "gn:feature_code":"PPL",
    "gn:name":"Imazi",
    "gn:population":0,
    "gn:timezone":"Africa/Casablanca",
    "iso:country":"MA",
    "wof:name":"Imazi",
    "wof:placetype":"locality"
},
  "geometry": {"coordinates":[-6.8023,31.47787000000001],"type":"Point"}
}