{
  "type": "Feature",
  "properties": {
    "gn:admin1_code":"9.0",
    "gn:asciiname":"Zawiyat Sidi Mohannd ou Calah",
    "gn:country_code":"MA",
    "gn:dem":1290,
    "gn:feature_class":"P",
    "gn:feature_code":"PPL",
    "gn:name":"Zawiyat Sidi Mohannd ou \u00c7alah",
    "gn:population":0,
    "gn:timezone":"Africa/Casablanca",
    "iso:country":"MA",
    "wof:name":"Zawiyat Sidi Mohannd ou Calah",
    "wof:placetype":"locality"
},
  "geometry": {"coordinates":[-8.51126,30.4448],"type":"Point"}
}