{
  "type": "Feature",
  "properties": {
    "gn:admin1_code":"2.0",
    "gn:asciiname":"Dar Deghbachi Mohamed",
    "gn:country_code":"MA",
    "gn:dem":583,
    "gn:feature_class":"P",
    "gn:feature_code":"PPL",
    "gn:name":"Dar Deghbachi Mohamed",
    "gn:population":0,
    "gn:timezone":"Africa/Casablanca",
    "iso:country":"MA",
    "wof:name":"Dar Deghbachi Mohamed",
    "wof:placetype":"locality"
},
  "geometry": {"coordinates":[-2.46814,34.61013],"type":"Point"}
}