{
  "type": "Feature",
  "properties": {
    "gn:admin1_code":"1.0",
    "gn:asciiname":"Houmat Mazdoui",
    "gn:country_code":"MA",
    "gn:dem":1110,
    "gn:feature_class":"P",
    "gn:feature_code":"PPL",
    "gn:name":"Houmat Mazdoui",
    "gn:population":0,
    "gn:timezone":"Africa/Casablanca",
    "iso:country":"MA",
    "wof:name":"Houmat Mazdoui",
    "wof:placetype":"locality"
},
  "geometry": {"coordinates":[-5.24063,34.99886],"type":"Point"}
}