{
  "type": "Feature",
  "properties": {
    "gn:admin1_code":"07",
    "gn:asciiname":"Ktawa",
    "gn:country_code":"MA",
    "gn:dem":542,
    "gn:feature_class":"P",
    "gn:feature_code":"PPL",
    "gn:name":"Ktawa",
    "gn:population":0,
    "gn:timezone":"Africa/Casablanca",
    "iso:country":"MA",
    "name:und_x_variant":[
        "Douar Ktaoua",
        "Ktaoua",
        "Ktawa"
    ],
    "wof:name":"Ktawa",
    "wof:placetype":"locality"
},
  "geometry": {"coordinates":[-7.37941,31.95264],"type":"Point"}
}