{
  "type": "Feature",
  "properties": {
    "gn:admin1_code":"1.0",
    "gn:asciiname":"Douar Boulaaychich",
    "gn:country_code":"MA",
    "gn:dem":310,
    "gn:feature_class":"P",
    "gn:feature_code":"PPL",
    "gn:name":"Douar Boulaaychich",
    "gn:population":0,
    "gn:timezone":"Africa/Casablanca",
    "iso:country":"MA",
    "wof:name":"Douar Boulaaychich",
    "wof:placetype":"locality"
},
  "geometry": {"coordinates":[-5.52788,35.69145],"type":"Point"}
}