{
  "type": "Feature",
  "properties": {
    "gn:admin1_code":"5.0",
    "gn:asciiname":"Laksatla",
    "gn:country_code":"MA",
    "gn:dem":789,
    "gn:feature_class":"P",
    "gn:feature_code":"PPL",
    "gn:name":"Laksatla",
    "gn:population":0,
    "gn:timezone":"Africa/Casablanca",
    "iso:country":"MA",
    "wof:name":"Laksatla",
    "wof:placetype":"locality"
},
  "geometry": {"coordinates":[-6.37293,32.8284],"type":"Point"}
}