{
  "type": "Feature",
  "properties": {
    "gn:admin1_code":"01",
    "gn:asciiname":"Sabariene",
    "gn:country_code":"MA",
    "gn:dem":383,
    "gn:feature_class":"P",
    "gn:feature_code":"PPL",
    "gn:name":"Sabariene",
    "gn:population":0,
    "gn:timezone":"Africa/Casablanca",
    "iso:country":"MA",
    "name:und_x_variant":[
        "Sabarien",
        "Sabariene"
    ],
    "wof:name":"Sabariene",
    "wof:placetype":"locality"
},
  "geometry": {"coordinates":[-4.11,35.15],"type":"Point"}
}