{
  "type": "Feature",
  "properties": {
    "gn:admin1_code":"02",
    "gn:asciiname":"Douar Ioumarene",
    "gn:country_code":"MA",
    "gn:dem":1005,
    "gn:feature_class":"P",
    "gn:feature_code":"PPL",
    "gn:name":"Douar Ioumarene",
    "gn:population":0,
    "gn:timezone":"Africa/Casablanca",
    "iso:country":"MA",
    "name:und_x_variant":[
        "Iomar\u00e8n",
        "I\u00f4marene",
        "Douar Ioumarene"
    ],
    "wof:name":"Douar Ioumarene",
    "wof:placetype":"locality"
},
  "geometry": {"coordinates":[-3.79067,33.80395],"type":"Point"}
}