{
  "type": "Feature",
  "properties": {
    "gn:admin1_code":"07",
    "gn:asciiname":"Douar Sdira",
    "gn:country_code":"MA",
    "gn:dem":428,
    "gn:feature_class":"P",
    "gn:feature_code":"PPL",
    "gn:name":"Douar Sdira",
    "gn:population":0,
    "gn:timezone":"Africa/Casablanca",
    "iso:country":"MA",
    "name:und_x_variant":[
        "Douar Sidi el Hadj Mohammed Ben Rhir",
        "Douar Sidi el Hajj Mohammed Ben Rdir",
        "Sdira",
        "Douar Sdira"
    ],
    "wof:name":"Douar Sdira",
    "wof:placetype":"locality"
},
  "geometry": {"coordinates":[-9.05125,31.63627],"type":"Point"}
}