{
  "type": "Feature",
  "properties": {
    "gn:admin1_code":"09",
    "gn:asciiname":"Mezzint",
    "gn:country_code":"MA",
    "gn:dem":756,
    "gn:feature_class":"P",
    "gn:feature_code":"PPL",
    "gn:name":"Mezzint",
    "gn:population":0,
    "gn:timezone":"Africa/Casablanca",
    "iso:country":"MA",
    "name:und_x_variant":[
        "Mzemt",
        "Mezzint"
    ],
    "wof:name":"Mezzint",
    "wof:placetype":"locality"
},
  "geometry": {"coordinates":[-9.14293,30.76642],"type":"Point"}
}