{
  "type": "Feature",
  "properties": {
    "gn:admin1_code":"4.0",
    "gn:asciiname":"Douar Zemrani",
    "gn:country_code":"MA",
    "gn:dem":34,
    "gn:feature_class":"P",
    "gn:feature_code":"PPL",
    "gn:name":"Douar Zemrani",
    "gn:population":0,
    "gn:timezone":"Africa/Casablanca",
    "iso:country":"MA",
    "wof:name":"Douar Zemrani",
    "wof:placetype":"locality"
},
  "geometry": {"coordinates":[-6.322,34.25842],"type":"Point"}
}