{
  "type": "Feature",
  "properties": {
    "gn:admin1_code":"02",
    "gn:asciiname":"Dhar n-Tizdam",
    "gn:country_code":"MA",
    "gn:dem":295,
    "gn:feature_class":"P",
    "gn:feature_code":"PPL",
    "gn:name":"Dhar n-Tizdam",
    "gn:population":0,
    "gn:timezone":"Africa/Casablanca",
    "iso:country":"MA",
    "wof:name":"Dhar n-Tizdam",
    "wof:placetype":"locality"
},
  "geometry": {"coordinates":[-3.67262,35.17667],"type":"Point"}
}