{
  "type": "Feature",
  "properties": {
    "gn:admin1_code":"9.0",
    "gn:asciiname":"Tin Gaoua",
    "gn:country_code":"MA",
    "gn:dem":222,
    "gn:feature_class":"P",
    "gn:feature_code":"PPL",
    "gn:name":"Tin Gaoua",
    "gn:population":0,
    "gn:timezone":"Africa/Casablanca",
    "iso:country":"MA",
    "wof:name":"Tin Gaoua",
    "wof:placetype":"locality"
},
  "geometry": {"coordinates":[-9.27799,30.08531],"type":"Point"}
}