{
  "type": "Feature",
  "properties": {
    "gn:admin1_code":"04",
    "gn:asciiname":"Douar Azib Sidi El Malidi",
    "gn:country_code":"MA",
    "gn:dem":284,
    "gn:feature_class":"P",
    "gn:feature_code":"PPL",
    "gn:name":"Douar Azib Sidi El Malidi",
    "gn:population":0,
    "gn:timezone":"Africa/Casablanca",
    "iso:country":"MA",
    "name:und_x_variant":[
        "Aomar Ben Chiheb"
    ],
    "wof:name":"Douar Azib Sidi El Malidi",
    "wof:placetype":"locality"
},
  "geometry": {"coordinates":[-5.52117,34.16157],"type":"Point"}
}