{
  "type": "Feature",
  "properties": {
    "gn:admin1_code":"6.0",
    "gn:asciiname":"Difouriya",
    "gn:country_code":"MA",
    "gn:dem":200,
    "gn:feature_class":"P",
    "gn:feature_code":"PPL",
    "gn:name":"Difouriya",
    "gn:population":0,
    "gn:timezone":"Africa/Casablanca",
    "iso:country":"MA",
    "wof:name":"Difouriya",
    "wof:placetype":"locality"
},
  "geometry": {"coordinates":[-7.16226,33.66789],"type":"Point"}
}