{
  "type": "Feature",
  "properties": {
    "gn:admin1_code":"09",
    "gn:asciiname":"Irhil",
    "gn:country_code":"MA",
    "gn:dem":535,
    "gn:feature_class":"P",
    "gn:feature_code":"PPL",
    "gn:name":"Irhil",
    "gn:population":0,
    "gn:timezone":"Africa/Casablanca",
    "iso:country":"MA",
    "name:und_x_variant":[
        "Ighil",
        "Irhil"
    ],
    "wof:name":"Irhil",
    "wof:placetype":"locality"
},
  "geometry": {"coordinates":[-9.25,29.88],"type":"Point"}
}