{
  "type": "Feature",
  "properties": {
    "gn:admin1_code":"05",
    "gn:asciiname":"Izaritane",
    "gn:country_code":"MA",
    "gn:dem":1534,
    "gn:elevation":"0.0",
    "gn:feature_class":"P",
    "gn:feature_code":"PPL",
    "gn:name":"Izaritane",
    "gn:population":0,
    "gn:timezone":"Africa/Casablanca",
    "iso:country":"MA",
    "name:und_x_variant":[
        "Izarifen",
        "Izenfen",
        "Izrifene",
        "Izarifene",
        "Izaritane"
    ],
    "wof:name":"Izaritane",
    "wof:placetype":"locality"
},
  "geometry": {"coordinates":[-6.93937,31.59301],"type":"Point"}
}