{
  "type": "Feature",
  "properties": {
    "gn:admin1_code":"07",
    "gn:asciiname":"'Azib al Mahareg",
    "gn:country_code":"MA",
    "gn:dem":520,
    "gn:feature_class":"P",
    "gn:feature_code":"PPL",
    "gn:name":"\u2019Azib al Mahareg",
    "gn:population":0,
    "gn:timezone":"Africa/Casablanca",
    "iso:country":"MA",
    "name:und_x_variant":[
        "Azib el Mahareg",
        "Azib el Marog",
        "\u2019Azib al Mahareg"
    ],
    "wof:name":"'Azib al Mahareg",
    "wof:placetype":"locality"
},
  "geometry": {"coordinates":[-8.43615,31.46746],"type":"Point"}
}