{
  "type": "Feature",
  "properties": {
    "gn:admin1_code":"07",
    "gn:asciiname":"Imi N'Zguer",
    "gn:country_code":"MA",
    "gn:dem":938,
    "gn:feature_class":"P",
    "gn:feature_code":"PPL",
    "gn:name":"Imi N\u2019Zguer",
    "gn:population":0,
    "gn:timezone":"Africa/Casablanca",
    "iso:country":"MA",
    "name:und_x_variant":[
        "Amnzgar",
        "Iminsguer",
        "Imi N\u2019Zguer"
    ],
    "wof:name":"Imi N'Zguer",
    "wof:placetype":"locality"
},
  "geometry": {"coordinates":[-9.02361,30.87053],"type":"Point"}
}