{
  "type": "Feature",
  "properties": {
    "gn:admin1_code":"04",
    "gn:asciiname":"Douar Tfaoutya",
    "gn:country_code":"MA",
    "gn:dem":67,
    "gn:feature_class":"P",
    "gn:feature_code":"PPL",
    "gn:name":"Douar Tfaoutya",
    "gn:population":0,
    "gn:timezone":"Africa/Casablanca",
    "iso:country":"MA",
    "name:und_x_variant":[
        "Douar Tefoutya",
        "Tfeuitia",
        "Tefoutia",
        "Douar Tfaoutya"
    ],
    "wof:name":"Douar Tfaoutya",
    "wof:placetype":"locality"
},
  "geometry": {"coordinates":[-5.78909,34.62713],"type":"Point"}
}