{
  "type": "Feature",
  "properties": {
    "gn:admin1_code":"08",
    "gn:asciiname":"Ikkis",
    "gn:country_code":"MA",
    "gn:dem":1605,
    "gn:feature_class":"P",
    "gn:feature_code":"PPL",
    "gn:name":"Ikkis",
    "gn:population":0,
    "gn:timezone":"Africa/Casablanca",
    "iso:country":"MA",
    "name:und_x_variant":[
        "Ikis",
        "Ikiss",
        "Ikkis"
    ],
    "wof:name":"Ikkis",
    "wof:placetype":"locality"
},
  "geometry": {"coordinates":[-7.39285,31.14055],"type":"Point"}
}