{
  "type": "Feature",
  "properties": {
    "gn:admin1_code":"08",
    "gn:asciiname":"Ait Fatah",
    "gn:country_code":"MA",
    "gn:dem":1845,
    "gn:feature_class":"P",
    "gn:feature_code":"PPL",
    "gn:name":"A\u00eft Fatah",
    "gn:population":0,
    "gn:timezone":"Africa/Casablanca",
    "iso:country":"MA",
    "name:und_x_variant":[
        "A\u00eft Fatah",
        "A\u00eft Feth",
        "A\u00eft Fatou"
    ],
    "wof:name":"Ait Fatah",
    "wof:placetype":"locality"
},
  "geometry": {"coordinates":[-7.2673,31.28877],"type":"Point"}
}