{
  "type": "Feature",
  "properties": {
    "iso:country":"MA",
    "name:und_x_variant":[
        "Asggaour"
    ],
    "qs:gn_country":"MA",
    "qs:gn_fcode":"PPL",
    "qs:gn_pop":0,
    "qs:name":"Asgaour",
    "qs:name_adm0":"\u0627\u0644\u0645\u063a\u0631\u0628",
    "qs:name_adm1":"\u0645\u0631\u0627\u0643\u0634 \u0640 \u062a\u0627\u0646\u0633\u064a\u0641\u062a \u0640 \u0627\u0644\u062d\u0648\u0632",
    "qs:photos":567,
    "qs:photos_1k":115,
    "qs:photos_9k":3,
    "qs:photos_9r":5,
    "qs:photos_all":567,
    "qs:photos_sr":8,
    "qs:placetype":"Town",
    "qs:pop_sr":"3",
    "qs:woe_adm0":23424893,
    "wof:name":"Asgaour",
    "wof:placetype":"locality"
},
  "geometry": {"coordinates":[-7.66867,31.23107],"type":"Point"}
}