{
  "type": "Feature",
  "properties": {
    "gn:admin1_code":"09",
    "gn:asciiname":"Wislane",
    "gn:country_code":"MA",
    "gn:dem":1384,
    "gn:feature_class":"P",
    "gn:feature_code":"PPL",
    "gn:name":"Wislane",
    "gn:population":0,
    "gn:timezone":"Africa/Casablanca",
    "iso:country":"MA",
    "name:ara_x_preferred":[
        "\u0648\u064a\u0633\u0644\u0627\u0646"
    ],
    "name:cat_x_preferred":[
        "Ouislane"
    ],
    "name:ceb_x_preferred":[
        "Ouislane"
    ],
    "name:fra_x_preferred":[
        "Ouislane"
    ],
    "name:swe_x_preferred":[
        "Ouislane"
    ],
    "wof:name":"Wislane",
    "wof:placetype":"locality"
},
  "geometry": {"coordinates":[-8.38006,30.22497000000001],"type":"Point"}
}