{
  "type": "Feature",
  "properties": {
    "gn:admin1_code":"02",
    "gn:asciiname":"Mhajar",
    "gn:country_code":"MA",
    "gn:dem":850,
    "gn:feature_class":"P",
    "gn:feature_code":"PPL",
    "gn:name":"Mh\u00e2j\u00e2r",
    "gn:population":0,
    "gn:timezone":"Africa/Casablanca",
    "iso:country":"MA",
    "name:und_x_variant":[
        "Mehajer",
        "Mehayart",
        "Mehajart",
        "Mh\u00e2j\u00e2r"
    ],
    "wof:name":"Mhajar",
    "wof:placetype":"locality"
},
  "geometry": {"coordinates":[-3.50535,35.12428],"type":"Point"}
}