{
  "type": "Feature",
  "properties": {
    "gn:admin1_code":"3.0",
    "gn:asciiname":"Douar Od. Sidi Mhamed",
    "gn:country_code":"MA",
    "gn:dem":1005,
    "gn:feature_class":"P",
    "gn:feature_code":"PPL",
    "gn:name":"Douar Od. Sidi Mhamed",
    "gn:population":0,
    "gn:timezone":"Africa/Casablanca",
    "iso:country":"MA",
    "wof:name":"Douar Od. Sidi Mhamed",
    "wof:placetype":"locality"
},
  "geometry": {"coordinates":[-4.68957,33.76287],"type":"Point"}
}