{
  "type": "Feature",
  "properties": {
    "gn:admin1_code":"09",
    "gn:asciiname":"Wit Wourrayn",
    "gn:country_code":"MA",
    "gn:dem":1155,
    "gn:feature_class":"P",
    "gn:feature_code":"PPL",
    "gn:name":"Wit Wourrayn",
    "gn:population":0,
    "gn:timezone":"Africa/Casablanca",
    "iso:country":"MA",
    "name:und_x_variant":[
        "Omla Ourouine",
        "Outourouine",
        "Wit Wourrayn"
    ],
    "wof:name":"Wit Wourrayn",
    "wof:placetype":"locality"
},
  "geometry": {"coordinates":[-8.94581,29.87652000000001],"type":"Point"}
}