{
  "type": "Feature",
  "properties": {
    "gn:admin1_code":"05",
    "gn:asciiname":"Tit-N-Saqqa",
    "gn:country_code":"MA",
    "gn:dem":1794,
    "gn:feature_class":"P",
    "gn:feature_code":"PPL",
    "gn:name":"Tit-N-Saqqa",
    "gn:population":0,
    "gn:timezone":"Africa/Casablanca",
    "iso:country":"MA",
    "name:und_x_variant":[
        "Tit-n-Sagga",
        "Ksour Tit\u00e8n n\u2019Seka",
        "Ksour Titene n\u2019Seka"
    ],
    "wof:name":"Tit-N-Saqqa",
    "wof:placetype":"locality"
},
  "geometry": {"coordinates":[-5.63966,32.64850999999999],"type":"Point"}
}