{
  "type": "Feature",
  "properties": {
    "gn:admin1_code":"08",
    "gn:asciiname":"Ait Dawd Ou Moussa",
    "gn:country_code":"MA",
    "gn:dem":1848,
    "gn:feature_class":"P",
    "gn:feature_code":"PPL",
    "gn:name":"A\u00eft Dawd Ou Moussa",
    "gn:population":0,
    "gn:timezone":"Africa/Casablanca",
    "iso:country":"MA",
    "name:und_x_variant":[
        "A\u00eft Dawd Ou Moussa",
        "A\u00eft Daoud Ou Moussa"
    ],
    "wof:name":"Ait Dawd Ou Moussa",
    "wof:placetype":"locality"
},
  "geometry": {"coordinates":[-4.57393,32.52276],"type":"Point"}
}