{
  "type": "Feature",
  "properties": {
    "gn:admin1_code":"9.0",
    "gn:asciiname":"Ait Haida",
    "gn:country_code":"MA",
    "gn:dem":209,
    "gn:feature_class":"P",
    "gn:feature_code":"PPL",
    "gn:name":"A\u00eft Ha\u00efda",
    "gn:population":0,
    "gn:timezone":"Africa/Casablanca",
    "iso:country":"MA",
    "wof:name":"Ait Haida",
    "wof:placetype":"locality"
},
  "geometry": {"coordinates":[-8.93254,30.46102],"type":"Point"}
}