{
  "type": "Feature",
  "properties": {
    "gn:admin1_code":"7.0",
    "gn:asciiname":"Am Moulay Tehmis",
    "gn:country_code":"MA",
    "gn:dem":108,
    "gn:feature_class":"P",
    "gn:feature_code":"PPL",
    "gn:name":"Am Moulay Tehmis",
    "gn:population":0,
    "gn:timezone":"Africa/Casablanca",
    "iso:country":"MA",
    "wof:name":"Am Moulay Tehmis",
    "wof:placetype":"locality"
},
  "geometry": {"coordinates":[-9.13401,32.39927],"type":"Point"}
}