{
  "type": "Feature",
  "properties": {
    "gn:admin1_code":"3.0",
    "gn:asciiname":"Ghroul",
    "gn:country_code":"MA",
    "gn:dem":265,
    "gn:feature_class":"P",
    "gn:feature_code":"PPL",
    "gn:name":"Ghroul",
    "gn:population":0,
    "gn:timezone":"Africa/Casablanca",
    "iso:country":"MA",
    "wof:name":"Ghroul",
    "wof:placetype":"locality"
},
  "geometry": {"coordinates":[-5.104,34.50704],"type":"Point"}
}