{
  "type": "Feature",
  "properties": {
    "gn:admin1_code":"07",
    "gn:asciiname":"Ifis",
    "gn:country_code":"MA",
    "gn:dem":885,
    "gn:feature_class":"P",
    "gn:feature_code":"PPL",
    "gn:name":"Ifis",
    "gn:population":0,
    "gn:timezone":"Africa/Casablanca",
    "iso:country":"MA",
    "name:und_x_variant":[
        "Yfis",
        "Ifis"
    ],
    "wof:name":"Ifis",
    "wof:placetype":"locality"
},
  "geometry": {"coordinates":[-9.34273,30.89456],"type":"Point"}
}