{
  "type": "Feature",
  "properties": {
    "gn:admin1_code":"4.0",
    "gn:asciiname":"Alamet Zaabata",
    "gn:country_code":"MA",
    "gn:dem":8,
    "gn:feature_class":"P",
    "gn:feature_code":"PPL",
    "gn:name":"Alamet Zaabata",
    "gn:population":0,
    "gn:timezone":"Africa/Casablanca",
    "iso:country":"MA",
    "wof:name":"Alamet Zaabata",
    "wof:placetype":"locality"
},
  "geometry": {"coordinates":[-6.41913,34.42],"type":"Point"}
}