{
  "type": "Feature",
  "properties": {
    "gn:admin1_code":"01",
    "gn:asciiname":"El Khokh",
    "gn:country_code":"MA",
    "gn:dem":106,
    "gn:feature_class":"P",
    "gn:feature_code":"PPL",
    "gn:name":"El Khokh",
    "gn:population":0,
    "gn:timezone":"Africa/Casablanca",
    "iso:country":"MA",
    "wof:name":"El Khokh",
    "wof:placetype":"locality"
},
  "geometry": {"coordinates":[-5.16859,35.36393],"type":"Point"}
}