{
  "type": "Feature",
  "properties": {
    "gn:admin1_code":"07",
    "gn:asciiname":"Tabou",
    "gn:country_code":"MA",
    "gn:dem":1028,
    "gn:feature_class":"P",
    "gn:feature_code":"PPL",
    "gn:name":"Tabou",
    "gn:population":0,
    "gn:timezone":"Africa/Casablanca",
    "iso:country":"MA",
    "name:ceb_x_preferred":[
        "Tabou"
    ],
    "name:deu_x_preferred":[
        "Tabou"
    ],
    "name:fra_x_preferred":[
        "Tabou"
    ],
    "name:ita_x_preferred":[
        "Tabou"
    ],
    "name:swa_x_preferred":[
        "Tabou"
    ],
    "name:swe_x_preferred":[
        "Tabou"
    ],
    "name:und_x_variant":[
        "Tagout",
        "Tabout"
    ],
    "wof:name":"Tabou",
    "wof:placetype":"locality"
},
  "geometry": {"coordinates":[-9.34342,31.11862],"type":"Point"}
}