{
  "type": "Feature",
  "properties": {
    "gn:admin1_code":"9.0",
    "gn:asciiname":"Id Yahya",
    "gn:country_code":"MA",
    "gn:dem":454,
    "gn:feature_class":"P",
    "gn:feature_code":"PPL",
    "gn:name":"Id Yahya",
    "gn:population":0,
    "gn:timezone":"Africa/Casablanca",
    "iso:country":"MA",
    "wof:name":"Id Yahya",
    "wof:placetype":"locality"
},
  "geometry": {"coordinates":[-9.77106,30.75575],"type":"Point"}
}