{
  "type": "Feature",
  "properties": {
    "gn:admin1_code":"9.0",
    "gn:asciiname":"Ait 'Abdallah",
    "gn:country_code":"MA",
    "gn:dem":504,
    "gn:feature_class":"P",
    "gn:feature_code":"PPL",
    "gn:name":"A\u00eft \u2019Abdallah",
    "gn:population":0,
    "gn:timezone":"Africa/Casablanca",
    "iso:country":"MA",
    "wof:name":"Ait 'Abdallah",
    "wof:placetype":"locality"
},
  "geometry": {"coordinates":[-8.40667,30.62607],"type":"Point"}
}