{
  "type": "Feature",
  "properties": {
    "gn:admin1_code":"03",
    "gn:asciiname":"Douar Joulyane",
    "gn:country_code":"MA",
    "gn:dem":734,
    "gn:feature_class":"P",
    "gn:feature_code":"PPL",
    "gn:name":"Douar Joulyane",
    "gn:population":0,
    "gn:timezone":"Africa/Casablanca",
    "iso:country":"MA",
    "wof:name":"Douar Joulyane",
    "wof:placetype":"locality"
},
  "geometry": {"coordinates":[-5.51478,33.72631],"type":"Point"}
}