{
  "type": "Feature",
  "properties": {
    "gn:admin1_code":"09",
    "gn:asciiname":"Tililine",
    "gn:country_code":"MA",
    "gn:dem":1412,
    "gn:feature_class":"P",
    "gn:feature_code":"PPL",
    "gn:name":"Tililine",
    "gn:population":0,
    "gn:timezone":"Africa/Casablanca",
    "iso:country":"MA",
    "wof:name":"Tililine",
    "wof:placetype":"locality"
},
  "geometry": {"coordinates":[-8.32278,30.24294],"type":"Point"}
}