{
  "type": "Feature",
  "properties": {
    "gn:admin1_code":"9.0",
    "gn:asciiname":"Tamchirt",
    "gn:country_code":"MA",
    "gn:dem":841,
    "gn:feature_class":"P",
    "gn:feature_code":"PPL",
    "gn:name":"Tamchirt",
    "gn:population":0,
    "gn:timezone":"Africa/Casablanca",
    "iso:country":"MA",
    "wof:name":"Tamchirt",
    "wof:placetype":"locality"
},
  "geometry": {"coordinates":[-9.1862,30.75686],"type":"Point"}
}