{
  "type": "Feature",
  "properties": {
    "gn:admin1_code":"09",
    "gn:asciiname":"Id Mohammed",
    "gn:country_code":"MA",
    "gn:dem":213,
    "gn:feature_class":"P",
    "gn:feature_code":"PPL",
    "gn:name":"Id Mohammed",
    "gn:population":0,
    "gn:timezone":"Africa/Casablanca",
    "iso:country":"MA",
    "wof:name":"Id Mohammed",
    "wof:placetype":"locality"
},
  "geometry": {"coordinates":[-9.98,29.52],"type":"Point"}
}