{
  "type": "Feature",
  "properties": {
    "gn:admin1_code":"5.0",
    "gn:asciiname":"Tighza",
    "gn:country_code":"MA",
    "gn:dem":1786,
    "gn:feature_class":"P",
    "gn:feature_code":"PPL",
    "gn:name":"Tighza",
    "gn:population":0,
    "gn:timezone":"Africa/Casablanca",
    "iso:country":"MA",
    "wof:name":"Tighza",
    "wof:placetype":"locality"
},
  "geometry": {"coordinates":[-6.45513,31.81433],"type":"Point"}
}