{
  "type": "Feature",
  "properties": {
    "gn:admin1_code":"07",
    "gn:asciiname":"Douar Jaafra",
    "gn:country_code":"MA",
    "gn:dem":582,
    "gn:feature_class":"P",
    "gn:feature_code":"PPL",
    "gn:name":"Douar Jaafra",
    "gn:population":0,
    "gn:timezone":"Africa/Casablanca",
    "iso:country":"MA",
    "name:und_x_variant":[
        "Douar Sidi Brahim",
        "Sidi Brahim",
        "Douar Jaafra"
    ],
    "wof:name":"Douar Jaafra",
    "wof:placetype":"locality"
},
  "geometry": {"coordinates":[-7.66867,31.76878],"type":"Point"}
}