{
  "type": "Feature",
  "properties": {
    "gn:admin1_code":"9.0",
    "gn:asciiname":"Toufrar",
    "gn:country_code":"MA",
    "gn:dem":1032,
    "gn:feature_class":"P",
    "gn:feature_code":"PPL",
    "gn:name":"Toufrar",
    "gn:population":0,
    "gn:timezone":"Africa/Casablanca",
    "iso:country":"MA",
    "wof:name":"Toufrar",
    "wof:placetype":"locality"
},
  "geometry": {"coordinates":[-9.25466,29.59124000000001],"type":"Point"}
}