{
  "type": "Feature",
  "properties": {
    "gn:admin1_code":"3.0",
    "gn:asciiname":"Douar Ait Yahya ou Alla",
    "gn:country_code":"MA",
    "gn:dem":940,
    "gn:feature_class":"P",
    "gn:feature_code":"PPL",
    "gn:name":"Douar Ait Yahya ou Alla",
    "gn:population":0,
    "gn:timezone":"Africa/Casablanca",
    "iso:country":"MA",
    "wof:name":"Douar Ait Yahya ou Alla",
    "wof:placetype":"locality"
},
  "geometry": {"coordinates":[-5.51143,33.50244],"type":"Point"}
}