{
  "type": "Feature",
  "properties": {
    "gn:admin1_code":"5.0",
    "gn:asciiname":"Ait 'Ali Qaddour",
    "gn:country_code":"MA",
    "gn:dem":721,
    "gn:feature_class":"P",
    "gn:feature_code":"PPL",
    "gn:name":"A\u00eft \u2019Ali Qaddour",
    "gn:population":0,
    "gn:timezone":"Africa/Casablanca",
    "iso:country":"MA",
    "wof:name":"Ait 'Ali Qaddour",
    "wof:placetype":"locality"
},
  "geometry": {"coordinates":[-6.99041,32.0138],"type":"Point"}
}