{
  "type": "Feature",
  "properties": {
    "gn:admin1_code":"03",
    "gn:asciiname":"Chekka",
    "gn:country_code":"MA",
    "gn:dem":761,
    "gn:feature_class":"P",
    "gn:feature_code":"PPL",
    "gn:name":"Chekka",
    "gn:population":0,
    "gn:timezone":"Africa/Casablanca",
    "iso:country":"MA",
    "name:ara_x_preferred":[
        "\u0634\u0643\u0627"
    ],
    "name:fas_x_preferred":[
        "\u0634\u06a9\u0627"
    ],
    "name:fra_x_preferred":[
        "Chekka"
    ],
    "name:heb_x_preferred":[
        "\u05e9\u05db\u05d0"
    ],
    "name:ita_x_preferred":[
        "Chekka"
    ],
    "name:nno_x_preferred":[
        "Chekka"
    ],
    "name:nor_x_preferred":[
        "Chekka"
    ],
    "name:pol_x_preferred":[
        "Szikka"
    ],
    "name:und_x_variant":[
        "Douar Chekka"
    ],
    "wof:name":"Chekka",
    "wof:placetype":"locality"
},
  "geometry": {"coordinates":[-4.03,34.18],"type":"Point"}
}