{
  "type": "Feature",
  "properties": {
    "gn:admin1_code":"03",
    "gn:asciiname":"Chekka",
    "gn:country_code":"MA",
    "gn:dem":761,
    "gn:feature_class":"P",
    "gn:feature_code":"PPL",
    "gn:name":"Chekka",
    "gn:population":0,
    "gn:timezone":"Africa/Casablanca",
    "iso:country":"MA",
    "name:und_x_variant":[
        "Douar Chekka",
        "Chekka"
    ],
    "wof:name":"Chekka",
    "wof:placetype":"locality"
},
  "geometry": {"coordinates":[-4.03,34.18],"type":"Point"}
}