{
  "type": "Feature",
  "properties": {
    "gn:admin1_code":"3.0",
    "gn:asciiname":"Tgharghour",
    "gn:country_code":"MA",
    "gn:dem":820,
    "gn:feature_class":"P",
    "gn:feature_code":"PPL",
    "gn:name":"Tgharghour",
    "gn:population":0,
    "gn:timezone":"Africa/Casablanca",
    "iso:country":"MA",
    "wof:name":"Tgharghour",
    "wof:placetype":"locality"
},
  "geometry": {"coordinates":[-4.37147,33.7947],"type":"Point"}
}