{
  "type": "Feature",
  "properties": {
    "gn:admin1_code":"03",
    "gn:asciiname":"Douar Echbaniyine",
    "gn:country_code":"MA",
    "gn:dem":350,
    "gn:feature_class":"P",
    "gn:feature_code":"PPL",
    "gn:name":"Douar Echbaniyine",
    "gn:population":0,
    "gn:timezone":"Africa/Casablanca",
    "iso:country":"MA",
    "name:und_x_variant":[
        "Chebaayne"
    ],
    "wof:name":"Douar Echbaniyine",
    "wof:placetype":"locality"
},
  "geometry": {"coordinates":[-5.03254,34.22568],"type":"Point"}
}