{
  "type": "Feature",
  "properties": {
    "gn:admin1_code":"08",
    "gn:asciiname":"Achdad",
    "gn:country_code":"MA",
    "gn:dem":1188,
    "gn:feature_class":"P",
    "gn:feature_code":"PPL",
    "gn:name":"Achdad",
    "gn:population":0,
    "gn:timezone":"Africa/Casablanca",
    "iso:country":"MA",
    "wof:name":"Achdad",
    "wof:placetype":"locality"
},
  "geometry": {"coordinates":[-5.43807,31.4431],"type":"Point"}
}