{
  "type": "Feature",
  "properties": {
    "gn:admin1_code":"1.0",
    "gn:asciiname":"Douar Bou Brahem",
    "gn:country_code":"MA",
    "gn:dem":146,
    "gn:feature_class":"P",
    "gn:feature_code":"PPL",
    "gn:name":"Douar Bou Brahem",
    "gn:population":0,
    "gn:timezone":"Africa/Casablanca",
    "iso:country":"MA",
    "wof:name":"Douar Bou Brahem",
    "wof:placetype":"locality"
},
  "geometry": {"coordinates":[-3.84865,35.09323],"type":"Point"}
}