{
  "type": "Feature",
  "properties": {
    "gn:admin1_code":"4.0",
    "gn:asciiname":"Sale Al Jadida",
    "gn:country_code":"MA",
    "gn:dem":119,
    "gn:feature_class":"P",
    "gn:feature_code":"PPL",
    "gn:name":"Sal\u00e9 Al Jadida",
    "gn:population":0,
    "gn:timezone":"Africa/Casablanca",
    "iso:country":"MA",
    "wof:name":"Sale Al Jadida",
    "wof:placetype":"locality"
},
  "geometry": {"coordinates":[-6.74047,33.99722],"type":"Point"}
}