{
  "type": "Feature",
  "properties": {
    "gn:admin1_code":"08",
    "gn:asciiname":"El Hart",
    "gn:country_code":"MA",
    "gn:dem":1536,
    "gn:feature_class":"P",
    "gn:feature_code":"PPL",
    "gn:name":"El Hart",
    "gn:population":0,
    "gn:timezone":"Africa/Casablanca",
    "iso:country":"MA",
    "wof:name":"El Hart",
    "wof:placetype":"locality"
},
  "geometry": {"coordinates":[-6.58226,31.26333],"type":"Point"}
}