{
  "type": "Feature",
  "properties": {
    "gn:admin1_code":"07",
    "gn:asciiname":"Tamismamane",
    "gn:country_code":"MA",
    "gn:dem":2133,
    "gn:feature_class":"P",
    "gn:feature_code":"PPL",
    "gn:name":"Tamismamane",
    "gn:population":0,
    "gn:timezone":"Africa/Casablanca",
    "iso:country":"MA",
    "name:und_x_variant":[
        "Timeslat",
        "Timeslaht",
        "Timeslah",
        "Tamismamane"
    ],
    "wof:name":"Tamismamane",
    "wof:placetype":"locality"
},
  "geometry": {"coordinates":[-8.36404,30.98275],"type":"Point"}
}