{
  "type": "Feature",
  "properties": {
    "gn:admin1_code":"01",
    "gn:asciiname":"Douar Ain Dalya Lkebira",
    "gn:country_code":"MA",
    "gn:dem":66,
    "gn:feature_class":"P",
    "gn:feature_code":"PPL",
    "gn:name":"Douar Ain Dalya Lkebira",
    "gn:population":0,
    "gn:timezone":"Africa/Casablanca",
    "iso:country":"MA",
    "name:und_x_variant":[
        "A\u00efn Dalia Kbira",
        "A\u00efn Dalia Kebira",
        "Douar Ain Dalya Lkebira"
    ],
    "wof:name":"Douar Ain Dalya Lkebira",
    "wof:placetype":"locality"
},
  "geometry": {"coordinates":[-5.837,35.66227],"type":"Point"}
}