{
  "type": "Feature",
  "properties": {
    "gn:admin1_code":"7.0",
    "gn:asciiname":"Laajalat",
    "gn:country_code":"MA",
    "gn:dem":314,
    "gn:feature_class":"P",
    "gn:feature_code":"PPL",
    "gn:name":"Laajalat",
    "gn:population":0,
    "gn:timezone":"Africa/Casablanca",
    "iso:country":"MA",
    "wof:name":"Laajalat",
    "wof:placetype":"locality"
},
  "geometry": {"coordinates":[-8.77907,31.98249],"type":"Point"}
}