{
  "type": "Feature",
  "properties": {
    "gn:admin1_code":"08",
    "gn:asciiname":"Mazguida",
    "gn:country_code":"MA",
    "gn:dem":775,
    "gn:feature_class":"P",
    "gn:feature_code":"PPL",
    "gn:name":"Mazguida",
    "gn:population":0,
    "gn:timezone":"Africa/Casablanca",
    "iso:country":"MA",
    "name:und_x_variant":[
        "Ksar de Meguida",
        "Mezguida",
        "Mesguida",
        "Mazguida",
        "Merzouga"
    ],
    "wof:name":"Mazguida",
    "wof:placetype":"locality"
},
  "geometry": {"coordinates":[-4.2574,31.3242],"type":"Point"}
}