{
  "type": "Feature",
  "properties": {
    "gn:admin1_code":"10.0",
    "gn:asciiname":"Id Sira",
    "gn:country_code":"MA",
    "gn:dem":814,
    "gn:feature_class":"P",
    "gn:feature_code":"PPL",
    "gn:name":"Id Sira",
    "gn:population":0,
    "gn:timezone":"Africa/Casablanca",
    "iso:country":"MA",
    "wof:name":"Id Sira",
    "wof:placetype":"locality"
},
  "geometry": {"coordinates":[-9.86364,29.31447],"type":"Point"}
}