{
  "type": "Feature",
  "properties": {
    "gn:admin1_code":"7.0",
    "gn:asciiname":"Ait Sidi Mbarek",
    "gn:country_code":"MA",
    "gn:dem":183,
    "gn:feature_class":"P",
    "gn:feature_code":"PPL",
    "gn:name":"Ait Sidi Mbarek",
    "gn:population":0,
    "gn:timezone":"Africa/Casablanca",
    "iso:country":"MA",
    "wof:name":"Ait Sidi Mbarek",
    "wof:placetype":"locality"
},
  "geometry": {"coordinates":[-9.74904,31.26513],"type":"Point"}
}