{
  "type": "Feature",
  "properties": {
    "gn:admin1_code":"01",
    "gn:asciiname":"Lahyata",
    "gn:country_code":"MA",
    "gn:dem":36,
    "gn:feature_class":"P",
    "gn:feature_code":"PPL",
    "gn:name":"Lahyata",
    "gn:population":0,
    "gn:timezone":"Africa/Casablanca",
    "iso:country":"MA",
    "name:und_x_variant":[
        "El Hiata",
        "El Hiatal",
        "Lahyata"
    ],
    "wof:name":"Lahyata",
    "wof:placetype":"locality"
},
  "geometry": {"coordinates":[-5.87858,35.05257],"type":"Point"}
}