{
  "type": "Feature",
  "properties": {
    "gn:admin1_code":"3.0",
    "gn:asciiname":"Hay Ain Karmous",
    "gn:country_code":"MA",
    "gn:dem":310,
    "gn:feature_class":"P",
    "gn:feature_code":"PPL",
    "gn:name":"Hay Ain Karmous",
    "gn:population":0,
    "gn:timezone":"Africa/Casablanca",
    "iso:country":"MA",
    "wof:name":"Hay Ain Karmous",
    "wof:placetype":"locality"
},
  "geometry": {"coordinates":[-4.67266,34.29971],"type":"Point"}
}