{
  "type": "Feature",
  "properties": {
    "gn:admin1_code":"04",
    "gn:asciiname":"Oulad Saar",
    "gn:country_code":"MA",
    "gn:dem":13,
    "gn:feature_class":"P",
    "gn:feature_code":"PPL",
    "gn:name":"Oulad Saar",
    "gn:population":0,
    "gn:timezone":"Africa/Casablanca",
    "iso:country":"MA",
    "name:und_x_variant":[
        "Douar Oulad Saar",
        "Oulad Saar"
    ],
    "wof:name":"Oulad Saar",
    "wof:placetype":"locality"
},
  "geometry": {"coordinates":[-6.18209,34.40904],"type":"Point"}
}