{
  "type": "Feature",
  "properties": {
    "gn:admin1_code":"9.0",
    "gn:asciiname":"Azrib",
    "gn:country_code":"MA",
    "gn:dem":162,
    "gn:feature_class":"P",
    "gn:feature_code":"PPL",
    "gn:name":"Azrib",
    "gn:population":0,
    "gn:timezone":"Africa/Casablanca",
    "iso:country":"MA",
    "wof:name":"Azrib",
    "wof:placetype":"locality"
},
  "geometry": {"coordinates":[-9.35515,30.03062000000001],"type":"Point"}
}