{
  "type": "Feature",
  "properties": {
    "gn:admin1_code":"02",
    "gn:asciiname":"El Msaada",
    "gn:country_code":"MA",
    "gn:dem":71,
    "gn:feature_class":"P",
    "gn:feature_code":"PPL",
    "gn:name":"El Msaada",
    "gn:population":0,
    "gn:timezone":"Africa/Casablanca",
    "iso:country":"MA",
    "wof:name":"El Msaada",
    "wof:placetype":"locality"
},
  "geometry": {"coordinates":[-2.36883,35.07555],"type":"Point"}
}