{
  "type": "Feature",
  "properties": {
    "gn:admin1_code":"6.0",
    "gn:asciiname":"Douar Charqaoua Morsliyyine",
    "gn:country_code":"MA",
    "gn:dem":692,
    "gn:feature_class":"P",
    "gn:feature_code":"PPL",
    "gn:name":"Douar Charqaoua Morsliyyine",
    "gn:population":0,
    "gn:timezone":"Africa/Casablanca",
    "iso:country":"MA",
    "wof:name":"Douar Charqaoua Morsliyyine",
    "wof:placetype":"locality"
},
  "geometry": {"coordinates":[-7.21272,33.01236],"type":"Point"}
}