{
  "type": "Feature",
  "properties": {
    "gn:admin1_code":"03",
    "gn:asciiname":"Taouerta",
    "gn:country_code":"MA",
    "gn:dem":824,
    "gn:feature_class":"P",
    "gn:feature_code":"PPL",
    "gn:name":"Taouerta",
    "gn:population":0,
    "gn:timezone":"Africa/Casablanca",
    "iso:country":"MA",
    "name:und_x_variant":[
        "Taourta",
        "Taouerta"
    ],
    "wof:name":"Taouerta",
    "wof:placetype":"locality"
},
  "geometry": {"coordinates":[-4.64822,34.66285999999999],"type":"Point"}
}