{
  "type": "Feature",
  "properties": {
    "gn:admin1_code":"04",
    "gn:asciiname":"Douar Fraouat",
    "gn:country_code":"MA",
    "gn:dem":258,
    "gn:feature_class":"P",
    "gn:feature_code":"PPL",
    "gn:name":"Douar Fraouat",
    "gn:population":0,
    "gn:timezone":"Africa/Casablanca",
    "iso:country":"MA",
    "wof:name":"Douar Fraouat",
    "wof:placetype":"locality"
},
  "geometry": {"coordinates":[-5.5355,34.29374],"type":"Point"}
}