{
  "type": "Feature",
  "properties": {
    "gn:admin1_code":"03",
    "gn:asciiname":"Douar Gaddara",
    "gn:country_code":"MA",
    "gn:dem":138,
    "gn:feature_class":"P",
    "gn:feature_code":"PPL",
    "gn:name":"Douar Gaddara",
    "gn:population":0,
    "gn:timezone":"Africa/Casablanca",
    "iso:country":"MA",
    "name:und_x_variant":[
        "Douar Gueddara",
        "Gueddara",
        "Douar Gaddara"
    ],
    "wof:name":"Douar Gaddara",
    "wof:placetype":"locality"
},
  "geometry": {"coordinates":[-5.45696,34.21911],"type":"Point"}
}