{
  "type": "Feature",
  "properties": {
    "gn:admin1_code":"1.0",
    "gn:asciiname":"Douar Errokba",
    "gn:country_code":"MA",
    "gn:dem":443,
    "gn:feature_class":"P",
    "gn:feature_code":"PPL",
    "gn:name":"Douar Errokba",
    "gn:population":0,
    "gn:timezone":"Africa/Casablanca",
    "iso:country":"MA",
    "wof:name":"Douar Errokba",
    "wof:placetype":"locality"
},
  "geometry": {"coordinates":[-5.55273,35.53015999999999],"type":"Point"}
}