{
  "type": "Feature",
  "properties": {
    "gn:admin1_code":"07",
    "gn:asciiname":"Ait Maouch",
    "gn:country_code":"MA",
    "gn:dem":455,
    "gn:feature_class":"P",
    "gn:feature_code":"PPL",
    "gn:name":"A\u00eft M\u00e2ouch",
    "gn:population":0,
    "gn:timezone":"Africa/Casablanca",
    "iso:country":"MA",
    "name:und_x_variant":[
        "Douar A\u00eft Maouch",
        "A\u00eft M\u00e2ouch"
    ],
    "wof:name":"Ait Maouch",
    "wof:placetype":"locality"
},
  "geometry": {"coordinates":[-8.30194,31.52692],"type":"Point"}
}