{
  "type": "Feature",
  "properties": {
    "gn:admin1_code":"07",
    "gn:asciiname":"Ouch Filene",
    "gn:country_code":"MA",
    "gn:dem":917,
    "gn:feature_class":"P",
    "gn:feature_code":"PPL",
    "gn:name":"Ouch Filene",
    "gn:population":0,
    "gn:timezone":"Africa/Casablanca",
    "iso:country":"MA",
    "name:und_x_variant":[
        "Ouch Fil\u00e8n",
        "Ouch Filene"
    ],
    "wof:name":"Ouch Filene",
    "wof:placetype":"locality"
},
  "geometry": {"coordinates":[-8.11037,31.20458],"type":"Point"}
}