{
  "type": "Feature",
  "properties": {
    "gn:admin1_code":"7.0",
    "gn:asciiname":"Agadir Ayt Mechkor",
    "gn:country_code":"MA",
    "gn:dem":837,
    "gn:feature_class":"P",
    "gn:feature_code":"PPL",
    "gn:name":"Agadir Ayt Mechkor",
    "gn:population":0,
    "gn:timezone":"Africa/Casablanca",
    "iso:country":"MA",
    "wof:name":"Agadir Ayt Mechkor",
    "wof:placetype":"locality"
},
  "geometry": {"coordinates":[-7.78443,31.38168],"type":"Point"}
}