{
  "type": "Feature",
  "properties": {
    "gn:admin1_code":"04",
    "gn:asciiname":"Douar Chemmakh",
    "gn:country_code":"MA",
    "gn:dem":64,
    "gn:feature_class":"P",
    "gn:feature_code":"PPL",
    "gn:name":"Douar Chemmakh",
    "gn:population":0,
    "gn:timezone":"Africa/Casablanca",
    "iso:country":"MA",
    "name:und_x_variant":[
        "Douar Oulad Mejdoub",
        "Douar Chemmakh",
        "Oulad Mejdoub"
    ],
    "wof:name":"Douar Chemmakh",
    "wof:placetype":"locality"
},
  "geometry": {"coordinates":[-5.79912,34.68591],"type":"Point"}
}