{
  "type": "Feature",
  "properties": {
    "gn:admin1_code":"9.0",
    "gn:asciiname":"Imi Wandrat",
    "gn:country_code":"MA",
    "gn:dem":1416,
    "gn:feature_class":"P",
    "gn:feature_code":"PPL",
    "gn:name":"Imi Wandrat",
    "gn:population":0,
    "gn:timezone":"Africa/Casablanca",
    "iso:country":"MA",
    "wof:name":"Imi Wandrat",
    "wof:placetype":"locality"
},
  "geometry": {"coordinates":[-9.10458,29.8708],"type":"Point"}
}