{
  "type": "Feature",
  "properties": {
    "gn:admin1_code":"9.0",
    "gn:asciiname":"Tiguemmi Assouab El Houssine",
    "gn:country_code":"MA",
    "gn:dem":441,
    "gn:feature_class":"P",
    "gn:feature_code":"PPL",
    "gn:name":"Tiguemmi Assouab El Houssine",
    "gn:population":0,
    "gn:timezone":"Africa/Casablanca",
    "iso:country":"MA",
    "wof:name":"Tiguemmi Assouab El Houssine",
    "wof:placetype":"locality"
},
  "geometry": {"coordinates":[-9.7208,29.53775],"type":"Point"}
}