{
  "type": "Feature",
  "properties": {
    "gn:admin1_code":"7.0",
    "gn:asciiname":"Timsouriene",
    "gn:country_code":"MA",
    "gn:dem":1102,
    "gn:feature_class":"P",
    "gn:feature_code":"PPL",
    "gn:name":"Timsouriene",
    "gn:population":0,
    "gn:timezone":"Africa/Casablanca",
    "iso:country":"MA",
    "wof:name":"Timsouriene",
    "wof:placetype":"locality"
},
  "geometry": {"coordinates":[-8.25818,31.2118],"type":"Point"}
}