{
  "type": "Feature",
  "properties": {
    "gn:admin1_code":"5.0",
    "gn:asciiname":"Bou Remane",
    "gn:country_code":"MA",
    "gn:dem":951,
    "gn:feature_class":"P",
    "gn:feature_code":"PPL",
    "gn:name":"Bou Remane",
    "gn:population":0,
    "gn:timezone":"Africa/Casablanca",
    "iso:country":"MA",
    "wof:name":"Bou Remane",
    "wof:placetype":"locality"
},
  "geometry": {"coordinates":[-5.59087,32.85962],"type":"Point"}
}