{
  "type": "Feature",
  "properties": {
    "gn:country":"MA",
    "gn:fcode":"ADM3",
    "gn:population":8092,
    "iso:country":"MA",
    "name:ara_x_preferred":[
        "\u0631\u0648\u0627\u0636\u064a"
    ],
    "name:ary_x_preferred":[
        "\u0627\u0644\u0631\u0648\u0627\u0636\u064a"
    ],
    "name:bul_x_preferred":[
        "\u0420\u043e\u0443\u0430\u0434\u0438"
    ],
    "name:cat_x_preferred":[
        "Rouadi"
    ],
    "name:ceb_x_preferred":[
        "Rouadi"
    ],
    "name:eng_x_preferred":[
        "Rouadi"
    ],
    "name:fra_x_preferred":[
        "Rouadi"
    ],
    "name:fra_x_variant":[
        "Rouadi (CR)",
        "Rouadi (Commune Rurale)"
    ],
    "name:ita_x_preferred":[
        "Rouadi"
    ],
    "name:spa_x_preferred":[
        "Rouadi"
    ],
    "name:swe_x_preferred":[
        "Rouadi"
    ],
    "name:urd_x_preferred":[
        "\u0631\u0648\u0627\u0636\u06cc"
    ],
    "qs:name":"Rouadi",
    "qs:photos_9r":0,
    "qs:photos_sr":0,
    "qs:pop_sr":"5",
    "wd:wordcount":62,
    "wof:name":"Rouadi",
    "wof:placetype":"localadmin",
    "wof:population":8092
},
  "geometry": {"coordinates":[-4.17843,35.15613],"type":"Point"}
}