{
  "type": "Feature",
  "properties": {
    "gn:admin1_code":"7.0",
    "gn:asciiname":"Laarassiya",
    "gn:country_code":"MA",
    "gn:dem":128,
    "gn:feature_class":"P",
    "gn:feature_code":"PPL",
    "gn:name":"Laarassiya",
    "gn:population":0,
    "gn:timezone":"Africa/Casablanca",
    "iso:country":"MA",
    "wof:name":"Laarassiya",
    "wof:placetype":"locality"
},
  "geometry": {"coordinates":[-9.24055,32.09491],"type":"Point"}
}