{
  "type": "Feature",
  "properties": {
    "gn:admin1_code":"7.0",
    "gn:asciiname":"Ait Mokaila",
    "gn:country_code":"MA",
    "gn:dem":628,
    "gn:feature_class":"P",
    "gn:feature_code":"PPL",
    "gn:name":"A\u00eft Moka\u00efla",
    "gn:population":0,
    "gn:timezone":"Africa/Casablanca",
    "iso:country":"MA",
    "wof:name":"Ait Mokaila",
    "wof:placetype":"locality"
},
  "geometry": {"coordinates":[-9.173,31.4586],"type":"Point"}
}