{
  "type": "Feature",
  "properties": {
    "gn:admin1_code":"7.0",
    "gn:asciiname":"Ichatbine",
    "gn:country_code":"MA",
    "gn:dem":1205,
    "gn:feature_class":"P",
    "gn:feature_code":"PPL",
    "gn:name":"Ichatbine",
    "gn:population":0,
    "gn:timezone":"Africa/Casablanca",
    "iso:country":"MA",
    "wof:name":"Ichatbine",
    "wof:placetype":"locality"
},
  "geometry": {"coordinates":[-7.61721,31.43589],"type":"Point"}
}