{
  "type": "Feature",
  "properties": {
    "gn:admin1_code":"08",
    "gn:asciiname":"Zaouiet Dekhlaniya",
    "gn:country_code":"MA",
    "gn:dem":598,
    "gn:feature_class":"P",
    "gn:feature_code":"PPL",
    "gn:name":"Z\u00e2ou\u00efet Dekhl\u00e2niy\u00e2",
    "gn:population":0,
    "gn:timezone":"Africa/Casablanca",
    "iso:country":"MA",
    "wof:name":"Zaouiet Dekhlaniya",
    "wof:placetype":"locality"
},
  "geometry": {"coordinates":[-5.57,29.93],"type":"Point"}
}