{
  "type": "Feature",
  "properties": {
    "gn:admin1_code":"7.0",
    "gn:asciiname":"Douar Ait Tikrout",
    "gn:country_code":"MA",
    "gn:dem":261,
    "gn:feature_class":"P",
    "gn:feature_code":"PPL",
    "gn:name":"Douar Ait Tikrout",
    "gn:population":0,
    "gn:timezone":"Africa/Casablanca",
    "iso:country":"MA",
    "wof:name":"Douar Ait Tikrout",
    "wof:placetype":"locality"
},
  "geometry": {"coordinates":[-9.56713,31.51151],"type":"Point"}
}