{
  "type": "Feature",
  "properties": {
    "gn:admin1_code":"6.0",
    "gn:asciiname":"Bouch'aibou ben Lahbib",
    "gn:country_code":"MA",
    "gn:dem":182,
    "gn:feature_class":"P",
    "gn:feature_code":"PPL",
    "gn:name":"Bouch\u2019a\u00efbou ben Lahbib",
    "gn:population":0,
    "gn:timezone":"Africa/Casablanca",
    "iso:country":"MA",
    "wof:name":"Bouch'aibou ben Lahbib",
    "wof:placetype":"locality"
},
  "geometry": {"coordinates":[-8.11317,32.87862],"type":"Point"}
}