{
  "type": "Feature",
  "properties": {
    "gn:admin1_code":"7.0",
    "gn:asciiname":"El Husaine Sidi Abdellah",
    "gn:country_code":"MA",
    "gn:dem":263,
    "gn:feature_class":"P",
    "gn:feature_code":"PPL",
    "gn:name":"El Husaine Sidi Abdellah",
    "gn:population":0,
    "gn:timezone":"Africa/Casablanca",
    "iso:country":"MA",
    "wof:name":"El Husaine Sidi Abdellah",
    "wof:placetype":"locality"
},
  "geometry": {"coordinates":[-9.44862,31.56623],"type":"Point"}
}