{
  "type": "Feature",
  "properties": {
    "gn:admin1_code":"7.0",
    "gn:asciiname":"Ihaouatn",
    "gn:country_code":"MA",
    "gn:dem":1063,
    "gn:feature_class":"P",
    "gn:feature_code":"PPL",
    "gn:name":"Ihaouatn",
    "gn:population":0,
    "gn:timezone":"Africa/Casablanca",
    "iso:country":"MA",
    "wof:name":"Ihaouatn",
    "wof:placetype":"locality"
},
  "geometry": {"coordinates":[-9.09386,31.24281],"type":"Point"}
}