{
  "type": "Feature",
  "properties": {
    "gn:admin1_code":"03",
    "gn:asciiname":"Dlimet",
    "gn:country_code":"MA",
    "gn:dem":714,
    "gn:feature_class":"P",
    "gn:feature_code":"PPL",
    "gn:name":"Dlimet",
    "gn:population":0,
    "gn:timezone":"Africa/Casablanca",
    "iso:country":"MA",
    "name:und_x_variant":[
        "Delimiat",
        "Dlimet"
    ],
    "wof:name":"Dlimet",
    "wof:placetype":"locality"
},
  "geometry": {"coordinates":[-4.48928,34.60359],"type":"Point"}
}