{
  "type": "Feature",
  "properties": {
    "gn:admin1_code":"07",
    "gn:asciiname":"'Zib Assagl",
    "gn:country_code":"MA",
    "gn:dem":2250,
    "gn:feature_class":"P",
    "gn:feature_code":"PPL",
    "gn:name":"\u2019Zib Assagl",
    "gn:population":0,
    "gn:timezone":"Africa/Casablanca",
    "iso:country":"MA",
    "name:und_x_variant":[
        "\u2019Zib Assagl",
        "Adarza"
    ],
    "wof:name":"'Zib Assagl",
    "wof:placetype":"locality"
},
  "geometry": {"coordinates":[-7.56105,31.30344],"type":"Point"}
}