{
  "type": "Feature",
  "properties": {
    "gn:admin1_code":"07",
    "gn:asciiname":"Ben Ali",
    "gn:country_code":"MA",
    "gn:dem":185,
    "gn:feature_class":"P",
    "gn:feature_code":"PPL",
    "gn:name":"Ben Ali",
    "gn:population":0,
    "gn:timezone":"Africa/Casablanca",
    "iso:country":"MA",
    "name:deu_x_preferred":[
        "Ben Ali"
    ],
    "name:fra_x_preferred":[
        "Ben Ali"
    ],
    "wof:name":"Ben Ali",
    "wof:placetype":"locality"
},
  "geometry": {"coordinates":[-9.12516,32.10517],"type":"Point"}
}