{
  "type": "Feature",
  "properties": {
    "gn:admin1_code":"05",
    "gn:asciiname":"Ertmata",
    "gn:country_code":"MA",
    "gn:dem":644,
    "gn:feature_class":"P",
    "gn:feature_code":"PPL",
    "gn:name":"Ertmata",
    "gn:population":0,
    "gn:timezone":"Africa/Casablanca",
    "iso:country":"MA",
    "wof:name":"Ertmata",
    "wof:placetype":"locality"
},
  "geometry": {"coordinates":[-6.22249,32.40996],"type":"Point"}
}