{
  "type": "Feature",
  "properties": {
    "gn:admin1_code":"7.0",
    "gn:asciiname":"Douar Qbabja",
    "gn:country_code":"MA",
    "gn:dem":514,
    "gn:feature_class":"P",
    "gn:feature_code":"PPL",
    "gn:name":"Douar Qbabja",
    "gn:population":0,
    "gn:timezone":"Africa/Casablanca",
    "iso:country":"MA",
    "wof:name":"Douar Qbabja",
    "wof:placetype":"locality"
},
  "geometry": {"coordinates":[-7.7874,31.6197],"type":"Point"}
}