{
  "type": "Feature",
  "properties": {
    "gn:admin1_code":"7.0",
    "gn:asciiname":"Ayt Ajjilali",
    "gn:country_code":"MA",
    "gn:dem":705,
    "gn:feature_class":"P",
    "gn:feature_code":"PPL",
    "gn:name":"Ayt Ajjilali",
    "gn:population":0,
    "gn:timezone":"Africa/Casablanca",
    "iso:country":"MA",
    "wof:name":"Ayt Ajjilali",
    "wof:placetype":"locality"
},
  "geometry": {"coordinates":[-7.30881,31.75408],"type":"Point"}
}