{
  "type": "Feature",
  "properties": {
    "gn:admin1_code":"08",
    "gn:asciiname":"Aguerzga",
    "gn:country_code":"MA",
    "gn:dem":1893,
    "gn:feature_class":"P",
    "gn:feature_code":"PPL",
    "gn:name":"Aguerzga",
    "gn:population":0,
    "gn:timezone":"Africa/Casablanca",
    "iso:country":"MA",
    "name:und_x_variant":[
        "Aguerzgua",
        "Aguerzga"
    ],
    "wof:name":"Aguerzga",
    "wof:placetype":"locality"
},
  "geometry": {"coordinates":[-6.71598,31.30515],"type":"Point"}
}