{
  "type": "Feature",
  "properties": {
    "gn:admin1_code":"2.0",
    "gn:asciiname":"Dar Bou Felfoul",
    "gn:country_code":"MA",
    "gn:dem":44,
    "gn:feature_class":"P",
    "gn:feature_code":"PPL",
    "gn:name":"Dar Bou Felfoul",
    "gn:population":0,
    "gn:timezone":"Africa/Casablanca",
    "iso:country":"MA",
    "wof:name":"Dar Bou Felfoul",
    "wof:placetype":"locality"
},
  "geometry": {"coordinates":[-2.86645,35.07353],"type":"Point"}
}