{
  "type": "Feature",
  "properties": {
    "gn:admin1_code":"7.0",
    "gn:asciiname":"Ch'ibat",
    "gn:country_code":"MA",
    "gn:dem":63,
    "gn:feature_class":"P",
    "gn:feature_code":"PPL",
    "gn:name":"Ch\u2019ibat",
    "gn:population":0,
    "gn:timezone":"Africa/Casablanca",
    "iso:country":"MA",
    "wof:name":"Ch'ibat",
    "wof:placetype":"locality"
},
  "geometry": {"coordinates":[-9.31072,32.09331],"type":"Point"}
}