{
  "type": "Feature",
  "properties": {
    "gn:admin1_code":"7.0",
    "gn:asciiname":"Douar Oulad Lhiri",
    "gn:country_code":"MA",
    "gn:dem":262,
    "gn:feature_class":"P",
    "gn:feature_code":"PPL",
    "gn:name":"Douar Oulad Lhiri",
    "gn:population":0,
    "gn:timezone":"Africa/Casablanca",
    "iso:country":"MA",
    "wof:name":"Douar Oulad Lhiri",
    "wof:placetype":"locality"
},
  "geometry": {"coordinates":[-9.10277,32.04548],"type":"Point"}
}