{
  "type": "Feature",
  "properties": {
    "gn:admin1_code":"7.0",
    "gn:asciiname":"Id Ali Ou Amer",
    "gn:country_code":"MA",
    "gn:dem":165,
    "gn:feature_class":"P",
    "gn:feature_code":"PPL",
    "gn:name":"Id Ali Ou Amer",
    "gn:population":0,
    "gn:timezone":"Africa/Casablanca",
    "iso:country":"MA",
    "wof:name":"Id Ali Ou Amer",
    "wof:placetype":"locality"
},
  "geometry": {"coordinates":[-9.80388,31.21265],"type":"Point"}
}