{
  "type": "Feature",
  "properties": {
    "gn:admin1_code":"9.0",
    "gn:asciiname":"Askstou",
    "gn:country_code":"MA",
    "gn:dem":654,
    "gn:feature_class":"P",
    "gn:feature_code":"PPL",
    "gn:name":"Askstou",
    "gn:population":0,
    "gn:timezone":"Africa/Casablanca",
    "iso:country":"MA",
    "wof:name":"Askstou",
    "wof:placetype":"locality"
},
  "geometry": {"coordinates":[-8.61651,30.39354],"type":"Point"}
}