{
  "type": "Feature",
  "properties": {
    "gn:admin1_code":"05",
    "gn:asciiname":"Imi -n- Ounfid",
    "gn:country_code":"MA",
    "gn:dem":1938,
    "gn:elevation":"0.0",
    "gn:feature_class":"P",
    "gn:feature_code":"PPL",
    "gn:name":"Imi -n- Ounfid",
    "gn:population":0,
    "gn:timezone":"Africa/Casablanca",
    "iso:country":"MA",
    "name:und_x_variant":[
        "mi-n-Oumfid",
        "Imi n\u2019Oumfid",
        "Imi -n- Ounfid"
    ],
    "wof:name":"Imi -n- Ounfid",
    "wof:placetype":"locality"
},
  "geometry": {"coordinates":[-6.62448,31.5505],"type":"Point"}
}