{
  "type": "Feature",
  "properties": {
    "gn:admin1_code":"07",
    "gn:asciiname":"Taguiout",
    "gn:country_code":"MA",
    "gn:dem":283,
    "gn:feature_class":"P",
    "gn:feature_code":"PPL",
    "gn:name":"Taguiout",
    "gn:population":0,
    "gn:timezone":"Africa/Casablanca",
    "iso:country":"MA",
    "name:und_x_variant":[
        "Taguiyoute",
        "Taguiyout",
        "Taguiout"
    ],
    "wof:name":"Taguiout",
    "wof:placetype":"locality"
},
  "geometry": {"coordinates":[-9.76865,30.98781],"type":"Point"}
}