{
  "type": "Feature",
  "properties": {
    "gn:admin1_code":"7.0",
    "gn:asciiname":"Ch'ab Nda",
    "gn:country_code":"MA",
    "gn:dem":672,
    "gn:feature_class":"P",
    "gn:feature_code":"PPL",
    "gn:name":"Ch\u2019ab Nda",
    "gn:population":0,
    "gn:timezone":"Africa/Casablanca",
    "iso:country":"MA",
    "wof:name":"Ch'ab Nda",
    "wof:placetype":"locality"
},
  "geometry": {"coordinates":[-7.49617,31.96134],"type":"Point"}
}