{
  "type": "Feature",
  "properties": {
    "gn:admin1_code":"5.0",
    "gn:asciiname":"Ait Wa'la",
    "gn:country_code":"MA",
    "gn:dem":1288,
    "gn:feature_class":"P",
    "gn:feature_code":"PPL",
    "gn:name":"A\u00eft Wa\u2019la",
    "gn:population":0,
    "gn:timezone":"Africa/Casablanca",
    "iso:country":"MA",
    "wof:name":"Ait Wa'la",
    "wof:placetype":"locality"
},
  "geometry": {"coordinates":[-6.62058,31.98951],"type":"Point"}
}