{
  "type": "Feature",
  "properties": {
    "gn:admin1_code":"07",
    "gn:asciiname":"Douar Laababat",
    "gn:country_code":"MA",
    "gn:dem":416,
    "gn:feature_class":"P",
    "gn:feature_code":"PPL",
    "gn:name":"Douar Laababat",
    "gn:population":0,
    "gn:timezone":"Africa/Casablanca",
    "iso:country":"MA",
    "name:und_x_variant":[
        "Douar el Ababat"
    ],
    "wof:name":"Douar Laababat",
    "wof:placetype":"locality"
},
  "geometry": {"coordinates":[-7.57031,32.17798],"type":"Point"}
}