{
  "type": "Feature",
  "properties": {
    "gn:admin1_code":"4.0",
    "gn:asciiname":"Lfoqra",
    "gn:country_code":"MA",
    "gn:dem":250,
    "gn:feature_class":"P",
    "gn:feature_code":"PPL",
    "gn:name":"Lfoqra",
    "gn:population":0,
    "gn:timezone":"Africa/Casablanca",
    "iso:country":"MA",
    "wof:name":"Lfoqra",
    "wof:placetype":"locality"
},
  "geometry": {"coordinates":[-6.78922,33.77526],"type":"Point"}
}