{
  "type": "Feature",
  "properties": {
    "gn:admin1_code":"05",
    "gn:asciiname":"Khelalta",
    "gn:country_code":"MA",
    "gn:dem":619,
    "gn:feature_class":"P",
    "gn:feature_code":"PPL",
    "gn:name":"Khelalta",
    "gn:population":0,
    "gn:timezone":"Africa/Casablanca",
    "iso:country":"MA",
    "name:und_x_variant":[
        "Khelalka",
        "Khelalta"
    ],
    "wof:name":"Khelalta",
    "wof:placetype":"locality"
},
  "geometry": {"coordinates":[-6.9466,32.74606],"type":"Point"}
}