{
  "type": "Feature",
  "properties": {
    "gn:admin1_code":"7.0",
    "gn:asciiname":"Douar Lehfayba",
    "gn:country_code":"MA",
    "gn:dem":307,
    "gn:feature_class":"P",
    "gn:feature_code":"PPL",
    "gn:name":"Douar Lehfayba",
    "gn:population":0,
    "gn:timezone":"Africa/Casablanca",
    "iso:country":"MA",
    "wof:name":"Douar Lehfayba",
    "wof:placetype":"locality"
},
  "geometry": {"coordinates":[-8.73354,31.95886],"type":"Point"}
}