{
  "type": "Feature",
  "properties": {
    "gn:admin1_code":"6.0",
    "gn:asciiname":"Oulad Ali Ben Allou",
    "gn:country_code":"MA",
    "gn:dem":349,
    "gn:feature_class":"P",
    "gn:feature_code":"PPL",
    "gn:name":"Oulad Ali Ben Allou",
    "gn:population":0,
    "gn:timezone":"Africa/Casablanca",
    "iso:country":"MA",
    "wof:name":"Oulad Ali Ben Allou",
    "wof:placetype":"locality"
},
  "geometry": {"coordinates":[-7.30282,33.2276],"type":"Point"}
}