{
  "type": "Feature",
  "properties": {
    "gn:admin1_code":"07",
    "gn:asciiname":"Guemirs",
    "gn:country_code":"MA",
    "gn:dem":795,
    "gn:feature_class":"P",
    "gn:feature_code":"PPL",
    "gn:name":"Guemirs",
    "gn:population":0,
    "gn:timezone":"Africa/Casablanca",
    "iso:country":"MA",
    "wof:name":"Guemirs",
    "wof:placetype":"locality"
},
  "geometry": {"coordinates":[-9.3531,31.19228],"type":"Point"}
}