{
  "type": "Feature",
  "properties": {
    "gn:admin1_code":"2.0",
    "gn:asciiname":"Dar Abd Slam",
    "gn:country_code":"MA",
    "gn:dem":382,
    "gn:feature_class":"P",
    "gn:feature_code":"PPL",
    "gn:name":"Dar Abd Slam",
    "gn:population":0,
    "gn:timezone":"Africa/Casablanca",
    "iso:country":"MA",
    "wof:name":"Dar Abd Slam",
    "wof:placetype":"locality"
},
  "geometry": {"coordinates":[-3.48192,35.01573],"type":"Point"}
}