{
  "type": "Feature",
  "properties": {
    "gn:admin1_code":"7.0",
    "gn:asciiname":"Jbar",
    "gn:country_code":"MA",
    "gn:dem":798,
    "gn:feature_class":"P",
    "gn:feature_code":"PPL",
    "gn:name":"Jbar",
    "gn:population":0,
    "gn:timezone":"Africa/Casablanca",
    "iso:country":"MA",
    "wof:name":"Jbar",
    "wof:placetype":"locality"
},
  "geometry": {"coordinates":[-9.23209,31.32372],"type":"Point"}
}