{
  "type": "Feature",
  "properties": {
    "gn:admin1_code":"47.0",
    "gn:asciiname":"Ouaousseft",
    "gn:country_code":"MA",
    "gn:dem":1526,
    "gn:feature_class":"P",
    "gn:feature_code":"PPL",
    "gn:name":"Ouaousseft",
    "gn:population":0,
    "gn:timezone":"Africa/Casablanca",
    "iso:country":"MA",
    "wof:name":"Ouaousseft",
    "wof:placetype":"locality"
},
  "geometry": {"coordinates":[-7.94578,31.18005],"type":"Point"}
}