{
  "type": "Feature",
  "properties": {
    "gn:admin1_code":"1.0",
    "gn:asciiname":"Azriba",
    "gn:country_code":"MA",
    "gn:dem":147,
    "gn:feature_class":"P",
    "gn:feature_code":"PPL",
    "gn:name":"Azriba",
    "gn:population":0,
    "gn:timezone":"Africa/Casablanca",
    "iso:country":"MA",
    "wof:name":"Azriba",
    "wof:placetype":"locality"
},
  "geometry": {"coordinates":[-5.82808,35.25379],"type":"Point"}
}