{
  "type": "Feature",
  "properties": {
    "iso:country":"MA",
    "qs:gn_country":"MA",
    "qs:gn_fcode":"PPL",
    "qs:gn_pop":0,
    "qs:name":"Had Beni Chiker",
    "qs:name_adm0":"\u0627\u0644\u0645\u063a\u0631\u0628",
    "qs:name_adm1":"\u0627\u0644\u062c\u0647\u0629 \u0627\u0644\u0634\u0631\u0642\u064a\u0629",
    "qs:photos":18,
    "qs:photos_1k":4,
    "qs:photos_9k":1,
    "qs:photos_9r":1,
    "qs:photos_all":18,
    "qs:photos_sr":1,
    "qs:placetype":"Town",
    "qs:pop_sr":"0",
    "qs:woe_adm0":23424893,
    "wof:name":"Had Beni Chiker",
    "wof:placetype":"locality"
},
  "geometry": {"coordinates":[-3.01452,35.27652],"type":"Point"}
}