{
  "type": "Feature",
  "properties": {
    "gn:admin1_code":"47.0",
    "gn:asciiname":"Douar Lachgoura",
    "gn:country_code":"MA",
    "gn:dem":500,
    "gn:feature_class":"P",
    "gn:feature_code":"PPL",
    "gn:name":"Douar Lachgoura",
    "gn:population":0,
    "gn:timezone":"Africa/Casablanca",
    "iso:country":"MA",
    "wof:name":"Douar Lachgoura",
    "wof:placetype":"locality"
},
  "geometry": {"coordinates":[-8.12139,31.53746],"type":"Point"}
}