{
  "type": "Feature",
  "properties": {
    "gn:admin1_code":"09",
    "gn:asciiname":"Ait Laati",
    "gn:country_code":"MA",
    "gn:dem":209,
    "gn:feature_class":"P",
    "gn:feature_code":"PPL",
    "gn:name":"Ait Laati",
    "gn:population":0,
    "gn:timezone":"Africa/Casablanca",
    "iso:country":"MA",
    "name:und_x_variant":[
        "A\u00eft Lhati",
        "A\u00eft Laati",
        "Ait Laati"
    ],
    "wof:name":"Ait Laati",
    "wof:placetype":"locality"
},
  "geometry": {"coordinates":[-9.28603,30.10906],"type":"Point"}
}