{
  "type": "Feature",
  "properties": {
    "gn:admin1_code":"02",
    "gn:asciiname":"Douar Aanguiche",
    "gn:country_code":"MA",
    "gn:dem":621,
    "gn:feature_class":"P",
    "gn:feature_code":"PPL",
    "gn:name":"Douar Aanguiche",
    "gn:population":0,
    "gn:timezone":"Africa/Casablanca",
    "iso:country":"MA",
    "name:und_x_variant":[
        "Angouich",
        "Angu\u00eech",
        "Douar Aanguiche"
    ],
    "wof:name":"Douar Aanguiche",
    "wof:placetype":"locality"
},
  "geometry": {"coordinates":[-3.61298,35.05864],"type":"Point"}
}