{
  "type": "Feature",
  "properties": {
    "gn:admin1_code":"5.0",
    "gn:asciiname":"Tamajjout",
    "gn:country_code":"MA",
    "gn:dem":913,
    "gn:feature_class":"P",
    "gn:feature_code":"PPL",
    "gn:name":"Tamajjout",
    "gn:population":0,
    "gn:timezone":"Africa/Casablanca",
    "iso:country":"MA",
    "wof:name":"Tamajjout",
    "wof:placetype":"locality"
},
  "geometry": {"coordinates":[-7.02672,31.73253],"type":"Point"}
}