{
  "type": "Feature",
  "properties": {
    "gn:admin1_code":"8.0",
    "gn:asciiname":"Azlag-n-Tamdwiyn",
    "gn:country_code":"MA",
    "gn:dem":2559,
    "gn:feature_class":"P",
    "gn:feature_code":"PPL",
    "gn:name":"Azlag-n-Tamdwiyn",
    "gn:population":0,
    "gn:timezone":"Africa/Casablanca",
    "iso:country":"MA",
    "wof:name":"Azlag-n-Tamdwiyn",
    "wof:placetype":"locality"
},
  "geometry": {"coordinates":[-7.33773,31.29387],"type":"Point"}
}