{
  "type": "Feature",
  "properties": {
    "gn:admin1_code":"03",
    "gn:asciiname":"Douar Ain Bou Harrouch",
    "gn:country_code":"MA",
    "gn:dem":258,
    "gn:feature_class":"P",
    "gn:feature_code":"PPL",
    "gn:name":"Douar Ain Bou Harrouch",
    "gn:population":0,
    "gn:timezone":"Africa/Casablanca",
    "iso:country":"MA",
    "wof:name":"Douar Ain Bou Harrouch",
    "wof:placetype":"locality"
},
  "geometry": {"coordinates":[-4.65226,34.48324],"type":"Point"}
}