{
  "type": "Feature",
  "properties": {
    "gn:admin1_code":"7.0",
    "gn:asciiname":"Ikraymiyine",
    "gn:country_code":"MA",
    "gn:dem":379,
    "gn:feature_class":"P",
    "gn:feature_code":"PPL",
    "gn:name":"Ikraymiyine",
    "gn:population":0,
    "gn:timezone":"Africa/Casablanca",
    "iso:country":"MA",
    "wof:name":"Ikraymiyine",
    "wof:placetype":"locality"
},
  "geometry": {"coordinates":[-9.67983,31.20397],"type":"Point"}
}