{
  "type": "Feature",
  "properties": {
    "gn:admin1_code":"4.0",
    "gn:asciiname":"El Menzeh",
    "gn:country_code":"MA",
    "gn:dem":60,
    "gn:feature_class":"P",
    "gn:feature_code":"PPL",
    "gn:name":"El Menzeh",
    "gn:population":0,
    "gn:timezone":"Africa/Casablanca",
    "iso:country":"MA",
    "wof:name":"El Menzeh",
    "wof:placetype":"locality"
},
  "geometry": {"coordinates":[-6.46344,34.28363],"type":"Point"}
}