{
  "type": "Feature",
  "properties": {
    "gn:admin1_code":"6.0",
    "gn:asciiname":"Lebbada",
    "gn:country_code":"MA",
    "gn:dem":330,
    "gn:feature_class":"P",
    "gn:feature_code":"PPL",
    "gn:name":"Lebbada",
    "gn:population":0,
    "gn:timezone":"Africa/Casablanca",
    "iso:country":"MA",
    "wof:name":"Lebbada",
    "wof:placetype":"locality"
},
  "geometry": {"coordinates":[-6.99034,33.29190999999999],"type":"Point"}
}