{
  "type": "Feature",
  "properties": {
    "gn:admin1_code":"03",
    "gn:asciiname":"Dar El Caid Haddou",
    "gn:country_code":"MA",
    "gn:dem":739,
    "gn:feature_class":"P",
    "gn:feature_code":"PPL",
    "gn:name":"Dar El Caid Haddou",
    "gn:population":0,
    "gn:timezone":"Africa/Casablanca",
    "iso:country":"MA",
    "name:und_x_variant":[
        "Dar Ca\u00efd Addou"
    ],
    "wof:name":"Dar El Caid Haddou",
    "wof:placetype":"locality"
},
  "geometry": {"coordinates":[-5.32176,33.78652],"type":"Point"}
}