{
  "type": "Feature",
  "properties": {
    "gn:admin1_code":"5.0",
    "gn:asciiname":"Tizi-n-Tarba't",
    "gn:country_code":"MA",
    "gn:dem":1702,
    "gn:feature_class":"P",
    "gn:feature_code":"PPL",
    "gn:name":"Tizi-n-Tarba\u2019t",
    "gn:population":0,
    "gn:timezone":"Africa/Casablanca",
    "iso:country":"MA",
    "wof:name":"Tizi-n-Tarba't",
    "wof:placetype":"locality"
},
  "geometry": {"coordinates":[-6.55124,31.85228],"type":"Point"}
}