{
  "type": "Feature",
  "properties": {
    "gn:admin1_code":"03",
    "gn:asciiname":"Douar Al Qacba",
    "gn:country_code":"MA",
    "gn:dem":831,
    "gn:feature_class":"P",
    "gn:feature_code":"PPL",
    "gn:name":"Douar Al Qa\u00e7ba",
    "gn:population":0,
    "gn:timezone":"Africa/Casablanca",
    "iso:country":"MA",
    "name:und_x_variant":[
        "El Qasba",
        "El Kasba",
        "Douar Al Qa\u00e7ba"
    ],
    "wof:name":"Douar Al Qacba",
    "wof:placetype":"locality"
},
  "geometry": {"coordinates":[-4.46027,33.77281],"type":"Point"}
}