{
  "type": "Feature",
  "properties": {
    "gn:admin1_code":"02",
    "gn:asciiname":"Talezart",
    "gn:country_code":"MA",
    "gn:dem":503,
    "gn:feature_class":"P",
    "gn:feature_code":"PPL",
    "gn:name":"Talezart",
    "gn:population":0,
    "gn:timezone":"Africa/Casablanca",
    "iso:country":"MA",
    "name:und_x_variant":[
        "Talezzerte",
        "Talezzert",
        "Talezart",
        "Talezzert Talezart"
    ],
    "wof:name":"Talezart",
    "wof:placetype":"locality"
},
  "geometry": {"coordinates":[-2.56989,34.79277],"type":"Point"}
}