{
  "type": "Feature",
  "properties": {
    "gn:admin1_code":"08",
    "gn:asciiname":"Azib n'Idmamene",
    "gn:country_code":"MA",
    "gn:dem":2384,
    "gn:feature_class":"P",
    "gn:feature_code":"PPL",
    "gn:name":"Azib n\u2019Idmamene",
    "gn:population":0,
    "gn:timezone":"Africa/Casablanca",
    "iso:country":"MA",
    "wof:name":"Azib n'Idmamene",
    "wof:placetype":"locality"
},
  "geometry": {"coordinates":[-6.63238,31.42345],"type":"Point"}
}