{
  "type": "Feature",
  "properties": {
    "gn:admin1_code":"01",
    "gn:asciiname":"Tangero",
    "gn:country_code":"MA",
    "gn:dem":308,
    "gn:feature_class":"P",
    "gn:feature_code":"PPL",
    "gn:name":"Tangero",
    "gn:population":0,
    "gn:timezone":"Africa/Casablanca",
    "iso:country":"MA",
    "name:und_x_variant":[
        "Tannjerou",
        "Tanjro",
        "Tangero"
    ],
    "wof:name":"Tangero",
    "wof:placetype":"locality"
},
  "geometry": {"coordinates":[-5.44368,34.95585999999999],"type":"Point"}
}