{
  "type": "Feature",
  "properties": {
    "gn:admin1_code":"09",
    "gn:asciiname":"Tizi Mous",
    "gn:country_code":"MA",
    "gn:dem":999,
    "gn:feature_class":"P",
    "gn:feature_code":"PPL",
    "gn:name":"Tizi Mous",
    "gn:population":0,
    "gn:timezone":"Africa/Casablanca",
    "iso:country":"MA",
    "name:und_x_variant":[
        "Tizi Mouss",
        "Tizi Moust",
        "Tizi Mous"
    ],
    "wof:name":"Tizi Mous",
    "wof:placetype":"locality"
},
  "geometry": {"coordinates":[-9.37084,29.59951],"type":"Point"}
}