{
  "type": "Feature",
  "properties": {
    "gn:admin1_code":"05",
    "gn:asciiname":"Igourdane",
    "gn:country_code":"MA",
    "gn:dem":1185,
    "gn:feature_class":"P",
    "gn:feature_code":"PPL",
    "gn:name":"Igourdane",
    "gn:population":0,
    "gn:timezone":"Africa/Casablanca",
    "iso:country":"MA",
    "name:und_x_variant":[
        "A\u00eft Igourdane",
        "Igourdane"
    ],
    "wof:name":"Igourdane",
    "wof:placetype":"locality"
},
  "geometry": {"coordinates":[-6.65655,32.04071],"type":"Point"}
}