{
  "type": "Feature",
  "properties": {
    "gn:admin1_code":"08",
    "gn:asciiname":"El Had",
    "gn:country_code":"MA",
    "gn:dem":855,
    "gn:feature_class":"P",
    "gn:feature_code":"PPL",
    "gn:name":"El Had",
    "gn:population":0,
    "gn:timezone":"Africa/Casablanca",
    "iso:country":"MA",
    "wof:name":"El Had",
    "wof:placetype":"locality"
},
  "geometry": {"coordinates":[-6.14417,30.6521],"type":"Point"}
}