{
  "type": "Feature",
  "properties": {
    "gn:admin1_code":"7.0",
    "gn:asciiname":"Dar Si-Rahal",
    "gn:country_code":"MA",
    "gn:dem":421,
    "gn:feature_class":"P",
    "gn:feature_code":"PPL",
    "gn:name":"Dar Si-Rahal",
    "gn:population":0,
    "gn:timezone":"Africa/Casablanca",
    "iso:country":"MA",
    "wof:name":"Dar Si-Rahal",
    "wof:placetype":"locality"
},
  "geometry": {"coordinates":[-7.70235,32.17678],"type":"Point"}
}