{
  "type": "Feature",
  "properties": {
    "gn:admin1_code":"2.0",
    "gn:asciiname":"Douar Dzioua",
    "gn:country_code":"MA",
    "gn:dem":219,
    "gn:feature_class":"P",
    "gn:feature_code":"PPL",
    "gn:name":"Douar Dzioua",
    "gn:population":0,
    "gn:timezone":"Africa/Casablanca",
    "iso:country":"MA",
    "wof:name":"Douar Dzioua",
    "wof:placetype":"locality"
},
  "geometry": {"coordinates":[-2.49435,34.85111],"type":"Point"}
}