{
  "type": "Feature",
  "properties": {
    "gn:admin1_code":"3.0",
    "gn:asciiname":"Douar Ait Bou Attar",
    "gn:country_code":"MA",
    "gn:dem":614,
    "gn:feature_class":"P",
    "gn:feature_code":"PPL",
    "gn:name":"Douar Ait Bou Attar",
    "gn:population":0,
    "gn:timezone":"Africa/Casablanca",
    "iso:country":"MA",
    "wof:name":"Douar Ait Bou Attar",
    "wof:placetype":"locality"
},
  "geometry": {"coordinates":[-4.60927,33.95975],"type":"Point"}
}