{
  "type": "Feature",
  "properties": {
    "gn:admin1_code":"7.0",
    "gn:asciiname":"El Maachat",
    "gn:country_code":"MA",
    "gn:dem":118,
    "gn:feature_class":"P",
    "gn:feature_code":"PPL",
    "gn:name":"El Maachat",
    "gn:population":0,
    "gn:timezone":"Africa/Casablanca",
    "iso:country":"MA",
    "wof:name":"El Maachat",
    "wof:placetype":"locality"
},
  "geometry": {"coordinates":[-9.12016,32.33128],"type":"Point"}
}