{
  "type": "Feature",
  "properties": {
    "gn:admin1_code":"09",
    "gn:asciiname":"Aniy",
    "gn:country_code":"MA",
    "gn:dem":1185,
    "gn:feature_class":"P",
    "gn:feature_code":"PPL",
    "gn:name":"Aniy",
    "gn:population":0,
    "gn:timezone":"Africa/Casablanca",
    "iso:country":"MA",
    "name:und_x_variant":[
        "Amy",
        "Ani",
        "Ane\u00ef",
        "Aniy"
    ],
    "wof:name":"Aniy",
    "wof:placetype":"locality"
},
  "geometry": {"coordinates":[-8.65258,30.20732000000001],"type":"Point"}
}