{
  "type": "Feature",
  "properties": {
    "gn:admin1_code":"07",
    "gn:asciiname":"Agadir N'Ait-Brahim",
    "gn:country_code":"MA",
    "gn:dem":957,
    "gn:feature_class":"P",
    "gn:feature_code":"PPL",
    "gn:name":"Agadir N\u2019A\u00eft-Brahim",
    "gn:population":0,
    "gn:timezone":"Africa/Casablanca",
    "iso:country":"MA",
    "name:und_x_variant":[
        "Agadir N\u2019A\u00eft-Brahim",
        "Agadir n\u2019A\u00eft Ali"
    ],
    "wof:name":"Agadir N'Ait-Brahim",
    "wof:placetype":"locality"
},
  "geometry": {"coordinates":[-9.2588,31.03038],"type":"Point"}
}