{
  "type": "Feature",
  "properties": {
    "gn:admin1_code":"7.0",
    "gn:asciiname":"Dar Erraji Hachem",
    "gn:country_code":"MA",
    "gn:dem":358,
    "gn:feature_class":"P",
    "gn:feature_code":"PPL",
    "gn:name":"Dar Erraji Hachem",
    "gn:population":0,
    "gn:timezone":"Africa/Casablanca",
    "iso:country":"MA",
    "wof:name":"Dar Erraji Hachem",
    "wof:placetype":"locality"
},
  "geometry": {"coordinates":[-7.96793,32.60456],"type":"Point"}
}