{
  "type": "Feature",
  "properties": {
    "gn:admin1_code":"9.0",
    "gn:asciiname":"El Borj n'Tfilcht",
    "gn:country_code":"MA",
    "gn:dem":411,
    "gn:feature_class":"P",
    "gn:feature_code":"PPL",
    "gn:name":"El Borj n\u2019Tfilcht",
    "gn:population":0,
    "gn:timezone":"Africa/Casablanca",
    "iso:country":"MA",
    "wof:name":"El Borj n'Tfilcht",
    "wof:placetype":"locality"
},
  "geometry": {"coordinates":[-9.20111,30.16524],"type":"Point"}
}