{
  "type": "Feature",
  "properties": {
    "gn:admin1_code":"55",
    "gn:asciiname":"Agouni Izim",
    "gn:country_code":"MA",
    "gn:dem":1393,
    "gn:feature_class":"P",
    "gn:feature_code":"PPL",
    "gn:name":"Agouni Izim",
    "gn:population":0,
    "gn:timezone":"Africa/Casablanca",
    "iso:country":"MA",
    "wof:name":"Agouni Izim",
    "wof:placetype":"locality"
},
  "geometry": {"coordinates":[-9.23,29.38],"type":"Point"}
}