{
  "type": "Feature",
  "properties": {
    "gn:admin1_code":"7.0",
    "gn:asciiname":"El Harch",
    "gn:country_code":"MA",
    "gn:dem":647,
    "gn:feature_class":"P",
    "gn:feature_code":"PPL",
    "gn:name":"El Harch",
    "gn:population":0,
    "gn:timezone":"Africa/Casablanca",
    "iso:country":"MA",
    "wof:name":"El Harch",
    "wof:placetype":"locality"
},
  "geometry": {"coordinates":[-8.59766,31.27832],"type":"Point"}
}