{
  "type": "Feature",
  "properties": {
    "gn:country":"MA",
    "gn:fcode":"ADM3",
    "gn:population":7880,
    "iso:country":"MA",
    "name:ara_x_preferred":[
        "\u0633\u064a\u062f\u064a \u0639\u0644\u064a \u0627\u0644\u0643\u0631\u0627\u062a\u064a"
    ],
    "name:ara_x_variant":[
        "\u0633\u064a\u062f\u064a \u0628\u0648\u0644\u0639\u0644\u0627\u0645"
    ],
    "name:ary_x_preferred":[
        "\u0633\u064a\u062f\u064a \u0628\u0648\u0639\u0644\u0627\u0645"
    ],
    "name:cat_x_preferred":[
        "Sidi Boulaalam"
    ],
    "name:ceb_x_preferred":[
        "Sidi Boulaalam"
    ],
    "name:eng_x_preferred":[
        "Sidi Boulaalam"
    ],
    "name:fra_x_preferred":[
        "Sidi Boulaalam"
    ],
    "name:fra_x_variant":[
        "Sidi Boulaalam (CR)",
        "Sidi Boulaalam (Commune Rurale)"
    ],
    "name:ita_x_preferred":[
        "Sidi Boulaalam"
    ],
    "name:jpn_x_preferred":[
        "\u30b7\u30c7\u30a3\u30fb\u30d6\u30e9\u30a2\u30e9\u30e0"
    ],
    "qs:name":"Sidi Boulaalam",
    "qs:photos_9r":0,
    "qs:photos_sr":0,
    "qs:pop_sr":"5",
    "wd:wordcount":62,
    "wof:name":"Sidi Boulaalam",
    "wof:placetype":"localadmin",
    "wof:population":7880
},
  "geometry": {"coordinates":[-9.28276,31.69775],"type":"Point"}
}