{
  "type": "Feature",
  "properties": {
    "gn:admin1_code":"7.0",
    "gn:asciiname":"Stara",
    "gn:country_code":"MA",
    "gn:dem":385,
    "gn:feature_class":"P",
    "gn:feature_code":"PPL",
    "gn:name":"Stara",
    "gn:population":0,
    "gn:timezone":"Africa/Casablanca",
    "iso:country":"MA",
    "name:ceb_x_preferred":[
        "Stara"
    ],
    "name:fra_x_preferred":[
        "Stara"
    ],
    "name:pol_x_preferred":[
        "Stara"
    ],
    "name:ukr_x_preferred":[
        "\u0421\u0442\u0430\u0440\u0430"
    ],
    "wof:name":"Stara",
    "wof:placetype":"locality"
},
  "geometry": {"coordinates":[-9.44233,31.47244],"type":"Point"}
}