{
  "type": "Feature",
  "properties": {
    "gn:admin1_code":"7.0",
    "gn:asciiname":"Khamkham",
    "gn:country_code":"MA",
    "gn:dem":124,
    "gn:feature_class":"P",
    "gn:feature_code":"PPL",
    "gn:name":"Khamkham",
    "gn:population":0,
    "gn:timezone":"Africa/Casablanca",
    "iso:country":"MA",
    "wof:name":"Khamkham",
    "wof:placetype":"locality"
},
  "geometry": {"coordinates":[-9.17718,32.38108],"type":"Point"}
}