{
  "type": "Feature",
  "properties": {
    "gn:gn_country":"MA",
    "gn:gn_fcode":"ADM3",
    "gn:gn_pop":8112,
    "gn:population":8112,
    "iso:country":"MA",
    "name:ara_x_preferred":[
        "\u0645\u0648\u0644\u0627\u064a \u0628\u0648\u0633\u0644\u0647\u0627\u0645"
    ],
    "name:ara_x_variant":[
        "\u0622\u064a\u062a \u062d\u0643\u064a\u0645 \u0622\u064a\u062a \u064a\u0632\u064a\u062f"
    ],
    "name:azb_x_preferred":[
        "\u0622\u06cc\u062a \u062d\u06a9\u06cc\u0645 \u0622\u06cc\u062a \u06cc\u0632\u06cc\u062f"
    ],
    "name:cat_x_preferred":[
        "Ait Hkim Ait Yzid"
    ],
    "name:ceb_x_preferred":[
        "Ait Hkim Ait Yzid"
    ],
    "name:fas_x_preferred":[
        "\u0622\u06cc\u062a \u062d\u06a9\u06cc\u0645 \u0622\u06cc\u062a \u06cc\u0632\u06cc\u062f"
    ],
    "name:fra_x_preferred":[
        "Ait Hkim Ait Yzid"
    ],
    "name:fra_x_variant":[
        "Ait Hkim Ait Yzid (CR)",
        "Ait Hkim Ait Yzid (Commune Rurale)",
        "A\u00eft Hkim-A\u00eft Yzid"
    ],
    "name:ita_x_preferred":[
        "Ait Hkim-Ait Yzid"
    ],
    "name:swe_x_preferred":[
        "Ait Hkim Ait Yzid"
    ],
    "name:urd_x_preferred":[
        "\u0622\u06cc\u062a \u062d\u06a9\u06cc\u0645 \u0622\u06cc\u062a \u06cc\u0632\u06cc\u062f"
    ],
    "qs_pg:aaroncc":"MA",
    "qs_pg:gn_country":"MA",
    "qs_pg:gn_fcode":"ADM3",
    "qs_pg:gn_pop":8112,
    "qs_pg:name":"Ait Hkim Ait Yzid",
    "qs_pg:photos_9r":0,
    "qs_pg:photos_sr":0,
    "qs_pg:pop_sr":5,
    "qs_pg:qs_pg_placetype":"localadmin",
    "wof:name":"Ait Hkim Ait Yzid",
    "wof:placetype":"localadmin",
    "wof:population":8112
},
  "geometry": {"coordinates":[-7.20407,31.48829],"type":"Point"}
}