{
  "type": "Feature",
  "properties": {
    "gn:admin1_code":"01",
    "gn:asciiname":"Daimous",
    "gn:country_code":"MA",
    "gn:dem":95,
    "gn:feature_class":"P",
    "gn:feature_code":"PPL",
    "gn:name":"Da\u00efmous",
    "gn:population":0,
    "gn:timezone":"Africa/Casablanca",
    "iso:country":"MA",
    "name:und_x_variant":[
        "Deimous",
        "Da\u00efmous"
    ],
    "wof:name":"Daimous",
    "wof:placetype":"locality"
},
  "geometry": {"coordinates":[-5.79011,35.69194],"type":"Point"}
}