{
  "type": "Feature",
  "properties": {
    "gn:admin1_code":"9.0",
    "gn:asciiname":"Ait Ben Hammou",
    "gn:country_code":"MA",
    "gn:dem":683,
    "gn:feature_class":"P",
    "gn:feature_code":"PPL",
    "gn:name":"A\u00eft Ben Hammou",
    "gn:population":0,
    "gn:timezone":"Africa/Casablanca",
    "iso:country":"MA",
    "wof:name":"Ait Ben Hammou",
    "wof:placetype":"locality"
},
  "geometry": {"coordinates":[-9.31816,29.70472],"type":"Point"}
}