{
  "type": "Feature",
  "properties": {
    "gn:admin1_code":"6.0",
    "gn:asciiname":"Oulad el Maati el Araj",
    "gn:country_code":"MA",
    "gn:dem":370,
    "gn:feature_class":"P",
    "gn:feature_code":"PPL",
    "gn:name":"Oulad el Maati el Araj",
    "gn:population":0,
    "gn:timezone":"Africa/Casablanca",
    "iso:country":"MA",
    "wof:name":"Oulad el Maati el Araj",
    "wof:placetype":"locality"
},
  "geometry": {"coordinates":[-7.75472,32.91196],"type":"Point"}
}