{
  "type": "Feature",
  "properties": {
    "gn:admin1_code":"5.0",
    "gn:asciiname":"Tizougaghine",
    "gn:country_code":"MA",
    "gn:dem":1718,
    "gn:feature_class":"P",
    "gn:feature_code":"PPL",
    "gn:name":"Tizougaghine",
    "gn:population":0,
    "gn:timezone":"Africa/Casablanca",
    "iso:country":"MA",
    "wof:name":"Tizougaghine",
    "wof:placetype":"locality"
},
  "geometry": {"coordinates":[-6.92401,31.56551],"type":"Point"}
}