{
  "type": "Feature",
  "properties": {
    "gn:admin1_code":"7.0",
    "gn:asciiname":"Aguerrouj",
    "gn:country_code":"MA",
    "gn:dem":153,
    "gn:feature_class":"P",
    "gn:feature_code":"PPL",
    "gn:name":"Aguerrouj",
    "gn:population":0,
    "gn:timezone":"Africa/Casablanca",
    "iso:country":"MA",
    "wof:name":"Aguerrouj",
    "wof:placetype":"locality"
},
  "geometry": {"coordinates":[-9.77735,31.2539],"type":"Point"}
}