{
  "type": "Feature",
  "properties": {
    "gn:admin1_code":"09",
    "gn:asciiname":"Mnabha",
    "gn:country_code":"MA",
    "gn:dem":490,
    "gn:feature_class":"P",
    "gn:feature_code":"PPL",
    "gn:name":"Mnabha",
    "gn:population":0,
    "gn:timezone":"Africa/Casablanca",
    "iso:country":"MA",
    "name:und_x_variant":[
        "Madida"
    ],
    "wof:name":"Mnabha",
    "wof:placetype":"locality"
},
  "geometry": {"coordinates":[-8.44689,30.61761],"type":"Point"}
}