{
  "type": "Feature",
  "properties": {
    "gn:admin1_code":"1.0",
    "gn:asciiname":"Dchichat",
    "gn:country_code":"MA",
    "gn:dem":290,
    "gn:feature_class":"P",
    "gn:feature_code":"PPL",
    "gn:name":"Dchichat",
    "gn:population":0,
    "gn:timezone":"Africa/Casablanca",
    "iso:country":"MA",
    "wof:name":"Dchichat",
    "wof:placetype":"locality"
},
  "geometry": {"coordinates":[-5.64124,35.69517000000001],"type":"Point"}
}