{
  "type": "Feature",
  "properties": {
    "gn:admin1_code":"07",
    "gn:asciiname":"Id Mahfoud",
    "gn:country_code":"MA",
    "gn:dem":1112,
    "gn:feature_class":"P",
    "gn:feature_code":"PPL",
    "gn:name":"Id Mahfoud",
    "gn:population":0,
    "gn:timezone":"Africa/Casablanca",
    "iso:country":"MA",
    "name:und_x_variant":[
        "A\u00efda Mahgoud Etdir",
        "A\u00eft Mahfoud",
        "Id Mahfoud"
    ],
    "wof:name":"Id Mahfoud",
    "wof:placetype":"locality"
},
  "geometry": {"coordinates":[-8.93938,31.19251],"type":"Point"}
}