{
  "type": "Feature",
  "properties": {
    "gn:admin1_code":"09",
    "gn:asciiname":"Dousdremt",
    "gn:country_code":"MA",
    "gn:dem":1125,
    "gn:feature_class":"P",
    "gn:feature_code":"PPL",
    "gn:name":"Dousdremt",
    "gn:population":0,
    "gn:timezone":"Africa/Casablanca",
    "iso:country":"MA",
    "name:und_x_variant":[
        "Dousderme",
        "Dousdremt"
    ],
    "wof:name":"Dousdremt",
    "wof:placetype":"locality"
},
  "geometry": {"coordinates":[-8.97646,29.63526],"type":"Point"}
}