{
  "type": "Feature",
  "properties": {
    "gn:admin1_code":"10",
    "gn:asciiname":"Boul Nouit",
    "gn:country_code":"MA",
    "gn:dem":270,
    "gn:feature_class":"P",
    "gn:feature_code":"PPL",
    "gn:name":"Boul Nouit",
    "gn:population":0,
    "gn:timezone":"Africa/Casablanca",
    "iso:country":"MA",
    "name:und_x_variant":[
        "Bulenuit",
        "Butenuit",
        "Boul Nouit"
    ],
    "wof:name":"Boul Nouit",
    "wof:placetype":"locality"
},
  "geometry": {"coordinates":[-10.21974,29.14864],"type":"Point"}
}