{
  "type": "Feature",
  "properties": {
    "gn:admin1_code":"3.0",
    "gn:asciiname":"Lborj Ou Keraouch",
    "gn:country_code":"MA",
    "gn:dem":1675,
    "gn:feature_class":"P",
    "gn:feature_code":"PPL",
    "gn:name":"Lborj Ou Keraouch",
    "gn:population":0,
    "gn:timezone":"Africa/Casablanca",
    "iso:country":"MA",
    "wof:name":"Lborj Ou Keraouch",
    "wof:placetype":"locality"
},
  "geometry": {"coordinates":[-4.92829,33.6084],"type":"Point"}
}