{
  "type": "Feature",
  "properties": {
    "gn:admin1_code":"03",
    "gn:asciiname":"Douar Nmala",
    "gn:country_code":"MA",
    "gn:dem":375,
    "gn:feature_class":"P",
    "gn:feature_code":"PPL",
    "gn:name":"Douar Nmala",
    "gn:population":0,
    "gn:timezone":"Africa/Casablanca",
    "iso:country":"MA",
    "name:und_x_variant":[
        "Douar en Nemala",
        "Douar en Nouala",
        "Douar Nmala"
    ],
    "wof:name":"Douar Nmala",
    "wof:placetype":"locality"
},
  "geometry": {"coordinates":[-4.73086,34.17876],"type":"Point"}
}