{
  "type": "Feature",
  "properties": {
    "gn:admin1_code":"7.0",
    "gn:asciiname":"Aguermawne",
    "gn:country_code":"MA",
    "gn:dem":2001,
    "gn:feature_class":"P",
    "gn:feature_code":"PPL",
    "gn:name":"Aguermawne",
    "gn:population":0,
    "gn:timezone":"Africa/Casablanca",
    "iso:country":"MA",
    "wof:name":"Aguermawne",
    "wof:placetype":"locality"
},
  "geometry": {"coordinates":[-7.78189,31.25443],"type":"Point"}
}