{
  "type": "Feature",
  "properties": {
    "gn:admin1_code":"08",
    "gn:asciiname":"Asserghine",
    "gn:country_code":"MA",
    "gn:dem":757,
    "gn:feature_class":"P",
    "gn:feature_code":"PPL",
    "gn:name":"Asserghine",
    "gn:population":0,
    "gn:timezone":"Africa/Casablanca",
    "iso:country":"MA",
    "name:und_x_variant":[
        "Ksiret Asserghine",
        "Ksir Asserrhine",
        "Asserghine",
        "Asserrhine",
        "Asserhine"
    ],
    "wof:name":"Asserghine",
    "wof:placetype":"locality"
},
  "geometry": {"coordinates":[-4.22104,31.25729],"type":"Point"}
}