{
  "type": "Feature",
  "properties": {
    "gn:admin1_code":"6.0",
    "gn:asciiname":"Douar Sidi Eddahbi",
    "gn:country_code":"MA",
    "gn:dem":386,
    "gn:feature_class":"P",
    "gn:feature_code":"PPL",
    "gn:name":"Douar Sidi Eddahbi",
    "gn:population":0,
    "gn:timezone":"Africa/Casablanca",
    "iso:country":"MA",
    "wof:name":"Douar Sidi Eddahbi",
    "wof:placetype":"locality"
},
  "geometry": {"coordinates":[-7.02004,33.351],"type":"Point"}
}