{
  "type": "Feature",
  "properties": {
    "gn:admin1_code":"7.0",
    "gn:asciiname":"Ibaline",
    "gn:country_code":"MA",
    "gn:dem":1347,
    "gn:feature_class":"P",
    "gn:feature_code":"PPL",
    "gn:name":"Ibaline",
    "gn:population":0,
    "gn:timezone":"Africa/Casablanca",
    "iso:country":"MA",
    "wof:name":"Ibaline",
    "wof:placetype":"locality"
},
  "geometry": {"coordinates":[-9.11323,31.04329],"type":"Point"}
}