{
  "type": "Feature",
  "properties": {
    "gn:admin1_code":"1.0",
    "gn:asciiname":"Rkiba",
    "gn:country_code":"MA",
    "gn:dem":78,
    "gn:feature_class":"P",
    "gn:feature_code":"PPL",
    "gn:name":"Rkiba",
    "gn:population":0,
    "gn:timezone":"Africa/Casablanca",
    "iso:country":"MA",
    "wof:name":"Rkiba",
    "wof:placetype":"locality"
},
  "geometry": {"coordinates":[-5.93155,35.49269],"type":"Point"}
}