{
  "type": "Feature",
  "properties": {
    "gn:admin1_code":"5.0",
    "gn:asciiname":"Douar Ayt Cam",
    "gn:country_code":"MA",
    "gn:dem":521,
    "gn:feature_class":"P",
    "gn:feature_code":"PPL",
    "gn:name":"Douar Ayt \u00c7am",
    "gn:population":0,
    "gn:timezone":"Africa/Casablanca",
    "iso:country":"MA",
    "wof:name":"Douar Ayt Cam",
    "wof:placetype":"locality"
},
  "geometry": {"coordinates":[-6.28109,32.53108],"type":"Point"}
}