{
  "type": "Feature",
  "properties": {
    "gn:admin1_code":"07",
    "gn:asciiname":"Douar Bouchaayh Ben Rahal",
    "gn:country_code":"MA",
    "gn:dem":160,
    "gn:feature_class":"P",
    "gn:feature_code":"PPL",
    "gn:name":"Douar Bouchaayh Ben Rahal",
    "gn:population":0,
    "gn:timezone":"Africa/Casablanca",
    "iso:country":"MA",
    "name:und_x_variant":[
        "Bouchaib Ben Rahhal"
    ],
    "wof:name":"Douar Bouchaayh Ben Rahal",
    "wof:placetype":"locality"
},
  "geometry": {"coordinates":[-8.92723,32.40095],"type":"Point"}
}