{
  "type": "Feature",
  "properties": {
    "gn:gn_country":"MA",
    "gn:gn_fcode":"ADM3",
    "gn:gn_pop":71522,
    "gn:population":71522,
    "iso:country":"MA",
    "name:ara_x_preferred":[
        "\u062a\u064a\u0632\u0643\u064a\u062a"
    ],
    "name:fra_x_preferred":[
        "Khenifra"
    ],
    "name:fra_x_variant":[
        "Khenifra (MU)",
        "Khenifra (Commune Urbaine)"
    ],
    "qs_pg:aaroncc":"MA",
    "qs_pg:gn_country":"MA",
    "qs_pg:gn_fcode":"ADM3",
    "qs_pg:gn_pop":71522,
    "qs_pg:name":"Khenifra",
    "qs_pg:photos_9r":0,
    "qs_pg:photos_sr":0,
    "qs_pg:pop_sr":8,
    "qs_pg:qs_pg_placetype":"localadmin",
    "wof:name":"Khenifra",
    "wof:placetype":"localadmin",
    "wof:population":71522
},
  "geometry": {"coordinates":[-5.66629,32.93207],"type":"Point"}
}