{
  "type": "Feature",
  "properties": {
    "gn:country":"MA",
    "gn:fcode":"ADM3",
    "gn:population":71522,
    "iso:country":"MA",
    "name:ara_x_preferred":[
        "\u062a\u064a\u0632\u0643\u064a\u062a"
    ],
    "name:ara_x_variant":[
        "\u062e\u0646\u064a\u0641\u0631\u0629"
    ],
    "name:azb_x_preferred":[
        "\u062e\u0646\u06cc\u0641\u0631\u0647"
    ],
    "name:cat_x_preferred":[
        "Khenifra"
    ],
    "name:ceb_x_preferred":[
        "Khenifra"
    ],
    "name:cym_x_preferred":[
        "Kh\u00e9nifra"
    ],
    "name:deu_x_preferred":[
        "Kh\u00e9nifra"
    ],
    "name:fas_x_preferred":[
        "\u062e\u0646\u06cc\u0641\u0631\u0647"
    ],
    "name:fra_x_preferred":[
        "Khenifra"
    ],
    "name:fra_x_variant":[
        "Khenifra (MU)",
        "Khenifra (Commune Urbaine)",
        "Kh\u00e9nifra"
    ],
    "name:ita_x_preferred":[
        "Khenifra"
    ],
    "name:kab_x_preferred":[
        "Xnifra"
    ],
    "name:kor_x_preferred":[
        "\ucf00\ub2c8\ud504\ub77c"
    ],
    "name:lit_x_preferred":[
        "Chenifra"
    ],
    "name:nld_x_preferred":[
        "Kh\u00e9nifra"
    ],
    "name:pol_x_preferred":[
        "Chunajfira"
    ],
    "name:por_x_preferred":[
        "Quenifra"
    ],
    "name:ron_x_preferred":[
        "Khenifra"
    ],
    "name:rus_x_preferred":[
        "\u0425\u0435\u043d\u0438\u0444\u0440\u0430"
    ],
    "name:spa_x_preferred":[
        "Jenifra"
    ],
    "name:swe_x_preferred":[
        "Kh\u00e9nifra"
    ],
    "name:urd_x_preferred":[
        "\u062e\u0646\u06cc\u0641\u0631\u06c1"
    ],
    "name:zho_x_preferred":[
        "\u6d77\u5c3c\u592b\u62c9"
    ],
    "qs_pg:aaroncc":"MA",
    "qs_pg:gn_country":"MA",
    "qs_pg:gn_fcode":"ADM3",
    "qs_pg:gn_pop":71522,
    "qs_pg:name":"Khenifra",
    "qs_pg:photos_9r":0,
    "qs_pg:photos_sr":0,
    "qs_pg:pop_sr":8,
    "qs_pg:qs_pg_placetype":"localadmin",
    "wof:name":"Khenifra",
    "wof:placetype":"localadmin",
    "wof:population":71522
},
  "geometry": {"coordinates":[-5.66629,32.93207],"type":"Point"}
}