{
  "type": "Feature",
  "properties": {
    "gn:admin1_code":"7.0",
    "gn:asciiname":"Ahfir Hawfa",
    "gn:country_code":"MA",
    "gn:dem":474,
    "gn:feature_class":"P",
    "gn:feature_code":"PPL",
    "gn:name":"Ahfir Hawfa",
    "gn:population":0,
    "gn:timezone":"Africa/Casablanca",
    "iso:country":"MA",
    "wof:name":"Ahfir Hawfa",
    "wof:placetype":"locality"
},
  "geometry": {"coordinates":[-8.09346,32.08081],"type":"Point"}
}