{
  "type": "Feature",
  "properties": {
    "gn:admin1_code":"3.0",
    "gn:asciiname":"Douar Ait Othmane Oucheaua",
    "gn:country_code":"MA",
    "gn:dem":681,
    "gn:feature_class":"P",
    "gn:feature_code":"PPL",
    "gn:name":"Douar Ait Othmane Oucheaua",
    "gn:population":0,
    "gn:timezone":"Africa/Casablanca",
    "iso:country":"MA",
    "wof:name":"Douar Ait Othmane Oucheaua",
    "wof:placetype":"locality"
},
  "geometry": {"coordinates":[-5.55092,33.78659],"type":"Point"}
}