{
  "type": "Feature",
  "properties": {
    "gn:admin1_code":"7.0",
    "gn:asciiname":"Afrad",
    "gn:country_code":"MA",
    "gn:dem":490,
    "gn:feature_class":"P",
    "gn:feature_code":"PPL",
    "gn:name":"Afrad",
    "gn:population":0,
    "gn:timezone":"Africa/Casablanca",
    "iso:country":"MA",
    "wof:name":"Afrad",
    "wof:placetype":"locality"
},
  "geometry": {"coordinates":[-9.64699,30.91435],"type":"Point"}
}