{
  "type": "Feature",
  "properties": {
    "gn:admin1_code":"7.0",
    "gn:asciiname":"Dar El Himer Mohamed",
    "gn:country_code":"MA",
    "gn:dem":369,
    "gn:feature_class":"P",
    "gn:feature_code":"PPL",
    "gn:name":"Dar El Himer Mohamed",
    "gn:population":0,
    "gn:timezone":"Africa/Casablanca",
    "iso:country":"MA",
    "wof:name":"Dar El Himer Mohamed",
    "wof:placetype":"locality"
},
  "geometry": {"coordinates":[-8.45707,31.60628],"type":"Point"}
}