{
  "type": "Feature",
  "properties": {
    "gn:admin1_code":"10",
    "gn:asciiname":"Irhir Nallouch",
    "gn:country_code":"MA",
    "gn:dem":1277,
    "gn:feature_class":"P",
    "gn:feature_code":"PPL",
    "gn:name":"Irhir Nallouch",
    "gn:population":0,
    "gn:timezone":"Africa/Casablanca",
    "iso:country":"MA",
    "wof:name":"Irhir Nallouch",
    "wof:placetype":"locality"
},
  "geometry": {"coordinates":[-9.39629,29.37898],"type":"Point"}
}