{
  "type": "Feature",
  "properties": {
    "gn:admin1_code":"7.0",
    "gn:asciiname":"Douar Oulad Sidi Sallam",
    "gn:country_code":"MA",
    "gn:dem":124,
    "gn:feature_class":"P",
    "gn:feature_code":"PPL",
    "gn:name":"Douar Oulad Sidi Sallam",
    "gn:population":0,
    "gn:timezone":"Africa/Casablanca",
    "iso:country":"MA",
    "wof:name":"Douar Oulad Sidi Sallam",
    "wof:placetype":"locality"
},
  "geometry": {"coordinates":[-9.23306,32.01807],"type":"Point"}
}