{
  "type": "Feature",
  "properties": {
    "gn:admin1_code":"1.0",
    "gn:asciiname":"Dar Myazid",
    "gn:country_code":"MA",
    "gn:dem":927,
    "gn:feature_class":"P",
    "gn:feature_code":"PPL",
    "gn:name":"Dar Myazid",
    "gn:population":0,
    "gn:timezone":"Africa/Casablanca",
    "iso:country":"MA",
    "wof:name":"Dar Myazid",
    "wof:placetype":"locality"
},
  "geometry": {"coordinates":[-5.49343,35.3153],"type":"Point"}
}