{
  "type": "Feature",
  "properties": {
    "gn:admin1_code":"9.0",
    "gn:asciiname":"Ayt Agouhawe",
    "gn:country_code":"MA",
    "gn:dem":1012,
    "gn:feature_class":"P",
    "gn:feature_code":"PPL",
    "gn:name":"Ayt Agouhawe",
    "gn:population":0,
    "gn:timezone":"Africa/Casablanca",
    "iso:country":"MA",
    "wof:name":"Ayt Agouhawe",
    "wof:placetype":"locality"
},
  "geometry": {"coordinates":[-8.72494,30.24769],"type":"Point"}
}