{
  "type": "Feature",
  "properties": {
    "gn:admin1_code":"7.0",
    "gn:asciiname":"Chorfa",
    "gn:country_code":"MA",
    "gn:dem":494,
    "gn:feature_class":"P",
    "gn:feature_code":"PPL",
    "gn:name":"Chorfa",
    "gn:population":0,
    "gn:timezone":"Africa/Casablanca",
    "iso:country":"MA",
    "wof:name":"Chorfa",
    "wof:placetype":"locality"
},
  "geometry": {"coordinates":[-9.38457,31.44846],"type":"Point"}
}