{
  "type": "Feature",
  "properties": {
    "gn:admin1_code":"08",
    "gn:asciiname":"Talharit",
    "gn:country_code":"MA",
    "gn:dem":1446,
    "gn:feature_class":"P",
    "gn:feature_code":"PPL",
    "gn:name":"Talharit",
    "gn:population":0,
    "gn:timezone":"Africa/Casablanca",
    "iso:country":"MA",
    "name:und_x_variant":[
        "Tallahrit",
        "Talharite",
        "Talharit"
    ],
    "wof:name":"Talharit",
    "wof:placetype":"locality"
},
  "geometry": {"coordinates":[-4.1532,32.38864],"type":"Point"}
}