{
  "type": "Feature",
  "properties": {
    "gn:admin1_code":"2.0",
    "gn:asciiname":"Douar Oulad Maaminer",
    "gn:country_code":"MA",
    "gn:dem":737,
    "gn:feature_class":"P",
    "gn:feature_code":"PPL",
    "gn:name":"Douar Oulad Maaminer",
    "gn:population":0,
    "gn:timezone":"Africa/Casablanca",
    "iso:country":"MA",
    "wof:name":"Douar Oulad Maaminer",
    "wof:placetype":"locality"
},
  "geometry": {"coordinates":[-1.9598,34.5997],"type":"Point"}
}