{
  "type": "Feature",
  "properties": {
    "gn:admin1_code":"01",
    "gn:asciiname":"El Berhadda",
    "gn:country_code":"MA",
    "gn:dem":21,
    "gn:feature_class":"P",
    "gn:feature_code":"PPL",
    "gn:name":"El Berhadda",
    "gn:population":0,
    "gn:timezone":"Africa/Casablanca",
    "iso:country":"MA",
    "name:und_x_variant":[
        "El Barhadda",
        "El Berhadda"
    ],
    "wof:name":"El Berhadda",
    "wof:placetype":"locality"
},
  "geometry": {"coordinates":[-5.99366,35.17346],"type":"Point"}
}