{
  "type": "Feature",
  "properties": {
    "gn:admin1_code":"6.0",
    "gn:asciiname":"Douar Oulad Chemissa Ouaul Oahbou",
    "gn:country_code":"MA",
    "gn:dem":412,
    "gn:feature_class":"P",
    "gn:feature_code":"PPL",
    "gn:name":"Douar Oulad Chemissa Ouaul Oahbou",
    "gn:population":0,
    "gn:timezone":"Africa/Casablanca",
    "iso:country":"MA",
    "wof:name":"Douar Oulad Chemissa Ouaul Oahbou",
    "wof:placetype":"locality"
},
  "geometry": {"coordinates":[-6.86825,33.3869],"type":"Point"}
}