{
  "type": "Feature",
  "properties": {
    "gn:admin1_code":"1.0",
    "gn:asciiname":"Douar Isalhiouene",
    "gn:country_code":"MA",
    "gn:dem":288,
    "gn:feature_class":"P",
    "gn:feature_code":"PPL",
    "gn:name":"Douar Isalhiouene",
    "gn:population":0,
    "gn:timezone":"Africa/Casablanca",
    "iso:country":"MA",
    "wof:name":"Douar Isalhiouene",
    "wof:placetype":"locality"
},
  "geometry": {"coordinates":[-4.20872,35.08191],"type":"Point"}
}