{
  "type": "Feature",
  "properties": {
    "gn:admin1_code":"9.0",
    "gn:asciiname":"Agourzi",
    "gn:country_code":"MA",
    "gn:dem":1441,
    "gn:feature_class":"P",
    "gn:feature_code":"PPL",
    "gn:name":"Agourzi",
    "gn:population":0,
    "gn:timezone":"Africa/Casablanca",
    "iso:country":"MA",
    "wof:name":"Agourzi",
    "wof:placetype":"locality"
},
  "geometry": {"coordinates":[-8.82429,30.75819000000001],"type":"Point"}
}