{
  "type": "Feature",
  "properties": {
    "gn:admin1_code":"03",
    "gn:asciiname":"Za Bougrine",
    "gn:country_code":"MA",
    "gn:dem":993,
    "gn:feature_class":"P",
    "gn:feature_code":"PPL",
    "gn:name":"Za Bougrine",
    "gn:population":0,
    "gn:timezone":"Africa/Casablanca",
    "iso:country":"MA",
    "name:und_x_variant":[
        "Zaouia Bougrine",
        "Zouiat Bougrine",
        "Za Bougrine"
    ],
    "wof:name":"Za Bougrine",
    "wof:placetype":"locality"
},
  "geometry": {"coordinates":[-4.48813,33.85524],"type":"Point"}
}