{
  "type": "Feature",
  "properties": {
    "gn:admin1_code":"09",
    "gn:asciiname":"Tanabdant",
    "gn:country_code":"MA",
    "gn:dem":997,
    "gn:feature_class":"P",
    "gn:feature_code":"PPL",
    "gn:name":"Tanabdant",
    "gn:population":0,
    "gn:timezone":"Africa/Casablanca",
    "iso:country":"MA",
    "name:und_x_variant":[
        "Tanabdainte",
        "Tanebdant",
        "Tanabdant"
    ],
    "wof:name":"Tanabdant",
    "wof:placetype":"locality"
},
  "geometry": {"coordinates":[-8.44777,30.81868],"type":"Point"}
}