{
  "type": "Feature",
  "properties": {
    "gn:admin1_code":"4.0",
    "gn:asciiname":"Douar Dridika",
    "gn:country_code":"MA",
    "gn:dem":39,
    "gn:feature_class":"P",
    "gn:feature_code":"PPL",
    "gn:name":"Douar Dridika",
    "gn:population":0,
    "gn:timezone":"Africa/Casablanca",
    "iso:country":"MA",
    "wof:name":"Douar Dridika",
    "wof:placetype":"locality"
},
  "geometry": {"coordinates":[-5.92864,34.60761],"type":"Point"}
}