{
  "type": "Feature",
  "properties": {
    "gn:admin1_code":"06",
    "gn:asciiname":"Douar Oulad Sidi El Aydi",
    "gn:country_code":"MA",
    "gn:dem":327,
    "gn:feature_class":"P",
    "gn:feature_code":"PPL",
    "gn:name":"Douar Oulad Sidi El Aydi",
    "gn:population":0,
    "gn:timezone":"Africa/Casablanca",
    "iso:country":"MA",
    "name:und_x_variant":[
        "Sidi el A\u00efdi"
    ],
    "wof:name":"Douar Oulad Sidi El Aydi",
    "wof:placetype":"locality"
},
  "geometry": {"coordinates":[-7.39562,33.16261],"type":"Point"}
}