{
  "type": "Feature",
  "properties": {
    "gn:country":"MA",
    "gn:fcode":"ADM3",
    "gn:population":5762,
    "iso:country":"MA",
    "name:ara_x_preferred":[
        "\u0627\u0632\u0643\u0648\u0631"
    ],
    "name:ara_x_variant":[
        "\u062f\u0627\u0631 \u0627\u0644\u062c\u0627\u0645\u0639"
    ],
    "name:azb_x_preferred":[
        "\u062f\u0627\u0631\u0627\u0644\u062c\u0627\u0645\u0639"
    ],
    "name:cat_x_preferred":[
        "Dar Jamaa"
    ],
    "name:ceb_x_preferred":[
        "Dar Jamaa"
    ],
    "name:fas_x_preferred":[
        "\u062f\u0627\u0631\u0627\u0644\u062c\u0627\u0645\u0639"
    ],
    "name:fra_x_preferred":[
        "Dar Jamaa"
    ],
    "name:fra_x_variant":[
        "Dar Jamaa (CR)",
        "Dar Jamaa (Commune Rurale)",
        "Dar Jama\u00e2"
    ],
    "name:ita_x_preferred":[
        "Dar Jamaa"
    ],
    "name:swe_x_preferred":[
        "Dar Jamaa"
    ],
    "name:urd_x_preferred":[
        "\u062f\u0627\u0631 \u062c\u0645\u0639\u06c1"
    ],
    "qs_pg:aaroncc":"MA",
    "qs_pg:gn_country":"MA",
    "qs_pg:gn_fcode":"ADM3",
    "qs_pg:gn_pop":5762,
    "qs_pg:name":"Dar Jamaa",
    "qs_pg:photos_9r":0,
    "qs_pg:photos_sr":0,
    "qs_pg:pop_sr":5,
    "qs_pg:qs_pg_placetype":"localadmin",
    "wof:name":"Dar Jamaa",
    "wof:placetype":"localadmin",
    "wof:population":5911
},
  "geometry": {"coordinates":[-8.38501,31.25236],"type":"Point"}
}