{
  "type": "Feature",
  "properties": {
    "gn:gn_country":"MA",
    "gn:gn_fcode":"ADM3",
    "gn:gn_pop":5762,
    "gn:population":5911,
    "iso:country":"MA",
    "name:ara_x_preferred":[
        "\u0627\u0632\u0643\u0648\u0631"
    ],
    "name:fra_x_preferred":[
        "Dar Jamaa"
    ],
    "name:fra_x_variant":[
        "Dar Jamaa (CR)",
        "Dar Jamaa (Commune Rurale)"
    ],
    "qs_pg:aaroncc":"MA",
    "qs_pg:gn_country":"MA",
    "qs_pg:gn_fcode":"ADM3",
    "qs_pg:gn_pop":5762,
    "qs_pg:name":"Dar Jamaa",
    "qs_pg:photos_9r":0,
    "qs_pg:photos_sr":0,
    "qs_pg:pop_sr":5,
    "qs_pg:qs_pg_placetype":"localadmin",
    "wof:name":"Dar Jamaa",
    "wof:placetype":"localadmin",
    "wof:population":5911
},
  "geometry": {"coordinates":[-8.38501,31.25236],"type":"Point"}
}