{
  "type": "Feature",
  "properties": {
    "gn:admin1_code":"01",
    "gn:asciiname":"Douar Daidaat",
    "gn:country_code":"MA",
    "gn:dem":27,
    "gn:feature_class":"P",
    "gn:feature_code":"PPL",
    "gn:name":"Douar Daidaat",
    "gn:population":0,
    "gn:timezone":"Africa/Casablanca",
    "iso:country":"MA",
    "name:und_x_variant":[
        "Da\u00efdat",
        "Daidatz",
        "Douar Daidaat"
    ],
    "wof:name":"Douar Daidaat",
    "wof:placetype":"locality"
},
  "geometry": {"coordinates":[-5.9336,35.65381],"type":"Point"}
}