{
  "type": "Feature",
  "properties": {
    "gn:admin1_code":"09",
    "gn:asciiname":"Iggui n'Blal",
    "gn:country_code":"MA",
    "gn:dem":1273,
    "gn:feature_class":"P",
    "gn:feature_code":"PPL",
    "gn:name":"Iggui n\u2019Blal",
    "gn:population":0,
    "gn:timezone":"Africa/Casablanca",
    "iso:country":"MA",
    "name:und_x_variant":[
        "Ignibelal",
        "Iggi n\u2019Bla",
        "Iggui n\u2019Blal"
    ],
    "wof:name":"Iggui n'Blal",
    "wof:placetype":"locality"
},
  "geometry": {"coordinates":[-9.26207,30.74462],"type":"Point"}
}