{
  "type": "Feature",
  "properties": {
    "gn:admin1_code":"7.0",
    "gn:asciiname":"Oulad Hammou",
    "gn:country_code":"MA",
    "gn:dem":93,
    "gn:feature_class":"P",
    "gn:feature_code":"PPL",
    "gn:name":"Oulad Hammou",
    "gn:population":0,
    "gn:timezone":"Africa/Casablanca",
    "iso:country":"MA",
    "wof:name":"Oulad Hammou",
    "wof:placetype":"locality"
},
  "geometry": {"coordinates":[-9.3749,31.9816],"type":"Point"}
}