{
  "type": "Feature",
  "properties": {
    "gn:admin1_code":"7.0",
    "gn:asciiname":"Tarhzout",
    "gn:country_code":"MA",
    "gn:dem":1258,
    "gn:feature_class":"P",
    "gn:feature_code":"PPL",
    "gn:name":"Tarhzout",
    "gn:population":0,
    "gn:timezone":"Africa/Casablanca",
    "iso:country":"MA",
    "wof:name":"Tarhzout",
    "wof:placetype":"locality"
},
  "geometry": {"coordinates":[-7.30374,31.55807],"type":"Point"}
}