{
  "type": "Feature",
  "properties": {
    "gn:admin1_code":"6.0",
    "gn:asciiname":"Douret Lakhafi",
    "gn:country_code":"MA",
    "gn:dem":192,
    "gn:feature_class":"P",
    "gn:feature_code":"PPL",
    "gn:name":"Douret Lakhafi",
    "gn:population":0,
    "gn:timezone":"Africa/Casablanca",
    "iso:country":"MA",
    "wof:name":"Douret Lakhafi",
    "wof:placetype":"locality"
},
  "geometry": {"coordinates":[-7.09633,33.69593],"type":"Point"}
}