{
  "type": "Feature",
  "properties": {
    "gn:admin1_code":"07",
    "gn:asciiname":"Douar Oulad Rhalem",
    "gn:country_code":"MA",
    "gn:dem":463,
    "gn:feature_class":"P",
    "gn:feature_code":"PPL",
    "gn:name":"Douar Oulad Rhalem",
    "gn:population":0,
    "gn:timezone":"Africa/Casablanca",
    "iso:country":"MA",
    "name:und_x_variant":[
        "Oulad Ralm",
        "Douar Oulad Rhalem"
    ],
    "wof:name":"Douar Oulad Rhalem",
    "wof:placetype":"locality"
},
  "geometry": {"coordinates":[-7.23602,32.06924],"type":"Point"}
}