{
  "type": "Feature",
  "properties": {
    "gn:admin1_code":"5.0",
    "gn:asciiname":"Tamsiliyn",
    "gn:country_code":"MA",
    "gn:dem":1416,
    "gn:feature_class":"P",
    "gn:feature_code":"PPL",
    "gn:name":"Tamsiliyn",
    "gn:population":0,
    "gn:timezone":"Africa/Casablanca",
    "iso:country":"MA",
    "wof:name":"Tamsiliyn",
    "wof:placetype":"locality"
},
  "geometry": {"coordinates":[-6.57052,31.93828],"type":"Point"}
}