{
  "type": "Feature",
  "properties": {
    "gn:admin1_code":"7.0",
    "gn:asciiname":"Tadouart Qimuzzond",
    "gn:country_code":"MA",
    "gn:dem":332,
    "gn:feature_class":"P",
    "gn:feature_code":"PPL",
    "gn:name":"Tadouart Qimuzzond",
    "gn:population":0,
    "gn:timezone":"Africa/Casablanca",
    "iso:country":"MA",
    "wof:name":"Tadouart Qimuzzond",
    "wof:placetype":"locality"
},
  "geometry": {"coordinates":[-9.61891,31.14039],"type":"Point"}
}