{
  "type": "Feature",
  "properties": {
    "gn:admin1_code":"4.0",
    "gn:asciiname":"Oulad El Caid",
    "gn:country_code":"MA",
    "gn:dem":272,
    "gn:feature_class":"P",
    "gn:feature_code":"PPL",
    "gn:name":"Oulad El Caid",
    "gn:population":0,
    "gn:timezone":"Africa/Casablanca",
    "iso:country":"MA",
    "wof:name":"Oulad El Caid",
    "wof:placetype":"locality"
},
  "geometry": {"coordinates":[-5.50267,34.59403],"type":"Point"}
}