{
  "type": "Feature",
  "properties": {
    "gn:admin1_code":"9.0",
    "gn:asciiname":"Oughzif",
    "gn:country_code":"MA",
    "gn:dem":1314,
    "gn:feature_class":"P",
    "gn:feature_code":"PPL",
    "gn:name":"Oughzif",
    "gn:population":0,
    "gn:timezone":"Africa/Casablanca",
    "iso:country":"MA",
    "wof:name":"Oughzif",
    "wof:placetype":"locality"
},
  "geometry": {"coordinates":[-8.77419,30.06303],"type":"Point"}
}