{
  "type": "Feature",
  "properties": {
    "gn:admin1_code":"07",
    "gn:asciiname":"Douar Houmane",
    "gn:country_code":"MA",
    "gn:dem":160,
    "gn:feature_class":"P",
    "gn:feature_code":"PPL",
    "gn:name":"Douar Houmane",
    "gn:population":0,
    "gn:timezone":"Africa/Casablanca",
    "iso:country":"MA",
    "name:und_x_variant":[
        "Douar Hommane",
        "Hommane",
        "Douar Houmane"
    ],
    "wof:name":"Douar Houmane",
    "wof:placetype":"locality"
},
  "geometry": {"coordinates":[-8.93602,32.38627],"type":"Point"}
}