{
  "type": "Feature",
  "properties": {
    "gn:admin1_code":"7.0",
    "gn:asciiname":"Douar Oulad Abbou",
    "gn:country_code":"MA",
    "gn:dem":395,
    "gn:feature_class":"P",
    "gn:feature_code":"PPL",
    "gn:name":"Douar Oulad Abbou",
    "gn:population":0,
    "gn:timezone":"Africa/Casablanca",
    "iso:country":"MA",
    "wof:name":"Douar Oulad Abbou",
    "wof:placetype":"locality"
},
  "geometry": {"coordinates":[-8.60004,32.04636],"type":"Point"}
}