{
  "type": "Feature",
  "properties": {
    "gn:admin1_code":"6.0",
    "gn:asciiname":"Lefinla Jouabriya",
    "gn:country_code":"MA",
    "gn:dem":535,
    "gn:feature_class":"P",
    "gn:feature_code":"PPL",
    "gn:name":"Lefinla Jouabriya",
    "gn:population":0,
    "gn:timezone":"Africa/Casablanca",
    "iso:country":"MA",
    "wof:name":"Lefinla Jouabriya",
    "wof:placetype":"locality"
},
  "geometry": {"coordinates":[-7.42279,33.04748],"type":"Point"}
}