{
  "type": "Feature",
  "properties": {
    "gn:admin1_code":"07",
    "gn:asciiname":"Toughnist",
    "gn:country_code":"MA",
    "gn:dem":395,
    "gn:feature_class":"P",
    "gn:feature_code":"PPL",
    "gn:name":"Toughnist",
    "gn:population":0,
    "gn:timezone":"Africa/Casablanca",
    "iso:country":"MA",
    "name:und_x_variant":[
        "Tournnist",
        "Tourhnist",
        "Toughnist"
    ],
    "wof:name":"Toughnist",
    "wof:placetype":"locality"
},
  "geometry": {"coordinates":[-9.74242,31.15065],"type":"Point"}
}