{
  "type": "Feature",
  "properties": {
    "gn:admin1_code":"9.0",
    "gn:asciiname":"Tamzououl",
    "gn:country_code":"MA",
    "gn:dem":911,
    "gn:feature_class":"P",
    "gn:feature_code":"PPL",
    "gn:name":"Tamzououl",
    "gn:population":0,
    "gn:timezone":"Africa/Casablanca",
    "iso:country":"MA",
    "wof:name":"Tamzououl",
    "wof:placetype":"locality"
},
  "geometry": {"coordinates":[-9.13588,30.03325],"type":"Point"}
}