{
  "type": "Feature",
  "properties": {
    "gn:admin1_code":"05",
    "gn:asciiname":"Koumch",
    "gn:country_code":"MA",
    "gn:dem":1147,
    "gn:feature_class":"P",
    "gn:feature_code":"PPL",
    "gn:name":"Koumch",
    "gn:population":0,
    "gn:timezone":"Africa/Casablanca",
    "iso:country":"MA",
    "wof:name":"Koumch",
    "wof:placetype":"locality"
},
  "geometry": {"coordinates":[-5.86504,32.63827],"type":"Point"}
}