{
  "type": "Feature",
  "properties": {
    "gn:admin1_code":"9.0",
    "gn:asciiname":"Lderbe",
    "gn:country_code":"MA",
    "gn:dem":195,
    "gn:feature_class":"P",
    "gn:feature_code":"PPL",
    "gn:name":"Lderbe",
    "gn:population":0,
    "gn:timezone":"Africa/Casablanca",
    "iso:country":"MA",
    "wof:name":"Lderbe",
    "wof:placetype":"locality"
},
  "geometry": {"coordinates":[-9.39378,30.47387],"type":"Point"}
}