{
  "type": "Feature",
  "properties": {
    "gn:admin1_code":"9.0",
    "gn:asciiname":"Ait Belouah",
    "gn:country_code":"MA",
    "gn:dem":778,
    "gn:feature_class":"P",
    "gn:feature_code":"PPL",
    "gn:name":"A\u00eft Belouah",
    "gn:population":0,
    "gn:timezone":"Africa/Casablanca",
    "iso:country":"MA",
    "wof:name":"Ait Belouah",
    "wof:placetype":"locality"
},
  "geometry": {"coordinates":[-8.75674,30.6552],"type":"Point"}
}