{
  "type": "Feature",
  "properties": {
    "gn:admin1_code":"9.0",
    "gn:asciiname":"Cercle Ait Melloul",
    "gn:country_code":"MA",
    "gn:dem":30,
    "gn:feature_class":"P",
    "gn:feature_code":"PPL",
    "gn:name":"Cercle Ait Melloul",
    "gn:population":0,
    "gn:timezone":"Africa/Casablanca",
    "iso:country":"MA",
    "wof:name":"Cercle Ait Melloul",
    "wof:placetype":"locality"
},
  "geometry": {"coordinates":[-9.48837,30.3329],"type":"Point"}
}