{
  "type": "Feature",
  "properties": {
    "gn:admin1_code":"7.0",
    "gn:asciiname":"Ait Aroussi",
    "gn:country_code":"MA",
    "gn:dem":610,
    "gn:feature_class":"P",
    "gn:feature_code":"PPL",
    "gn:name":"A\u00eft Aroussi",
    "gn:population":0,
    "gn:timezone":"Africa/Casablanca",
    "iso:country":"MA",
    "wof:name":"Ait Aroussi",
    "wof:placetype":"locality"
},
  "geometry": {"coordinates":[-9.15959,31.41981],"type":"Point"}
}