{
  "type": "Feature",
  "properties": {
    "gn:admin1_code":"9.0",
    "gn:asciiname":"Amrouz",
    "gn:country_code":"MA",
    "gn:dem":625,
    "gn:feature_class":"P",
    "gn:feature_code":"PPL",
    "gn:name":"Amrouz",
    "gn:population":0,
    "gn:timezone":"Africa/Casablanca",
    "iso:country":"MA",
    "wof:name":"Amrouz",
    "wof:placetype":"locality"
},
  "geometry": {"coordinates":[-8.31455,30.72495],"type":"Point"}
}