{
  "type": "Feature",
  "properties": {
    "gn:admin1_code":"01",
    "gn:asciiname":"Ras el Aswad",
    "gn:country_code":"MA",
    "gn:dem":40,
    "gn:feature_class":"P",
    "gn:feature_code":"PPL",
    "gn:name":"Ras el Aswad",
    "gn:population":0,
    "gn:timezone":"Africa/Casablanca",
    "iso:country":"MA",
    "wof:name":"Ras el Aswad",
    "wof:placetype":"locality"
},
  "geometry": {"coordinates":[-5.27477,35.68549],"type":"Point"}
}