{
  "type": "Feature",
  "properties": {
    "gn:admin1_code":"07",
    "gn:asciiname":"Tafliht",
    "gn:country_code":"MA",
    "gn:dem":1419,
    "gn:feature_class":"P",
    "gn:feature_code":"PPL",
    "gn:name":"Tafliht",
    "gn:population":0,
    "gn:timezone":"Africa/Casablanca",
    "iso:country":"MA",
    "name:und_x_variant":[
        "Toufleht"
    ],
    "wof:name":"Tafliht",
    "wof:placetype":"locality"
},
  "geometry": {"coordinates":[-7.43235,31.48171],"type":"Point"}
}