{
  "type": "Feature",
  "properties": {
    "gn:admin1_code":"07",
    "gn:asciiname":"Iguer-n-'Ali",
    "gn:country_code":"MA",
    "gn:dem":1538,
    "gn:feature_class":"P",
    "gn:feature_code":"PPL",
    "gn:name":"Iguer-n-\u2019Ali",
    "gn:population":0,
    "gn:timezone":"Africa/Casablanca",
    "iso:country":"MA",
    "name:und_x_variant":[
        "Iguernalt",
        "Iguernali",
        "Iguer-n-\u2019Ali"
    ],
    "wof:name":"Iguer-n-'Ali",
    "wof:placetype":"locality"
},
  "geometry": {"coordinates":[-8.81709,31.13144],"type":"Point"}
}