{
  "type": "Feature",
  "properties": {
    "gn:admin1_code":"07",
    "gn:asciiname":"Awinnas",
    "gn:country_code":"MA",
    "gn:dem":976,
    "gn:feature_class":"P",
    "gn:feature_code":"PPL",
    "gn:name":"Awinnas",
    "gn:population":0,
    "gn:timezone":"Africa/Casablanca",
    "iso:country":"MA",
    "name:und_x_variant":[
        "Ouines"
    ],
    "wof:name":"Awinnas",
    "wof:placetype":"locality"
},
  "geometry": {"coordinates":[-8.78227,31.12372],"type":"Point"}
}