{
  "type": "Feature",
  "properties": {
    "gn:admin1_code":"9.0",
    "gn:asciiname":"Agni-n-Hggoun",
    "gn:country_code":"MA",
    "gn:dem":715,
    "gn:feature_class":"P",
    "gn:feature_code":"PPL",
    "gn:name":"Agni-n-Hggoun",
    "gn:population":0,
    "gn:timezone":"Africa/Casablanca",
    "iso:country":"MA",
    "wof:name":"Agni-n-Hggoun",
    "wof:placetype":"locality"
},
  "geometry": {"coordinates":[-9.2906,29.67467000000001],"type":"Point"}
}