{
  "type": "Feature",
  "properties": {
    "gn:admin1_code":"7.0",
    "gn:asciiname":"Douar Laayaycha Oulad Jnani",
    "gn:country_code":"MA",
    "gn:dem":273,
    "gn:feature_class":"P",
    "gn:feature_code":"PPL",
    "gn:name":"Douar Laayaycha Oulad Jnani",
    "gn:population":0,
    "gn:timezone":"Africa/Casablanca",
    "iso:country":"MA",
    "wof:name":"Douar Laayaycha Oulad Jnani",
    "wof:placetype":"locality"
},
  "geometry": {"coordinates":[-9.10571,32.03204],"type":"Point"}
}