{
  "type": "Feature",
  "properties": {
    "gn:admin1_code":"07",
    "gn:asciiname":"El-Arouga",
    "gn:country_code":"MA",
    "gn:dem":491,
    "gn:feature_class":"P",
    "gn:feature_code":"PPL",
    "gn:name":"El-Arouga",
    "gn:population":0,
    "gn:timezone":"Africa/Casablanca",
    "iso:country":"MA",
    "wof:name":"El-Arouga",
    "wof:placetype":"locality"
},
  "geometry": {"coordinates":[-8.17561,31.97284],"type":"Point"}
}