{
  "type": "Feature",
  "properties": {
    "gn:admin1_code":"7.0",
    "gn:asciiname":"Imengayene",
    "gn:country_code":"MA",
    "gn:dem":77,
    "gn:feature_class":"P",
    "gn:feature_code":"PPL",
    "gn:name":"Imengayene",
    "gn:population":0,
    "gn:timezone":"Africa/Casablanca",
    "iso:country":"MA",
    "wof:name":"Imengayene",
    "wof:placetype":"locality"
},
  "geometry": {"coordinates":[-9.77953,31.31687],"type":"Point"}
}