{
  "type": "Feature",
  "properties": {
    "gn:admin1_code":"2.0",
    "gn:asciiname":"Ihmidatene",
    "gn:country_code":"MA",
    "gn:dem":459,
    "gn:feature_class":"P",
    "gn:feature_code":"PPL",
    "gn:name":"Ihmidatene",
    "gn:population":0,
    "gn:timezone":"Africa/Casablanca",
    "iso:country":"MA",
    "wof:name":"Ihmidatene",
    "wof:placetype":"locality"
},
  "geometry": {"coordinates":[-3.24413,35.17495],"type":"Point"}
}