{
  "type": "Feature",
  "properties": {
    "gn:admin1_code":"03",
    "gn:asciiname":"Izemmourene",
    "gn:country_code":"MA",
    "gn:dem":1111,
    "gn:feature_class":"P",
    "gn:feature_code":"PPL",
    "gn:name":"Izemmourene",
    "gn:population":0,
    "gn:timezone":"Africa/Casablanca",
    "iso:country":"MA",
    "wof:name":"Izemmourene",
    "wof:placetype":"locality"
},
  "geometry": {"coordinates":[-3.86576,34.69425],"type":"Point"}
}