{
  "type": "Feature",
  "properties": {
    "gn:admin1_code":"08",
    "gn:asciiname":"Tiouna n'Iarabene",
    "gn:country_code":"MA",
    "gn:dem":913,
    "gn:feature_class":"P",
    "gn:feature_code":"PPL",
    "gn:name":"Tiouna n\u2019Iarabene",
    "gn:population":0,
    "gn:timezone":"Africa/Casablanca",
    "iso:country":"MA",
    "name:und_x_variant":[
        "Touna n\u2019Iarab\u00e8n",
        "Tiouna n\u2019Iarabene"
    ],
    "wof:name":"Tiouna n'Iarabene",
    "wof:placetype":"locality"
},
  "geometry": {"coordinates":[-5.83058,30.62693],"type":"Point"}
}