{
  "type": "Feature",
  "properties": {
    "gn:admin1_code":"1.0",
    "gn:asciiname":"Moulay Tayeb",
    "gn:country_code":"MA",
    "gn:dem":901,
    "gn:feature_class":"P",
    "gn:feature_code":"PPL",
    "gn:name":"Moulay Tayeb",
    "gn:population":0,
    "gn:timezone":"Africa/Casablanca",
    "iso:country":"MA",
    "wof:name":"Moulay Tayeb",
    "wof:placetype":"locality"
},
  "geometry": {"coordinates":[-4.87048,35.02385],"type":"Point"}
}