{
  "type": "Feature",
  "properties": {
    "gn:admin1_code":"1.0",
    "gn:asciiname":"Dar El Ayachi Hanafi",
    "gn:country_code":"MA",
    "gn:dem":128,
    "gn:feature_class":"P",
    "gn:feature_code":"PPL",
    "gn:name":"Dar El Ayachi Hanafi",
    "gn:population":0,
    "gn:timezone":"Africa/Casablanca",
    "iso:country":"MA",
    "wof:name":"Dar El Ayachi Hanafi",
    "wof:placetype":"locality"
},
  "geometry": {"coordinates":[-5.72957,35.59924],"type":"Point"}
}