{
  "type": "Feature",
  "properties": {
    "gn:admin1_code":"01",
    "gn:asciiname":"Bouhelal",
    "gn:country_code":"MA",
    "gn:dem":663,
    "gn:feature_class":"P",
    "gn:feature_code":"PPL",
    "gn:name":"Bouhelal",
    "gn:population":0,
    "gn:timezone":"Africa/Casablanca",
    "iso:country":"MA",
    "name:und_x_variant":[
        "Bouhellal",
        "Bou hilal",
        "Bouhelal"
    ],
    "wof:name":"Bouhelal",
    "wof:placetype":"locality"
},
  "geometry": {"coordinates":[-5.3097,34.72438],"type":"Point"}
}