{
  "type": "Feature",
  "properties": {
    "gn:admin1_code":"05",
    "gn:asciiname":"Agard-n-Ouqiydoun",
    "gn:country_code":"MA",
    "gn:dem":1761,
    "gn:elevation":"0.0",
    "gn:feature_class":"P",
    "gn:feature_code":"PPL",
    "gn:name":"Agard-n-Ouqiydoun",
    "gn:population":0,
    "gn:timezone":"Africa/Casablanca",
    "iso:country":"MA",
    "name:und_x_variant":[
        "Aguerd n\u2019Ougidoum"
    ],
    "wof:name":"Agard-n-Ouqiydoun",
    "wof:placetype":"locality"
},
  "geometry": {"coordinates":[-6.50483,31.82922],"type":"Point"}
}