{
  "type": "Feature",
  "properties": {
    "gn:country":"MA",
    "gn:fcode":"ADM3",
    "gn:population":13328,
    "iso:country":"MA",
    "name:ara_x_preferred":[
        "\u062c\u0627\u0642\u0645\u0629"
    ],
    "name:ara_x_variant":[
        "\u0642\u0635\u0628\u0629 \u0628\u0646 \u0645\u0634\u064a\u0634"
    ],
    "name:ary_x_preferred":[
        "\u0642\u0635\u0628\u0629 \u0628\u0646 \u0645\u0634\u064a\u0634"
    ],
    "name:azb_x_preferred":[
        "\u0642\u0635\u0628\u0647 \u0628\u0646 \u0645\u0634\u06cc\u0634"
    ],
    "name:cat_x_preferred":[
        "Kasbat Ben Mchich"
    ],
    "name:ceb_x_preferred":[
        "Kasbat Ben Mchich"
    ],
    "name:eng_x_preferred":[
        "Kasbat Ben Mchich"
    ],
    "name:fas_x_preferred":[
        "\u0642\u0635\u0628\u0647 \u0628\u0646 \u0645\u0634\u06cc\u0634"
    ],
    "name:fra_x_preferred":[
        "Kasbat Ben Mchich"
    ],
    "name:fra_x_variant":[
        "Kasbat Ben Mchich (CR)",
        "Kasbat Ben Mchich (Commune Rurale)"
    ],
    "name:ita_x_preferred":[
        "Kasbat Ben Mchich"
    ],
    "name:swe_x_preferred":[
        "Kasbat Ben Mchich"
    ],
    "qs:name":"Kasbat Ben Mchich",
    "qs:photos_9r":0,
    "qs:photos_sr":0,
    "qs:pop_sr":"6",
    "wd:wordcount":69,
    "wof:name":"Kasbat Ben Mchich",
    "wof:placetype":"localadmin",
    "wof:population":13328
},
  "geometry": {"coordinates":[-7.46321,33.35958],"type":"Point"}
}