{
  "type": "Feature",
  "properties": {
    "gn:country":"MA",
    "gn:fcode":"ADM3",
    "gn:pop":13328,
    "iso:country":"MA",
    "name:ara_x_preferred":[
        "\u062c\u0627\u0642\u0645\u0629"
    ],
    "name:fra_x_preferred":[
        "Kasbat Ben Mchich"
    ],
    "name:fra_x_variant":[
        "Kasbat Ben Mchich (CR)",
        "Kasbat Ben Mchich (Commune Rurale)"
    ],
    "qs:name":"Kasbat Ben Mchich",
    "qs:photos_9r":0,
    "qs:photos_sr":0,
    "qs:pop_sr":"6",
    "wd:wordcount":69,
    "wof:name":"Kasbat Ben Mchich",
    "wof:placetype":"localadmin",
    "wof:population":13328
},
  "geometry": {"coordinates":[-7.46321,33.35958],"type":"Point"}
}