{
  "type": "Feature",
  "properties": {
    "gn:admin1_code":"7.0",
    "gn:asciiname":"Douar Eddokhane",
    "gn:country_code":"MA",
    "gn:dem":454,
    "gn:feature_class":"P",
    "gn:feature_code":"PPL",
    "gn:name":"Douar Eddokhane",
    "gn:population":0,
    "gn:timezone":"Africa/Casablanca",
    "iso:country":"MA",
    "wof:name":"Douar Eddokhane",
    "wof:placetype":"locality"
},
  "geometry": {"coordinates":[-8.28106,31.82144000000001],"type":"Point"}
}