{
  "type": "Feature",
  "properties": {
    "gn:admin1_code":"6.0",
    "gn:asciiname":"Douar Zrayeb",
    "gn:country_code":"MA",
    "gn:dem":136,
    "gn:feature_class":"P",
    "gn:feature_code":"PPL",
    "gn:name":"Douar Zrayeb",
    "gn:population":0,
    "gn:timezone":"Africa/Casablanca",
    "iso:country":"MA",
    "wof:name":"Douar Zrayeb",
    "wof:placetype":"locality"
},
  "geometry": {"coordinates":[-8.81861,32.5369],"type":"Point"}
}