{
  "type": "Feature",
  "properties": {
    "gn:admin1_code":"07",
    "gn:asciiname":"Oulad Ali",
    "gn:country_code":"MA",
    "gn:dem":310,
    "gn:feature_class":"P",
    "gn:feature_code":"PPL",
    "gn:name":"Oulad Ali",
    "gn:population":0,
    "gn:timezone":"Africa/Casablanca",
    "iso:country":"MA",
    "name:und_x_variant":[
        "Dar Oulad Ali",
        "Douar Oulad Ali",
        "Oulad Ali"
    ],
    "wof:name":"Oulad Ali",
    "wof:placetype":"locality"
},
  "geometry": {"coordinates":[-8.66149,31.89828],"type":"Point"}
}