{
  "type": "Feature",
  "properties": {
    "gn:admin1_code":"3.0",
    "gn:asciiname":"Ain Karma",
    "gn:country_code":"MA",
    "gn:dem":267,
    "gn:feature_class":"P",
    "gn:feature_code":"PPL",
    "gn:name":"Ain Karma",
    "gn:population":0,
    "gn:timezone":"Africa/Casablanca",
    "iso:country":"MA",
    "name:ara_x_preferred":[
        "\u0639\u064a\u0646 \u0643\u0631\u0645\u0629"
    ],
    "name:azb_x_preferred":[
        "\u0639\u06cc\u0646 \u06a9\u0631\u0645\u0647"
    ],
    "name:cat_x_preferred":[
        "Ain Karma"
    ],
    "name:fas_x_preferred":[
        "\u0639\u06cc\u0646 \u06a9\u0631\u0645\u0647"
    ],
    "name:fra_x_preferred":[
        "A\u00efn Karma"
    ],
    "wof:name":"Ain Karma",
    "wof:placetype":"locality"
},
  "geometry": {"coordinates":[-5.6157,34.00664],"type":"Point"}
}