{
  "type": "Feature",
  "properties": {
    "gn:admin1_code":"3.0",
    "gn:asciiname":"Ain Karma",
    "gn:country_code":"MA",
    "gn:dem":267,
    "gn:feature_class":"P",
    "gn:feature_code":"PPL",
    "gn:name":"Ain Karma",
    "gn:population":0,
    "gn:timezone":"Africa/Casablanca",
    "iso:country":"MA",
    "wof:name":"Ain Karma",
    "wof:placetype":"locality"
},
  "geometry": {"coordinates":[-5.6157,34.00664],"type":"Point"}
}