{
  "type": "Feature",
  "properties": {
    "gn:admin1_code":"1.0",
    "gn:asciiname":"Maya",
    "gn:country_code":"MA",
    "gn:dem":20,
    "gn:feature_class":"P",
    "gn:feature_code":"PPL",
    "gn:name":"Maya",
    "gn:population":0,
    "gn:timezone":"Africa/Casablanca",
    "iso:country":"MA",
    "wof:name":"Maya",
    "wof:placetype":"locality"
},
  "geometry": {"coordinates":[-5.12355,35.40147],"type":"Point"}
}