{
  "type": "Feature",
  "properties": {
    "gn:admin1_code":"01",
    "gn:asciiname":"Mechtata",
    "gn:country_code":"MA",
    "gn:dem":322,
    "gn:feature_class":"P",
    "gn:feature_code":"PPL",
    "gn:name":"Mechtata",
    "gn:population":0,
    "gn:timezone":"Africa/Casablanca",
    "iso:country":"MA",
    "wof:name":"Mechtata",
    "wof:placetype":"locality"
},
  "geometry": {"coordinates":[-5.30813,34.67201],"type":"Point"}
}