{
  "type": "Feature",
  "properties": {
    "gn:admin1_code":"09",
    "gn:asciiname":"Anrwiy",
    "gn:country_code":"MA",
    "gn:dem":1262,
    "gn:feature_class":"P",
    "gn:feature_code":"PPL",
    "gn:name":"Anrwiy",
    "gn:population":0,
    "gn:timezone":"Africa/Casablanca",
    "iso:country":"MA",
    "name:und_x_variant":[
        "Tizi n\u2019 Tguemmi",
        "Anrouy"
    ],
    "wof:name":"Anrwiy",
    "wof:placetype":"locality"
},
  "geometry": {"coordinates":[-8.66597,30.14869],"type":"Point"}
}