{
  "type": "Feature",
  "properties": {
    "gn:admin1_code":"06",
    "gn:asciiname":"Souq Jamaa Fdalate",
    "gn:country_code":"MA",
    "gn:dem":193,
    "gn:feature_class":"P",
    "gn:feature_code":"PPL",
    "gn:name":"Souq Jamaa Fdalate",
    "gn:population":0,
    "gn:timezone":"Africa/Casablanca",
    "iso:country":"MA",
    "name:und_x_variant":[
        "Souq aj Jem\u2019a-Fedalat",
        "Souk el Jemaa",
        "El Djeama",
        "El Jema",
        "El Djem\u00e2",
        "Fedalate",
        "Souq Jamaa Fdalate"
    ],
    "wof:name":"Souq Jamaa Fdalate",
    "wof:placetype":"locality"
},
  "geometry": {"coordinates":[-7.30991,33.56748],"type":"Point"}
}