{
  "type": "Feature",
  "properties": {
    "gn:admin1_code":"9.0",
    "gn:asciiname":"Tagadirt",
    "gn:country_code":"MA",
    "gn:dem":834,
    "gn:feature_class":"P",
    "gn:feature_code":"PPL",
    "gn:name":"Tagadirt",
    "gn:population":0,
    "gn:timezone":"Africa/Casablanca",
    "iso:country":"MA",
    "wof:name":"Tagadirt",
    "wof:placetype":"locality"
},
  "geometry": {"coordinates":[-8.05993,30.67695],"type":"Point"}
}