{
  "type": "Feature",
  "properties": {
    "gn:admin1_code":"8.0",
    "gn:asciiname":"Tawrirt",
    "gn:country_code":"MA",
    "gn:dem":1378,
    "gn:feature_class":"P",
    "gn:feature_code":"PPL",
    "gn:name":"Tawrirt",
    "gn:population":0,
    "gn:timezone":"Africa/Casablanca",
    "iso:country":"MA",
    "wof:name":"Tawrirt",
    "wof:placetype":"locality"
},
  "geometry": {"coordinates":[-6.19195,31.19589],"type":"Point"}
}