{
  "type": "Feature",
  "properties": {
    "gn:admin1_code":"4.0",
    "gn:asciiname":"Douar Sidi Ali Lmouddene",
    "gn:country_code":"MA",
    "gn:dem":40,
    "gn:feature_class":"P",
    "gn:feature_code":"PPL",
    "gn:name":"Douar Sidi Ali Lmouddene",
    "gn:population":0,
    "gn:timezone":"Africa/Casablanca",
    "iso:country":"MA",
    "wof:name":"Douar Sidi Ali Lmouddene",
    "wof:placetype":"locality"
},
  "geometry": {"coordinates":[-6.39415,34.2633],"type":"Point"}
}