{
  "type": "Feature",
  "properties": {
    "gn:admin1_code":"01",
    "gn:asciiname":"Douar Bou Quorra",
    "gn:country_code":"MA",
    "gn:dem":472,
    "gn:feature_class":"P",
    "gn:feature_code":"PPL",
    "gn:name":"Douar Bou Quorra",
    "gn:population":0,
    "gn:timezone":"Africa/Casablanca",
    "iso:country":"MA",
    "name:und_x_variant":[
        "Bouchorra Dchar el K\u00e9bir",
        "Bou Korra",
        "Douar Bou Quorra"
    ],
    "wof:name":"Douar Bou Quorra",
    "wof:placetype":"locality"
},
  "geometry": {"coordinates":[-5.2428,34.76738],"type":"Point"}
}