{
  "type": "Feature",
  "properties": {
    "gn:admin1_code":"3.0",
    "gn:asciiname":"Douar Ain Sahnj",
    "gn:country_code":"MA",
    "gn:dem":112,
    "gn:feature_class":"P",
    "gn:feature_code":"PPL",
    "gn:name":"Douar Ain Sahnj",
    "gn:population":0,
    "gn:timezone":"Africa/Casablanca",
    "iso:country":"MA",
    "wof:name":"Douar Ain Sahnj",
    "wof:placetype":"locality"
},
  "geometry": {"coordinates":[-5.22992,34.51802],"type":"Point"}
}