{
  "type": "Feature",
  "properties": {
    "gn:admin1_code":"4.0",
    "gn:asciiname":"Cafcaf",
    "gn:country_code":"MA",
    "gn:dem":11,
    "gn:feature_class":"P",
    "gn:feature_code":"PPL",
    "gn:name":"\u00c7af\u00e7af",
    "gn:population":0,
    "gn:timezone":"Africa/Casablanca",
    "iso:country":"MA",
    "wof:name":"Cafcaf",
    "wof:placetype":"locality"
},
  "geometry": {"coordinates":[-6.53267,34.35619000000001],"type":"Point"}
}