{
  "type": "Feature",
  "properties": {
    "gn:admin1_code":"06",
    "gn:asciiname":"Douar Oulad El Caid Charqi",
    "gn:country_code":"MA",
    "gn:dem":601,
    "gn:feature_class":"P",
    "gn:feature_code":"PPL",
    "gn:name":"Douar Oulad El Caid Charqi",
    "gn:population":0,
    "gn:timezone":"Africa/Casablanca",
    "iso:country":"MA",
    "name:und_x_variant":[
        "Dar Ca\u00efd Cheroui"
    ],
    "wof:name":"Douar Oulad El Caid Charqi",
    "wof:placetype":"locality"
},
  "geometry": {"coordinates":[-7.0567,33.10416],"type":"Point"}
}