{
  "type": "Feature",
  "properties": {
    "gn:admin1_code":"2.0",
    "gn:asciiname":"Bni Sidel",
    "gn:country_code":"MA",
    "gn:dem":218,
    "gn:feature_class":"P",
    "gn:feature_code":"PPL",
    "gn:name":"Bni Sidel",
    "gn:population":0,
    "gn:timezone":"Africa/Casablanca",
    "iso:country":"MA",
    "wof:name":"Bni Sidel",
    "wof:placetype":"locality"
},
  "geometry": {"coordinates":[-3.04434,35.18685],"type":"Point"}
}