{
  "type": "Feature",
  "properties": {
    "gn:admin1_code":"7.0",
    "gn:asciiname":"Dar Mohamed Ezzouini",
    "gn:country_code":"MA",
    "gn:dem":343,
    "gn:feature_class":"P",
    "gn:feature_code":"PPL",
    "gn:name":"Dar Mohamed Ezzouini",
    "gn:population":0,
    "gn:timezone":"Africa/Casablanca",
    "iso:country":"MA",
    "wof:name":"Dar Mohamed Ezzouini",
    "wof:placetype":"locality"
},
  "geometry": {"coordinates":[-8.37484,31.67023],"type":"Point"}
}