{
  "type": "Feature",
  "properties": {
    "gn:admin1_code":"01",
    "gn:asciiname":"Khemis Sahel",
    "gn:country_code":"MA",
    "gn:dem":180,
    "gn:feature_class":"P",
    "gn:feature_code":"PPL",
    "gn:name":"Khemis Sahel",
    "gn:population":0,
    "gn:timezone":"Africa/Casablanca",
    "iso:country":"MA",
    "name:ara_x_preferred":[
        "\u062e\u0645\u064a\u0633 \u0627\u0644\u0633\u0627\u062d\u0644"
    ],
    "name:ceb_x_preferred":[
        "Khemis du Sahel"
    ],
    "name:fra_x_preferred":[
        "Kh\u00e9mis Sahel"
    ],
    "name:swe_x_preferred":[
        "Khemis du Sahel"
    ],
    "name:und_x_variant":[
        "El Jmis",
        "Zoco el Jemis",
        "Soko el Jemis",
        "Kh\u00e9mis Sahel",
        "Souk Khemis du Sahel",
        "El Khemis",
        "Khemis du Sahel",
        "Khemis Sahel"
    ],
    "wof:name":"Khemis Sahel",
    "wof:placetype":"locality"
},
  "geometry": {"coordinates":[-6.0796,35.25344000000001],"type":"Point"}
}