{
  "type": "Feature",
  "properties": {
    "gn:admin1_code":"09",
    "gn:asciiname":"Tamsoult",
    "gn:country_code":"MA",
    "gn:dem":1553,
    "gn:feature_class":"P",
    "gn:feature_code":"PPL",
    "gn:name":"Tamsoult",
    "gn:population":0,
    "gn:timezone":"Africa/Casablanca",
    "iso:country":"MA",
    "wof:name":"Tamsoult",
    "wof:placetype":"locality"
},
  "geometry": {"coordinates":[-8.38712,30.05571],"type":"Point"}
}