{
  "type": "Feature",
  "properties": {
    "gn:admin1_code":"01",
    "gn:asciiname":"Douar Dehiyer",
    "gn:country_code":"MA",
    "gn:dem":320,
    "gn:feature_class":"P",
    "gn:feature_code":"PPL",
    "gn:name":"Douar Dehiyer",
    "gn:population":0,
    "gn:timezone":"Africa/Casablanca",
    "iso:country":"MA",
    "name:und_x_variant":[
        "Dechiar Seflia",
        "Dechiar",
        "Ed Dechiyar",
        "Douar Dehiyer"
    ],
    "wof:name":"Douar Dehiyer",
    "wof:placetype":"locality"
},
  "geometry": {"coordinates":[-5.58593,35.2509],"type":"Point"}
}