{
  "type": "Feature",
  "properties": {
    "gn:admin1_code":"07",
    "gn:asciiname":"Douar Timajdarra",
    "gn:country_code":"MA",
    "gn:dem":360,
    "gn:feature_class":"P",
    "gn:feature_code":"PPL",
    "gn:name":"Douar Timajdarra",
    "gn:population":0,
    "gn:timezone":"Africa/Casablanca",
    "iso:country":"MA",
    "name:und_x_variant":[
        "Douar Ahl Timjederra",
        "Timjdara",
        "Douar Timajdarra"
    ],
    "wof:name":"Douar Timajdarra",
    "wof:placetype":"locality"
},
  "geometry": {"coordinates":[-9.15366,31.64427],"type":"Point"}
}