{
  "type": "Feature",
  "properties": {
    "gn:admin1_code":"03",
    "gn:asciiname":"Douar Ait Alla",
    "gn:country_code":"MA",
    "gn:dem":921,
    "gn:feature_class":"P",
    "gn:feature_code":"PPL",
    "gn:name":"Douar Ait Alla",
    "gn:population":0,
    "gn:timezone":"Africa/Casablanca",
    "iso:country":"MA",
    "name:und_x_variant":[
        "A\u00eft Alla",
        "Douar A\u00eft Allah",
        "Douar Ait Alla"
    ],
    "wof:name":"Douar Ait Alla",
    "wof:placetype":"locality"
},
  "geometry": {"coordinates":[-5.51764,33.6335],"type":"Point"}
}