{
  "type": "Feature",
  "properties": {
    "gn:admin1_code":"07",
    "gn:asciiname":"Khoual",
    "gn:country_code":"MA",
    "gn:dem":48,
    "gn:feature_class":"P",
    "gn:feature_code":"PPL",
    "gn:name":"Khou\u00e2l",
    "gn:population":0,
    "gn:timezone":"Africa/Casablanca",
    "iso:country":"MA",
    "name:und_x_variant":[
        "Douar el Moueddene",
        "Khou\u00e2l"
    ],
    "wof:name":"Khoual",
    "wof:placetype":"locality"
},
  "geometry": {"coordinates":[-9.31,31.93],"type":"Point"}
}