{
  "type": "Feature",
  "properties": {
    "gn:admin1_code":"09",
    "gn:asciiname":"Tikiout",
    "gn:country_code":"MA",
    "gn:dem":32,
    "gn:feature_class":"P",
    "gn:feature_code":"PPL",
    "gn:name":"Tikiout",
    "gn:population":0,
    "gn:timezone":"Africa/Casablanca",
    "iso:country":"MA",
    "name:und_x_variant":[
        "Tikioute",
        "Tikiout"
    ],
    "wof:name":"Tikiout",
    "wof:placetype":"locality"
},
  "geometry": {"coordinates":[-9.66873,29.98251],"type":"Point"}
}