{
  "type": "Feature",
  "properties": {
    "gn:country":"MA",
    "gn:fcode":"ADM3",
    "gn:population":14203,
    "iso:country":"MA",
    "name:ara_x_preferred":[
        "\u0633\u0631\u0648\u0627"
    ],
    "name:ara_x_variant":[
        "\u062a\u064a\u0644\u0648\u064a\u062a"
    ],
    "name:ary_x_preferred":[
        "\u062a\u064a\u0644\u0648\u064a\u062a"
    ],
    "name:bul_x_preferred":[
        "\u0422\u0435\u043b\u043e\u0443\u0435\u0442"
    ],
    "name:cat_x_preferred":[
        "Telouet"
    ],
    "name:ceb_x_preferred":[
        "Telouet"
    ],
    "name:deu_x_preferred":[
        "Telouet"
    ],
    "name:eng_x_preferred":[
        "Telouet"
    ],
    "name:fra_x_preferred":[
        "Telouet"
    ],
    "name:fra_x_variant":[
        "Telouet (CR)",
        "Telouet (Commune Rurale)",
        "T\u00e9louet"
    ],
    "name:ita_x_preferred":[
        "T\u00e9louet"
    ],
    "name:nld_x_preferred":[
        "Telouet"
    ],
    "name:por_x_preferred":[
        "T\u00e9louet"
    ],
    "name:swe_x_preferred":[
        "Telouet"
    ],
    "qs:name":"Telouet",
    "qs:photos_9r":0,
    "qs:photos_sr":0,
    "qs:pop_sr":"6",
    "wd:wordcount":125,
    "wof:name":"Telouet",
    "wof:placetype":"localadmin",
    "wof:population":14203
},
  "geometry": {"coordinates":[-7.17601,31.29383],"type":"Point"}
}