{
  "type": "Feature",
  "properties": {
    "gn:admin1_code":"08",
    "gn:asciiname":"Taerguiout",
    "gn:country_code":"MA",
    "gn:dem":1479,
    "gn:feature_class":"P",
    "gn:feature_code":"PPL",
    "gn:name":"Taerguiout",
    "gn:population":0,
    "gn:timezone":"Africa/Casablanca",
    "iso:country":"MA",
    "name:und_x_variant":[
        "Targuiout",
        "Taghembout Ksar",
        "Taerguiout"
    ],
    "wof:name":"Taerguiout",
    "wof:placetype":"locality"
},
  "geometry": {"coordinates":[-5.30913,31.73581],"type":"Point"}
}