{
  "type": "Feature",
  "properties": {
    "gn:admin1_code":"3.0",
    "gn:asciiname":"Oulad Amrane",
    "gn:country_code":"MA",
    "gn:dem":404,
    "gn:feature_class":"P",
    "gn:feature_code":"PPL",
    "gn:name":"Oulad Amrane",
    "gn:population":0,
    "gn:timezone":"Africa/Casablanca",
    "iso:country":"MA",
    "name:ara_x_preferred":[
        "\u0623\u0648\u0644\u0627\u062f \u0639\u0645\u0631\u0627\u0646"
    ],
    "name:azb_x_preferred":[
        "\u0627\u0648\u0644\u0627\u062f \u0639\u0645\u0631\u0627\u0646"
    ],
    "name:cat_x_preferred":[
        "Oulad Amrane"
    ],
    "name:fas_x_preferred":[
        "\u0627\u0648\u0644\u0627\u062f \u0639\u0645\u0631\u0627\u0646"
    ],
    "name:fra_x_preferred":[
        "Oulad Amrane"
    ],
    "name:ita_x_preferred":[
        "Oulad Amrane"
    ],
    "wof:name":"Oulad Amrane",
    "wof:placetype":"locality"
},
  "geometry": {"coordinates":[-5.35141,33.9768],"type":"Point"}
}