{
  "type": "Feature",
  "properties": {
    "gn:admin1_code":"5.0",
    "gn:asciiname":"El Jadid",
    "gn:country_code":"MA",
    "gn:dem":986,
    "gn:feature_class":"P",
    "gn:feature_code":"PPL",
    "gn:name":"El Jadid",
    "gn:population":0,
    "gn:timezone":"Africa/Casablanca",
    "iso:country":"MA",
    "wof:name":"El Jadid",
    "wof:placetype":"neighbourhood"
},
  "geometry": {"coordinates":[-7.00786,31.72418],"type":"Point"}
}