{
  "type": "Feature",
  "properties": {
    "gn:admin1_code":"6.0",
    "gn:asciiname":"Derkaoua",
    "gn:country_code":"MA",
    "gn:dem":333,
    "gn:feature_class":"P",
    "gn:feature_code":"PPL",
    "gn:name":"Derkaoua",
    "gn:population":0,
    "gn:timezone":"Africa/Casablanca",
    "iso:country":"MA",
    "wof:name":"Derkaoua",
    "wof:placetype":"locality"
},
  "geometry": {"coordinates":[-7.62235,32.53218],"type":"Point"}
}