{
  "type": "Feature",
  "properties": {
    "gn:admin1_code":"07",
    "gn:asciiname":"Douar Saadla",
    "gn:country_code":"MA",
    "gn:dem":143,
    "gn:feature_class":"P",
    "gn:feature_code":"PPL",
    "gn:name":"Douar Saadla",
    "gn:population":0,
    "gn:timezone":"Africa/Casablanca",
    "iso:country":"MA",
    "name:und_x_variant":[
        "Douar S\u00e2dla",
        "Sa\u00e2dla",
        "S\u00e2dla",
        "Douar Saadla"
    ],
    "wof:name":"Douar Saadla",
    "wof:placetype":"locality"
},
  "geometry": {"coordinates":[-9.09362,32.37719],"type":"Point"}
}