{
  "type": "Feature",
  "properties": {
    "gn:admin1_code":"9.0",
    "gn:asciiname":"Tazart",
    "gn:country_code":"MA",
    "gn:dem":1123,
    "gn:feature_class":"P",
    "gn:feature_code":"PPL",
    "gn:name":"Tazart",
    "gn:population":0,
    "gn:timezone":"Africa/Casablanca",
    "iso:country":"MA",
    "name:ara_x_preferred":[
        "\u062a\u0632\u0627\u0631\u062a"
    ],
    "name:azb_x_preferred":[
        "\u062a\u0632\u0627\u0631\u062a"
    ],
    "name:cat_x_preferred":[
        "Tazart"
    ],
    "name:ceb_x_preferred":[
        "Tazart"
    ],
    "name:fas_x_preferred":[
        "\u062a\u0632\u0627\u0631\u062a"
    ],
    "name:fra_x_preferred":[
        "Tazart"
    ],
    "name:ita_x_preferred":[
        "Tazart"
    ],
    "name:swe_x_preferred":[
        "Tazart"
    ],
    "name:urd_x_preferred":[
        "\u062a\u0632\u0627\u0631\u062a"
    ],
    "wof:name":"Tazart",
    "wof:placetype":"locality"
},
  "geometry": {"coordinates":[-8.83857,30.14277],"type":"Point"}
}