{
  "type": "Feature",
  "properties": {
    "gn:admin1_code":"07",
    "gn:asciiname":"Draouch",
    "gn:country_code":"MA",
    "gn:dem":119,
    "gn:feature_class":"P",
    "gn:feature_code":"PPL",
    "gn:name":"Draouch",
    "gn:population":0,
    "gn:timezone":"Africa/Casablanca",
    "iso:country":"MA",
    "name:und_x_variant":[
        "Douar Draouch",
        "Draouach",
        "Douar Larbi",
        "Draouch",
        "Draoueh"
    ],
    "wof:name":"Draouch",
    "wof:placetype":"locality"
},
  "geometry": {"coordinates":[-9.15274,32.41065],"type":"Point"}
}