{
  "type": "Feature",
  "properties": {
    "gn:country":"MA",
    "gn:fcode":"ADM3",
    "gn:population":2934,
    "iso:country":"MA",
    "name:ara_x_preferred":[
        "\u0627\u0644\u0648\u0643\u0648\u0645"
    ],
    "name:fra_x_preferred":[
        "Ibn Yacoub"
    ],
    "name:fra_x_variant":[
        "Ibn Yacoub (CR)",
        "Ibn Yacoub (Commune Rurale)"
    ],
    "qs_pg:aaroncc":"MA",
    "qs_pg:gn_country":"MA",
    "qs_pg:gn_fcode":"ADM3",
    "qs_pg:gn_pop":2934,
    "qs_pg:name":"Ibn Yacoub",
    "qs_pg:photos_9r":0,
    "qs_pg:photos_sr":0,
    "qs_pg:pop_sr":4,
    "qs_pg:qs_pg_placetype":"localadmin",
    "wof:name":"Ibn Yacoub",
    "wof:placetype":"localadmin",
    "wof:population":2934
},
  "geometry": {"coordinates":[-7.84312,30.00843],"type":"Point"}
}