{
  "type": "Feature",
  "properties": {
    "gn:admin1_code":"09",
    "gn:asciiname":"Tisksal",
    "gn:country_code":"MA",
    "gn:dem":391,
    "gn:feature_class":"P",
    "gn:feature_code":"PPL",
    "gn:name":"Tisksal",
    "gn:population":0,
    "gn:timezone":"Africa/Casablanca",
    "iso:country":"MA",
    "name:und_x_variant":[
        "Takaliest"
    ],
    "wof:name":"Tisksal",
    "wof:placetype":"locality"
},
  "geometry": {"coordinates":[-9.44552,29.65273],"type":"Point"}
}