{
  "type": "Feature",
  "properties": {
    "gn:country":"MA",
    "gn:fcode":"ADM3",
    "gn:population":1997,
    "iso:country":"MA",
    "name:ara_x_preferred":[
        "\u0645\u0631\u0643\u0632 \u0645\u0639\u0627\u0632\u064a\u0632"
    ],
    "name:fra_x_preferred":[
        "Oued El Heimer"
    ],
    "name:fra_x_variant":[
        "Oued El Heimer (AC)",
        "Oued El Heimer (Agglomeration Communale)"
    ],
    "qs:name":"Oued El Heimer",
    "qs:photos_9r":0,
    "qs:photos_sr":0,
    "qs:pop_sr":"3",
    "wof:name":"Oued El Heimer",
    "wof:placetype":"localadmin",
    "wof:population":1997
},
  "geometry": {"coordinates":[-1.90686,34.44723],"type":"Point"}
}