{
  "type": "Feature",
  "properties": {
    "gn:admin1_code":"07",
    "gn:asciiname":"Dr. Mbarek Bou Souna",
    "gn:country_code":"MA",
    "gn:dem":391,
    "gn:feature_class":"P",
    "gn:feature_code":"PPL",
    "gn:name":"Dr. Mbarek Bou Souna",
    "gn:population":0,
    "gn:timezone":"Africa/Casablanca",
    "iso:country":"MA",
    "name:und_x_variant":[
        "Sidi-Embarek-b-Boussoum"
    ],
    "wof:name":"Dr. Mbarek Bou Souna",
    "wof:placetype":"locality"
},
  "geometry": {"coordinates":[-8.5916,32.03184],"type":"Point"}
}