{
  "type": "Feature",
  "properties": {
    "gn:admin1_code":"9.0",
    "gn:asciiname":"Iramrai",
    "gn:country_code":"MA",
    "gn:dem":518,
    "gn:feature_class":"P",
    "gn:feature_code":"PPL",
    "gn:name":"Iramrai",
    "gn:population":0,
    "gn:timezone":"Africa/Casablanca",
    "iso:country":"MA",
    "wof:name":"Iramrai",
    "wof:placetype":"locality"
},
  "geometry": {"coordinates":[-9.82791,29.4748],"type":"Point"}
}