{
  "type": "Feature",
  "properties": {
    "gn:admin1_code":"04",
    "gn:asciiname":"Douar Oulad Hommad",
    "gn:country_code":"MA",
    "gn:dem":43,
    "gn:feature_class":"P",
    "gn:feature_code":"PPL",
    "gn:name":"Douar Oulad Hommad",
    "gn:population":0,
    "gn:timezone":"Africa/Casablanca",
    "iso:country":"MA",
    "name:und_x_variant":[
        "Oulad Ahmed",
        "Ouled Hmed",
        "Douar Oulad Ahmed",
        "Douar Oulad Hommad"
    ],
    "wof:name":"Douar Oulad Hommad",
    "wof:placetype":"locality"
},
  "geometry": {"coordinates":[-5.83194,34.59304],"type":"Point"}
}