{
  "type": "Feature",
  "properties": {
    "gn:admin1_code":"7.0",
    "gn:asciiname":"Ait Ben Hammou Ou 'Ali",
    "gn:country_code":"MA",
    "gn:dem":939,
    "gn:feature_class":"P",
    "gn:feature_code":"PPL",
    "gn:name":"A\u00eft Ben Hammou Ou \u2019Ali",
    "gn:population":0,
    "gn:timezone":"Africa/Casablanca",
    "iso:country":"MA",
    "wof:name":"Ait Ben Hammou Ou 'Ali",
    "wof:placetype":"locality"
},
  "geometry": {"coordinates":[-7.54172,31.47627],"type":"Point"}
}