{
  "type": "Feature",
  "properties": {
    "gn:admin1_code":"9.0",
    "gn:asciiname":"Id Zinad",
    "gn:country_code":"MA",
    "gn:dem":545,
    "gn:feature_class":"P",
    "gn:feature_code":"PPL",
    "gn:name":"Id Zinad",
    "gn:population":0,
    "gn:timezone":"Africa/Casablanca",
    "iso:country":"MA",
    "wof:name":"Id Zinad",
    "wof:placetype":"locality"
},
  "geometry": {"coordinates":[-9.88976,29.49511],"type":"Point"}
}