{
  "type": "Feature",
  "properties": {
    "gn:admin1_code":"07",
    "gn:asciiname":"Tourirt",
    "gn:country_code":"MA",
    "gn:dem":1078,
    "gn:feature_class":"P",
    "gn:feature_code":"PPL",
    "gn:name":"Tourirt",
    "gn:population":0,
    "gn:timezone":"Africa/Casablanca",
    "iso:country":"MA",
    "wof:name":"Tourirt",
    "wof:placetype":"locality"
},
  "geometry": {"coordinates":[-9.27614,30.903],"type":"Point"}
}