{
  "type": "Feature",
  "properties": {
    "gn:admin1_code":"7.0",
    "gn:asciiname":"Agadir Laachour",
    "gn:country_code":"MA",
    "gn:dem":396,
    "gn:feature_class":"P",
    "gn:feature_code":"PPL",
    "gn:name":"Agadir Laachour",
    "gn:population":0,
    "gn:timezone":"Africa/Casablanca",
    "iso:country":"MA",
    "wof:name":"Agadir Laachour",
    "wof:placetype":"locality"
},
  "geometry": {"coordinates":[-9.45697,31.3651],"type":"Point"}
}