{
  "type": "Feature",
  "properties": {
    "gn:admin1_code":"08",
    "gn:asciiname":"Zaouia el Cadi",
    "gn:country_code":"MA",
    "gn:dem":742,
    "gn:feature_class":"P",
    "gn:feature_code":"PPL",
    "gn:name":"Zaouia el Cadi",
    "gn:population":0,
    "gn:timezone":"Africa/Casablanca",
    "iso:country":"MA",
    "name:und_x_variant":[
        "Zaouia el Kadi",
        "Zaouia el Cadi"
    ],
    "wof:name":"Zaouia el Cadi",
    "wof:placetype":"locality"
},
  "geometry": {"coordinates":[-5.86,30.41],"type":"Point"}
}