{
  "type": "Feature",
  "properties": {
    "gn:admin1_code":"7.0",
    "gn:asciiname":"Douar Id Aqdim",
    "gn:country_code":"MA",
    "gn:dem":209,
    "gn:feature_class":"P",
    "gn:feature_code":"PPL",
    "gn:name":"Douar Id Aqdim",
    "gn:population":0,
    "gn:timezone":"Africa/Casablanca",
    "iso:country":"MA",
    "wof:name":"Douar Id Aqdim",
    "wof:placetype":"locality"
},
  "geometry": {"coordinates":[-9.54097,31.45317],"type":"Point"}
}