{
  "type": "Feature",
  "properties": {
    "gn:admin1_code":"1.0",
    "gn:asciiname":"Oulad Rafaa",
    "gn:country_code":"MA",
    "gn:dem":64,
    "gn:feature_class":"P",
    "gn:feature_code":"PPL",
    "gn:name":"Oulad Rafaa",
    "gn:population":0,
    "gn:timezone":"Africa/Casablanca",
    "iso:country":"MA",
    "wof:name":"Oulad Rafaa",
    "wof:placetype":"locality"
},
  "geometry": {"coordinates":[-6.06187,35.03179],"type":"Point"}
}