{
  "type": "Feature",
  "properties": {
    "gn:admin1_code":"6.0",
    "gn:asciiname":"Anouda",
    "gn:country_code":"MA",
    "gn:dem":429,
    "gn:feature_class":"P",
    "gn:feature_code":"PPL",
    "gn:name":"Anouda",
    "gn:population":0,
    "gn:timezone":"Africa/Casablanca",
    "iso:country":"MA",
    "wof:name":"Anouda",
    "wof:placetype":"locality"
},
  "geometry": {"coordinates":[-7.65257,32.97833],"type":"Point"}
}