{
  "type": "Feature",
  "properties": {
    "gn:admin1_code":"8.0",
    "gn:asciiname":"Ait Ourjdar",
    "gn:country_code":"MA",
    "gn:dem":1961,
    "gn:feature_class":"P",
    "gn:feature_code":"PPL",
    "gn:name":"A\u00eft Ourjdar",
    "gn:population":0,
    "gn:timezone":"Africa/Casablanca",
    "iso:country":"MA",
    "wof:name":"Ait Ourjdar",
    "wof:placetype":"locality"
},
  "geometry": {"coordinates":[-5.785,31.17662],"type":"Point"}
}