{
  "type": "Feature",
  "properties": {
    "gn:admin1_code":"1.0",
    "gn:asciiname":"Douar Ait Amer Ou Chaayb",
    "gn:country_code":"MA",
    "gn:dem":214,
    "gn:feature_class":"P",
    "gn:feature_code":"PPL",
    "gn:name":"Douar Ait Amer Ou Chaayb",
    "gn:population":0,
    "gn:timezone":"Africa/Casablanca",
    "iso:country":"MA",
    "wof:name":"Douar Ait Amer Ou Chaayb",
    "wof:placetype":"locality"
},
  "geometry": {"coordinates":[-3.90441,35.12075],"type":"Point"}
}