{
  "type": "Feature",
  "properties": {
    "gn:admin1_code":"09",
    "gn:asciiname":"Anamerane",
    "gn:country_code":"MA",
    "gn:dem":453,
    "gn:feature_class":"P",
    "gn:feature_code":"PPL",
    "gn:name":"Anamerane",
    "gn:population":0,
    "gn:timezone":"Africa/Casablanca",
    "iso:country":"MA",
    "wof:name":"Anamerane",
    "wof:placetype":"locality"
},
  "geometry": {"coordinates":[-9.49946,30.49624],"type":"Point"}
}