{
  "type": "Feature",
  "properties": {
    "gn:admin1_code":"07",
    "gn:asciiname":"Ammasennkik",
    "gn:country_code":"MA",
    "gn:dem":1326,
    "gn:feature_class":"P",
    "gn:feature_code":"PPL",
    "gn:name":"Ammasennkik",
    "gn:population":0,
    "gn:timezone":"Africa/Casablanca",
    "iso:country":"MA",
    "name:und_x_variant":[
        "Ammasennikik",
        "Ammassenkik",
        "Ammasennkik"
    ],
    "wof:name":"Ammasennkik",
    "wof:placetype":"locality"
},
  "geometry": {"coordinates":[-8.03688,31.28414],"type":"Point"}
}