{
  "type": "Feature",
  "properties": {
    "gn:admin1_code":"07",
    "gn:asciiname":"As Salek",
    "gn:country_code":"MA",
    "gn:dem":714,
    "gn:feature_class":"P",
    "gn:feature_code":"PPL",
    "gn:name":"As Salek",
    "gn:population":0,
    "gn:timezone":"Africa/Casablanca",
    "iso:country":"MA",
    "name:und_x_variant":[
        "Douar es Salek",
        "Selk",
        "As Salek"
    ],
    "wof:name":"As Salek",
    "wof:placetype":"locality"
},
  "geometry": {"coordinates":[-8.33593,31.39143],"type":"Point"}
}