{
  "type": "Feature",
  "properties": {
    "gn:admin1_code":"07",
    "gn:asciiname":"Tichgout",
    "gn:country_code":"MA",
    "gn:dem":1172,
    "gn:feature_class":"P",
    "gn:feature_code":"PPL",
    "gn:name":"Tichgout",
    "gn:population":0,
    "gn:timezone":"Africa/Casablanca",
    "iso:country":"MA",
    "name:und_x_variant":[
        "Tijgout"
    ],
    "wof:name":"Tichgout",
    "wof:placetype":"locality"
},
  "geometry": {"coordinates":[-9.24297,31.13862],"type":"Point"}
}