{
  "type": "Feature",
  "properties": {
    "gn:admin1_code":"09",
    "gn:asciiname":"Talat Wamane",
    "gn:country_code":"MA",
    "gn:dem":1777,
    "gn:feature_class":"P",
    "gn:feature_code":"PPL",
    "gn:name":"Talat Wamane",
    "gn:population":0,
    "gn:timezone":"Africa/Casablanca",
    "iso:country":"MA",
    "name:und_x_variant":[
        "Talate Ouamane",
        "Talat Wamane",
        "Tal\u00e2at Nouamane",
        "Jebel Talat Ouamane",
        "Jebel Talate Ouamane"
    ],
    "wof:name":"Talat Wamane",
    "wof:placetype":"locality"
},
  "geometry": {"coordinates":[-8.37025,30.11563],"type":"Point"}
}