{
  "type": "Feature",
  "properties": {
    "gn:admin1_code":"9.0",
    "gn:asciiname":"I'atrane",
    "gn:country_code":"MA",
    "gn:dem":182,
    "gn:feature_class":"P",
    "gn:feature_code":"PPL",
    "gn:name":"I\u2019atrane",
    "gn:population":0,
    "gn:timezone":"Africa/Casablanca",
    "iso:country":"MA",
    "wof:name":"I'atrane",
    "wof:placetype":"locality"
},
  "geometry": {"coordinates":[-9.28528,30.17583],"type":"Point"}
}