{
  "type": "Feature",
  "properties": {
    "gn:admin1_code":"07",
    "gn:asciiname":"Ait Zaoueg",
    "gn:country_code":"MA",
    "gn:dem":594,
    "gn:feature_class":"P",
    "gn:feature_code":"PPL",
    "gn:name":"Ait Zaoueg",
    "gn:population":0,
    "gn:timezone":"Africa/Casablanca",
    "iso:country":"MA",
    "name:und_x_variant":[
        "A\u00eft Zdoigue",
        "A\u00eft Azouk",
        "Ait Zaoueg"
    ],
    "wof:name":"Ait Zaoueg",
    "wof:placetype":"locality"
},
  "geometry": {"coordinates":[-7.72827,31.57195],"type":"Point"}
}