{
  "type": "Feature",
  "properties": {
    "gn:admin1_code":"9.0",
    "gn:asciiname":"Agni Iygjjiymn",
    "gn:country_code":"MA",
    "gn:dem":667,
    "gn:feature_class":"P",
    "gn:feature_code":"PPL",
    "gn:name":"Agni Iygjjiymn",
    "gn:population":0,
    "gn:timezone":"Africa/Casablanca",
    "iso:country":"MA",
    "wof:name":"Agni Iygjjiymn",
    "wof:placetype":"locality"
},
  "geometry": {"coordinates":[-9.31215,29.6014],"type":"Point"}
}