{
  "type": "Feature",
  "properties": {
    "gn:admin1_code":"9.0",
    "gn:asciiname":"Id Ou Touf",
    "gn:country_code":"MA",
    "gn:dem":799,
    "gn:feature_class":"P",
    "gn:feature_code":"PPL",
    "gn:name":"Id Ou Touf",
    "gn:population":0,
    "gn:timezone":"Africa/Casablanca",
    "iso:country":"MA",
    "wof:name":"Id Ou Touf",
    "wof:placetype":"locality"
},
  "geometry": {"coordinates":[-9.75706,29.4558],"type":"Point"}
}