{
  "type": "Feature",
  "properties": {
    "gn:admin1_code":"7.0",
    "gn:asciiname":"Leftaynat",
    "gn:country_code":"MA",
    "gn:dem":478,
    "gn:feature_class":"P",
    "gn:feature_code":"PPL",
    "gn:name":"Leftaynat",
    "gn:population":0,
    "gn:timezone":"Africa/Casablanca",
    "iso:country":"MA",
    "wof:name":"Leftaynat",
    "wof:placetype":"locality"
},
  "geometry": {"coordinates":[-8.86776,31.99504],"type":"Point"}
}