{
  "type": "Feature",
  "properties": {
    "gn:admin1_code":"7.0",
    "gn:asciiname":"Ait Hamma",
    "gn:country_code":"MA",
    "gn:dem":1024,
    "gn:feature_class":"P",
    "gn:feature_code":"PPL",
    "gn:name":"A\u00eft Hamma",
    "gn:population":0,
    "gn:timezone":"Africa/Casablanca",
    "iso:country":"MA",
    "wof:name":"Ait Hamma",
    "wof:placetype":"locality"
},
  "geometry": {"coordinates":[-7.71421,31.39754000000001],"type":"Point"}
}