{
  "type": "Feature",
  "properties": {
    "gn:admin1_code":"05",
    "gn:asciiname":"Ait Ben Sa'id",
    "gn:country_code":"MA",
    "gn:dem":821,
    "gn:feature_class":"P",
    "gn:feature_code":"PPL",
    "gn:name":"A\u00eft Ben Sa\u2019id",
    "gn:population":0,
    "gn:timezone":"Africa/Casablanca",
    "iso:country":"MA",
    "name:und_x_variant":[
        "A\u00eft Ben Sa\u2019id",
        "A\u00eft Sa\u00efd"
    ],
    "wof:name":"Ait Ben Sa'id",
    "wof:placetype":"locality"
},
  "geometry": {"coordinates":[-5.8192,32.69864],"type":"Point"}
}