{
  "type": "Feature",
  "properties": {
    "gn:admin1_code":"09",
    "gn:asciiname":"Tighoula",
    "gn:country_code":"MA",
    "gn:dem":1633,
    "gn:feature_class":"P",
    "gn:feature_code":"PPL",
    "gn:name":"Tighoula",
    "gn:population":0,
    "gn:timezone":"Africa/Casablanca",
    "iso:country":"MA",
    "name:und_x_variant":[
        "Tiroula"
    ],
    "wof:name":"Tighoula",
    "wof:placetype":"locality"
},
  "geometry": {"coordinates":[-8.5557,30.09865],"type":"Point"}
}