{
  "type": "Feature",
  "properties": {
    "gn:admin1_code":"1.0",
    "gn:asciiname":"Douar Ferraha",
    "gn:country_code":"MA",
    "gn:dem":311,
    "gn:feature_class":"P",
    "gn:feature_code":"PPL",
    "gn:name":"Douar Ferraha",
    "gn:population":0,
    "gn:timezone":"Africa/Casablanca",
    "iso:country":"MA",
    "wof:name":"Douar Ferraha",
    "wof:placetype":"locality"
},
  "geometry": {"coordinates":[-5.51992,34.97453],"type":"Point"}
}