{
  "type": "Feature",
  "properties": {
    "gn:admin1_code":"7.0",
    "gn:asciiname":"Douar Lahbib",
    "gn:country_code":"MA",
    "gn:dem":432,
    "gn:feature_class":"P",
    "gn:feature_code":"PPL",
    "gn:name":"Douar Lahbib",
    "gn:population":0,
    "gn:timezone":"Africa/Casablanca",
    "iso:country":"MA",
    "wof:name":"Douar Lahbib",
    "wof:placetype":"locality"
},
  "geometry": {"coordinates":[-8.826,32.11168],"type":"Point"}
}