{
  "type": "Feature",
  "properties": {
    "gn:admin1_code":"3.0",
    "gn:asciiname":"Douar El Mehajet",
    "gn:country_code":"MA",
    "gn:dem":1107,
    "gn:feature_class":"P",
    "gn:feature_code":"PPL",
    "gn:name":"Douar El Mehajet",
    "gn:population":0,
    "gn:timezone":"Africa/Casablanca",
    "iso:country":"MA",
    "wof:name":"Douar El Mehajet",
    "wof:placetype":"locality"
},
  "geometry": {"coordinates":[-4.07789,33.91726],"type":"Point"}
}