{
  "type": "Feature",
  "properties": {
    "gn:admin1_code":"08",
    "gn:asciiname":"Taourirt n'Ounissi",
    "gn:country_code":"MA",
    "gn:dem":1570,
    "gn:feature_class":"P",
    "gn:feature_code":"PPL",
    "gn:name":"Taourirt n\u2019Ounissi",
    "gn:population":0,
    "gn:timezone":"Africa/Casablanca",
    "iso:country":"MA",
    "name:und_x_variant":[
        "A\u00eft Anissi Taourirt",
        "Taourirt n\u2019Ounissi"
    ],
    "wof:name":"Taourirt n'Ounissi",
    "wof:placetype":"locality"
},
  "geometry": {"coordinates":[-7.44714,30.25535],"type":"Point"}
}