{
  "type": "Feature",
  "properties": {
    "gn:admin1_code":"02",
    "gn:asciiname":"Douar Sidi Mohamed",
    "gn:country_code":"MA",
    "gn:dem":826,
    "gn:feature_class":"P",
    "gn:feature_code":"PPL",
    "gn:name":"Douar Sidi Mohamed",
    "gn:population":0,
    "gn:timezone":"Africa/Casablanca",
    "iso:country":"MA",
    "wof:name":"Douar Sidi Mohamed",
    "wof:placetype":"locality"
},
  "geometry": {"coordinates":[-3.0985,34.85747],"type":"Point"}
}