{
  "type": "Feature",
  "properties": {
    "gn:admin1_code":"6.0",
    "gn:asciiname":"Dar Sidi Mohamed",
    "gn:country_code":"MA",
    "gn:dem":172,
    "gn:feature_class":"P",
    "gn:feature_code":"PPL",
    "gn:name":"Dar Sidi Mohamed",
    "gn:population":0,
    "gn:timezone":"Africa/Casablanca",
    "iso:country":"MA",
    "wof:name":"Dar Sidi Mohamed",
    "wof:placetype":"locality"
},
  "geometry": {"coordinates":[-7.12077,33.70692],"type":"Point"}
}