{
  "type": "Feature",
  "properties": {
    "gn:admin1_code":"01",
    "gn:asciiname":"Zitouna",
    "gn:country_code":"MA",
    "gn:dem":107,
    "gn:feature_class":"P",
    "gn:feature_code":"PPL",
    "gn:name":"Zitouna",
    "gn:population":0,
    "gn:timezone":"Africa/Casablanca",
    "iso:country":"MA",
    "name:und_x_variant":[
        "Ze\u00eftouna",
        "Ez Zitounal",
        "Zitounate",
        "Ez Zitouna",
        "Zitouna"
    ],
    "wof:name":"Zitouna",
    "wof:placetype":"locality"
},
  "geometry": {"coordinates":[-5.75829,35.40503],"type":"Point"}
}