{
  "type": "Feature",
  "properties": {
    "gn:admin1_code":"07",
    "gn:asciiname":"Mannsour",
    "gn:country_code":"MA",
    "gn:dem":385,
    "gn:feature_class":"P",
    "gn:feature_code":"PPL",
    "gn:name":"Mannsour",
    "gn:population":0,
    "gn:timezone":"Africa/Casablanca",
    "iso:country":"MA",
    "wof:name":"Mannsour",
    "wof:placetype":"locality"
},
  "geometry": {"coordinates":[-8.81132,31.55626],"type":"Point"}
}