{
  "type": "Feature",
  "properties": {
    "gn:admin1_code":"08",
    "gn:asciiname":"Oufella Ou Assif",
    "gn:country_code":"MA",
    "gn:dem":1593,
    "gn:feature_class":"P",
    "gn:feature_code":"PPL",
    "gn:name":"Oufella Ou Assif",
    "gn:population":0,
    "gn:timezone":"Africa/Casablanca",
    "iso:country":"MA",
    "name:und_x_variant":[
        "Afellah n\u2019Ouassif",
        "Oufella Ou Asif",
        "Oufella Ou Assif"
    ],
    "wof:name":"Oufella Ou Assif",
    "wof:placetype":"locality"
},
  "geometry": {"coordinates":[-7.30039,30.75626],"type":"Point"}
}