{
  "type": "Feature",
  "properties": {
    "gn:admin1_code":"9.0",
    "gn:asciiname":"Touammal",
    "gn:country_code":"MA",
    "gn:dem":86,
    "gn:feature_class":"P",
    "gn:feature_code":"PPL",
    "gn:name":"Touammal",
    "gn:population":0,
    "gn:timezone":"Africa/Casablanca",
    "iso:country":"MA",
    "wof:name":"Touammal",
    "wof:placetype":"locality"
},
  "geometry": {"coordinates":[-9.50352,30.12551],"type":"Point"}
}