{
  "type": "Feature",
  "properties": {
    "gn:admin1_code":"9.0",
    "gn:asciiname":"Ighir-n-Waboud",
    "gn:country_code":"MA",
    "gn:dem":1633,
    "gn:feature_class":"P",
    "gn:feature_code":"PPL",
    "gn:name":"Ighir-n-Waboud",
    "gn:population":0,
    "gn:timezone":"Africa/Casablanca",
    "iso:country":"MA",
    "wof:name":"Ighir-n-Waboud",
    "wof:placetype":"locality"
},
  "geometry": {"coordinates":[-8.63894,30.00013],"type":"Point"}
}