{
  "type": "Feature",
  "properties": {
    "gn:admin1_code":"4.0",
    "gn:asciiname":"Douar Boumlil",
    "gn:country_code":"MA",
    "gn:dem":443,
    "gn:feature_class":"P",
    "gn:feature_code":"PPL",
    "gn:name":"Douar Boumlil",
    "gn:population":0,
    "gn:timezone":"Africa/Casablanca",
    "iso:country":"MA",
    "wof:name":"Douar Boumlil",
    "wof:placetype":"locality"
},
  "geometry": {"coordinates":[-6.49825,33.63861],"type":"Point"}
}