{
  "type": "Feature",
  "properties": {
    "gn:admin1_code":"3.0",
    "gn:asciiname":"Douar Tanout",
    "gn:country_code":"MA",
    "gn:dem":965,
    "gn:feature_class":"P",
    "gn:feature_code":"PPL",
    "gn:name":"Douar Tanout",
    "gn:population":0,
    "gn:timezone":"Africa/Casablanca",
    "iso:country":"MA",
    "wof:name":"Douar Tanout",
    "wof:placetype":"locality"
},
  "geometry": {"coordinates":[-4.56207,33.55475999999999],"type":"Point"}
}