{
  "type": "Feature",
  "properties": {
    "gn:admin1_code":"3.0",
    "gn:asciiname":"Douar Ben Chenna",
    "gn:country_code":"MA",
    "gn:dem":367,
    "gn:feature_class":"P",
    "gn:feature_code":"PPL",
    "gn:name":"Douar Ben Chenna",
    "gn:population":0,
    "gn:timezone":"Africa/Casablanca",
    "iso:country":"MA",
    "wof:name":"Douar Ben Chenna",
    "wof:placetype":"locality"
},
  "geometry": {"coordinates":[-5.2538,33.99328],"type":"Point"}
}