{
  "type": "Feature",
  "properties": {
    "gn:admin1_code":"08",
    "gn:asciiname":"Ait Yassine",
    "gn:country_code":"MA",
    "gn:dem":1449,
    "gn:feature_class":"P",
    "gn:feature_code":"PPL",
    "gn:name":"A\u00eft Yassine",
    "gn:population":0,
    "gn:timezone":"Africa/Casablanca",
    "iso:country":"MA",
    "name:und_x_variant":[
        "A\u00eft Yasine",
        "A\u00eft Yassine"
    ],
    "wof:name":"Ait Yassine",
    "wof:placetype":"locality"
},
  "geometry": {"coordinates":[-6.05,31.26],"type":"Point"}
}