{
  "type": "Feature",
  "properties": {
    "gn:admin1_code":"09",
    "gn:asciiname":"Sinit",
    "gn:country_code":"MA",
    "gn:dem":1076,
    "gn:feature_class":"P",
    "gn:feature_code":"PPL",
    "gn:name":"Sinit",
    "gn:population":0,
    "gn:timezone":"Africa/Casablanca",
    "iso:country":"MA",
    "name:und_x_variant":[
        "Is Sinite",
        "Bilraman Simit",
        "Sinit"
    ],
    "wof:name":"Sinit",
    "wof:placetype":"locality"
},
  "geometry": {"coordinates":[-9.23389,30.742],"type":"Point"}
}