{
  "type": "Feature",
  "properties": {
    "gn:admin1_code":"03",
    "gn:asciiname":"Sakendous",
    "gn:country_code":"MA",
    "gn:dem":739,
    "gn:feature_class":"P",
    "gn:feature_code":"PPL",
    "gn:name":"Sakendous",
    "gn:population":0,
    "gn:timezone":"Africa/Casablanca",
    "iso:country":"MA",
    "name:und_x_variant":[
        "Douar Sakenndous",
        "Sakenndouss",
        "Sakendous"
    ],
    "wof:name":"Sakendous",
    "wof:placetype":"locality"
},
  "geometry": {"coordinates":[-4.20417,34.15396],"type":"Point"}
}