{
  "type": "Feature",
  "properties": {
    "gn:admin1_code":"02",
    "gn:asciiname":"Douar Ouartas",
    "gn:country_code":"MA",
    "gn:dem":250,
    "gn:feature_class":"P",
    "gn:feature_code":"PPL",
    "gn:name":"Douar Ouartas",
    "gn:population":0,
    "gn:timezone":"Africa/Casablanca",
    "iso:country":"MA",
    "name:und_x_variant":[
        "Ououtasse",
        "Ouartass",
        "Douar Ouartas"
    ],
    "wof:name":"Douar Ouartas",
    "wof:placetype":"locality"
},
  "geometry": {"coordinates":[-2.29936,34.89834],"type":"Point"}
}