{
  "type": "Feature",
  "properties": {
    "gn:admin1_code":"9.0",
    "gn:asciiname":"Tafourtane",
    "gn:country_code":"MA",
    "gn:dem":1843,
    "gn:feature_class":"P",
    "gn:feature_code":"PPL",
    "gn:name":"Tafourtane",
    "gn:population":0,
    "gn:timezone":"Africa/Casablanca",
    "iso:country":"MA",
    "wof:name":"Tafourtane",
    "wof:placetype":"locality"
},
  "geometry": {"coordinates":[-8.5806,30.86832],"type":"Point"}
}