{
  "type": "Feature",
  "properties": {
    "gn:admin1_code":"03",
    "gn:asciiname":"Douar Oulad Ajal",
    "gn:country_code":"MA",
    "gn:dem":380,
    "gn:feature_class":"P",
    "gn:feature_code":"PPL",
    "gn:name":"Douar Oulad Ajal",
    "gn:population":0,
    "gn:timezone":"Africa/Casablanca",
    "iso:country":"MA",
    "name:und_x_variant":[
        "Douar Ouled Ajel",
        "Oulad Ajel",
        "Douar Oulad Ajal"
    ],
    "wof:name":"Douar Oulad Ajal",
    "wof:placetype":"locality"
},
  "geometry": {"coordinates":[-4.5949,34.15669],"type":"Point"}
}