{
  "type": "Feature",
  "properties": {
    "gn:admin1_code":"10.0",
    "gn:asciiname":"Ta'chou",
    "gn:country_code":"MA",
    "gn:dem":810,
    "gn:feature_class":"P",
    "gn:feature_code":"PPL",
    "gn:name":"Ta\u2019chou",
    "gn:population":0,
    "gn:timezone":"Africa/Casablanca",
    "iso:country":"MA",
    "wof:name":"Ta'chou",
    "wof:placetype":"locality"
},
  "geometry": {"coordinates":[-9.81019,29.36475],"type":"Point"}
}