{
  "type": "Feature",
  "properties": {
    "gn:admin1_code":"08",
    "gn:asciiname":"Zaouia Ifrioun",
    "gn:country_code":"MA",
    "gn:dem":830,
    "gn:feature_class":"P",
    "gn:feature_code":"PPL",
    "gn:name":"Zaouia Ifrioun",
    "gn:population":0,
    "gn:timezone":"Africa/Casablanca",
    "iso:country":"MA",
    "wof:name":"Zaouia Ifrioun",
    "wof:placetype":"locality"
},
  "geometry": {"coordinates":[-6.14416,30.60258],"type":"Point"}
}