{
  "type": "Feature",
  "properties": {
    "gn:admin1_code":"07",
    "gn:asciiname":"Gammasa",
    "gn:country_code":"MA",
    "gn:dem":579,
    "gn:feature_class":"P",
    "gn:feature_code":"PPL",
    "gn:name":"Gammasa",
    "gn:population":0,
    "gn:timezone":"Africa/Casablanca",
    "iso:country":"MA",
    "name:und_x_variant":[
        "Guemassa"
    ],
    "wof:name":"Gammasa",
    "wof:placetype":"locality"
},
  "geometry": {"coordinates":[-8.4021,31.40765],"type":"Point"}
}