{
  "type": "Feature",
  "properties": {
    "gn:admin1_code":"03",
    "gn:asciiname":"Kasbat Ben Yazgha",
    "gn:country_code":"MA",
    "gn:dem":807,
    "gn:feature_class":"P",
    "gn:feature_code":"PPL",
    "gn:name":"Kasbat Ben Yazgha",
    "gn:population":0,
    "gn:timezone":"Africa/Casablanca",
    "iso:country":"MA",
    "name:und_x_variant":[
        "Qacbat Beni Yazgha",
        "Kasbah",
        "Kasba des Beni Yazrha",
        "El Kasba"
    ],
    "wof:name":"Kasbat Ben Yazgha",
    "wof:placetype":"locality"
},
  "geometry": {"coordinates":[-4.59161,33.82414],"type":"Point"}
}