{
  "type": "Feature",
  "properties": {
    "gn:admin1_code":"09",
    "gn:asciiname":"Issii",
    "gn:country_code":"MA",
    "gn:dem":179,
    "gn:feature_class":"P",
    "gn:feature_code":"PPL",
    "gn:name":"Issii",
    "gn:population":0,
    "gn:timezone":"Africa/Casablanca",
    "iso:country":"MA",
    "name:und_x_variant":[
        "Issil"
    ],
    "wof:name":"Issii",
    "wof:placetype":"locality"
},
  "geometry": {"coordinates":[-9.32377,29.84082],"type":"Point"}
}