{
  "type": "Feature",
  "properties": {
    "gn:admin1_code":"7.0",
    "gn:asciiname":"Douar Gdidrat Sidi Damene",
    "gn:country_code":"MA",
    "gn:dem":420,
    "gn:feature_class":"P",
    "gn:feature_code":"PPL",
    "gn:name":"Douar Gdidrat Sidi Damene",
    "gn:population":0,
    "gn:timezone":"Africa/Casablanca",
    "iso:country":"MA",
    "wof:name":"Douar Gdidrat Sidi Damene",
    "wof:placetype":"locality"
},
  "geometry": {"coordinates":[-8.82112,32.09273],"type":"Point"}
}