{
  "type": "Feature",
  "properties": {
    "gn:admin1_code":"09",
    "gn:asciiname":"Afra",
    "gn:country_code":"MA",
    "gn:dem":1071,
    "gn:feature_class":"P",
    "gn:feature_code":"PPL",
    "gn:name":"Afra",
    "gn:population":0,
    "gn:timezone":"Africa/Casablanca",
    "iso:country":"MA",
    "wof:name":"Afra",
    "wof:placetype":"locality"
},
  "geometry": {"coordinates":[-8.83,30.18],"type":"Point"}
}