{
  "type": "Feature",
  "properties": {
    "gn:country":"MA",
    "gn:fcode":"ADM3",
    "gn:population":6552,
    "iso:country":"MA",
    "name:ara_x_preferred":[
        "\u0627\u0632\u0644\u0627"
    ],
    "name:fra_x_preferred":[
        "Ain Lahsan"
    ],
    "name:fra_x_variant":[
        "Ain Lahsan (CR)",
        "Ain Lahsan (Commune Rurale)"
    ],
    "qs_pg:aaroncc":"MA",
    "qs_pg:gn_country":"MA",
    "qs_pg:gn_fcode":"ADM3",
    "qs_pg:gn_pop":6552,
    "qs_pg:name":"Ain Lahsan",
    "qs_pg:photos_9r":0,
    "qs_pg:photos_sr":0,
    "qs_pg:pop_sr":5,
    "qs_pg:qs_pg_placetype":"localadmin",
    "wof:name":"Ain Lahsan",
    "wof:placetype":"localadmin",
    "wof:population":6742
},
  "geometry": {"coordinates":[-5.57686,35.56209],"type":"Point"}
}