{
  "type": "Feature",
  "properties": {
    "gn:admin1_code":"4.0",
    "gn:asciiname":"Douar Laanabsa",
    "gn:country_code":"MA",
    "gn:dem":60,
    "gn:feature_class":"P",
    "gn:feature_code":"PPL",
    "gn:name":"Douar Laanabsa",
    "gn:population":0,
    "gn:timezone":"Africa/Casablanca",
    "iso:country":"MA",
    "wof:name":"Douar Laanabsa",
    "wof:placetype":"locality"
},
  "geometry": {"coordinates":[-5.97478,34.7808],"type":"Point"}
}