{
  "type": "Feature",
  "properties": {
    "gn:admin1_code":"04",
    "gn:asciiname":"Dar Azzi Rami",
    "gn:country_code":"MA",
    "gn:dem":34,
    "gn:feature_class":"P",
    "gn:feature_code":"PPL",
    "gn:name":"Dar Azzi Rami",
    "gn:population":0,
    "gn:timezone":"Africa/Casablanca",
    "iso:country":"MA",
    "name:und_x_variant":[
        "Hofra Sidi Radi"
    ],
    "wof:name":"Dar Azzi Rami",
    "wof:placetype":"locality"
},
  "geometry": {"coordinates":[-6.64758,34.23656],"type":"Point"}
}