{
  "type": "Feature",
  "properties": {
    "gn:admin1_code":"5.0",
    "gn:asciiname":"Imziln",
    "gn:country_code":"MA",
    "gn:dem":1047,
    "gn:feature_class":"P",
    "gn:feature_code":"PPL",
    "gn:name":"Imziln",
    "gn:population":0,
    "gn:timezone":"Africa/Casablanca",
    "iso:country":"MA",
    "wof:name":"Imziln",
    "wof:placetype":"locality"
},
  "geometry": {"coordinates":[-6.76041,31.93865],"type":"Point"}
}