{
  "type": "Feature",
  "properties": {
    "gn:admin1_code":"03",
    "gn:asciiname":"Msikhine",
    "gn:country_code":"MA",
    "gn:dem":820,
    "gn:feature_class":"P",
    "gn:feature_code":"PPL",
    "gn:name":"Msikhine",
    "gn:population":0,
    "gn:timezone":"Africa/Casablanca",
    "iso:country":"MA",
    "name:und_x_variant":[
        "Douar Msikhine",
        "Msikhine"
    ],
    "wof:name":"Msikhine",
    "wof:placetype":"locality"
},
  "geometry": {"coordinates":[-4.21408,34.1399],"type":"Point"}
}