{
  "type": "Feature",
  "properties": {
    "gn:admin1_code":"7.0",
    "gn:asciiname":"Douar Chrouqat",
    "gn:country_code":"MA",
    "gn:dem":312,
    "gn:feature_class":"P",
    "gn:feature_code":"PPL",
    "gn:name":"Douar Chrouqat",
    "gn:population":0,
    "gn:timezone":"Africa/Casablanca",
    "iso:country":"MA",
    "wof:name":"Douar Chrouqat",
    "wof:placetype":"locality"
},
  "geometry": {"coordinates":[-9.05649,32.04903],"type":"Point"}
}