{
  "type": "Feature",
  "properties": {
    "gn:admin1_code":"3.0",
    "gn:asciiname":"Khemis Oued Errihane",
    "gn:country_code":"MA",
    "gn:dem":432,
    "gn:feature_class":"P",
    "gn:feature_code":"PPL",
    "gn:name":"Khemis Oued Errihane",
    "gn:population":0,
    "gn:timezone":"Africa/Casablanca",
    "iso:country":"MA",
    "wof:name":"Khemis Oued Errihane",
    "wof:placetype":"locality"
},
  "geometry": {"coordinates":[-4.34976,34.45180999999999],"type":"Point"}
}