{
  "type": "Feature",
  "properties": {
    "gn:admin1_code":"03",
    "gn:asciiname":"Hamma",
    "gn:country_code":"MA",
    "gn:dem":139,
    "gn:feature_class":"P",
    "gn:feature_code":"PPL",
    "gn:name":"Hamma",
    "gn:population":0,
    "gn:timezone":"Africa/Casablanca",
    "iso:country":"MA",
    "name:bak_x_preferred":[
        "\u0425\u0430\u043c\u043c\u0430"
    ],
    "name:cat_x_preferred":[
        "Hamma"
    ],
    "name:ceb_x_preferred":[
        "Hamma"
    ],
    "name:deu_x_preferred":[
        "Hamma"
    ],
    "name:epo_x_preferred":[
        "Hamma"
    ],
    "name:fas_x_preferred":[
        "\u0647\u0627\u0645\u0627"
    ],
    "name:ita_x_preferred":[
        "Hamma"
    ],
    "name:kaz_x_preferred":[
        "\u0425\u0430\u043c\u043c\u0430"
    ],
    "name:mkd_x_preferred":[
        "\u0425\u0430\u043c\u0430"
    ],
    "name:nld_x_preferred":[
        "Hamma"
    ],
    "name:por_x_preferred":[
        "Hamma"
    ],
    "name:ron_x_preferred":[
        "Hamma"
    ],
    "name:rus_x_preferred":[
        "\u0425\u0430\u043c\u043c\u0430"
    ],
    "name:srp_x_preferred":[
        "\u0425\u0430\u043c\u0430"
    ],
    "name:uzb_x_preferred":[
        "Hamma"
    ],
    "name:vie_x_preferred":[
        "Hamma"
    ],
    "name:vol_x_preferred":[
        "Hamma"
    ],
    "name:war_x_preferred":[
        "Hamma"
    ],
    "wof:name":"Hamma",
    "wof:placetype":"locality"
},
  "geometry": {"coordinates":[-5.25186,34.41264],"type":"Point"}
}