{
  "type": "Feature",
  "properties": {
    "gn:admin1_code":"09",
    "gn:asciiname":"Afza",
    "gn:country_code":"MA",
    "gn:dem":1149,
    "gn:feature_class":"P",
    "gn:feature_code":"PPL",
    "gn:name":"Afza",
    "gn:population":0,
    "gn:timezone":"Africa/Casablanca",
    "iso:country":"MA",
    "name:und_x_variant":[
        "Afeza"
    ],
    "wof:name":"Afza",
    "wof:placetype":"locality"
},
  "geometry": {"coordinates":[-8.52502,30.78654],"type":"Point"}
}