{
  "type": "Feature",
  "properties": {
    "gn:admin1_code":"2.0",
    "gn:asciiname":"Douar Leqsaqsa Oulad Braz",
    "gn:country_code":"MA",
    "gn:dem":698,
    "gn:feature_class":"P",
    "gn:feature_code":"PPL",
    "gn:name":"Douar Leqsaqsa Oulad Braz",
    "gn:population":0,
    "gn:timezone":"Africa/Casablanca",
    "iso:country":"MA",
    "wof:name":"Douar Leqsaqsa Oulad Braz",
    "wof:placetype":"locality"
},
  "geometry": {"coordinates":[-2.23914,34.61838],"type":"Point"}
}