{
  "type": "Feature",
  "properties": {
    "gn:admin1_code":"09",
    "gn:asciiname":"Tizguiy",
    "gn:country_code":"MA",
    "gn:dem":1384,
    "gn:feature_class":"P",
    "gn:feature_code":"PPL",
    "gn:name":"Tizguiy",
    "gn:population":0,
    "gn:timezone":"Africa/Casablanca",
    "iso:country":"MA",
    "name:und_x_variant":[
        "Tizgue",
        "Tisgui",
        "Tizguiy"
    ],
    "wof:name":"Tizguiy",
    "wof:placetype":"locality"
},
  "geometry": {"coordinates":[-7.68781,30.18778],"type":"Point"}
}