{
  "type": "Feature",
  "properties": {
    "gn:admin1_code":"01",
    "gn:asciiname":"Fahsiene",
    "gn:country_code":"MA",
    "gn:dem":400,
    "gn:feature_class":"P",
    "gn:feature_code":"PPL",
    "gn:name":"Fahsiene",
    "gn:population":0,
    "gn:timezone":"Africa/Casablanca",
    "iso:country":"MA",
    "name:und_x_variant":[
        "El Fahsien",
        "El Fahsy\u00e8ne",
        "Fahsiene"
    ],
    "wof:name":"Fahsiene",
    "wof:placetype":"locality"
},
  "geometry": {"coordinates":[-5.17184,34.87829],"type":"Point"}
}