{
  "type": "Feature",
  "properties": {
    "gn:admin1_code":"08",
    "gn:asciiname":"Lemri",
    "gn:country_code":"MA",
    "gn:dem":1950,
    "gn:feature_class":"P",
    "gn:feature_code":"PPL",
    "gn:name":"Lemri",
    "gn:population":0,
    "gn:timezone":"Africa/Casablanca",
    "iso:country":"MA",
    "name:und_x_variant":[
        "El Meri",
        "Lemri"
    ],
    "wof:name":"Lemri",
    "wof:placetype":"locality"
},
  "geometry": {"coordinates":[-5.34345,32.3984],"type":"Point"}
}