{
  "type": "Feature",
  "properties": {
    "gn:admin1_code":"7.0",
    "gn:asciiname":"Oulad El Marsli",
    "gn:country_code":"MA",
    "gn:dem":414,
    "gn:feature_class":"P",
    "gn:feature_code":"PPL",
    "gn:name":"Oulad El Marsli",
    "gn:population":0,
    "gn:timezone":"Africa/Casablanca",
    "iso:country":"MA",
    "wof:name":"Oulad El Marsli",
    "wof:placetype":"locality"
},
  "geometry": {"coordinates":[-7.44684,32.23025],"type":"Point"}
}