{
  "type": "Feature",
  "properties": {
    "gn:admin1_code":"04",
    "gn:asciiname":"Douar Oulad Marouane",
    "gn:country_code":"MA",
    "gn:dem":12,
    "gn:feature_class":"P",
    "gn:feature_code":"PPL",
    "gn:name":"Douar Oulad Marouane",
    "gn:population":0,
    "gn:timezone":"Africa/Casablanca",
    "iso:country":"MA",
    "name:und_x_variant":[
        "Douar Oulad Merouane",
        "Ouled Marouane",
        "Oulad Merouane",
        "Douar Oulad Marouane"
    ],
    "wof:name":"Douar Oulad Marouane",
    "wof:placetype":"locality"
},
  "geometry": {"coordinates":[-6.40265,34.59574],"type":"Point"}
}