{
  "type": "Feature",
  "properties": {
    "gn:admin1_code":"09",
    "gn:asciiname":"Ait Iftane",
    "gn:country_code":"MA",
    "gn:dem":1531,
    "gn:feature_class":"P",
    "gn:feature_code":"PPL",
    "gn:name":"A\u00eft Iftane",
    "gn:population":0,
    "gn:timezone":"Africa/Casablanca",
    "iso:country":"MA",
    "name:und_x_variant":[
        "A\u00eft Iftane",
        "A\u00eft Iftene"
    ],
    "wof:name":"Ait Iftane",
    "wof:placetype":"locality"
},
  "geometry": {"coordinates":[-9.04002,29.81685],"type":"Point"}
}