{
  "type": "Feature",
  "properties": {
    "gn:admin1_code":"09",
    "gn:asciiname":"Tabarbout",
    "gn:country_code":"MA",
    "gn:dem":622,
    "gn:feature_class":"P",
    "gn:feature_code":"PPL",
    "gn:name":"Tabarbout",
    "gn:population":0,
    "gn:timezone":"Africa/Casablanca",
    "iso:country":"MA",
    "name:und_x_variant":[
        "Taberbort",
        "Tabercourt",
        "Taberbourt",
        "Tabarbout"
    ],
    "wof:name":"Tabarbout",
    "wof:placetype":"locality"
},
  "geometry": {"coordinates":[-8.35385,30.72691],"type":"Point"}
}