{
  "type": "Feature",
  "properties": {
    "gn:admin1_code":"05",
    "gn:asciiname":"Irgragane",
    "gn:country_code":"MA",
    "gn:dem":1429,
    "gn:elevation":"0.0",
    "gn:feature_class":"P",
    "gn:feature_code":"PPL",
    "gn:name":"Irgragane",
    "gn:population":0,
    "gn:timezone":"Africa/Casablanca",
    "iso:country":"MA",
    "name:und_x_variant":[
        "Irgraguene"
    ],
    "wof:name":"Irgragane",
    "wof:placetype":"locality"
},
  "geometry": {"coordinates":[-6.96906,31.66502],"type":"Point"}
}