{
  "type": "Feature",
  "properties": {
    "gn:admin1_code":"8.0",
    "gn:asciiname":"Tilamsine",
    "gn:country_code":"MA",
    "gn:dem":2215,
    "gn:feature_class":"P",
    "gn:feature_code":"PPL",
    "gn:name":"Tilamsine",
    "gn:population":0,
    "gn:timezone":"Africa/Casablanca",
    "iso:country":"MA",
    "wof:name":"Tilamsine",
    "wof:placetype":"locality"
},
  "geometry": {"coordinates":[-7.61637,30.84234],"type":"Point"}
}