{
  "type": "Feature",
  "properties": {
    "gn:admin1_code":"1.0",
    "gn:asciiname":"Bab Afouzar",
    "gn:country_code":"MA",
    "gn:dem":1208,
    "gn:feature_class":"P",
    "gn:feature_code":"PPL",
    "gn:name":"Bab Afouzar",
    "gn:population":0,
    "gn:timezone":"Africa/Casablanca",
    "iso:country":"MA",
    "wof:name":"Bab Afouzar",
    "wof:placetype":"locality"
},
  "geometry": {"coordinates":[-4.87372,35.09319],"type":"Point"}
}