{
  "type": "Feature",
  "properties": {
    "gn:admin1_code":"09",
    "gn:asciiname":"Foum el Oued",
    "gn:country_code":"MA",
    "gn:dem":849,
    "gn:feature_class":"P",
    "gn:feature_code":"PPL",
    "gn:name":"Foum el Oued",
    "gn:population":0,
    "gn:timezone":"Africa/Casablanca",
    "iso:country":"MA",
    "wof:name":"Foum el Oued",
    "wof:placetype":"locality"
},
  "geometry": {"coordinates":[-6.84,30.35],"type":"Point"}
}