{
  "type": "Feature",
  "properties": {
    "gn:admin1_code":"09",
    "gn:asciiname":"Ait Choufoua",
    "gn:country_code":"MA",
    "gn:dem":410,
    "gn:feature_class":"P",
    "gn:feature_code":"PPL",
    "gn:name":"A\u00eft Choufoua",
    "gn:population":0,
    "gn:timezone":"Africa/Casablanca",
    "iso:country":"MA",
    "name:und_x_variant":[
        "A\u00eft Lhoufoua\u00e2",
        "A\u00eft Choufoua"
    ],
    "wof:name":"Ait Choufoua",
    "wof:placetype":"locality"
},
  "geometry": {"coordinates":[-9.37793,29.7872],"type":"Point"}
}