{
  "type": "Feature",
  "properties": {
    "gn:admin1_code":"9.0",
    "gn:asciiname":"Tawrirt",
    "gn:country_code":"MA",
    "gn:dem":777,
    "gn:feature_class":"P",
    "gn:feature_code":"PPL",
    "gn:name":"Tawrirt",
    "gn:population":0,
    "gn:timezone":"Africa/Casablanca",
    "iso:country":"MA",
    "wof:name":"Tawrirt",
    "wof:placetype":"locality"
},
  "geometry": {"coordinates":[-8.9546,30.1619],"type":"Point"}
}