{
  "type": "Feature",
  "properties": {
    "gn:admin1_code":"2.0",
    "gn:asciiname":"Douar Oulad Alla Ouhriqene",
    "gn:country_code":"MA",
    "gn:dem":615,
    "gn:feature_class":"P",
    "gn:feature_code":"PPL",
    "gn:name":"Douar Oulad Alla Ouhriqene",
    "gn:population":0,
    "gn:timezone":"Africa/Casablanca",
    "iso:country":"MA",
    "wof:name":"Douar Oulad Alla Ouhriqene",
    "wof:placetype":"locality"
},
  "geometry": {"coordinates":[-2.27827,34.70503],"type":"Point"}
}