{
  "type": "Feature",
  "properties": {
    "gn:admin1_code":"5.0",
    "gn:asciiname":"Ait Ksou",
    "gn:country_code":"MA",
    "gn:dem":915,
    "gn:feature_class":"P",
    "gn:feature_code":"PPL",
    "gn:name":"A\u00eft Ksou",
    "gn:population":0,
    "gn:timezone":"Africa/Casablanca",
    "iso:country":"MA",
    "wof:name":"Ait Ksou",
    "wof:placetype":"locality"
},
  "geometry": {"coordinates":[-5.83238,32.98143],"type":"Point"}
}