{
  "type": "Feature",
  "properties": {
    "gn:admin1_code":"03",
    "gn:asciiname":"Kermets",
    "gn:country_code":"MA",
    "gn:dem":458,
    "gn:feature_class":"P",
    "gn:feature_code":"PPL",
    "gn:name":"Kermets",
    "gn:population":0,
    "gn:timezone":"Africa/Casablanca",
    "iso:country":"MA",
    "name:und_x_variant":[
        "Kermet Ben Salem",
        "Kermet centre",
        "Kermets"
    ],
    "wof:name":"Kermets",
    "wof:placetype":"locality"
},
  "geometry": {"coordinates":[-5.49382,34.10665],"type":"Point"}
}