{
  "type": "Feature",
  "properties": {
    "gn:admin1_code":"02",
    "gn:asciiname":"Douar Leari",
    "gn:country_code":"MA",
    "gn:dem":375,
    "gn:feature_class":"P",
    "gn:feature_code":"PPL",
    "gn:name":"Douar Leari",
    "gn:population":0,
    "gn:timezone":"Africa/Casablanca",
    "iso:country":"MA",
    "wof:name":"Douar Leari",
    "wof:placetype":"locality"
},
  "geometry": {"coordinates":[-3.69979,35.22916],"type":"Point"}
}