{
  "type": "Feature",
  "properties": {
    "gn:admin1_code":"5.0",
    "gn:asciiname":"Tafrawt-n-Oussanous",
    "gn:country_code":"MA",
    "gn:dem":1864,
    "gn:feature_class":"P",
    "gn:feature_code":"PPL",
    "gn:name":"Tafrawt-n-Oussanous",
    "gn:population":0,
    "gn:timezone":"Africa/Casablanca",
    "iso:country":"MA",
    "wof:name":"Tafrawt-n-Oussanous",
    "wof:placetype":"locality"
},
  "geometry": {"coordinates":[-6.47058,31.92723],"type":"Point"}
}