{
  "type": "Feature",
  "properties": {
    "gn:admin1_code":"04",
    "gn:asciiname":"El Arab",
    "gn:country_code":"MA",
    "gn:dem":127,
    "gn:feature_class":"P",
    "gn:feature_code":"PPL",
    "gn:name":"El Arab",
    "gn:population":0,
    "gn:timezone":"Africa/Casablanca",
    "iso:country":"MA",
    "name:und_x_variant":[
        "El Arb",
        "El Arab"
    ],
    "wof:name":"El Arab",
    "wof:placetype":"locality"
},
  "geometry": {"coordinates":[-6.04476,34.76669],"type":"Point"}
}