{
  "type": "Feature",
  "properties": {
    "gn:admin1_code":"7.0",
    "gn:asciiname":"Anammer",
    "gn:country_code":"MA",
    "gn:dem":1513,
    "gn:feature_class":"P",
    "gn:feature_code":"PPL",
    "gn:name":"Anammer",
    "gn:population":0,
    "gn:timezone":"Africa/Casablanca",
    "iso:country":"MA",
    "wof:name":"Anammer",
    "wof:placetype":"locality"
},
  "geometry": {"coordinates":[-7.81597,31.26919],"type":"Point"}
}