{
  "type": "Feature",
  "properties": {
    "gn:admin1_code":"7.0",
    "gn:asciiname":"Sidi 'Ali Ben Mess'aoud",
    "gn:country_code":"MA",
    "gn:dem":826,
    "gn:feature_class":"P",
    "gn:feature_code":"PPL",
    "gn:name":"Sidi \u2019Ali Ben Mess\u2019aoud",
    "gn:population":0,
    "gn:timezone":"Africa/Casablanca",
    "iso:country":"MA",
    "wof:name":"Sidi 'Ali Ben Mess'aoud",
    "wof:placetype":"locality"
},
  "geometry": {"coordinates":[-7.99098,31.39992],"type":"Point"}
}