{
  "type": "Feature",
  "properties": {
    "gn:admin1_code":"6.0",
    "gn:asciiname":"Douar Drioua",
    "gn:country_code":"MA",
    "gn:dem":263,
    "gn:feature_class":"P",
    "gn:feature_code":"PPL",
    "gn:name":"Douar Drioua",
    "gn:population":0,
    "gn:timezone":"Africa/Casablanca",
    "iso:country":"MA",
    "wof:name":"Douar Drioua",
    "wof:placetype":"locality"
},
  "geometry": {"coordinates":[-8.43007,32.4182],"type":"Point"}
}