{
  "type": "Feature",
  "properties": {
    "gn:admin1_code":"9.0",
    "gn:asciiname":"Tamsriout",
    "gn:country_code":"MA",
    "gn:dem":733,
    "gn:feature_class":"P",
    "gn:feature_code":"PPL",
    "gn:name":"Tamsriout",
    "gn:population":0,
    "gn:timezone":"Africa/Casablanca",
    "iso:country":"MA",
    "wof:name":"Tamsriout",
    "wof:placetype":"locality"
},
  "geometry": {"coordinates":[-9.03063,30.14146],"type":"Point"}
}